Workbook

Sheet Summary
A1: Coral Village Housing LP
A2: Coral Village — 121 NE 10th Pl, Cape Coral, FL 33909
A3: EIN: 87-2205593 · FYE: December 31, 2024 · Year of Change: 1/1/2024
A4: Summary of Cost Segregation Adjustments — CSSI Report #107752-01 (CAM — DCN #7)
A7: Acq Date | B7: Asset Description | C7: Total | D7: Site | E7: Bldg 1 | F7: Bldg 2 | G7: Bldg 3 | H7: Bldg 4 | I7: Bldg 5 | J7: Bldg 6 | K7: Bldg 7 | L7: Bldg 8 | M7: Bldg 9 | N7: Office
A8: 9/22/21 | B8: 2-Building | C8: =SUM(D8:N8) -> 3697723 | D8: =Site!$D$10 -> 531007.07 | E8: ='Bldg 1'!$D$10 -> 383408.73 | F8: ='Bldg 2'!$D$10 -> 302676.39 | G8: ='Bldg 3'!$D$10 -> 383408.73 | H8: ='Bldg 4'!$D$10 -> 302676.39 | I8: ='Bldg 5'!$D$10 -> 383408.73 | J8: ='Bldg 6'!$D$10 -> 302676.39 | K8: ='Bldg 7'!$D$10 -> 383408.73 | L8: ='Bldg 8'!$D$10 -> 302676.39 | M8: ='Bldg 9'!$D$10 -> 302676.39 | N8: =Office!$D$10 -> 119699.06
A9: 9/22/21 | B9: 3-Land Improvements | C9: =SUM(D9:N9) -> 402935 | D9: =Site!$D$11 -> 57862.97 | E9: ='Bldg 1'!$D$11 -> 41779.44 | F9: ='Bldg 2'!$D$11 -> 32982.17 | G9: ='Bldg 3'!$D$11 -> 41779.44 | H9: ='Bldg 4'!$D$11 -> 32982.17 | I9: ='Bldg 5'!$D$11 -> 41779.44 | J9: ='Bldg 6'!$D$11 -> 32982.17 | K9: ='Bldg 7'!$D$11 -> 41779.44 | L9: ='Bldg 8'!$D$11 -> 32982.17 | M9: ='Bldg 9'!$D$11 -> 32982.17 | N9: =Office!$D$11 -> 13043.42
A10: 9/22/21 | B10: 4-Equipment | C10: =SUM(D10:N10) -> 755504 | D10: =Site!$D$12 -> 108493.26 | E10: ='Bldg 1'!$D$12 -> 78336.54 | F10: ='Bldg 2'!$D$12 -> 61841.63 | G10: ='Bldg 3'!$D$12 -> 78336.54 | H10: ='Bldg 4'!$D$12 -> 61841.63 | I10: ='Bldg 5'!$D$12 -> 78336.54 | J10: ='Bldg 6'!$D$12 -> 61841.63 | K10: ='Bldg 7'!$D$12 -> 78336.54 | L10: ='Bldg 8'!$D$12 -> 61841.63 | M10: ='Bldg 9'!$D$12 -> 61841.63 | N10: =Office!$D$12 -> 24456.43
B11: Grand Total | C11: =SUM(C8:C10) -> 4856162 | D11: =SUM(D8:D10) -> 697363.3 | E11: =SUM(E8:E10) -> 503524.71 | F11: =SUM(F8:F10) -> 397500.19 | G11: =SUM(G8:G10) -> 503524.71 | H11: =SUM(H8:H10) -> 397500.19 | I11: =SUM(I8:I10) -> 503524.71 | J11: =SUM(J8:J10) -> 397500.19 | ... N11: =SUM(N8:N10) -> 157198.91
B13: MACRS Reclassification
A14: 9/22/21 | B14: 2-Building-7yr | C14: =SUM(D14:N14) -> 1284.15 | D14: =Site!$D$17 -> 1284.15
A15: 9/22/21 | B15: 2-Building-15yr | C15: =SUM(D15:N15) -> 290971.55 | D15: =Site!$D$18 -> 290971.55
A16: 9/22/21 | B16: 2-Building-27.5yr | C16: =SUM(D16:N16) -> 2841737 | D16: =Site!$D$19 -> 238751.37 | E16: ='Bldg 1'!$D$18+'Bldg 1'!$D$20 -> 318990.65 | F16: ='Bldg 2'!$D$18+'Bldg 2'!$D$20 -> 242958.97 | G16: ='Bldg 3'!$D$18+'Bldg 3'!$D$20 -> 318990.65 | H16: ='Bldg 4'!$D$18+'Bldg 4'!$D$20 -> 242958.97 | I16: ='Bldg 5'!$D$18+'Bldg 5'!$D$20 -> 318990.65 | J16: ='Bldg 6'!$D$18+'Bldg 6'!$D$20 -> 242958.97 | K16: ='Bldg 7'!$D$18+'Bldg 7'!$D$20 -> 318990.65 | L16: ='Bldg 8'!$D$18+'Bldg 8'!$D$20 -> 242958.97 | M16: ='Bldg 9'!$D$18+'Bldg 9'!$D$20 -> 242958.97 | N16: =Office!$D$18+Office!$D$20 -> 112228.18
A17: 9/22/21 | B17: 3-Land Improvements-7yr | C17: =SUM(D17:N17) -> 139.93 | D17: =Site!$D$20 -> 139.93
A18: 9/22/21 | B18: 3-Land Improvements-15yr | C18: =SUM(D18:N18) -> 31706.69 | D18: =Site!$D$21 -> 31706.69
A19: 9/22/21 | B19: 3-Land Improvements-27.5yr | C19: =SUM(D19:N19) -> 26016.35 | D19: =Site!$D$22 -> 26016.35
A20: 9/22/21 | B20: 4-Equipment-7yr | C20: =SUM(D20:N20) -> 262.37 | D20: =Site!$D$23 -> 262.37
A21: 9/22/21 | B21: 4-Equipment-15yr | C21: =SUM(D21:N21) -> 59450.16 | D21: =Site!$D$24 -> 59450.16
A22: 9/22/21 | B22: 4-Equipment-27.5yr | C22: =SUM(D22:N22) -> 528354.02 | D22: =Site!$D$25 -> 48780.73 | E22: ='Bldg 1'!$D$22 -> 58770.74 | F22: ='Bldg 2'!$D$22 -> 44762.69 | G22: ='Bldg 3'!$D$22 -> 58770.74 | H22: ='Bldg 4'!$D$22 -> 44762.69 | I22: ='Bldg 5'!$D$22 -> 58770.74 | J22: ='Bldg 6'!$D$22 -> 44762.69 | K22: ='Bldg 7'!$D$22 -> 58770.74 | L22: ='Bldg 8'!$D$22 -> 44762.69 | M22: ='Bldg 9'!$D$22 -> 44762.69 | N22: =Office!$D$22 -> 20676.88
A23: 9/22/21 | B23: 2-Building-5yr | C23: =SUM(D23:N23) -> 819502.45 | E23: ='Bldg 1'!$D$17 -> 95762.44 | F23: ='Bldg 2'!$D$17 -> 83590.83 | G23: ='Bldg 3'!$D$17 -> 95762.44 | H23: ='Bldg 4'!$D$17 -> 83590.83 | I23: ='Bldg 5'!$D$17 -> 95762.44 | J23: ='Bldg 6'!$D$17 -> 83590.83 | K23: ='Bldg 7'!$D$17 -> 95762.44 | L23: ='Bldg 8'!$D$17 -> 83590.83 | M23: ='Bldg 9'!$D$17 -> 83590.83 | N23: =Office!$D$17 -> 18498.54
A24: 9/22/21 | B24: 3-Land Improvements-5yr | C24: =SUM(D24:N24) -> 89299.88 | E24: ='Bldg 1'!$D$19 -> 10435.08 | F24: ='Bldg 2'!$D$19 -> 9108.76 | G24: ='Bldg 3'!$D$19 -> 10435.08 | H24: ='Bldg 4'!$D$19 -> 9108.76 | I24: ='Bldg 5'!$D$19 -> 10435.08 | J24: ='Bldg 6'!$D$19 -> 9108.76 | K24: ='Bldg 7'!$D$19 -> 10435.08 | L24: ='Bldg 8'!$D$19 -> 9108.76 | M24: ='Bldg 9'!$D$19 -> 9108.76 | N24: =Office!$D$19 -> 2015.76
A25: 9/22/21 | B25: 4-Equipment-5yr | C25: =SUM(D25:N25) -> 167437.45 | E25: ='Bldg 1'!$D$21 -> 19565.8 | F25: ='Bldg 2'!$D$21 -> 17078.94 | G25: ='Bldg 3'!$D$21 -> 19565.8 | H25: ='Bldg 4'!$D$21 -> 17078.94 | I25: ='Bldg 5'!$D$21 -> 19565.8 | J25: ='Bldg 6'!$D$21 -> 17078.94 | K25: ='Bldg 7'!$D$21 -> 19565.8 | L25: ='Bldg 8'!$D$21 -> 17078.94 | M25: ='Bldg 9'!$D$21 -> 17078.94 | N25: =Office!$D$21 -> 3779.55
B26: Total MACRS Reclassification | C26: =SUM(C14:C25) -> 4856162 | D26: =SUM(D14:D25) -> 697363.3 | E26: =SUM(E14:E25) -> 503524.71 | F26: =SUM(F14:F25) -> 397500.19 | G26: =SUM(G14:G25) -> 503524.71 | H26: =SUM(H14:H25) -> 397500.19 | I26: =SUM(I14:I25) -> 503524.71 | J26: =SUM(J14:J25) -> 397500.19 | ... N26: =SUM(N14:N25) -> 157198.91
B27: Difference (should be zero) | C27: =C11-C26 -> 0 | D27: =D11-D26 -> 0 | E27: =E11-E26 -> 0 | F27: =F11-F26 -> 0 | G27: =G11-G26 -> 0 | H27: =H11-H26 -> 0 | I27: =I11-I26 -> 0 | J27: =J11-J26 -> 0 | ... N27: =N11-N26 -> 0
B29: End Depreciation Reconciliation
B30: Before Cost Segregation (As Previously Filed) | C30: =SUM(D30:N30) -> 1601046 | D30: =Site!$I$13 -> 229916.28 | E30: ='Bldg 1'!$I$13 -> 166008.92 | F30: ='Bldg 2'!$I$13 -> 131053.31 | G30: ='Bldg 3'!$I$13 -> 166008.92 | H30: ='Bldg 4'!$I$13 -> 131053.31 | I30: ='Bldg 5'!$I$13 -> 166008.92 | J30: ='Bldg 6'!$I$13 -> 131053.31 | K30: ='Bldg 7'!$I$13 -> 166008.92 | L30: ='Bldg 8'!$I$13 -> 131053.31 | M30: ='Bldg 9'!$I$13 -> 131053.31 | N30: =Office!$I$13 -> 51827.49
B31: 2-Building-7yr | C31: =SUM(D31:N31) -> 1284.15 | D31: =Site!$I$17 -> 1284.15
B32: 2-Building-15yr | C32: =SUM(D32:N32) -> 290971.55 | D32: =Site!$I$18 -> 290971.55
B33: 2-Building-27.5yr | C33: =SUM(D33:N33) -> 340147.25 | D33: =Site!$I$19 -> 28577.82 | E33: ='Bldg 1'!$I$18+'Bldg 1'!$I$20 -> 38182.21 | F33: ='Bldg 2'!$I$18+'Bldg 2'!$I$20 -> 29081.44 | G33: ='Bldg 3'!$I$18+'Bldg 3'!$I$20 -> 38182.21 | H33: ='Bldg 4'!$I$18+'Bldg 4'!$I$20 -> 29081.44 | I33: ='Bldg 5'!$I$18+'Bldg 5'!$I$20 -> 38182.21 | J33: ='Bldg 6'!$I$18+'Bldg 6'!$I$20 -> 29081.44 | K33: ='Bldg 7'!$I$18+'Bldg 7'!$I$20 -> 38182.21 | L33: ='Bldg 8'!$I$18+'Bldg 8'!$I$20 -> 29081.44 | M33: ='Bldg 9'!$I$18+'Bldg 9'!$I$20 -> 29081.44 | N33: =Office!$I$18+Office!$I$20 -> 13433.39
B34: 3-Land Improvements-7yr | C34: =SUM(D34:N34) -> 139.93 | D34: =Site!$I$20 -> 139.93
B35: 3-Land Improvements-15yr | C35: =SUM(D35:N35) -> 31706.69 | D35: =Site!$I$21 -> 31706.69
B36: 3-Land Improvements-27.5yr | C36: =SUM(D36:N36) -> 3114.08 | D36: =Site!$I$22 -> 3114.08
B37: 4-Equipment-7yr | C37: =SUM(D37:N37) -> 262.37 | D37: =Site!$I$23 -> 262.37
B38: 4-Equipment-15yr | C38: =SUM(D38:N38) -> 59450.16 | D38: =Site!$I$24 -> 59450.16
B39: 4-Equipment-27.5yr | C39: =SUM(D39:N39) -> 63242.37 | D39: =Site!$I$25 -> 5838.89 | E39: ='Bldg 1'!$I$22 -> 7034.69 | F39: ='Bldg 2'!$I$22 -> 5357.95 | G39: ='Bldg 3'!$I$22 -> 7034.69 | H39: ='Bldg 4'!$I$22 -> 5357.95 | I39: ='Bldg 5'!$I$22 -> 7034.69 | J39: ='Bldg 6'!$I$22 -> 5357.95 | K39: ='Bldg 7'!$I$22 -> 7034.69 | L39: ='Bldg 8'!$I$22 -> 5357.95 | M39: ='Bldg 9'!$I$22 -> 5357.95 | N39: =Office!$I$22 -> 2474.97
B40: 2-Building-5yr | C40: =SUM(D40:N40) -> 819502.45 | E40: ='Bldg 1'!$I$17 -> 95762.44 | F40: ='Bldg 2'!$I$17 -> 83590.83 | G40: ='Bldg 3'!$I$17 -> 95762.44 | H40: ='Bldg 4'!$I$17 -> 83590.83 | I40: ='Bldg 5'!$I$17 -> 95762.44 | J40: ='Bldg 6'!$I$17 -> 83590.83 | K40: ='Bldg 7'!$I$17 -> 95762.44 | L40: ='Bldg 8'!$I$17 -> 83590.83 | M40: ='Bldg 9'!$I$17 -> 83590.83 | N40: =Office!$I$17 -> 18498.54
B41: 3-Land Improvements-5yr | C41: =SUM(D41:N41) -> 89299.88 | E41: ='Bldg 1'!$I$19 -> 10435.08 | F41: ='Bldg 2'!$I$19 -> 9108.76 | G41: ='Bldg 3'!$I$19 -> 10435.08 | H41: ='Bldg 4'!$I$19 -> 9108.76 | I41: ='Bldg 5'!$I$19 -> 10435.08 | J41: ='Bldg 6'!$I$19 -> 9108.76 | K41: ='Bldg 7'!$I$19 -> 10435.08 | L41: ='Bldg 8'!$I$19 -> 9108.76 | M41: ='Bldg 9'!$I$19 -> 9108.76 | N41: =Office!$I$19 -> 2015.76
B42: 4-Equipment-5yr | C42: =SUM(D42:N42) -> 167437.45 | E42: ='Bldg 1'!$I$21 -> 19565.8 | F42: ='Bldg 2'!$I$21 -> 17078.94 | G42: ='Bldg 3'!$I$21 -> 19565.8 | H42: ='Bldg 4'!$I$21 -> 17078.94 | I42: ='Bldg 5'!$I$21 -> 19565.8 | J42: ='Bldg 6'!$I$21 -> 17078.94 | K42: ='Bldg 7'!$I$21 -> 19565.8 | L42: ='Bldg 8'!$I$21 -> 17078.94 | M42: ='Bldg 9'!$I$21 -> 17078.94 | N42: =Office!$I$21 -> 3779.55
B43: After Cost Segregation (Corrected) | C43: =SUM(C31:C42) -> 1866558.3 | D43: =SUM(D31:D42) -> 421345.64 | E43: =SUM(E31:E42) -> 170980.22 | F43: =SUM(F31:F42) -> 144217.92 | G43: =SUM(G31:G42) -> 170980.22 | H43: =SUM(H31:H42) -> 144217.92 | I43: =SUM(I31:I42) -> 170980.22 | J43: =SUM(J31:J42) -> 144217.92 | ... N43: =SUM(N31:N42) -> 40202.21
B44: Section 481(a) Adjustment | C44: =C30-C43 -> -265512.33 | D44: =D30-D43 -> -191429.36 | E44: =E30-E43 -> -4971.3 | F44: =F30-F43 -> -13164.61 | G44: =G30-G43 -> -4971.3 | H44: =H30-H43 -> -13164.61 | I44: =I30-I43 -> -4971.3 | J44: =J30-J43 -> -13164.61 | ... N44: =N30-N43 -> 11625.28
B45: Check vs. unit-tab 481(a) cells (should be zero) | C45: =C44-(-265512.33) -> 0 | D45: =D44-Site!$D$31 -> 0 | E45: =E44-'Bldg 1'!$D$28 -> 0 | F45: =F44-'Bldg 2'!$D$28 -> 0 | G45: =G44-'Bldg 3'!$D$28 -> 0 | H45: =H44-'Bldg 4'!$D$28 -> 0 | I45: =I44-'Bldg 5'!$D$28 -> 0 | J45: =J44-'Bldg 6'!$D$28 -> 0 | K45: =K44-'Bldg 7'!$D$28 -> 0 | L45: =L44-'Bldg 8'!$D$28 -> 0 | M45: =M44-'Bldg 9'!$D$28 -> 0 | N45: =N44-Office!$D$28 -> 0
B47: Notes
B48: 1. Total footed §481(a) adjustment across all units: -265,512.33 (Regular Tax; AMT equals Regular Tax on every unit in this report).
B49: 2. DISCREPANCY: the CSSI Summary Sheet prints a total of -277,137.61, but its own line items sum to -265,512.33. Unit schedules are internally consistent; the printed total does not foot. Refer to CSSI for correction.
B50: 3. The Form 3115 face page states a tax year of change beginning 1/1/2025, while the attached statements and all 481(a) schedules use a year of change beginning 1/1/2024 (FYE 12/31/2024). Confirm the intended year of change with the preparer before filing.
B51: 4. All End Depreciation, Net Book Value, totals, and 481(a) cells are live formulas; asset-level inputs are transcribed from the CSSI PDF. The Difference and Check rows must remain zero after any edit.

Sheet Site
A1: Coral Village Housing LP
A2: Coral Village — 121 NE 10th Pl, Cape Coral, FL 33909
A3: EIN: 87-2205593 · FYE: December 31, 2024 · Year of Change: 1/1/2024
A4: Site — Attachment to Form 3115 (DCN #7, Rev. Proc. 2024-23 §6.01)
A5: Source: CSSI Report #107752-01, "Coral Village Housing LP - 3115 - 107752-01 - Combined.pdf"
A7: CALCULATION OF §481(a) ADJUSTMENT — REGULAR TAX
A8: As Previously Filed
A9: Asset | B9: Property Description | C9: Date In Service | D9: Cost | E9: Sec 179 Exp | F9: Bonus Amt | G9: Tax Prior Depreciation | H9: Tax Current Depreciation | I9: End Depreciation | J9: Net Book Value | K9: Method | L9: Period
A10: 1 | B10: 2-Building | C10: 9/22/21 | D10: 531007.07 | E10: 0 | F10: 0 | G10: 44250.63 | H10: 19309.42 | I10: =G10+H10 -> 63560.05 | J10: =D10-I10 -> 467447.02 | K10: S/L | L10: 27.5
A11: 2 | B11: 3-Land Improvements | C11: 9/22/21 | D11: 57862.97 | E11: 0 | F11: 57862.97 | G11: 57862.97 | H11: 0 | I11: =G11+H11 -> 57862.97 | J11: =D11-I11 -> 0 | K11: 150DB | L11: 15.0
A12: 3 | B12: 4-Equipment | C12: 9/22/21 | D12: 108493.26 | E12: 0 | F12: 108493.26 | G12: 108493.26 | H12: 0 | I12: =G12+H12 -> 108493.26 | J12: =D12-I12 -> 0 | K12: 200DB | L12: 5.0
B13: Grand Total | D13: =SUM(D10:D12) -> 697363.3 | E13: =SUM(E10:E12) -> 0 | F13: =SUM(F10:F12) -> 166356.23 | G13: =SUM(G10:G12) -> 210606.86 | H13: =SUM(H10:H12) -> 19309.42 | I13: =SUM(I10:I12) -> 229916.28 | J13: =SUM(J10:J12) -> 467447.02
A15: After Cost Segregation Correction
A16: Asset | B16: Property Description | C16: Date In Service | D16: Cost | E16: Sec 179 Exp | F16: Bonus Amt | G16: Tax Prior Depreciation | H16: Tax Current Depreciation | I16: End Depreciation | J16: Net Book Value | K16: Method | L16: Period
A17: 1 | B17: 2-Building-7yr | C17: 9/22/21 | D17: 1284.15 | E17: 0 | F17: 1284.15 | G17: 1284.15 | H17: 0 | I17: =G17+H17 -> 1284.15 | J17: =D17-I17 -> 0 | K17: 200DB | L17: 7.0
A18: 2 | B18: 2-Building-15yr | C18: 9/22/21 | D18: 290971.55 | E18: 0 | F18: 290971.55 | G18: 290971.55 | H18: 0 | I18: =G18+H18 -> 290971.55 | J18: =D18-I18 -> 0 | K18: 150DB | L18: 15.0
A19: 3 | B19: 2-Building-27.5yr | C19: 9/22/21 | D19: 238751.37 | E19: 0 | F19: 0 | G19: 19895.95 | H19: 8681.87 | I19: =G19+H19 -> 28577.82 | J19: =D19-I19 -> 210173.55 | K19: S/L | L19: 27.5
A20: 4 | B20: 3-Land Improvements-7yr | C20: 9/22/21 | D20: 139.93 | E20: 0 | F20: 139.93 | G20: 139.93 | H20: 0 | I20: =G20+H20 -> 139.93 | J20: =D20-I20 -> 0 | K20: 200DB | L20: 7.0
A21: 5 | B21: 3-Land Improvements-15yr | C21: 9/22/21 | D21: 31706.69 | E21: 0 | F21: 31706.69 | G21: 31706.69 | H21: 0 | I21: =G21+H21 -> 31706.69 | J21: =D21-I21 -> 0 | K21: 150DB | L21: 15.0
A22: 6 | B22: 3-Land Improvements-27.5yr | C22: 9/22/21 | D22: 26016.35 | E22: 0 | F22: 0 | G22: 2168.03 | H22: 946.05 | I22: =G22+H22 -> 3114.08 | J22: =D22-I22 -> 22902.27 | K22: S/L | L22: 27.5
A23: 7 | B23: 4-Equipment-7yr | C23: 9/22/21 | D23: 262.37 | E23: 0 | F23: 262.37 | G23: 262.37 | H23: 0 | I23: =G23+H23 -> 262.37 | J23: =D23-I23 -> 0 | K23: 200DB | L23: 7.0
A24: 8 | B24: 4-Equipment-15yr | C24: 9/22/21 | D24: 59450.16 | E24: 0 | F24: 59450.16 | G24: 59450.16 | H24: 0 | I24: =G24+H24 -> 59450.16 | J24: =D24-I24 -> 0 | K24: 150DB | L24: 15.0
A25: 9 | B25: 4-Equipment-27.5yr | C25: 9/22/21 | D25: 48780.73 | E25: 0 | F25: 0 | G25: 4065.05 | H25: 1773.84 | I25: =G25+H25 -> 5838.89 | J25: =D25-I25 -> 42941.84 | K25: S/L | L25: 27.5
B26: Grand Total | D26: =SUM(D17:D25) -> 697363.3 | E26: =SUM(E17:E25) -> 0 | F26: =SUM(F17:F25) -> 383814.85 | G26: =SUM(G17:G25) -> 409943.88 | H26: =SUM(H17:H25) -> 11401.76 | I26: =SUM(I17:I25) -> 421345.64 | J26: =SUM(J17:J25) -> 276017.66
B28: Section 481(a) Adjustment — Regular Tax
B29: Depreciation reported previously | D29: =I13 -> 229916.28
B30: Cost Segregation Corrected Depreciation | D30: =I26 -> 421345.64
B31: Section 481(a) Adjustment — Regular Tax | D31: =D29-D30 -> -191429.36
A33: CALCULATION OF §481(a) ADJUSTMENT — AMT
A34: As Previously Filed — AMT
A35: Asset | B35: Property Description | C35: Date In Service | D35: Cost | E35: Sec 179 Exp | F35: Bonus Amt | G35: AMT Prior Depreciation | H35: AMT Current Depreciation | I35: End Depreciation | J35: Net Book Value | K35: Method | L35: Period
A36: 1 | B36: 2-Building | C36: 9/22/21 | D36: 531007.07 | E36: 0 | F36: 0 | G36: 44250.63 | H36: 19309.42 | I36: =G36+H36 -> 63560.05 | J36: =D36-I36 -> 467447.02 | K36: S/L | L36: 27.5
A37: 2 | B37: 3-Land Improvements | C37: 9/22/21 | D37: 57862.97 | E37: 0 | F37: 57862.97 | G37: 57862.97 | H37: 0 | I37: =G37+H37 -> 57862.97 | J37: =D37-I37 -> 0 | K37: 150DB | L37: 15.0
A38: 3 | B38: 4-Equipment | C38: 9/22/21 | D38: 108493.26 | E38: 0 | F38: 108493.26 | G38: 108493.26 | H38: 0 | I38: =G38+H38 -> 108493.26 | J38: =D38-I38 -> 0 | K38: 200DB | L38: 5.0
B39: Grand Total | D39: =SUM(D36:D38) -> 697363.3 | E39: =SUM(E36:E38) -> 0 | F39: =SUM(F36:F38) -> 166356.23 | G39: =SUM(G36:G38) -> 210606.86 | H39: =SUM(H36:H38) -> 19309.42 | I39: =SUM(I36:I38) -> 229916.28 | J39: =SUM(J36:J38) -> 467447.02
A41: After Cost Segregation Correction — AMT
A42: Asset | B42: Property Description | C42: Date In Service | D42: Cost | E42: Sec 179 Exp | F42: Bonus Amt | G42: AMT Prior Depreciation | H42: AMT Current Depreciation | I42: End Depreciation | J42: Net Book Value | K42: Method | L42: Period
A43: 1 | B43: 2-Building-7yr | C43: 9/22/21 | D43: 1284.15 | E43: 0 | F43: 1284.15 | G43: 1284.15 | H43: 0 | I43: =G43+H43 -> 1284.15 | J43: =D43-I43 -> 0 | K43: 200DB | L43: 7.0
A44: 2 | B44: 2-Building-15yr | C44: 9/22/21 | D44: 290971.55 | E44: 0 | F44: 290971.55 | G44: 290971.55 | H44: 0 | I44: =G44+H44 -> 290971.55 | J44: =D44-I44 -> 0 | K44: 150DB | L44: 15.0
A45: 3 | B45: 2-Building-27.5yr | C45: 9/22/21 | D45: 238751.37 | E45: 0 | F45: 0 | G45: 19895.95 | H45: 8681.87 | I45: =G45+H45 -> 28577.82 | J45: =D45-I45 -> 210173.55 | K45: S/L | L45: 27.5
A46: 4 | B46: 3-Land Improvements-7yr | C46: 9/22/21 | D46: 139.93 | E46: 0 | F46: 139.93 | G46: 139.93 | H46: 0 | I46: =G46+H46 -> 139.93 | J46: =D46-I46 -> 0 | K46: 200DB | L46: 7.0
A47: 5 | B47: 3-Land Improvements-15yr | C47: 9/22/21 | D47: 31706.69 | E47: 0 | F47: 31706.69 | G47: 31706.69 | H47: 0 | I47: =G47+H47 -> 31706.69 | J47: =D47-I47 -> 0 | K47: 150DB | L47: 15.0
A48: 6 | B48: 3-Land Improvements-27.5yr | C48: 9/22/21 | D48: 26016.35 | E48: 0 | F48: 0 | G48: 2168.03 | H48: 946.05 | I48: =G48+H48 -> 3114.08 | J48: =D48-I48 -> 22902.27 | K48: S/L | L48: 27.5
A49: 7 | B49: 4-Equipment-7yr | C49: 9/22/21 | D49: 262.37 | E49: 0 | F49: 262.37 | G49: 262.37 | H49: 0 | I49: =G49+H49 -> 262.37 | J49: =D49-I49 -> 0 | K49: 200DB | L49: 7.0
A50: 8 | B50: 4-Equipment-15yr | C50: 9/22/21 | D50: 59450.16 | E50: 0 | F50: 59450.16 | G50: 59450.16 | H50: 0 | I50: =G50+H50 -> 59450.16 | J50: =D50-I50 -> 0 | K50: 150DB | L50: 15.0
A51: 9 | B51: 4-Equipment-27.5yr | C51: 9/22/21 | D51: 48780.73 | E51: 0 | F51: 0 | G51: 4065.05 | H51: 1773.84 | I51: =G51+H51 -> 5838.89 | J51: =D51-I51 -> 42941.84 | K51: S/L | L51: 27.5
B52: Grand Total | D52: =SUM(D43:D51) -> 697363.3 | E52: =SUM(E43:E51) -> 0 | F52: =SUM(F43:F51) -> 383814.85 | G52: =SUM(G43:G51) -> 409943.88 | H52: =SUM(H43:H51) -> 11401.76 | I52: =SUM(I43:I51) -> 421345.64 | J52: =SUM(J43:J51) -> 276017.66
B54: Section 481(a) Adjustment — AMT
B55: Depreciation reported previously | D55: =I39 -> 229916.28
B56: Cost Segregation Corrected Depreciation | D56: =I52 -> 421345.64
B57: Section 481(a) Adjustment — AMT | D57: =D55-D56 -> -191429.36
A59: COST SEGREGATION STUDY — COST SUMMARY
B60: Total Site Cost | D60: =D89 -> 697363.3
B61: Site Components: 7 Year | D61: =F89 -> 1686.45
B62: % of Cost | D62: =F90 -> 0.0024183234
B63: Site Improvements: 15 Year | D63: =H89 -> 382128.4
B64: % of Cost | D64: =H90 -> 0.54796173
B65: Site Structure: 27.5 Year | D65: =J89 -> 313548.45
B66: % of Cost | D66: =J90 -> 0.44961995
A68: COST SEGREGATION STUDY — COST DETAIL
B69: Property Category | D69: Cost | F69: 7 Year | H69: 15 Year | J69: 27.5 Year
B70: Site Components
B71: Movable Shed | D71: =SUM(F71:J71) -> 1686.45 | F71: 1686.45
B72: Site Work / Improvements
B73: Site Drainage | D73: =SUM(F73:J73) -> 39048.7 | H73: 39048.7
B74: Parking Lot | D74: =SUM(F74:J74) -> 153576.44 | H74: 153576.44
B75: Exterior Signage | D75: =SUM(F75:J75) -> 4980.7 | H75: 4980.7
B76: Parking Lot Striping / Barriers | D76: =SUM(F76:J76) -> 7221.77 | H76: 7221.77
B77: Sidewalks / Curbs | D77: =SUM(F77:J77) -> 84027.83 | H77: 84027.83
B78: Landscaping & Flagpole | D78: =SUM(F78:J78) -> 9631.81 | H78: 9631.81
B79: Security Lighting Poles | D79: =SUM(F79:J79) -> 20401.97 | H79: 20401.97
B80: Exterior Fencing | D80: =SUM(F80:J80) -> 1644.48 | H80: 1644.48
B81: Dumpster Enclosures | D81: =SUM(F81:J81) -> 11153.66 | H81: 11153.66
B82: Swimming Pool | D82: =SUM(F82:J82) -> 24156.38 | H82: 24156.38
B83: Fire Hydrants | D83: =SUM(F83:J83) -> 8313.83 | H83: 8313.83
B84: Wood Bridge | D84: =SUM(F84:J84) -> 424.82 | H84: 424.82
... B86: Mailboxes | D86: =SUM(F86:J86) -> 10157.17 | H86: 10157.17
B87: Site Utilities
B88: Site Utilities | D88: =SUM(F88:J88) -> 313548.45 | J88: 313548.45
B89: Total Site Cost | D89: =SUM(D70:D88) -> 697363.3 | F89: =SUM(F70:F88) -> 1686.45 | H89: =SUM(H70:H88) -> 382128.4 | J89: =SUM(J70:J88) -> 313548.45
B90: % of Cost | F90: =F89/D89 -> 0.0024183234 | H90: =H89/D89 -> 0.54796173 | J90: =J89/D89 -> 0.44961995
A92: ASSET ALLOCATION (per After Cost Segregation schedule)
B93: Asset (as reclassified) | D93: Cost | F93: 7 Year | H93: 15 Year | J93: 27.5 Year
B94: =Site!B17 -> 2-Building-7yr | D94: =SUM(F94:J94) -> 1284.15 | F94: =Site!D17 -> 1284.15
B95: =Site!B18 -> 2-Building-15yr | D95: =SUM(F95:J95) -> 290971.55 | H95: =Site!D18 -> 290971.55
B96: =Site!B19 -> 2-Building-27.5yr | D96: =SUM(F96:J96) -> 238751.37 | J96: =Site!D19 -> 238751.37
B97: =Site!B20 -> 3-Land Improvements-7yr | D97: =SUM(F97:J97) -> 139.93 | F97: =Site!D20 -> 139.93
B98: =Site!B21 -> 3-Land Improvements-15yr | D98: =SUM(F98:J98) -> 31706.69 | H98: =Site!D21 -> 31706.69
B99: =Site!B22 -> 3-Land Improvements-27.5yr | D99: =SUM(F99:J99) -> 26016.35 | J99: =Site!D22 -> 26016.35
B100: =Site!B23 -> 4-Equipment-7yr | D100: =SUM(F100:J100) -> 262.37 | F100: =Site!D23 -> 262.37
B101: =Site!B24 -> 4-Equipment-15yr | D101: =SUM(F101:J101) -> 59450.16 | H101: =Site!D24 -> 59450.16
B102: =Site!B25 -> 4-Equipment-27.5yr | D102: =SUM(F102:J102) -> 48780.73 | J102: =Site!D25 -> 48780.73
B103: Total Allocation | D103: =SUM(D94:D102) -> 697363.3 | F103: =SUM(F94:F102) -> 1686.45 | H103: =SUM(H94:H102) -> 382128.4 | J103: =SUM(J94:J102) -> 313548.45
B104: Check: Allocation vs. Cost Detail (should be zero) | D104: =D103-D89 -> 0

Sheet Bldg 1
A1: Coral Village Housing LP
A2: Coral Village — 121 NE 10th Pl, Cape Coral, FL 33909
A3: EIN: 87-2205593 · FYE: December 31, 2024 · Year of Change: 1/1/2024
A4: Bldg 1 — Attachment to Form 3115 (DCN #7, Rev. Proc. 2024-23 §6.01)
A5: Source: CSSI Report #107752-01, "Coral Village Housing LP - 3115 - 107752-01 - Combined.pdf"
A7: CALCULATION OF §481(a) ADJUSTMENT — REGULAR TAX
A8: As Previously Filed
A9: Asset | B9: Property Description | C9: Date In Service | D9: Cost | E9: Sec 179 Exp | F9: Bonus Amt | G9: Tax Prior Depreciation | H9: Tax Current Depreciation | I9: End Depreciation | J9: Net Book Value | K9: Method | L9: Period
A10: 1 | B10: 2-Building | C10: 9/22/21 | D10: 383408.73 | E10: 0 | F10: 0 | G10: 31950.77 | H10: 13942.17 | I10: =G10+H10 -> 45892.94 | J10: =D10-I10 -> 337515.79 | K10: S/L | L10: 27.5
A11: 2 | B11: 3-Land Improvements | C11: 9/22/21 | D11: 41779.44 | E11: 0 | F11: 41779.44 | G11: 41779.44 | H11: 0 | I11: =G11+H11 -> 41779.44 | J11: =D11-I11 -> 0 | K11: 150DB | L11: 15.0
A12: 3 | B12: 4-Equipment | C12: 9/22/21 | D12: 78336.54 | E12: 0 | F12: 78336.54 | G12: 78336.54 | H12: 0 | I12: =G12+H12 -> 78336.54 | J12: =D12-I12 -> 0 | K12: 200DB | L12: 5.0
B13: Grand Total | D13: =SUM(D10:D12) -> 503524.71 | E13: =SUM(E10:E12) -> 0 | F13: =SUM(F10:F12) -> 120115.98 | G13: =SUM(G10:G12) -> 152066.75 | H13: =SUM(H10:H12) -> 13942.17 | I13: =SUM(I10:I12) -> 166008.92 | J13: =SUM(J10:J12) -> 337515.79
A15: After Cost Segregation Correction
A16: Asset | B16: Property Description | C16: Date In Service | D16: Cost | E16: Sec 179 Exp | F16: Bonus Amt | G16: Tax Prior Depreciation | H16: Tax Current Depreciation | I16: End Depreciation | J16: Net Book Value | K16: Method | L16: Period
A17: 1 | B17: 2-Building-5yr | C17: 9/22/21 | D17: 95762.44 | E17: 0 | F17: 95762.44 | G17: 95762.44 | H17: 0 | I17: =G17+H17 -> 95762.44 | J17: =D17-I17 -> 0 | K17: 200DB | L17: 5.0
A18: 2 | B18: 2-Building-27.5yr | C18: 9/22/21 | D18: 287646.29 | E18: 0 | F18: 0 | G18: 23970.53 | H18: 10459.87 | I18: =G18+H18 -> 34430.4 | J18: =D18-I18 -> 253215.89 | K18: S/L | L18: 27.5
A19: 3 | B19: 3-Land Improvements-5yr | C19: 9/22/21 | D19: 10435.08 | E19: 0 | F19: 10435.08 | G19: 10435.08 | H19: 0 | I19: =G19+H19 -> 10435.08 | J19: =D19-I19 -> 0 | K19: 200DB | L19: 5.0
A20: 4 | B20: 2-Building-27.5yr | C20: 9/22/21 | D20: 31344.36 | E20: 0 | F20: 0 | G20: 2612.02 | H20: 1139.79 | I20: =G20+H20 -> 3751.81 | J20: =D20-I20 -> 27592.55 | K20: S/L | L20: 27.5
A21: 5 | B21: 4-Equipment-5yr | C21: 9/22/21 | D21: 19565.8 | E21: 0 | F21: 19565.8 | G21: 19565.8 | H21: 0 | I21: =G21+H21 -> 19565.8 | J21: =D21-I21 -> 0 | K21: 200DB | L21: 5.0
A22: 6 | B22: 4-Equipment-27.5yr | C22: 9/22/21 | D22: 58770.74 | E22: 0 | F22: 0 | G22: 4897.57 | H22: 2137.12 | I22: =G22+H22 -> 7034.69 | J22: =D22-I22 -> 51736.05 | K22: S/L | L22: 27.5
B23: Grand Total | D23: =SUM(D17:D22) -> 503524.71 | E23: =SUM(E17:E22) -> 0 | F23: =SUM(F17:F22) -> 125763.32 | G23: =SUM(G17:G22) -> 157243.44 | H23: =SUM(H17:H22) -> 13736.78 | I23: =SUM(I17:I22) -> 170980.22 | J23: =SUM(J17:J22) -> 332544.49
B25: Section 481(a) Adjustment — Regular Tax
B26: Depreciation reported previously | D26: =I13 -> 166008.92
B27: Cost Segregation Corrected Depreciation | D27: =I23 -> 170980.22
B28: Section 481(a) Adjustment — Regular Tax | D28: =D26-D27 -> -4971.3
A30: CALCULATION OF §481(a) ADJUSTMENT — AMT
A31: As Previously Filed — AMT
A32: Asset | B32: Property Description | C32: Date In Service | D32: Cost | E32: Sec 179 Exp | F32: Bonus Amt | G32: AMT Prior Depreciation | H32: AMT Current Depreciation | I32: End Depreciation | J32: Net Book Value | K32: Method | L32: Period
A33: 1 | B33: 2-Building | C33: 9/22/21 | D33: 383408.73 | E33: 0 | F33: 0 | G33: 31950.77 | H33: 13942.17 | I33: =G33+H33 -> 45892.94 | J33: =D33-I33 -> 337515.79 | K33: S/L | L33: 27.5
A34: 2 | B34: 3-Land Improvements | C34: 9/22/21 | D34: 41779.44 | E34: 0 | F34: 41779.44 | G34: 41779.44 | H34: 0 | I34: =G34+H34 -> 41779.44 | J34: =D34-I34 -> 0 | K34: 150DB | L34: 15.0
A35: 3 | B35: 4-Equipment | C35: 9/22/21 | D35: 78336.54 | E35: 0 | F35: 78336.54 | G35: 78336.54 | H35: 0 | I35: =G35+H35 -> 78336.54 | J35: =D35-I35 -> 0 | K35: 200DB | L35: 5.0
B36: Grand Total | D36: =SUM(D33:D35) -> 503524.71 | E36: =SUM(E33:E35) -> 0 | F36: =SUM(F33:F35) -> 120115.98 | G36: =SUM(G33:G35) -> 152066.75 | H36: =SUM(H33:H35) -> 13942.17 | I36: =SUM(I33:I35) -> 166008.92 | J36: =SUM(J33:J35) -> 337515.79
A38: After Cost Segregation Correction — AMT
A39: Asset | B39: Property Description | C39: Date In Service | D39: Cost | E39: Sec 179 Exp | F39: Bonus Amt | G39: AMT Prior Depreciation | H39: AMT Current Depreciation | I39: End Depreciation | J39: Net Book Value | K39: Method | L39: Period
A40: 1 | B40: 2-Building-5yr | C40: 9/22/21 | D40: 95762.44 | E40: 0 | F40: 95762.44 | G40: 95762.44 | H40: 0 | I40: =G40+H40 -> 95762.44 | J40: =D40-I40 -> 0 | K40: 200DB | L40: 5.0
A41: 2 | B41: 2-Building-27.5yr | C41: 9/22/21 | D41: 287646.29 | E41: 0 | F41: 0 | G41: 23970.53 | H41: 10459.87 | I41: =G41+H41 -> 34430.4 | J41: =D41-I41 -> 253215.89 | K41: S/L | L41: 27.5
A42: 3 | B42: 3-Land Improvements-5yr | C42: 9/22/21 | D42: 10435.08 | E42: 0 | F42: 10435.08 | G42: 10435.08 | H42: 0 | I42: =G42+H42 -> 10435.08 | J42: =D42-I42 -> 0 | K42: 200DB | L42: 5.0
A43: 4 | B43: 2-Building-27.5yr | C43: 9/22/21 | D43: 31344.36 | E43: 0 | F43: 0 | G43: 2612.02 | H43: 1139.79 | I43: =G43+H43 -> 3751.81 | J43: =D43-I43 -> 27592.55 | K43: S/L | L43: 27.5
A44: 5 | B44: 4-Equipment-5yr | C44: 9/22/21 | D44: 19565.8 | E44: 0 | F44: 19565.8 | G44: 19565.8 | H44: 0 | I44: =G44+H44 -> 19565.8 | J44: =D44-I44 -> 0 | K44: 200DB | L44: 5.0
A45: 6 | B45: 4-Equipment-27.5yr | C45: 9/22/21 | D45: 58770.74 | E45: 0 | F45: 0 | G45: 4897.57 | H45: 2137.12 | I45: =G45+H45 -> 7034.69 | J45: =D45-I45 -> 51736.05 | K45: S/L | L45: 27.5
B46: Grand Total | D46: =SUM(D40:D45) -> 503524.71 | E46: =SUM(E40:E45) -> 0 | F46: =SUM(F40:F45) -> 125763.32 | G46: =SUM(G40:G45) -> 157243.44 | H46: =SUM(H40:H45) -> 13736.78 | I46: =SUM(I40:I45) -> 170980.22 | J46: =SUM(J40:J45) -> 332544.49
B48: Section 481(a) Adjustment — AMT
B49: Depreciation reported previously | D49: =I36 -> 166008.92
B50: Cost Segregation Corrected Depreciation | D50: =I46 -> 170980.22
B51: Section 481(a) Adjustment — AMT | D51: =D49-D50 -> -4971.3
A53: COST SEGREGATION STUDY — COST SUMMARY
B54: Total Building Cost | D54: =D93 -> 503524.71
B55: Building Components: 5 Year | D55: =F93 -> 125763.32
B56: % of Cost | D56: =F94 -> 0.24976594
B57: Building Structure: 27.5 Year | D57: =H93 -> 377761.39
B58: % of Cost | D58: =H94 -> 0.75023406
A60: COST SEGREGATION STUDY — COST DETAIL
B61: Property Category | D61: Cost | F61: 5 Year | H61: 27.5 Year
B62: Building Components
B63: Cabinets / Millwork | D63: =SUM(F63:H63) -> 26757.81 | F63: 26757.81
B64: Moldings | D64: =SUM(F64:H64) -> 7990.89 | F64: 7990.89
B65: Flooring - Vinyl Plank | D65: =SUM(F65:H65) -> 37800.94 | F65: 37800.94
B66: Door & Window Guards | D66: =SUM(F66:H66) -> 2842.52 | F66: 2842.52
B67: Window Treatments | D67: =SUM(F67:H67) -> 2418.44 | F67: 2418.44
B68: Specialty HVAC - Dryer Vents | D68: =SUM(F68:H68) -> 718.3 | F68: 718.3
B69: Building Signage | D69: =SUM(F69:H69) -> 705.03 | F69: 705.03
B70: Specialty Electrical - Appliances | D70: =SUM(F70:H70) -> 12363.8 | F70: 12363.8
B71: Communication / Data | D71: =SUM(F71:H71) -> 3400.77 | F71: 3400.77
B72: Specialty Plumbing - Kitchen Sinks / Laundry | D72: =SUM(F72:H72) -> 13431.92 | F72: 13431.92
B73: Security / Exterior Lighting | D73: =SUM(F73:H73) -> 1140.5 | F73: 1140.5
B74: Access Control | D74: =SUM(F74:H74) -> 1360.86 | F74: 1360.86
B75: Appliances | D75: =SUM(F75:H75) -> 14831.54 | F75: 14831.54
B76: Building Structure
B77: Foundations | D77: =SUM(F77:H77) -> 25110.72 | H77: 25110.72
B78: HVAC | D78: =SUM(F78:H78) -> 35390.34 | H78: 35390.34
B79: Electrical | D79: =SUM(F79:H79) -> 29008.33 | H79: 29008.33
B80: Plumbing | D80: =SUM(F80:H80) -> 31389.04 | H80: 31389.04
B81: Fire Protection & Alarm | D81: =SUM(F81:H81) -> 26496.62 | H81: 26496.62
B82: Exterior Façade / Building Skin | D82: =SUM(F82:H82) -> 12009.05 | H82: 12009.05
B83: Doors & Frames | D83: =SUM(F83:H83) -> 23153.47 | H83: 23153.47
B84: Windows | D84: =SUM(F84:H84) -> 10659.46 | H84: 10659.46
B85: Ceiling Systems | D85: =SUM(F85:H85) -> 16835.06 | H85: 16835.06
B86: Interior Framing / Partitions | D86: =SUM(F86:H86) -> 39604.25 | H86: 39604.25
B87: Painting | D87: =SUM(F87:H87) -> 16001 | H87: 16001
B88: Gutter Systems | D88: =SUM(F88:H88) -> 1863.69 | H88: 1863.69
... B92: Cabinets / Millwork - Restrooms | D92: =SUM(F92:H92) -> 6970.48 | H92: 6970.48
B93: Total Building Cost | D93: =SUM(D62:D92) -> 503524.71 | F93: =SUM(F62:F92) -> 125763.32 | H93: =SUM(H62:H92) -> 377761.39
B94: % of Cost | F94: =F93/D93 -> 0.24976594 | H94: =H93/D93 -> 0.75023406
A96: ASSET ALLOCATION (per After Cost Segregation schedule)
B97: Asset (as reclassified) | D97: Cost | F97: 5 Year | H97: 27.5 Year
B98: ='Bldg 1'!B17 -> 2-Building-5yr | D98: =SUM(F98:H98) -> 95762.44 | F98: ='Bldg 1'!D17 -> 95762.44
B99: ='Bldg 1'!B18 -> 2-Building-27.5yr | D99: =SUM(F99:H99) -> 287646.29 | H99: ='Bldg 1'!D18 -> 287646.29
B100: ='Bldg 1'!B19 -> 3-Land Improvements-5yr | D100: =SUM(F100:H100) -> 10435.08 | F100: ='Bldg 1'!D19 -> 10435.08
B101: ='Bldg 1'!B20 -> 2-Building-27.5yr | D101: =SUM(F101:H101) -> 31344.36 | H101: ='Bldg 1'!D20 -> 31344.36
B102: ='Bldg 1'!B21 -> 4-Equipment-5yr | D102: =SUM(F102:H102) -> 19565.8 | F102: ='Bldg 1'!D21 -> 19565.8
B103: ='Bldg 1'!B22 -> 4-Equipment-27.5yr | D103: =SUM(F103:H103) -> 58770.74 | H103: ='Bldg 1'!D22 -> 58770.74
B104: Total Allocation | D104: =SUM(D98:D103) -> 503524.71 | F104: =SUM(F98:F103) -> 125763.32 | H104: =SUM(H98:H103) -> 377761.39
B105: Check: Allocation vs. Cost Detail (should be zero) | D105: =D104-D93 -> 0

Sheet Bldg 2
A1: Coral Village Housing LP
A2: Coral Village — 121 NE 10th Pl, Cape Coral, FL 33909
A3: EIN: 87-2205593 · FYE: December 31, 2024 · Year of Change: 1/1/2024
A4: Bldg 2 — Attachment to Form 3115 (DCN #7, Rev. Proc. 2024-23 §6.01)
A5: Source: CSSI Report #107752-01, "Coral Village Housing LP - 3115 - 107752-01 - Combined.pdf"
A7: CALCULATION OF §481(a) ADJUSTMENT — REGULAR TAX
A8: As Previously Filed
A9: Asset | B9: Property Description | C9: Date In Service | D9: Cost | E9: Sec 179 Exp | F9: Bonus Amt | G9: Tax Prior Depreciation | H9: Tax Current Depreciation | I9: End Depreciation | J9: Net Book Value | K9: Method | L9: Period
A10: 1 | B10: 2-Building | C10: 9/22/21 | D10: 302676.39 | E10: 0 | F10: 0 | G10: 25223.07 | H10: 11006.44 | I10: =G10+H10 -> 36229.51 | J10: =D10-I10 -> 266446.88 | K10: S/L | L10: 27.5
A11: 2 | B11: 3-Land Improvements | C11: 9/22/21 | D11: 32982.17 | E11: 0 | F11: 32982.17 | G11: 32982.17 | H11: 0 | I11: =G11+H11 -> 32982.17 | J11: =D11-I11 -> 0 | K11: 150DB | L11: 15.0
A12: 3 | B12: 4-Equipment | C12: 9/22/21 | D12: 61841.63 | E12: 0 | F12: 61841.63 | G12: 61841.63 | H12: 0 | I12: =G12+H12 -> 61841.63 | J12: =D12-I12 -> 0 | K12: 200DB | L12: 5.0
B13: Grand Total | D13: =SUM(D10:D12) -> 397500.19 | E13: =SUM(E10:E12) -> 0 | F13: =SUM(F10:F12) -> 94823.8 | G13: =SUM(G10:G12) -> 120046.87 | H13: =SUM(H10:H12) -> 11006.44 | I13: =SUM(I10:I12) -> 131053.31 | J13: =SUM(J10:J12) -> 266446.88
A15: After Cost Segregation Correction
A16: Asset | B16: Property Description | C16: Date In Service | D16: Cost | E16: Sec 179 Exp | F16: Bonus Amt | G16: Tax Prior Depreciation | H16: Tax Current Depreciation | I16: End Depreciation | J16: Net Book Value | K16: Method | L16: Period
A17: 1 | B17: 2-Building-5yr | C17: 9/22/21 | D17: 83590.83 | E17: 0 | F17: 83590.83 | G17: 83590.83 | H17: 0 | I17: =G17+H17 -> 83590.83 | J17: =D17-I17 -> 0 | K17: 200DB | L17: 5.0
A18: 2 | B18: 2-Building-27.5yr | C18: 9/22/21 | D18: 219085.56 | E18: 0 | F18: 0 | G18: 18257.13 | H18: 7966.75 | I18: =G18+H18 -> 26223.88 | J18: =D18-I18 -> 192861.68 | K18: S/L | L18: 27.5
A19: 3 | B19: 3-Land Improvements-5yr | C19: 9/22/21 | D19: 9108.76 | E19: 0 | F19: 9108.76 | G19: 9108.76 | H19: 0 | I19: =G19+H19 -> 9108.76 | J19: =D19-I19 -> 0 | K19: 200DB | L19: 5.0
A20: 4 | B20: 2-Building-27.5yr | C20: 9/22/21 | D20: 23873.41 | E20: 0 | F20: 0 | G20: 1989.44 | H20: 868.12 | I20: =G20+H20 -> 2857.56 | J20: =D20-I20 -> 21015.85 | K20: S/L | L20: 27.5
A21: 5 | B21: 4-Equipment-5yr | C21: 9/22/21 | D21: 17078.94 | E21: 0 | F21: 17078.94 | G21: 17078.94 | H21: 0 | I21: =G21+H21 -> 17078.94 | J21: =D21-I21 -> 0 | K21: 200DB | L21: 5.0
A22: 6 | B22: 4-Equipment-27.5yr | C22: 9/22/21 | D22: 44762.69 | E22: 0 | F22: 0 | G22: 3730.22 | H22: 1627.73 | I22: =G22+H22 -> 5357.95 | J22: =D22-I22 -> 39404.74 | K22: S/L | L22: 27.5
B23: Grand Total | D23: =SUM(D17:D22) -> 397500.19 | E23: =SUM(E17:E22) -> 0 | F23: =SUM(F17:F22) -> 109778.53 | G23: =SUM(G17:G22) -> 133755.32 | H23: =SUM(H17:H22) -> 10462.6 | I23: =SUM(I17:I22) -> 144217.92 | J23: =SUM(J17:J22) -> 253282.27
B25: Section 481(a) Adjustment — Regular Tax
B26: Depreciation reported previously | D26: =I13 -> 131053.31
B27: Cost Segregation Corrected Depreciation | D27: =I23 -> 144217.92
B28: Section 481(a) Adjustment — Regular Tax | D28: =D26-D27 -> -13164.61
A30: CALCULATION OF §481(a) ADJUSTMENT — AMT
A31: As Previously Filed — AMT
A32: Asset | B32: Property Description | C32: Date In Service | D32: Cost | E32: Sec 179 Exp | F32: Bonus Amt | G32: AMT Prior Depreciation | H32: AMT Current Depreciation | I32: End Depreciation | J32: Net Book Value | K32: Method | L32: Period
A33: 1 | B33: 2-Building | C33: 9/22/21 | D33: 302676.39 | E33: 0 | F33: 0 | G33: 25223.07 | H33: 11006.44 | I33: =G33+H33 -> 36229.51 | J33: =D33-I33 -> 266446.88 | K33: S/L | L33: 27.5
A34: 2 | B34: 3-Land Improvements | C34: 9/22/21 | D34: 32982.17 | E34: 0 | F34: 32982.17 | G34: 32982.17 | H34: 0 | I34: =G34+H34 -> 32982.17 | J34: =D34-I34 -> 0 | K34: 150DB | L34: 15.0
A35: 3 | B35: 4-Equipment | C35: 9/22/21 | D35: 61841.63 | E35: 0 | F35: 61841.63 | G35: 61841.63 | H35: 0 | I35: =G35+H35 -> 61841.63 | J35: =D35-I35 -> 0 | K35: 200DB | L35: 5.0
B36: Grand Total | D36: =SUM(D33:D35) -> 397500.19 | E36: =SUM(E33:E35) -> 0 | F36: =SUM(F33:F35) -> 94823.8 | G36: =SUM(G33:G35) -> 120046.87 | H36: =SUM(H33:H35) -> 11006.44 | I36: =SUM(I33:I35) -> 131053.31 | J36: =SUM(J33:J35) -> 266446.88
A38: After Cost Segregation Correction — AMT
A39: Asset | B39: Property Description | C39: Date In Service | D39: Cost | E39: Sec 179 Exp | F39: Bonus Amt | G39: AMT Prior Depreciation | H39: AMT Current Depreciation | I39: End Depreciation | J39: Net Book Value | K39: Method | L39: Period
A40: 1 | B40: 2-Building-5yr | C40: 9/22/21 | D40: 83590.83 | E40: 0 | F40: 83590.83 | G40: 83590.83 | H40: 0 | I40: =G40+H40 -> 83590.83 | J40: =D40-I40 -> 0 | K40: 200DB | L40: 5.0
A41: 2 | B41: 2-Building-27.5yr | C41: 9/22/21 | D41: 219085.56 | E41: 0 | F41: 0 | G41: 18257.13 | H41: 7966.75 | I41: =G41+H41 -> 26223.88 | J41: =D41-I41 -> 192861.68 | K41: S/L | L41: 27.5
A42: 3 | B42: 3-Land Improvements-5yr | C42: 9/22/21 | D42: 9108.76 | E42: 0 | F42: 9108.76 | G42: 9108.76 | H42: 0 | I42: =G42+H42 -> 9108.76 | J42: =D42-I42 -> 0 | K42: 200DB | L42: 5.0
A43: 4 | B43: 2-Building-27.5yr | C43: 9/22/21 | D43: 23873.41 | E43: 0 | F43: 0 | G43: 1989.44 | H43: 868.12 | I43: =G43+H43 -> 2857.56 | J43: =D43-I43 -> 21015.85 | K43: S/L | L43: 27.5
A44: 5 | B44: 4-Equipment-5yr | C44: 9/22/21 | D44: 17078.94 | E44: 0 | F44: 17078.94 | G44: 17078.94 | H44: 0 | I44: =G44+H44 -> 17078.94 | J44: =D44-I44 -> 0 | K44: 200DB | L44: 5.0
A45: 6 | B45: 4-Equipment-27.5yr | C45: 9/22/21 | D45: 44762.69 | E45: 0 | F45: 0 | G45: 3730.22 | H45: 1627.73 | I45: =G45+H45 -> 5357.95 | J45: =D45-I45 -> 39404.74 | K45: S/L | L45: 27.5
B46: Grand Total | D46: =SUM(D40:D45) -> 397500.19 | E46: =SUM(E40:E45) -> 0 | F46: =SUM(F40:F45) -> 109778.53 | G46: =SUM(G40:G45) -> 133755.32 | H46: =SUM(H40:H45) -> 10462.6 | I46: =SUM(I40:I45) -> 144217.92 | J46: =SUM(J40:J45) -> 253282.27
B48: Section 481(a) Adjustment — AMT
B49: Depreciation reported previously | D49: =I36 -> 131053.31
B50: Cost Segregation Corrected Depreciation | D50: =I46 -> 144217.92
B51: Section 481(a) Adjustment — AMT | D51: =D49-D50 -> -13164.61
A53: COST SEGREGATION STUDY — COST SUMMARY
B54: Total Building Cost | D54: =D94 -> 397500.19
B55: Building Components: 5 Year | D55: =F94 -> 109778.53
B56: % of Cost | D56: =F95 -> 0.27617227
B57: Building Structure: 27.5 Year | D57: =H94 -> 287721.66
B58: % of Cost | D58: =H95 -> 0.72382773
A60: COST SEGREGATION STUDY — COST DETAIL
B61: Property Category | D61: Cost | F61: 5 Year | H61: 27.5 Year
B62: Building Components
B63: Cabinets / Millwork | D63: =SUM(F63:H63) -> 26445.19 | F63: 26445.19
B64: Moldings | D64: =SUM(F64:H64) -> 4635.69 | F64: 4635.69
B65: Flooring - Carpet | D65: =SUM(F65:H65) -> 9118.09 | F65: 9118.09
B66: Flooring - Vinyl Plank | D66: =SUM(F66:H66) -> 17166.07 | F66: 17166.07
B67: Door & Window Guards | D67: =SUM(F67:H67) -> 2842.52 | F67: 2842.52
B68: Window Treatments | D68: =SUM(F68:H68) -> 2418.44 | F68: 2418.44
B69: Specialty HVAC - Dryer Vents | D69: =SUM(F69:H69) -> 718.3 | F69: 718.3
B70: Building Signage | D70: =SUM(F70:H70) -> 705.03 | F70: 705.03
B71: Specialty Electrical - Appliances | D71: =SUM(F71:H71) -> 12363.8 | F71: 12363.8
B72: Communication / Data | D72: =SUM(F72:H72) -> 2600.58 | F72: 2600.58
B73: Specialty Plumbing - Kitchen Sinks / Laundry | D73: =SUM(F73:H73) -> 13431.92 | F73: 13431.92
B74: Security / Exterior Lighting | D74: =SUM(F74:H74) -> 1140.5 | F74: 1140.5
... B76: Appliances | D76: =SUM(F76:H76) -> 14831.54 | F76: 14831.54
B77: Building Structure
B78: Foundations | D78: =SUM(F78:H78) -> 19166.81 | H78: 19166.81
B79: HVAC | D79: =SUM(F79:H79) -> 26894.18 | H79: 26894.18
B80: Electrical | D80: =SUM(F80:H80) -> 19273.71 | H80: 19273.71
B81: Plumbing | D81: =SUM(F81:H81) -> 24003.39 | H81: 24003.39
B82: Fire Protection & Alarm | D82: =SUM(F82:H82) -> 23233.4 | H82: 23233.4
B83: Exterior Façade / Building Skin | D83: =SUM(F83:H83) -> 8832.92 | H83: 8832.92
B84: Doors & Frames | D84: =SUM(F84:H84) -> 17315.31 | H84: 17315.31
B85: Windows | D85: =SUM(F85:H85) -> 10659.46 | H85: 10659.46
B86: Ceiling Systems | D86: =SUM(F86:H86) -> 12873.87 | H86: 12873.87
B87: Interior Framing / Partitions | D87: =SUM(F87:H87) -> 29302.11 | H87: 29302.11
B88: Painting | D88: =SUM(F88:H88) -> 11976.41 | H88: 11976.41
B89: Gutter Systems | D89: =SUM(F89:H89) -> 1737.32 | H89: 1737.32
... B93: Cabinets / Millwork - Restrooms | D93: =SUM(F93:H93) -> 3303.27 | H93: 3303.27
B94: Total Building Cost | D94: =SUM(D62:D93) -> 397500.19 | F94: =SUM(F62:F93) -> 109778.53 | H94: =SUM(H62:H93) -> 287721.66
B95: % of Cost | F95: =F94/D94 -> 0.27617227 | H95: =H94/D94 -> 0.72382773
A97: ASSET ALLOCATION (per After Cost Segregation schedule)
B98: Asset (as reclassified) | D98: Cost | F98: 5 Year | H98: 27.5 Year
B99: ='Bldg 2'!B17 -> 2-Building-5yr | D99: =SUM(F99:H99) -> 83590.83 | F99: ='Bldg 2'!D17 -> 83590.83
B100: ='Bldg 2'!B18 -> 2-Building-27.5yr | D100: =SUM(F100:H100) -> 219085.56 | H100: ='Bldg 2'!D18 -> 219085.56
B101: ='Bldg 2'!B19 -> 3-Land Improvements-5yr | D101: =SUM(F101:H101) -> 9108.76 | F101: ='Bldg 2'!D19 -> 9108.76
B102: ='Bldg 2'!B20 -> 2-Building-27.5yr | D102: =SUM(F102:H102) -> 23873.41 | H102: ='Bldg 2'!D20 -> 23873.41
B103: ='Bldg 2'!B21 -> 4-Equipment-5yr | D103: =SUM(F103:H103) -> 17078.94 | F103: ='Bldg 2'!D21 -> 17078.94
B104: ='Bldg 2'!B22 -> 4-Equipment-27.5yr | D104: =SUM(F104:H104) -> 44762.69 | H104: ='Bldg 2'!D22 -> 44762.69
B105: Total Allocation | D105: =SUM(D99:D104) -> 397500.19 | F105: =SUM(F99:F104) -> 109778.53 | H105: =SUM(H99:H104) -> 287721.66
B106: Check: Allocation vs. Cost Detail (should be zero) | D106: =D105-D94 -> 0

Sheet Bldg 3
A1: Coral Village Housing LP
A2: Coral Village — 121 NE 10th Pl, Cape Coral, FL 33909
A3: EIN: 87-2205593 · FYE: December 31, 2024 · Year of Change: 1/1/2024
A4: Bldg 3 — Attachment to Form 3115 (DCN #7, Rev. Proc. 2024-23 §6.01)
A5: Source: CSSI Report #107752-01, "Coral Village Housing LP - 3115 - 107752-01 - Combined.pdf"
A7: CALCULATION OF §481(a) ADJUSTMENT — REGULAR TAX
A8: As Previously Filed
A9: Asset | B9: Property Description | C9: Date In Service | D9: Cost | E9: Sec 179 Exp | F9: Bonus Amt | G9: Tax Prior Depreciation | H9: Tax Current Depreciation | I9: End Depreciation | J9: Net Book Value | K9: Method | L9: Period
A10: 1 | B10: 2-Building | C10: 9/22/21 | D10: 383408.73 | E10: 0 | F10: 0 | G10: 31950.77 | H10: 13942.17 | I10: =G10+H10 -> 45892.94 | J10: =D10-I10 -> 337515.79 | K10: S/L | L10: 27.5
A11: 2 | B11: 3-Land Improvements | C11: 9/22/21 | D11: 41779.44 | E11: 0 | F11: 41779.44 | G11: 41779.44 | H11: 0 | I11: =G11+H11 -> 41779.44 | J11: =D11-I11 -> 0 | K11: 150DB | L11: 15.0
A12: 3 | B12: 4-Equipment | C12: 9/22/21 | D12: 78336.54 | E12: 0 | F12: 78336.54 | G12: 78336.54 | H12: 0 | I12: =G12+H12 -> 78336.54 | J12: =D12-I12 -> 0 | K12: 200DB | L12: 5.0
B13: Grand Total | D13: =SUM(D10:D12) -> 503524.71 | E13: =SUM(E10:E12) -> 0 | F13: =SUM(F10:F12) -> 120115.98 | G13: =SUM(G10:G12) -> 152066.75 | H13: =SUM(H10:H12) -> 13942.17 | I13: =SUM(I10:I12) -> 166008.92 | J13: =SUM(J10:J12) -> 337515.79
A15: After Cost Segregation Correction
A16: Asset | B16: Property Description | C16: Date In Service | D16: Cost | E16: Sec 179 Exp | F16: Bonus Amt | G16: Tax Prior Depreciation | H16: Tax Current Depreciation | I16: End Depreciation | J16: Net Book Value | K16: Method | L16: Period
A17: 1 | B17: 2-Building-5yr | C17: 9/22/21 | D17: 95762.44 | E17: 0 | F17: 95762.44 | G17: 95762.44 | H17: 0 | I17: =G17+H17 -> 95762.44 | J17: =D17-I17 -> 0 | K17: 200DB | L17: 5.0
A18: 2 | B18: 2-Building-27.5yr | C18: 9/22/21 | D18: 287646.29 | E18: 0 | F18: 0 | G18: 23970.53 | H18: 10459.87 | I18: =G18+H18 -> 34430.4 | J18: =D18-I18 -> 253215.89 | K18: S/L | L18: 27.5
A19: 3 | B19: 3-Land Improvements-5yr | C19: 9/22/21 | D19: 10435.08 | E19: 0 | F19: 10435.08 | G19: 10435.08 | H19: 0 | I19: =G19+H19 -> 10435.08 | J19: =D19-I19 -> 0 | K19: 200DB | L19: 5.0
A20: 4 | B20: 2-Building-27.5yr | C20: 9/22/21 | D20: 31344.36 | E20: 0 | F20: 0 | G20: 2612.02 | H20: 1139.79 | I20: =G20+H20 -> 3751.81 | J20: =D20-I20 -> 27592.55 | K20: S/L | L20: 27.5
A21: 5 | B21: 4-Equipment-5yr | C21: 9/22/21 | D21: 19565.8 | E21: 0 | F21: 19565.8 | G21: 19565.8 | H21: 0 | I21: =G21+H21 -> 19565.8 | J21: =D21-I21 -> 0 | K21: 200DB | L21: 5.0
A22: 6 | B22: 4-Equipment-27.5yr | C22: 9/22/21 | D22: 58770.74 | E22: 0 | F22: 0 | G22: 4897.57 | H22: 2137.12 | I22: =G22+H22 -> 7034.69 | J22: =D22-I22 -> 51736.05 | K22: S/L | L22: 27.5
B23: Grand Total | D23: =SUM(D17:D22) -> 503524.71 | E23: =SUM(E17:E22) -> 0 | F23: =SUM(F17:F22) -> 125763.32 | G23: =SUM(G17:G22) -> 157243.44 | H23: =SUM(H17:H22) -> 13736.78 | I23: =SUM(I17:I22) -> 170980.22 | J23: =SUM(J17:J22) -> 332544.49
B25: Section 481(a) Adjustment — Regular Tax
B26: Depreciation reported previously | D26: =I13 -> 166008.92
B27: Cost Segregation Corrected Depreciation | D27: =I23 -> 170980.22
B28: Section 481(a) Adjustment — Regular Tax | D28: =D26-D27 -> -4971.3
A30: CALCULATION OF §481(a) ADJUSTMENT — AMT
A31: As Previously Filed — AMT
A32: Asset | B32: Property Description | C32: Date In Service | D32: Cost | E32: Sec 179 Exp | F32: Bonus Amt | G32: AMT Prior Depreciation | H32: AMT Current Depreciation | I32: End Depreciation | J32: Net Book Value | K32: Method | L32: Period
A33: 1 | B33: 2-Building | C33: 9/22/21 | D33: 383408.73 | E33: 0 | F33: 0 | G33: 31950.77 | H33: 13942.17 | I33: =G33+H33 -> 45892.94 | J33: =D33-I33 -> 337515.79 | K33: S/L | L33: 27.5
A34: 2 | B34: 3-Land Improvements | C34: 9/22/21 | D34: 41779.44 | E34: 0 | F34: 41779.44 | G34: 41779.44 | H34: 0 | I34: =G34+H34 -> 41779.44 | J34: =D34-I34 -> 0 | K34: 150DB | L34: 15.0
A35: 3 | B35: 4-Equipment | C35: 9/22/21 | D35: 78336.54 | E35: 0 | F35: 78336.54 | G35: 78336.54 | H35: 0 | I35: =G35+H35 -> 78336.54 | J35: =D35-I35 -> 0 | K35: 200DB | L35: 5.0
B36: Grand Total | D36: =SUM(D33:D35) -> 503524.71 | E36: =SUM(E33:E35) -> 0 | F36: =SUM(F33:F35) -> 120115.98 | G36: =SUM(G33:G35) -> 152066.75 | H36: =SUM(H33:H35) -> 13942.17 | I36: =SUM(I33:I35) -> 166008.92 | J36: =SUM(J33:J35) -> 337515.79
A38: After Cost Segregation Correction — AMT
A39: Asset | B39: Property Description | C39: Date In Service | D39: Cost | E39: Sec 179 Exp | F39: Bonus Amt | G39: AMT Prior Depreciation | H39: AMT Current Depreciation | I39: End Depreciation | J39: Net Book Value | K39: Method | L39: Period
A40: 1 | B40: 2-Building-5yr | C40: 9/22/21 | D40: 95762.44 | E40: 0 | F40: 95762.44 | G40: 95762.44 | H40: 0 | I40: =G40+H40 -> 95762.44 | J40: =D40-I40 -> 0 | K40: 200DB | L40: 5.0
A41: 2 | B41: 2-Building-27.5yr | C41: 9/22/21 | D41: 287646.29 | E41: 0 | F41: 0 | G41: 23970.53 | H41: 10459.87 | I41: =G41+H41 -> 34430.4 | J41: =D41-I41 -> 253215.89 | K41: S/L | L41: 27.5
A42: 3 | B42: 3-Land Improvements-5yr | C42: 9/22/21 | D42: 10435.08 | E42: 0 | F42: 10435.08 | G42: 10435.08 | H42: 0 | I42: =G42+H42 -> 10435.08 | J42: =D42-I42 -> 0 | K42: 200DB | L42: 5.0
A43: 4 | B43: 2-Building-27.5yr | C43: 9/22/21 | D43: 31344.36 | E43: 0 | F43: 0 | G43: 2612.02 | H43: 1139.79 | I43: =G43+H43 -> 3751.81 | J43: =D43-I43 -> 27592.55 | K43: S/L | L43: 27.5
A44: 5 | B44: 4-Equipment-5yr | C44: 9/22/21 | D44: 19565.8 | E44: 0 | F44: 19565.8 | G44: 19565.8 | H44: 0 | I44: =G44+H44 -> 19565.8 | J44: =D44-I44 -> 0 | K44: 200DB | L44: 5.0
A45: 6 | B45: 4-Equipment-27.5yr | C45: 9/22/21 | D45: 58770.74 | E45: 0 | F45: 0 | G45: 4897.57 | H45: 2137.12 | I45: =G45+H45 -> 7034.69 | J45: =D45-I45 -> 51736.05 | K45: S/L | L45: 27.5
B46: Grand Total | D46: =SUM(D40:D45) -> 503524.71 | E46: =SUM(E40:E45) -> 0 | F46: =SUM(F40:F45) -> 125763.32 | G46: =SUM(G40:G45) -> 157243.44 | H46: =SUM(H40:H45) -> 13736.78 | I46: =SUM(I40:I45) -> 170980.22 | J46: =SUM(J40:J45) -> 332544.49
B48: Section 481(a) Adjustment — AMT
B49: Depreciation reported previously | D49: =I36 -> 166008.92
B50: Cost Segregation Corrected Depreciation | D50: =I46 -> 170980.22
B51: Section 481(a) Adjustment — AMT | D51: =D49-D50 -> -4971.3
A53: COST SEGREGATION STUDY — COST SUMMARY
B54: Total Building Cost | D54: =D93 -> 503524.71
B55: Building Components: 5 Year | D55: =F93 -> 125763.32
B56: % of Cost | D56: =F94 -> 0.24976594
B57: Building Structure: 27.5 Year | D57: =H93 -> 377761.39
B58: % of Cost | D58: =H94 -> 0.75023406
A60: COST SEGREGATION STUDY — COST DETAIL
B61: Property Category | D61: Cost | F61: 5 Year | H61: 27.5 Year
B62: Building Components
B63: Cabinets / Millwork | D63: =SUM(F63:H63) -> 26757.81 | F63: 26757.81
B64: Moldings | D64: =SUM(F64:H64) -> 7990.89 | F64: 7990.89
B65: Flooring - Vinyl Plank | D65: =SUM(F65:H65) -> 37800.94 | F65: 37800.94
B66: Door & Window Guards | D66: =SUM(F66:H66) -> 2842.52 | F66: 2842.52
B67: Window Treatments | D67: =SUM(F67:H67) -> 2418.44 | F67: 2418.44
B68: Specialty HVAC - Dryer Vents | D68: =SUM(F68:H68) -> 718.3 | F68: 718.3
B69: Building Signage | D69: =SUM(F69:H69) -> 705.03 | F69: 705.03
B70: Specialty Electrical - Appliances | D70: =SUM(F70:H70) -> 12363.8 | F70: 12363.8
B71: Communication / Data | D71: =SUM(F71:H71) -> 3400.77 | F71: 3400.77
B72: Specialty Plumbing - Kitchen Sinks / Laundry | D72: =SUM(F72:H72) -> 13431.92 | F72: 13431.92
B73: Security / Exterior Lighting | D73: =SUM(F73:H73) -> 1140.5 | F73: 1140.5
B74: Access Control | D74: =SUM(F74:H74) -> 1360.86 | F74: 1360.86
B75: Appliances | D75: =SUM(F75:H75) -> 14831.54 | F75: 14831.54
B76: Building Structure
B77: Foundations | D77: =SUM(F77:H77) -> 25110.72 | H77: 25110.72
B78: HVAC | D78: =SUM(F78:H78) -> 35390.34 | H78: 35390.34
B79: Electrical | D79: =SUM(F79:H79) -> 29008.33 | H79: 29008.33
B80: Plumbing | D80: =SUM(F80:H80) -> 31389.04 | H80: 31389.04
B81: Fire Protection & Alarm | D81: =SUM(F81:H81) -> 26496.62 | H81: 26496.62
B82: Exterior Façade / Building Skin | D82: =SUM(F82:H82) -> 12009.05 | H82: 12009.05
B83: Doors & Frames | D83: =SUM(F83:H83) -> 23153.47 | H83: 23153.47
B84: Windows | D84: =SUM(F84:H84) -> 10659.46 | H84: 10659.46
B85: Ceiling Systems | D85: =SUM(F85:H85) -> 16835.06 | H85: 16835.06
B86: Interior Framing / Partitions | D86: =SUM(F86:H86) -> 39604.25 | H86: 39604.25
B87: Painting | D87: =SUM(F87:H87) -> 16001 | H87: 16001
B88: Gutter Systems | D88: =SUM(F88:H88) -> 1863.69 | H88: 1863.69
... B92: Cabinets / Millwork - Restrooms | D92: =SUM(F92:H92) -> 6970.48 | H92: 6970.48
B93: Total Building Cost | D93: =SUM(D62:D92) -> 503524.71 | F93: =SUM(F62:F92) -> 125763.32 | H93: =SUM(H62:H92) -> 377761.39
B94: % of Cost | F94: =F93/D93 -> 0.24976594 | H94: =H93/D93 -> 0.75023406
A96: ASSET ALLOCATION (per After Cost Segregation schedule)
B97: Asset (as reclassified) | D97: Cost | F97: 5 Year | H97: 27.5 Year
B98: ='Bldg 3'!B17 -> 2-Building-5yr | D98: =SUM(F98:H98) -> 95762.44 | F98: ='Bldg 3'!D17 -> 95762.44
B99: ='Bldg 3'!B18 -> 2-Building-27.5yr | D99: =SUM(F99:H99) -> 287646.29 | H99: ='Bldg 3'!D18 -> 287646.29
B100: ='Bldg 3'!B19 -> 3-Land Improvements-5yr | D100: =SUM(F100:H100) -> 10435.08 | F100: ='Bldg 3'!D19 -> 10435.08
B101: ='Bldg 3'!B20 -> 2-Building-27.5yr | D101: =SUM(F101:H101) -> 31344.36 | H101: ='Bldg 3'!D20 -> 31344.36
B102: ='Bldg 3'!B21 -> 4-Equipment-5yr | D102: =SUM(F102:H102) -> 19565.8 | F102: ='Bldg 3'!D21 -> 19565.8
B103: ='Bldg 3'!B22 -> 4-Equipment-27.5yr | D103: =SUM(F103:H103) -> 58770.74 | H103: ='Bldg 3'!D22 -> 58770.74
B104: Total Allocation | D104: =SUM(D98:D103) -> 503524.71 | F104: =SUM(F98:F103) -> 125763.32 | H104: =SUM(H98:H103) -> 377761.39
B105: Check: Allocation vs. Cost Detail (should be zero) | D105: =D104-D93 -> 0

Sheet Bldg 4
A1: Coral Village Housing LP
A2: Coral Village — 121 NE 10th Pl, Cape Coral, FL 33909
A3: EIN: 87-2205593 · FYE: December 31, 2024 · Year of Change: 1/1/2024
A4: Bldg 4 — Attachment to Form 3115 (DCN #7, Rev. Proc. 2024-23 §6.01)
A5: Source: CSSI Report #107752-01, "Coral Village Housing LP - 3115 - 107752-01 - Combined.pdf"
A7: CALCULATION OF §481(a) ADJUSTMENT — REGULAR TAX
A8: As Previously Filed
A9: Asset | B9: Property Description | C9: Date In Service | D9: Cost | E9: Sec 179 Exp | F9: Bonus Amt | G9: Tax Prior Depreciation | H9: Tax Current Depreciation | I9: End Depreciation | J9: Net Book Value | K9: Method | L9: Period
A10: 1 | B10: 2-Building | C10: 9/22/21 | D10: 302676.39 | E10: 0 | F10: 0 | G10: 25223.07 | H10: 11006.44 | I10: =G10+H10 -> 36229.51 | J10: =D10-I10 -> 266446.88 | K10: S/L | L10: 27.5
A11: 2 | B11: 3-Land Improvements | C11: 9/22/21 | D11: 32982.17 | E11: 0 | F11: 32982.17 | G11: 32982.17 | H11: 0 | I11: =G11+H11 -> 32982.17 | J11: =D11-I11 -> 0 | K11: 150DB | L11: 15.0
A12: 3 | B12: 4-Equipment | C12: 9/22/21 | D12: 61841.63 | E12: 0 | F12: 61841.63 | G12: 61841.63 | H12: 0 | I12: =G12+H12 -> 61841.63 | J12: =D12-I12 -> 0 | K12: 200DB | L12: 5.0
B13: Grand Total | D13: =SUM(D10:D12) -> 397500.19 | E13: =SUM(E10:E12) -> 0 | F13: =SUM(F10:F12) -> 94823.8 | G13: =SUM(G10:G12) -> 120046.87 | H13: =SUM(H10:H12) -> 11006.44 | I13: =SUM(I10:I12) -> 131053.31 | J13: =SUM(J10:J12) -> 266446.88
A15: After Cost Segregation Correction
A16: Asset | B16: Property Description | C16: Date In Service | D16: Cost | E16: Sec 179 Exp | F16: Bonus Amt | G16: Tax Prior Depreciation | H16: Tax Current Depreciation | I16: End Depreciation | J16: Net Book Value | K16: Method | L16: Period
A17: 1 | B17: 2-Building-5yr | C17: 9/22/21 | D17: 83590.83 | E17: 0 | F17: 83590.83 | G17: 83590.83 | H17: 0 | I17: =G17+H17 -> 83590.83 | J17: =D17-I17 -> 0 | K17: 200DB | L17: 5.0
A18: 2 | B18: 2-Building-27.5yr | C18: 9/22/21 | D18: 219085.56 | E18: 0 | F18: 0 | G18: 18257.13 | H18: 7966.75 | I18: =G18+H18 -> 26223.88 | J18: =D18-I18 -> 192861.68 | K18: S/L | L18: 27.5
A19: 3 | B19: 3-Land Improvements-5yr | C19: 9/22/21 | D19: 9108.76 | E19: 0 | F19: 9108.76 | G19: 9108.76 | H19: 0 | I19: =G19+H19 -> 9108.76 | J19: =D19-I19 -> 0 | K19: 200DB | L19: 5.0
A20: 4 | B20: 2-Building-27.5yr | C20: 9/22/21 | D20: 23873.41 | E20: 0 | F20: 0 | G20: 1989.44 | H20: 868.12 | I20: =G20+H20 -> 2857.56 | J20: =D20-I20 -> 21015.85 | K20: S/L | L20: 27.5
A21: 5 | B21: 4-Equipment-5yr | C21: 9/22/21 | D21: 17078.94 | E21: 0 | F21: 17078.94 | G21: 17078.94 | H21: 0 | I21: =G21+H21 -> 17078.94 | J21: =D21-I21 -> 0 | K21: 200DB | L21: 5.0
A22: 6 | B22: 4-Equipment-27.5yr | C22: 9/22/21 | D22: 44762.69 | E22: 0 | F22: 0 | G22: 3730.22 | H22: 1627.73 | I22: =G22+H22 -> 5357.95 | J22: =D22-I22 -> 39404.74 | K22: S/L | L22: 27.5
B23: Grand Total | D23: =SUM(D17:D22) -> 397500.19 | E23: =SUM(E17:E22) -> 0 | F23: =SUM(F17:F22) -> 109778.53 | G23: =SUM(G17:G22) -> 133755.32 | H23: =SUM(H17:H22) -> 10462.6 | I23: =SUM(I17:I22) -> 144217.92 | J23: =SUM(J17:J22) -> 253282.27
B25: Section 481(a) Adjustment — Regular Tax
B26: Depreciation reported previously | D26: =I13 -> 131053.31
B27: Cost Segregation Corrected Depreciation | D27: =I23 -> 144217.92
B28: Section 481(a) Adjustment — Regular Tax | D28: =D26-D27 -> -13164.61
A30: CALCULATION OF §481(a) ADJUSTMENT — AMT
A31: As Previously Filed — AMT
A32: Asset | B32: Property Description | C32: Date In Service | D32: Cost | E32: Sec 179 Exp | F32: Bonus Amt | G32: AMT Prior Depreciation | H32: AMT Current Depreciation | I32: End Depreciation | J32: Net Book Value | K32: Method | L32: Period
A33: 1 | B33: 2-Building | C33: 9/22/21 | D33: 302676.39 | E33: 0 | F33: 0 | G33: 25223.07 | H33: 11006.44 | I33: =G33+H33 -> 36229.51 | J33: =D33-I33 -> 266446.88 | K33: S/L | L33: 27.5
A34: 2 | B34: 3-Land Improvements | C34: 9/22/21 | D34: 32982.17 | E34: 0 | F34: 32982.17 | G34: 32982.17 | H34: 0 | I34: =G34+H34 -> 32982.17 | J34: =D34-I34 -> 0 | K34: 150DB | L34: 15.0
A35: 3 | B35: 4-Equipment | C35: 9/22/21 | D35: 61841.63 | E35: 0 | F35: 61841.63 | G35: 61841.63 | H35: 0 | I35: =G35+H35 -> 61841.63 | J35: =D35-I35 -> 0 | K35: 200DB | L35: 5.0
B36: Grand Total | D36: =SUM(D33:D35) -> 397500.19 | E36: =SUM(E33:E35) -> 0 | F36: =SUM(F33:F35) -> 94823.8 | G36: =SUM(G33:G35) -> 120046.87 | H36: =SUM(H33:H35) -> 11006.44 | I36: =SUM(I33:I35) -> 131053.31 | J36: =SUM(J33:J35) -> 266446.88
A38: After Cost Segregation Correction — AMT
A39: Asset | B39: Property Description | C39: Date In Service | D39: Cost | E39: Sec 179 Exp | F39: Bonus Amt | G39: AMT Prior Depreciation | H39: AMT Current Depreciation | I39: End Depreciation | J39: Net Book Value | K39: Method | L39: Period
A40: 1 | B40: 2-Building-5yr | C40: 9/22/21 | D40: 83590.83 | E40: 0 | F40: 83590.83 | G40: 83590.83 | H40: 0 | I40: =G40+H40 -> 83590.83 | J40: =D40-I40 -> 0 | K40: 200DB | L40: 5.0
A41: 2 | B41: 2-Building-27.5yr | C41: 9/22/21 | D41: 219085.56 | E41: 0 | F41: 0 | G41: 18257.13 | H41: 7966.75 | I41: =G41+H41 -> 26223.88 | J41: =D41-I41 -> 192861.68 | K41: S/L | L41: 27.5
A42: 3 | B42: 3-Land Improvements-5yr | C42: 9/22/21 | D42: 9108.76 | E42: 0 | F42: 9108.76 | G42: 9108.76 | H42: 0 | I42: =G42+H42 -> 9108.76 | J42: =D42-I42 -> 0 | K42: 200DB | L42: 5.0
A43: 4 | B43: 2-Building-27.5yr | C43: 9/22/21 | D43: 23873.41 | E43: 0 | F43: 0 | G43: 1989.44 | H43: 868.12 | I43: =G43+H43 -> 2857.56 | J43: =D43-I43 -> 21015.85 | K43: S/L | L43: 27.5
A44: 5 | B44: 4-Equipment-5yr | C44: 9/22/21 | D44: 17078.94 | E44: 0 | F44: 17078.94 | G44: 17078.94 | H44: 0 | I44: =G44+H44 -> 17078.94 | J44: =D44-I44 -> 0 | K44: 200DB | L44: 5.0
A45: 6 | B45: 4-Equipment-27.5yr | C45: 9/22/21 | D45: 44762.69 | E45: 0 | F45: 0 | G45: 3730.22 | H45: 1627.73 | I45: =G45+H45 -> 5357.95 | J45: =D45-I45 -> 39404.74 | K45: S/L | L45: 27.5
B46: Grand Total | D46: =SUM(D40:D45) -> 397500.19 | E46: =SUM(E40:E45) -> 0 | F46: =SUM(F40:F45) -> 109778.53 | G46: =SUM(G40:G45) -> 133755.32 | H46: =SUM(H40:H45) -> 10462.6 | I46: =SUM(I40:I45) -> 144217.92 | J46: =SUM(J40:J45) -> 253282.27
B48: Section 481(a) Adjustment — AMT
B49: Depreciation reported previously | D49: =I36 -> 131053.31
B50: Cost Segregation Corrected Depreciation | D50: =I46 -> 144217.92
B51: Section 481(a) Adjustment — AMT | D51: =D49-D50 -> -13164.61
A53: COST SEGREGATION STUDY — COST SUMMARY
B54: Total Building Cost | D54: =D94 -> 397500.19
B55: Building Components: 5 Year | D55: =F94 -> 109778.53
B56: % of Cost | D56: =F95 -> 0.27617227
B57: Building Structure: 27.5 Year | D57: =H94 -> 287721.66
B58: % of Cost | D58: =H95 -> 0.72382773
A60: COST SEGREGATION STUDY — COST DETAIL
B61: Property Category | D61: Cost | F61: 5 Year | H61: 27.5 Year
B62: Building Components
B63: Cabinets / Millwork | D63: =SUM(F63:H63) -> 26445.19 | F63: 26445.19
B64: Moldings | D64: =SUM(F64:H64) -> 4635.69 | F64: 4635.69
B65: Flooring - Carpet | D65: =SUM(F65:H65) -> 9118.09 | F65: 9118.09
B66: Flooring - Vinyl Plank | D66: =SUM(F66:H66) -> 17166.07 | F66: 17166.07
B67: Door & Window Guards | D67: =SUM(F67:H67) -> 2842.52 | F67: 2842.52
B68: Window Treatments | D68: =SUM(F68:H68) -> 2418.44 | F68: 2418.44
B69: Specialty HVAC - Dryer Vents | D69: =SUM(F69:H69) -> 718.3 | F69: 718.3
B70: Building Signage | D70: =SUM(F70:H70) -> 705.03 | F70: 705.03
B71: Specialty Electrical - Appliances | D71: =SUM(F71:H71) -> 12363.8 | F71: 12363.8
B72: Communication / Data | D72: =SUM(F72:H72) -> 2600.58 | F72: 2600.58
B73: Specialty Plumbing - Kitchen Sinks / Laundry | D73: =SUM(F73:H73) -> 13431.92 | F73: 13431.92
B74: Security / Exterior Lighting | D74: =SUM(F74:H74) -> 1140.5 | F74: 1140.5
... B76: Appliances | D76: =SUM(F76:H76) -> 14831.54 | F76: 14831.54
B77: Building Structure
B78: Foundations | D78: =SUM(F78:H78) -> 19166.81 | H78: 19166.81
B79: HVAC | D79: =SUM(F79:H79) -> 26894.18 | H79: 26894.18
B80: Electrical | D80: =SUM(F80:H80) -> 19273.71 | H80: 19273.71
B81: Plumbing | D81: =SUM(F81:H81) -> 24003.39 | H81: 24003.39
B82: Fire Protection & Alarm | D82: =SUM(F82:H82) -> 23233.4 | H82: 23233.4
B83: Exterior Façade / Building Skin | D83: =SUM(F83:H83) -> 8832.92 | H83: 8832.92
B84: Doors & Frames | D84: =SUM(F84:H84) -> 17315.31 | H84: 17315.31
B85: Windows | D85: =SUM(F85:H85) -> 10659.46 | H85: 10659.46
B86: Ceiling Systems | D86: =SUM(F86:H86) -> 12873.87 | H86: 12873.87
B87: Interior Framing / Partitions | D87: =SUM(F87:H87) -> 29302.11 | H87: 29302.11
B88: Painting | D88: =SUM(F88:H88) -> 11976.41 | H88: 11976.41
B89: Gutter Systems | D89: =SUM(F89:H89) -> 1737.32 | H89: 1737.32
... B93: Cabinets / Millwork - Restrooms | D93: =SUM(F93:H93) -> 3303.27 | H93: 3303.27
B94: Total Building Cost | D94: =SUM(D62:D93) -> 397500.19 | F94: =SUM(F62:F93) -> 109778.53 | H94: =SUM(H62:H93) -> 287721.66
B95: % of Cost | F95: =F94/D94 -> 0.27617227 | H95: =H94/D94 -> 0.72382773
A97: ASSET ALLOCATION (per After Cost Segregation schedule)
B98: Asset (as reclassified) | D98: Cost | F98: 5 Year | H98: 27.5 Year
B99: ='Bldg 4'!B17 -> 2-Building-5yr | D99: =SUM(F99:H99) -> 83590.83 | F99: ='Bldg 4'!D17 -> 83590.83
B100: ='Bldg 4'!B18 -> 2-Building-27.5yr | D100: =SUM(F100:H100) -> 219085.56 | H100: ='Bldg 4'!D18 -> 219085.56
B101: ='Bldg 4'!B19 -> 3-Land Improvements-5yr | D101: =SUM(F101:H101) -> 9108.76 | F101: ='Bldg 4'!D19 -> 9108.76
B102: ='Bldg 4'!B20 -> 2-Building-27.5yr | D102: =SUM(F102:H102) -> 23873.41 | H102: ='Bldg 4'!D20 -> 23873.41
B103: ='Bldg 4'!B21 -> 4-Equipment-5yr | D103: =SUM(F103:H103) -> 17078.94 | F103: ='Bldg 4'!D21 -> 17078.94
B104: ='Bldg 4'!B22 -> 4-Equipment-27.5yr | D104: =SUM(F104:H104) -> 44762.69 | H104: ='Bldg 4'!D22 -> 44762.69
B105: Total Allocation | D105: =SUM(D99:D104) -> 397500.19 | F105: =SUM(F99:F104) -> 109778.53 | H105: =SUM(H99:H104) -> 287721.66
B106: Check: Allocation vs. Cost Detail (should be zero) | D106: =D105-D94 -> 0

Sheet Bldg 5
A1: Coral Village Housing LP
A2: Coral Village — 121 NE 10th Pl, Cape Coral, FL 33909
A3: EIN: 87-2205593 · FYE: December 31, 2024 · Year of Change: 1/1/2024
A4: Bldg 5 — Attachment to Form 3115 (DCN #7, Rev. Proc. 2024-23 §6.01)
A5: Source: CSSI Report #107752-01, "Coral Village Housing LP - 3115 - 107752-01 - Combined.pdf"
A7: CALCULATION OF §481(a) ADJUSTMENT — REGULAR TAX
A8: As Previously Filed
A9: Asset | B9: Property Description | C9: Date In Service | D9: Cost | E9: Sec 179 Exp | F9: Bonus Amt | G9: Tax Prior Depreciation | H9: Tax Current Depreciation | I9: End Depreciation | J9: Net Book Value | K9: Method | L9: Period
A10: 1 | B10: 2-Building | C10: 9/22/21 | D10: 383408.73 | E10: 0 | F10: 0 | G10: 31950.77 | H10: 13942.17 | I10: =G10+H10 -> 45892.94 | J10: =D10-I10 -> 337515.79 | K10: S/L | L10: 27.5
A11: 2 | B11: 3-Land Improvements | C11: 9/22/21 | D11: 41779.44 | E11: 0 | F11: 41779.44 | G11: 41779.44 | H11: 0 | I11: =G11+H11 -> 41779.44 | J11: =D11-I11 -> 0 | K11: 150DB | L11: 15.0
A12: 3 | B12: 4-Equipment | C12: 9/22/21 | D12: 78336.54 | E12: 0 | F12: 78336.54 | G12: 78336.54 | H12: 0 | I12: =G12+H12 -> 78336.54 | J12: =D12-I12 -> 0 | K12: 200DB | L12: 5.0
B13: Grand Total | D13: =SUM(D10:D12) -> 503524.71 | E13: =SUM(E10:E12) -> 0 | F13: =SUM(F10:F12) -> 120115.98 | G13: =SUM(G10:G12) -> 152066.75 | H13: =SUM(H10:H12) -> 13942.17 | I13: =SUM(I10:I12) -> 166008.92 | J13: =SUM(J10:J12) -> 337515.79
A15: After Cost Segregation Correction
A16: Asset | B16: Property Description | C16: Date In Service | D16: Cost | E16: Sec 179 Exp | F16: Bonus Amt | G16: Tax Prior Depreciation | H16: Tax Current Depreciation | I16: End Depreciation | J16: Net Book Value | K16: Method | L16: Period
A17: 1 | B17: 2-Building-5yr | C17: 9/22/21 | D17: 95762.44 | E17: 0 | F17: 95762.44 | G17: 95762.44 | H17: 0 | I17: =G17+H17 -> 95762.44 | J17: =D17-I17 -> 0 | K17: 200DB | L17: 5.0
A18: 2 | B18: 2-Building-27.5yr | C18: 9/22/21 | D18: 287646.29 | E18: 0 | F18: 0 | G18: 23970.53 | H18: 10459.87 | I18: =G18+H18 -> 34430.4 | J18: =D18-I18 -> 253215.89 | K18: S/L | L18: 27.5
A19: 3 | B19: 3-Land Improvements-5yr | C19: 9/22/21 | D19: 10435.08 | E19: 0 | F19: 10435.08 | G19: 10435.08 | H19: 0 | I19: =G19+H19 -> 10435.08 | J19: =D19-I19 -> 0 | K19: 200DB | L19: 5.0
A20: 4 | B20: 2-Building-27.5yr | C20: 9/22/21 | D20: 31344.36 | E20: 0 | F20: 0 | G20: 2612.02 | H20: 1139.79 | I20: =G20+H20 -> 3751.81 | J20: =D20-I20 -> 27592.55 | K20: S/L | L20: 27.5
A21: 5 | B21: 4-Equipment-5yr | C21: 9/22/21 | D21: 19565.8 | E21: 0 | F21: 19565.8 | G21: 19565.8 | H21: 0 | I21: =G21+H21 -> 19565.8 | J21: =D21-I21 -> 0 | K21: 200DB | L21: 5.0
A22: 6 | B22: 4-Equipment-27.5yr | C22: 9/22/21 | D22: 58770.74 | E22: 0 | F22: 0 | G22: 4897.57 | H22: 2137.12 | I22: =G22+H22 -> 7034.69 | J22: =D22-I22 -> 51736.05 | K22: S/L | L22: 27.5
B23: Grand Total | D23: =SUM(D17:D22) -> 503524.71 | E23: =SUM(E17:E22) -> 0 | F23: =SUM(F17:F22) -> 125763.32 | G23: =SUM(G17:G22) -> 157243.44 | H23: =SUM(H17:H22) -> 13736.78 | I23: =SUM(I17:I22) -> 170980.22 | J23: =SUM(J17:J22) -> 332544.49
B25: Section 481(a) Adjustment — Regular Tax
B26: Depreciation reported previously | D26: =I13 -> 166008.92
B27: Cost Segregation Corrected Depreciation | D27: =I23 -> 170980.22
B28: Section 481(a) Adjustment — Regular Tax | D28: =D26-D27 -> -4971.3
A30: CALCULATION OF §481(a) ADJUSTMENT — AMT
A31: As Previously Filed — AMT
A32: Asset | B32: Property Description | C32: Date In Service | D32: Cost | E32: Sec 179 Exp | F32: Bonus Amt | G32: AMT Prior Depreciation | H32: AMT Current Depreciation | I32: End Depreciation | J32: Net Book Value | K32: Method | L32: Period
A33: 1 | B33: 2-Building | C33: 9/22/21 | D33: 383408.73 | E33: 0 | F33: 0 | G33: 31950.77 | H33: 13942.17 | I33: =G33+H33 -> 45892.94 | J33: =D33-I33 -> 337515.79 | K33: S/L | L33: 27.5
A34: 2 | B34: 3-Land Improvements | C34: 9/22/21 | D34: 41779.44 | E34: 0 | F34: 41779.44 | G34: 41779.44 | H34: 0 | I34: =G34+H34 -> 41779.44 | J34: =D34-I34 -> 0 | K34: 150DB | L34: 15.0
A35: 3 | B35: 4-Equipment | C35: 9/22/21 | D35: 78336.54 | E35: 0 | F35: 78336.54 | G35: 78336.54 | H35: 0 | I35: =G35+H35 -> 78336.54 | J35: =D35-I35 -> 0 | K35: 200DB | L35: 5.0
B36: Grand Total | D36: =SUM(D33:D35) -> 503524.71 | E36: =SUM(E33:E35) -> 0 | F36: =SUM(F33:F35) -> 120115.98 | G36: =SUM(G33:G35) -> 152066.75 | H36: =SUM(H33:H35) -> 13942.17 | I36: =SUM(I33:I35) -> 166008.92 | J36: =SUM(J33:J35) -> 337515.79
A38: After Cost Segregation Correction — AMT
A39: Asset | B39: Property Description | C39: Date In Service | D39: Cost | E39: Sec 179 Exp | F39: Bonus Amt | G39: AMT Prior Depreciation | H39: AMT Current Depreciation | I39: End Depreciation | J39: Net Book Value | K39: Method | L39: Period
A40: 1 | B40: 2-Building-5yr | C40: 9/22/21 | D40: 95762.44 | E40: 0 | F40: 95762.44 | G40: 95762.44 | H40: 0 | I40: =G40+H40 -> 95762.44 | J40: =D40-I40 -> 0 | K40: 200DB | L40: 5.0
A41: 2 | B41: 2-Building-27.5yr | C41: 9/22/21 | D41: 287646.29 | E41: 0 | F41: 0 | G41: 23970.53 | H41: 10459.87 | I41: =G41+H41 -> 34430.4 | J41: =D41-I41 -> 253215.89 | K41: S/L | L41: 27.5
A42: 3 | B42: 3-Land Improvements-5yr | C42: 9/22/21 | D42: 10435.08 | E42: 0 | F42: 10435.08 | G42: 10435.08 | H42: 0 | I42: =G42+H42 -> 10435.08 | J42: =D42-I42 -> 0 | K42: 200DB | L42: 5.0
A43: 4 | B43: 2-Building-27.5yr | C43: 9/22/21 | D43: 31344.36 | E43: 0 | F43: 0 | G43: 2612.02 | H43: 1139.79 | I43: =G43+H43 -> 3751.81 | J43: =D43-I43 -> 27592.55 | K43: S/L | L43: 27.5
A44: 5 | B44: 4-Equipment-5yr | C44: 9/22/21 | D44: 19565.8 | E44: 0 | F44: 19565.8 | G44: 19565.8 | H44: 0 | I44: =G44+H44 -> 19565.8 | J44: =D44-I44 -> 0 | K44: 200DB | L44: 5.0
A45: 6 | B45: 4-Equipment-27.5yr | C45: 9/22/21 | D45: 58770.74 | E45: 0 | F45: 0 | G45: 4897.57 | H45: 2137.12 | I45: =G45+H45 -> 7034.69 | J45: =D45-I45 -> 51736.05 | K45: S/L | L45: 27.5
B46: Grand Total | D46: =SUM(D40:D45) -> 503524.71 | E46: =SUM(E40:E45) -> 0 | F46: =SUM(F40:F45) -> 125763.32 | G46: =SUM(G40:G45) -> 157243.44 | H46: =SUM(H40:H45) -> 13736.78 | I46: =SUM(I40:I45) -> 170980.22 | J46: =SUM(J40:J45) -> 332544.49
B48: Section 481(a) Adjustment — AMT
B49: Depreciation reported previously | D49: =I36 -> 166008.92
B50: Cost Segregation Corrected Depreciation | D50: =I46 -> 170980.22
B51: Section 481(a) Adjustment — AMT | D51: =D49-D50 -> -4971.3
A53: COST SEGREGATION STUDY — COST SUMMARY
B54: Total Building Cost | D54: =D93 -> 503524.71
B55: Building Components: 5 Year | D55: =F93 -> 125763.32
B56: % of Cost | D56: =F94 -> 0.24976594
B57: Building Structure: 27.5 Year | D57: =H93 -> 377761.39
B58: % of Cost | D58: =H94 -> 0.75023406
A60: COST SEGREGATION STUDY — COST DETAIL
B61: Property Category | D61: Cost | F61: 5 Year | H61: 27.5 Year
B62: Building Components
B63: Cabinets / Millwork | D63: =SUM(F63:H63) -> 26757.81 | F63: 26757.81
B64: Moldings | D64: =SUM(F64:H64) -> 7990.89 | F64: 7990.89
B65: Flooring - Vinyl Plank | D65: =SUM(F65:H65) -> 37800.94 | F65: 37800.94
B66: Door & Window Guards | D66: =SUM(F66:H66) -> 2842.52 | F66: 2842.52
B67: Window Treatments | D67: =SUM(F67:H67) -> 2418.44 | F67: 2418.44
B68: Specialty HVAC - Dryer Vents | D68: =SUM(F68:H68) -> 718.3 | F68: 718.3
B69: Building Signage | D69: =SUM(F69:H69) -> 705.03 | F69: 705.03
B70: Specialty Electrical - Appliances | D70: =SUM(F70:H70) -> 12363.8 | F70: 12363.8
B71: Communication / Data | D71: =SUM(F71:H71) -> 3400.77 | F71: 3400.77
B72: Specialty Plumbing - Kitchen Sinks / Laundry | D72: =SUM(F72:H72) -> 13431.92 | F72: 13431.92
B73: Security / Exterior Lighting | D73: =SUM(F73:H73) -> 1140.5 | F73: 1140.5
B74: Access Control | D74: =SUM(F74:H74) -> 1360.86 | F74: 1360.86
B75: Appliances | D75: =SUM(F75:H75) -> 14831.54 | F75: 14831.54
B76: Building Structure
B77: Foundations | D77: =SUM(F77:H77) -> 25110.72 | H77: 25110.72
B78: HVAC | D78: =SUM(F78:H78) -> 35390.34 | H78: 35390.34
B79: Electrical | D79: =SUM(F79:H79) -> 29008.33 | H79: 29008.33
B80: Plumbing | D80: =SUM(F80:H80) -> 31389.04 | H80: 31389.04
B81: Fire Protection & Alarm | D81: =SUM(F81:H81) -> 26496.62 | H81: 26496.62
B82: Exterior Façade / Building Skin | D82: =SUM(F82:H82) -> 12009.05 | H82: 12009.05
B83: Doors & Frames | D83: =SUM(F83:H83) -> 23153.47 | H83: 23153.47
B84: Windows | D84: =SUM(F84:H84) -> 10659.46 | H84: 10659.46
B85: Ceiling Systems | D85: =SUM(F85:H85) -> 16835.06 | H85: 16835.06
B86: Interior Framing / Partitions | D86: =SUM(F86:H86) -> 39604.25 | H86: 39604.25
B87: Painting | D87: =SUM(F87:H87) -> 16001 | H87: 16001
B88: Gutter Systems | D88: =SUM(F88:H88) -> 1863.69 | H88: 1863.69
... B92: Cabinets / Millwork - Restrooms | D92: =SUM(F92:H92) -> 6970.48 | H92: 6970.48
B93: Total Building Cost | D93: =SUM(D62:D92) -> 503524.71 | F93: =SUM(F62:F92) -> 125763.32 | H93: =SUM(H62:H92) -> 377761.39
B94: % of Cost | F94: =F93/D93 -> 0.24976594 | H94: =H93/D93 -> 0.75023406
A96: ASSET ALLOCATION (per After Cost Segregation schedule)
B97: Asset (as reclassified) | D97: Cost | F97: 5 Year | H97: 27.5 Year
B98: ='Bldg 5'!B17 -> 2-Building-5yr | D98: =SUM(F98:H98) -> 95762.44 | F98: ='Bldg 5'!D17 -> 95762.44
B99: ='Bldg 5'!B18 -> 2-Building-27.5yr | D99: =SUM(F99:H99) -> 287646.29 | H99: ='Bldg 5'!D18 -> 287646.29
B100: ='Bldg 5'!B19 -> 3-Land Improvements-5yr | D100: =SUM(F100:H100) -> 10435.08 | F100: ='Bldg 5'!D19 -> 10435.08
B101: ='Bldg 5'!B20 -> 2-Building-27.5yr | D101: =SUM(F101:H101) -> 31344.36 | H101: ='Bldg 5'!D20 -> 31344.36
B102: ='Bldg 5'!B21 -> 4-Equipment-5yr | D102: =SUM(F102:H102) -> 19565.8 | F102: ='Bldg 5'!D21 -> 19565.8
B103: ='Bldg 5'!B22 -> 4-Equipment-27.5yr | D103: =SUM(F103:H103) -> 58770.74 | H103: ='Bldg 5'!D22 -> 58770.74
B104: Total Allocation | D104: =SUM(D98:D103) -> 503524.71 | F104: =SUM(F98:F103) -> 125763.32 | H104: =SUM(H98:H103) -> 377761.39
B105: Check: Allocation vs. Cost Detail (should be zero) | D105: =D104-D93 -> 0

Sheet Bldg 6
A1: Coral Village Housing LP
A2: Coral Village — 121 NE 10th Pl, Cape Coral, FL 33909
A3: EIN: 87-2205593 · FYE: December 31, 2024 · Year of Change: 1/1/2024
A4: Bldg 6 — Attachment to Form 3115 (DCN #7, Rev. Proc. 2024-23 §6.01)
A5: Source: CSSI Report #107752-01, "Coral Village Housing LP - 3115 - 107752-01 - Combined.pdf"
A7: CALCULATION OF §481(a) ADJUSTMENT — REGULAR TAX
A8: As Previously Filed
A9: Asset | B9: Property Description | C9: Date In Service | D9: Cost | E9: Sec 179 Exp | F9: Bonus Amt | G9: Tax Prior Depreciation | H9: Tax Current Depreciation | I9: End Depreciation | J9: Net Book Value | K9: Method | L9: Period
A10: 1 | B10: 2-Building | C10: 9/22/21 | D10: 302676.39 | E10: 0 | F10: 0 | G10: 25223.07 | H10: 11006.44 | I10: =G10+H10 -> 36229.51 | J10: =D10-I10 -> 266446.88 | K10: S/L | L10: 27.5
A11: 2 | B11: 3-Land Improvements | C11: 9/22/21 | D11: 32982.17 | E11: 0 | F11: 32982.17 | G11: 32982.17 | H11: 0 | I11: =G11+H11 -> 32982.17 | J11: =D11-I11 -> 0 | K11: 150DB | L11: 15.0
A12: 3 | B12: 4-Equipment | C12: 9/22/21 | D12: 61841.63 | E12: 0 | F12: 61841.63 | G12: 61841.63 | H12: 0 | I12: =G12+H12 -> 61841.63 | J12: =D12-I12 -> 0 | K12: 200DB | L12: 5.0
B13: Grand Total | D13: =SUM(D10:D12) -> 397500.19 | E13: =SUM(E10:E12) -> 0 | F13: =SUM(F10:F12) -> 94823.8 | G13: =SUM(G10:G12) -> 120046.87 | H13: =SUM(H10:H12) -> 11006.44 | I13: =SUM(I10:I12) -> 131053.31 | J13: =SUM(J10:J12) -> 266446.88
A15: After Cost Segregation Correction
A16: Asset | B16: Property Description | C16: Date In Service | D16: Cost | E16: Sec 179 Exp | F16: Bonus Amt | G16: Tax Prior Depreciation | H16: Tax Current Depreciation | I16: End Depreciation | J16: Net Book Value | K16: Method | L16: Period
A17: 1 | B17: 2-Building-5yr | C17: 9/22/21 | D17: 83590.83 | E17: 0 | F17: 83590.83 | G17: 83590.83 | H17: 0 | I17: =G17+H17 -> 83590.83 | J17: =D17-I17 -> 0 | K17: 200DB | L17: 5.0
A18: 2 | B18: 2-Building-27.5yr | C18: 9/22/21 | D18: 219085.56 | E18: 0 | F18: 0 | G18: 18257.13 | H18: 7966.75 | I18: =G18+H18 -> 26223.88 | J18: =D18-I18 -> 192861.68 | K18: S/L | L18: 27.5
A19: 3 | B19: 3-Land Improvements-5yr | C19: 9/22/21 | D19: 9108.76 | E19: 0 | F19: 9108.76 | G19: 9108.76 | H19: 0 | I19: =G19+H19 -> 9108.76 | J19: =D19-I19 -> 0 | K19: 200DB | L19: 5.0
A20: 4 | B20: 2-Building-27.5yr | C20: 9/22/21 | D20: 23873.41 | E20: 0 | F20: 0 | G20: 1989.44 | H20: 868.12 | I20: =G20+H20 -> 2857.56 | J20: =D20-I20 -> 21015.85 | K20: S/L | L20: 27.5
A21: 5 | B21: 4-Equipment-5yr | C21: 9/22/21 | D21: 17078.94 | E21: 0 | F21: 17078.94 | G21: 17078.94 | H21: 0 | I21: =G21+H21 -> 17078.94 | J21: =D21-I21 -> 0 | K21: 200DB | L21: 5.0
A22: 6 | B22: 4-Equipment-27.5yr | C22: 9/22/21 | D22: 44762.69 | E22: 0 | F22: 0 | G22: 3730.22 | H22: 1627.73 | I22: =G22+H22 -> 5357.95 | J22: =D22-I22 -> 39404.74 | K22: S/L | L22: 27.5
B23: Grand Total | D23: =SUM(D17:D22) -> 397500.19 | E23: =SUM(E17:E22) -> 0 | F23: =SUM(F17:F22) -> 109778.53 | G23: =SUM(G17:G22) -> 133755.32 | H23: =SUM(H17:H22) -> 10462.6 | I23: =SUM(I17:I22) -> 144217.92 | J23: =SUM(J17:J22) -> 253282.27
B25: Section 481(a) Adjustment — Regular Tax
B26: Depreciation reported previously | D26: =I13 -> 131053.31
B27: Cost Segregation Corrected Depreciation | D27: =I23 -> 144217.92
B28: Section 481(a) Adjustment — Regular Tax | D28: =D26-D27 -> -13164.61
A30: CALCULATION OF §481(a) ADJUSTMENT — AMT
A31: As Previously Filed — AMT
A32: Asset | B32: Property Description | C32: Date In Service | D32: Cost | E32: Sec 179 Exp | F32: Bonus Amt | G32: AMT Prior Depreciation | H32: AMT Current Depreciation | I32: End Depreciation | J32: Net Book Value | K32: Method | L32: Period
A33: 1 | B33: 2-Building | C33: 9/22/21 | D33: 302676.39 | E33: 0 | F33: 0 | G33: 25223.07 | H33: 11006.44 | I33: =G33+H33 -> 36229.51 | J33: =D33-I33 -> 266446.88 | K33: S/L | L33: 27.5
A34: 2 | B34: 3-Land Improvements | C34: 9/22/21 | D34: 32982.17 | E34: 0 | F34: 32982.17 | G34: 32982.17 | H34: 0 | I34: =G34+H34 -> 32982.17 | J34: =D34-I34 -> 0 | K34: 150DB | L34: 15.0
A35: 3 | B35: 4-Equipment | C35: 9/22/21 | D35: 61841.63 | E35: 0 | F35: 61841.63 | G35: 61841.63 | H35: 0 | I35: =G35+H35 -> 61841.63 | J35: =D35-I35 -> 0 | K35: 200DB | L35: 5.0
B36: Grand Total | D36: =SUM(D33:D35) -> 397500.19 | E36: =SUM(E33:E35) -> 0 | F36: =SUM(F33:F35) -> 94823.8 | G36: =SUM(G33:G35) -> 120046.87 | H36: =SUM(H33:H35) -> 11006.44 | I36: =SUM(I33:I35) -> 131053.31 | J36: =SUM(J33:J35) -> 266446.88
A38: After Cost Segregation Correction — AMT
A39: Asset | B39: Property Description | C39: Date In Service | D39: Cost | E39: Sec 179 Exp | F39: Bonus Amt | G39: AMT Prior Depreciation | H39: AMT Current Depreciation | I39: End Depreciation | J39: Net Book Value | K39: Method | L39: Period
A40: 1 | B40: 2-Building-5yr | C40: 9/22/21 | D40: 83590.83 | E40: 0 | F40: 83590.83 | G40: 83590.83 | H40: 0 | I40: =G40+H40 -> 83590.83 | J40: =D40-I40 -> 0 | K40: 200DB | L40: 5.0
A41: 2 | B41: 2-Building-27.5yr | C41: 9/22/21 | D41: 219085.56 | E41: 0 | F41: 0 | G41: 18257.13 | H41: 7966.75 | I41: =G41+H41 -> 26223.88 | J41: =D41-I41 -> 192861.68 | K41: S/L | L41: 27.5
A42: 3 | B42: 3-Land Improvements-5yr | C42: 9/22/21 | D42: 9108.76 | E42: 0 | F42: 9108.76 | G42: 9108.76 | H42: 0 | I42: =G42+H42 -> 9108.76 | J42: =D42-I42 -> 0 | K42: 200DB | L42: 5.0
A43: 4 | B43: 2-Building-27.5yr | C43: 9/22/21 | D43: 23873.41 | E43: 0 | F43: 0 | G43: 1989.44 | H43: 868.12 | I43: =G43+H43 -> 2857.56 | J43: =D43-I43 -> 21015.85 | K43: S/L | L43: 27.5
A44: 5 | B44: 4-Equipment-5yr | C44: 9/22/21 | D44: 17078.94 | E44: 0 | F44: 17078.94 | G44: 17078.94 | H44: 0 | I44: =G44+H44 -> 17078.94 | J44: =D44-I44 -> 0 | K44: 200DB | L44: 5.0
A45: 6 | B45: 4-Equipment-27.5yr | C45: 9/22/21 | D45: 44762.69 | E45: 0 | F45: 0 | G45: 3730.22 | H45: 1627.73 | I45: =G45+H45 -> 5357.95 | J45: =D45-I45 -> 39404.74 | K45: S/L | L45: 27.5
B46: Grand Total | D46: =SUM(D40:D45) -> 397500.19 | E46: =SUM(E40:E45) -> 0 | F46: =SUM(F40:F45) -> 109778.53 | G46: =SUM(G40:G45) -> 133755.32 | H46: =SUM(H40:H45) -> 10462.6 | I46: =SUM(I40:I45) -> 144217.92 | J46: =SUM(J40:J45) -> 253282.27
B48: Section 481(a) Adjustment — AMT
B49: Depreciation reported previously | D49: =I36 -> 131053.31
B50: Cost Segregation Corrected Depreciation | D50: =I46 -> 144217.92
B51: Section 481(a) Adjustment — AMT | D51: =D49-D50 -> -13164.61
A53: COST SEGREGATION STUDY — COST SUMMARY
B54: Total Building Cost | D54: =D94 -> 397500.19
B55: Building Components: 5 Year | D55: =F94 -> 109778.53
B56: % of Cost | D56: =F95 -> 0.27617227
B57: Building Structure: 27.5 Year | D57: =H94 -> 287721.66
B58: % of Cost | D58: =H95 -> 0.72382773
A60: COST SEGREGATION STUDY — COST DETAIL
B61: Property Category | D61: Cost | F61: 5 Year | H61: 27.5 Year
B62: Building Components
B63: Cabinets / Millwork | D63: =SUM(F63:H63) -> 26445.19 | F63: 26445.19
B64: Moldings | D64: =SUM(F64:H64) -> 4635.69 | F64: 4635.69
B65: Flooring - Carpet | D65: =SUM(F65:H65) -> 9118.09 | F65: 9118.09
B66: Flooring - Vinyl Plank | D66: =SUM(F66:H66) -> 17166.07 | F66: 17166.07
B67: Door & Window Guards | D67: =SUM(F67:H67) -> 2842.52 | F67: 2842.52
B68: Window Treatments | D68: =SUM(F68:H68) -> 2418.44 | F68: 2418.44
B69: Specialty HVAC - Dryer Vents | D69: =SUM(F69:H69) -> 718.3 | F69: 718.3
B70: Building Signage | D70: =SUM(F70:H70) -> 705.03 | F70: 705.03
B71: Specialty Electrical - Appliances | D71: =SUM(F71:H71) -> 12363.8 | F71: 12363.8
B72: Communication / Data | D72: =SUM(F72:H72) -> 2600.58 | F72: 2600.58
B73: Specialty Plumbing - Kitchen Sinks / Laundry | D73: =SUM(F73:H73) -> 13431.92 | F73: 13431.92
B74: Security / Exterior Lighting | D74: =SUM(F74:H74) -> 1140.5 | F74: 1140.5
... B76: Appliances | D76: =SUM(F76:H76) -> 14831.54 | F76: 14831.54
B77: Building Structure
B78: Foundations | D78: =SUM(F78:H78) -> 19166.81 | H78: 19166.81
B79: HVAC | D79: =SUM(F79:H79) -> 26894.18 | H79: 26894.18
B80: Electrical | D80: =SUM(F80:H80) -> 19273.71 | H80: 19273.71
B81: Plumbing | D81: =SUM(F81:H81) -> 24003.39 | H81: 24003.39
B82: Fire Protection & Alarm | D82: =SUM(F82:H82) -> 23233.4 | H82: 23233.4
B83: Exterior Façade / Building Skin | D83: =SUM(F83:H83) -> 8832.92 | H83: 8832.92
B84: Doors & Frames | D84: =SUM(F84:H84) -> 17315.31 | H84: 17315.31
B85: Windows | D85: =SUM(F85:H85) -> 10659.46 | H85: 10659.46
B86: Ceiling Systems | D86: =SUM(F86:H86) -> 12873.87 | H86: 12873.87
B87: Interior Framing / Partitions | D87: =SUM(F87:H87) -> 29302.11 | H87: 29302.11
B88: Painting | D88: =SUM(F88:H88) -> 11976.41 | H88: 11976.41
B89: Gutter Systems | D89: =SUM(F89:H89) -> 1737.32 | H89: 1737.32
... B93: Cabinets / Millwork - Restrooms | D93: =SUM(F93:H93) -> 3303.27 | H93: 3303.27
B94: Total Building Cost | D94: =SUM(D62:D93) -> 397500.19 | F94: =SUM(F62:F93) -> 109778.53 | H94: =SUM(H62:H93) -> 287721.66
B95: % of Cost | F95: =F94/D94 -> 0.27617227 | H95: =H94/D94 -> 0.72382773
A97: ASSET ALLOCATION (per After Cost Segregation schedule)
B98: Asset (as reclassified) | D98: Cost | F98: 5 Year | H98: 27.5 Year
B99: ='Bldg 6'!B17 -> 2-Building-5yr | D99: =SUM(F99:H99) -> 83590.83 | F99: ='Bldg 6'!D17 -> 83590.83
B100: ='Bldg 6'!B18 -> 2-Building-27.5yr | D100: =SUM(F100:H100) -> 219085.56 | H100: ='Bldg 6'!D18 -> 219085.56
B101: ='Bldg 6'!B19 -> 3-Land Improvements-5yr | D101: =SUM(F101:H101) -> 9108.76 | F101: ='Bldg 6'!D19 -> 9108.76
B102: ='Bldg 6'!B20 -> 2-Building-27.5yr | D102: =SUM(F102:H102) -> 23873.41 | H102: ='Bldg 6'!D20 -> 23873.41
B103: ='Bldg 6'!B21 -> 4-Equipment-5yr | D103: =SUM(F103:H103) -> 17078.94 | F103: ='Bldg 6'!D21 -> 17078.94
B104: ='Bldg 6'!B22 -> 4-Equipment-27.5yr | D104: =SUM(F104:H104) -> 44762.69 | H104: ='Bldg 6'!D22 -> 44762.69
B105: Total Allocation | D105: =SUM(D99:D104) -> 397500.19 | F105: =SUM(F99:F104) -> 109778.53 | H105: =SUM(H99:H104) -> 287721.66
B106: Check: Allocation vs. Cost Detail (should be zero) | D106: =D105-D94 -> 0

Sheet Bldg 7
A1: Coral Village Housing LP
A2: Coral Village — 121 NE 10th Pl, Cape Coral, FL 33909
A3: EIN: 87-2205593 · FYE: December 31, 2024 · Year of Change: 1/1/2024
A4: Bldg 7 — Attachment to Form 3115 (DCN #7, Rev. Proc. 2024-23 §6.01)
A5: Source: CSSI Report #107752-01, "Coral Village Housing LP - 3115 - 107752-01 - Combined.pdf"
A7: CALCULATION OF §481(a) ADJUSTMENT — REGULAR TAX
A8: As Previously Filed
A9: Asset | B9: Property Description | C9: Date In Service | D9: Cost | E9: Sec 179 Exp | F9: Bonus Amt | G9: Tax Prior Depreciation | H9: Tax Current Depreciation | I9: End Depreciation | J9: Net Book Value | K9: Method | L9: Period
A10: 1 | B10: 2-Building | C10: 9/22/21 | D10: 383408.73 | E10: 0 | F10: 0 | G10: 31950.77 | H10: 13942.17 | I10: =G10+H10 -> 45892.94 | J10: =D10-I10 -> 337515.79 | K10: S/L | L10: 27.5
A11: 2 | B11: 3-Land Improvements | C11: 9/22/21 | D11: 41779.44 | E11: 0 | F11: 41779.44 | G11: 41779.44 | H11: 0 | I11: =G11+H11 -> 41779.44 | J11: =D11-I11 -> 0 | K11: 150DB | L11: 15.0
A12: 3 | B12: 4-Equipment | C12: 9/22/21 | D12: 78336.54 | E12: 0 | F12: 78336.54 | G12: 78336.54 | H12: 0 | I12: =G12+H12 -> 78336.54 | J12: =D12-I12 -> 0 | K12: 200DB | L12: 5.0
B13: Grand Total | D13: =SUM(D10:D12) -> 503524.71 | E13: =SUM(E10:E12) -> 0 | F13: =SUM(F10:F12) -> 120115.98 | G13: =SUM(G10:G12) -> 152066.75 | H13: =SUM(H10:H12) -> 13942.17 | I13: =SUM(I10:I12) -> 166008.92 | J13: =SUM(J10:J12) -> 337515.79
A15: After Cost Segregation Correction
A16: Asset | B16: Property Description | C16: Date In Service | D16: Cost | E16: Sec 179 Exp | F16: Bonus Amt | G16: Tax Prior Depreciation | H16: Tax Current Depreciation | I16: End Depreciation | J16: Net Book Value | K16: Method | L16: Period
A17: 1 | B17: 2-Building-5yr | C17: 9/22/21 | D17: 95762.44 | E17: 0 | F17: 95762.44 | G17: 95762.44 | H17: 0 | I17: =G17+H17 -> 95762.44 | J17: =D17-I17 -> 0 | K17: 200DB | L17: 5.0
A18: 2 | B18: 2-Building-27.5yr | C18: 9/22/21 | D18: 287646.29 | E18: 0 | F18: 0 | G18: 23970.53 | H18: 10459.87 | I18: =G18+H18 -> 34430.4 | J18: =D18-I18 -> 253215.89 | K18: S/L | L18: 27.5
A19: 3 | B19: 3-Land Improvements-5yr | C19: 9/22/21 | D19: 10435.08 | E19: 0 | F19: 10435.08 | G19: 10435.08 | H19: 0 | I19: =G19+H19 -> 10435.08 | J19: =D19-I19 -> 0 | K19: 200DB | L19: 5.0
A20: 4 | B20: 2-Building-27.5yr | C20: 9/22/21 | D20: 31344.36 | E20: 0 | F20: 0 | G20: 2612.02 | H20: 1139.79 | I20: =G20+H20 -> 3751.81 | J20: =D20-I20 -> 27592.55 | K20: S/L | L20: 27.5
A21: 5 | B21: 4-Equipment-5yr | C21: 9/22/21 | D21: 19565.8 | E21: 0 | F21: 19565.8 | G21: 19565.8 | H21: 0 | I21: =G21+H21 -> 19565.8 | J21: =D21-I21 -> 0 | K21: 200DB | L21: 5.0
A22: 6 | B22: 4-Equipment-27.5yr | C22: 9/22/21 | D22: 58770.74 | E22: 0 | F22: 0 | G22: 4897.57 | H22: 2137.12 | I22: =G22+H22 -> 7034.69 | J22: =D22-I22 -> 51736.05 | K22: S/L | L22: 27.5
B23: Grand Total | D23: =SUM(D17:D22) -> 503524.71 | E23: =SUM(E17:E22) -> 0 | F23: =SUM(F17:F22) -> 125763.32 | G23: =SUM(G17:G22) -> 157243.44 | H23: =SUM(H17:H22) -> 13736.78 | I23: =SUM(I17:I22) -> 170980.22 | J23: =SUM(J17:J22) -> 332544.49
B25: Section 481(a) Adjustment — Regular Tax
B26: Depreciation reported previously | D26: =I13 -> 166008.92
B27: Cost Segregation Corrected Depreciation | D27: =I23 -> 170980.22
B28: Section 481(a) Adjustment — Regular Tax | D28: =D26-D27 -> -4971.3
A30: CALCULATION OF §481(a) ADJUSTMENT — AMT
A31: As Previously Filed — AMT
A32: Asset | B32: Property Description | C32: Date In Service | D32: Cost | E32: Sec 179 Exp | F32: Bonus Amt | G32: AMT Prior Depreciation | H32: AMT Current Depreciation | I32: End Depreciation | J32: Net Book Value | K32: Method | L32: Period
A33: 1 | B33: 2-Building | C33: 9/22/21 | D33: 383408.73 | E33: 0 | F33: 0 | G33: 31950.77 | H33: 13942.17 | I33: =G33+H33 -> 45892.94 | J33: =D33-I33 -> 337515.79 | K33: S/L | L33: 27.5
A34: 2 | B34: 3-Land Improvements | C34: 9/22/21 | D34: 41779.44 | E34: 0 | F34: 41779.44 | G34: 41779.44 | H34: 0 | I34: =G34+H34 -> 41779.44 | J34: =D34-I34 -> 0 | K34: 150DB | L34: 15.0
A35: 3 | B35: 4-Equipment | C35: 9/22/21 | D35: 78336.54 | E35: 0 | F35: 78336.54 | G35: 78336.54 | H35: 0 | I35: =G35+H35 -> 78336.54 | J35: =D35-I35 -> 0 | K35: 200DB | L35: 5.0
B36: Grand Total | D36: =SUM(D33:D35) -> 503524.71 | E36: =SUM(E33:E35) -> 0 | F36: =SUM(F33:F35) -> 120115.98 | G36: =SUM(G33:G35) -> 152066.75 | H36: =SUM(H33:H35) -> 13942.17 | I36: =SUM(I33:I35) -> 166008.92 | J36: =SUM(J33:J35) -> 337515.79
A38: After Cost Segregation Correction — AMT
A39: Asset | B39: Property Description | C39: Date In Service | D39: Cost | E39: Sec 179 Exp | F39: Bonus Amt | G39: AMT Prior Depreciation | H39: AMT Current Depreciation | I39: End Depreciation | J39: Net Book Value | K39: Method | L39: Period
A40: 1 | B40: 2-Building-5yr | C40: 9/22/21 | D40: 95762.44 | E40: 0 | F40: 95762.44 | G40: 95762.44 | H40: 0 | I40: =G40+H40 -> 95762.44 | J40: =D40-I40 -> 0 | K40: 200DB | L40: 5.0
A41: 2 | B41: 2-Building-27.5yr | C41: 9/22/21 | D41: 287646.29 | E41: 0 | F41: 0 | G41: 23970.53 | H41: 10459.87 | I41: =G41+H41 -> 34430.4 | J41: =D41-I41 -> 253215.89 | K41: S/L | L41: 27.5
A42: 3 | B42: 3-Land Improvements-5yr | C42: 9/22/21 | D42: 10435.08 | E42: 0 | F42: 10435.08 | G42: 10435.08 | H42: 0 | I42: =G42+H42 -> 10435.08 | J42: =D42-I42 -> 0 | K42: 200DB | L42: 5.0
A43: 4 | B43: 2-Building-27.5yr | C43: 9/22/21 | D43: 31344.36 | E43: 0 | F43: 0 | G43: 2612.02 | H43: 1139.79 | I43: =G43+H43 -> 3751.81 | J43: =D43-I43 -> 27592.55 | K43: S/L | L43: 27.5
A44: 5 | B44: 4-Equipment-5yr | C44: 9/22/21 | D44: 19565.8 | E44: 0 | F44: 19565.8 | G44: 19565.8 | H44: 0 | I44: =G44+H44 -> 19565.8 | J44: =D44-I44 -> 0 | K44: 200DB | L44: 5.0
A45: 6 | B45: 4-Equipment-27.5yr | C45: 9/22/21 | D45: 58770.74 | E45: 0 | F45: 0 | G45: 4897.57 | H45: 2137.12 | I45: =G45+H45 -> 7034.69 | J45: =D45-I45 -> 51736.05 | K45: S/L | L45: 27.5
B46: Grand Total | D46: =SUM(D40:D45) -> 503524.71 | E46: =SUM(E40:E45) -> 0 | F46: =SUM(F40:F45) -> 125763.32 | G46: =SUM(G40:G45) -> 157243.44 | H46: =SUM(H40:H45) -> 13736.78 | I46: =SUM(I40:I45) -> 170980.22 | J46: =SUM(J40:J45) -> 332544.49
B48: Section 481(a) Adjustment — AMT
B49: Depreciation reported previously | D49: =I36 -> 166008.92
B50: Cost Segregation Corrected Depreciation | D50: =I46 -> 170980.22
B51: Section 481(a) Adjustment — AMT | D51: =D49-D50 -> -4971.3
A53: COST SEGREGATION STUDY — COST SUMMARY
B54: Total Building Cost | D54: =D93 -> 503524.71
B55: Building Components: 5 Year | D55: =F93 -> 125763.32
B56: % of Cost | D56: =F94 -> 0.24976594
B57: Building Structure: 27.5 Year | D57: =H93 -> 377761.39
B58: % of Cost | D58: =H94 -> 0.75023406
A60: COST SEGREGATION STUDY — COST DETAIL
B61: Property Category | D61: Cost | F61: 5 Year | H61: 27.5 Year
B62: Building Components
B63: Cabinets / Millwork | D63: =SUM(F63:H63) -> 26757.81 | F63: 26757.81
B64: Moldings | D64: =SUM(F64:H64) -> 7990.89 | F64: 7990.89
B65: Flooring - Vinyl Plank | D65: =SUM(F65:H65) -> 37800.94 | F65: 37800.94
B66: Door & Window Guards | D66: =SUM(F66:H66) -> 2842.52 | F66: 2842.52
B67: Window Treatments | D67: =SUM(F67:H67) -> 2418.44 | F67: 2418.44
B68: Specialty HVAC - Dryer Vents | D68: =SUM(F68:H68) -> 718.3 | F68: 718.3
B69: Building Signage | D69: =SUM(F69:H69) -> 705.03 | F69: 705.03
B70: Specialty Electrical - Appliances | D70: =SUM(F70:H70) -> 12363.8 | F70: 12363.8
B71: Communication / Data | D71: =SUM(F71:H71) -> 3400.77 | F71: 3400.77
B72: Specialty Plumbing - Kitchen Sinks / Laundry | D72: =SUM(F72:H72) -> 13431.92 | F72: 13431.92
B73: Security / Exterior Lighting | D73: =SUM(F73:H73) -> 1140.5 | F73: 1140.5
B74: Access Control | D74: =SUM(F74:H74) -> 1360.86 | F74: 1360.86
B75: Appliances | D75: =SUM(F75:H75) -> 14831.54 | F75: 14831.54
B76: Building Structure
B77: Foundations | D77: =SUM(F77:H77) -> 25110.72 | H77: 25110.72
B78: HVAC | D78: =SUM(F78:H78) -> 35390.34 | H78: 35390.34
B79: Electrical | D79: =SUM(F79:H79) -> 29008.33 | H79: 29008.33
B80: Plumbing | D80: =SUM(F80:H80) -> 31389.04 | H80: 31389.04
B81: Fire Protection & Alarm | D81: =SUM(F81:H81) -> 26496.62 | H81: 26496.62
B82: Exterior Façade / Building Skin | D82: =SUM(F82:H82) -> 12009.05 | H82: 12009.05
B83: Doors & Frames | D83: =SUM(F83:H83) -> 23153.47 | H83: 23153.47
B84: Windows | D84: =SUM(F84:H84) -> 10659.46 | H84: 10659.46
B85: Ceiling Systems | D85: =SUM(F85:H85) -> 16835.06 | H85: 16835.06
B86: Interior Framing / Partitions | D86: =SUM(F86:H86) -> 39604.25 | H86: 39604.25
B87: Painting | D87: =SUM(F87:H87) -> 16001 | H87: 16001
B88: Gutter Systems | D88: =SUM(F88:H88) -> 1863.69 | H88: 1863.69
... B92: Cabinets / Millwork - Restrooms | D92: =SUM(F92:H92) -> 6970.48 | H92: 6970.48
B93: Total Building Cost | D93: =SUM(D62:D92) -> 503524.71 | F93: =SUM(F62:F92) -> 125763.32 | H93: =SUM(H62:H92) -> 377761.39
B94: % of Cost | F94: =F93/D93 -> 0.24976594 | H94: =H93/D93 -> 0.75023406
A96: ASSET ALLOCATION (per After Cost Segregation schedule)
B97: Asset (as reclassified) | D97: Cost | F97: 5 Year | H97: 27.5 Year
B98: ='Bldg 7'!B17 -> 2-Building-5yr | D98: =SUM(F98:H98) -> 95762.44 | F98: ='Bldg 7'!D17 -> 95762.44
B99: ='Bldg 7'!B18 -> 2-Building-27.5yr | D99: =SUM(F99:H99) -> 287646.29 | H99: ='Bldg 7'!D18 -> 287646.29
B100: ='Bldg 7'!B19 -> 3-Land Improvements-5yr | D100: =SUM(F100:H100) -> 10435.08 | F100: ='Bldg 7'!D19 -> 10435.08
B101: ='Bldg 7'!B20 -> 2-Building-27.5yr | D101: =SUM(F101:H101) -> 31344.36 | H101: ='Bldg 7'!D20 -> 31344.36
B102: ='Bldg 7'!B21 -> 4-Equipment-5yr | D102: =SUM(F102:H102) -> 19565.8 | F102: ='Bldg 7'!D21 -> 19565.8
B103: ='Bldg 7'!B22 -> 4-Equipment-27.5yr | D103: =SUM(F103:H103) -> 58770.74 | H103: ='Bldg 7'!D22 -> 58770.74
B104: Total Allocation | D104: =SUM(D98:D103) -> 503524.71 | F104: =SUM(F98:F103) -> 125763.32 | H104: =SUM(H98:H103) -> 377761.39
B105: Check: Allocation vs. Cost Detail (should be zero) | D105: =D104-D93 -> 0

Sheet Bldg 8
A1: Coral Village Housing LP
A2: Coral Village — 121 NE 10th Pl, Cape Coral, FL 33909
A3: EIN: 87-2205593 · FYE: December 31, 2024 · Year of Change: 1/1/2024
A4: Bldg 8 — Attachment to Form 3115 (DCN #7, Rev. Proc. 2024-23 §6.01)
A5: Source: CSSI Report #107752-01, "Coral Village Housing LP - 3115 - 107752-01 - Combined.pdf"
A7: CALCULATION OF §481(a) ADJUSTMENT — REGULAR TAX
A8: As Previously Filed
A9: Asset | B9: Property Description | C9: Date In Service | D9: Cost | E9: Sec 179 Exp | F9: Bonus Amt | G9: Tax Prior Depreciation | H9: Tax Current Depreciation | I9: End Depreciation | J9: Net Book Value | K9: Method | L9: Period
A10: 1 | B10: 2-Building | C10: 9/22/21 | D10: 302676.39 | E10: 0 | F10: 0 | G10: 25223.07 | H10: 11006.44 | I10: =G10+H10 -> 36229.51 | J10: =D10-I10 -> 266446.88 | K10: S/L | L10: 27.5
A11: 2 | B11: 3-Land Improvements | C11: 9/22/21 | D11: 32982.17 | E11: 0 | F11: 32982.17 | G11: 32982.17 | H11: 0 | I11: =G11+H11 -> 32982.17 | J11: =D11-I11 -> 0 | K11: 150DB | L11: 15.0
A12: 3 | B12: 4-Equipment | C12: 9/22/21 | D12: 61841.63 | E12: 0 | F12: 61841.63 | G12: 61841.63 | H12: 0 | I12: =G12+H12 -> 61841.63 | J12: =D12-I12 -> 0 | K12: 200DB | L12: 5.0
B13: Grand Total | D13: =SUM(D10:D12) -> 397500.19 | E13: =SUM(E10:E12) -> 0 | F13: =SUM(F10:F12) -> 94823.8 | G13: =SUM(G10:G12) -> 120046.87 | H13: =SUM(H10:H12) -> 11006.44 | I13: =SUM(I10:I12) -> 131053.31 | J13: =SUM(J10:J12) -> 266446.88
A15: After Cost Segregation Correction
A16: Asset | B16: Property Description | C16: Date In Service | D16: Cost | E16: Sec 179 Exp | F16: Bonus Amt | G16: Tax Prior Depreciation | H16: Tax Current Depreciation | I16: End Depreciation | J16: Net Book Value | K16: Method | L16: Period
A17: 1 | B17: 2-Building-5yr | C17: 9/22/21 | D17: 83590.83 | E17: 0 | F17: 83590.83 | G17: 83590.83 | H17: 0 | I17: =G17+H17 -> 83590.83 | J17: =D17-I17 -> 0 | K17: 200DB | L17: 5.0
A18: 2 | B18: 2-Building-27.5yr | C18: 9/22/21 | D18: 219085.56 | E18: 0 | F18: 0 | G18: 18257.13 | H18: 7966.75 | I18: =G18+H18 -> 26223.88 | J18: =D18-I18 -> 192861.68 | K18: S/L | L18: 27.5
A19: 3 | B19: 3-Land Improvements-5yr | C19: 9/22/21 | D19: 9108.76 | E19: 0 | F19: 9108.76 | G19: 9108.76 | H19: 0 | I19: =G19+H19 -> 9108.76 | J19: =D19-I19 -> 0 | K19: 200DB | L19: 5.0
A20: 4 | B20: 2-Building-27.5yr | C20: 9/22/21 | D20: 23873.41 | E20: 0 | F20: 0 | G20: 1989.44 | H20: 868.12 | I20: =G20+H20 -> 2857.56 | J20: =D20-I20 -> 21015.85 | K20: S/L | L20: 27.5
A21: 5 | B21: 4-Equipment-5yr | C21: 9/22/21 | D21: 17078.94 | E21: 0 | F21: 17078.94 | G21: 17078.94 | H21: 0 | I21: =G21+H21 -> 17078.94 | J21: =D21-I21 -> 0 | K21: 200DB | L21: 5.0
A22: 6 | B22: 4-Equipment-27.5yr | C22: 9/22/21 | D22: 44762.69 | E22: 0 | F22: 0 | G22: 3730.22 | H22: 1627.73 | I22: =G22+H22 -> 5357.95 | J22: =D22-I22 -> 39404.74 | K22: S/L | L22: 27.5
B23: Grand Total | D23: =SUM(D17:D22) -> 397500.19 | E23: =SUM(E17:E22) -> 0 | F23: =SUM(F17:F22) -> 109778.53 | G23: =SUM(G17:G22) -> 133755.32 | H23: =SUM(H17:H22) -> 10462.6 | I23: =SUM(I17:I22) -> 144217.92 | J23: =SUM(J17:J22) -> 253282.27
B25: Section 481(a) Adjustment — Regular Tax
B26: Depreciation reported previously | D26: =I13 -> 131053.31
B27: Cost Segregation Corrected Depreciation | D27: =I23 -> 144217.92
B28: Section 481(a) Adjustment — Regular Tax | D28: =D26-D27 -> -13164.61
A30: CALCULATION OF §481(a) ADJUSTMENT — AMT
A31: As Previously Filed — AMT
A32: Asset | B32: Property Description | C32: Date In Service | D32: Cost | E32: Sec 179 Exp | F32: Bonus Amt | G32: AMT Prior Depreciation | H32: AMT Current Depreciation | I32: End Depreciation | J32: Net Book Value | K32: Method | L32: Period
A33: 1 | B33: 2-Building | C33: 9/22/21 | D33: 302676.39 | E33: 0 | F33: 0 | G33: 25223.07 | H33: 11006.44 | I33: =G33+H33 -> 36229.51 | J33: =D33-I33 -> 266446.88 | K33: S/L | L33: 27.5
A34: 2 | B34: 3-Land Improvements | C34: 9/22/21 | D34: 32982.17 | E34: 0 | F34: 32982.17 | G34: 32982.17 | H34: 0 | I34: =G34+H34 -> 32982.17 | J34: =D34-I34 -> 0 | K34: 150DB | L34: 15.0
A35: 3 | B35: 4-Equipment | C35: 9/22/21 | D35: 61841.63 | E35: 0 | F35: 61841.63 | G35: 61841.63 | H35: 0 | I35: =G35+H35 -> 61841.63 | J35: =D35-I35 -> 0 | K35: 200DB | L35: 5.0
B36: Grand Total | D36: =SUM(D33:D35) -> 397500.19 | E36: =SUM(E33:E35) -> 0 | F36: =SUM(F33:F35) -> 94823.8 | G36: =SUM(G33:G35) -> 120046.87 | H36: =SUM(H33:H35) -> 11006.44 | I36: =SUM(I33:I35) -> 131053.31 | J36: =SUM(J33:J35) -> 266446.88
A38: After Cost Segregation Correction — AMT
A39: Asset | B39: Property Description | C39: Date In Service | D39: Cost | E39: Sec 179 Exp | F39: Bonus Amt | G39: AMT Prior Depreciation | H39: AMT Current Depreciation | I39: End Depreciation | J39: Net Book Value | K39: Method | L39: Period
A40: 1 | B40: 2-Building-5yr | C40: 9/22/21 | D40: 83590.83 | E40: 0 | F40: 83590.83 | G40: 83590.83 | H40: 0 | I40: =G40+H40 -> 83590.83 | J40: =D40-I40 -> 0 | K40: 200DB | L40: 5.0
A41: 2 | B41: 2-Building-27.5yr | C41: 9/22/21 | D41: 219085.56 | E41: 0 | F41: 0 | G41: 18257.13 | H41: 7966.75 | I41: =G41+H41 -> 26223.88 | J41: =D41-I41 -> 192861.68 | K41: S/L | L41: 27.5
A42: 3 | B42: 3-Land Improvements-5yr | C42: 9/22/21 | D42: 9108.76 | E42: 0 | F42: 9108.76 | G42: 9108.76 | H42: 0 | I42: =G42+H42 -> 9108.76 | J42: =D42-I42 -> 0 | K42: 200DB | L42: 5.0
A43: 4 | B43: 2-Building-27.5yr | C43: 9/22/21 | D43: 23873.41 | E43: 0 | F43: 0 | G43: 1989.44 | H43: 868.12 | I43: =G43+H43 -> 2857.56 | J43: =D43-I43 -> 21015.85 | K43: S/L | L43: 27.5
A44: 5 | B44: 4-Equipment-5yr | C44: 9/22/21 | D44: 17078.94 | E44: 0 | F44: 17078.94 | G44: 17078.94 | H44: 0 | I44: =G44+H44 -> 17078.94 | J44: =D44-I44 -> 0 | K44: 200DB | L44: 5.0
A45: 6 | B45: 4-Equipment-27.5yr | C45: 9/22/21 | D45: 44762.69 | E45: 0 | F45: 0 | G45: 3730.22 | H45: 1627.73 | I45: =G45+H45 -> 5357.95 | J45: =D45-I45 -> 39404.74 | K45: S/L | L45: 27.5
B46: Grand Total | D46: =SUM(D40:D45) -> 397500.19 | E46: =SUM(E40:E45) -> 0 | F46: =SUM(F40:F45) -> 109778.53 | G46: =SUM(G40:G45) -> 133755.32 | H46: =SUM(H40:H45) -> 10462.6 | I46: =SUM(I40:I45) -> 144217.92 | J46: =SUM(J40:J45) -> 253282.27
B48: Section 481(a) Adjustment — AMT
B49: Depreciation reported previously | D49: =I36 -> 131053.31
B50: Cost Segregation Corrected Depreciation | D50: =I46 -> 144217.92
B51: Section 481(a) Adjustment — AMT | D51: =D49-D50 -> -13164.61
A53: COST SEGREGATION STUDY — COST SUMMARY
B54: Total Building Cost | D54: =D94 -> 397500.19
B55: Building Components: 5 Year | D55: =F94 -> 109778.53
B56: % of Cost | D56: =F95 -> 0.27617227
B57: Building Structure: 27.5 Year | D57: =H94 -> 287721.66
B58: % of Cost | D58: =H95 -> 0.72382773
A60: COST SEGREGATION STUDY — COST DETAIL
B61: Property Category | D61: Cost | F61: 5 Year | H61: 27.5 Year
B62: Building Components
B63: Cabinets / Millwork | D63: =SUM(F63:H63) -> 26445.19 | F63: 26445.19
B64: Moldings | D64: =SUM(F64:H64) -> 4635.69 | F64: 4635.69
B65: Flooring - Carpet | D65: =SUM(F65:H65) -> 9118.09 | F65: 9118.09
B66: Flooring - Vinyl Plank | D66: =SUM(F66:H66) -> 17166.07 | F66: 17166.07
B67: Door & Window Guards | D67: =SUM(F67:H67) -> 2842.52 | F67: 2842.52
B68: Window Treatments | D68: =SUM(F68:H68) -> 2418.44 | F68: 2418.44
B69: Specialty HVAC - Dryer Vents | D69: =SUM(F69:H69) -> 718.3 | F69: 718.3
B70: Building Signage | D70: =SUM(F70:H70) -> 705.03 | F70: 705.03
B71: Specialty Electrical - Appliances | D71: =SUM(F71:H71) -> 12363.8 | F71: 12363.8
B72: Communication / Data | D72: =SUM(F72:H72) -> 2600.58 | F72: 2600.58
B73: Specialty Plumbing - Kitchen Sinks / Laundry | D73: =SUM(F73:H73) -> 13431.92 | F73: 13431.92
B74: Security / Exterior Lighting | D74: =SUM(F74:H74) -> 1140.5 | F74: 1140.5
... B76: Appliances | D76: =SUM(F76:H76) -> 14831.54 | F76: 14831.54
B77: Building Structure
B78: Foundations | D78: =SUM(F78:H78) -> 19166.81 | H78: 19166.81
B79: HVAC | D79: =SUM(F79:H79) -> 26894.18 | H79: 26894.18
B80: Electrical | D80: =SUM(F80:H80) -> 19273.71 | H80: 19273.71
B81: Plumbing | D81: =SUM(F81:H81) -> 24003.39 | H81: 24003.39
B82: Fire Protection & Alarm | D82: =SUM(F82:H82) -> 23233.4 | H82: 23233.4
B83: Exterior Façade / Building Skin | D83: =SUM(F83:H83) -> 8832.92 | H83: 8832.92
B84: Doors & Frames | D84: =SUM(F84:H84) -> 17315.31 | H84: 17315.31
B85: Windows | D85: =SUM(F85:H85) -> 10659.46 | H85: 10659.46
B86: Ceiling Systems | D86: =SUM(F86:H86) -> 12873.87 | H86: 12873.87
B87: Interior Framing / Partitions | D87: =SUM(F87:H87) -> 29302.11 | H87: 29302.11
B88: Painting | D88: =SUM(F88:H88) -> 11976.41 | H88: 11976.41
B89: Gutter Systems | D89: =SUM(F89:H89) -> 1737.32 | H89: 1737.32
... B93: Cabinets / Millwork - Restrooms | D93: =SUM(F93:H93) -> 3303.27 | H93: 3303.27
B94: Total Building Cost | D94: =SUM(D62:D93) -> 397500.19 | F94: =SUM(F62:F93) -> 109778.53 | H94: =SUM(H62:H93) -> 287721.66
B95: % of Cost | F95: =F94/D94 -> 0.27617227 | H95: =H94/D94 -> 0.72382773
A97: ASSET ALLOCATION (per After Cost Segregation schedule)
B98: Asset (as reclassified) | D98: Cost | F98: 5 Year | H98: 27.5 Year
B99: ='Bldg 8'!B17 -> 2-Building-5yr | D99: =SUM(F99:H99) -> 83590.83 | F99: ='Bldg 8'!D17 -> 83590.83
B100: ='Bldg 8'!B18 -> 2-Building-27.5yr | D100: =SUM(F100:H100) -> 219085.56 | H100: ='Bldg 8'!D18 -> 219085.56
B101: ='Bldg 8'!B19 -> 3-Land Improvements-5yr | D101: =SUM(F101:H101) -> 9108.76 | F101: ='Bldg 8'!D19 -> 9108.76
B102: ='Bldg 8'!B20 -> 2-Building-27.5yr | D102: =SUM(F102:H102) -> 23873.41 | H102: ='Bldg 8'!D20 -> 23873.41
B103: ='Bldg 8'!B21 -> 4-Equipment-5yr | D103: =SUM(F103:H103) -> 17078.94 | F103: ='Bldg 8'!D21 -> 17078.94
B104: ='Bldg 8'!B22 -> 4-Equipment-27.5yr | D104: =SUM(F104:H104) -> 44762.69 | H104: ='Bldg 8'!D22 -> 44762.69
B105: Total Allocation | D105: =SUM(D99:D104) -> 397500.19 | F105: =SUM(F99:F104) -> 109778.53 | H105: =SUM(H99:H104) -> 287721.66
B106: Check: Allocation vs. Cost Detail (should be zero) | D106: =D105-D94 -> 0

Sheet Bldg 9
A1: Coral Village Housing LP
A2: Coral Village — 121 NE 10th Pl, Cape Coral, FL 33909
A3: EIN: 87-2205593 · FYE: December 31, 2024 · Year of Change: 1/1/2024
A4: Bldg 9 — Attachment to Form 3115 (DCN #7, Rev. Proc. 2024-23 §6.01)
A5: Source: CSSI Report #107752-01, "Coral Village Housing LP - 3115 - 107752-01 - Combined.pdf"
A7: CALCULATION OF §481(a) ADJUSTMENT — REGULAR TAX
A8: As Previously Filed
A9: Asset | B9: Property Description | C9: Date In Service | D9: Cost | E9: Sec 179 Exp | F9: Bonus Amt | G9: Tax Prior Depreciation | H9: Tax Current Depreciation | I9: End Depreciation | J9: Net Book Value | K9: Method | L9: Period
A10: 1 | B10: 2-Building | C10: 9/22/21 | D10: 302676.39 | E10: 0 | F10: 0 | G10: 25223.07 | H10: 11006.44 | I10: =G10+H10 -> 36229.51 | J10: =D10-I10 -> 266446.88 | K10: S/L | L10: 27.5
A11: 2 | B11: 3-Land Improvements | C11: 9/22/21 | D11: 32982.17 | E11: 0 | F11: 32982.17 | G11: 32982.17 | H11: 0 | I11: =G11+H11 -> 32982.17 | J11: =D11-I11 -> 0 | K11: 150DB | L11: 15.0
A12: 3 | B12: 4-Equipment | C12: 9/22/21 | D12: 61841.63 | E12: 0 | F12: 61841.63 | G12: 61841.63 | H12: 0 | I12: =G12+H12 -> 61841.63 | J12: =D12-I12 -> 0 | K12: 200DB | L12: 5.0
B13: Grand Total | D13: =SUM(D10:D12) -> 397500.19 | E13: =SUM(E10:E12) -> 0 | F13: =SUM(F10:F12) -> 94823.8 | G13: =SUM(G10:G12) -> 120046.87 | H13: =SUM(H10:H12) -> 11006.44 | I13: =SUM(I10:I12) -> 131053.31 | J13: =SUM(J10:J12) -> 266446.88
A15: After Cost Segregation Correction
A16: Asset | B16: Property Description | C16: Date In Service | D16: Cost | E16: Sec 179 Exp | F16: Bonus Amt | G16: Tax Prior Depreciation | H16: Tax Current Depreciation | I16: End Depreciation | J16: Net Book Value | K16: Method | L16: Period
A17: 1 | B17: 2-Building-5yr | C17: 9/22/21 | D17: 83590.83 | E17: 0 | F17: 83590.83 | G17: 83590.83 | H17: 0 | I17: =G17+H17 -> 83590.83 | J17: =D17-I17 -> 0 | K17: 200DB | L17: 5.0
A18: 2 | B18: 2-Building-27.5yr | C18: 9/22/21 | D18: 219085.56 | E18: 0 | F18: 0 | G18: 18257.13 | H18: 7966.75 | I18: =G18+H18 -> 26223.88 | J18: =D18-I18 -> 192861.68 | K18: S/L | L18: 27.5
A19: 3 | B19: 3-Land Improvements-5yr | C19: 9/22/21 | D19: 9108.76 | E19: 0 | F19: 9108.76 | G19: 9108.76 | H19: 0 | I19: =G19+H19 -> 9108.76 | J19: =D19-I19 -> 0 | K19: 200DB | L19: 5.0
A20: 4 | B20: 2-Building-27.5yr | C20: 9/22/21 | D20: 23873.41 | E20: 0 | F20: 0 | G20: 1989.44 | H20: 868.12 | I20: =G20+H20 -> 2857.56 | J20: =D20-I20 -> 21015.85 | K20: S/L | L20: 27.5
A21: 5 | B21: 4-Equipment-5yr | C21: 9/22/21 | D21: 17078.94 | E21: 0 | F21: 17078.94 | G21: 17078.94 | H21: 0 | I21: =G21+H21 -> 17078.94 | J21: =D21-I21 -> 0 | K21: 200DB | L21: 5.0
A22: 6 | B22: 4-Equipment-27.5yr | C22: 9/22/21 | D22: 44762.69 | E22: 0 | F22: 0 | G22: 3730.22 | H22: 1627.73 | I22: =G22+H22 -> 5357.95 | J22: =D22-I22 -> 39404.74 | K22: S/L | L22: 27.5
B23: Grand Total | D23: =SUM(D17:D22) -> 397500.19 | E23: =SUM(E17:E22) -> 0 | F23: =SUM(F17:F22) -> 109778.53 | G23: =SUM(G17:G22) -> 133755.32 | H23: =SUM(H17:H22) -> 10462.6 | I23: =SUM(I17:I22) -> 144217.92 | J23: =SUM(J17:J22) -> 253282.27
B25: Section 481(a) Adjustment — Regular Tax
B26: Depreciation reported previously | D26: =I13 -> 131053.31
B27: Cost Segregation Corrected Depreciation | D27: =I23 -> 144217.92
B28: Section 481(a) Adjustment — Regular Tax | D28: =D26-D27 -> -13164.61
A30: CALCULATION OF §481(a) ADJUSTMENT — AMT
A31: As Previously Filed — AMT
A32: Asset | B32: Property Description | C32: Date In Service | D32: Cost | E32: Sec 179 Exp | F32: Bonus Amt | G32: AMT Prior Depreciation | H32: AMT Current Depreciation | I32: End Depreciation | J32: Net Book Value | K32: Method | L32: Period
A33: 1 | B33: 2-Building | C33: 9/22/21 | D33: 302676.39 | E33: 0 | F33: 0 | G33: 25223.07 | H33: 11006.44 | I33: =G33+H33 -> 36229.51 | J33: =D33-I33 -> 266446.88 | K33: S/L | L33: 27.5
A34: 2 | B34: 3-Land Improvements | C34: 9/22/21 | D34: 32982.17 | E34: 0 | F34: 32982.17 | G34: 32982.17 | H34: 0 | I34: =G34+H34 -> 32982.17 | J34: =D34-I34 -> 0 | K34: 150DB | L34: 15.0
A35: 3 | B35: 4-Equipment | C35: 9/22/21 | D35: 61841.63 | E35: 0 | F35: 61841.63 | G35: 61841.63 | H35: 0 | I35: =G35+H35 -> 61841.63 | J35: =D35-I35 -> 0 | K35: 200DB | L35: 5.0
B36: Grand Total | D36: =SUM(D33:D35) -> 397500.19 | E36: =SUM(E33:E35) -> 0 | F36: =SUM(F33:F35) -> 94823.8 | G36: =SUM(G33:G35) -> 120046.87 | H36: =SUM(H33:H35) -> 11006.44 | I36: =SUM(I33:I35) -> 131053.31 | J36: =SUM(J33:J35) -> 266446.88
A38: After Cost Segregation Correction — AMT
A39: Asset | B39: Property Description | C39: Date In Service | D39: Cost | E39: Sec 179 Exp | F39: Bonus Amt | G39: AMT Prior Depreciation | H39: AMT Current Depreciation | I39: End Depreciation | J39: Net Book Value | K39: Method | L39: Period
A40: 1 | B40: 2-Building-5yr | C40: 9/22/21 | D40: 83590.83 | E40: 0 | F40: 83590.83 | G40: 83590.83 | H40: 0 | I40: =G40+H40 -> 83590.83 | J40: =D40-I40 -> 0 | K40: 200DB | L40: 5.0
A41: 2 | B41: 2-Building-27.5yr | C41: 9/22/21 | D41: 219085.56 | E41: 0 | F41: 0 | G41: 18257.13 | H41: 7966.75 | I41: =G41+H41 -> 26223.88 | J41: =D41-I41 -> 192861.68 | K41: S/L | L41: 27.5
A42: 3 | B42: 3-Land Improvements-5yr | C42: 9/22/21 | D42: 9108.76 | E42: 0 | F42: 9108.76 | G42: 9108.76 | H42: 0 | I42: =G42+H42 -> 9108.76 | J42: =D42-I42 -> 0 | K42: 200DB | L42: 5.0
A43: 4 | B43: 2-Building-27.5yr | C43: 9/22/21 | D43: 23873.41 | E43: 0 | F43: 0 | G43: 1989.44 | H43: 868.12 | I43: =G43+H43 -> 2857.56 | J43: =D43-I43 -> 21015.85 | K43: S/L | L43: 27.5
A44: 5 | B44: 4-Equipment-5yr | C44: 9/22/21 | D44: 17078.94 | E44: 0 | F44: 17078.94 | G44: 17078.94 | H44: 0 | I44: =G44+H44 -> 17078.94 | J44: =D44-I44 -> 0 | K44: 200DB | L44: 5.0
A45: 6 | B45: 4-Equipment-27.5yr | C45: 9/22/21 | D45: 44762.69 | E45: 0 | F45: 0 | G45: 3730.22 | H45: 1627.73 | I45: =G45+H45 -> 5357.95 | J45: =D45-I45 -> 39404.74 | K45: S/L | L45: 27.5
B46: Grand Total | D46: =SUM(D40:D45) -> 397500.19 | E46: =SUM(E40:E45) -> 0 | F46: =SUM(F40:F45) -> 109778.53 | G46: =SUM(G40:G45) -> 133755.32 | H46: =SUM(H40:H45) -> 10462.6 | I46: =SUM(I40:I45) -> 144217.92 | J46: =SUM(J40:J45) -> 253282.27
B48: Section 481(a) Adjustment — AMT
B49: Depreciation reported previously | D49: =I36 -> 131053.31
B50: Cost Segregation Corrected Depreciation | D50: =I46 -> 144217.92
B51: Section 481(a) Adjustment — AMT | D51: =D49-D50 -> -13164.61
A53: COST SEGREGATION STUDY — COST SUMMARY
B54: Total Building Cost | D54: =D94 -> 397500.19
B55: Building Components: 5 Year | D55: =F94 -> 109778.53
B56: % of Cost | D56: =F95 -> 0.27617227
B57: Building Structure: 27.5 Year | D57: =H94 -> 287721.66
B58: % of Cost | D58: =H95 -> 0.72382773
A60: COST SEGREGATION STUDY — COST DETAIL
B61: Property Category | D61: Cost | F61: 5 Year | H61: 27.5 Year
B62: Building Components
B63: Cabinets / Millwork | D63: =SUM(F63:H63) -> 26445.19 | F63: 26445.19
B64: Moldings | D64: =SUM(F64:H64) -> 4635.69 | F64: 4635.69
B65: Flooring - Carpet | D65: =SUM(F65:H65) -> 9118.09 | F65: 9118.09
B66: Flooring - Vinyl Plank | D66: =SUM(F66:H66) -> 17166.07 | F66: 17166.07
B67: Door & Window Guards | D67: =SUM(F67:H67) -> 2842.52 | F67: 2842.52
B68: Window Treatments | D68: =SUM(F68:H68) -> 2418.44 | F68: 2418.44
B69: Specialty HVAC - Dryer Vents | D69: =SUM(F69:H69) -> 718.3 | F69: 718.3
B70: Building Signage | D70: =SUM(F70:H70) -> 705.03 | F70: 705.03
B71: Specialty Electrical - Appliances | D71: =SUM(F71:H71) -> 12363.8 | F71: 12363.8
B72: Communication / Data | D72: =SUM(F72:H72) -> 2600.58 | F72: 2600.58
B73: Specialty Plumbing - Kitchen Sinks / Laundry | D73: =SUM(F73:H73) -> 13431.92 | F73: 13431.92
B74: Security / Exterior Lighting | D74: =SUM(F74:H74) -> 1140.5 | F74: 1140.5
... B76: Appliances | D76: =SUM(F76:H76) -> 14831.54 | F76: 14831.54
B77: Building Structure
B78: Foundations | D78: =SUM(F78:H78) -> 19166.81 | H78: 19166.81
B79: HVAC | D79: =SUM(F79:H79) -> 26894.18 | H79: 26894.18
B80: Electrical | D80: =SUM(F80:H80) -> 19273.71 | H80: 19273.71
B81: Plumbing | D81: =SUM(F81:H81) -> 24003.39 | H81: 24003.39
B82: Fire Protection & Alarm | D82: =SUM(F82:H82) -> 23233.4 | H82: 23233.4
B83: Exterior Façade / Building Skin | D83: =SUM(F83:H83) -> 8832.92 | H83: 8832.92
B84: Doors & Frames | D84: =SUM(F84:H84) -> 17315.31 | H84: 17315.31
B85: Windows | D85: =SUM(F85:H85) -> 10659.46 | H85: 10659.46
B86: Ceiling Systems | D86: =SUM(F86:H86) -> 12873.87 | H86: 12873.87
B87: Interior Framing / Partitions | D87: =SUM(F87:H87) -> 29302.11 | H87: 29302.11
B88: Painting | D88: =SUM(F88:H88) -> 11976.41 | H88: 11976.41
B89: Gutter Systems | D89: =SUM(F89:H89) -> 1737.32 | H89: 1737.32
... B93: Cabinets / Millwork - Restrooms | D93: =SUM(F93:H93) -> 3303.27 | H93: 3303.27
B94: Total Building Cost | D94: =SUM(D62:D93) -> 397500.19 | F94: =SUM(F62:F93) -> 109778.53 | H94: =SUM(H62:H93) -> 287721.66
B95: % of Cost | F95: =F94/D94 -> 0.27617227 | H95: =H94/D94 -> 0.72382773
A97: ASSET ALLOCATION (per After Cost Segregation schedule)
B98: Asset (as reclassified) | D98: Cost | F98: 5 Year | H98: 27.5 Year
B99: ='Bldg 9'!B17 -> 2-Building-5yr | D99: =SUM(F99:H99) -> 83590.83 | F99: ='Bldg 9'!D17 -> 83590.83
B100: ='Bldg 9'!B18 -> 2-Building-27.5yr | D100: =SUM(F100:H100) -> 219085.56 | H100: ='Bldg 9'!D18 -> 219085.56
B101: ='Bldg 9'!B19 -> 3-Land Improvements-5yr | D101: =SUM(F101:H101) -> 9108.76 | F101: ='Bldg 9'!D19 -> 9108.76
B102: ='Bldg 9'!B20 -> 2-Building-27.5yr | D102: =SUM(F102:H102) -> 23873.41 | H102: ='Bldg 9'!D20 -> 23873.41
B103: ='Bldg 9'!B21 -> 4-Equipment-5yr | D103: =SUM(F103:H103) -> 17078.94 | F103: ='Bldg 9'!D21 -> 17078.94
B104: ='Bldg 9'!B22 -> 4-Equipment-27.5yr | D104: =SUM(F104:H104) -> 44762.69 | H104: ='Bldg 9'!D22 -> 44762.69
B105: Total Allocation | D105: =SUM(D99:D104) -> 397500.19 | F105: =SUM(F99:F104) -> 109778.53 | H105: =SUM(H99:H104) -> 287721.66
B106: Check: Allocation vs. Cost Detail (should be zero) | D106: =D105-D94 -> 0

Sheet Office
A1: Coral Village Housing LP
A2: Coral Village — 121 NE 10th Pl, Cape Coral, FL 33909
A3: EIN: 87-2205593 · FYE: December 31, 2024 · Year of Change: 1/1/2024
A4: Office — Attachment to Form 3115 (DCN #7, Rev. Proc. 2024-23 §6.01)
A5: Source: CSSI Report #107752-01, "Coral Village Housing LP - 3115 - 107752-01 - Combined.pdf"
A7: CALCULATION OF §481(a) ADJUSTMENT — REGULAR TAX
A8: As Previously Filed
A9: Asset | B9: Property Description | C9: Date In Service | D9: Cost | E9: Sec 179 Exp | F9: Bonus Amt | G9: Tax Prior Depreciation | H9: Tax Current Depreciation | I9: End Depreciation | J9: Net Book Value | K9: Method | L9: Period
A10: 1 | B10: 2-Building | C10: 9/22/21 | D10: 119699.06 | E10: 0 | F10: 0 | G10: 9974.94 | H10: 4352.7 | I10: =G10+H10 -> 14327.64 | J10: =D10-I10 -> 105371.42 | K10: S/L | L10: 27.5
A11: 2 | B11: 3-Land Improvements | C11: 9/22/21 | D11: 13043.42 | E11: 0 | F11: 13043.42 | G11: 13043.42 | H11: 0 | I11: =G11+H11 -> 13043.42 | J11: =D11-I11 -> 0 | K11: 150DB | L11: 15.0
A12: 3 | B12: 4-Equipment | C12: 9/22/21 | D12: 24456.43 | E12: 0 | F12: 24456.43 | G12: 24456.43 | H12: 0 | I12: =G12+H12 -> 24456.43 | J12: =D12-I12 -> 0 | K12: 200DB | L12: 5.0
B13: Grand Total | D13: =SUM(D10:D12) -> 157198.91 | E13: =SUM(E10:E12) -> 0 | F13: =SUM(F10:F12) -> 37499.85 | G13: =SUM(G10:G12) -> 47474.79 | H13: =SUM(H10:H12) -> 4352.7 | I13: =SUM(I10:I12) -> 51827.49 | J13: =SUM(J10:J12) -> 105371.42
A15: After Cost Segregation Correction
A16: Asset | B16: Property Description | C16: Date In Service | D16: Cost | E16: Sec 179 Exp | F16: Bonus Amt | G16: Tax Prior Depreciation | H16: Tax Current Depreciation | I16: End Depreciation | J16: Net Book Value | K16: Method | L16: Period
A17: 1 | B17: 2-Building-5yr | C17: 9/22/21 | D17: 18498.54 | E17: 0 | F17: 18498.54 | G17: 18498.54 | H17: 0 | I17: =G17+H17 -> 18498.54 | J17: =D17-I17 -> 0 | K17: 200DB | L17: 5.0
A18: 2 | B18: 2-Building-27.5yr | C18: 9/22/21 | D18: 101200.52 | E18: 0 | F18: 0 | G18: 8433.38 | H18: 3680.02 | I18: =G18+H18 -> 12113.4 | J18: =D18-I18 -> 89087.12 | K18: S/L | L18: 27.5
A19: 3 | B19: 3-Land Improvements-5yr | C19: 9/22/21 | D19: 2015.76 | E19: 0 | F19: 2015.76 | G19: 2015.76 | H19: 0 | I19: =G19+H19 -> 2015.76 | J19: =D19-I19 -> 0 | K19: 200DB | L19: 5.0
A20: 4 | B20: 2-Building-27.5yr | C20: 9/22/21 | D20: 11027.66 | E20: 0 | F20: 0 | G20: 918.98 | H20: 401.01 | I20: =G20+H20 -> 1319.99 | J20: =D20-I20 -> 9707.67 | K20: S/L | L20: 27.5
A21: 5 | B21: 4-Equipment-5yr | C21: 9/22/21 | D21: 3779.55 | E21: 0 | F21: 3779.55 | G21: 3779.55 | H21: 0 | I21: =G21+H21 -> 3779.55 | J21: =D21-I21 -> 0 | K21: 200DB | L21: 5.0
A22: 6 | B22: 4-Equipment-27.5yr | C22: 9/22/21 | D22: 20676.88 | E22: 0 | F22: 0 | G22: 1723.08 | H22: 751.89 | I22: =G22+H22 -> 2474.97 | J22: =D22-I22 -> 18201.91 | K22: S/L | L22: 27.5
B23: Grand Total | D23: =SUM(D17:D22) -> 157198.91 | E23: =SUM(E17:E22) -> 0 | F23: =SUM(F17:F22) -> 24293.85 | G23: =SUM(G17:G22) -> 35369.29 | H23: =SUM(H17:H22) -> 4832.92 | I23: =SUM(I17:I22) -> 40202.21 | J23: =SUM(J17:J22) -> 116996.7
B25: Section 481(a) Adjustment — Regular Tax
B26: Depreciation reported previously | D26: =I13 -> 51827.49
B27: Cost Segregation Corrected Depreciation | D27: =I23 -> 40202.21
B28: Section 481(a) Adjustment — Regular Tax | D28: =D26-D27 -> 11625.28
A30: CALCULATION OF §481(a) ADJUSTMENT — AMT
A31: As Previously Filed — AMT
A32: Asset | B32: Property Description | C32: Date In Service | D32: Cost | E32: Sec 179 Exp | F32: Bonus Amt | G32: AMT Prior Depreciation | H32: AMT Current Depreciation | I32: End Depreciation | J32: Net Book Value | K32: Method | L32: Period
A33: 1 | B33: 2-Building | C33: 9/22/21 | D33: 119699.06 | E33: 0 | F33: 0 | G33: 9974.94 | H33: 4352.7 | I33: =G33+H33 -> 14327.64 | J33: =D33-I33 -> 105371.42 | K33: S/L | L33: 27.5
A34: 2 | B34: 3-Land Improvements | C34: 9/22/21 | D34: 13043.42 | E34: 0 | F34: 13043.42 | G34: 13043.42 | H34: 0 | I34: =G34+H34 -> 13043.42 | J34: =D34-I34 -> 0 | K34: 150DB | L34: 15.0
A35: 3 | B35: 4-Equipment | C35: 9/22/21 | D35: 24456.43 | E35: 0 | F35: 24456.43 | G35: 24456.43 | H35: 0 | I35: =G35+H35 -> 24456.43 | J35: =D35-I35 -> 0 | K35: 200DB | L35: 5.0
B36: Grand Total | D36: =SUM(D33:D35) -> 157198.91 | E36: =SUM(E33:E35) -> 0 | F36: =SUM(F33:F35) -> 37499.85 | G36: =SUM(G33:G35) -> 47474.79 | H36: =SUM(H33:H35) -> 4352.7 | I36: =SUM(I33:I35) -> 51827.49 | J36: =SUM(J33:J35) -> 105371.42
A38: After Cost Segregation Correction — AMT
A39: Asset | B39: Property Description | C39: Date In Service | D39: Cost | E39: Sec 179 Exp | F39: Bonus Amt | G39: AMT Prior Depreciation | H39: AMT Current Depreciation | I39: End Depreciation | J39: Net Book Value | K39: Method | L39: Period
A40: 1 | B40: 2-Building-5yr | C40: 9/22/21 | D40: 18498.54 | E40: 0 | F40: 18498.54 | G40: 18498.54 | H40: 0 | I40: =G40+H40 -> 18498.54 | J40: =D40-I40 -> 0 | K40: 200DB | L40: 5.0
A41: 2 | B41: 2-Building-27.5yr | C41: 9/22/21 | D41: 101200.52 | E41: 0 | F41: 0 | G41: 8433.38 | H41: 3680.02 | I41: =G41+H41 -> 12113.4 | J41: =D41-I41 -> 89087.12 | K41: S/L | L41: 27.5
A42: 3 | B42: 3-Land Improvements-5yr | C42: 9/22/21 | D42: 2015.76 | E42: 0 | F42: 2015.76 | G42: 2015.76 | H42: 0 | I42: =G42+H42 -> 2015.76 | J42: =D42-I42 -> 0 | K42: 200DB | L42: 5.0
A43: 4 | B43: 2-Building-27.5yr | C43: 9/22/21 | D43: 11027.66 | E43: 0 | F43: 0 | G43: 918.98 | H43: 401.01 | I43: =G43+H43 -> 1319.99 | J43: =D43-I43 -> 9707.67 | K43: S/L | L43: 27.5
A44: 5 | B44: 4-Equipment-5yr | C44: 9/22/21 | D44: 3779.55 | E44: 0 | F44: 3779.55 | G44: 3779.55 | H44: 0 | I44: =G44+H44 -> 3779.55 | J44: =D44-I44 -> 0 | K44: 200DB | L44: 5.0
A45: 6 | B45: 4-Equipment-27.5yr | C45: 9/22/21 | D45: 20676.88 | E45: 0 | F45: 0 | G45: 1723.08 | H45: 751.89 | I45: =G45+H45 -> 2474.97 | J45: =D45-I45 -> 18201.91 | K45: S/L | L45: 27.5
B46: Grand Total | D46: =SUM(D40:D45) -> 157198.91 | E46: =SUM(E40:E45) -> 0 | F46: =SUM(F40:F45) -> 24293.85 | G46: =SUM(G40:G45) -> 35369.29 | H46: =SUM(H40:H45) -> 4832.92 | I46: =SUM(I40:I45) -> 40202.21 | J46: =SUM(J40:J45) -> 116996.7
B48: Section 481(a) Adjustment — AMT
B49: Depreciation reported previously | D49: =I36 -> 51827.49
B50: Cost Segregation Corrected Depreciation | D50: =I46 -> 40202.21
B51: Section 481(a) Adjustment — AMT | D51: =D49-D50 -> 11625.28
A53: COST SEGREGATION STUDY — COST SUMMARY
B54: Total Building Cost | D54: =D95 -> 157198.91
B55: Building Components: 5 Year | D55: =F95 -> 24293.85
B56: % of Cost | D56: =F96 -> 0.1545421
B57: Building Structure: 27.5 Year | D57: =H95 -> 132905.06
B58: % of Cost | D58: =H96 -> 0.8454579
A60: COST SEGREGATION STUDY — COST DETAIL
B61: Property Category | D61: Cost | F61: 5 Year | H61: 27.5 Year
B62: Building Components
B63: Cabinets / Millwork | D63: =SUM(F63:H63) -> 2291.97 | F63: 2291.97
B64: Moldings | D64: =SUM(F64:H64) -> 2430.16 | F64: 2430.16
B65: Flooring - Carpet | D65: =SUM(F65:H65) -> 2419.4 | F65: 2419.4
B66: Flooring - Vinyl Plank | D66: =SUM(F66:H66) -> 555.89 | F66: 555.89
B67: Security System | D67: =SUM(F67:H67) -> 599.12 | F67: 599.12
B68: Window Treatments | D68: =SUM(F68:H68) -> 1112.48 | F68: 1112.48
B69: Specialty HVAC - Dryer Vents | D69: =SUM(F69:H69) -> 269.36 | F69: 269.36
B70: Building Signage | D70: =SUM(F70:H70) -> 92.21 | F70: 92.21
B71: Specialty Electrical - Appliances | D71: =SUM(F71:H71) -> 1299.33 | F71: 1299.33
B72: Communication / Data | D72: =SUM(F72:H72) -> 3490.05 | F72: 3490.05
B73: Specialty Plumbing - Kitchen Sink / Laundry | D73: =SUM(F73:H73) -> 3357.95 | F73: 3357.95
B74: Security / Exterior Lighting | D74: =SUM(F74:H74) -> 554.78 | F74: 554.78
... B76: Appliances | D76: =SUM(F76:H76) -> 3435.67 | F76: 3435.67
B77: Building Structure
B78: Foundations | D78: =SUM(F78:H78) -> 14287.74 | H78: 14287.74
B79: HVAC | D79: =SUM(F79:H79) -> 9649.9 | H79: 9649.9
B80: Electrical | D80: =SUM(F80:H80) -> 10065.83 | H80: 10065.83
B81: Plumbing | D81: =SUM(F81:H81) -> 5264.8 | H81: 5264.8
B82: Fire Protection & Alarm | D82: =SUM(F82:H82) -> 12711.3 | H82: 12711.3
B83: Exterior Façade / Building Skin | D83: =SUM(F83:H83) -> 5317.82 | H83: 5317.82
B84: Doors & Frames | D84: =SUM(F84:H84) -> 6989.18 | H84: 6989.18
B85: Windows | D85: =SUM(F85:H85) -> 4903.35 | H85: 4903.35
B86: Ceiling Systems | D86: =SUM(F86:H86) -> 4624.69 | H86: 4624.69
B87: Interior Framing / Partitions | D87: =SUM(F87:H87) -> 14835.75 | H87: 14835.75
B88: Painting | D88: =SUM(F88:H88) -> 5494.23 | H88: 5494.23
B89: Gutter Systems | D89: =SUM(F89:H89) -> 966.23 | H89: 966.23
... B94: Cabinets / Millwork - Restrooms | D94: =SUM(F94:H94) -> 134.1 | H94: 134.1
B95: Total Building Cost | D95: =SUM(D62:D94) -> 157198.91 | F95: =SUM(F62:F94) -> 24293.85 | H95: =SUM(H62:H94) -> 132905.06
B96: % of Cost | F96: =F95/D95 -> 0.1545421 | H96: =H95/D95 -> 0.8454579
A98: ASSET ALLOCATION (per After Cost Segregation schedule)
B99: Asset (as reclassified) | D99: Cost | F99: 5 Year | H99: 27.5 Year
B100: =Office!B17 -> 2-Building-5yr | D100: =SUM(F100:H100) -> 18498.54 | F100: =Office!D17 -> 18498.54
B101: =Office!B18 -> 2-Building-27.5yr | D101: =SUM(F101:H101) -> 101200.52 | H101: =Office!D18 -> 101200.52
B102: =Office!B19 -> 3-Land Improvements-5yr | D102: =SUM(F102:H102) -> 2015.76 | F102: =Office!D19 -> 2015.76
B103: =Office!B20 -> 2-Building-27.5yr | D103: =SUM(F103:H103) -> 11027.66 | H103: =Office!D20 -> 11027.66
B104: =Office!B21 -> 4-Equipment-5yr | D104: =SUM(F104:H104) -> 3779.55 | F104: =Office!D21 -> 3779.55
B105: =Office!B22 -> 4-Equipment-27.5yr | D105: =SUM(F105:H105) -> 20676.88 | H105: =Office!D22 -> 20676.88
B106: Total Allocation | D106: =SUM(D100:D105) -> 157198.91 | F106: =SUM(F100:F105) -> 24293.85 | H106: =SUM(H100:H105) -> 132905.06
B107: Check: Allocation vs. Cost Detail (should be zero) | D107: =D106-D95 -> 0
