Workbook

Sheet Summary
A1: Grace Townhomes Housing, LLC
A2: Grace Townhomes — 1212 Grace Cir, Ennis, TX 75119
A3: EIN: 47-5360069 · FYE: December 31, 2024 · Year of Change: 1/1/2024
A4: Summary of Cost Segregation Adjustments — CSSI Report #107752-11 (CAM — DCN #7)
A7: Acq Date | B7: Asset Description | C7: Total | D7: Site | E7: Clubhouse | F7: Building 1 | G7: Building 2 | H7: Building 3 | I7: Building 4 | J7: Building 5 | K7: Building 6 | L7: Building 7 | M7: Building 8 | N7: Building 9 | O7: Building 10 | P7: Building 11 | Q7: Building 12 | R7: Building 13 | S7: Building 14 | T7: Building 15 | U7: Building 16 | V7: Building 17 | W7: Building 18 | X7: Building 19 | Y7: Building 20 | Z7: Building 21 | AA7: Building 22 | AB7: Building 23 | AC7: Building 24 | AD7: Building 25 | AE7: Storage
A8: 12/17/15 | B8: 1 - Buillding - Site | C8: =SUM(D8:AE8) -> 636512.99 | D8: =Site!$D$10 -> 636512.99
A9: 1/14/16 | B9: 5 - Building - Site | C9: =SUM(D9:AE9) -> 1159.28 | D9: =Site!$D$11 -> 1159.28
A10: 12/17/15 | B10: 3 - Land Improvements - Site | C10: =SUM(D10:AE10) -> 60048.41 | D10: =Site!$D$12 -> 60048.41
A11: 12/17/15 | B11: 4 - Equipment - Site | C11: =SUM(D11:AE11) -> 108770.22 | D11: =Site!$D$13 -> 108770.22
A12: 12/17/15 | B12: 1 - Buillding - Clubhouse | C12: =SUM(D12:AE12) -> 87855.35 | E12: =Clubhouse!$D$10 -> 87855.35
A13: 1/14/16 | B13: 5 - Building - Clubhouse | C13: =SUM(D13:AE13) -> 160.01 | E13: =Clubhouse!$D$11 -> 160.01
A14: 12/17/15 | B14: 3 - Land Improvements - Clubhouse | C14: =SUM(D14:AE14) -> 8288.23 | E14: =Clubhouse!$D$12 -> 8288.23
A15: 12/17/15 | B15: 4 - Equipment - Clubhouse | C15: =SUM(D15:AE15) -> 15013.12 | E15: =Clubhouse!$D$13 -> 15013.12
A16: 12/17/15 | B16: 1 - Buillding - Apt | C16: =SUM(D16:AE16) -> 3337378.8 | F16: ='Building 1'!$D$10 -> 212191.05 | G16: ='Building 2'!$D$10 -> 212191.05 | H16: ='Building 3'!$D$10 -> 116723.12 | I16: ='Building 4'!$D$10 -> 91140.5 | J16: ='Building 5'!$D$10 -> 116723.12 | K16: ='Building 6'!$D$10 -> 116723.12 | L16: ='Building 7'!$D$10 -> 116723.12 | M16: ='Building 8'!$D$10 -> 116723.12 | N16: ='Building 9'!$D$10 -> 116723.12 | O16: ='Building 10'!$D$10 -> 116723.12 | P16: ='Building 11'!$D$10 -> 91140.5 | Q16: ='Building 12'!$D$10 -> 212191.05 | R16: ='Building 13'!$D$10 -> 282065.31 | S16: ='Building 14'!$D$10 -> 212191.05 | T16: ='Building 15'!$D$10 -> 91140.5 | U16: ='Building 16'!$D$10 -> 116723.12 | V16: ='Building 17'!$D$10 -> 116723.12 | W16: ='Building 18'!$D$10 -> 91140.5 | X16: ='Building 19'!$D$10 -> 116723.12 | Y16: ='Building 20'!$D$10 -> 91140.5 | Z16: ='Building 21'!$D$10 -> 116723.12 | AA16: ='Building 22'!$D$10 -> 116723.12 | AB16: ='Building 23'!$D$10 -> 116723.12 | AC16: ='Building 24'!$D$10 -> 116723.12 | AD16: ='Building 25'!$D$10 -> 116723.12
A17: 1/14/16 | B17: 5 - Building - Apt | C17: =SUM(D17:AE17) -> 6078.16 | F17: ='Building 1'!$D$11 -> 386.45 | G17: ='Building 2'!$D$11 -> 386.45 | H17: ='Building 3'!$D$11 -> 212.58 | I17: ='Building 4'!$D$11 -> 165.99 | J17: ='Building 5'!$D$11 -> 212.58 | K17: ='Building 6'!$D$11 -> 212.58 | L17: ='Building 7'!$D$11 -> 212.58 | M17: ='Building 8'!$D$11 -> 212.58 | N17: ='Building 9'!$D$11 -> 212.58 | O17: ='Building 10'!$D$11 -> 212.58 | P17: ='Building 11'!$D$11 -> 165.99 | Q17: ='Building 12'!$D$11 -> 386.45 | R17: ='Building 13'!$D$11 -> 513.71 | S17: ='Building 14'!$D$11 -> 386.45 | T17: ='Building 15'!$D$11 -> 165.99 | U17: ='Building 16'!$D$11 -> 212.58 | V17: ='Building 17'!$D$11 -> 212.58 | W17: ='Building 18'!$D$11 -> 165.99 | X17: ='Building 19'!$D$11 -> 212.58 | Y17: ='Building 20'!$D$11 -> 165.99 | Z17: ='Building 21'!$D$11 -> 212.58 | AA17: ='Building 22'!$D$11 -> 212.58 | AB17: ='Building 23'!$D$11 -> 212.58 | AC17: ='Building 24'!$D$11 -> 212.58 | AD17: ='Building 25'!$D$11 -> 212.58
A18: 12/17/15 | B18: 3 - Land Improvements - Apt | C18: =SUM(D18:AE18) -> 314846.66 | F18: ='Building 1'!$D$12 -> 20018 | G18: ='Building 2'!$D$12 -> 20018 | H18: ='Building 3'!$D$12 -> 11011.6 | I18: ='Building 4'!$D$12 -> 8598.15 | J18: ='Building 5'!$D$12 -> 11011.6 | K18: ='Building 6'!$D$12 -> 11011.6 | L18: ='Building 7'!$D$12 -> 11011.6 | M18: ='Building 8'!$D$12 -> 11011.6 | N18: ='Building 9'!$D$12 -> 11011.6 | O18: ='Building 10'!$D$12 -> 11011.6 | P18: ='Building 11'!$D$12 -> 8598.15 | Q18: ='Building 12'!$D$12 -> 20018 | R18: ='Building 13'!$D$12 -> 26609.91 | S18: ='Building 14'!$D$12 -> 20018 | T18: ='Building 15'!$D$12 -> 8598.15 | U18: ='Building 16'!$D$12 -> 11011.6 | V18: ='Building 17'!$D$12 -> 11011.6 | W18: ='Building 18'!$D$12 -> 8598.15 | X18: ='Building 19'!$D$12 -> 11011.6 | Y18: ='Building 20'!$D$12 -> 8598.15 | Z18: ='Building 21'!$D$12 -> 11011.6 | AA18: ='Building 22'!$D$12 -> 11011.6 | AB18: ='Building 23'!$D$12 -> 11011.6 | AC18: ='Building 24'!$D$12 -> 11011.6 | AD18: ='Building 25'!$D$12 -> 11011.6
A19: 12/17/15 | B19: 4 - Equipment - Apt | C19: =SUM(D19:AE19) -> 570306.32 | F19: ='Building 1'!$D$13 -> 36260.17 | G19: ='Building 2'!$D$13 -> 36260.17 | H19: ='Building 3'!$D$13 -> 19946.17 | I19: ='Building 4'!$D$13 -> 15574.5 | J19: ='Building 5'!$D$13 -> 19946.17 | K19: ='Building 6'!$D$13 -> 19946.17 | L19: ='Building 7'!$D$13 -> 19946.17 | M19: ='Building 8'!$D$13 -> 19946.17 | N19: ='Building 9'!$D$13 -> 19946.17 | O19: ='Building 10'!$D$13 -> 19946.17 | P19: ='Building 11'!$D$13 -> 15574.5 | Q19: ='Building 12'!$D$13 -> 36260.17 | R19: ='Building 13'!$D$13 -> 48200.59 | S19: ='Building 14'!$D$13 -> 36260.17 | T19: ='Building 15'!$D$13 -> 15574.5 | U19: ='Building 16'!$D$13 -> 19946.17 | V19: ='Building 17'!$D$13 -> 19946.17 | W19: ='Building 18'!$D$13 -> 15574.5 | X19: ='Building 19'!$D$13 -> 19946.17 | Y19: ='Building 20'!$D$13 -> 15574.5 | Z19: ='Building 21'!$D$13 -> 19946.17 | AA19: ='Building 22'!$D$13 -> 19946.17 | AB19: ='Building 23'!$D$13 -> 19946.17 | AC19: ='Building 24'!$D$13 -> 19946.17 | AD19: ='Building 25'!$D$13 -> 19946.17
A20: 12/17/15 | B20: 1 - Buillding - Storage | C20: =SUM(D20:AE20) -> 12928.85 | AE20: =Storage!$D$10 -> 12928.85
A21: 1/14/16 | B21: 5 - Building - Storage | C21: =SUM(D21:AE21) -> 23.55 | AE21: =Storage!$D$11 -> 23.55
A22: 12/17/15 | B22: 3 - Land Improvements - Storage | C22: =SUM(D22:AE22) -> 1219.7 | AE22: =Storage!$D$12 -> 1219.7
A23: 12/17/15 | B23: 4 - Equipment - Storage | C23: =SUM(D23:AE23) -> 2209.34 | AE23: =Storage!$D$13 -> 2209.34
B24: Grand Total | C24: =SUM(C8:C23) -> 5162799 | D24: =SUM(D8:D23) -> 806490.9 | E24: =SUM(E8:E23) -> 111316.71 | F24: =SUM(F8:F23) -> 268855.67 | G24: =SUM(G8:G23) -> 268855.67 | H24: =SUM(H8:H23) -> 147893.47 | I24: =SUM(I8:I23) -> 115479.14 | J24: =SUM(J8:J23) -> 147893.47 | ... AE24: =SUM(AE8:AE23) -> 16381.44
B26: MACRS Reclassification
A27: 12/17/15 | B27: 1 - Buillding - Site - 15yr | C27: =SUM(D27:AE27) -> 385433.18 | D27: =Site!$D$18 -> 385433.18
A28: 12/17/15 | B28: 1 - Buillding - Site - 27.5yr | C28: =SUM(D28:AE28) -> 251079.81 | D28: =Site!$D$19 -> 251079.81
A29: 1/14/16 | B29: 5 - Building - Site - 15yr | C29: =SUM(D29:AE29) -> 701.99 | D29: =Site!$D$20 -> 701.99
A30: 1/14/16 | B30: 5 - Building - Site - 27.5yr | C30: =SUM(D30:AE30) -> 457.29 | D30: =Site!$D$21 -> 457.29
A31: 12/17/15 | B31: 3 - Land Improvements - Site - 15yr | C31: =SUM(D31:AE31) -> 36361.63 | D31: =Site!$D$22 -> 36361.63
A32: 12/17/15 | B32: 3 - Land Improvements - Site - 27.5yr | C32: =SUM(D32:AE32) -> 23686.78 | D32: =Site!$D$23 -> 23686.78
A33: 12/17/15 | B33: 4 - Equipment - Site - 15yr | C33: =SUM(D33:AE33) -> 65864.56 | D33: =Site!$D$24 -> 65864.56
A34: 12/17/15 | B34: 4 - Equipment - Site - 27.5yr | C34: =SUM(D34:AE34) -> 42905.66 | D34: =Site!$D$25 -> 42905.66
A35: 12/17/15 | B35: 1 - Buillding - Clubhouse - 5yr | C35: =SUM(D35:AE35) -> 15749.94 | E35: =Clubhouse!$D$18 -> 15749.94
A36: 12/17/15 | B36: 1 - Buillding - Clubhouse - 27.5yr | C36: =SUM(D36:AE36) -> 72105.41 | E36: =Clubhouse!$D$19 -> 72105.41
A37: 1/14/16 | B37: 5 - Building - Clubhouse - 5yr | C37: =SUM(D37:AE37) -> 28.69 | E37: =Clubhouse!$D$20 -> 28.69
A38: 1/14/16 | B38: 5 - Building - Clubhouse - 27.5yr | C38: =SUM(D38:AE38) -> 131.32 | E38: =Clubhouse!$D$21 -> 131.32
A39: 12/17/15 | B39: 3 - Land Improvements - Clubhouse - 5yr | C39: =SUM(D39:AE39) -> 1485.84 | E39: =Clubhouse!$D$22 -> 1485.84
A40: 12/17/15 | B40: 3 - Land Improvements - Clubhouse - 27.5yr | C40: =SUM(D40:AE40) -> 6802.39 | E40: =Clubhouse!$D$23 -> 6802.39
A41: 12/17/15 | B41: 4 - Equipment - Clubhouse - 5yr | C41: =SUM(D41:AE41) -> 2691.42 | E41: =Clubhouse!$D$24 -> 2691.42
A42: 12/17/15 | B42: 4 - Equipment - Clubhouse - 27.5yr | C42: =SUM(D42:AE42) -> 12321.7 | E42: =Clubhouse!$D$25 -> 12321.7
A43: 12/17/15 | B43: 1 - Buillding - Apt - 5yr | C43: =SUM(D43:AE43) -> 692389.05 | F43: ='Building 1'!$D$18 -> 41085.46 | G43: ='Building 2'!$D$18 -> 41085.46 | H43: ='Building 3'!$D$18 -> 24387.48 | I43: ='Building 4'!$D$18 -> 21279.35 | J43: ='Building 5'!$D$18 -> 24387.48 | K43: ='Building 6'!$D$18 -> 24387.48 | L43: ='Building 7'!$D$18 -> 24387.48 | M43: ='Building 8'!$D$18 -> 24387.48 | N43: ='Building 9'!$D$18 -> 24387.48 | O43: ='Building 10'!$D$18 -> 24387.48 | P43: ='Building 11'!$D$18 -> 21279.35 | Q43: ='Building 12'!$D$18 -> 41085.46 | R43: ='Building 13'!$D$18 -> 55838.26 | S43: ='Building 14'!$D$18 -> 41085.46 | T43: ='Building 15'!$D$18 -> 21279.35 | U43: ='Building 16'!$D$18 -> 24387.48 | V43: ='Building 17'!$D$18 -> 24387.48 | W43: ='Building 18'!$D$18 -> 21279.35 | X43: ='Building 19'!$D$18 -> 24387.48 | Y43: ='Building 20'!$D$18 -> 21279.35 | Z43: ='Building 21'!$D$18 -> 24387.48 | AA43: ='Building 22'!$D$18 -> 24387.48 | AB43: ='Building 23'!$D$18 -> 24387.48 | AC43: ='Building 24'!$D$18 -> 24387.48 | AD43: ='Building 25'!$D$18 -> 24387.48
A44: 12/17/15 | B44: 1 - Buillding - Apt - 27.5yr | C44: =SUM(D44:AE44) -> 2644989.8 | F44: ='Building 1'!$D$19 -> 171105.59 | G44: ='Building 2'!$D$19 -> 171105.59 | H44: ='Building 3'!$D$19 -> 92335.64 | I44: ='Building 4'!$D$19 -> 69861.15 | J44: ='Building 5'!$D$19 -> 92335.64 | K44: ='Building 6'!$D$19 -> 92335.64 | L44: ='Building 7'!$D$19 -> 92335.64 | M44: ='Building 8'!$D$19 -> 92335.64 | N44: ='Building 9'!$D$19 -> 92335.64 | O44: ='Building 10'!$D$19 -> 92335.64 | P44: ='Building 11'!$D$19 -> 69861.15 | Q44: ='Building 12'!$D$19 -> 171105.59 | R44: ='Building 13'!$D$19 -> 226227.05 | S44: ='Building 14'!$D$19 -> 171105.59 | T44: ='Building 15'!$D$19 -> 69861.15 | U44: ='Building 16'!$D$19 -> 92335.64 | V44: ='Building 17'!$D$19 -> 92335.64 | W44: ='Building 18'!$D$19 -> 69861.15 | X44: ='Building 19'!$D$19 -> 92335.64 | Y44: ='Building 20'!$D$19 -> 69861.15 | Z44: ='Building 21'!$D$19 -> 92335.64 | AA44: ='Building 22'!$D$19 -> 92335.64 | AB44: ='Building 23'!$D$19 -> 92335.64 | AC44: ='Building 24'!$D$19 -> 92335.64 | AD44: ='Building 25'!$D$19 -> 92335.64
A45: 1/14/16 | B45: 5 - Building - Apt - 5yr | C45: =SUM(D45:AE45) -> 1261.12 | F45: ='Building 1'!$D$20 -> 74.83 | G45: ='Building 2'!$D$20 -> 74.83 | H45: ='Building 3'!$D$20 -> 44.42 | I45: ='Building 4'!$D$20 -> 38.76 | J45: ='Building 5'!$D$20 -> 44.42 | K45: ='Building 6'!$D$20 -> 44.42 | L45: ='Building 7'!$D$20 -> 44.42 | M45: ='Building 8'!$D$20 -> 44.42 | N45: ='Building 9'!$D$20 -> 44.42 | O45: ='Building 10'!$D$20 -> 44.42 | P45: ='Building 11'!$D$20 -> 38.76 | Q45: ='Building 12'!$D$20 -> 74.83 | R45: ='Building 13'!$D$20 -> 101.7 | S45: ='Building 14'!$D$20 -> 74.83 | T45: ='Building 15'!$D$20 -> 38.76 | U45: ='Building 16'!$D$20 -> 44.42 | V45: ='Building 17'!$D$20 -> 44.42 | W45: ='Building 18'!$D$20 -> 38.76 | X45: ='Building 19'!$D$20 -> 44.42 | Y45: ='Building 20'!$D$20 -> 38.76 | Z45: ='Building 21'!$D$20 -> 44.42 | AA45: ='Building 22'!$D$20 -> 44.42 | AB45: ='Building 23'!$D$20 -> 44.42 | AC45: ='Building 24'!$D$20 -> 44.42 | AD45: ='Building 25'!$D$20 -> 44.42
A46: 1/14/16 | B46: 5 - Building - Apt - 27.5yr | C46: =SUM(D46:AE46) -> 4817.04 | F46: ='Building 1'!$D$21 -> 311.62 | G46: ='Building 2'!$D$21 -> 311.62 | H46: ='Building 3'!$D$21 -> 168.16 | I46: ='Building 4'!$D$21 -> 127.23 | J46: ='Building 5'!$D$21 -> 168.16 | K46: ='Building 6'!$D$21 -> 168.16 | L46: ='Building 7'!$D$21 -> 168.16 | M46: ='Building 8'!$D$21 -> 168.16 | N46: ='Building 9'!$D$21 -> 168.16 | O46: ='Building 10'!$D$21 -> 168.16 | P46: ='Building 11'!$D$21 -> 127.23 | Q46: ='Building 12'!$D$21 -> 311.62 | R46: ='Building 13'!$D$21 -> 412.01 | S46: ='Building 14'!$D$21 -> 311.62 | T46: ='Building 15'!$D$21 -> 127.23 | U46: ='Building 16'!$D$21 -> 168.16 | V46: ='Building 17'!$D$21 -> 168.16 | W46: ='Building 18'!$D$21 -> 127.23 | X46: ='Building 19'!$D$21 -> 168.16 | Y46: ='Building 20'!$D$21 -> 127.23 | Z46: ='Building 21'!$D$21 -> 168.16 | AA46: ='Building 22'!$D$21 -> 168.16 | AB46: ='Building 23'!$D$21 -> 168.16 | AC46: ='Building 24'!$D$21 -> 168.16 | AD46: ='Building 25'!$D$21 -> 168.16
A47: 12/17/15 | B47: 3 - Land Improvements - Apt - 5yr | C47: =SUM(D47:AE47) -> 55282.18 | F47: ='Building 1'!$D$22 -> 3875.98 | G47: ='Building 2'!$D$22 -> 3875.98 | H47: ='Building 3'!$D$22 -> 2300.7 | J47: ='Building 5'!$D$22 -> 2300.7 | K47: ='Building 6'!$D$22 -> 2300.7 | L47: ='Building 7'!$D$22 -> 2300.7 | M47: ='Building 8'!$D$22 -> 2300.7 | N47: ='Building 9'!$D$22 -> 2300.7 | O47: ='Building 10'!$D$22 -> 2300.7 | Q47: ='Building 12'!$D$22 -> 3875.98 | R47: ='Building 13'!$D$22 -> 5267.76 | S47: ='Building 14'!$D$22 -> 3875.98 | U47: ='Building 16'!$D$22 -> 2300.7 | V47: ='Building 17'!$D$22 -> 2300.7 | X47: ='Building 19'!$D$22 -> 2300.7 | Z47: ='Building 21'!$D$22 -> 2300.7 | AA47: ='Building 22'!$D$22 -> 2300.7 | AB47: ='Building 23'!$D$22 -> 2300.7 | AC47: ='Building 24'!$D$22 -> 2300.7 | AD47: ='Building 25'!$D$22 -> 2300.7
A48: 12/17/15 | B48: 3 - Land Improvements - Apt - 27.5yr | C48: =SUM(D48:AE48) -> 216573.73 | F48: ='Building 1'!$D$23 -> 16142.02 | G48: ='Building 2'!$D$23 -> 16142.02 | H48: ='Building 3'!$D$23 -> 8710.9 | J48: ='Building 5'!$D$23 -> 8710.9 | K48: ='Building 6'!$D$23 -> 8710.9 | L48: ='Building 7'!$D$23 -> 8710.9 | M48: ='Building 8'!$D$23 -> 8710.9 | N48: ='Building 9'!$D$23 -> 8710.9 | O48: ='Building 10'!$D$23 -> 8710.9 | Q48: ='Building 12'!$D$23 -> 16142.02 | R48: ='Building 13'!$D$23 -> 21342.15 | S48: ='Building 14'!$D$23 -> 16142.02 | U48: ='Building 16'!$D$23 -> 8710.9 | V48: ='Building 17'!$D$23 -> 8710.9 | X48: ='Building 19'!$D$23 -> 8710.9 | Z48: ='Building 21'!$D$23 -> 8710.9 | AA48: ='Building 22'!$D$23 -> 8710.9 | AB48: ='Building 23'!$D$23 -> 8710.9 | AC48: ='Building 24'!$D$23 -> 8710.9 | AD48: ='Building 25'!$D$23 -> 8710.9
A49: 12/17/15 | B49: 4 - Equipment - Apt - 5yr | C49: =SUM(D49:AE49) -> 118318.61 | F49: ='Building 1'!$D$24 -> 7020.87 | G49: ='Building 2'!$D$24 -> 7020.87 | H49: ='Building 3'!$D$24 -> 4167.44 | I49: ='Building 4'!$D$24 -> 3636.33 | J49: ='Building 5'!$D$24 -> 4167.44 | K49: ='Building 6'!$D$24 -> 4167.44 | L49: ='Building 7'!$D$24 -> 4167.44 | M49: ='Building 8'!$D$24 -> 4167.44 | N49: ='Building 9'!$D$24 -> 4167.44 | O49: ='Building 10'!$D$24 -> 4167.44 | P49: ='Building 11'!$D$24 -> 3636.33 | Q49: ='Building 12'!$D$24 -> 7020.87 | R49: ='Building 13'!$D$24 -> 9541.88 | S49: ='Building 14'!$D$24 -> 7020.87 | T49: ='Building 15'!$D$24 -> 3636.33 | U49: ='Building 16'!$D$24 -> 4167.44 | V49: ='Building 17'!$D$24 -> 4167.44 | W49: ='Building 18'!$D$24 -> 3636.33 | X49: ='Building 19'!$D$24 -> 4167.44 | Y49: ='Building 20'!$D$24 -> 3636.33 | Z49: ='Building 21'!$D$24 -> 4167.44 | AA49: ='Building 22'!$D$24 -> 4167.44 | AB49: ='Building 23'!$D$24 -> 4167.44 | AC49: ='Building 24'!$D$24 -> 4167.44 | AD49: ='Building 25'!$D$24 -> 4167.44
A50: 12/17/15 | B50: 4 - Equipment - Apt - 27.5yr | C50: =SUM(D50:AE50) -> 451987.81 | F50: ='Building 1'!$D$25 -> 29239.3 | G50: ='Building 2'!$D$25 -> 29239.3 | H50: ='Building 3'!$D$25 -> 15778.73 | I50: ='Building 4'!$D$25 -> 11938.19 | J50: ='Building 5'!$D$25 -> 15778.73 | K50: ='Building 6'!$D$25 -> 15778.73 | L50: ='Building 7'!$D$25 -> 15778.73 | M50: ='Building 8'!$D$25 -> 15778.73 | N50: ='Building 9'!$D$25 -> 15778.73 | O50: ='Building 10'!$D$25 -> 15778.73 | P50: ='Building 11'!$D$25 -> 11938.19 | Q50: ='Building 12'!$D$25 -> 29239.3 | R50: ='Building 13'!$D$25 -> 38658.71 | S50: ='Building 14'!$D$25 -> 29239.3 | T50: ='Building 15'!$D$25 -> 11938.19 | U50: ='Building 16'!$D$25 -> 15778.73 | V50: ='Building 17'!$D$25 -> 15778.73 | W50: ='Building 18'!$D$25 -> 11938.19 | X50: ='Building 19'!$D$25 -> 15778.73 | Y50: ='Building 20'!$D$25 -> 11938.19 | Z50: ='Building 21'!$D$25 -> 15778.73 | AA50: ='Building 22'!$D$25 -> 15778.73 | AB50: ='Building 23'!$D$25 -> 15778.73 | AC50: ='Building 24'!$D$25 -> 15778.73 | AD50: ='Building 25'!$D$25 -> 15778.73
A51: 12/17/15 | B51: 3 - Land Improvements - Apt 5yr | C51: =SUM(D51:AE51) -> 10037.4 | I51: ='Building 4'!$D$22 -> 2007.48 | P51: ='Building 11'!$D$22 -> 2007.48 | T51: ='Building 15'!$D$22 -> 2007.48 | W51: ='Building 18'!$D$22 -> 2007.48 | Y51: ='Building 20'!$D$22 -> 2007.48
A52: 12/17/15 | B52: 3 - Land Improvements - Apt 27.5yr | C52: =SUM(D52:AE52) -> 32953.35 | I52: ='Building 4'!$D$23 -> 6590.67 | P52: ='Building 11'!$D$23 -> 6590.67 | T52: ='Building 15'!$D$23 -> 6590.67 | W52: ='Building 18'!$D$23 -> 6590.67 | Y52: ='Building 20'!$D$23 -> 6590.67
A53: 12/17/15 | B53: 1 - Buillding - Storage - 5yr | C53: =SUM(D53:AE53) -> 368.29 | AE53: =Storage!$D$18 -> 368.29
A54: 12/17/15 | B54: 1 - Buillding - Storage - 27.5yr | C54: =SUM(D54:AE54) -> 12560.56 | AE54: =Storage!$D$19 -> 12560.56
A55: 1/14/16 | B55: 5 - Building - Storage - 5yr | C55: =SUM(D55:AE55) -> 0.67 | AE55: =Storage!$D$20 -> 0.67
A56: 1/14/16 | B56: 5 - Building - Storage - 27.5yr | C56: =SUM(D56:AE56) -> 22.88 | AE56: =Storage!$D$21 -> 22.88
A57: 12/17/15 | B57: 3 - Land Improvements - Storage - 5yr | C57: =SUM(D57:AE57) -> 34.74 | AE57: =Storage!$D$22 -> 34.74
A58: 12/17/15 | B58: 3 - Land Improvements - Storage - 27.5yr | C58: =SUM(D58:AE58) -> 1184.96 | AE58: =Storage!$D$23 -> 1184.96
A59: 12/17/15 | B59: 4 - Equipment - Storage - 5yr | C59: =SUM(D59:AE59) -> 62.94 | AE59: =Storage!$D$24 -> 62.94
A60: 12/17/15 | B60: 4 - Equipment - Storage - 27.5yr | C60: =SUM(D60:AE60) -> 2146.4 | AE60: =Storage!$D$25 -> 2146.4
B61: Total MACRS Reclassification | C61: =SUM(C27:C60) -> 5162799.1 | D61: =SUM(D27:D60) -> 806490.9 | E61: =SUM(E27:E60) -> 111316.71 | F61: =SUM(F27:F60) -> 268855.67 | G61: =SUM(G27:G60) -> 268855.67 | H61: =SUM(H27:H60) -> 147893.47 | I61: =SUM(I27:I60) -> 115479.16 | J61: =SUM(J27:J60) -> 147893.47 | ... AE61: =SUM(AE27:AE60) -> 16381.44
B62: Difference (should be zero) | C62: =C24-C61 -> -0.1 | D62: =D24-D61 -> 0 | E62: =E24-E61 -> 0 | F62: =F24-F61 -> 0 | G62: =G24-G61 -> 0 | H62: =H24-H61 -> 0 | I62: =I24-I61 -> -0.02 | J62: =J24-J61 -> 0 | ... AE62: =AE24-AE61 -> 0
B64: End Depreciation Reconciliation
B65: Before Cost Segregation (As Previously Filed) | C65: =SUM(D65:AE65) -> 2263046.9 | D65: =Site!$I$14 -> 353546.9 | E65: =Clubhouse!$I$14 -> 48793.35 | F65: ='Building 1'!$I$14 -> 117847.47 | G65: ='Building 2'!$I$14 -> 117847.47 | H65: ='Building 3'!$I$14 -> 64826.13 | I65: ='Building 4'!$I$14 -> 50617.97 | J65: ='Building 5'!$I$14 -> 64826.13 | K65: ='Building 6'!$I$14 -> 64826.13 | L65: ='Building 7'!$I$14 -> 64826.13 | M65: ='Building 8'!$I$14 -> 64826.13 | N65: ='Building 9'!$I$14 -> 64826.13 | O65: ='Building 10'!$I$14 -> 64826.13 | P65: ='Building 11'!$I$14 -> 50617.97 | Q65: ='Building 12'!$I$14 -> 117847.47 | R65: ='Building 13'!$I$14 -> 156654.5 | S65: ='Building 14'!$I$14 -> 117847.47 | T65: ='Building 15'!$I$14 -> 50617.97 | U65: ='Building 16'!$I$14 -> 64826.13 | V65: ='Building 17'!$I$14 -> 64826.13 | W65: ='Building 18'!$I$14 -> 50617.97 | X65: ='Building 19'!$I$14 -> 64826.13 | Y65: ='Building 20'!$I$14 -> 50617.97 | Z65: ='Building 21'!$I$14 -> 64826.13 | AA65: ='Building 22'!$I$14 -> 64826.13 | AB65: ='Building 23'!$I$14 -> 64826.13 | AC65: ='Building 24'!$I$14 -> 64826.13 | AD65: ='Building 25'!$I$14 -> 64826.13 | AE65: =Storage!$I$14 -> 7180.48
B66: 1 - Buillding - Site - 15yr | C66: =SUM(D66:AE66) -> 260256.23 | D66: =Site!$I$18 -> 260256.23
B67: 1 - Buillding - Site - 27.5yr | C67: =SUM(D67:AE67) -> 82551.95 | D67: =Site!$I$19 -> 82551.95
B68: 5 - Building - Site - 15yr | C68: =SUM(D68:AE68) -> 432.55 | D68: =Site!$I$20 -> 432.55
B69: 5 - Building - Site - 27.5yr | C69: =SUM(D69:AE69) -> 148.98 | D69: =Site!$I$21 -> 148.98
B70: 3 - Land Improvements - Site - 15yr | C70: =SUM(D70:AE70) -> 24031.1 | D70: =Site!$I$22 -> 24031.1
B71: 3 - Land Improvements - Site - 27.5yr | C71: =SUM(D71:AE71) -> 7787.95 | D71: =Site!$I$23 -> 7787.95
B72: 4 - Equipment - Site - 15yr | C72: =SUM(D72:AE72) -> 44473.77 | D72: =Site!$I$24 -> 44473.77
B73: 4 - Equipment - Site - 27.5yr | C73: =SUM(D73:AE73) -> 14106.9 | D73: =Site!$I$25 -> 14106.9
B74: 1 - Buillding - Clubhouse - 5yr | C74: =SUM(D74:AE74) -> 15749.94 | E74: =Clubhouse!$I$18 -> 15749.94
B75: 1 - Buillding - Clubhouse - 27.5yr | C75: =SUM(D75:AE75) -> 23707.34 | E75: =Clubhouse!$I$19 -> 23707.34
B76: 5 - Building - Clubhouse - 5yr | C76: =SUM(D76:AE76) -> 28.69 | E76: =Clubhouse!$I$20 -> 28.69
B77: 5 - Building - Clubhouse - 27.5yr | C77: =SUM(D77:AE77) -> 42.82 | E77: =Clubhouse!$I$21 -> 42.82
B78: 3 - Land Improvements - Clubhouse - 5yr | C78: =SUM(D78:AE78) -> 1485.84 | E78: =Clubhouse!$I$22 -> 1485.84
B79: 3 - Land Improvements - Clubhouse - 27.5yr | C79: =SUM(D79:AE79) -> 2236.55 | E79: =Clubhouse!$I$23 -> 2236.55
B80: 4 - Equipment - Clubhouse - 5yr | C80: =SUM(D80:AE80) -> 2691.42 | E80: =Clubhouse!$I$24 -> 2691.42
B81: 4 - Equipment - Clubhouse - 27.5yr | C81: =SUM(D81:AE81) -> 4051.21 | E81: =Clubhouse!$I$25 -> 4051.21
B82: 1 - Buillding - Apt - 5yr | C82: =SUM(D82:AE82) -> 692389.05 | F82: ='Building 1'!$I$18 -> 41085.46 | G82: ='Building 2'!$I$18 -> 41085.46 | H82: ='Building 3'!$I$18 -> 24387.48 | I82: ='Building 4'!$I$18 -> 21279.35 | J82: ='Building 5'!$I$18 -> 24387.48 | K82: ='Building 6'!$I$18 -> 24387.48 | L82: ='Building 7'!$I$18 -> 24387.48 | M82: ='Building 8'!$I$18 -> 24387.48 | N82: ='Building 9'!$I$18 -> 24387.48 | O82: ='Building 10'!$I$18 -> 24387.48 | P82: ='Building 11'!$I$18 -> 21279.35 | Q82: ='Building 12'!$I$18 -> 41085.46 | R82: ='Building 13'!$I$18 -> 55838.26 | S82: ='Building 14'!$I$18 -> 41085.46 | T82: ='Building 15'!$I$18 -> 21279.35 | U82: ='Building 16'!$I$18 -> 24387.48 | V82: ='Building 17'!$I$18 -> 24387.48 | W82: ='Building 18'!$I$18 -> 21279.35 | X82: ='Building 19'!$I$18 -> 24387.48 | Y82: ='Building 20'!$I$18 -> 21279.35 | Z82: ='Building 21'!$I$18 -> 24387.48 | AA82: ='Building 22'!$I$18 -> 24387.48 | AB82: ='Building 23'!$I$18 -> 24387.48 | AC82: ='Building 24'!$I$18 -> 24387.48 | AD82: ='Building 25'!$I$18 -> 24387.48
B83: 1 - Buillding - Apt - 27.5yr | C83: =SUM(D83:AE83) -> 869640.75 | F83: ='Building 1'!$I$19 -> 56257.43 | G83: ='Building 2'!$I$19 -> 56257.43 | H83: ='Building 3'!$I$19 -> 30358.84 | I83: ='Building 4'!$I$19 -> 22969.54 | J83: ='Building 5'!$I$19 -> 30358.84 | K83: ='Building 6'!$I$19 -> 30358.84 | L83: ='Building 7'!$I$19 -> 30358.84 | M83: ='Building 8'!$I$19 -> 30358.84 | N83: ='Building 9'!$I$19 -> 30358.84 | O83: ='Building 10'!$I$19 -> 30358.84 | P83: ='Building 11'!$I$19 -> 22969.54 | Q83: ='Building 12'!$I$19 -> 56257.43 | R83: ='Building 13'!$I$19 -> 74380.73 | S83: ='Building 14'!$I$19 -> 56257.43 | T83: ='Building 15'!$I$19 -> 22969.54 | U83: ='Building 16'!$I$19 -> 30358.84 | V83: ='Building 17'!$I$19 -> 30358.84 | W83: ='Building 18'!$I$19 -> 22969.54 | X83: ='Building 19'!$I$19 -> 30358.84 | Y83: ='Building 20'!$I$19 -> 22969.54 | Z83: ='Building 21'!$I$19 -> 30358.84 | AA83: ='Building 22'!$I$19 -> 30358.84 | AB83: ='Building 23'!$I$19 -> 30358.84 | AC83: ='Building 24'!$I$19 -> 30358.84 | AD83: ='Building 25'!$I$19 -> 30358.84
B84: 5 - Building - Apt - 5yr | C84: =SUM(D84:AE84) -> 1261.12 | F84: ='Building 1'!$I$20 -> 74.83 | G84: ='Building 2'!$I$20 -> 74.83 | H84: ='Building 3'!$I$20 -> 44.42 | I84: ='Building 4'!$I$20 -> 38.76 | J84: ='Building 5'!$I$20 -> 44.42 | K84: ='Building 6'!$I$20 -> 44.42 | L84: ='Building 7'!$I$20 -> 44.42 | M84: ='Building 8'!$I$20 -> 44.42 | N84: ='Building 9'!$I$20 -> 44.42 | O84: ='Building 10'!$I$20 -> 44.42 | P84: ='Building 11'!$I$20 -> 38.76 | Q84: ='Building 12'!$I$20 -> 74.83 | R84: ='Building 13'!$I$20 -> 101.7 | S84: ='Building 14'!$I$20 -> 74.83 | T84: ='Building 15'!$I$20 -> 38.76 | U84: ='Building 16'!$I$20 -> 44.42 | V84: ='Building 17'!$I$20 -> 44.42 | W84: ='Building 18'!$I$20 -> 38.76 | X84: ='Building 19'!$I$20 -> 44.42 | Y84: ='Building 20'!$I$20 -> 38.76 | Z84: ='Building 21'!$I$20 -> 44.42 | AA84: ='Building 22'!$I$20 -> 44.42 | AB84: ='Building 23'!$I$20 -> 44.42 | AC84: ='Building 24'!$I$20 -> 44.42 | AD84: ='Building 25'!$I$20 -> 44.42
B85: 5 - Building - Apt - 27.5yr | C85: =SUM(D85:AE85) -> 1568.65 | F85: ='Building 1'!$I$21 -> 101.5 | G85: ='Building 2'!$I$21 -> 101.5 | H85: ='Building 3'!$I$21 -> 54.74 | I85: ='Building 4'!$I$21 -> 41.47 | J85: ='Building 5'!$I$21 -> 54.74 | K85: ='Building 6'!$I$21 -> 54.74 | L85: ='Building 7'!$I$21 -> 54.74 | M85: ='Building 8'!$I$21 -> 54.74 | N85: ='Building 9'!$I$21 -> 54.74 | O85: ='Building 10'!$I$21 -> 54.74 | P85: ='Building 11'!$I$21 -> 41.47 | Q85: ='Building 12'!$I$21 -> 101.5 | R85: ='Building 13'!$I$21 -> 134.2 | S85: ='Building 14'!$I$21 -> 101.5 | T85: ='Building 15'!$I$21 -> 41.47 | U85: ='Building 16'!$I$21 -> 54.74 | V85: ='Building 17'!$I$21 -> 54.74 | W85: ='Building 18'!$I$21 -> 41.47 | X85: ='Building 19'!$I$21 -> 54.74 | Y85: ='Building 20'!$I$21 -> 41.47 | Z85: ='Building 21'!$I$21 -> 54.74 | AA85: ='Building 22'!$I$21 -> 54.74 | AB85: ='Building 23'!$I$21 -> 54.74 | AC85: ='Building 24'!$I$21 -> 54.74 | AD85: ='Building 25'!$I$21 -> 54.74
B86: 3 - Land Improvements - Apt - 5yr | C86: =SUM(D86:AE86) -> 55282.18 | F86: ='Building 1'!$I$22 -> 3875.98 | G86: ='Building 2'!$I$22 -> 3875.98 | H86: ='Building 3'!$I$22 -> 2300.7 | J86: ='Building 5'!$I$22 -> 2300.7 | K86: ='Building 6'!$I$22 -> 2300.7 | L86: ='Building 7'!$I$22 -> 2300.7 | M86: ='Building 8'!$I$22 -> 2300.7 | N86: ='Building 9'!$I$22 -> 2300.7 | O86: ='Building 10'!$I$22 -> 2300.7 | Q86: ='Building 12'!$I$22 -> 3875.98 | R86: ='Building 13'!$I$22 -> 5267.76 | S86: ='Building 14'!$I$22 -> 3875.98 | U86: ='Building 16'!$I$22 -> 2300.7 | V86: ='Building 17'!$I$22 -> 2300.7 | X86: ='Building 19'!$I$22 -> 2300.7 | Z86: ='Building 21'!$I$22 -> 2300.7 | AA86: ='Building 22'!$I$22 -> 2300.7 | AB86: ='Building 23'!$I$22 -> 2300.7 | AC86: ='Building 24'!$I$22 -> 2300.7 | AD86: ='Building 25'!$I$22 -> 2300.7
B87: 3 - Land Improvements - Apt - 27.5yr | C87: =SUM(D87:AE87) -> 71206.78 | F87: ='Building 1'!$I$23 -> 5307.28 | G87: ='Building 2'!$I$23 -> 5307.28 | H87: ='Building 3'!$I$23 -> 2864.04 | J87: ='Building 5'!$I$23 -> 2864.04 | K87: ='Building 6'!$I$23 -> 2864.04 | L87: ='Building 7'!$I$23 -> 2864.04 | M87: ='Building 8'!$I$23 -> 2864.04 | N87: ='Building 9'!$I$23 -> 2864.04 | O87: ='Building 10'!$I$23 -> 2864.04 | Q87: ='Building 12'!$I$23 -> 5307.28 | R87: ='Building 13'!$I$23 -> 7017.06 | S87: ='Building 14'!$I$23 -> 5307.28 | U87: ='Building 16'!$I$23 -> 2864.04 | V87: ='Building 17'!$I$23 -> 2864.04 | X87: ='Building 19'!$I$23 -> 2864.04 | Z87: ='Building 21'!$I$23 -> 2864.04 | AA87: ='Building 22'!$I$23 -> 2864.04 | AB87: ='Building 23'!$I$23 -> 2864.04 | AC87: ='Building 24'!$I$23 -> 2864.04 | AD87: ='Building 25'!$I$23 -> 2864.04
B88: 4 - Equipment - Apt - 5yr | C88: =SUM(D88:AE88) -> 118318.61 | F88: ='Building 1'!$I$24 -> 7020.87 | G88: ='Building 2'!$I$24 -> 7020.87 | H88: ='Building 3'!$I$24 -> 4167.44 | I88: ='Building 4'!$I$24 -> 3636.33 | J88: ='Building 5'!$I$24 -> 4167.44 | K88: ='Building 6'!$I$24 -> 4167.44 | L88: ='Building 7'!$I$24 -> 4167.44 | M88: ='Building 8'!$I$24 -> 4167.44 | N88: ='Building 9'!$I$24 -> 4167.44 | O88: ='Building 10'!$I$24 -> 4167.44 | P88: ='Building 11'!$I$24 -> 3636.33 | Q88: ='Building 12'!$I$24 -> 7020.87 | R88: ='Building 13'!$I$24 -> 9541.88 | S88: ='Building 14'!$I$24 -> 7020.87 | T88: ='Building 15'!$I$24 -> 3636.33 | U88: ='Building 16'!$I$24 -> 4167.44 | V88: ='Building 17'!$I$24 -> 4167.44 | W88: ='Building 18'!$I$24 -> 3636.33 | X88: ='Building 19'!$I$24 -> 4167.44 | Y88: ='Building 20'!$I$24 -> 3636.33 | Z88: ='Building 21'!$I$24 -> 4167.44 | AA88: ='Building 22'!$I$24 -> 4167.44 | AB88: ='Building 23'!$I$24 -> 4167.44 | AC88: ='Building 24'!$I$24 -> 4167.44 | AD88: ='Building 25'!$I$24 -> 4167.44
B89: 4 - Equipment - Apt - 27.5yr | C89: =SUM(D89:AE89) -> 148608.15 | F89: ='Building 1'!$I$25 -> 9613.55 | G89: ='Building 2'!$I$25 -> 9613.55 | H89: ='Building 3'!$I$25 -> 5187.84 | I89: ='Building 4'!$I$25 -> 3925.17 | J89: ='Building 5'!$I$25 -> 5187.84 | K89: ='Building 6'!$I$25 -> 5187.84 | L89: ='Building 7'!$I$25 -> 5187.84 | M89: ='Building 8'!$I$25 -> 5187.84 | N89: ='Building 9'!$I$25 -> 5187.84 | O89: ='Building 10'!$I$25 -> 5187.84 | P89: ='Building 11'!$I$25 -> 3925.17 | Q89: ='Building 12'!$I$25 -> 9613.55 | R89: ='Building 13'!$I$25 -> 12710.5 | S89: ='Building 14'!$I$25 -> 9613.55 | T89: ='Building 15'!$I$25 -> 3925.17 | U89: ='Building 16'!$I$25 -> 5187.84 | V89: ='Building 17'!$I$25 -> 5187.84 | W89: ='Building 18'!$I$25 -> 3925.17 | X89: ='Building 19'!$I$25 -> 5187.84 | Y89: ='Building 20'!$I$25 -> 3925.17 | Z89: ='Building 21'!$I$25 -> 5187.84 | AA89: ='Building 22'!$I$25 -> 5187.84 | AB89: ='Building 23'!$I$25 -> 5187.84 | AC89: ='Building 24'!$I$25 -> 5187.84 | AD89: ='Building 25'!$I$25 -> 5187.84
B90: 3 - Land Improvements - Apt 5yr | C90: =SUM(D90:AE90) -> 10037.4 | I90: ='Building 4'!$I$22 -> 2007.48 | P90: ='Building 11'!$I$22 -> 2007.48 | T90: ='Building 15'!$I$22 -> 2007.48 | W90: ='Building 18'!$I$22 -> 2007.48 | Y90: ='Building 20'!$I$22 -> 2007.48
B91: 3 - Land Improvements - Apt 27.5yr | C91: =SUM(D91:AE91) -> 10834.65 | I91: ='Building 4'!$I$23 -> 2166.93 | P91: ='Building 11'!$I$23 -> 2166.93 | T91: ='Building 15'!$I$23 -> 2166.93 | W91: ='Building 18'!$I$23 -> 2166.93 | Y91: ='Building 20'!$I$23 -> 2166.93
B92: 1 - Buillding - Storage - 5yr | C92: =SUM(D92:AE92) -> 368.29 | AE92: =Storage!$I$18 -> 368.29
B93: 1 - Buillding - Storage - 27.5yr | C93: =SUM(D93:AE93) -> 4129.78 | AE93: =Storage!$I$19 -> 4129.78
B94: 5 - Building - Storage - 5yr | C94: =SUM(D94:AE94) -> 0.67 | AE94: =Storage!$I$20 -> 0.67
B95: 5 - Building - Storage - 27.5yr | C95: =SUM(D95:AE95) -> 7.44 | AE95: =Storage!$I$21 -> 7.44
B96: 3 - Land Improvements - Storage - 5yr | C96: =SUM(D96:AE96) -> 34.74 | AE96: =Storage!$I$22 -> 34.74
B97: 3 - Land Improvements - Storage - 27.5yr | C97: =SUM(D97:AE97) -> 389.61 | AE97: =Storage!$I$23 -> 389.61
B98: 4 - Equipment - Storage - 5yr | C98: =SUM(D98:AE98) -> 62.94 | AE98: =Storage!$I$24 -> 62.94
B99: 4 - Equipment - Storage - 27.5yr | C99: =SUM(D99:AE99) -> 705.7 | AE99: =Storage!$I$25 -> 705.7
B100: After Cost Segregation (Corrected) | C100: =SUM(C66:C99) -> 2468629.8 | D100: =SUM(D66:D99) -> 433789.43 | E100: =SUM(E66:E99) -> 49993.81 | F100: =SUM(F66:F99) -> 123336.9 | G100: =SUM(G66:G99) -> 123336.9 | H100: =SUM(H66:H99) -> 69365.5 | I100: =SUM(I66:I99) -> 56065.03 | J100: =SUM(J66:J99) -> 69365.5 | ... AE100: =SUM(AE66:AE99) -> 5699.17
B101: Section 481(a) Adjustment | C101: =C65-C100 -> -205582.84 | D101: =D65-D100 -> -80242.53 | E101: =E65-E100 -> -1200.46 | F101: =F65-F100 -> -5489.43 | G101: =G65-G100 -> -5489.43 | H101: =H65-H100 -> -4539.37 | I101: =I65-I100 -> -5447.06 | J101: =J65-J100 -> -4539.37 | ... AE101: =AE65-AE100 -> 1481.31
B102: Check vs. unit-tab 481(a) cells (should be zero) | C102: =C101-(-205582.84) -> 0 | D102: =D101-Site!$D$31 -> 0 | E102: =E101-Clubhouse!$D$31 -> 0 | F102: =F101-'Building 1'!$D$31 -> 0 | G102: =G101-'Building 2'!$D$31 -> 0 | H102: =H101-'Building 3'!$D$31 -> 0 | I102: =I101-'Building 4'!$D$31 -> 0 | J102: =J101-'Building 5'!$D$31 -> 0 | K102: =K101-'Building 6'!$D$31 -> 0 | L102: =L101-'Building 7'!$D$31 -> 0 | M102: =M101-'Building 8'!$D$31 -> 0 | N102: =N101-'Building 9'!$D$31 -> 0 | O102: =O101-'Building 10'!$D$31 -> 0 | P102: =P101-'Building 11'!$D$31 -> 0 | Q102: =Q101-'Building 12'!$D$31 -> 0 | R102: =R101-'Building 13'!$D$31 -> 0 | S102: =S101-'Building 14'!$D$31 -> 0 | T102: =T101-'Building 15'!$D$31 -> 0 | U102: =U101-'Building 16'!$D$31 -> 0 | V102: =V101-'Building 17'!$D$31 -> 0 | W102: =W101-'Building 18'!$D$31 -> 0 | X102: =X101-'Building 19'!$D$31 -> 0 | Y102: =Y101-'Building 20'!$D$31 -> 0 | Z102: =Z101-'Building 21'!$D$31 -> 0 | AA102: =AA101-'Building 22'!$D$31 -> 0 | AB102: =AB101-'Building 23'!$D$31 -> 0 | AC102: =AC101-'Building 24'!$D$31 -> 0 | AD102: =AD101-'Building 25'!$D$31 -> 0 | AE102: =AE101-Storage!$D$31 -> 0
B104: Notes
B105: 1. Total footed §481(a) adjustment across all units: -205,582.84 (Regular Tax; AMT equals Regular Tax on every unit in this report).
...

Sheet Site
A1: Grace Townhomes Housing, LLC
A2: Grace Townhomes — 1212 Grace Cir, Ennis, TX 75119
A3: EIN: 47-5360069 · FYE: December 31, 2024 · Year of Change: 1/1/2024
A4: Site — Attachment to Form 3115 (DCN #7, Rev. Proc. 2024-23 §6.01)
A5: Source: CSSI Report #107752-11, "#107752-11_Grace Townhomes - 3115 - Combined R2.pdf"
A7: CALCULATION OF §481(a) ADJUSTMENT — REGULAR TAX
A8: As Previously Filed
A9: Asset | B9: Property Description | C9: Date In Service | D9: Cost | E9: Sec 179 Exp | F9: Bonus Amt | G9: Tax Prior Depreciation | H9: Tax Current Depreciation | I9: End Depreciation | J9: Net Book Value | K9: Method | L9: Period
A10: 1 | B10: 1 - Buillding - Site | C10: 12/17/15 | D10: 636512.99 | E10: 0 | F10: 0 | G10: 186129.48 | H10: 23145.82 | I10: =G10+H10 -> 209275.3 | J10: =D10-I10 -> 427237.69 | K10: S/L | L10: 27.5
A11: 2 | B11: 5 - Building - Site | C11: 1/14/16 | D11: 1159.28 | E11: 0 | F11: 0 | G11: 335.69 | H11: 42.24 | I11: =G11+H11 -> 377.93 | J11: =D11-I11 -> 781.35 | K11: S/L | L11: 27.5
A12: 3 | B12: 3 - Land Improvements - Site | C12: 12/17/15 | D12: 60048.41 | E12: 0 | F12: 0 | G12: 35168.3 | H12: 3580.9 | I12: =G12+H12 -> 38749.2 | J12: =D12-I12 -> 21299.21 | K12: 150DB | L12: 15.0
A13: 4 | B13: 4 - Equipment - Site | C13: 12/17/15 | D13: 108770.22 | E13: 0 | F13: 0 | G13: 105144.47 | H13: 0 | I13: =G13+H13 -> 105144.47 | J13: =D13-I13 -> 3625.75 | K13: 200DB | L13: 5.0
B14: Grand Total | D14: =SUM(D10:D13) -> 806490.9 | E14: =SUM(E10:E13) -> 0 | F14: =SUM(F10:F13) -> 0 | G14: =SUM(G10:G13) -> 326777.94 | H14: =SUM(H10:H13) -> 26768.96 | I14: =SUM(I10:I13) -> 353546.9 | J14: =SUM(J10:J13) -> 452944
A16: After Cost Segregation Correction
A17: Asset | B17: Property Description | C17: Date In Service | D17: Cost | E17: Sec 179 Exp | F17: Bonus Amt | G17: Tax Prior Depreciation | H17: Tax Current Depreciation | I17: End Depreciation | J17: Net Book Value | K17: Method | L17: Period
A18: 1 | B18: 1 - Buillding - Site - 15yr | C18: 12/17/15 | D18: 385433.18 | E18: 0 | F18: 0 | G18: 237496.79 | H18: 22759.44 | I18: =G18+H18 -> 260256.23 | J18: =D18-I18 -> 125176.95 | K18: 150DB | L18: 15.0
A19: 2 | B19: 1 - Buillding - Site - 27.5yr | C19: 12/17/15 | D19: 251079.81 | E19: 0 | F19: 0 | G19: 73421.78 | H19: 9130.17 | I19: =G19+H19 -> 82551.95 | J19: =D19-I19 -> 168527.86 | K19: S/L | L19: 27.5
A20: 3 | B20: 5 - Building - Site - 15yr | C20: 1/14/16 | D20: 701.99 | E20: 0 | F20: 0 | G20: 391.1 | H20: 41.45 | I20: =G20+H20 -> 432.55 | J20: =D20-I20 -> 269.44 | K20: 150DB | L20: 15.0
A21: 4 | B21: 5 - Building - Site - 27.5yr | C21: 1/14/16 | D21: 457.29 | E21: 0 | F21: 0 | G21: 132.35 | H21: 16.63 | I21: =G21+H21 -> 148.98 | J21: =D21-I21 -> 308.31 | K21: S/L | L21: 27.5
A22: 5 | B22: 3 - Land Improvements - Site - 15yr | C22: 12/17/15 | D22: 36361.63 | E22: 0 | F22: 0 | G22: 21789.19 | H22: 2241.91 | I22: =G22+H22 -> 24031.1 | J22: =D22-I22 -> 12330.53 | K22: 150DB | L22: 15.0
A23: 6 | B23: 3 - Land Improvements - Site - 27.5yr | C23: 12/17/15 | D23: 23686.78 | E23: 0 | F23: 0 | G23: 6926.61 | H23: 861.34 | I23: =G23+H23 -> 7787.95 | J23: =D23-I23 -> 15898.83 | K23: S/L | L23: 27.5
A24: 7 | B24: 4 - Equipment - Site - 15yr | C24: 12/17/15 | D24: 65864.56 | E24: 0 | F24: 0 | G24: 40584.53 | H24: 3889.24 | I24: =G24+H24 -> 44473.77 | J24: =D24-I24 -> 21390.79 | K24: 150DB | L24: 15.0
A25: 8 | B25: 4 - Equipment - Site - 27.5yr | C25: 12/17/15 | D25: 42905.66 | E25: 0 | F25: 0 | G25: 12546.69 | H25: 1560.21 | I25: =G25+H25 -> 14106.9 | J25: =D25-I25 -> 28798.76 | K25: S/L | L25: 27.5
B26: Grand Total | D26: =SUM(D18:D25) -> 806490.9 | E26: =SUM(E18:E25) -> 0 | F26: =SUM(F18:F25) -> 0 | G26: =SUM(G18:G25) -> 393289.04 | H26: =SUM(H18:H25) -> 40500.39 | I26: =SUM(I18:I25) -> 433789.43 | J26: =SUM(J18:J25) -> 372701.47
B28: Section 481(a) Adjustment — Regular Tax
B29: Depreciation reported previously | D29: =I14 -> 353546.9
B30: Cost Segregation Corrected Depreciation | D30: =I26 -> 433789.43
B31: Section 481(a) Adjustment — Regular Tax | D31: =D29-D30 -> -80242.53
A33: CALCULATION OF §481(a) ADJUSTMENT — AMT
A34: As Previously Filed — AMT
A35: Asset | B35: Property Description | C35: Date In Service | D35: Cost | E35: Sec 179 Exp | F35: Bonus Amt | G35: AMT Prior Depreciation | H35: AMT Current Depreciation | I35: End Depreciation | J35: Net Book Value | K35: Method | L35: Period
A36: 1 | B36: 1 - Buillding - Site | C36: 12/17/15 | D36: 636512.99 | E36: 0 | F36: 0 | G36: 186129.48 | H36: 23145.82 | I36: =G36+H36 -> 209275.3 | J36: =D36-I36 -> 427237.69 | K36: S/L | L36: 27.5
A37: 2 | B37: 5 - Building - Site | C37: 1/14/16 | D37: 1159.28 | E37: 0 | F37: 0 | G37: 335.69 | H37: 42.24 | I37: =G37+H37 -> 377.93 | J37: =D37-I37 -> 781.35 | K37: S/L | L37: 27.5
A38: 3 | B38: 3 - Land Improvements - Site | C38: 12/17/15 | D38: 60048.41 | E38: 0 | F38: 0 | G38: 35168.3 | H38: 3580.9 | I38: =G38+H38 -> 38749.2 | J38: =D38-I38 -> 21299.21 | K38: 150DB | L38: 15.0
A39: 4 | B39: 4 - Equipment - Site | C39: 12/17/15 | D39: 108770.22 | E39: 0 | F39: 0 | G39: 105144.47 | H39: 0 | I39: =G39+H39 -> 105144.47 | J39: =D39-I39 -> 3625.75 | K39: 200DB | L39: 5.0
B40: Grand Total | D40: =SUM(D36:D39) -> 806490.9 | E40: =SUM(E36:E39) -> 0 | F40: =SUM(F36:F39) -> 0 | G40: =SUM(G36:G39) -> 326777.94 | H40: =SUM(H36:H39) -> 26768.96 | I40: =SUM(I36:I39) -> 353546.9 | J40: =SUM(J36:J39) -> 452944
A42: After Cost Segregation Correction — AMT
A43: Asset | B43: Property Description | C43: Date In Service | D43: Cost | E43: Sec 179 Exp | F43: Bonus Amt | G43: AMT Prior Depreciation | H43: AMT Current Depreciation | I43: End Depreciation | J43: Net Book Value | K43: Method | L43: Period
A44: 1 | B44: 1 - Buillding - Site - 15yr | C44: 12/17/15 | D44: 385433.18 | E44: 0 | F44: 0 | G44: 237496.79 | H44: 22759.44 | I44: =G44+H44 -> 260256.23 | J44: =D44-I44 -> 125176.95 | K44: 150DB | L44: 15.0
A45: 2 | B45: 1 - Buillding - Site - 27.5yr | C45: 12/17/15 | D45: 251079.81 | E45: 0 | F45: 0 | G45: 73421.78 | H45: 9130.17 | I45: =G45+H45 -> 82551.95 | J45: =D45-I45 -> 168527.86 | K45: S/L | L45: 27.5
A46: 3 | B46: 5 - Building - Site - 15yr | C46: 1/14/16 | D46: 701.99 | E46: 0 | F46: 0 | G46: 391.1 | H46: 41.45 | I46: =G46+H46 -> 432.55 | J46: =D46-I46 -> 269.44 | K46: 150DB | L46: 15.0
A47: 4 | B47: 5 - Building - Site - 27.5yr | C47: 1/14/16 | D47: 457.29 | E47: 0 | F47: 0 | G47: 132.35 | H47: 16.63 | I47: =G47+H47 -> 148.98 | J47: =D47-I47 -> 308.31 | K47: S/L | L47: 27.5
A48: 5 | B48: 3 - Land Improvements - Site - 15yr | C48: 12/17/15 | D48: 36361.63 | E48: 0 | F48: 0 | G48: 21789.19 | H48: 2241.91 | I48: =G48+H48 -> 24031.1 | J48: =D48-I48 -> 12330.53 | K48: 150DB | L48: 15.0
A49: 6 | B49: 3 - Land Improvements - Site - 27.5yr | C49: 12/17/15 | D49: 23686.78 | E49: 0 | F49: 0 | G49: 6926.61 | H49: 861.34 | I49: =G49+H49 -> 7787.95 | J49: =D49-I49 -> 15898.83 | K49: S/L | L49: 27.5
A50: 7 | B50: 4 - Equipment - Site - 15yr | C50: 12/17/15 | D50: 65864.56 | E50: 0 | F50: 0 | G50: 40584.53 | H50: 3889.24 | I50: =G50+H50 -> 44473.77 | J50: =D50-I50 -> 21390.79 | K50: 150DB | L50: 15.0
A51: 8 | B51: 4 - Equipment - Site - 27.5yr | C51: 12/17/15 | D51: 42905.66 | E51: 0 | F51: 0 | G51: 12546.69 | H51: 1560.21 | I51: =G51+H51 -> 14106.9 | J51: =D51-I51 -> 28798.76 | K51: S/L | L51: 27.5
B52: Grand Total | D52: =SUM(D44:D51) -> 806490.9 | E52: =SUM(E44:E51) -> 0 | F52: =SUM(F44:F51) -> 0 | G52: =SUM(G44:G51) -> 393289.04 | H52: =SUM(H44:H51) -> 40500.39 | I52: =SUM(I44:I51) -> 433789.43 | J52: =SUM(J44:J51) -> 372701.47
B54: Section 481(a) Adjustment — AMT
B55: Depreciation reported previously | D55: =I40 -> 353546.9
B56: Cost Segregation Corrected Depreciation | D56: =I52 -> 433789.43
B57: Section 481(a) Adjustment — AMT | D57: =D55-D56 -> -80242.53
A59: COST SEGREGATION STUDY — COST SUMMARY
B60: Total Site Cost | D60: =D84 -> 806490.9
B61: Site Improvements: 15 Year | D61: =F84 -> 488361.36
B62: % of Cost | D62: =F85 -> 0.60553859
B63: Site Utilities: 27.5 Year | D63: =H84 -> 318129.54
B64: % of Cost | D64: =H85 -> 0.39446141
A66: COST SEGREGATION STUDY — COST DETAIL
B67: Property Category | D67: Cost | F67: 15 Year | H67: 27.5 Year
B68: Site Work / Improvements
B69: Site Drainage | D69: =SUM(F69:H69) -> 6585 | F69: 6585
B70: Parking Lot | D70: =SUM(F70:H70) -> 197049.29 | F70: 197049.29
B71: Exterior Signage | D71: =SUM(F71:H71) -> 1558.83 | F71: 1558.83
B72: Parking Lot Striping / Barriers | D72: =SUM(F72:H72) -> 3348.88 | F72: 3348.88
B73: Sidewalks / Curbs | D73: =SUM(F73:H73) -> 171862.61 | F73: 171862.61
B74: Landscaping | D74: =SUM(F74:H74) -> 3748.12 | F74: 3748.12
B75: Security Lighting Poles | D75: =SUM(F75:H75) -> 5352.49 | F75: 5352.49
B76: Exterior Fencing | D76: =SUM(F76:H76) -> 43171.77 | F76: 43171.77
B77: Dumpster Enclosures | D77: =SUM(F77:H77) -> 3820.42 | F77: 3820.42
B78: Swimming Pool & Spa | D78: =SUM(F78:H78) -> 29214.83 | F78: 29214.83
B79: Fire Hydrants | D79: =SUM(F79:H79) -> 5694.27 | F79: 5694.27
B80: Exterior Equipment Concrete Pads | D80: =SUM(F80:H80) -> 6803.37 | F80: 6803.37
B81: Playgrounds | D81: =SUM(F81:H81) -> 10151.48 | F81: 10151.48
B82: Site Utilities
B83: Site Utilities | D83: =SUM(F83:H83) -> 318129.54 | H83: 318129.54
B84: Total Site Cost | D84: =SUM(D68:D83) -> 806490.9 | F84: =SUM(F68:F83) -> 488361.36 | H84: =SUM(H68:H83) -> 318129.54
B85: % of Cost | F85: =F84/D84 -> 0.60553859 | H85: =H84/D84 -> 0.39446141
A87: ASSET ALLOCATION (per After Cost Segregation schedule)
B88: Asset (as reclassified) | D88: Cost | F88: 15 Year | H88: 27.5 Year
B89: =Site!B18 -> 1 - Buillding - Site - 15yr | D89: =SUM(F89:H89) -> 385433.18 | F89: =Site!D18 -> 385433.18
B90: =Site!B19 -> 1 - Buillding - Site - 27.5yr | D90: =SUM(F90:H90) -> 251079.81 | H90: =Site!D19 -> 251079.81
B91: =Site!B20 -> 5 - Building - Site - 15yr | D91: =SUM(F91:H91) -> 701.99 | F91: =Site!D20 -> 701.99
B92: =Site!B21 -> 5 - Building - Site - 27.5yr | D92: =SUM(F92:H92) -> 457.29 | H92: =Site!D21 -> 457.29
B93: =Site!B22 -> 3 - Land Improvements - Site - 15yr | D93: =SUM(F93:H93) -> 36361.63 | F93: =Site!D22 -> 36361.63
B94: =Site!B23 -> 3 - Land Improvements - Site - 27.5yr | D94: =SUM(F94:H94) -> 23686.78 | H94: =Site!D23 -> 23686.78
B95: =Site!B24 -> 4 - Equipment - Site - 15yr | D95: =SUM(F95:H95) -> 65864.56 | F95: =Site!D24 -> 65864.56
B96: =Site!B25 -> 4 - Equipment - Site - 27.5yr | D96: =SUM(F96:H96) -> 42905.66 | H96: =Site!D25 -> 42905.66
B97: Total Allocation | D97: =SUM(D89:D96) -> 806490.9 | F97: =SUM(F89:F96) -> 488361.36 | H97: =SUM(H89:H96) -> 318129.54
B98: Check: Allocation vs. Cost Detail (should be zero) | D98: =D97-D84 -> 0

Sheet Clubhouse
A1: Grace Townhomes Housing, LLC
A2: Grace Townhomes — 1212 Grace Cir, Ennis, TX 75119
A3: EIN: 47-5360069 · FYE: December 31, 2024 · Year of Change: 1/1/2024
A4: Clubhouse — Attachment to Form 3115 (DCN #7, Rev. Proc. 2024-23 §6.01)
A5: Source: CSSI Report #107752-11, "#107752-11_Grace Townhomes - 3115 - Combined R2.pdf"
A7: CALCULATION OF §481(a) ADJUSTMENT — REGULAR TAX
A8: As Previously Filed
A9: Asset | B9: Property Description | C9: Date In Service | D9: Cost | E9: Sec 179 Exp | F9: Bonus Amt | G9: Tax Prior Depreciation | H9: Tax Current Depreciation | I9: End Depreciation | J9: Net Book Value | K9: Method | L9: Period
A10: 1 | B10: 1 - Buillding - Clubhouse | C10: 12/17/15 | D10: 87855.35 | E10: 0 | F10: 0 | G10: 25690.6 | H10: 3194.76 | I10: =G10+H10 -> 28885.36 | J10: =D10-I10 -> 58969.99 | K10: S/L | L10: 27.5
A11: 2 | B11: 5 - Building - Clubhouse | C11: 1/14/16 | D11: 160.01 | E11: 0 | F11: 0 | G11: 46.34 | H11: 5.82 | I11: =G11+H11 -> 52.16 | J11: =D11-I11 -> 107.85 | K11: S/L | L11: 27.5
A12: 3 | B12: 3 - Land Improvements - Clubhouse | C12: 12/17/15 | D12: 8288.23 | E12: 0 | F12: 0 | G12: 4854.14 | H12: 489.01 | I12: =G12+H12 -> 5343.15 | J12: =D12-I12 -> 2945.08 | K12: 150DB | L12: 15.0
A13: 4 | B13: 4 - Equipment - Clubhouse | C13: 12/17/15 | D13: 15013.12 | E13: 0 | F13: 0 | G13: 14512.68 | H13: 0 | I13: =G13+H13 -> 14512.68 | J13: =D13-I13 -> 500.44 | K13: 200DB | L13: 5.0
B14: Grand Total | D14: =SUM(D10:D13) -> 111316.71 | E14: =SUM(E10:E13) -> 0 | F14: =SUM(F10:F13) -> 0 | G14: =SUM(G10:G13) -> 45103.76 | H14: =SUM(H10:H13) -> 3689.59 | I14: =SUM(I10:I13) -> 48793.35 | J14: =SUM(J10:J13) -> 62523.36
A16: After Cost Segregation Correction
A17: Asset | B17: Property Description | C17: Date In Service | D17: Cost | E17: Sec 179 Exp | F17: Bonus Amt | G17: Tax Prior Depreciation | H17: Tax Current Depreciation | I17: End Depreciation | J17: Net Book Value | K17: Method | L17: Period
A18: 1 | B18: 1 - Buillding - Clubhouse - 5yr | C18: 12/17/15 | D18: 15749.94 | E18: 0 | F18: 0 | G18: 15749.94 | H18: 0 | I18: =G18+H18 -> 15749.94 | J18: =D18-I18 -> 0 | K18: 200DB | L18: 5.0
A19: 2 | B19: 1 - Buillding - Clubhouse - 27.5yr | C19: 12/17/15 | D19: 72105.41 | E19: 0 | F19: 0 | G19: 21085.33 | H19: 2622.01 | I19: =G19+H19 -> 23707.34 | J19: =D19-I19 -> 48398.07 | K19: S/L | L19: 27.5
A20: 3 | B20: 5 - Building - Clubhouse - 5yr | C20: 1/14/16 | D20: 28.69 | E20: 0 | F20: 0 | G20: 28.69 | H20: 0 | I20: =G20+H20 -> 28.69 | J20: =D20-I20 -> 0 | K20: 200DB | L20: 5.0
A21: 4 | B21: 5 - Building - Clubhouse - 27.5yr | C21: 1/14/16 | D21: 131.32 | E21: 0 | F21: 0 | G21: 38.04 | H21: 4.78 | I21: =G21+H21 -> 42.82 | J21: =D21-I21 -> 88.5 | K21: S/L | L21: 27.5
A22: 5 | B22: 3 - Land Improvements - Clubhouse - 5yr | C22: 12/17/15 | D22: 1485.84 | E22: 0 | F22: 0 | G22: 1485.84 | H22: 0 | I22: =G22+H22 -> 1485.84 | J22: =D22-I22 -> 0 | K22: 200DB | L22: 5.0
A23: 6 | B23: 3 - Land Improvements - Clubhouse - 27.5yr | C23: 12/17/15 | D23: 6802.39 | E23: 0 | F23: 0 | G23: 1989.19 | H23: 247.36 | I23: =G23+H23 -> 2236.55 | J23: =D23-I23 -> 4565.84 | K23: S/L | L23: 27.5
A24: 7 | B24: 4 - Equipment - Clubhouse - 5yr | C24: 12/17/15 | D24: 2691.42 | E24: 0 | F24: 0 | G24: 2691.42 | H24: 0 | I24: =G24+H24 -> 2691.42 | J24: =D24-I24 -> 0 | K24: 200DB | L24: 5.0
A25: 8 | B25: 4 - Equipment - Clubhouse - 27.5yr | C25: 12/17/15 | D25: 12321.7 | E25: 0 | F25: 0 | G25: 3603.15 | H25: 448.06 | I25: =G25+H25 -> 4051.21 | J25: =D25-I25 -> 8270.49 | K25: S/L | L25: 27.5
B26: Grand Total | D26: =SUM(D18:D25) -> 111316.71 | E26: =SUM(E18:E25) -> 0 | F26: =SUM(F18:F25) -> 0 | G26: =SUM(G18:G25) -> 46671.6 | H26: =SUM(H18:H25) -> 3322.21 | I26: =SUM(I18:I25) -> 49993.81 | J26: =SUM(J18:J25) -> 61322.9
B28: Section 481(a) Adjustment — Regular Tax
B29: Depreciation reported previously | D29: =I14 -> 48793.35
B30: Cost Segregation Corrected Depreciation | D30: =I26 -> 49993.81
B31: Section 481(a) Adjustment — Regular Tax | D31: =D29-D30 -> -1200.46
A33: CALCULATION OF §481(a) ADJUSTMENT — AMT
A34: As Previously Filed — AMT
A35: Asset | B35: Property Description | C35: Date In Service | D35: Cost | E35: Sec 179 Exp | F35: Bonus Amt | G35: AMT Prior Depreciation | H35: AMT Current Depreciation | I35: End Depreciation | J35: Net Book Value | K35: Method | L35: Period
A36: 1 | B36: 1 - Buillding - Clubhouse | C36: 12/17/15 | D36: 87855.35 | E36: 0 | F36: 0 | G36: 25690.6 | H36: 3194.76 | I36: =G36+H36 -> 28885.36 | J36: =D36-I36 -> 58969.99 | K36: S/L | L36: 27.5
A37: 2 | B37: 5 - Building - Clubhouse | C37: 1/14/16 | D37: 160.01 | E37: 0 | F37: 0 | G37: 46.34 | H37: 5.82 | I37: =G37+H37 -> 52.16 | J37: =D37-I37 -> 107.85 | K37: S/L | L37: 27.5
A38: 3 | B38: 3 - Land Improvements - Clubhouse | C38: 12/17/15 | D38: 8288.23 | E38: 0 | F38: 0 | G38: 4854.14 | H38: 489.01 | I38: =G38+H38 -> 5343.15 | J38: =D38-I38 -> 2945.08 | K38: 150DB | L38: 15.0
A39: 4 | B39: 4 - Equipment - Clubhouse | C39: 12/17/15 | D39: 15013.12 | E39: 0 | F39: 0 | G39: 14512.68 | H39: 0 | I39: =G39+H39 -> 14512.68 | J39: =D39-I39 -> 500.44 | K39: 200DB | L39: 5.0
B40: Grand Total | D40: =SUM(D36:D39) -> 111316.71 | E40: =SUM(E36:E39) -> 0 | F40: =SUM(F36:F39) -> 0 | G40: =SUM(G36:G39) -> 45103.76 | H40: =SUM(H36:H39) -> 3689.59 | I40: =SUM(I36:I39) -> 48793.35 | J40: =SUM(J36:J39) -> 62523.36
A42: After Cost Segregation Correction — AMT
A43: Asset | B43: Property Description | C43: Date In Service | D43: Cost | E43: Sec 179 Exp | F43: Bonus Amt | G43: AMT Prior Depreciation | H43: AMT Current Depreciation | I43: End Depreciation | J43: Net Book Value | K43: Method | L43: Period
A44: 1 | B44: 1 - Buillding - Clubhouse - 5yr | C44: 12/17/15 | D44: 15749.94 | E44: 0 | F44: 0 | G44: 15749.94 | H44: 0 | I44: =G44+H44 -> 15749.94 | J44: =D44-I44 -> 0 | K44: 200DB | L44: 5.0
A45: 2 | B45: 1 - Buillding - Clubhouse - 27.5yr | C45: 12/17/15 | D45: 72105.41 | E45: 0 | F45: 0 | G45: 21085.33 | H45: 2622.01 | I45: =G45+H45 -> 23707.34 | J45: =D45-I45 -> 48398.07 | K45: S/L | L45: 27.5
A46: 3 | B46: 5 - Building - Clubhouse - 5yr | C46: 1/14/16 | D46: 28.69 | E46: 0 | F46: 0 | G46: 28.69 | H46: 0 | I46: =G46+H46 -> 28.69 | J46: =D46-I46 -> 0 | K46: 200DB | L46: 5.0
A47: 4 | B47: 5 - Building - Clubhouse - 27.5yr | C47: 1/14/16 | D47: 131.32 | E47: 0 | F47: 0 | G47: 38.04 | H47: 4.78 | I47: =G47+H47 -> 42.82 | J47: =D47-I47 -> 88.5 | K47: S/L | L47: 27.5
A48: 5 | B48: 3 - Land Improvements - Clubhouse - 5yr | C48: 12/17/15 | D48: 1485.84 | E48: 0 | F48: 0 | G48: 1485.84 | H48: 0 | I48: =G48+H48 -> 1485.84 | J48: =D48-I48 -> 0 | K48: 200DB | L48: 5.0
A49: 6 | B49: 3 - Land Improvements - Clubhouse - 27.5yr | C49: 12/17/15 | D49: 6802.39 | E49: 0 | F49: 0 | G49: 1989.19 | H49: 247.36 | I49: =G49+H49 -> 2236.55 | J49: =D49-I49 -> 4565.84 | K49: S/L | L49: 27.5
A50: 7 | B50: 4 - Equipment - Clubhouse - 5yr | C50: 12/17/15 | D50: 2691.42 | E50: 0 | F50: 0 | G50: 2691.42 | H50: 0 | I50: =G50+H50 -> 2691.42 | J50: =D50-I50 -> 0 | K50: 200DB | L50: 5.0
A51: 8 | B51: 4 - Equipment - Clubhouse - 27.5yr | C51: 12/17/15 | D51: 12321.7 | E51: 0 | F51: 0 | G51: 3603.15 | H51: 448.06 | I51: =G51+H51 -> 4051.21 | J51: =D51-I51 -> 8270.49 | K51: S/L | L51: 27.5
B52: Grand Total | D52: =SUM(D44:D51) -> 111316.71 | E52: =SUM(E44:E51) -> 0 | F52: =SUM(F44:F51) -> 0 | G52: =SUM(G44:G51) -> 46671.6 | H52: =SUM(H44:H51) -> 3322.21 | I52: =SUM(I44:I51) -> 49993.81 | J52: =SUM(J44:J51) -> 61322.9
B54: Section 481(a) Adjustment — AMT
B55: Depreciation reported previously | D55: =I40 -> 48793.35
B56: Cost Segregation Corrected Depreciation | D56: =I52 -> 49993.81
B57: Section 481(a) Adjustment — AMT | D57: =D55-D56 -> -1200.46
A59: COST SEGREGATION STUDY — COST SUMMARY
B60: Total Building Cost | D60: =D97 -> 111316.71
B61: Building Components: 5 Year | D61: =F97 -> 19955.89
B62: % of Cost | D62: =F98 -> 0.17927129
B63: Building Structure: 27.5 Year | D63: =H97 -> 91360.82
B64: % of Cost | D64: =H98 -> 0.82072871
A66: COST SEGREGATION STUDY — COST DETAIL
B67: Property Category | D67: Cost | F67: 5 Year | H67: 27.5 Year
B68: Building Components
B69: Cabinets / Millwork | D69: =SUM(F69:H69) -> 1211.6 | F69: 1211.6
B70: Moldings | D70: =SUM(F70:H70) -> 2930.23 | F70: 2930.23
B71: Flooring - Vinyl Plank | D71: =SUM(F71:H71) -> 7111.65 | F71: 7111.65
B72: Security System | D72: =SUM(F72:H72) -> 782.67 | F72: 782.67
B73: Window Treatments | D73: =SUM(F73:H73) -> 369.85 | F73: 369.85
B74: Specialty Electrical - Appliances | D74: =SUM(F74:H74) -> 364.47 | F74: 364.47
B75: Communication / Data | D75: =SUM(F75:H75) -> 2369.45 | F75: 2369.45
B76: Specialty Plumbing - Kitchen Sink | D76: =SUM(F76:H76) -> 665.54 | F76: 665.54
B77: Security / Exterior Lighting | D77: =SUM(F77:H77) -> 318.98 | F77: 318.98
B78: Mailboxes | D78: =SUM(F78:H78) -> 3831.45 | F78: 3831.45
B79: Building Structure
B80: Roofing Systems | D80: =SUM(F80:H80) -> 7015.23 | H80: 7015.23
B81: Foundations | D81: =SUM(F81:H81) -> 9776.15 | H81: 9776.15
B82: HVAC | D82: =SUM(F82:H82) -> 7127.17 | H82: 7127.17
B83: Electrical | D83: =SUM(F83:H83) -> 7351.5 | H83: 7351.5
B84: Plumbing | D84: =SUM(F84:H84) -> 6195.62 | H84: 6195.62
B85: Fire Protection & Alarm | D85: =SUM(F85:H85) -> 247.19 | H85: 247.19
B86: Exterior Façade / Building Skin | D86: =SUM(F86:H86) -> 4165.79 | H86: 4165.79
B87: Doors & Frames | D87: =SUM(F87:H87) -> 2464.17 | H87: 2464.17
B88: Windows | D88: =SUM(F88:H88) -> 1928.81 | H88: 1928.81
B89: Ceiling Systems | D89: =SUM(F89:H89) -> 3233.65 | H89: 3233.65
B90: Interior Framing / Partitions | D90: =SUM(F90:H90) -> 18160.96 | H90: 18160.96
B91: Painting | D91: =SUM(F91:H91) -> 6068.28 | H91: 6068.28
... B96: Ceramic Tile Flooring | D96: =SUM(F96:H96) -> 146.01 | H96: 146.01
B97: Total Building Cost | D97: =SUM(D68:D96) -> 111316.71 | F97: =SUM(F68:F96) -> 19955.89 | H97: =SUM(H68:H96) -> 91360.82
B98: % of Cost | F98: =F97/D97 -> 0.17927129 | H98: =H97/D97 -> 0.82072871
A100: ASSET ALLOCATION (per After Cost Segregation schedule)
B101: Asset (as reclassified) | D101: Cost | F101: 5 Year | H101: 27.5 Year
B102: =Clubhouse!B18 -> 1 - Buillding - Clubhouse - 5yr | D102: =SUM(F102:H102) -> 15749.94 | F102: =Clubhouse!D18 -> 15749.94
B103: =Clubhouse!B19 -> 1 - Buillding - Clubhouse - 27.5yr | D103: =SUM(F103:H103) -> 72105.41 | H103: =Clubhouse!D19 -> 72105.41
B104: =Clubhouse!B20 -> 5 - Building - Clubhouse - 5yr | D104: =SUM(F104:H104) -> 28.69 | F104: =Clubhouse!D20 -> 28.69
B105: =Clubhouse!B21 -> 5 - Building - Clubhouse - 27.5yr | D105: =SUM(F105:H105) -> 131.32 | H105: =Clubhouse!D21 -> 131.32
B106: =Clubhouse!B22 -> 3 - Land Improvements - Clubhouse - 5yr | D106: =SUM(F106:H106) -> 1485.84 | F106: =Clubhouse!D22 -> 1485.84
B107: =Clubhouse!B23 -> 3 - Land Improvements - Clubhouse - 27.5yr | D107: =SUM(F107:H107) -> 6802.39 | H107: =Clubhouse!D23 -> 6802.39
B108: =Clubhouse!B24 -> 4 - Equipment - Clubhouse - 5yr | D108: =SUM(F108:H108) -> 2691.42 | F108: =Clubhouse!D24 -> 2691.42
B109: =Clubhouse!B25 -> 4 - Equipment - Clubhouse - 27.5yr | D109: =SUM(F109:H109) -> 12321.7 | H109: =Clubhouse!D25 -> 12321.7
B110: Total Allocation | D110: =SUM(D102:D109) -> 111316.71 | F110: =SUM(F102:F109) -> 19955.89 | H110: =SUM(H102:H109) -> 91360.82
B111: Check: Allocation vs. Cost Detail (should be zero) | D111: =D110-D97 -> 0

Sheet Building 1
A1: Grace Townhomes Housing, LLC
A2: Grace Townhomes — 1212 Grace Cir, Ennis, TX 75119
A3: EIN: 47-5360069 · FYE: December 31, 2024 · Year of Change: 1/1/2024
A4: Building 1 — Attachment to Form 3115 (DCN #7, Rev. Proc. 2024-23 §6.01)
A5: Source: CSSI Report #107752-11, "#107752-11_Grace Townhomes - 3115 - Combined R2.pdf"
A7: CALCULATION OF §481(a) ADJUSTMENT — REGULAR TAX
A8: As Previously Filed
A9: Asset | B9: Property Description | C9: Date In Service | D9: Cost | E9: Sec 179 Exp | F9: Bonus Amt | G9: Tax Prior Depreciation | H9: Tax Current Depreciation | I9: End Depreciation | J9: Net Book Value | K9: Method | L9: Period
A10: 1 | B10: 1 - Buillding - Apt | C10: 12/17/15 | D10: 212191.05 | E10: 0 | F10: 0 | G10: 62049.02 | H10: 7716.04 | I10: =G10+H10 -> 69765.06 | J10: =D10-I10 -> 142425.99 | K10: S/L | L10: 27.5
A11: 2 | B11: 5 - Building - Apt | C11: 1/14/16 | D11: 386.45 | E11: 0 | F11: 0 | G11: 111.91 | H11: 14.06 | I11: =G11+H11 -> 125.97 | J11: =D11-I11 -> 260.48 | K11: S/L | L11: 27.5
A12: 3 | B12: 3 - Land Improvements - Apt | C12: 12/17/15 | D12: 20018 | E12: 0 | F12: 0 | G12: 11723.87 | H12: 1181.07 | I12: =G12+H12 -> 12904.94 | J12: =D12-I12 -> 7113.06 | K12: 150DB | L12: 15.0
A13: 4 | B13: 4 - Equipment - Apt | C13: 12/17/15 | D13: 36260.17 | E13: 0 | F13: 0 | G13: 35051.5 | H13: 0 | I13: =G13+H13 -> 35051.5 | J13: =D13-I13 -> 1208.67 | K13: 200DB | L13: 5.0
B14: Grand Total | D14: =SUM(D10:D13) -> 268855.67 | E14: =SUM(E10:E13) -> 0 | F14: =SUM(F10:F13) -> 0 | G14: =SUM(G10:G13) -> 108936.3 | H14: =SUM(H10:H13) -> 8911.17 | I14: =SUM(I10:I13) -> 117847.47 | J14: =SUM(J10:J13) -> 151008.2
A16: After Cost Segregation Correction
A17: Asset | B17: Property Description | C17: Date In Service | D17: Cost | E17: Sec 179 Exp | F17: Bonus Amt | G17: Tax Prior Depreciation | H17: Tax Current Depreciation | I17: End Depreciation | J17: Net Book Value | K17: Method | L17: Period
A18: 1 | B18: 1 - Buillding - Apt - 5yr | C18: 12/17/15 | D18: 41085.46 | E18: 0 | F18: 0 | G18: 41085.46 | H18: 0 | I18: =G18+H18 -> 41085.46 | J18: =D18-I18 -> 0 | K18: 200DB | L18: 5.0
A19: 2 | B19: 1 - Buillding - Apt - 27.5yr | C19: 12/17/15 | D19: 171105.59 | E19: 0 | F19: 0 | G19: 50035.41 | H19: 6222.02 | I19: =G19+H19 -> 56257.43 | J19: =D19-I19 -> 114848.16 | K19: S/L | L19: 27.5
A20: 3 | B20: 5 - Building - Apt - 5yr | C20: 1/14/16 | D20: 74.83 | E20: 0 | F20: 0 | G20: 74.83 | H20: 0 | I20: =G20+H20 -> 74.83 | J20: =D20-I20 -> 0 | K20: 200DB | L20: 5.0
A21: 4 | B21: 5 - Building - Apt - 27.5yr | C21: 1/14/16 | D21: 311.62 | E21: 0 | F21: 0 | G21: 90.17 | H21: 11.33 | I21: =G21+H21 -> 101.5 | J21: =D21-I21 -> 210.12 | K21: S/L | L21: 27.5
A22: 5 | B22: 3 - Land Improvements - Apt - 5yr | C22: 12/17/15 | D22: 3875.98 | E22: 0 | F22: 0 | G22: 3875.98 | H22: 0 | I22: =G22+H22 -> 3875.98 | J22: =D22-I22 -> 0 | K22: 200DB | L22: 5.0
A23: 6 | B23: 3 - Land Improvements - Apt - 27.5yr | C23: 12/17/15 | D23: 16142.02 | E23: 0 | F23: 0 | G23: 4720.3 | H23: 586.98 | I23: =G23+H23 -> 5307.28 | J23: =D23-I23 -> 10834.74 | K23: S/L | L23: 27.5
A24: 7 | B24: 4 - Equipment - Apt - 5yr | C24: 12/17/15 | D24: 7020.87 | E24: 0 | F24: 0 | G24: 7020.87 | H24: 0 | I24: =G24+H24 -> 7020.87 | J24: =D24-I24 -> 0 | K24: 200DB | L24: 5.0
A25: 8 | B25: 4 - Equipment - Apt - 27.5yr | C25: 12/17/15 | D25: 29239.3 | E25: 0 | F25: 0 | G25: 8550.3 | H25: 1063.25 | I25: =G25+H25 -> 9613.55 | J25: =D25-I25 -> 19625.75 | K25: S/L | L25: 27.5
B26: Grand Total | D26: =SUM(D18:D25) -> 268855.67 | E26: =SUM(E18:E25) -> 0 | F26: =SUM(F18:F25) -> 0 | G26: =SUM(G18:G25) -> 115453.32 | H26: =SUM(H18:H25) -> 7883.58 | I26: =SUM(I18:I25) -> 123336.9 | J26: =SUM(J18:J25) -> 145518.77
B28: Section 481(a) Adjustment — Regular Tax
B29: Depreciation reported previously | D29: =I14 -> 117847.47
B30: Cost Segregation Corrected Depreciation | D30: =I26 -> 123336.9
B31: Section 481(a) Adjustment — Regular Tax | D31: =D29-D30 -> -5489.43
A33: CALCULATION OF §481(a) ADJUSTMENT — AMT
A34: As Previously Filed — AMT
A35: Asset | B35: Property Description | C35: Date In Service | D35: Cost | E35: Sec 179 Exp | F35: Bonus Amt | G35: AMT Prior Depreciation | H35: AMT Current Depreciation | I35: End Depreciation | J35: Net Book Value | K35: Method | L35: Period
A36: 1 | B36: 1 - Buillding - Apt | C36: 12/17/15 | D36: 212191.05 | E36: 0 | F36: 0 | G36: 62049.02 | H36: 7716.04 | I36: =G36+H36 -> 69765.06 | J36: =D36-I36 -> 142425.99 | K36: S/L | L36: 27.5
A37: 2 | B37: 5 - Building - Apt | C37: 1/14/16 | D37: 386.45 | E37: 0 | F37: 0 | G37: 111.91 | H37: 14.06 | I37: =G37+H37 -> 125.97 | J37: =D37-I37 -> 260.48 | K37: S/L | L37: 27.5
A38: 3 | B38: 3 - Land Improvements - Apt | C38: 12/17/15 | D38: 20018 | E38: 0 | F38: 0 | G38: 11723.87 | H38: 1181.07 | I38: =G38+H38 -> 12904.94 | J38: =D38-I38 -> 7113.06 | K38: 150DB | L38: 15.0
A39: 4 | B39: 4 - Equipment - Apt | C39: 12/17/15 | D39: 36260.17 | E39: 0 | F39: 0 | G39: 35051.5 | H39: 0 | I39: =G39+H39 -> 35051.5 | J39: =D39-I39 -> 1208.67 | K39: 200DB | L39: 5.0
B40: Grand Total | D40: =SUM(D36:D39) -> 268855.67 | E40: =SUM(E36:E39) -> 0 | F40: =SUM(F36:F39) -> 0 | G40: =SUM(G36:G39) -> 108936.3 | H40: =SUM(H36:H39) -> 8911.17 | I40: =SUM(I36:I39) -> 117847.47 | J40: =SUM(J36:J39) -> 151008.2
A42: After Cost Segregation Correction — AMT
A43: Asset | B43: Property Description | C43: Date In Service | D43: Cost | E43: Sec 179 Exp | F43: Bonus Amt | G43: AMT Prior Depreciation | H43: AMT Current Depreciation | I43: End Depreciation | J43: Net Book Value | K43: Method | L43: Period
A44: 1 | B44: 1 - Buillding - Apt - 5yr | C44: 12/17/15 | D44: 41085.46 | E44: 0 | F44: 0 | G44: 41085.46 | H44: 0 | I44: =G44+H44 -> 41085.46 | J44: =D44-I44 -> 0 | K44: 200DB | L44: 5.0
A45: 2 | B45: 1 - Buillding - Apt - 27.5yr | C45: 12/17/15 | D45: 171105.59 | E45: 0 | F45: 0 | G45: 50035.41 | H45: 6222.02 | I45: =G45+H45 -> 56257.43 | J45: =D45-I45 -> 114848.16 | K45: S/L | L45: 27.5
A46: 3 | B46: 5 - Building - Apt - 5yr | C46: 1/14/16 | D46: 74.83 | E46: 0 | F46: 0 | G46: 74.83 | H46: 0 | I46: =G46+H46 -> 74.83 | J46: =D46-I46 -> 0 | K46: 200DB | L46: 5.0
A47: 4 | B47: 5 - Building - Apt - 27.5yr | C47: 1/14/16 | D47: 311.62 | E47: 0 | F47: 0 | G47: 90.17 | H47: 11.33 | I47: =G47+H47 -> 101.5 | J47: =D47-I47 -> 210.12 | K47: S/L | L47: 27.5
A48: 5 | B48: 3 - Land Improvements - Apt - 5yr | C48: 12/17/15 | D48: 3875.98 | E48: 0 | F48: 0 | G48: 3875.98 | H48: 0 | I48: =G48+H48 -> 3875.98 | J48: =D48-I48 -> 0 | K48: 200DB | L48: 5.0
A49: 6 | B49: 3 - Land Improvements - Apt - 27.5yr | C49: 12/17/15 | D49: 16142.02 | E49: 0 | F49: 0 | G49: 4720.3 | H49: 586.98 | I49: =G49+H49 -> 5307.28 | J49: =D49-I49 -> 10834.74 | K49: S/L | L49: 27.5
A50: 7 | B50: 4 - Equipment - Apt - 5yr | C50: 12/17/15 | D50: 7020.87 | E50: 0 | F50: 0 | G50: 7020.87 | H50: 0 | I50: =G50+H50 -> 7020.87 | J50: =D50-I50 -> 0 | K50: 200DB | L50: 5.0
A51: 8 | B51: 4 - Equipment - Apt - 27.5yr | C51: 12/17/15 | D51: 29239.3 | E51: 0 | F51: 0 | G51: 8550.3 | H51: 1063.25 | I51: =G51+H51 -> 9613.55 | J51: =D51-I51 -> 19625.75 | K51: S/L | L51: 27.5
B52: Grand Total | D52: =SUM(D44:D51) -> 268855.67 | E52: =SUM(E44:E51) -> 0 | F52: =SUM(F44:F51) -> 0 | G52: =SUM(G44:G51) -> 115453.32 | H52: =SUM(H44:H51) -> 7883.58 | I52: =SUM(I44:I51) -> 123336.9 | J52: =SUM(J44:J51) -> 145518.77
B54: Section 481(a) Adjustment — AMT
B55: Depreciation reported previously | D55: =I40 -> 117847.47
B56: Cost Segregation Corrected Depreciation | D56: =I52 -> 123336.9
B57: Section 481(a) Adjustment — AMT | D57: =D55-D56 -> -5489.43
A59: COST SEGREGATION STUDY — COST SUMMARY
B60: Total Building Cost | D60: =D99 -> 268855.67
B61: Building Components: 5 Year | D61: =F99 -> 52057.14
B62: % of Cost | D62: =F100 -> 0.19362485
B63: Building Structure: 27.5 Year | D63: =H99 -> 216798.53
B64: % of Cost | D64: =H100 -> 0.80637515
A66: COST SEGREGATION STUDY — COST DETAIL
B67: Property Category | D67: Cost | F67: 5 Year | H67: 27.5 Year
B68: Building Components
B69: Cabinets / Millwork | D69: =SUM(F69:H69) -> 7759.94 | F69: 7759.94
B70: Moldings | D70: =SUM(F70:H70) -> 4601.14 | F70: 4601.14
B71: Flooring - Vinyl Plank | D71: =SUM(F71:H71) -> 18695.69 | F71: 18695.69
B72: Window Treatments | D72: =SUM(F72:H72) -> 2235.2 | F72: 2235.2
B73: Specialty HVAC - Dryer Vents | D73: =SUM(F73:H73) -> 274.94 | F73: 274.94
B74: Building Signage | D74: =SUM(F74:H74) -> 120.68 | F74: 120.68
B75: Specialty Electrical - Appliances | D75: =SUM(F75:H75) -> 4471.44 | F75: 4471.44
B76: Communication / Data | D76: =SUM(F76:H76) -> 1633.14 | F76: 1633.14
B77: Specialty Plumbing - Kitchen Sinks / Laundry | D77: =SUM(F77:H77) -> 5141.11 | F77: 5141.11
B78: Security / Exterior Lighting | D78: =SUM(F78:H78) -> 1534.74 | F78: 1534.74
B79: Access Control | D79: =SUM(F79:H79) -> 64.8 | F79: 64.8
B80: Appliances | D80: =SUM(F80:H80) -> 5524.32 | F80: 5524.32
B81: Building Structure
B82: Roofing Systems | D82: =SUM(F82:H82) -> 10400.92 | H82: 10400.92
B83: Foundations | D83: =SUM(F83:H83) -> 19732.45 | H83: 19732.45
B84: HVAC | D84: =SUM(F84:H84) -> 18076.85 | H84: 18076.85
B85: Electrical | D85: =SUM(F85:H85) -> 19867.9 | H85: 19867.9
B86: Plumbing | D86: =SUM(F86:H86) -> 15953.11 | H86: 15953.11
B87: Fire Protection & Alarm | D87: =SUM(F87:H87) -> 1077 | H87: 1077
B88: Exterior Façade / Building Skin | D88: =SUM(F88:H88) -> 24515.03 | H88: 24515.03
B89: Doors & Frames | D89: =SUM(F89:H89) -> 18444.72 | H89: 18444.72
B90: Windows | D90: =SUM(F90:H90) -> 11037.53 | H90: 11037.53
B91: Ceiling Systems | D91: =SUM(F91:H91) -> 8326.32 | H91: 8326.32
B92: Interior Framing / Partitions | D92: =SUM(F92:H92) -> 20278.2 | H92: 20278.2
B93: Painting | D93: =SUM(F93:H93) -> 8613.97 | H93: 8613.97
... B98: Cabinets / Millwork - Restrooms | D98: =SUM(F98:H98) -> 2564.71 | H98: 2564.71
B99: Total Building Cost | D99: =SUM(D68:D98) -> 268855.67 | F99: =SUM(F68:F98) -> 52057.14 | H99: =SUM(H68:H98) -> 216798.53
B100: % of Cost | F100: =F99/D99 -> 0.19362485 | H100: =H99/D99 -> 0.80637515
A102: ASSET ALLOCATION (per After Cost Segregation schedule)
B103: Asset (as reclassified) | D103: Cost | F103: 5 Year | H103: 27.5 Year
B104: ='Building 1'!B18 -> 1 - Buillding - Apt - 5yr | D104: =SUM(F104:H104) -> 41085.46 | F104: ='Building 1'!D18 -> 41085.46
B105: ='Building 1'!B19 -> 1 - Buillding - Apt - 27.5yr | D105: =SUM(F105:H105) -> 171105.59 | H105: ='Building 1'!D19 -> 171105.59
B106: ='Building 1'!B20 -> 5 - Building - Apt - 5yr | D106: =SUM(F106:H106) -> 74.83 | F106: ='Building 1'!D20 -> 74.83
B107: ='Building 1'!B21 -> 5 - Building - Apt - 27.5yr | D107: =SUM(F107:H107) -> 311.62 | H107: ='Building 1'!D21 -> 311.62
B108: ='Building 1'!B22 -> 3 - Land Improvements - Apt - 5yr | D108: =SUM(F108:H108) -> 3875.98 | F108: ='Building 1'!D22 -> 3875.98
B109: ='Building 1'!B23 -> 3 - Land Improvements - Apt - 27.5yr | D109: =SUM(F109:H109) -> 16142.02 | H109: ='Building 1'!D23 -> 16142.02
B110: ='Building 1'!B24 -> 4 - Equipment - Apt - 5yr | D110: =SUM(F110:H110) -> 7020.87 | F110: ='Building 1'!D24 -> 7020.87
B111: ='Building 1'!B25 -> 4 - Equipment - Apt - 27.5yr | D111: =SUM(F111:H111) -> 29239.3 | H111: ='Building 1'!D25 -> 29239.3
B112: Total Allocation | D112: =SUM(D104:D111) -> 268855.67 | F112: =SUM(F104:F111) -> 52057.14 | H112: =SUM(H104:H111) -> 216798.53
B113: Check: Allocation vs. Cost Detail (should be zero) | D113: =D112-D99 -> 0

Sheet Building 2
A1: Grace Townhomes Housing, LLC
A2: Grace Townhomes — 1212 Grace Cir, Ennis, TX 75119
A3: EIN: 47-5360069 · FYE: December 31, 2024 · Year of Change: 1/1/2024
A4: Building 2 — Attachment to Form 3115 (DCN #7, Rev. Proc. 2024-23 §6.01)
A5: Source: CSSI Report #107752-11, "#107752-11_Grace Townhomes - 3115 - Combined R2.pdf"
A7: CALCULATION OF §481(a) ADJUSTMENT — REGULAR TAX
A8: As Previously Filed
A9: Asset | B9: Property Description | C9: Date In Service | D9: Cost | E9: Sec 179 Exp | F9: Bonus Amt | G9: Tax Prior Depreciation | H9: Tax Current Depreciation | I9: End Depreciation | J9: Net Book Value | K9: Method | L9: Period
A10: 1 | B10: 1 - Buillding - Apt | C10: 12/17/15 | D10: 212191.05 | E10: 0 | F10: 0 | G10: 62049.02 | H10: 7716.04 | I10: =G10+H10 -> 69765.06 | J10: =D10-I10 -> 142425.99 | K10: S/L | L10: 27.5
A11: 2 | B11: 5 - Building - Apt | C11: 1/14/16 | D11: 386.45 | E11: 0 | F11: 0 | G11: 111.91 | H11: 14.06 | I11: =G11+H11 -> 125.97 | J11: =D11-I11 -> 260.48 | K11: S/L | L11: 27.5
A12: 3 | B12: 3 - Land Improvements - Apt | C12: 12/17/15 | D12: 20018 | E12: 0 | F12: 0 | G12: 11723.87 | H12: 1181.07 | I12: =G12+H12 -> 12904.94 | J12: =D12-I12 -> 7113.06 | K12: 150DB | L12: 15.0
A13: 4 | B13: 4 - Equipment - Apt | C13: 12/17/15 | D13: 36260.17 | E13: 0 | F13: 0 | G13: 35051.5 | H13: 0 | I13: =G13+H13 -> 35051.5 | J13: =D13-I13 -> 1208.67 | K13: 200DB | L13: 5.0
B14: Grand Total | D14: =SUM(D10:D13) -> 268855.67 | E14: =SUM(E10:E13) -> 0 | F14: =SUM(F10:F13) -> 0 | G14: =SUM(G10:G13) -> 108936.3 | H14: =SUM(H10:H13) -> 8911.17 | I14: =SUM(I10:I13) -> 117847.47 | J14: =SUM(J10:J13) -> 151008.2
A16: After Cost Segregation Correction
A17: Asset | B17: Property Description | C17: Date In Service | D17: Cost | E17: Sec 179 Exp | F17: Bonus Amt | G17: Tax Prior Depreciation | H17: Tax Current Depreciation | I17: End Depreciation | J17: Net Book Value | K17: Method | L17: Period
A18: 1 | B18: 1 - Buillding - Apt - 5yr | C18: 12/17/15 | D18: 41085.46 | E18: 0 | F18: 0 | G18: 41085.46 | H18: 0 | I18: =G18+H18 -> 41085.46 | J18: =D18-I18 -> 0 | K18: 200DB | L18: 5.0
A19: 2 | B19: 1 - Buillding - Apt - 27.5yr | C19: 12/17/15 | D19: 171105.59 | E19: 0 | F19: 0 | G19: 50035.41 | H19: 6222.02 | I19: =G19+H19 -> 56257.43 | J19: =D19-I19 -> 114848.16 | K19: S/L | L19: 27.5
A20: 3 | B20: 5 - Building - Apt - 5yr | C20: 1/14/16 | D20: 74.83 | E20: 0 | F20: 0 | G20: 74.83 | H20: 0 | I20: =G20+H20 -> 74.83 | J20: =D20-I20 -> 0 | K20: 200DB | L20: 5.0
A21: 4 | B21: 5 - Building - Apt - 27.5yr | C21: 1/14/16 | D21: 311.62 | E21: 0 | F21: 0 | G21: 90.17 | H21: 11.33 | I21: =G21+H21 -> 101.5 | J21: =D21-I21 -> 210.12 | K21: S/L | L21: 27.5
A22: 5 | B22: 3 - Land Improvements - Apt - 5yr | C22: 12/17/15 | D22: 3875.98 | E22: 0 | F22: 0 | G22: 3875.98 | H22: 0 | I22: =G22+H22 -> 3875.98 | J22: =D22-I22 -> 0 | K22: 200DB | L22: 5.0
A23: 6 | B23: 3 - Land Improvements - Apt - 27.5yr | C23: 12/17/15 | D23: 16142.02 | E23: 0 | F23: 0 | G23: 4720.3 | H23: 586.98 | I23: =G23+H23 -> 5307.28 | J23: =D23-I23 -> 10834.74 | K23: S/L | L23: 27.5
A24: 7 | B24: 4 - Equipment - Apt - 5yr | C24: 12/17/15 | D24: 7020.87 | E24: 0 | F24: 0 | G24: 7020.87 | H24: 0 | I24: =G24+H24 -> 7020.87 | J24: =D24-I24 -> 0 | K24: 200DB | L24: 5.0
A25: 8 | B25: 4 - Equipment - Apt - 27.5yr | C25: 12/17/15 | D25: 29239.3 | E25: 0 | F25: 0 | G25: 8550.3 | H25: 1063.25 | I25: =G25+H25 -> 9613.55 | J25: =D25-I25 -> 19625.75 | K25: S/L | L25: 27.5
B26: Grand Total | D26: =SUM(D18:D25) -> 268855.67 | E26: =SUM(E18:E25) -> 0 | F26: =SUM(F18:F25) -> 0 | G26: =SUM(G18:G25) -> 115453.32 | H26: =SUM(H18:H25) -> 7883.58 | I26: =SUM(I18:I25) -> 123336.9 | J26: =SUM(J18:J25) -> 145518.77
B28: Section 481(a) Adjustment — Regular Tax
B29: Depreciation reported previously | D29: =I14 -> 117847.47
B30: Cost Segregation Corrected Depreciation | D30: =I26 -> 123336.9
B31: Section 481(a) Adjustment — Regular Tax | D31: =D29-D30 -> -5489.43
A33: CALCULATION OF §481(a) ADJUSTMENT — AMT
A34: As Previously Filed — AMT
A35: Asset | B35: Property Description | C35: Date In Service | D35: Cost | E35: Sec 179 Exp | F35: Bonus Amt | G35: AMT Prior Depreciation | H35: AMT Current Depreciation | I35: End Depreciation | J35: Net Book Value | K35: Method | L35: Period
A36: 1 | B36: 1 - Buillding - Apt | C36: 12/17/15 | D36: 212191.05 | E36: 0 | F36: 0 | G36: 62049.02 | H36: 7716.04 | I36: =G36+H36 -> 69765.06 | J36: =D36-I36 -> 142425.99 | K36: S/L | L36: 27.5
A37: 2 | B37: 5 - Building - Apt | C37: 1/14/16 | D37: 386.45 | E37: 0 | F37: 0 | G37: 111.91 | H37: 14.06 | I37: =G37+H37 -> 125.97 | J37: =D37-I37 -> 260.48 | K37: S/L | L37: 27.5
A38: 3 | B38: 3 - Land Improvements - Apt | C38: 12/17/15 | D38: 20018 | E38: 0 | F38: 0 | G38: 11723.87 | H38: 1181.07 | I38: =G38+H38 -> 12904.94 | J38: =D38-I38 -> 7113.06 | K38: 150DB | L38: 15.0
A39: 4 | B39: 4 - Equipment - Apt | C39: 12/17/15 | D39: 36260.17 | E39: 0 | F39: 0 | G39: 35051.5 | H39: 0 | I39: =G39+H39 -> 35051.5 | J39: =D39-I39 -> 1208.67 | K39: 200DB | L39: 5.0
B40: Grand Total | D40: =SUM(D36:D39) -> 268855.67 | E40: =SUM(E36:E39) -> 0 | F40: =SUM(F36:F39) -> 0 | G40: =SUM(G36:G39) -> 108936.3 | H40: =SUM(H36:H39) -> 8911.17 | I40: =SUM(I36:I39) -> 117847.47 | J40: =SUM(J36:J39) -> 151008.2
A42: After Cost Segregation Correction — AMT
A43: Asset | B43: Property Description | C43: Date In Service | D43: Cost | E43: Sec 179 Exp | F43: Bonus Amt | G43: AMT Prior Depreciation | H43: AMT Current Depreciation | I43: End Depreciation | J43: Net Book Value | K43: Method | L43: Period
A44: 1 | B44: 1 - Buillding - Apt - 5yr | C44: 12/17/15 | D44: 41085.46 | E44: 0 | F44: 0 | G44: 41085.46 | H44: 0 | I44: =G44+H44 -> 41085.46 | J44: =D44-I44 -> 0 | K44: 200DB | L44: 5.0
A45: 2 | B45: 1 - Buillding - Apt - 27.5yr | C45: 12/17/15 | D45: 171105.59 | E45: 0 | F45: 0 | G45: 50035.41 | H45: 6222.02 | I45: =G45+H45 -> 56257.43 | J45: =D45-I45 -> 114848.16 | K45: S/L | L45: 27.5
A46: 3 | B46: 5 - Building - Apt - 5yr | C46: 1/14/16 | D46: 74.83 | E46: 0 | F46: 0 | G46: 74.83 | H46: 0 | I46: =G46+H46 -> 74.83 | J46: =D46-I46 -> 0 | K46: 200DB | L46: 5.0
A47: 4 | B47: 5 - Building - Apt - 27.5yr | C47: 1/14/16 | D47: 311.62 | E47: 0 | F47: 0 | G47: 90.17 | H47: 11.33 | I47: =G47+H47 -> 101.5 | J47: =D47-I47 -> 210.12 | K47: S/L | L47: 27.5
A48: 5 | B48: 3 - Land Improvements - Apt - 5yr | C48: 12/17/15 | D48: 3875.98 | E48: 0 | F48: 0 | G48: 3875.98 | H48: 0 | I48: =G48+H48 -> 3875.98 | J48: =D48-I48 -> 0 | K48: 200DB | L48: 5.0
A49: 6 | B49: 3 - Land Improvements - Apt - 27.5yr | C49: 12/17/15 | D49: 16142.02 | E49: 0 | F49: 0 | G49: 4720.3 | H49: 586.98 | I49: =G49+H49 -> 5307.28 | J49: =D49-I49 -> 10834.74 | K49: S/L | L49: 27.5
A50: 7 | B50: 4 - Equipment - Apt - 5yr | C50: 12/17/15 | D50: 7020.87 | E50: 0 | F50: 0 | G50: 7020.87 | H50: 0 | I50: =G50+H50 -> 7020.87 | J50: =D50-I50 -> 0 | K50: 200DB | L50: 5.0
A51: 8 | B51: 4 - Equipment - Apt - 27.5yr | C51: 12/17/15 | D51: 29239.3 | E51: 0 | F51: 0 | G51: 8550.3 | H51: 1063.25 | I51: =G51+H51 -> 9613.55 | J51: =D51-I51 -> 19625.75 | K51: S/L | L51: 27.5
B52: Grand Total | D52: =SUM(D44:D51) -> 268855.67 | E52: =SUM(E44:E51) -> 0 | F52: =SUM(F44:F51) -> 0 | G52: =SUM(G44:G51) -> 115453.32 | H52: =SUM(H44:H51) -> 7883.58 | I52: =SUM(I44:I51) -> 123336.9 | J52: =SUM(J44:J51) -> 145518.77
B54: Section 481(a) Adjustment — AMT
B55: Depreciation reported previously | D55: =I40 -> 117847.47
B56: Cost Segregation Corrected Depreciation | D56: =I52 -> 123336.9
B57: Section 481(a) Adjustment — AMT | D57: =D55-D56 -> -5489.43
A59: COST SEGREGATION STUDY — COST SUMMARY
B60: Total Building Cost | D60: =D99 -> 268855.67
B61: Building Components: 5 Year | D61: =F99 -> 52057.14
B62: % of Cost | D62: =F100 -> 0.19362485
B63: Building Structure: 27.5 Year | D63: =H99 -> 216798.53
B64: % of Cost | D64: =H100 -> 0.80637515
A66: COST SEGREGATION STUDY — COST DETAIL
B67: Property Category | D67: Cost | F67: 5 Year | H67: 27.5 Year
B68: Building Components
B69: Cabinets / Millwork | D69: =SUM(F69:H69) -> 7759.94 | F69: 7759.94
B70: Moldings | D70: =SUM(F70:H70) -> 4601.14 | F70: 4601.14
B71: Flooring - Vinyl Plank | D71: =SUM(F71:H71) -> 18695.69 | F71: 18695.69
B72: Window Treatments | D72: =SUM(F72:H72) -> 2235.2 | F72: 2235.2
B73: Specialty HVAC - Dryer Vents | D73: =SUM(F73:H73) -> 274.94 | F73: 274.94
B74: Building Signage | D74: =SUM(F74:H74) -> 120.68 | F74: 120.68
B75: Specialty Electrical - Appliances | D75: =SUM(F75:H75) -> 4471.44 | F75: 4471.44
B76: Communication / Data | D76: =SUM(F76:H76) -> 1633.14 | F76: 1633.14
B77: Specialty Plumbing - Kitchen Sinks / Laundry | D77: =SUM(F77:H77) -> 5141.11 | F77: 5141.11
B78: Security / Exterior Lighting | D78: =SUM(F78:H78) -> 1534.74 | F78: 1534.74
B79: Access Control | D79: =SUM(F79:H79) -> 64.8 | F79: 64.8
B80: Appliances | D80: =SUM(F80:H80) -> 5524.32 | F80: 5524.32
B81: Building Structure
B82: Roofing Systems | D82: =SUM(F82:H82) -> 10400.92 | H82: 10400.92
B83: Foundations | D83: =SUM(F83:H83) -> 19732.45 | H83: 19732.45
B84: HVAC | D84: =SUM(F84:H84) -> 18076.85 | H84: 18076.85
B85: Electrical | D85: =SUM(F85:H85) -> 19867.9 | H85: 19867.9
B86: Plumbing | D86: =SUM(F86:H86) -> 15953.11 | H86: 15953.11
B87: Fire Protection & Alarm | D87: =SUM(F87:H87) -> 1077 | H87: 1077
B88: Exterior Façade / Building Skin | D88: =SUM(F88:H88) -> 24515.03 | H88: 24515.03
B89: Doors & Frames | D89: =SUM(F89:H89) -> 18444.72 | H89: 18444.72
B90: Windows | D90: =SUM(F90:H90) -> 11037.53 | H90: 11037.53
B91: Ceiling Systems | D91: =SUM(F91:H91) -> 8326.32 | H91: 8326.32
B92: Interior Framing / Partitions | D92: =SUM(F92:H92) -> 20278.2 | H92: 20278.2
B93: Painting | D93: =SUM(F93:H93) -> 8613.97 | H93: 8613.97
... B98: Cabinets / Millwork - Restrooms | D98: =SUM(F98:H98) -> 2564.71 | H98: 2564.71
B99: Total Building Cost | D99: =SUM(D68:D98) -> 268855.67 | F99: =SUM(F68:F98) -> 52057.14 | H99: =SUM(H68:H98) -> 216798.53
B100: % of Cost | F100: =F99/D99 -> 0.19362485 | H100: =H99/D99 -> 0.80637515
A102: ASSET ALLOCATION (per After Cost Segregation schedule)
B103: Asset (as reclassified) | D103: Cost | F103: 5 Year | H103: 27.5 Year
B104: ='Building 2'!B18 -> 1 - Buillding - Apt - 5yr | D104: =SUM(F104:H104) -> 41085.46 | F104: ='Building 2'!D18 -> 41085.46
B105: ='Building 2'!B19 -> 1 - Buillding - Apt - 27.5yr | D105: =SUM(F105:H105) -> 171105.59 | H105: ='Building 2'!D19 -> 171105.59
B106: ='Building 2'!B20 -> 5 - Building - Apt - 5yr | D106: =SUM(F106:H106) -> 74.83 | F106: ='Building 2'!D20 -> 74.83
B107: ='Building 2'!B21 -> 5 - Building - Apt - 27.5yr | D107: =SUM(F107:H107) -> 311.62 | H107: ='Building 2'!D21 -> 311.62
B108: ='Building 2'!B22 -> 3 - Land Improvements - Apt - 5yr | D108: =SUM(F108:H108) -> 3875.98 | F108: ='Building 2'!D22 -> 3875.98
B109: ='Building 2'!B23 -> 3 - Land Improvements - Apt - 27.5yr | D109: =SUM(F109:H109) -> 16142.02 | H109: ='Building 2'!D23 -> 16142.02
B110: ='Building 2'!B24 -> 4 - Equipment - Apt - 5yr | D110: =SUM(F110:H110) -> 7020.87 | F110: ='Building 2'!D24 -> 7020.87
B111: ='Building 2'!B25 -> 4 - Equipment - Apt - 27.5yr | D111: =SUM(F111:H111) -> 29239.3 | H111: ='Building 2'!D25 -> 29239.3
B112: Total Allocation | D112: =SUM(D104:D111) -> 268855.67 | F112: =SUM(F104:F111) -> 52057.14 | H112: =SUM(H104:H111) -> 216798.53
B113: Check: Allocation vs. Cost Detail (should be zero) | D113: =D112-D99 -> 0

Sheet Building 3
A1: Grace Townhomes Housing, LLC
A2: Grace Townhomes — 1212 Grace Cir, Ennis, TX 75119
A3: EIN: 47-5360069 · FYE: December 31, 2024 · Year of Change: 1/1/2024
A4: Building 3 — Attachment to Form 3115 (DCN #7, Rev. Proc. 2024-23 §6.01)
A5: Source: CSSI Report #107752-11, "#107752-11_Grace Townhomes - 3115 - Combined R2.pdf"
A7: CALCULATION OF §481(a) ADJUSTMENT — REGULAR TAX
A8: As Previously Filed
A9: Asset | B9: Property Description | C9: Date In Service | D9: Cost | E9: Sec 179 Exp | F9: Bonus Amt | G9: Tax Prior Depreciation | H9: Tax Current Depreciation | I9: End Depreciation | J9: Net Book Value | K9: Method | L9: Period
A10: 1 | B10: 1 - Buillding - Apt | C10: 12/17/15 | D10: 116723.12 | E10: 0 | F10: 0 | G10: 34132.24 | H10: 4244.48 | I10: =G10+H10 -> 38376.72 | J10: =D10-I10 -> 78346.4 | K10: S/L | L10: 27.5
A11: 2 | B11: 5 - Building - Apt | C11: 1/14/16 | D11: 212.58 | E11: 0 | F11: 0 | G11: 61.56 | H11: 7.73 | I11: =G11+H11 -> 69.29 | J11: =D11-I11 -> 143.29 | K11: S/L | L11: 27.5
A12: 3 | B12: 3 - Land Improvements - Apt | C12: 12/17/15 | D12: 11011.6 | E12: 0 | F12: 0 | G12: 6449.13 | H12: 649.69 | I12: =G12+H12 -> 7098.82 | J12: =D12-I12 -> 3912.78 | K12: 150DB | L12: 15.0
A13: 4 | B13: 4 - Equipment - Apt | C13: 12/17/15 | D13: 19946.17 | E13: 0 | F13: 0 | G13: 19281.3 | H13: 0 | I13: =G13+H13 -> 19281.3 | J13: =D13-I13 -> 664.87 | K13: 200DB | L13: 5.0
B14: Grand Total | D14: =SUM(D10:D13) -> 147893.47 | E14: =SUM(E10:E13) -> 0 | F14: =SUM(F10:F13) -> 0 | G14: =SUM(G10:G13) -> 59924.23 | H14: =SUM(H10:H13) -> 4901.9 | I14: =SUM(I10:I13) -> 64826.13 | J14: =SUM(J10:J13) -> 83067.34
A16: After Cost Segregation Correction
A17: Asset | B17: Property Description | C17: Date In Service | D17: Cost | E17: Sec 179 Exp | F17: Bonus Amt | G17: Tax Prior Depreciation | H17: Tax Current Depreciation | I17: End Depreciation | J17: Net Book Value | K17: Method | L17: Period
A18: 1 | B18: 1 - Buillding - Apt - 5yr | C18: 12/17/15 | D18: 24387.48 | E18: 0 | F18: 0 | G18: 24387.48 | H18: 0 | I18: =G18+H18 -> 24387.48 | J18: =D18-I18 -> 0 | K18: 200DB | L18: 5.0
A19: 2 | B19: 1 - Buillding - Apt - 27.5yr | C19: 12/17/15 | D19: 92335.64 | E19: 0 | F19: 0 | G19: 27001.18 | H19: 3357.66 | I19: =G19+H19 -> 30358.84 | J19: =D19-I19 -> 61976.8 | K19: S/L | L19: 27.5
A20: 3 | B20: 5 - Building - Apt - 5yr | C20: 1/14/16 | D20: 44.42 | E20: 0 | F20: 0 | G20: 44.42 | H20: 0 | I20: =G20+H20 -> 44.42 | J20: =D20-I20 -> 0 | K20: 200DB | L20: 5.0
A21: 4 | B21: 5 - Building - Apt - 27.5yr | C21: 1/14/16 | D21: 168.16 | E21: 0 | F21: 0 | G21: 48.63 | H21: 6.11 | I21: =G21+H21 -> 54.74 | J21: =D21-I21 -> 113.42 | K21: S/L | L21: 27.5
A22: 5 | B22: 3 - Land Improvements - Apt - 5yr | C22: 12/17/15 | D22: 2300.7 | E22: 0 | F22: 0 | G22: 2300.7 | H22: 0 | I22: =G22+H22 -> 2300.7 | J22: =D22-I22 -> 0 | K22: 200DB | L22: 5.0
A23: 6 | B23: 3 - Land Improvements - Apt - 27.5yr | C23: 12/17/15 | D23: 8710.9 | E23: 0 | F23: 0 | G23: 2547.28 | H23: 316.76 | I23: =G23+H23 -> 2864.04 | J23: =D23-I23 -> 5846.86 | K23: S/L | L23: 27.5
A24: 7 | B24: 4 - Equipment - Apt - 5yr | C24: 12/17/15 | D24: 4167.44 | E24: 0 | F24: 0 | G24: 4167.44 | H24: 0 | I24: =G24+H24 -> 4167.44 | J24: =D24-I24 -> 0 | K24: 200DB | L24: 5.0
A25: 8 | B25: 4 - Equipment - Apt - 27.5yr | C25: 12/17/15 | D25: 15778.73 | E25: 0 | F25: 0 | G25: 4614.07 | H25: 573.77 | I25: =G25+H25 -> 5187.84 | J25: =D25-I25 -> 10590.89 | K25: S/L | L25: 27.5
B26: Grand Total | D26: =SUM(D18:D25) -> 147893.47 | E26: =SUM(E18:E25) -> 0 | F26: =SUM(F18:F25) -> 0 | G26: =SUM(G18:G25) -> 65111.2 | H26: =SUM(H18:H25) -> 4254.3 | I26: =SUM(I18:I25) -> 69365.5 | J26: =SUM(J18:J25) -> 78527.97
B28: Section 481(a) Adjustment — Regular Tax
B29: Depreciation reported previously | D29: =I14 -> 64826.13
B30: Cost Segregation Corrected Depreciation | D30: =I26 -> 69365.5
B31: Section 481(a) Adjustment — Regular Tax | D31: =D29-D30 -> -4539.37
A33: CALCULATION OF §481(a) ADJUSTMENT — AMT
A34: As Previously Filed — AMT
A35: Asset | B35: Property Description | C35: Date In Service | D35: Cost | E35: Sec 179 Exp | F35: Bonus Amt | G35: AMT Prior Depreciation | H35: AMT Current Depreciation | I35: End Depreciation | J35: Net Book Value | K35: Method | L35: Period
A36: 1 | B36: 1 - Buillding - Apt | C36: 12/17/15 | D36: 116723.12 | E36: 0 | F36: 0 | G36: 34132.24 | H36: 4244.48 | I36: =G36+H36 -> 38376.72 | J36: =D36-I36 -> 78346.4 | K36: S/L | L36: 27.5
A37: 2 | B37: 5 - Building - Apt | C37: 1/14/16 | D37: 212.58 | E37: 0 | F37: 0 | G37: 61.56 | H37: 7.73 | I37: =G37+H37 -> 69.29 | J37: =D37-I37 -> 143.29 | K37: S/L | L37: 27.5
A38: 3 | B38: 3 - Land Improvements - Apt | C38: 12/17/15 | D38: 11011.6 | E38: 0 | F38: 0 | G38: 6449.13 | H38: 649.69 | I38: =G38+H38 -> 7098.82 | J38: =D38-I38 -> 3912.78 | K38: 150DB | L38: 15.0
A39: 4 | B39: 4 - Equipment - Apt | C39: 12/17/15 | D39: 19946.17 | E39: 0 | F39: 0 | G39: 19281.3 | H39: 0 | I39: =G39+H39 -> 19281.3 | J39: =D39-I39 -> 664.87 | K39: 200DB | L39: 5.0
B40: Grand Total | D40: =SUM(D36:D39) -> 147893.47 | E40: =SUM(E36:E39) -> 0 | F40: =SUM(F36:F39) -> 0 | G40: =SUM(G36:G39) -> 59924.23 | H40: =SUM(H36:H39) -> 4901.9 | I40: =SUM(I36:I39) -> 64826.13 | J40: =SUM(J36:J39) -> 83067.34
A42: After Cost Segregation Correction — AMT
A43: Asset | B43: Property Description | C43: Date In Service | D43: Cost | E43: Sec 179 Exp | F43: Bonus Amt | G43: AMT Prior Depreciation | H43: AMT Current Depreciation | I43: End Depreciation | J43: Net Book Value | K43: Method | L43: Period
A44: 1 | B44: 1 - Buillding - Apt - 5yr | C44: 12/17/15 | D44: 24387.48 | E44: 0 | F44: 0 | G44: 24387.48 | H44: 0 | I44: =G44+H44 -> 24387.48 | J44: =D44-I44 -> 0 | K44: 200DB | L44: 5.0
A45: 2 | B45: 1 - Buillding - Apt - 27.5yr | C45: 12/17/15 | D45: 92335.64 | E45: 0 | F45: 0 | G45: 27001.18 | H45: 3357.66 | I45: =G45+H45 -> 30358.84 | J45: =D45-I45 -> 61976.8 | K45: S/L | L45: 27.5
A46: 3 | B46: 5 - Building - Apt - 5yr | C46: 1/14/16 | D46: 44.42 | E46: 0 | F46: 0 | G46: 44.42 | H46: 0 | I46: =G46+H46 -> 44.42 | J46: =D46-I46 -> 0 | K46: 200DB | L46: 5.0
A47: 4 | B47: 5 - Building - Apt - 27.5yr | C47: 1/14/16 | D47: 168.16 | E47: 0 | F47: 0 | G47: 48.63 | H47: 6.11 | I47: =G47+H47 -> 54.74 | J47: =D47-I47 -> 113.42 | K47: S/L | L47: 27.5
A48: 5 | B48: 3 - Land Improvements - Apt - 5yr | C48: 12/17/15 | D48: 2300.7 | E48: 0 | F48: 0 | G48: 2300.7 | H48: 0 | I48: =G48+H48 -> 2300.7 | J48: =D48-I48 -> 0 | K48: 200DB | L48: 5.0
A49: 6 | B49: 3 - Land Improvements - Apt - 27.5yr | C49: 12/17/15 | D49: 8710.9 | E49: 0 | F49: 0 | G49: 2547.28 | H49: 316.76 | I49: =G49+H49 -> 2864.04 | J49: =D49-I49 -> 5846.86 | K49: S/L | L49: 27.5
A50: 7 | B50: 4 - Equipment - Apt - 5yr | C50: 12/17/15 | D50: 4167.44 | E50: 0 | F50: 0 | G50: 4167.44 | H50: 0 | I50: =G50+H50 -> 4167.44 | J50: =D50-I50 -> 0 | K50: 200DB | L50: 5.0
A51: 8 | B51: 4 - Equipment - Apt - 27.5yr | C51: 12/17/15 | D51: 15778.73 | E51: 0 | F51: 0 | G51: 4614.07 | H51: 573.77 | I51: =G51+H51 -> 5187.84 | J51: =D51-I51 -> 10590.89 | K51: S/L | L51: 27.5
B52: Grand Total | D52: =SUM(D44:D51) -> 147893.47 | E52: =SUM(E44:E51) -> 0 | F52: =SUM(F44:F51) -> 0 | G52: =SUM(G44:G51) -> 65111.2 | H52: =SUM(H44:H51) -> 4254.3 | I52: =SUM(I44:I51) -> 69365.5 | J52: =SUM(J44:J51) -> 78527.97
B54: Section 481(a) Adjustment — AMT
B55: Depreciation reported previously | D55: =I40 -> 64826.13
B56: Cost Segregation Corrected Depreciation | D56: =I52 -> 69365.5
B57: Section 481(a) Adjustment — AMT | D57: =D55-D56 -> -4539.37
A59: COST SEGREGATION STUDY — COST SUMMARY
B60: Total Building Cost | D60: =D98 -> 147893.47
B61: Building Components: 5 Year | D61: =F98 -> 30900.04
B62: % of Cost | D62: =F99 -> 0.20893444
B63: Building Structure: 27.5 Year | D63: =H98 -> 116993.43
B64: % of Cost | D64: =H99 -> 0.79106556
A66: COST SEGREGATION STUDY — COST DETAIL
B67: Property Category | D67: Cost | F67: 5 Year | H67: 27.5 Year
B68: Building Components
B69: Cabinets / Millwork | D69: =SUM(F69:H69) -> 4901.61 | F69: 4901.61
B70: Moldings | D70: =SUM(F70:H70) -> 2185.54 | F70: 2185.54
B71: Flooring - Vinyl Plank | D71: =SUM(F71:H71) -> 11385.26 | F71: 11385.26
B72: Window Treatments | D72: =SUM(F72:H72) -> 589.62 | F72: 589.62
B73: Specialty HVAC - Dryer Vents | D73: =SUM(F73:H73) -> 183.29 | F73: 183.29
B74: Building Signage | D74: =SUM(F74:H74) -> 96.76 | F74: 96.76
B75: Specialty Electrical - Appliances | D75: =SUM(F75:H75) -> 2980.97 | F75: 2980.97
B76: Communication / Data | D76: =SUM(F76:H76) -> 994.55 | F76: 994.55
B77: Specialty Plumbing - Kitchen Sinks / Laundry | D77: =SUM(F77:H77) -> 3427.41 | F77: 3427.41
B78: Security / Exterior Lighting | D78: =SUM(F78:H78) -> 428.96 | F78: 428.96
B79: Access Control | D79: =SUM(F79:H79) -> 43.2 | F79: 43.2
B80: Appliances | D80: =SUM(F80:H80) -> 3682.87 | F80: 3682.87
B81: Building Structure
B82: Roofing Systems | D82: =SUM(F82:H82) -> 8561.68 | H82: 8561.68
B83: Foundations | D83: =SUM(F83:H83) -> 16225.62 | H83: 16225.62
B84: HVAC | D84: =SUM(F84:H84) -> 10992.55 | H84: 10992.55
B85: Electrical | D85: =SUM(F85:H85) -> 12099.12 | H85: 12099.12
B86: Plumbing | D86: =SUM(F86:H86) -> 9715.1 | H86: 9715.1
B87: Fire Protection & Alarm | D87: =SUM(F87:H87) -> 548.48 | H87: 548.48
B88: Exterior Façade / Building Skin | D88: =SUM(F88:H88) -> 12559.71 | H88: 12559.71
B89: Doors & Frames | D89: =SUM(F89:H89) -> 5680.09 | H89: 5680.09
B90: Windows | D90: =SUM(F90:H90) -> 2911.57 | H90: 2911.57
B91: Ceiling Systems | D91: =SUM(F91:H91) -> 5070.55 | H91: 5070.55
B92: Interior Framing / Partitions | D92: =SUM(F92:H92) -> 9837.36 | H92: 9837.36
B93: Painting | D93: =SUM(F93:H93) -> 4408.6 | H93: 4408.6
... B97: Cabinets / Millwork - Restrooms | D97: =SUM(F97:H97) -> 1709.81 | H97: 1709.81
B98: Total Building Cost | D98: =SUM(D68:D97) -> 147893.47 | F98: =SUM(F68:F97) -> 30900.04 | H98: =SUM(H68:H97) -> 116993.43
B99: % of Cost | F99: =F98/D98 -> 0.20893444 | H99: =H98/D98 -> 0.79106556
A101: ASSET ALLOCATION (per After Cost Segregation schedule)
B102: Asset (as reclassified) | D102: Cost | F102: 5 Year | H102: 27.5 Year
B103: ='Building 3'!B18 -> 1 - Buillding - Apt - 5yr | D103: =SUM(F103:H103) -> 24387.48 | F103: ='Building 3'!D18 -> 24387.48
B104: ='Building 3'!B19 -> 1 - Buillding - Apt - 27.5yr | D104: =SUM(F104:H104) -> 92335.64 | H104: ='Building 3'!D19 -> 92335.64
B105: ='Building 3'!B20 -> 5 - Building - Apt - 5yr | D105: =SUM(F105:H105) -> 44.42 | F105: ='Building 3'!D20 -> 44.42
B106: ='Building 3'!B21 -> 5 - Building - Apt - 27.5yr | D106: =SUM(F106:H106) -> 168.16 | H106: ='Building 3'!D21 -> 168.16
B107: ='Building 3'!B22 -> 3 - Land Improvements - Apt - 5yr | D107: =SUM(F107:H107) -> 2300.7 | F107: ='Building 3'!D22 -> 2300.7
B108: ='Building 3'!B23 -> 3 - Land Improvements - Apt - 27.5yr | D108: =SUM(F108:H108) -> 8710.9 | H108: ='Building 3'!D23 -> 8710.9
B109: ='Building 3'!B24 -> 4 - Equipment - Apt - 5yr | D109: =SUM(F109:H109) -> 4167.44 | F109: ='Building 3'!D24 -> 4167.44
B110: ='Building 3'!B25 -> 4 - Equipment - Apt - 27.5yr | D110: =SUM(F110:H110) -> 15778.73 | H110: ='Building 3'!D25 -> 15778.73
B111: Total Allocation | D111: =SUM(D103:D110) -> 147893.47 | F111: =SUM(F103:F110) -> 30900.04 | H111: =SUM(H103:H110) -> 116993.43
B112: Check: Allocation vs. Cost Detail (should be zero) | D112: =D111-D98 -> 0

Sheet Building 4
A1: Grace Townhomes Housing, LLC
A2: Grace Townhomes — 1212 Grace Cir, Ennis, TX 75119
A3: EIN: 47-5360069 · FYE: December 31, 2024 · Year of Change: 1/1/2024
A4: Building 4 — Attachment to Form 3115 (DCN #7, Rev. Proc. 2024-23 §6.01)
A5: Source: CSSI Report #107752-11, "#107752-11_Grace Townhomes - 3115 - Combined R2.pdf"
A7: CALCULATION OF §481(a) ADJUSTMENT — REGULAR TAX
A8: As Previously Filed
A9: Asset | B9: Property Description | C9: Date In Service | D9: Cost | E9: Sec 179 Exp | F9: Bonus Amt | G9: Tax Prior Depreciation | H9: Tax Current Depreciation | I9: End Depreciation | J9: Net Book Value | K9: Method | L9: Period
A10: 1 | B10: 1 - Buillding - Apt | C10: 12/17/15 | D10: 91140.5 | E10: 0 | F10: 0 | G10: 26651.36 | H10: 3314.2 | I10: =G10+H10 -> 29965.56 | J10: =D10-I10 -> 61174.94 | K10: S/L | L10: 27.5
A11: 2 | B11: 5 - Building - Apt | C11: 1/14/16 | D11: 165.99 | E11: 0 | F11: 0 | G11: 48.07 | H11: 6.04 | I11: =G11+H11 -> 54.11 | J11: =D11-I11 -> 111.88 | K11: S/L | L11: 27.5
A12: 3 | B12: 3 - Land Improvements - Apt | C12: 12/17/15 | D12: 8598.15 | E12: 0 | F12: 0 | G12: 5035.65 | H12: 507.3 | I12: =G12+H12 -> 5542.95 | J12: =D12-I12 -> 3055.2 | K12: 150DB | L12: 15.0
A13: 4 | B13: 4 - Equipment - Apt | C13: 12/17/15 | D13: 15574.5 | E13: 0 | F13: 0 | G13: 15055.35 | H13: 0 | I13: =G13+H13 -> 15055.35 | J13: =D13-I13 -> 519.15 | K13: 200DB | L13: 5.0
B14: Grand Total | D14: =SUM(D10:D13) -> 115479.14 | E14: =SUM(E10:E13) -> 0 | F14: =SUM(F10:F13) -> 0 | G14: =SUM(G10:G13) -> 46790.43 | H14: =SUM(H10:H13) -> 3827.54 | I14: =SUM(I10:I13) -> 50617.97 | J14: =SUM(J10:J13) -> 64861.17
A16: After Cost Segregation Correction
A17: Asset | B17: Property Description | C17: Date In Service | D17: Cost | E17: Sec 179 Exp | F17: Bonus Amt | G17: Tax Prior Depreciation | H17: Tax Current Depreciation | I17: End Depreciation | J17: Net Book Value | K17: Method | L17: Period
A18: 1 | B18: 1 - Buillding - Apt - 5yr | C18: 12/17/15 | D18: 21279.35 | E18: 0 | F18: 0 | G18: 21279.35 | H18: 0 | I18: =G18+H18 -> 21279.35 | J18: =D18-I18 -> 0 | K18: 200DB | L18: 5.0
A19: 2 | B19: 1 - Buillding - Apt - 27.5yr | C19: 12/17/15 | D19: 69861.15 | E19: 0 | F19: 0 | G19: 20429.13 | H19: 2540.41 | I19: =G19+H19 -> 22969.54 | J19: =D19-I19 -> 46891.61 | K19: S/L | L19: 27.5
A20: 3 | B20: 5 - Building - Apt - 5yr | C20: 1/14/16 | D20: 38.76 | E20: 0 | F20: 0 | G20: 38.76 | H20: 0 | I20: =G20+H20 -> 38.76 | J20: =D20-I20 -> 0 | K20: 200DB | L20: 5.0
A21: 4 | B21: 5 - Building - Apt - 27.5yr | C21: 1/14/16 | D21: 127.23 | E21: 0 | F21: 0 | G21: 36.84 | H21: 4.63 | I21: =G21+H21 -> 41.47 | J21: =D21-I21 -> 85.76 | K21: S/L | L21: 27.5
A22: 5 | B22: 3 - Land Improvements - Apt 5yr | C22: 12/17/15 | D22: 2007.48 | E22: 0 | F22: 0 | G22: 2007.48 | H22: 0 | I22: =G22+H22 -> 2007.48 | J22: =D22-I22 -> 0 | K22: 200DB | L22: 5.0
A23: 6 | B23: 3 - Land Improvements - Apt 27.5yr | C23: 12/17/15 | D23: 6590.67 | E23: 0 | F23: 0 | G23: 1927.27 | H23: 239.66 | I23: =G23+H23 -> 2166.93 | J23: =D23-I23 -> 4423.74 | K23: S/L | L23: 27.5
A24: 7 | B24: 4 - Equipment - Apt - 5yr | C24: 12/17/15 | D24: 3636.33 | E24: 0 | F24: 0 | G24: 3636.33 | H24: 0 | I24: =G24+H24 -> 3636.33 | J24: =D24-I24 -> 0 | K24: 200DB | L24: 5.0
A25: 8 | B25: 4 - Equipment - Apt - 27.5yr | C25: 12/17/15 | D25: 11938.19 | E25: 0 | F25: 0 | G25: 3491.05 | H25: 434.12 | I25: =G25+H25 -> 3925.17 | J25: =D25-I25 -> 8013.02 | K25: S/L | L25: 27.5
B26: Grand Total | D26: =SUM(D18:D25) -> 115479.16 | E26: =SUM(E18:E25) -> 0 | F26: =SUM(F18:F25) -> 0 | G26: =SUM(G18:G25) -> 52846.21 | H26: =SUM(H18:H25) -> 3218.82 | I26: =SUM(I18:I25) -> 56065.03 | J26: =SUM(J18:J25) -> 59414.13
B28: Section 481(a) Adjustment — Regular Tax
B29: Depreciation reported previously | D29: =I14 -> 50617.97
B30: Cost Segregation Corrected Depreciation | D30: =I26 -> 56065.03
B31: Section 481(a) Adjustment — Regular Tax | D31: =D29-D30 -> -5447.06
A33: CALCULATION OF §481(a) ADJUSTMENT — AMT
A34: As Previously Filed — AMT
A35: Asset | B35: Property Description | C35: Date In Service | D35: Cost | E35: Sec 179 Exp | F35: Bonus Amt | G35: AMT Prior Depreciation | H35: AMT Current Depreciation | I35: End Depreciation | J35: Net Book Value | K35: Method | L35: Period
A36: 1 | B36: 1 - Buillding - Apt | C36: 12/17/15 | D36: 91140.5 | E36: 0 | F36: 0 | G36: 26651.36 | H36: 3314.2 | I36: =G36+H36 -> 29965.56 | J36: =D36-I36 -> 61174.94 | K36: S/L | L36: 27.5
A37: 2 | B37: 5 - Building - Apt | C37: 1/14/16 | D37: 165.99 | E37: 0 | F37: 0 | G37: 48.07 | H37: 6.04 | I37: =G37+H37 -> 54.11 | J37: =D37-I37 -> 111.88 | K37: S/L | L37: 27.5
A38: 3 | B38: 3 - Land Improvements - Apt | C38: 12/17/15 | D38: 8598.15 | E38: 0 | F38: 0 | G38: 5035.65 | H38: 507.3 | I38: =G38+H38 -> 5542.95 | J38: =D38-I38 -> 3055.2 | K38: 150DB | L38: 15.0
A39: 4 | B39: 4 - Equipment - Apt | C39: 12/17/15 | D39: 15574.5 | E39: 0 | F39: 0 | G39: 15055.35 | H39: 0 | I39: =G39+H39 -> 15055.35 | J39: =D39-I39 -> 519.15 | K39: 200DB | L39: 5.0
B40: Grand Total | D40: =SUM(D36:D39) -> 115479.14 | E40: =SUM(E36:E39) -> 0 | F40: =SUM(F36:F39) -> 0 | G40: =SUM(G36:G39) -> 46790.43 | H40: =SUM(H36:H39) -> 3827.54 | I40: =SUM(I36:I39) -> 50617.97 | J40: =SUM(J36:J39) -> 64861.17
A42: After Cost Segregation Correction — AMT
A43: Asset | B43: Property Description | C43: Date In Service | D43: Cost | E43: Sec 179 Exp | F43: Bonus Amt | G43: AMT Prior Depreciation | H43: AMT Current Depreciation | I43: End Depreciation | J43: Net Book Value | K43: Method | L43: Period
A44: 1 | B44: 1 - Buillding - Apt - 5yr | C44: 12/17/15 | D44: 21279.35 | E44: 0 | F44: 0 | G44: 21279.35 | H44: 0 | I44: =G44+H44 -> 21279.35 | J44: =D44-I44 -> 0 | K44: 200DB | L44: 5.0
A45: 2 | B45: 1 - Buillding - Apt - 27.5yr | C45: 12/17/15 | D45: 69861.15 | E45: 0 | F45: 0 | G45: 20429.13 | H45: 2540.41 | I45: =G45+H45 -> 22969.54 | J45: =D45-I45 -> 46891.61 | K45: S/L | L45: 27.5
A46: 3 | B46: 5 - Building - Apt - 5yr | C46: 1/14/16 | D46: 38.76 | E46: 0 | F46: 0 | G46: 38.76 | H46: 0 | I46: =G46+H46 -> 38.76 | J46: =D46-I46 -> 0 | K46: 200DB | L46: 5.0
A47: 4 | B47: 5 - Building - Apt - 27.5yr | C47: 1/14/16 | D47: 127.23 | E47: 0 | F47: 0 | G47: 36.84 | H47: 4.63 | I47: =G47+H47 -> 41.47 | J47: =D47-I47 -> 85.76 | K47: S/L | L47: 27.5
A48: 5 | B48: 3 - Land Improvements - Apt 5yr | C48: 12/17/15 | D48: 2007.48 | E48: 0 | F48: 0 | G48: 2007.48 | H48: 0 | I48: =G48+H48 -> 2007.48 | J48: =D48-I48 -> 0 | K48: 200DB | L48: 5.0
A49: 6 | B49: 3 - Land Improvements - Apt 27.5yr | C49: 12/17/15 | D49: 6590.67 | E49: 0 | F49: 0 | G49: 1927.27 | H49: 239.66 | I49: =G49+H49 -> 2166.93 | J49: =D49-I49 -> 4423.74 | K49: S/L | L49: 27.5
A50: 7 | B50: 4 - Equipment - Apt - 5yr | C50: 12/17/15 | D50: 3636.33 | E50: 0 | F50: 0 | G50: 3636.33 | H50: 0 | I50: =G50+H50 -> 3636.33 | J50: =D50-I50 -> 0 | K50: 200DB | L50: 5.0
A51: 8 | B51: 4 - Equipment - Apt - 27.5yr | C51: 12/17/15 | D51: 11938.19 | E51: 0 | F51: 0 | G51: 3491.05 | H51: 434.12 | I51: =G51+H51 -> 3925.17 | J51: =D51-I51 -> 8013.02 | K51: S/L | L51: 27.5
B52: Grand Total | D52: =SUM(D44:D51) -> 115479.16 | E52: =SUM(E44:E51) -> 0 | F52: =SUM(F44:F51) -> 0 | G52: =SUM(G44:G51) -> 52846.21 | H52: =SUM(H44:H51) -> 3218.82 | I52: =SUM(I44:I51) -> 56065.03 | J52: =SUM(J44:J51) -> 59414.13
B54: Section 481(a) Adjustment — AMT
B55: Depreciation reported previously | D55: =I40 -> 50617.97
B56: Cost Segregation Corrected Depreciation | D56: =I52 -> 56065.03
B57: Section 481(a) Adjustment — AMT | D57: =D55-D56 -> -5447.06
A59: COST SEGREGATION STUDY — COST SUMMARY
B60: Total Building Cost | D60: =D98 -> 115479.14
B61: Building Components: 5 Year | D61: =F98 -> 26961.9
B62: % of Cost | D62: =F99 -> 0.23347853
B63: Building Structure: 27.5 Year | D63: =H98 -> 88517.24
B64: % of Cost | D64: =H99 -> 0.76652147
A66: COST SEGREGATION STUDY — COST DETAIL
B67: Property Category | D67: Cost | F67: 5 Year | H67: 27.5 Year
B68: Building Components
B69: Cabinets / Millwork | D69: =SUM(F69:H69) -> 4785.17 | F69: 4785.17
B70: Moldings | D70: =SUM(F70:H70) -> 1941.11 | F70: 1941.11
B71: Flooring - Vinyl Plank | D71: =SUM(F71:H71) -> 7939.87 | F71: 7939.87
B72: Window Treatments | D72: =SUM(F72:H72) -> 428.82 | F72: 428.82
B73: Specialty HVAC - Dryer Vents | D73: =SUM(F73:H73) -> 183.29 | F73: 183.29
B74: Building Signage | D74: =SUM(F74:H74) -> 96.76 | F74: 96.76
B75: Specialty Electrical - Appliances | D75: =SUM(F75:H75) -> 2980.97 | F75: 2980.97
B76: Communication / Data | D76: =SUM(F76:H76) -> 693.58 | F76: 693.58
B77: Specialty Plumbing - Kitchen Sinks / Laundry | D77: =SUM(F77:H77) -> 3427.41 | F77: 3427.41
B78: Security / Exterior Lighting | D78: =SUM(F78:H78) -> 758.85 | F78: 758.85
B79: Access Control | D79: =SUM(F79:H79) -> 43.2 | F79: 43.2
B80: Appliances | D80: =SUM(F80:H80) -> 3682.87 | F80: 3682.87
B81: Building Structure
B82: Roofing Systems | D82: =SUM(F82:H82) -> 6281.12 | H82: 6281.12
B83: Foundations | D83: =SUM(F83:H83) -> 12157.7 | H83: 12157.7
B84: HVAC | D84: =SUM(F84:H84) -> 7610.53 | H84: 7610.53
B85: Electrical | D85: =SUM(F85:H85) -> 8437.69 | H85: 8437.69
B86: Plumbing | D86: =SUM(F86:H86) -> 6775.13 | H86: 6775.13
B87: Fire Protection & Alarm | D87: =SUM(F87:H87) -> 378.96 | H87: 378.96
B88: Exterior Façade / Building Skin | D88: =SUM(F88:H88) -> 10712.7 | H88: 10712.7
B89: Doors & Frames | D89: =SUM(F89:H89) -> 5035.68 | H89: 5035.68
B90: Windows | D90: =SUM(F90:H90) -> 2117.51 | H90: 2117.51
B91: Ceiling Systems | D91: =SUM(F91:H91) -> 3536.09 | H91: 3536.09
B92: Interior Framing / Partitions | D92: =SUM(F92:H92) -> 8613.79 | H92: 8613.79
B93: Painting | D93: =SUM(F93:H93) -> 3604.7 | H93: 3604.7
... B97: Cabinets / Millwork - Restrooms | D97: =SUM(F97:H97) -> 811.57 | H97: 811.57
B98: Total Building Cost | D98: =SUM(D68:D97) -> 115479.14 | F98: =SUM(F68:F97) -> 26961.9 | H98: =SUM(H68:H97) -> 88517.24
B99: % of Cost | F99: =F98/D98 -> 0.23347853 | H99: =H98/D98 -> 0.76652147
A101: ASSET ALLOCATION (per After Cost Segregation schedule)
B102: Asset (as reclassified) | D102: Cost | F102: 5 Year | H102: 27.5 Year
B103: ='Building 4'!B18 -> 1 - Buillding - Apt - 5yr | D103: =SUM(F103:H103) -> 21279.35 | F103: ='Building 4'!D18 -> 21279.35
B104: ='Building 4'!B19 -> 1 - Buillding - Apt - 27.5yr | D104: =SUM(F104:H104) -> 69861.15 | H104: ='Building 4'!D19 -> 69861.15
B105: ='Building 4'!B20 -> 5 - Building - Apt - 5yr | D105: =SUM(F105:H105) -> 38.76 | F105: ='Building 4'!D20 -> 38.76
B106: ='Building 4'!B21 -> 5 - Building - Apt - 27.5yr | D106: =SUM(F106:H106) -> 127.23 | H106: ='Building 4'!D21 -> 127.23
B107: ='Building 4'!B22 -> 3 - Land Improvements - Apt 5yr | D107: =SUM(F107:H107) -> 2007.48 | F107: ='Building 4'!D22 -> 2007.48
B108: ='Building 4'!B23 -> 3 - Land Improvements - Apt 27.5yr | D108: =SUM(F108:H108) -> 6590.67 | H108: ='Building 4'!D23 -> 6590.67
B109: ='Building 4'!B24 -> 4 - Equipment - Apt - 5yr | D109: =SUM(F109:H109) -> 3636.33 | F109: ='Building 4'!D24 -> 3636.33
B110: ='Building 4'!B25 -> 4 - Equipment - Apt - 27.5yr | D110: =SUM(F110:H110) -> 11938.19 | H110: ='Building 4'!D25 -> 11938.19
B111: Total Allocation | D111: =SUM(D103:D110) -> 115479.16 | F111: =SUM(F103:F110) -> 26961.92 | H111: =SUM(H103:H110) -> 88517.24
B112: Check: Allocation vs. Cost Detail (should be zero) | D112: =D111-D98 -> 0.02

Sheet Building 5
A1: Grace Townhomes Housing, LLC
A2: Grace Townhomes — 1212 Grace Cir, Ennis, TX 75119
A3: EIN: 47-5360069 · FYE: December 31, 2024 · Year of Change: 1/1/2024
A4: Building 5 — Attachment to Form 3115 (DCN #7, Rev. Proc. 2024-23 §6.01)
A5: Source: CSSI Report #107752-11, "#107752-11_Grace Townhomes - 3115 - Combined R2.pdf"
A7: CALCULATION OF §481(a) ADJUSTMENT — REGULAR TAX
A8: As Previously Filed
A9: Asset | B9: Property Description | C9: Date In Service | D9: Cost | E9: Sec 179 Exp | F9: Bonus Amt | G9: Tax Prior Depreciation | H9: Tax Current Depreciation | I9: End Depreciation | J9: Net Book Value | K9: Method | L9: Period
A10: 1 | B10: 1 - Buillding - Apt | C10: 12/17/15 | D10: 116723.12 | E10: 0 | F10: 0 | G10: 34132.24 | H10: 4244.48 | I10: =G10+H10 -> 38376.72 | J10: =D10-I10 -> 78346.4 | K10: S/L | L10: 27.5
A11: 2 | B11: 5 - Building - Apt | C11: 1/14/16 | D11: 212.58 | E11: 0 | F11: 0 | G11: 61.56 | H11: 7.73 | I11: =G11+H11 -> 69.29 | J11: =D11-I11 -> 143.29 | K11: S/L | L11: 27.5
A12: 3 | B12: 3 - Land Improvements - Apt | C12: 12/17/15 | D12: 11011.6 | E12: 0 | F12: 0 | G12: 6449.13 | H12: 649.69 | I12: =G12+H12 -> 7098.82 | J12: =D12-I12 -> 3912.78 | K12: 150DB | L12: 15.0
A13: 4 | B13: 4 - Equipment - Apt | C13: 12/17/15 | D13: 19946.17 | E13: 0 | F13: 0 | G13: 19281.3 | H13: 0 | I13: =G13+H13 -> 19281.3 | J13: =D13-I13 -> 664.87 | K13: 200DB | L13: 5.0
B14: Grand Total | D14: =SUM(D10:D13) -> 147893.47 | E14: =SUM(E10:E13) -> 0 | F14: =SUM(F10:F13) -> 0 | G14: =SUM(G10:G13) -> 59924.23 | H14: =SUM(H10:H13) -> 4901.9 | I14: =SUM(I10:I13) -> 64826.13 | J14: =SUM(J10:J13) -> 83067.34
A16: After Cost Segregation Correction
A17: Asset | B17: Property Description | C17: Date In Service | D17: Cost | E17: Sec 179 Exp | F17: Bonus Amt | G17: Tax Prior Depreciation | H17: Tax Current Depreciation | I17: End Depreciation | J17: Net Book Value | K17: Method | L17: Period
A18: 1 | B18: 1 - Buillding - Apt - 5yr | C18: 12/17/15 | D18: 24387.48 | E18: 0 | F18: 0 | G18: 24387.48 | H18: 0 | I18: =G18+H18 -> 24387.48 | J18: =D18-I18 -> 0 | K18: 200DB | L18: 5.0
A19: 2 | B19: 1 - Buillding - Apt - 27.5yr | C19: 12/17/15 | D19: 92335.64 | E19: 0 | F19: 0 | G19: 27001.18 | H19: 3357.66 | I19: =G19+H19 -> 30358.84 | J19: =D19-I19 -> 61976.8 | K19: S/L | L19: 27.5
A20: 3 | B20: 5 - Building - Apt - 5yr | C20: 1/14/16 | D20: 44.42 | E20: 0 | F20: 0 | G20: 44.42 | H20: 0 | I20: =G20+H20 -> 44.42 | J20: =D20-I20 -> 0 | K20: 200DB | L20: 5.0
A21: 4 | B21: 5 - Building - Apt - 27.5yr | C21: 1/14/16 | D21: 168.16 | E21: 0 | F21: 0 | G21: 48.63 | H21: 6.11 | I21: =G21+H21 -> 54.74 | J21: =D21-I21 -> 113.42 | K21: S/L | L21: 27.5
A22: 5 | B22: 3 - Land Improvements - Apt - 5yr | C22: 12/17/15 | D22: 2300.7 | E22: 0 | F22: 0 | G22: 2300.7 | H22: 0 | I22: =G22+H22 -> 2300.7 | J22: =D22-I22 -> 0 | K22: 200DB | L22: 5.0
A23: 6 | B23: 3 - Land Improvements - Apt - 27.5yr | C23: 12/17/15 | D23: 8710.9 | E23: 0 | F23: 0 | G23: 2547.28 | H23: 316.76 | I23: =G23+H23 -> 2864.04 | J23: =D23-I23 -> 5846.86 | K23: S/L | L23: 27.5
A24: 7 | B24: 4 - Equipment - Apt - 5yr | C24: 12/17/15 | D24: 4167.44 | E24: 0 | F24: 0 | G24: 4167.44 | H24: 0 | I24: =G24+H24 -> 4167.44 | J24: =D24-I24 -> 0 | K24: 200DB | L24: 5.0
A25: 8 | B25: 4 - Equipment - Apt - 27.5yr | C25: 12/17/15 | D25: 15778.73 | E25: 0 | F25: 0 | G25: 4614.07 | H25: 573.77 | I25: =G25+H25 -> 5187.84 | J25: =D25-I25 -> 10590.89 | K25: S/L | L25: 27.5
B26: Grand Total | D26: =SUM(D18:D25) -> 147893.47 | E26: =SUM(E18:E25) -> 0 | F26: =SUM(F18:F25) -> 0 | G26: =SUM(G18:G25) -> 65111.2 | H26: =SUM(H18:H25) -> 4254.3 | I26: =SUM(I18:I25) -> 69365.5 | J26: =SUM(J18:J25) -> 78527.97
B28: Section 481(a) Adjustment — Regular Tax
B29: Depreciation reported previously | D29: =I14 -> 64826.13
B30: Cost Segregation Corrected Depreciation | D30: =I26 -> 69365.5
B31: Section 481(a) Adjustment — Regular Tax | D31: =D29-D30 -> -4539.37
A33: CALCULATION OF §481(a) ADJUSTMENT — AMT
A34: As Previously Filed — AMT
A35: Asset | B35: Property Description | C35: Date In Service | D35: Cost | E35: Sec 179 Exp | F35: Bonus Amt | G35: AMT Prior Depreciation | H35: AMT Current Depreciation | I35: End Depreciation | J35: Net Book Value | K35: Method | L35: Period
A36: 1 | B36: 1 - Buillding - Apt | C36: 12/17/15 | D36: 116723.12 | E36: 0 | F36: 0 | G36: 34132.24 | H36: 4244.48 | I36: =G36+H36 -> 38376.72 | J36: =D36-I36 -> 78346.4 | K36: S/L | L36: 27.5
A37: 2 | B37: 5 - Building - Apt | C37: 1/14/16 | D37: 212.58 | E37: 0 | F37: 0 | G37: 61.56 | H37: 7.73 | I37: =G37+H37 -> 69.29 | J37: =D37-I37 -> 143.29 | K37: S/L | L37: 27.5
A38: 3 | B38: 3 - Land Improvements - Apt | C38: 12/17/15 | D38: 11011.6 | E38: 0 | F38: 0 | G38: 6449.13 | H38: 649.69 | I38: =G38+H38 -> 7098.82 | J38: =D38-I38 -> 3912.78 | K38: 150DB | L38: 15.0
A39: 4 | B39: 4 - Equipment - Apt | C39: 12/17/15 | D39: 19946.17 | E39: 0 | F39: 0 | G39: 19281.3 | H39: 0 | I39: =G39+H39 -> 19281.3 | J39: =D39-I39 -> 664.87 | K39: 200DB | L39: 5.0
B40: Grand Total | D40: =SUM(D36:D39) -> 147893.47 | E40: =SUM(E36:E39) -> 0 | F40: =SUM(F36:F39) -> 0 | G40: =SUM(G36:G39) -> 59924.23 | H40: =SUM(H36:H39) -> 4901.9 | I40: =SUM(I36:I39) -> 64826.13 | J40: =SUM(J36:J39) -> 83067.34
A42: After Cost Segregation Correction — AMT
A43: Asset | B43: Property Description | C43: Date In Service | D43: Cost | E43: Sec 179 Exp | F43: Bonus Amt | G43: AMT Prior Depreciation | H43: AMT Current Depreciation | I43: End Depreciation | J43: Net Book Value | K43: Method | L43: Period
A44: 1 | B44: 1 - Buillding - Apt - 5yr | C44: 12/17/15 | D44: 24387.48 | E44: 0 | F44: 0 | G44: 24387.48 | H44: 0 | I44: =G44+H44 -> 24387.48 | J44: =D44-I44 -> 0 | K44: 200DB | L44: 5.0
A45: 2 | B45: 1 - Buillding - Apt - 27.5yr | C45: 12/17/15 | D45: 92335.64 | E45: 0 | F45: 0 | G45: 27001.18 | H45: 3357.66 | I45: =G45+H45 -> 30358.84 | J45: =D45-I45 -> 61976.8 | K45: S/L | L45: 27.5
A46: 3 | B46: 5 - Building - Apt - 5yr | C46: 1/14/16 | D46: 44.42 | E46: 0 | F46: 0 | G46: 44.42 | H46: 0 | I46: =G46+H46 -> 44.42 | J46: =D46-I46 -> 0 | K46: 200DB | L46: 5.0
A47: 4 | B47: 5 - Building - Apt - 27.5yr | C47: 1/14/16 | D47: 168.16 | E47: 0 | F47: 0 | G47: 48.63 | H47: 6.11 | I47: =G47+H47 -> 54.74 | J47: =D47-I47 -> 113.42 | K47: S/L | L47: 27.5
A48: 5 | B48: 3 - Land Improvements - Apt - 5yr | C48: 12/17/15 | D48: 2300.7 | E48: 0 | F48: 0 | G48: 2300.7 | H48: 0 | I48: =G48+H48 -> 2300.7 | J48: =D48-I48 -> 0 | K48: 200DB | L48: 5.0
A49: 6 | B49: 3 - Land Improvements - Apt - 27.5yr | C49: 12/17/15 | D49: 8710.9 | E49: 0 | F49: 0 | G49: 2547.28 | H49: 316.76 | I49: =G49+H49 -> 2864.04 | J49: =D49-I49 -> 5846.86 | K49: S/L | L49: 27.5
A50: 7 | B50: 4 - Equipment - Apt - 5yr | C50: 12/17/15 | D50: 4167.44 | E50: 0 | F50: 0 | G50: 4167.44 | H50: 0 | I50: =G50+H50 -> 4167.44 | J50: =D50-I50 -> 0 | K50: 200DB | L50: 5.0
A51: 8 | B51: 4 - Equipment - Apt - 27.5yr | C51: 12/17/15 | D51: 15778.73 | E51: 0 | F51: 0 | G51: 4614.07 | H51: 573.77 | I51: =G51+H51 -> 5187.84 | J51: =D51-I51 -> 10590.89 | K51: S/L | L51: 27.5
B52: Grand Total | D52: =SUM(D44:D51) -> 147893.47 | E52: =SUM(E44:E51) -> 0 | F52: =SUM(F44:F51) -> 0 | G52: =SUM(G44:G51) -> 65111.2 | H52: =SUM(H44:H51) -> 4254.3 | I52: =SUM(I44:I51) -> 69365.5 | J52: =SUM(J44:J51) -> 78527.97
B54: Section 481(a) Adjustment — AMT
B55: Depreciation reported previously | D55: =I40 -> 64826.13
B56: Cost Segregation Corrected Depreciation | D56: =I52 -> 69365.5
B57: Section 481(a) Adjustment — AMT | D57: =D55-D56 -> -4539.37
A59: COST SEGREGATION STUDY — COST SUMMARY
B60: Total Building Cost | D60: =D98 -> 147893.47
B61: Building Components: 5 Year | D61: =F98 -> 30900.04
B62: % of Cost | D62: =F99 -> 0.20893444
B63: Building Structure: 27.5 Year | D63: =H98 -> 116993.43
B64: % of Cost | D64: =H99 -> 0.79106556
A66: COST SEGREGATION STUDY — COST DETAIL
B67: Property Category | D67: Cost | F67: 5 Year | H67: 27.5 Year
B68: Building Components
B69: Cabinets / Millwork | D69: =SUM(F69:H69) -> 4901.61 | F69: 4901.61
B70: Moldings | D70: =SUM(F70:H70) -> 2185.54 | F70: 2185.54
B71: Flooring - Vinyl Plank | D71: =SUM(F71:H71) -> 11385.26 | F71: 11385.26
B72: Window Treatments | D72: =SUM(F72:H72) -> 589.62 | F72: 589.62
B73: Specialty HVAC - Dryer Vents | D73: =SUM(F73:H73) -> 183.29 | F73: 183.29
B74: Building Signage | D74: =SUM(F74:H74) -> 96.76 | F74: 96.76
B75: Specialty Electrical - Appliances | D75: =SUM(F75:H75) -> 2980.97 | F75: 2980.97
B76: Communication / Data | D76: =SUM(F76:H76) -> 994.55 | F76: 994.55
B77: Specialty Plumbing - Kitchen Sinks / Laundry | D77: =SUM(F77:H77) -> 3427.41 | F77: 3427.41
B78: Security / Exterior Lighting | D78: =SUM(F78:H78) -> 428.96 | F78: 428.96
B79: Access Control | D79: =SUM(F79:H79) -> 43.2 | F79: 43.2
B80: Appliances | D80: =SUM(F80:H80) -> 3682.87 | F80: 3682.87
B81: Building Structure
B82: Roofing Systems | D82: =SUM(F82:H82) -> 8561.68 | H82: 8561.68
B83: Foundations | D83: =SUM(F83:H83) -> 16225.62 | H83: 16225.62
B84: HVAC | D84: =SUM(F84:H84) -> 10992.55 | H84: 10992.55
B85: Electrical | D85: =SUM(F85:H85) -> 12099.12 | H85: 12099.12
B86: Plumbing | D86: =SUM(F86:H86) -> 9715.1 | H86: 9715.1
B87: Fire Protection & Alarm | D87: =SUM(F87:H87) -> 548.48 | H87: 548.48
B88: Exterior Façade / Building Skin | D88: =SUM(F88:H88) -> 12559.71 | H88: 12559.71
B89: Doors & Frames | D89: =SUM(F89:H89) -> 5680.09 | H89: 5680.09
B90: Windows | D90: =SUM(F90:H90) -> 2911.57 | H90: 2911.57
B91: Ceiling Systems | D91: =SUM(F91:H91) -> 5070.55 | H91: 5070.55
B92: Interior Framing / Partitions | D92: =SUM(F92:H92) -> 9837.36 | H92: 9837.36
B93: Painting | D93: =SUM(F93:H93) -> 4408.6 | H93: 4408.6
... B97: Cabinets / Millwork - Restrooms | D97: =SUM(F97:H97) -> 1709.81 | H97: 1709.81
B98: Total Building Cost | D98: =SUM(D68:D97) -> 147893.47 | F98: =SUM(F68:F97) -> 30900.04 | H98: =SUM(H68:H97) -> 116993.43
B99: % of Cost | F99: =F98/D98 -> 0.20893444 | H99: =H98/D98 -> 0.79106556
A101: ASSET ALLOCATION (per After Cost Segregation schedule)
B102: Asset (as reclassified) | D102: Cost | F102: 5 Year | H102: 27.5 Year
B103: ='Building 5'!B18 -> 1 - Buillding - Apt - 5yr | D103: =SUM(F103:H103) -> 24387.48 | F103: ='Building 5'!D18 -> 24387.48
B104: ='Building 5'!B19 -> 1 - Buillding - Apt - 27.5yr | D104: =SUM(F104:H104) -> 92335.64 | H104: ='Building 5'!D19 -> 92335.64
B105: ='Building 5'!B20 -> 5 - Building - Apt - 5yr | D105: =SUM(F105:H105) -> 44.42 | F105: ='Building 5'!D20 -> 44.42
B106: ='Building 5'!B21 -> 5 - Building - Apt - 27.5yr | D106: =SUM(F106:H106) -> 168.16 | H106: ='Building 5'!D21 -> 168.16
B107: ='Building 5'!B22 -> 3 - Land Improvements - Apt - 5yr | D107: =SUM(F107:H107) -> 2300.7 | F107: ='Building 5'!D22 -> 2300.7
B108: ='Building 5'!B23 -> 3 - Land Improvements - Apt - 27.5yr | D108: =SUM(F108:H108) -> 8710.9 | H108: ='Building 5'!D23 -> 8710.9
B109: ='Building 5'!B24 -> 4 - Equipment - Apt - 5yr | D109: =SUM(F109:H109) -> 4167.44 | F109: ='Building 5'!D24 -> 4167.44
B110: ='Building 5'!B25 -> 4 - Equipment - Apt - 27.5yr | D110: =SUM(F110:H110) -> 15778.73 | H110: ='Building 5'!D25 -> 15778.73
B111: Total Allocation | D111: =SUM(D103:D110) -> 147893.47 | F111: =SUM(F103:F110) -> 30900.04 | H111: =SUM(H103:H110) -> 116993.43
B112: Check: Allocation vs. Cost Detail (should be zero) | D112: =D111-D98 -> 0

Sheet Building 6
A1: Grace Townhomes Housing, LLC
A2: Grace Townhomes — 1212 Grace Cir, Ennis, TX 75119
A3: EIN: 47-5360069 · FYE: December 31, 2024 · Year of Change: 1/1/2024
A4: Building 6 — Attachment to Form 3115 (DCN #7, Rev. Proc. 2024-23 §6.01)
A5: Source: CSSI Report #107752-11, "#107752-11_Grace Townhomes - 3115 - Combined R2.pdf"
A7: CALCULATION OF §481(a) ADJUSTMENT — REGULAR TAX
A8: As Previously Filed
A9: Asset | B9: Property Description | C9: Date In Service | D9: Cost | E9: Sec 179 Exp | F9: Bonus Amt | G9: Tax Prior Depreciation | H9: Tax Current Depreciation | I9: End Depreciation | J9: Net Book Value | K9: Method | L9: Period
A10: 1 | B10: 1 - Buillding - Apt | C10: 12/17/15 | D10: 116723.12 | E10: 0 | F10: 0 | G10: 34132.24 | H10: 4244.48 | I10: =G10+H10 -> 38376.72 | J10: =D10-I10 -> 78346.4 | K10: S/L | L10: 27.5
A11: 2 | B11: 5 - Building - Apt | C11: 1/14/16 | D11: 212.58 | E11: 0 | F11: 0 | G11: 61.56 | H11: 7.73 | I11: =G11+H11 -> 69.29 | J11: =D11-I11 -> 143.29 | K11: S/L | L11: 27.5
A12: 3 | B12: 3 - Land Improvements - Apt | C12: 12/17/15 | D12: 11011.6 | E12: 0 | F12: 0 | G12: 6449.13 | H12: 649.69 | I12: =G12+H12 -> 7098.82 | J12: =D12-I12 -> 3912.78 | K12: 150DB | L12: 15.0
A13: 4 | B13: 4 - Equipment - Apt | C13: 12/17/15 | D13: 19946.17 | E13: 0 | F13: 0 | G13: 19281.3 | H13: 0 | I13: =G13+H13 -> 19281.3 | J13: =D13-I13 -> 664.87 | K13: 200DB | L13: 5.0
B14: Grand Total | D14: =SUM(D10:D13) -> 147893.47 | E14: =SUM(E10:E13) -> 0 | F14: =SUM(F10:F13) -> 0 | G14: =SUM(G10:G13) -> 59924.23 | H14: =SUM(H10:H13) -> 4901.9 | I14: =SUM(I10:I13) -> 64826.13 | J14: =SUM(J10:J13) -> 83067.34
A16: After Cost Segregation Correction
A17: Asset | B17: Property Description | C17: Date In Service | D17: Cost | E17: Sec 179 Exp | F17: Bonus Amt | G17: Tax Prior Depreciation | H17: Tax Current Depreciation | I17: End Depreciation | J17: Net Book Value | K17: Method | L17: Period
A18: 1 | B18: 1 - Buillding - Apt - 5yr | C18: 12/17/15 | D18: 24387.48 | E18: 0 | F18: 0 | G18: 24387.48 | H18: 0 | I18: =G18+H18 -> 24387.48 | J18: =D18-I18 -> 0 | K18: 200DB | L18: 5.0
A19: 2 | B19: 1 - Buillding - Apt - 27.5yr | C19: 12/17/15 | D19: 92335.64 | E19: 0 | F19: 0 | G19: 27001.18 | H19: 3357.66 | I19: =G19+H19 -> 30358.84 | J19: =D19-I19 -> 61976.8 | K19: S/L | L19: 27.5
A20: 3 | B20: 5 - Building - Apt - 5yr | C20: 1/14/16 | D20: 44.42 | E20: 0 | F20: 0 | G20: 44.42 | H20: 0 | I20: =G20+H20 -> 44.42 | J20: =D20-I20 -> 0 | K20: 200DB | L20: 5.0
A21: 4 | B21: 5 - Building - Apt - 27.5yr | C21: 1/14/16 | D21: 168.16 | E21: 0 | F21: 0 | G21: 48.63 | H21: 6.11 | I21: =G21+H21 -> 54.74 | J21: =D21-I21 -> 113.42 | K21: S/L | L21: 27.5
A22: 5 | B22: 3 - Land Improvements - Apt - 5yr | C22: 12/17/15 | D22: 2300.7 | E22: 0 | F22: 0 | G22: 2300.7 | H22: 0 | I22: =G22+H22 -> 2300.7 | J22: =D22-I22 -> 0 | K22: 200DB | L22: 5.0
A23: 6 | B23: 3 - Land Improvements - Apt - 27.5yr | C23: 12/17/15 | D23: 8710.9 | E23: 0 | F23: 0 | G23: 2547.28 | H23: 316.76 | I23: =G23+H23 -> 2864.04 | J23: =D23-I23 -> 5846.86 | K23: S/L | L23: 27.5
A24: 7 | B24: 4 - Equipment - Apt - 5yr | C24: 12/17/15 | D24: 4167.44 | E24: 0 | F24: 0 | G24: 4167.44 | H24: 0 | I24: =G24+H24 -> 4167.44 | J24: =D24-I24 -> 0 | K24: 200DB | L24: 5.0
A25: 8 | B25: 4 - Equipment - Apt - 27.5yr | C25: 12/17/15 | D25: 15778.73 | E25: 0 | F25: 0 | G25: 4614.07 | H25: 573.77 | I25: =G25+H25 -> 5187.84 | J25: =D25-I25 -> 10590.89 | K25: S/L | L25: 27.5
B26: Grand Total | D26: =SUM(D18:D25) -> 147893.47 | E26: =SUM(E18:E25) -> 0 | F26: =SUM(F18:F25) -> 0 | G26: =SUM(G18:G25) -> 65111.2 | H26: =SUM(H18:H25) -> 4254.3 | I26: =SUM(I18:I25) -> 69365.5 | J26: =SUM(J18:J25) -> 78527.97
B28: Section 481(a) Adjustment — Regular Tax
B29: Depreciation reported previously | D29: =I14 -> 64826.13
B30: Cost Segregation Corrected Depreciation | D30: =I26 -> 69365.5
B31: Section 481(a) Adjustment — Regular Tax | D31: =D29-D30 -> -4539.37
A33: CALCULATION OF §481(a) ADJUSTMENT — AMT
A34: As Previously Filed — AMT
A35: Asset | B35: Property Description | C35: Date In Service | D35: Cost | E35: Sec 179 Exp | F35: Bonus Amt | G35: AMT Prior Depreciation | H35: AMT Current Depreciation | I35: End Depreciation | J35: Net Book Value | K35: Method | L35: Period
A36: 1 | B36: 1 - Buillding - Apt | C36: 12/17/15 | D36: 116723.12 | E36: 0 | F36: 0 | G36: 34132.24 | H36: 4244.48 | I36: =G36+H36 -> 38376.72 | J36: =D36-I36 -> 78346.4 | K36: S/L | L36: 27.5
A37: 2 | B37: 5 - Building - Apt | C37: 1/14/16 | D37: 212.58 | E37: 0 | F37: 0 | G37: 61.56 | H37: 7.73 | I37: =G37+H37 -> 69.29 | J37: =D37-I37 -> 143.29 | K37: S/L | L37: 27.5
A38: 3 | B38: 3 - Land Improvements - Apt | C38: 12/17/15 | D38: 11011.6 | E38: 0 | F38: 0 | G38: 6449.13 | H38: 649.69 | I38: =G38+H38 -> 7098.82 | J38: =D38-I38 -> 3912.78 | K38: 150DB | L38: 15.0
A39: 4 | B39: 4 - Equipment - Apt | C39: 12/17/15 | D39: 19946.17 | E39: 0 | F39: 0 | G39: 19281.3 | H39: 0 | I39: =G39+H39 -> 19281.3 | J39: =D39-I39 -> 664.87 | K39: 200DB | L39: 5.0
B40: Grand Total | D40: =SUM(D36:D39) -> 147893.47 | E40: =SUM(E36:E39) -> 0 | F40: =SUM(F36:F39) -> 0 | G40: =SUM(G36:G39) -> 59924.23 | H40: =SUM(H36:H39) -> 4901.9 | I40: =SUM(I36:I39) -> 64826.13 | J40: =SUM(J36:J39) -> 83067.34
A42: After Cost Segregation Correction — AMT
A43: Asset | B43: Property Description | C43: Date In Service | D43: Cost | E43: Sec 179 Exp | F43: Bonus Amt | G43: AMT Prior Depreciation | H43: AMT Current Depreciation | I43: End Depreciation | J43: Net Book Value | K43: Method | L43: Period
A44: 1 | B44: 1 - Buillding - Apt - 5yr | C44: 12/17/15 | D44: 24387.48 | E44: 0 | F44: 0 | G44: 24387.48 | H44: 0 | I44: =G44+H44 -> 24387.48 | J44: =D44-I44 -> 0 | K44: 200DB | L44: 5.0
A45: 2 | B45: 1 - Buillding - Apt - 27.5yr | C45: 12/17/15 | D45: 92335.64 | E45: 0 | F45: 0 | G45: 27001.18 | H45: 3357.66 | I45: =G45+H45 -> 30358.84 | J45: =D45-I45 -> 61976.8 | K45: S/L | L45: 27.5
A46: 3 | B46: 5 - Building - Apt - 5yr | C46: 1/14/16 | D46: 44.42 | E46: 0 | F46: 0 | G46: 44.42 | H46: 0 | I46: =G46+H46 -> 44.42 | J46: =D46-I46 -> 0 | K46: 200DB | L46: 5.0
A47: 4 | B47: 5 - Building - Apt - 27.5yr | C47: 1/14/16 | D47: 168.16 | E47: 0 | F47: 0 | G47: 48.63 | H47: 6.11 | I47: =G47+H47 -> 54.74 | J47: =D47-I47 -> 113.42 | K47: S/L | L47: 27.5
A48: 5 | B48: 3 - Land Improvements - Apt - 5yr | C48: 12/17/15 | D48: 2300.7 | E48: 0 | F48: 0 | G48: 2300.7 | H48: 0 | I48: =G48+H48 -> 2300.7 | J48: =D48-I48 -> 0 | K48: 200DB | L48: 5.0
A49: 6 | B49: 3 - Land Improvements - Apt - 27.5yr | C49: 12/17/15 | D49: 8710.9 | E49: 0 | F49: 0 | G49: 2547.28 | H49: 316.76 | I49: =G49+H49 -> 2864.04 | J49: =D49-I49 -> 5846.86 | K49: S/L | L49: 27.5
A50: 7 | B50: 4 - Equipment - Apt - 5yr | C50: 12/17/15 | D50: 4167.44 | E50: 0 | F50: 0 | G50: 4167.44 | H50: 0 | I50: =G50+H50 -> 4167.44 | J50: =D50-I50 -> 0 | K50: 200DB | L50: 5.0
A51: 8 | B51: 4 - Equipment - Apt - 27.5yr | C51: 12/17/15 | D51: 15778.73 | E51: 0 | F51: 0 | G51: 4614.07 | H51: 573.77 | I51: =G51+H51 -> 5187.84 | J51: =D51-I51 -> 10590.89 | K51: S/L | L51: 27.5
B52: Grand Total | D52: =SUM(D44:D51) -> 147893.47 | E52: =SUM(E44:E51) -> 0 | F52: =SUM(F44:F51) -> 0 | G52: =SUM(G44:G51) -> 65111.2 | H52: =SUM(H44:H51) -> 4254.3 | I52: =SUM(I44:I51) -> 69365.5 | J52: =SUM(J44:J51) -> 78527.97
B54: Section 481(a) Adjustment — AMT
B55: Depreciation reported previously | D55: =I40 -> 64826.13
B56: Cost Segregation Corrected Depreciation | D56: =I52 -> 69365.5
B57: Section 481(a) Adjustment — AMT | D57: =D55-D56 -> -4539.37
A59: COST SEGREGATION STUDY — COST SUMMARY
B60: Total Building Cost | D60: =D98 -> 147893.47
B61: Building Components: 5 Year | D61: =F98 -> 30900.04
B62: % of Cost | D62: =F99 -> 0.20893444
B63: Building Structure: 27.5 Year | D63: =H98 -> 116993.43
B64: % of Cost | D64: =H99 -> 0.79106556
A66: COST SEGREGATION STUDY — COST DETAIL
B67: Property Category | D67: Cost | F67: 5 Year | H67: 27.5 Year
B68: Building Components
B69: Cabinets / Millwork | D69: =SUM(F69:H69) -> 4901.61 | F69: 4901.61
B70: Moldings | D70: =SUM(F70:H70) -> 2185.54 | F70: 2185.54
B71: Flooring - Vinyl Plank | D71: =SUM(F71:H71) -> 11385.26 | F71: 11385.26
B72: Window Treatments | D72: =SUM(F72:H72) -> 589.62 | F72: 589.62
B73: Specialty HVAC - Dryer Vents | D73: =SUM(F73:H73) -> 183.29 | F73: 183.29
B74: Building Signage | D74: =SUM(F74:H74) -> 96.76 | F74: 96.76
B75: Specialty Electrical - Appliances | D75: =SUM(F75:H75) -> 2980.97 | F75: 2980.97
B76: Communication / Data | D76: =SUM(F76:H76) -> 994.55 | F76: 994.55
B77: Specialty Plumbing - Kitchen Sinks / Laundry | D77: =SUM(F77:H77) -> 3427.41 | F77: 3427.41
B78: Security / Exterior Lighting | D78: =SUM(F78:H78) -> 428.96 | F78: 428.96
B79: Access Control | D79: =SUM(F79:H79) -> 43.2 | F79: 43.2
B80: Appliances | D80: =SUM(F80:H80) -> 3682.87 | F80: 3682.87
B81: Building Structure
B82: Roofing Systems | D82: =SUM(F82:H82) -> 8561.68 | H82: 8561.68
B83: Foundations | D83: =SUM(F83:H83) -> 16225.62 | H83: 16225.62
B84: HVAC | D84: =SUM(F84:H84) -> 10992.55 | H84: 10992.55
B85: Electrical | D85: =SUM(F85:H85) -> 12099.12 | H85: 12099.12
B86: Plumbing | D86: =SUM(F86:H86) -> 9715.1 | H86: 9715.1
B87: Fire Protection & Alarm | D87: =SUM(F87:H87) -> 548.48 | H87: 548.48
B88: Exterior Façade / Building Skin | D88: =SUM(F88:H88) -> 12559.71 | H88: 12559.71
B89: Doors & Frames | D89: =SUM(F89:H89) -> 5680.09 | H89: 5680.09
B90: Windows | D90: =SUM(F90:H90) -> 2911.57 | H90: 2911.57
B91: Ceiling Systems | D91: =SUM(F91:H91) -> 5070.55 | H91: 5070.55
B92: Interior Framing / Partitions | D92: =SUM(F92:H92) -> 9837.36 | H92: 9837.36
B93: Painting | D93: =SUM(F93:H93) -> 4408.6 | H93: 4408.6
... B97: Cabinets / Millwork - Restrooms | D97: =SUM(F97:H97) -> 1709.81 | H97: 1709.81
B98: Total Building Cost | D98: =SUM(D68:D97) -> 147893.47 | F98: =SUM(F68:F97) -> 30900.04 | H98: =SUM(H68:H97) -> 116993.43
B99: % of Cost | F99: =F98/D98 -> 0.20893444 | H99: =H98/D98 -> 0.79106556
A101: ASSET ALLOCATION (per After Cost Segregation schedule)
B102: Asset (as reclassified) | D102: Cost | F102: 5 Year | H102: 27.5 Year
B103: ='Building 6'!B18 -> 1 - Buillding - Apt - 5yr | D103: =SUM(F103:H103) -> 24387.48 | F103: ='Building 6'!D18 -> 24387.48
B104: ='Building 6'!B19 -> 1 - Buillding - Apt - 27.5yr | D104: =SUM(F104:H104) -> 92335.64 | H104: ='Building 6'!D19 -> 92335.64
B105: ='Building 6'!B20 -> 5 - Building - Apt - 5yr | D105: =SUM(F105:H105) -> 44.42 | F105: ='Building 6'!D20 -> 44.42
B106: ='Building 6'!B21 -> 5 - Building - Apt - 27.5yr | D106: =SUM(F106:H106) -> 168.16 | H106: ='Building 6'!D21 -> 168.16
B107: ='Building 6'!B22 -> 3 - Land Improvements - Apt - 5yr | D107: =SUM(F107:H107) -> 2300.7 | F107: ='Building 6'!D22 -> 2300.7
B108: ='Building 6'!B23 -> 3 - Land Improvements - Apt - 27.5yr | D108: =SUM(F108:H108) -> 8710.9 | H108: ='Building 6'!D23 -> 8710.9
B109: ='Building 6'!B24 -> 4 - Equipment - Apt - 5yr | D109: =SUM(F109:H109) -> 4167.44 | F109: ='Building 6'!D24 -> 4167.44
B110: ='Building 6'!B25 -> 4 - Equipment - Apt - 27.5yr | D110: =SUM(F110:H110) -> 15778.73 | H110: ='Building 6'!D25 -> 15778.73
B111: Total Allocation | D111: =SUM(D103:D110) -> 147893.47 | F111: =SUM(F103:F110) -> 30900.04 | H111: =SUM(H103:H110) -> 116993.43
B112: Check: Allocation vs. Cost Detail (should be zero) | D112: =D111-D98 -> 0

Sheet Building 7
A1: Grace Townhomes Housing, LLC
A2: Grace Townhomes — 1212 Grace Cir, Ennis, TX 75119
A3: EIN: 47-5360069 · FYE: December 31, 2024 · Year of Change: 1/1/2024
A4: Building 7 — Attachment to Form 3115 (DCN #7, Rev. Proc. 2024-23 §6.01)
A5: Source: CSSI Report #107752-11, "#107752-11_Grace Townhomes - 3115 - Combined R2.pdf"
A7: CALCULATION OF §481(a) ADJUSTMENT — REGULAR TAX
A8: As Previously Filed
A9: Asset | B9: Property Description | C9: Date In Service | D9: Cost | E9: Sec 179 Exp | F9: Bonus Amt | G9: Tax Prior Depreciation | H9: Tax Current Depreciation | I9: End Depreciation | J9: Net Book Value | K9: Method | L9: Period
A10: 1 | B10: 1 - Buillding - Apt | C10: 12/17/15 | D10: 116723.12 | E10: 0 | F10: 0 | G10: 34132.24 | H10: 4244.48 | I10: =G10+H10 -> 38376.72 | J10: =D10-I10 -> 78346.4 | K10: S/L | L10: 27.5
A11: 2 | B11: 5 - Building - Apt | C11: 1/14/16 | D11: 212.58 | E11: 0 | F11: 0 | G11: 61.56 | H11: 7.73 | I11: =G11+H11 -> 69.29 | J11: =D11-I11 -> 143.29 | K11: S/L | L11: 27.5
A12: 3 | B12: 3 - Land Improvements - Apt | C12: 12/17/15 | D12: 11011.6 | E12: 0 | F12: 0 | G12: 6449.13 | H12: 649.69 | I12: =G12+H12 -> 7098.82 | J12: =D12-I12 -> 3912.78 | K12: 150DB | L12: 15.0
A13: 4 | B13: 4 - Equipment - Apt | C13: 12/17/15 | D13: 19946.17 | E13: 0 | F13: 0 | G13: 19281.3 | H13: 0 | I13: =G13+H13 -> 19281.3 | J13: =D13-I13 -> 664.87 | K13: 200DB | L13: 5.0
B14: Grand Total | D14: =SUM(D10:D13) -> 147893.47 | E14: =SUM(E10:E13) -> 0 | F14: =SUM(F10:F13) -> 0 | G14: =SUM(G10:G13) -> 59924.23 | H14: =SUM(H10:H13) -> 4901.9 | I14: =SUM(I10:I13) -> 64826.13 | J14: =SUM(J10:J13) -> 83067.34
A16: After Cost Segregation Correction
A17: Asset | B17: Property Description | C17: Date In Service | D17: Cost | E17: Sec 179 Exp | F17: Bonus Amt | G17: Tax Prior Depreciation | H17: Tax Current Depreciation | I17: End Depreciation | J17: Net Book Value | K17: Method | L17: Period
A18: 1 | B18: 1 - Buillding - Apt - 5yr | C18: 12/17/15 | D18: 24387.48 | E18: 0 | F18: 0 | G18: 24387.48 | H18: 0 | I18: =G18+H18 -> 24387.48 | J18: =D18-I18 -> 0 | K18: 200DB | L18: 5.0
A19: 2 | B19: 1 - Buillding - Apt - 27.5yr | C19: 12/17/15 | D19: 92335.64 | E19: 0 | F19: 0 | G19: 27001.18 | H19: 3357.66 | I19: =G19+H19 -> 30358.84 | J19: =D19-I19 -> 61976.8 | K19: S/L | L19: 27.5
A20: 3 | B20: 5 - Building - Apt - 5yr | C20: 1/14/16 | D20: 44.42 | E20: 0 | F20: 0 | G20: 44.42 | H20: 0 | I20: =G20+H20 -> 44.42 | J20: =D20-I20 -> 0 | K20: 200DB | L20: 5.0
A21: 4 | B21: 5 - Building - Apt - 27.5yr | C21: 1/14/16 | D21: 168.16 | E21: 0 | F21: 0 | G21: 48.63 | H21: 6.11 | I21: =G21+H21 -> 54.74 | J21: =D21-I21 -> 113.42 | K21: S/L | L21: 27.5
A22: 5 | B22: 3 - Land Improvements - Apt - 5yr | C22: 12/17/15 | D22: 2300.7 | E22: 0 | F22: 0 | G22: 2300.7 | H22: 0 | I22: =G22+H22 -> 2300.7 | J22: =D22-I22 -> 0 | K22: 200DB | L22: 5.0
A23: 6 | B23: 3 - Land Improvements - Apt - 27.5yr | C23: 12/17/15 | D23: 8710.9 | E23: 0 | F23: 0 | G23: 2547.28 | H23: 316.76 | I23: =G23+H23 -> 2864.04 | J23: =D23-I23 -> 5846.86 | K23: S/L | L23: 27.5
A24: 7 | B24: 4 - Equipment - Apt - 5yr | C24: 12/17/15 | D24: 4167.44 | E24: 0 | F24: 0 | G24: 4167.44 | H24: 0 | I24: =G24+H24 -> 4167.44 | J24: =D24-I24 -> 0 | K24: 200DB | L24: 5.0
A25: 8 | B25: 4 - Equipment - Apt - 27.5yr | C25: 12/17/15 | D25: 15778.73 | E25: 0 | F25: 0 | G25: 4614.07 | H25: 573.77 | I25: =G25+H25 -> 5187.84 | J25: =D25-I25 -> 10590.89 | K25: S/L | L25: 27.5
B26: Grand Total | D26: =SUM(D18:D25) -> 147893.47 | E26: =SUM(E18:E25) -> 0 | F26: =SUM(F18:F25) -> 0 | G26: =SUM(G18:G25) -> 65111.2 | H26: =SUM(H18:H25) -> 4254.3 | I26: =SUM(I18:I25) -> 69365.5 | J26: =SUM(J18:J25) -> 78527.97
B28: Section 481(a) Adjustment — Regular Tax
B29: Depreciation reported previously | D29: =I14 -> 64826.13
B30: Cost Segregation Corrected Depreciation | D30: =I26 -> 69365.5
B31: Section 481(a) Adjustment — Regular Tax | D31: =D29-D30 -> -4539.37
A33: CALCULATION OF §481(a) ADJUSTMENT — AMT
A34: As Previously Filed — AMT
A35: Asset | B35: Property Description | C35: Date In Service | D35: Cost | E35: Sec 179 Exp | F35: Bonus Amt | G35: AMT Prior Depreciation | H35: AMT Current Depreciation | I35: End Depreciation | J35: Net Book Value | K35: Method | L35: Period
A36: 1 | B36: 1 - Buillding - Apt | C36: 12/17/15 | D36: 116723.12 | E36: 0 | F36: 0 | G36: 34132.24 | H36: 4244.48 | I36: =G36+H36 -> 38376.72 | J36: =D36-I36 -> 78346.4 | K36: S/L | L36: 27.5
A37: 2 | B37: 5 - Building - Apt | C37: 1/14/16 | D37: 212.58 | E37: 0 | F37: 0 | G37: 61.56 | H37: 7.73 | I37: =G37+H37 -> 69.29 | J37: =D37-I37 -> 143.29 | K37: S/L | L37: 27.5
A38: 3 | B38: 3 - Land Improvements - Apt | C38: 12/17/15 | D38: 11011.6 | E38: 0 | F38: 0 | G38: 6449.13 | H38: 649.69 | I38: =G38+H38 -> 7098.82 | J38: =D38-I38 -> 3912.78 | K38: 150DB | L38: 15.0
A39: 4 | B39: 4 - Equipment - Apt | C39: 12/17/15 | D39: 19946.17 | E39: 0 | F39: 0 | G39: 19281.3 | H39: 0 | I39: =G39+H39 -> 19281.3 | J39: =D39-I39 -> 664.87 | K39: 200DB | L39: 5.0
B40: Grand Total | D40: =SUM(D36:D39) -> 147893.47 | E40: =SUM(E36:E39) -> 0 | F40: =SUM(F36:F39) -> 0 | G40: =SUM(G36:G39) -> 59924.23 | H40: =SUM(H36:H39) -> 4901.9 | I40: =SUM(I36:I39) -> 64826.13 | J40: =SUM(J36:J39) -> 83067.34
A42: After Cost Segregation Correction — AMT
A43: Asset | B43: Property Description | C43: Date In Service | D43: Cost | E43: Sec 179 Exp | F43: Bonus Amt | G43: AMT Prior Depreciation | H43: AMT Current Depreciation | I43: End Depreciation | J43: Net Book Value | K43: Method | L43: Period
A44: 1 | B44: 1 - Buillding - Apt - 5yr | C44: 12/17/15 | D44: 24387.48 | E44: 0 | F44: 0 | G44: 24387.48 | H44: 0 | I44: =G44+H44 -> 24387.48 | J44: =D44-I44 -> 0 | K44: 200DB | L44: 5.0
A45: 2 | B45: 1 - Buillding - Apt - 27.5yr | C45: 12/17/15 | D45: 92335.64 | E45: 0 | F45: 0 | G45: 27001.18 | H45: 3357.66 | I45: =G45+H45 -> 30358.84 | J45: =D45-I45 -> 61976.8 | K45: S/L | L45: 27.5
A46: 3 | B46: 5 - Building - Apt - 5yr | C46: 1/14/16 | D46: 44.42 | E46: 0 | F46: 0 | G46: 44.42 | H46: 0 | I46: =G46+H46 -> 44.42 | J46: =D46-I46 -> 0 | K46: 200DB | L46: 5.0
A47: 4 | B47: 5 - Building - Apt - 27.5yr | C47: 1/14/16 | D47: 168.16 | E47: 0 | F47: 0 | G47: 48.63 | H47: 6.11 | I47: =G47+H47 -> 54.74 | J47: =D47-I47 -> 113.42 | K47: S/L | L47: 27.5
A48: 5 | B48: 3 - Land Improvements - Apt - 5yr | C48: 12/17/15 | D48: 2300.7 | E48: 0 | F48: 0 | G48: 2300.7 | H48: 0 | I48: =G48+H48 -> 2300.7 | J48: =D48-I48 -> 0 | K48: 200DB | L48: 5.0
A49: 6 | B49: 3 - Land Improvements - Apt - 27.5yr | C49: 12/17/15 | D49: 8710.9 | E49: 0 | F49: 0 | G49: 2547.28 | H49: 316.76 | I49: =G49+H49 -> 2864.04 | J49: =D49-I49 -> 5846.86 | K49: S/L | L49: 27.5
A50: 7 | B50: 4 - Equipment - Apt - 5yr | C50: 12/17/15 | D50: 4167.44 | E50: 0 | F50: 0 | G50: 4167.44 | H50: 0 | I50: =G50+H50 -> 4167.44 | J50: =D50-I50 -> 0 | K50: 200DB | L50: 5.0
A51: 8 | B51: 4 - Equipment - Apt - 27.5yr | C51: 12/17/15 | D51: 15778.73 | E51: 0 | F51: 0 | G51: 4614.07 | H51: 573.77 | I51: =G51+H51 -> 5187.84 | J51: =D51-I51 -> 10590.89 | K51: S/L | L51: 27.5
B52: Grand Total | D52: =SUM(D44:D51) -> 147893.47 | E52: =SUM(E44:E51) -> 0 | F52: =SUM(F44:F51) -> 0 | G52: =SUM(G44:G51) -> 65111.2 | H52: =SUM(H44:H51) -> 4254.3 | I52: =SUM(I44:I51) -> 69365.5 | J52: =SUM(J44:J51) -> 78527.97
B54: Section 481(a) Adjustment — AMT
B55: Depreciation reported previously | D55: =I40 -> 64826.13
B56: Cost Segregation Corrected Depreciation | D56: =I52 -> 69365.5
B57: Section 481(a) Adjustment — AMT | D57: =D55-D56 -> -4539.37
A59: COST SEGREGATION STUDY — COST SUMMARY
B60: Total Building Cost | D60: =D98 -> 147893.47
B61: Building Components: 5 Year | D61: =F98 -> 30900.04
B62: % of Cost | D62: =F99 -> 0.20893444
B63: Building Structure: 27.5 Year | D63: =H98 -> 116993.43
B64: % of Cost | D64: =H99 -> 0.79106556
A66: COST SEGREGATION STUDY — COST DETAIL
B67: Property Category | D67: Cost | F67: 5 Year | H67: 27.5 Year
B68: Building Components
B69: Cabinets / Millwork | D69: =SUM(F69:H69) -> 4901.61 | F69: 4901.61
B70: Moldings | D70: =SUM(F70:H70) -> 2185.54 | F70: 2185.54
B71: Flooring - Vinyl Plank | D71: =SUM(F71:H71) -> 11385.26 | F71: 11385.26
B72: Window Treatments | D72: =SUM(F72:H72) -> 589.62 | F72: 589.62
B73: Specialty HVAC - Dryer Vents | D73: =SUM(F73:H73) -> 183.29 | F73: 183.29
B74: Building Signage | D74: =SUM(F74:H74) -> 96.76 | F74: 96.76
B75: Specialty Electrical - Appliances | D75: =SUM(F75:H75) -> 2980.97 | F75: 2980.97
B76: Communication / Data | D76: =SUM(F76:H76) -> 994.55 | F76: 994.55
B77: Specialty Plumbing - Kitchen Sinks / Laundry | D77: =SUM(F77:H77) -> 3427.41 | F77: 3427.41
B78: Security / Exterior Lighting | D78: =SUM(F78:H78) -> 428.96 | F78: 428.96
B79: Access Control | D79: =SUM(F79:H79) -> 43.2 | F79: 43.2
B80: Appliances | D80: =SUM(F80:H80) -> 3682.87 | F80: 3682.87
B81: Building Structure
B82: Roofing Systems | D82: =SUM(F82:H82) -> 8561.68 | H82: 8561.68
B83: Foundations | D83: =SUM(F83:H83) -> 16225.62 | H83: 16225.62
B84: HVAC | D84: =SUM(F84:H84) -> 10992.55 | H84: 10992.55
B85: Electrical | D85: =SUM(F85:H85) -> 12099.12 | H85: 12099.12
B86: Plumbing | D86: =SUM(F86:H86) -> 9715.1 | H86: 9715.1
B87: Fire Protection & Alarm | D87: =SUM(F87:H87) -> 548.48 | H87: 548.48
B88: Exterior Façade / Building Skin | D88: =SUM(F88:H88) -> 12559.71 | H88: 12559.71
B89: Doors & Frames | D89: =SUM(F89:H89) -> 5680.09 | H89: 5680.09
B90: Windows | D90: =SUM(F90:H90) -> 2911.57 | H90: 2911.57
B91: Ceiling Systems | D91: =SUM(F91:H91) -> 5070.55 | H91: 5070.55
B92: Interior Framing / Partitions | D92: =SUM(F92:H92) -> 9837.36 | H92: 9837.36
B93: Painting | D93: =SUM(F93:H93) -> 4408.6 | H93: 4408.6
... B97: Cabinets / Millwork - Restrooms | D97: =SUM(F97:H97) -> 1709.81 | H97: 1709.81
B98: Total Building Cost | D98: =SUM(D68:D97) -> 147893.47 | F98: =SUM(F68:F97) -> 30900.04 | H98: =SUM(H68:H97) -> 116993.43
B99: % of Cost | F99: =F98/D98 -> 0.20893444 | H99: =H98/D98 -> 0.79106556
A101: ASSET ALLOCATION (per After Cost Segregation schedule)
B102: Asset (as reclassified) | D102: Cost | F102: 5 Year | H102: 27.5 Year
B103: ='Building 7'!B18 -> 1 - Buillding - Apt - 5yr | D103: =SUM(F103:H103) -> 24387.48 | F103: ='Building 7'!D18 -> 24387.48
B104: ='Building 7'!B19 -> 1 - Buillding - Apt - 27.5yr | D104: =SUM(F104:H104) -> 92335.64 | H104: ='Building 7'!D19 -> 92335.64
B105: ='Building 7'!B20 -> 5 - Building - Apt - 5yr | D105: =SUM(F105:H105) -> 44.42 | F105: ='Building 7'!D20 -> 44.42
B106: ='Building 7'!B21 -> 5 - Building - Apt - 27.5yr | D106: =SUM(F106:H106) -> 168.16 | H106: ='Building 7'!D21 -> 168.16
B107: ='Building 7'!B22 -> 3 - Land Improvements - Apt - 5yr | D107: =SUM(F107:H107) -> 2300.7 | F107: ='Building 7'!D22 -> 2300.7
B108: ='Building 7'!B23 -> 3 - Land Improvements - Apt - 27.5yr | D108: =SUM(F108:H108) -> 8710.9 | H108: ='Building 7'!D23 -> 8710.9
B109: ='Building 7'!B24 -> 4 - Equipment - Apt - 5yr | D109: =SUM(F109:H109) -> 4167.44 | F109: ='Building 7'!D24 -> 4167.44
B110: ='Building 7'!B25 -> 4 - Equipment - Apt - 27.5yr | D110: =SUM(F110:H110) -> 15778.73 | H110: ='Building 7'!D25 -> 15778.73
B111: Total Allocation | D111: =SUM(D103:D110) -> 147893.47 | F111: =SUM(F103:F110) -> 30900.04 | H111: =SUM(H103:H110) -> 116993.43
B112: Check: Allocation vs. Cost Detail (should be zero) | D112: =D111-D98 -> 0

Sheet Building 8
A1: Grace Townhomes Housing, LLC
A2: Grace Townhomes — 1212 Grace Cir, Ennis, TX 75119
A3: EIN: 47-5360069 · FYE: December 31, 2024 · Year of Change: 1/1/2024
A4: Building 8 — Attachment to Form 3115 (DCN #7, Rev. Proc. 2024-23 §6.01)
A5: Source: CSSI Report #107752-11, "#107752-11_Grace Townhomes - 3115 - Combined R2.pdf"
A7: CALCULATION OF §481(a) ADJUSTMENT — REGULAR TAX
A8: As Previously Filed
A9: Asset | B9: Property Description | C9: Date In Service | D9: Cost | E9: Sec 179 Exp | F9: Bonus Amt | G9: Tax Prior Depreciation | H9: Tax Current Depreciation | I9: End Depreciation | J9: Net Book Value | K9: Method | L9: Period
A10: 1 | B10: 1 - Buillding - Apt | C10: 12/17/15 | D10: 116723.12 | E10: 0 | F10: 0 | G10: 34132.24 | H10: 4244.48 | I10: =G10+H10 -> 38376.72 | J10: =D10-I10 -> 78346.4 | K10: S/L | L10: 27.5
A11: 2 | B11: 5 - Building - Apt | C11: 1/14/16 | D11: 212.58 | E11: 0 | F11: 0 | G11: 61.56 | H11: 7.73 | I11: =G11+H11 -> 69.29 | J11: =D11-I11 -> 143.29 | K11: S/L | L11: 27.5
A12: 3 | B12: 3 - Land Improvements - Apt | C12: 12/17/15 | D12: 11011.6 | E12: 0 | F12: 0 | G12: 6449.13 | H12: 649.69 | I12: =G12+H12 -> 7098.82 | J12: =D12-I12 -> 3912.78 | K12: 150DB | L12: 15.0
A13: 4 | B13: 4 - Equipment - Apt | C13: 12/17/15 | D13: 19946.17 | E13: 0 | F13: 0 | G13: 19281.3 | H13: 0 | I13: =G13+H13 -> 19281.3 | J13: =D13-I13 -> 664.87 | K13: 200DB | L13: 5.0
B14: Grand Total | D14: =SUM(D10:D13) -> 147893.47 | E14: =SUM(E10:E13) -> 0 | F14: =SUM(F10:F13) -> 0 | G14: =SUM(G10:G13) -> 59924.23 | H14: =SUM(H10:H13) -> 4901.9 | I14: =SUM(I10:I13) -> 64826.13 | J14: =SUM(J10:J13) -> 83067.34
A16: After Cost Segregation Correction
A17: Asset | B17: Property Description | C17: Date In Service | D17: Cost | E17: Sec 179 Exp | F17: Bonus Amt | G17: Tax Prior Depreciation | H17: Tax Current Depreciation | I17: End Depreciation | J17: Net Book Value | K17: Method | L17: Period
A18: 1 | B18: 1 - Buillding - Apt - 5yr | C18: 12/17/15 | D18: 24387.48 | E18: 0 | F18: 0 | G18: 24387.48 | H18: 0 | I18: =G18+H18 -> 24387.48 | J18: =D18-I18 -> 0 | K18: 200DB | L18: 5.0
A19: 2 | B19: 1 - Buillding - Apt - 27.5yr | C19: 12/17/15 | D19: 92335.64 | E19: 0 | F19: 0 | G19: 27001.18 | H19: 3357.66 | I19: =G19+H19 -> 30358.84 | J19: =D19-I19 -> 61976.8 | K19: S/L | L19: 27.5
A20: 3 | B20: 5 - Building - Apt - 5yr | C20: 1/14/16 | D20: 44.42 | E20: 0 | F20: 0 | G20: 44.42 | H20: 0 | I20: =G20+H20 -> 44.42 | J20: =D20-I20 -> 0 | K20: 200DB | L20: 5.0
A21: 4 | B21: 5 - Building - Apt - 27.5yr | C21: 1/14/16 | D21: 168.16 | E21: 0 | F21: 0 | G21: 48.63 | H21: 6.11 | I21: =G21+H21 -> 54.74 | J21: =D21-I21 -> 113.42 | K21: S/L | L21: 27.5
A22: 5 | B22: 3 - Land Improvements - Apt - 5yr | C22: 12/17/15 | D22: 2300.7 | E22: 0 | F22: 0 | G22: 2300.7 | H22: 0 | I22: =G22+H22 -> 2300.7 | J22: =D22-I22 -> 0 | K22: 200DB | L22: 5.0
A23: 6 | B23: 3 - Land Improvements - Apt - 27.5yr | C23: 12/17/15 | D23: 8710.9 | E23: 0 | F23: 0 | G23: 2547.28 | H23: 316.76 | I23: =G23+H23 -> 2864.04 | J23: =D23-I23 -> 5846.86 | K23: S/L | L23: 27.5
A24: 7 | B24: 4 - Equipment - Apt - 5yr | C24: 12/17/15 | D24: 4167.44 | E24: 0 | F24: 0 | G24: 4167.44 | H24: 0 | I24: =G24+H24 -> 4167.44 | J24: =D24-I24 -> 0 | K24: 200DB | L24: 5.0
A25: 8 | B25: 4 - Equipment - Apt - 27.5yr | C25: 12/17/15 | D25: 15778.73 | E25: 0 | F25: 0 | G25: 4614.07 | H25: 573.77 | I25: =G25+H25 -> 5187.84 | J25: =D25-I25 -> 10590.89 | K25: S/L | L25: 27.5
B26: Grand Total | D26: =SUM(D18:D25) -> 147893.47 | E26: =SUM(E18:E25) -> 0 | F26: =SUM(F18:F25) -> 0 | G26: =SUM(G18:G25) -> 65111.2 | H26: =SUM(H18:H25) -> 4254.3 | I26: =SUM(I18:I25) -> 69365.5 | J26: =SUM(J18:J25) -> 78527.97
B28: Section 481(a) Adjustment — Regular Tax
B29: Depreciation reported previously | D29: =I14 -> 64826.13
B30: Cost Segregation Corrected Depreciation | D30: =I26 -> 69365.5
B31: Section 481(a) Adjustment — Regular Tax | D31: =D29-D30 -> -4539.37
A33: CALCULATION OF §481(a) ADJUSTMENT — AMT
A34: As Previously Filed — AMT
A35: Asset | B35: Property Description | C35: Date In Service | D35: Cost | E35: Sec 179 Exp | F35: Bonus Amt | G35: AMT Prior Depreciation | H35: AMT Current Depreciation | I35: End Depreciation | J35: Net Book Value | K35: Method | L35: Period
A36: 1 | B36: 1 - Buillding - Apt | C36: 12/17/15 | D36: 116723.12 | E36: 0 | F36: 0 | G36: 34132.24 | H36: 4244.48 | I36: =G36+H36 -> 38376.72 | J36: =D36-I36 -> 78346.4 | K36: S/L | L36: 27.5
A37: 2 | B37: 5 - Building - Apt | C37: 1/14/16 | D37: 212.58 | E37: 0 | F37: 0 | G37: 61.56 | H37: 7.73 | I37: =G37+H37 -> 69.29 | J37: =D37-I37 -> 143.29 | K37: S/L | L37: 27.5
A38: 3 | B38: 3 - Land Improvements - Apt | C38: 12/17/15 | D38: 11011.6 | E38: 0 | F38: 0 | G38: 6449.13 | H38: 649.69 | I38: =G38+H38 -> 7098.82 | J38: =D38-I38 -> 3912.78 | K38: 150DB | L38: 15.0
A39: 4 | B39: 4 - Equipment - Apt | C39: 12/17/15 | D39: 19946.17 | E39: 0 | F39: 0 | G39: 19281.3 | H39: 0 | I39: =G39+H39 -> 19281.3 | J39: =D39-I39 -> 664.87 | K39: 200DB | L39: 5.0
B40: Grand Total | D40: =SUM(D36:D39) -> 147893.47 | E40: =SUM(E36:E39) -> 0 | F40: =SUM(F36:F39) -> 0 | G40: =SUM(G36:G39) -> 59924.23 | H40: =SUM(H36:H39) -> 4901.9 | I40: =SUM(I36:I39) -> 64826.13 | J40: =SUM(J36:J39) -> 83067.34
A42: After Cost Segregation Correction — AMT
A43: Asset | B43: Property Description | C43: Date In Service | D43: Cost | E43: Sec 179 Exp | F43: Bonus Amt | G43: AMT Prior Depreciation | H43: AMT Current Depreciation | I43: End Depreciation | J43: Net Book Value | K43: Method | L43: Period
A44: 1 | B44: 1 - Buillding - Apt - 5yr | C44: 12/17/15 | D44: 24387.48 | E44: 0 | F44: 0 | G44: 24387.48 | H44: 0 | I44: =G44+H44 -> 24387.48 | J44: =D44-I44 -> 0 | K44: 200DB | L44: 5.0
A45: 2 | B45: 1 - Buillding - Apt - 27.5yr | C45: 12/17/15 | D45: 92335.64 | E45: 0 | F45: 0 | G45: 27001.18 | H45: 3357.66 | I45: =G45+H45 -> 30358.84 | J45: =D45-I45 -> 61976.8 | K45: S/L | L45: 27.5
A46: 3 | B46: 5 - Building - Apt - 5yr | C46: 1/14/16 | D46: 44.42 | E46: 0 | F46: 0 | G46: 44.42 | H46: 0 | I46: =G46+H46 -> 44.42 | J46: =D46-I46 -> 0 | K46: 200DB | L46: 5.0
A47: 4 | B47: 5 - Building - Apt - 27.5yr | C47: 1/14/16 | D47: 168.16 | E47: 0 | F47: 0 | G47: 48.63 | H47: 6.11 | I47: =G47+H47 -> 54.74 | J47: =D47-I47 -> 113.42 | K47: S/L | L47: 27.5
A48: 5 | B48: 3 - Land Improvements - Apt - 5yr | C48: 12/17/15 | D48: 2300.7 | E48: 0 | F48: 0 | G48: 2300.7 | H48: 0 | I48: =G48+H48 -> 2300.7 | J48: =D48-I48 -> 0 | K48: 200DB | L48: 5.0
A49: 6 | B49: 3 - Land Improvements - Apt - 27.5yr | C49: 12/17/15 | D49: 8710.9 | E49: 0 | F49: 0 | G49: 2547.28 | H49: 316.76 | I49: =G49+H49 -> 2864.04 | J49: =D49-I49 -> 5846.86 | K49: S/L | L49: 27.5
A50: 7 | B50: 4 - Equipment - Apt - 5yr | C50: 12/17/15 | D50: 4167.44 | E50: 0 | F50: 0 | G50: 4167.44 | H50: 0 | I50: =G50+H50 -> 4167.44 | J50: =D50-I50 -> 0 | K50: 200DB | L50: 5.0
A51: 8 | B51: 4 - Equipment - Apt - 27.5yr | C51: 12/17/15 | D51: 15778.73 | E51: 0 | F51: 0 | G51: 4614.07 | H51: 573.77 | I51: =G51+H51 -> 5187.84 | J51: =D51-I51 -> 10590.89 | K51: S/L | L51: 27.5
B52: Grand Total | D52: =SUM(D44:D51) -> 147893.47 | E52: =SUM(E44:E51) -> 0 | F52: =SUM(F44:F51) -> 0 | G52: =SUM(G44:G51) -> 65111.2 | H52: =SUM(H44:H51) -> 4254.3 | I52: =SUM(I44:I51) -> 69365.5 | J52: =SUM(J44:J51) -> 78527.97
B54: Section 481(a) Adjustment — AMT
B55: Depreciation reported previously | D55: =I40 -> 64826.13
B56: Cost Segregation Corrected Depreciation | D56: =I52 -> 69365.5
B57: Section 481(a) Adjustment — AMT | D57: =D55-D56 -> -4539.37
A59: COST SEGREGATION STUDY — COST SUMMARY
B60: Total Building Cost | D60: =D98 -> 147893.47
B61: Building Components: 5 Year | D61: =F98 -> 30900.04
B62: % of Cost | D62: =F99 -> 0.20893444
B63: Building Structure: 27.5 Year | D63: =H98 -> 116993.43
B64: % of Cost | D64: =H99 -> 0.79106556
A66: COST SEGREGATION STUDY — COST DETAIL
B67: Property Category | D67: Cost | F67: 5 Year | H67: 27.5 Year
B68: Building Components
B69: Cabinets / Millwork | D69: =SUM(F69:H69) -> 4901.61 | F69: 4901.61
B70: Moldings | D70: =SUM(F70:H70) -> 2185.54 | F70: 2185.54
B71: Flooring - Vinyl Plank | D71: =SUM(F71:H71) -> 11385.26 | F71: 11385.26
B72: Window Treatments | D72: =SUM(F72:H72) -> 589.62 | F72: 589.62
B73: Specialty HVAC - Dryer Vents | D73: =SUM(F73:H73) -> 183.29 | F73: 183.29
B74: Building Signage | D74: =SUM(F74:H74) -> 96.76 | F74: 96.76
B75: Specialty Electrical - Appliances | D75: =SUM(F75:H75) -> 2980.97 | F75: 2980.97
B76: Communication / Data | D76: =SUM(F76:H76) -> 994.55 | F76: 994.55
B77: Specialty Plumbing - Kitchen Sinks / Laundry | D77: =SUM(F77:H77) -> 3427.41 | F77: 3427.41
B78: Security / Exterior Lighting | D78: =SUM(F78:H78) -> 428.96 | F78: 428.96
B79: Access Control | D79: =SUM(F79:H79) -> 43.2 | F79: 43.2
B80: Appliances | D80: =SUM(F80:H80) -> 3682.87 | F80: 3682.87
B81: Building Structure
B82: Roofing Systems | D82: =SUM(F82:H82) -> 8561.68 | H82: 8561.68
B83: Foundations | D83: =SUM(F83:H83) -> 16225.62 | H83: 16225.62
B84: HVAC | D84: =SUM(F84:H84) -> 10992.55 | H84: 10992.55
B85: Electrical | D85: =SUM(F85:H85) -> 12099.12 | H85: 12099.12
B86: Plumbing | D86: =SUM(F86:H86) -> 9715.1 | H86: 9715.1
B87: Fire Protection & Alarm | D87: =SUM(F87:H87) -> 548.48 | H87: 548.48
B88: Exterior Façade / Building Skin | D88: =SUM(F88:H88) -> 12559.71 | H88: 12559.71
B89: Doors & Frames | D89: =SUM(F89:H89) -> 5680.09 | H89: 5680.09
B90: Windows | D90: =SUM(F90:H90) -> 2911.57 | H90: 2911.57
B91: Ceiling Systems | D91: =SUM(F91:H91) -> 5070.55 | H91: 5070.55
B92: Interior Framing / Partitions | D92: =SUM(F92:H92) -> 9837.36 | H92: 9837.36
B93: Painting | D93: =SUM(F93:H93) -> 4408.6 | H93: 4408.6
... B97: Cabinets / Millwork - Restrooms | D97: =SUM(F97:H97) -> 1709.81 | H97: 1709.81
B98: Total Building Cost | D98: =SUM(D68:D97) -> 147893.47 | F98: =SUM(F68:F97) -> 30900.04 | H98: =SUM(H68:H97) -> 116993.43
B99: % of Cost | F99: =F98/D98 -> 0.20893444 | H99: =H98/D98 -> 0.79106556
A101: ASSET ALLOCATION (per After Cost Segregation schedule)
B102: Asset (as reclassified) | D102: Cost | F102: 5 Year | H102: 27.5 Year
B103: ='Building 8'!B18 -> 1 - Buillding - Apt - 5yr | D103: =SUM(F103:H103) -> 24387.48 | F103: ='Building 8'!D18 -> 24387.48
B104: ='Building 8'!B19 -> 1 - Buillding - Apt - 27.5yr | D104: =SUM(F104:H104) -> 92335.64 | H104: ='Building 8'!D19 -> 92335.64
B105: ='Building 8'!B20 -> 5 - Building - Apt - 5yr | D105: =SUM(F105:H105) -> 44.42 | F105: ='Building 8'!D20 -> 44.42
B106: ='Building 8'!B21 -> 5 - Building - Apt - 27.5yr | D106: =SUM(F106:H106) -> 168.16 | H106: ='Building 8'!D21 -> 168.16
B107: ='Building 8'!B22 -> 3 - Land Improvements - Apt - 5yr | D107: =SUM(F107:H107) -> 2300.7 | F107: ='Building 8'!D22 -> 2300.7
B108: ='Building 8'!B23 -> 3 - Land Improvements - Apt - 27.5yr | D108: =SUM(F108:H108) -> 8710.9 | H108: ='Building 8'!D23 -> 8710.9
B109: ='Building 8'!B24 -> 4 - Equipment - Apt - 5yr | D109: =SUM(F109:H109) -> 4167.44 | F109: ='Building 8'!D24 -> 4167.44
B110: ='Building 8'!B25 -> 4 - Equipment - Apt - 27.5yr | D110: =SUM(F110:H110) -> 15778.73 | H110: ='Building 8'!D25 -> 15778.73
B111: Total Allocation | D111: =SUM(D103:D110) -> 147893.47 | F111: =SUM(F103:F110) -> 30900.04 | H111: =SUM(H103:H110) -> 116993.43
B112: Check: Allocation vs. Cost Detail (should be zero) | D112: =D111-D98 -> 0

Sheet Building 9
A1: Grace Townhomes Housing, LLC
A2: Grace Townhomes — 1212 Grace Cir, Ennis, TX 75119
A3: EIN: 47-5360069 · FYE: December 31, 2024 · Year of Change: 1/1/2024
A4: Building 9 — Attachment to Form 3115 (DCN #7, Rev. Proc. 2024-23 §6.01)
A5: Source: CSSI Report #107752-11, "#107752-11_Grace Townhomes - 3115 - Combined R2.pdf"
A7: CALCULATION OF §481(a) ADJUSTMENT — REGULAR TAX
A8: As Previously Filed
A9: Asset | B9: Property Description | C9: Date In Service | D9: Cost | E9: Sec 179 Exp | F9: Bonus Amt | G9: Tax Prior Depreciation | H9: Tax Current Depreciation | I9: End Depreciation | J9: Net Book Value | K9: Method | L9: Period
A10: 1 | B10: 1 - Buillding - Apt | C10: 12/17/15 | D10: 116723.12 | E10: 0 | F10: 0 | G10: 34132.24 | H10: 4244.48 | I10: =G10+H10 -> 38376.72 | J10: =D10-I10 -> 78346.4 | K10: S/L | L10: 27.5
A11: 2 | B11: 5 - Building - Apt | C11: 1/14/16 | D11: 212.58 | E11: 0 | F11: 0 | G11: 61.56 | H11: 7.73 | I11: =G11+H11 -> 69.29 | J11: =D11-I11 -> 143.29 | K11: S/L | L11: 27.5
A12: 3 | B12: 3 - Land Improvements - Apt | C12: 12/17/15 | D12: 11011.6 | E12: 0 | F12: 0 | G12: 6449.13 | H12: 649.69 | I12: =G12+H12 -> 7098.82 | J12: =D12-I12 -> 3912.78 | K12: 150DB | L12: 15.0
A13: 4 | B13: 4 - Equipment - Apt | C13: 12/17/15 | D13: 19946.17 | E13: 0 | F13: 0 | G13: 19281.3 | H13: 0 | I13: =G13+H13 -> 19281.3 | J13: =D13-I13 -> 664.87 | K13: 200DB | L13: 5.0
B14: Grand Total | D14: =SUM(D10:D13) -> 147893.47 | E14: =SUM(E10:E13) -> 0 | F14: =SUM(F10:F13) -> 0 | G14: =SUM(G10:G13) -> 59924.23 | H14: =SUM(H10:H13) -> 4901.9 | I14: =SUM(I10:I13) -> 64826.13 | J14: =SUM(J10:J13) -> 83067.34
A16: After Cost Segregation Correction
A17: Asset | B17: Property Description | C17: Date In Service | D17: Cost | E17: Sec 179 Exp | F17: Bonus Amt | G17: Tax Prior Depreciation | H17: Tax Current Depreciation | I17: End Depreciation | J17: Net Book Value | K17: Method | L17: Period
A18: 1 | B18: 1 - Buillding - Apt - 5yr | C18: 12/17/15 | D18: 24387.48 | E18: 0 | F18: 0 | G18: 24387.48 | H18: 0 | I18: =G18+H18 -> 24387.48 | J18: =D18-I18 -> 0 | K18: 200DB | L18: 5.0
A19: 2 | B19: 1 - Buillding - Apt - 27.5yr | C19: 12/17/15 | D19: 92335.64 | E19: 0 | F19: 0 | G19: 27001.18 | H19: 3357.66 | I19: =G19+H19 -> 30358.84 | J19: =D19-I19 -> 61976.8 | K19: S/L | L19: 27.5
A20: 3 | B20: 5 - Building - Apt - 5yr | C20: 1/14/16 | D20: 44.42 | E20: 0 | F20: 0 | G20: 44.42 | H20: 0 | I20: =G20+H20 -> 44.42 | J20: =D20-I20 -> 0 | K20: 200DB | L20: 5.0
A21: 4 | B21: 5 - Building - Apt - 27.5yr | C21: 1/14/16 | D21: 168.16 | E21: 0 | F21: 0 | G21: 48.63 | H21: 6.11 | I21: =G21+H21 -> 54.74 | J21: =D21-I21 -> 113.42 | K21: S/L | L21: 27.5
A22: 5 | B22: 3 - Land Improvements - Apt - 5yr | C22: 12/17/15 | D22: 2300.7 | E22: 0 | F22: 0 | G22: 2300.7 | H22: 0 | I22: =G22+H22 -> 2300.7 | J22: =D22-I22 -> 0 | K22: 200DB | L22: 5.0
A23: 6 | B23: 3 - Land Improvements - Apt - 27.5yr | C23: 12/17/15 | D23: 8710.9 | E23: 0 | F23: 0 | G23: 2547.28 | H23: 316.76 | I23: =G23+H23 -> 2864.04 | J23: =D23-I23 -> 5846.86 | K23: S/L | L23: 27.5
A24: 7 | B24: 4 - Equipment - Apt - 5yr | C24: 12/17/15 | D24: 4167.44 | E24: 0 | F24: 0 | G24: 4167.44 | H24: 0 | I24: =G24+H24 -> 4167.44 | J24: =D24-I24 -> 0 | K24: 200DB | L24: 5.0
A25: 8 | B25: 4 - Equipment - Apt - 27.5yr | C25: 12/17/15 | D25: 15778.73 | E25: 0 | F25: 0 | G25: 4614.07 | H25: 573.77 | I25: =G25+H25 -> 5187.84 | J25: =D25-I25 -> 10590.89 | K25: S/L | L25: 27.5
B26: Grand Total | D26: =SUM(D18:D25) -> 147893.47 | E26: =SUM(E18:E25) -> 0 | F26: =SUM(F18:F25) -> 0 | G26: =SUM(G18:G25) -> 65111.2 | H26: =SUM(H18:H25) -> 4254.3 | I26: =SUM(I18:I25) -> 69365.5 | J26: =SUM(J18:J25) -> 78527.97
B28: Section 481(a) Adjustment — Regular Tax
B29: Depreciation reported previously | D29: =I14 -> 64826.13
B30: Cost Segregation Corrected Depreciation | D30: =I26 -> 69365.5
B31: Section 481(a) Adjustment — Regular Tax | D31: =D29-D30 -> -4539.37
A33: CALCULATION OF §481(a) ADJUSTMENT — AMT
A34: As Previously Filed — AMT
A35: Asset | B35: Property Description | C35: Date In Service | D35: Cost | E35: Sec 179 Exp | F35: Bonus Amt | G35: AMT Prior Depreciation | H35: AMT Current Depreciation | I35: End Depreciation | J35: Net Book Value | K35: Method | L35: Period
A36: 1 | B36: 1 - Buillding - Apt | C36: 12/17/15 | D36: 116723.12 | E36: 0 | F36: 0 | G36: 34132.24 | H36: 4244.48 | I36: =G36+H36 -> 38376.72 | J36: =D36-I36 -> 78346.4 | K36: S/L | L36: 27.5
A37: 2 | B37: 5 - Building - Apt | C37: 1/14/16 | D37: 212.58 | E37: 0 | F37: 0 | G37: 61.56 | H37: 7.73 | I37: =G37+H37 -> 69.29 | J37: =D37-I37 -> 143.29 | K37: S/L | L37: 27.5
A38: 3 | B38: 3 - Land Improvements - Apt | C38: 12/17/15 | D38: 11011.6 | E38: 0 | F38: 0 | G38: 6449.13 | H38: 649.69 | I38: =G38+H38 -> 7098.82 | J38: =D38-I38 -> 3912.78 | K38: 150DB | L38: 15.0
A39: 4 | B39: 4 - Equipment - Apt | C39: 12/17/15 | D39: 19946.17 | E39: 0 | F39: 0 | G39: 19281.3 | H39: 0 | I39: =G39+H39 -> 19281.3 | J39: =D39-I39 -> 664.87 | K39: 200DB | L39: 5.0
B40: Grand Total | D40: =SUM(D36:D39) -> 147893.47 | E40: =SUM(E36:E39) -> 0 | F40: =SUM(F36:F39) -> 0 | G40: =SUM(G36:G39) -> 59924.23 | H40: =SUM(H36:H39) -> 4901.9 | I40: =SUM(I36:I39) -> 64826.13 | J40: =SUM(J36:J39) -> 83067.34
A42: After Cost Segregation Correction — AMT
A43: Asset | B43: Property Description | C43: Date In Service | D43: Cost | E43: Sec 179 Exp | F43: Bonus Amt | G43: AMT Prior Depreciation | H43: AMT Current Depreciation | I43: End Depreciation | J43: Net Book Value | K43: Method | L43: Period
A44: 1 | B44: 1 - Buillding - Apt - 5yr | C44: 12/17/15 | D44: 24387.48 | E44: 0 | F44: 0 | G44: 24387.48 | H44: 0 | I44: =G44+H44 -> 24387.48 | J44: =D44-I44 -> 0 | K44: 200DB | L44: 5.0
A45: 2 | B45: 1 - Buillding - Apt - 27.5yr | C45: 12/17/15 | D45: 92335.64 | E45: 0 | F45: 0 | G45: 27001.18 | H45: 3357.66 | I45: =G45+H45 -> 30358.84 | J45: =D45-I45 -> 61976.8 | K45: S/L | L45: 27.5
A46: 3 | B46: 5 - Building - Apt - 5yr | C46: 1/14/16 | D46: 44.42 | E46: 0 | F46: 0 | G46: 44.42 | H46: 0 | I46: =G46+H46 -> 44.42 | J46: =D46-I46 -> 0 | K46: 200DB | L46: 5.0
A47: 4 | B47: 5 - Building - Apt - 27.5yr | C47: 1/14/16 | D47: 168.16 | E47: 0 | F47: 0 | G47: 48.63 | H47: 6.11 | I47: =G47+H47 -> 54.74 | J47: =D47-I47 -> 113.42 | K47: S/L | L47: 27.5
A48: 5 | B48: 3 - Land Improvements - Apt - 5yr | C48: 12/17/15 | D48: 2300.7 | E48: 0 | F48: 0 | G48: 2300.7 | H48: 0 | I48: =G48+H48 -> 2300.7 | J48: =D48-I48 -> 0 | K48: 200DB | L48: 5.0
A49: 6 | B49: 3 - Land Improvements - Apt - 27.5yr | C49: 12/17/15 | D49: 8710.9 | E49: 0 | F49: 0 | G49: 2547.28 | H49: 316.76 | I49: =G49+H49 -> 2864.04 | J49: =D49-I49 -> 5846.86 | K49: S/L | L49: 27.5
A50: 7 | B50: 4 - Equipment - Apt - 5yr | C50: 12/17/15 | D50: 4167.44 | E50: 0 | F50: 0 | G50: 4167.44 | H50: 0 | I50: =G50+H50 -> 4167.44 | J50: =D50-I50 -> 0 | K50: 200DB | L50: 5.0
A51: 8 | B51: 4 - Equipment - Apt - 27.5yr | C51: 12/17/15 | D51: 15778.73 | E51: 0 | F51: 0 | G51: 4614.07 | H51: 573.77 | I51: =G51+H51 -> 5187.84 | J51: =D51-I51 -> 10590.89 | K51: S/L | L51: 27.5
B52: Grand Total | D52: =SUM(D44:D51) -> 147893.47 | E52: =SUM(E44:E51) -> 0 | F52: =SUM(F44:F51) -> 0 | G52: =SUM(G44:G51) -> 65111.2 | H52: =SUM(H44:H51) -> 4254.3 | I52: =SUM(I44:I51) -> 69365.5 | J52: =SUM(J44:J51) -> 78527.97
B54: Section 481(a) Adjustment — AMT
B55: Depreciation reported previously | D55: =I40 -> 64826.13
B56: Cost Segregation Corrected Depreciation | D56: =I52 -> 69365.5
B57: Section 481(a) Adjustment — AMT | D57: =D55-D56 -> -4539.37
A59: COST SEGREGATION STUDY — COST SUMMARY
B60: Total Building Cost | D60: =D98 -> 147893.47
B61: Building Components: 5 Year | D61: =F98 -> 30900.04
B62: % of Cost | D62: =F99 -> 0.20893444
B63: Building Structure: 27.5 Year | D63: =H98 -> 116993.43
B64: % of Cost | D64: =H99 -> 0.79106556
A66: COST SEGREGATION STUDY — COST DETAIL
B67: Property Category | D67: Cost | F67: 5 Year | H67: 27.5 Year
B68: Building Components
B69: Cabinets / Millwork | D69: =SUM(F69:H69) -> 4901.61 | F69: 4901.61
B70: Moldings | D70: =SUM(F70:H70) -> 2185.54 | F70: 2185.54
B71: Flooring - Vinyl Plank | D71: =SUM(F71:H71) -> 11385.26 | F71: 11385.26
B72: Window Treatments | D72: =SUM(F72:H72) -> 589.62 | F72: 589.62
B73: Specialty HVAC - Dryer Vents | D73: =SUM(F73:H73) -> 183.29 | F73: 183.29
B74: Building Signage | D74: =SUM(F74:H74) -> 96.76 | F74: 96.76
B75: Specialty Electrical - Appliances | D75: =SUM(F75:H75) -> 2980.97 | F75: 2980.97
B76: Communication / Data | D76: =SUM(F76:H76) -> 994.55 | F76: 994.55
B77: Specialty Plumbing - Kitchen Sinks / Laundry | D77: =SUM(F77:H77) -> 3427.41 | F77: 3427.41
B78: Security / Exterior Lighting | D78: =SUM(F78:H78) -> 428.96 | F78: 428.96
B79: Access Control | D79: =SUM(F79:H79) -> 43.2 | F79: 43.2
B80: Appliances | D80: =SUM(F80:H80) -> 3682.87 | F80: 3682.87
B81: Building Structure
B82: Roofing Systems | D82: =SUM(F82:H82) -> 8561.68 | H82: 8561.68
B83: Foundations | D83: =SUM(F83:H83) -> 16225.62 | H83: 16225.62
B84: HVAC | D84: =SUM(F84:H84) -> 10992.55 | H84: 10992.55
B85: Electrical | D85: =SUM(F85:H85) -> 12099.12 | H85: 12099.12
B86: Plumbing | D86: =SUM(F86:H86) -> 9715.1 | H86: 9715.1
B87: Fire Protection & Alarm | D87: =SUM(F87:H87) -> 548.48 | H87: 548.48
B88: Exterior Façade / Building Skin | D88: =SUM(F88:H88) -> 12559.71 | H88: 12559.71
B89: Doors & Frames | D89: =SUM(F89:H89) -> 5680.09 | H89: 5680.09
B90: Windows | D90: =SUM(F90:H90) -> 2911.57 | H90: 2911.57
B91: Ceiling Systems | D91: =SUM(F91:H91) -> 5070.55 | H91: 5070.55
B92: Interior Framing / Partitions | D92: =SUM(F92:H92) -> 9837.36 | H92: 9837.36
B93: Painting | D93: =SUM(F93:H93) -> 4408.6 | H93: 4408.6
... B97: Cabinets / Millwork - Restrooms | D97: =SUM(F97:H97) -> 1709.81 | H97: 1709.81
B98: Total Building Cost | D98: =SUM(D68:D97) -> 147893.47 | F98: =SUM(F68:F97) -> 30900.04 | H98: =SUM(H68:H97) -> 116993.43
B99: % of Cost | F99: =F98/D98 -> 0.20893444 | H99: =H98/D98 -> 0.79106556
A101: ASSET ALLOCATION (per After Cost Segregation schedule)
B102: Asset (as reclassified) | D102: Cost | F102: 5 Year | H102: 27.5 Year
B103: ='Building 9'!B18 -> 1 - Buillding - Apt - 5yr | D103: =SUM(F103:H103) -> 24387.48 | F103: ='Building 9'!D18 -> 24387.48
B104: ='Building 9'!B19 -> 1 - Buillding - Apt - 27.5yr | D104: =SUM(F104:H104) -> 92335.64 | H104: ='Building 9'!D19 -> 92335.64
B105: ='Building 9'!B20 -> 5 - Building - Apt - 5yr | D105: =SUM(F105:H105) -> 44.42 | F105: ='Building 9'!D20 -> 44.42
B106: ='Building 9'!B21 -> 5 - Building - Apt - 27.5yr | D106: =SUM(F106:H106) -> 168.16 | H106: ='Building 9'!D21 -> 168.16
B107: ='Building 9'!B22 -> 3 - Land Improvements - Apt - 5yr | D107: =SUM(F107:H107) -> 2300.7 | F107: ='Building 9'!D22 -> 2300.7
B108: ='Building 9'!B23 -> 3 - Land Improvements - Apt - 27.5yr | D108: =SUM(F108:H108) -> 8710.9 | H108: ='Building 9'!D23 -> 8710.9
B109: ='Building 9'!B24 -> 4 - Equipment - Apt - 5yr | D109: =SUM(F109:H109) -> 4167.44 | F109: ='Building 9'!D24 -> 4167.44
B110: ='Building 9'!B25 -> 4 - Equipment - Apt - 27.5yr | D110: =SUM(F110:H110) -> 15778.73 | H110: ='Building 9'!D25 -> 15778.73
B111: Total Allocation | D111: =SUM(D103:D110) -> 147893.47 | F111: =SUM(F103:F110) -> 30900.04 | H111: =SUM(H103:H110) -> 116993.43
B112: Check: Allocation vs. Cost Detail (should be zero) | D112: =D111-D98 -> 0

Sheet Building 10
A1: Grace Townhomes Housing, LLC
A2: Grace Townhomes — 1212 Grace Cir, Ennis, TX 75119
A3: EIN: 47-5360069 · FYE: December 31, 2024 · Year of Change: 1/1/2024
A4: Building 10 — Attachment to Form 3115 (DCN #7, Rev. Proc. 2024-23 §6.01)
A5: Source: CSSI Report #107752-11, "#107752-11_Grace Townhomes - 3115 - Combined R2.pdf"
A7: CALCULATION OF §481(a) ADJUSTMENT — REGULAR TAX
A8: As Previously Filed
A9: Asset | B9: Property Description | C9: Date In Service | D9: Cost | E9: Sec 179 Exp | F9: Bonus Amt | G9: Tax Prior Depreciation | H9: Tax Current Depreciation | I9: End Depreciation | J9: Net Book Value | K9: Method | L9: Period
A10: 1 | B10: 1 - Buillding - Apt | C10: 12/17/15 | D10: 116723.12 | E10: 0 | F10: 0 | G10: 34132.24 | H10: 4244.48 | I10: =G10+H10 -> 38376.72 | J10: =D10-I10 -> 78346.4 | K10: S/L | L10: 27.5
A11: 2 | B11: 5 - Building - Apt | C11: 1/14/16 | D11: 212.58 | E11: 0 | F11: 0 | G11: 61.56 | H11: 7.73 | I11: =G11+H11 -> 69.29 | J11: =D11-I11 -> 143.29 | K11: S/L | L11: 27.5
A12: 3 | B12: 3 - Land Improvements - Apt | C12: 12/17/15 | D12: 11011.6 | E12: 0 | F12: 0 | G12: 6449.13 | H12: 649.69 | I12: =G12+H12 -> 7098.82 | J12: =D12-I12 -> 3912.78 | K12: 150DB | L12: 15.0
A13: 4 | B13: 4 - Equipment - Apt | C13: 12/17/15 | D13: 19946.17 | E13: 0 | F13: 0 | G13: 19281.3 | H13: 0 | I13: =G13+H13 -> 19281.3 | J13: =D13-I13 -> 664.87 | K13: 200DB | L13: 5.0
B14: Grand Total | D14: =SUM(D10:D13) -> 147893.47 | E14: =SUM(E10:E13) -> 0 | F14: =SUM(F10:F13) -> 0 | G14: =SUM(G10:G13) -> 59924.23 | H14: =SUM(H10:H13) -> 4901.9 | I14: =SUM(I10:I13) -> 64826.13 | J14: =SUM(J10:J13) -> 83067.34
A16: After Cost Segregation Correction
A17: Asset | B17: Property Description | C17: Date In Service | D17: Cost | E17: Sec 179 Exp | F17: Bonus Amt | G17: Tax Prior Depreciation | H17: Tax Current Depreciation | I17: End Depreciation | J17: Net Book Value | K17: Method | L17: Period
A18: 1 | B18: 1 - Buillding - Apt - 5yr | C18: 12/17/15 | D18: 24387.48 | E18: 0 | F18: 0 | G18: 24387.48 | H18: 0 | I18: =G18+H18 -> 24387.48 | J18: =D18-I18 -> 0 | K18: 200DB | L18: 5.0
A19: 2 | B19: 1 - Buillding - Apt - 27.5yr | C19: 12/17/15 | D19: 92335.64 | E19: 0 | F19: 0 | G19: 27001.18 | H19: 3357.66 | I19: =G19+H19 -> 30358.84 | J19: =D19-I19 -> 61976.8 | K19: S/L | L19: 27.5
A20: 3 | B20: 5 - Building - Apt - 5yr | C20: 1/14/16 | D20: 44.42 | E20: 0 | F20: 0 | G20: 44.42 | H20: 0 | I20: =G20+H20 -> 44.42 | J20: =D20-I20 -> 0 | K20: 200DB | L20: 5.0
A21: 4 | B21: 5 - Building - Apt - 27.5yr | C21: 1/14/16 | D21: 168.16 | E21: 0 | F21: 0 | G21: 48.63 | H21: 6.11 | I21: =G21+H21 -> 54.74 | J21: =D21-I21 -> 113.42 | K21: S/L | L21: 27.5
A22: 5 | B22: 3 - Land Improvements - Apt - 5yr | C22: 12/17/15 | D22: 2300.7 | E22: 0 | F22: 0 | G22: 2300.7 | H22: 0 | I22: =G22+H22 -> 2300.7 | J22: =D22-I22 -> 0 | K22: 200DB | L22: 5.0
A23: 6 | B23: 3 - Land Improvements - Apt - 27.5yr | C23: 12/17/15 | D23: 8710.9 | E23: 0 | F23: 0 | G23: 2547.28 | H23: 316.76 | I23: =G23+H23 -> 2864.04 | J23: =D23-I23 -> 5846.86 | K23: S/L | L23: 27.5
A24: 7 | B24: 4 - Equipment - Apt - 5yr | C24: 12/17/15 | D24: 4167.44 | E24: 0 | F24: 0 | G24: 4167.44 | H24: 0 | I24: =G24+H24 -> 4167.44 | J24: =D24-I24 -> 0 | K24: 200DB | L24: 5.0
A25: 8 | B25: 4 - Equipment - Apt - 27.5yr | C25: 12/17/15 | D25: 15778.73 | E25: 0 | F25: 0 | G25: 4614.07 | H25: 573.77 | I25: =G25+H25 -> 5187.84 | J25: =D25-I25 -> 10590.89 | K25: S/L | L25: 27.5
B26: Grand Total | D26: =SUM(D18:D25) -> 147893.47 | E26: =SUM(E18:E25) -> 0 | F26: =SUM(F18:F25) -> 0 | G26: =SUM(G18:G25) -> 65111.2 | H26: =SUM(H18:H25) -> 4254.3 | I26: =SUM(I18:I25) -> 69365.5 | J26: =SUM(J18:J25) -> 78527.97
B28: Section 481(a) Adjustment — Regular Tax
B29: Depreciation reported previously | D29: =I14 -> 64826.13
B30: Cost Segregation Corrected Depreciation | D30: =I26 -> 69365.5
B31: Section 481(a) Adjustment — Regular Tax | D31: =D29-D30 -> -4539.37
A33: CALCULATION OF §481(a) ADJUSTMENT — AMT
A34: As Previously Filed — AMT
A35: Asset | B35: Property Description | C35: Date In Service | D35: Cost | E35: Sec 179 Exp | F35: Bonus Amt | G35: AMT Prior Depreciation | H35: AMT Current Depreciation | I35: End Depreciation | J35: Net Book Value | K35: Method | L35: Period
A36: 1 | B36: 1 - Buillding - Apt | C36: 12/17/15 | D36: 116723.12 | E36: 0 | F36: 0 | G36: 34132.24 | H36: 4244.48 | I36: =G36+H36 -> 38376.72 | J36: =D36-I36 -> 78346.4 | K36: S/L | L36: 27.5
A37: 2 | B37: 5 - Building - Apt | C37: 1/14/16 | D37: 212.58 | E37: 0 | F37: 0 | G37: 61.56 | H37: 7.73 | I37: =G37+H37 -> 69.29 | J37: =D37-I37 -> 143.29 | K37: S/L | L37: 27.5
A38: 3 | B38: 3 - Land Improvements - Apt | C38: 12/17/15 | D38: 11011.6 | E38: 0 | F38: 0 | G38: 6449.13 | H38: 649.69 | I38: =G38+H38 -> 7098.82 | J38: =D38-I38 -> 3912.78 | K38: 150DB | L38: 15.0
A39: 4 | B39: 4 - Equipment - Apt | C39: 12/17/15 | D39: 19946.17 | E39: 0 | F39: 0 | G39: 19281.3 | H39: 0 | I39: =G39+H39 -> 19281.3 | J39: =D39-I39 -> 664.87 | K39: 200DB | L39: 5.0
B40: Grand Total | D40: =SUM(D36:D39) -> 147893.47 | E40: =SUM(E36:E39) -> 0 | F40: =SUM(F36:F39) -> 0 | G40: =SUM(G36:G39) -> 59924.23 | H40: =SUM(H36:H39) -> 4901.9 | I40: =SUM(I36:I39) -> 64826.13 | J40: =SUM(J36:J39) -> 83067.34
A42: After Cost Segregation Correction — AMT
A43: Asset | B43: Property Description | C43: Date In Service | D43: Cost | E43: Sec 179 Exp | F43: Bonus Amt | G43: AMT Prior Depreciation | H43: AMT Current Depreciation | I43: End Depreciation | J43: Net Book Value | K43: Method | L43: Period
A44: 1 | B44: 1 - Buillding - Apt - 5yr | C44: 12/17/15 | D44: 24387.48 | E44: 0 | F44: 0 | G44: 24387.48 | H44: 0 | I44: =G44+H44 -> 24387.48 | J44: =D44-I44 -> 0 | K44: 200DB | L44: 5.0
A45: 2 | B45: 1 - Buillding - Apt - 27.5yr | C45: 12/17/15 | D45: 92335.64 | E45: 0 | F45: 0 | G45: 27001.18 | H45: 3357.66 | I45: =G45+H45 -> 30358.84 | J45: =D45-I45 -> 61976.8 | K45: S/L | L45: 27.5
A46: 3 | B46: 5 - Building - Apt - 5yr | C46: 1/14/16 | D46: 44.42 | E46: 0 | F46: 0 | G46: 44.42 | H46: 0 | I46: =G46+H46 -> 44.42 | J46: =D46-I46 -> 0 | K46: 200DB | L46: 5.0
A47: 4 | B47: 5 - Building - Apt - 27.5yr | C47: 1/14/16 | D47: 168.16 | E47: 0 | F47: 0 | G47: 48.63 | H47: 6.11 | I47: =G47+H47 -> 54.74 | J47: =D47-I47 -> 113.42 | K47: S/L | L47: 27.5
A48: 5 | B48: 3 - Land Improvements - Apt - 5yr | C48: 12/17/15 | D48: 2300.7 | E48: 0 | F48: 0 | G48: 2300.7 | H48: 0 | I48: =G48+H48 -> 2300.7 | J48: =D48-I48 -> 0 | K48: 200DB | L48: 5.0
A49: 6 | B49: 3 - Land Improvements - Apt - 27.5yr | C49: 12/17/15 | D49: 8710.9 | E49: 0 | F49: 0 | G49: 2547.28 | H49: 316.76 | I49: =G49+H49 -> 2864.04 | J49: =D49-I49 -> 5846.86 | K49: S/L | L49: 27.5
A50: 7 | B50: 4 - Equipment - Apt - 5yr | C50: 12/17/15 | D50: 4167.44 | E50: 0 | F50: 0 | G50: 4167.44 | H50: 0 | I50: =G50+H50 -> 4167.44 | J50: =D50-I50 -> 0 | K50: 200DB | L50: 5.0
A51: 8 | B51: 4 - Equipment - Apt - 27.5yr | C51: 12/17/15 | D51: 15778.73 | E51: 0 | F51: 0 | G51: 4614.07 | H51: 573.77 | I51: =G51+H51 -> 5187.84 | J51: =D51-I51 -> 10590.89 | K51: S/L | L51: 27.5
B52: Grand Total | D52: =SUM(D44:D51) -> 147893.47 | E52: =SUM(E44:E51) -> 0 | F52: =SUM(F44:F51) -> 0 | G52: =SUM(G44:G51) -> 65111.2 | H52: =SUM(H44:H51) -> 4254.3 | I52: =SUM(I44:I51) -> 69365.5 | J52: =SUM(J44:J51) -> 78527.97
B54: Section 481(a) Adjustment — AMT
B55: Depreciation reported previously | D55: =I40 -> 64826.13
B56: Cost Segregation Corrected Depreciation | D56: =I52 -> 69365.5
B57: Section 481(a) Adjustment — AMT | D57: =D55-D56 -> -4539.37
A59: COST SEGREGATION STUDY — COST SUMMARY
B60: Total Building Cost | D60: =D98 -> 147893.47
B61: Building Components: 5 Year | D61: =F98 -> 30900.04
B62: % of Cost | D62: =F99 -> 0.20893444
B63: Building Structure: 27.5 Year | D63: =H98 -> 116993.43
B64: % of Cost | D64: =H99 -> 0.79106556
A66: COST SEGREGATION STUDY — COST DETAIL
B67: Property Category | D67: Cost | F67: 5 Year | H67: 27.5 Year
B68: Building Components
B69: Cabinets / Millwork | D69: =SUM(F69:H69) -> 4901.61 | F69: 4901.61
B70: Moldings | D70: =SUM(F70:H70) -> 2185.54 | F70: 2185.54
B71: Flooring - Vinyl Plank | D71: =SUM(F71:H71) -> 11385.26 | F71: 11385.26
B72: Window Treatments | D72: =SUM(F72:H72) -> 589.62 | F72: 589.62
B73: Specialty HVAC - Dryer Vents | D73: =SUM(F73:H73) -> 183.29 | F73: 183.29
B74: Building Signage | D74: =SUM(F74:H74) -> 96.76 | F74: 96.76
B75: Specialty Electrical - Appliances | D75: =SUM(F75:H75) -> 2980.97 | F75: 2980.97
B76: Communication / Data | D76: =SUM(F76:H76) -> 994.55 | F76: 994.55
B77: Specialty Plumbing - Kitchen Sinks / Laundry | D77: =SUM(F77:H77) -> 3427.41 | F77: 3427.41
B78: Security / Exterior Lighting | D78: =SUM(F78:H78) -> 428.96 | F78: 428.96
B79: Access Control | D79: =SUM(F79:H79) -> 43.2 | F79: 43.2
B80: Appliances | D80: =SUM(F80:H80) -> 3682.87 | F80: 3682.87
B81: Building Structure
B82: Roofing Systems | D82: =SUM(F82:H82) -> 8561.68 | H82: 8561.68
B83: Foundations | D83: =SUM(F83:H83) -> 16225.62 | H83: 16225.62
B84: HVAC | D84: =SUM(F84:H84) -> 10992.55 | H84: 10992.55
B85: Electrical | D85: =SUM(F85:H85) -> 12099.12 | H85: 12099.12
B86: Plumbing | D86: =SUM(F86:H86) -> 9715.1 | H86: 9715.1
B87: Fire Protection & Alarm | D87: =SUM(F87:H87) -> 548.48 | H87: 548.48
B88: Exterior Façade / Building Skin | D88: =SUM(F88:H88) -> 12559.71 | H88: 12559.71
B89: Doors & Frames | D89: =SUM(F89:H89) -> 5680.09 | H89: 5680.09
B90: Windows | D90: =SUM(F90:H90) -> 2911.57 | H90: 2911.57
B91: Ceiling Systems | D91: =SUM(F91:H91) -> 5070.55 | H91: 5070.55
B92: Interior Framing / Partitions | D92: =SUM(F92:H92) -> 9837.36 | H92: 9837.36
B93: Painting | D93: =SUM(F93:H93) -> 4408.6 | H93: 4408.6
... B97: Cabinets / Millwork - Restrooms | D97: =SUM(F97:H97) -> 1709.81 | H97: 1709.81
B98: Total Building Cost | D98: =SUM(D68:D97) -> 147893.47 | F98: =SUM(F68:F97) -> 30900.04 | H98: =SUM(H68:H97) -> 116993.43
B99: % of Cost | F99: =F98/D98 -> 0.20893444 | H99: =H98/D98 -> 0.79106556
A101: ASSET ALLOCATION (per After Cost Segregation schedule)
B102: Asset (as reclassified) | D102: Cost | F102: 5 Year | H102: 27.5 Year
B103: ='Building 10'!B18 -> 1 - Buillding - Apt - 5yr | D103: =SUM(F103:H103) -> 24387.48 | F103: ='Building 10'!D18 -> 24387.48
B104: ='Building 10'!B19 -> 1 - Buillding - Apt - 27.5yr | D104: =SUM(F104:H104) -> 92335.64 | H104: ='Building 10'!D19 -> 92335.64
B105: ='Building 10'!B20 -> 5 - Building - Apt - 5yr | D105: =SUM(F105:H105) -> 44.42 | F105: ='Building 10'!D20 -> 44.42
B106: ='Building 10'!B21 -> 5 - Building - Apt - 27.5yr | D106: =SUM(F106:H106) -> 168.16 | H106: ='Building 10'!D21 -> 168.16
B107: ='Building 10'!B22 -> 3 - Land Improvements - Apt - 5yr | D107: =SUM(F107:H107) -> 2300.7 | F107: ='Building 10'!D22 -> 2300.7
B108: ='Building 10'!B23 -> 3 - Land Improvements - Apt - 27.5yr | D108: =SUM(F108:H108) -> 8710.9 | H108: ='Building 10'!D23 -> 8710.9
B109: ='Building 10'!B24 -> 4 - Equipment - Apt - 5yr | D109: =SUM(F109:H109) -> 4167.44 | F109: ='Building 10'!D24 -> 4167.44
B110: ='Building 10'!B25 -> 4 - Equipment - Apt - 27.5yr | D110: =SUM(F110:H110) -> 15778.73 | H110: ='Building 10'!D25 -> 15778.73
B111: Total Allocation | D111: =SUM(D103:D110) -> 147893.47 | F111: =SUM(F103:F110) -> 30900.04 | H111: =SUM(H103:H110) -> 116993.43
B112: Check: Allocation vs. Cost Detail (should be zero) | D112: =D111-D98 -> 0

Sheet Building 11
A1: Grace Townhomes Housing, LLC
A2: Grace Townhomes — 1212 Grace Cir, Ennis, TX 75119
A3: EIN: 47-5360069 · FYE: December 31, 2024 · Year of Change: 1/1/2024
A4: Building 11 — Attachment to Form 3115 (DCN #7, Rev. Proc. 2024-23 §6.01)
A5: Source: CSSI Report #107752-11, "#107752-11_Grace Townhomes - 3115 - Combined R2.pdf"
A7: CALCULATION OF §481(a) ADJUSTMENT — REGULAR TAX
A8: As Previously Filed
A9: Asset | B9: Property Description | C9: Date In Service | D9: Cost | E9: Sec 179 Exp | F9: Bonus Amt | G9: Tax Prior Depreciation | H9: Tax Current Depreciation | I9: End Depreciation | J9: Net Book Value | K9: Method | L9: Period
A10: 1 | B10: 1 - Buillding - Apt | C10: 12/17/15 | D10: 91140.5 | E10: 0 | F10: 0 | G10: 26651.36 | H10: 3314.2 | I10: =G10+H10 -> 29965.56 | J10: =D10-I10 -> 61174.94 | K10: S/L | L10: 27.5
A11: 2 | B11: 5 - Building - Apt | C11: 1/14/16 | D11: 165.99 | E11: 0 | F11: 0 | G11: 48.07 | H11: 6.04 | I11: =G11+H11 -> 54.11 | J11: =D11-I11 -> 111.88 | K11: S/L | L11: 27.5
A12: 3 | B12: 3 - Land Improvements - Apt | C12: 12/17/15 | D12: 8598.15 | E12: 0 | F12: 0 | G12: 5035.65 | H12: 507.3 | I12: =G12+H12 -> 5542.95 | J12: =D12-I12 -> 3055.2 | K12: 150DB | L12: 15.0
A13: 4 | B13: 4 - Equipment - Apt | C13: 12/17/15 | D13: 15574.5 | E13: 0 | F13: 0 | G13: 15055.35 | H13: 0 | I13: =G13+H13 -> 15055.35 | J13: =D13-I13 -> 519.15 | K13: 200DB | L13: 5.0
B14: Grand Total | D14: =SUM(D10:D13) -> 115479.14 | E14: =SUM(E10:E13) -> 0 | F14: =SUM(F10:F13) -> 0 | G14: =SUM(G10:G13) -> 46790.43 | H14: =SUM(H10:H13) -> 3827.54 | I14: =SUM(I10:I13) -> 50617.97 | J14: =SUM(J10:J13) -> 64861.17
A16: After Cost Segregation Correction
A17: Asset | B17: Property Description | C17: Date In Service | D17: Cost | E17: Sec 179 Exp | F17: Bonus Amt | G17: Tax Prior Depreciation | H17: Tax Current Depreciation | I17: End Depreciation | J17: Net Book Value | K17: Method | L17: Period
A18: 1 | B18: 1 - Buillding - Apt - 5yr | C18: 12/17/15 | D18: 21279.35 | E18: 0 | F18: 0 | G18: 21279.35 | H18: 0 | I18: =G18+H18 -> 21279.35 | J18: =D18-I18 -> 0 | K18: 200DB | L18: 5.0
A19: 2 | B19: 1 - Buillding - Apt - 27.5yr | C19: 12/17/15 | D19: 69861.15 | E19: 0 | F19: 0 | G19: 20429.13 | H19: 2540.41 | I19: =G19+H19 -> 22969.54 | J19: =D19-I19 -> 46891.61 | K19: S/L | L19: 27.5
A20: 3 | B20: 5 - Building - Apt - 5yr | C20: 1/14/16 | D20: 38.76 | E20: 0 | F20: 0 | G20: 38.76 | H20: 0 | I20: =G20+H20 -> 38.76 | J20: =D20-I20 -> 0 | K20: 200DB | L20: 5.0
A21: 4 | B21: 5 - Building - Apt - 27.5yr | C21: 1/14/16 | D21: 127.23 | E21: 0 | F21: 0 | G21: 36.84 | H21: 4.63 | I21: =G21+H21 -> 41.47 | J21: =D21-I21 -> 85.76 | K21: S/L | L21: 27.5
A22: 5 | B22: 3 - Land Improvements - Apt 5yr | C22: 12/17/15 | D22: 2007.48 | E22: 0 | F22: 0 | G22: 2007.48 | H22: 0 | I22: =G22+H22 -> 2007.48 | J22: =D22-I22 -> 0 | K22: 200DB | L22: 5.0
A23: 6 | B23: 3 - Land Improvements - Apt 27.5yr | C23: 12/17/15 | D23: 6590.67 | E23: 0 | F23: 0 | G23: 1927.27 | H23: 239.66 | I23: =G23+H23 -> 2166.93 | J23: =D23-I23 -> 4423.74 | K23: S/L | L23: 27.5
A24: 7 | B24: 4 - Equipment - Apt - 5yr | C24: 12/17/15 | D24: 3636.33 | E24: 0 | F24: 0 | G24: 3636.33 | H24: 0 | I24: =G24+H24 -> 3636.33 | J24: =D24-I24 -> 0 | K24: 200DB | L24: 5.0
A25: 8 | B25: 4 - Equipment - Apt - 27.5yr | C25: 12/17/15 | D25: 11938.19 | E25: 0 | F25: 0 | G25: 3491.05 | H25: 434.12 | I25: =G25+H25 -> 3925.17 | J25: =D25-I25 -> 8013.02 | K25: S/L | L25: 27.5
B26: Grand Total | D26: =SUM(D18:D25) -> 115479.16 | E26: =SUM(E18:E25) -> 0 | F26: =SUM(F18:F25) -> 0 | G26: =SUM(G18:G25) -> 52846.21 | H26: =SUM(H18:H25) -> 3218.82 | I26: =SUM(I18:I25) -> 56065.03 | J26: =SUM(J18:J25) -> 59414.13
B28: Section 481(a) Adjustment — Regular Tax
B29: Depreciation reported previously | D29: =I14 -> 50617.97
B30: Cost Segregation Corrected Depreciation | D30: =I26 -> 56065.03
B31: Section 481(a) Adjustment — Regular Tax | D31: =D29-D30 -> -5447.06
A33: CALCULATION OF §481(a) ADJUSTMENT — AMT
A34: As Previously Filed — AMT
A35: Asset | B35: Property Description | C35: Date In Service | D35: Cost | E35: Sec 179 Exp | F35: Bonus Amt | G35: AMT Prior Depreciation | H35: AMT Current Depreciation | I35: End Depreciation | J35: Net Book Value | K35: Method | L35: Period
A36: 1 | B36: 1 - Buillding - Apt | C36: 12/17/15 | D36: 91140.5 | E36: 0 | F36: 0 | G36: 26651.36 | H36: 3314.2 | I36: =G36+H36 -> 29965.56 | J36: =D36-I36 -> 61174.94 | K36: S/L | L36: 27.5
A37: 2 | B37: 5 - Building - Apt | C37: 1/14/16 | D37: 165.99 | E37: 0 | F37: 0 | G37: 48.07 | H37: 6.04 | I37: =G37+H37 -> 54.11 | J37: =D37-I37 -> 111.88 | K37: S/L | L37: 27.5
A38: 3 | B38: 3 - Land Improvements - Apt | C38: 12/17/15 | D38: 8598.15 | E38: 0 | F38: 0 | G38: 5035.65 | H38: 507.3 | I38: =G38+H38 -> 5542.95 | J38: =D38-I38 -> 3055.2 | K38: 150DB | L38: 15.0
A39: 4 | B39: 4 - Equipment - Apt | C39: 12/17/15 | D39: 15574.5 | E39: 0 | F39: 0 | G39: 15055.35 | H39: 0 | I39: =G39+H39 -> 15055.35 | J39: =D39-I39 -> 519.15 | K39: 200DB | L39: 5.0
B40: Grand Total | D40: =SUM(D36:D39) -> 115479.14 | E40: =SUM(E36:E39) -> 0 | F40: =SUM(F36:F39) -> 0 | G40: =SUM(G36:G39) -> 46790.43 | H40: =SUM(H36:H39) -> 3827.54 | I40: =SUM(I36:I39) -> 50617.97 | J40: =SUM(J36:J39) -> 64861.17
A42: After Cost Segregation Correction — AMT
A43: Asset | B43: Property Description | C43: Date In Service | D43: Cost | E43: Sec 179 Exp | F43: Bonus Amt | G43: AMT Prior Depreciation | H43: AMT Current Depreciation | I43: End Depreciation | J43: Net Book Value | K43: Method | L43: Period
A44: 1 | B44: 1 - Buillding - Apt - 5yr | C44: 12/17/15 | D44: 21279.35 | E44: 0 | F44: 0 | G44: 21279.35 | H44: 0 | I44: =G44+H44 -> 21279.35 | J44: =D44-I44 -> 0 | K44: 200DB | L44: 5.0
A45: 2 | B45: 1 - Buillding - Apt - 27.5yr | C45: 12/17/15 | D45: 69861.15 | E45: 0 | F45: 0 | G45: 20429.13 | H45: 2540.41 | I45: =G45+H45 -> 22969.54 | J45: =D45-I45 -> 46891.61 | K45: S/L | L45: 27.5
A46: 3 | B46: 5 - Building - Apt - 5yr | C46: 1/14/16 | D46: 38.76 | E46: 0 | F46: 0 | G46: 38.76 | H46: 0 | I46: =G46+H46 -> 38.76 | J46: =D46-I46 -> 0 | K46: 200DB | L46: 5.0
A47: 4 | B47: 5 - Building - Apt - 27.5yr | C47: 1/14/16 | D47: 127.23 | E47: 0 | F47: 0 | G47: 36.84 | H47: 4.63 | I47: =G47+H47 -> 41.47 | J47: =D47-I47 -> 85.76 | K47: S/L | L47: 27.5
A48: 5 | B48: 3 - Land Improvements - Apt 5yr | C48: 12/17/15 | D48: 2007.48 | E48: 0 | F48: 0 | G48: 2007.48 | H48: 0 | I48: =G48+H48 -> 2007.48 | J48: =D48-I48 -> 0 | K48: 200DB | L48: 5.0
A49: 6 | B49: 3 - Land Improvements - Apt 27.5yr | C49: 12/17/15 | D49: 6590.67 | E49: 0 | F49: 0 | G49: 1927.27 | H49: 239.66 | I49: =G49+H49 -> 2166.93 | J49: =D49-I49 -> 4423.74 | K49: S/L | L49: 27.5
A50: 7 | B50: 4 - Equipment - Apt - 5yr | C50: 12/17/15 | D50: 3636.33 | E50: 0 | F50: 0 | G50: 3636.33 | H50: 0 | I50: =G50+H50 -> 3636.33 | J50: =D50-I50 -> 0 | K50: 200DB | L50: 5.0
A51: 8 | B51: 4 - Equipment - Apt - 27.5yr | C51: 12/17/15 | D51: 11938.19 | E51: 0 | F51: 0 | G51: 3491.05 | H51: 434.12 | I51: =G51+H51 -> 3925.17 | J51: =D51-I51 -> 8013.02 | K51: S/L | L51: 27.5
B52: Grand Total | D52: =SUM(D44:D51) -> 115479.16 | E52: =SUM(E44:E51) -> 0 | F52: =SUM(F44:F51) -> 0 | G52: =SUM(G44:G51) -> 52846.21 | H52: =SUM(H44:H51) -> 3218.82 | I52: =SUM(I44:I51) -> 56065.03 | J52: =SUM(J44:J51) -> 59414.13
B54: Section 481(a) Adjustment — AMT
B55: Depreciation reported previously | D55: =I40 -> 50617.97
B56: Cost Segregation Corrected Depreciation | D56: =I52 -> 56065.03
B57: Section 481(a) Adjustment — AMT | D57: =D55-D56 -> -5447.06
A59: COST SEGREGATION STUDY — COST SUMMARY
B60: Total Building Cost | D60: =D98 -> 115479.14
B61: Building Components: 5 Year | D61: =F98 -> 26961.9
B62: % of Cost | D62: =F99 -> 0.23347853
B63: Building Structure: 27.5 Year | D63: =H98 -> 88517.24
B64: % of Cost | D64: =H99 -> 0.76652147
A66: COST SEGREGATION STUDY — COST DETAIL
B67: Property Category | D67: Cost | F67: 5 Year | H67: 27.5 Year
B68: Building Components
B69: Cabinets / Millwork | D69: =SUM(F69:H69) -> 4785.17 | F69: 4785.17
B70: Moldings | D70: =SUM(F70:H70) -> 1941.11 | F70: 1941.11
B71: Flooring - Vinyl Plank | D71: =SUM(F71:H71) -> 7939.87 | F71: 7939.87
B72: Window Treatments | D72: =SUM(F72:H72) -> 428.82 | F72: 428.82
B73: Specialty HVAC - Dryer Vents | D73: =SUM(F73:H73) -> 183.29 | F73: 183.29
B74: Building Signage | D74: =SUM(F74:H74) -> 96.76 | F74: 96.76
B75: Specialty Electrical - Appliances | D75: =SUM(F75:H75) -> 2980.97 | F75: 2980.97
B76: Communication / Data | D76: =SUM(F76:H76) -> 693.58 | F76: 693.58
B77: Specialty Plumbing - Kitchen Sinks / Laundry | D77: =SUM(F77:H77) -> 3427.41 | F77: 3427.41
B78: Security / Exterior Lighting | D78: =SUM(F78:H78) -> 758.85 | F78: 758.85
B79: Access Control | D79: =SUM(F79:H79) -> 43.2 | F79: 43.2
B80: Appliances | D80: =SUM(F80:H80) -> 3682.87 | F80: 3682.87
B81: Building Structure
B82: Roofing Systems | D82: =SUM(F82:H82) -> 6281.12 | H82: 6281.12
B83: Foundations | D83: =SUM(F83:H83) -> 12157.7 | H83: 12157.7
B84: HVAC | D84: =SUM(F84:H84) -> 7610.53 | H84: 7610.53
B85: Electrical | D85: =SUM(F85:H85) -> 8437.69 | H85: 8437.69
B86: Plumbing | D86: =SUM(F86:H86) -> 6775.13 | H86: 6775.13
B87: Fire Protection & Alarm | D87: =SUM(F87:H87) -> 378.96 | H87: 378.96
B88: Exterior Façade / Building Skin | D88: =SUM(F88:H88) -> 10712.7 | H88: 10712.7
B89: Doors & Frames | D89: =SUM(F89:H89) -> 5035.68 | H89: 5035.68
B90: Windows | D90: =SUM(F90:H90) -> 2117.51 | H90: 2117.51
B91: Ceiling Systems | D91: =SUM(F91:H91) -> 3536.09 | H91: 3536.09
B92: Interior Framing / Partitions | D92: =SUM(F92:H92) -> 8613.79 | H92: 8613.79
B93: Painting | D93: =SUM(F93:H93) -> 3604.7 | H93: 3604.7
... B97: Cabinets / Millwork - Restrooms | D97: =SUM(F97:H97) -> 811.57 | H97: 811.57
B98: Total Building Cost | D98: =SUM(D68:D97) -> 115479.14 | F98: =SUM(F68:F97) -> 26961.9 | H98: =SUM(H68:H97) -> 88517.24
B99: % of Cost | F99: =F98/D98 -> 0.23347853 | H99: =H98/D98 -> 0.76652147
A101: ASSET ALLOCATION (per After Cost Segregation schedule)
B102: Asset (as reclassified) | D102: Cost | F102: 5 Year | H102: 27.5 Year
B103: ='Building 11'!B18 -> 1 - Buillding - Apt - 5yr | D103: =SUM(F103:H103) -> 21279.35 | F103: ='Building 11'!D18 -> 21279.35
B104: ='Building 11'!B19 -> 1 - Buillding - Apt - 27.5yr | D104: =SUM(F104:H104) -> 69861.15 | H104: ='Building 11'!D19 -> 69861.15
B105: ='Building 11'!B20 -> 5 - Building - Apt - 5yr | D105: =SUM(F105:H105) -> 38.76 | F105: ='Building 11'!D20 -> 38.76
B106: ='Building 11'!B21 -> 5 - Building - Apt - 27.5yr | D106: =SUM(F106:H106) -> 127.23 | H106: ='Building 11'!D21 -> 127.23
B107: ='Building 11'!B22 -> 3 - Land Improvements - Apt 5yr | D107: =SUM(F107:H107) -> 2007.48 | F107: ='Building 11'!D22 -> 2007.48
B108: ='Building 11'!B23 -> 3 - Land Improvements - Apt 27.5yr | D108: =SUM(F108:H108) -> 6590.67 | H108: ='Building 11'!D23 -> 6590.67
B109: ='Building 11'!B24 -> 4 - Equipment - Apt - 5yr | D109: =SUM(F109:H109) -> 3636.33 | F109: ='Building 11'!D24 -> 3636.33
B110: ='Building 11'!B25 -> 4 - Equipment - Apt - 27.5yr | D110: =SUM(F110:H110) -> 11938.19 | H110: ='Building 11'!D25 -> 11938.19
B111: Total Allocation | D111: =SUM(D103:D110) -> 115479.16 | F111: =SUM(F103:F110) -> 26961.92 | H111: =SUM(H103:H110) -> 88517.24
B112: Check: Allocation vs. Cost Detail (should be zero) | D112: =D111-D98 -> 0.02

Sheet Building 12
A1: Grace Townhomes Housing, LLC
A2: Grace Townhomes — 1212 Grace Cir, Ennis, TX 75119
A3: EIN: 47-5360069 · FYE: December 31, 2024 · Year of Change: 1/1/2024
A4: Building 12 — Attachment to Form 3115 (DCN #7, Rev. Proc. 2024-23 §6.01)
A5: Source: CSSI Report #107752-11, "#107752-11_Grace Townhomes - 3115 - Combined R2.pdf"
A7: CALCULATION OF §481(a) ADJUSTMENT — REGULAR TAX
A8: As Previously Filed
A9: Asset | B9: Property Description | C9: Date In Service | D9: Cost | E9: Sec 179 Exp | F9: Bonus Amt | G9: Tax Prior Depreciation | H9: Tax Current Depreciation | I9: End Depreciation | J9: Net Book Value | K9: Method | L9: Period
A10: 1 | B10: 1 - Buillding - Apt | C10: 12/17/15 | D10: 212191.05 | E10: 0 | F10: 0 | G10: 62049.02 | H10: 7716.04 | I10: =G10+H10 -> 69765.06 | J10: =D10-I10 -> 142425.99 | K10: S/L | L10: 27.5
A11: 2 | B11: 5 - Building - Apt | C11: 1/14/16 | D11: 386.45 | E11: 0 | F11: 0 | G11: 111.91 | H11: 14.06 | I11: =G11+H11 -> 125.97 | J11: =D11-I11 -> 260.48 | K11: S/L | L11: 27.5
A12: 3 | B12: 3 - Land Improvements - Apt | C12: 12/17/15 | D12: 20018 | E12: 0 | F12: 0 | G12: 11723.87 | H12: 1181.07 | I12: =G12+H12 -> 12904.94 | J12: =D12-I12 -> 7113.06 | K12: 150DB | L12: 15.0
A13: 4 | B13: 4 - Equipment - Apt | C13: 12/17/15 | D13: 36260.17 | E13: 0 | F13: 0 | G13: 35051.5 | H13: 0 | I13: =G13+H13 -> 35051.5 | J13: =D13-I13 -> 1208.67 | K13: 200DB | L13: 5.0
B14: Grand Total | D14: =SUM(D10:D13) -> 268855.67 | E14: =SUM(E10:E13) -> 0 | F14: =SUM(F10:F13) -> 0 | G14: =SUM(G10:G13) -> 108936.3 | H14: =SUM(H10:H13) -> 8911.17 | I14: =SUM(I10:I13) -> 117847.47 | J14: =SUM(J10:J13) -> 151008.2
A16: After Cost Segregation Correction
A17: Asset | B17: Property Description | C17: Date In Service | D17: Cost | E17: Sec 179 Exp | F17: Bonus Amt | G17: Tax Prior Depreciation | H17: Tax Current Depreciation | I17: End Depreciation | J17: Net Book Value | K17: Method | L17: Period
A18: 1 | B18: 1 - Buillding - Apt - 5yr | C18: 12/17/15 | D18: 41085.46 | E18: 0 | F18: 0 | G18: 41085.46 | H18: 0 | I18: =G18+H18 -> 41085.46 | J18: =D18-I18 -> 0 | K18: 200DB | L18: 5.0
A19: 2 | B19: 1 - Buillding - Apt - 27.5yr | C19: 12/17/15 | D19: 171105.59 | E19: 0 | F19: 0 | G19: 50035.41 | H19: 6222.02 | I19: =G19+H19 -> 56257.43 | J19: =D19-I19 -> 114848.16 | K19: S/L | L19: 27.5
A20: 3 | B20: 5 - Building - Apt - 5yr | C20: 1/14/16 | D20: 74.83 | E20: 0 | F20: 0 | G20: 74.83 | H20: 0 | I20: =G20+H20 -> 74.83 | J20: =D20-I20 -> 0 | K20: 200DB | L20: 5.0
A21: 4 | B21: 5 - Building - Apt - 27.5yr | C21: 1/14/16 | D21: 311.62 | E21: 0 | F21: 0 | G21: 90.17 | H21: 11.33 | I21: =G21+H21 -> 101.5 | J21: =D21-I21 -> 210.12 | K21: S/L | L21: 27.5
A22: 5 | B22: 3 - Land Improvements - Apt - 5yr | C22: 12/17/15 | D22: 3875.98 | E22: 0 | F22: 0 | G22: 3875.98 | H22: 0 | I22: =G22+H22 -> 3875.98 | J22: =D22-I22 -> 0 | K22: 200DB | L22: 5.0
A23: 6 | B23: 3 - Land Improvements - Apt - 27.5yr | C23: 12/17/15 | D23: 16142.02 | E23: 0 | F23: 0 | G23: 4720.3 | H23: 586.98 | I23: =G23+H23 -> 5307.28 | J23: =D23-I23 -> 10834.74 | K23: S/L | L23: 27.5
A24: 7 | B24: 4 - Equipment - Apt - 5yr | C24: 12/17/15 | D24: 7020.87 | E24: 0 | F24: 0 | G24: 7020.87 | H24: 0 | I24: =G24+H24 -> 7020.87 | J24: =D24-I24 -> 0 | K24: 200DB | L24: 5.0
A25: 8 | B25: 4 - Equipment - Apt - 27.5yr | C25: 12/17/15 | D25: 29239.3 | E25: 0 | F25: 0 | G25: 8550.3 | H25: 1063.25 | I25: =G25+H25 -> 9613.55 | J25: =D25-I25 -> 19625.75 | K25: S/L | L25: 27.5
B26: Grand Total | D26: =SUM(D18:D25) -> 268855.67 | E26: =SUM(E18:E25) -> 0 | F26: =SUM(F18:F25) -> 0 | G26: =SUM(G18:G25) -> 115453.32 | H26: =SUM(H18:H25) -> 7883.58 | I26: =SUM(I18:I25) -> 123336.9 | J26: =SUM(J18:J25) -> 145518.77
B28: Section 481(a) Adjustment — Regular Tax
B29: Depreciation reported previously | D29: =I14 -> 117847.47
B30: Cost Segregation Corrected Depreciation | D30: =I26 -> 123336.9
B31: Section 481(a) Adjustment — Regular Tax | D31: =D29-D30 -> -5489.43
A33: CALCULATION OF §481(a) ADJUSTMENT — AMT
A34: As Previously Filed — AMT
A35: Asset | B35: Property Description | C35: Date In Service | D35: Cost | E35: Sec 179 Exp | F35: Bonus Amt | G35: AMT Prior Depreciation | H35: AMT Current Depreciation | I35: End Depreciation | J35: Net Book Value | K35: Method | L35: Period
A36: 1 | B36: 1 - Buillding - Apt | C36: 12/17/15 | D36: 212191.05 | E36: 0 | F36: 0 | G36: 62049.02 | H36: 7716.04 | I36: =G36+H36 -> 69765.06 | J36: =D36-I36 -> 142425.99 | K36: S/L | L36: 27.5
A37: 2 | B37: 5 - Building - Apt | C37: 1/14/16 | D37: 386.45 | E37: 0 | F37: 0 | G37: 111.91 | H37: 14.06 | I37: =G37+H37 -> 125.97 | J37: =D37-I37 -> 260.48 | K37: S/L | L37: 27.5
A38: 3 | B38: 3 - Land Improvements - Apt | C38: 12/17/15 | D38: 20018 | E38: 0 | F38: 0 | G38: 11723.87 | H38: 1181.07 | I38: =G38+H38 -> 12904.94 | J38: =D38-I38 -> 7113.06 | K38: 150DB | L38: 15.0
A39: 4 | B39: 4 - Equipment - Apt | C39: 12/17/15 | D39: 36260.17 | E39: 0 | F39: 0 | G39: 35051.5 | H39: 0 | I39: =G39+H39 -> 35051.5 | J39: =D39-I39 -> 1208.67 | K39: 200DB | L39: 5.0
B40: Grand Total | D40: =SUM(D36:D39) -> 268855.67 | E40: =SUM(E36:E39) -> 0 | F40: =SUM(F36:F39) -> 0 | G40: =SUM(G36:G39) -> 108936.3 | H40: =SUM(H36:H39) -> 8911.17 | I40: =SUM(I36:I39) -> 117847.47 | J40: =SUM(J36:J39) -> 151008.2
A42: After Cost Segregation Correction — AMT
A43: Asset | B43: Property Description | C43: Date In Service | D43: Cost | E43: Sec 179 Exp | F43: Bonus Amt | G43: AMT Prior Depreciation | H43: AMT Current Depreciation | I43: End Depreciation | J43: Net Book Value | K43: Method | L43: Period
A44: 1 | B44: 1 - Buillding - Apt - 5yr | C44: 12/17/15 | D44: 41085.46 | E44: 0 | F44: 0 | G44: 41085.46 | H44: 0 | I44: =G44+H44 -> 41085.46 | J44: =D44-I44 -> 0 | K44: 200DB | L44: 5.0
A45: 2 | B45: 1 - Buillding - Apt - 27.5yr | C45: 12/17/15 | D45: 171105.59 | E45: 0 | F45: 0 | G45: 50035.41 | H45: 6222.02 | I45: =G45+H45 -> 56257.43 | J45: =D45-I45 -> 114848.16 | K45: S/L | L45: 27.5
A46: 3 | B46: 5 - Building - Apt - 5yr | C46: 1/14/16 | D46: 74.83 | E46: 0 | F46: 0 | G46: 74.83 | H46: 0 | I46: =G46+H46 -> 74.83 | J46: =D46-I46 -> 0 | K46: 200DB | L46: 5.0
A47: 4 | B47: 5 - Building - Apt - 27.5yr | C47: 1/14/16 | D47: 311.62 | E47: 0 | F47: 0 | G47: 90.17 | H47: 11.33 | I47: =G47+H47 -> 101.5 | J47: =D47-I47 -> 210.12 | K47: S/L | L47: 27.5
A48: 5 | B48: 3 - Land Improvements - Apt - 5yr | C48: 12/17/15 | D48: 3875.98 | E48: 0 | F48: 0 | G48: 3875.98 | H48: 0 | I48: =G48+H48 -> 3875.98 | J48: =D48-I48 -> 0 | K48: 200DB | L48: 5.0
A49: 6 | B49: 3 - Land Improvements - Apt - 27.5yr | C49: 12/17/15 | D49: 16142.02 | E49: 0 | F49: 0 | G49: 4720.3 | H49: 586.98 | I49: =G49+H49 -> 5307.28 | J49: =D49-I49 -> 10834.74 | K49: S/L | L49: 27.5
A50: 7 | B50: 4 - Equipment - Apt - 5yr | C50: 12/17/15 | D50: 7020.87 | E50: 0 | F50: 0 | G50: 7020.87 | H50: 0 | I50: =G50+H50 -> 7020.87 | J50: =D50-I50 -> 0 | K50: 200DB | L50: 5.0
A51: 8 | B51: 4 - Equipment - Apt - 27.5yr | C51: 12/17/15 | D51: 29239.3 | E51: 0 | F51: 0 | G51: 8550.3 | H51: 1063.25 | I51: =G51+H51 -> 9613.55 | J51: =D51-I51 -> 19625.75 | K51: S/L | L51: 27.5
B52: Grand Total | D52: =SUM(D44:D51) -> 268855.67 | E52: =SUM(E44:E51) -> 0 | F52: =SUM(F44:F51) -> 0 | G52: =SUM(G44:G51) -> 115453.32 | H52: =SUM(H44:H51) -> 7883.58 | I52: =SUM(I44:I51) -> 123336.9 | J52: =SUM(J44:J51) -> 145518.77
B54: Section 481(a) Adjustment — AMT
B55: Depreciation reported previously | D55: =I40 -> 117847.47
B56: Cost Segregation Corrected Depreciation | D56: =I52 -> 123336.9
B57: Section 481(a) Adjustment — AMT | D57: =D55-D56 -> -5489.43
A59: COST SEGREGATION STUDY — COST SUMMARY
B60: Total Building Cost | D60: =D99 -> 268855.67
B61: Building Components: 5 Year | D61: =F99 -> 52057.14
B62: % of Cost | D62: =F100 -> 0.19362485
B63: Building Structure: 27.5 Year | D63: =H99 -> 216798.53
B64: % of Cost | D64: =H100 -> 0.80637515
A66: COST SEGREGATION STUDY — COST DETAIL
B67: Property Category | D67: Cost | F67: 5 Year | H67: 27.5 Year
B68: Building Components
B69: Cabinets / Millwork | D69: =SUM(F69:H69) -> 7759.94 | F69: 7759.94
B70: Moldings | D70: =SUM(F70:H70) -> 4601.14 | F70: 4601.14
B71: Flooring - Vinyl Plank | D71: =SUM(F71:H71) -> 18695.69 | F71: 18695.69
B72: Window Treatments | D72: =SUM(F72:H72) -> 2235.2 | F72: 2235.2
B73: Specialty HVAC - Dryer Vents | D73: =SUM(F73:H73) -> 274.94 | F73: 274.94
B74: Building Signage | D74: =SUM(F74:H74) -> 120.68 | F74: 120.68
B75: Specialty Electrical - Appliances | D75: =SUM(F75:H75) -> 4471.44 | F75: 4471.44
B76: Communication / Data | D76: =SUM(F76:H76) -> 1633.14 | F76: 1633.14
B77: Specialty Plumbing - Kitchen Sinks / Laundry | D77: =SUM(F77:H77) -> 5141.11 | F77: 5141.11
B78: Security / Exterior Lighting | D78: =SUM(F78:H78) -> 1534.74 | F78: 1534.74
B79: Access Control | D79: =SUM(F79:H79) -> 64.8 | F79: 64.8
B80: Appliances | D80: =SUM(F80:H80) -> 5524.32 | F80: 5524.32
B81: Building Structure
B82: Roofing Systems | D82: =SUM(F82:H82) -> 10400.92 | H82: 10400.92
B83: Foundations | D83: =SUM(F83:H83) -> 19732.45 | H83: 19732.45
B84: HVAC | D84: =SUM(F84:H84) -> 18076.85 | H84: 18076.85
B85: Electrical | D85: =SUM(F85:H85) -> 19867.9 | H85: 19867.9
B86: Plumbing | D86: =SUM(F86:H86) -> 15953.11 | H86: 15953.11
B87: Fire Protection & Alarm | D87: =SUM(F87:H87) -> 1077 | H87: 1077
B88: Exterior Façade / Building Skin | D88: =SUM(F88:H88) -> 24515.03 | H88: 24515.03
B89: Doors & Frames | D89: =SUM(F89:H89) -> 18444.72 | H89: 18444.72
B90: Windows | D90: =SUM(F90:H90) -> 11037.53 | H90: 11037.53
B91: Ceiling Systems | D91: =SUM(F91:H91) -> 8326.32 | H91: 8326.32
B92: Interior Framing / Partitions | D92: =SUM(F92:H92) -> 20278.2 | H92: 20278.2
B93: Painting | D93: =SUM(F93:H93) -> 8613.97 | H93: 8613.97
... B98: Cabinets / Millwork - Restrooms | D98: =SUM(F98:H98) -> 2564.71 | H98: 2564.71
B99: Total Building Cost | D99: =SUM(D68:D98) -> 268855.67 | F99: =SUM(F68:F98) -> 52057.14 | H99: =SUM(H68:H98) -> 216798.53
B100: % of Cost | F100: =F99/D99 -> 0.19362485 | H100: =H99/D99 -> 0.80637515
A102: ASSET ALLOCATION (per After Cost Segregation schedule)
B103: Asset (as reclassified) | D103: Cost | F103: 5 Year | H103: 27.5 Year
B104: ='Building 12'!B18 -> 1 - Buillding - Apt - 5yr | D104: =SUM(F104:H104) -> 41085.46 | F104: ='Building 12'!D18 -> 41085.46
B105: ='Building 12'!B19 -> 1 - Buillding - Apt - 27.5yr | D105: =SUM(F105:H105) -> 171105.59 | H105: ='Building 12'!D19 -> 171105.59
B106: ='Building 12'!B20 -> 5 - Building - Apt - 5yr | D106: =SUM(F106:H106) -> 74.83 | F106: ='Building 12'!D20 -> 74.83
B107: ='Building 12'!B21 -> 5 - Building - Apt - 27.5yr | D107: =SUM(F107:H107) -> 311.62 | H107: ='Building 12'!D21 -> 311.62
B108: ='Building 12'!B22 -> 3 - Land Improvements - Apt - 5yr | D108: =SUM(F108:H108) -> 3875.98 | F108: ='Building 12'!D22 -> 3875.98
B109: ='Building 12'!B23 -> 3 - Land Improvements - Apt - 27.5yr | D109: =SUM(F109:H109) -> 16142.02 | H109: ='Building 12'!D23 -> 16142.02
B110: ='Building 12'!B24 -> 4 - Equipment - Apt - 5yr | D110: =SUM(F110:H110) -> 7020.87 | F110: ='Building 12'!D24 -> 7020.87
B111: ='Building 12'!B25 -> 4 - Equipment - Apt - 27.5yr | D111: =SUM(F111:H111) -> 29239.3 | H111: ='Building 12'!D25 -> 29239.3
B112: Total Allocation | D112: =SUM(D104:D111) -> 268855.67 | F112: =SUM(F104:F111) -> 52057.14 | H112: =SUM(H104:H111) -> 216798.53
B113: Check: Allocation vs. Cost Detail (should be zero) | D113: =D112-D99 -> 0

Sheet Building 13
A1: Grace Townhomes Housing, LLC
A2: Grace Townhomes — 1212 Grace Cir, Ennis, TX 75119
A3: EIN: 47-5360069 · FYE: December 31, 2024 · Year of Change: 1/1/2024
A4: Building 13 — Attachment to Form 3115 (DCN #7, Rev. Proc. 2024-23 §6.01)
A5: Source: CSSI Report #107752-11, "#107752-11_Grace Townhomes - 3115 - Combined R2.pdf"
A7: CALCULATION OF §481(a) ADJUSTMENT — REGULAR TAX
A8: As Previously Filed
A9: Asset | B9: Property Description | C9: Date In Service | D9: Cost | E9: Sec 179 Exp | F9: Bonus Amt | G9: Tax Prior Depreciation | H9: Tax Current Depreciation | I9: End Depreciation | J9: Net Book Value | K9: Method | L9: Period
A10: 1 | B10: 1 - Buillding - Apt | C10: 12/17/15 | D10: 282065.31 | E10: 0 | F10: 0 | G10: 82481.69 | H10: 10256.92 | I10: =G10+H10 -> 92738.61 | J10: =D10-I10 -> 189326.7 | K10: S/L | L10: 27.5
A11: 2 | B11: 5 - Building - Apt | C11: 1/14/16 | D11: 513.71 | E11: 0 | F11: 0 | G11: 148.76 | H11: 18.69 | I11: =G11+H11 -> 167.45 | J11: =D11-I11 -> 346.26 | K11: S/L | L11: 27.5
A12: 3 | B12: 3 - Land Improvements - Apt | C12: 12/17/15 | D12: 26609.91 | E12: 0 | F12: 0 | G12: 15584.54 | H12: 1570 | I12: =G12+H12 -> 17154.54 | J12: =D12-I12 -> 9455.37 | K12: 150DB | L12: 15.0
A13: 4 | B13: 4 - Equipment - Apt | C13: 12/17/15 | D13: 48200.59 | E13: 0 | F13: 0 | G13: 46593.9 | H13: 0 | I13: =G13+H13 -> 46593.9 | J13: =D13-I13 -> 1606.69 | K13: 200DB | L13: 5.0
B14: Grand Total | D14: =SUM(D10:D13) -> 357389.52 | E14: =SUM(E10:E13) -> 0 | F14: =SUM(F10:F13) -> 0 | G14: =SUM(G10:G13) -> 144808.89 | H14: =SUM(H10:H13) -> 11845.61 | I14: =SUM(I10:I13) -> 156654.5 | J14: =SUM(J10:J13) -> 200735.02
A16: After Cost Segregation Correction
A17: Asset | B17: Property Description | C17: Date In Service | D17: Cost | E17: Sec 179 Exp | F17: Bonus Amt | G17: Tax Prior Depreciation | H17: Tax Current Depreciation | I17: End Depreciation | J17: Net Book Value | K17: Method | L17: Period
A18: 1 | B18: 1 - Buillding - Apt - 5yr | C18: 12/17/15 | D18: 55838.26 | E18: 0 | F18: 0 | G18: 55838.26 | H18: 0 | I18: =G18+H18 -> 55838.26 | J18: =D18-I18 -> 0 | K18: 200DB | L18: 5.0
A19: 2 | B19: 1 - Buillding - Apt - 27.5yr | C19: 12/17/15 | D19: 226227.05 | E19: 0 | F19: 0 | G19: 66154.29 | H19: 8226.44 | I19: =G19+H19 -> 74380.73 | J19: =D19-I19 -> 151846.32 | K19: S/L | L19: 27.5
A20: 3 | B20: 5 - Building - Apt - 5yr | C20: 1/14/16 | D20: 101.7 | E20: 0 | F20: 0 | G20: 101.7 | H20: 0 | I20: =G20+H20 -> 101.7 | J20: =D20-I20 -> 0 | K20: 200DB | L20: 5.0
A21: 4 | B21: 5 - Building - Apt - 27.5yr | C21: 1/14/16 | D21: 412.01 | E21: 0 | F21: 0 | G21: 119.22 | H21: 14.98 | I21: =G21+H21 -> 134.2 | J21: =D21-I21 -> 277.81 | K21: S/L | L21: 27.5
A22: 5 | B22: 3 - Land Improvements - Apt - 5yr | C22: 12/17/15 | D22: 5267.76 | E22: 0 | F22: 0 | G22: 5267.76 | H22: 0 | I22: =G22+H22 -> 5267.76 | J22: =D22-I22 -> 0 | K22: 200DB | L22: 5.0
A23: 6 | B23: 3 - Land Improvements - Apt - 27.5yr | C23: 12/17/15 | D23: 21342.15 | E23: 0 | F23: 0 | G23: 6240.98 | H23: 776.08 | I23: =G23+H23 -> 7017.06 | J23: =D23-I23 -> 14325.09 | K23: S/L | L23: 27.5
A24: 7 | B24: 4 - Equipment - Apt - 5yr | C24: 12/17/15 | D24: 9541.88 | E24: 0 | F24: 0 | G24: 9541.88 | H24: 0 | I24: =G24+H24 -> 9541.88 | J24: =D24-I24 -> 0 | K24: 200DB | L24: 5.0
A25: 8 | B25: 4 - Equipment - Apt - 27.5yr | C25: 12/17/15 | D25: 38658.71 | E25: 0 | F25: 0 | G25: 11304.73 | H25: 1405.77 | I25: =G25+H25 -> 12710.5 | J25: =D25-I25 -> 25948.21 | K25: S/L | L25: 27.5
B26: Grand Total | D26: =SUM(D18:D25) -> 357389.52 | E26: =SUM(E18:E25) -> 0 | F26: =SUM(F18:F25) -> 0 | G26: =SUM(G18:G25) -> 154568.82 | H26: =SUM(H18:H25) -> 10423.27 | I26: =SUM(I18:I25) -> 164992.09 | J26: =SUM(J18:J25) -> 192397.43
B28: Section 481(a) Adjustment — Regular Tax
B29: Depreciation reported previously | D29: =I14 -> 156654.5
B30: Cost Segregation Corrected Depreciation | D30: =I26 -> 164992.09
B31: Section 481(a) Adjustment — Regular Tax | D31: =D29-D30 -> -8337.59
A33: CALCULATION OF §481(a) ADJUSTMENT — AMT
A34: As Previously Filed — AMT
A35: Asset | B35: Property Description | C35: Date In Service | D35: Cost | E35: Sec 179 Exp | F35: Bonus Amt | G35: AMT Prior Depreciation | H35: AMT Current Depreciation | I35: End Depreciation | J35: Net Book Value | K35: Method | L35: Period
A36: 1 | B36: 1 - Buillding - Apt | C36: 12/17/15 | D36: 282065.31 | E36: 0 | F36: 0 | G36: 82481.69 | H36: 10256.92 | I36: =G36+H36 -> 92738.61 | J36: =D36-I36 -> 189326.7 | K36: S/L | L36: 27.5
A37: 2 | B37: 5 - Building - Apt | C37: 1/14/16 | D37: 513.71 | E37: 0 | F37: 0 | G37: 148.76 | H37: 18.69 | I37: =G37+H37 -> 167.45 | J37: =D37-I37 -> 346.26 | K37: S/L | L37: 27.5
A38: 3 | B38: 3 - Land Improvements - Apt | C38: 12/17/15 | D38: 26609.91 | E38: 0 | F38: 0 | G38: 15584.54 | H38: 1570 | I38: =G38+H38 -> 17154.54 | J38: =D38-I38 -> 9455.37 | K38: 150DB | L38: 15.0
A39: 4 | B39: 4 - Equipment - Apt | C39: 12/17/15 | D39: 48200.59 | E39: 0 | F39: 0 | G39: 46593.9 | H39: 0 | I39: =G39+H39 -> 46593.9 | J39: =D39-I39 -> 1606.69 | K39: 200DB | L39: 5.0
B40: Grand Total | D40: =SUM(D36:D39) -> 357389.52 | E40: =SUM(E36:E39) -> 0 | F40: =SUM(F36:F39) -> 0 | G40: =SUM(G36:G39) -> 144808.89 | H40: =SUM(H36:H39) -> 11845.61 | I40: =SUM(I36:I39) -> 156654.5 | J40: =SUM(J36:J39) -> 200735.02
A42: After Cost Segregation Correction — AMT
A43: Asset | B43: Property Description | C43: Date In Service | D43: Cost | E43: Sec 179 Exp | F43: Bonus Amt | G43: AMT Prior Depreciation | H43: AMT Current Depreciation | I43: End Depreciation | J43: Net Book Value | K43: Method | L43: Period
A44: 1 | B44: 1 - Buillding - Apt - 5yr | C44: 12/17/15 | D44: 55838.26 | E44: 0 | F44: 0 | G44: 55838.26 | H44: 0 | I44: =G44+H44 -> 55838.26 | J44: =D44-I44 -> 0 | K44: 200DB | L44: 5.0
A45: 2 | B45: 1 - Buillding - Apt - 27.5yr | C45: 12/17/15 | D45: 226227.05 | E45: 0 | F45: 0 | G45: 66154.29 | H45: 8226.44 | I45: =G45+H45 -> 74380.73 | J45: =D45-I45 -> 151846.32 | K45: S/L | L45: 27.5
A46: 3 | B46: 5 - Building - Apt - 5yr | C46: 1/14/16 | D46: 101.7 | E46: 0 | F46: 0 | G46: 101.7 | H46: 0 | I46: =G46+H46 -> 101.7 | J46: =D46-I46 -> 0 | K46: 200DB | L46: 5.0
A47: 4 | B47: 5 - Building - Apt - 27.5yr | C47: 1/14/16 | D47: 412.01 | E47: 0 | F47: 0 | G47: 119.22 | H47: 14.98 | I47: =G47+H47 -> 134.2 | J47: =D47-I47 -> 277.81 | K47: S/L | L47: 27.5
A48: 5 | B48: 3 - Land Improvements - Apt - 5yr | C48: 12/17/15 | D48: 5267.76 | E48: 0 | F48: 0 | G48: 5267.76 | H48: 0 | I48: =G48+H48 -> 5267.76 | J48: =D48-I48 -> 0 | K48: 200DB | L48: 5.0
A49: 6 | B49: 3 - Land Improvements - Apt - 27.5yr | C49: 12/17/15 | D49: 21342.15 | E49: 0 | F49: 0 | G49: 6240.98 | H49: 776.08 | I49: =G49+H49 -> 7017.06 | J49: =D49-I49 -> 14325.09 | K49: S/L | L49: 27.5
A50: 7 | B50: 4 - Equipment - Apt - 5yr | C50: 12/17/15 | D50: 9541.88 | E50: 0 | F50: 0 | G50: 9541.88 | H50: 0 | I50: =G50+H50 -> 9541.88 | J50: =D50-I50 -> 0 | K50: 200DB | L50: 5.0
A51: 8 | B51: 4 - Equipment - Apt - 27.5yr | C51: 12/17/15 | D51: 38658.71 | E51: 0 | F51: 0 | G51: 11304.73 | H51: 1405.77 | I51: =G51+H51 -> 12710.5 | J51: =D51-I51 -> 25948.21 | K51: S/L | L51: 27.5
B52: Grand Total | D52: =SUM(D44:D51) -> 357389.52 | E52: =SUM(E44:E51) -> 0 | F52: =SUM(F44:F51) -> 0 | G52: =SUM(G44:G51) -> 154568.82 | H52: =SUM(H44:H51) -> 10423.27 | I52: =SUM(I44:I51) -> 164992.09 | J52: =SUM(J44:J51) -> 192397.43
B54: Section 481(a) Adjustment — AMT
B55: Depreciation reported previously | D55: =I40 -> 156654.5
B56: Cost Segregation Corrected Depreciation | D56: =I52 -> 164992.09
B57: Section 481(a) Adjustment — AMT | D57: =D55-D56 -> -8337.59
A59: COST SEGREGATION STUDY — COST SUMMARY
B60: Total Building Cost | D60: =D99 -> 357389.52
B61: Building Components: 5 Year | D61: =F99 -> 70749.6
B62: % of Cost | D62: =F100 -> 0.19796216
B63: Building Structure: 27.5 Year | D63: =H99 -> 286639.92
B64: % of Cost | D64: =H100 -> 0.80203784
A66: COST SEGREGATION STUDY — COST DETAIL
B67: Property Category | D67: Cost | F67: 5 Year | H67: 27.5 Year
B68: Building Components
B69: Cabinets / Millwork | D69: =SUM(F69:H69) -> 10346.61 | F69: 10346.61
B70: Moldings | D70: =SUM(F70:H70) -> 5291.32 | F70: 5291.32
B71: Flooring - Vinyl Plank | D71: =SUM(F71:H71) -> 26950.29 | F71: 26950.29
B72: Window Treatments | D72: =SUM(F72:H72) -> 2980.26 | F72: 2980.26
B73: Specialty HVAC - Dryer Vents | D73: =SUM(F73:H73) -> 366.57 | F73: 366.57
B74: Building Signage | D74: =SUM(F74:H74) -> 144.58 | F74: 144.58
B75: Specialty Electrical - Appliances | D75: =SUM(F75:H75) -> 5961.89 | F75: 5961.89
B76: Communication / Data | D76: =SUM(F76:H76) -> 2354.19 | F76: 2354.19
B77: Specialty Plumbing - Kitchen Sinks / Laundry | D77: =SUM(F77:H77) -> 6854.82 | F77: 6854.82
B78: Security / Exterior Lighting | D78: =SUM(F78:H78) -> 2046.92 | F78: 2046.92
B79: Access Control | D79: =SUM(F79:H79) -> 86.4 | F79: 86.4
