Workbook

Sheet Summary
A1: Grove Park Housing, LP
A2: Grove Park — 400 Peters St, Waxahachie, TX 75165
A3: EIN: 85-1924921 · FYE: December 31, 2024 · Year of Change: 1/1/2024
A4: Summary of Cost Segregation Adjustments — CSSI Report #107752-14 (CAM — DCN #7)
A7: Acq Date | B7: Asset Description | C7: Total | D7: Site | E7: Office | F7: Building 1 | G7: Building 2 | H7: Building 3 | I7: Building 4 | J7: Building 5 | K7: Imp
A8: 10/30/20 | B8: 2 - Land Imp - Peter St - Site | C8: =SUM(D8:K8) -> 27390.6 | D8: =Site!$D$10 -> 27390.6
A9: 10/30/20 | B9: 3 - Building - Peter St - Site | C9: =SUM(D9:K9) -> 267346.37 | D9: =Site!$D$11 -> 267346.37
A10: 10/30/20 | B10: 4 - Equipment - Peter St - Site | C10: =SUM(D10:K10) -> 20373.17 | D10: =Site!$D$12 -> 20373.17
A11: 10/30/20 | B11: 2 - Land Imp - Peter St - Office | C11: =SUM(D11:K11) -> 17779.38 | E11: =Office!$D$10 -> 17779.38
A12: 10/30/20 | B12: 3 - Building - Peter St - Office | C12: =SUM(D12:K12) -> 173535.93 | E12: =Office!$D$11 -> 173535.93
A13: 10/30/20 | B13: 4 - Equipment - Peter St - Office | C13: =SUM(D13:K13) -> 13224.33 | E13: =Office!$D$12 -> 13224.33
A14: 10/30/20 | B14: 2 - Land Imp - Peter St - 1 | C14: =SUM(D14:K14) -> 39470.87 | F14: ='Building 1'!$D$10 -> 39470.87
A15: 10/30/20 | B15: 3 - Building - Peter St - 1 | C15: =SUM(D15:K15) -> 385256.09 | F15: ='Building 1'!$D$11 -> 385256.09
A16: 10/30/20 | B16: 4 - Equipment - Peter St - 1 | C16: =SUM(D16:K16) -> 29358.5 | F16: ='Building 1'!$D$12 -> 29358.5
A17: 10/30/20 | B17: 2 - Land Imp - Peter St - 2 | C17: =SUM(D17:K17) -> 36341.07 | G17: ='Building 2'!$D$10 -> 36341.07
A18: 10/30/20 | B18: 3 - Building - Peter St - 2 | C18: =SUM(D18:K18) -> 354707.57 | G18: ='Building 2'!$D$11 -> 354707.57
A19: 10/30/20 | B19: 4 - Equipment - Peter St - 2 | C19: =SUM(D19:K19) -> 27030.55 | G19: ='Building 2'!$D$12 -> 27030.55
A20: 10/30/20 | B20: 2 - Land Imp - Peter St - 3 | C20: =SUM(D20:K20) -> 39460.94 | H20: ='Building 3'!$D$10 -> 39460.94
A21: 10/30/20 | B21: 3 - Building - Peter St - 3 | C21: =SUM(D21:K21) -> 385159.17 | H21: ='Building 3'!$D$11 -> 385159.17
A22: 10/30/20 | B22: 4 - Equipment - Peter St - 3 | C22: =SUM(D22:K22) -> 29351.11 | H22: ='Building 3'!$D$12 -> 29351.11
A23: 10/30/20 | B23: 2 - Land Imp - Peter St - 4 | C23: =SUM(D23:K23) -> 40404.35 | I23: ='Building 4'!$D$10 -> 40404.35
A24: 10/30/20 | B24: 3 - Building - Peter St - 4 | C24: =SUM(D24:K24) -> 394367.34 | I24: ='Building 4'!$D$11 -> 394367.34
A25: 10/30/20 | B25: 4 - Equipment - Peter St - 4 | C25: =SUM(D25:K25) -> 30052.82 | I25: ='Building 4'!$D$12 -> 30052.82
A26: 10/30/20 | B26: 2 - Land Imp - Peter St - 5 | C26: =SUM(D26:K26) -> 41152.79 | J26: ='Building 5'!$D$10 -> 41152.79
A27: 10/30/20 | B27: 3 - Building - Peter St - 5 | C27: =SUM(D27:K27) -> 401672.53 | J27: ='Building 5'!$D$11 -> 401672.53
A28: 10/30/20 | B28: 4 - Equipment - Peter St - 5 | C28: =SUM(D28:K28) -> 30609.52 | J28: ='Building 5'!$D$12 -> 30609.52
A29: 7/01/21 | B29: 8 - Building Improvement - Peter St | C29: =SUM(D29:K29) -> 86347 | K29: =Imp!$D$10 -> 86347
B30: Grand Total | C30: =SUM(C8:C29) -> 2870392 | D30: =SUM(D8:D29) -> 315110.14 | E30: =SUM(E8:E29) -> 204539.64 | F30: =SUM(F8:F29) -> 454085.46 | G30: =SUM(G8:G29) -> 418079.19 | H30: =SUM(H8:H29) -> 453971.22 | I30: =SUM(I8:I29) -> 464824.51 | J30: =SUM(J8:J29) -> 473434.84 | K30: =SUM(K8:K29) -> 86347
B32: MACRS Reclassification
A33: 10/30/20 | B33: 2 - Land Imp - Peter St - Site - 15yr | C33: =SUM(D33:K33) -> 18977.49 | D33: =Site!$D$17 -> 18977.49
A34: 10/30/20 | B34: 2 - Land Imp - Peter St - Site - 27.5yr | C34: =SUM(D34:K34) -> 8413.11 | D34: =Site!$D$18 -> 8413.11
A35: 10/30/20 | B35: 3 - Building - Peter St - Site - 15yr | C35: =SUM(D35:K35) -> 185230.12 | D35: =Site!$D$19 -> 185230.12
A36: 10/30/20 | B36: 3 - Building - Peter St - Site - 27.5yr | C36: =SUM(D36:K36) -> 82116.25 | D36: =Site!$D$20 -> 82116.25
A37: 10/30/20 | B37: 4 - Equipment - Peter St - Site - 15yr | C37: =SUM(D37:K37) -> 14115.49 | D37: =Site!$D$21 -> 14115.49
A38: 10/30/20 | B38: 4 - Equipment - Peter St - Site - 27.5yr | C38: =SUM(D38:K38) -> 6257.68 | D38: =Site!$D$22 -> 6257.68
A39: 10/30/20 | B39: 2 - Land Imp - Peter St - Office - 5yr | C39: =SUM(D39:K39) -> 2803.75 | E39: =Office!$D$17 -> 2803.75
A40: 10/30/20 | B40: 2 - Land Imp - Peter St - Office - 27.5yr | C40: =SUM(D40:K40) -> 14975.63 | E40: =Office!$D$18 -> 14975.63
A41: 10/30/20 | B41: 3 - Building - Peter St - Office - 5yr | C41: =SUM(D41:K41) -> 27366.04 | E41: =Office!$D$19 -> 27366.04
A42: 10/30/20 | B42: 3 - Building - Peter St - Office - 27.5yr | C42: =SUM(D42:K42) -> 146169.89 | E42: =Office!$D$20 -> 146169.89
A43: 10/30/20 | B43: 4 - Equipment - Peter St - Office - 5yr | C43: =SUM(D43:K43) -> 2085.43 | E43: =Office!$D$21 -> 2085.43
A44: 10/30/20 | B44: 4 - Equipment - Peter St - Office - 27.5yr | C44: =SUM(D44:K44) -> 11138.9 | E44: =Office!$D$22 -> 11138.9
A45: 10/30/20 | B45: 2 - Land Imp - Peter St - 1 - 5yr | C45: =SUM(D45:K45) -> 8187.59 | F45: ='Building 1'!$D$17 -> 8187.59
A46: 10/30/20 | B46: 2 - Land Imp - Peter St - 1 - 27.5yr | C46: =SUM(D46:K46) -> 31283.28 | F46: ='Building 1'!$D$18 -> 31283.28
A47: 10/30/20 | B47: 3 - Building - Peter St - 1 - 5yr | C47: =SUM(D47:K47) -> 79915.16 | F47: ='Building 1'!$D$19 -> 79915.16
A48: 10/30/20 | B48: 3 - Building - Peter St - 1 - 27.5yr | C48: =SUM(D48:K48) -> 305340.93 | F48: ='Building 1'!$D$20 -> 305340.93
A49: 10/30/20 | B49: 4 - Equipment - Peter St - 1 - 5yr | C49: =SUM(D49:K49) -> 6089.95 | F49: ='Building 1'!$D$21 -> 6089.95
A50: 10/30/20 | B50: 4 - Equipment - Peter St - 1 - 27.5yr | C50: =SUM(D50:K50) -> 23268.55 | F50: ='Building 1'!$D$22 -> 23268.55
A51: 10/30/20 | B51: 2 - Land Imp - Peter St - 2 - 5yr | C51: =SUM(D51:K51) -> 7790.52 | G51: ='Building 2'!$D$17 -> 7790.52
A52: 10/30/20 | B52: 2 - Land Imp - Peter St - 2 - 27.5yr | C52: =SUM(D52:K52) -> 28550.55 | G52: ='Building 2'!$D$18 -> 28550.55
A53: 10/30/20 | B53: 3 - Building - Peter St - 2 - 5yr | C53: =SUM(D53:K53) -> 76039.51 | G53: ='Building 2'!$D$19 -> 76039.51
A54: 10/30/20 | B54: 3 - Building - Peter St - 2 - 27.5yr | C54: =SUM(D54:K54) -> 278668.06 | G54: ='Building 2'!$D$20 -> 278668.06
A55: 10/30/20 | B55: 4 - Equipment - Peter St - 2 - 5yr | C55: =SUM(D55:K55) -> 5794.61 | G55: ='Building 2'!$D$21 -> 5794.61
A56: 10/30/20 | B56: 4 - Equipment - Peter St - 2 - 27.5yr | C56: =SUM(D56:K56) -> 21235.94 | G56: ='Building 2'!$D$22 -> 21235.94
A57: 10/30/20 | B57: 2 - Land Imp - Peter St - 3 - 5yr | C57: =SUM(D57:K57) -> 8072.77 | H57: ='Building 3'!$D$17 -> 8072.77
A58: 10/30/20 | B58: 2 - Land Imp - Peter St - 3 - 27.5yr | C58: =SUM(D58:K58) -> 31388.17 | H58: ='Building 3'!$D$18 -> 31388.17
A59: 10/30/20 | B59: 3 - Building - Peter St - 3 - 5yr | C59: =SUM(D59:K59) -> 78794.38 | H59: ='Building 3'!$D$19 -> 78794.38
A60: 10/30/20 | B60: 3 - Building - Peter St - 3 - 27.5yr | C60: =SUM(D60:K60) -> 306364.79 | H60: ='Building 3'!$D$20 -> 306364.79
A61: 10/30/20 | B61: 4 - Equipment - Peter St - 3 - 5yr | C61: =SUM(D61:K61) -> 6004.53 | H61: ='Building 3'!$D$21 -> 6004.53
A62: 10/30/20 | B62: 4 - Equipment - Peter St - 3 - 27.5yr | C62: =SUM(D62:K62) -> 23346.58 | H62: ='Building 3'!$D$22 -> 23346.58
A63: 10/30/20 | B63: 2 - Land Imp - Peter St - 4 - 5yr | C63: =SUM(D63:K63) -> 8405.66 | I63: ='Building 4'!$D$17 -> 8405.66
A64: 10/30/20 | B64: 2 - Land Imp - Peter St - 4 - 27.5yr | C64: =SUM(D64:K64) -> 31998.69 | I64: ='Building 4'!$D$18 -> 31998.69
A65: 10/30/20 | B65: 3 - Building - Peter St - 4 - 5yr | C65: =SUM(D65:K65) -> 82043.63 | I65: ='Building 4'!$D$19 -> 82043.63
A66: 10/30/20 | B66: 3 - Building - Peter St - 4 - 27.5yr | C66: =SUM(D66:K66) -> 312323.71 | I66: ='Building 4'!$D$20 -> 312323.71
A67: 10/30/20 | B67: 4 - Equipment - Peter St - 4 - 5yr | C67: =SUM(D67:K67) -> 6252.15 | I67: ='Building 4'!$D$21 -> 6252.15
A68: 10/30/20 | B68: 4 - Equipment - Peter St - 4 - 27.5yr | C68: =SUM(D68:K68) -> 23800.67 | I68: ='Building 4'!$D$22 -> 23800.67
A69: 10/30/20 | B69: 2 - Land Imp - Peter St - 5 - 5yr | C69: =SUM(D69:K69) -> 8405.66 | J69: ='Building 5'!$D$17 -> 8405.66
A70: 10/30/20 | B70: 2 - Land Imp - Peter St - 5 - 27.5yr | C70: =SUM(D70:K70) -> 32747.13 | J70: ='Building 5'!$D$18 -> 32747.13
A71: 10/30/20 | B71: 3 - Building - Peter St - 5 - 5yr | C71: =SUM(D71:K71) -> 82043.63 | J71: ='Building 5'!$D$19 -> 82043.63
A72: 10/30/20 | B72: 3 - Building - Peter St - 5 - 27.5yr | C72: =SUM(D72:K72) -> 319628.9 | J72: ='Building 5'!$D$20 -> 319628.9
A73: 10/30/20 | B73: 4 - Equipment - Peter St - 5 - 5yr | C73: =SUM(D73:K73) -> 6252.15 | J73: ='Building 5'!$D$21 -> 6252.15
A74: 10/30/20 | B74: 4 - Equipment - Peter St - 5 - 27.5yr | C74: =SUM(D74:K74) -> 24357.37 | J74: ='Building 5'!$D$22 -> 24357.37
A75: 7/01/21 | B75: 8 - Building Improvement - Peter St - 5yr | C75: =SUM(D75:K75) -> 23596 | K75: =Imp!$D$15 -> 23596
A76: 7/01/21 | B76: 8 - Building Improvement - Peter St - 27.5yr | C76: =SUM(D76:K76) -> 62751 | K76: =Imp!$D$16 -> 62751
B77: Total MACRS Reclassification | C77: =SUM(C33:C76) -> 2870392 | D77: =SUM(D33:D76) -> 315110.14 | E77: =SUM(E33:E76) -> 204539.64 | F77: =SUM(F33:F76) -> 454085.46 | G77: =SUM(G33:G76) -> 418079.19 | H77: =SUM(H33:H76) -> 453971.22 | I77: =SUM(I33:I76) -> 464824.51 | J77: =SUM(J33:J76) -> 473434.84 | K77: =SUM(K33:K76) -> 86347
B78: Difference (should be zero) | C78: =C30-C77 -> 0 | D78: =D30-D77 -> 0 | E78: =E30-E77 -> 0 | F78: =F30-F77 -> 0 | G78: =G30-G77 -> 0 | H78: =H30-H77 -> 0 | I78: =I30-I77 -> 0 | J78: =J30-J77 -> 0 | K78: =K30-K77 -> 0
B80: End Depreciation Reconciliation
B81: Before Cost Segregation (As Previously Filed) | C81: =SUM(D81:K81) -> 810043 | D81: =Site!$I$13 -> 88679.32 | E81: =Office!$I$13 -> 57562.21 | F81: ='Building 1'!$I$13 -> 127790.21 | G81: ='Building 2'!$I$13 -> 117657.22 | H81: ='Building 3'!$I$13 -> 127758.05 | I81: ='Building 4'!$I$13 -> 130812.43 | J81: ='Building 5'!$I$13 -> 133235.56 | K81: =Imp!$I$11 -> 26548
B82: 2 - Land Imp - Peter St - Site - 15yr | C82: =SUM(D82:K82) -> 18977.49 | D82: =Site!$I$17 -> 18977.49
B83: 2 - Land Imp - Peter St - Site - 27.5yr | C83: =SUM(D83:K83) -> 1287.46 | D83: =Site!$I$18 -> 1287.46
B84: 3 - Building - Peter St - Site - 15yr | C84: =SUM(D84:K84) -> 185230.12 | D84: =Site!$I$19 -> 185230.12
B85: 3 - Building - Peter St - Site - 27.5yr | C85: =SUM(D85:K85) -> 12566.29 | D85: =Site!$I$20 -> 12566.29
B86: 4 - Equipment - Peter St - Site - 15yr | C86: =SUM(D86:K86) -> 14115.49 | D86: =Site!$I$21 -> 14115.49
B87: 4 - Equipment - Peter St - Site - 27.5yr | C87: =SUM(D87:K87) -> 957.61 | D87: =Site!$I$22 -> 957.61
B88: 2 - Land Imp - Peter St - Office - 5yr | C88: =SUM(D88:K88) -> 2803.75 | E88: =Office!$I$17 -> 2803.75
B89: 2 - Land Imp - Peter St - Office - 27.5yr | C89: =SUM(D89:K89) -> 2291.73 | E89: =Office!$I$18 -> 2291.73
B90: 3 - Building - Peter St - Office - 5yr | C90: =SUM(D90:K90) -> 27366.04 | E90: =Office!$I$19 -> 27366.04
B91: 3 - Building - Peter St - Office - 27.5yr | C91: =SUM(D91:K91) -> 22368.43 | E91: =Office!$I$20 -> 22368.43
B92: 4 - Equipment - Peter St - Office - 5yr | C92: =SUM(D92:K92) -> 2085.43 | E92: =Office!$I$21 -> 2085.43
B93: 4 - Equipment - Peter St - Office - 27.5yr | C93: =SUM(D93:K93) -> 1704.59 | E93: =Office!$I$22 -> 1704.59
B94: 2 - Land Imp - Peter St - 1 - 5yr | C94: =SUM(D94:K94) -> 8187.59 | F94: ='Building 1'!$I$17 -> 8187.59
B95: 2 - Land Imp - Peter St - 1 - 27.5yr | C95: =SUM(D95:K95) -> 4787.27 | F95: ='Building 1'!$I$18 -> 4787.27
B96: 3 - Building - Peter St - 1 - 5yr | C96: =SUM(D96:K96) -> 79915.16 | F96: ='Building 1'!$I$19 -> 79915.16
B97: 3 - Building - Peter St - 1 - 27.5yr | C97: =SUM(D97:K97) -> 46726.43 | F97: ='Building 1'!$I$20 -> 46726.43
B98: 4 - Equipment - Peter St - 1 - 5yr | C98: =SUM(D98:K98) -> 6089.95 | F98: ='Building 1'!$I$21 -> 6089.95
B99: 4 - Equipment - Peter St - 1 - 27.5yr | C99: =SUM(D99:K99) -> 3560.8 | F99: ='Building 1'!$I$22 -> 3560.8
B100: 2 - Land Imp - Peter St - 2 - 5yr | C100: =SUM(D100:K100) -> 7790.52 | G100: ='Building 2'!$I$17 -> 7790.52
B101: 2 - Land Imp - Peter St - 2 - 27.5yr | C101: =SUM(D101:K101) -> 4369.09 | G101: ='Building 2'!$I$18 -> 4369.09
B102: 3 - Building - Peter St - 2 - 5yr | C102: =SUM(D102:K102) -> 76039.51 | G102: ='Building 2'!$I$19 -> 76039.51
B103: 3 - Building - Peter St - 2 - 27.5yr | C103: =SUM(D103:K103) -> 42644.64 | G103: ='Building 2'!$I$20 -> 42644.64
B104: 4 - Equipment - Peter St - 2 - 5yr | C104: =SUM(D104:K104) -> 5794.61 | G104: ='Building 2'!$I$21 -> 5794.61
...

Sheet Site
A1: Grove Park Housing, LP
A2: Grove Park — 400 Peters St, Waxahachie, TX 75165
A3: EIN: 85-1924921 · FYE: December 31, 2024 · Year of Change: 1/1/2024
A4: Site — Attachment to Form 3115 (DCN #7, Rev. Proc. 2024-23 §6.01)
A5: Source: CSSI Report #107752-14, "#107752-14_Grove Park Housing LP - 3115 - combined R1.pdf"
A7: CALCULATION OF §481(a) ADJUSTMENT — REGULAR TAX
A8: As Previously Filed
A9: Asset | B9: Property Description | C9: Date In Service | D9: Cost | E9: Sec 179 Exp | F9: Bonus Amt | G9: Tax Prior Depreciation | H9: Tax Current Depreciation | I9: End Depreciation | J9: Net Book Value | K9: Method | L9: Period
A10: 1 | B10: 2 - Land Imp - Peter St - Site | C10: 10/30/20 | D10: 27390.6 | E10: 0 | F10: 27390.6 | G10: 27390.6 | H10: 0 | I10: =G10+H10 -> 27390.6 | J10: =D10-I10 -> 0 | K10: 150DB | L10: 15.0
A11: 2 | B11: 3 - Building - Peter St - Site | C11: 10/30/20 | D11: 267346.37 | E11: 0 | F11: 0 | G11: 31193.81 | H11: 9721.74 | I11: =G11+H11 -> 40915.55 | J11: =D11-I11 -> 226430.82 | K11: S/L | L11: 27.5
A12: 3 | B12: 4 - Equipment - Peter St - Site | C12: 10/30/20 | D12: 20373.17 | E12: 0 | F12: 20373.17 | G12: 20373.17 | H12: 0 | I12: =G12+H12 -> 20373.17 | J12: =D12-I12 -> 0 | K12: 200DB | L12: 5.0
B13: Grand Total | D13: =SUM(D10:D12) -> 315110.14 | E13: =SUM(E10:E12) -> 0 | F13: =SUM(F10:F12) -> 47763.77 | G13: =SUM(G10:G12) -> 78957.58 | H13: =SUM(H10:H12) -> 9721.74 | I13: =SUM(I10:I12) -> 88679.32 | J13: =SUM(J10:J12) -> 226430.82
A15: After Cost Segregation Correction
A16: Asset | B16: Property Description | C16: Date In Service | D16: Cost | E16: Sec 179 Exp | F16: Bonus Amt | G16: Tax Prior Depreciation | H16: Tax Current Depreciation | I16: End Depreciation | J16: Net Book Value | K16: Method | L16: Period
A17: 1 | B17: 2 - Land Imp - Peter St - Site - 15yr | C17: 10/30/20 | D17: 18977.49 | E17: 0 | F17: 18977.49 | G17: 18977.49 | H17: 0 | I17: =G17+H17 -> 18977.49 | J17: =D17-I17 -> 0 | K17: 150DB | L17: 15.0
A18: 2 | B18: 2 - Land Imp - Peter St - Site - 27.5yr | C18: 10/30/20 | D18: 8413.11 | E18: 0 | F18: 0 | G18: 981.53 | H18: 305.93 | I18: =G18+H18 -> 1287.46 | J18: =D18-I18 -> 7125.65 | K18: S/L | L18: 27.5
A19: 3 | B19: 3 - Building - Peter St - Site - 15yr | C19: 10/30/20 | D19: 185230.12 | E19: 0 | F19: 185230.12 | G19: 185230.12 | H19: 0 | I19: =G19+H19 -> 185230.12 | J19: =D19-I19 -> 0 | K19: 150DB | L19: 15.0
A20: 4 | B20: 3 - Building - Peter St - Site - 27.5yr | C20: 10/30/20 | D20: 82116.25 | E20: 0 | F20: 0 | G20: 9580.24 | H20: 2986.05 | I20: =G20+H20 -> 12566.29 | J20: =D20-I20 -> 69549.96 | K20: S/L | L20: 27.5
A21: 5 | B21: 4 - Equipment - Peter St - Site - 15yr | C21: 10/30/20 | D21: 14115.49 | E21: 0 | F21: 14115.49 | G21: 14115.49 | H21: 0 | I21: =G21+H21 -> 14115.49 | J21: =D21-I21 -> 0 | K21: 150DB | L21: 15.0
A22: 6 | B22: 4 - Equipment - Peter St - Site - 27.5yr | C22: 10/30/20 | D22: 6257.68 | E22: 0 | F22: 0 | G22: 730.06 | H22: 227.55 | I22: =G22+H22 -> 957.61 | J22: =D22-I22 -> 5300.07 | K22: S/L | L22: 27.5
B23: Grand Total | D23: =SUM(D17:D22) -> 315110.14 | E23: =SUM(E17:E22) -> 0 | F23: =SUM(F17:F22) -> 218323.1 | G23: =SUM(G17:G22) -> 229614.93 | H23: =SUM(H17:H22) -> 3519.53 | I23: =SUM(I17:I22) -> 233134.46 | J23: =SUM(J17:J22) -> 81975.68
B25: Section 481(a) Adjustment — Regular Tax
B26: Depreciation reported previously | D26: =I13 -> 88679.32
B27: Cost Segregation Corrected Depreciation | D27: =I23 -> 233134.46
B28: Section 481(a) Adjustment — Regular Tax | D28: =D26-D27 -> -144455.14
A30: CALCULATION OF §481(a) ADJUSTMENT — AMT
A31: As Previously Filed — AMT
A32: Asset | B32: Property Description | C32: Date In Service | D32: Cost | E32: Sec 179 Exp | F32: Bonus Amt | G32: AMT Prior Depreciation | H32: AMT Current Depreciation | I32: End Depreciation | J32: Net Book Value | K32: Method | L32: Period
A33: 1 | B33: 2 - Land Imp - Peter St - Site | C33: 10/30/20 | D33: 27390.6 | E33: 0 | F33: 27390.6 | G33: 27390.6 | H33: 0 | I33: =G33+H33 -> 27390.6 | J33: =D33-I33 -> 0 | K33: 150DB | L33: 15.0
A34: 2 | B34: 3 - Building - Peter St - Site | C34: 10/30/20 | D34: 267346.37 | E34: 0 | F34: 0 | G34: 31193.81 | H34: 9721.74 | I34: =G34+H34 -> 40915.55 | J34: =D34-I34 -> 226430.82 | K34: S/L | L34: 27.5
A35: 3 | B35: 4 - Equipment - Peter St - Site | C35: 10/30/20 | D35: 20373.17 | E35: 0 | F35: 20373.17 | G35: 20373.17 | H35: 0 | I35: =G35+H35 -> 20373.17 | J35: =D35-I35 -> 0 | K35: 200DB | L35: 5.0
B36: Grand Total | D36: =SUM(D33:D35) -> 315110.14 | E36: =SUM(E33:E35) -> 0 | F36: =SUM(F33:F35) -> 47763.77 | G36: =SUM(G33:G35) -> 78957.58 | H36: =SUM(H33:H35) -> 9721.74 | I36: =SUM(I33:I35) -> 88679.32 | J36: =SUM(J33:J35) -> 226430.82
A38: After Cost Segregation Correction — AMT
A39: Asset | B39: Property Description | C39: Date In Service | D39: Cost | E39: Sec 179 Exp | F39: Bonus Amt | G39: AMT Prior Depreciation | H39: AMT Current Depreciation | I39: End Depreciation | J39: Net Book Value | K39: Method | L39: Period
A40: 1 | B40: 2 - Land Imp - Peter St - Site - 15yr | C40: 10/30/20 | D40: 18977.49 | E40: 0 | F40: 18977.49 | G40: 18977.49 | H40: 0 | I40: =G40+H40 -> 18977.49 | J40: =D40-I40 -> 0 | K40: 150DB | L40: 15.0
A41: 2 | B41: 2 - Land Imp - Peter St - Site - 27.5yr | C41: 10/30/20 | D41: 8413.11 | E41: 0 | F41: 0 | G41: 981.53 | H41: 305.93 | I41: =G41+H41 -> 1287.46 | J41: =D41-I41 -> 7125.65 | K41: S/L | L41: 27.5
A42: 3 | B42: 3 - Building - Peter St - Site - 15yr | C42: 10/30/20 | D42: 185230.12 | E42: 0 | F42: 185230.12 | G42: 185230.12 | H42: 0 | I42: =G42+H42 -> 185230.12 | J42: =D42-I42 -> 0 | K42: 150DB | L42: 15.0
A43: 4 | B43: 3 - Building - Peter St - Site - 27.5yr | C43: 10/30/20 | D43: 82116.25 | E43: 0 | F43: 0 | G43: 9580.24 | H43: 2986.05 | I43: =G43+H43 -> 12566.29 | J43: =D43-I43 -> 69549.96 | K43: S/L | L43: 27.5
A44: 5 | B44: 4 - Equipment - Peter St - Site - 15yr | C44: 10/30/20 | D44: 14115.49 | E44: 0 | F44: 14115.49 | G44: 14115.49 | H44: 0 | I44: =G44+H44 -> 14115.49 | J44: =D44-I44 -> 0 | K44: 150DB | L44: 15.0
A45: 6 | B45: 4 - Equipment - Peter St - Site - 27.5yr | C45: 10/30/20 | D45: 6257.68 | E45: 0 | F45: 0 | G45: 730.06 | H45: 227.55 | I45: =G45+H45 -> 957.61 | J45: =D45-I45 -> 5300.07 | K45: S/L | L45: 27.5
B46: Grand Total | D46: =SUM(D40:D45) -> 315110.14 | E46: =SUM(E40:E45) -> 0 | F46: =SUM(F40:F45) -> 218323.1 | G46: =SUM(G40:G45) -> 229614.93 | H46: =SUM(H40:H45) -> 3519.53 | I46: =SUM(I40:I45) -> 233134.46 | J46: =SUM(J40:J45) -> 81975.68
B48: Section 481(a) Adjustment — AMT
B49: Depreciation reported previously | D49: =I36 -> 88679.32
B50: Cost Segregation Corrected Depreciation | D50: =I46 -> 233134.46
B51: Section 481(a) Adjustment — AMT | D51: =D49-D50 -> -144455.14
A53: COST SEGREGATION STUDY — COST SUMMARY
B54: Total Site Cost | D54: =D80 -> 315110.14
B55: Site Improvements: 15 Year | D55: =F80 -> 218323.1
B56: % of Cost | D56: =F81 -> 0.69284695
B57: Site Utilities: 27.5 Year | D57: =H80 -> 96787.04
B58: % of Cost | D58: =H81 -> 0.30715305
A60: COST SEGREGATION STUDY — COST DETAIL
B61: Property Category | D61: Cost | F61: 15 Year | H61: 27.5 Year
B62: Site Work / Improvements
B63: Site Drainage | D63: =SUM(F63:H63) -> 8837.71 | F63: 8837.71
B64: Parking Lot | D64: =SUM(F64:H64) -> 95451.19 | F64: 95451.19
B65: Exterior Signage | D65: =SUM(F65:H65) -> 1321.09 | F65: 1321.09
B66: Parking Lot Striping / Barriers | D66: =SUM(F66:H66) -> 1952.9 | F66: 1952.9
B67: Sidewalks / Curbs | D67: =SUM(F67:H67) -> 59245.72 | F67: 59245.72
B68: Landscaping | D68: =SUM(F68:H68) -> 618.33 | F68: 618.33
B69: Security Lighting Poles | D69: =SUM(F69:H69) -> 12771.52 | F69: 12771.52
B70: Exterior Fencing | D70: =SUM(F70:H70) -> 15090.04 | F70: 15090.04
B71: Fire Hydrants | D71: =SUM(F71:H71) -> 2157.03 | F71: 2157.03
B72: Exterior Equipment Concrete Pads | D72: =SUM(F72:H72) -> 4129.23 | F72: 4129.23
B73: Mailboxes | D73: =SUM(F73:H73) -> 5494.17 | F73: 5494.17
B74: Mailbox Canopy | D74: =SUM(F74:H74) -> 1151.63 | F74: 1151.63
... B77: Site Seating | D77: =SUM(F77:H77) -> 252.44 | F77: 252.44
B78: Site Utilities
B79: Site Utilities | D79: =SUM(F79:H79) -> 96787.04 | H79: 96787.04
B80: Total Site Cost | D80: =SUM(D62:D79) -> 315110.14 | F80: =SUM(F62:F79) -> 218323.1 | H80: =SUM(H62:H79) -> 96787.04
B81: % of Cost | F81: =F80/D80 -> 0.69284695 | H81: =H80/D80 -> 0.30715305
A83: ASSET ALLOCATION (per After Cost Segregation schedule)
B84: Asset (as reclassified) | D84: Cost | F84: 15 Year | H84: 27.5 Year
B85: =Site!B17 -> 2 - Land Imp - Peter St - Site - 15yr | D85: =SUM(F85:H85) -> 18977.49 | F85: =Site!D17 -> 18977.49
B86: =Site!B18 -> 2 - Land Imp - Peter St - Site - 27.5yr | D86: =SUM(F86:H86) -> 8413.11 | H86: =Site!D18 -> 8413.11
B87: =Site!B19 -> 3 - Building - Peter St - Site - 15yr | D87: =SUM(F87:H87) -> 185230.12 | F87: =Site!D19 -> 185230.12
B88: =Site!B20 -> 3 - Building - Peter St - Site - 27.5yr | D88: =SUM(F88:H88) -> 82116.25 | H88: =Site!D20 -> 82116.25
B89: =Site!B21 -> 4 - Equipment - Peter St - Site - 15yr | D89: =SUM(F89:H89) -> 14115.49 | F89: =Site!D21 -> 14115.49
B90: =Site!B22 -> 4 - Equipment - Peter St - Site - 27.5yr | D90: =SUM(F90:H90) -> 6257.68 | H90: =Site!D22 -> 6257.68
B91: Total Allocation | D91: =SUM(D85:D90) -> 315110.14 | F91: =SUM(F85:F90) -> 218323.1 | H91: =SUM(H85:H90) -> 96787.04
B92: Check: Allocation vs. Cost Detail (should be zero) | D92: =D91-D80 -> 0

Sheet Office
A1: Grove Park Housing, LP
A2: Grove Park — 400 Peters St, Waxahachie, TX 75165
A3: EIN: 85-1924921 · FYE: December 31, 2024 · Year of Change: 1/1/2024
A4: Office — Attachment to Form 3115 (DCN #7, Rev. Proc. 2024-23 §6.01)
A5: Source: CSSI Report #107752-14, "#107752-14_Grove Park Housing LP - 3115 - combined R1.pdf"
A7: CALCULATION OF §481(a) ADJUSTMENT — REGULAR TAX
A8: As Previously Filed
A9: Asset | B9: Property Description | C9: Date In Service | D9: Cost | E9: Sec 179 Exp | F9: Bonus Amt | G9: Tax Prior Depreciation | H9: Tax Current Depreciation | I9: End Depreciation | J9: Net Book Value | K9: Method | L9: Period
A10: 1 | B10: 2 - Land Imp - Peter St - Office | C10: 10/30/20 | D10: 17779.38 | E10: 0 | F10: 17779.38 | G10: 17779.38 | H10: 0 | I10: =G10+H10 -> 17779.38 | J10: =D10-I10 -> 0 | K10: 150DB | L10: 15.0
A11: 2 | B11: 3 - Building - Peter St - Office | C11: 10/30/20 | D11: 173535.93 | E11: 0 | F11: 0 | G11: 20248.07 | H11: 6310.43 | I11: =G11+H11 -> 26558.5 | J11: =D11-I11 -> 146977.43 | K11: S/L | L11: 27.5
A12: 3 | B12: 4 - Equipment - Peter St - Office | C12: 10/30/20 | D12: 13224.33 | E12: 0 | F12: 13224.33 | G12: 13224.33 | H12: 0 | I12: =G12+H12 -> 13224.33 | J12: =D12-I12 -> 0 | K12: 200DB | L12: 5.0
B13: Grand Total | D13: =SUM(D10:D12) -> 204539.64 | E13: =SUM(E10:E12) -> 0 | F13: =SUM(F10:F12) -> 31003.71 | G13: =SUM(G10:G12) -> 51251.78 | H13: =SUM(H10:H12) -> 6310.43 | I13: =SUM(I10:I12) -> 57562.21 | J13: =SUM(J10:J12) -> 146977.43
A15: After Cost Segregation Correction
A16: Asset | B16: Property Description | C16: Date In Service | D16: Cost | E16: Sec 179 Exp | F16: Bonus Amt | G16: Tax Prior Depreciation | H16: Tax Current Depreciation | I16: End Depreciation | J16: Net Book Value | K16: Method | L16: Period
A17: 1 | B17: 2 - Land Imp - Peter St - Office - 5yr | C17: 10/30/20 | D17: 2803.75 | E17: 0 | F17: 2803.75 | G17: 2803.75 | H17: 0 | I17: =G17+H17 -> 2803.75 | J17: =D17-I17 -> 0 | K17: 200DB | L17: 5.0
A18: 2 | B18: 2 - Land Imp - Peter St - Office - 27.5yr | C18: 10/30/20 | D18: 14975.63 | E18: 0 | F18: 0 | G18: 1747.16 | H18: 544.57 | I18: =G18+H18 -> 2291.73 | J18: =D18-I18 -> 12683.9 | K18: S/L | L18: 27.5
A19: 3 | B19: 3 - Building - Peter St - Office - 5yr | C19: 10/30/20 | D19: 27366.04 | E19: 0 | F19: 27366.04 | G19: 27366.04 | H19: 0 | I19: =G19+H19 -> 27366.04 | J19: =D19-I19 -> 0 | K19: 200DB | L19: 5.0
A20: 4 | B20: 3 - Building - Peter St - Office - 27.5yr | C20: 10/30/20 | D20: 146169.89 | E20: 0 | F20: 0 | G20: 17053.16 | H20: 5315.27 | I20: =G20+H20 -> 22368.43 | J20: =D20-I20 -> 123801.46 | K20: S/L | L20: 27.5
A21: 5 | B21: 4 - Equipment - Peter St - Office - 5yr | C21: 10/30/20 | D21: 2085.43 | E21: 0 | F21: 2085.43 | G21: 2085.43 | H21: 0 | I21: =G21+H21 -> 2085.43 | J21: =D21-I21 -> 0 | K21: 200DB | L21: 5.0
A22: 6 | B22: 4 - Equipment - Peter St - Office - 27.5yr | C22: 10/30/20 | D22: 11138.9 | E22: 0 | F22: 0 | G22: 1299.54 | H22: 405.05 | I22: =G22+H22 -> 1704.59 | J22: =D22-I22 -> 9434.31 | K22: S/L | L22: 27.5
B23: Grand Total | D23: =SUM(D17:D22) -> 204539.64 | E23: =SUM(E17:E22) -> 0 | F23: =SUM(F17:F22) -> 32255.22 | G23: =SUM(G17:G22) -> 52355.08 | H23: =SUM(H17:H22) -> 6264.89 | I23: =SUM(I17:I22) -> 58619.97 | J23: =SUM(J17:J22) -> 145919.67
B25: Section 481(a) Adjustment — Regular Tax
B26: Depreciation reported previously | D26: =I13 -> 57562.21
B27: Cost Segregation Corrected Depreciation | D27: =I23 -> 58619.97
B28: Section 481(a) Adjustment — Regular Tax | D28: =D26-D27 -> -1057.76
A30: CALCULATION OF §481(a) ADJUSTMENT — AMT
A31: As Previously Filed — AMT
A32: Asset | B32: Property Description | C32: Date In Service | D32: Cost | E32: Sec 179 Exp | F32: Bonus Amt | G32: AMT Prior Depreciation | H32: AMT Current Depreciation | I32: End Depreciation | J32: Net Book Value | K32: Method | L32: Period
A33: 1 | B33: 2 - Land Imp - Peter St - Office | C33: 10/30/20 | D33: 17779.38 | E33: 0 | F33: 17779.38 | G33: 17779.38 | H33: 0 | I33: =G33+H33 -> 17779.38 | J33: =D33-I33 -> 0 | K33: 150DB | L33: 15.0
A34: 2 | B34: 3 - Building - Peter St - Office | C34: 10/30/20 | D34: 173535.93 | E34: 0 | F34: 0 | G34: 20248.07 | H34: 6310.43 | I34: =G34+H34 -> 26558.5 | J34: =D34-I34 -> 146977.43 | K34: S/L | L34: 27.5
A35: 3 | B35: 4 - Equipment - Peter St - Office | C35: 10/30/20 | D35: 13224.33 | E35: 0 | F35: 13224.33 | G35: 13224.33 | H35: 0 | I35: =G35+H35 -> 13224.33 | J35: =D35-I35 -> 0 | K35: 200DB | L35: 5.0
B36: Grand Total | D36: =SUM(D33:D35) -> 204539.64 | E36: =SUM(E33:E35) -> 0 | F36: =SUM(F33:F35) -> 31003.71 | G36: =SUM(G33:G35) -> 51251.78 | H36: =SUM(H33:H35) -> 6310.43 | I36: =SUM(I33:I35) -> 57562.21 | J36: =SUM(J33:J35) -> 146977.43
A38: After Cost Segregation Correction — AMT
A39: Asset | B39: Property Description | C39: Date In Service | D39: Cost | E39: Sec 179 Exp | F39: Bonus Amt | G39: AMT Prior Depreciation | H39: AMT Current Depreciation | I39: End Depreciation | J39: Net Book Value | K39: Method | L39: Period
A40: 1 | B40: 2 - Land Imp - Peter St - Office - 5yr | C40: 10/30/20 | D40: 2803.75 | E40: 0 | F40: 2803.75 | G40: 2803.75 | H40: 0 | I40: =G40+H40 -> 2803.75 | J40: =D40-I40 -> 0 | K40: 200DB | L40: 5.0
A41: 2 | B41: 2 - Land Imp - Peter St - Office - 27.5yr | C41: 10/30/20 | D41: 14975.63 | E41: 0 | F41: 0 | G41: 1747.16 | H41: 544.57 | I41: =G41+H41 -> 2291.73 | J41: =D41-I41 -> 12683.9 | K41: S/L | L41: 27.5
A42: 3 | B42: 3 - Building - Peter St - Office - 5yr | C42: 10/30/20 | D42: 27366.04 | E42: 0 | F42: 27366.04 | G42: 27366.04 | H42: 0 | I42: =G42+H42 -> 27366.04 | J42: =D42-I42 -> 0 | K42: 200DB | L42: 5.0
A43: 4 | B43: 3 - Building - Peter St - Office - 27.5yr | C43: 10/30/20 | D43: 146169.89 | E43: 0 | F43: 0 | G43: 17053.16 | H43: 5315.27 | I43: =G43+H43 -> 22368.43 | J43: =D43-I43 -> 123801.46 | K43: S/L | L43: 27.5
A44: 5 | B44: 4 - Equipment - Peter St - Office - 5yr | C44: 10/30/20 | D44: 2085.43 | E44: 0 | F44: 2085.43 | G44: 2085.43 | H44: 0 | I44: =G44+H44 -> 2085.43 | J44: =D44-I44 -> 0 | K44: 200DB | L44: 5.0
A45: 6 | B45: 4 - Equipment - Peter St - Office - 27.5yr | C45: 10/30/20 | D45: 11138.9 | E45: 0 | F45: 0 | G45: 1299.54 | H45: 405.05 | I45: =G45+H45 -> 1704.59 | J45: =D45-I45 -> 9434.31 | K45: S/L | L45: 27.5
B46: Grand Total | D46: =SUM(D40:D45) -> 204539.64 | E46: =SUM(E40:E45) -> 0 | F46: =SUM(F40:F45) -> 32255.22 | G46: =SUM(G40:G45) -> 52355.08 | H46: =SUM(H40:H45) -> 6264.89 | I46: =SUM(I40:I45) -> 58619.97 | J46: =SUM(J40:J45) -> 145919.67
B48: Section 481(a) Adjustment — AMT
B49: Depreciation reported previously | D49: =I36 -> 57562.21
B50: Cost Segregation Corrected Depreciation | D50: =I46 -> 58619.97
B51: Section 481(a) Adjustment — AMT | D51: =D49-D50 -> -1057.76
A53: COST SEGREGATION STUDY — COST SUMMARY
B54: Total Building Cost | D54: =D94 -> 204539.64
B55: Building Components: 5 Year | D55: =F94 -> 32255.22
B56: % of Cost | D56: =F95 -> 0.15769667
B57: Building Structure: 27.5 Year | D57: =H94 -> 172284.42
B58: % of Cost | D58: =H95 -> 0.84230333
A60: COST SEGREGATION STUDY — COST DETAIL
B61: Property Category | D61: Cost | F61: 5 Year | H61: 27.5 Year
B62: Building Components
B63: Cabinets / Millwork | D63: =SUM(F63:H63) -> 303.64 | F63: 303.64
B64: Moldings | D64: =SUM(F64:H64) -> 2289.4 | F64: 2289.4
B65: Flooring - Vinyl Plank | D65: =SUM(F65:H65) -> 16164.52 | F65: 16164.52
B66: Window Treatments | D66: =SUM(F66:H66) -> 1679.16 | F66: 1679.16
B67: Specialty HVAC - Dryer Vents | D67: =SUM(F67:H67) -> 230.59 | F67: 230.59
B68: Specialty Electrical - Appliances | D68: =SUM(F68:H68) -> 1250.74 | F68: 1250.74
B69: Communication / Data | D69: =SUM(F69:H69) -> 5275.08 | F69: 5275.08
B70: Specialty Plumbing - Laundry | D70: =SUM(F70:H70) -> 962.76 | F70: 962.76
B71: Security / Exterior Lighting | D71: =SUM(F71:H71) -> 645.41 | F71: 645.41
B72: Interior Windows | D72: =SUM(F72:H72) -> 99.9 | F72: 99.9
B73: Mailboxes | D73: =SUM(F73:H73) -> 45.48 | F73: 45.48
B74: Appliances | D74: =SUM(F74:H74) -> 3308.54 | F74: 3308.54
B75: Building Structure
B76: Roofing Systems | D76: =SUM(F76:H76) -> 11830.03 | H76: 11830.03
B77: Foundations | D77: =SUM(F77:H77) -> 21317.77 | H77: 21317.77
B78: HVAC | D78: =SUM(F78:H78) -> 15636.59 | H78: 15636.59
B79: Electrical | D79: =SUM(F79:H79) -> 15927.28 | H79: 15927.28
B80: Plumbing | D80: =SUM(F80:H80) -> 12830.5 | H80: 12830.5
B81: Fire Protection & Alarm | D81: =SUM(F81:H81) -> 1203.33 | H81: 1203.33
B82: Exterior Façade / Building Skin | D82: =SUM(F82:H82) -> 17377.25 | H82: 17377.25
B83: Doors & Frames | D83: =SUM(F83:H83) -> 4999.87 | H83: 4999.87
B84: Windows | D84: =SUM(F84:H84) -> 8291.76 | H84: 8291.76
B85: Ceiling Systems | D85: =SUM(F85:H85) -> 7199.05 | H85: 7199.05
B86: Interior Framing / Partitions | D86: =SUM(F86:H86) -> 18442.92 | H86: 18442.92
B87: Painting | D87: =SUM(F87:H87) -> 7118.71 | H87: 7118.71
... B93: Bathroom Accessories | D93: =SUM(F93:H93) -> 502.72 | H93: 502.72
B94: Total Building Cost | D94: =SUM(D62:D93) -> 204539.64 | F94: =SUM(F62:F93) -> 32255.22 | H94: =SUM(H62:H93) -> 172284.42
B95: % of Cost | F95: =F94/D94 -> 0.15769667 | H95: =H94/D94 -> 0.84230333
A97: ASSET ALLOCATION (per After Cost Segregation schedule)
B98: Asset (as reclassified) | D98: Cost | F98: 5 Year | H98: 27.5 Year
B99: =Office!B17 -> 2 - Land Imp - Peter St - Office - 5yr | D99: =SUM(F99:H99) -> 2803.75 | F99: =Office!D17 -> 2803.75
B100: =Office!B18 -> 2 - Land Imp - Peter St - Office - 27.5yr | D100: =SUM(F100:H100) -> 14975.63 | H100: =Office!D18 -> 14975.63
B101: =Office!B19 -> 3 - Building - Peter St - Office - 5yr | D101: =SUM(F101:H101) -> 27366.04 | F101: =Office!D19 -> 27366.04
B102: =Office!B20 -> 3 - Building - Peter St - Office - 27.5yr | D102: =SUM(F102:H102) -> 146169.89 | H102: =Office!D20 -> 146169.89
B103: =Office!B21 -> 4 - Equipment - Peter St - Office - 5yr | D103: =SUM(F103:H103) -> 2085.43 | F103: =Office!D21 -> 2085.43
B104: =Office!B22 -> 4 - Equipment - Peter St - Office - 27.5yr | D104: =SUM(F104:H104) -> 11138.9 | H104: =Office!D22 -> 11138.9
B105: Total Allocation | D105: =SUM(D99:D104) -> 204539.64 | F105: =SUM(F99:F104) -> 32255.22 | H105: =SUM(H99:H104) -> 172284.42
B106: Check: Allocation vs. Cost Detail (should be zero) | D106: =D105-D94 -> 0

Sheet Building 1
A1: Grove Park Housing, LP
A2: Grove Park — 400 Peters St, Waxahachie, TX 75165
A3: EIN: 85-1924921 · FYE: December 31, 2024 · Year of Change: 1/1/2024
A4: Building 1 — Attachment to Form 3115 (DCN #7, Rev. Proc. 2024-23 §6.01)
A5: Source: CSSI Report #107752-14, "#107752-14_Grove Park Housing LP - 3115 - combined R1.pdf"
A7: CALCULATION OF §481(a) ADJUSTMENT — REGULAR TAX
A8: As Previously Filed
A9: Asset | B9: Property Description | C9: Date In Service | D9: Cost | E9: Sec 179 Exp | F9: Bonus Amt | G9: Tax Prior Depreciation | H9: Tax Current Depreciation | I9: End Depreciation | J9: Net Book Value | K9: Method | L9: Period
A10: 1 | B10: 2 - Land Imp - Peter St - 1 | C10: 10/30/20 | D10: 39470.87 | E10: 0 | F10: 39470.87 | G10: 39470.87 | H10: 0 | I10: =G10+H10 -> 39470.87 | J10: =D10-I10 -> 0 | K10: 150DB | L10: 15.0
A11: 2 | B11: 3 - Building - Peter St - 1 | C11: 10/30/20 | D11: 385256.09 | E11: 0 | F11: 0 | G11: 44951.45 | H11: 14009.39 | I11: =G11+H11 -> 58960.84 | J11: =D11-I11 -> 326295.25 | K11: S/L | L11: 27.5
A12: 3 | B12: 4 - Equipment - Peter St - 1 | C12: 10/30/20 | D12: 29358.5 | E12: 0 | F12: 29358.5 | G12: 29358.5 | H12: 0 | I12: =G12+H12 -> 29358.5 | J12: =D12-I12 -> 0 | K12: 200DB | L12: 5.0
B13: Grand Total | D13: =SUM(D10:D12) -> 454085.46 | E13: =SUM(E10:E12) -> 0 | F13: =SUM(F10:F12) -> 68829.37 | G13: =SUM(G10:G12) -> 113780.82 | H13: =SUM(H10:H12) -> 14009.39 | I13: =SUM(I10:I12) -> 127790.21 | J13: =SUM(J10:J12) -> 326295.25
A15: After Cost Segregation Correction
A16: Asset | B16: Property Description | C16: Date In Service | D16: Cost | E16: Sec 179 Exp | F16: Bonus Amt | G16: Tax Prior Depreciation | H16: Tax Current Depreciation | I16: End Depreciation | J16: Net Book Value | K16: Method | L16: Period
A17: 1 | B17: 2 - Land Imp - Peter St - 1 - 5yr | C17: 10/30/20 | D17: 8187.59 | E17: 0 | F17: 8187.59 | G17: 8187.59 | H17: 0 | I17: =G17+H17 -> 8187.59 | J17: =D17-I17 -> 0 | K17: 200DB | L17: 5.0
A18: 2 | B18: 2 - Land Imp - Peter St - 1 - 27.5yr | C18: 10/30/20 | D18: 31283.28 | E18: 0 | F18: 0 | G18: 3649.7 | H18: 1137.57 | I18: =G18+H18 -> 4787.27 | J18: =D18-I18 -> 26496.01 | K18: S/L | L18: 27.5
A19: 3 | B19: 3 - Building - Peter St - 1 - 5yr | C19: 10/30/20 | D19: 79915.16 | E19: 0 | F19: 79915.16 | G19: 79915.16 | H19: 0 | I19: =G19+H19 -> 79915.16 | J19: =D19-I19 -> 0 | K19: 200DB | L19: 5.0
A20: 4 | B20: 3 - Building - Peter St - 1 - 27.5yr | C20: 10/30/20 | D20: 305340.93 | E20: 0 | F20: 0 | G20: 35623.12 | H20: 11103.31 | I20: =G20+H20 -> 46726.43 | J20: =D20-I20 -> 258614.5 | K20: S/L | L20: 27.5
A21: 5 | B21: 4 - Equipment - Peter St - 1 - 5yr | C21: 10/30/20 | D21: 6089.95 | E21: 0 | F21: 6089.95 | G21: 6089.95 | H21: 0 | I21: =G21+H21 -> 6089.95 | J21: =D21-I21 -> 0 | K21: 200DB | L21: 5.0
A22: 6 | B22: 4 - Equipment - Peter St - 1 - 27.5yr | C22: 10/30/20 | D22: 23268.55 | E22: 0 | F22: 0 | G22: 2714.67 | H22: 846.13 | I22: =G22+H22 -> 3560.8 | J22: =D22-I22 -> 19707.75 | K22: S/L | L22: 27.5
B23: Grand Total | D23: =SUM(D17:D22) -> 454085.46 | E23: =SUM(E17:E22) -> 0 | F23: =SUM(F17:F22) -> 94192.7 | G23: =SUM(G17:G22) -> 136180.19 | H23: =SUM(H17:H22) -> 13087.01 | I23: =SUM(I17:I22) -> 149267.2 | J23: =SUM(J17:J22) -> 304818.26
B25: Section 481(a) Adjustment — Regular Tax
B26: Depreciation reported previously | D26: =I13 -> 127790.21
B27: Cost Segregation Corrected Depreciation | D27: =I23 -> 149267.2
B28: Section 481(a) Adjustment — Regular Tax | D28: =D26-D27 -> -21476.99
A30: CALCULATION OF §481(a) ADJUSTMENT — AMT
A31: As Previously Filed — AMT
A32: Asset | B32: Property Description | C32: Date In Service | D32: Cost | E32: Sec 179 Exp | F32: Bonus Amt | G32: AMT Prior Depreciation | H32: AMT Current Depreciation | I32: End Depreciation | J32: Net Book Value | K32: Method | L32: Period
A33: 1 | B33: 2 - Land Imp - Peter St - 1 | C33: 10/30/20 | D33: 39470.87 | E33: 0 | F33: 39470.87 | G33: 39470.87 | H33: 0 | I33: =G33+H33 -> 39470.87 | J33: =D33-I33 -> 0 | K33: 150DB | L33: 15.0
A34: 2 | B34: 3 - Building - Peter St - 1 | C34: 10/30/20 | D34: 385256.09 | E34: 0 | F34: 0 | G34: 44951.45 | H34: 14009.39 | I34: =G34+H34 -> 58960.84 | J34: =D34-I34 -> 326295.25 | K34: S/L | L34: 27.5
A35: 3 | B35: 4 - Equipment - Peter St - 1 | C35: 10/30/20 | D35: 29358.5 | E35: 0 | F35: 29358.5 | G35: 29358.5 | H35: 0 | I35: =G35+H35 -> 29358.5 | J35: =D35-I35 -> 0 | K35: 200DB | L35: 5.0
B36: Grand Total | D36: =SUM(D33:D35) -> 454085.46 | E36: =SUM(E33:E35) -> 0 | F36: =SUM(F33:F35) -> 68829.37 | G36: =SUM(G33:G35) -> 113780.82 | H36: =SUM(H33:H35) -> 14009.39 | I36: =SUM(I33:I35) -> 127790.21 | J36: =SUM(J33:J35) -> 326295.25
A38: After Cost Segregation Correction — AMT
A39: Asset | B39: Property Description | C39: Date In Service | D39: Cost | E39: Sec 179 Exp | F39: Bonus Amt | G39: AMT Prior Depreciation | H39: AMT Current Depreciation | I39: End Depreciation | J39: Net Book Value | K39: Method | L39: Period
A40: 1 | B40: 2 - Land Imp - Peter St - 1 - 5yr | C40: 10/30/20 | D40: 8187.59 | E40: 0 | F40: 8187.59 | G40: 8187.59 | H40: 0 | I40: =G40+H40 -> 8187.59 | J40: =D40-I40 -> 0 | K40: 200DB | L40: 5.0
A41: 2 | B41: 2 - Land Imp - Peter St - 1 - 27.5yr | C41: 10/30/20 | D41: 31283.28 | E41: 0 | F41: 0 | G41: 3649.7 | H41: 1137.57 | I41: =G41+H41 -> 4787.27 | J41: =D41-I41 -> 26496.01 | K41: S/L | L41: 27.5
A42: 3 | B42: 3 - Building - Peter St - 1 - 5yr | C42: 10/30/20 | D42: 79915.16 | E42: 0 | F42: 79915.16 | G42: 79915.16 | H42: 0 | I42: =G42+H42 -> 79915.16 | J42: =D42-I42 -> 0 | K42: 200DB | L42: 5.0
A43: 4 | B43: 3 - Building - Peter St - 1 - 27.5yr | C43: 10/30/20 | D43: 305340.93 | E43: 0 | F43: 0 | G43: 35623.12 | H43: 11103.31 | I43: =G43+H43 -> 46726.43 | J43: =D43-I43 -> 258614.5 | K43: S/L | L43: 27.5
A44: 5 | B44: 4 - Equipment - Peter St - 1 - 5yr | C44: 10/30/20 | D44: 6089.95 | E44: 0 | F44: 6089.95 | G44: 6089.95 | H44: 0 | I44: =G44+H44 -> 6089.95 | J44: =D44-I44 -> 0 | K44: 200DB | L44: 5.0
A45: 6 | B45: 4 - Equipment - Peter St - 1 - 27.5yr | C45: 10/30/20 | D45: 23268.55 | E45: 0 | F45: 0 | G45: 2714.67 | H45: 846.13 | I45: =G45+H45 -> 3560.8 | J45: =D45-I45 -> 19707.75 | K45: S/L | L45: 27.5
B46: Grand Total | D46: =SUM(D40:D45) -> 454085.46 | E46: =SUM(E40:E45) -> 0 | F46: =SUM(F40:F45) -> 94192.7 | G46: =SUM(G40:G45) -> 136180.19 | H46: =SUM(H40:H45) -> 13087.01 | I46: =SUM(I40:I45) -> 149267.2 | J46: =SUM(J40:J45) -> 304818.26
B48: Section 481(a) Adjustment — AMT
B49: Depreciation reported previously | D49: =I36 -> 127790.21
B50: Cost Segregation Corrected Depreciation | D50: =I46 -> 149267.2
B51: Section 481(a) Adjustment — AMT | D51: =D49-D50 -> -21476.99
A53: COST SEGREGATION STUDY — COST SUMMARY
B54: Total Building Cost | D54: =D91 -> 454085.46
B55: Building Components: 5 Year | D55: =F91 -> 94192.7
B56: % of Cost | D56: =F92 -> 0.20743386
B57: Building Structure: 27.5 Year | D57: =H91 -> 359892.76
B58: % of Cost | D58: =H92 -> 0.79256614
A60: COST SEGREGATION STUDY — COST DETAIL
B61: Property Category | D61: Cost | F61: 5 Year | H61: 27.5 Year
B62: Building Components
B63: Cabinets / Millwork | D63: =SUM(F63:H63) -> 13460.19 | F63: 13460.19
B64: Moldings | D64: =SUM(F64:H64) -> 8863.88 | F64: 8863.88
B65: Flooring - Vinyl Plank | D65: =SUM(F65:H65) -> 33857.28 | F65: 33857.28
B66: Window Treatments | D66: =SUM(F66:H66) -> 3263.85 | F66: 3263.85
B67: Building Signage | D67: =SUM(F67:H67) -> 199.25 | F67: 199.25
B68: Specialty Electrical - Appliances | D68: =SUM(F68:H68) -> 7199.04 | F68: 7199.04
B69: Communication / Data | D69: =SUM(F69:H69) -> 2957.54 | F69: 2957.54
B70: Specialty Plumbing - Kitchen Sinks / Laundry | D70: =SUM(F70:H70) -> 10047.72 | F70: 10047.72
B71: Security / Exterior Lighting | D71: =SUM(F71:H71) -> 1797.27 | F71: 1797.27
B72: Appliances | D72: =SUM(F72:H72) -> 12546.68 | F72: 12546.68
B73: Building Structure
B74: Roofing Systems | D74: =SUM(F74:H74) -> 13938.65 | H74: 13938.65
B75: Foundations | D75: =SUM(F75:H75) -> 23175.05 | H75: 23175.05
B76: HVAC | D76: =SUM(F76:H76) -> 33234.48 | H76: 33234.48
B77: Electrical | D77: =SUM(F77:H77) -> 35980.1 | H77: 35980.1
B78: Plumbing | D78: =SUM(F78:H78) -> 28890.57 | H78: 28890.57
B79: Fire Protection & Alarm | D79: =SUM(F79:H79) -> 1919.47 | H79: 1919.47
B80: Exterior Façade / Building Skin | D80: =SUM(F80:H80) -> 37996.67 | H80: 37996.67
B81: Doors & Frames | D81: =SUM(F81:H81) -> 24344.21 | H81: 24344.21
B82: Windows | D82: =SUM(F82:H82) -> 14385.72 | H82: 14385.72
B83: Ceiling Systems | D83: =SUM(F83:H83) -> 15078.71 | H83: 15078.71
B84: Interior Framing / Partitions | D84: =SUM(F84:H84) -> 38493.03 | H84: 38493.03
B85: Painting | D85: =SUM(F85:H85) -> 16746.67 | H85: 16746.67
... B90: Cabinets / Millwork - Restrooms | D90: =SUM(F90:H90) -> 2575.94 | H90: 2575.94
B91: Total Building Cost | D91: =SUM(D62:D90) -> 454085.46 | F91: =SUM(F62:F90) -> 94192.7 | H91: =SUM(H62:H90) -> 359892.76
B92: % of Cost | F92: =F91/D91 -> 0.20743386 | H92: =H91/D91 -> 0.79256614
A94: ASSET ALLOCATION (per After Cost Segregation schedule)
B95: Asset (as reclassified) | D95: Cost | F95: 5 Year | H95: 27.5 Year
B96: ='Building 1'!B17 -> 2 - Land Imp - Peter St - 1 - 5yr | D96: =SUM(F96:H96) -> 8187.59 | F96: ='Building 1'!D17 -> 8187.59
B97: ='Building 1'!B18 -> 2 - Land Imp - Peter St - 1 - 27.5yr | D97: =SUM(F97:H97) -> 31283.28 | H97: ='Building 1'!D18 -> 31283.28
B98: ='Building 1'!B19 -> 3 - Building - Peter St - 1 - 5yr | D98: =SUM(F98:H98) -> 79915.16 | F98: ='Building 1'!D19 -> 79915.16
B99: ='Building 1'!B20 -> 3 - Building - Peter St - 1 - 27.5yr | D99: =SUM(F99:H99) -> 305340.93 | H99: ='Building 1'!D20 -> 305340.93
B100: ='Building 1'!B21 -> 4 - Equipment - Peter St - 1 - 5yr | D100: =SUM(F100:H100) -> 6089.95 | F100: ='Building 1'!D21 -> 6089.95
B101: ='Building 1'!B22 -> 4 - Equipment - Peter St - 1 - 27.5yr | D101: =SUM(F101:H101) -> 23268.55 | H101: ='Building 1'!D22 -> 23268.55
B102: Total Allocation | D102: =SUM(D96:D101) -> 454085.46 | F102: =SUM(F96:F101) -> 94192.7 | H102: =SUM(H96:H101) -> 359892.76
B103: Check: Allocation vs. Cost Detail (should be zero) | D103: =D102-D91 -> 0

Sheet Building 2
A1: Grove Park Housing, LP
A2: Grove Park — 400 Peters St, Waxahachie, TX 75165
A3: EIN: 85-1924921 · FYE: December 31, 2024 · Year of Change: 1/1/2024
A4: Building 2 — Attachment to Form 3115 (DCN #7, Rev. Proc. 2024-23 §6.01)
A5: Source: CSSI Report #107752-14, "#107752-14_Grove Park Housing LP - 3115 - combined R1.pdf"
A7: CALCULATION OF §481(a) ADJUSTMENT — REGULAR TAX
A8: As Previously Filed
A9: Asset | B9: Property Description | C9: Date In Service | D9: Cost | E9: Sec 179 Exp | F9: Bonus Amt | G9: Tax Prior Depreciation | H9: Tax Current Depreciation | I9: End Depreciation | J9: Net Book Value | K9: Method | L9: Period
A10: 1 | B10: 2 - Land Imp - Peter St - 2 | C10: 10/30/20 | D10: 36341.07 | E10: 0 | F10: 36341.07 | G10: 36341.07 | H10: 0 | I10: =G10+H10 -> 36341.07 | J10: =D10-I10 -> 0 | K10: 150DB | L10: 15.0
A11: 2 | B11: 3 - Building - Peter St - 2 | C11: 10/30/20 | D11: 354707.57 | E11: 0 | F11: 0 | G11: 41387.07 | H11: 12898.53 | I11: =G11+H11 -> 54285.6 | J11: =D11-I11 -> 300421.97 | K11: S/L | L11: 27.5
A12: 3 | B12: 4 - Equipment - Peter St - 2 | C12: 10/30/20 | D12: 27030.55 | E12: 0 | F12: 27030.55 | G12: 27030.55 | H12: 0 | I12: =G12+H12 -> 27030.55 | J12: =D12-I12 -> 0 | K12: 200DB | L12: 5.0
B13: Grand Total | D13: =SUM(D10:D12) -> 418079.19 | E13: =SUM(E10:E12) -> 0 | F13: =SUM(F10:F12) -> 63371.62 | G13: =SUM(G10:G12) -> 104758.69 | H13: =SUM(H10:H12) -> 12898.53 | I13: =SUM(I10:I12) -> 117657.22 | J13: =SUM(J10:J12) -> 300421.97
A15: After Cost Segregation Correction
A16: Asset | B16: Property Description | C16: Date In Service | D16: Cost | E16: Sec 179 Exp | F16: Bonus Amt | G16: Tax Prior Depreciation | H16: Tax Current Depreciation | I16: End Depreciation | J16: Net Book Value | K16: Method | L16: Period
A17: 1 | B17: 2 - Land Imp - Peter St - 2 - 5yr | C17: 10/30/20 | D17: 7790.52 | E17: 0 | F17: 7790.52 | G17: 7790.52 | H17: 0 | I17: =G17+H17 -> 7790.52 | J17: =D17-I17 -> 0 | K17: 200DB | L17: 5.0
A18: 2 | B18: 2 - Land Imp - Peter St - 2 - 27.5yr | C18: 10/30/20 | D18: 28550.55 | E18: 0 | F18: 0 | G18: 3330.89 | H18: 1038.2 | I18: =G18+H18 -> 4369.09 | J18: =D18-I18 -> 24181.46 | K18: S/L | L18: 27.5
A19: 3 | B19: 3 - Building - Peter St - 2 - 5yr | C19: 10/30/20 | D19: 76039.51 | E19: 0 | F19: 76039.51 | G19: 76039.51 | H19: 0 | I19: =G19+H19 -> 76039.51 | J19: =D19-I19 -> 0 | K19: 200DB | L19: 5.0
A20: 4 | B20: 3 - Building - Peter St - 2 - 27.5yr | C20: 10/30/20 | D20: 278668.06 | E20: 0 | F20: 0 | G20: 32511.26 | H20: 10133.38 | I20: =G20+H20 -> 42644.64 | J20: =D20-I20 -> 236023.42 | K20: S/L | L20: 27.5
A21: 5 | B21: 4 - Equipment - Peter St - 2 - 5yr | C21: 10/30/20 | D21: 5794.61 | E21: 0 | F21: 5794.61 | G21: 5794.61 | H21: 0 | I21: =G21+H21 -> 5794.61 | J21: =D21-I21 -> 0 | K21: 200DB | L21: 5.0
A22: 6 | B22: 4 - Equipment - Peter St - 2 - 27.5yr | C22: 10/30/20 | D22: 21235.94 | E22: 0 | F22: 0 | G22: 2477.54 | H22: 772.22 | I22: =G22+H22 -> 3249.76 | J22: =D22-I22 -> 17986.18 | K22: S/L | L22: 27.5
B23: Grand Total | D23: =SUM(D17:D22) -> 418079.19 | E23: =SUM(E17:E22) -> 0 | F23: =SUM(F17:F22) -> 89624.64 | G23: =SUM(G17:G22) -> 127944.33 | H23: =SUM(H17:H22) -> 11943.8 | I23: =SUM(I17:I22) -> 139888.13 | J23: =SUM(J17:J22) -> 278191.06
B25: Section 481(a) Adjustment — Regular Tax
B26: Depreciation reported previously | D26: =I13 -> 117657.22
B27: Cost Segregation Corrected Depreciation | D27: =I23 -> 139888.13
B28: Section 481(a) Adjustment — Regular Tax | D28: =D26-D27 -> -22230.91
A30: CALCULATION OF §481(a) ADJUSTMENT — AMT
A31: As Previously Filed — AMT
A32: Asset | B32: Property Description | C32: Date In Service | D32: Cost | E32: Sec 179 Exp | F32: Bonus Amt | G32: AMT Prior Depreciation | H32: AMT Current Depreciation | I32: End Depreciation | J32: Net Book Value | K32: Method | L32: Period
A33: 1 | B33: 2 - Land Imp - Peter St - 2 | C33: 10/30/20 | D33: 36341.07 | E33: 0 | F33: 36341.07 | G33: 36341.07 | H33: 0 | I33: =G33+H33 -> 36341.07 | J33: =D33-I33 -> 0 | K33: 150DB | L33: 15.0
A34: 2 | B34: 3 - Building - Peter St - 2 | C34: 10/30/20 | D34: 354707.57 | E34: 0 | F34: 0 | G34: 41387.07 | H34: 12898.53 | I34: =G34+H34 -> 54285.6 | J34: =D34-I34 -> 300421.97 | K34: S/L | L34: 27.5
A35: 3 | B35: 4 - Equipment - Peter St - 2 | C35: 10/30/20 | D35: 27030.55 | E35: 0 | F35: 27030.55 | G35: 27030.55 | H35: 0 | I35: =G35+H35 -> 27030.55 | J35: =D35-I35 -> 0 | K35: 200DB | L35: 5.0
B36: Grand Total | D36: =SUM(D33:D35) -> 418079.19 | E36: =SUM(E33:E35) -> 0 | F36: =SUM(F33:F35) -> 63371.62 | G36: =SUM(G33:G35) -> 104758.69 | H36: =SUM(H33:H35) -> 12898.53 | I36: =SUM(I33:I35) -> 117657.22 | J36: =SUM(J33:J35) -> 300421.97
A38: After Cost Segregation Correction — AMT
A39: Asset | B39: Property Description | C39: Date In Service | D39: Cost | E39: Sec 179 Exp | F39: Bonus Amt | G39: AMT Prior Depreciation | H39: AMT Current Depreciation | I39: End Depreciation | J39: Net Book Value | K39: Method | L39: Period
A40: 1 | B40: 2 - Land Imp - Peter St - 2 - 5yr | C40: 10/30/20 | D40: 7790.52 | E40: 0 | F40: 7790.52 | G40: 7790.52 | H40: 0 | I40: =G40+H40 -> 7790.52 | J40: =D40-I40 -> 0 | K40: 200DB | L40: 5.0
A41: 2 | B41: 2 - Land Imp - Peter St - 2 - 27.5yr | C41: 10/30/20 | D41: 28550.55 | E41: 0 | F41: 0 | G41: 3330.89 | H41: 1038.2 | I41: =G41+H41 -> 4369.09 | J41: =D41-I41 -> 24181.46 | K41: S/L | L41: 27.5
A42: 3 | B42: 3 - Building - Peter St - 2 - 5yr | C42: 10/30/20 | D42: 76039.51 | E42: 0 | F42: 76039.51 | G42: 76039.51 | H42: 0 | I42: =G42+H42 -> 76039.51 | J42: =D42-I42 -> 0 | K42: 200DB | L42: 5.0
A43: 4 | B43: 3 - Building - Peter St - 2 - 27.5yr | C43: 10/30/20 | D43: 278668.06 | E43: 0 | F43: 0 | G43: 32511.26 | H43: 10133.38 | I43: =G43+H43 -> 42644.64 | J43: =D43-I43 -> 236023.42 | K43: S/L | L43: 27.5
A44: 5 | B44: 4 - Equipment - Peter St - 2 - 5yr | C44: 10/30/20 | D44: 5794.61 | E44: 0 | F44: 5794.61 | G44: 5794.61 | H44: 0 | I44: =G44+H44 -> 5794.61 | J44: =D44-I44 -> 0 | K44: 200DB | L44: 5.0
A45: 6 | B45: 4 - Equipment - Peter St - 2 - 27.5yr | C45: 10/30/20 | D45: 21235.94 | E45: 0 | F45: 0 | G45: 2477.54 | H45: 772.22 | I45: =G45+H45 -> 3249.76 | J45: =D45-I45 -> 17986.18 | K45: S/L | L45: 27.5
B46: Grand Total | D46: =SUM(D40:D45) -> 418079.19 | E46: =SUM(E40:E45) -> 0 | F46: =SUM(F40:F45) -> 89624.64 | G46: =SUM(G40:G45) -> 127944.33 | H46: =SUM(H40:H45) -> 11943.8 | I46: =SUM(I40:I45) -> 139888.13 | J46: =SUM(J40:J45) -> 278191.06
B48: Section 481(a) Adjustment — AMT
B49: Depreciation reported previously | D49: =I36 -> 117657.22
B50: Cost Segregation Corrected Depreciation | D50: =I46 -> 139888.13
B51: Section 481(a) Adjustment — AMT | D51: =D49-D50 -> -22230.91
A53: COST SEGREGATION STUDY — COST SUMMARY
B54: Total Building Cost | D54: =D91 -> 418079.19
B55: Building Components: 5 Year | D55: =F91 -> 89624.64
B56: % of Cost | D56: =F92 -> 0.2143724
B57: Building Structure: 27.5 Year | D57: =H91 -> 328454.55
B58: % of Cost | D58: =H92 -> 0.7856276
A60: COST SEGREGATION STUDY — COST DETAIL
B61: Property Category | D61: Cost | F61: 5 Year | H61: 27.5 Year
B62: Building Components
B63: Cabinets / Millwork | D63: =SUM(F63:H63) -> 12955.58 | F63: 12955.58
B64: Moldings | D64: =SUM(F64:H64) -> 7814.7 | F64: 7814.7
B65: Flooring - Vinyl Plank | D65: =SUM(F65:H65) -> 31009.21 | F65: 31009.21
B66: Window Treatments | D66: =SUM(F66:H66) -> 3263.85 | F66: 3263.85
B67: Building Signage | D67: =SUM(F67:H67) -> 281.84 | F67: 281.84
B68: Specialty Electrical - Appliances | D68: =SUM(F68:H68) -> 7199.04 | F68: 7199.04
B69: Communication / Data | D69: =SUM(F69:H69) -> 2708.75 | F69: 2708.75
B70: Specialty Plumbing - Kitchen Sinks / Laundry | D70: =SUM(F70:H70) -> 10047.72 | F70: 10047.72
B71: Security / Exterior Lighting | D71: =SUM(F71:H71) -> 1797.27 | F71: 1797.27
B72: Appliances | D72: =SUM(F72:H72) -> 12546.68 | F72: 12546.68
B73: Building Structure
B74: Roofing Systems | D74: =SUM(F74:H74) -> 11905.28 | H74: 11905.28
B75: Foundations | D75: =SUM(F75:H75) -> 21103.9 | H75: 21103.9
B76: HVAC | D76: =SUM(F76:H76) -> 30438.8 | H76: 30438.8
B77: Electrical | D77: =SUM(F77:H77) -> 32953.46 | H77: 32953.46
B78: Plumbing | D78: =SUM(F78:H78) -> 26460.29 | H78: 26460.29
B79: Fire Protection & Alarm | D79: =SUM(F79:H79) -> 1706.2 | H79: 1706.2
B80: Exterior Façade / Building Skin | D80: =SUM(F80:H80) -> 32377.33 | H80: 32377.33
B81: Doors & Frames | D81: =SUM(F81:H81) -> 21744.5 | H81: 21744.5
B82: Windows | D82: =SUM(F82:H82) -> 14385.72 | H82: 14385.72
B83: Ceiling Systems | D83: =SUM(F83:H83) -> 13810.29 | H83: 13810.29
B84: Interior Framing / Partitions | D84: =SUM(F84:H84) -> 33717.23 | H84: 33717.23
B85: Painting | D85: =SUM(F85:H85) -> 14723.39 | H85: 14723.39
... B90: Cabinets / Millwork - Restrooms | D90: =SUM(F90:H90) -> 1717.29 | H90: 1717.29
B91: Total Building Cost | D91: =SUM(D62:D90) -> 418079.19 | F91: =SUM(F62:F90) -> 89624.64 | H91: =SUM(H62:H90) -> 328454.55
B92: % of Cost | F92: =F91/D91 -> 0.2143724 | H92: =H91/D91 -> 0.7856276
A94: ASSET ALLOCATION (per After Cost Segregation schedule)
B95: Asset (as reclassified) | D95: Cost | F95: 5 Year | H95: 27.5 Year
B96: ='Building 2'!B17 -> 2 - Land Imp - Peter St - 2 - 5yr | D96: =SUM(F96:H96) -> 7790.52 | F96: ='Building 2'!D17 -> 7790.52
B97: ='Building 2'!B18 -> 2 - Land Imp - Peter St - 2 - 27.5yr | D97: =SUM(F97:H97) -> 28550.55 | H97: ='Building 2'!D18 -> 28550.55
B98: ='Building 2'!B19 -> 3 - Building - Peter St - 2 - 5yr | D98: =SUM(F98:H98) -> 76039.51 | F98: ='Building 2'!D19 -> 76039.51
B99: ='Building 2'!B20 -> 3 - Building - Peter St - 2 - 27.5yr | D99: =SUM(F99:H99) -> 278668.06 | H99: ='Building 2'!D20 -> 278668.06
B100: ='Building 2'!B21 -> 4 - Equipment - Peter St - 2 - 5yr | D100: =SUM(F100:H100) -> 5794.61 | F100: ='Building 2'!D21 -> 5794.61
B101: ='Building 2'!B22 -> 4 - Equipment - Peter St - 2 - 27.5yr | D101: =SUM(F101:H101) -> 21235.94 | H101: ='Building 2'!D22 -> 21235.94
B102: Total Allocation | D102: =SUM(D96:D101) -> 418079.19 | F102: =SUM(F96:F101) -> 89624.64 | H102: =SUM(H96:H101) -> 328454.55
B103: Check: Allocation vs. Cost Detail (should be zero) | D103: =D102-D91 -> 0

Sheet Building 3
A1: Grove Park Housing, LP
A2: Grove Park — 400 Peters St, Waxahachie, TX 75165
A3: EIN: 85-1924921 · FYE: December 31, 2024 · Year of Change: 1/1/2024
A4: Building 3 — Attachment to Form 3115 (DCN #7, Rev. Proc. 2024-23 §6.01)
A5: Source: CSSI Report #107752-14, "#107752-14_Grove Park Housing LP - 3115 - combined R1.pdf"
A7: CALCULATION OF §481(a) ADJUSTMENT — REGULAR TAX
A8: As Previously Filed
A9: Asset | B9: Property Description | C9: Date In Service | D9: Cost | E9: Sec 179 Exp | F9: Bonus Amt | G9: Tax Prior Depreciation | H9: Tax Current Depreciation | I9: End Depreciation | J9: Net Book Value | K9: Method | L9: Period
A10: 1 | B10: 2 - Land Imp - Peter St - 3 | C10: 10/30/20 | D10: 39460.94 | E10: 0 | F10: 39460.94 | G10: 39460.94 | H10: 0 | I10: =G10+H10 -> 39460.94 | J10: =D10-I10 -> 0 | K10: 150DB | L10: 15.0
A11: 2 | B11: 3 - Building - Peter St - 3 | C11: 10/30/20 | D11: 385159.17 | E11: 0 | F11: 0 | G11: 44940.14 | H11: 14005.86 | I11: =G11+H11 -> 58946 | J11: =D11-I11 -> 326213.17 | K11: S/L | L11: 27.5
A12: 3 | B12: 4 - Equipment - Peter St - 3 | C12: 10/30/20 | D12: 29351.11 | E12: 0 | F12: 29351.11 | G12: 29351.11 | H12: 0 | I12: =G12+H12 -> 29351.11 | J12: =D12-I12 -> 0 | K12: 200DB | L12: 5.0
B13: Grand Total | D13: =SUM(D10:D12) -> 453971.22 | E13: =SUM(E10:E12) -> 0 | F13: =SUM(F10:F12) -> 68812.05 | G13: =SUM(G10:G12) -> 113752.19 | H13: =SUM(H10:H12) -> 14005.86 | I13: =SUM(I10:I12) -> 127758.05 | J13: =SUM(J10:J12) -> 326213.17
A15: After Cost Segregation Correction
A16: Asset | B16: Property Description | C16: Date In Service | D16: Cost | E16: Sec 179 Exp | F16: Bonus Amt | G16: Tax Prior Depreciation | H16: Tax Current Depreciation | I16: End Depreciation | J16: Net Book Value | K16: Method | L16: Period
A17: 1 | B17: 2 - Land Imp - Peter St - 3 - 5yr | C17: 10/30/20 | D17: 8072.77 | E17: 0 | F17: 8072.77 | G17: 8072.77 | H17: 0 | I17: =G17+H17 -> 8072.77 | J17: =D17-I17 -> 0 | K17: 200DB | L17: 5.0
A18: 2 | B18: 2 - Land Imp - Peter St - 3 - 27.5yr | C18: 10/30/20 | D18: 31388.17 | E18: 0 | F18: 0 | G18: 3661.96 | H18: 1141.39 | I18: =G18+H18 -> 4803.35 | J18: =D18-I18 -> 26584.82 | K18: S/L | L18: 27.5
A19: 3 | B19: 3 - Building - Peter St - 3 - 5yr | C19: 10/30/20 | D19: 78794.38 | E19: 0 | F19: 78794.38 | G19: 78794.38 | H19: 0 | I19: =G19+H19 -> 78794.38 | J19: =D19-I19 -> 0 | K19: 200DB | L19: 5.0
A20: 4 | B20: 3 - Building - Peter St - 3 - 27.5yr | C20: 10/30/20 | D20: 306364.79 | E20: 0 | F20: 0 | G20: 35742.57 | H20: 11140.54 | I20: =G20+H20 -> 46883.11 | J20: =D20-I20 -> 259481.68 | K20: S/L | L20: 27.5
A21: 5 | B21: 4 - Equipment - Peter St - 3 - 5yr | C21: 10/30/20 | D21: 6004.53 | E21: 0 | F21: 6004.53 | G21: 6004.53 | H21: 0 | I21: =G21+H21 -> 6004.53 | J21: =D21-I21 -> 0 | K21: 200DB | L21: 5.0
A22: 6 | B22: 4 - Equipment - Peter St - 3 - 27.5yr | C22: 10/30/20 | D22: 23346.58 | E22: 0 | F22: 0 | G22: 2723.78 | H22: 848.97 | I22: =G22+H22 -> 3572.75 | J22: =D22-I22 -> 19773.83 | K22: S/L | L22: 27.5
B23: Grand Total | D23: =SUM(D17:D22) -> 453971.22 | E23: =SUM(E17:E22) -> 0 | F23: =SUM(F17:F22) -> 92871.68 | G23: =SUM(G17:G22) -> 134999.99 | H23: =SUM(H17:H22) -> 13130.9 | I23: =SUM(I17:I22) -> 148130.89 | J23: =SUM(J17:J22) -> 305840.33
B25: Section 481(a) Adjustment — Regular Tax
B26: Depreciation reported previously | D26: =I13 -> 127758.05
B27: Cost Segregation Corrected Depreciation | D27: =I23 -> 148130.89
B28: Section 481(a) Adjustment — Regular Tax | D28: =D26-D27 -> -20372.84
A30: CALCULATION OF §481(a) ADJUSTMENT — AMT
A31: As Previously Filed — AMT
A32: Asset | B32: Property Description | C32: Date In Service | D32: Cost | E32: Sec 179 Exp | F32: Bonus Amt | G32: AMT Prior Depreciation | H32: AMT Current Depreciation | I32: End Depreciation | J32: Net Book Value | K32: Method | L32: Period
A33: 1 | B33: 2 - Land Imp - Peter St - 3 | C33: 10/30/20 | D33: 39460.94 | E33: 0 | F33: 39460.94 | G33: 39460.94 | H33: 0 | I33: =G33+H33 -> 39460.94 | J33: =D33-I33 -> 0 | K33: 150DB | L33: 15.0
A34: 2 | B34: 3 - Building - Peter St - 3 | C34: 10/30/20 | D34: 385159.17 | E34: 0 | F34: 0 | G34: 44940.14 | H34: 14005.86 | I34: =G34+H34 -> 58946 | J34: =D34-I34 -> 326213.17 | K34: S/L | L34: 27.5
A35: 3 | B35: 4 - Equipment - Peter St - 3 | C35: 10/30/20 | D35: 29351.11 | E35: 0 | F35: 29351.11 | G35: 29351.11 | H35: 0 | I35: =G35+H35 -> 29351.11 | J35: =D35-I35 -> 0 | K35: 200DB | L35: 5.0
B36: Grand Total | D36: =SUM(D33:D35) -> 453971.22 | E36: =SUM(E33:E35) -> 0 | F36: =SUM(F33:F35) -> 68812.05 | G36: =SUM(G33:G35) -> 113752.19 | H36: =SUM(H33:H35) -> 14005.86 | I36: =SUM(I33:I35) -> 127758.05 | J36: =SUM(J33:J35) -> 326213.17
A38: After Cost Segregation Correction — AMT
A39: Asset | B39: Property Description | C39: Date In Service | D39: Cost | E39: Sec 179 Exp | F39: Bonus Amt | G39: AMT Prior Depreciation | H39: AMT Current Depreciation | I39: End Depreciation | J39: Net Book Value | K39: Method | L39: Period
A40: 1 | B40: 2 - Land Imp - Peter St - 3 - 5yr | C40: 10/30/20 | D40: 8072.77 | E40: 0 | F40: 8072.77 | G40: 8072.77 | H40: 0 | I40: =G40+H40 -> 8072.77 | J40: =D40-I40 -> 0 | K40: 200DB | L40: 5.0
A41: 2 | B41: 2 - Land Imp - Peter St - 3 - 27.5yr | C41: 10/30/20 | D41: 31388.17 | E41: 0 | F41: 0 | G41: 3661.96 | H41: 1141.39 | I41: =G41+H41 -> 4803.35 | J41: =D41-I41 -> 26584.82 | K41: S/L | L41: 27.5
A42: 3 | B42: 3 - Building - Peter St - 3 - 5yr | C42: 10/30/20 | D42: 78794.38 | E42: 0 | F42: 78794.38 | G42: 78794.38 | H42: 0 | I42: =G42+H42 -> 78794.38 | J42: =D42-I42 -> 0 | K42: 200DB | L42: 5.0
A43: 4 | B43: 3 - Building - Peter St - 3 - 27.5yr | C43: 10/30/20 | D43: 306364.79 | E43: 0 | F43: 0 | G43: 35742.57 | H43: 11140.54 | I43: =G43+H43 -> 46883.11 | J43: =D43-I43 -> 259481.68 | K43: S/L | L43: 27.5
A44: 5 | B44: 4 - Equipment - Peter St - 3 - 5yr | C44: 10/30/20 | D44: 6004.53 | E44: 0 | F44: 6004.53 | G44: 6004.53 | H44: 0 | I44: =G44+H44 -> 6004.53 | J44: =D44-I44 -> 0 | K44: 200DB | L44: 5.0
A45: 6 | B45: 4 - Equipment - Peter St - 3 - 27.5yr | C45: 10/30/20 | D45: 23346.58 | E45: 0 | F45: 0 | G45: 2723.78 | H45: 848.97 | I45: =G45+H45 -> 3572.75 | J45: =D45-I45 -> 19773.83 | K45: S/L | L45: 27.5
B46: Grand Total | D46: =SUM(D40:D45) -> 453971.22 | E46: =SUM(E40:E45) -> 0 | F46: =SUM(F40:F45) -> 92871.68 | G46: =SUM(G40:G45) -> 134999.99 | H46: =SUM(H40:H45) -> 13130.9 | I46: =SUM(I40:I45) -> 148130.89 | J46: =SUM(J40:J45) -> 305840.33
B48: Section 481(a) Adjustment — AMT
B49: Depreciation reported previously | D49: =I36 -> 127758.05
B50: Cost Segregation Corrected Depreciation | D50: =I46 -> 148130.89
B51: Section 481(a) Adjustment — AMT | D51: =D49-D50 -> -20372.84
A53: COST SEGREGATION STUDY — COST SUMMARY
B54: Total Building Cost | D54: =D91 -> 453971.22
B55: Building Components: 5 Year | D55: =F91 -> 92871.68
B56: % of Cost | D56: =F92 -> 0.20457614
B57: Building Structure: 27.5 Year | D57: =H91 -> 361099.54
B58: % of Cost | D58: =H92 -> 0.79542386
A60: COST SEGREGATION STUDY — COST DETAIL
B61: Property Category | D61: Cost | F61: 5 Year | H61: 27.5 Year
B62: Building Components
B63: Cabinets / Millwork | D63: =SUM(F63:H63) -> 13928.67 | F63: 13928.67
B64: Moldings | D64: =SUM(F64:H64) -> 9008.6 | F64: 9008.6
B65: Flooring - Vinyl Plank | D65: =SUM(F65:H65) -> 32335.99 | F65: 32335.99
B66: Window Treatments | D66: =SUM(F66:H66) -> 2901.21 | F66: 2901.21
B67: Building Signage | D67: =SUM(F67:H67) -> 281.84 | F67: 281.84
B68: Specialty Electrical - Appliances | D68: =SUM(F68:H68) -> 7199.04 | F68: 7199.04
B69: Communication / Data | D69: =SUM(F69:H69) -> 2824.66 | F69: 2824.66
B70: Specialty Plumbing - Kitchen Sinks / Laundry | D70: =SUM(F70:H70) -> 10047.72 | F70: 10047.72
B71: Security / Exterior Lighting | D71: =SUM(F71:H71) -> 1797.27 | F71: 1797.27
B72: Appliances | D72: =SUM(F72:H72) -> 12546.68 | F72: 12546.68
B73: Building Structure
B74: Roofing Systems | D74: =SUM(F74:H74) -> 13679.1 | H74: 13679.1
B75: Foundations | D75: =SUM(F75:H75) -> 22351.4 | H75: 22351.4
B76: HVAC | D76: =SUM(F76:H76) -> 31741.18 | H76: 31741.18
B77: Electrical | D77: =SUM(F77:H77) -> 34363.44 | H77: 34363.44
B78: Plumbing | D78: =SUM(F78:H78) -> 27592.44 | H78: 27592.44
B79: Fire Protection & Alarm | D79: =SUM(F79:H79) -> 2132.75 | H79: 2132.75
B80: Exterior Façade / Building Skin | D80: =SUM(F80:H80) -> 38791.31 | H80: 38791.31
B81: Doors & Frames | D81: =SUM(F81:H81) -> 26943.94 | H81: 26943.94
B82: Windows | D82: =SUM(F82:H82) -> 12787.3 | H82: 12787.3
B83: Ceiling Systems | D83: =SUM(F83:H83) -> 14401.19 | H83: 14401.19
B84: Interior Framing / Partitions | D84: =SUM(F84:H84) -> 39311.25 | H84: 39311.25
B85: Painting | D85: =SUM(F85:H85) -> 16831.85 | H85: 16831.85
... B90: Cabinets / Millwork - Restrooms | D90: =SUM(F90:H90) -> 2749.23 | H90: 2749.23
B91: Total Building Cost | D91: =SUM(D62:D90) -> 453971.22 | F91: =SUM(F62:F90) -> 92871.68 | H91: =SUM(H62:H90) -> 361099.54
B92: % of Cost | F92: =F91/D91 -> 0.20457614 | H92: =H91/D91 -> 0.79542386
A94: ASSET ALLOCATION (per After Cost Segregation schedule)
B95: Asset (as reclassified) | D95: Cost | F95: 5 Year | H95: 27.5 Year
B96: ='Building 3'!B17 -> 2 - Land Imp - Peter St - 3 - 5yr | D96: =SUM(F96:H96) -> 8072.77 | F96: ='Building 3'!D17 -> 8072.77
B97: ='Building 3'!B18 -> 2 - Land Imp - Peter St - 3 - 27.5yr | D97: =SUM(F97:H97) -> 31388.17 | H97: ='Building 3'!D18 -> 31388.17
B98: ='Building 3'!B19 -> 3 - Building - Peter St - 3 - 5yr | D98: =SUM(F98:H98) -> 78794.38 | F98: ='Building 3'!D19 -> 78794.38
B99: ='Building 3'!B20 -> 3 - Building - Peter St - 3 - 27.5yr | D99: =SUM(F99:H99) -> 306364.79 | H99: ='Building 3'!D20 -> 306364.79
B100: ='Building 3'!B21 -> 4 - Equipment - Peter St - 3 - 5yr | D100: =SUM(F100:H100) -> 6004.53 | F100: ='Building 3'!D21 -> 6004.53
B101: ='Building 3'!B22 -> 4 - Equipment - Peter St - 3 - 27.5yr | D101: =SUM(F101:H101) -> 23346.58 | H101: ='Building 3'!D22 -> 23346.58
B102: Total Allocation | D102: =SUM(D96:D101) -> 453971.22 | F102: =SUM(F96:F101) -> 92871.68 | H102: =SUM(H96:H101) -> 361099.54
B103: Check: Allocation vs. Cost Detail (should be zero) | D103: =D102-D91 -> 0

Sheet Building 4
A1: Grove Park Housing, LP
A2: Grove Park — 400 Peters St, Waxahachie, TX 75165
A3: EIN: 85-1924921 · FYE: December 31, 2024 · Year of Change: 1/1/2024
A4: Building 4 — Attachment to Form 3115 (DCN #7, Rev. Proc. 2024-23 §6.01)
A5: Source: CSSI Report #107752-14, "#107752-14_Grove Park Housing LP - 3115 - combined R1.pdf"
A7: CALCULATION OF §481(a) ADJUSTMENT — REGULAR TAX
A8: As Previously Filed
A9: Asset | B9: Property Description | C9: Date In Service | D9: Cost | E9: Sec 179 Exp | F9: Bonus Amt | G9: Tax Prior Depreciation | H9: Tax Current Depreciation | I9: End Depreciation | J9: Net Book Value | K9: Method | L9: Period
A10: 1 | B10: 2 - Land Imp - Peter St - 4 | C10: 10/30/20 | D10: 40404.35 | E10: 0 | F10: 40404.35 | G10: 40404.35 | H10: 0 | I10: =G10+H10 -> 40404.35 | J10: =D10-I10 -> 0 | K10: 150DB | L10: 15.0
A11: 2 | B11: 3 - Building - Peter St - 4 | C11: 10/30/20 | D11: 394367.34 | E11: 0 | F11: 0 | G11: 46014.55 | H11: 14340.71 | I11: =G11+H11 -> 60355.26 | J11: =D11-I11 -> 334012.08 | K11: S/L | L11: 27.5
A12: 3 | B12: 4 - Equipment - Peter St - 4 | C12: 10/30/20 | D12: 30052.82 | E12: 0 | F12: 30052.82 | G12: 30052.82 | H12: 0 | I12: =G12+H12 -> 30052.82 | J12: =D12-I12 -> 0 | K12: 200DB | L12: 5.0
B13: Grand Total | D13: =SUM(D10:D12) -> 464824.51 | E13: =SUM(E10:E12) -> 0 | F13: =SUM(F10:F12) -> 70457.17 | G13: =SUM(G10:G12) -> 116471.72 | H13: =SUM(H10:H12) -> 14340.71 | I13: =SUM(I10:I12) -> 130812.43 | J13: =SUM(J10:J12) -> 334012.08
A15: After Cost Segregation Correction
A16: Asset | B16: Property Description | C16: Date In Service | D16: Cost | E16: Sec 179 Exp | F16: Bonus Amt | G16: Tax Prior Depreciation | H16: Tax Current Depreciation | I16: End Depreciation | J16: Net Book Value | K16: Method | L16: Period
A17: 1 | B17: 2 - Land Imp - Peter St - 4 - 5yr | C17: 10/30/20 | D17: 8405.66 | E17: 0 | F17: 8405.66 | G17: 8405.66 | H17: 0 | I17: =G17+H17 -> 8405.66 | J17: =D17-I17 -> 0 | K17: 200DB | L17: 5.0
A18: 2 | B18: 2 - Land Imp - Peter St - 4 - 27.5yr | C18: 10/30/20 | D18: 31998.69 | E18: 0 | F18: 0 | G18: 3733.18 | H18: 1163.59 | I18: =G18+H18 -> 4896.77 | J18: =D18-I18 -> 27101.92 | K18: S/L | L18: 27.5
A19: 3 | B19: 3 - Building - Peter St - 4 - 5yr | C19: 10/30/20 | D19: 82043.63 | E19: 0 | F19: 82043.63 | G19: 82043.63 | H19: 0 | I19: =G19+H19 -> 82043.63 | J19: =D19-I19 -> 0 | K19: 200DB | L19: 5.0
A20: 4 | B20: 3 - Building - Peter St - 4 - 27.5yr | C20: 10/30/20 | D20: 312323.71 | E20: 0 | F20: 0 | G20: 36437.78 | H20: 11357.23 | I20: =G20+H20 -> 47795.01 | J20: =D20-I20 -> 264528.7 | K20: S/L | L20: 27.5
A21: 5 | B21: 4 - Equipment - Peter St - 4 - 5yr | C21: 10/30/20 | D21: 6252.15 | E21: 0 | F21: 6252.15 | G21: 6252.15 | H21: 0 | I21: =G21+H21 -> 6252.15 | J21: =D21-I21 -> 0 | K21: 200DB | L21: 5.0
A22: 6 | B22: 4 - Equipment - Peter St - 4 - 27.5yr | C22: 10/30/20 | D22: 23800.67 | E22: 0 | F22: 0 | G22: 2776.75 | H22: 865.48 | I22: =G22+H22 -> 3642.23 | J22: =D22-I22 -> 20158.44 | K22: S/L | L22: 27.5
B23: Grand Total | D23: =SUM(D17:D22) -> 464824.51 | E23: =SUM(E17:E22) -> 0 | F23: =SUM(F17:F22) -> 96701.44 | G23: =SUM(G17:G22) -> 139649.15 | H23: =SUM(H17:H22) -> 13386.3 | I23: =SUM(I17:I22) -> 153035.45 | J23: =SUM(J17:J22) -> 311789.06
B25: Section 481(a) Adjustment — Regular Tax
B26: Depreciation reported previously | D26: =I13 -> 130812.43
B27: Cost Segregation Corrected Depreciation | D27: =I23 -> 153035.45
B28: Section 481(a) Adjustment — Regular Tax | D28: =D26-D27 -> -22223.02
A30: CALCULATION OF §481(a) ADJUSTMENT — AMT
A31: As Previously Filed — AMT
A32: Asset | B32: Property Description | C32: Date In Service | D32: Cost | E32: Sec 179 Exp | F32: Bonus Amt | G32: AMT Prior Depreciation | H32: AMT Current Depreciation | I32: End Depreciation | J32: Net Book Value | K32: Method | L32: Period
A33: 1 | B33: 2 - Land Imp - Peter St - 4 | C33: 10/30/20 | D33: 40404.35 | E33: 0 | F33: 40404.35 | G33: 40404.35 | H33: 0 | I33: =G33+H33 -> 40404.35 | J33: =D33-I33 -> 0 | K33: 150DB | L33: 15.0
A34: 2 | B34: 3 - Building - Peter St - 4 | C34: 10/30/20 | D34: 394367.34 | E34: 0 | F34: 0 | G34: 46014.55 | H34: 14340.71 | I34: =G34+H34 -> 60355.26 | J34: =D34-I34 -> 334012.08 | K34: S/L | L34: 27.5
A35: 3 | B35: 4 - Equipment - Peter St - 4 | C35: 10/30/20 | D35: 30052.82 | E35: 0 | F35: 30052.82 | G35: 30052.82 | H35: 0 | I35: =G35+H35 -> 30052.82 | J35: =D35-I35 -> 0 | K35: 200DB | L35: 5.0
B36: Grand Total | D36: =SUM(D33:D35) -> 464824.51 | E36: =SUM(E33:E35) -> 0 | F36: =SUM(F33:F35) -> 70457.17 | G36: =SUM(G33:G35) -> 116471.72 | H36: =SUM(H33:H35) -> 14340.71 | I36: =SUM(I33:I35) -> 130812.43 | J36: =SUM(J33:J35) -> 334012.08
A38: After Cost Segregation Correction — AMT
A39: Asset | B39: Property Description | C39: Date In Service | D39: Cost | E39: Sec 179 Exp | F39: Bonus Amt | G39: AMT Prior Depreciation | H39: AMT Current Depreciation | I39: End Depreciation | J39: Net Book Value | K39: Method | L39: Period
A40: 1 | B40: 2 - Land Imp - Peter St - 4 - 5yr | C40: 10/30/20 | D40: 8405.66 | E40: 0 | F40: 8405.66 | G40: 8405.66 | H40: 0 | I40: =G40+H40 -> 8405.66 | J40: =D40-I40 -> 0 | K40: 200DB | L40: 5.0
A41: 2 | B41: 2 - Land Imp - Peter St - 4 - 27.5yr | C41: 10/30/20 | D41: 31998.69 | E41: 0 | F41: 0 | G41: 3733.18 | H41: 1163.59 | I41: =G41+H41 -> 4896.77 | J41: =D41-I41 -> 27101.92 | K41: S/L | L41: 27.5
A42: 3 | B42: 3 - Building - Peter St - 4 - 5yr | C42: 10/30/20 | D42: 82043.63 | E42: 0 | F42: 82043.63 | G42: 82043.63 | H42: 0 | I42: =G42+H42 -> 82043.63 | J42: =D42-I42 -> 0 | K42: 200DB | L42: 5.0
A43: 4 | B43: 3 - Building - Peter St - 4 - 27.5yr | C43: 10/30/20 | D43: 312323.71 | E43: 0 | F43: 0 | G43: 36437.78 | H43: 11357.23 | I43: =G43+H43 -> 47795.01 | J43: =D43-I43 -> 264528.7 | K43: S/L | L43: 27.5
A44: 5 | B44: 4 - Equipment - Peter St - 4 - 5yr | C44: 10/30/20 | D44: 6252.15 | E44: 0 | F44: 6252.15 | G44: 6252.15 | H44: 0 | I44: =G44+H44 -> 6252.15 | J44: =D44-I44 -> 0 | K44: 200DB | L44: 5.0
A45: 6 | B45: 4 - Equipment - Peter St - 4 - 27.5yr | C45: 10/30/20 | D45: 23800.67 | E45: 0 | F45: 0 | G45: 2776.75 | H45: 865.48 | I45: =G45+H45 -> 3642.23 | J45: =D45-I45 -> 20158.44 | K45: S/L | L45: 27.5
B46: Grand Total | D46: =SUM(D40:D45) -> 464824.51 | E46: =SUM(E40:E45) -> 0 | F46: =SUM(F40:F45) -> 96701.44 | G46: =SUM(G40:G45) -> 139649.15 | H46: =SUM(H40:H45) -> 13386.3 | I46: =SUM(I40:I45) -> 153035.45 | J46: =SUM(J40:J45) -> 311789.06
B48: Section 481(a) Adjustment — AMT
B49: Depreciation reported previously | D49: =I36 -> 130812.43
B50: Cost Segregation Corrected Depreciation | D50: =I46 -> 153035.45
B51: Section 481(a) Adjustment — AMT | D51: =D49-D50 -> -22223.02
A53: COST SEGREGATION STUDY — COST SUMMARY
B54: Total Building Cost | D54: =D91 -> 464824.51
B55: Building Components: 5 Year | D55: =F91 -> 96701.44
B56: % of Cost | D56: =F92 -> 0.2080386
B57: Building Structure: 27.5 Year | D57: =H91 -> 368123.07
B58: % of Cost | D58: =H92 -> 0.7919614
A60: COST SEGREGATION STUDY — COST DETAIL
B61: Property Category | D61: Cost | F61: 5 Year | H61: 27.5 Year
B62: Building Components
B63: Cabinets / Millwork | D63: =SUM(F63:H63) -> 14397.17 | F63: 14397.17
B64: Moldings | D64: =SUM(F64:H64) -> 9008.6 | F64: 9008.6
B65: Flooring - Vinyl Plank | D65: =SUM(F65:H65) -> 35260.48 | F65: 35260.48
B66: Window Treatments | D66: =SUM(F66:H66) -> 3082.53 | F66: 3082.53
B67: Building Signage | D67: =SUM(F67:H67) -> 281.84 | F67: 281.84
B68: Specialty Electrical - Appliances | D68: =SUM(F68:H68) -> 7199.04 | F68: 7199.04
B69: Communication / Data | D69: =SUM(F69:H69) -> 3080.11 | F69: 3080.11
B70: Specialty Plumbing - Kitchen Sinks / Laundry | D70: =SUM(F70:H70) -> 10047.72 | F70: 10047.72
B71: Security / Exterior Lighting | D71: =SUM(F71:H71) -> 1797.27 | F71: 1797.27
B72: Appliances | D72: =SUM(F72:H72) -> 12546.68 | F72: 12546.68
B73: Building Structure
B74: Roofing Systems | D74: =SUM(F74:H74) -> 5968.07 | H74: 5968.07
B75: Foundations | D75: =SUM(F75:H75) -> 24046.3 | H75: 24046.3
B76: HVAC | D76: =SUM(F76:H76) -> 34611.87 | H76: 34611.87
B77: Electrical | D77: =SUM(F77:H77) -> 37471.27 | H77: 37471.27
B78: Plumbing | D78: =SUM(F78:H78) -> 30087.91 | H78: 30087.91
B79: Fire Protection & Alarm | D79: =SUM(F79:H79) -> 2346.02 | H79: 2346.02
B80: Exterior Façade / Building Skin | D80: =SUM(F80:H80) -> 39682.92 | H80: 39682.92
B81: Doors & Frames | D81: =SUM(F81:H81) -> 29543.65 | H81: 29543.65
B82: Windows | D82: =SUM(F82:H82) -> 13586.51 | H82: 13586.51
B83: Ceiling Systems | D83: =SUM(F83:H83) -> 15703.63 | H83: 15703.63
B84: Interior Framing / Partitions | D84: =SUM(F84:H84) -> 39231.5 | H84: 39231.5
B85: Painting | D85: =SUM(F85:H85) -> 17248.35 | H85: 17248.35
... B90: Cabinets / Millwork - Restrooms | D90: =SUM(F90:H90) -> 2922.55 | H90: 2922.55
B91: Total Building Cost | D91: =SUM(D62:D90) -> 464824.51 | F91: =SUM(F62:F90) -> 96701.44 | H91: =SUM(H62:H90) -> 368123.07
B92: % of Cost | F92: =F91/D91 -> 0.2080386 | H92: =H91/D91 -> 0.7919614
A94: ASSET ALLOCATION (per After Cost Segregation schedule)
B95: Asset (as reclassified) | D95: Cost | F95: 5 Year | H95: 27.5 Year
B96: ='Building 4'!B17 -> 2 - Land Imp - Peter St - 4 - 5yr | D96: =SUM(F96:H96) -> 8405.66 | F96: ='Building 4'!D17 -> 8405.66
B97: ='Building 4'!B18 -> 2 - Land Imp - Peter St - 4 - 27.5yr | D97: =SUM(F97:H97) -> 31998.69 | H97: ='Building 4'!D18 -> 31998.69
B98: ='Building 4'!B19 -> 3 - Building - Peter St - 4 - 5yr | D98: =SUM(F98:H98) -> 82043.63 | F98: ='Building 4'!D19 -> 82043.63
B99: ='Building 4'!B20 -> 3 - Building - Peter St - 4 - 27.5yr | D99: =SUM(F99:H99) -> 312323.71 | H99: ='Building 4'!D20 -> 312323.71
B100: ='Building 4'!B21 -> 4 - Equipment - Peter St - 4 - 5yr | D100: =SUM(F100:H100) -> 6252.15 | F100: ='Building 4'!D21 -> 6252.15
B101: ='Building 4'!B22 -> 4 - Equipment - Peter St - 4 - 27.5yr | D101: =SUM(F101:H101) -> 23800.67 | H101: ='Building 4'!D22 -> 23800.67
B102: Total Allocation | D102: =SUM(D96:D101) -> 464824.51 | F102: =SUM(F96:F101) -> 96701.44 | H102: =SUM(H96:H101) -> 368123.07
B103: Check: Allocation vs. Cost Detail (should be zero) | D103: =D102-D91 -> 0

Sheet Building 5
A1: Grove Park Housing, LP
A2: Grove Park — 400 Peters St, Waxahachie, TX 75165
A3: EIN: 85-1924921 · FYE: December 31, 2024 · Year of Change: 1/1/2024
A4: Building 5 — Attachment to Form 3115 (DCN #7, Rev. Proc. 2024-23 §6.01)
A5: Source: CSSI Report #107752-14, "#107752-14_Grove Park Housing LP - 3115 - combined R1.pdf"
A7: CALCULATION OF §481(a) ADJUSTMENT — REGULAR TAX
A8: As Previously Filed
A9: Asset | B9: Property Description | C9: Date In Service | D9: Cost | E9: Sec 179 Exp | F9: Bonus Amt | G9: Tax Prior Depreciation | H9: Tax Current Depreciation | I9: End Depreciation | J9: Net Book Value | K9: Method | L9: Period
A10: 1 | B10: 2 - Land Imp - Peter St - 5 | C10: 10/30/20 | D10: 41152.79 | E10: 0 | F10: 41152.79 | G10: 41152.79 | H10: 0 | I10: =G10+H10 -> 41152.79 | J10: =D10-I10 -> 0 | K10: 150DB | L10: 15.0
A11: 2 | B11: 3 - Building - Peter St - 5 | C11: 10/30/20 | D11: 401672.53 | E11: 0 | F11: 0 | G11: 46866.91 | H11: 14606.34 | I11: =G11+H11 -> 61473.25 | J11: =D11-I11 -> 340199.28 | K11: S/L | L11: 27.5
A12: 3 | B12: 4 - Equipment - Peter St - 5 | C12: 10/30/20 | D12: 30609.52 | E12: 0 | F12: 30609.52 | G12: 30609.52 | H12: 0 | I12: =G12+H12 -> 30609.52 | J12: =D12-I12 -> 0 | K12: 200DB | L12: 5.0
B13: Grand Total | D13: =SUM(D10:D12) -> 473434.84 | E13: =SUM(E10:E12) -> 0 | F13: =SUM(F10:F12) -> 71762.31 | G13: =SUM(G10:G12) -> 118629.22 | H13: =SUM(H10:H12) -> 14606.34 | I13: =SUM(I10:I12) -> 133235.56 | J13: =SUM(J10:J12) -> 340199.28
A15: After Cost Segregation Correction
A16: Asset | B16: Property Description | C16: Date In Service | D16: Cost | E16: Sec 179 Exp | F16: Bonus Amt | G16: Tax Prior Depreciation | H16: Tax Current Depreciation | I16: End Depreciation | J16: Net Book Value | K16: Method | L16: Period
A17: 1 | B17: 2 - Land Imp - Peter St - 5 - 5yr | C17: 10/30/20 | D17: 8405.66 | E17: 0 | F17: 8405.66 | G17: 8405.66 | H17: 0 | I17: =G17+H17 -> 8405.66 | J17: =D17-I17 -> 0 | K17: 200DB | L17: 5.0
A18: 2 | B18: 2 - Land Imp - Peter St - 5 - 27.5yr | C18: 10/30/20 | D18: 32747.13 | E18: 0 | F18: 0 | G18: 3820.48 | H18: 1190.8 | I18: =G18+H18 -> 5011.28 | J18: =D18-I18 -> 27735.85 | K18: S/L | L18: 27.5
A19: 3 | B19: 3 - Building - Peter St - 5 - 5yr | C19: 10/30/20 | D19: 82043.63 | E19: 0 | F19: 82043.63 | G19: 82043.63 | H19: 0 | I19: =G19+H19 -> 82043.63 | J19: =D19-I19 -> 0 | K19: 200DB | L19: 5.0
A20: 4 | B20: 3 - Building - Peter St - 5 - 27.5yr | C20: 10/30/20 | D20: 319628.9 | E20: 0 | F20: 0 | G20: 37290.04 | H20: 11622.87 | I20: =G20+H20 -> 48912.91 | J20: =D20-I20 -> 270715.99 | K20: S/L | L20: 27.5
A21: 5 | B21: 4 - Equipment - Peter St - 5 - 5yr | C21: 10/30/20 | D21: 6252.15 | E21: 0 | F21: 6252.15 | G21: 6252.15 | H21: 0 | I21: =G21+H21 -> 6252.15 | J21: =D21-I21 -> 0 | K21: 200DB | L21: 5.0
A22: 6 | B22: 4 - Equipment - Peter St - 5 - 27.5yr | C22: 10/30/20 | D22: 24357.37 | E22: 0 | F22: 0 | G22: 2841.69 | H22: 885.72 | I22: =G22+H22 -> 3727.41 | J22: =D22-I22 -> 20629.96 | K22: S/L | L22: 27.5
B23: Grand Total | D23: =SUM(D17:D22) -> 473434.84 | E23: =SUM(E17:E22) -> 0 | F23: =SUM(F17:F22) -> 96701.44 | G23: =SUM(G17:G22) -> 140653.65 | H23: =SUM(H17:H22) -> 13699.39 | I23: =SUM(I17:I22) -> 154353.04 | J23: =SUM(J17:J22) -> 319081.8
B25: Section 481(a) Adjustment — Regular Tax
B26: Depreciation reported previously | D26: =I13 -> 133235.56
B27: Cost Segregation Corrected Depreciation | D27: =I23 -> 154353.04
B28: Section 481(a) Adjustment — Regular Tax | D28: =D26-D27 -> -21117.48
A30: CALCULATION OF §481(a) ADJUSTMENT — AMT
A31: As Previously Filed — AMT
A32: Asset | B32: Property Description | C32: Date In Service | D32: Cost | E32: Sec 179 Exp | F32: Bonus Amt | G32: AMT Prior Depreciation | H32: AMT Current Depreciation | I32: End Depreciation | J32: Net Book Value | K32: Method | L32: Period
A33: 1 | B33: 2 - Land Imp - Peter St - 5 | C33: 10/30/20 | D33: 41152.79 | E33: 0 | F33: 41152.79 | G33: 41152.79 | H33: 0 | I33: =G33+H33 -> 41152.79 | J33: =D33-I33 -> 0 | K33: 150DB | L33: 15.0
A34: 2 | B34: 3 - Building - Peter St - 5 | C34: 10/30/20 | D34: 401672.53 | E34: 0 | F34: 0 | G34: 46866.91 | H34: 14606.34 | I34: =G34+H34 -> 61473.25 | J34: =D34-I34 -> 340199.28 | K34: S/L | L34: 27.5
A35: 3 | B35: 4 - Equipment - Peter St - 5 | C35: 10/30/20 | D35: 30609.52 | E35: 0 | F35: 30609.52 | G35: 30609.52 | H35: 0 | I35: =G35+H35 -> 30609.52 | J35: =D35-I35 -> 0 | K35: 200DB | L35: 5.0
B36: Grand Total | D36: =SUM(D33:D35) -> 473434.84 | E36: =SUM(E33:E35) -> 0 | F36: =SUM(F33:F35) -> 71762.31 | G36: =SUM(G33:G35) -> 118629.22 | H36: =SUM(H33:H35) -> 14606.34 | I36: =SUM(I33:I35) -> 133235.56 | J36: =SUM(J33:J35) -> 340199.28
A38: After Cost Segregation Correction — AMT
A39: Asset | B39: Property Description | C39: Date In Service | D39: Cost | E39: Sec 179 Exp | F39: Bonus Amt | G39: AMT Prior Depreciation | H39: AMT Current Depreciation | I39: End Depreciation | J39: Net Book Value | K39: Method | L39: Period
A40: 1 | B40: 2 - Land Imp - Peter St - 5 - 5yr | C40: 10/30/20 | D40: 8405.66 | E40: 0 | F40: 8405.66 | G40: 8405.66 | H40: 0 | I40: =G40+H40 -> 8405.66 | J40: =D40-I40 -> 0 | K40: 200DB | L40: 5.0
A41: 2 | B41: 2 - Land Imp - Peter St - 5 - 27.5yr | C41: 10/30/20 | D41: 32747.13 | E41: 0 | F41: 0 | G41: 3820.48 | H41: 1190.8 | I41: =G41+H41 -> 5011.28 | J41: =D41-I41 -> 27735.85 | K41: S/L | L41: 27.5
A42: 3 | B42: 3 - Building - Peter St - 5 - 5yr | C42: 10/30/20 | D42: 82043.63 | E42: 0 | F42: 82043.63 | G42: 82043.63 | H42: 0 | I42: =G42+H42 -> 82043.63 | J42: =D42-I42 -> 0 | K42: 200DB | L42: 5.0
A43: 4 | B43: 3 - Building - Peter St - 5 - 27.5yr | C43: 10/30/20 | D43: 319628.9 | E43: 0 | F43: 0 | G43: 37290.04 | H43: 11622.87 | I43: =G43+H43 -> 48912.91 | J43: =D43-I43 -> 270715.99 | K43: S/L | L43: 27.5
A44: 5 | B44: 4 - Equipment - Peter St - 5 - 5yr | C44: 10/30/20 | D44: 6252.15 | E44: 0 | F44: 6252.15 | G44: 6252.15 | H44: 0 | I44: =G44+H44 -> 6252.15 | J44: =D44-I44 -> 0 | K44: 200DB | L44: 5.0
A45: 6 | B45: 4 - Equipment - Peter St - 5 - 27.5yr | C45: 10/30/20 | D45: 24357.37 | E45: 0 | F45: 0 | G45: 2841.69 | H45: 885.72 | I45: =G45+H45 -> 3727.41 | J45: =D45-I45 -> 20629.96 | K45: S/L | L45: 27.5
B46: Grand Total | D46: =SUM(D40:D45) -> 473434.84 | E46: =SUM(E40:E45) -> 0 | F46: =SUM(F40:F45) -> 96701.44 | G46: =SUM(G40:G45) -> 140653.65 | H46: =SUM(H40:H45) -> 13699.39 | I46: =SUM(I40:I45) -> 154353.04 | J46: =SUM(J40:J45) -> 319081.8
B48: Section 481(a) Adjustment — AMT
B49: Depreciation reported previously | D49: =I36 -> 133235.56
B50: Cost Segregation Corrected Depreciation | D50: =I46 -> 154353.04
B51: Section 481(a) Adjustment — AMT | D51: =D49-D50 -> -21117.48
A53: COST SEGREGATION STUDY — COST SUMMARY
B54: Total Building Cost | D54: =D91 -> 473434.84
B55: Building Components: 5 Year | D55: =F91 -> 96701.44
B56: % of Cost | D56: =F92 -> 0.20425501
B57: Building Structure: 27.5 Year | D57: =H91 -> 376733.4
B58: % of Cost | D58: =H92 -> 0.79574499
A60: COST SEGREGATION STUDY — COST DETAIL
B61: Property Category | D61: Cost | F61: 5 Year | H61: 27.5 Year
B62: Building Components
B63: Cabinets / Millwork | D63: =SUM(F63:H63) -> 14397.17 | F63: 14397.17
B64: Moldings | D64: =SUM(F64:H64) -> 9008.6 | F64: 9008.6
B65: Flooring - Vinyl Plank | D65: =SUM(F65:H65) -> 35260.48 | F65: 35260.48
B66: Window Treatments | D66: =SUM(F66:H66) -> 3082.53 | F66: 3082.53
B67: Building Signage | D67: =SUM(F67:H67) -> 281.84 | F67: 281.84
B68: Specialty Electrical - Appliances | D68: =SUM(F68:H68) -> 7199.04 | F68: 7199.04
B69: Communication / Data | D69: =SUM(F69:H69) -> 3080.11 | F69: 3080.11
B70: Specialty Plumbing - Kitchen Sinks / Laundry | D70: =SUM(F70:H70) -> 10047.72 | F70: 10047.72
B71: Security / Exterior Lighting | D71: =SUM(F71:H71) -> 1797.27 | F71: 1797.27
B72: Appliances | D72: =SUM(F72:H72) -> 12546.68 | F72: 12546.68
B73: Building Structure
B74: Roofing Systems | D74: =SUM(F74:H74) -> 14578.39 | H74: 14578.39
B75: Foundations | D75: =SUM(F75:H75) -> 24046.3 | H75: 24046.3
B76: HVAC | D76: =SUM(F76:H76) -> 34611.88 | H76: 34611.88
B77: Electrical | D77: =SUM(F77:H77) -> 37471.27 | H77: 37471.27
B78: Plumbing | D78: =SUM(F78:H78) -> 30087.91 | H78: 30087.91
B79: Fire Protection & Alarm | D79: =SUM(F79:H79) -> 2346.02 | H79: 2346.02
B80: Exterior Façade / Building Skin | D80: =SUM(F80:H80) -> 39682.92 | H80: 39682.92
B81: Doors & Frames | D81: =SUM(F81:H81) -> 29543.65 | H81: 29543.65
B82: Windows | D82: =SUM(F82:H82) -> 13586.51 | H82: 13586.51
B83: Ceiling Systems | D83: =SUM(F83:H83) -> 15703.63 | H83: 15703.63
B84: Interior Framing / Partitions | D84: =SUM(F84:H84) -> 39231.5 | H84: 39231.5
B85: Painting | D85: =SUM(F85:H85) -> 17248.35 | H85: 17248.35
... B90: Cabinets / Millwork - Restrooms | D90: =SUM(F90:H90) -> 2922.55 | H90: 2922.55
B91: Total Building Cost | D91: =SUM(D62:D90) -> 473434.84 | F91: =SUM(F62:F90) -> 96701.44 | H91: =SUM(H62:H90) -> 376733.4
B92: % of Cost | F92: =F91/D91 -> 0.20425501 | H92: =H91/D91 -> 0.79574499
A94: ASSET ALLOCATION (per After Cost Segregation schedule)
B95: Asset (as reclassified) | D95: Cost | F95: 5 Year | H95: 27.5 Year
B96: ='Building 5'!B17 -> 2 - Land Imp - Peter St - 5 - 5yr | D96: =SUM(F96:H96) -> 8405.66 | F96: ='Building 5'!D17 -> 8405.66
B97: ='Building 5'!B18 -> 2 - Land Imp - Peter St - 5 - 27.5yr | D97: =SUM(F97:H97) -> 32747.13 | H97: ='Building 5'!D18 -> 32747.13
B98: ='Building 5'!B19 -> 3 - Building - Peter St - 5 - 5yr | D98: =SUM(F98:H98) -> 82043.63 | F98: ='Building 5'!D19 -> 82043.63
B99: ='Building 5'!B20 -> 3 - Building - Peter St - 5 - 27.5yr | D99: =SUM(F99:H99) -> 319628.9 | H99: ='Building 5'!D20 -> 319628.9
B100: ='Building 5'!B21 -> 4 - Equipment - Peter St - 5 - 5yr | D100: =SUM(F100:H100) -> 6252.15 | F100: ='Building 5'!D21 -> 6252.15
B101: ='Building 5'!B22 -> 4 - Equipment - Peter St - 5 - 27.5yr | D101: =SUM(F101:H101) -> 24357.37 | H101: ='Building 5'!D22 -> 24357.37
B102: Total Allocation | D102: =SUM(D96:D101) -> 473434.84 | F102: =SUM(F96:F101) -> 96701.44 | H102: =SUM(H96:H101) -> 376733.4
B103: Check: Allocation vs. Cost Detail (should be zero) | D103: =D102-D91 -> 0

Sheet Imp
A1: Grove Park Housing, LP
A2: Grove Park — 400 Peters St, Waxahachie, TX 75165
A3: EIN: 85-1924921 · FYE: December 31, 2024 · Year of Change: 1/1/2024
A4: Imp — Attachment to Form 3115 (DCN #7, Rev. Proc. 2024-23 §6.01)
A5: Source: CSSI Report #107752-14, "#107752-14_Grove Park Housing LP - 3115 - combined R1.pdf"
A7: CALCULATION OF §481(a) ADJUSTMENT — REGULAR TAX
A8: As Previously Filed
A9: Asset | B9: Property Description | C9: Date In Service | D9: Cost | E9: Sec 179 Exp | F9: Bonus Amt | G9: Tax Prior Depreciation | H9: Tax Current Depreciation | I9: End Depreciation | J9: Net Book Value | K9: Method | L9: Period
A10: 1 | B10: 8 - Building Improvement - Peter St | C10: 7/01/21 | D10: 86347 | E10: 0 | F10: 19904 | G10: 19904 | H10: 6644 | I10: 26548 | J10: 33192 | K10: 150DB | L10: 15.0
B11: Grand Total | D11: =SUM(D10:D10) -> 86347 | E11: =SUM(E10:E10) -> 0 | F11: =SUM(F10:F10) -> 19904 | G11: =SUM(G10:G10) -> 19904 | H11: =SUM(H10:H10) -> 6644 | I11: =SUM(I10:I10) -> 26548 | J11: =SUM(J10:J10) -> 33192
A13: After Cost Segregation Correction
A14: Asset | B14: Property Description | C14: Date In Service | D14: Cost | E14: Sec 179 Exp | F14: Bonus Amt | G14: Tax Prior Depreciation | H14: Tax Current Depreciation | I14: End Depreciation | J14: Net Book Value | K14: Method | L14: Period
A15: 1 | B15: 8 - Building Improvement - Peter St - 5yr | C15: 7/01/21 | D15: 23596 | E15: 0 | F15: 23596 | G15: 23596 | H15: 0 | I15: =G15+H15 -> 23596 | J15: =D15-I15 -> 0 | K15: 200DB | L15: 5.0
A16: 2 | B16: 8 - Building Improvement - Peter St - 27.5yr | C16: 7/01/21 | D16: 62751 | E16: 0 | F16: 0 | G16: 5609.55 | H16: 2281.85 | I16: =G16+H16 -> 7891.4 | J16: =D16-I16 -> 54859.6 | K16: S/L | L16: 27.5
B17: Grand Total | D17: =SUM(D15:D16) -> 86347 | E17: =SUM(E15:E16) -> 0 | F17: =SUM(F15:F16) -> 23596 | G17: =SUM(G15:G16) -> 29205.55 | H17: =SUM(H15:H16) -> 2281.85 | I17: =SUM(I15:I16) -> 31487.4 | J17: =SUM(J15:J16) -> 54859.6
B19: Section 481(a) Adjustment — Regular Tax
B20: Depreciation reported previously | D20: =I11 -> 26548
B21: Cost Segregation Corrected Depreciation | D21: =I17 -> 31487.4
B22: Section 481(a) Adjustment — Regular Tax | D22: =D20-D21 -> -4939.4
A24: CALCULATION OF §481(a) ADJUSTMENT — AMT
A25: As Previously Filed — AMT
A26: Asset | B26: Property Description | C26: Date In Service | D26: Cost | E26: Sec 179 Exp | F26: Bonus Amt | G26: AMT Prior Depreciation | H26: AMT Current Depreciation | I26: End Depreciation | J26: Net Book Value | K26: Method | L26: Period
A27: 1 | B27: 8 - Building Improvement - Peter St | C27: 7/01/21 | D27: 86347 | E27: 0 | F27: 19904 | G27: 19904 | H27: 6644 | I27: 26548 | J27: 33192 | K27: 150DB | L27: 15.0
B28: Grand Total | D28: =SUM(D27:D27) -> 86347 | E28: =SUM(E27:E27) -> 0 | F28: =SUM(F27:F27) -> 19904 | G28: =SUM(G27:G27) -> 19904 | H28: =SUM(H27:H27) -> 6644 | I28: =SUM(I27:I27) -> 26548 | J28: =SUM(J27:J27) -> 33192
A30: After Cost Segregation Correction — AMT
A31: Asset | B31: Property Description | C31: Date In Service | D31: Cost | E31: Sec 179 Exp | F31: Bonus Amt | G31: AMT Prior Depreciation | H31: AMT Current Depreciation | I31: End Depreciation | J31: Net Book Value | K31: Method | L31: Period
A32: 1 | B32: 8 - Building Improvement - Peter St - 5yr | C32: 7/01/21 | D32: 23596 | E32: 0 | F32: 23596 | G32: 23596 | H32: 0 | I32: =G32+H32 -> 23596 | J32: =D32-I32 -> 0 | K32: 200DB | L32: 5.0
A33: 2 | B33: 8 - Building Improvement - Peter St - 27.5yr | C33: 7/01/21 | D33: 62751 | E33: 0 | F33: 0 | G33: 5609.55 | H33: 2281.85 | I33: =G33+H33 -> 7891.4 | J33: =D33-I33 -> 54859.6 | K33: S/L | L33: 27.5
B34: Grand Total | D34: =SUM(D32:D33) -> 86347 | E34: =SUM(E32:E33) -> 0 | F34: =SUM(F32:F33) -> 23596 | G34: =SUM(G32:G33) -> 29205.55 | H34: =SUM(H32:H33) -> 2281.85 | I34: =SUM(I32:I33) -> 31487.4 | J34: =SUM(J32:J33) -> 54859.6
B36: Section 481(a) Adjustment — AMT
B37: Depreciation reported previously | D37: =I28 -> 26548
B38: Cost Segregation Corrected Depreciation | D38: =I34 -> 31487.4
B39: Section 481(a) Adjustment — AMT | D39: =D37-D38 -> -4939.4
A41: COST SEGREGATION STUDY — COST SUMMARY
B42: Total Building Cost | D42: =D54 -> 86347
B43: Building Components: 5 Year | D43: =F54 -> 23596
B44: % of Cost | D44: =F55 -> 0.27326948
B45: Building Structure: 27.5 Year | D45: =H54 -> 62751
B46: % of Cost | D46: =H55 -> 0.72673052
A48: COST SEGREGATION STUDY — COST DETAIL
B49: Property Category | D49: Cost | F49: 5 Year | H49: 27.5 Year
B50: Building Components
B51: Window Treatments | D51: =SUM(F51:H51) -> 23596 | F51: 23596
B52: Building Structure
B53: Miscellaneous Building Components | D53: =SUM(F53:H53) -> 62751 | H53: 62751
B54: Total Building Cost | D54: =SUM(D50:D53) -> 86347 | F54: =SUM(F50:F53) -> 23596 | H54: =SUM(H50:H53) -> 62751
B55: % of Cost | F55: =F54/D54 -> 0.27326948 | H55: =H54/D54 -> 0.72673052
A57: ASSET ALLOCATION (per After Cost Segregation schedule)
B58: Asset (as reclassified) | D58: Cost | F58: 5 Year | H58: 27.5 Year
B59: =Imp!B15 -> 8 - Building Improvement - Peter St - 5yr | D59: =SUM(F59:H59) -> 23596 | F59: =Imp!D15 -> 23596
B60: =Imp!B16 -> 8 - Building Improvement - Peter St - 27.5yr | D60: =SUM(F60:H60) -> 62751 | H60: =Imp!D16 -> 62751
B61: Total Allocation | D61: =SUM(D59:D60) -> 86347 | F61: =SUM(F59:F60) -> 23596 | H61: =SUM(H59:H60) -> 62751
B62: Check: Allocation vs. Cost Detail (should be zero) | D62: =D61-D54 -> 0
