Workbook

Sheet Summary
A1: Macedonia Apartments LLC
A2: Macedonia Apartments — 1722 W 17th St, Panama City, FL 32405
A3: EIN: 27-3618924 · FYE: December 31, 2024 · Year of Change: 1/1/2024
A4: Summary of Cost Segregation Adjustments — CSSI Report #107752-05 (CAM — DCN #7)
A7: Acq Date | B7: Asset Description | C7: Total | D7: Site | E7: Office | F7: A | G7: B | H7: C | I7: D | J7: E | K7: F | L7: G | M7: H | N7: I | O7: J | P7: K | Q7: L | R7: M | S7: Imp
A8: 5/12/11 | B8: Building - Site | C8: =SUM(D8:S8) -> 142802.44 | D8: =Site!$D$10 -> 142802.44
A9: 5/31/22 | B9: Building Improvements - Site | C9: =SUM(D9:S9) -> 440052.61 | D9: =Site!$D$11 -> 440052.61
A10: 7/01/23 | B10: Building Improvements - Site | C10: =SUM(D10:S10) -> 2396.64 | D10: =Site!$D$12 -> 2396.64
A11: 5/12/11 | B11: Land Improvements - Site | C11: =SUM(D11:S11) -> 34976.58 | D11: =Site!$D$13 -> 34976.58
A12: 5/31/22 | B12: Land Improvements - Site | C12: =SUM(D12:S12) -> 70357.38 | D12: =Site!$D$14 -> 70357.38
A13: 5/31/22 | B13: Equipment - Site | C13: =SUM(D13:S13) -> 108447.32 | D13: =Site!$D$15 -> 108447.32
A14: 5/12/11 | B14: Building - Office | C14: =SUM(D14:S14) -> 29464.18 | E14: =Office!$D$10 -> 29464.18
A15: 5/31/22 | B15: Building Improvements - Office | C15: =SUM(D15:S15) -> 90795.27 | E15: =Office!$D$11 -> 90795.27
A16: 7/01/23 | B16: Building Improvements - Office | C16: =SUM(D16:S16) -> 494.5 | E16: =Office!$D$12 -> 494.5
A17: 5/12/11 | B17: Land Improvements - Office | C17: =SUM(D17:S17) -> 7216.65 | E17: =Office!$D$13 -> 7216.65
A18: 5/31/22 | B18: Land Improvements - Office | C18: =SUM(D18:S18) -> 14516.71 | E18: =Office!$D$14 -> 14516.71
A19: 5/31/22 | B19: Equipment - Office | C19: =SUM(D19:S19) -> 22375.75 | E19: =Office!$D$15 -> 22375.75
A20: 5/12/11 | B20: Building - Apt | C20: =SUM(D20:S20) -> 1144524.4 | F20: =A!$D$10 -> 92190.66 | G20: =B!$D$10 -> 92190.66 | H20: =C!$D$10 -> 92190.66 | I20: =D!$D$10 -> 92190.66 | J20: =E!$D$10 -> 92190.66 | K20: =F!$D$10 -> 92190.66 | L20: =G!$D$10 -> 92190.66 | M20: =H!$D$10 -> 92190.66 | N20: =I!$D$10 -> 92190.66 | O20: =J!$D$10 -> 78702.11 | P20: =K!$D$10 -> 78702.11 | Q20: =L!$D$10 -> 78702.11 | R20: =M!$D$10 -> 78702.11
A21: 5/31/22 | B21: Building Improvements - Apt | C21: =SUM(D21:S21) -> 3526906.1 | F21: =A!$D$11 -> 284089.88 | G21: =B!$D$11 -> 284089.88 | H21: =C!$D$11 -> 284089.88 | I21: =D!$D$11 -> 284089.88 | J21: =E!$D$11 -> 284089.88 | K21: =F!$D$11 -> 284089.88 | L21: =G!$D$11 -> 284089.88 | M21: =H!$D$11 -> 284089.88 | N21: =I!$D$11 -> 284089.88 | O21: =J!$D$11 -> 242524.3 | P21: =K!$D$11 -> 242524.3 | Q21: =L!$D$11 -> 242524.3 | R21: =M!$D$11 -> 242524.3
A22: 7/01/23 | B22: Building Improvements - Apt | C22: =SUM(D22:S22) -> 19208.86 | F22: =A!$D$12 -> 1547.26 | G22: =B!$D$12 -> 1547.26 | H22: =C!$D$12 -> 1547.26 | I22: =D!$D$12 -> 1547.26 | J22: =E!$D$12 -> 1547.26 | K22: =F!$D$12 -> 1547.26 | L22: =G!$D$12 -> 1547.26 | M22: =H!$D$12 -> 1547.26 | N22: =I!$D$12 -> 1547.26 | O22: =J!$D$12 -> 1320.88 | P22: =K!$D$12 -> 1320.88 | Q22: =L!$D$12 -> 1320.88 | R22: =M!$D$12 -> 1320.88
A23: 5/12/11 | B23: Land Improvements - Apt | C23: =SUM(D23:S23) -> 280327.77 | F23: =A!$D$13 -> 22580.21 | G23: =B!$D$13 -> 22580.21 | H23: =C!$D$13 -> 22580.21 | I23: =D!$D$13 -> 22580.21 | J23: =E!$D$13 -> 22580.21 | K23: =F!$D$13 -> 22580.21 | L23: =G!$D$13 -> 22580.21 | M23: =H!$D$13 -> 22580.21 | N23: =I!$D$13 -> 22580.21 | O23: =J!$D$13 -> 19276.47 | P23: =K!$D$13 -> 19276.47 | Q23: =L!$D$13 -> 19276.47 | R23: =M!$D$13 -> 19276.47
A24: 5/31/22 | B24: Land Improvements - Apt | C24: =SUM(D24:S24) -> 563895.91 | F24: =A!$D$14 -> 45421.43 | G24: =B!$D$14 -> 45421.43 | H24: =C!$D$14 -> 45421.43 | I24: =D!$D$14 -> 45421.43 | J24: =E!$D$14 -> 45421.43 | K24: =F!$D$14 -> 45421.43 | L24: =G!$D$14 -> 45421.43 | M24: =H!$D$14 -> 45421.43 | N24: =I!$D$14 -> 45421.43 | O24: =J!$D$14 -> 38775.76 | P24: =K!$D$14 -> 38775.76 | Q24: =L!$D$14 -> 38775.76 | R24: =M!$D$14 -> 38775.76
A25: 5/31/22 | B25: Equipment - Apt | C25: =SUM(D25:S25) -> 869176.93 | F25: =A!$D$15 -> 70011.61 | G25: =B!$D$15 -> 70011.61 | H25: =C!$D$15 -> 70011.61 | I25: =D!$D$15 -> 70011.61 | J25: =E!$D$15 -> 70011.61 | K25: =F!$D$15 -> 70011.61 | L25: =G!$D$15 -> 70011.61 | M25: =H!$D$15 -> 70011.61 | N25: =I!$D$15 -> 70011.61 | O25: =J!$D$15 -> 59768.11 | P25: =K!$D$15 -> 59768.11 | Q25: =L!$D$15 -> 59768.11 | R25: =M!$D$15 -> 59768.11
A26: 6/30/13 | B26: Buidling Improvement | C26: =SUM(D26:S26) -> 68710 | S26: =Imp!$D$10 -> 68710
A27: 6/30/14 | B27: Buidling Improvement | C27: =SUM(D27:S27) -> 5854 | S27: =Imp!$D$11 -> 5854
A28: 10/18/17 | B28: Buidling Improvement | C28: =SUM(D28:S28) -> 118173 | S28: =Imp!$D$12 -> 118173
B29: Grand Total | C29: =SUM(C8:C28) -> 7560673 | D29: =SUM(D8:D28) -> 799032.97 | E29: =SUM(E8:E28) -> 164863.06 | F29: =SUM(F8:F28) -> 515841.05 | G29: =SUM(G8:G28) -> 515841.05 | H29: =SUM(H8:H28) -> 515841.05 | I29: =SUM(I8:I28) -> 515841.05 | J29: =SUM(J8:J28) -> 515841.05 | ... S29: =SUM(S8:S28) -> 192737
B31: MACRS Reclassification
A32: 5/12/11 | B32: Building - Site - 15yr | C32: =SUM(D32:S32) -> 91941.42 | D32: =Site!$D$20 -> 91941.42
A33: 5/12/11 | B33: Building - Site - 27.5yr | C33: =SUM(D33:S33) -> 50861.02 | D33: =Site!$D$21 -> 50861.02
A34: 5/31/22 | B34: Building Improvements - Site - 15yr | C34: =SUM(D34:S34) -> 283321.93 | D34: =Site!$D$22 -> 283321.93
A35: 5/31/22 | B35: Building Improvements - Site - 27.5yr | C35: =SUM(D35:S35) -> 156730.68 | D35: =Site!$D$23 -> 156730.68
A36: 7/01/23 | B36: Building Improvements - Site - 15yr | C36: =SUM(D36:S36) -> 1543.04 | D36: =Site!$D$24 -> 1543.04
A37: 7/01/23 | B37: Building Improvements - Site - 27.5yr | C37: =SUM(D37:S37) -> 853.6 | D37: =Site!$D$25 -> 853.6
A38: 5/12/11 | B38: Land Improvements - Site - 15yr | C38: =SUM(D38:S38) -> 22519.2 | D38: =Site!$D$26 -> 22519.2
A39: 5/12/11 | B39: Land Improvements - Site - 27.5yr | C39: =SUM(D39:S39) -> 12457.38 | D39: =Site!$D$27 -> 12457.38
A40: 5/31/22 | B40: Land Improvements - Site - 15yr | C40: =SUM(D40:S40) -> 45298.65 | D40: =Site!$D$28 -> 45298.65
A41: 5/31/22 | B41: Land Improvements - Site - 27.5yr | C41: =SUM(D41:S41) -> 25058.73 | D41: =Site!$D$29 -> 25058.73
A42: 5/31/22 | B42: Equipment - Site - 15yr | C42: =SUM(D42:S42) -> 69822.35 | D42: =Site!$D$30 -> 69822.35
A43: 5/31/22 | B43: Equipment - Site - 27.5yr | C43: =SUM(D43:S43) -> 38624.97 | D43: =Site!$D$31 -> 38624.97
A44: 5/12/11 | B44: Building - Office - 5yr | C44: =SUM(D44:S44) -> 4304.14 | E44: =Office!$D$20 -> 4304.14
A45: 5/12/11 | B45: Building - Office - 27.5yr | C45: =SUM(D45:S45) -> 25160.04 | E45: =Office!$D$21 -> 25160.04
A46: 5/31/22 | B46: Building Improvements - Office - 5yr | C46: =SUM(D46:S46) -> 13263.4 | E46: =Office!$D$22 -> 13263.4
A47: 5/31/22 | B47: Building Improvements - Office - 27.5yr | C47: =SUM(D47:S47) -> 77531.87 | E47: =Office!$D$23 -> 77531.87
A48: 7/01/23 | B48: Building Improvements - Office - 5yr | C48: =SUM(D48:S48) -> 72.24 | E48: =Office!$D$24 -> 72.24
A49: 7/01/23 | B49: Building Improvements - Office - 27.5yr | C49: =SUM(D49:S49) -> 422.26 | E49: =Office!$D$25 -> 422.26
A50: 5/12/11 | B50: Land Improvements - Office - 5yr | C50: =SUM(D50:S50) -> 1054.21 | E50: =Office!$D$26 -> 1054.21
A51: 5/12/11 | B51: Land Improvements - Office - 27.5yr | C51: =SUM(D51:S51) -> 6162.44 | E51: =Office!$D$27 -> 6162.44
A52: 5/31/22 | B52: Land Improvements - Office - 5yr | C52: =SUM(D52:S52) -> 2120.61 | E52: =Office!$D$28 -> 2120.61
A53: 5/31/22 | B53: Land Improvements - Office - 27.5yr | C53: =SUM(D53:S53) -> 12396.1 | E53: =Office!$D$29 -> 12396.1
A54: 5/31/22 | B54: Equipment - Office - 5yr | C54: =SUM(D54:S54) -> 3268.65 | E54: =Office!$D$30 -> 3268.65
A55: 5/31/22 | B55: Equipment - Office - 27.5yr | C55: =SUM(D55:S55) -> 19107.1 | E55: =Office!$D$31 -> 19107.1
A56: 5/12/11 | B56: Building - Apt - 5yr | C56: =SUM(D56:S56) -> 233911.9 | F56: =A!$D$20 -> 18720.42 | G56: =B!$D$20 -> 18720.42 | H56: =C!$D$20 -> 18720.42 | I56: =D!$D$20 -> 18720.42 | J56: =E!$D$20 -> 18720.42 | K56: =F!$D$20 -> 18720.42 | L56: =G!$D$20 -> 18720.42 | M56: =H!$D$20 -> 18720.42 | N56: =I!$D$20 -> 18720.42 | O56: =J!$D$20 -> 16357.03 | P56: =K!$D$20 -> 16357.03 | Q56: =L!$D$20 -> 16357.03 | R56: =M!$D$20 -> 16357.03
A57: 5/12/11 | B57: Building - Apt - 27.5yr | C57: =SUM(D57:S57) -> 910612.48 | F57: =A!$D$21 -> 73470.24 | G57: =B!$D$21 -> 73470.24 | H57: =C!$D$21 -> 73470.24 | I57: =D!$D$21 -> 73470.24 | J57: =E!$D$21 -> 73470.24 | K57: =F!$D$21 -> 73470.24 | L57: =G!$D$21 -> 73470.24 | M57: =H!$D$21 -> 73470.24 | N57: =I!$D$21 -> 73470.24 | O57: =J!$D$21 -> 62345.08 | P57: =K!$D$21 -> 62345.08 | Q57: =L!$D$21 -> 62345.08 | R57: =M!$D$21 -> 62345.08
A58: 5/31/22 | B58: Building Improvements - Apt - 5yr | C58: =SUM(D58:S58) -> 720810.45 | F58: =A!$D$22 -> 57687.85 | G58: =B!$D$22 -> 57687.85 | H58: =C!$D$22 -> 57687.85 | I58: =D!$D$22 -> 57687.85 | J58: =E!$D$22 -> 57687.85 | K58: =F!$D$22 -> 57687.85 | L58: =G!$D$22 -> 57687.85 | M58: =H!$D$22 -> 57687.85 | N58: =I!$D$22 -> 57687.85 | O58: =J!$D$22 -> 50404.95 | P58: =K!$D$22 -> 50404.95 | Q58: =L!$D$22 -> 50404.95 | R58: =M!$D$22 -> 50404.95
A59: 5/31/22 | B59: Building Improvements - Apt - 27.5yr | C59: =SUM(D59:S59) -> 2806095.7 | F59: =A!$D$23 -> 226402.03 | G59: =B!$D$23 -> 226402.03 | H59: =C!$D$23 -> 226402.03 | I59: =D!$D$23 -> 226402.03 | J59: =E!$D$23 -> 226402.03 | K59: =F!$D$23 -> 226402.03 | L59: =G!$D$23 -> 226402.03 | M59: =H!$D$23 -> 226402.03 | N59: =I!$D$23 -> 226402.03 | O59: =J!$D$23 -> 192119.35 | P59: =K!$D$23 -> 192119.35 | Q59: =L!$D$23 -> 192119.35 | R59: =M!$D$23 -> 192119.35
A60: 7/01/23 | B60: Building Improvements - Apt - 5yr | C60: =SUM(D60:S60) -> 3925.79 | F60: =A!$D$24 -> 314.19 | G60: =B!$D$24 -> 314.19 | H60: =C!$D$24 -> 314.19 | I60: =D!$D$24 -> 314.19 | J60: =E!$D$24 -> 314.19 | K60: =F!$D$24 -> 314.19 | L60: =G!$D$24 -> 314.19 | M60: =H!$D$24 -> 314.19 | N60: =I!$D$24 -> 314.19 | O60: =J!$D$24 -> 274.52 | P60: =K!$D$24 -> 274.52 | Q60: =L!$D$24 -> 274.52 | R60: =M!$D$24 -> 274.52
A61: 7/01/23 | B61: Building Improvements - Apt - 27.5yr | C61: =SUM(D61:S61) -> 15283.07 | F61: =A!$D$25 -> 1233.07 | G61: =B!$D$25 -> 1233.07 | H61: =C!$D$25 -> 1233.07 | I61: =D!$D$25 -> 1233.07 | J61: =E!$D$25 -> 1233.07 | K61: =F!$D$25 -> 1233.07 | L61: =G!$D$25 -> 1233.07 | M61: =H!$D$25 -> 1233.07 | N61: =I!$D$25 -> 1233.07 | O61: =J!$D$25 -> 1046.36 | P61: =K!$D$25 -> 1046.36 | Q61: =L!$D$25 -> 1046.36 | R61: =M!$D$25 -> 1046.36
A62: 5/12/11 | B62: Land Improvements - Apt - 5yr | C62: =SUM(D62:S62) -> 57291.9 | F62: =A!$D$26 -> 4585.18 | G62: =B!$D$26 -> 4585.18 | H62: =C!$D$26 -> 4585.18 | I62: =D!$D$26 -> 4585.18 | J62: =E!$D$26 -> 4585.18 | K62: =F!$D$26 -> 4585.18 | L62: =G!$D$26 -> 4585.18 | M62: =H!$D$26 -> 4585.18 | N62: =I!$D$26 -> 4585.18 | O62: =J!$D$26 -> 4006.32 | P62: =K!$D$26 -> 4006.32 | Q62: =L!$D$26 -> 4006.32 | R62: =M!$D$26 -> 4006.32
A63: 5/12/11 | B63: Land Improvements - Apt - 27.5yr | C63: =SUM(D63:S63) -> 223035.87 | F63: =A!$D$27 -> 17995.03 | G63: =B!$D$27 -> 17995.03 | H63: =C!$D$27 -> 17995.03 | I63: =D!$D$27 -> 17995.03 | J63: =E!$D$27 -> 17995.03 | K63: =F!$D$27 -> 17995.03 | L63: =G!$D$27 -> 17995.03 | M63: =H!$D$27 -> 17995.03 | N63: =I!$D$27 -> 17995.03 | O63: =J!$D$27 -> 15270.15 | P63: =K!$D$27 -> 15270.15 | Q63: =L!$D$27 -> 15270.15 | R63: =M!$D$27 -> 15270.15
A64: 5/31/22 | B64: Land Improvements - Apt - 5yr | C64: =SUM(D64:S64) -> 115246.04 | F64: =A!$D$28 -> 9223.36 | G64: =B!$D$28 -> 9223.36 | H64: =C!$D$28 -> 9223.36 | I64: =D!$D$28 -> 9223.36 | J64: =E!$D$28 -> 9223.36 | K64: =F!$D$28 -> 9223.36 | L64: =G!$D$28 -> 9223.36 | M64: =H!$D$28 -> 9223.36 | N64: =I!$D$28 -> 9223.36 | O64: =J!$D$28 -> 8058.95 | P64: =K!$D$28 -> 8058.95 | Q64: =L!$D$28 -> 8058.95 | R64: =M!$D$28 -> 8058.95
A65: 5/31/22 | B65: Land Improvements - Apt - 27.5yr | C65: =SUM(D65:S65) -> 448649.87 | F65: =A!$D$29 -> 36198.07 | G65: =B!$D$29 -> 36198.07 | H65: =C!$D$29 -> 36198.07 | I65: =D!$D$29 -> 36198.07 | J65: =E!$D$29 -> 36198.07 | K65: =F!$D$29 -> 36198.07 | L65: =G!$D$29 -> 36198.07 | M65: =H!$D$29 -> 36198.07 | N65: =I!$D$29 -> 36198.07 | O65: =J!$D$29 -> 30716.81 | P65: =K!$D$29 -> 30716.81 | Q65: =L!$D$29 -> 30716.81 | R65: =M!$D$29 -> 30716.81
A66: 5/31/22 | B66: Equipment - Apt - 5yr | C66: =SUM(D66:S66) -> 177637.73 | F66: =A!$D$30 -> 14216.69 | G66: =B!$D$30 -> 14216.69 | H66: =C!$D$30 -> 14216.69 | I66: =D!$D$30 -> 14216.69 | J66: =E!$D$30 -> 14216.69 | K66: =F!$D$30 -> 14216.69 | L66: =G!$D$30 -> 14216.69 | M66: =H!$D$30 -> 14216.69 | N66: =I!$D$30 -> 14216.69 | O66: =J!$D$30 -> 12421.88 | P66: =K!$D$30 -> 12421.88 | Q66: =L!$D$30 -> 12421.88 | R66: =M!$D$30 -> 12421.88
A67: 5/31/22 | B67: Equipment - Apt - 27.5yr | C67: =SUM(D67:S67) -> 691539.2 | F67: =A!$D$31 -> 55794.92 | G67: =B!$D$31 -> 55794.92 | H67: =C!$D$31 -> 55794.92 | I67: =D!$D$31 -> 55794.92 | J67: =E!$D$31 -> 55794.92 | K67: =F!$D$31 -> 55794.92 | L67: =G!$D$31 -> 55794.92 | M67: =H!$D$31 -> 55794.92 | N67: =I!$D$31 -> 55794.92 | O67: =J!$D$31 -> 47346.23 | P67: =K!$D$31 -> 47346.23 | Q67: =L!$D$31 -> 47346.23 | R67: =M!$D$31 -> 47346.23
A68: 6/30/13 | B68: Buidling Improvement - 5yr | C68: =SUM(D68:S68) -> 68710 | S68: =Imp!$D$17 -> 68710
A69: 6/30/14 | B69: Buidling Improvement - 5yr | C69: =SUM(D69:S69) -> 5854 | S69: =Imp!$D$18 -> 5854
A70: 10/18/17 | B70: Buidling Improvement - 15yr | C70: =SUM(D70:S70) -> 77000 | S70: =Imp!$D$19 -> 77000
A71: 10/18/17 | B71: Buidling Improvement - 27.5yr | C71: =SUM(D71:S71) -> 41173 | S71: =Imp!$D$20 -> 41173
B72: Total MACRS Reclassification | C72: =SUM(C32:C71) -> 7560673 | D72: =SUM(D32:D71) -> 799032.97 | E72: =SUM(E32:E71) -> 164863.06 | F72: =SUM(F32:F71) -> 515841.05 | G72: =SUM(G32:G71) -> 515841.05 | H72: =SUM(H32:H71) -> 515841.05 | I72: =SUM(I32:I71) -> 515841.05 | J72: =SUM(J32:J71) -> 515841.05 | ... S72: =SUM(S32:S71) -> 192737
B73: Difference (should be zero) | C73: =C29-C72 -> 0 | D73: =D29-D72 -> 0 | E73: =E29-E72 -> 0 | F73: =F29-F72 -> 0 | G73: =G29-G72 -> 0 | H73: =H29-H72 -> 0 | I73: =I29-I72 -> 0 | J73: =J29-J72 -> 0 | ... S73: =S29-S72 -> 0
B75: End Depreciation Reconciliation
B76: Before Cost Segregation (As Previously Filed) | C76: =SUM(D76:S76) -> 2803838 | D76: =Site!$I$16 -> 299829.27 | E76: =Office!$I$16 -> 61853.94 | F76: =A!$I$16 -> 193535.18 | G76: =B!$I$16 -> 193535.18 | H76: =C!$I$16 -> 193535.18 | I76: =D!$I$16 -> 193535.18 | J76: =E!$I$16 -> 193535.18 | K76: =F!$I$16 -> 193535.18 | L76: =G!$I$16 -> 193535.18 | M76: =H!$I$16 -> 193535.18 | N76: =I!$I$16 -> 193535.18 | O76: =J!$I$16 -> 165218.78 | P76: =K!$I$16 -> 165218.78 | Q76: =L!$I$16 -> 165218.78 | R76: =M!$I$16 -> 165218.78 | S76: =Imp!$I$13 -> 39463
B77: Building - Site - 15yr | C77: =SUM(D77:S77) -> 83797.85 | D77: =Site!$I$20 -> 83797.85
B78: Building - Site - 27.5yr | C78: =SUM(D78:S78) -> 25199.3 | D78: =Site!$I$21 -> 25199.3
B79: Building Improvements - Site - 15yr | C79: =SUM(D79:S79) -> 283321.93 | D79: =Site!$I$22 -> 283321.93
B80: Building Improvements - Site - 27.5yr | C80: =SUM(D80:S80) -> 14960.66 | D80: =Site!$I$23 -> 14960.66
B81: Building Improvements - Site - 15yr | C81: =SUM(D81:S81) -> 1279.18 | D81: =Site!$I$24 -> 1279.18
B82: Building Improvements - Site - 27.5yr | C82: =SUM(D82:S82) -> 45.27 | D82: =Site!$I$25 -> 45.27
B83: Land Improvements - Site - 15yr | C83: =SUM(D83:S83) -> 22519.2 | D83: =Site!$I$26 -> 22519.2
B84: Land Improvements - Site - 27.5yr | C84: =SUM(D84:S84) -> 11957.28 | D84: =Site!$I$27 -> 11957.28
B85: Land Improvements - Site - 15yr | C85: =SUM(D85:S85) -> 45298.65 | D85: =Site!$I$28 -> 45298.65
B86: Land Improvements - Site - 27.5yr | C86: =SUM(D86:S86) -> 2391.98 | D86: =Site!$I$29 -> 2391.98
B87: Equipment - Site - 15yr | C87: =SUM(D87:S87) -> 69822.35 | D87: =Site!$I$30 -> 69822.35
B88: Equipment - Site - 27.5yr | C88: =SUM(D88:S88) -> 3686.92 | D88: =Site!$I$31 -> 3686.92
B89: Building - Office - 5yr | C89: =SUM(D89:S89) -> 4304.14 | E89: =Office!$I$20 -> 4304.14
B90: Building - Office - 27.5yr | C90: =SUM(D90:S90) -> 12465.65 | E90: =Office!$I$21 -> 12465.65
B91: Building Improvements - Office - 5yr | C91: =SUM(D91:S91) -> 13263.4 | E91: =Office!$I$22 -> 13263.4
B92: Building Improvements - Office - 27.5yr | C92: =SUM(D92:S92) -> 7400.77 | E92: =Office!$I$23 -> 7400.77
B93: Building Improvements - Office - 5yr | C93: =SUM(D93:S93) -> 65.3 | E93: =Office!$I$24 -> 65.3
B94: Building Improvements - Office - 27.5yr | C94: =SUM(D94:S94) -> 22.39 | E94: =Office!$I$25 -> 22.39
B95: Land Improvements - Office - 5yr | C95: =SUM(D95:S95) -> 1054.21 | E95: =Office!$I$26 -> 1054.21
B96: Land Improvements - Office - 27.5yr | C96: =SUM(D96:S96) -> 3053.23 | E96: =Office!$I$27 -> 3053.23
B97: Land Improvements - Office - 5yr | C97: =SUM(D97:S97) -> 2120.61 | E97: =Office!$I$28 -> 2120.61
B98: Land Improvements - Office - 27.5yr | C98: =SUM(D98:S98) -> 1183.27 | E98: =Office!$I$29 -> 1183.27
B99: Equipment - Office - 5yr | C99: =SUM(D99:S99) -> 3268.65 | E99: =Office!$I$30 -> 3268.65
B100: Equipment - Office - 27.5yr | C100: =SUM(D100:S100) -> 1823.85 | E100: =Office!$I$31 -> 1823.85
B101: Building - Apt - 5yr | C101: =SUM(D101:S101) -> 233911.9 | F101: =A!$I$20 -> 18720.42 | G101: =B!$I$20 -> 18720.42 | H101: =C!$I$20 -> 18720.42 | I101: =D!$I$20 -> 18720.42 | J101: =E!$I$20 -> 18720.42 | K101: =F!$I$20 -> 18720.42 | L101: =G!$I$20 -> 18720.42 | M101: =H!$I$20 -> 18720.42 | N101: =I!$I$20 -> 18720.42 | O101: =J!$I$20 -> 16357.03 | P101: =K!$I$20 -> 16357.03 | Q101: =L!$I$20 -> 16357.03 | R101: =M!$I$20 -> 16357.03
B102: Building - Apt - 27.5yr | C102: =SUM(D102:S102) -> 451167.47 | F102: =A!$I$21 -> 36401.23 | G102: =B!$I$21 -> 36401.23 | H102: =C!$I$21 -> 36401.23 | I102: =D!$I$21 -> 36401.23 | J102: =E!$I$21 -> 36401.23 | K102: =F!$I$21 -> 36401.23 | L102: =G!$I$21 -> 36401.23 | M102: =H!$I$21 -> 36401.23 | N102: =I!$I$21 -> 36401.23 | O102: =J!$I$21 -> 30889.1 | P102: =K!$I$21 -> 30889.1 | Q102: =L!$I$21 -> 30889.1 | R102: =M!$I$21 -> 30889.1
B103: Building Improvements - Apt - 5yr | C103: =SUM(D103:S103) -> 720810.45 | F103: =A!$I$22 -> 57687.85 | G103: =B!$I$22 -> 57687.85 | H103: =C!$I$22 -> 57687.85 | I103: =D!$I$22 -> 57687.85 | J103: =E!$I$22 -> 57687.85 | K103: =F!$I$22 -> 57687.85 | L103: =G!$I$22 -> 57687.85 | M103: =H!$I$22 -> 57687.85 | N103: =I!$I$22 -> 57687.85 | O103: =J!$I$22 -> 50404.95 | P103: =K!$I$22 -> 50404.95 | Q103: =L!$I$22 -> 50404.95 | R103: =M!$I$22 -> 50404.95
B104: Building Improvements - Apt - 27.5yr | C104: =SUM(D104:S104) -> 267854.58 | F104: =A!$I$23 -> 21611.1 | G104: =B!$I$23 -> 21611.1 | H104: =C!$I$23 -> 21611.1 | I104: =D!$I$23 -> 21611.1 | J104: =E!$I$23 -> 21611.1 | K104: =F!$I$23 -> 21611.1 | L104: =G!$I$23 -> 21611.1 | M104: =H!$I$23 -> 21611.1 | N104: =I!$I$23 -> 21611.1 | O104: =J!$I$23 -> 18338.67 | P104: =K!$I$23 -> 18338.67 | Q104: =L!$I$23 -> 18338.67 | R104: =M!$I$23 -> 18338.67
...

Sheet Site
A1: Macedonia Apartments LLC
A2: Macedonia Apartments — 1722 W 17th St, Panama City, FL 32405
A3: EIN: 27-3618924 · FYE: December 31, 2024 · Year of Change: 1/1/2024
A4: Site — Attachment to Form 3115 (DCN #7, Rev. Proc. 2024-23 §6.01)
A5: Source: CSSI Report #107752-05, "#107752-05_Macedonia Apartments, LLC - 3115 - combined R1.pdf"
A7: CALCULATION OF §481(a) ADJUSTMENT — REGULAR TAX
A8: As Previously Filed
A9: Asset | B9: Property Description | C9: Date In Service | D9: Cost | E9: Sec 179 Exp | F9: Bonus Amt | G9: Tax Prior Depreciation | H9: Tax Current Depreciation | I9: End Depreciation | J9: Net Book Value | K9: Method | L9: Period
A10: 1 | B10: Building - Site | C10: 5/12/11 | D10: 142802.44 | E10: 0 | F10: 0 | G10: 48820.24 | H10: 5205.3 | I10: =G10+H10 -> 54025.54 | J10: =D10-I10 -> 88776.9 | K10: S/L | L10: 27.5
A11: 2 | B11: Building Improvements - Site | C11: 5/31/22 | D11: 440052.61 | E11: 0 | F11: 0 | G11: 26002.77 | H11: 16000.33 | I11: =G11+H11 -> 42003.1 | J11: =D11-I11 -> 398049.51 | K11: S/L | L11: 27.5
A12: 3 | B12: Building Improvements - Site | C12: 7/01/23 | D12: 2396.64 | E12: 0 | F12: 0 | G12: 39.97 | H12: 87.2 | I12: 127.12 | J12: 2269.52 | K12: S/L | L12: 27.5
A13: 4 | B13: Land Improvements - Site | C13: 5/12/11 | D13: 34976.58 | E13: 0 | F13: 22769.68 | G13: 22769.68 | H13: 2099.13 | I13: =G13+H13 -> 24868.81 | J13: =D13-I13 -> 10107.77 | K13: 150DB | L13: 15.0
A14: 5 | B14: Land Improvements - Site | C14: 5/31/22 | D14: 70357.38 | E14: 0 | F14: 70357.38 | G14: 70357.38 | H14: 0 | I14: =G14+H14 -> 70357.38 | J14: =D14-I14 -> 0 | K14: 150DB | L14: 15.0
A15: 6 | B15: Equipment - Site | C15: 5/31/22 | D15: 108447.32 | E15: 0 | F15: 108447.32 | G15: 108447.32 | H15: 0 | I15: =G15+H15 -> 108447.32 | J15: =D15-I15 -> 0 | K15: 200DB | L15: 5.0
B16: Grand Total | D16: =SUM(D10:D15) -> 799032.97 | E16: =SUM(E10:E15) -> 0 | F16: =SUM(F10:F15) -> 201574.38 | G16: =SUM(G10:G15) -> 276437.36 | H16: =SUM(H10:H15) -> 23391.96 | I16: =SUM(I10:I15) -> 299829.27 | J16: =SUM(J10:J15) -> 499203.7
A18: After Cost Segregation Correction
A19: Asset | B19: Property Description | C19: Date In Service | D19: Cost | E19: Sec 179 Exp | F19: Bonus Amt | G19: Tax Prior Depreciation | H19: Tax Current Depreciation | I19: End Depreciation | J19: Net Book Value | K19: Method | L19: Period
A20: 1 | B20: Building - Site - 15yr | C20: 5/12/11 | D20: 91941.42 | E20: 0 | F20: 0 | G20: 78368.8 | H20: 5429.05 | I20: =G20+H20 -> 83797.85 | J20: =D20-I20 -> 8143.57 | K20: 150DB | L20: 15.0
A21: 2 | B21: Building - Site - 27.5yr | C21: 5/12/11 | D21: 50861.02 | E21: 0 | F21: 0 | G21: 23349.81 | H21: 1849.49 | I21: =G21+H21 -> 25199.3 | J21: =D21-I21 -> 25661.72 | K21: S/L | L21: 27.5
A22: 3 | B22: Building Improvements - Site - 15yr | C22: 5/31/22 | D22: 283321.93 | E22: 0 | F22: 283321.93 | G22: 283321.93 | H22: 0 | I22: =G22+H22 -> 283321.93 | J22: =D22-I22 -> 0 | K22: 150DB | L22: 15.0
A23: 4 | B23: Building Improvements - Site - 27.5yr | C23: 5/31/22 | D23: 156730.68 | E23: 0 | F23: 0 | G23: 9261.36 | H23: 5699.3 | I23: =G23+H23 -> 14960.66 | J23: =D23-I23 -> 141770.02 | K23: S/L | L23: 27.5
A24: 5 | B24: Building Improvements - Site - 15yr | C24: 7/01/23 | D24: 1543.04 | E24: 0 | F24: 1234.43 | G24: 1249.86 | H24: 29.32 | I24: =G24+H24 -> 1279.18 | J24: =D24-I24 -> 263.86 | K24: 150DB | L24: 15.0
A25: 6 | B25: Building Improvements - Site - 27.5yr | C25: 7/01/23 | D25: 853.6 | E25: 0 | F25: 0 | G25: 14.23 | H25: 31.04 | I25: =G25+H25 -> 45.27 | J25: =D25-I25 -> 808.33 | K25: S/L | L25: 27.5
A26: 7 | B26: Land Improvements - Site - 15yr | C26: 5/12/11 | D26: 22519.2 | E26: 0 | F26: 22519.2 | G26: 22519.2 | H26: 0 | I26: =G26+H26 -> 22519.2 | J26: =D26-I26 -> 0 | K26: 150DB | L26: 15.0
A27: 8 | B27: Land Improvements - Site - 27.5yr | C27: 5/12/11 | D27: 12457.38 | E27: 0 | F27: 0 | G27: 11504.28 | H27: 453 | I27: =G27+H27 -> 11957.28 | J27: =D27-I27 -> 500.1 | K27: S/L | L27: 27.5
A28: 9 | B28: Land Improvements - Site - 15yr | C28: 5/31/22 | D28: 45298.65 | E28: 0 | F28: 45298.65 | G28: 45298.65 | H28: 0 | I28: =G28+H28 -> 45298.65 | J28: =D28-I28 -> 0 | K28: 150DB | L28: 15.0
A29: 10 | B29: Land Improvements - Site - 27.5yr | C29: 5/31/22 | D29: 25058.73 | E29: 0 | F29: 0 | G29: 1480.75 | H29: 911.23 | I29: =G29+H29 -> 2391.98 | J29: =D29-I29 -> 22666.75 | K29: S/L | L29: 27.5
A30: 11 | B30: Equipment - Site - 15yr | C30: 5/31/22 | D30: 69822.35 | E30: 0 | F30: 69822.35 | G30: 69822.35 | H30: 0 | I30: =G30+H30 -> 69822.35 | J30: =D30-I30 -> 0 | K30: 150DB | L30: 15.0
A31: 12 | B31: Equipment - Site - 27.5yr | C31: 5/31/22 | D31: 38624.97 | E31: 0 | F31: 0 | G31: 2282.38 | H31: 1404.54 | I31: =G31+H31 -> 3686.92 | J31: =D31-I31 -> 34938.05 | K31: S/L | L31: 27.5
B32: Grand Total | D32: =SUM(D20:D31) -> 799032.97 | E32: =SUM(E20:E31) -> 0 | F32: =SUM(F20:F31) -> 422196.56 | G32: =SUM(G20:G31) -> 548473.6 | H32: =SUM(H20:H31) -> 15806.97 | I32: =SUM(I20:I31) -> 564280.57 | J32: =SUM(J20:J31) -> 234752.4
B34: Section 481(a) Adjustment — Regular Tax
B35: Depreciation reported previously | D35: =I16 -> 299829.27
B36: Cost Segregation Corrected Depreciation | D36: =I32 -> 564280.57
B37: Section 481(a) Adjustment — Regular Tax | D37: =D35-D36 -> -264451.3
A39: CALCULATION OF §481(a) ADJUSTMENT — AMT
A40: As Previously Filed — AMT
A41: Asset | B41: Property Description | C41: Date In Service | D41: Cost | E41: Sec 179 Exp | F41: Bonus Amt | G41: AMT Prior Depreciation | H41: AMT Current Depreciation | I41: End Depreciation | J41: Net Book Value | K41: Method | L41: Period
A42: 1 | B42: Building - Site | C42: 5/12/11 | D42: 142802.44 | E42: 0 | F42: 0 | G42: 48820.24 | H42: 5205.3 | I42: =G42+H42 -> 54025.54 | J42: =D42-I42 -> 88776.9 | K42: S/L | L42: 27.5
A43: 2 | B43: Building Improvements - Site | C43: 5/31/22 | D43: 440052.61 | E43: 0 | F43: 0 | G43: 26002.77 | H43: 16000.33 | I43: =G43+H43 -> 42003.1 | J43: =D43-I43 -> 398049.51 | K43: S/L | L43: 27.5
A44: 3 | B44: Building Improvements - Site | C44: 7/01/23 | D44: 2396.64 | E44: 0 | F44: 0 | G44: 39.97 | H44: 87.2 | I44: 127.12 | J44: 2269.52 | K44: S/L | L44: 27.5
A45: 4 | B45: Land Improvements - Site | C45: 5/12/11 | D45: 34976.58 | E45: 0 | F45: 22769.68 | G45: 22769.68 | H45: 2099.13 | I45: =G45+H45 -> 24868.81 | J45: =D45-I45 -> 10107.77 | K45: 150DB | L45: 15.0
A46: 5 | B46: Land Improvements - Site | C46: 5/31/22 | D46: 70357.38 | E46: 0 | F46: 70357.38 | G46: 70357.38 | H46: 0 | I46: =G46+H46 -> 70357.38 | J46: =D46-I46 -> 0 | K46: 150DB | L46: 15.0
A47: 6 | B47: Equipment - Site | C47: 5/31/22 | D47: 108447.32 | E47: 0 | F47: 108447.32 | G47: 108447.32 | H47: 0 | I47: =G47+H47 -> 108447.32 | J47: =D47-I47 -> 0 | K47: 200DB | L47: 5.0
B48: Grand Total | D48: =SUM(D42:D47) -> 799032.97 | E48: =SUM(E42:E47) -> 0 | F48: =SUM(F42:F47) -> 201574.38 | G48: =SUM(G42:G47) -> 276437.36 | H48: =SUM(H42:H47) -> 23391.96 | I48: =SUM(I42:I47) -> 299829.27 | J48: =SUM(J42:J47) -> 499203.7
A50: After Cost Segregation Correction — AMT
A51: Asset | B51: Property Description | C51: Date In Service | D51: Cost | E51: Sec 179 Exp | F51: Bonus Amt | G51: AMT Prior Depreciation | H51: AMT Current Depreciation | I51: End Depreciation | J51: Net Book Value | K51: Method | L51: Period
A52: 1 | B52: Building - Site - 15yr | C52: 5/12/11 | D52: 91941.42 | E52: 0 | F52: 0 | G52: 78368.8 | H52: 5429.05 | I52: =G52+H52 -> 83797.85 | J52: =D52-I52 -> 8143.57 | K52: 150DB | L52: 15.0
A53: 2 | B53: Building - Site - 27.5yr | C53: 5/12/11 | D53: 50861.02 | E53: 0 | F53: 0 | G53: 23349.81 | H53: 1849.49 | I53: =G53+H53 -> 25199.3 | J53: =D53-I53 -> 25661.72 | K53: S/L | L53: 27.5
A54: 3 | B54: Building Improvements - Site - 15yr | C54: 5/31/22 | D54: 283321.93 | E54: 0 | F54: 283321.93 | G54: 283321.93 | H54: 0 | I54: =G54+H54 -> 283321.93 | J54: =D54-I54 -> 0 | K54: 150DB | L54: 15.0
A55: 4 | B55: Building Improvements - Site - 27.5yr | C55: 5/31/22 | D55: 156730.68 | E55: 0 | F55: 0 | G55: 9261.36 | H55: 5699.3 | I55: =G55+H55 -> 14960.66 | J55: =D55-I55 -> 141770.02 | K55: S/L | L55: 27.5
A56: 5 | B56: Building Improvements - Site - 15yr | C56: 7/01/23 | D56: 1543.04 | E56: 0 | F56: 1234.43 | G56: 1249.86 | H56: 29.32 | I56: =G56+H56 -> 1279.18 | J56: =D56-I56 -> 263.86 | K56: 150DB | L56: 15.0
A57: 6 | B57: Building Improvements - Site - 27.5yr | C57: 7/01/23 | D57: 853.6 | E57: 0 | F57: 0 | G57: 14.23 | H57: 31.04 | I57: =G57+H57 -> 45.27 | J57: =D57-I57 -> 808.33 | K57: S/L | L57: 27.5
A58: 7 | B58: Land Improvements - Site - 15yr | C58: 5/12/11 | D58: 22519.2 | E58: 0 | F58: 22519.2 | G58: 22519.2 | H58: 0 | I58: =G58+H58 -> 22519.2 | J58: =D58-I58 -> 0 | K58: 150DB | L58: 15.0
A59: 8 | B59: Land Improvements - Site - 27.5yr | C59: 5/12/11 | D59: 12457.38 | E59: 0 | F59: 0 | G59: 11504.28 | H59: 453 | I59: =G59+H59 -> 11957.28 | J59: =D59-I59 -> 500.1 | K59: S/L | L59: 27.5
A60: 9 | B60: Land Improvements - Site - 15yr | C60: 5/31/22 | D60: 45298.65 | E60: 0 | F60: 45298.65 | G60: 45298.65 | H60: 0 | I60: =G60+H60 -> 45298.65 | J60: =D60-I60 -> 0 | K60: 150DB | L60: 15.0
A61: 10 | B61: Land Improvements - Site - 27.5yr | C61: 5/31/22 | D61: 25058.73 | E61: 0 | F61: 0 | G61: 1480.75 | H61: 911.23 | I61: =G61+H61 -> 2391.98 | J61: =D61-I61 -> 22666.75 | K61: S/L | L61: 27.5
A62: 11 | B62: Equipment - Site - 15yr | C62: 5/31/22 | D62: 69822.35 | E62: 0 | F62: 69822.35 | G62: 69822.35 | H62: 0 | I62: =G62+H62 -> 69822.35 | J62: =D62-I62 -> 0 | K62: 150DB | L62: 15.0
A63: 12 | B63: Equipment - Site - 27.5yr | C63: 5/31/22 | D63: 38624.97 | E63: 0 | F63: 0 | G63: 2282.38 | H63: 1404.54 | I63: =G63+H63 -> 3686.92 | J63: =D63-I63 -> 34938.05 | K63: S/L | L63: 27.5
B64: Grand Total | D64: =SUM(D52:D63) -> 799032.97 | E64: =SUM(E52:E63) -> 0 | F64: =SUM(F52:F63) -> 422196.56 | G64: =SUM(G52:G63) -> 548473.6 | H64: =SUM(H52:H63) -> 15806.97 | I64: =SUM(I52:I63) -> 564280.57 | J64: =SUM(J52:J63) -> 234752.4
B66: Section 481(a) Adjustment — AMT
B67: Depreciation reported previously | D67: =I48 -> 299829.27
B68: Cost Segregation Corrected Depreciation | D68: =I64 -> 564280.57
B69: Section 481(a) Adjustment — AMT | D69: =D67-D68 -> -264451.3
A71: COST SEGREGATION STUDY — COST SUMMARY
B72: Total Site Cost | D72: =D94 -> 799032.97
B73: Site Improvements: 15 Year | D73: =F94 -> 514446.59
B74: % of Cost | D74: =F95 -> 0.6438365
B75: Site Utilities: 27.5 Year | D75: =H94 -> 284586.38
B76: % of Cost | D76: =H95 -> 0.3561635
A78: COST SEGREGATION STUDY — COST DETAIL
B79: Property Category | D79: Cost | F79: 15 Year | H79: 27.5 Year
B80: Site Work / Improvements
B81: Parking Lot | D81: =SUM(F81:H81) -> 164940.99 | F81: 164940.99
B82: Exterior Signage | D82: =SUM(F82:H82) -> 4143.78 | F82: 4143.78
B83: Parking Lot Striping / Barriers | D83: =SUM(F83:H83) -> 5521.24 | F83: 5521.24
B84: Sidewalks / Curbs | D84: =SUM(F84:H84) -> 186309.99 | F84: 186309.99
B85: Landscaping & Flagpole | D85: =SUM(F85:H85) -> 1745.22 | F85: 1745.22
B86: Security Lighting Poles | D86: =SUM(F86:H86) -> 4914.87 | F86: 4914.87
B87: Exterior Fencing | D87: =SUM(F87:H87) -> 103840.57 | F87: 103840.57
B88: Dumpster Epads | D88: =SUM(F88:H88) -> 2527.13 | F88: 2527.13
B89: Retaining Walls | D89: =SUM(F89:H89) -> 16871.66 | F89: 16871.66
B90: Exterior Equipment Concrete Pads | D90: =SUM(F90:H90) -> 11284.92 | F90: 11284.92
B91: Mailboxes | D91: =SUM(F91:H91) -> 12346.22 | F91: 12346.22
B92: Site Utilities
B93: Site Utilities | D93: =SUM(F93:H93) -> 284586.38 | H93: 284586.38
B94: Total Site Cost | D94: =SUM(D80:D93) -> 799032.97 | F94: =SUM(F80:F93) -> 514446.59 | H94: =SUM(H80:H93) -> 284586.38
B95: % of Cost | F95: =F94/D94 -> 0.6438365 | H95: =H94/D94 -> 0.3561635
A97: ASSET ALLOCATION (per After Cost Segregation schedule)
B98: Asset (as reclassified) | D98: Cost | F98: 15 Year | H98: 27.5 Year
B99: =Site!B20 -> Building - Site - 15yr | D99: =SUM(F99:H99) -> 91941.42 | F99: =Site!D20 -> 91941.42
B100: =Site!B21 -> Building - Site - 27.5yr | D100: =SUM(F100:H100) -> 50861.02 | H100: =Site!D21 -> 50861.02
B101: =Site!B22 -> Building Improvements - Site - 15yr | D101: =SUM(F101:H101) -> 283321.93 | F101: =Site!D22 -> 283321.93
B102: =Site!B23 -> Building Improvements - Site - 27.5yr | D102: =SUM(F102:H102) -> 156730.68 | H102: =Site!D23 -> 156730.68
B103: =Site!B24 -> Building Improvements - Site - 15yr | D103: =SUM(F103:H103) -> 1543.04 | F103: =Site!D24 -> 1543.04
B104: =Site!B25 -> Building Improvements - Site - 27.5yr | D104: =SUM(F104:H104) -> 853.6 | H104: =Site!D25 -> 853.6
B105: =Site!B26 -> Land Improvements - Site - 15yr | D105: =SUM(F105:H105) -> 22519.2 | F105: =Site!D26 -> 22519.2
B106: =Site!B27 -> Land Improvements - Site - 27.5yr | D106: =SUM(F106:H106) -> 12457.38 | H106: =Site!D27 -> 12457.38
B107: =Site!B28 -> Land Improvements - Site - 15yr | D107: =SUM(F107:H107) -> 45298.65 | F107: =Site!D28 -> 45298.65
B108: =Site!B29 -> Land Improvements - Site - 27.5yr | D108: =SUM(F108:H108) -> 25058.73 | H108: =Site!D29 -> 25058.73
B109: =Site!B30 -> Equipment - Site - 15yr | D109: =SUM(F109:H109) -> 69822.35 | F109: =Site!D30 -> 69822.35
...

Sheet Office
A1: Macedonia Apartments LLC
A2: Macedonia Apartments — 1722 W 17th St, Panama City, FL 32405
A3: EIN: 27-3618924 · FYE: December 31, 2024 · Year of Change: 1/1/2024
A4: Office — Attachment to Form 3115 (DCN #7, Rev. Proc. 2024-23 §6.01)
A5: Source: CSSI Report #107752-05, "#107752-05_Macedonia Apartments, LLC - 3115 - combined R1.pdf"
A7: CALCULATION OF §481(a) ADJUSTMENT — REGULAR TAX
A8: As Previously Filed
A9: Asset | B9: Property Description | C9: Date In Service | D9: Cost | E9: Sec 179 Exp | F9: Bonus Amt | G9: Tax Prior Depreciation | H9: Tax Current Depreciation | I9: End Depreciation | J9: Net Book Value | K9: Method | L9: Period
A10: 1 | B10: Building - Office | C10: 5/12/11 | D10: 29464.18 | E10: 0 | F10: 0 | G10: 10073 | H10: 1071.33 | I10: =G10+H10 -> 11144.33 | J10: =D10-I10 -> 18319.85 | K10: S/L | L10: 27.5
A11: 2 | B11: Building Improvements - Office | C11: 5/31/22 | D11: 90795.27 | E11: 0 | F11: 0 | G11: 5365.1 | H11: 3301.32 | I11: =G11+H11 -> 8666.42 | J11: =D11-I11 -> 82128.85 | K11: S/L | L11: 27.5
A12: 3 | B12: Building Improvements - Office | C12: 7/01/23 | D12: 494.5 | E12: 0 | F12: 0 | G12: 8.23 | H12: 17.99 | I12: =G12+H12 -> 26.22 | J12: =D12-I12 -> 468.28 | K12: S/L | L12: 27.5
A13: 4 | B13: Land Improvements - Office | C13: 5/12/11 | D13: 7216.65 | E13: 0 | F13: 4698.01 | G13: 4698.01 | H13: 426.5 | I13: =G13+H13 -> 5124.51 | J13: =D13-I13 -> 2092.14 | K13: 150DB | L13: 15.0
A14: 5 | B14: Land Improvements - Office | C14: 5/31/22 | D14: 14516.71 | E14: 0 | F14: 14516.71 | G14: 14516.71 | H14: 0 | I14: =G14+H14 -> 14516.71 | J14: =D14-I14 -> 0 | K14: 150DB | L14: 15.0
A15: 6 | B15: Equipment - Office | C15: 5/31/22 | D15: 22375.75 | E15: 0 | F15: 22375.75 | G15: 22375.75 | H15: 0 | I15: =G15+H15 -> 22375.75 | J15: =D15-I15 -> 0 | K15: 200DB | L15: 5.0
B16: Grand Total | D16: =SUM(D10:D15) -> 164863.06 | E16: =SUM(E10:E15) -> 0 | F16: =SUM(F10:F15) -> 41590.47 | G16: =SUM(G10:G15) -> 57036.8 | H16: =SUM(H10:H15) -> 4817.14 | I16: =SUM(I10:I15) -> 61853.94 | J16: =SUM(J10:J15) -> 103009.12
A18: After Cost Segregation Correction
A19: Asset | B19: Property Description | C19: Date In Service | D19: Cost | E19: Sec 179 Exp | F19: Bonus Amt | G19: Tax Prior Depreciation | H19: Tax Current Depreciation | I19: End Depreciation | J19: Net Book Value | K19: Method | L19: Period
A20: 1 | B20: Building - Office - 5yr | C20: 5/12/11 | D20: 4304.14 | E20: 0 | F20: 0 | G20: 4304.14 | H20: 0 | I20: =G20+H20 -> 4304.14 | J20: =D20-I20 -> 0 | K20: 200DB | L20: 5.0
A21: 2 | B21: Building - Office - 27.5yr | C21: 5/12/11 | D21: 25160.04 | E21: 0 | F21: 0 | G21: 11550.74 | H21: 914.91 | I21: =G21+H21 -> 12465.65 | J21: =D21-I21 -> 12694.39 | K21: S/L | L21: 27.5
A22: 3 | B22: Building Improvements - Office - 5yr | C22: 5/31/22 | D22: 13263.4 | E22: 0 | F22: 13263.4 | G22: 13263.4 | H22: 0 | I22: =G22+H22 -> 13263.4 | J22: =D22-I22 -> 0 | K22: 200DB | L22: 5.0
A23: 4 | B23: Building Improvements - Office - 27.5yr | C23: 5/31/22 | D23: 77531.87 | E23: 0 | F23: 0 | G23: 4581.43 | H23: 2819.34 | I23: =G23+H23 -> 7400.77 | J23: =D23-I23 -> 70131.1 | K23: S/L | L23: 27.5
A24: 5 | B24: Building Improvements - Office - 5yr | C24: 7/01/23 | D24: 72.24 | E24: 0 | F24: 57.79 | G24: 60.68 | H24: 4.62 | I24: =G24+H24 -> 65.3 | J24: =D24-I24 -> 6.94 | K24: 200DB | L24: 5.0
A25: 6 | B25: Building Improvements - Office - 27.5yr | C25: 7/01/23 | D25: 422.26 | E25: 0 | F25: 0 | G25: 7.04 | H25: 15.35 | I25: =G25+H25 -> 22.39 | J25: =D25-I25 -> 399.87 | K25: S/L | L25: 27.5
A26: 7 | B26: Land Improvements - Office - 5yr | C26: 5/12/11 | D26: 1054.21 | E26: 0 | F26: 1054.21 | G26: 1054.21 | H26: 0 | I26: =G26+H26 -> 1054.21 | J26: =D26-I26 -> 0 | K26: 200DB | L26: 5.0
A27: 8 | B27: Land Improvements - Office - 27.5yr | C27: 5/12/11 | D27: 6162.44 | E27: 0 | F27: 0 | G27: 2829.14 | H27: 224.09 | I27: =G27+H27 -> 3053.23 | J27: =D27-I27 -> 3109.21 | K27: S/L | L27: 27.5
A28: 9 | B28: Land Improvements - Office - 5yr | C28: 5/31/22 | D28: 2120.61 | E28: 0 | F28: 2120.61 | G28: 2120.61 | H28: 0 | I28: =G28+H28 -> 2120.61 | J28: =D28-I28 -> 0 | K28: 200DB | L28: 5.0
A29: 10 | B29: Land Improvements - Office - 27.5yr | C29: 5/31/22 | D29: 12396.1 | E29: 0 | F29: 0 | G29: 732.5 | H29: 450.77 | I29: =G29+H29 -> 1183.27 | J29: =D29-I29 -> 11212.83 | K29: S/L | L29: 27.5
A30: 11 | B30: Equipment - Office - 5yr | C30: 5/31/22 | D30: 3268.65 | E30: 0 | F30: 3268.65 | G30: 3268.65 | H30: 0 | I30: =G30+H30 -> 3268.65 | J30: =D30-I30 -> 0 | K30: 200DB | L30: 5.0
A31: 12 | B31: Equipment - Office - 27.5yr | C31: 5/31/22 | D31: 19107.1 | E31: 0 | F31: 0 | G31: 1129.05 | H31: 694.8 | I31: =G31+H31 -> 1823.85 | J31: =D31-I31 -> 17283.25 | K31: S/L | L31: 27.5
B32: Grand Total | D32: =SUM(D20:D31) -> 164863.06 | E32: =SUM(E20:E31) -> 0 | F32: =SUM(F20:F31) -> 19764.66 | G32: =SUM(G20:G31) -> 44901.59 | H32: =SUM(H20:H31) -> 5123.88 | I32: =SUM(I20:I31) -> 50025.47 | J32: =SUM(J20:J31) -> 114837.59
B34: Section 481(a) Adjustment — Regular Tax
B35: Depreciation reported previously | D35: =I16 -> 61853.94
B36: Cost Segregation Corrected Depreciation | D36: =I32 -> 50025.47
B37: Section 481(a) Adjustment — Regular Tax | D37: =D35-D36 -> 11828.47
A39: CALCULATION OF §481(a) ADJUSTMENT — AMT
A40: As Previously Filed — AMT
A41: Asset | B41: Property Description | C41: Date In Service | D41: Cost | E41: Sec 179 Exp | F41: Bonus Amt | G41: AMT Prior Depreciation | H41: AMT Current Depreciation | I41: End Depreciation | J41: Net Book Value | K41: Method | L41: Period
A42: 1 | B42: Building - Office | C42: 5/12/11 | D42: 29464.18 | E42: 0 | F42: 0 | G42: 10073 | H42: 1071.33 | I42: =G42+H42 -> 11144.33 | J42: =D42-I42 -> 18319.85 | K42: S/L | L42: 27.5
A43: 2 | B43: Building Improvements - Office | C43: 5/31/22 | D43: 90795.27 | E43: 0 | F43: 0 | G43: 5365.1 | H43: 3301.32 | I43: =G43+H43 -> 8666.42 | J43: =D43-I43 -> 82128.85 | K43: S/L | L43: 27.5
A44: 3 | B44: Building Improvements - Office | C44: 7/01/23 | D44: 494.5 | E44: 0 | F44: 0 | G44: 8.23 | H44: 17.99 | I44: =G44+H44 -> 26.22 | J44: =D44-I44 -> 468.28 | K44: S/L | L44: 27.5
A45: 4 | B45: Land Improvements - Office | C45: 5/12/11 | D45: 7216.65 | E45: 0 | F45: 4698.01 | G45: 4698.01 | H45: 426.5 | I45: =G45+H45 -> 5124.51 | J45: =D45-I45 -> 2092.14 | K45: 150DB | L45: 15.0
A46: 5 | B46: Land Improvements - Office | C46: 5/31/22 | D46: 14516.71 | E46: 0 | F46: 14516.71 | G46: 14516.71 | H46: 0 | I46: =G46+H46 -> 14516.71 | J46: =D46-I46 -> 0 | K46: 150DB | L46: 15.0
A47: 6 | B47: Equipment - Office | C47: 5/31/22 | D47: 22375.75 | E47: 0 | F47: 22375.75 | G47: 22375.75 | H47: 0 | I47: =G47+H47 -> 22375.75 | J47: =D47-I47 -> 0 | K47: 200DB | L47: 5.0
B48: Grand Total | D48: =SUM(D42:D47) -> 164863.06 | E48: =SUM(E42:E47) -> 0 | F48: =SUM(F42:F47) -> 41590.47 | G48: =SUM(G42:G47) -> 57036.8 | H48: =SUM(H42:H47) -> 4817.14 | I48: =SUM(I42:I47) -> 61853.94 | J48: =SUM(J42:J47) -> 103009.12
A50: After Cost Segregation Correction — AMT
A51: Asset | B51: Property Description | C51: Date In Service | D51: Cost | E51: Sec 179 Exp | F51: Bonus Amt | G51: AMT Prior Depreciation | H51: AMT Current Depreciation | I51: End Depreciation | J51: Net Book Value | K51: Method | L51: Period
A52: 1 | B52: Building - Office - 5yr | C52: 5/12/11 | D52: 4304.14 | E52: 0 | F52: 0 | G52: 4304.14 | H52: 0 | I52: =G52+H52 -> 4304.14 | J52: =D52-I52 -> 0 | K52: 200DB | L52: 5.0
A53: 2 | B53: Building - Office - 27.5yr | C53: 5/12/11 | D53: 25160.04 | E53: 0 | F53: 0 | G53: 11550.74 | H53: 914.91 | I53: =G53+H53 -> 12465.65 | J53: =D53-I53 -> 12694.39 | K53: S/L | L53: 27.5
A54: 3 | B54: Building Improvements - Office - 5yr | C54: 5/31/22 | D54: 13263.4 | E54: 0 | F54: 13263.4 | G54: 13263.4 | H54: 0 | I54: =G54+H54 -> 13263.4 | J54: =D54-I54 -> 0 | K54: 200DB | L54: 5.0
A55: 4 | B55: Building Improvements - Office - 27.5yr | C55: 5/31/22 | D55: 77531.87 | E55: 0 | F55: 0 | G55: 4581.43 | H55: 2819.34 | I55: =G55+H55 -> 7400.77 | J55: =D55-I55 -> 70131.1 | K55: S/L | L55: 27.5
A56: 5 | B56: Building Improvements - Office - 5yr | C56: 7/01/23 | D56: 72.24 | E56: 0 | F56: 57.79 | G56: 60.68 | H56: 4.62 | I56: =G56+H56 -> 65.3 | J56: =D56-I56 -> 6.94 | K56: 200DB | L56: 5.0
A57: 6 | B57: Building Improvements - Office - 27.5yr | C57: 7/01/23 | D57: 422.26 | E57: 0 | F57: 0 | G57: 7.04 | H57: 15.35 | I57: =G57+H57 -> 22.39 | J57: =D57-I57 -> 399.87 | K57: S/L | L57: 27.5
A58: 7 | B58: Land Improvements - Office - 5yr | C58: 5/12/11 | D58: 1054.21 | E58: 0 | F58: 1054.21 | G58: 1054.21 | H58: 0 | I58: =G58+H58 -> 1054.21 | J58: =D58-I58 -> 0 | K58: 200DB | L58: 5.0
A59: 8 | B59: Land Improvements - Office - 27.5yr | C59: 5/12/11 | D59: 6162.44 | E59: 0 | F59: 0 | G59: 2829.14 | H59: 224.09 | I59: =G59+H59 -> 3053.23 | J59: =D59-I59 -> 3109.21 | K59: S/L | L59: 27.5
A60: 9 | B60: Land Improvements - Office - 5yr | C60: 5/31/22 | D60: 2120.61 | E60: 0 | F60: 2120.61 | G60: 2120.61 | H60: 0 | I60: =G60+H60 -> 2120.61 | J60: =D60-I60 -> 0 | K60: 200DB | L60: 5.0
A61: 10 | B61: Land Improvements - Office - 27.5yr | C61: 5/31/22 | D61: 12396.1 | E61: 0 | F61: 0 | G61: 732.5 | H61: 450.77 | I61: =G61+H61 -> 1183.27 | J61: =D61-I61 -> 11212.83 | K61: S/L | L61: 27.5
A62: 11 | B62: Equipment - Office - 5yr | C62: 5/31/22 | D62: 3268.65 | E62: 0 | F62: 3268.65 | G62: 3268.65 | H62: 0 | I62: =G62+H62 -> 3268.65 | J62: =D62-I62 -> 0 | K62: 200DB | L62: 5.0
A63: 12 | B63: Equipment - Office - 27.5yr | C63: 5/31/22 | D63: 19107.1 | E63: 0 | F63: 0 | G63: 1129.05 | H63: 694.8 | I63: =G63+H63 -> 1823.85 | J63: =D63-I63 -> 17283.25 | K63: S/L | L63: 27.5
B64: Grand Total | D64: =SUM(D52:D63) -> 164863.06 | E64: =SUM(E52:E63) -> 0 | F64: =SUM(F52:F63) -> 19764.66 | G64: =SUM(G52:G63) -> 44901.59 | H64: =SUM(H52:H63) -> 5123.88 | I64: =SUM(I52:I63) -> 50025.47 | J64: =SUM(J52:J63) -> 114837.59
B66: Section 481(a) Adjustment — AMT
B67: Depreciation reported previously | D67: =I48 -> 61853.94
B68: Cost Segregation Corrected Depreciation | D68: =I64 -> 50025.47
B69: Section 481(a) Adjustment — AMT | D69: =D67-D68 -> 11828.47
A71: COST SEGREGATION STUDY — COST SUMMARY
B72: Total Building Cost | D72: =D109 -> 164863.06
B73: Building Components: 5 Year | D73: =F109 -> 24083.25
B74: % of Cost | D74: =F110 -> 0.14608033
B75: Building Structure: 27.5 Year | D75: =H109 -> 140779.81
B76: % of Cost | D76: =H110 -> 0.85391967
A78: COST SEGREGATION STUDY — COST DETAIL
B79: Property Category | D79: Cost | F79: 5 Year | H79: 27.5 Year
B80: Building Components
B81: Moldings | D81: =SUM(F81:H81) -> 2971.24 | F81: 2971.24
B82: Flooring - Vinyl Plank | D82: =SUM(F82:H82) -> 11681.93 | F82: 11681.93
B83: Specialty HVAC - Dryer Vents | D83: =SUM(F83:H83) -> 197.41 | F83: 197.41
B84: Specialty Electrical - Appliances | D84: =SUM(F84:H84) -> 944.53 | F84: 944.53
B85: Communication / Data | D85: =SUM(F85:H85) -> 3452.88 | F85: 3452.88
B86: Specialty Plumbing - Laundry | D86: =SUM(F86:H86) -> 824.22 | F86: 824.22
B87: Security / Exterior Lighting | D87: =SUM(F87:H87) -> 796.45 | F87: 796.45
B88: Canopies | D88: =SUM(F88:H88) -> 456.05 | F88: 456.05
B89: Appliances | D89: =SUM(F89:H89) -> 2758.54 | F89: 2758.54
B90: Building Structure
B91: Roofing Systems | D91: =SUM(F91:H91) -> 16214.15 | H91: 16214.15
B92: Foundations | D92: =SUM(F92:H92) -> 22421.29 | H92: 22421.29
B93: HVAC | D93: =SUM(F93:H93) -> 11576.74 | H93: 11576.74
B94: Electrical | D94: =SUM(F94:H94) -> 12631.83 | H94: 12631.83
B95: Plumbing | D95: =SUM(F95:H95) -> 9410.98 | H95: 9410.98
B96: Fire Protection & Alarm | D96: =SUM(F96:H96) -> 74.04 | H96: 74.04
B97: Exterior Façade / Building Skin | D97: =SUM(F97:H97) -> 10563.11 | H97: 10563.11
B98: Doors & Frames | D98: =SUM(F98:H98) -> 4305.7 | H98: 4305.7
B99: Windows | D99: =SUM(F99:H99) -> 3720.44 | H99: 3720.44
B100: Ceiling Systems | D100: =SUM(F100:H100) -> 5202.67 | H100: 5202.67
B101: Interior Framing / Partitions | D101: =SUM(F101:H101) -> 18937.43 | H101: 18937.43
B102: Painting | D102: =SUM(F102:H102) -> 6328.16 | H102: 6328.16
... B108: Bathroom Accessories | D108: =SUM(F108:H108) -> 419.16 | H108: 419.16
B109: Total Building Cost | D109: =SUM(D80:D108) -> 164863.06 | F109: =SUM(F80:F108) -> 24083.25 | H109: =SUM(H80:H108) -> 140779.81
B110: % of Cost | F110: =F109/D109 -> 0.14608033 | H110: =H109/D109 -> 0.85391967
A112: ASSET ALLOCATION (per After Cost Segregation schedule)
B113: Asset (as reclassified) | D113: Cost | F113: 5 Year | H113: 27.5 Year
B114: =Office!B20 -> Building - Office - 5yr | D114: =SUM(F114:H114) -> 4304.14 | F114: =Office!D20 -> 4304.14
...

Sheet A
A1: Macedonia Apartments LLC
A2: Macedonia Apartments — 1722 W 17th St, Panama City, FL 32405
A3: EIN: 27-3618924 · FYE: December 31, 2024 · Year of Change: 1/1/2024
A4: A — Attachment to Form 3115 (DCN #7, Rev. Proc. 2024-23 §6.01)
A5: Source: CSSI Report #107752-05, "#107752-05_Macedonia Apartments, LLC - 3115 - combined R1.pdf"
A7: CALCULATION OF §481(a) ADJUSTMENT — REGULAR TAX
A8: As Previously Filed
A9: Asset | B9: Property Description | C9: Date In Service | D9: Cost | E9: Sec 179 Exp | F9: Bonus Amt | G9: Tax Prior Depreciation | H9: Tax Current Depreciation | I9: End Depreciation | J9: Net Book Value | K9: Method | L9: Period
A10: 1 | B10: Building - Apt | C10: 5/12/11 | D10: 92190.66 | E10: 0 | F10: 0 | G10: 31517.48 | H10: 3352.09 | I10: =G10+H10 -> 34869.57 | J10: =D10-I10 -> 57321.09 | K10: S/L | L10: 27.5
A11: 2 | B11: Building Improvements - Apt | C11: 5/31/22 | D11: 284089.88 | E11: 0 | F11: 0 | G11: 16786.89 | H11: 10329.51 | I11: =G11+H11 -> 27116.4 | J11: =D11-I11 -> 256973.48 | K11: S/L | L11: 27.5
A12: 3 | B12: Building Improvements - Apt | C12: 7/01/23 | D12: 1547.26 | E12: 0 | F12: 0 | G12: 25.76 | H12: 56.29 | I12: =G12+H12 -> 82.05 | J12: =D12-I12 -> 1465.21 | K12: S/L | L12: 27.5
A13: 4 | B13: Land Improvements - Apt | C13: 5/12/11 | D13: 22580.21 | E13: 0 | F13: 14699.63 | G13: 14699.63 | H13: 1334.49 | I13: =G13+H13 -> 16034.12 | J13: =D13-I13 -> 6546.09 | K13: 150DB | L13: 15.0
A14: 5 | B14: Land Improvements - Apt | C14: 5/31/22 | D14: 45421.43 | E14: 0 | F14: 45421.43 | G14: 45421.43 | H14: 0 | I14: =G14+H14 -> 45421.43 | J14: =D14-I14 -> 0 | K14: 150DB | L14: 15.0
A15: 6 | B15: Equipment - Apt | C15: 5/31/22 | D15: 70011.61 | E15: 0 | F15: 70011.61 | G15: 70011.61 | H15: 0 | I15: =G15+H15 -> 70011.61 | J15: =D15-I15 -> 0 | K15: 200DB | L15: 5.0
B16: Grand Total | D16: =SUM(D10:D15) -> 515841.05 | E16: =SUM(E10:E15) -> 0 | F16: =SUM(F10:F15) -> 130132.67 | G16: =SUM(G10:G15) -> 178462.8 | H16: =SUM(H10:H15) -> 15072.38 | I16: =SUM(I10:I15) -> 193535.18 | J16: =SUM(J10:J15) -> 322305.87
A18: After Cost Segregation Correction
A19: Asset | B19: Property Description | C19: Date In Service | D19: Cost | E19: Sec 179 Exp | F19: Bonus Amt | G19: Tax Prior Depreciation | H19: Tax Current Depreciation | I19: End Depreciation | J19: Net Book Value | K19: Method | L19: Period
A20: 1 | B20: Building - Apt - 5yr | C20: 5/12/11 | D20: 18720.42 | E20: 0 | F20: 0 | G20: 18720.42 | H20: 0 | I20: =G20+H20 -> 18720.42 | J20: =D20-I20 -> 0 | K20: 200DB | L20: 5.0
A21: 2 | B21: Building - Apt - 27.5yr | C21: 5/12/11 | D21: 73470.24 | E21: 0 | F21: 0 | G21: 33729.58 | H21: 2671.65 | I21: =G21+H21 -> 36401.23 | J21: =D21-I21 -> 37069.01 | K21: S/L | L21: 27.5
A22: 3 | B22: Building Improvements - Apt - 5yr | C22: 5/31/22 | D22: 57687.85 | E22: 0 | F22: 57687.85 | G22: 57687.85 | H22: 0 | I22: =G22+H22 -> 57687.85 | J22: =D22-I22 -> 0 | K22: 200DB | L22: 5.0
A23: 4 | B23: Building Improvements - Apt - 27.5yr | C23: 5/31/22 | D23: 226402.03 | E23: 0 | F23: 0 | G23: 13378.3 | H23: 8232.8 | I23: =G23+H23 -> 21611.1 | J23: =D23-I23 -> 204790.93 | K23: S/L | L23: 27.5
A24: 5 | B24: Building Improvements - Apt - 5yr | C24: 7/01/23 | D24: 314.19 | E24: 0 | F24: 251.35 | G24: 263.92 | H24: 20.11 | I24: =G24+H24 -> 284.03 | J24: =D24-I24 -> 30.16 | K24: 200DB | L24: 5.0
A25: 6 | B25: Building Improvements - Apt - 27.5yr | C25: 7/01/23 | D25: 1233.07 | E25: 0 | F25: 0 | G25: 20.55 | H25: 44.84 | I25: =G25+H25 -> 65.39 | J25: =D25-I25 -> 1167.68 | K25: S/L | L25: 27.5
A26: 7 | B26: Land Improvements - Apt - 5yr | C26: 5/12/11 | D26: 4585.18 | E26: 0 | F26: 4585.18 | G26: 4585.18 | H26: 0 | I26: =G26+H26 -> 4585.18 | J26: =D26-I26 -> 0 | K26: 200DB | L26: 5.0
A27: 8 | B27: Land Improvements - Apt - 27.5yr | C27: 5/12/11 | D27: 17995.03 | E27: 0 | F27: 0 | G27: 8261.3 | H27: 654.36 | I27: =G27+H27 -> 8915.66 | J27: =D27-I27 -> 9079.37 | K27: S/L | L27: 27.5
A28: 9 | B28: Land Improvements - Apt - 5yr | C28: 5/31/22 | D28: 9223.36 | E28: 0 | F28: 9223.36 | G28: 9223.36 | H28: 0 | I28: =G28+H28 -> 9223.36 | J28: =D28-I28 -> 0 | K28: 200DB | L28: 5.0
A29: 10 | B29: Land Improvements - Apt - 27.5yr | C29: 5/31/22 | D29: 36198.07 | E29: 0 | F29: 0 | G29: 2138.97 | H29: 1316.29 | I29: =G29+H29 -> 3455.26 | J29: =D29-I29 -> 32742.81 | K29: S/L | L29: 27.5
A30: 11 | B30: Equipment - Apt - 5yr | C30: 5/31/22 | D30: 14216.69 | E30: 0 | F30: 14216.69 | G30: 14216.69 | H30: 0 | I30: =G30+H30 -> 14216.69 | J30: =D30-I30 -> 0 | K30: 200DB | L30: 5.0
A31: 12 | B31: Equipment - Apt - 27.5yr | C31: 5/31/22 | D31: 55794.92 | E31: 0 | F31: 0 | G31: 3296.98 | H31: 2028.91 | I31: =G31+H31 -> 5325.89 | J31: =D31-I31 -> 50469.03 | K31: S/L | L31: 27.5
B32: Grand Total | D32: =SUM(D20:D31) -> 515841.05 | E32: =SUM(E20:E31) -> 0 | F32: =SUM(F20:F31) -> 85964.43 | G32: =SUM(G20:G31) -> 165523.1 | H32: =SUM(H20:H31) -> 14968.96 | I32: =SUM(I20:I31) -> 180492.06 | J32: =SUM(J20:J31) -> 335348.99
B34: Section 481(a) Adjustment — Regular Tax
B35: Depreciation reported previously | D35: =I16 -> 193535.18
B36: Cost Segregation Corrected Depreciation | D36: =I32 -> 180492.06
B37: Section 481(a) Adjustment — Regular Tax | D37: =D35-D36 -> 13043.12
A39: CALCULATION OF §481(a) ADJUSTMENT — AMT
A40: As Previously Filed — AMT
A41: Asset | B41: Property Description | C41: Date In Service | D41: Cost | E41: Sec 179 Exp | F41: Bonus Amt | G41: AMT Prior Depreciation | H41: AMT Current Depreciation | I41: End Depreciation | J41: Net Book Value | K41: Method | L41: Period
A42: 1 | B42: Building - Apt | C42: 5/12/11 | D42: 92190.66 | E42: 0 | F42: 0 | G42: 31517.48 | H42: 3352.09 | I42: =G42+H42 -> 34869.57 | J42: =D42-I42 -> 57321.09 | K42: S/L | L42: 27.5
A43: 2 | B43: Building Improvements - Apt | C43: 5/31/22 | D43: 284089.88 | E43: 0 | F43: 0 | G43: 16786.89 | H43: 10329.51 | I43: =G43+H43 -> 27116.4 | J43: =D43-I43 -> 256973.48 | K43: S/L | L43: 27.5
A44: 3 | B44: Building Improvements - Apt | C44: 7/01/23 | D44: 1547.26 | E44: 0 | F44: 0 | G44: 25.76 | H44: 56.29 | I44: =G44+H44 -> 82.05 | J44: =D44-I44 -> 1465.21 | K44: S/L | L44: 27.5
A45: 4 | B45: Land Improvements - Apt | C45: 5/12/11 | D45: 22580.21 | E45: 0 | F45: 14699.63 | G45: 14699.63 | H45: 1334.49 | I45: =G45+H45 -> 16034.12 | J45: =D45-I45 -> 6546.09 | K45: 150DB | L45: 15.0
A46: 5 | B46: Land Improvements - Apt | C46: 5/31/22 | D46: 45421.43 | E46: 0 | F46: 45421.43 | G46: 45421.43 | H46: 0 | I46: =G46+H46 -> 45421.43 | J46: =D46-I46 -> 0 | K46: 150DB | L46: 15.0
A47: 6 | B47: Equipment - Apt | C47: 5/31/22 | D47: 70011.61 | E47: 0 | F47: 70011.61 | G47: 70011.61 | H47: 0 | I47: =G47+H47 -> 70011.61 | J47: =D47-I47 -> 0 | K47: 200DB | L47: 5.0
B48: Grand Total | D48: =SUM(D42:D47) -> 515841.05 | E48: =SUM(E42:E47) -> 0 | F48: =SUM(F42:F47) -> 130132.67 | G48: =SUM(G42:G47) -> 178462.8 | H48: =SUM(H42:H47) -> 15072.38 | I48: =SUM(I42:I47) -> 193535.18 | J48: =SUM(J42:J47) -> 322305.87
A50: After Cost Segregation Correction — AMT
A51: Asset | B51: Property Description | C51: Date In Service | D51: Cost | E51: Sec 179 Exp | F51: Bonus Amt | G51: AMT Prior Depreciation | H51: AMT Current Depreciation | I51: End Depreciation | J51: Net Book Value | K51: Method | L51: Period
A52: 1 | B52: Building - Apt - 5yr | C52: 5/12/11 | D52: 18720.42 | E52: 0 | F52: 0 | G52: 18720.42 | H52: 0 | I52: =G52+H52 -> 18720.42 | J52: =D52-I52 -> 0 | K52: 200DB | L52: 5.0
A53: 2 | B53: Building - Apt - 27.5yr | C53: 5/12/11 | D53: 73470.24 | E53: 0 | F53: 0 | G53: 33729.58 | H53: 2671.65 | I53: =G53+H53 -> 36401.23 | J53: =D53-I53 -> 37069.01 | K53: S/L | L53: 27.5
A54: 3 | B54: Building Improvements - Apt - 5yr | C54: 5/31/22 | D54: 57687.85 | E54: 0 | F54: 57687.85 | G54: 57687.85 | H54: 0 | I54: =G54+H54 -> 57687.85 | J54: =D54-I54 -> 0 | K54: 200DB | L54: 5.0
A55: 4 | B55: Building Improvements - Apt - 27.5yr | C55: 5/31/22 | D55: 226402.03 | E55: 0 | F55: 0 | G55: 13378.3 | H55: 8232.8 | I55: =G55+H55 -> 21611.1 | J55: =D55-I55 -> 204790.93 | K55: S/L | L55: 27.5
A56: 5 | B56: Building Improvements - Apt - 5yr | C56: 7/01/23 | D56: 314.19 | E56: 0 | F56: 251.35 | G56: 263.92 | H56: 20.11 | I56: =G56+H56 -> 284.03 | J56: =D56-I56 -> 30.16 | K56: 200DB | L56: 5.0
A57: 6 | B57: Building Improvements - Apt - 27.5yr | C57: 7/01/23 | D57: 1233.07 | E57: 0 | F57: 0 | G57: 20.55 | H57: 44.84 | I57: =G57+H57 -> 65.39 | J57: =D57-I57 -> 1167.68 | K57: S/L | L57: 27.5
A58: 7 | B58: Land Improvements - Apt - 5yr | C58: 5/12/11 | D58: 4585.18 | E58: 0 | F58: 4585.18 | G58: 4585.18 | H58: 0 | I58: =G58+H58 -> 4585.18 | J58: =D58-I58 -> 0 | K58: 200DB | L58: 5.0
A59: 8 | B59: Land Improvements - Apt - 27.5yr | C59: 5/12/11 | D59: 17995.03 | E59: 0 | F59: 0 | G59: 8261.3 | H59: 654.36 | I59: =G59+H59 -> 8915.66 | J59: =D59-I59 -> 9079.37 | K59: S/L | L59: 27.5
A60: 9 | B60: Land Improvements - Apt - 5yr | C60: 5/31/22 | D60: 9223.36 | E60: 0 | F60: 9223.36 | G60: 9223.36 | H60: 0 | I60: =G60+H60 -> 9223.36 | J60: =D60-I60 -> 0 | K60: 200DB | L60: 5.0
A61: 10 | B61: Land Improvements - Apt - 27.5yr | C61: 5/31/22 | D61: 36198.07 | E61: 0 | F61: 0 | G61: 2138.97 | H61: 1316.29 | I61: =G61+H61 -> 3455.26 | J61: =D61-I61 -> 32742.81 | K61: S/L | L61: 27.5
A62: 11 | B62: Equipment - Apt - 5yr | C62: 5/31/22 | D62: 14216.69 | E62: 0 | F62: 14216.69 | G62: 14216.69 | H62: 0 | I62: =G62+H62 -> 14216.69 | J62: =D62-I62 -> 0 | K62: 200DB | L62: 5.0
A63: 12 | B63: Equipment - Apt - 27.5yr | C63: 5/31/22 | D63: 55794.92 | E63: 0 | F63: 0 | G63: 3296.98 | H63: 2028.91 | I63: =G63+H63 -> 5325.89 | J63: =D63-I63 -> 50469.03 | K63: S/L | L63: 27.5
B64: Grand Total | D64: =SUM(D52:D63) -> 515841.05 | E64: =SUM(E52:E63) -> 0 | F64: =SUM(F52:F63) -> 85964.43 | G64: =SUM(G52:G63) -> 165523.1 | H64: =SUM(H52:H63) -> 14968.96 | I64: =SUM(I52:I63) -> 180492.06 | J64: =SUM(J52:J63) -> 335348.99
B66: Section 481(a) Adjustment — AMT
B67: Depreciation reported previously | D67: =I48 -> 193535.18
B68: Cost Segregation Corrected Depreciation | D68: =I64 -> 180492.06
B69: Section 481(a) Adjustment — AMT | D69: =D67-D68 -> 13043.12
A71: COST SEGREGATION STUDY — COST SUMMARY
B72: Total Building Cost | D72: =D109 -> 515841.05
B73: Building Components: 5 Year | D73: =F109 -> 104747.69
B74: % of Cost | D74: =F110 -> 0.20306195
B75: Building Structure: 27.5 Year | D75: =H109 -> 411093.36
B76: % of Cost | D76: =H110 -> 0.79693805
A78: COST SEGREGATION STUDY — COST DETAIL
B79: Property Category | D79: Cost | F79: 5 Year | H79: 27.5 Year
B80: Building Components
B81: Cabinets / Millwork | D81: =SUM(F81:H81) -> 14924.28 | F81: 14924.28
B82: Moldings | D82: =SUM(F82:H82) -> 10497.34 | F82: 10497.34
B83: Flooring - Vinyl Plank | D83: =SUM(F83:H83) -> 42163.82 | F83: 42163.82
B84: Window Treatments | D84: =SUM(F84:H84) -> 5291.37 | F84: 5291.37
B85: Building Signage | D85: =SUM(F85:H85) -> 297.35 | F85: 297.35
B86: Specialty Electrical - Appliances | D86: =SUM(F86:H86) -> 5540.41 | F86: 5540.41
B87: Communication / Data | D87: =SUM(F87:H87) -> 3335.96 | F87: 3335.96
B88: Specialty Plumbing - Kitchen Sinks | D88: =SUM(F88:H88) -> 11469.05 | F88: 11469.05
B89: Security / Exterior Lighting | D89: =SUM(F89:H89) -> 1722.5 | F89: 1722.5
B90: Appliances | D90: =SUM(F90:H90) -> 9505.61 | F90: 9505.61
B91: Building Structure
B92: Roofing Systems | D92: =SUM(F92:H92) -> 23533.09 | H92: 23533.09
B93: Foundations | D93: =SUM(F93:H93) -> 28643.92 | H93: 28643.92
B94: HVAC | D94: =SUM(F94:H94) -> 42496.69 | H94: 42496.69
B95: Electrical | D95: =SUM(F95:H95) -> 35043.34 | H95: 35043.34
B96: Plumbing | D96: =SUM(F96:H96) -> 36942.14 | H96: 36942.14
B97: Fire Protection & Alarm | D97: =SUM(F97:H97) -> 1288.46 | H97: 1288.46
B98: Exterior Façade / Building Skin | D98: =SUM(F98:H98) -> 22726.22 | H98: 22726.22
B99: Doors & Frames | D99: =SUM(F99:H99) -> 21445.66 | H99: 21445.66
B100: Windows | D100: =SUM(F100:H100) -> 23322.18 | H100: 23322.18
B101: Ceiling Systems | D101: =SUM(F101:H101) -> 18778.11 | H101: 18778.11
B102: Interior Framing / Partitions | D102: =SUM(F102:H102) -> 45770.64 | H102: 45770.64
B103: Painting | D103: =SUM(F103:H103) -> 19814.11 | H103: 19814.11
... B108: Cabinets / Millwork - Restrooms | D108: =SUM(F108:H108) -> 4754 | H108: 4754
B109: Total Building Cost | D109: =SUM(D80:D108) -> 515841.05 | F109: =SUM(F80:F108) -> 104747.69 | H109: =SUM(H80:H108) -> 411093.36
B110: % of Cost | F110: =F109/D109 -> 0.20306195 | H110: =H109/D109 -> 0.79693805
A112: ASSET ALLOCATION (per After Cost Segregation schedule)
B113: Asset (as reclassified) | D113: Cost | F113: 5 Year | H113: 27.5 Year
...

Sheet B
A1: Macedonia Apartments LLC
A2: Macedonia Apartments — 1722 W 17th St, Panama City, FL 32405
A3: EIN: 27-3618924 · FYE: December 31, 2024 · Year of Change: 1/1/2024
A4: B — Attachment to Form 3115 (DCN #7, Rev. Proc. 2024-23 §6.01)
A5: Source: CSSI Report #107752-05, "#107752-05_Macedonia Apartments, LLC - 3115 - combined R1.pdf"
A7: CALCULATION OF §481(a) ADJUSTMENT — REGULAR TAX
A8: As Previously Filed
A9: Asset | B9: Property Description | C9: Date In Service | D9: Cost | E9: Sec 179 Exp | F9: Bonus Amt | G9: Tax Prior Depreciation | H9: Tax Current Depreciation | I9: End Depreciation | J9: Net Book Value | K9: Method | L9: Period
A10: 1 | B10: Building - Apt | C10: 5/12/11 | D10: 92190.66 | E10: 0 | F10: 0 | G10: 31517.48 | H10: 3352.09 | I10: =G10+H10 -> 34869.57 | J10: =D10-I10 -> 57321.09 | K10: S/L | L10: 27.5
A11: 2 | B11: Building Improvements - Apt | C11: 5/31/22 | D11: 284089.88 | E11: 0 | F11: 0 | G11: 16786.89 | H11: 10329.51 | I11: =G11+H11 -> 27116.4 | J11: =D11-I11 -> 256973.48 | K11: S/L | L11: 27.5
A12: 3 | B12: Building Improvements - Apt | C12: 7/01/23 | D12: 1547.26 | E12: 0 | F12: 0 | G12: 25.76 | H12: 56.29 | I12: =G12+H12 -> 82.05 | J12: =D12-I12 -> 1465.21 | K12: S/L | L12: 27.5
A13: 4 | B13: Land Improvements - Apt | C13: 5/12/11 | D13: 22580.21 | E13: 0 | F13: 14699.63 | G13: 14699.63 | H13: 1334.49 | I13: =G13+H13 -> 16034.12 | J13: =D13-I13 -> 6546.09 | K13: 150DB | L13: 15.0
A14: 5 | B14: Land Improvements - Apt | C14: 5/31/22 | D14: 45421.43 | E14: 0 | F14: 45421.43 | G14: 45421.43 | H14: 0 | I14: =G14+H14 -> 45421.43 | J14: =D14-I14 -> 0 | K14: 150DB | L14: 15.0
A15: 6 | B15: Equipment - Apt | C15: 5/31/22 | D15: 70011.61 | E15: 0 | F15: 70011.61 | G15: 70011.61 | H15: 0 | I15: =G15+H15 -> 70011.61 | J15: =D15-I15 -> 0 | K15: 200DB | L15: 5.0
B16: Grand Total | D16: =SUM(D10:D15) -> 515841.05 | E16: =SUM(E10:E15) -> 0 | F16: =SUM(F10:F15) -> 130132.67 | G16: =SUM(G10:G15) -> 178462.8 | H16: =SUM(H10:H15) -> 15072.38 | I16: =SUM(I10:I15) -> 193535.18 | J16: =SUM(J10:J15) -> 322305.87
A18: After Cost Segregation Correction
A19: Asset | B19: Property Description | C19: Date In Service | D19: Cost | E19: Sec 179 Exp | F19: Bonus Amt | G19: Tax Prior Depreciation | H19: Tax Current Depreciation | I19: End Depreciation | J19: Net Book Value | K19: Method | L19: Period
A20: 1 | B20: Building - Apt - 5yr | C20: 5/12/11 | D20: 18720.42 | E20: 0 | F20: 0 | G20: 18720.42 | H20: 0 | I20: =G20+H20 -> 18720.42 | J20: =D20-I20 -> 0 | K20: 200DB | L20: 5.0
A21: 2 | B21: Building - Apt - 27.5yr | C21: 5/12/11 | D21: 73470.24 | E21: 0 | F21: 0 | G21: 33729.58 | H21: 2671.65 | I21: =G21+H21 -> 36401.23 | J21: =D21-I21 -> 37069.01 | K21: S/L | L21: 27.5
A22: 3 | B22: Building Improvements - Apt - 5yr | C22: 5/31/22 | D22: 57687.85 | E22: 0 | F22: 57687.85 | G22: 57687.85 | H22: 0 | I22: =G22+H22 -> 57687.85 | J22: =D22-I22 -> 0 | K22: 200DB | L22: 5.0
A23: 4 | B23: Building Improvements - Apt - 27.5yr | C23: 5/31/22 | D23: 226402.03 | E23: 0 | F23: 0 | G23: 13378.3 | H23: 8232.8 | I23: =G23+H23 -> 21611.1 | J23: =D23-I23 -> 204790.93 | K23: S/L | L23: 27.5
A24: 5 | B24: Building Improvements - Apt - 5yr | C24: 7/01/23 | D24: 314.19 | E24: 0 | F24: 251.35 | G24: 263.92 | H24: 20.11 | I24: =G24+H24 -> 284.03 | J24: =D24-I24 -> 30.16 | K24: 200DB | L24: 5.0
A25: 6 | B25: Building Improvements - Apt - 27.5yr | C25: 7/01/23 | D25: 1233.07 | E25: 0 | F25: 0 | G25: 20.55 | H25: 44.84 | I25: =G25+H25 -> 65.39 | J25: =D25-I25 -> 1167.68 | K25: S/L | L25: 27.5
A26: 7 | B26: Land Improvements - Apt - 5yr | C26: 5/12/11 | D26: 4585.18 | E26: 0 | F26: 4585.18 | G26: 4585.18 | H26: 0 | I26: =G26+H26 -> 4585.18 | J26: =D26-I26 -> 0 | K26: 200DB | L26: 5.0
A27: 8 | B27: Land Improvements - Apt - 27.5yr | C27: 5/12/11 | D27: 17995.03 | E27: 0 | F27: 0 | G27: 8261.3 | H27: 654.36 | I27: =G27+H27 -> 8915.66 | J27: =D27-I27 -> 9079.37 | K27: S/L | L27: 27.5
A28: 9 | B28: Land Improvements - Apt - 5yr | C28: 5/31/22 | D28: 9223.36 | E28: 0 | F28: 9223.36 | G28: 9223.36 | H28: 0 | I28: =G28+H28 -> 9223.36 | J28: =D28-I28 -> 0 | K28: 200DB | L28: 5.0
A29: 10 | B29: Land Improvements - Apt - 27.5yr | C29: 5/31/22 | D29: 36198.07 | E29: 0 | F29: 0 | G29: 2138.97 | H29: 1316.29 | I29: =G29+H29 -> 3455.26 | J29: =D29-I29 -> 32742.81 | K29: S/L | L29: 27.5
A30: 11 | B30: Equipment - Apt - 5yr | C30: 5/31/22 | D30: 14216.69 | E30: 0 | F30: 14216.69 | G30: 14216.69 | H30: 0 | I30: =G30+H30 -> 14216.69 | J30: =D30-I30 -> 0 | K30: 200DB | L30: 5.0
A31: 12 | B31: Equipment - Apt - 27.5yr | C31: 5/31/22 | D31: 55794.92 | E31: 0 | F31: 0 | G31: 3296.98 | H31: 2028.91 | I31: =G31+H31 -> 5325.89 | J31: =D31-I31 -> 50469.03 | K31: S/L | L31: 27.5
B32: Grand Total | D32: =SUM(D20:D31) -> 515841.05 | E32: =SUM(E20:E31) -> 0 | F32: =SUM(F20:F31) -> 85964.43 | G32: =SUM(G20:G31) -> 165523.1 | H32: =SUM(H20:H31) -> 14968.96 | I32: =SUM(I20:I31) -> 180492.06 | J32: =SUM(J20:J31) -> 335348.99
B34: Section 481(a) Adjustment — Regular Tax
B35: Depreciation reported previously | D35: =I16 -> 193535.18
B36: Cost Segregation Corrected Depreciation | D36: =I32 -> 180492.06
B37: Section 481(a) Adjustment — Regular Tax | D37: =D35-D36 -> 13043.12
A39: CALCULATION OF §481(a) ADJUSTMENT — AMT
A40: As Previously Filed — AMT
A41: Asset | B41: Property Description | C41: Date In Service | D41: Cost | E41: Sec 179 Exp | F41: Bonus Amt | G41: AMT Prior Depreciation | H41: AMT Current Depreciation | I41: End Depreciation | J41: Net Book Value | K41: Method | L41: Period
A42: 1 | B42: Building - Apt | C42: 5/12/11 | D42: 92190.66 | E42: 0 | F42: 0 | G42: 31517.48 | H42: 3352.09 | I42: =G42+H42 -> 34869.57 | J42: =D42-I42 -> 57321.09 | K42: S/L | L42: 27.5
A43: 2 | B43: Building Improvements - Apt | C43: 5/31/22 | D43: 284089.88 | E43: 0 | F43: 0 | G43: 16786.89 | H43: 10329.51 | I43: =G43+H43 -> 27116.4 | J43: =D43-I43 -> 256973.48 | K43: S/L | L43: 27.5
A44: 3 | B44: Building Improvements - Apt | C44: 7/01/23 | D44: 1547.26 | E44: 0 | F44: 0 | G44: 25.76 | H44: 56.29 | I44: =G44+H44 -> 82.05 | J44: =D44-I44 -> 1465.21 | K44: S/L | L44: 27.5
A45: 4 | B45: Land Improvements - Apt | C45: 5/12/11 | D45: 22580.21 | E45: 0 | F45: 14699.63 | G45: 14699.63 | H45: 1334.49 | I45: =G45+H45 -> 16034.12 | J45: =D45-I45 -> 6546.09 | K45: 150DB | L45: 15.0
A46: 5 | B46: Land Improvements - Apt | C46: 5/31/22 | D46: 45421.43 | E46: 0 | F46: 45421.43 | G46: 45421.43 | H46: 0 | I46: =G46+H46 -> 45421.43 | J46: =D46-I46 -> 0 | K46: 150DB | L46: 15.0
A47: 6 | B47: Equipment - Apt | C47: 5/31/22 | D47: 70011.61 | E47: 0 | F47: 70011.61 | G47: 70011.61 | H47: 0 | I47: =G47+H47 -> 70011.61 | J47: =D47-I47 -> 0 | K47: 200DB | L47: 5.0
B48: Grand Total | D48: =SUM(D42:D47) -> 515841.05 | E48: =SUM(E42:E47) -> 0 | F48: =SUM(F42:F47) -> 130132.67 | G48: =SUM(G42:G47) -> 178462.8 | H48: =SUM(H42:H47) -> 15072.38 | I48: =SUM(I42:I47) -> 193535.18 | J48: =SUM(J42:J47) -> 322305.87
A50: After Cost Segregation Correction — AMT
A51: Asset | B51: Property Description | C51: Date In Service | D51: Cost | E51: Sec 179 Exp | F51: Bonus Amt | G51: AMT Prior Depreciation | H51: AMT Current Depreciation | I51: End Depreciation | J51: Net Book Value | K51: Method | L51: Period
A52: 1 | B52: Building - Apt - 5yr | C52: 5/12/11 | D52: 18720.42 | E52: 0 | F52: 0 | G52: 18720.42 | H52: 0 | I52: =G52+H52 -> 18720.42 | J52: =D52-I52 -> 0 | K52: 200DB | L52: 5.0
A53: 2 | B53: Building - Apt - 27.5yr | C53: 5/12/11 | D53: 73470.24 | E53: 0 | F53: 0 | G53: 33729.58 | H53: 2671.65 | I53: =G53+H53 -> 36401.23 | J53: =D53-I53 -> 37069.01 | K53: S/L | L53: 27.5
A54: 3 | B54: Building Improvements - Apt - 5yr | C54: 5/31/22 | D54: 57687.85 | E54: 0 | F54: 57687.85 | G54: 57687.85 | H54: 0 | I54: =G54+H54 -> 57687.85 | J54: =D54-I54 -> 0 | K54: 200DB | L54: 5.0
A55: 4 | B55: Building Improvements - Apt - 27.5yr | C55: 5/31/22 | D55: 226402.03 | E55: 0 | F55: 0 | G55: 13378.3 | H55: 8232.8 | I55: =G55+H55 -> 21611.1 | J55: =D55-I55 -> 204790.93 | K55: S/L | L55: 27.5
A56: 5 | B56: Building Improvements - Apt - 5yr | C56: 7/01/23 | D56: 314.19 | E56: 0 | F56: 251.35 | G56: 263.92 | H56: 20.11 | I56: =G56+H56 -> 284.03 | J56: =D56-I56 -> 30.16 | K56: 200DB | L56: 5.0
A57: 6 | B57: Building Improvements - Apt - 27.5yr | C57: 7/01/23 | D57: 1233.07 | E57: 0 | F57: 0 | G57: 20.55 | H57: 44.84 | I57: =G57+H57 -> 65.39 | J57: =D57-I57 -> 1167.68 | K57: S/L | L57: 27.5
A58: 7 | B58: Land Improvements - Apt - 5yr | C58: 5/12/11 | D58: 4585.18 | E58: 0 | F58: 4585.18 | G58: 4585.18 | H58: 0 | I58: =G58+H58 -> 4585.18 | J58: =D58-I58 -> 0 | K58: 200DB | L58: 5.0
A59: 8 | B59: Land Improvements - Apt - 27.5yr | C59: 5/12/11 | D59: 17995.03 | E59: 0 | F59: 0 | G59: 8261.3 | H59: 654.36 | I59: =G59+H59 -> 8915.66 | J59: =D59-I59 -> 9079.37 | K59: S/L | L59: 27.5
A60: 9 | B60: Land Improvements - Apt - 5yr | C60: 5/31/22 | D60: 9223.36 | E60: 0 | F60: 9223.36 | G60: 9223.36 | H60: 0 | I60: =G60+H60 -> 9223.36 | J60: =D60-I60 -> 0 | K60: 200DB | L60: 5.0
A61: 10 | B61: Land Improvements - Apt - 27.5yr | C61: 5/31/22 | D61: 36198.07 | E61: 0 | F61: 0 | G61: 2138.97 | H61: 1316.29 | I61: =G61+H61 -> 3455.26 | J61: =D61-I61 -> 32742.81 | K61: S/L | L61: 27.5
A62: 11 | B62: Equipment - Apt - 5yr | C62: 5/31/22 | D62: 14216.69 | E62: 0 | F62: 14216.69 | G62: 14216.69 | H62: 0 | I62: =G62+H62 -> 14216.69 | J62: =D62-I62 -> 0 | K62: 200DB | L62: 5.0
A63: 12 | B63: Equipment - Apt - 27.5yr | C63: 5/31/22 | D63: 55794.92 | E63: 0 | F63: 0 | G63: 3296.98 | H63: 2028.91 | I63: =G63+H63 -> 5325.89 | J63: =D63-I63 -> 50469.03 | K63: S/L | L63: 27.5
B64: Grand Total | D64: =SUM(D52:D63) -> 515841.05 | E64: =SUM(E52:E63) -> 0 | F64: =SUM(F52:F63) -> 85964.43 | G64: =SUM(G52:G63) -> 165523.1 | H64: =SUM(H52:H63) -> 14968.96 | I64: =SUM(I52:I63) -> 180492.06 | J64: =SUM(J52:J63) -> 335348.99
B66: Section 481(a) Adjustment — AMT
B67: Depreciation reported previously | D67: =I48 -> 193535.18
B68: Cost Segregation Corrected Depreciation | D68: =I64 -> 180492.06
B69: Section 481(a) Adjustment — AMT | D69: =D67-D68 -> 13043.12
A71: COST SEGREGATION STUDY — COST SUMMARY
B72: Total Building Cost | D72: =D109 -> 515841.05
B73: Building Components: 5 Year | D73: =F109 -> 104747.69
B74: % of Cost | D74: =F110 -> 0.20306195
B75: Building Structure: 27.5 Year | D75: =H109 -> 411093.36
B76: % of Cost | D76: =H110 -> 0.79693805
A78: COST SEGREGATION STUDY — COST DETAIL
B79: Property Category | D79: Cost | F79: 5 Year | H79: 27.5 Year
B80: Building Components
B81: Cabinets / Millwork | D81: =SUM(F81:H81) -> 14924.28 | F81: 14924.28
B82: Moldings | D82: =SUM(F82:H82) -> 10497.34 | F82: 10497.34
B83: Flooring - Vinyl Plank | D83: =SUM(F83:H83) -> 42163.82 | F83: 42163.82
B84: Window Treatments | D84: =SUM(F84:H84) -> 5291.37 | F84: 5291.37
B85: Building Signage | D85: =SUM(F85:H85) -> 297.35 | F85: 297.35
B86: Specialty Electrical - Appliances | D86: =SUM(F86:H86) -> 5540.41 | F86: 5540.41
B87: Communication / Data | D87: =SUM(F87:H87) -> 3335.96 | F87: 3335.96
B88: Specialty Plumbing - Kitchen Sinks | D88: =SUM(F88:H88) -> 11469.05 | F88: 11469.05
B89: Security / Exterior Lighting | D89: =SUM(F89:H89) -> 1722.5 | F89: 1722.5
B90: Appliances | D90: =SUM(F90:H90) -> 9505.61 | F90: 9505.61
B91: Building Structure
B92: Roofing Systems | D92: =SUM(F92:H92) -> 23533.09 | H92: 23533.09
B93: Foundations | D93: =SUM(F93:H93) -> 28643.92 | H93: 28643.92
B94: HVAC | D94: =SUM(F94:H94) -> 42496.69 | H94: 42496.69
B95: Electrical | D95: =SUM(F95:H95) -> 35043.34 | H95: 35043.34
B96: Plumbing | D96: =SUM(F96:H96) -> 36942.14 | H96: 36942.14
B97: Fire Protection & Alarm | D97: =SUM(F97:H97) -> 1288.46 | H97: 1288.46
B98: Exterior Façade / Building Skin | D98: =SUM(F98:H98) -> 22726.22 | H98: 22726.22
B99: Doors & Frames | D99: =SUM(F99:H99) -> 21445.66 | H99: 21445.66
B100: Windows | D100: =SUM(F100:H100) -> 23322.18 | H100: 23322.18
B101: Ceiling Systems | D101: =SUM(F101:H101) -> 18778.11 | H101: 18778.11
B102: Interior Framing / Partitions | D102: =SUM(F102:H102) -> 45770.64 | H102: 45770.64
B103: Painting | D103: =SUM(F103:H103) -> 19814.11 | H103: 19814.11
... B108: Cabinets / Millwork - Restrooms | D108: =SUM(F108:H108) -> 4754 | H108: 4754
B109: Total Building Cost | D109: =SUM(D80:D108) -> 515841.05 | F109: =SUM(F80:F108) -> 104747.69 | H109: =SUM(H80:H108) -> 411093.36
B110: % of Cost | F110: =F109/D109 -> 0.20306195 | H110: =H109/D109 -> 0.79693805
A112: ASSET ALLOCATION (per After Cost Segregation schedule)
B113: Asset (as reclassified) | D113: Cost | F113: 5 Year | H113: 27.5 Year
...

Sheet C
A1: Macedonia Apartments LLC
A2: Macedonia Apartments — 1722 W 17th St, Panama City, FL 32405
A3: EIN: 27-3618924 · FYE: December 31, 2024 · Year of Change: 1/1/2024
A4: C — Attachment to Form 3115 (DCN #7, Rev. Proc. 2024-23 §6.01)
A5: Source: CSSI Report #107752-05, "#107752-05_Macedonia Apartments, LLC - 3115 - combined R1.pdf"
A7: CALCULATION OF §481(a) ADJUSTMENT — REGULAR TAX
A8: As Previously Filed
A9: Asset | B9: Property Description | C9: Date In Service | D9: Cost | E9: Sec 179 Exp | F9: Bonus Amt | G9: Tax Prior Depreciation | H9: Tax Current Depreciation | I9: End Depreciation | J9: Net Book Value | K9: Method | L9: Period
A10: 1 | B10: Building - Apt | C10: 5/12/11 | D10: 92190.66 | E10: 0 | F10: 0 | G10: 31517.48 | H10: 3352.09 | I10: =G10+H10 -> 34869.57 | J10: =D10-I10 -> 57321.09 | K10: S/L | L10: 27.5
A11: 2 | B11: Building Improvements - Apt | C11: 5/31/22 | D11: 284089.88 | E11: 0 | F11: 0 | G11: 16786.89 | H11: 10329.51 | I11: =G11+H11 -> 27116.4 | J11: =D11-I11 -> 256973.48 | K11: S/L | L11: 27.5
A12: 3 | B12: Building Improvements - Apt | C12: 7/01/23 | D12: 1547.26 | E12: 0 | F12: 0 | G12: 25.76 | H12: 56.29 | I12: =G12+H12 -> 82.05 | J12: =D12-I12 -> 1465.21 | K12: S/L | L12: 27.5
A13: 4 | B13: Land Improvements - Apt | C13: 5/12/11 | D13: 22580.21 | E13: 0 | F13: 14699.63 | G13: 14699.63 | H13: 1334.49 | I13: =G13+H13 -> 16034.12 | J13: =D13-I13 -> 6546.09 | K13: 150DB | L13: 15.0
A14: 5 | B14: Land Improvements - Apt | C14: 5/31/22 | D14: 45421.43 | E14: 0 | F14: 45421.43 | G14: 45421.43 | H14: 0 | I14: =G14+H14 -> 45421.43 | J14: =D14-I14 -> 0 | K14: 150DB | L14: 15.0
A15: 6 | B15: Equipment - Apt | C15: 5/31/22 | D15: 70011.61 | E15: 0 | F15: 70011.61 | G15: 70011.61 | H15: 0 | I15: =G15+H15 -> 70011.61 | J15: =D15-I15 -> 0 | K15: 200DB | L15: 5.0
B16: Grand Total | D16: =SUM(D10:D15) -> 515841.05 | E16: =SUM(E10:E15) -> 0 | F16: =SUM(F10:F15) -> 130132.67 | G16: =SUM(G10:G15) -> 178462.8 | H16: =SUM(H10:H15) -> 15072.38 | I16: =SUM(I10:I15) -> 193535.18 | J16: =SUM(J10:J15) -> 322305.87
A18: After Cost Segregation Correction
A19: Asset | B19: Property Description | C19: Date In Service | D19: Cost | E19: Sec 179 Exp | F19: Bonus Amt | G19: Tax Prior Depreciation | H19: Tax Current Depreciation | I19: End Depreciation | J19: Net Book Value | K19: Method | L19: Period
A20: 1 | B20: Building - Apt - 5yr | C20: 5/12/11 | D20: 18720.42 | E20: 0 | F20: 0 | G20: 18720.42 | H20: 0 | I20: =G20+H20 -> 18720.42 | J20: =D20-I20 -> 0 | K20: 200DB | L20: 5.0
A21: 2 | B21: Building - Apt - 27.5yr | C21: 5/12/11 | D21: 73470.24 | E21: 0 | F21: 0 | G21: 33729.58 | H21: 2671.65 | I21: =G21+H21 -> 36401.23 | J21: =D21-I21 -> 37069.01 | K21: S/L | L21: 27.5
A22: 3 | B22: Building Improvements - Apt - 5yr | C22: 5/31/22 | D22: 57687.85 | E22: 0 | F22: 57687.85 | G22: 57687.85 | H22: 0 | I22: =G22+H22 -> 57687.85 | J22: =D22-I22 -> 0 | K22: 200DB | L22: 5.0
A23: 4 | B23: Building Improvements - Apt - 27.5yr | C23: 5/31/22 | D23: 226402.03 | E23: 0 | F23: 0 | G23: 13378.3 | H23: 8232.8 | I23: =G23+H23 -> 21611.1 | J23: =D23-I23 -> 204790.93 | K23: S/L | L23: 27.5
A24: 5 | B24: Building Improvements - Apt - 5yr | C24: 7/01/23 | D24: 314.19 | E24: 0 | F24: 251.35 | G24: 263.92 | H24: 20.11 | I24: =G24+H24 -> 284.03 | J24: =D24-I24 -> 30.16 | K24: 200DB | L24: 5.0
A25: 6 | B25: Building Improvements - Apt - 27.5yr | C25: 7/01/23 | D25: 1233.07 | E25: 0 | F25: 0 | G25: 20.55 | H25: 44.84 | I25: =G25+H25 -> 65.39 | J25: =D25-I25 -> 1167.68 | K25: S/L | L25: 27.5
A26: 7 | B26: Land Improvements - Apt - 5yr | C26: 5/12/11 | D26: 4585.18 | E26: 0 | F26: 4585.18 | G26: 4585.18 | H26: 0 | I26: =G26+H26 -> 4585.18 | J26: =D26-I26 -> 0 | K26: 200DB | L26: 5.0
A27: 8 | B27: Land Improvements - Apt - 27.5yr | C27: 5/12/11 | D27: 17995.03 | E27: 0 | F27: 0 | G27: 8261.3 | H27: 654.36 | I27: =G27+H27 -> 8915.66 | J27: =D27-I27 -> 9079.37 | K27: S/L | L27: 27.5
A28: 9 | B28: Land Improvements - Apt - 5yr | C28: 5/31/22 | D28: 9223.36 | E28: 0 | F28: 9223.36 | G28: 9223.36 | H28: 0 | I28: =G28+H28 -> 9223.36 | J28: =D28-I28 -> 0 | K28: 200DB | L28: 5.0
A29: 10 | B29: Land Improvements - Apt - 27.5yr | C29: 5/31/22 | D29: 36198.07 | E29: 0 | F29: 0 | G29: 2138.97 | H29: 1316.29 | I29: =G29+H29 -> 3455.26 | J29: =D29-I29 -> 32742.81 | K29: S/L | L29: 27.5
A30: 11 | B30: Equipment - Apt - 5yr | C30: 5/31/22 | D30: 14216.69 | E30: 0 | F30: 14216.69 | G30: 14216.69 | H30: 0 | I30: =G30+H30 -> 14216.69 | J30: =D30-I30 -> 0 | K30: 200DB | L30: 5.0
A31: 12 | B31: Equipment - Apt - 27.5yr | C31: 5/31/22 | D31: 55794.92 | E31: 0 | F31: 0 | G31: 3296.98 | H31: 2028.91 | I31: =G31+H31 -> 5325.89 | J31: =D31-I31 -> 50469.03 | K31: S/L | L31: 27.5
B32: Grand Total | D32: =SUM(D20:D31) -> 515841.05 | E32: =SUM(E20:E31) -> 0 | F32: =SUM(F20:F31) -> 85964.43 | G32: =SUM(G20:G31) -> 165523.1 | H32: =SUM(H20:H31) -> 14968.96 | I32: =SUM(I20:I31) -> 180492.06 | J32: =SUM(J20:J31) -> 335348.99
B34: Section 481(a) Adjustment — Regular Tax
B35: Depreciation reported previously | D35: =I16 -> 193535.18
B36: Cost Segregation Corrected Depreciation | D36: =I32 -> 180492.06
B37: Section 481(a) Adjustment — Regular Tax | D37: =D35-D36 -> 13043.12
A39: CALCULATION OF §481(a) ADJUSTMENT — AMT
A40: As Previously Filed — AMT
A41: Asset | B41: Property Description | C41: Date In Service | D41: Cost | E41: Sec 179 Exp | F41: Bonus Amt | G41: AMT Prior Depreciation | H41: AMT Current Depreciation | I41: End Depreciation | J41: Net Book Value | K41: Method | L41: Period
A42: 1 | B42: Building - Apt | C42: 5/12/11 | D42: 92190.66 | E42: 0 | F42: 0 | G42: 31517.48 | H42: 3352.09 | I42: =G42+H42 -> 34869.57 | J42: =D42-I42 -> 57321.09 | K42: S/L | L42: 27.5
A43: 2 | B43: Building Improvements - Apt | C43: 5/31/22 | D43: 284089.88 | E43: 0 | F43: 0 | G43: 16786.89 | H43: 10329.51 | I43: =G43+H43 -> 27116.4 | J43: =D43-I43 -> 256973.48 | K43: S/L | L43: 27.5
A44: 3 | B44: Building Improvements - Apt | C44: 7/01/23 | D44: 1547.26 | E44: 0 | F44: 0 | G44: 25.76 | H44: 56.29 | I44: =G44+H44 -> 82.05 | J44: =D44-I44 -> 1465.21 | K44: S/L | L44: 27.5
A45: 4 | B45: Land Improvements - Apt | C45: 5/12/11 | D45: 22580.21 | E45: 0 | F45: 14699.63 | G45: 14699.63 | H45: 1334.49 | I45: =G45+H45 -> 16034.12 | J45: =D45-I45 -> 6546.09 | K45: 150DB | L45: 15.0
A46: 5 | B46: Land Improvements - Apt | C46: 5/31/22 | D46: 45421.43 | E46: 0 | F46: 45421.43 | G46: 45421.43 | H46: 0 | I46: =G46+H46 -> 45421.43 | J46: =D46-I46 -> 0 | K46: 150DB | L46: 15.0
A47: 6 | B47: Equipment - Apt | C47: 5/31/22 | D47: 70011.61 | E47: 0 | F47: 70011.61 | G47: 70011.61 | H47: 0 | I47: =G47+H47 -> 70011.61 | J47: =D47-I47 -> 0 | K47: 200DB | L47: 5.0
B48: Grand Total | D48: =SUM(D42:D47) -> 515841.05 | E48: =SUM(E42:E47) -> 0 | F48: =SUM(F42:F47) -> 130132.67 | G48: =SUM(G42:G47) -> 178462.8 | H48: =SUM(H42:H47) -> 15072.38 | I48: =SUM(I42:I47) -> 193535.18 | J48: =SUM(J42:J47) -> 322305.87
A50: After Cost Segregation Correction — AMT
A51: Asset | B51: Property Description | C51: Date In Service | D51: Cost | E51: Sec 179 Exp | F51: Bonus Amt | G51: AMT Prior Depreciation | H51: AMT Current Depreciation | I51: End Depreciation | J51: Net Book Value | K51: Method | L51: Period
A52: 1 | B52: Building - Apt - 5yr | C52: 5/12/11 | D52: 18720.42 | E52: 0 | F52: 0 | G52: 18720.42 | H52: 0 | I52: =G52+H52 -> 18720.42 | J52: =D52-I52 -> 0 | K52: 200DB | L52: 5.0
A53: 2 | B53: Building - Apt - 27.5yr | C53: 5/12/11 | D53: 73470.24 | E53: 0 | F53: 0 | G53: 33729.58 | H53: 2671.65 | I53: =G53+H53 -> 36401.23 | J53: =D53-I53 -> 37069.01 | K53: S/L | L53: 27.5
A54: 3 | B54: Building Improvements - Apt - 5yr | C54: 5/31/22 | D54: 57687.85 | E54: 0 | F54: 57687.85 | G54: 57687.85 | H54: 0 | I54: =G54+H54 -> 57687.85 | J54: =D54-I54 -> 0 | K54: 200DB | L54: 5.0
A55: 4 | B55: Building Improvements - Apt - 27.5yr | C55: 5/31/22 | D55: 226402.03 | E55: 0 | F55: 0 | G55: 13378.3 | H55: 8232.8 | I55: =G55+H55 -> 21611.1 | J55: =D55-I55 -> 204790.93 | K55: S/L | L55: 27.5
A56: 5 | B56: Building Improvements - Apt - 5yr | C56: 7/01/23 | D56: 314.19 | E56: 0 | F56: 251.35 | G56: 263.92 | H56: 20.11 | I56: =G56+H56 -> 284.03 | J56: =D56-I56 -> 30.16 | K56: 200DB | L56: 5.0
A57: 6 | B57: Building Improvements - Apt - 27.5yr | C57: 7/01/23 | D57: 1233.07 | E57: 0 | F57: 0 | G57: 20.55 | H57: 44.84 | I57: =G57+H57 -> 65.39 | J57: =D57-I57 -> 1167.68 | K57: S/L | L57: 27.5
A58: 7 | B58: Land Improvements - Apt - 5yr | C58: 5/12/11 | D58: 4585.18 | E58: 0 | F58: 4585.18 | G58: 4585.18 | H58: 0 | I58: =G58+H58 -> 4585.18 | J58: =D58-I58 -> 0 | K58: 200DB | L58: 5.0
A59: 8 | B59: Land Improvements - Apt - 27.5yr | C59: 5/12/11 | D59: 17995.03 | E59: 0 | F59: 0 | G59: 8261.3 | H59: 654.36 | I59: =G59+H59 -> 8915.66 | J59: =D59-I59 -> 9079.37 | K59: S/L | L59: 27.5
A60: 9 | B60: Land Improvements - Apt - 5yr | C60: 5/31/22 | D60: 9223.36 | E60: 0 | F60: 9223.36 | G60: 9223.36 | H60: 0 | I60: =G60+H60 -> 9223.36 | J60: =D60-I60 -> 0 | K60: 200DB | L60: 5.0
A61: 10 | B61: Land Improvements - Apt - 27.5yr | C61: 5/31/22 | D61: 36198.07 | E61: 0 | F61: 0 | G61: 2138.97 | H61: 1316.29 | I61: =G61+H61 -> 3455.26 | J61: =D61-I61 -> 32742.81 | K61: S/L | L61: 27.5
A62: 11 | B62: Equipment - Apt - 5yr | C62: 5/31/22 | D62: 14216.69 | E62: 0 | F62: 14216.69 | G62: 14216.69 | H62: 0 | I62: =G62+H62 -> 14216.69 | J62: =D62-I62 -> 0 | K62: 200DB | L62: 5.0
A63: 12 | B63: Equipment - Apt - 27.5yr | C63: 5/31/22 | D63: 55794.92 | E63: 0 | F63: 0 | G63: 3296.98 | H63: 2028.91 | I63: =G63+H63 -> 5325.89 | J63: =D63-I63 -> 50469.03 | K63: S/L | L63: 27.5
B64: Grand Total | D64: =SUM(D52:D63) -> 515841.05 | E64: =SUM(E52:E63) -> 0 | F64: =SUM(F52:F63) -> 85964.43 | G64: =SUM(G52:G63) -> 165523.1 | H64: =SUM(H52:H63) -> 14968.96 | I64: =SUM(I52:I63) -> 180492.06 | J64: =SUM(J52:J63) -> 335348.99
B66: Section 481(a) Adjustment — AMT
B67: Depreciation reported previously | D67: =I48 -> 193535.18
B68: Cost Segregation Corrected Depreciation | D68: =I64 -> 180492.06
B69: Section 481(a) Adjustment — AMT | D69: =D67-D68 -> 13043.12
A71: COST SEGREGATION STUDY — COST SUMMARY
B72: Total Building Cost | D72: =D109 -> 515841.05
B73: Building Components: 5 Year | D73: =F109 -> 104747.69
B74: % of Cost | D74: =F110 -> 0.20306195
B75: Building Structure: 27.5 Year | D75: =H109 -> 411093.36
B76: % of Cost | D76: =H110 -> 0.79693805
A78: COST SEGREGATION STUDY — COST DETAIL
B79: Property Category | D79: Cost | F79: 5 Year | H79: 27.5 Year
B80: Building Components
B81: Cabinets / Millwork | D81: =SUM(F81:H81) -> 14924.28 | F81: 14924.28
B82: Moldings | D82: =SUM(F82:H82) -> 10497.34 | F82: 10497.34
B83: Flooring - Vinyl Plank | D83: =SUM(F83:H83) -> 42163.82 | F83: 42163.82
B84: Window Treatments | D84: =SUM(F84:H84) -> 5291.37 | F84: 5291.37
B85: Building Signage | D85: =SUM(F85:H85) -> 297.35 | F85: 297.35
B86: Specialty Electrical - Appliances | D86: =SUM(F86:H86) -> 5540.41 | F86: 5540.41
B87: Communication / Data | D87: =SUM(F87:H87) -> 3335.96 | F87: 3335.96
B88: Specialty Plumbing - Kitchen Sinks | D88: =SUM(F88:H88) -> 11469.05 | F88: 11469.05
B89: Security / Exterior Lighting | D89: =SUM(F89:H89) -> 1722.5 | F89: 1722.5
B90: Appliances | D90: =SUM(F90:H90) -> 9505.61 | F90: 9505.61
B91: Building Structure
B92: Roofing Systems | D92: =SUM(F92:H92) -> 23533.09 | H92: 23533.09
B93: Foundations | D93: =SUM(F93:H93) -> 28643.92 | H93: 28643.92
B94: HVAC | D94: =SUM(F94:H94) -> 42496.69 | H94: 42496.69
B95: Electrical | D95: =SUM(F95:H95) -> 35043.34 | H95: 35043.34
B96: Plumbing | D96: =SUM(F96:H96) -> 36942.14 | H96: 36942.14
B97: Fire Protection & Alarm | D97: =SUM(F97:H97) -> 1288.46 | H97: 1288.46
B98: Exterior Façade / Building Skin | D98: =SUM(F98:H98) -> 22726.22 | H98: 22726.22
B99: Doors & Frames | D99: =SUM(F99:H99) -> 21445.66 | H99: 21445.66
B100: Windows | D100: =SUM(F100:H100) -> 23322.18 | H100: 23322.18
B101: Ceiling Systems | D101: =SUM(F101:H101) -> 18778.11 | H101: 18778.11
B102: Interior Framing / Partitions | D102: =SUM(F102:H102) -> 45770.64 | H102: 45770.64
B103: Painting | D103: =SUM(F103:H103) -> 19814.11 | H103: 19814.11
... B108: Cabinets / Millwork - Restrooms | D108: =SUM(F108:H108) -> 4754 | H108: 4754
B109: Total Building Cost | D109: =SUM(D80:D108) -> 515841.05 | F109: =SUM(F80:F108) -> 104747.69 | H109: =SUM(H80:H108) -> 411093.36
B110: % of Cost | F110: =F109/D109 -> 0.20306195 | H110: =H109/D109 -> 0.79693805
A112: ASSET ALLOCATION (per After Cost Segregation schedule)
B113: Asset (as reclassified) | D113: Cost | F113: 5 Year | H113: 27.5 Year
...

Sheet D
A1: Macedonia Apartments LLC
A2: Macedonia Apartments — 1722 W 17th St, Panama City, FL 32405
A3: EIN: 27-3618924 · FYE: December 31, 2024 · Year of Change: 1/1/2024
A4: D — Attachment to Form 3115 (DCN #7, Rev. Proc. 2024-23 §6.01)
A5: Source: CSSI Report #107752-05, "#107752-05_Macedonia Apartments, LLC - 3115 - combined R1.pdf"
A7: CALCULATION OF §481(a) ADJUSTMENT — REGULAR TAX
A8: As Previously Filed
A9: Asset | B9: Property Description | C9: Date In Service | D9: Cost | E9: Sec 179 Exp | F9: Bonus Amt | G9: Tax Prior Depreciation | H9: Tax Current Depreciation | I9: End Depreciation | J9: Net Book Value | K9: Method | L9: Period
A10: 1 | B10: Building - Apt | C10: 5/12/11 | D10: 92190.66 | E10: 0 | F10: 0 | G10: 31517.48 | H10: 3352.09 | I10: =G10+H10 -> 34869.57 | J10: =D10-I10 -> 57321.09 | K10: S/L | L10: 27.5
A11: 2 | B11: Building Improvements - Apt | C11: 5/31/22 | D11: 284089.88 | E11: 0 | F11: 0 | G11: 16786.89 | H11: 10329.51 | I11: =G11+H11 -> 27116.4 | J11: =D11-I11 -> 256973.48 | K11: S/L | L11: 27.5
A12: 3 | B12: Building Improvements - Apt | C12: 7/01/23 | D12: 1547.26 | E12: 0 | F12: 0 | G12: 25.76 | H12: 56.29 | I12: =G12+H12 -> 82.05 | J12: =D12-I12 -> 1465.21 | K12: S/L | L12: 27.5
A13: 4 | B13: Land Improvements - Apt | C13: 5/12/11 | D13: 22580.21 | E13: 0 | F13: 14699.63 | G13: 14699.63 | H13: 1334.49 | I13: =G13+H13 -> 16034.12 | J13: =D13-I13 -> 6546.09 | K13: 150DB | L13: 15.0
A14: 5 | B14: Land Improvements - Apt | C14: 5/31/22 | D14: 45421.43 | E14: 0 | F14: 45421.43 | G14: 45421.43 | H14: 0 | I14: =G14+H14 -> 45421.43 | J14: =D14-I14 -> 0 | K14: 150DB | L14: 15.0
A15: 6 | B15: Equipment - Apt | C15: 5/31/22 | D15: 70011.61 | E15: 0 | F15: 70011.61 | G15: 70011.61 | H15: 0 | I15: =G15+H15 -> 70011.61 | J15: =D15-I15 -> 0 | K15: 200DB | L15: 5.0
B16: Grand Total | D16: =SUM(D10:D15) -> 515841.05 | E16: =SUM(E10:E15) -> 0 | F16: =SUM(F10:F15) -> 130132.67 | G16: =SUM(G10:G15) -> 178462.8 | H16: =SUM(H10:H15) -> 15072.38 | I16: =SUM(I10:I15) -> 193535.18 | J16: =SUM(J10:J15) -> 322305.87
A18: After Cost Segregation Correction
A19: Asset | B19: Property Description | C19: Date In Service | D19: Cost | E19: Sec 179 Exp | F19: Bonus Amt | G19: Tax Prior Depreciation | H19: Tax Current Depreciation | I19: End Depreciation | J19: Net Book Value | K19: Method | L19: Period
A20: 1 | B20: Building - Apt - 5yr | C20: 5/12/11 | D20: 18720.42 | E20: 0 | F20: 0 | G20: 18720.42 | H20: 0 | I20: =G20+H20 -> 18720.42 | J20: =D20-I20 -> 0 | K20: 200DB | L20: 5.0
A21: 2 | B21: Building - Apt - 27.5yr | C21: 5/12/11 | D21: 73470.24 | E21: 0 | F21: 0 | G21: 33729.58 | H21: 2671.65 | I21: =G21+H21 -> 36401.23 | J21: =D21-I21 -> 37069.01 | K21: S/L | L21: 27.5
A22: 3 | B22: Building Improvements - Apt - 5yr | C22: 5/31/22 | D22: 57687.85 | E22: 0 | F22: 57687.85 | G22: 57687.85 | H22: 0 | I22: =G22+H22 -> 57687.85 | J22: =D22-I22 -> 0 | K22: 200DB | L22: 5.0
A23: 4 | B23: Building Improvements - Apt - 27.5yr | C23: 5/31/22 | D23: 226402.03 | E23: 0 | F23: 0 | G23: 13378.3 | H23: 8232.8 | I23: =G23+H23 -> 21611.1 | J23: =D23-I23 -> 204790.93 | K23: S/L | L23: 27.5
A24: 5 | B24: Building Improvements - Apt - 5yr | C24: 7/01/23 | D24: 314.19 | E24: 0 | F24: 251.35 | G24: 263.92 | H24: 20.11 | I24: =G24+H24 -> 284.03 | J24: =D24-I24 -> 30.16 | K24: 200DB | L24: 5.0
A25: 6 | B25: Building Improvements - Apt - 27.5yr | C25: 7/01/23 | D25: 1233.07 | E25: 0 | F25: 0 | G25: 20.55 | H25: 44.84 | I25: =G25+H25 -> 65.39 | J25: =D25-I25 -> 1167.68 | K25: S/L | L25: 27.5
A26: 7 | B26: Land Improvements - Apt - 5yr | C26: 5/12/11 | D26: 4585.18 | E26: 0 | F26: 4585.18 | G26: 4585.18 | H26: 0 | I26: =G26+H26 -> 4585.18 | J26: =D26-I26 -> 0 | K26: 200DB | L26: 5.0
A27: 8 | B27: Land Improvements - Apt - 27.5yr | C27: 5/12/11 | D27: 17995.03 | E27: 0 | F27: 0 | G27: 8261.3 | H27: 654.36 | I27: =G27+H27 -> 8915.66 | J27: =D27-I27 -> 9079.37 | K27: S/L | L27: 27.5
A28: 9 | B28: Land Improvements - Apt - 5yr | C28: 5/31/22 | D28: 9223.36 | E28: 0 | F28: 9223.36 | G28: 9223.36 | H28: 0 | I28: =G28+H28 -> 9223.36 | J28: =D28-I28 -> 0 | K28: 200DB | L28: 5.0
A29: 10 | B29: Land Improvements - Apt - 27.5yr | C29: 5/31/22 | D29: 36198.07 | E29: 0 | F29: 0 | G29: 2138.97 | H29: 1316.29 | I29: =G29+H29 -> 3455.26 | J29: =D29-I29 -> 32742.81 | K29: S/L | L29: 27.5
A30: 11 | B30: Equipment - Apt - 5yr | C30: 5/31/22 | D30: 14216.69 | E30: 0 | F30: 14216.69 | G30: 14216.69 | H30: 0 | I30: =G30+H30 -> 14216.69 | J30: =D30-I30 -> 0 | K30: 200DB | L30: 5.0
A31: 12 | B31: Equipment - Apt - 27.5yr | C31: 5/31/22 | D31: 55794.92 | E31: 0 | F31: 0 | G31: 3296.98 | H31: 2028.91 | I31: =G31+H31 -> 5325.89 | J31: =D31-I31 -> 50469.03 | K31: S/L | L31: 27.5
B32: Grand Total | D32: =SUM(D20:D31) -> 515841.05 | E32: =SUM(E20:E31) -> 0 | F32: =SUM(F20:F31) -> 85964.43 | G32: =SUM(G20:G31) -> 165523.1 | H32: =SUM(H20:H31) -> 14968.96 | I32: =SUM(I20:I31) -> 180492.06 | J32: =SUM(J20:J31) -> 335348.99
B34: Section 481(a) Adjustment — Regular Tax
B35: Depreciation reported previously | D35: =I16 -> 193535.18
B36: Cost Segregation Corrected Depreciation | D36: =I32 -> 180492.06
B37: Section 481(a) Adjustment — Regular Tax | D37: =D35-D36 -> 13043.12
A39: CALCULATION OF §481(a) ADJUSTMENT — AMT
A40: As Previously Filed — AMT
A41: Asset | B41: Property Description | C41: Date In Service | D41: Cost | E41: Sec 179 Exp | F41: Bonus Amt | G41: AMT Prior Depreciation | H41: AMT Current Depreciation | I41: End Depreciation | J41: Net Book Value | K41: Method | L41: Period
A42: 1 | B42: Building - Apt | C42: 5/12/11 | D42: 92190.66 | E42: 0 | F42: 0 | G42: 31517.48 | H42: 3352.09 | I42: =G42+H42 -> 34869.57 | J42: =D42-I42 -> 57321.09 | K42: S/L | L42: 27.5
A43: 2 | B43: Building Improvements - Apt | C43: 5/31/22 | D43: 284089.88 | E43: 0 | F43: 0 | G43: 16786.89 | H43: 10329.51 | I43: =G43+H43 -> 27116.4 | J43: =D43-I43 -> 256973.48 | K43: S/L | L43: 27.5
A44: 3 | B44: Building Improvements - Apt | C44: 7/01/23 | D44: 1547.26 | E44: 0 | F44: 0 | G44: 25.76 | H44: 56.29 | I44: =G44+H44 -> 82.05 | J44: =D44-I44 -> 1465.21 | K44: S/L | L44: 27.5
A45: 4 | B45: Land Improvements - Apt | C45: 5/12/11 | D45: 22580.21 | E45: 0 | F45: 14699.63 | G45: 14699.63 | H45: 1334.49 | I45: =G45+H45 -> 16034.12 | J45: =D45-I45 -> 6546.09 | K45: 150DB | L45: 15.0
A46: 5 | B46: Land Improvements - Apt | C46: 5/31/22 | D46: 45421.43 | E46: 0 | F46: 45421.43 | G46: 45421.43 | H46: 0 | I46: =G46+H46 -> 45421.43 | J46: =D46-I46 -> 0 | K46: 150DB | L46: 15.0
A47: 6 | B47: Equipment - Apt | C47: 5/31/22 | D47: 70011.61 | E47: 0 | F47: 70011.61 | G47: 70011.61 | H47: 0 | I47: =G47+H47 -> 70011.61 | J47: =D47-I47 -> 0 | K47: 200DB | L47: 5.0
B48: Grand Total | D48: =SUM(D42:D47) -> 515841.05 | E48: =SUM(E42:E47) -> 0 | F48: =SUM(F42:F47) -> 130132.67 | G48: =SUM(G42:G47) -> 178462.8 | H48: =SUM(H42:H47) -> 15072.38 | I48: =SUM(I42:I47) -> 193535.18 | J48: =SUM(J42:J47) -> 322305.87
A50: After Cost Segregation Correction — AMT
A51: Asset | B51: Property Description | C51: Date In Service | D51: Cost | E51: Sec 179 Exp | F51: Bonus Amt | G51: AMT Prior Depreciation | H51: AMT Current Depreciation | I51: End Depreciation | J51: Net Book Value | K51: Method | L51: Period
A52: 1 | B52: Building - Apt - 5yr | C52: 5/12/11 | D52: 18720.42 | E52: 0 | F52: 0 | G52: 18720.42 | H52: 0 | I52: =G52+H52 -> 18720.42 | J52: =D52-I52 -> 0 | K52: 200DB | L52: 5.0
A53: 2 | B53: Building - Apt - 27.5yr | C53: 5/12/11 | D53: 73470.24 | E53: 0 | F53: 0 | G53: 33729.58 | H53: 2671.65 | I53: =G53+H53 -> 36401.23 | J53: =D53-I53 -> 37069.01 | K53: S/L | L53: 27.5
A54: 3 | B54: Building Improvements - Apt - 5yr | C54: 5/31/22 | D54: 57687.85 | E54: 0 | F54: 57687.85 | G54: 57687.85 | H54: 0 | I54: =G54+H54 -> 57687.85 | J54: =D54-I54 -> 0 | K54: 200DB | L54: 5.0
A55: 4 | B55: Building Improvements - Apt - 27.5yr | C55: 5/31/22 | D55: 226402.03 | E55: 0 | F55: 0 | G55: 13378.3 | H55: 8232.8 | I55: =G55+H55 -> 21611.1 | J55: =D55-I55 -> 204790.93 | K55: S/L | L55: 27.5
A56: 5 | B56: Building Improvements - Apt - 5yr | C56: 7/01/23 | D56: 314.19 | E56: 0 | F56: 251.35 | G56: 263.92 | H56: 20.11 | I56: =G56+H56 -> 284.03 | J56: =D56-I56 -> 30.16 | K56: 200DB | L56: 5.0
A57: 6 | B57: Building Improvements - Apt - 27.5yr | C57: 7/01/23 | D57: 1233.07 | E57: 0 | F57: 0 | G57: 20.55 | H57: 44.84 | I57: =G57+H57 -> 65.39 | J57: =D57-I57 -> 1167.68 | K57: S/L | L57: 27.5
A58: 7 | B58: Land Improvements - Apt - 5yr | C58: 5/12/11 | D58: 4585.18 | E58: 0 | F58: 4585.18 | G58: 4585.18 | H58: 0 | I58: =G58+H58 -> 4585.18 | J58: =D58-I58 -> 0 | K58: 200DB | L58: 5.0
A59: 8 | B59: Land Improvements - Apt - 27.5yr | C59: 5/12/11 | D59: 17995.03 | E59: 0 | F59: 0 | G59: 8261.3 | H59: 654.36 | I59: =G59+H59 -> 8915.66 | J59: =D59-I59 -> 9079.37 | K59: S/L | L59: 27.5
A60: 9 | B60: Land Improvements - Apt - 5yr | C60: 5/31/22 | D60: 9223.36 | E60: 0 | F60: 9223.36 | G60: 9223.36 | H60: 0 | I60: =G60+H60 -> 9223.36 | J60: =D60-I60 -> 0 | K60: 200DB | L60: 5.0
A61: 10 | B61: Land Improvements - Apt - 27.5yr | C61: 5/31/22 | D61: 36198.07 | E61: 0 | F61: 0 | G61: 2138.97 | H61: 1316.29 | I61: =G61+H61 -> 3455.26 | J61: =D61-I61 -> 32742.81 | K61: S/L | L61: 27.5
A62: 11 | B62: Equipment - Apt - 5yr | C62: 5/31/22 | D62: 14216.69 | E62: 0 | F62: 14216.69 | G62: 14216.69 | H62: 0 | I62: =G62+H62 -> 14216.69 | J62: =D62-I62 -> 0 | K62: 200DB | L62: 5.0
A63: 12 | B63: Equipment - Apt - 27.5yr | C63: 5/31/22 | D63: 55794.92 | E63: 0 | F63: 0 | G63: 3296.98 | H63: 2028.91 | I63: =G63+H63 -> 5325.89 | J63: =D63-I63 -> 50469.03 | K63: S/L | L63: 27.5
B64: Grand Total | D64: =SUM(D52:D63) -> 515841.05 | E64: =SUM(E52:E63) -> 0 | F64: =SUM(F52:F63) -> 85964.43 | G64: =SUM(G52:G63) -> 165523.1 | H64: =SUM(H52:H63) -> 14968.96 | I64: =SUM(I52:I63) -> 180492.06 | J64: =SUM(J52:J63) -> 335348.99
B66: Section 481(a) Adjustment — AMT
B67: Depreciation reported previously | D67: =I48 -> 193535.18
B68: Cost Segregation Corrected Depreciation | D68: =I64 -> 180492.06
B69: Section 481(a) Adjustment — AMT | D69: =D67-D68 -> 13043.12
A71: COST SEGREGATION STUDY — COST SUMMARY
B72: Total Building Cost | D72: =D109 -> 515841.05
B73: Building Components: 5 Year | D73: =F109 -> 104747.69
B74: % of Cost | D74: =F110 -> 0.20306195
B75: Building Structure: 27.5 Year | D75: =H109 -> 411093.36
B76: % of Cost | D76: =H110 -> 0.79693805
A78: COST SEGREGATION STUDY — COST DETAIL
B79: Property Category | D79: Cost | F79: 5 Year | H79: 27.5 Year
B80: Building Components
B81: Cabinets / Millwork | D81: =SUM(F81:H81) -> 14924.28 | F81: 14924.28
B82: Moldings | D82: =SUM(F82:H82) -> 10497.34 | F82: 10497.34
B83: Flooring - Vinyl Plank | D83: =SUM(F83:H83) -> 42163.82 | F83: 42163.82
B84: Window Treatments | D84: =SUM(F84:H84) -> 5291.37 | F84: 5291.37
B85: Building Signage | D85: =SUM(F85:H85) -> 297.35 | F85: 297.35
B86: Specialty Electrical - Appliances | D86: =SUM(F86:H86) -> 5540.41 | F86: 5540.41
B87: Communication / Data | D87: =SUM(F87:H87) -> 3335.96 | F87: 3335.96
B88: Specialty Plumbing - Kitchen Sinks | D88: =SUM(F88:H88) -> 11469.05 | F88: 11469.05
B89: Security / Exterior Lighting | D89: =SUM(F89:H89) -> 1722.5 | F89: 1722.5
B90: Appliances | D90: =SUM(F90:H90) -> 9505.61 | F90: 9505.61
B91: Building Structure
B92: Roofing Systems | D92: =SUM(F92:H92) -> 23533.09 | H92: 23533.09
B93: Foundations | D93: =SUM(F93:H93) -> 28643.92 | H93: 28643.92
B94: HVAC | D94: =SUM(F94:H94) -> 42496.69 | H94: 42496.69
B95: Electrical | D95: =SUM(F95:H95) -> 35043.34 | H95: 35043.34
B96: Plumbing | D96: =SUM(F96:H96) -> 36942.14 | H96: 36942.14
B97: Fire Protection & Alarm | D97: =SUM(F97:H97) -> 1288.46 | H97: 1288.46
B98: Exterior Façade / Building Skin | D98: =SUM(F98:H98) -> 22726.22 | H98: 22726.22
B99: Doors & Frames | D99: =SUM(F99:H99) -> 21445.66 | H99: 21445.66
B100: Windows | D100: =SUM(F100:H100) -> 23322.18 | H100: 23322.18
B101: Ceiling Systems | D101: =SUM(F101:H101) -> 18778.11 | H101: 18778.11
B102: Interior Framing / Partitions | D102: =SUM(F102:H102) -> 45770.64 | H102: 45770.64
B103: Painting | D103: =SUM(F103:H103) -> 19814.11 | H103: 19814.11
... B108: Cabinets / Millwork - Restrooms | D108: =SUM(F108:H108) -> 4754 | H108: 4754
B109: Total Building Cost | D109: =SUM(D80:D108) -> 515841.05 | F109: =SUM(F80:F108) -> 104747.69 | H109: =SUM(H80:H108) -> 411093.36
B110: % of Cost | F110: =F109/D109 -> 0.20306195 | H110: =H109/D109 -> 0.79693805
A112: ASSET ALLOCATION (per After Cost Segregation schedule)
B113: Asset (as reclassified) | D113: Cost | F113: 5 Year | H113: 27.5 Year
...

Sheet E
A1: Macedonia Apartments LLC
A2: Macedonia Apartments — 1722 W 17th St, Panama City, FL 32405
A3: EIN: 27-3618924 · FYE: December 31, 2024 · Year of Change: 1/1/2024
A4: E — Attachment to Form 3115 (DCN #7, Rev. Proc. 2024-23 §6.01)
A5: Source: CSSI Report #107752-05, "#107752-05_Macedonia Apartments, LLC - 3115 - combined R1.pdf"
A7: CALCULATION OF §481(a) ADJUSTMENT — REGULAR TAX
A8: As Previously Filed
A9: Asset | B9: Property Description | C9: Date In Service | D9: Cost | E9: Sec 179 Exp | F9: Bonus Amt | G9: Tax Prior Depreciation | H9: Tax Current Depreciation | I9: End Depreciation | J9: Net Book Value | K9: Method | L9: Period
A10: 1 | B10: Building - Apt | C10: 5/12/11 | D10: 92190.66 | E10: 0 | F10: 0 | G10: 31517.48 | H10: 3352.09 | I10: =G10+H10 -> 34869.57 | J10: =D10-I10 -> 57321.09 | K10: S/L | L10: 27.5
A11: 2 | B11: Building Improvements - Apt | C11: 5/31/22 | D11: 284089.88 | E11: 0 | F11: 0 | G11: 16786.89 | H11: 10329.51 | I11: =G11+H11 -> 27116.4 | J11: =D11-I11 -> 256973.48 | K11: S/L | L11: 27.5
A12: 3 | B12: Building Improvements - Apt | C12: 7/01/23 | D12: 1547.26 | E12: 0 | F12: 0 | G12: 25.76 | H12: 56.29 | I12: =G12+H12 -> 82.05 | J12: =D12-I12 -> 1465.21 | K12: S/L | L12: 27.5
A13: 4 | B13: Land Improvements - Apt | C13: 5/12/11 | D13: 22580.21 | E13: 0 | F13: 14699.63 | G13: 14699.63 | H13: 1334.49 | I13: =G13+H13 -> 16034.12 | J13: =D13-I13 -> 6546.09 | K13: 150DB | L13: 15.0
A14: 5 | B14: Land Improvements - Apt | C14: 5/31/22 | D14: 45421.43 | E14: 0 | F14: 45421.43 | G14: 45421.43 | H14: 0 | I14: =G14+H14 -> 45421.43 | J14: =D14-I14 -> 0 | K14: 150DB | L14: 15.0
A15: 6 | B15: Equipment - Apt | C15: 5/31/22 | D15: 70011.61 | E15: 0 | F15: 70011.61 | G15: 70011.61 | H15: 0 | I15: =G15+H15 -> 70011.61 | J15: =D15-I15 -> 0 | K15: 200DB | L15: 5.0
B16: Grand Total | D16: =SUM(D10:D15) -> 515841.05 | E16: =SUM(E10:E15) -> 0 | F16: =SUM(F10:F15) -> 130132.67 | G16: =SUM(G10:G15) -> 178462.8 | H16: =SUM(H10:H15) -> 15072.38 | I16: =SUM(I10:I15) -> 193535.18 | J16: =SUM(J10:J15) -> 322305.87
A18: After Cost Segregation Correction
A19: Asset | B19: Property Description | C19: Date In Service | D19: Cost | E19: Sec 179 Exp | F19: Bonus Amt | G19: Tax Prior Depreciation | H19: Tax Current Depreciation | I19: End Depreciation | J19: Net Book Value | K19: Method | L19: Period
A20: 1 | B20: Building - Apt - 5yr | C20: 5/12/11 | D20: 18720.42 | E20: 0 | F20: 0 | G20: 18720.42 | H20: 0 | I20: =G20+H20 -> 18720.42 | J20: =D20-I20 -> 0 | K20: 200DB | L20: 5.0
A21: 2 | B21: Building - Apt - 27.5yr | C21: 5/12/11 | D21: 73470.24 | E21: 0 | F21: 0 | G21: 33729.58 | H21: 2671.65 | I21: =G21+H21 -> 36401.23 | J21: =D21-I21 -> 37069.01 | K21: S/L | L21: 27.5
A22: 3 | B22: Building Improvements - Apt - 5yr | C22: 5/31/22 | D22: 57687.85 | E22: 0 | F22: 57687.85 | G22: 57687.85 | H22: 0 | I22: =G22+H22 -> 57687.85 | J22: =D22-I22 -> 0 | K22: 200DB | L22: 5.0
A23: 4 | B23: Building Improvements - Apt - 27.5yr | C23: 5/31/22 | D23: 226402.03 | E23: 0 | F23: 0 | G23: 13378.3 | H23: 8232.8 | I23: =G23+H23 -> 21611.1 | J23: =D23-I23 -> 204790.93 | K23: S/L | L23: 27.5
A24: 5 | B24: Building Improvements - Apt - 5yr | C24: 7/01/23 | D24: 314.19 | E24: 0 | F24: 251.35 | G24: 263.92 | H24: 20.11 | I24: =G24+H24 -> 284.03 | J24: =D24-I24 -> 30.16 | K24: 200DB | L24: 5.0
A25: 6 | B25: Building Improvements - Apt - 27.5yr | C25: 7/01/23 | D25: 1233.07 | E25: 0 | F25: 0 | G25: 20.55 | H25: 44.84 | I25: =G25+H25 -> 65.39 | J25: =D25-I25 -> 1167.68 | K25: S/L | L25: 27.5
A26: 7 | B26: Land Improvements - Apt - 5yr | C26: 5/12/11 | D26: 4585.18 | E26: 0 | F26: 4585.18 | G26: 4585.18 | H26: 0 | I26: =G26+H26 -> 4585.18 | J26: =D26-I26 -> 0 | K26: 200DB | L26: 5.0
A27: 8 | B27: Land Improvements - Apt - 27.5yr | C27: 5/12/11 | D27: 17995.03 | E27: 0 | F27: 0 | G27: 8261.3 | H27: 654.36 | I27: =G27+H27 -> 8915.66 | J27: =D27-I27 -> 9079.37 | K27: S/L | L27: 27.5
A28: 9 | B28: Land Improvements - Apt - 5yr | C28: 5/31/22 | D28: 9223.36 | E28: 0 | F28: 9223.36 | G28: 9223.36 | H28: 0 | I28: =G28+H28 -> 9223.36 | J28: =D28-I28 -> 0 | K28: 200DB | L28: 5.0
A29: 10 | B29: Land Improvements - Apt - 27.5yr | C29: 5/31/22 | D29: 36198.07 | E29: 0 | F29: 0 | G29: 2138.97 | H29: 1316.29 | I29: =G29+H29 -> 3455.26 | J29: =D29-I29 -> 32742.81 | K29: S/L | L29: 27.5
A30: 11 | B30: Equipment - Apt - 5yr | C30: 5/31/22 | D30: 14216.69 | E30: 0 | F30: 14216.69 | G30: 14216.69 | H30: 0 | I30: =G30+H30 -> 14216.69 | J30: =D30-I30 -> 0 | K30: 200DB | L30: 5.0
A31: 12 | B31: Equipment - Apt - 27.5yr | C31: 5/31/22 | D31: 55794.92 | E31: 0 | F31: 0 | G31: 3296.98 | H31: 2028.91 | I31: =G31+H31 -> 5325.89 | J31: =D31-I31 -> 50469.03 | K31: S/L | L31: 27.5
B32: Grand Total | D32: =SUM(D20:D31) -> 515841.05 | E32: =SUM(E20:E31) -> 0 | F32: =SUM(F20:F31) -> 85964.43 | G32: =SUM(G20:G31) -> 165523.1 | H32: =SUM(H20:H31) -> 14968.96 | I32: =SUM(I20:I31) -> 180492.06 | J32: =SUM(J20:J31) -> 335348.99
B34: Section 481(a) Adjustment — Regular Tax
B35: Depreciation reported previously | D35: =I16 -> 193535.18
B36: Cost Segregation Corrected Depreciation | D36: =I32 -> 180492.06
B37: Section 481(a) Adjustment — Regular Tax | D37: =D35-D36 -> 13043.12
A39: CALCULATION OF §481(a) ADJUSTMENT — AMT
A40: As Previously Filed — AMT
A41: Asset | B41: Property Description | C41: Date In Service | D41: Cost | E41: Sec 179 Exp | F41: Bonus Amt | G41: AMT Prior Depreciation | H41: AMT Current Depreciation | I41: End Depreciation | J41: Net Book Value | K41: Method | L41: Period
A42: 1 | B42: Building - Apt | C42: 5/12/11 | D42: 92190.66 | E42: 0 | F42: 0 | G42: 31517.48 | H42: 3352.09 | I42: =G42+H42 -> 34869.57 | J42: =D42-I42 -> 57321.09 | K42: S/L | L42: 27.5
A43: 2 | B43: Building Improvements - Apt | C43: 5/31/22 | D43: 284089.88 | E43: 0 | F43: 0 | G43: 16786.89 | H43: 10329.51 | I43: =G43+H43 -> 27116.4 | J43: =D43-I43 -> 256973.48 | K43: S/L | L43: 27.5
A44: 3 | B44: Building Improvements - Apt | C44: 7/01/23 | D44: 1547.26 | E44: 0 | F44: 0 | G44: 25.76 | H44: 56.29 | I44: =G44+H44 -> 82.05 | J44: =D44-I44 -> 1465.21 | K44: S/L | L44: 27.5
A45: 4 | B45: Land Improvements - Apt | C45: 5/12/11 | D45: 22580.21 | E45: 0 | F45: 14699.63 | G45: 14699.63 | H45: 1334.49 | I45: =G45+H45 -> 16034.12 | J45: =D45-I45 -> 6546.09 | K45: 150DB | L45: 15.0
A46: 5 | B46: Land Improvements - Apt | C46: 5/31/22 | D46: 45421.43 | E46: 0 | F46: 45421.43 | G46: 45421.43 | H46: 0 | I46: =G46+H46 -> 45421.43 | J46: =D46-I46 -> 0 | K46: 150DB | L46: 15.0
A47: 6 | B47: Equipment - Apt | C47: 5/31/22 | D47: 70011.61 | E47: 0 | F47: 70011.61 | G47: 70011.61 | H47: 0 | I47: =G47+H47 -> 70011.61 | J47: =D47-I47 -> 0 | K47: 200DB | L47: 5.0
B48: Grand Total | D48: =SUM(D42:D47) -> 515841.05 | E48: =SUM(E42:E47) -> 0 | F48: =SUM(F42:F47) -> 130132.67 | G48: =SUM(G42:G47) -> 178462.8 | H48: =SUM(H42:H47) -> 15072.38 | I48: =SUM(I42:I47) -> 193535.18 | J48: =SUM(J42:J47) -> 322305.87
A50: After Cost Segregation Correction — AMT
A51: Asset | B51: Property Description | C51: Date In Service | D51: Cost | E51: Sec 179 Exp | F51: Bonus Amt | G51: AMT Prior Depreciation | H51: AMT Current Depreciation | I51: End Depreciation | J51: Net Book Value | K51: Method | L51: Period
A52: 1 | B52: Building - Apt - 5yr | C52: 5/12/11 | D52: 18720.42 | E52: 0 | F52: 0 | G52: 18720.42 | H52: 0 | I52: =G52+H52 -> 18720.42 | J52: =D52-I52 -> 0 | K52: 200DB | L52: 5.0
A53: 2 | B53: Building - Apt - 27.5yr | C53: 5/12/11 | D53: 73470.24 | E53: 0 | F53: 0 | G53: 33729.58 | H53: 2671.65 | I53: =G53+H53 -> 36401.23 | J53: =D53-I53 -> 37069.01 | K53: S/L | L53: 27.5
A54: 3 | B54: Building Improvements - Apt - 5yr | C54: 5/31/22 | D54: 57687.85 | E54: 0 | F54: 57687.85 | G54: 57687.85 | H54: 0 | I54: =G54+H54 -> 57687.85 | J54: =D54-I54 -> 0 | K54: 200DB | L54: 5.0
A55: 4 | B55: Building Improvements - Apt - 27.5yr | C55: 5/31/22 | D55: 226402.03 | E55: 0 | F55: 0 | G55: 13378.3 | H55: 8232.8 | I55: =G55+H55 -> 21611.1 | J55: =D55-I55 -> 204790.93 | K55: S/L | L55: 27.5
A56: 5 | B56: Building Improvements - Apt - 5yr | C56: 7/01/23 | D56: 314.19 | E56: 0 | F56: 251.35 | G56: 263.92 | H56: 20.11 | I56: =G56+H56 -> 284.03 | J56: =D56-I56 -> 30.16 | K56: 200DB | L56: 5.0
A57: 6 | B57: Building Improvements - Apt - 27.5yr | C57: 7/01/23 | D57: 1233.07 | E57: 0 | F57: 0 | G57: 20.55 | H57: 44.84 | I57: =G57+H57 -> 65.39 | J57: =D57-I57 -> 1167.68 | K57: S/L | L57: 27.5
A58: 7 | B58: Land Improvements - Apt - 5yr | C58: 5/12/11 | D58: 4585.18 | E58: 0 | F58: 4585.18 | G58: 4585.18 | H58: 0 | I58: =G58+H58 -> 4585.18 | J58: =D58-I58 -> 0 | K58: 200DB | L58: 5.0
A59: 8 | B59: Land Improvements - Apt - 27.5yr | C59: 5/12/11 | D59: 17995.03 | E59: 0 | F59: 0 | G59: 8261.3 | H59: 654.36 | I59: =G59+H59 -> 8915.66 | J59: =D59-I59 -> 9079.37 | K59: S/L | L59: 27.5
A60: 9 | B60: Land Improvements - Apt - 5yr | C60: 5/31/22 | D60: 9223.36 | E60: 0 | F60: 9223.36 | G60: 9223.36 | H60: 0 | I60: =G60+H60 -> 9223.36 | J60: =D60-I60 -> 0 | K60: 200DB | L60: 5.0
A61: 10 | B61: Land Improvements - Apt - 27.5yr | C61: 5/31/22 | D61: 36198.07 | E61: 0 | F61: 0 | G61: 2138.97 | H61: 1316.29 | I61: =G61+H61 -> 3455.26 | J61: =D61-I61 -> 32742.81 | K61: S/L | L61: 27.5
A62: 11 | B62: Equipment - Apt - 5yr | C62: 5/31/22 | D62: 14216.69 | E62: 0 | F62: 14216.69 | G62: 14216.69 | H62: 0 | I62: =G62+H62 -> 14216.69 | J62: =D62-I62 -> 0 | K62: 200DB | L62: 5.0
A63: 12 | B63: Equipment - Apt - 27.5yr | C63: 5/31/22 | D63: 55794.92 | E63: 0 | F63: 0 | G63: 3296.98 | H63: 2028.91 | I63: =G63+H63 -> 5325.89 | J63: =D63-I63 -> 50469.03 | K63: S/L | L63: 27.5
B64: Grand Total | D64: =SUM(D52:D63) -> 515841.05 | E64: =SUM(E52:E63) -> 0 | F64: =SUM(F52:F63) -> 85964.43 | G64: =SUM(G52:G63) -> 165523.1 | H64: =SUM(H52:H63) -> 14968.96 | I64: =SUM(I52:I63) -> 180492.06 | J64: =SUM(J52:J63) -> 335348.99
B66: Section 481(a) Adjustment — AMT
B67: Depreciation reported previously | D67: =I48 -> 193535.18
B68: Cost Segregation Corrected Depreciation | D68: =I64 -> 180492.06
B69: Section 481(a) Adjustment — AMT | D69: =D67-D68 -> 13043.12
A71: COST SEGREGATION STUDY — COST SUMMARY
B72: Total Building Cost | D72: =D109 -> 515841.05
B73: Building Components: 5 Year | D73: =F109 -> 104747.69
B74: % of Cost | D74: =F110 -> 0.20306195
B75: Building Structure: 27.5 Year | D75: =H109 -> 411093.36
B76: % of Cost | D76: =H110 -> 0.79693805
A78: COST SEGREGATION STUDY — COST DETAIL
B79: Property Category | D79: Cost | F79: 5 Year | H79: 27.5 Year
B80: Building Components
B81: Cabinets / Millwork | D81: =SUM(F81:H81) -> 14924.28 | F81: 14924.28
B82: Moldings | D82: =SUM(F82:H82) -> 10497.34 | F82: 10497.34
B83: Flooring - Vinyl Plank | D83: =SUM(F83:H83) -> 42163.82 | F83: 42163.82
B84: Window Treatments | D84: =SUM(F84:H84) -> 5291.37 | F84: 5291.37
B85: Building Signage | D85: =SUM(F85:H85) -> 297.35 | F85: 297.35
B86: Specialty Electrical - Appliances | D86: =SUM(F86:H86) -> 5540.41 | F86: 5540.41
B87: Communication / Data | D87: =SUM(F87:H87) -> 3335.96 | F87: 3335.96
B88: Specialty Plumbing - Kitchen Sinks | D88: =SUM(F88:H88) -> 11469.05 | F88: 11469.05
B89: Security / Exterior Lighting | D89: =SUM(F89:H89) -> 1722.5 | F89: 1722.5
B90: Appliances | D90: =SUM(F90:H90) -> 9505.61 | F90: 9505.61
B91: Building Structure
B92: Roofing Systems | D92: =SUM(F92:H92) -> 23533.09 | H92: 23533.09
B93: Foundations | D93: =SUM(F93:H93) -> 28643.92 | H93: 28643.92
B94: HVAC | D94: =SUM(F94:H94) -> 42496.69 | H94: 42496.69
B95: Electrical | D95: =SUM(F95:H95) -> 35043.34 | H95: 35043.34
B96: Plumbing | D96: =SUM(F96:H96) -> 36942.14 | H96: 36942.14
B97: Fire Protection & Alarm | D97: =SUM(F97:H97) -> 1288.46 | H97: 1288.46
B98: Exterior Façade / Building Skin | D98: =SUM(F98:H98) -> 22726.22 | H98: 22726.22
B99: Doors & Frames | D99: =SUM(F99:H99) -> 21445.66 | H99: 21445.66
B100: Windows | D100: =SUM(F100:H100) -> 23322.18 | H100: 23322.18
B101: Ceiling Systems | D101: =SUM(F101:H101) -> 18778.11 | H101: 18778.11
B102: Interior Framing / Partitions | D102: =SUM(F102:H102) -> 45770.64 | H102: 45770.64
B103: Painting | D103: =SUM(F103:H103) -> 19814.11 | H103: 19814.11
... B108: Cabinets / Millwork - Restrooms | D108: =SUM(F108:H108) -> 4754 | H108: 4754
B109: Total Building Cost | D109: =SUM(D80:D108) -> 515841.05 | F109: =SUM(F80:F108) -> 104747.69 | H109: =SUM(H80:H108) -> 411093.36
B110: % of Cost | F110: =F109/D109 -> 0.20306195 | H110: =H109/D109 -> 0.79693805
A112: ASSET ALLOCATION (per After Cost Segregation schedule)
B113: Asset (as reclassified) | D113: Cost | F113: 5 Year | H113: 27.5 Year
...

Sheet F
A1: Macedonia Apartments LLC
A2: Macedonia Apartments — 1722 W 17th St, Panama City, FL 32405
A3: EIN: 27-3618924 · FYE: December 31, 2024 · Year of Change: 1/1/2024
A4: F — Attachment to Form 3115 (DCN #7, Rev. Proc. 2024-23 §6.01)
A5: Source: CSSI Report #107752-05, "#107752-05_Macedonia Apartments, LLC - 3115 - combined R1.pdf"
A7: CALCULATION OF §481(a) ADJUSTMENT — REGULAR TAX
A8: As Previously Filed
A9: Asset | B9: Property Description | C9: Date In Service | D9: Cost | E9: Sec 179 Exp | F9: Bonus Amt | G9: Tax Prior Depreciation | H9: Tax Current Depreciation | I9: End Depreciation | J9: Net Book Value | K9: Method | L9: Period
A10: 1 | B10: Building - Apt | C10: 5/12/11 | D10: 92190.66 | E10: 0 | F10: 0 | G10: 31517.48 | H10: 3352.09 | I10: =G10+H10 -> 34869.57 | J10: =D10-I10 -> 57321.09 | K10: S/L | L10: 27.5
A11: 2 | B11: Building Improvements - Apt | C11: 5/31/22 | D11: 284089.88 | E11: 0 | F11: 0 | G11: 16786.89 | H11: 10329.51 | I11: =G11+H11 -> 27116.4 | J11: =D11-I11 -> 256973.48 | K11: S/L | L11: 27.5
A12: 3 | B12: Building Improvements - Apt | C12: 7/01/23 | D12: 1547.26 | E12: 0 | F12: 0 | G12: 25.76 | H12: 56.29 | I12: =G12+H12 -> 82.05 | J12: =D12-I12 -> 1465.21 | K12: S/L | L12: 27.5
A13: 4 | B13: Land Improvements - Apt | C13: 5/12/11 | D13: 22580.21 | E13: 0 | F13: 14699.63 | G13: 14699.63 | H13: 1334.49 | I13: =G13+H13 -> 16034.12 | J13: =D13-I13 -> 6546.09 | K13: 150DB | L13: 15.0
A14: 5 | B14: Land Improvements - Apt | C14: 5/31/22 | D14: 45421.43 | E14: 0 | F14: 45421.43 | G14: 45421.43 | H14: 0 | I14: =G14+H14 -> 45421.43 | J14: =D14-I14 -> 0 | K14: 150DB | L14: 15.0
A15: 6 | B15: Equipment - Apt | C15: 5/31/22 | D15: 70011.61 | E15: 0 | F15: 70011.61 | G15: 70011.61 | H15: 0 | I15: =G15+H15 -> 70011.61 | J15: =D15-I15 -> 0 | K15: 200DB | L15: 5.0
B16: Grand Total | D16: =SUM(D10:D15) -> 515841.05 | E16: =SUM(E10:E15) -> 0 | F16: =SUM(F10:F15) -> 130132.67 | G16: =SUM(G10:G15) -> 178462.8 | H16: =SUM(H10:H15) -> 15072.38 | I16: =SUM(I10:I15) -> 193535.18 | J16: =SUM(J10:J15) -> 322305.87
A18: After Cost Segregation Correction
A19: Asset | B19: Property Description | C19: Date In Service | D19: Cost | E19: Sec 179 Exp | F19: Bonus Amt | G19: Tax Prior Depreciation | H19: Tax Current Depreciation | I19: End Depreciation | J19: Net Book Value | K19: Method | L19: Period
A20: 1 | B20: Building - Apt - 5yr | C20: 5/12/11 | D20: 18720.42 | E20: 0 | F20: 0 | G20: 18720.42 | H20: 0 | I20: =G20+H20 -> 18720.42 | J20: =D20-I20 -> 0 | K20: 200DB | L20: 5.0
A21: 2 | B21: Building - Apt - 27.5yr | C21: 5/12/11 | D21: 73470.24 | E21: 0 | F21: 0 | G21: 33729.58 | H21: 2671.65 | I21: =G21+H21 -> 36401.23 | J21: =D21-I21 -> 37069.01 | K21: S/L | L21: 27.5
A22: 3 | B22: Building Improvements - Apt - 5yr | C22: 5/31/22 | D22: 57687.85 | E22: 0 | F22: 57687.85 | G22: 57687.85 | H22: 0 | I22: =G22+H22 -> 57687.85 | J22: =D22-I22 -> 0 | K22: 200DB | L22: 5.0
A23: 4 | B23: Building Improvements - Apt - 27.5yr | C23: 5/31/22 | D23: 226402.03 | E23: 0 | F23: 0 | G23: 13378.3 | H23: 8232.8 | I23: =G23+H23 -> 21611.1 | J23: =D23-I23 -> 204790.93 | K23: S/L | L23: 27.5
A24: 5 | B24: Building Improvements - Apt - 5yr | C24: 7/01/23 | D24: 314.19 | E24: 0 | F24: 251.35 | G24: 263.92 | H24: 20.11 | I24: =G24+H24 -> 284.03 | J24: =D24-I24 -> 30.16 | K24: 200DB | L24: 5.0
A25: 6 | B25: Building Improvements - Apt - 27.5yr | C25: 7/01/23 | D25: 1233.07 | E25: 0 | F25: 0 | G25: 20.55 | H25: 44.84 | I25: =G25+H25 -> 65.39 | J25: =D25-I25 -> 1167.68 | K25: S/L | L25: 27.5
A26: 7 | B26: Land Improvements - Apt - 5yr | C26: 5/12/11 | D26: 4585.18 | E26: 0 | F26: 4585.18 | G26: 4585.18 | H26: 0 | I26: =G26+H26 -> 4585.18 | J26: =D26-I26 -> 0 | K26: 200DB | L26: 5.0
A27: 8 | B27: Land Improvements - Apt - 27.5yr | C27: 5/12/11 | D27: 17995.03 | E27: 0 | F27: 0 | G27: 8261.3 | H27: 654.36 | I27: =G27+H27 -> 8915.66 | J27: =D27-I27 -> 9079.37 | K27: S/L | L27: 27.5
A28: 9 | B28: Land Improvements - Apt - 5yr | C28: 5/31/22 | D28: 9223.36 | E28: 0 | F28: 9223.36 | G28: 9223.36 | H28: 0 | I28: =G28+H28 -> 9223.36 | J28: =D28-I28 -> 0 | K28: 200DB | L28: 5.0
A29: 10 | B29: Land Improvements - Apt - 27.5yr | C29: 5/31/22 | D29: 36198.07 | E29: 0 | F29: 0 | G29: 2138.97 | H29: 1316.29 | I29: =G29+H29 -> 3455.26 | J29: =D29-I29 -> 32742.81 | K29: S/L | L29: 27.5
A30: 11 | B30: Equipment - Apt - 5yr | C30: 5/31/22 | D30: 14216.69 | E30: 0 | F30: 14216.69 | G30: 14216.69 | H30: 0 | I30: =G30+H30 -> 14216.69 | J30: =D30-I30 -> 0 | K30: 200DB | L30: 5.0
A31: 12 | B31: Equipment - Apt - 27.5yr | C31: 5/31/22 | D31: 55794.92 | E31: 0 | F31: 0 | G31: 3296.98 | H31: 2028.91 | I31: =G31+H31 -> 5325.89 | J31: =D31-I31 -> 50469.03 | K31: S/L | L31: 27.5
B32: Grand Total | D32: =SUM(D20:D31) -> 515841.05 | E32: =SUM(E20:E31) -> 0 | F32: =SUM(F20:F31) -> 85964.43 | G32: =SUM(G20:G31) -> 165523.1 | H32: =SUM(H20:H31) -> 14968.96 | I32: =SUM(I20:I31) -> 180492.06 | J32: =SUM(J20:J31) -> 335348.99
B34: Section 481(a) Adjustment — Regular Tax
B35: Depreciation reported previously | D35: =I16 -> 193535.18
B36: Cost Segregation Corrected Depreciation | D36: =I32 -> 180492.06
B37: Section 481(a) Adjustment — Regular Tax | D37: =D35-D36 -> 13043.12
A39: CALCULATION OF §481(a) ADJUSTMENT — AMT
A40: As Previously Filed — AMT
A41: Asset | B41: Property Description | C41: Date In Service | D41: Cost | E41: Sec 179 Exp | F41: Bonus Amt | G41: AMT Prior Depreciation | H41: AMT Current Depreciation | I41: End Depreciation | J41: Net Book Value | K41: Method | L41: Period
A42: 1 | B42: Building - Apt | C42: 5/12/11 | D42: 92190.66 | E42: 0 | F42: 0 | G42: 31517.48 | H42: 3352.09 | I42: =G42+H42 -> 34869.57 | J42: =D42-I42 -> 57321.09 | K42: S/L | L42: 27.5
A43: 2 | B43: Building Improvements - Apt | C43: 5/31/22 | D43: 284089.88 | E43: 0 | F43: 0 | G43: 16786.89 | H43: 10329.51 | I43: =G43+H43 -> 27116.4 | J43: =D43-I43 -> 256973.48 | K43: S/L | L43: 27.5
A44: 3 | B44: Building Improvements - Apt | C44: 7/01/23 | D44: 1547.26 | E44: 0 | F44: 0 | G44: 25.76 | H44: 56.29 | I44: =G44+H44 -> 82.05 | J44: =D44-I44 -> 1465.21 | K44: S/L | L44: 27.5
A45: 4 | B45: Land Improvements - Apt | C45: 5/12/11 | D45: 22580.21 | E45: 0 | F45: 14699.63 | G45: 14699.63 | H45: 1334.49 | I45: =G45+H45 -> 16034.12 | J45: =D45-I45 -> 6546.09 | K45: 150DB | L45: 15.0
A46: 5 | B46: Land Improvements - Apt | C46: 5/31/22 | D46: 45421.43 | E46: 0 | F46: 45421.43 | G46: 45421.43 | H46: 0 | I46: =G46+H46 -> 45421.43 | J46: =D46-I46 -> 0 | K46: 150DB | L46: 15.0
A47: 6 | B47: Equipment - Apt | C47: 5/31/22 | D47: 70011.61 | E47: 0 | F47: 70011.61 | G47: 70011.61 | H47: 0 | I47: =G47+H47 -> 70011.61 | J47: =D47-I47 -> 0 | K47: 200DB | L47: 5.0
B48: Grand Total | D48: =SUM(D42:D47) -> 515841.05 | E48: =SUM(E42:E47) -> 0 | F48: =SUM(F42:F47) -> 130132.67 | G48: =SUM(G42:G47) -> 178462.8 | H48: =SUM(H42:H47) -> 15072.38 | I48: =SUM(I42:I47) -> 193535.18 | J48: =SUM(J42:J47) -> 322305.87
A50: After Cost Segregation Correction — AMT
A51: Asset | B51: Property Description | C51: Date In Service | D51: Cost | E51: Sec 179 Exp | F51: Bonus Amt | G51: AMT Prior Depreciation | H51: AMT Current Depreciation | I51: End Depreciation | J51: Net Book Value | K51: Method | L51: Period
A52: 1 | B52: Building - Apt - 5yr | C52: 5/12/11 | D52: 18720.42 | E52: 0 | F52: 0 | G52: 18720.42 | H52: 0 | I52: =G52+H52 -> 18720.42 | J52: =D52-I52 -> 0 | K52: 200DB | L52: 5.0
A53: 2 | B53: Building - Apt - 27.5yr | C53: 5/12/11 | D53: 73470.24 | E53: 0 | F53: 0 | G53: 33729.58 | H53: 2671.65 | I53: =G53+H53 -> 36401.23 | J53: =D53-I53 -> 37069.01 | K53: S/L | L53: 27.5
A54: 3 | B54: Building Improvements - Apt - 5yr | C54: 5/31/22 | D54: 57687.85 | E54: 0 | F54: 57687.85 | G54: 57687.85 | H54: 0 | I54: =G54+H54 -> 57687.85 | J54: =D54-I54 -> 0 | K54: 200DB | L54: 5.0
A55: 4 | B55: Building Improvements - Apt - 27.5yr | C55: 5/31/22 | D55: 226402.03 | E55: 0 | F55: 0 | G55: 13378.3 | H55: 8232.8 | I55: =G55+H55 -> 21611.1 | J55: =D55-I55 -> 204790.93 | K55: S/L | L55: 27.5
A56: 5 | B56: Building Improvements - Apt - 5yr | C56: 7/01/23 | D56: 314.19 | E56: 0 | F56: 251.35 | G56: 263.92 | H56: 20.11 | I56: =G56+H56 -> 284.03 | J56: =D56-I56 -> 30.16 | K56: 200DB | L56: 5.0
A57: 6 | B57: Building Improvements - Apt - 27.5yr | C57: 7/01/23 | D57: 1233.07 | E57: 0 | F57: 0 | G57: 20.55 | H57: 44.84 | I57: =G57+H57 -> 65.39 | J57: =D57-I57 -> 1167.68 | K57: S/L | L57: 27.5
A58: 7 | B58: Land Improvements - Apt - 5yr | C58: 5/12/11 | D58: 4585.18 | E58: 0 | F58: 4585.18 | G58: 4585.18 | H58: 0 | I58: =G58+H58 -> 4585.18 | J58: =D58-I58 -> 0 | K58: 200DB | L58: 5.0
A59: 8 | B59: Land Improvements - Apt - 27.5yr | C59: 5/12/11 | D59: 17995.03 | E59: 0 | F59: 0 | G59: 8261.3 | H59: 654.36 | I59: =G59+H59 -> 8915.66 | J59: =D59-I59 -> 9079.37 | K59: S/L | L59: 27.5
A60: 9 | B60: Land Improvements - Apt - 5yr | C60: 5/31/22 | D60: 9223.36 | E60: 0 | F60: 9223.36 | G60: 9223.36 | H60: 0 | I60: =G60+H60 -> 9223.36 | J60: =D60-I60 -> 0 | K60: 200DB | L60: 5.0
A61: 10 | B61: Land Improvements - Apt - 27.5yr | C61: 5/31/22 | D61: 36198.07 | E61: 0 | F61: 0 | G61: 2138.97 | H61: 1316.29 | I61: =G61+H61 -> 3455.26 | J61: =D61-I61 -> 32742.81 | K61: S/L | L61: 27.5
A62: 11 | B62: Equipment - Apt - 5yr | C62: 5/31/22 | D62: 14216.69 | E62: 0 | F62: 14216.69 | G62: 14216.69 | H62: 0 | I62: =G62+H62 -> 14216.69 | J62: =D62-I62 -> 0 | K62: 200DB | L62: 5.0
A63: 12 | B63: Equipment - Apt - 27.5yr | C63: 5/31/22 | D63: 55794.92 | E63: 0 | F63: 0 | G63: 3296.98 | H63: 2028.91 | I63: =G63+H63 -> 5325.89 | J63: =D63-I63 -> 50469.03 | K63: S/L | L63: 27.5
B64: Grand Total | D64: =SUM(D52:D63) -> 515841.05 | E64: =SUM(E52:E63) -> 0 | F64: =SUM(F52:F63) -> 85964.43 | G64: =SUM(G52:G63) -> 165523.1 | H64: =SUM(H52:H63) -> 14968.96 | I64: =SUM(I52:I63) -> 180492.06 | J64: =SUM(J52:J63) -> 335348.99
B66: Section 481(a) Adjustment — AMT
B67: Depreciation reported previously | D67: =I48 -> 193535.18
B68: Cost Segregation Corrected Depreciation | D68: =I64 -> 180492.06
B69: Section 481(a) Adjustment — AMT | D69: =D67-D68 -> 13043.12
A71: COST SEGREGATION STUDY — COST SUMMARY
B72: Total Building Cost | D72: =D109 -> 515841.05
B73: Building Components: 5 Year | D73: =F109 -> 104747.69
B74: % of Cost | D74: =F110 -> 0.20306195
B75: Building Structure: 27.5 Year | D75: =H109 -> 411093.36
B76: % of Cost | D76: =H110 -> 0.79693805
A78: COST SEGREGATION STUDY — COST DETAIL
B79: Property Category | D79: Cost | F79: 5 Year | H79: 27.5 Year
B80: Building Components
B81: Cabinets / Millwork | D81: =SUM(F81:H81) -> 14924.28 | F81: 14924.28
B82: Moldings | D82: =SUM(F82:H82) -> 10497.34 | F82: 10497.34
B83: Flooring - Vinyl Plank | D83: =SUM(F83:H83) -> 42163.82 | F83: 42163.82
B84: Window Treatments | D84: =SUM(F84:H84) -> 5291.37 | F84: 5291.37
B85: Building Signage | D85: =SUM(F85:H85) -> 297.35 | F85: 297.35
B86: Specialty Electrical - Appliances | D86: =SUM(F86:H86) -> 5540.41 | F86: 5540.41
B87: Communication / Data | D87: =SUM(F87:H87) -> 3335.96 | F87: 3335.96
B88: Specialty Plumbing - Kitchen Sinks | D88: =SUM(F88:H88) -> 11469.05 | F88: 11469.05
B89: Security / Exterior Lighting | D89: =SUM(F89:H89) -> 1722.5 | F89: 1722.5
B90: Appliances | D90: =SUM(F90:H90) -> 9505.61 | F90: 9505.61
B91: Building Structure
B92: Roofing Systems | D92: =SUM(F92:H92) -> 23533.09 | H92: 23533.09
B93: Foundations | D93: =SUM(F93:H93) -> 28643.92 | H93: 28643.92
B94: HVAC | D94: =SUM(F94:H94) -> 42496.69 | H94: 42496.69
B95: Electrical | D95: =SUM(F95:H95) -> 35043.34 | H95: 35043.34
B96: Plumbing | D96: =SUM(F96:H96) -> 36942.14 | H96: 36942.14
B97: Fire Protection & Alarm | D97: =SUM(F97:H97) -> 1288.46 | H97: 1288.46
B98: Exterior Façade / Building Skin | D98: =SUM(F98:H98) -> 22726.22 | H98: 22726.22
B99: Doors & Frames | D99: =SUM(F99:H99) -> 21445.66 | H99: 21445.66
B100: Windows | D100: =SUM(F100:H100) -> 23322.18 | H100: 23322.18
B101: Ceiling Systems | D101: =SUM(F101:H101) -> 18778.11 | H101: 18778.11
B102: Interior Framing / Partitions | D102: =SUM(F102:H102) -> 45770.64 | H102: 45770.64
B103: Painting | D103: =SUM(F103:H103) -> 19814.11 | H103: 19814.11
... B108: Cabinets / Millwork - Restrooms | D108: =SUM(F108:H108) -> 4754 | H108: 4754
B109: Total Building Cost | D109: =SUM(D80:D108) -> 515841.05 | F109: =SUM(F80:F108) -> 104747.69 | H109: =SUM(H80:H108) -> 411093.36
B110: % of Cost | F110: =F109/D109 -> 0.20306195 | H110: =H109/D109 -> 0.79693805
A112: ASSET ALLOCATION (per After Cost Segregation schedule)
B113: Asset (as reclassified) | D113: Cost | F113: 5 Year | H113: 27.5 Year
...

Sheet G
A1: Macedonia Apartments LLC
A2: Macedonia Apartments — 1722 W 17th St, Panama City, FL 32405
A3: EIN: 27-3618924 · FYE: December 31, 2024 · Year of Change: 1/1/2024
A4: G — Attachment to Form 3115 (DCN #7, Rev. Proc. 2024-23 §6.01)
A5: Source: CSSI Report #107752-05, "#107752-05_Macedonia Apartments, LLC - 3115 - combined R1.pdf"
A7: CALCULATION OF §481(a) ADJUSTMENT — REGULAR TAX
A8: As Previously Filed
A9: Asset | B9: Property Description | C9: Date In Service | D9: Cost | E9: Sec 179 Exp | F9: Bonus Amt | G9: Tax Prior Depreciation | H9: Tax Current Depreciation | I9: End Depreciation | J9: Net Book Value | K9: Method | L9: Period
A10: 1 | B10: Building - Apt | C10: 5/12/11 | D10: 92190.66 | E10: 0 | F10: 0 | G10: 31517.48 | H10: 3352.09 | I10: =G10+H10 -> 34869.57 | J10: =D10-I10 -> 57321.09 | K10: S/L | L10: 27.5
A11: 2 | B11: Building Improvements - Apt | C11: 5/31/22 | D11: 284089.88 | E11: 0 | F11: 0 | G11: 16786.89 | H11: 10329.51 | I11: =G11+H11 -> 27116.4 | J11: =D11-I11 -> 256973.48 | K11: S/L | L11: 27.5
A12: 3 | B12: Building Improvements - Apt | C12: 7/01/23 | D12: 1547.26 | E12: 0 | F12: 0 | G12: 25.76 | H12: 56.29 | I12: =G12+H12 -> 82.05 | J12: =D12-I12 -> 1465.21 | K12: S/L | L12: 27.5
A13: 4 | B13: Land Improvements - Apt | C13: 5/12/11 | D13: 22580.21 | E13: 0 | F13: 14699.63 | G13: 14699.63 | H13: 1334.49 | I13: =G13+H13 -> 16034.12 | J13: =D13-I13 -> 6546.09 | K13: 150DB | L13: 15.0
A14: 5 | B14: Land Improvements - Apt | C14: 5/31/22 | D14: 45421.43 | E14: 0 | F14: 45421.43 | G14: 45421.43 | H14: 0 | I14: =G14+H14 -> 45421.43 | J14: =D14-I14 -> 0 | K14: 150DB | L14: 15.0
A15: 6 | B15: Equipment - Apt | C15: 5/31/22 | D15: 70011.61 | E15: 0 | F15: 70011.61 | G15: 70011.61 | H15: 0 | I15: =G15+H15 -> 70011.61 | J15: =D15-I15 -> 0 | K15: 200DB | L15: 5.0
B16: Grand Total | D16: =SUM(D10:D15) -> 515841.05 | E16: =SUM(E10:E15) -> 0 | F16: =SUM(F10:F15) -> 130132.67 | G16: =SUM(G10:G15) -> 178462.8 | H16: =SUM(H10:H15) -> 15072.38 | I16: =SUM(I10:I15) -> 193535.18 | J16: =SUM(J10:J15) -> 322305.87
A18: After Cost Segregation Correction
A19: Asset | B19: Property Description | C19: Date In Service | D19: Cost | E19: Sec 179 Exp | F19: Bonus Amt | G19: Tax Prior Depreciation | H19: Tax Current Depreciation | I19: End Depreciation | J19: Net Book Value | K19: Method | L19: Period
A20: 1 | B20: Building - Apt - 5yr | C20: 5/12/11 | D20: 18720.42 | E20: 0 | F20: 0 | G20: 18720.42 | H20: 0 | I20: =G20+H20 -> 18720.42 | J20: =D20-I20 -> 0 | K20: 200DB | L20: 5.0
A21: 2 | B21: Building - Apt - 27.5yr | C21: 5/12/11 | D21: 73470.24 | E21: 0 | F21: 0 | G21: 33729.58 | H21: 2671.65 | I21: =G21+H21 -> 36401.23 | J21: =D21-I21 -> 37069.01 | K21: S/L | L21: 27.5
A22: 3 | B22: Building Improvements - Apt - 5yr | C22: 5/31/22 | D22: 57687.85 | E22: 0 | F22: 57687.85 | G22: 57687.85 | H22: 0 | I22: =G22+H22 -> 57687.85 | J22: =D22-I22 -> 0 | K22: 200DB | L22: 5.0
A23: 4 | B23: Building Improvements - Apt - 27.5yr | C23: 5/31/22 | D23: 226402.03 | E23: 0 | F23: 0 | G23: 13378.3 | H23: 8232.8 | I23: =G23+H23 -> 21611.1 | J23: =D23-I23 -> 204790.93 | K23: S/L | L23: 27.5
A24: 5 | B24: Building Improvements - Apt - 5yr | C24: 7/01/23 | D24: 314.19 | E24: 0 | F24: 251.35 | G24: 263.92 | H24: 20.11 | I24: =G24+H24 -> 284.03 | J24: =D24-I24 -> 30.16 | K24: 200DB | L24: 5.0
A25: 6 | B25: Building Improvements - Apt - 27.5yr | C25: 7/01/23 | D25: 1233.07 | E25: 0 | F25: 0 | G25: 20.55 | H25: 44.84 | I25: =G25+H25 -> 65.39 | J25: =D25-I25 -> 1167.68 | K25: S/L | L25: 27.5
A26: 7 | B26: Land Improvements - Apt - 5yr | C26: 5/12/11 | D26: 4585.18 | E26: 0 | F26: 4585.18 | G26: 4585.18 | H26: 0 | I26: =G26+H26 -> 4585.18 | J26: =D26-I26 -> 0 | K26: 200DB | L26: 5.0
A27: 8 | B27: Land Improvements - Apt - 27.5yr | C27: 5/12/11 | D27: 17995.03 | E27: 0 | F27: 0 | G27: 8261.3 | H27: 654.36 | I27: =G27+H27 -> 8915.66 | J27: =D27-I27 -> 9079.37 | K27: S/L | L27: 27.5
A28: 9 | B28: Land Improvements - Apt - 5yr | C28: 5/31/22 | D28: 9223.36 | E28: 0 | F28: 9223.36 | G28: 9223.36 | H28: 0 | I28: =G28+H28 -> 9223.36 | J28: =D28-I28 -> 0 | K28: 200DB | L28: 5.0
A29: 10 | B29: Land Improvements - Apt - 27.5yr | C29: 5/31/22 | D29: 36198.07 | E29: 0 | F29: 0 | G29: 2138.97 | H29: 1316.29 | I29: =G29+H29 -> 3455.26 | J29: =D29-I29 -> 32742.81 | K29: S/L | L29: 27.5
A30: 11 | B30: Equipment - Apt - 5yr | C30: 5/31/22 | D30: 14216.69 | E30: 0 | F30: 14216.69 | G30: 14216.69 | H30: 0 | I30: =G30+H30 -> 14216.69 | J30: =D30-I30 -> 0 | K30: 200DB | L30: 5.0
A31: 12 | B31: Equipment - Apt - 27.5yr | C31: 5/31/22 | D31: 55794.92 | E31: 0 | F31: 0 | G31: 3296.98 | H31: 2028.91 | I31: =G31+H31 -> 5325.89 | J31: =D31-I31 -> 50469.03 | K31: S/L | L31: 27.5
B32: Grand Total | D32: =SUM(D20:D31) -> 515841.05 | E32: =SUM(E20:E31) -> 0 | F32: =SUM(F20:F31) -> 85964.43 | G32: =SUM(G20:G31) -> 165523.1 | H32: =SUM(H20:H31) -> 14968.96 | I32: =SUM(I20:I31) -> 180492.06 | J32: =SUM(J20:J31) -> 335348.99
B34: Section 481(a) Adjustment — Regular Tax
B35: Depreciation reported previously | D35: =I16 -> 193535.18
B36: Cost Segregation Corrected Depreciation | D36: =I32 -> 180492.06
B37: Section 481(a) Adjustment — Regular Tax | D37: =D35-D36 -> 13043.12
A39: CALCULATION OF §481(a) ADJUSTMENT — AMT
A40: As Previously Filed — AMT
A41: Asset | B41: Property Description | C41: Date In Service | D41: Cost | E41: Sec 179 Exp | F41: Bonus Amt | G41: AMT Prior Depreciation | H41: AMT Current Depreciation | I41: End Depreciation | J41: Net Book Value | K41: Method | L41: Period
A42: 1 | B42: Building - Apt | C42: 5/12/11 | D42: 92190.66 | E42: 0 | F42: 0 | G42: 31517.48 | H42: 3352.09 | I42: =G42+H42 -> 34869.57 | J42: =D42-I42 -> 57321.09 | K42: S/L | L42: 27.5
A43: 2 | B43: Building Improvements - Apt | C43: 5/31/22 | D43: 284089.88 | E43: 0 | F43: 0 | G43: 16786.89 | H43: 10329.51 | I43: =G43+H43 -> 27116.4 | J43: =D43-I43 -> 256973.48 | K43: S/L | L43: 27.5
A44: 3 | B44: Building Improvements - Apt | C44: 7/01/23 | D44: 1547.26 | E44: 0 | F44: 0 | G44: 25.76 | H44: 56.29 | I44: =G44+H44 -> 82.05 | J44: =D44-I44 -> 1465.21 | K44: S/L | L44: 27.5
A45: 4 | B45: Land Improvements - Apt | C45: 5/12/11 | D45: 22580.21 | E45: 0 | F45: 14699.63 | G45: 14699.63 | H45: 1334.49 | I45: =G45+H45 -> 16034.12 | J45: =D45-I45 -> 6546.09 | K45: 150DB | L45: 15.0
A46: 5 | B46: Land Improvements - Apt | C46: 5/31/22 | D46: 45421.43 | E46: 0 | F46: 45421.43 | G46: 45421.43 | H46: 0 | I46: =G46+H46 -> 45421.43 | J46: =D46-I46 -> 0 | K46: 150DB | L46: 15.0
A47: 6 | B47: Equipment - Apt | C47: 5/31/22 | D47: 70011.61 | E47: 0 | F47: 70011.61 | G47: 70011.61 | H47: 0 | I47: =G47+H47 -> 70011.61 | J47: =D47-I47 -> 0 | K47: 200DB | L47: 5.0
B48: Grand Total | D48: =SUM(D42:D47) -> 515841.05 | E48: =SUM(E42:E47) -> 0 | F48: =SUM(F42:F47) -> 130132.67 | G48: =SUM(G42:G47) -> 178462.8 | H48: =SUM(H42:H47) -> 15072.38 | I48: =SUM(I42:I47) -> 193535.18 | J48: =SUM(J42:J47) -> 322305.87
A50: After Cost Segregation Correction — AMT
A51: Asset | B51: Property Description | C51: Date In Service | D51: Cost | E51: Sec 179 Exp | F51: Bonus Amt | G51: AMT Prior Depreciation | H51: AMT Current Depreciation | I51: End Depreciation | J51: Net Book Value | K51: Method | L51: Period
A52: 1 | B52: Building - Apt - 5yr | C52: 5/12/11 | D52: 18720.42 | E52: 0 | F52: 0 | G52: 18720.42 | H52: 0 | I52: =G52+H52 -> 18720.42 | J52: =D52-I52 -> 0 | K52: 200DB | L52: 5.0
A53: 2 | B53: Building - Apt - 27.5yr | C53: 5/12/11 | D53: 73470.24 | E53: 0 | F53: 0 | G53: 33729.58 | H53: 2671.65 | I53: =G53+H53 -> 36401.23 | J53: =D53-I53 -> 37069.01 | K53: S/L | L53: 27.5
A54: 3 | B54: Building Improvements - Apt - 5yr | C54: 5/31/22 | D54: 57687.85 | E54: 0 | F54: 57687.85 | G54: 57687.85 | H54: 0 | I54: =G54+H54 -> 57687.85 | J54: =D54-I54 -> 0 | K54: 200DB | L54: 5.0
A55: 4 | B55: Building Improvements - Apt - 27.5yr | C55: 5/31/22 | D55: 226402.03 | E55: 0 | F55: 0 | G55: 13378.3 | H55: 8232.8 | I55: =G55+H55 -> 21611.1 | J55: =D55-I55 -> 204790.93 | K55: S/L | L55: 27.5
A56: 5 | B56: Building Improvements - Apt - 5yr | C56: 7/01/23 | D56: 314.19 | E56: 0 | F56: 251.35 | G56: 263.92 | H56: 20.11 | I56: =G56+H56 -> 284.03 | J56: =D56-I56 -> 30.16 | K56: 200DB | L56: 5.0
A57: 6 | B57: Building Improvements - Apt - 27.5yr | C57: 7/01/23 | D57: 1233.07 | E57: 0 | F57: 0 | G57: 20.55 | H57: 44.84 | I57: =G57+H57 -> 65.39 | J57: =D57-I57 -> 1167.68 | K57: S/L | L57: 27.5
A58: 7 | B58: Land Improvements - Apt - 5yr | C58: 5/12/11 | D58: 4585.18 | E58: 0 | F58: 4585.18 | G58: 4585.18 | H58: 0 | I58: =G58+H58 -> 4585.18 | J58: =D58-I58 -> 0 | K58: 200DB | L58: 5.0
A59: 8 | B59: Land Improvements - Apt - 27.5yr | C59: 5/12/11 | D59: 17995.03 | E59: 0 | F59: 0 | G59: 8261.3 | H59: 654.36 | I59: =G59+H59 -> 8915.66 | J59: =D59-I59 -> 9079.37 | K59: S/L | L59: 27.5
A60: 9 | B60: Land Improvements - Apt - 5yr | C60: 5/31/22 | D60: 9223.36 | E60: 0 | F60: 9223.36 | G60: 9223.36 | H60: 0 | I60: =G60+H60 -> 9223.36 | J60: =D60-I60 -> 0 | K60: 200DB | L60: 5.0
A61: 10 | B61: Land Improvements - Apt - 27.5yr | C61: 5/31/22 | D61: 36198.07 | E61: 0 | F61: 0 | G61: 2138.97 | H61: 1316.29 | I61: =G61+H61 -> 3455.26 | J61: =D61-I61 -> 32742.81 | K61: S/L | L61: 27.5
A62: 11 | B62: Equipment - Apt - 5yr | C62: 5/31/22 | D62: 14216.69 | E62: 0 | F62: 14216.69 | G62: 14216.69 | H62: 0 | I62: =G62+H62 -> 14216.69 | J62: =D62-I62 -> 0 | K62: 200DB | L62: 5.0
A63: 12 | B63: Equipment - Apt - 27.5yr | C63: 5/31/22 | D63: 55794.92 | E63: 0 | F63: 0 | G63: 3296.98 | H63: 2028.91 | I63: =G63+H63 -> 5325.89 | J63: =D63-I63 -> 50469.03 | K63: S/L | L63: 27.5
B64: Grand Total | D64: =SUM(D52:D63) -> 515841.05 | E64: =SUM(E52:E63) -> 0 | F64: =SUM(F52:F63) -> 85964.43 | G64: =SUM(G52:G63) -> 165523.1 | H64: =SUM(H52:H63) -> 14968.96 | I64: =SUM(I52:I63) -> 180492.06 | J64: =SUM(J52:J63) -> 335348.99
B66: Section 481(a) Adjustment — AMT
B67: Depreciation reported previously | D67: =I48 -> 193535.18
B68: Cost Segregation Corrected Depreciation | D68: =I64 -> 180492.06
B69: Section 481(a) Adjustment — AMT | D69: =D67-D68 -> 13043.12
A71: COST SEGREGATION STUDY — COST SUMMARY
B72: Total Building Cost | D72: =D109 -> 515841.05
B73: Building Components: 5 Year | D73: =F109 -> 104747.69
B74: % of Cost | D74: =F110 -> 0.20306195
B75: Building Structure: 27.5 Year | D75: =H109 -> 411093.36
B76: % of Cost | D76: =H110 -> 0.79693805
A78: COST SEGREGATION STUDY — COST DETAIL
B79: Property Category | D79: Cost | F79: 5 Year | H79: 27.5 Year
B80: Building Components
B81: Cabinets / Millwork | D81: =SUM(F81:H81) -> 14924.28 | F81: 14924.28
B82: Moldings | D82: =SUM(F82:H82) -> 10497.34 | F82: 10497.34
B83: Flooring - Vinyl Plank | D83: =SUM(F83:H83) -> 42163.82 | F83: 42163.82
B84: Window Treatments | D84: =SUM(F84:H84) -> 5291.37 | F84: 5291.37
B85: Building Signage | D85: =SUM(F85:H85) -> 297.35 | F85: 297.35
B86: Specialty Electrical - Appliances | D86: =SUM(F86:H86) -> 5540.41 | F86: 5540.41
B87: Communication / Data | D87: =SUM(F87:H87) -> 3335.96 | F87: 3335.96
B88: Specialty Plumbing - Kitchen Sinks | D88: =SUM(F88:H88) -> 11469.05 | F88: 11469.05
B89: Security / Exterior Lighting | D89: =SUM(F89:H89) -> 1722.5 | F89: 1722.5
B90: Appliances | D90: =SUM(F90:H90) -> 9505.61 | F90: 9505.61
B91: Building Structure
B92: Roofing Systems | D92: =SUM(F92:H92) -> 23533.09 | H92: 23533.09
B93: Foundations | D93: =SUM(F93:H93) -> 28643.92 | H93: 28643.92
B94: HVAC | D94: =SUM(F94:H94) -> 42496.69 | H94: 42496.69
B95: Electrical | D95: =SUM(F95:H95) -> 35043.34 | H95: 35043.34
B96: Plumbing | D96: =SUM(F96:H96) -> 36942.14 | H96: 36942.14
B97: Fire Protection & Alarm | D97: =SUM(F97:H97) -> 1288.46 | H97: 1288.46
B98: Exterior Façade / Building Skin | D98: =SUM(F98:H98) -> 22726.22 | H98: 22726.22
B99: Doors & Frames | D99: =SUM(F99:H99) -> 21445.66 | H99: 21445.66
B100: Windows | D100: =SUM(F100:H100) -> 23322.18 | H100: 23322.18
B101: Ceiling Systems | D101: =SUM(F101:H101) -> 18778.11 | H101: 18778.11
B102: Interior Framing / Partitions | D102: =SUM(F102:H102) -> 45770.64 | H102: 45770.64
B103: Painting | D103: =SUM(F103:H103) -> 19814.11 | H103: 19814.11
... B108: Cabinets / Millwork - Restrooms | D108: =SUM(F108:H108) -> 4754 | H108: 4754
B109: Total Building Cost | D109: =SUM(D80:D108) -> 515841.05 | F109: =SUM(F80:F108) -> 104747.69 | H109: =SUM(H80:H108) -> 411093.36
B110: % of Cost | F110: =F109/D109 -> 0.20306195 | H110: =H109/D109 -> 0.79693805
A112: ASSET ALLOCATION (per After Cost Segregation schedule)
B113: Asset (as reclassified) | D113: Cost | F113: 5 Year | H113: 27.5 Year
...

Sheet H
A1: Macedonia Apartments LLC
A2: Macedonia Apartments — 1722 W 17th St, Panama City, FL 32405
A3: EIN: 27-3618924 · FYE: December 31, 2024 · Year of Change: 1/1/2024
A4: H — Attachment to Form 3115 (DCN #7, Rev. Proc. 2024-23 §6.01)
A5: Source: CSSI Report #107752-05, "#107752-05_Macedonia Apartments, LLC - 3115 - combined R1.pdf"
A7: CALCULATION OF §481(a) ADJUSTMENT — REGULAR TAX
A8: As Previously Filed
A9: Asset | B9: Property Description | C9: Date In Service | D9: Cost | E9: Sec 179 Exp | F9: Bonus Amt | G9: Tax Prior Depreciation | H9: Tax Current Depreciation | I9: End Depreciation | J9: Net Book Value | K9: Method | L9: Period
A10: 1 | B10: Building - Apt | C10: 5/12/11 | D10: 92190.66 | E10: 0 | F10: 0 | G10: 31517.48 | H10: 3352.09 | I10: =G10+H10 -> 34869.57 | J10: =D10-I10 -> 57321.09 | K10: S/L | L10: 27.5
A11: 2 | B11: Building Improvements - Apt | C11: 5/31/22 | D11: 284089.88 | E11: 0 | F11: 0 | G11: 16786.89 | H11: 10329.51 | I11: =G11+H11 -> 27116.4 | J11: =D11-I11 -> 256973.48 | K11: S/L | L11: 27.5
A12: 3 | B12: Building Improvements - Apt | C12: 7/01/23 | D12: 1547.26 | E12: 0 | F12: 0 | G12: 25.76 | H12: 56.29 | I12: =G12+H12 -> 82.05 | J12: =D12-I12 -> 1465.21 | K12: S/L | L12: 27.5
A13: 4 | B13: Land Improvements - Apt | C13: 5/12/11 | D13: 22580.21 | E13: 0 | F13: 14699.63 | G13: 14699.63 | H13: 1334.49 | I13: =G13+H13 -> 16034.12 | J13: =D13-I13 -> 6546.09 | K13: 150DB | L13: 15.0
A14: 5 | B14: Land Improvements - Apt | C14: 5/31/22 | D14: 45421.43 | E14: 0 | F14: 45421.43 | G14: 45421.43 | H14: 0 | I14: =G14+H14 -> 45421.43 | J14: =D14-I14 -> 0 | K14: 150DB | L14: 15.0
A15: 6 | B15: Equipment - Apt | C15: 5/31/22 | D15: 70011.61 | E15: 0 | F15: 70011.61 | G15: 70011.61 | H15: 0 | I15: =G15+H15 -> 70011.61 | J15: =D15-I15 -> 0 | K15: 200DB | L15: 5.0
B16: Grand Total | D16: =SUM(D10:D15) -> 515841.05 | E16: =SUM(E10:E15) -> 0 | F16: =SUM(F10:F15) -> 130132.67 | G16: =SUM(G10:G15) -> 178462.8 | H16: =SUM(H10:H15) -> 15072.38 | I16: =SUM(I10:I15) -> 193535.18 | J16: =SUM(J10:J15) -> 322305.87
A18: After Cost Segregation Correction
A19: Asset | B19: Property Description | C19: Date In Service | D19: Cost | E19: Sec 179 Exp | F19: Bonus Amt | G19: Tax Prior Depreciation | H19: Tax Current Depreciation | I19: End Depreciation | J19: Net Book Value | K19: Method | L19: Period
A20: 1 | B20: Building - Apt - 5yr | C20: 5/12/11 | D20: 18720.42 | E20: 0 | F20: 0 | G20: 18720.42 | H20: 0 | I20: =G20+H20 -> 18720.42 | J20: =D20-I20 -> 0 | K20: 200DB | L20: 5.0
A21: 2 | B21: Building - Apt - 27.5yr | C21: 5/12/11 | D21: 73470.24 | E21: 0 | F21: 0 | G21: 33729.58 | H21: 2671.65 | I21: =G21+H21 -> 36401.23 | J21: =D21-I21 -> 37069.01 | K21: S/L | L21: 27.5
A22: 3 | B22: Building Improvements - Apt - 5yr | C22: 5/31/22 | D22: 57687.85 | E22: 0 | F22: 57687.85 | G22: 57687.85 | H22: 0 | I22: =G22+H22 -> 57687.85 | J22: =D22-I22 -> 0 | K22: 200DB | L22: 5.0
A23: 4 | B23: Building Improvements - Apt - 27.5yr | C23: 5/31/22 | D23: 226402.03 | E23: 0 | F23: 0 | G23: 13378.3 | H23: 8232.8 | I23: =G23+H23 -> 21611.1 | J23: =D23-I23 -> 204790.93 | K23: S/L | L23: 27.5
A24: 5 | B24: Building Improvements - Apt - 5yr | C24: 7/01/23 | D24: 314.19 | E24: 0 | F24: 251.35 | G24: 263.92 | H24: 20.11 | I24: =G24+H24 -> 284.03 | J24: =D24-I24 -> 30.16 | K24: 200DB | L24: 5.0
A25: 6 | B25: Building Improvements - Apt - 27.5yr | C25: 7/01/23 | D25: 1233.07 | E25: 0 | F25: 0 | G25: 20.55 | H25: 44.84 | I25: =G25+H25 -> 65.39 | J25: =D25-I25 -> 1167.68 | K25: S/L | L25: 27.5
A26: 7 | B26: Land Improvements - Apt - 5yr | C26: 5/12/11 | D26: 4585.18 | E26: 0 | F26: 4585.18 | G26: 4585.18 | H26: 0 | I26: =G26+H26 -> 4585.18 | J26: =D26-I26 -> 0 | K26: 200DB | L26: 5.0
A27: 8 | B27: Land Improvements - Apt - 27.5yr | C27: 5/12/11 | D27: 17995.03 | E27: 0 | F27: 0 | G27: 8261.3 | H27: 654.36 | I27: =G27+H27 -> 8915.66 | J27: =D27-I27 -> 9079.37 | K27: S/L | L27: 27.5
A28: 9 | B28: Land Improvements - Apt - 5yr | C28: 5/31/22 | D28: 9223.36 | E28: 0 | F28: 9223.36 | G28: 9223.36 | H28: 0 | I28: =G28+H28 -> 9223.36 | J28: =D28-I28 -> 0 | K28: 200DB | L28: 5.0
A29: 10 | B29: Land Improvements - Apt - 27.5yr | C29: 5/31/22 | D29: 36198.07 | E29: 0 | F29: 0 | G29: 2138.97 | H29: 1316.29 | I29: =G29+H29 -> 3455.26 | J29: =D29-I29 -> 32742.81 | K29: S/L | L29: 27.5
A30: 11 | B30: Equipment - Apt - 5yr | C30: 5/31/22 | D30: 14216.69 | E30: 0 | F30: 14216.69 | G30: 14216.69 | H30: 0 | I30: =G30+H30 -> 14216.69 | J30: =D30-I30 -> 0 | K30: 200DB | L30: 5.0
A31: 12 | B31: Equipment - Apt - 27.5yr | C31: 5/31/22 | D31: 55794.92 | E31: 0 | F31: 0 | G31: 3296.98 | H31: 2028.91 | I31: =G31+H31 -> 5325.89 | J31: =D31-I31 -> 50469.03 | K31: S/L | L31: 27.5
B32: Grand Total | D32: =SUM(D20:D31) -> 515841.05 | E32: =SUM(E20:E31) -> 0 | F32: =SUM(F20:F31) -> 85964.43 | G32: =SUM(G20:G31) -> 165523.1 | H32: =SUM(H20:H31) -> 14968.96 | I32: =SUM(I20:I31) -> 180492.06 | J32: =SUM(J20:J31) -> 335348.99
B34: Section 481(a) Adjustment — Regular Tax
B35: Depreciation reported previously | D35: =I16 -> 193535.18
B36: Cost Segregation Corrected Depreciation | D36: =I32 -> 180492.06
B37: Section 481(a) Adjustment — Regular Tax | D37: =D35-D36 -> 13043.12
A39: CALCULATION OF §481(a) ADJUSTMENT — AMT
A40: As Previously Filed — AMT
A41: Asset | B41: Property Description | C41: Date In Service | D41: Cost | E41: Sec 179 Exp | F41: Bonus Amt | G41: AMT Prior Depreciation | H41: AMT Current Depreciation | I41: End Depreciation | J41: Net Book Value | K41: Method | L41: Period
A42: 1 | B42: Building - Apt | C42: 5/12/11 | D42: 92190.66 | E42: 0 | F42: 0 | G42: 31517.48 | H42: 3352.09 | I42: =G42+H42 -> 34869.57 | J42: =D42-I42 -> 57321.09 | K42: S/L | L42: 27.5
A43: 2 | B43: Building Improvements - Apt | C43: 5/31/22 | D43: 284089.88 | E43: 0 | F43: 0 | G43: 16786.89 | H43: 10329.51 | I43: =G43+H43 -> 27116.4 | J43: =D43-I43 -> 256973.48 | K43: S/L | L43: 27.5
A44: 3 | B44: Building Improvements - Apt | C44: 7/01/23 | D44: 1547.26 | E44: 0 | F44: 0 | G44: 25.76 | H44: 56.29 | I44: =G44+H44 -> 82.05 | J44: =D44-I44 -> 1465.21 | K44: S/L | L44: 27.5
A45: 4 | B45: Land Improvements - Apt | C45: 5/12/11 | D45: 22580.21 | E45: 0 | F45: 14699.63 | G45: 14699.63 | H45: 1334.49 | I45: =G45+H45 -> 16034.12 | J45: =D45-I45 -> 6546.09 | K45: 150DB | L45: 15.0
A46: 5 | B46: Land Improvements - Apt | C46: 5/31/22 | D46: 45421.43 | E46: 0 | F46: 45421.43 | G46: 45421.43 | H46: 0 | I46: =G46+H46 -> 45421.43 | J46: =D46-I46 -> 0 | K46: 150DB | L46: 15.0
A47: 6 | B47: Equipment - Apt | C47: 5/31/22 | D47: 70011.61 | E47: 0 | F47: 70011.61 | G47: 70011.61 | H47: 0 | I47: =G47+H47 -> 70011.61 | J47: =D47-I47 -> 0 | K47: 200DB | L47: 5.0
B48: Grand Total | D48: =SUM(D42:D47) -> 515841.05 | E48: =SUM(E42:E47) -> 0 | F48: =SUM(F42:F47) -> 130132.67 | G48: =SUM(G42:G47) -> 178462.8 | H48: =SUM(H42:H47) -> 15072.38 | I48: =SUM(I42:I47) -> 193535.18 | J48: =SUM(J42:J47) -> 322305.87
A50: After Cost Segregation Correction — AMT
A51: Asset | B51: Property Description | C51: Date In Service | D51: Cost | E51: Sec 179 Exp | F51: Bonus Amt | G51: AMT Prior Depreciation | H51: AMT Current Depreciation | I51: End Depreciation | J51: Net Book Value | K51: Method | L51: Period
A52: 1 | B52: Building - Apt - 5yr | C52: 5/12/11 | D52: 18720.42 | E52: 0 | F52: 0 | G52: 18720.42 | H52: 0 | I52: =G52+H52 -> 18720.42 | J52: =D52-I52 -> 0 | K52: 200DB | L52: 5.0
A53: 2 | B53: Building - Apt - 27.5yr | C53: 5/12/11 | D53: 73470.24 | E53: 0 | F53: 0 | G53: 33729.58 | H53: 2671.65 | I53: =G53+H53 -> 36401.23 | J53: =D53-I53 -> 37069.01 | K53: S/L | L53: 27.5
A54: 3 | B54: Building Improvements - Apt - 5yr | C54: 5/31/22 | D54: 57687.85 | E54: 0 | F54: 57687.85 | G54: 57687.85 | H54: 0 | I54: =G54+H54 -> 57687.85 | J54: =D54-I54 -> 0 | K54: 200DB | L54: 5.0
A55: 4 | B55: Building Improvements - Apt - 27.5yr | C55: 5/31/22 | D55: 226402.03 | E55: 0 | F55: 0 | G55: 13378.3 | H55: 8232.8 | I55: =G55+H55 -> 21611.1 | J55: =D55-I55 -> 204790.93 | K55: S/L | L55: 27.5
A56: 5 | B56: Building Improvements - Apt - 5yr | C56: 7/01/23 | D56: 314.19 | E56: 0 | F56: 251.35 | G56: 263.92 | H56: 20.11 | I56: =G56+H56 -> 284.03 | J56: =D56-I56 -> 30.16 | K56: 200DB | L56: 5.0
A57: 6 | B57: Building Improvements - Apt - 27.5yr | C57: 7/01/23 | D57: 1233.07 | E57: 0 | F57: 0 | G57: 20.55 | H57: 44.84 | I57: =G57+H57 -> 65.39 | J57: =D57-I57 -> 1167.68 | K57: S/L | L57: 27.5
A58: 7 | B58: Land Improvements - Apt - 5yr | C58: 5/12/11 | D58: 4585.18 | E58: 0 | F58: 4585.18 | G58: 4585.18 | H58: 0 | I58: =G58+H58 -> 4585.18 | J58: =D58-I58 -> 0 | K58: 200DB | L58: 5.0
A59: 8 | B59: Land Improvements - Apt - 27.5yr | C59: 5/12/11 | D59: 17995.03 | E59: 0 | F59: 0 | G59: 8261.3 | H59: 654.36 | I59: =G59+H59 -> 8915.66 | J59: =D59-I59 -> 9079.37 | K59: S/L | L59: 27.5
A60: 9 | B60: Land Improvements - Apt - 5yr | C60: 5/31/22 | D60: 9223.36 | E60: 0 | F60: 9223.36 | G60: 9223.36 | H60: 0 | I60: =G60+H60 -> 9223.36 | J60: =D60-I60 -> 0 | K60: 200DB | L60: 5.0
A61: 10 | B61: Land Improvements - Apt - 27.5yr | C61: 5/31/22 | D61: 36198.07 | E61: 0 | F61: 0 | G61: 2138.97 | H61: 1316.29 | I61: =G61+H61 -> 3455.26 | J61: =D61-I61 -> 32742.81 | K61: S/L | L61: 27.5
A62: 11 | B62: Equipment - Apt - 5yr | C62: 5/31/22 | D62: 14216.69 | E62: 0 | F62: 14216.69 | G62: 14216.69 | H62: 0 | I62: =G62+H62 -> 14216.69 | J62: =D62-I62 -> 0 | K62: 200DB | L62: 5.0
A63: 12 | B63: Equipment - Apt - 27.5yr | C63: 5/31/22 | D63: 55794.92 | E63: 0 | F63: 0 | G63: 3296.98 | H63: 2028.91 | I63: =G63+H63 -> 5325.89 | J63: =D63-I63 -> 50469.03 | K63: S/L | L63: 27.5
B64: Grand Total | D64: =SUM(D52:D63) -> 515841.05 | E64: =SUM(E52:E63) -> 0 | F64: =SUM(F52:F63) -> 85964.43 | G64: =SUM(G52:G63) -> 165523.1 | H64: =SUM(H52:H63) -> 14968.96 | I64: =SUM(I52:I63) -> 180492.06 | J64: =SUM(J52:J63) -> 335348.99
B66: Section 481(a) Adjustment — AMT
B67: Depreciation reported previously | D67: =I48 -> 193535.18
B68: Cost Segregation Corrected Depreciation | D68: =I64 -> 180492.06
B69: Section 481(a) Adjustment — AMT | D69: =D67-D68 -> 13043.12
A71: COST SEGREGATION STUDY — COST SUMMARY
B72: Total Building Cost | D72: =D109 -> 515841.05
B73: Building Components: 5 Year | D73: =F109 -> 104747.69
B74: % of Cost | D74: =F110 -> 0.20306195
B75: Building Structure: 27.5 Year | D75: =H109 -> 411093.36
B76: % of Cost | D76: =H110 -> 0.79693805
A78: COST SEGREGATION STUDY — COST DETAIL
B79: Property Category | D79: Cost | F79: 5 Year | H79: 27.5 Year
B80: Building Components
B81: Cabinets / Millwork | D81: =SUM(F81:H81) -> 14924.28 | F81: 14924.28
B82: Moldings | D82: =SUM(F82:H82) -> 10497.34 | F82: 10497.34
B83: Flooring - Vinyl Plank | D83: =SUM(F83:H83) -> 42163.82 | F83: 42163.82
B84: Window Treatments | D84: =SUM(F84:H84) -> 5291.37 | F84: 5291.37
B85: Building Signage | D85: =SUM(F85:H85) -> 297.35 | F85: 297.35
B86: Specialty Electrical - Appliances | D86: =SUM(F86:H86) -> 5540.41 | F86: 5540.41
B87: Communication / Data | D87: =SUM(F87:H87) -> 3335.96 | F87: 3335.96
B88: Specialty Plumbing - Kitchen Sinks | D88: =SUM(F88:H88) -> 11469.05 | F88: 11469.05
B89: Security / Exterior Lighting | D89: =SUM(F89:H89) -> 1722.5 | F89: 1722.5
B90: Appliances | D90: =SUM(F90:H90) -> 9505.61 | F90: 9505.61
B91: Building Structure
B92: Roofing Systems | D92: =SUM(F92:H92) -> 23533.09 | H92: 23533.09
B93: Foundations | D93: =SUM(F93:H93) -> 28643.92 | H93: 28643.92
B94: HVAC | D94: =SUM(F94:H94) -> 42496.69 | H94: 42496.69
B95: Electrical | D95: =SUM(F95:H95) -> 35043.34 | H95: 35043.34
B96: Plumbing | D96: =SUM(F96:H96) -> 36942.14 | H96: 36942.14
B97: Fire Protection & Alarm | D97: =SUM(F97:H97) -> 1288.46 | H97: 1288.46
B98: Exterior Façade / Building Skin | D98: =SUM(F98:H98) -> 22726.22 | H98: 22726.22
B99: Doors & Frames | D99: =SUM(F99:H99) -> 21445.66 | H99: 21445.66
B100: Windows | D100: =SUM(F100:H100) -> 23322.18 | H100: 23322.18
B101: Ceiling Systems | D101: =SUM(F101:H101) -> 18778.11 | H101: 18778.11
B102: Interior Framing / Partitions | D102: =SUM(F102:H102) -> 45770.64 | H102: 45770.64
B103: Painting | D103: =SUM(F103:H103) -> 19814.11 | H103: 19814.11
... B108: Cabinets / Millwork - Restrooms | D108: =SUM(F108:H108) -> 4754 | H108: 4754
B109: Total Building Cost | D109: =SUM(D80:D108) -> 515841.05 | F109: =SUM(F80:F108) -> 104747.69 | H109: =SUM(H80:H108) -> 411093.36
B110: % of Cost | F110: =F109/D109 -> 0.20306195 | H110: =H109/D109 -> 0.79693805
A112: ASSET ALLOCATION (per After Cost Segregation schedule)
B113: Asset (as reclassified) | D113: Cost | F113: 5 Year | H113: 27.5 Year
...

Sheet I
A1: Macedonia Apartments LLC
A2: Macedonia Apartments — 1722 W 17th St, Panama City, FL 32405
A3: EIN: 27-3618924 · FYE: December 31, 2024 · Year of Change: 1/1/2024
A4: I — Attachment to Form 3115 (DCN #7, Rev. Proc. 2024-23 §6.01)
A5: Source: CSSI Report #107752-05, "#107752-05_Macedonia Apartments, LLC - 3115 - combined R1.pdf"
A7: CALCULATION OF §481(a) ADJUSTMENT — REGULAR TAX
A8: As Previously Filed
A9: Asset | B9: Property Description | C9: Date In Service | D9: Cost | E9: Sec 179 Exp | F9: Bonus Amt | G9: Tax Prior Depreciation | H9: Tax Current Depreciation | I9: End Depreciation | J9: Net Book Value | K9: Method | L9: Period
A10: 1 | B10: Building - Apt | C10: 5/12/11 | D10: 92190.66 | E10: 0 | F10: 0 | G10: 31517.48 | H10: 3352.09 | I10: =G10+H10 -> 34869.57 | J10: =D10-I10 -> 57321.09 | K10: S/L | L10: 27.5
A11: 2 | B11: Building Improvements - Apt | C11: 5/31/22 | D11: 284089.88 | E11: 0 | F11: 0 | G11: 16786.89 | H11: 10329.51 | I11: =G11+H11 -> 27116.4 | J11: =D11-I11 -> 256973.48 | K11: S/L | L11: 27.5
A12: 3 | B12: Building Improvements - Apt | C12: 7/01/23 | D12: 1547.26 | E12: 0 | F12: 0 | G12: 25.76 | H12: 56.29 | I12: =G12+H12 -> 82.05 | J12: =D12-I12 -> 1465.21 | K12: S/L | L12: 27.5
A13: 4 | B13: Land Improvements - Apt | C13: 5/12/11 | D13: 22580.21 | E13: 0 | F13: 14699.63 | G13: 14699.63 | H13: 1334.49 | I13: =G13+H13 -> 16034.12 | J13: =D13-I13 -> 6546.09 | K13: 150DB | L13: 15.0
A14: 5 | B14: Land Improvements - Apt | C14: 5/31/22 | D14: 45421.43 | E14: 0 | F14: 45421.43 | G14: 45421.43 | H14: 0 | I14: =G14+H14 -> 45421.43 | J14: =D14-I14 -> 0 | K14: 150DB | L14: 15.0
A15: 6 | B15: Equipment - Apt | C15: 5/31/22 | D15: 70011.61 | E15: 0 | F15: 70011.61 | G15: 70011.61 | H15: 0 | I15: =G15+H15 -> 70011.61 | J15: =D15-I15 -> 0 | K15: 200DB | L15: 5.0
B16: Grand Total | D16: =SUM(D10:D15) -> 515841.05 | E16: =SUM(E10:E15) -> 0 | F16: =SUM(F10:F15) -> 130132.67 | G16: =SUM(G10:G15) -> 178462.8 | H16: =SUM(H10:H15) -> 15072.38 | I16: =SUM(I10:I15) -> 193535.18 | J16: =SUM(J10:J15) -> 322305.87
A18: After Cost Segregation Correction
A19: Asset | B19: Property Description | C19: Date In Service | D19: Cost | E19: Sec 179 Exp | F19: Bonus Amt | G19: Tax Prior Depreciation | H19: Tax Current Depreciation | I19: End Depreciation | J19: Net Book Value | K19: Method | L19: Period
A20: 1 | B20: Building - Apt - 5yr | C20: 5/12/11 | D20: 18720.42 | E20: 0 | F20: 0 | G20: 18720.42 | H20: 0 | I20: =G20+H20 -> 18720.42 | J20: =D20-I20 -> 0 | K20: 200DB | L20: 5.0
A21: 2 | B21: Building - Apt - 27.5yr | C21: 5/12/11 | D21: 73470.24 | E21: 0 | F21: 0 | G21: 33729.58 | H21: 2671.65 | I21: =G21+H21 -> 36401.23 | J21: =D21-I21 -> 37069.01 | K21: S/L | L21: 27.5
A22: 3 | B22: Building Improvements - Apt - 5yr | C22: 5/31/22 | D22: 57687.85 | E22: 0 | F22: 57687.85 | G22: 57687.85 | H22: 0 | I22: =G22+H22 -> 57687.85 | J22: =D22-I22 -> 0 | K22: 200DB | L22: 5.0
A23: 4 | B23: Building Improvements - Apt - 27.5yr | C23: 5/31/22 | D23: 226402.03 | E23: 0 | F23: 0 | G23: 13378.3 | H23: 8232.8 | I23: =G23+H23 -> 21611.1 | J23: =D23-I23 -> 204790.93 | K23: S/L | L23: 27.5
A24: 5 | B24: Building Improvements - Apt - 5yr | C24: 7/01/23 | D24: 314.19 | E24: 0 | F24: 251.35 | G24: 263.92 | H24: 20.11 | I24: =G24+H24 -> 284.03 | J24: =D24-I24 -> 30.16 | K24: 200DB | L24: 5.0
A25: 6 | B25: Building Improvements - Apt - 27.5yr | C25: 7/01/23 | D25: 1233.07 | E25: 0 | F25: 0 | G25: 20.55 | H25: 44.84 | I25: =G25+H25 -> 65.39 | J25: =D25-I25 -> 1167.68 | K25: S/L | L25: 27.5
A26: 7 | B26: Land Improvements - Apt - 5yr | C26: 5/12/11 | D26: 4585.18 | E26: 0 | F26: 4585.18 | G26: 4585.18 | H26: 0 | I26: =G26+H26 -> 4585.18 | J26: =D26-I26 -> 0 | K26: 200DB | L26: 5.0
A27: 8 | B27: Land Improvements - Apt - 27.5yr | C27: 5/12/11 | D27: 17995.03 | E27: 0 | F27: 0 | G27: 8261.3 | H27: 654.36 | I27: =G27+H27 -> 8915.66 | J27: =D27-I27 -> 9079.37 | K27: S/L | L27: 27.5
A28: 9 | B28: Land Improvements - Apt - 5yr | C28: 5/31/22 | D28: 9223.36 | E28: 0 | F28: 9223.36 | G28: 9223.36 | H28: 0 | I28: =G28+H28 -> 9223.36 | J28: =D28-I28 -> 0 | K28: 200DB | L28: 5.0
A29: 10 | B29: Land Improvements - Apt - 27.5yr | C29: 5/31/22 | D29: 36198.07 | E29: 0 | F29: 0 | G29: 2138.97 | H29: 1316.29 | I29: =G29+H29 -> 3455.26 | J29: =D29-I29 -> 32742.81 | K29: S/L | L29: 27.5
A30: 11 | B30: Equipment - Apt - 5yr | C30: 5/31/22 | D30: 14216.69 | E30: 0 | F30: 14216.69 | G30: 14216.69 | H30: 0 | I30: =G30+H30 -> 14216.69 | J30: =D30-I30 -> 0 | K30: 200DB | L30: 5.0
A31: 12 | B31: Equipment - Apt - 27.5yr | C31: 5/31/22 | D31: 55794.92 | E31: 0 | F31: 0 | G31: 3296.98 | H31: 2028.91 | I31: =G31+H31 -> 5325.89 | J31: =D31-I31 -> 50469.03 | K31: S/L | L31: 27.5
B32: Grand Total | D32: =SUM(D20:D31) -> 515841.05 | E32: =SUM(E20:E31) -> 0 | F32: =SUM(F20:F31) -> 85964.43 | G32: =SUM(G20:G31) -> 165523.1 | H32: =SUM(H20:H31) -> 14968.96 | I32: =SUM(I20:I31) -> 180492.06 | J32: =SUM(J20:J31) -> 335348.99
B34: Section 481(a) Adjustment — Regular Tax
B35: Depreciation reported previously | D35: =I16 -> 193535.18
B36: Cost Segregation Corrected Depreciation | D36: =I32 -> 180492.06
B37: Section 481(a) Adjustment — Regular Tax | D37: =D35-D36 -> 13043.12
A39: CALCULATION OF §481(a) ADJUSTMENT — AMT
A40: As Previously Filed — AMT
A41: Asset | B41: Property Description | C41: Date In Service | D41: Cost | E41: Sec 179 Exp | F41: Bonus Amt | G41: AMT Prior Depreciation | H41: AMT Current Depreciation | I41: End Depreciation | J41: Net Book Value | K41: Method | L41: Period
A42: 1 | B42: Building - Apt | C42: 5/12/11 | D42: 92190.66 | E42: 0 | F42: 0 | G42: 31517.48 | H42: 3352.09 | I42: =G42+H42 -> 34869.57 | J42: =D42-I42 -> 57321.09 | K42: S/L | L42: 27.5
A43: 2 | B43: Building Improvements - Apt | C43: 5/31/22 | D43: 284089.88 | E43: 0 | F43: 0 | G43: 16786.89 | H43: 10329.51 | I43: =G43+H43 -> 27116.4 | J43: =D43-I43 -> 256973.48 | K43: S/L | L43: 27.5
A44: 3 | B44: Building Improvements - Apt | C44: 7/01/23 | D44: 1547.26 | E44: 0 | F44: 0 | G44: 25.76 | H44: 56.29 | I44: =G44+H44 -> 82.05 | J44: =D44-I44 -> 1465.21 | K44: S/L | L44: 27.5
A45: 4 | B45: Land Improvements - Apt | C45: 5/12/11 | D45: 22580.21 | E45: 0 | F45: 14699.63 | G45: 14699.63 | H45: 1334.49 | I45: =G45+H45 -> 16034.12 | J45: =D45-I45 -> 6546.09 | K45: 150DB | L45: 15.0
A46: 5 | B46: Land Improvements - Apt | C46: 5/31/22 | D46: 45421.43 | E46: 0 | F46: 45421.43 | G46: 45421.43 | H46: 0 | I46: =G46+H46 -> 45421.43 | J46: =D46-I46 -> 0 | K46: 150DB | L46: 15.0
A47: 6 | B47: Equipment - Apt | C47: 5/31/22 | D47: 70011.61 | E47: 0 | F47: 70011.61 | G47: 70011.61 | H47: 0 | I47: =G47+H47 -> 70011.61 | J47: =D47-I47 -> 0 | K47: 200DB | L47: 5.0
B48: Grand Total | D48: =SUM(D42:D47) -> 515841.05 | E48: =SUM(E42:E47) -> 0 | F48: =SUM(F42:F47) -> 130132.67 | G48: =SUM(G42:G47) -> 178462.8 | H48: =SUM(H42:H47) -> 15072.38 | I48: =SUM(I42:I47) -> 193535.18 | J48: =SUM(J42:J47) -> 322305.87
A50: After Cost Segregation Correction — AMT
A51: Asset | B51: Property Description | C51: Date In Service | D51: Cost | E51: Sec 179 Exp | F51: Bonus Amt | G51: AMT Prior Depreciation | H51: AMT Current Depreciation | I51: End Depreciation | J51: Net Book Value | K51: Method | L51: Period
A52: 1 | B52: Building - Apt - 5yr | C52: 5/12/11 | D52: 18720.42 | E52: 0 | F52: 0 | G52: 18720.42 | H52: 0 | I52: =G52+H52 -> 18720.42 | J52: =D52-I52 -> 0 | K52: 200DB | L52: 5.0
A53: 2 | B53: Building - Apt - 27.5yr | C53: 5/12/11 | D53: 73470.24 | E53: 0 | F53: 0 | G53: 33729.58 | H53: 2671.65 | I53: =G53+H53 -> 36401.23 | J53: =D53-I53 -> 37069.01 | K53: S/L | L53: 27.5
A54: 3 | B54: Building Improvements - Apt - 5yr | C54: 5/31/22 | D54: 57687.85 | E54: 0 | F54: 57687.85 | G54: 57687.85 | H54: 0 | I54: =G54+H54 -> 57687.85 | J54: =D54-I54 -> 0 | K54: 200DB | L54: 5.0
A55: 4 | B55: Building Improvements - Apt - 27.5yr | C55: 5/31/22 | D55: 226402.03 | E55: 0 | F55: 0 | G55: 13378.3 | H55: 8232.8 | I55: =G55+H55 -> 21611.1 | J55: =D55-I55 -> 204790.93 | K55: S/L | L55: 27.5
A56: 5 | B56: Building Improvements - Apt - 5yr | C56: 7/01/23 | D56: 314.19 | E56: 0 | F56: 251.35 | G56: 263.92 | H56: 20.11 | I56: =G56+H56 -> 284.03 | J56: =D56-I56 -> 30.16 | K56: 200DB | L56: 5.0
A57: 6 | B57: Building Improvements - Apt - 27.5yr | C57: 7/01/23 | D57: 1233.07 | E57: 0 | F57: 0 | G57: 20.55 | H57: 44.84 | I57: =G57+H57 -> 65.39 | J57: =D57-I57 -> 1167.68 | K57: S/L | L57: 27.5
A58: 7 | B58: Land Improvements - Apt - 5yr | C58: 5/12/11 | D58: 4585.18 | E58: 0 | F58: 4585.18 | G58: 4585.18 | H58: 0 | I58: =G58+H58 -> 4585.18 | J58: =D58-I58 -> 0 | K58: 200DB | L58: 5.0
A59: 8 | B59: Land Improvements - Apt - 27.5yr | C59: 5/12/11 | D59: 17995.03 | E59: 0 | F59: 0 | G59: 8261.3 | H59: 654.36 | I59: =G59+H59 -> 8915.66 | J59: =D59-I59 -> 9079.37 | K59: S/L | L59: 27.5
A60: 9 | B60: Land Improvements - Apt - 5yr | C60: 5/31/22 | D60: 9223.36 | E60: 0 | F60: 9223.36 | G60: 9223.36 | H60: 0 | I60: =G60+H60 -> 9223.36 | J60: =D60-I60 -> 0 | K60: 200DB | L60: 5.0
A61: 10 | B61: Land Improvements - Apt - 27.5yr | C61: 5/31/22 | D61: 36198.07 | E61: 0 | F61: 0 | G61: 2138.97 | H61: 1316.29 | I61: =G61+H61 -> 3455.26 | J61: =D61-I61 -> 32742.81 | K61: S/L | L61: 27.5
A62: 11 | B62: Equipment - Apt - 5yr | C62: 5/31/22 | D62: 14216.69 | E62: 0 | F62: 14216.69 | G62: 14216.69 | H62: 0 | I62: =G62+H62 -> 14216.69 | J62: =D62-I62 -> 0 | K62: 200DB | L62: 5.0
A63: 12 | B63: Equipment - Apt - 27.5yr | C63: 5/31/22 | D63: 55794.92 | E63: 0 | F63: 0 | G63: 3296.98 | H63: 2028.91 | I63: =G63+H63 -> 5325.89 | J63: =D63-I63 -> 50469.03 | K63: S/L | L63: 27.5
B64: Grand Total | D64: =SUM(D52:D63) -> 515841.05 | E64: =SUM(E52:E63) -> 0 | F64: =SUM(F52:F63) -> 85964.43 | G64: =SUM(G52:G63) -> 165523.1 | H64: =SUM(H52:H63) -> 14968.96 | I64: =SUM(I52:I63) -> 180492.06 | J64: =SUM(J52:J63) -> 335348.99
B66: Section 481(a) Adjustment — AMT
B67: Depreciation reported previously | D67: =I48 -> 193535.18
B68: Cost Segregation Corrected Depreciation | D68: =I64 -> 180492.06
B69: Section 481(a) Adjustment — AMT | D69: =D67-D68 -> 13043.12
A71: COST SEGREGATION STUDY — COST SUMMARY
B72: Total Building Cost | D72: =D109 -> 515841.05
B73: Building Components: 5 Year | D73: =F109 -> 104747.69
B74: % of Cost | D74: =F110 -> 0.20306195
B75: Building Structure: 27.5 Year | D75: =H109 -> 411093.36
B76: % of Cost | D76: =H110 -> 0.79693805
A78: COST SEGREGATION STUDY — COST DETAIL
B79: Property Category | D79: Cost | F79: 5 Year | H79: 27.5 Year
B80: Building Components
B81: Cabinets / Millwork | D81: =SUM(F81:H81) -> 14924.28 | F81: 14924.28
B82: Moldings | D82: =SUM(F82:H82) -> 10497.34 | F82: 10497.34
B83: Flooring - Vinyl Plank | D83: =SUM(F83:H83) -> 42163.82 | F83: 42163.82
B84: Window Treatments | D84: =SUM(F84:H84) -> 5291.37 | F84: 5291.37
B85: Building Signage | D85: =SUM(F85:H85) -> 297.35 | F85: 297.35
B86: Specialty Electrical - Appliances | D86: =SUM(F86:H86) -> 5540.41 | F86: 5540.41
B87: Communication / Data | D87: =SUM(F87:H87) -> 3335.96 | F87: 3335.96
B88: Specialty Plumbing - Kitchen Sinks | D88: =SUM(F88:H88) -> 11469.05 | F88: 11469.05
B89: Security / Exterior Lighting | D89: =SUM(F89:H89) -> 1722.5 | F89: 1722.5
B90: Appliances | D90: =SUM(F90:H90) -> 9505.61 | F90: 9505.61
B91: Building Structure
B92: Roofing Systems | D92: =SUM(F92:H92) -> 23533.09 | H92: 23533.09
B93: Foundations | D93: =SUM(F93:H93) -> 28643.92 | H93: 28643.92
B94: HVAC | D94: =SUM(F94:H94) -> 42496.69 | H94: 42496.69
B95: Electrical | D95: =SUM(F95:H95) -> 35043.34 | H95: 35043.34
B96: Plumbing | D96: =SUM(F96:H96) -> 36942.14 | H96: 36942.14
B97: Fire Protection & Alarm | D97: =SUM(F97:H97) -> 1288.46 | H97: 1288.46
B98: Exterior Façade / Building Skin | D98: =SUM(F98:H98) -> 22726.22 | H98: 22726.22
B99: Doors & Frames | D99: =SUM(F99:H99) -> 21445.66 | H99: 21445.66
B100: Windows | D100: =SUM(F100:H100) -> 23322.18 | H100: 23322.18
B101: Ceiling Systems | D101: =SUM(F101:H101) -> 18778.11 | H101: 18778.11
B102: Interior Framing / Partitions | D102: =SUM(F102:H102) -> 45770.64 | H102: 45770.64
B103: Painting | D103: =SUM(F103:H103) -> 19814.11 | H103: 19814.11
... B108: Cabinets / Millwork - Restrooms | D108: =SUM(F108:H108) -> 4754 | H108: 4754
B109: Total Building Cost | D109: =SUM(D80:D108) -> 515841.05 | F109: =SUM(F80:F108) -> 104747.69 | H109: =SUM(H80:H108) -> 411093.36
B110: % of Cost | F110: =F109/D109 -> 0.20306195 | H110: =H109/D109 -> 0.79693805
A112: ASSET ALLOCATION (per After Cost Segregation schedule)
B113: Asset (as reclassified) | D113: Cost | F113: 5 Year | H113: 27.5 Year
...

Sheet J
A1: Macedonia Apartments LLC
A2: Macedonia Apartments — 1722 W 17th St, Panama City, FL 32405
A3: EIN: 27-3618924 · FYE: December 31, 2024 · Year of Change: 1/1/2024
A4: J — Attachment to Form 3115 (DCN #7, Rev. Proc. 2024-23 §6.01)
A5: Source: CSSI Report #107752-05, "#107752-05_Macedonia Apartments, LLC - 3115 - combined R1.pdf"
A7: CALCULATION OF §481(a) ADJUSTMENT — REGULAR TAX
A8: As Previously Filed
A9: Asset | B9: Property Description | C9: Date In Service | D9: Cost | E9: Sec 179 Exp | F9: Bonus Amt | G9: Tax Prior Depreciation | H9: Tax Current Depreciation | I9: End Depreciation | J9: Net Book Value | K9: Method | L9: Period
A10: 1 | B10: Building - Apt | C10: 5/12/11 | D10: 78702.11 | E10: 0 | F10: 0 | G10: 26906.11 | H10: 2861.64 | I10: =G10+H10 -> 29767.75 | J10: =D10-I10 -> 48934.36 | K10: S/L | L10: 27.5
A11: 2 | B11: Building Improvements - Apt | C11: 5/31/22 | D11: 242524.3 | E11: 0 | F11: 0 | G11: 14330.78 | H11: 8818.19 | I11: =G11+H11 -> 23148.97 | J11: =D11-I11 -> 219375.33 | K11: S/L | L11: 27.5
A12: 3 | B12: Building Improvements - Apt | C12: 7/01/23 | D12: 1320.88 | E12: 0 | F12: 0 | G12: 21.99 | H12: 48.05 | I12: =G12+H12 -> 70.04 | J12: =D12-I12 -> 1250.84 | K12: S/L | L12: 27.5
A13: 4 | B13: Land Improvements - Apt | C13: 5/12/11 | D13: 19276.47 | E13: 0 | F13: 12548.91 | G13: 12548.91 | H13: 1139.24 | I13: =G13+H13 -> 13688.15 | J13: =D13-I13 -> 5588.32 | K13: 150DB | L13: 15.0
A14: 5 | B14: Land Improvements - Apt | C14: 5/31/22 | D14: 38775.76 | E14: 0 | F14: 38775.76 | G14: 38775.76 | H14: 0 | I14: =G14+H14 -> 38775.76 | J14: =D14-I14 -> 0 | K14: 150DB | L14: 15.0
A15: 6 | B15: Equipment - Apt | C15: 5/31/22 | D15: 59768.11 | E15: 0 | F15: 59768.11 | G15: 59768.11 | H15: 0 | I15: =G15+H15 -> 59768.11 | J15: =D15-I15 -> 0 | K15: 200DB | L15: 5.0
B16: Grand Total | D16: =SUM(D10:D15) -> 440367.63 | E16: =SUM(E10:E15) -> 0 | F16: =SUM(F10:F15) -> 111092.78 | G16: =SUM(G10:G15) -> 152351.66 | H16: =SUM(H10:H15) -> 12867.12 | I16: =SUM(I10:I15) -> 165218.78 | J16: =SUM(J10:J15) -> 275148.85
A18: After Cost Segregation Correction
A19: Asset | B19: Property Description | C19: Date In Service | D19: Cost | E19: Sec 179 Exp | F19: Bonus Amt | G19: Tax Prior Depreciation | H19: Tax Current Depreciation | I19: End Depreciation | J19: Net Book Value | K19: Method | L19: Period
A20: 1 | B20: Building - Apt - 5yr | C20: 5/12/11 | D20: 16357.03 | E20: 0 | F20: 0 | G20: 16357.03 | H20: 0 | I20: =G20+H20 -> 16357.03 | J20: =D20-I20 -> 0 | K20: 200DB | L20: 5.0
A21: 2 | B21: Building - Apt - 27.5yr | C21: 5/12/11 | D21: 62345.08 | E21: 0 | F21: 0 | G21: 28622.01 | H21: 2267.09 | I21: =G21+H21 -> 30889.1 | J21: =D21-I21 -> 31455.98 | K21: S/L | L21: 27.5
A22: 3 | B22: Building Improvements - Apt - 5yr | C22: 5/31/22 | D22: 50404.95 | E22: 0 | F22: 50404.95 | G22: 50404.95 | H22: 0 | I22: =G22+H22 -> 50404.95 | J22: =D22-I22 -> 0 | K22: 200DB | L22: 5.0
A23: 4 | B23: Building Improvements - Apt - 27.5yr | C23: 5/31/22 | D23: 192119.35 | E23: 0 | F23: 0 | G23: 11352.51 | H23: 6986.16 | I23: =G23+H23 -> 18338.67 | J23: =D23-I23 -> 173780.68 | K23: S/L | L23: 27.5
A24: 5 | B24: Building Improvements - Apt - 5yr | C24: 7/01/23 | D24: 274.52 | E24: 0 | F24: 219.62 | G24: 230.6 | H24: 17.57 | I24: =G24+H24 -> 248.17 | J24: =D24-I24 -> 26.35 | K24: 200DB | L24: 5.0
A25: 6 | B25: Building Improvements - Apt - 27.5yr | C25: 7/01/23 | D25: 1046.36 | E25: 0 | F25: 0 | G25: 17.44 | H25: 38.05 | I25: =G25+H25 -> 55.49 | J25: =D25-I25 -> 990.87 | K25: S/L | L25: 27.5
A26: 7 | B26: Land Improvements - Apt - 5yr | C26: 5/12/11 | D26: 4006.32 | E26: 0 | F26: 4006.32 | G26: 4006.32 | H26: 0 | I26: =G26+H26 -> 4006.32 | J26: =D26-I26 -> 0 | K26: 200DB | L26: 5.0
A27: 8 | B27: Land Improvements - Apt - 27.5yr | C27: 5/12/11 | D27: 15270.15 | E27: 0 | F27: 0 | G27: 7010.41 | H27: 555.28 | I27: =G27+H27 -> 7565.69 | J27: =D27-I27 -> 7704.46 | K27: S/L | L27: 27.5
A28: 9 | B28: Land Improvements - Apt - 5yr | C28: 5/31/22 | D28: 8058.95 | E28: 0 | F28: 8058.95 | G28: 8058.95 | H28: 0 | I28: =G28+H28 -> 8058.95 | J28: =D28-I28 -> 0 | K28: 200DB | L28: 5.0
A29: 10 | B29: Land Improvements - Apt - 27.5yr | C29: 5/31/22 | D29: 30716.81 | E29: 0 | F29: 0 | G29: 1815.08 | H29: 1116.97 | I29: =G29+H29 -> 2932.05 | J29: =D29-I29 -> 27784.76 | K29: S/L | L29: 27.5
A30: 11 | B30: Equipment - Apt - 5yr | C30: 5/31/22 | D30: 12421.88 | E30: 0 | F30: 12421.88 | G30: 12421.88 | H30: 0 | I30: =G30+H30 -> 12421.88 | J30: =D30-I30 -> 0 | K30: 200DB | L30: 5.0
A31: 12 | B31: Equipment - Apt - 27.5yr | C31: 5/31/22 | D31: 47346.23 | E31: 0 | F31: 0 | G31: 2797.73 | H31: 1721.68 | I31: =G31+H31 -> 4519.41 | J31: =D31-I31 -> 42826.82 | K31: S/L | L31: 27.5
B32: Grand Total | D32: =SUM(D20:D31) -> 440367.63 | E32: =SUM(E20:E31) -> 0 | F32: =SUM(F20:F31) -> 75111.72 | G32: =SUM(G20:G31) -> 143094.91 | H32: =SUM(H20:H31) -> 12702.8 | I32: =SUM(I20:I31) -> 155797.71 | J32: =SUM(J20:J31) -> 284569.92
B34: Section 481(a) Adjustment — Regular Tax
B35: Depreciation reported previously | D35: =I16 -> 165218.78
B36: Cost Segregation Corrected Depreciation | D36: =I32 -> 155797.71
B37: Section 481(a) Adjustment — Regular Tax | D37: =D35-D36 -> 9421.07
A39: CALCULATION OF §481(a) ADJUSTMENT — AMT
A40: As Previously Filed — AMT
A41: Asset | B41: Property Description | C41: Date In Service | D41: Cost | E41: Sec 179 Exp | F41: Bonus Amt | G41: AMT Prior Depreciation | H41: AMT Current Depreciation | I41: End Depreciation | J41: Net Book Value | K41: Method | L41: Period
A42: 1 | B42: Building - Apt | C42: 5/12/11 | D42: 78702.11 | E42: 0 | F42: 0 | G42: 26906.11 | H42: 2861.64 | I42: =G42+H42 -> 29767.75 | J42: =D42-I42 -> 48934.36 | K42: S/L | L42: 27.5
A43: 2 | B43: Building Improvements - Apt | C43: 5/31/22 | D43: 242524.3 | E43: 0 | F43: 0 | G43: 14330.78 | H43: 8818.19 | I43: =G43+H43 -> 23148.97 | J43: =D43-I43 -> 219375.33 | K43: S/L | L43: 27.5
A44: 3 | B44: Building Improvements - Apt | C44: 7/01/23 | D44: 1320.88 | E44: 0 | F44: 0 | G44: 21.99 | H44: 48.05 | I44: =G44+H44 -> 70.04 | J44: =D44-I44 -> 1250.84 | K44: S/L | L44: 27.5
A45: 4 | B45: Land Improvements - Apt | C45: 5/12/11 | D45: 19276.47 | E45: 0 | F45: 12548.91 | G45: 12548.91 | H45: 1139.24 | I45: =G45+H45 -> 13688.15 | J45: =D45-I45 -> 5588.32 | K45: 150DB | L45: 15.0
A46: 5 | B46: Land Improvements - Apt | C46: 5/31/22 | D46: 38775.76 | E46: 0 | F46: 38775.76 | G46: 38775.76 | H46: 0 | I46: =G46+H46 -> 38775.76 | J46: =D46-I46 -> 0 | K46: 150DB | L46: 15.0
A47: 6 | B47: Equipment - Apt | C47: 5/31/22 | D47: 59768.11 | E47: 0 | F47: 59768.11 | G47: 59768.11 | H47: 0 | I47: =G47+H47 -> 59768.11 | J47: =D47-I47 -> 0 | K47: 200DB | L47: 5.0
B48: Grand Total | D48: =SUM(D42:D47) -> 440367.63 | E48: =SUM(E42:E47) -> 0 | F48: =SUM(F42:F47) -> 111092.78 | G48: =SUM(G42:G47) -> 152351.66 | H48: =SUM(H42:H47) -> 12867.12 | I48: =SUM(I42:I47) -> 165218.78 | J48: =SUM(J42:J47) -> 275148.85
A50: After Cost Segregation Correction — AMT
A51: Asset | B51: Property Description | C51: Date In Service | D51: Cost | E51: Sec 179 Exp | F51: Bonus Amt | G51: AMT Prior Depreciation | H51: AMT Current Depreciation | I51: End Depreciation | J51: Net Book Value | K51: Method | L51: Period
A52: 1 | B52: Building - Apt - 5yr | C52: 5/12/11 | D52: 16357.03 | E52: 0 | F52: 0 | G52: 16357.03 | H52: 0 | I52: =G52+H52 -> 16357.03 | J52: =D52-I52 -> 0 | K52: 200DB | L52: 5.0
A53: 2 | B53: Building - Apt - 27.5yr | C53: 5/12/11 | D53: 62345.08 | E53: 0 | F53: 0 | G53: 28622.01 | H53: 2267.09 | I53: =G53+H53 -> 30889.1 | J53: =D53-I53 -> 31455.98 | K53: S/L | L53: 27.5
A54: 3 | B54: Building Improvements - Apt - 5yr | C54: 5/31/22 | D54: 50404.95 | E54: 0 | F54: 50404.95 | G54: 50404.95 | H54: 0 | I54: =G54+H54 -> 50404.95 | J54: =D54-I54 -> 0 | K54: 200DB | L54: 5.0
A55: 4 | B55: Building Improvements - Apt - 27.5yr | C55: 5/31/22 | D55: 192119.35 | E55: 0 | F55: 0 | G55: 11352.51 | H55: 6986.16 | I55: =G55+H55 -> 18338.67 | J55: =D55-I55 -> 173780.68 | K55: S/L | L55: 27.5
A56: 5 | B56: Building Improvements - Apt - 5yr | C56: 7/01/23 | D56: 274.52 | E56: 0 | F56: 219.62 | G56: 230.6 | H56: 17.57 | I56: =G56+H56 -> 248.17 | J56: =D56-I56 -> 26.35 | K56: 200DB | L56: 5.0
A57: 6 | B57: Building Improvements - Apt - 27.5yr | C57: 7/01/23 | D57: 1046.36 | E57: 0 | F57: 0 | G57: 17.44 | H57: 38.05 | I57: =G57+H57 -> 55.49 | J57: =D57-I57 -> 990.87 | K57: S/L | L57: 27.5
A58: 7 | B58: Land Improvements - Apt - 5yr | C58: 5/12/11 | D58: 4006.32 | E58: 0 | F58: 4006.32 | G58: 4006.32 | H58: 0 | I58: =G58+H58 -> 4006.32 | J58: =D58-I58 -> 0 | K58: 200DB | L58: 5.0
A59: 8 | B59: Land Improvements - Apt - 27.5yr | C59: 5/12/11 | D59: 15270.15 | E59: 0 | F59: 0 | G59: 7010.41 | H59: 555.28 | I59: =G59+H59 -> 7565.69 | J59: =D59-I59 -> 7704.46 | K59: S/L | L59: 27.5
A60: 9 | B60: Land Improvements - Apt - 5yr | C60: 5/31/22 | D60: 8058.95 | E60: 0 | F60: 8058.95 | G60: 8058.95 | H60: 0 | I60: =G60+H60 -> 8058.95 | J60: =D60-I60 -> 0 | K60: 200DB | L60: 5.0
A61: 10 | B61: Land Improvements - Apt - 27.5yr | C61: 5/31/22 | D61: 30716.81 | E61: 0 | F61: 0 | G61: 1815.08 | H61: 1116.97 | I61: =G61+H61 -> 2932.05 | J61: =D61-I61 -> 27784.76 | K61: S/L | L61: 27.5
A62: 11 | B62: Equipment - Apt - 5yr | C62: 5/31/22 | D62: 12421.88 | E62: 0 | F62: 12421.88 | G62: 12421.88 | H62: 0 | I62: =G62+H62 -> 12421.88 | J62: =D62-I62 -> 0 | K62: 200DB | L62: 5.0
A63: 12 | B63: Equipment - Apt - 27.5yr | C63: 5/31/22 | D63: 47346.23 | E63: 0 | F63: 0 | G63: 2797.73 | H63: 1721.68 | I63: =G63+H63 -> 4519.41 | J63: =D63-I63 -> 42826.82 | K63: S/L | L63: 27.5
B64: Grand Total | D64: =SUM(D52:D63) -> 440367.63 | E64: =SUM(E52:E63) -> 0 | F64: =SUM(F52:F63) -> 75111.72 | G64: =SUM(G52:G63) -> 143094.91 | H64: =SUM(H52:H63) -> 12702.8 | I64: =SUM(I52:I63) -> 155797.71 | J64: =SUM(J52:J63) -> 284569.92
B66: Section 481(a) Adjustment — AMT
B67: Depreciation reported previously | D67: =I48 -> 165218.78
B68: Cost Segregation Corrected Depreciation | D68: =I64 -> 155797.71
B69: Section 481(a) Adjustment — AMT | D69: =D67-D68 -> 9421.07
A71: COST SEGREGATION STUDY — COST SUMMARY
B72: Total Building Cost | D72: =D109 -> 440367.63
B73: Building Components: 5 Year | D73: =F109 -> 91523.65
B74: % of Cost | D74: =F110 -> 0.20783464
B75: Building Structure: 27.5 Year | D75: =H109 -> 348843.98
B76: % of Cost | D76: =H110 -> 0.79216536
A78: COST SEGREGATION STUDY — COST DETAIL
B79: Property Category | D79: Cost | F79: 5 Year | H79: 27.5 Year
B80: Building Components
B81: Cabinets / Millwork | D81: =SUM(F81:H81) -> 14219.24 | F81: 14219.24
B82: Moldings | D82: =SUM(F82:H82) -> 9652.73 | F82: 9652.73
B83: Flooring - Vinyl Plank | D83: =SUM(F83:H83) -> 33731.06 | F83: 33731.06
B84: Window Treatments | D84: =SUM(F84:H84) -> 3552.78 | F84: 3552.78
B85: Building Signage | D85: =SUM(F85:H85) -> 297.35 | F85: 297.35
B86: Specialty Electrical - Appliances | D86: =SUM(F86:H86) -> 5540.41 | F86: 5540.41
B87: Communication / Data | D87: =SUM(F87:H87) -> 2668.77 | F87: 2668.77
B88: Specialty Plumbing - Kitchen Sinks | D88: =SUM(F88:H88) -> 11469.05 | F88: 11469.05
B89: Security / Exterior Lighting | D89: =SUM(F89:H89) -> 886.65 | F89: 886.65
B90: Appliances | D90: =SUM(F90:H90) -> 9505.61 | F90: 9505.61
B91: Building Structure
B92: Roofing Systems | D92: =SUM(F92:H92) -> 19629.66 | H92: 19629.66
B93: Foundations | D93: =SUM(F93:H93) -> 23418.11 | H93: 23418.11
B94: HVAC | D94: =SUM(F94:H94) -> 33997.34 | H94: 33997.34
B95: Electrical | D95: =SUM(F95:H95) -> 26926.59 | H95: 26926.59
B96: Plumbing | D96: =SUM(F96:H96) -> 29553.7 | H96: 29553.7
B97: Fire Protection & Alarm | D97: =SUM(F97:H97) -> 1932.7 | H97: 1932.7
B98: Exterior Façade / Building Skin | D98: =SUM(F98:H98) -> 21649.45 | H98: 21649.45
B99: Doors & Frames | D99: =SUM(F99:H99) -> 18392.87 | H99: 18392.87
B100: Windows | D100: =SUM(F100:H100) -> 15659.18 | H100: 15659.18
B101: Ceiling Systems | D101: =SUM(F101:H101) -> 15022.49 | H101: 15022.49
B102: Interior Framing / Partitions | D102: =SUM(F102:H102) -> 42580.32 | H102: 42580.32
B103: Painting | D103: =SUM(F103:H103) -> 17847.95 | H103: 17847.95
... B108: Cabinets / Millwork - Restrooms | D108: =SUM(F108:H108) -> 4062.57 | H108: 4062.57
B109: Total Building Cost | D109: =SUM(D80:D108) -> 440367.63 | F109: =SUM(F80:F108) -> 91523.65 | H109: =SUM(H80:H108) -> 348843.98
B110: % of Cost | F110: =F109/D109 -> 0.20783464 | H110: =H109/D109 -> 0.79216536
A112: ASSET ALLOCATION (per After Cost Segregation schedule)
B113: Asset (as reclassified) | D113: Cost | F113: 5 Year | H113: 27.5 Year
...

Sheet K
A1: Macedonia Apartments LLC
A2: Macedonia Apartments — 1722 W 17th St, Panama City, FL 32405
A3: EIN: 27-3618924 · FYE: December 31, 2024 · Year of Change: 1/1/2024
A4: K — Attachment to Form 3115 (DCN #7, Rev. Proc. 2024-23 §6.01)
A5: Source: CSSI Report #107752-05, "#107752-05_Macedonia Apartments, LLC - 3115 - combined R1.pdf"
A7: CALCULATION OF §481(a) ADJUSTMENT — REGULAR TAX
A8: As Previously Filed
A9: Asset | B9: Property Description | C9: Date In Service | D9: Cost | E9: Sec 179 Exp | F9: Bonus Amt | G9: Tax Prior Depreciation | H9: Tax Current Depreciation | I9: End Depreciation | J9: Net Book Value | K9: Method | L9: Period
A10: 1 | B10: Building - Apt | C10: 5/12/11 | D10: 78702.11 | E10: 0 | F10: 0 | G10: 26906.11 | H10: 2861.64 | I10: =G10+H10 -> 29767.75 | J10: =D10-I10 -> 48934.36 | K10: S/L | L10: 27.5
A11: 2 | B11: Building Improvements - Apt | C11: 5/31/22 | D11: 242524.3 | E11: 0 | F11: 0 | G11: 14330.78 | H11: 8818.19 | I11: =G11+H11 -> 23148.97 | J11: =D11-I11 -> 219375.33 | K11: S/L | L11: 27.5
A12: 3 | B12: Building Improvements - Apt | C12: 7/01/23 | D12: 1320.88 | E12: 0 | F12: 0 | G12: 21.99 | H12: 48.05 | I12: =G12+H12 -> 70.04 | J12: =D12-I12 -> 1250.84 | K12: S/L | L12: 27.5
A13: 4 | B13: Land Improvements - Apt | C13: 5/12/11 | D13: 19276.47 | E13: 0 | F13: 12548.91 | G13: 12548.91 | H13: 1139.24 | I13: =G13+H13 -> 13688.15 | J13: =D13-I13 -> 5588.32 | K13: 150DB | L13: 15.0
A14: 5 | B14: Land Improvements - Apt | C14: 5/31/22 | D14: 38775.76 | E14: 0 | F14: 38775.76 | G14: 38775.76 | H14: 0 | I14: =G14+H14 -> 38775.76 | J14: =D14-I14 -> 0 | K14: 150DB | L14: 15.0
A15: 6 | B15: Equipment - Apt | C15: 5/31/22 | D15: 59768.11 | E15: 0 | F15: 59768.11 | G15: 59768.11 | H15: 0 | I15: =G15+H15 -> 59768.11 | J15: =D15-I15 -> 0 | K15: 200DB | L15: 5.0
B16: Grand Total | D16: =SUM(D10:D15) -> 440367.63 | E16: =SUM(E10:E15) -> 0 | F16: =SUM(F10:F15) -> 111092.78 | G16: =SUM(G10:G15) -> 152351.66 | H16: =SUM(H10:H15) -> 12867.12 | I16: =SUM(I10:I15) -> 165218.78 | J16: =SUM(J10:J15) -> 275148.85
A18: After Cost Segregation Correction
A19: Asset | B19: Property Description | C19: Date In Service | D19: Cost | E19: Sec 179 Exp | F19: Bonus Amt | G19: Tax Prior Depreciation | H19: Tax Current Depreciation | I19: End Depreciation | J19: Net Book Value | K19: Method | L19: Period
A20: 1 | B20: Building - Apt - 5yr | C20: 5/12/11 | D20: 16357.03 | E20: 0 | F20: 0 | G20: 16357.03 | H20: 0 | I20: =G20+H20 -> 16357.03 | J20: =D20-I20 -> 0 | K20: 200DB | L20: 5.0
A21: 2 | B21: Building - Apt - 27.5yr | C21: 5/12/11 | D21: 62345.08 | E21: 0 | F21: 0 | G21: 28622.01 | H21: 2267.09 | I21: =G21+H21 -> 30889.1 | J21: =D21-I21 -> 31455.98 | K21: S/L | L21: 27.5
A22: 3 | B22: Building Improvements - Apt - 5yr | C22: 5/31/22 | D22: 50404.95 | E22: 0 | F22: 50404.95 | G22: 50404.95 | H22: 0 | I22: =G22+H22 -> 50404.95 | J22: =D22-I22 -> 0 | K22: 200DB | L22: 5.0
A23: 4 | B23: Building Improvements - Apt - 27.5yr | C23: 5/31/22 | D23: 192119.35 | E23: 0 | F23: 0 | G23: 11352.51 | H23: 6986.16 | I23: =G23+H23 -> 18338.67 | J23: =D23-I23 -> 173780.68 | K23: S/L | L23: 27.5
A24: 5 | B24: Building Improvements - Apt - 5yr | C24: 7/01/23 | D24: 274.52 | E24: 0 | F24: 219.62 | G24: 230.6 | H24: 17.57 | I24: =G24+H24 -> 248.17 | J24: =D24-I24 -> 26.35 | K24: 200DB | L24: 5.0
A25: 6 | B25: Building Improvements - Apt - 27.5yr | C25: 7/01/23 | D25: 1046.36 | E25: 0 | F25: 0 | G25: 17.44 | H25: 38.05 | I25: =G25+H25 -> 55.49 | J25: =D25-I25 -> 990.87 | K25: S/L | L25: 27.5
A26: 7 | B26: Land Improvements - Apt - 5yr | C26: 5/12/11 | D26: 4006.32 | E26: 0 | F26: 4006.32 | G26: 4006.32 | H26: 0 | I26: =G26+H26 -> 4006.32 | J26: =D26-I26 -> 0 | K26: 200DB | L26: 5.0
A27: 8 | B27: Land Improvements - Apt - 27.5yr | C27: 5/12/11 | D27: 15270.15 | E27: 0 | F27: 0 | G27: 7010.41 | H27: 555.28 | I27: =G27+H27 -> 7565.69 | J27: =D27-I27 -> 7704.46 | K27: S/L | L27: 27.5
A28: 9 | B28: Land Improvements - Apt - 5yr | C28: 5/31/22 | D28: 8058.95 | E28: 0 | F28: 8058.95 | G28: 8058.95 | H28: 0 | I28: =G28+H28 -> 8058.95 | J28: =D28-I28 -> 0 | K28: 200DB | L28: 5.0
A29: 10 | B29: Land Improvements - Apt - 27.5yr | C29: 5/31/22 | D29: 30716.81 | E29: 0 | F29: 0 | G29: 1815.08 | H29: 1116.97 | I29: =G29+H29 -> 2932.05 | J29: =D29-I29 -> 27784.76 | K29: S/L | L29: 27.5
A30: 11 | B30: Equipment - Apt - 5yr | C30: 5/31/22 | D30: 12421.88 | E30: 0 | F30: 12421.88 | G30: 12421.88 | H30: 0 | I30: =G30+H30 -> 12421.88 | J30: =D30-I30 -> 0 | K30: 200DB | L30: 5.0
A31: 12 | B31: Equipment - Apt - 27.5yr | C31: 5/31/22 | D31: 47346.23 | E31: 0 | F31: 0 | G31: 2797.73 | H31: 1721.68 | I31: =G31+H31 -> 4519.41 | J31: =D31-I31 -> 42826.82 | K31: S/L | L31: 27.5
B32: Grand Total | D32: =SUM(D20:D31) -> 440367.63 | E32: =SUM(E20:E31) -> 0 | F32: =SUM(F20:F31) -> 75111.72 | G32: =SUM(G20:G31) -> 143094.91 | H32: =SUM(H20:H31) -> 12702.8 | I32: =SUM(I20:I31) -> 155797.71 | J32: =SUM(J20:J31) -> 284569.92
B34: Section 481(a) Adjustment — Regular Tax
B35: Depreciation reported previously | D35: =I16 -> 165218.78
B36: Cost Segregation Corrected Depreciation | D36: =I32 -> 155797.71
B37: Section 481(a) Adjustment — Regular Tax | D37: =D35-D36 -> 9421.07
A39: CALCULATION OF §481(a) ADJUSTMENT — AMT
A40: As Previously Filed — AMT
A41: Asset | B41: Property Description | C41: Date In Service | D41: Cost | E41: Sec 179 Exp | F41: Bonus Amt | G41: AMT Prior Depreciation | H41: AMT Current Depreciation | I41: End Depreciation | J41: Net Book Value | K41: Method | L41: Period
A42: 1 | B42: Building - Apt | C42: 5/12/11 | D42: 78702.11 | E42: 0 | F42: 0 | G42: 26906.11 | H42: 2861.64 | I42: =G42+H42 -> 29767.75 | J42: =D42-I42 -> 48934.36 | K42: S/L | L42: 27.5
A43: 2 | B43: Building Improvements - Apt | C43: 5/31/22 | D43: 242524.3 | E43: 0 | F43: 0 | G43: 14330.78 | H43: 8818.19 | I43: =G43+H43 -> 23148.97 | J43: =D43-I43 -> 219375.33 | K43: S/L | L43: 27.5
A44: 3 | B44: Building Improvements - Apt | C44: 7/01/23 | D44: 1320.88 | E44: 0 | F44: 0 | G44: 21.99 | H44: 48.05 | I44: =G44+H44 -> 70.04 | J44: =D44-I44 -> 1250.84 | K44: S/L | L44: 27.5
A45: 4 | B45: Land Improvements - Apt | C45: 5/12/11 | D45: 19276.47 | E45: 0 | F45: 12548.91 | G45: 12548.91 | H45: 1139.24 | I45: =G45+H45 -> 13688.15 | J45: =D45-I45 -> 5588.32 | K45: 150DB | L45: 15.0
A46: 5 | B46: Land Improvements - Apt | C46: 5/31/22 | D46: 38775.76 | E46: 0 | F46: 38775.76 | G46: 38775.76 | H46: 0 | I46: =G46+H46 -> 38775.76 | J46: =D46-I46 -> 0 | K46: 150DB | L46: 15.0
A47: 6 | B47: Equipment - Apt | C47: 5/31/22 | D47: 59768.11 | E47: 0 | F47: 59768.11 | G47: 59768.11 | H47: 0 | I47: =G47+H47 -> 59768.11 | J47: =D47-I47 -> 0 | K47: 200DB | L47: 5.0
B48: Grand Total | D48: =SUM(D42:D47) -> 440367.63 | E48: =SUM(E42:E47) -> 0 | F48: =SUM(F42:F47) -> 111092.78 | G48: =SUM(G42:G47) -> 152351.66 | H48: =SUM(H42:H47) -> 12867.12 | I48: =SUM(I42:I47) -> 165218.78 | J48: =SUM(J42:J47) -> 275148.85
A50: After Cost Segregation Correction — AMT
A51: Asset | B51: Property Description | C51: Date In Service | D51: Cost | E51: Sec 179 Exp | F51: Bonus Amt | G51: AMT Prior Depreciation | H51: AMT Current Depreciation | I51: End Depreciation | J51: Net Book Value | K51: Method | L51: Period
A52: 1 | B52: Building - Apt - 5yr | C52: 5/12/11 | D52: 16357.03 | E52: 0 | F52: 0 | G52: 16357.03 | H52: 0 | I52: =G52+H52 -> 16357.03 | J52: =D52-I52 -> 0 | K52: 200DB | L52: 5.0
A53: 2 | B53: Building - Apt - 27.5yr | C53: 5/12/11 | D53: 62345.08 | E53: 0 | F53: 0 | G53: 28622.01 | H53: 2267.09 | I53: =G53+H53 -> 30889.1 | J53: =D53-I53 -> 31455.98 | K53: S/L | L53: 27.5
A54: 3 | B54: Building Improvements - Apt - 5yr | C54: 5/31/22 | D54: 50404.95 | E54: 0 | F54: 50404.95 | G54: 50404.95 | H54: 0 | I54: =G54+H54 -> 50404.95 | J54: =D54-I54 -> 0 | K54: 200DB | L54: 5.0
A55: 4 | B55: Building Improvements - Apt - 27.5yr | C55: 5/31/22 | D55: 192119.35 | E55: 0 | F55: 0 | G55: 11352.51 | H55: 6986.16 | I55: =G55+H55 -> 18338.67 | J55: =D55-I55 -> 173780.68 | K55: S/L | L55: 27.5
A56: 5 | B56: Building Improvements - Apt - 5yr | C56: 7/01/23 | D56: 274.52 | E56: 0 | F56: 219.62 | G56: 230.6 | H56: 17.57 | I56: =G56+H56 -> 248.17 | J56: =D56-I56 -> 26.35 | K56: 200DB | L56: 5.0
A57: 6 | B57: Building Improvements - Apt - 27.5yr | C57: 7/01/23 | D57: 1046.36 | E57: 0 | F57: 0 | G57: 17.44 | H57: 38.05 | I57: =G57+H57 -> 55.49 | J57: =D57-I57 -> 990.87 | K57: S/L | L57: 27.5
A58: 7 | B58: Land Improvements - Apt - 5yr | C58: 5/12/11 | D58: 4006.32 | E58: 0 | F58: 4006.32 | G58: 4006.32 | H58: 0 | I58: =G58+H58 -> 4006.32 | J58: =D58-I58 -> 0 | K58: 200DB | L58: 5.0
A59: 8 | B59: Land Improvements - Apt - 27.5yr | C59: 5/12/11 | D59: 15270.15 | E59: 0 | F59: 0 | G59: 7010.41 | H59: 555.28 | I59: =G59+H59 -> 7565.69 | J59: =D59-I59 -> 7704.46 | K59: S/L | L59: 27.5
A60: 9 | B60: Land Improvements - Apt - 5yr | C60: 5/31/22 | D60: 8058.95 | E60: 0 | F60: 8058.95 | G60: 8058.95 | H60: 0 | I60: =G60+H60 -> 8058.95 | J60: =D60-I60 -> 0 | K60: 200DB | L60: 5.0
A61: 10 | B61: Land Improvements - Apt - 27.5yr | C61: 5/31/22 | D61: 30716.81 | E61: 0 | F61: 0 | G61: 1815.08 | H61: 1116.97 | I61: =G61+H61 -> 2932.05 | J61: =D61-I61 -> 27784.76 | K61: S/L | L61: 27.5
A62: 11 | B62: Equipment - Apt - 5yr | C62: 5/31/22 | D62: 12421.88 | E62: 0 | F62: 12421.88 | G62: 12421.88 | H62: 0 | I62: =G62+H62 -> 12421.88 | J62: =D62-I62 -> 0 | K62: 200DB | L62: 5.0
A63: 12 | B63: Equipment - Apt - 27.5yr | C63: 5/31/22 | D63: 47346.23 | E63: 0 | F63: 0 | G63: 2797.73 | H63: 1721.68 | I63: =G63+H63 -> 4519.41 | J63: =D63-I63 -> 42826.82 | K63: S/L | L63: 27.5
B64: Grand Total | D64: =SUM(D52:D63) -> 440367.63 | E64: =SUM(E52:E63) -> 0 | F64: =SUM(F52:F63) -> 75111.72 | G64: =SUM(G52:G63) -> 143094.91 | H64: =SUM(H52:H63) -> 12702.8 | I64: =SUM(I52:I63) -> 155797.71 | J64: =SUM(J52:J63) -> 284569.92
B66: Section 481(a) Adjustment — AMT
B67: Depreciation reported previously | D67: =I48 -> 165218.78
B68: Cost Segregation Corrected Depreciation | D68: =I64 -> 155797.71
B69: Section 481(a) Adjustment — AMT | D69: =D67-D68 -> 9421.07
A71: COST SEGREGATION STUDY — COST SUMMARY
B72: Total Building Cost | D72: =D109 -> 440367.63
B73: Building Components: 5 Year | D73: =F109 -> 91523.65
B74: % of Cost | D74: =F110 -> 0.20783464
B75: Building Structure: 27.5 Year | D75: =H109 -> 348843.98
B76: % of Cost | D76: =H110 -> 0.79216536
A78: COST SEGREGATION STUDY — COST DETAIL
B79: Property Category | D79: Cost | F79: 5 Year | H79: 27.5 Year
B80: Building Components
B81: Cabinets / Millwork | D81: =SUM(F81:H81) -> 14219.24 | F81: 14219.24
B82: Moldings | D82: =SUM(F82:H82) -> 9652.73 | F82: 9652.73
B83: Flooring - Vinyl Plank | D83: =SUM(F83:H83) -> 33731.06 | F83: 33731.06
B84: Window Treatments | D84: =SUM(F84:H84) -> 3552.78 | F84: 3552.78
B85: Building Signage | D85: =SUM(F85:H85) -> 297.35 | F85: 297.35
B86: Specialty Electrical - Appliances | D86: =SUM(F86:H86) -> 5540.41 | F86: 5540.41
B87: Communication / Data | D87: =SUM(F87:H87) -> 2668.77 | F87: 2668.77
B88: Specialty Plumbing - Kitchen Sinks | D88: =SUM(F88:H88) -> 11469.05 | F88: 11469.05
B89: Security / Exterior Lighting | D89: =SUM(F89:H89) -> 886.65 | F89: 886.65
B90: Appliances | D90: =SUM(F90:H90) -> 9505.61 | F90: 9505.61
B91: Building Structure
B92: Roofing Systems | D92: =SUM(F92:H92) -> 19629.66 | H92: 19629.66
B93: Foundations | D93: =SUM(F93:H93) -> 23418.11 | H93: 23418.11
B94: HVAC | D94: =SUM(F94:H94) -> 33997.34 | H94: 33997.34
B95: Electrical | D95: =SUM(F95:H95) -> 26926.59 | H95: 26926.59
B96: Plumbing | D96: =SUM(F96:H96) -> 29553.7 | H96: 29553.7
B97: Fire Protection & Alarm | D97: =SUM(F97:H97) -> 1932.7 | H97: 1932.7
B98: Exterior Façade / Building Skin | D98: =SUM(F98:H98) -> 21649.45 | H98: 21649.45
B99: Doors & Frames | D99: =SUM(F99:H99) -> 18392.87 | H99: 18392.87
B100: Windows | D100: =SUM(F100:H100) -> 15659.18 | H100: 15659.18
B101: Ceiling Systems | D101: =SUM(F101:H101) -> 15022.49 | H101: 15022.49
B102: Interior Framing / Partitions | D102: =SUM(F102:H102) -> 42580.32 | H102: 42580.32
B103: Painting | D103: =SUM(F103:H103) -> 17847.95 | H103: 17847.95
... B108: Cabinets / Millwork - Restrooms | D108: =SUM(F108:H108) -> 4062.57 | H108: 4062.57
B109: Total Building Cost | D109: =SUM(D80:D108) -> 440367.63 | F109: =SUM(F80:F108) -> 91523.65 | H109: =SUM(H80:H108) -> 348843.98
B110: % of Cost | F110: =F109/D109 -> 0.20783464 | H110: =H109/D109 -> 0.79216536
A112: ASSET ALLOCATION (per After Cost Segregation schedule)
B113: Asset (as reclassified) | D113: Cost | F113: 5 Year | H113: 27.5 Year
...

Sheet L
A1: Macedonia Apartments LLC
A2: Macedonia Apartments — 1722 W 17th St, Panama City, FL 32405
A3: EIN: 27-3618924 · FYE: December 31, 2024 · Year of Change: 1/1/2024
A4: L — Attachment to Form 3115 (DCN #7, Rev. Proc. 2024-23 §6.01)
A5: Source: CSSI Report #107752-05, "#107752-05_Macedonia Apartments, LLC - 3115 - combined R1.pdf"
A7: CALCULATION OF §481(a) ADJUSTMENT — REGULAR TAX
A8: As Previously Filed
A9: Asset | B9: Property Description | C9: Date In Service | D9: Cost | E9: Sec 179 Exp | F9: Bonus Amt | G9: Tax Prior Depreciation | H9: Tax Current Depreciation | I9: End Depreciation | J9: Net Book Value | K9: Method | L9: Period
A10: 1 | B10: Building - Apt | C10: 5/12/11 | D10: 78702.11 | E10: 0 | F10: 0 | G10: 26906.11 | H10: 2861.64 | I10: =G10+H10 -> 29767.75 | J10: =D10-I10 -> 48934.36 | K10: S/L | L10: 27.5
A11: 2 | B11: Building Improvements - Apt | C11: 5/31/22 | D11: 242524.3 | E11: 0 | F11: 0 | G11: 14330.78 | H11: 8818.19 | I11: =G11+H11 -> 23148.97 | J11: =D11-I11 -> 219375.33 | K11: S/L | L11: 27.5
A12: 3 | B12: Building Improvements - Apt | C12: 7/01/23 | D12: 1320.88 | E12: 0 | F12: 0 | G12: 21.99 | H12: 48.05 | I12: =G12+H12 -> 70.04 | J12: =D12-I12 -> 1250.84 | K12: S/L | L12: 27.5
A13: 4 | B13: Land Improvements - Apt | C13: 5/12/11 | D13: 19276.47 | E13: 0 | F13: 12548.91 | G13: 12548.91 | H13: 1139.24 | I13: =G13+H13 -> 13688.15 | J13: =D13-I13 -> 5588.32 | K13: 150DB | L13: 15.0
A14: 5 | B14: Land Improvements - Apt | C14: 5/31/22 | D14: 38775.76 | E14: 0 | F14: 38775.76 | G14: 38775.76 | H14: 0 | I14: =G14+H14 -> 38775.76 | J14: =D14-I14 -> 0 | K14: 150DB | L14: 15.0
A15: 6 | B15: Equipment - Apt | C15: 5/31/22 | D15: 59768.11 | E15: 0 | F15: 59768.11 | G15: 59768.11 | H15: 0 | I15: =G15+H15 -> 59768.11 | J15: =D15-I15 -> 0 | K15: 200DB | L15: 5.0
B16: Grand Total | D16: =SUM(D10:D15) -> 440367.63 | E16: =SUM(E10:E15) -> 0 | F16: =SUM(F10:F15) -> 111092.78 | G16: =SUM(G10:G15) -> 152351.66 | H16: =SUM(H10:H15) -> 12867.12 | I16: =SUM(I10:I15) -> 165218.78 | J16: =SUM(J10:J15) -> 275148.85
A18: After Cost Segregation Correction
A19: Asset | B19: Property Description | C19: Date In Service | D19: Cost | E19: Sec 179 Exp | F19: Bonus Amt | G19: Tax Prior Depreciation | H19: Tax Current Depreciation | I19: End Depreciation | J19: Net Book Value | K19: Method | L19: Period
A20: 1 | B20: Building - Apt - 5yr | C20: 5/12/11 | D20: 16357.03 | E20: 0 | F20: 0 | G20: 16357.03 | H20: 0 | I20: =G20+H20 -> 16357.03 | J20: =D20-I20 -> 0 | K20: 200DB | L20: 5.0
A21: 2 | B21: Building - Apt - 27.5yr | C21: 5/12/11 | D21: 62345.08 | E21: 0 | F21: 0 | G21: 28622.01 | H21: 2267.09 | I21: =G21+H21 -> 30889.1 | J21: =D21-I21 -> 31455.98 | K21: S/L | L21: 27.5
A22: 3 | B22: Building Improvements - Apt - 5yr | C22: 5/31/22 | D22: 50404.95 | E22: 0 | F22: 50404.95 | G22: 50404.95 | H22: 0 | I22: =G22+H22 -> 50404.95 | J22: =D22-I22 -> 0 | K22: 200DB | L22: 5.0
A23: 4 | B23: Building Improvements - Apt - 27.5yr | C23: 5/31/22 | D23: 192119.35 | E23: 0 | F23: 0 | G23: 11352.51 | H23: 6986.16 | I23: =G23+H23 -> 18338.67 | J23: =D23-I23 -> 173780.68 | K23: S/L | L23: 27.5
A24: 5 | B24: Building Improvements - Apt - 5yr | C24: 7/01/23 | D24: 274.52 | E24: 0 | F24: 219.62 | G24: 230.6 | H24: 17.57 | I24: =G24+H24 -> 248.17 | J24: =D24-I24 -> 26.35 | K24: 200DB | L24: 5.0
A25: 6 | B25: Building Improvements - Apt - 27.5yr | C25: 7/01/23 | D25: 1046.36 | E25: 0 | F25: 0 | G25: 17.44 | H25: 38.05 | I25: =G25+H25 -> 55.49 | J25: =D25-I25 -> 990.87 | K25: S/L | L25: 27.5
A26: 7 | B26: Land Improvements - Apt - 5yr | C26: 5/12/11 | D26: 4006.32 | E26: 0 | F26: 4006.32 | G26: 4006.32 | H26: 0 | I26: =G26+H26 -> 4006.32 | J26: =D26-I26 -> 0 | K26: 200DB | L26: 5.0
A27: 8 | B27: Land Improvements - Apt - 27.5yr | C27: 5/12/11 | D27: 15270.15 | E27: 0 | F27: 0 | G27: 7010.41 | H27: 555.28 | I27: =G27+H27 -> 7565.69 | J27: =D27-I27 -> 7704.46 | K27: S/L | L27: 27.5
A28: 9 | B28: Land Improvements - Apt - 5yr | C28: 5/31/22 | D28: 8058.95 | E28: 0 | F28: 8058.95 | G28: 8058.95 | H28: 0 | I28: =G28+H28 -> 8058.95 | J28: =D28-I28 -> 0 | K28: 200DB | L28: 5.0
A29: 10 | B29: Land Improvements - Apt - 27.5yr | C29: 5/31/22 | D29: 30716.81 | E29: 0 | F29: 0 | G29: 1815.08 | H29: 1116.97 | I29: =G29+H29 -> 2932.05 | J29: =D29-I29 -> 27784.76 | K29: S/L | L29: 27.5
A30: 11 | B30: Equipment - Apt - 5yr | C30: 5/31/22 | D30: 12421.88 | E30: 0 | F30: 12421.88 | G30: 12421.88 | H30: 0 | I30: =G30+H30 -> 12421.88 | J30: =D30-I30 -> 0 | K30: 200DB | L30: 5.0
A31: 12 | B31: Equipment - Apt - 27.5yr | C31: 5/31/22 | D31: 47346.23 | E31: 0 | F31: 0 | G31: 2797.73 | H31: 1721.68 | I31: =G31+H31 -> 4519.41 | J31: =D31-I31 -> 42826.82 | K31: S/L | L31: 27.5
B32: Grand Total | D32: =SUM(D20:D31) -> 440367.63 | E32: =SUM(E20:E31) -> 0 | F32: =SUM(F20:F31) -> 75111.72 | G32: =SUM(G20:G31) -> 143094.91 | H32: =SUM(H20:H31) -> 12702.8 | I32: =SUM(I20:I31) -> 155797.71 | J32: =SUM(J20:J31) -> 284569.92
B34: Section 481(a) Adjustment — Regular Tax
B35: Depreciation reported previously | D35: =I16 -> 165218.78
B36: Cost Segregation Corrected Depreciation | D36: =I32 -> 155797.71
B37: Section 481(a) Adjustment — Regular Tax | D37: =D35-D36 -> 9421.07
A39: CALCULATION OF §481(a) ADJUSTMENT — AMT
A40: As Previously Filed — AMT
A41: Asset | B41: Property Description | C41: Date In Service | D41: Cost | E41: Sec 179 Exp | F41: Bonus Amt | G41: AMT Prior Depreciation | H41: AMT Current Depreciation | I41: End Depreciation | J41: Net Book Value | K41: Method | L41: Period
A42: 1 | B42: Building - Apt | C42: 5/12/11 | D42: 78702.11 | E42: 0 | F42: 0 | G42: 26906.11 | H42: 2861.64 | I42: =G42+H42 -> 29767.75 | J42: =D42-I42 -> 48934.36 | K42: S/L | L42: 27.5
A43: 2 | B43: Building Improvements - Apt | C43: 5/31/22 | D43: 242524.3 | E43: 0 | F43: 0 | G43: 14330.78 | H43: 8818.19 | I43: =G43+H43 -> 23148.97 | J43: =D43-I43 -> 219375.33 | K43: S/L | L43: 27.5
A44: 3 | B44: Building Improvements - Apt | C44: 7/01/23 | D44: 1320.88 | E44: 0 | F44: 0 | G44: 21.99 | H44: 48.05 | I44: =G44+H44 -> 70.04 | J44: =D44-I44 -> 1250.84 | K44: S/L | L44: 27.5
A45: 4 | B45: Land Improvements - Apt | C45: 5/12/11 | D45: 19276.47 | E45: 0 | F45: 12548.91 | G45: 12548.91 | H45: 1139.24 | I45: =G45+H45 -> 13688.15 | J45: =D45-I45 -> 5588.32 | K45: 150DB | L45: 15.0
A46: 5 | B46: Land Improvements - Apt | C46: 5/31/22 | D46: 38775.76 | E46: 0 | F46: 38775.76 | G46: 38775.76 | H46: 0 | I46: =G46+H46 -> 38775.76 | J46: =D46-I46 -> 0 | K46: 150DB | L46: 15.0
A47: 6 | B47: Equipment - Apt | C47: 5/31/22 | D47: 59768.11 | E47: 0 | F47: 59768.11 | G47: 59768.11 | H47: 0 | I47: =G47+H47 -> 59768.11 | J47: =D47-I47 -> 0 | K47: 200DB | L47: 5.0
B48: Grand Total | D48: =SUM(D42:D47) -> 440367.63 | E48: =SUM(E42:E47) -> 0 | F48: =SUM(F42:F47) -> 111092.78 | G48: =SUM(G42:G47) -> 152351.66 | H48: =SUM(H42:H47) -> 12867.12 | I48: =SUM(I42:I47) -> 165218.78 | J48: =SUM(J42:J47) -> 275148.85
A50: After Cost Segregation Correction — AMT
A51: Asset | B51: Property Description | C51: Date In Service | D51: Cost | E51: Sec 179 Exp | F51: Bonus Amt | G51: AMT Prior Depreciation | H51: AMT Current Depreciation | I51: End Depreciation | J51: Net Book Value | K51: Method | L51: Period
A52: 1 | B52: Building - Apt - 5yr | C52: 5/12/11 | D52: 16357.03 | E52: 0 | F52: 0 | G52: 16357.03 | H52: 0 | I52: =G52+H52 -> 16357.03 | J52: =D52-I52 -> 0 | K52: 200DB | L52: 5.0
A53: 2 | B53: Building - Apt - 27.5yr | C53: 5/12/11 | D53: 62345.08 | E53: 0 | F53: 0 | G53: 28622.01 | H53: 2267.09 | I53: =G53+H53 -> 30889.1 | J53: =D53-I53 -> 31455.98 | K53: S/L | L53: 27.5
A54: 3 | B54: Building Improvements - Apt - 5yr | C54: 5/31/22 | D54: 50404.95 | E54: 0 | F54: 50404.95 | G54: 50404.95 | H54: 0 | I54: =G54+H54 -> 50404.95 | J54: =D54-I54 -> 0 | K54: 200DB | L54: 5.0
A55: 4 | B55: Building Improvements - Apt - 27.5yr | C55: 5/31/22 | D55: 192119.35 | E55: 0 | F55: 0 | G55: 11352.51 | H55: 6986.16 | I55: =G55+H55 -> 18338.67 | J55: =D55-I55 -> 173780.68 | K55: S/L | L55: 27.5
A56: 5 | B56: Building Improvements - Apt - 5yr | C56: 7/01/23 | D56: 274.52 | E56: 0 | F56: 219.62 | G56: 230.6 | H56: 17.57 | I56: =G56+H56 -> 248.17 | J56: =D56-I56 -> 26.35 | K56: 200DB | L56: 5.0
A57: 6 | B57: Building Improvements - Apt - 27.5yr | C57: 7/01/23 | D57: 1046.36 | E57: 0 | F57: 0 | G57: 17.44 | H57: 38.05 | I57: =G57+H57 -> 55.49 | J57: =D57-I57 -> 990.87 | K57: S/L | L57: 27.5
A58: 7 | B58: Land Improvements - Apt - 5yr | C58: 5/12/11 | D58: 4006.32 | E58: 0 | F58: 4006.32 | G58: 4006.32 | H58: 0 | I58: =G58+H58 -> 4006.32 | J58: =D58-I58 -> 0 | K58: 200DB | L58: 5.0
A59: 8 | B59: Land Improvements - Apt - 27.5yr | C59: 5/12/11 | D59: 15270.15 | E59: 0 | F59: 0 | G59: 7010.41 | H59: 555.28 | I59: =G59+H59 -> 7565.69 | J59: =D59-I59 -> 7704.46 | K59: S/L | L59: 27.5
A60: 9 | B60: Land Improvements - Apt - 5yr | C60: 5/31/22 | D60: 8058.95 | E60: 0 | F60: 8058.95 | G60: 8058.95 | H60: 0 | I60: =G60+H60 -> 8058.95 | J60: =D60-I60 -> 0 | K60: 200DB | L60: 5.0
A61: 10 | B61: Land Improvements - Apt - 27.5yr | C61: 5/31/22 | D61: 30716.81 | E61: 0 | F61: 0 | G61: 1815.08 | H61: 1116.97 | I61: =G61+H61 -> 2932.05 | J61: =D61-I61 -> 27784.76 | K61: S/L | L61: 27.5
A62: 11 | B62: Equipment - Apt - 5yr | C62: 5/31/22 | D62: 12421.88 | E62: 0 | F62: 12421.88 | G62: 12421.88 | H62: 0 | I62: =G62+H62 -> 12421.88 | J62: =D62-I62 -> 0 | K62: 200DB | L62: 5.0
A63: 12 | B63: Equipment - Apt - 27.5yr | C63: 5/31/22 | D63: 47346.23 | E63: 0 | F63: 0 | G63: 2797.73 | H63: 1721.68 | I63: =G63+H63 -> 4519.41 | J63: =D63-I63 -> 42826.82 | K63: S/L | L63: 27.5
B64: Grand Total | D64: =SUM(D52:D63) -> 440367.63 | E64: =SUM(E52:E63) -> 0 | F64: =SUM(F52:F63) -> 75111.72 | G64: =SUM(G52:G63) -> 143094.91 | H64: =SUM(H52:H63) -> 12702.8 | I64: =SUM(I52:I63) -> 155797.71 | J64: =SUM(J52:J63) -> 284569.92
B66: Section 481(a) Adjustment — AMT
B67: Depreciation reported previously | D67: =I48 -> 165218.78
B68: Cost Segregation Corrected Depreciation | D68: =I64 -> 155797.71
B69: Section 481(a) Adjustment — AMT | D69: =D67-D68 -> 9421.07
A71: COST SEGREGATION STUDY — COST SUMMARY
B72: Total Building Cost | D72: =D109 -> 440367.63
B73: Building Components: 5 Year | D73: =F109 -> 91523.65
B74: % of Cost | D74: =F110 -> 0.20783464
B75: Building Structure: 27.5 Year | D75: =H109 -> 348843.98
B76: % of Cost | D76: =H110 -> 0.79216536
A78: COST SEGREGATION STUDY — COST DETAIL
B79: Property Category | D79: Cost | F79: 5 Year | H79: 27.5 Year
B80: Building Components
B81: Cabinets / Millwork | D81: =SUM(F81:H81) -> 14219.24 | F81: 14219.24
B82: Moldings | D82: =SUM(F82:H82) -> 9652.73 | F82: 9652.73
B83: Flooring - Vinyl Plank | D83: =SUM(F83:H83) -> 33731.06 | F83: 33731.06
B84: Window Treatments | D84: =SUM(F84:H84) -> 3552.78 | F84: 3552.78
B85: Building Signage | D85: =SUM(F85:H85) -> 297.35 | F85: 297.35
B86: Specialty Electrical - Appliances | D86: =SUM(F86:H86) -> 5540.41 | F86: 5540.41
B87: Communication / Data | D87: =SUM(F87:H87) -> 2668.77 | F87: 2668.77
B88: Specialty Plumbing - Kitchen Sinks | D88: =SUM(F88:H88) -> 11469.05 | F88: 11469.05
B89: Security / Exterior Lighting | D89: =SUM(F89:H89) -> 886.65 | F89: 886.65
B90: Appliances | D90: =SUM(F90:H90) -> 9505.61 | F90: 9505.61
B91: Building Structure
B92: Roofing Systems | D92: =SUM(F92:H92) -> 19629.66 | H92: 19629.66
B93: Foundations | D93: =SUM(F93:H93) -> 23418.11 | H93: 23418.11
B94: HVAC | D94: =SUM(F94:H94) -> 33997.34 | H94: 33997.34
B95: Electrical | D95: =SUM(F95:H95) -> 26926.59 | H95: 26926.59
B96: Plumbing | D96: =SUM(F96:H96) -> 29553.7 | H96: 29553.7
B97: Fire Protection & Alarm | D97: =SUM(F97:H97) -> 1932.7 | H97: 1932.7
B98: Exterior Façade / Building Skin | D98: =SUM(F98:H98) -> 21649.45 | H98: 21649.45
B99: Doors & Frames | D99: =SUM(F99:H99) -> 18392.87 | H99: 18392.87
B100: Windows | D100: =SUM(F100:H100) -> 15659.18 | H100: 15659.18
B101: Ceiling Systems | D101: =SUM(F101:H101) -> 15022.49 | H101: 15022.49
B102: Interior Framing / Partitions | D102: =SUM(F102:H102) -> 42580.32 | H102: 42580.32
B103: Painting | D103: =SUM(F103:H103) -> 17847.95 | H103: 17847.95
... B108: Cabinets / Millwork - Restrooms | D108: =SUM(F108:H108) -> 4062.57 | H108: 4062.57
B109: Total Building Cost | D109: =SUM(D80:D108) -> 440367.63 | F109: =SUM(F80:F108) -> 91523.65 | H109: =SUM(H80:H108) -> 348843.98
B110: % of Cost | F110: =F109/D109 -> 0.20783464 | H110: =H109/D109 -> 0.79216536
A112: ASSET ALLOCATION (per After Cost Segregation schedule)
B113: Asset (as reclassified) | D113: Cost | F113: 5 Year | H113: 27.5 Year
...

Sheet M
A1: Macedonia Apartments LLC
A2: Macedonia Apartments — 1722 W 17th St, Panama City, FL 32405
A3: EIN: 27-3618924 · FYE: December 31, 2024 · Year of Change: 1/1/2024
A4: M — Attachment to Form 3115 (DCN #7, Rev. Proc. 2024-23 §6.01)
A5: Source: CSSI Report #107752-05, "#107752-05_Macedonia Apartments, LLC - 3115 - combined R1.pdf"
A7: CALCULATION OF §481(a) ADJUSTMENT — REGULAR TAX
A8: As Previously Filed
A9: Asset | B9: Property Description | C9: Date In Service | D9: Cost | E9: Sec 179 Exp | F9: Bonus Amt | G9: Tax Prior Depreciation | H9: Tax Current Depreciation | I9: End Depreciation | J9: Net Book Value | K9: Method | L9: Period
A10: 1 | B10: Building - Apt | C10: 5/12/11 | D10: 78702.11 | E10: 0 | F10: 0 | G10: 26906.11 | H10: 2861.64 | I10: =G10+H10 -> 29767.75 | J10: =D10-I10 -> 48934.36 | K10: S/L | L10: 27.5
A11: 2 | B11: Building Improvements - Apt | C11: 5/31/22 | D11: 242524.3 | E11: 0 | F11: 0 | G11: 14330.78 | H11: 8818.19 | I11: =G11+H11 -> 23148.97 | J11: =D11-I11 -> 219375.33 | K11: S/L | L11: 27.5
A12: 3 | B12: Building Improvements - Apt | C12: 7/01/23 | D12: 1320.88 | E12: 0 | F12: 0 | G12: 21.99 | H12: 48.05 | I12: =G12+H12 -> 70.04 | J12: =D12-I12 -> 1250.84 | K12: S/L | L12: 27.5
A13: 4 | B13: Land Improvements - Apt | C13: 5/12/11 | D13: 19276.47 | E13: 0 | F13: 12548.91 | G13: 12548.91 | H13: 1139.24 | I13: =G13+H13 -> 13688.15 | J13: =D13-I13 -> 5588.32 | K13: 150DB | L13: 15.0
A14: 5 | B14: Land Improvements - Apt | C14: 5/31/22 | D14: 38775.76 | E14: 0 | F14: 38775.76 | G14: 38775.76 | H14: 0 | I14: =G14+H14 -> 38775.76 | J14: =D14-I14 -> 0 | K14: 150DB | L14: 15.0
A15: 6 | B15: Equipment - Apt | C15: 5/31/22 | D15: 59768.11 | E15: 0 | F15: 59768.11 | G15: 59768.11 | H15: 0 | I15: =G15+H15 -> 59768.11 | J15: =D15-I15 -> 0 | K15: 200DB | L15: 5.0
B16: Grand Total | D16: =SUM(D10:D15) -> 440367.63 | E16: =SUM(E10:E15) -> 0 | F16: =SUM(F10:F15) -> 111092.78 | G16: =SUM(G10:G15) -> 152351.66 | H16: =SUM(H10:H15) -> 12867.12 | I16: =SUM(I10:I15) -> 165218.78 | J16: =SUM(J10:J15) -> 275148.85
A18: After Cost Segregation Correction
A19: Asset | B19: Property Description | C19: Date In Service | D19: Cost | E19: Sec 179 Exp | F19: Bonus Amt | G19: Tax Prior Depreciation | H19: Tax Current Depreciation | I19: End Depreciation | J19: Net Book Value | K19: Method | L19: Period
A20: 1 | B20: Building - Apt - 5yr | C20: 5/12/11 | D20: 16357.03 | E20: 0 | F20: 0 | G20: 16357.03 | H20: 0 | I20: =G20+H20 -> 16357.03 | J20: =D20-I20 -> 0 | K20: 200DB | L20: 5.0
A21: 2 | B21: Building - Apt - 27.5yr | C21: 5/12/11 | D21: 62345.08 | E21: 0 | F21: 0 | G21: 28622.01 | H21: 2267.09 | I21: =G21+H21 -> 30889.1 | J21: =D21-I21 -> 31455.98 | K21: S/L | L21: 27.5
A22: 3 | B22: Building Improvements - Apt - 5yr | C22: 5/31/22 | D22: 50404.95 | E22: 0 | F22: 50404.95 | G22: 50404.95 | H22: 0 | I22: =G22+H22 -> 50404.95 | J22: =D22-I22 -> 0 | K22: 200DB | L22: 5.0
A23: 4 | B23: Building Improvements - Apt - 27.5yr | C23: 5/31/22 | D23: 192119.35 | E23: 0 | F23: 0 | G23: 11352.51 | H23: 6986.16 | I23: =G23+H23 -> 18338.67 | J23: =D23-I23 -> 173780.68 | K23: S/L | L23: 27.5
A24: 5 | B24: Building Improvements - Apt - 5yr | C24: 7/01/23 | D24: 274.52 | E24: 0 | F24: 219.62 | G24: 230.6 | H24: 17.57 | I24: =G24+H24 -> 248.17 | J24: =D24-I24 -> 26.35 | K24: 200DB | L24: 5.0
A25: 6 | B25: Building Improvements - Apt - 27.5yr | C25: 7/01/23 | D25: 1046.36 | E25: 0 | F25: 0 | G25: 17.44 | H25: 38.05 | I25: =G25+H25 -> 55.49 | J25: =D25-I25 -> 990.87 | K25: S/L | L25: 27.5
A26: 7 | B26: Land Improvements - Apt - 5yr | C26: 5/12/11 | D26: 4006.32 | E26: 0 | F26: 4006.32 | G26: 4006.32 | H26: 0 | I26: =G26+H26 -> 4006.32 | J26: =D26-I26 -> 0 | K26: 200DB | L26: 5.0
A27: 8 | B27: Land Improvements - Apt - 27.5yr | C27: 5/12/11 | D27: 15270.15 | E27: 0 | F27: 0 | G27: 7010.41 | H27: 555.28 | I27: =G27+H27 -> 7565.69 | J27: =D27-I27 -> 7704.46 | K27: S/L | L27: 27.5
A28: 9 | B28: Land Improvements - Apt - 5yr | C28: 5/31/22 | D28: 8058.95 | E28: 0 | F28: 8058.95 | G28: 8058.95 | H28: 0 | I28: =G28+H28 -> 8058.95 | J28: =D28-I28 -> 0 | K28: 200DB | L28: 5.0
A29: 10 | B29: Land Improvements - Apt - 27.5yr | C29: 5/31/22 | D29: 30716.81 | E29: 0 | F29: 0 | G29: 1815.08 | H29: 1116.97 | I29: =G29+H29 -> 2932.05 | J29: =D29-I29 -> 27784.76 | K29: S/L | L29: 27.5
