Workbook

Sheet Summary
A1: Marrero 3 LP
A2: Marrero 3 — 530 Ames Blvd, Marrero, LA 70072
A3: EIN: 82-2324040 · FYE: December 31, 2024 · Year of Change: 1/1/2024
A4: Summary of Cost Segregation Adjustments — CSSI Report #107752-18 (CAM — DCN #7)
A7: Acq Date | B7: Asset Description | C7: Total | D7: 530 Ames | E7: 540 Freedom | F7: 1208 Smith | G7: 1209 Smith | H7: 3112 Havenwood | I7: 3117 Barbwood | J7: 6805 Sayres | K7: 6800 Sayres | L7: 7112 Kayla | M7: 7141 Kayla
A8: 12/08/17 | B8: 17 - Land Improvements - Ames | C8: =SUM(D8:M8) -> 127145 | D8: ='530 Ames'!$D$10 -> 121057 | E8: ='540 Freedom'!$D$10 -> 6088
A9: 12/08/17 | B9: 18 - Buidling - Ames | C9: =SUM(D9:M9) -> 1652880 | D9: ='530 Ames'!$D$11 -> 1573731 | E9: ='540 Freedom'!$D$11 -> 79149
A10: 12/08/17 | B10: 19 - Equpiment - Ames | C10: =SUM(D10:M10) -> 339052 | D10: ='530 Ames'!$D$12 -> 322816 | E10: ='540 Freedom'!$D$12 -> 16236
A11: 12/08/17 | B11: 12 - Land Improvements - Smith Square | C11: =SUM(D11:M11) -> 52733 | F11: ='1208 Smith'!$D$10 -> 43832 | G11: ='1209 Smith'!$D$10 -> 8901
A12: 12/08/17 | B12: 13 - Buidling - Smith Square | C12: =SUM(D12:M12) -> 685526 | F12: ='1208 Smith'!$D$11 -> 569814 | G12: ='1209 Smith'!$D$11 -> 115712
A13: 12/08/17 | B13: 14 - Equpiment - Smith Square | C13: =SUM(D13:M13) -> 140621 | F13: ='1208 Smith'!$D$12 -> 116885 | G13: ='1209 Smith'!$D$12 -> 23736
A14: 12/08/17 | B14: 2 - Land Improvements - Havenwood | C14: =SUM(D14:M14) -> 55121 | H14: ='3112 Havenwood'!$D$10 -> 47472 | I14: ='3117 Barbwood'!$D$10 -> 7649
A15: 12/08/17 | B15: 3 - Buidling - Havenwood | C15: =SUM(D15:M15) -> 716569 | H15: ='3112 Havenwood'!$D$11 -> 617127 | I15: ='3117 Barbwood'!$D$11 -> 99442
A16: 12/08/17 | B16: 4 - Equipment - Havenwood | C16: =SUM(D16:M16) -> 146988 | H16: ='3112 Havenwood'!$D$12 -> 126590 | I16: ='3117 Barbwood'!$D$12 -> 20398
A17: 1/09/18 | B17: 22 - Land Improvements - Gentry | C17: =SUM(D17:M17) -> 48962 | J17: ='6805 Sayres'!$D$10 -> 40887 | K17: ='6800 Sayres'!$D$10 -> 8075
A18: 1/29/18 | B18: 23 - Buidling - Gentry | C18: =SUM(D18:M18) -> 1354621 | J18: ='6805 Sayres'!$D$11 -> 1131216 | K18: ='6800 Sayres'!$D$11 -> 223405
A19: 1/29/18 | B19: 24 - Equipment - Gentry | C19: =SUM(D19:M19) -> 228490 | J19: ='6805 Sayres'!$D$12 -> 190807 | K19: ='6800 Sayres'!$D$12 -> 37683
A20: 12/08/17 | B20: 7 - Land Improvements - Kayla | C20: =SUM(D20:M20) -> 98354 | L20: ='7112 Kayla'!$D$10 -> 80244 | M20: ='7141 Kayla'!$D$10 -> 18110
A21: 12/08/17 | B21: 8 - Buidling - Kayla | C21: =SUM(D21:M21) -> 1278607 | L21: ='7112 Kayla'!$D$11 -> 1043171 | M21: ='7141 Kayla'!$D$11 -> 235436
A22: 12/08/17 | B22: 9 - Equipment - Kayla | C22: =SUM(D22:M22) -> 262278 | L22: ='7112 Kayla'!$D$12 -> 213983 | M22: ='7141 Kayla'!$D$12 -> 48295
B23: Grand Total | C23: =SUM(C8:C22) -> 7187947 | D23: =SUM(D8:D22) -> 2017604 | E23: =SUM(E8:E22) -> 101473 | F23: =SUM(F8:F22) -> 730531 | G23: =SUM(G8:G22) -> 148349 | H23: =SUM(H8:H22) -> 791189 | I23: =SUM(I8:I22) -> 127489 | J23: =SUM(J8:J22) -> 1362910 | ... M23: =SUM(M8:M22) -> 301841
B25: MACRS Reclassification
A26: 12/08/17 | B26: 17 - Land Improvements - Ames - 5yr | C26: =SUM(D26:M26) -> 23248 | D26: ='530 Ames'!$D$17 -> 22198 | E26: ='540 Freedom'!$D$17 -> 1050
A27: 12/08/17 | B27: 17 - Land Improvements - Ames - 15yr | C27: =SUM(D27:M27) -> 99020 | D27: ='530 Ames'!$D$18+'530 Ames'!$D$19 -> 98858 | E27: ='540 Freedom'!$D$18 -> 162
A28: 12/08/17 | B28: 18 - Buidling - Ames - 5yr | C28: =SUM(D28:M28) -> 302225 | D28: ='530 Ames'!$D$20 -> 288575 | E28: ='540 Freedom'!$D$20 -> 13650
A29: 12/08/17 | B29: 18 - Buidling - Ames - 15yr | C29: =SUM(D29:M29) -> 28407 | D29: ='530 Ames'!$D$21 -> 26299 | E29: ='540 Freedom'!$D$21 -> 2108
A30: 12/08/17 | B30: 18 - Buidling - Ames - 27.5yr | C30: =SUM(D30:M30) -> 1322248 | D30: ='530 Ames'!$D$22 -> 1258857 | E30: ='540 Freedom'!$D$22 -> 63391
A31: 12/08/17 | B31: 19 - Equpiment - Ames - 5yr | C31: =SUM(D31:M31) -> 61995 | D31: ='530 Ames'!$D$23 -> 59195 | E31: ='540 Freedom'!$D$23 -> 2800
A32: 12/08/17 | B32: 19 - Equpiment - Ames - 15yr | C32: =SUM(D32:M32) -> 5827 | D32: ='530 Ames'!$D$24 -> 5395 | E32: ='540 Freedom'!$D$24 -> 432
A33: 12/08/17 | B33: 19 - Equpiment - Ames - 27.5yr | C33: =SUM(D33:M33) -> 271231 | D33: ='530 Ames'!$D$25 -> 258227 | E33: ='540 Freedom'!$D$25 -> 13004
A34: 12/08/17 | B34: 17 - Land Improvements - Ames - 27.5yr | C34: =SUM(D34:M34) -> 4876 | E34: ='540 Freedom'!$D$19 -> 4876
A35: 12/08/17 | B35: 12 - Land Improvements - Smith Square - 5yr | C35: =SUM(D35:M35) -> 9671 | F35: ='1208 Smith'!$D$17 -> 8155 | G35: ='1209 Smith'!$D$17 -> 1516
A36: 12/08/17 | B36: 12 - Land Improvements - Smith Square - 15yr | C36: =SUM(D36:M36) -> 1549 | F36: ='1208 Smith'!$D$18 -> 1280 | G36: ='1209 Smith'!$D$18 -> 269
A37: 12/08/17 | B37: 12 - Land Improvements - Smith Square - 275yr | C37: =SUM(D37:M37) -> 41513 | F37: ='1208 Smith'!$D$19 -> 34397 | G37: ='1209 Smith'!$D$19 -> 7116
A38: 12/08/17 | B38: 13 - Buidling - Smith Square - 5yr | C38: =SUM(D38:M38) -> 125729 | F38: ='1208 Smith'!$D$20 -> 106017 | G38: ='1209 Smith'!$D$20 -> 19712
A39: 12/08/17 | B39: 13 - Buidling - Smith Square - 15yr | C39: =SUM(D39:M39) -> 20130 | F39: ='1208 Smith'!$D$21 -> 16634 | G39: ='1209 Smith'!$D$21 -> 3496
A40: 12/08/17 | B40: 13 - Buidling - Smith Square - 27.5yr | C40: =SUM(D40:M40) -> 539667 | F40: ='1208 Smith'!$D$22 -> 447163 | G40: ='1209 Smith'!$D$22 -> 92504
A41: 12/08/17 | B41: 14 - Equpiment - Smith Square - 5yr | C41: =SUM(D41:M41) -> 25790 | F41: ='1208 Smith'!$D$23 -> 21747 | G41: ='1209 Smith'!$D$23 -> 4043
A42: 12/08/17 | B42: 14 - Equpiment - Smith Square - 15yr | C42: =SUM(D42:M42) -> 4129 | F42: ='1208 Smith'!$D$24 -> 3412 | G42: ='1209 Smith'!$D$24 -> 717
A43: 12/08/17 | B43: 14 - Equpiment - Smith Square - 27.5yr | C43: =SUM(D43:M43) -> 110702 | F43: ='1208 Smith'!$D$25 -> 91726 | G43: ='1209 Smith'!$D$25 -> 18976
A44: 12/08/17 | B44: 2 - Land Improvements - Havenwood -5yr | C44: =SUM(D44:M44) -> 8161 | H44: ='3112 Havenwood'!$D$17 -> 8161
A45: 12/08/17 | B45: 2 - Land Improvements - Havenwood -15yr | C45: =SUM(D45:M45) -> 1164 | H45: ='3112 Havenwood'!$D$18 -> 1164
A46: 12/08/17 | B46: 2 - Land Improvements - Havenwood -27.5yr | C46: =SUM(D46:M46) -> 38146 | H46: ='3112 Havenwood'!$D$19 -> 38146
A47: 12/08/17 | B47: 13 - Buidling - Havenwood - 5yr | C47: =SUM(D47:M47) -> 106098 | H47: ='3112 Havenwood'!$D$20 -> 106098
A48: 12/08/17 | B48: 13 - Buidling - Havenwood - 15yr | C48: =SUM(D48:M48) -> 15130 | H48: ='3112 Havenwood'!$D$21 -> 15130
A49: 12/08/17 | B49: 13 - Buidling - Havenwood - 27.5yr | C49: =SUM(D49:M49) -> 495900 | H49: ='3112 Havenwood'!$D$22 -> 495900
A50: 12/08/17 | B50: 14 - Equipment - Havenwood - 5yr | C50: =SUM(D50:M50) -> 21764 | H50: ='3112 Havenwood'!$D$23 -> 21764
A51: 12/08/17 | B51: 14 - Equipment - Havenwood - 15yr | C51: =SUM(D51:M51) -> 104826 | H51: ='3112 Havenwood'!$D$24+'3112 Havenwood'!$D$25 -> 104826
A52: 12/08/17 | B52: 2 - Land Improvements - Havenwood - 5yr | C52: =SUM(D52:M52) -> 1030 | I52: ='3117 Barbwood'!$D$17 -> 1030
A53: 12/08/17 | B53: 2 - Land Improvements - Havenwood - 15yr | C53: =SUM(D53:M53) -> 127 | I53: ='3117 Barbwood'!$D$18 -> 127
A54: 12/08/17 | B54: 2 - Land Improvements - Havenwood - 27.5yr | C54: =SUM(D54:M54) -> 6493 | I54: ='3117 Barbwood'!$D$19 -> 6493
A55: 12/08/17 | B55: 3 - Buidling - Havenwood - 5yr | C55: =SUM(D55:M55) -> 13389 | I55: ='3117 Barbwood'!$D$20 -> 13389
A56: 12/08/17 | B56: 3 - Buidling - Havenwood - 15yr | C56: =SUM(D56:M56) -> 1655 | I56: ='3117 Barbwood'!$D$21 -> 1655
A57: 12/08/17 | B57: 3 - Buidling - Havenwood - 27.5yr | C57: =SUM(D57:M57) -> 84398 | I57: ='3117 Barbwood'!$D$22 -> 84398
A58: 12/08/17 | B58: 4 - Equipment - Havenwood - 5yr | C58: =SUM(D58:M58) -> 2746 | I58: ='3117 Barbwood'!$D$23 -> 2746
A59: 12/08/17 | B59: 4 - Equipment - Havenwood - 15yr | C59: =SUM(D59:M59) -> 340 | I59: ='3117 Barbwood'!$D$24 -> 340
A60: 12/08/17 | B60: 4 - Equipment - Havenwood - 27.5yr | C60: =SUM(D60:M60) -> 17312 | I60: ='3117 Barbwood'!$D$25 -> 17312
A61: 1/09/18 | B61: 22 - Land Improvements - Gentry - 5yr | C61: =SUM(D61:M61) -> 7434 | J61: ='6805 Sayres'!$D$17 -> 6134 | K61: ='6800 Sayres'!$D$17 -> 1300
A62: 1/09/18 | B62: 22 - Land Improvements - Gentry - 15yr | C62: =SUM(D62:M62) -> 877 | J62: ='6805 Sayres'!$D$18 -> 692 | K62: ='6800 Sayres'!$D$18 -> 185
A63: 1/09/18 | B63: 22 - Land Improvements - Gentry - 27.5yr | C63: =SUM(D63:M63) -> 40651 | J63: ='6805 Sayres'!$D$19 -> 34061 | K63: ='6800 Sayres'!$D$19 -> 6590
A64: 1/29/18 | B64: 23 - Buidling - Gentry - 5yr | C64: =SUM(D64:M64) -> 205675 | J64: ='6805 Sayres'!$D$20 -> 169707 | K64: ='6800 Sayres'!$D$20 -> 35968
A65: 1/29/18 | B65: 23 - Buidling - Gentry - 15yr | C65: =SUM(D65:M65) -> 24254 | J65: ='6805 Sayres'!$D$21 -> 19148 | K65: ='6800 Sayres'!$D$21 -> 5106
A66: 1/29/18 | B66: 23 - Buidling - Gentry - 27.5yr | C66: =SUM(D66:M66) -> 1124692 | J66: ='6805 Sayres'!$D$22 -> 942361 | K66: ='6800 Sayres'!$D$22 -> 182331
A67: 1/29/18 | B67: 24 - Equipment - Gentry - 5yr | C67: =SUM(D67:M67) -> 34692 | J67: ='6805 Sayres'!$D$23 -> 28625 | K67: ='6800 Sayres'!$D$23 -> 6067
A68: 1/29/18 | B68: 24 - Equipment - Gentry - 15yr | C68: =SUM(D68:M68) -> 4091 | J68: ='6805 Sayres'!$D$24 -> 3230 | K68: ='6800 Sayres'!$D$24 -> 861
A69: 1/29/18 | B69: 24 - Equipment - Gentry - 27.5yr | C69: =SUM(D69:M69) -> 189708 | J69: ='6805 Sayres'!$D$25 -> 158953 | K69: ='6800 Sayres'!$D$25 -> 30755
A70: 12/08/17 | B70: 7 - Land Improvements - Kayla - 5yr | C70: =SUM(D70:M70) -> 16361 | L70: ='7112 Kayla'!$D$17 -> 13399 | M70: ='7141 Kayla'!$D$17 -> 2962
A71: 12/08/17 | B71: 7 - Land Improvements - Kayla - 15yr | C71: =SUM(D71:M71) -> 1530 | L71: ='7112 Kayla'!$D$18 -> 1194 | M71: ='7141 Kayla'!$D$18 -> 336
A72: 12/08/17 | B72: 7 - Land Improvements - Kayla - 27.5yr | C72: =SUM(D72:M72) -> 80463 | L72: ='7112 Kayla'!$D$19 -> 65650 | M72: ='7141 Kayla'!$D$19 -> 14813
A73: 12/08/17 | B73: 8 - Buidling - Kayla - 5yr | C73: =SUM(D73:M73) -> 212691 | L73: ='7112 Kayla'!$D$20 -> 174191 | M73: ='7141 Kayla'!$D$20 -> 38500
A74: 12/08/17 | B74: 8 - Buidling - Kayla - 15yr | C74: =SUM(D74:M74) -> 19888 | L74: ='7112 Kayla'!$D$21 -> 15524 | M74: ='7141 Kayla'!$D$21 -> 4364
A75: 12/08/17 | B75: 8 - Buidling - Kayla - 27.5yr | C75: =SUM(D75:M75) -> 1046028 | L75: ='7112 Kayla'!$D$22 -> 853456 | M75: ='7141 Kayla'!$D$22 -> 192572
A76: 12/08/17 | B76: 9 - Equipment - Kayla - 5yr | C76: =SUM(D76:M76) -> 43629 | L76: ='7112 Kayla'!$D$23 -> 35731 | M76: ='7141 Kayla'!$D$23 -> 7898
A77: 12/08/17 | B77: 9 - Equipment - Kayla - 15yr | C77: =SUM(D77:M77) -> 4080 | L77: ='7112 Kayla'!$D$24 -> 3185 | M77: ='7141 Kayla'!$D$24 -> 895
A78: 12/08/17 | B78: 9 - Equipment - Kayla - 27.5yr | C78: =SUM(D78:M78) -> 214569 | L78: ='7112 Kayla'!$D$25 -> 175068 | M78: ='7141 Kayla'!$D$25 -> 39501
B79: Total MACRS Reclassification | C79: =SUM(C26:C78) -> 7187949 | D79: =SUM(D26:D78) -> 2017604 | E79: =SUM(E26:E78) -> 101473 | F79: =SUM(F26:F78) -> 730531 | G79: =SUM(G26:G78) -> 148349 | H79: =SUM(H26:H78) -> 791189 | I79: =SUM(I26:I78) -> 127490 | J79: =SUM(J26:J78) -> 1362911 | ... M79: =SUM(M26:M78) -> 301841
B80: Difference (should be zero) | C80: =C23-C79 -> -2 | D80: =D23-D79 -> 0 | E80: =E23-E79 -> 0 | F80: =F23-F79 -> 0 | G80: =G23-G79 -> 0 | H80: =H23-H79 -> 0 | I80: =I23-I79 -> -1 | J80: =J23-J79 -> -1 | ... M80: =M23-M79 -> 0
B82: End Depreciation Reconciliation
B83: Before Cost Segregation (As Previously Filed) | C83: =SUM(D83:M83) -> 2796334 | D83: ='530 Ames'!$I$13 -> 790255.88 | E83: ='540 Freedom'!$I$13 -> 39745.12 | F83: ='1208 Smith'!$I$13 -> 286132.85 | G83: ='1209 Smith'!$I$13 -> 58105.15 | H83: ='3112 Havenwood'!$I$13 -> 309892.45 | I83: ='3117 Barbwood'!$I$13 -> 49934.55 | J83: ='6805 Sayres'!$I$13 -> 517926.62 | K83: ='6800 Sayres'!$I$13 -> 102285.38 | L83: ='7112 Kayla'!$I$13 -> 523830.88 | M83: ='7141 Kayla'!$I$13 -> 118225.12
B84: 17 - Land Improvements - Ames - 5yr | C84: =SUM(D84:M84) -> 23248 | D84: ='530 Ames'!$I$17 -> 22198 | E84: ='540 Freedom'!$I$17 -> 1050
B85: 17 - Land Improvements - Ames - 15yr | C85: =SUM(D85:M85) -> 26908.87 | D85: ='530 Ames'!$I$18+'530 Ames'!$I$19 -> 26818.61 | E85: ='540 Freedom'!$I$18 -> 90.26
B86: 18 - Buidling - Ames - 5yr | C86: =SUM(D86:M86) -> 302225 | D86: ='530 Ames'!$I$20 -> 288575 | E86: ='540 Freedom'!$I$20 -> 13650
B87: 18 - Buidling - Ames - 15yr | C87: =SUM(D87:M87) -> 28407 | D87: ='530 Ames'!$I$21 -> 26299 | E87: ='540 Freedom'!$I$21 -> 2108
B88: 18 - Buidling - Ames - 27.5yr | C88: =SUM(D88:M88) -> 338575.66 | D88: ='530 Ames'!$I$22 -> 322343.7 | E88: ='540 Freedom'!$I$22 -> 16231.96
B89: 19 - Equpiment - Ames - 5yr | C89: =SUM(D89:M89) -> 61995 | D89: ='530 Ames'!$I$23 -> 59195 | E89: ='540 Freedom'!$I$23 -> 2800
B90: 19 - Equpiment - Ames - 15yr | C90: =SUM(D90:M90) -> 5827 | D90: ='530 Ames'!$I$24 -> 5395 | E90: ='540 Freedom'!$I$24 -> 432
B91: 19 - Equpiment - Ames - 27.5yr | C91: =SUM(D91:M91) -> 69451.35 | D91: ='530 Ames'!$I$25 -> 66121.74 | E91: ='540 Freedom'!$I$25 -> 3329.61
B92: 17 - Land Improvements - Ames - 27.5yr | C92: =SUM(D92:M92) -> 1248.56 | E92: ='540 Freedom'!$I$19 -> 1248.56
B93: 12 - Land Improvements - Smith Square - 5yr | C93: =SUM(D93:M93) -> 9671 | F93: ='1208 Smith'!$I$17 -> 8155 | G93: ='1209 Smith'!$I$17 -> 1516
B94: 12 - Land Improvements - Smith Square - 15yr | C94: =SUM(D94:M94) -> 1549 | F94: ='1208 Smith'!$I$18 -> 1280 | G94: ='1209 Smith'!$I$18 -> 269
B95: 12 - Land Improvements - Smith Square - 275yr | C95: =SUM(D95:M95) -> 10629.82 | F95: ='1208 Smith'!$I$19 -> 8807.72 | G95: ='1209 Smith'!$I$19 -> 1822.1
B96: 13 - Buidling - Smith Square - 5yr | C96: =SUM(D96:M96) -> 125729 | F96: ='1208 Smith'!$I$20 -> 106017 | G96: ='1209 Smith'!$I$20 -> 19712
B97: 13 - Buidling - Smith Square - 15yr | C97: =SUM(D97:M97) -> 20130 | F97: ='1208 Smith'!$I$21 -> 16634 | G97: ='1209 Smith'!$I$21 -> 3496
B98: 13 - Buidling - Smith Square - 27.5yr | C98: =SUM(D98:M98) -> 138187.43 | F98: ='1208 Smith'!$I$22 -> 114500.81 | G98: ='1209 Smith'!$I$22 -> 23686.62
B99: 14 - Equpiment - Smith Square - 5yr | C99: =SUM(D99:M99) -> 25790 | F99: ='1208 Smith'!$I$23 -> 21747 | G99: ='1209 Smith'!$I$23 -> 4043
B100: 14 - Equpiment - Smith Square - 15yr | C100: =SUM(D100:M100) -> 4129 | F100: ='1208 Smith'!$I$24 -> 3412 | G100: ='1209 Smith'!$I$24 -> 717
B101: 14 - Equpiment - Smith Square - 27.5yr | C101: =SUM(D101:M101) -> 28346.2 | F101: ='1208 Smith'!$I$25 -> 23487.41 | G101: ='1209 Smith'!$I$25 -> 4858.79
B102: 2 - Land Improvements - Havenwood -5yr | C102: =SUM(D102:M102) -> 8161 | H102: ='3112 Havenwood'!$I$17 -> 8161
B103: 2 - Land Improvements - Havenwood -15yr | C103: =SUM(D103:M103) -> 1164 | H103: ='3112 Havenwood'!$I$18 -> 1164
B104: 2 - Land Improvements - Havenwood -27.5yr | C104: =SUM(D104:M104) -> 9767.89 | H104: ='3112 Havenwood'!$I$19 -> 9767.89
...

Sheet 530 Ames
A1: Marrero 3 LP
A2: Marrero 3 — 530 Ames Blvd, Marrero, LA 70072
A3: EIN: 82-2324040 · FYE: December 31, 2024 · Year of Change: 1/1/2024
A4: 530 Ames — Attachment to Form 3115 (DCN #7, Rev. Proc. 2024-23 §6.01)
A5: Source: CSSI Report #107752-18, "#107752-18_Marrero 3 - 3115 Combined.pdf"
A7: CALCULATION OF §481(a) ADJUSTMENT — REGULAR TAX
A8: As Previously Filed
A9: Asset | B9: Property Description | C9: Date In Service | D9: Cost | E9: Sec 179 Exp | F9: Bonus Amt | G9: Tax Prior Depreciation | H9: Tax Current Depreciation | I9: End Depreciation | J9: Net Book Value | K9: Method | L9: Period
A10: 1 | B10: 17 - Land Improvements - Ames | C10: 12/08/17 | D10: 121057 | E10: 0 | F10: 0 | G10: 57319.39 | H10: 7148.5 | I10: =G10+H10 -> 64467.89 | J10: =D10-I10 -> 56589.11 | K10: 150DB | L10: 15.0
A11: 2 | B11: 18 - Buidling - Ames | C11: 12/08/17 | D11: 1573731 | E11: 0 | F11: 0 | G11: 345745.14 | H11: 57226.85 | I11: =G11+H11 -> 402971.99 | J11: =D11-I11 -> 1170759 | K11: S/L | L11: 27.5
A12: 3 | B12: 19 - Equpiment - Ames | C12: 12/08/17 | D12: 322816 | E12: 0 | F12: 0 | G12: 322816 | H12: 0 | I12: =G12+H12 -> 322816 | J12: =D12-I12 -> 0 | K12: S/L | L12: 5.0
B13: Grand Total | D13: =SUM(D10:D12) -> 2017604 | E13: =SUM(E10:E12) -> 0 | F13: =SUM(F10:F12) -> 0 | G13: =SUM(G10:G12) -> 725880.53 | H13: =SUM(H10:H12) -> 64375.35 | I13: =SUM(I10:I12) -> 790255.88 | J13: =SUM(J10:J12) -> 1227348.1
A15: After Cost Segregation Correction
A16: Asset | B16: Property Description | C16: Date In Service | D16: Cost | E16: Sec 179 Exp | F16: Bonus Amt | G16: Tax Prior Depreciation | H16: Tax Current Depreciation | I16: End Depreciation | J16: Net Book Value | K16: Method | L16: Period
A17: 1 | B17: 17 - Land Improvements - Ames - 5yr | C17: 12/08/17 | D17: 22198 | E17: 0 | F17: 0 | G17: 22198 | H17: 0 | I17: =G17+H17 -> 22198 | J17: =D17-I17 -> 0 | K17: 200DB | L17: 5.0
A18: 2 | B18: 17 - Land Improvements - Ames - 15yr | C18: 12/08/17 | D18: 2023 | E18: 0 | F18: 0 | G18: 2023 | H18: 0 | I18: =G18+H18 -> 2023 | J18: =D18-I18 -> 0 | K18: 150DB | L18: 15.0
A19: 3 | B19: 17 - Land Improvements - Ames - 15yr | C19: 12/08/17 | D19: 96835 | E19: 0 | F19: 0 | G19: 21274.34 | H19: 3521.27 | I19: =G19+H19 -> 24795.61 | J19: =D19-I19 -> 72039.39 | K19: S/L | L19: 27.5
A20: 4 | B20: 18 - Buidling - Ames - 5yr | C20: 12/08/17 | D20: 288575 | E20: 0 | F20: 288575 | G20: 288575 | H20: 0 | I20: =G20+H20 -> 288575 | J20: =D20-I20 -> 0 | K20: 200DB | L20: 5.0
A21: 5 | B21: 18 - Buidling - Ames - 15yr | C21: 12/08/17 | D21: 26299 | E21: 0 | F21: 26299 | G21: 26299 | H21: 0 | I21: =G21+H21 -> 26299 | J21: =D21-I21 -> 0 | K21: 150DB | L21: 15.0
A22: 6 | B22: 18 - Buidling - Ames - 27.5yr | C22: 12/08/17 | D22: 1258857 | E22: 0 | F22: 0 | G22: 276567.08 | H22: 45776.62 | I22: =G22+H22 -> 322343.7 | J22: =D22-I22 -> 936513.3 | K22: S/L | L22: 27.5
A23: 7 | B23: 19 - Equpiment - Ames - 5yr | C23: 12/08/17 | D23: 59195 | E23: 0 | F23: 59195 | G23: 59195 | H23: 0 | I23: =G23+H23 -> 59195 | J23: =D23-I23 -> 0 | K23: 200DB | L23: 5.0
A24: 8 | B24: 19 - Equpiment - Ames - 15yr | C24: 12/08/17 | D24: 5395 | E24: 0 | F24: 5395 | G24: 5395 | H24: 0 | I24: =G24+H24 -> 5395 | J24: =D24-I24 -> 0 | K24: 150DB | L24: 15.0
A25: 9 | B25: 19 - Equpiment - Ames - 27.5yr | C25: 12/08/17 | D25: 258227 | E25: 0 | F25: 0 | G25: 56731.67 | H25: 9390.07 | I25: =G25+H25 -> 66121.74 | J25: =D25-I25 -> 192105.26 | K25: S/L | L25: 27.5
B26: Grand Total | D26: =SUM(D17:D25) -> 2017604 | E26: =SUM(E17:E25) -> 0 | F26: =SUM(F17:F25) -> 379464 | G26: =SUM(G17:G25) -> 758258.09 | H26: =SUM(H17:H25) -> 58687.96 | I26: =SUM(I17:I25) -> 816946.05 | J26: =SUM(J17:J25) -> 1200657.9
B28: Section 481(a) Adjustment — Regular Tax
B29: Depreciation reported previously | D29: =I13 -> 790255.88
B30: Cost Segregation Corrected Depreciation | D30: =I26 -> 816946.05
B31: Section 481(a) Adjustment — Regular Tax | D31: =D29-D30 -> -26690.17
A33: CALCULATION OF §481(a) ADJUSTMENT — AMT
A34: As Previously Filed — AMT
A35: Asset | B35: Property Description | C35: Date In Service | D35: Cost | E35: Sec 179 Exp | F35: Bonus Amt | G35: AMT Prior Depreciation | H35: AMT Current Depreciation | I35: End Depreciation | J35: Net Book Value | K35: Method | L35: Period
A36: 1 | B36: 17 - Land Improvements - Ames | C36: 12/08/17 | D36: 121057 | E36: 0 | F36: 0 | G36: 57319.39 | H36: 7148.5 | I36: =G36+H36 -> 64467.89 | J36: =D36-I36 -> 56589.11 | K36: 150DB | L36: 15.0
A37: 2 | B37: 18 - Buidling - Ames | C37: 12/08/17 | D37: 1573731 | E37: 0 | F37: 0 | G37: 345745.14 | H37: 57226.85 | I37: =G37+H37 -> 402971.99 | J37: =D37-I37 -> 1170759 | K37: S/L | L37: 27.5
A38: 3 | B38: 19 - Equpiment - Ames | C38: 12/08/17 | D38: 322816 | E38: 0 | F38: 0 | G38: 322816 | H38: 0 | I38: =G38+H38 -> 322816 | J38: =D38-I38 -> 0 | K38: S/L | L38: 5.0
B39: Grand Total | D39: =SUM(D36:D38) -> 2017604 | E39: =SUM(E36:E38) -> 0 | F39: =SUM(F36:F38) -> 0 | G39: =SUM(G36:G38) -> 725880.53 | H39: =SUM(H36:H38) -> 64375.35 | I39: =SUM(I36:I38) -> 790255.88 | J39: =SUM(J36:J38) -> 1227348.1
A41: After Cost Segregation Correction — AMT
A42: Asset | B42: Property Description | C42: Date In Service | D42: Cost | E42: Sec 179 Exp | F42: Bonus Amt | G42: AMT Prior Depreciation | H42: AMT Current Depreciation | I42: End Depreciation | J42: Net Book Value | K42: Method | L42: Period
A43: 1 | B43: 17 - Land Improvements - Ames - 5yr | C43: 12/08/17 | D43: 22198 | E43: 0 | F43: 0 | G43: 22198 | H43: 0 | I43: =G43+H43 -> 22198 | J43: =D43-I43 -> 0 | K43: 200DB | L43: 5.0
A44: 2 | B44: 17 - Land Improvements - Ames - 15yr | C44: 12/08/17 | D44: 2023 | E44: 0 | F44: 0 | G44: 2023 | H44: 0 | I44: =G44+H44 -> 2023 | J44: =D44-I44 -> 0 | K44: 150DB | L44: 15.0
A45: 3 | B45: 17 - Land Improvements - Ames - 15yr | C45: 12/08/17 | D45: 96835 | E45: 0 | F45: 0 | G45: 21274.34 | H45: 3521.27 | I45: =G45+H45 -> 24795.61 | J45: =D45-I45 -> 72039.39 | K45: S/L | L45: 27.5
A46: 4 | B46: 18 - Buidling - Ames - 5yr | C46: 12/08/17 | D46: 288575 | E46: 0 | F46: 288575 | G46: 288575 | H46: 0 | I46: =G46+H46 -> 288575 | J46: =D46-I46 -> 0 | K46: 200DB | L46: 5.0
A47: 5 | B47: 18 - Buidling - Ames - 15yr | C47: 12/08/17 | D47: 26299 | E47: 0 | F47: 26299 | G47: 26299 | H47: 0 | I47: =G47+H47 -> 26299 | J47: =D47-I47 -> 0 | K47: 150DB | L47: 15.0
A48: 6 | B48: 18 - Buidling - Ames - 27.5yr | C48: 12/08/17 | D48: 1258857 | E48: 0 | F48: 0 | G48: 276567.08 | H48: 45776.62 | I48: =G48+H48 -> 322343.7 | J48: =D48-I48 -> 936513.3 | K48: S/L | L48: 27.5
A49: 7 | B49: 19 - Equpiment - Ames - 5yr | C49: 12/08/17 | D49: 59195 | E49: 0 | F49: 59195 | G49: 59195 | H49: 0 | I49: =G49+H49 -> 59195 | J49: =D49-I49 -> 0 | K49: 200DB | L49: 5.0
A50: 8 | B50: 19 - Equpiment - Ames - 15yr | C50: 12/08/17 | D50: 5395 | E50: 0 | F50: 5395 | G50: 5395 | H50: 0 | I50: =G50+H50 -> 5395 | J50: =D50-I50 -> 0 | K50: 150DB | L50: 15.0
A51: 9 | B51: 19 - Equpiment - Ames - 27.5yr | C51: 12/08/17 | D51: 258227 | E51: 0 | F51: 0 | G51: 56731.67 | H51: 9390.07 | I51: =G51+H51 -> 66121.74 | J51: =D51-I51 -> 192105.26 | K51: S/L | L51: 27.5
B52: Grand Total | D52: =SUM(D43:D51) -> 2017604 | E52: =SUM(E43:E51) -> 0 | F52: =SUM(F43:F51) -> 379464 | G52: =SUM(G43:G51) -> 758258.09 | H52: =SUM(H43:H51) -> 58687.96 | I52: =SUM(I43:I51) -> 816946.05 | J52: =SUM(J43:J51) -> 1200657.9
B54: Section 481(a) Adjustment — AMT
B55: Depreciation reported previously | D55: =I39 -> 790255.88
B56: Cost Segregation Corrected Depreciation | D56: =I52 -> 816946.05
B57: Section 481(a) Adjustment — AMT | D57: =D55-D56 -> -26690.17
A59: COST SEGREGATION STUDY — COST SUMMARY
B60: Total Building Cost | D60: =D105 -> 43860.96
B61: Building Components: 5 Year | D61: =F105 -> 8042.77
B62: % of Cost | D62: =F106 -> 0.18336968
B63: Site Improvements: 15 Year | D63: =H105 -> 732.98
B64: % of Cost | D64: =H106 -> 0.016711445
B65: Building Structure: 27.5 Year | D65: =J105 -> 35085.21
B66: % of Cost | D66: =J106 -> 0.79991888
A68: COST SEGREGATION STUDY — COST DETAIL
B69: Property Category | D69: Cost | F69: 5 Year | H69: 15 Year | J69: 27.5 Year
B70: Building Components
B71: Cabinets / Millwork | D71: =SUM(F71:J71) -> 1051.54 | F71: 1051.54
B72: Moldings | D72: =SUM(F72:J72) -> 998.91 | F72: 998.91
B73: Flooring - Wood Laminate | D73: =SUM(F73:J73) -> 2190.16 | F73: 2190.16
B74: Security System | D74: =SUM(F74:J74) -> 503.17 | F74: 503.17
B75: Window Treatments | D75: =SUM(F75:J75) -> 382.43 | F75: 382.43
B76: Specialty HVAC - Dryer Vents | D76: =SUM(F76:J76) -> 42.81 | F76: 42.81
B77: Building Signage | D77: =SUM(F77:J77) -> 21.12 | F77: 21.12
B78: Specialty Electrical - Appliances | D78: =SUM(F78:J78) -> 731.07 | F78: 731.07
B79: Communication / Data | D79: =SUM(F79:J79) -> 286.8 | F79: 286.8
B80: Specialty Plumbing - Kitchen Sink / Laundry | D80: =SUM(F80:J80) -> 800.46 | F80: 800.46
B81: Security / Exterior Lighting | D81: =SUM(F81:J81) -> 232.42 | F81: 232.42
B82: Appliances | D82: =SUM(F82:J82) -> 801.88 | F82: 801.88
B83: Site Work / Improvements
B84: Driveway | D84: =SUM(F84:J84) -> 463.54 | H84: 463.54
B85: Sidewalks / Curbs | D85: =SUM(F85:J85) -> 189.36 | H85: 189.36
B86: Exterior Equipment Concrete Pads | D86: =SUM(F86:J86) -> 49.43 | H86: 49.43
B87: Mailboxes | D87: =SUM(F87:J87) -> 30.65 | H87: 30.65
B88: Building Structure
B89: Roofing Systems | D89: =SUM(F89:J89) -> 2790.25 | J89: 2790.25
B90: Foundations | D90: =SUM(F90:J90) -> 4444.19 | J90: 4444.19
B91: HVAC | D91: =SUM(F91:J91) -> 2944.42 | J91: 2944.42
B92: Electrical | D92: =SUM(F92:J92) -> 2757.96 | J92: 2757.96
B93: Plumbing | D93: =SUM(F93:J93) -> 2596.79 | J93: 2596.79
B94: Fire Protection & Alarm | D94: =SUM(F94:J94) -> 170.86 | J94: 170.86
B95: Exterior Façade / Building Skin | D95: =SUM(F95:J95) -> 1575.35 | J95: 1575.35
B96: Doors & Frames | D96: =SUM(F96:J96) -> 2049.79 | J96: 2049.79
B97: Windows | D97: =SUM(F97:J97) -> 1685.6 | J97: 1685.6
B98: Ceiling Systems | D98: =SUM(F98:J98) -> 1546.81 | J98: 1546.81
B99: Interior Framing / Partitions | D99: =SUM(F99:J99) -> 4298.39 | J99: 4298.39
B100: Painting | D100: =SUM(F100:J100) -> 1463.49 | J100: 1463.49
... B104: Cabinets / Millwork - Restrooms | D104: =SUM(F104:J104) -> 430.4 | J104: 430.4
B105: Total Building Cost | D105: =SUM(D70:D104) -> 43860.96 | F105: =SUM(F70:F104) -> 8042.77 | H105: =SUM(H70:H104) -> 732.98 | J105: =SUM(J70:J104) -> 35085.21
B106: % of Cost | F106: =F105/D105 -> 0.18336968 | H106: =H105/D105 -> 0.016711445 | J106: =J105/D105 -> 0.79991888
A108: ASSET ALLOCATION (per After Cost Segregation schedule)
B109: Asset (as reclassified) | D109: Cost | F109: 5 Year | H109: 15 Year | J109: 27.5 Year
B110: ='530 Ames'!B17 -> 17 - Land Improvements - Ames - 5yr | D110: =SUM(F110:J110) -> 22198 | F110: ='530 Ames'!D17 -> 22198
B111: ='530 Ames'!B18 -> 17 - Land Improvements - Ames - 15yr | D111: =SUM(F111:J111) -> 2023 | H111: ='530 Ames'!D18 -> 2023
B112: ='530 Ames'!B19 -> 17 - Land Improvements - Ames - 15yr | D112: =SUM(F112:J112) -> 96835 | J112: ='530 Ames'!D19 -> 96835
...

Sheet 540 Freedom
A1: Marrero 3 LP
A2: Marrero 3 — 530 Ames Blvd, Marrero, LA 70072
A3: EIN: 82-2324040 · FYE: December 31, 2024 · Year of Change: 1/1/2024
A4: 540 Freedom — Attachment to Form 3115 (DCN #7, Rev. Proc. 2024-23 §6.01)
A5: Source: CSSI Report #107752-18, "#107752-18_Marrero 3 - 3115 Combined.pdf"
A7: CALCULATION OF §481(a) ADJUSTMENT — REGULAR TAX
A8: As Previously Filed
A9: Asset | B9: Property Description | C9: Date In Service | D9: Cost | E9: Sec 179 Exp | F9: Bonus Amt | G9: Tax Prior Depreciation | H9: Tax Current Depreciation | I9: End Depreciation | J9: Net Book Value | K9: Method | L9: Period
A10: 1 | B10: 17 - Land Improvements - Ames | C10: 12/08/17 | D10: 6088 | E10: 0 | F10: 0 | G10: 2882.61 | H10: 359.5 | I10: =G10+H10 -> 3242.11 | J10: =D10-I10 -> 2845.89 | K10: 150DB | L10: 15.0
A11: 2 | B11: 18 - Buidling - Ames | C11: 12/08/17 | D11: 79149 | E11: 0 | F11: 0 | G11: 17388.86 | H11: 2878.15 | I11: =G11+H11 -> 20267.01 | J11: =D11-I11 -> 58881.99 | K11: S/L | L11: 27.5
A12: 3 | B12: 19 - Equpiment - Ames | C12: 12/08/17 | D12: 16236 | E12: 0 | F12: 16236 | G12: 16236 | H12: 0 | I12: =G12+H12 -> 16236 | J12: =D12-I12 -> 0 | K12: 200DB | L12: 5.0
B13: Grand Total | D13: =SUM(D10:D12) -> 101473 | E13: =SUM(E10:E12) -> 0 | F13: =SUM(F10:F12) -> 16236 | G13: =SUM(G10:G12) -> 36507.47 | H13: =SUM(H10:H12) -> 3237.65 | I13: =SUM(I10:I12) -> 39745.12 | J13: =SUM(J10:J12) -> 61727.88
A15: After Cost Segregation Correction
A16: Asset | B16: Property Description | C16: Date In Service | D16: Cost | E16: Sec 179 Exp | F16: Bonus Amt | G16: Tax Prior Depreciation | H16: Tax Current Depreciation | I16: End Depreciation | J16: Net Book Value | K16: Method | L16: Period
A17: 1 | B17: 17 - Land Improvements - Ames - 5yr | C17: 12/08/17 | D17: 1050 | E17: 0 | F17: 0 | G17: 1050 | H17: 0 | I17: =G17+H17 -> 1050 | J17: =D17-I17 -> 0 | K17: 200DB | L17: 5.0
A18: 2 | B18: 17 - Land Improvements - Ames - 15yr | C18: 12/08/17 | D18: 162 | E18: 0 | F18: 0 | G18: 80.7 | H18: 9.56 | I18: =G18+H18 -> 90.26 | J18: =D18-I18 -> 71.74 | K18: 150DB | L18: 15.0
A19: 3 | B19: 17 - Land Improvements - Ames - 27.5yr | C19: 12/08/17 | D19: 4876 | E19: 0 | F19: 0 | G19: 1071.25 | H19: 177.31 | I19: =G19+H19 -> 1248.56 | J19: =D19-I19 -> 3627.44 | K19: S/L | L19: 27.5
A20: 4 | B20: 18 - Buidling - Ames - 5yr | C20: 12/08/17 | D20: 13650 | E20: 0 | F20: 13650 | G20: 13650 | H20: 0 | I20: =G20+H20 -> 13650 | J20: =D20-I20 -> 0 | K20: 200DB | L20: 5.0
A21: 5 | B21: 18 - Buidling - Ames - 15yr | C21: 12/08/17 | D21: 2108 | E21: 0 | F21: 2108 | G21: 2108 | H21: 0 | I21: =G21+H21 -> 2108 | J21: =D21-I21 -> 0 | K21: 150DB | L21: 15.0
A22: 6 | B22: 18 - Buidling - Ames - 27.5yr | C22: 12/08/17 | D22: 63391 | E22: 0 | F22: 0 | G22: 13926.83 | H22: 2305.13 | I22: =G22+H22 -> 16231.96 | J22: =D22-I22 -> 47159.04 | K22: S/L | L22: 27.5
A23: 7 | B23: 19 - Equpiment - Ames - 5yr | C23: 12/08/17 | D23: 2800 | E23: 0 | F23: 2800 | G23: 2800 | H23: 0 | I23: =G23+H23 -> 2800 | J23: =D23-I23 -> 0 | K23: 200DB | L23: 5.0
A24: 8 | B24: 19 - Equpiment - Ames - 15yr | C24: 12/08/17 | D24: 432 | E24: 0 | F24: 432 | G24: 432 | H24: 0 | I24: =G24+H24 -> 432 | J24: =D24-I24 -> 0 | K24: 150DB | L24: 15.0
A25: 9 | B25: 19 - Equpiment - Ames - 27.5yr | C25: 12/08/17 | D25: 13004 | E25: 0 | F25: 0 | G25: 2856.74 | H25: 472.87 | I25: =G25+H25 -> 3329.61 | J25: =D25-I25 -> 9674.39 | K25: S/L | L25: 27.5
B26: Grand Total | D26: =SUM(D17:D25) -> 101473 | E26: =SUM(E17:E25) -> 0 | F26: =SUM(F17:F25) -> 18990 | G26: =SUM(G17:G25) -> 37975.52 | H26: =SUM(H17:H25) -> 2964.87 | I26: =SUM(I17:I25) -> 40940.39 | J26: =SUM(J17:J25) -> 60532.61
B28: Section 481(a) Adjustment — Regular Tax
B29: Depreciation reported previously | D29: =I13 -> 39745.12
B30: Cost Segregation Corrected Depreciation | D30: =I26 -> 40940.39
B31: Section 481(a) Adjustment — Regular Tax | D31: =D29-D30 -> -1195.27
A33: CALCULATION OF §481(a) ADJUSTMENT — AMT
A34: As Previously Filed — AMT
A35: Asset | B35: Property Description | C35: Date In Service | D35: Cost | E35: Sec 179 Exp | F35: Bonus Amt | G35: AMT Prior Depreciation | H35: AMT Current Depreciation | I35: End Depreciation | J35: Net Book Value | K35: Method | L35: Period
A36: 1 | B36: 17 - Land Improvements - Ames | C36: 12/08/17 | D36: 6088 | E36: 0 | F36: 0 | G36: 2882.61 | H36: 359.5 | I36: =G36+H36 -> 3242.11 | J36: =D36-I36 -> 2845.89 | K36: 150DB | L36: 15.0
A37: 2 | B37: 18 - Buidling - Ames | C37: 12/08/17 | D37: 79149 | E37: 0 | F37: 0 | G37: 17388.86 | H37: 2878.15 | I37: =G37+H37 -> 20267.01 | J37: =D37-I37 -> 58881.99 | K37: S/L | L37: 27.5
A38: 3 | B38: 19 - Equpiment - Ames | C38: 12/08/17 | D38: 16236 | E38: 0 | F38: 16236 | G38: 16236 | H38: 0 | I38: =G38+H38 -> 16236 | J38: =D38-I38 -> 0 | K38: 200DB | L38: 5.0
B39: Grand Total | D39: =SUM(D36:D38) -> 101473 | E39: =SUM(E36:E38) -> 0 | F39: =SUM(F36:F38) -> 16236 | G39: =SUM(G36:G38) -> 36507.47 | H39: =SUM(H36:H38) -> 3237.65 | I39: =SUM(I36:I38) -> 39745.12 | J39: =SUM(J36:J38) -> 61727.88
A41: After Cost Segregation Correction — AMT
A42: Asset | B42: Property Description | C42: Date In Service | D42: Cost | E42: Sec 179 Exp | F42: Bonus Amt | G42: AMT Prior Depreciation | H42: AMT Current Depreciation | I42: End Depreciation | J42: Net Book Value | K42: Method | L42: Period
A43: 1 | B43: 17 - Land Improvements - Ames - 5yr | C43: 12/08/17 | D43: 1050 | E43: 0 | F43: 0 | G43: 1050 | H43: 0 | I43: =G43+H43 -> 1050 | J43: =D43-I43 -> 0 | K43: 200DB | L43: 5.0
A44: 2 | B44: 17 - Land Improvements - Ames - 15yr | C44: 12/08/17 | D44: 162 | E44: 0 | F44: 0 | G44: 80.7 | H44: 9.56 | I44: =G44+H44 -> 90.26 | J44: =D44-I44 -> 71.74 | K44: 150DB | L44: 15.0
A45: 3 | B45: 17 - Land Improvements - Ames - 27.5yr | C45: 12/08/17 | D45: 4876 | E45: 0 | F45: 0 | G45: 1071.25 | H45: 177.31 | I45: =G45+H45 -> 1248.56 | J45: =D45-I45 -> 3627.44 | K45: S/L | L45: 27.5
A46: 4 | B46: 18 - Buidling - Ames - 5yr | C46: 12/08/17 | D46: 13650 | E46: 0 | F46: 13650 | G46: 13650 | H46: 0 | I46: =G46+H46 -> 13650 | J46: =D46-I46 -> 0 | K46: 200DB | L46: 5.0
A47: 5 | B47: 18 - Buidling - Ames - 15yr | C47: 12/08/17 | D47: 2108 | E47: 0 | F47: 2108 | G47: 2108 | H47: 0 | I47: =G47+H47 -> 2108 | J47: =D47-I47 -> 0 | K47: 150DB | L47: 15.0
A48: 6 | B48: 18 - Buidling - Ames - 27.5yr | C48: 12/08/17 | D48: 63391 | E48: 0 | F48: 0 | G48: 13926.83 | H48: 2305.13 | I48: =G48+H48 -> 16231.96 | J48: =D48-I48 -> 47159.04 | K48: S/L | L48: 27.5
A49: 7 | B49: 19 - Equpiment - Ames - 5yr | C49: 12/08/17 | D49: 2800 | E49: 0 | F49: 2800 | G49: 2800 | H49: 0 | I49: =G49+H49 -> 2800 | J49: =D49-I49 -> 0 | K49: 200DB | L49: 5.0
A50: 8 | B50: 19 - Equpiment - Ames - 15yr | C50: 12/08/17 | D50: 432 | E50: 0 | F50: 432 | G50: 432 | H50: 0 | I50: =G50+H50 -> 432 | J50: =D50-I50 -> 0 | K50: 150DB | L50: 15.0
A51: 9 | B51: 19 - Equpiment - Ames - 27.5yr | C51: 12/08/17 | D51: 13004 | E51: 0 | F51: 0 | G51: 2856.74 | H51: 472.87 | I51: =G51+H51 -> 3329.61 | J51: =D51-I51 -> 9674.39 | K51: S/L | L51: 27.5
B52: Grand Total | D52: =SUM(D43:D51) -> 101473 | E52: =SUM(E43:E51) -> 0 | F52: =SUM(F43:F51) -> 18990 | G52: =SUM(G43:G51) -> 37975.52 | H52: =SUM(H43:H51) -> 2964.87 | I52: =SUM(I43:I51) -> 40940.39 | J52: =SUM(J43:J51) -> 60532.61
B54: Section 481(a) Adjustment — AMT
B55: Depreciation reported previously | D55: =I39 -> 39745.12
B56: Cost Segregation Corrected Depreciation | D56: =I52 -> 40940.39
B57: Section 481(a) Adjustment — AMT | D57: =D55-D56 -> -1195.27
A59: COST SEGREGATION STUDY — COST SUMMARY
B60: Total Building Cost | D60: =D107 -> 50736.5
B61: Building Components: 5 Year | D61: =F107 -> 8750.07
B62: % of Cost | D62: =F108 -> 0.17246105
B63: Site Improvements: 15 Year | D63: =H107 -> 1351.32
B64: % of Cost | D64: =H108 -> 0.02663408
B65: Building Structure: 27.5 Year | D65: =J107 -> 40635.11
B66: % of Cost | D66: =J108 -> 0.80090487
A68: COST SEGREGATION STUDY — COST DETAIL
B69: Property Category | D69: Cost | F69: 5 Year | H69: 15 Year | J69: 27.5 Year
B70: Building Components
B71: Cabinets / Millwork | D71: =SUM(F71:J71) -> 1413.34 | F71: 1413.34
B72: Moldings | D72: =SUM(F72:J72) -> 704.98 | F72: 704.98
B73: Flooring - Vinyl Tile | D73: =SUM(F73:J73) -> 115.67 | F73: 115.67
B74: Flooring - Carpet | D74: =SUM(F74:J74) -> 2552.89 | F74: 2552.89
B75: Flooring - Wood Laminate | D75: =SUM(F75:J75) -> 74.24 | F75: 74.24
B76: Security System | D76: =SUM(F76:J76) -> 503.17 | F76: 503.17
B77: Window Treatments | D77: =SUM(F77:J77) -> 417.2 | F77: 417.2
B78: Specialty HVAC - Dryer Vents | D78: =SUM(F78:J78) -> 42.81 | F78: 42.81
B79: Building Signage | D79: =SUM(F79:J79) -> 21.12 | F79: 21.12
B80: Specialty Electrical - Appliances | D80: =SUM(F80:J80) -> 731.07 | F80: 731.07
B81: Communication / Data | D81: =SUM(F81:J81) -> 338.82 | F81: 338.82
B82: Specialty Plumbing - Kitchen Sink / Laundry | D82: =SUM(F82:J82) -> 800.46 | F82: 800.46
... B84: Appliances | D84: =SUM(F84:J84) -> 801.88 | F84: 801.88
B85: Site Work / Improvements
B86: Driveway | D86: =SUM(F86:J86) -> 1053.33 | H86: 1053.33
B87: Sidewalks / Curbs | D87: =SUM(F87:J87) -> 217.91 | H87: 217.91
B88: Exterior Equipment Concrete Pads | D88: =SUM(F88:J88) -> 49.43 | H88: 49.43
B89: Mailboxes | D89: =SUM(F89:J89) -> 30.65 | H89: 30.65
B90: Building Structure
B91: Roofing Systems | D91: =SUM(F91:J91) -> 3154.94 | J91: 3154.94
B92: Foundations | D92: =SUM(F92:J92) -> 5238.39 | J92: 5238.39
B93: HVAC | D93: =SUM(F93:J93) -> 3486.17 | J93: 3486.17
B94: Electrical | D94: =SUM(F94:J94) -> 3390.72 | J94: 3390.72
B95: Plumbing | D95: =SUM(F95:J95) -> 3067.72 | J95: 3067.72
B96: Fire Protection & Alarm | D96: =SUM(F96:J96) -> 213.56 | J96: 213.56
B97: Exterior Façade / Building Skin | D97: =SUM(F97:J97) -> 1769.68 | J97: 1769.68
B98: Doors & Frames | D98: =SUM(F98:J98) -> 2247.15 | J98: 2247.15
B99: Windows | D99: =SUM(F99:J99) -> 1838.84 | J99: 1838.84
B100: Ceiling Systems | D100: =SUM(F100:J100) -> 1800.68 | J100: 1800.68
B101: Interior Framing / Partitions | D101: =SUM(F101:J101) -> 5040.91 | J101: 5040.91
B102: Painting | D102: =SUM(F102:J102) -> 1719.87 | J102: 1719.87
... B106: Cabinets / Millwork - Restrooms | D106: =SUM(F106:J106) -> 550.2 | J106: 550.2
B107: Total Building Cost | D107: =SUM(D70:D106) -> 50736.5 | F107: =SUM(F70:F106) -> 8750.07 | H107: =SUM(H70:H106) -> 1351.32 | J107: =SUM(J70:J106) -> 40635.11
B108: % of Cost | F108: =F107/D107 -> 0.17246105 | H108: =H107/D107 -> 0.02663408 | J108: =J107/D107 -> 0.80090487
A110: ASSET ALLOCATION (per After Cost Segregation schedule)
B111: Asset (as reclassified) | D111: Cost | F111: 5 Year | H111: 15 Year | J111: 27.5 Year
B112: ='540 Freedom'!B17 -> 17 - Land Improvements - Ames - 5yr | D112: =SUM(F112:J112) -> 1050 | F112: ='540 Freedom'!D17 -> 1050
B113: ='540 Freedom'!B18 -> 17 - Land Improvements - Ames - 15yr | D113: =SUM(F113:J113) -> 162 | H113: ='540 Freedom'!D18 -> 162
...

Sheet 1208 Smith
A1: Marrero 3 LP
A2: Marrero 3 — 530 Ames Blvd, Marrero, LA 70072
A3: EIN: 82-2324040 · FYE: December 31, 2024 · Year of Change: 1/1/2024
A4: 1208 Smith — Attachment to Form 3115 (DCN #7, Rev. Proc. 2024-23 §6.01)
A5: Source: CSSI Report #107752-18, "#107752-18_Marrero 3 - 3115 Combined.pdf"
A7: CALCULATION OF §481(a) ADJUSTMENT — REGULAR TAX
A8: As Previously Filed
A9: Asset | B9: Property Description | C9: Date In Service | D9: Cost | E9: Sec 179 Exp | F9: Bonus Amt | G9: Tax Prior Depreciation | H9: Tax Current Depreciation | I9: End Depreciation | J9: Net Book Value | K9: Method | L9: Period
A10: 1 | B10: 12 - Land Improvements - Smith Square | C10: 12/08/17 | D10: 43832 | E10: 0 | F10: 0 | G10: 20753.56 | H10: 2588.37 | I10: =G10+H10 -> 23341.93 | J10: =D10-I10 -> 20490.07 | K10: 150DB | L10: 15.0
A11: 2 | B11: 13 - Buidling - Smith Square | C11: 12/08/17 | D11: 569814 | E11: 0 | F11: 0 | G11: 125185.59 | H11: 20720.33 | I11: =G11+H11 -> 145905.92 | J11: =D11-I11 -> 423908.08 | K11: S/L | L11: 27.5
A12: 3 | B12: 14 - Equpiment - Smith Square | C12: 12/08/17 | D12: 116885 | E12: 0 | F12: 116885 | G12: 116885 | H12: 0 | I12: =G12+H12 -> 116885 | J12: =D12-I12 -> 0 | K12: 200DB | L12: 5.0
B13: Grand Total | D13: =SUM(D10:D12) -> 730531 | E13: =SUM(E10:E12) -> 0 | F13: =SUM(F10:F12) -> 116885 | G13: =SUM(G10:G12) -> 262824.15 | H13: =SUM(H10:H12) -> 23308.7 | I13: =SUM(I10:I12) -> 286132.85 | J13: =SUM(J10:J12) -> 444398.15
A15: After Cost Segregation Correction
A16: Asset | B16: Property Description | C16: Date In Service | D16: Cost | E16: Sec 179 Exp | F16: Bonus Amt | G16: Tax Prior Depreciation | H16: Tax Current Depreciation | I16: End Depreciation | J16: Net Book Value | K16: Method | L16: Period
A17: 1 | B17: 12 - Land Improvements - Smith Square - 5yr | C17: 12/08/17 | D17: 8155 | E17: 0 | F17: 0 | G17: 8155 | H17: 0 | I17: =G17+H17 -> 8155 | J17: =D17-I17 -> 0 | K17: 200DB | L17: 5.0
A18: 2 | B18: 12 - Land Improvements - Smith Square - 15yr | C18: 12/08/17 | D18: 1280 | E18: 0 | F18: 0 | G18: 1280 | H18: 0 | I18: =G18+H18 -> 1280 | J18: =D18-I18 -> 0 | K18: 150DB | L18: 15.0
A19: 3 | B19: 12 - Land Improvements - Smith Square - 275yr | C19: 12/08/17 | D19: 34397 | E19: 0 | F19: 0 | G19: 7556.92 | H19: 1250.8 | I19: =G19+H19 -> 8807.72 | J19: =D19-I19 -> 25589.28 | K19: S/L | L19: 27.5
A20: 4 | B20: 13 - Buidling - Smith Square - 5yr | C20: 12/08/17 | D20: 106017 | E20: 0 | F20: 106017 | G20: 106017 | H20: 0 | I20: =G20+H20 -> 106017 | J20: =D20-I20 -> 0 | K20: 200DB | L20: 5.0
A21: 5 | B21: 13 - Buidling - Smith Square - 15yr | C21: 12/08/17 | D21: 16634 | E21: 0 | F21: 16634 | G21: 16634 | H21: 0 | I21: =G21+H21 -> 16634 | J21: =D21-I21 -> 0 | K21: 150DB | L21: 15.0
A22: 6 | B22: 13 - Buidling - Smith Square - 27.5yr | C22: 12/08/17 | D22: 447163 | E22: 0 | F22: 0 | G22: 98240.34 | H22: 16260.47 | I22: =G22+H22 -> 114500.81 | J22: =D22-I22 -> 332662.19 | K22: S/L | L22: 27.5
A23: 7 | B23: 14 - Equpiment - Smith Square - 5yr | C23: 12/08/17 | D23: 21747 | E23: 0 | F23: 21747 | G23: 21747 | H23: 0 | I23: =G23+H23 -> 21747 | J23: =D23-I23 -> 0 | K23: 200DB | L23: 5.0
A24: 8 | B24: 14 - Equpiment - Smith Square - 15yr | C24: 12/08/17 | D24: 3412 | E24: 0 | F24: 3412 | G24: 3412 | H24: 0 | I24: =G24+H24 -> 3412 | J24: =D24-I24 -> 0 | K24: 150DB | L24: 15.0
A25: 9 | B25: 14 - Equpiment - Smith Square - 27.5yr | C25: 12/08/17 | D25: 91726 | E25: 0 | F25: 0 | G25: 20151.92 | H25: 3335.49 | I25: =G25+H25 -> 23487.41 | J25: =D25-I25 -> 68238.59 | K25: S/L | L25: 27.5
B26: Grand Total | D26: =SUM(D17:D25) -> 730531 | E26: =SUM(E17:E25) -> 0 | F26: =SUM(F17:F25) -> 147810 | G26: =SUM(G17:G25) -> 283194.18 | H26: =SUM(H17:H25) -> 20846.76 | I26: =SUM(I17:I25) -> 304040.94 | J26: =SUM(J17:J25) -> 426490.06
B28: Section 481(a) Adjustment — Regular Tax
B29: Depreciation reported previously | D29: =I13 -> 286132.85
B30: Cost Segregation Corrected Depreciation | D30: =I26 -> 304040.94
B31: Section 481(a) Adjustment — Regular Tax | D31: =D29-D30 -> -17908.09
A33: CALCULATION OF §481(a) ADJUSTMENT — AMT
A34: As Previously Filed — AMT
A35: Asset | B35: Property Description | C35: Date In Service | D35: Cost | E35: Sec 179 Exp | F35: Bonus Amt | G35: AMT Prior Depreciation | H35: AMT Current Depreciation | I35: End Depreciation | J35: Net Book Value | K35: Method | L35: Period
A36: 1 | B36: 12 - Land Improvements - Smith Square | C36: 12/08/17 | D36: 43832 | E36: 0 | F36: 0 | G36: 20753.56 | H36: 2588.37 | I36: =G36+H36 -> 23341.93 | J36: =D36-I36 -> 20490.07 | K36: 150DB | L36: 15.0
A37: 2 | B37: 13 - Buidling - Smith Square | C37: 12/08/17 | D37: 569814 | E37: 0 | F37: 0 | G37: 125185.59 | H37: 20720.33 | I37: =G37+H37 -> 145905.92 | J37: =D37-I37 -> 423908.08 | K37: S/L | L37: 27.5
A38: 3 | B38: 14 - Equpiment - Smith Square | C38: 12/08/17 | D38: 116885 | E38: 0 | F38: 116885 | G38: 116885 | H38: 0 | I38: =G38+H38 -> 116885 | J38: =D38-I38 -> 0 | K38: 200DB | L38: 5.0
B39: Grand Total | D39: =SUM(D36:D38) -> 730531 | E39: =SUM(E36:E38) -> 0 | F39: =SUM(F36:F38) -> 116885 | G39: =SUM(G36:G38) -> 262824.15 | H39: =SUM(H36:H38) -> 23308.7 | I39: =SUM(I36:I38) -> 286132.85 | J39: =SUM(J36:J38) -> 444398.15
A41: After Cost Segregation Correction — AMT
A42: Asset | B42: Property Description | C42: Date In Service | D42: Cost | E42: Sec 179 Exp | F42: Bonus Amt | G42: AMT Prior Depreciation | H42: AMT Current Depreciation | I42: End Depreciation | J42: Net Book Value | K42: Method | L42: Period
A43: 1 | B43: 12 - Land Improvements - Smith Square - 5yr | C43: 12/08/17 | D43: 8155 | E43: 0 | F43: 0 | G43: 8155 | H43: 0 | I43: =G43+H43 -> 8155 | J43: =D43-I43 -> 0 | K43: 200DB | L43: 5.0
A44: 2 | B44: 12 - Land Improvements - Smith Square - 15yr | C44: 12/08/17 | D44: 1280 | E44: 0 | F44: 0 | G44: 1280 | H44: 0 | I44: =G44+H44 -> 1280 | J44: =D44-I44 -> 0 | K44: 150DB | L44: 15.0
A45: 3 | B45: 13 - Buidling - Smith Square - 5yr | C45: 12/08/17 | D45: 106017 | E45: 0 | F45: 106017 | G45: 106017 | H45: 0 | I45: =G45+H45 -> 106017 | J45: =D45-I45 -> 0 | K45: 200DB | L45: 5.0
A46: 4 | B46: 13 - Buidling - Smith Square - 15yr | C46: 12/08/17 | D46: 16634 | E46: 0 | F46: 16634 | G46: 16634 | H46: 0 | I46: =G46+H46 -> 16634 | J46: =D46-I46 -> 0 | K46: 150DB | L46: 15.0
A47: 5 | B47: 13 - Buidling - Smith Square - 27.5yr | C47: 12/08/17 | D47: 447163 | E47: 0 | F47: 0 | G47: 98240.34 | H47: 16260.47 | I47: =G47+H47 -> 114500.81 | J47: =D47-I47 -> 332662.19 | K47: S/L | L47: 27.5
A48: 6 | B48: 14 - Equpiment - Smith Square - 5yr | C48: 12/08/17 | D48: 21747 | E48: 0 | F48: 21747 | G48: 21747 | H48: 0 | I48: =G48+H48 -> 21747 | J48: =D48-I48 -> 0 | K48: 200DB | L48: 5.0
A49: 7 | B49: 14 - Equpiment - Smith Square - 15yr | C49: 12/08/17 | D49: 3412 | E49: 0 | F49: 3412 | G49: 3412 | H49: 0 | I49: =G49+H49 -> 3412 | J49: =D49-I49 -> 0 | K49: 150DB | L49: 15.0
A50: 8 | B50: 14 - Equpiment - Smith Square - 27.5yr | C50: 12/08/17 | D50: 91726 | E50: 0 | F50: 0 | G50: 20151.92 | H50: 3335.49 | I50: =G50+H50 -> 23487.41 | J50: =D50-I50 -> 68238.59 | K50: S/L | L50: 27.5
B51: Grand Total | D51: =SUM(D43:D50) -> 696134 | E51: =SUM(E43:E50) -> 0 | F51: =SUM(F43:F50) -> 147810 | G51: =SUM(G43:G50) -> 275637.26 | H51: =SUM(H43:H50) -> 19595.96 | I51: =SUM(I43:I50) -> 295233.22 | J51: =SUM(J43:J50) -> 400900.78
B53: Section 481(a) Adjustment — AMT
B54: Depreciation reported previously | D54: =I39 -> 286132.85
B55: Cost Segregation Corrected Depreciation | D55: =I51 -> 295233.22
B56: Section 481(a) Adjustment — AMT | D56: =D54-D55 -> -9100.37
A58: COST SEGREGATION STUDY — COST SUMMARY
B59: Total Building Cost | D59: =D105 -> 37087.18
B60: Building Components: 5 Year | D60: =F105 -> 6317.92
B61: % of Cost | D61: =F106 -> 0.17035321
B62: Site Improvements: 15 Year | D62: =H105 -> 1120.51
B63: % of Cost | D63: =H106 -> 0.030212866
B64: Building Structure: 27.5 Year | D64: =J105 -> 29648.75
B65: % of Cost | D65: =J106 -> 0.79943393
A67: COST SEGREGATION STUDY — COST DETAIL
B68: Property Category | D68: Cost | F68: 5 Year | H68: 15 Year | J68: 27.5 Year
B69: Building Components
B70: Cabinets / Millwork | D70: =SUM(F70:J70) -> 857.75 | F70: 857.75
B71: Moldings | D71: =SUM(F71:J71) -> 846.07 | F71: 846.07
B72: Flooring - Wood Laminate | D72: =SUM(F72:J72) -> 2095.24 | F72: 2095.24
B73: Security System | D73: =SUM(F73:J73) -> 326.42 | F73: 326.42
B74: Window Treatments | D74: =SUM(F74:J74) -> 208.64 | F74: 208.64
B75: Specialty HVAC - Dryer Vents | D75: =SUM(F75:J75) -> 27.77 | F75: 27.77
B76: Building Signage | D76: =SUM(F76:J76) -> 18.26 | F76: 18.26
B77: Specialty Electrical - Appliances | D77: =SUM(F77:J77) -> 474.3 | F77: 474.3
B78: Communication / Data | D78: =SUM(F78:J78) -> 274.37 | F78: 274.37
B79: Specialty Plumbing - Kitchen Sink / Laundry | D79: =SUM(F79:J79) -> 519.3 | F79: 519.3
B80: Security / Exterior Lighting | D80: =SUM(F80:J80) -> 103 | F80: 103
B81: Access Control | D81: =SUM(F81:J81) -> 46.57 | F81: 46.57
B82: Appliances | D82: =SUM(F82:J82) -> 520.23 | F82: 520.23
B83: Site Work / Improvements
B84: Driveway | D84: =SUM(F84:J84) -> 938.31 | H84: 938.31
B85: Sidewalks / Curbs | D85: =SUM(F85:J85) -> 130.23 | H85: 130.23
B86: Exterior Equipment Concrete Pads | D86: =SUM(F86:J86) -> 32.07 | H86: 32.07
B87: Mailboxes | D87: =SUM(F87:J87) -> 19.9 | H87: 19.9
B88: Building Structure
B89: Roofing Systems | D89: =SUM(F89:J89) -> 2029.7 | J89: 2029.7
B90: Foundations | D90: =SUM(F90:J90) -> 4782.96 | J90: 4782.96
B91: HVAC | D91: =SUM(F91:J91) -> 2829.99 | J91: 2829.99
B92: Electrical | D92: =SUM(F92:J92) -> 2863.54 | J92: 2863.54
B93: Plumbing | D93: =SUM(F93:J93) -> 2484.23 | J93: 2484.23
B94: Fire Protection & Alarm | D94: =SUM(F94:J94) -> 138.55 | J94: 138.55
B95: Exterior Façade / Building Skin | D95: =SUM(F95:J95) -> 994.37 | J95: 994.37
B96: Doors & Frames | D96: =SUM(F96:J96) -> 1066.87 | J96: 1066.87
B97: Windows | D97: =SUM(F97:J97) -> 919.58 | J97: 919.58
B98: Ceiling Systems | D98: =SUM(F98:J98) -> 1434.53 | J98: 1434.53
B99: Interior Framing / Partitions | D99: =SUM(F99:J99) -> 3724.72 | J99: 3724.72
B100: Painting | D100: =SUM(F100:J100) -> 1303.94 | J100: 1303.94
... B104: Cabinets / Millwork - Restrooms | D104: =SUM(F104:J104) -> 256.73 | J104: 256.73
B105: Total Building Cost | D105: =SUM(D69:D104) -> 37087.18 | F105: =SUM(F69:F104) -> 6317.92 | H105: =SUM(H69:H104) -> 1120.51 | J105: =SUM(J69:J104) -> 29648.75
B106: % of Cost | F106: =F105/D105 -> 0.17035321 | H106: =H105/D105 -> 0.030212866 | J106: =J105/D105 -> 0.79943393
A108: ASSET ALLOCATION (per After Cost Segregation schedule)
B109: Asset (as reclassified) | D109: Cost | F109: 5 Year | H109: 15 Year | J109: 27.5 Year
B110: ='1208 Smith'!B17 -> 12 - Land Improvements - Smith Square - 5yr | D110: =SUM(F110:J110) -> 8155 | F110: ='1208 Smith'!D17 -> 8155
B111: ='1208 Smith'!B18 -> 12 - Land Improvements - Smith Square - 15yr | D111: =SUM(F111:J111) -> 1280 | H111: ='1208 Smith'!D18 -> 1280
B112: ='1208 Smith'!B19 -> 12 - Land Improvements - Smith Square - 275yr | D112: =SUM(F112:J112) -> 34397 | J112: ='1208 Smith'!D19 -> 34397
...

Sheet 1209 Smith
A1: Marrero 3 LP
A2: Marrero 3 — 530 Ames Blvd, Marrero, LA 70072
A3: EIN: 82-2324040 · FYE: December 31, 2024 · Year of Change: 1/1/2024
A4: 1209 Smith — Attachment to Form 3115 (DCN #7, Rev. Proc. 2024-23 §6.01)
A5: Source: CSSI Report #107752-18, "#107752-18_Marrero 3 - 3115 Combined.pdf"
A7: CALCULATION OF §481(a) ADJUSTMENT — REGULAR TAX
A8: As Previously Filed
A9: Asset | B9: Property Description | C9: Date In Service | D9: Cost | E9: Sec 179 Exp | F9: Bonus Amt | G9: Tax Prior Depreciation | H9: Tax Current Depreciation | I9: End Depreciation | J9: Net Book Value | K9: Method | L9: Period
A10: 1 | B10: 12 - Land Improvements - Smith Square | C10: 12/08/17 | D10: 8901 | E10: 0 | F10: 0 | G10: 4214.44 | H10: 525.63 | I10: =G10+H10 -> 4740.07 | J10: =D10-I10 -> 4160.93 | K10: 150DB | L10: 15.0
A11: 2 | B11: 13 - Buidling - Smith Square | C11: 12/08/17 | D11: 115712 | E11: 0 | F11: 0 | G11: 25421.41 | H11: 4207.67 | I11: =G11+H11 -> 29629.08 | J11: =D11-I11 -> 86082.92 | K11: S/L | L11: 27.5
A12: 3 | B12: 14 - Equpiment - Smith Square | C12: 12/08/17 | D12: 23736 | E12: 0 | F12: 23736 | G12: 23736 | H12: 0 | I12: =G12+H12 -> 23736 | J12: =D12-I12 -> 0 | K12: 200DB | L12: 5.0
B13: Grand Total | D13: =SUM(D10:D12) -> 148349 | E13: =SUM(E10:E12) -> 0 | F13: =SUM(F10:F12) -> 23736 | G13: =SUM(G10:G12) -> 53371.85 | H13: =SUM(H10:H12) -> 4733.3 | I13: =SUM(I10:I12) -> 58105.15 | J13: =SUM(J10:J12) -> 90243.85
A15: After Cost Segregation Correction
A16: Asset | B16: Property Description | C16: Date In Service | D16: Cost | E16: Sec 179 Exp | F16: Bonus Amt | G16: Tax Prior Depreciation | H16: Tax Current Depreciation | I16: End Depreciation | J16: Net Book Value | K16: Method | L16: Period
A17: 1 | B17: 12 - Land Improvements - Smith Square - 5yr | C17: 12/08/17 | D17: 1516 | E17: 0 | F17: 0 | G17: 1516 | H17: 0 | I17: =G17+H17 -> 1516 | J17: =D17-I17 -> 0 | K17: 200DB | L17: 5.0
A18: 2 | B18: 12 - Land Improvements - Smith Square - 15yr | C18: 12/08/17 | D18: 269 | E18: 0 | F18: 269 | G18: 269 | H18: 0 | I18: =G18+H18 -> 269 | J18: =D18-I18 -> 0 | K18: 150DB | L18: 15.0
A19: 3 | B19: 12 - Land Improvements - Smith Square - 275yr | C19: 12/08/17 | D19: 7116 | E19: 0 | F19: 0 | G19: 1563.34 | H19: 258.76 | I19: =G19+H19 -> 1822.1 | J19: =D19-I19 -> 5293.9 | K19: S/L | L19: 27.5
A20: 4 | B20: 13 - Buidling - Smith Square - 5yr | C20: 12/08/17 | D20: 19712 | E20: 0 | F20: 19712 | G20: 19712 | H20: 0 | I20: =G20+H20 -> 19712 | J20: =D20-I20 -> 0 | K20: 200DB | L20: 5.0
A21: 5 | B21: 13 - Buidling - Smith Square - 15yr | C21: 12/08/17 | D21: 3496 | E21: 0 | F21: 3496 | G21: 3496 | H21: 0 | I21: =G21+H21 -> 3496 | J21: =D21-I21 -> 0 | K21: 150DB | L21: 15.0
A22: 6 | B22: 13 - Buidling - Smith Square - 27.5yr | C22: 12/08/17 | D22: 92504 | E22: 0 | F22: 0 | G22: 20322.84 | H22: 3363.78 | I22: =G22+H22 -> 23686.62 | J22: =D22-I22 -> 68817.38 | K22: S/L | L22: 27.5
A23: 7 | B23: 14 - Equpiment - Smith Square - 5yr | C23: 12/08/17 | D23: 4043 | E23: 0 | F23: 4043 | G23: 4043 | H23: 0 | I23: =G23+H23 -> 4043 | J23: =D23-I23 -> 0 | K23: 200DB | L23: 5.0
A24: 8 | B24: 14 - Equpiment - Smith Square - 15yr | C24: 12/08/17 | D24: 717 | E24: 0 | F24: 717 | G24: 717 | H24: 0 | I24: =G24+H24 -> 717 | J24: =D24-I24 -> 0 | K24: 150DB | L24: 15.0
A25: 9 | B25: 14 - Equpiment - Smith Square - 27.5yr | C25: 12/08/17 | D25: 18976 | E25: 0 | F25: 0 | G25: 4168.75 | H25: 690.04 | I25: =G25+H25 -> 4858.79 | J25: =D25-I25 -> 14117.21 | K25: S/L | L25: 27.5
B26: Grand Total | D26: =SUM(D17:D25) -> 148349 | E26: =SUM(E17:E25) -> 0 | F26: =SUM(F17:F25) -> 28237 | G26: =SUM(G17:G25) -> 55807.93 | H26: =SUM(H17:H25) -> 4312.58 | I26: =SUM(I17:I25) -> 60120.51 | J26: =SUM(J17:J25) -> 88228.49
B28: Section 481(a) Adjustment — Regular Tax
B29: Depreciation reported previously | D29: =I13 -> 58105.15
B30: Cost Segregation Corrected Depreciation | D30: =I26 -> 60120.51
B31: Section 481(a) Adjustment — Regular Tax | D31: =D29-D30 -> -2015.36
A33: CALCULATION OF §481(a) ADJUSTMENT — AMT
A34: As Previously Filed — AMT
A35: Asset | B35: Property Description | C35: Date In Service | D35: Cost | E35: Sec 179 Exp | F35: Bonus Amt | G35: AMT Prior Depreciation | H35: AMT Current Depreciation | I35: End Depreciation | J35: Net Book Value | K35: Method | L35: Period
A36: 1 | B36: 12 - Land Improvements - Smith Square | C36: 12/08/17 | D36: 8901 | E36: 0 | F36: 0 | G36: 4214.44 | H36: 525.63 | I36: =G36+H36 -> 4740.07 | J36: =D36-I36 -> 4160.93 | K36: 150DB | L36: 15.0
A37: 2 | B37: 13 - Buidling - Smith Square | C37: 12/08/17 | D37: 115712 | E37: 0 | F37: 0 | G37: 25421.41 | H37: 4207.67 | I37: =G37+H37 -> 29629.08 | J37: =D37-I37 -> 86082.92 | K37: S/L | L37: 27.5
A38: 3 | B38: 14 - Equpiment - Smith Square | C38: 12/08/17 | D38: 23736 | E38: 0 | F38: 23736 | G38: 23736 | H38: 0 | I38: =G38+H38 -> 23736 | J38: =D38-I38 -> 0 | K38: 200DB | L38: 5.0
B39: Grand Total | D39: =SUM(D36:D38) -> 148349 | E39: =SUM(E36:E38) -> 0 | F39: =SUM(F36:F38) -> 23736 | G39: =SUM(G36:G38) -> 53371.85 | H39: =SUM(H36:H38) -> 4733.3 | I39: =SUM(I36:I38) -> 58105.15 | J39: =SUM(J36:J38) -> 90243.85
A41: After Cost Segregation Correction — AMT
A42: Asset | B42: Property Description | C42: Date In Service | D42: Cost | E42: Sec 179 Exp | F42: Bonus Amt | G42: AMT Prior Depreciation | H42: AMT Current Depreciation | I42: End Depreciation | J42: Net Book Value | K42: Method | L42: Period
A43: 1 | B43: 12 - Land Improvements - Smith Square - 5yr | C43: 12/08/17 | D43: 1516 | E43: 0 | F43: 0 | G43: 1516 | H43: 0 | I43: =G43+H43 -> 1516 | J43: =D43-I43 -> 0 | K43: 200DB | L43: 5.0
A44: 2 | B44: 12 - Land Improvements - Smith Square - 15yr | C44: 12/08/17 | D44: 269 | E44: 0 | F44: 269 | G44: 269 | H44: 0 | I44: =G44+H44 -> 269 | J44: =D44-I44 -> 0 | K44: 150DB | L44: 15.0
A45: 3 | B45: 13 - Buidling - Smith Square - 5yr | C45: 12/08/17 | D45: 19712 | E45: 0 | F45: 19712 | G45: 19712 | H45: 0 | I45: =G45+H45 -> 19712 | J45: =D45-I45 -> 0 | K45: 200DB | L45: 5.0
A46: 4 | B46: 13 - Buidling - Smith Square - 15yr | C46: 12/08/17 | D46: 3496 | E46: 0 | F46: 3496 | G46: 3496 | H46: 0 | I46: =G46+H46 -> 3496 | J46: =D46-I46 -> 0 | K46: 150DB | L46: 15.0
A47: 5 | B47: 13 - Buidling - Smith Square - 27.5yr | C47: 12/08/17 | D47: 92504 | E47: 0 | F47: 0 | G47: 20322.84 | H47: 3363.78 | I47: =G47+H47 -> 23686.62 | J47: =D47-I47 -> 68817.38 | K47: S/L | L47: 27.5
A48: 6 | B48: 14 - Equpiment - Smith Square - 5yr | C48: 12/08/17 | D48: 4043 | E48: 0 | F48: 4043 | G48: 4043 | H48: 0 | I48: =G48+H48 -> 4043 | J48: =D48-I48 -> 0 | K48: 200DB | L48: 5.0
A49: 7 | B49: 14 - Equpiment - Smith Square - 15yr | C49: 12/08/17 | D49: 717 | E49: 0 | F49: 717 | G49: 717 | H49: 0 | I49: =G49+H49 -> 717 | J49: =D49-I49 -> 0 | K49: 150DB | L49: 15.0
A50: 8 | B50: 14 - Equpiment - Smith Square - 27.5yr | C50: 12/08/17 | D50: 18976 | E50: 0 | F50: 0 | G50: 4168.75 | H50: 690.04 | I50: =G50+H50 -> 4858.79 | J50: =D50-I50 -> 14117.21 | K50: S/L | L50: 27.5
B51: Grand Total | D51: =SUM(D43:D50) -> 141233 | E51: =SUM(E43:E50) -> 0 | F51: =SUM(F43:F50) -> 28237 | G51: =SUM(G43:G50) -> 54244.59 | H51: =SUM(H43:H50) -> 4053.82 | I51: =SUM(I43:I50) -> 58298.41 | J51: =SUM(J43:J50) -> 82934.59
B53: Section 481(a) Adjustment — AMT
B54: Depreciation reported previously | D54: =I39 -> 58105.15
B55: Cost Segregation Corrected Depreciation | D55: =I51 -> 58298.41
B56: Section 481(a) Adjustment — AMT | D56: =D54-D55 -> -193.26
A58: COST SEGREGATION STUDY — COST SUMMARY
B59: Total Building Cost | D59: =D105 -> 30438.8
B60: Building Components: 5 Year | D60: =F105 -> 5663.28
B61: % of Cost | D61: =F106 -> 0.18605464
B62: Site Improvements: 15 Year | D62: =H105 -> 888.57
B63: % of Cost | D63: =H106 -> 0.029192018
B64: Building Structure: 27.5 Year | D64: =J105 -> 23886.95
B65: % of Cost | D65: =J106 -> 0.78475334
A67: COST SEGREGATION STUDY — COST DETAIL
B68: Property Category | D68: Cost | F68: 5 Year | H68: 15 Year | J68: 27.5 Year
B69: Building Components
B70: Cabinets / Millwork | D70: =SUM(F70:J70) -> 990.47 | F70: 990.47
B71: Moldings | D71: =SUM(F71:J71) -> 702.07 | F71: 702.07
B72: Flooring - Wood Laminate | D72: =SUM(F72:J72) -> 1541.32 | F72: 1541.32
B73: Security System | D73: =SUM(F73:J73) -> 326.42 | F73: 326.42
B74: Window Treatments | D74: =SUM(F74:J74) -> 191.73 | F74: 191.73
B75: Specialty HVAC - Dryer Vents | D75: =SUM(F75:J75) -> 27.77 | F75: 27.77
B76: Building Signage | D76: =SUM(F76:J76) -> 18.26 | F76: 18.26
B77: Specialty Electrical - Appliances | D77: =SUM(F77:J77) -> 474.3 | F77: 474.3
B78: Communication / Data | D78: =SUM(F78:J78) -> 201.84 | F78: 201.84
B79: Specialty Plumbing - Kitchen Sink / Laundry | D79: =SUM(F79:J79) -> 519.3 | F79: 519.3
B80: Security / Exterior Lighting | D80: =SUM(F80:J80) -> 103 | F80: 103
B81: Access Control | D81: =SUM(F81:J81) -> 46.57 | F81: 46.57
B82: Appliances | D82: =SUM(F82:J82) -> 520.23 | F82: 520.23
B83: Site Work / Improvements
B84: Driveway | D84: =SUM(F84:J84) -> 685.64 | H84: 685.64
B85: Sidewalks / Curbs | D85: =SUM(F85:J85) -> 150.96 | H85: 150.96
B86: Exterior Equipment Concrete Pads | D86: =SUM(F86:J86) -> 32.07 | H86: 32.07
B87: Mailboxes | D87: =SUM(F87:J87) -> 19.9 | H87: 19.9
B88: Building Structure
B89: Roofing Systems | D89: =SUM(F89:J89) -> 1795.53 | J89: 1795.53
B90: Foundations | D90: =SUM(F90:J90) -> 3640.65 | J90: 3640.65
B91: HVAC | D91: =SUM(F91:J91) -> 2074.48 | J91: 2074.48
B92: Electrical | D92: =SUM(F92:J92) -> 1981.12 | J92: 1981.12
B93: Plumbing | D93: =SUM(F93:J93) -> 1827.48 | J93: 1827.48
B94: Fire Protection & Alarm | D94: =SUM(F94:J94) -> 110.84 | J94: 110.84
B95: Exterior Façade / Building Skin | D95: =SUM(F95:J95) -> 1031.81 | J95: 1031.81
B96: Doors & Frames | D96: =SUM(F96:J96) -> 953.01 | J96: 953.01
B97: Windows | D97: =SUM(F97:J97) -> 845.03 | J97: 845.03
B98: Ceiling Systems | D98: =SUM(F98:J98) -> 1080.49 | J98: 1080.49
B99: Interior Framing / Partitions | D99: =SUM(F99:J99) -> 3076.64 | J99: 3076.64
B100: Painting | D100: =SUM(F100:J100) -> 1043.32 | J100: 1043.32
... B104: Cabinets / Millwork - Restrooms | D104: =SUM(F104:J104) -> 427.48 | J104: 427.48
B105: Total Building Cost | D105: =SUM(D69:D104) -> 30438.8 | F105: =SUM(F69:F104) -> 5663.28 | H105: =SUM(H69:H104) -> 888.57 | J105: =SUM(J69:J104) -> 23886.95
B106: % of Cost | F106: =F105/D105 -> 0.18605464 | H106: =H105/D105 -> 0.029192018 | J106: =J105/D105 -> 0.78475334
A108: ASSET ALLOCATION (per After Cost Segregation schedule)
B109: Asset (as reclassified) | D109: Cost | F109: 5 Year | H109: 15 Year | J109: 27.5 Year
B110: ='1209 Smith'!B17 -> 12 - Land Improvements - Smith Square - 5yr | D110: =SUM(F110:J110) -> 1516 | F110: ='1209 Smith'!D17 -> 1516
B111: ='1209 Smith'!B18 -> 12 - Land Improvements - Smith Square - 15yr | D111: =SUM(F111:J111) -> 269 | H111: ='1209 Smith'!D18 -> 269
B112: ='1209 Smith'!B19 -> 12 - Land Improvements - Smith Square - 275yr | D112: =SUM(F112:J112) -> 7116 | J112: ='1209 Smith'!D19 -> 7116
...

Sheet 3112 Havenwood
A1: Marrero 3 LP
A2: Marrero 3 — 530 Ames Blvd, Marrero, LA 70072
A3: EIN: 82-2324040 · FYE: December 31, 2024 · Year of Change: 1/1/2024
A4: 3112 Havenwood — Attachment to Form 3115 (DCN #7, Rev. Proc. 2024-23 §6.01)
A5: Source: CSSI Report #107752-18, "#107752-18_Marrero 3 - 3115 Combined.pdf"
A7: CALCULATION OF §481(a) ADJUSTMENT — REGULAR TAX
A8: As Previously Filed
A9: Asset | B9: Property Description | C9: Date In Service | D9: Cost | E9: Sec 179 Exp | F9: Bonus Amt | G9: Tax Prior Depreciation | H9: Tax Current Depreciation | I9: End Depreciation | J9: Net Book Value | K9: Method | L9: Period
A10: 1 | B10: 2 - Land Improvements - Havenwood | C10: 12/08/17 | D10: 47472 | E10: 0 | F10: 0 | G10: 22477.31 | H10: 2803.31 | I10: =G10+H10 -> 25280.62 | J10: =D10-I10 -> 22191.38 | K10: 150DB | L10: 15.0
A11: 2 | B11: 3 - Buidling - Havenwood | C11: 12/08/17 | D11: 617127 | E11: 0 | F11: 0 | G11: 135580.9 | H11: 22440.93 | I11: =G11+H11 -> 158021.83 | J11: =D11-I11 -> 459105.17 | K11: S/L | L11: 27.5
A12: 3 | B12: 4 - Equipment - Havenwood | C12: 12/08/17 | D12: 126590 | E12: 0 | F12: 126590 | G12: 126590 | H12: 0 | I12: =G12+H12 -> 126590 | J12: =D12-I12 -> 0 | K12: 200DB | L12: 5.0
B13: Grand Total | D13: =SUM(D10:D12) -> 791189 | E13: =SUM(E10:E12) -> 0 | F13: =SUM(F10:F12) -> 126590 | G13: =SUM(G10:G12) -> 284648.21 | H13: =SUM(H10:H12) -> 25244.24 | I13: =SUM(I10:I12) -> 309892.45 | J13: =SUM(J10:J12) -> 481296.55
A15: After Cost Segregation Correction
A16: Asset | B16: Property Description | C16: Date In Service | D16: Cost | E16: Sec 179 Exp | F16: Bonus Amt | G16: Tax Prior Depreciation | H16: Tax Current Depreciation | I16: End Depreciation | J16: Net Book Value | K16: Method | L16: Period
A17: 1 | B17: 2 - Land Improvements - Havenwood -5yr | C17: 12/08/17 | D17: 8161 | E17: 0 | F17: 0 | G17: 8161 | H17: 0 | I17: =G17+H17 -> 8161 | J17: =D17-I17 -> 0 | K17: 200DB | L17: 5.0
A18: 2 | B18: 2 - Land Improvements - Havenwood -15yr | C18: 12/08/17 | D18: 1164 | E18: 0 | F18: 0 | G18: 1164 | H18: 0 | I18: =G18+H18 -> 1164 | J18: =D18-I18 -> 0 | K18: 150DB | L18: 15.0
A19: 3 | B19: 2 - Land Improvements - Havenwood -27.5yr | C19: 12/08/17 | D19: 38146 | E19: 0 | F19: 0 | G19: 8380.76 | H19: 1387.13 | I19: =G19+H19 -> 9767.89 | J19: =D19-I19 -> 28378.11 | K19: S/L | L19: 27.5
A20: 4 | B20: 13 - Buidling - Havenwood - 5yr | C20: 12/08/17 | D20: 106098 | E20: 0 | F20: 106098 | G20: 106098 | H20: 0 | I20: =G20+H20 -> 106098 | J20: =D20-I20 -> 0 | K20: 200DB | L20: 5.0
A21: 5 | B21: 13 - Buidling - Havenwood - 15yr | C21: 12/08/17 | D21: 15130 | E21: 0 | F21: 15130 | G21: 15130 | H21: 0 | I21: =G21+H21 -> 15130 | J21: =D21-I21 -> 0 | K21: 150DB | L21: 15.0
A22: 6 | B22: 13 - Buidling - Havenwood - 27.5yr | C22: 12/08/17 | D22: 495900 | E22: 0 | F22: 0 | G22: 108947.74 | H22: 18032.73 | I22: =G22+H22 -> 126980.47 | J22: =D22-I22 -> 368919.53 | K22: S/L | L22: 27.5
A23: 7 | B23: 14 - Equipment - Havenwood - 5yr | C23: 12/08/17 | D23: 21764 | E23: 0 | F23: 21764 | G23: 21764 | H23: 0 | I23: =G23+H23 -> 21764 | J23: =D23-I23 -> 0 | K23: 200DB | L23: 5.0
A24: 8 | B24: 14 - Equipment - Havenwood - 15yr | C24: 12/08/17 | D24: 3103 | E24: 0 | F24: 3103 | G24: 3103 | H24: 0 | I24: =G24+H24 -> 3103 | J24: =D24-I24 -> 0 | K24: 150DB | L24: 15.0
A25: 9 | B25: 14 - Equipment - Havenwood - 15yr | C25: 12/08/17 | D25: 101723 | E25: 0 | F25: 0 | G25: 22348.25 | H25: 3699.02 | I25: =G25+H25 -> 26047.27 | J25: =D25-I25 -> 75675.73 | K25: S/L | L25: 27.5
B26: Grand Total | D26: =SUM(D17:D25) -> 791189 | E26: =SUM(E17:E25) -> 0 | F26: =SUM(F17:F25) -> 146095 | G26: =SUM(G17:G25) -> 295096.75 | H26: =SUM(H17:H25) -> 23118.88 | I26: =SUM(I17:I25) -> 318215.63 | J26: =SUM(J17:J25) -> 472973.37
B28: Section 481(a) Adjustment — Regular Tax
B29: Depreciation reported previously | D29: =I13 -> 309892.45
B30: Cost Segregation Corrected Depreciation | D30: =I26 -> 318215.63
B31: Section 481(a) Adjustment — Regular Tax | D31: =D29-D30 -> -8323.18
A33: CALCULATION OF §481(a) ADJUSTMENT — AMT
A34: As Previously Filed — AMT
A35: Asset | B35: Property Description | C35: Date In Service | D35: Cost | E35: Sec 179 Exp | F35: Bonus Amt | G35: AMT Prior Depreciation | H35: AMT Current Depreciation | I35: End Depreciation | J35: Net Book Value | K35: Method | L35: Period
A36: 1 | B36: 2 - Land Improvements - Havenwood | C36: 12/08/17 | D36: 47472 | E36: 0 | F36: 0 | G36: 22477.31 | H36: 2803.31 | I36: =G36+H36 -> 25280.62 | J36: =D36-I36 -> 22191.38 | K36: 150DB | L36: 15.0
A37: 2 | B37: 3 - Buidling - Havenwood | C37: 12/08/17 | D37: 617127 | E37: 0 | F37: 0 | G37: 135580.9 | H37: 22440.93 | I37: =G37+H37 -> 158021.83 | J37: =D37-I37 -> 459105.17 | K37: S/L | L37: 27.5
A38: 3 | B38: 4 - Equipment - Havenwood | C38: 12/08/17 | D38: 126590 | E38: 0 | F38: 126590 | G38: 126590 | H38: 0 | I38: =G38+H38 -> 126590 | J38: =D38-I38 -> 0 | K38: 200DB | L38: 5.0
B39: Grand Total | D39: =SUM(D36:D38) -> 791189 | E39: =SUM(E36:E38) -> 0 | F39: =SUM(F36:F38) -> 126590 | G39: =SUM(G36:G38) -> 284648.21 | H39: =SUM(H36:H38) -> 25244.24 | I39: =SUM(I36:I38) -> 309892.45 | J39: =SUM(J36:J38) -> 481296.55
A41: After Cost Segregation Correction — AMT
A42: Asset | B42: Property Description | C42: Date In Service | D42: Cost | E42: Sec 179 Exp | F42: Bonus Amt | G42: AMT Prior Depreciation | H42: AMT Current Depreciation | I42: End Depreciation | J42: Net Book Value | K42: Method | L42: Period
A43: 1 | B43: 2 - Land Improvements - Havenwood -5yr | C43: 12/08/17 | D43: 8161 | E43: 0 | F43: 0 | G43: 8161 | H43: 0 | I43: =G43+H43 -> 8161 | J43: =D43-I43 -> 0 | K43: 200DB | L43: 5.0
A44: 2 | B44: 2 - Land Improvements - Havenwood -15yr | C44: 12/08/17 | D44: 1164 | E44: 0 | F44: 0 | G44: 1164 | H44: 0 | I44: =G44+H44 -> 1164 | J44: =D44-I44 -> 0 | K44: 150DB | L44: 15.0
A45: 3 | B45: 2 - Land Improvements - Havenwood -27.5yr | C45: 12/08/17 | D45: 38146 | E45: 0 | F45: 0 | G45: 8380.76 | H45: 1387.13 | I45: =G45+H45 -> 9767.89 | J45: =D45-I45 -> 28378.11 | K45: S/L | L45: 27.5
A46: 4 | B46: 13 - Buidling - Havenwood - 5yr | C46: 12/08/17 | D46: 106098 | E46: 0 | F46: 106098 | G46: 106098 | H46: 0 | I46: =G46+H46 -> 106098 | J46: =D46-I46 -> 0 | K46: 200DB | L46: 5.0
A47: 5 | B47: 13 - Buidling - Havenwood - 15yr | C47: 12/08/17 | D47: 15130 | E47: 0 | F47: 15130 | G47: 15130 | H47: 0 | I47: =G47+H47 -> 15130 | J47: =D47-I47 -> 0 | K47: 150DB | L47: 15.0
A48: 6 | B48: 13 - Buidling - Havenwood - 27.5yr | C48: 12/08/17 | D48: 495900 | E48: 0 | F48: 0 | G48: 108947.74 | H48: 18032.73 | I48: =G48+H48 -> 126980.47 | J48: =D48-I48 -> 368919.53 | K48: S/L | L48: 27.5
A49: 7 | B49: 14 - Equipment - Havenwood - 5yr | C49: 12/08/17 | D49: 21764 | E49: 0 | F49: 21764 | G49: 21764 | H49: 0 | I49: =G49+H49 -> 21764 | J49: =D49-I49 -> 0 | K49: 200DB | L49: 5.0
A50: 8 | B50: 14 - Equipment - Havenwood - 15yr | C50: 12/08/17 | D50: 3103 | E50: 0 | F50: 3103 | G50: 3103 | H50: 0 | I50: =G50+H50 -> 3103 | J50: =D50-I50 -> 0 | K50: 150DB | L50: 15.0
A51: 9 | B51: 14 - Equipment - Havenwood - 15yr | C51: 12/08/17 | D51: 101723 | E51: 0 | F51: 0 | G51: 22348.25 | H51: 3699.02 | I51: =G51+H51 -> 26047.27 | J51: =D51-I51 -> 75675.73 | K51: S/L | L51: 27.5
B52: Grand Total | D52: =SUM(D43:D51) -> 791189 | E52: =SUM(E43:E51) -> 0 | F52: =SUM(F43:F51) -> 146095 | G52: =SUM(G43:G51) -> 295096.75 | H52: =SUM(H43:H51) -> 23118.88 | I52: =SUM(I43:I51) -> 318215.63 | J52: =SUM(J43:J51) -> 472973.37
B54: Section 481(a) Adjustment — AMT
B55: Depreciation reported previously | D55: =I39 -> 309892.45
B56: Cost Segregation Corrected Depreciation | D56: =I52 -> 318215.63
B57: Section 481(a) Adjustment — AMT | D57: =D55-D56 -> -8323.18
A59: COST SEGREGATION STUDY — COST SUMMARY
B60: Total Building Cost | D60: =D110 -> 41641.47
B61: Building Components: 5 Year | D61: =F110 -> 7159.08
B62: % of Cost | D62: =F111 -> 0.17192188
B63: Site Improvements: 15 Year | D63: =H110 -> 1020.89
B64: % of Cost | D64: =H111 -> 0.024516185
B65: Building Structure: 27.5 Year | D65: =J110 -> 33461.5
B66: % of Cost | D66: =J111 -> 0.80356193
A68: COST SEGREGATION STUDY — COST DETAIL
B69: Property Category | D69: Cost | F69: 5 Year | H69: 15 Year | J69: 27.5 Year
B70: Building Components
B71: Cabinets / Millwork | D71: =SUM(F71:J71) -> 1065.36 | F71: 1065.36
B72: Moldings | D72: =SUM(F72:J72) -> 894.1 | F72: 894.1
B73: Flooring - Wood Laminate | D73: =SUM(F73:J73) -> 1954.35 | F73: 1954.35
B74: Security System | D74: =SUM(F74:J74) -> 613.8 | F74: 613.8
B75: Door & Window Guards | D75: =SUM(F75:J75) -> 136.47 | F75: 136.47
B76: Window Treatments | D76: =SUM(F76:J76) -> 302.35 | F76: 302.35
B77: Specialty HVAC - Dryer Vents | D77: =SUM(F77:J77) -> 30.15 | F77: 30.15
B78: Building Signage | D78: =SUM(F78:J78) -> 19.82 | F78: 19.82
B79: Specialty Electrical - Appliances | D79: =SUM(F79:J79) -> 514.89 | F79: 514.89
B80: Communication / Data | D80: =SUM(F80:J80) -> 255.92 | F80: 255.92
B81: Specialty Plumbing - Kitchen Sink / Laundry | D81: =SUM(F81:J81) -> 563.75 | F81: 563.75
B82: Security / Exterior Lighting | D82: =SUM(F82:J82) -> 192.79 | F82: 192.79
... B84: Appliances | D84: =SUM(F84:J84) -> 564.76 | F84: 564.76
B85: Site Work / Improvements
B86: Driveway | D86: =SUM(F86:J86) -> 679.12 | H86: 679.12
B87: Sidewalks / Curbs | D87: =SUM(F87:J87) -> 285.36 | H87: 285.36
B88: Exterior Equipment Concrete Pads | D88: =SUM(F88:J88) -> 34.81 | H88: 34.81
B89: Mailboxes | D89: =SUM(F89:J89) -> 21.6 | H89: 21.6
B90: Building Structure
B91: Roofing Systems | D91: =SUM(F91:J91) -> 2393.31 | J91: 2393.31
B92: Foundations | D92: =SUM(F92:J92) -> 5241.81 | J92: 5241.81
B93: HVAC | D93: =SUM(F93:J93) -> 2635.44 | J93: 2635.44
B94: Electrical | D94: =SUM(F94:J94) -> 2808.52 | J94: 2808.52
B95: Plumbing | D95: =SUM(F95:J95) -> 2317.18 | J95: 2317.18
B96: Fire Protection & Alarm | D96: =SUM(F96:J96) -> 120.33 | J96: 120.33
B97: Exterior Façade / Building Skin | D97: =SUM(F97:J97) -> 1467.77 | J97: 1467.77
B98: Doors & Frames | D98: =SUM(F98:J98) -> 1559.85 | J98: 1559.85
B99: Windows | D99: =SUM(F99:J99) -> 1214.17 | J99: 1214.17
B100: Ceiling Systems | D100: =SUM(F100:J100) -> 1352.65 | J100: 1352.65
B101: Interior Framing / Partitions | D101: =SUM(F101:J101) -> 4299.13 | J101: 4299.13
B102: Painting | D102: =SUM(F102:J102) -> 1422.08 | J102: 1422.08
... B109: Cabinets / Millwork - Restrooms | D109: =SUM(F109:J109) -> 419.32 | J109: 419.32
B110: Total Building Cost | D110: =SUM(D70:D109) -> 41641.47 | F110: =SUM(F70:F109) -> 7159.08 | H110: =SUM(H70:H109) -> 1020.89 | J110: =SUM(J70:J109) -> 33461.5
B111: % of Cost | F111: =F110/D110 -> 0.17192188 | H111: =H110/D110 -> 0.024516185 | J111: =J110/D110 -> 0.80356193
A113: ASSET ALLOCATION (per After Cost Segregation schedule)
B114: Asset (as reclassified) | D114: Cost | F114: 5 Year | H114: 15 Year | J114: 27.5 Year
B115: ='3112 Havenwood'!B17 -> 2 - Land Improvements - Havenwood -5yr | D115: =SUM(F115:J115) -> 8161 | F115: ='3112 Havenwood'!D17 -> 8161
B116: ='3112 Havenwood'!B18 -> 2 - Land Improvements - Havenwood -15yr | D116: =SUM(F116:J116) -> 1164 | H116: ='3112 Havenwood'!D18 -> 1164
...

Sheet 3117 Barbwood
A1: Marrero 3 LP
A2: Marrero 3 — 530 Ames Blvd, Marrero, LA 70072
A3: EIN: 82-2324040 · FYE: December 31, 2024 · Year of Change: 1/1/2024
A4: 3117 Barbwood — Attachment to Form 3115 (DCN #7, Rev. Proc. 2024-23 §6.01)
A5: Source: CSSI Report #107752-18, "#107752-18_Marrero 3 - 3115 Combined.pdf"
A7: CALCULATION OF §481(a) ADJUSTMENT — REGULAR TAX
A8: As Previously Filed
A9: Asset | B9: Property Description | C9: Date In Service | D9: Cost | E9: Sec 179 Exp | F9: Bonus Amt | G9: Tax Prior Depreciation | H9: Tax Current Depreciation | I9: End Depreciation | J9: Net Book Value | K9: Method | L9: Period
A10: 1 | B10: 2 - Land Improvements - Havenwood | C10: 12/08/17 | D10: 7649 | E10: 0 | F10: 0 | G10: 3621.69 | H10: 451.69 | I10: =G10+H10 -> 4073.38 | J10: =D10-I10 -> 3575.62 | K10: 150DB | L10: 15.0
A11: 2 | B11: 3 - Buidling - Havenwood | C11: 12/08/17 | D11: 99442 | E11: 0 | F11: 0 | G11: 21847.1 | H11: 3616.07 | I11: =G11+H11 -> 25463.17 | J11: =D11-I11 -> 73978.83 | K11: S/L | L11: 27.5
A12: 3 | B12: 4 - Equipment - Havenwood | C12: 12/08/17 | D12: 20398 | E12: 0 | F12: 20398 | G12: 20398 | H12: 0 | I12: =G12+H12 -> 20398 | J12: =D12-I12 -> 0 | K12: 200DB | L12: 5.0
B13: Grand Total | D13: =SUM(D10:D12) -> 127489 | E13: =SUM(E10:E12) -> 0 | F13: =SUM(F10:F12) -> 20398 | G13: =SUM(G10:G12) -> 45866.79 | H13: =SUM(H10:H12) -> 4067.76 | I13: =SUM(I10:I12) -> 49934.55 | J13: =SUM(J10:J12) -> 77554.45
A15: After Cost Segregation Correction
A16: Asset | B16: Property Description | C16: Date In Service | D16: Cost | E16: Sec 179 Exp | F16: Bonus Amt | G16: Tax Prior Depreciation | H16: Tax Current Depreciation | I16: End Depreciation | J16: Net Book Value | K16: Method | L16: Period
A17: 1 | B17: 2 - Land Improvements - Havenwood - 5yr | C17: 12/08/17 | D17: 1030 | E17: 0 | F17: 0 | G17: 1030 | H17: 0 | I17: =G17+H17 -> 1030 | J17: =D17-I17 -> 0 | K17: 200DB | L17: 5.0
A18: 2 | B18: 2 - Land Improvements - Havenwood - 15yr | C18: 12/08/17 | D18: 127 | E18: 0 | F18: 0 | G18: 63.27 | H18: 7.5 | I18: =G18+H18 -> 70.77 | J18: =D18-I18 -> 56.23 | K18: 150DB | L18: 15.0
A19: 3 | B19: 2 - Land Improvements - Havenwood - 27.5yr | C19: 12/08/17 | D19: 6493 | E19: 0 | F19: 0 | G19: 1426.26 | H19: 236.11 | I19: =G19+H19 -> 1662.37 | J19: =D19-I19 -> 4830.63 | K19: S/L | L19: 27.5
A20: 4 | B20: 3 - Buidling - Havenwood - 5yr | C20: 12/08/17 | D20: 13389 | E20: 0 | F20: 13389 | G20: 13389 | H20: 0 | I20: =G20+H20 -> 13389 | J20: =D20-I20 -> 0 | K20: 200DB | L20: 5.0
A21: 5 | B21: 3 - Buidling - Havenwood - 15yr | C21: 12/08/17 | D21: 1655 | E21: 0 | F21: 1655 | G21: 1655 | H21: 0 | I21: =G21+H21 -> 1655 | J21: =D21-I21 -> 0 | K21: 150DB | L21: 15.0
A22: 6 | B22: 3 - Buidling - Havenwood - 27.5yr | C22: 12/08/17 | D22: 84398 | E22: 0 | F22: 0 | G22: 18542 | H22: 3069.02 | I22: =G22+H22 -> 21611.02 | J22: =D22-I22 -> 62786.98 | K22: S/L | L22: 27.5
A23: 7 | B23: 4 - Equipment - Havenwood - 5yr | C23: 12/08/17 | D23: 2746 | E23: 0 | F23: 2746 | G23: 2746 | H23: 0 | I23: =G23+H23 -> 2746 | J23: =D23-I23 -> 0 | K23: 200DB | L23: 5.0
A24: 8 | B24: 4 - Equipment - Havenwood - 15yr | C24: 12/08/17 | D24: 340 | E24: 0 | F24: 340 | G24: 340 | H24: 0 | I24: =G24+H24 -> 340 | J24: =D24-I24 -> 0 | K24: 150DB | L24: 15.0
A25: 9 | B25: 4 - Equipment - Havenwood - 27.5yr | C25: 12/08/17 | D25: 17312 | E25: 0 | F25: 0 | G25: 3803.41 | H25: 629.53 | I25: =G25+H25 -> 4432.94 | J25: =D25-I25 -> 12879.06 | K25: S/L | L25: 27.5
B26: Grand Total | D26: =SUM(D17:D25) -> 127490 | E26: =SUM(E17:E25) -> 0 | F26: =SUM(F17:F25) -> 18130 | G26: =SUM(G17:G25) -> 42994.94 | H26: =SUM(H17:H25) -> 3942.16 | I26: =SUM(I17:I25) -> 46937.1 | J26: =SUM(J17:J25) -> 80552.9
B28: Section 481(a) Adjustment — Regular Tax
B29: Depreciation reported previously | D29: =I13 -> 49934.55
B30: Cost Segregation Corrected Depreciation | D30: =I26 -> 46937.1
B31: Section 481(a) Adjustment — Regular Tax | D31: =D29-D30 -> 2997.45
A33: CALCULATION OF §481(a) ADJUSTMENT — AMT
A34: As Previously Filed — AMT
A35: Asset | B35: Property Description | C35: Date In Service | D35: Cost | E35: Sec 179 Exp | F35: Bonus Amt | G35: AMT Prior Depreciation | H35: AMT Current Depreciation | I35: End Depreciation | J35: Net Book Value | K35: Method | L35: Period
A36: 1 | B36: 2 - Land Improvements - Havenwood | C36: 12/08/17 | D36: 7649 | E36: 0 | F36: 0 | G36: 3621.69 | H36: 451.69 | I36: =G36+H36 -> 4073.38 | J36: =D36-I36 -> 3575.62 | K36: 150DB | L36: 15.0
A37: 2 | B37: 3 - Buidling - Havenwood | C37: 12/08/17 | D37: 99442 | E37: 0 | F37: 0 | G37: 21847.1 | H37: 3616.07 | I37: =G37+H37 -> 25463.17 | J37: =D37-I37 -> 73978.83 | K37: S/L | L37: 27.5
A38: 3 | B38: 4 - Equipment - Havenwood | C38: 12/08/17 | D38: 20398 | E38: 0 | F38: 20398 | G38: 20398 | H38: 0 | I38: =G38+H38 -> 20398 | J38: =D38-I38 -> 0 | K38: 200DB | L38: 5.0
B39: Grand Total | D39: =SUM(D36:D38) -> 127489 | E39: =SUM(E36:E38) -> 0 | F39: =SUM(F36:F38) -> 20398 | G39: =SUM(G36:G38) -> 45866.79 | H39: =SUM(H36:H38) -> 4067.76 | I39: =SUM(I36:I38) -> 49934.55 | J39: =SUM(J36:J38) -> 77554.45
A41: After Cost Segregation Correction — AMT
A42: Asset | B42: Property Description | C42: Date In Service | D42: Cost | E42: Sec 179 Exp | F42: Bonus Amt | G42: AMT Prior Depreciation | H42: AMT Current Depreciation | I42: End Depreciation | J42: Net Book Value | K42: Method | L42: Period
A43: 1 | B43: 2 - Land Improvements - Havenwood - 5yr | C43: 12/08/17 | D43: 1030 | E43: 0 | F43: 0 | G43: 1030 | H43: 0 | I43: =G43+H43 -> 1030 | J43: =D43-I43 -> 0 | K43: 200DB | L43: 5.0
A44: 2 | B44: 2 - Land Improvements - Havenwood - 15yr | C44: 12/08/17 | D44: 127 | E44: 0 | F44: 0 | G44: 63.27 | H44: 7.5 | I44: =G44+H44 -> 70.77 | J44: =D44-I44 -> 56.23 | K44: 150DB | L44: 15.0
A45: 3 | B45: 2 - Land Improvements - Havenwood - 27.5yr | C45: 12/08/17 | D45: 6493 | E45: 0 | F45: 0 | G45: 1426.26 | H45: 236.11 | I45: =G45+H45 -> 1662.37 | J45: =D45-I45 -> 4830.63 | K45: S/L | L45: 27.5
A46: 4 | B46: 3 - Buidling - Havenwood - 5yr | C46: 12/08/17 | D46: 13389 | E46: 0 | F46: 13389 | G46: 13389 | H46: 0 | I46: =G46+H46 -> 13389 | J46: =D46-I46 -> 0 | K46: 200DB | L46: 5.0
A47: 5 | B47: 3 - Buidling - Havenwood - 15yr | C47: 12/08/17 | D47: 1655 | E47: 0 | F47: 1655 | G47: 1655 | H47: 0 | I47: =G47+H47 -> 1655 | J47: =D47-I47 -> 0 | K47: 150DB | L47: 15.0
A48: 6 | B48: 3 - Buidling - Havenwood - 27.5yr | C48: 12/08/17 | D48: 84398 | E48: 0 | F48: 0 | G48: 18542 | H48: 3069.02 | I48: =G48+H48 -> 21611.02 | J48: =D48-I48 -> 62786.98 | K48: S/L | L48: 27.5
A49: 7 | B49: 4 - Equipment - Havenwood - 5yr | C49: 12/08/17 | D49: 2746 | E49: 0 | F49: 2746 | G49: 2746 | H49: 0 | I49: =G49+H49 -> 2746 | J49: =D49-I49 -> 0 | K49: 200DB | L49: 5.0
A50: 8 | B50: 4 - Equipment - Havenwood - 15yr | C50: 12/08/17 | D50: 340 | E50: 0 | F50: 340 | G50: 340 | H50: 0 | I50: =G50+H50 -> 340 | J50: =D50-I50 -> 0 | K50: 150DB | L50: 15.0
A51: 9 | B51: 4 - Equipment - Havenwood - 27.5yr | C51: 12/08/17 | D51: 17312 | E51: 0 | F51: 0 | G51: 3803.41 | H51: 629.53 | I51: =G51+H51 -> 4432.94 | J51: =D51-I51 -> 12879.06 | K51: S/L | L51: 27.5
B52: Grand Total | D52: =SUM(D43:D51) -> 127490 | E52: =SUM(E43:E51) -> 0 | F52: =SUM(F43:F51) -> 18130 | G52: =SUM(G43:G51) -> 42994.94 | H52: =SUM(H43:H51) -> 3942.16 | I52: =SUM(I43:I51) -> 46937.1 | J52: =SUM(J43:J51) -> 80552.9
B54: Section 481(a) Adjustment — AMT
B55: Depreciation reported previously | D55: =I39 -> 49934.55
B56: Cost Segregation Corrected Depreciation | D56: =I52 -> 46937.1
B57: Section 481(a) Adjustment — AMT | D57: =D55-D56 -> 2997.45
A59: COST SEGREGATION STUDY — COST SUMMARY
B60: Total Building Cost | D60: =D109 -> 42496.66
B61: Building Components: 5 Year | D61: =F109 -> 5721.63
B62: % of Cost | D62: =F110 -> 0.13463717
B63: Site Improvements: 15 Year | D63: =H109 -> 707.48
B64: % of Cost | D64: =H110 -> 0.016647897
B65: Building Structure: 27.5 Year | D65: =J109 -> 36067.55
B66: % of Cost | D66: =J110 -> 0.84871493
A68: COST SEGREGATION STUDY — COST DETAIL
B69: Property Category | D69: Cost | F69: 5 Year | H69: 15 Year | J69: 27.5 Year
B70: Building Components
B71: Cabinets / Millwork | D71: =SUM(F71:J71) -> 1194.23 | F71: 1194.23
B72: Moldings | D72: =SUM(F72:J72) -> 892.45 | F72: 892.45
B73: Flooring - Wood Laminate | D73: =SUM(F73:J73) -> 772.85 | F73: 772.85
B74: Security System | D74: =SUM(F74:J74) -> 479.69 | F74: 479.69
B75: Window Treatments | D75: =SUM(F75:J75) -> 324.2 | F75: 324.2
B76: Specialty HVAC - Dryer Vents | D76: =SUM(F76:J76) -> 30.15 | F76: 30.15
B77: Building Signage | D77: =SUM(F77:J77) -> 19.82 | F77: 19.82
B78: Specialty Electrical - Appliances | D78: =SUM(F78:J78) -> 514.89 | F78: 514.89
B79: Communication / Data | D79: =SUM(F79:J79) -> 253.01 | F79: 253.01
B80: Specialty Plumbing - Kitchen Sink / Laundry | D80: =SUM(F80:J80) -> 563.75 | F80: 563.75
B81: Security / Exterior Lighting | D81: =SUM(F81:J81) -> 111.83 | F81: 111.83
B82: Appliances | D82: =SUM(F82:J82) -> 564.76 | F82: 564.76
B83: Site Work / Improvements
B84: Driveway | D84: =SUM(F84:J84) -> 508.62 | H84: 508.62
B85: Sidewalks / Curbs | D85: =SUM(F85:J85) -> 142.45 | H85: 142.45
B86: Exterior Equipment Concrete Pads | D86: =SUM(F86:J86) -> 34.81 | H86: 34.81
B87: Mailboxes | D87: =SUM(F87:J87) -> 21.6 | H87: 21.6
B88: Building Structure
B89: Roofing Systems | D89: =SUM(F89:J89) -> 2544.9 | J89: 2544.9
B90: Foundations | D90: =SUM(F90:J90) -> 5290.6 | J90: 5290.6
B91: HVAC | D91: =SUM(F91:J91) -> 2605.13 | J91: 2605.13
B92: Electrical | D92: =SUM(F92:J92) -> 2808.12 | J92: 2808.12
B93: Plumbing | D93: =SUM(F93:J93) -> 2290.83 | J93: 2290.83
B94: Fire Protection & Alarm | D94: =SUM(F94:J94) -> 150.42 | J94: 150.42
B95: Exterior Façade / Building Skin | D95: =SUM(F95:J95) -> 1919.86 | J95: 1919.86
B96: Doors & Frames | D96: =SUM(F96:J96) -> 1776.29 | J96: 1776.29
B97: Windows | D97: =SUM(F97:J97) -> 1322.1 | J97: 1322.1
B98: Ceiling Systems | D98: =SUM(F98:J98) -> 1338.43 | J98: 1338.43
B99: Interior Framing / Partitions | D99: =SUM(F99:J99) -> 4310.61 | J99: 4310.61
B100: Painting | D100: =SUM(F100:J100) -> 1420.92 | J100: 1420.92
... B108: Cabinets / Millwork - Restrooms | D108: =SUM(F108:J108) -> 362.41 | J108: 362.41
B109: Total Building Cost | D109: =SUM(D70:D108) -> 42496.66 | F109: =SUM(F70:F108) -> 5721.63 | H109: =SUM(H70:H108) -> 707.48 | J109: =SUM(J70:J108) -> 36067.55
B110: % of Cost | F110: =F109/D109 -> 0.13463717 | H110: =H109/D109 -> 0.016647897 | J110: =J109/D109 -> 0.84871493
A112: ASSET ALLOCATION (per After Cost Segregation schedule)
B113: Asset (as reclassified) | D113: Cost | F113: 5 Year | H113: 15 Year | J113: 27.5 Year
B114: ='3117 Barbwood'!B17 -> 2 - Land Improvements - Havenwood - 5yr | D114: =SUM(F114:J114) -> 1030 | F114: ='3117 Barbwood'!D17 -> 1030
B115: ='3117 Barbwood'!B18 -> 2 - Land Improvements - Havenwood - 15yr | D115: =SUM(F115:J115) -> 127 | H115: ='3117 Barbwood'!D18 -> 127
B116: ='3117 Barbwood'!B19 -> 2 - Land Improvements - Havenwood - 27.5yr | D116: =SUM(F116:J116) -> 6493 | J116: ='3117 Barbwood'!D19 -> 6493
...

Sheet 6805 Sayres
A1: Marrero 3 LP
A2: Marrero 3 — 530 Ames Blvd, Marrero, LA 70072
A3: EIN: 82-2324040 · FYE: December 31, 2024 · Year of Change: 1/1/2024
A4: 6805 Sayres — Attachment to Form 3115 (DCN #7, Rev. Proc. 2024-23 §6.01)
A5: Source: CSSI Report #107752-18, "#107752-18_Marrero 3 - 3115 Combined.pdf"
A7: CALCULATION OF §481(a) ADJUSTMENT — REGULAR TAX
A8: As Previously Filed
A9: Asset | B9: Property Description | C9: Date In Service | D9: Cost | E9: Sec 179 Exp | F9: Bonus Amt | G9: Tax Prior Depreciation | H9: Tax Current Depreciation | I9: End Depreciation | J9: Net Book Value | K9: Method | L9: Period
A10: 1 | B10: 22 - Land Improvements - Gentry | C10: 1/09/18 | D10: 40887 | E10: 0 | F10: 0 | G10: 40887 | H10: 0 | I10: =G10+H10 -> 40887 | J10: =D10-I10 -> 0 | K10: 150DB | L10: 15.0
A11: 2 | B11: 23 - Buidling - Gentry | C11: 1/29/18 | D11: 1131216 | E11: 0 | F11: 0 | G11: 245097.45 | H11: 41135.17 | I11: =G11+H11 -> 286232.62 | J11: =D11-I11 -> 844983.38 | K11: S/L | L11: 27.5
A12: 3 | B12: 24 - Equipment - Gentry | C12: 1/29/18 | D12: 190807 | E12: 0 | F12: 190807 | G12: 190807 | H12: 0 | I12: =G12+H12 -> 190807 | J12: =D12-I12 -> 0 | K12: 200DB | L12: 5.0
B13: Grand Total | D13: =SUM(D10:D12) -> 1362910 | E13: =SUM(E10:E12) -> 0 | F13: =SUM(F10:F12) -> 190807 | G13: =SUM(G10:G12) -> 476791.45 | H13: =SUM(H10:H12) -> 41135.17 | I13: =SUM(I10:I12) -> 517926.62 | J13: =SUM(J10:J12) -> 844983.38
A15: After Cost Segregation Correction
A16: Asset | B16: Property Description | C16: Date In Service | D16: Cost | E16: Sec 179 Exp | F16: Bonus Amt | G16: Tax Prior Depreciation | H16: Tax Current Depreciation | I16: End Depreciation | J16: Net Book Value | K16: Method | L16: Period
A17: 1 | B17: 22 - Land Improvements - Gentry - 5yr | C17: 1/09/18 | D17: 6134 | E17: 0 | F17: 0 | G17: 6134 | H17: 0 | I17: =G17+H17 -> 6134 | J17: =D17-I17 -> 0 | K17: 200DB | L17: 5.0
A18: 2 | B18: 22 - Land Improvements - Gentry - 15yr | C18: 1/09/18 | D18: 692 | E18: 0 | F18: 0 | G18: 692 | H18: 0 | I18: =G18+H18 -> 692 | J18: =D18-I18 -> 0 | K18: 150DB | L18: 15.0
A19: 3 | B19: 22 - Land Improvements - Gentry - 27.5yr | C19: 1/09/18 | D19: 34061 | E19: 0 | F19: 0 | G19: 7379.87 | H19: 1238.58 | I19: =G19+H19 -> 8618.45 | J19: =D19-I19 -> 25442.55 | K19: S/L | L19: 27.5
A20: 4 | B20: 23 - Buidling - Gentry - 5yr | C20: 1/29/18 | D20: 169707 | E20: 0 | F20: 169707 | G20: 169707 | H20: 0 | I20: =G20+H20 -> 169707 | J20: =D20-I20 -> 0 | K20: 200DB | L20: 5.0
A21: 5 | B21: 23 - Buidling - Gentry - 15yr | C21: 1/29/18 | D21: 19148 | E21: 0 | F21: 19148 | G21: 19148 | H21: 0 | I21: =G21+H21 -> 19148 | J21: =D21-I21 -> 0 | K21: 150DB | L21: 15.0
A22: 6 | B22: 23 - Buidling - Gentry - 27.5yr | C22: 1/29/18 | D22: 942361 | E22: 0 | F22: 0 | G22: 204178.2 | H22: 34267.67 | I22: =G22+H22 -> 238445.87 | J22: =D22-I22 -> 703915.13 | K22: S/L | L22: 27.5
A23: 7 | B23: 24 - Equipment - Gentry - 5yr | C23: 1/29/18 | D23: 28625 | E23: 0 | F23: 28625 | G23: 28625 | H23: 0 | I23: =G23+H23 -> 28625 | J23: =D23-I23 -> 0 | K23: 200DB | L23: 5.0
A24: 8 | B24: 24 - Equipment - Gentry - 15yr | C24: 1/29/18 | D24: 3230 | E24: 0 | F24: 3230 | G24: 3230 | H24: 0 | I24: =G24+H24 -> 3230 | J24: =D24-I24 -> 0 | K24: 200DB | L24: 5.0
A25: 9 | B25: 24 - Equipment - Gentry - 27.5yr | C25: 1/29/18 | D25: 158953 | E25: 0 | F25: 0 | G25: 34439.59 | H25: 5780.11 | I25: =G25+H25 -> 40219.7 | J25: =D25-I25 -> 118733.3 | K25: S/L | L25: 27.5
B26: Grand Total | D26: =SUM(D17:D25) -> 1362911 | E26: =SUM(E17:E25) -> 0 | F26: =SUM(F17:F25) -> 220710 | G26: =SUM(G17:G25) -> 473533.66 | H26: =SUM(H17:H25) -> 41286.36 | I26: =SUM(I17:I25) -> 514820.02 | J26: =SUM(J17:J25) -> 848090.98
B28: Section 481(a) Adjustment — Regular Tax
B29: Depreciation reported previously | D29: =I13 -> 517926.62
B30: Cost Segregation Corrected Depreciation | D30: =I26 -> 514820.02
B31: Section 481(a) Adjustment — Regular Tax | D31: =D29-D30 -> 3106.6
A33: CALCULATION OF §481(a) ADJUSTMENT — AMT
A34: As Previously Filed — AMT
A35: Asset | B35: Property Description | C35: Date In Service | D35: Cost | E35: Sec 179 Exp | F35: Bonus Amt | G35: AMT Prior Depreciation | H35: AMT Current Depreciation | I35: End Depreciation | J35: Net Book Value | K35: Method | L35: Period
A36: 1 | B36: 22 - Land Improvements - Gentry | C36: 1/09/18 | D36: 40887 | E36: 0 | F36: 0 | G36: 40887 | H36: 0 | I36: =G36+H36 -> 40887 | J36: =D36-I36 -> 0 | K36: 150DB | L36: 15.0
A37: 2 | B37: 23 - Buidling - Gentry | C37: 1/29/18 | D37: 1131216 | E37: 0 | F37: 0 | G37: 245097.45 | H37: 41135.17 | I37: =G37+H37 -> 286232.62 | J37: =D37-I37 -> 844983.38 | K37: S/L | L37: 27.5
A38: 3 | B38: 24 - Equipment - Gentry | C38: 1/29/18 | D38: 190807 | E38: 0 | F38: 190807 | G38: 190807 | H38: 0 | I38: =G38+H38 -> 190807 | J38: =D38-I38 -> 0 | K38: 200DB | L38: 5.0
B39: Grand Total | D39: =SUM(D36:D38) -> 1362910 | E39: =SUM(E36:E38) -> 0 | F39: =SUM(F36:F38) -> 190807 | G39: =SUM(G36:G38) -> 476791.45 | H39: =SUM(H36:H38) -> 41135.17 | I39: =SUM(I36:I38) -> 517926.62 | J39: =SUM(J36:J38) -> 844983.38
A41: After Cost Segregation Correction — AMT
A42: Asset | B42: Property Description | C42: Date In Service | D42: Cost | E42: Sec 179 Exp | F42: Bonus Amt | G42: AMT Prior Depreciation | H42: AMT Current Depreciation | I42: End Depreciation | J42: Net Book Value | K42: Method | L42: Period
A43: 1 | B43: 22 - Land Improvements - Gentry - 5yr | C43: 1/09/18 | D43: 6134 | E43: 0 | F43: 0 | G43: 6134 | H43: 0 | I43: =G43+H43 -> 6134 | J43: =D43-I43 -> 0 | K43: 200DB | L43: 5.0
A44: 2 | B44: 22 - Land Improvements - Gentry - 15yr | C44: 1/09/18 | D44: 692 | E44: 0 | F44: 0 | G44: 692 | H44: 0 | I44: =G44+H44 -> 692 | J44: =D44-I44 -> 0 | K44: 150DB | L44: 15.0
A45: 3 | B45: 22 - Land Improvements - Gentry - 27.5yr | C45: 1/09/18 | D45: 34061 | E45: 0 | F45: 0 | G45: 7379.87 | H45: 1238.58 | I45: =G45+H45 -> 8618.45 | J45: =D45-I45 -> 25442.55 | K45: S/L | L45: 27.5
A46: 4 | B46: 23 - Buidling - Gentry - 5yr | C46: 1/29/18 | D46: 169707 | E46: 0 | F46: 169707 | G46: 169707 | H46: 0 | I46: =G46+H46 -> 169707 | J46: =D46-I46 -> 0 | K46: 200DB | L46: 5.0
A47: 5 | B47: 23 - Buidling - Gentry - 15yr | C47: 1/29/18 | D47: 19148 | E47: 0 | F47: 19148 | G47: 19148 | H47: 0 | I47: =G47+H47 -> 19148 | J47: =D47-I47 -> 0 | K47: 150DB | L47: 15.0
A48: 6 | B48: 23 - Buidling - Gentry - 27.5yr | C48: 1/29/18 | D48: 942361 | E48: 0 | F48: 0 | G48: 204178.2 | H48: 34267.67 | I48: =G48+H48 -> 238445.87 | J48: =D48-I48 -> 703915.13 | K48: S/L | L48: 27.5
A49: 7 | B49: 24 - Equipment - Gentry - 5yr | C49: 1/29/18 | D49: 28625 | E49: 0 | F49: 28625 | G49: 28625 | H49: 0 | I49: =G49+H49 -> 28625 | J49: =D49-I49 -> 0 | K49: 200DB | L49: 5.0
A50: 8 | B50: 24 - Equipment - Gentry - 15yr | C50: 1/29/18 | D50: 3230 | E50: 0 | F50: 3230 | G50: 3230 | H50: 0 | I50: =G50+H50 -> 3230 | J50: =D50-I50 -> 0 | K50: 200DB | L50: 5.0
A51: 9 | B51: 24 - Equipment - Gentry - 27.5yr | C51: 1/29/18 | D51: 158953 | E51: 0 | F51: 0 | G51: 34439.59 | H51: 5780.11 | I51: =G51+H51 -> 40219.7 | J51: =D51-I51 -> 118733.3 | K51: S/L | L51: 27.5
B52: Grand Total | D52: =SUM(D43:D51) -> 1362911 | E52: =SUM(E43:E51) -> 0 | F52: =SUM(F43:F51) -> 220710 | G52: =SUM(G43:G51) -> 473533.66 | H52: =SUM(H43:H51) -> 41286.36 | I52: =SUM(I43:I51) -> 514820.02 | J52: =SUM(J43:J51) -> 848090.98
B54: Section 481(a) Adjustment — AMT
B55: Depreciation reported previously | D55: =I39 -> 517926.62
B56: Cost Segregation Corrected Depreciation | D56: =I52 -> 514820.02
B57: Section 481(a) Adjustment — AMT | D57: =D55-D56 -> 3106.6
A59: COST SEGREGATION STUDY — COST SUMMARY
B60: Total Building Cost | D60: =D110 -> 42590.96
B61: Building Components: 5 Year | D61: =F110 -> 6389.57
B62: % of Cost | D62: =F111 -> 0.15002174
B63: Site Improvements: 15 Year | D63: =H110 -> 720.93
B64: % of Cost | D64: =H111 -> 0.016926831
B65: Building Structure: 27.5 Year | D65: =J110 -> 35480.46
B66: % of Cost | D66: =J111 -> 0.83305143
A68: COST SEGREGATION STUDY — COST DETAIL
B69: Property Category | D69: Cost | F69: 5 Year | H69: 15 Year | J69: 27.5 Year
B70: Building Components
B71: Cabinets / Millwork | D71: =SUM(F71:J71) -> 769.54 | F71: 769.54
B72: Moldings | D72: =SUM(F72:J72) -> 1073.38 | F72: 1073.38
B73: Flooring - Wood Laminate | D73: =SUM(F73:J73) -> 1525.14 | F73: 1525.14
B74: Security System | D74: =SUM(F74:J74) -> 391.94 | F74: 391.94
B75: Window Treatments | D75: =SUM(F75:J75) -> 399.45 | F75: 399.45
B76: Specialty HVAC - Dryer Vents | D76: =SUM(F76:J76) -> 33.34 | F76: 33.34
B77: Building Signage | D77: =SUM(F77:J77) -> 21.93 | F77: 21.93
B78: Specialty Electrical - Appliances | D78: =SUM(F78:J78) -> 569.4 | F78: 569.4
B79: Communication / Data | D79: =SUM(F79:J79) -> 233.79 | F79: 233.79
B80: Specialty Plumbing - Kitchen Sink / Laundry | D80: =SUM(F80:J80) -> 623.44 | F80: 623.44
B81: Security / Exterior Lighting | D81: =SUM(F81:J81) -> 123.66 | F81: 123.66
B82: Appliances | D82: =SUM(F82:J82) -> 624.56 | F82: 624.56
B83: Site Work / Improvements
B84: Driveway | D84: =SUM(F84:J84) -> 462.21 | H84: 462.21
B85: Sidewalks / Curbs | D85: =SUM(F85:J85) -> 179.88 | H85: 179.88
B86: Landscaping | D86: =SUM(F86:J86) -> 16.47 | H86: 16.47
B87: Exterior Equipment Concrete Pads | D87: =SUM(F87:J87) -> 38.5 | H87: 38.5
B88: Mailboxes | D88: =SUM(F88:J88) -> 23.87 | H88: 23.87
B89: Building Structure
B90: Roofing Systems | D90: =SUM(F90:J90) -> 2692.77 | J90: 2692.77
B91: Foundations | D91: =SUM(F91:J91) -> 4528.89 | J91: 4528.89
B92: HVAC | D92: =SUM(F92:J92) -> 2401.76 | J92: 2401.76
B93: Electrical | D93: =SUM(F93:J93) -> 2545.73 | J93: 2545.73
B94: Plumbing | D94: =SUM(F94:J94) -> 2116.83 | J94: 2116.83
B95: Fire Protection & Alarm | D95: =SUM(F95:J95) -> 133.07 | J95: 133.07
B96: Exterior Façade / Building Skin | D96: =SUM(F96:J96) -> 2525.75 | J96: 2525.75
B97: Doors & Frames | D97: =SUM(F97:J97) -> 1588.26 | J97: 1588.26
B98: Windows | D98: =SUM(F98:J98) -> 1402.38 | J98: 1402.38
B99: Ceiling Systems | D99: =SUM(F99:J99) -> 1255.57 | J99: 1255.57
B100: Interior Framing / Partitions | D100: =SUM(F100:J100) -> 5166.35 | J100: 5166.35
B101: Painting | D101: =SUM(F101:J101) -> 1609.06 | J101: 1609.06
... B109: Cabinets / Millwork - Restrooms | D109: =SUM(F109:J109) -> 304.95 | J109: 304.95
B110: Total Building Cost | D110: =SUM(D70:D109) -> 42590.96 | F110: =SUM(F70:F109) -> 6389.57 | H110: =SUM(H70:H109) -> 720.93 | J110: =SUM(J70:J109) -> 35480.46
B111: % of Cost | F111: =F110/D110 -> 0.15002174 | H111: =H110/D110 -> 0.016926831 | J111: =J110/D110 -> 0.83305143
A113: ASSET ALLOCATION (per After Cost Segregation schedule)
B114: Asset (as reclassified) | D114: Cost | F114: 5 Year | H114: 15 Year | J114: 27.5 Year
B115: ='6805 Sayres'!B17 -> 22 - Land Improvements - Gentry - 5yr | D115: =SUM(F115:J115) -> 6134 | F115: ='6805 Sayres'!D17 -> 6134
B116: ='6805 Sayres'!B18 -> 22 - Land Improvements - Gentry - 15yr | D116: =SUM(F116:J116) -> 692 | H116: ='6805 Sayres'!D18 -> 692
...

Sheet 6800 Sayres
A1: Marrero 3 LP
A2: Marrero 3 — 530 Ames Blvd, Marrero, LA 70072
A3: EIN: 82-2324040 · FYE: December 31, 2024 · Year of Change: 1/1/2024
A4: 6800 Sayres — Attachment to Form 3115 (DCN #7, Rev. Proc. 2024-23 §6.01)
A5: Source: CSSI Report #107752-18, "#107752-18_Marrero 3 - 3115 Combined.pdf"
A7: CALCULATION OF §481(a) ADJUSTMENT — REGULAR TAX
A8: As Previously Filed
A9: Asset | B9: Property Description | C9: Date In Service | D9: Cost | E9: Sec 179 Exp | F9: Bonus Amt | G9: Tax Prior Depreciation | H9: Tax Current Depreciation | I9: End Depreciation | J9: Net Book Value | K9: Method | L9: Period
A10: 1 | B10: 22 - Land Improvements - Gentry | C10: 1/09/18 | D10: 8075 | E10: 0 | F10: 0 | G10: 8075 | H10: 0 | I10: =G10+H10 -> 8075 | J10: =D10-I10 -> 0 | K10: 150DB | L10: 15.0
A11: 2 | B11: 23 - Buidling - Gentry | C11: 1/29/18 | D11: 223405 | E11: 0 | F11: 0 | G11: 48404.55 | H11: 8123.83 | I11: =G11+H11 -> 56528.38 | J11: =D11-I11 -> 166876.62 | K11: S/L | L11: 27.5
A12: 3 | B12: 24 - Equipment - Gentry | C12: 1/29/18 | D12: 37683 | E12: 0 | F12: 37682 | G12: 37682 | H12: 0 | I12: =G12+H12 -> 37682 | J12: =D12-I12 -> 1 | K12: 200DB | L12: 5.0
B13: Grand Total | D13: =SUM(D10:D12) -> 269163 | E13: =SUM(E10:E12) -> 0 | F13: =SUM(F10:F12) -> 37682 | G13: =SUM(G10:G12) -> 94161.55 | H13: =SUM(H10:H12) -> 8123.83 | I13: =SUM(I10:I12) -> 102285.38 | J13: =SUM(J10:J12) -> 166877.62
A15: After Cost Segregation Correction
A16: Asset | B16: Property Description | C16: Date In Service | D16: Cost | E16: Sec 179 Exp | F16: Bonus Amt | G16: Tax Prior Depreciation | H16: Tax Current Depreciation | I16: End Depreciation | J16: Net Book Value | K16: Method | L16: Period
A17: 1 | B17: 22 - Land Improvements - Gentry - 5yr | C17: 1/09/18 | D17: 1300 | E17: 0 | F17: 0 | G17: 1300 | H17: 0 | I17: =G17+H17 -> 1300 | J17: =D17-I17 -> 0 | K17: 200DB | L17: 5.0
A18: 2 | B18: 22 - Land Improvements - Gentry - 15yr | C18: 1/09/18 | D18: 185 | E18: 0 | F18: 0 | G18: 185 | H18: 0 | I18: =G18+H18 -> 185 | J18: =D18-I18 -> 0 | K18: 150DB | L18: 15.0
A19: 3 | B19: 22 - Land Improvements - Gentry - 27.5yr | C19: 1/09/18 | D19: 6590 | E19: 0 | F19: 0 | G19: 1427.85 | H19: 239.64 | I19: =G19+H19 -> 1667.49 | J19: =D19-I19 -> 4922.51 | K19: S/L | L19: 27.5
A20: 4 | B20: 23 - Buidling - Gentry - 5yr | C20: 1/29/18 | D20: 35968 | E20: 0 | F20: 35968 | G20: 35968 | H20: 0 | I20: =G20+H20 -> 35968 | J20: =D20-I20 -> 0 | K20: 200DB | L20: 5.0
A21: 5 | B21: 23 - Buidling - Gentry - 15yr | C21: 1/29/18 | D21: 5106 | E21: 0 | F21: 5106 | G21: 5106 | H21: 0 | I21: =G21+H21 -> 5106 | J21: =D21-I21 -> 0 | K21: 150DB | L21: 15.0
A22: 6 | B22: 23 - Buidling - Gentry - 27.5yr | C22: 1/29/18 | D22: 182331 | E22: 0 | F22: 0 | G22: 39505.06 | H22: 6630.22 | I22: =G22+H22 -> 46135.28 | J22: =D22-I22 -> 136195.72 | K22: S/L | L22: 27.5
A23: 7 | B23: 24 - Equipment - Gentry - 5yr | C23: 1/29/18 | D23: 6067 | E23: 0 | F23: 6067 | G23: 6067 | H23: 0 | I23: =G23+H23 -> 6067 | J23: =D23-I23 -> 0 | K23: 200DB | L23: 5.0
A24: 8 | B24: 24 - Equipment - Gentry - 15yr | C24: 1/29/18 | D24: 861 | E24: 0 | F24: 861 | G24: 861 | H24: 0 | I24: =G24+H24 -> 861 | J24: =D24-I24 -> 0 | K24: 150DB | L24: 15.0
A25: 9 | B25: 24 - Equipment - Gentry - 27.5yr | C25: 1/29/18 | D25: 30755 | E25: 0 | F25: 0 | G25: 6663.57 | H25: 1118.36 | I25: =G25+H25 -> 7781.93 | J25: =D25-I25 -> 22973.07 | K25: S/L | L25: 27.5
B26: Grand Total | D26: =SUM(D17:D25) -> 269163 | E26: =SUM(E17:E25) -> 0 | F26: =SUM(F17:F25) -> 48002 | G26: =SUM(G17:G25) -> 97083.48 | H26: =SUM(H17:H25) -> 7988.22 | I26: =SUM(I17:I25) -> 105071.7 | J26: =SUM(J17:J25) -> 164091.3
B28: Section 481(a) Adjustment — Regular Tax
B29: Depreciation reported previously | D29: =I13 -> 102285.38
B30: Cost Segregation Corrected Depreciation | D30: =I26 -> 105071.7
B31: Section 481(a) Adjustment — Regular Tax | D31: =D29-D30 -> -2786.32
A33: CALCULATION OF §481(a) ADJUSTMENT — AMT
A34: As Previously Filed — AMT
A35: Asset | B35: Property Description | C35: Date In Service | D35: Cost | E35: Sec 179 Exp | F35: Bonus Amt | G35: AMT Prior Depreciation | H35: AMT Current Depreciation | I35: End Depreciation | J35: Net Book Value | K35: Method | L35: Period
A36: 1 | B36: 22 - Land Improvements - Gentry | C36: 1/09/18 | D36: 8075 | E36: 0 | F36: 0 | G36: 8075 | H36: 0 | I36: =G36+H36 -> 8075 | J36: =D36-I36 -> 0 | K36: 150DB | L36: 15.0
A37: 2 | B37: 23 - Buidling - Gentry | C37: 1/29/18 | D37: 223405 | E37: 0 | F37: 0 | G37: 48404.55 | H37: 8123.83 | I37: =G37+H37 -> 56528.38 | J37: =D37-I37 -> 166876.62 | K37: S/L | L37: 27.5
A38: 3 | B38: 24 - Equipment - Gentry | C38: 1/29/18 | D38: 37683 | E38: 0 | F38: 37682 | G38: 37682 | H38: 0 | I38: =G38+H38 -> 37682 | J38: =D38-I38 -> 1 | K38: 200DB | L38: 5.0
B39: Grand Total | D39: =SUM(D36:D38) -> 269163 | E39: =SUM(E36:E38) -> 0 | F39: =SUM(F36:F38) -> 37682 | G39: =SUM(G36:G38) -> 94161.55 | H39: =SUM(H36:H38) -> 8123.83 | I39: =SUM(I36:I38) -> 102285.38 | J39: =SUM(J36:J38) -> 166877.62
A41: After Cost Segregation Correction — AMT
A42: Asset | B42: Property Description | C42: Date In Service | D42: Cost | E42: Sec 179 Exp | F42: Bonus Amt | G42: AMT Prior Depreciation | H42: AMT Current Depreciation | I42: End Depreciation | J42: Net Book Value | K42: Method | L42: Period
A43: 1 | B43: 22 - Land Improvements - Gentry - 5yr | C43: 1/09/18 | D43: 1300 | E43: 0 | F43: 0 | G43: 1300 | H43: 0 | I43: =G43+H43 -> 1300 | J43: =D43-I43 -> 0 | K43: 200DB | L43: 5.0
A44: 2 | B44: 22 - Land Improvements - Gentry - 15yr | C44: 1/09/18 | D44: 185 | E44: 0 | F44: 0 | G44: 185 | H44: 0 | I44: =G44+H44 -> 185 | J44: =D44-I44 -> 0 | K44: 150DB | L44: 15.0
A45: 3 | B45: 22 - Land Improvements - Gentry - 27.5yr | C45: 1/09/18 | D45: 6590 | E45: 0 | F45: 0 | G45: 1427.85 | H45: 239.64 | I45: =G45+H45 -> 1667.49 | J45: =D45-I45 -> 4922.51 | K45: S/L | L45: 27.5
A46: 4 | B46: 23 - Buidling - Gentry - 5yr | C46: 1/29/18 | D46: 35968 | E46: 0 | F46: 35968 | G46: 35968 | H46: 0 | I46: =G46+H46 -> 35968 | J46: =D46-I46 -> 0 | K46: 200DB | L46: 5.0
A47: 5 | B47: 23 - Buidling - Gentry - 15yr | C47: 1/29/18 | D47: 5106 | E47: 0 | F47: 5106 | G47: 5106 | H47: 0 | I47: =G47+H47 -> 5106 | J47: =D47-I47 -> 0 | K47: 150DB | L47: 15.0
A48: 6 | B48: 23 - Buidling - Gentry - 27.5yr | C48: 1/29/18 | D48: 182331 | E48: 0 | F48: 0 | G48: 39505.06 | H48: 6630.22 | I48: =G48+H48 -> 46135.28 | J48: =D48-I48 -> 136195.72 | K48: S/L | L48: 27.5
A49: 7 | B49: 24 - Equipment - Gentry - 5yr | C49: 1/29/18 | D49: 6067 | E49: 0 | F49: 6067 | G49: 6067 | H49: 0 | I49: =G49+H49 -> 6067 | J49: =D49-I49 -> 0 | K49: 200DB | L49: 5.0
A50: 8 | B50: 24 - Equipment - Gentry - 15yr | C50: 1/29/18 | D50: 861 | E50: 0 | F50: 861 | G50: 861 | H50: 0 | I50: =G50+H50 -> 861 | J50: =D50-I50 -> 0 | K50: 150DB | L50: 15.0
A51: 9 | B51: 24 - Equipment - Gentry - 27.5yr | C51: 1/29/18 | D51: 30755 | E51: 0 | F51: 0 | G51: 6663.57 | H51: 1118.36 | I51: =G51+H51 -> 7781.93 | J51: =D51-I51 -> 22973.07 | K51: S/L | L51: 27.5
B52: Grand Total | D52: =SUM(D43:D51) -> 269163 | E52: =SUM(E43:E51) -> 0 | F52: =SUM(F43:F51) -> 48002 | G52: =SUM(G43:G51) -> 97083.48 | H52: =SUM(H43:H51) -> 7988.22 | I52: =SUM(I43:I51) -> 105071.7 | J52: =SUM(J43:J51) -> 164091.3
B54: Section 481(a) Adjustment — AMT
B55: Depreciation reported previously | D55: =I39 -> 102285.38
B56: Cost Segregation Corrected Depreciation | D56: =I52 -> 105071.7
B57: Section 481(a) Adjustment — AMT | D57: =D55-D56 -> -2786.32
A59: COST SEGREGATION STUDY — COST SUMMARY
B60: Total Building Cost | D60: =D112 -> 44860.39
B61: Building Components: 5 Year | D61: =F112 -> 7222.56
B62: % of Cost | D62: =F113 -> 0.16100083
B63: Site Improvements: 15 Year | D63: =H112 -> 1025.24
B64: % of Cost | D64: =H113 -> 0.022854014
B65: Building Structure: 27.5 Year | D65: =J112 -> 36612.59
B66: % of Cost | D66: =J113 -> 0.81614516
A68: COST SEGREGATION STUDY — COST DETAIL
B69: Property Category | D69: Cost | F69: 5 Year | H69: 15 Year | J69: 27.5 Year
B70: Building Components
B71: Cabinets / Millwork | D71: =SUM(F71:J71) -> 835.76 | F71: 835.76
B72: Moldings | D72: =SUM(F72:J72) -> 712.35 | F72: 712.35
B73: Flooring - Carpet | D73: =SUM(F73:J73) -> 1187.54 | F73: 1187.54
B74: Flooring - Wood Laminate | D74: =SUM(F74:J74) -> 1052.42 | F74: 1052.42
B75: Security System | D75: =SUM(F75:J75) -> 530.5 | F75: 530.5
B76: Window Treatments | D76: =SUM(F76:J76) -> 622.76 | F76: 622.76
B77: Specialty HVAC - Dryer Vents | D77: =SUM(F77:J77) -> 33.34 | F77: 33.34
B78: Building Signage | D78: =SUM(F78:J78) -> 21.93 | F78: 21.93
B79: Specialty Electrical - Appliances | D79: =SUM(F79:J79) -> 569.4 | F79: 569.4
B80: Communication / Data | D80: =SUM(F80:J80) -> 284.9 | F80: 284.9
B81: Specialty Plumbing - Kitchen Sink / Laundry | D81: =SUM(F81:J81) -> 623.44 | F81: 623.44
B82: Security / Exterior Lighting | D82: =SUM(F82:J82) -> 123.66 | F82: 123.66
B83: Appliances | D83: =SUM(F83:J83) -> 624.56 | F83: 624.56
B84: Site Work / Improvements
B85: Driveway | D85: =SUM(F85:J85) -> 669.91 | H85: 669.91
B86: Sidewalks / Curbs | D86: =SUM(F86:J86) -> 276.49 | H86: 276.49
B87: Landscaping | D87: =SUM(F87:J87) -> 16.47 | H87: 16.47
B88: Exterior Equipment Concrete Pads | D88: =SUM(F88:J88) -> 38.5 | H88: 38.5
B89: Mailboxes | D89: =SUM(F89:J89) -> 23.87 | H89: 23.87
B90: Building Structure
B91: Roofing Systems | D91: =SUM(F91:J91) -> 1690.23 | J91: 1690.23
B92: Foundations | D92: =SUM(F92:J92) -> 2714.92 | J92: 2714.92
B93: HVAC | D93: =SUM(F93:J93) -> 2934.13 | J93: 2934.13
B94: Electrical | D94: =SUM(F94:J94) -> 3148.18 | J94: 3148.18
B95: Plumbing | D95: =SUM(F95:J95) -> 2579.61 | J95: 2579.61
B96: Fire Protection & Alarm | D96: =SUM(F96:J96) -> 199.61 | J96: 199.61
B97: Exterior Façade / Building Skin | D97: =SUM(F97:J97) -> 2160.08 | J97: 2160.08
B98: Doors & Frames | D98: =SUM(F98:J98) -> 1998.37 | J98: 1998.37
B99: Windows | D99: =SUM(F99:J99) -> 1909.62 | J99: 1909.62
B100: Ceiling Systems | D100: =SUM(F100:J100) -> 1505.06 | J100: 1505.06
B101: Interior Framing / Partitions | D101: =SUM(F101:J101) -> 5656.78 | J101: 5656.78
B102: Painting | D102: =SUM(F102:J102) -> 1800.79 | J102: 1800.79
... B111: Cabinets / Millwork - Restrooms | D111: =SUM(F111:J111) -> 308.22 | J111: 308.22
B112: Total Building Cost | D112: =SUM(D70:D111) -> 44860.39 | F112: =SUM(F70:F111) -> 7222.56 | H112: =SUM(H70:H111) -> 1025.24 | J112: =SUM(J70:J111) -> 36612.59
B113: % of Cost | F113: =F112/D112 -> 0.16100083 | H113: =H112/D112 -> 0.022854014 | J113: =J112/D112 -> 0.81614516
A115: ASSET ALLOCATION (per After Cost Segregation schedule)
B116: Asset (as reclassified) | D116: Cost | F116: 5 Year | H116: 15 Year | J116: 27.5 Year
B117: ='6800 Sayres'!B17 -> 22 - Land Improvements - Gentry - 5yr | D117: =SUM(F117:J117) -> 1300 | F117: ='6800 Sayres'!D17 -> 1300
...

Sheet 7112 Kayla
A1: Marrero 3 LP
A2: Marrero 3 — 530 Ames Blvd, Marrero, LA 70072
A3: EIN: 82-2324040 · FYE: December 31, 2024 · Year of Change: 1/1/2024
A4: 7112 Kayla — Attachment to Form 3115 (DCN #7, Rev. Proc. 2024-23 §6.01)
A5: Source: CSSI Report #107752-18, "#107752-18_Marrero 3 - 3115 Combined.pdf"
A7: CALCULATION OF §481(a) ADJUSTMENT — REGULAR TAX
A8: As Previously Filed
A9: Asset | B9: Property Description | C9: Date In Service | D9: Cost | E9: Sec 179 Exp | F9: Bonus Amt | G9: Tax Prior Depreciation | H9: Tax Current Depreciation | I9: End Depreciation | J9: Net Book Value | K9: Method | L9: Period
A10: 1 | B10: 7 - Land Improvements - Kayla | C10: 12/08/17 | D10: 80244 | E10: 0 | F10: 0 | G10: 37993.4 | H10: 4738.57 | I10: =G10+H10 -> 42731.97 | J10: =D10-I10 -> 37512.03 | K10: 150DB | L10: 15.0
A11: 2 | B11: 8 - Buidling - Kayla | C11: 12/08/17 | D11: 1043171 | E11: 0 | F11: 0 | G11: 229182.26 | H11: 37933.65 | I11: =G11+H11 -> 267115.91 | J11: =D11-I11 -> 776055.09 | K11: S/L | L11: 27.5
A12: 3 | B12: 9 - Equipment - Kayla | C12: 12/08/17 | D12: 213983 | E12: 0 | F12: 213983 | G12: 213983 | H12: 0 | I12: =G12+H12 -> 213983 | J12: =D12-I12 -> 0 | K12: 200DB | L12: 5.0
B13: Grand Total | D13: =SUM(D10:D12) -> 1337398 | E13: =SUM(E10:E12) -> 0 | F13: =SUM(F10:F12) -> 213983 | G13: =SUM(G10:G12) -> 481158.66 | H13: =SUM(H10:H12) -> 42672.22 | I13: =SUM(I10:I12) -> 523830.88 | J13: =SUM(J10:J12) -> 813567.12
A15: After Cost Segregation Correction
A16: Asset | B16: Property Description | C16: Date In Service | D16: Cost | E16: Sec 179 Exp | F16: Bonus Amt | G16: Tax Prior Depreciation | H16: Tax Current Depreciation | I16: End Depreciation | J16: Net Book Value | K16: Method | L16: Period
A17: 1 | B17: 7 - Land Improvements - Kayla - 5yr | C17: 12/08/17 | D17: 13399 | E17: 0 | F17: 0 | G17: 13399 | H17: 0 | I17: =G17+H17 -> 13399 | J17: =D17-I17 -> 0 | K17: 200DB | L17: 5.0
A18: 2 | B18: 7 - Land Improvements - Kayla - 15yr | C18: 12/08/17 | D18: 1194 | E18: 0 | F18: 0 | G18: 1194 | H18: 0 | I18: =G18+H18 -> 1194 | J18: =D18-I18 -> 0 | K18: 150DB | L18: 15.0
A19: 3 | B19: 7 - Land Improvements - Kayla - 27.5yr | C19: 12/08/17 | D19: 65650 | E19: 0 | F19: 0 | G19: 14423.09 | H19: 2387.27 | I19: =G19+H19 -> 16810.36 | J19: =D19-I19 -> 48839.64 | K19: S/L | L19: 27.5
A20: 4 | B20: 8 - Buidling - Kayla - 5yr | C20: 12/08/17 | D20: 174191 | E20: 0 | F20: 174191 | G20: 174191 | H20: 0 | I20: =G20+H20 -> 174191 | J20: =D20-I20 -> 0 | K20: 200DB | L20: 5.0
A21: 5 | B21: 8 - Buidling - Kayla - 15yr | C21: 12/08/17 | D21: 15524 | E21: 0 | F21: 15524 | G21: 15524 | H21: 0 | I21: =G21+H21 -> 15524 | J21: =D21-I21 -> 0 | K21: 150DB | L21: 15.0
A22: 6 | B22: 8 - Buidling - Kayla - 27.5yr | C22: 12/08/17 | D22: 853456 | E22: 0 | F22: 0 | G22: 187501.68 | H22: 31034.76 | I22: =G22+H22 -> 218536.44 | J22: =D22-I22 -> 634919.56 | K22: S/L | L22: 27.5
A23: 7 | B23: 9 - Equipment - Kayla - 5yr | C23: 12/08/17 | D23: 35731 | E23: 0 | F23: 35731 | G23: 35731 | H23: 0 | I23: =G23+H23 -> 35731 | J23: =D23-I23 -> 0 | K23: 200DB | L23: 5.0
A24: 8 | B24: 9 - Equipment - Kayla - 15yr | C24: 12/08/17 | D24: 3185 | E24: 0 | F24: 3185 | G24: 3185 | H24: 0 | I24: =G24+H24 -> 3185 | J24: =D24-I24 -> 0 | K24: 150DB | L24: 15.0
A25: 9 | B25: 9 - Equipment - Kayla - 27.5yr | C25: 12/08/17 | D25: 175068 | E25: 0 | F25: 0 | G25: 38461.91 | H25: 6366.11 | I25: =G25+H25 -> 44828.02 | J25: =D25-I25 -> 130239.98 | K25: S/L | L25: 27.5
B26: Grand Total | D26: =SUM(D17:D25) -> 1337398 | E26: =SUM(E17:E25) -> 0 | F26: =SUM(F17:F25) -> 228631 | G26: =SUM(G17:G25) -> 483610.68 | H26: =SUM(H17:H25) -> 39788.14 | I26: =SUM(I17:I25) -> 523398.82 | J26: =SUM(J17:J25) -> 813999.18
B28: Section 481(a) Adjustment — Regular Tax
B29: Depreciation reported previously | D29: =I13 -> 523830.88
B30: Cost Segregation Corrected Depreciation | D30: =I26 -> 523398.82
B31: Section 481(a) Adjustment — Regular Tax | D31: =D29-D30 -> 432.06
A33: CALCULATION OF §481(a) ADJUSTMENT — AMT
A34: As Previously Filed — AMT
A35: Asset | B35: Property Description | C35: Date In Service | D35: Cost | E35: Sec 179 Exp | F35: Bonus Amt | G35: AMT Prior Depreciation | H35: AMT Current Depreciation | I35: End Depreciation | J35: Net Book Value | K35: Method | L35: Period
A36: 1 | B36: 7 - Land Improvements - Kayla | C36: 12/08/17 | D36: 80244 | E36: 0 | F36: 0 | G36: 37993.4 | H36: 4738.57 | I36: =G36+H36 -> 42731.97 | J36: =D36-I36 -> 37512.03 | K36: 150DB | L36: 15.0
A37: 2 | B37: 8 - Buidling - Kayla | C37: 12/08/17 | D37: 1043171 | E37: 0 | F37: 0 | G37: 229182.26 | H37: 37933.65 | I37: =G37+H37 -> 267115.91 | J37: =D37-I37 -> 776055.09 | K37: S/L | L37: 27.5
A38: 3 | B38: 9 - Equipment - Kayla | C38: 12/08/17 | D38: 213983 | E38: 0 | F38: 213983 | G38: 213983 | H38: 0 | I38: =G38+H38 -> 213983 | J38: =D38-I38 -> 0 | K38: 200DB | L38: 5.0
B39: Grand Total | D39: =SUM(D36:D38) -> 1337398 | E39: =SUM(E36:E38) -> 0 | F39: =SUM(F36:F38) -> 213983 | G39: =SUM(G36:G38) -> 481158.66 | H39: =SUM(H36:H38) -> 42672.22 | I39: =SUM(I36:I38) -> 523830.88 | J39: =SUM(J36:J38) -> 813567.12
A41: After Cost Segregation Correction — AMT
A42: Asset | B42: Property Description | C42: Date In Service | D42: Cost | E42: Sec 179 Exp | F42: Bonus Amt | G42: AMT Prior Depreciation | H42: AMT Current Depreciation | I42: End Depreciation | J42: Net Book Value | K42: Method | L42: Period
A43: 1 | B43: 7 - Land Improvements - Kayla - 5yr | C43: 12/08/17 | D43: 13399 | E43: 0 | F43: 0 | G43: 13399 | H43: 0 | I43: =G43+H43 -> 13399 | J43: =D43-I43 -> 0 | K43: 200DB | L43: 5.0
A44: 2 | B44: 7 - Land Improvements - Kayla - 15yr | C44: 12/08/17 | D44: 1194 | E44: 0 | F44: 0 | G44: 1194 | H44: 0 | I44: =G44+H44 -> 1194 | J44: =D44-I44 -> 0 | K44: 150DB | L44: 15.0
A45: 3 | B45: 7 - Land Improvements - Kayla - 27.5yr | C45: 12/08/17 | D45: 65650 | E45: 0 | F45: 0 | G45: 14423.09 | H45: 2387.27 | I45: =G45+H45 -> 16810.36 | J45: =D45-I45 -> 48839.64 | K45: S/L | L45: 27.5
A46: 4 | B46: 8 - Buidling - Kayla - 5yr | C46: 12/08/17 | D46: 174191 | E46: 0 | F46: 174191 | G46: 174191 | H46: 0 | I46: =G46+H46 -> 174191 | J46: =D46-I46 -> 0 | K46: 200DB | L46: 5.0
A47: 5 | B47: 8 - Buidling - Kayla - 15yr | C47: 12/08/17 | D47: 15524 | E47: 0 | F47: 15524 | G47: 15524 | H47: 0 | I47: =G47+H47 -> 15524 | J47: =D47-I47 -> 0 | K47: 150DB | L47: 15.0
A48: 6 | B48: 8 - Buidling - Kayla - 27.5yr | C48: 12/08/17 | D48: 853456 | E48: 0 | F48: 0 | G48: 187501.68 | H48: 31034.76 | I48: =G48+H48 -> 218536.44 | J48: =D48-I48 -> 634919.56 | K48: S/L | L48: 27.5
A49: 7 | B49: 9 - Equipment - Kayla - 5yr | C49: 12/08/17 | D49: 35731 | E49: 0 | F49: 35731 | G49: 35731 | H49: 0 | I49: =G49+H49 -> 35731 | J49: =D49-I49 -> 0 | K49: 200DB | L49: 5.0
A50: 8 | B50: 9 - Equipment - Kayla - 15yr | C50: 12/08/17 | D50: 3185 | E50: 0 | F50: 3185 | G50: 3185 | H50: 0 | I50: =G50+H50 -> 3185 | J50: =D50-I50 -> 0 | K50: 150DB | L50: 15.0
A51: 9 | B51: 9 - Equipment - Kayla - 27.5yr | C51: 12/08/17 | D51: 175068 | E51: 0 | F51: 0 | G51: 38461.91 | H51: 6366.11 | I51: =G51+H51 -> 44828.02 | J51: =D51-I51 -> 130239.98 | K51: S/L | L51: 27.5
B52: Grand Total | D52: =SUM(D43:D51) -> 1337398 | E52: =SUM(E43:E51) -> 0 | F52: =SUM(F43:F51) -> 228631 | G52: =SUM(G43:G51) -> 483610.68 | H52: =SUM(H43:H51) -> 39788.14 | I52: =SUM(I43:I51) -> 523398.82 | J52: =SUM(J43:J51) -> 813999.18
B54: Section 481(a) Adjustment — AMT
B55: Depreciation reported previously | D55: =I39 -> 523830.88
B56: Cost Segregation Corrected Depreciation | D56: =I52 -> 523398.82
B57: Section 481(a) Adjustment — AMT | D57: =D55-D56 -> 432.06
A59: COST SEGREGATION STUDY — COST SUMMARY
B60: Total Building Cost | D60: =D107 -> 44579.92
B61: Building Components: 5 Year | D61: =F107 -> 7444.03
B62: % of Cost | D62: =F108 -> 0.16698168
B63: Site Improvements: 15 Year | D63: =H107 -> 663.44
B64: % of Cost | D64: =H108 -> 0.014882037
B65: Building Structure: 27.5 Year | D65: =J107 -> 36472.45
B66: % of Cost | D66: =J108 -> 0.81813628
A68: COST SEGREGATION STUDY — COST DETAIL
B69: Property Category | D69: Cost | F69: 5 Year | H69: 15 Year | J69: 27.5 Year
B70: Building Components
B71: Cabinets / Millwork | D71: =SUM(F71:J71) -> 1253.18 | F71: 1253.18
B72: Moldings | D72: =SUM(F72:J72) -> 1025.1 | F72: 1025.1
B73: Flooring - Wood Laminate | D73: =SUM(F73:J73) -> 1949.87 | F73: 1949.87
B74: Security System | D74: =SUM(F74:J74) -> 539.2 | F74: 539.2
B75: Window Treatments | D75: =SUM(F75:J75) -> 392.2 | F75: 392.2
B76: Specialty HVAC - Dryer Vents | D76: =SUM(F76:J76) -> 33.89 | F76: 33.89
B77: Building Signage | D77: =SUM(F77:J77) -> 22.29 | F77: 22.29
B78: Specialty Electrical - Appliances | D78: =SUM(F78:J78) -> 578.78 | F78: 578.78
B79: Communication / Data | D79: =SUM(F79:J79) -> 255.33 | F79: 255.33
B80: Specialty Plumbing - Kitchen Sink / Laundry | D80: =SUM(F80:J80) -> 633.66 | F80: 633.66
B81: Security / Exterior Lighting | D81: =SUM(F81:J81) -> 125.71 | F81: 125.71
B82: Appliances | D82: =SUM(F82:J82) -> 634.82 | F82: 634.82
B83: Site Work / Improvements
B84: Driveway | D84: =SUM(F84:J84) -> 440.5 | H84: 440.5
B85: Sidewalks / Curbs | D85: =SUM(F85:J85) -> 159.55 | H85: 159.55
B86: Exterior Equipment Concrete Pads | D86: =SUM(F86:J86) -> 39.13 | H86: 39.13
B87: Mailboxes | D87: =SUM(F87:J87) -> 24.26 | H87: 24.26
B88: Building Structure
B89: Roofing Systems | D89: =SUM(F89:J89) -> 2834.33 | J89: 2834.33
B90: Foundations | D90: =SUM(F90:J90) -> 5611.36 | J90: 5611.36
B91: HVAC | D91: =SUM(F91:J91) -> 2625.61 | J91: 2625.61
B92: Electrical | D92: =SUM(F92:J92) -> 2802.9 | J92: 2802.9
B93: Plumbing | D93: =SUM(F93:J93) -> 2311.88 | J93: 2311.88
B94: Fire Protection & Alarm | D94: =SUM(F94:J94) -> 135.25 | J94: 135.25
B95: Exterior Façade / Building Skin | D95: =SUM(F95:J95) -> 2244.42 | J95: 2244.42
B96: Doors & Frames | D96: =SUM(F96:J96) -> 1579.74 | J96: 1579.74
B97: Windows | D97: =SUM(F97:J97) -> 1728.69 | J97: 1728.69
B98: Ceiling Systems | D98: =SUM(F98:J98) -> 1362.6 | J98: 1362.6
B99: Interior Framing / Partitions | D99: =SUM(F99:J99) -> 4921.02 | J99: 4921.02
B100: Painting | D100: =SUM(F100:J100) -> 1576.54 | J100: 1576.54
... B106: Cabinets / Millwork - Restrooms | D106: =SUM(F106:J106) -> 311.62 | J106: 311.62
B107: Total Building Cost | D107: =SUM(D70:D106) -> 44579.92 | F107: =SUM(F70:F106) -> 7444.03 | H107: =SUM(H70:H106) -> 663.44 | J107: =SUM(J70:J106) -> 36472.45
B108: % of Cost | F108: =F107/D107 -> 0.16698168 | H108: =H107/D107 -> 0.014882037 | J108: =J107/D107 -> 0.81813628
A110: ASSET ALLOCATION (per After Cost Segregation schedule)
B111: Asset (as reclassified) | D111: Cost | F111: 5 Year | H111: 15 Year | J111: 27.5 Year
B112: ='7112 Kayla'!B17 -> 7 - Land Improvements - Kayla - 5yr | D112: =SUM(F112:J112) -> 13399 | F112: ='7112 Kayla'!D17 -> 13399
B113: ='7112 Kayla'!B18 -> 7 - Land Improvements - Kayla - 15yr | D113: =SUM(F113:J113) -> 1194 | H113: ='7112 Kayla'!D18 -> 1194
B114: ='7112 Kayla'!B19 -> 7 - Land Improvements - Kayla - 27.5yr | D114: =SUM(F114:J114) -> 65650 | J114: ='7112 Kayla'!D19 -> 65650
...

Sheet 7141 Kayla
A1: Marrero 3 LP
A2: Marrero 3 — 530 Ames Blvd, Marrero, LA 70072
A3: EIN: 82-2324040 · FYE: December 31, 2024 · Year of Change: 1/1/2024
A4: 7141 Kayla — Attachment to Form 3115 (DCN #7, Rev. Proc. 2024-23 §6.01)
A5: Source: CSSI Report #107752-18, "#107752-18_Marrero 3 - 3115 Combined.pdf"
A7: CALCULATION OF §481(a) ADJUSTMENT — REGULAR TAX
A8: As Previously Filed
A9: Asset | B9: Property Description | C9: Date In Service | D9: Cost | E9: Sec 179 Exp | F9: Bonus Amt | G9: Tax Prior Depreciation | H9: Tax Current Depreciation | I9: End Depreciation | J9: Net Book Value | K9: Method | L9: Period
A10: 1 | B10: 7 - Land Improvements - Kayla | C10: 12/08/17 | D10: 18110 | E10: 0 | F10: 0 | G10: 8574.6 | H10: 1069.43 | I10: =G10+H10 -> 9644.03 | J10: =D10-I10 -> 8465.97 | K10: 150DB | L10: 15.0
A11: 2 | B11: 8 - Buidling - Kayla | C11: 12/08/17 | D11: 235436 | E11: 0 | F11: 0 | G11: 51724.74 | H11: 8561.35 | I11: =G11+H11 -> 60286.09 | J11: =D11-I11 -> 175149.91 | K11: S/L | L11: 27.5
A12: 3 | B12: 9 - Equipment - Kayla | C12: 12/08/17 | D12: 48295 | E12: 0 | F12: 48295 | G12: 48295 | H12: 0 | I12: =G12+H12 -> 48295 | J12: =D12-I12 -> 0 | K12: 200DB | L12: 5.0
B13: Grand Total | D13: =SUM(D10:D12) -> 301841 | E13: =SUM(E10:E12) -> 0 | F13: =SUM(F10:F12) -> 48295 | G13: =SUM(G10:G12) -> 108594.34 | H13: =SUM(H10:H12) -> 9630.78 | I13: =SUM(I10:I12) -> 118225.12 | J13: =SUM(J10:J12) -> 183615.88
A15: After Cost Segregation Correction
A16: Asset | B16: Property Description | C16: Date In Service | D16: Cost | E16: Sec 179 Exp | F16: Bonus Amt | G16: Tax Prior Depreciation | H16: Tax Current Depreciation | I16: End Depreciation | J16: Net Book Value | K16: Method | L16: Period
A17: 1 | B17: 7 - Land Improvements - Kayla - 5yr | C17: 12/08/17 | D17: 2962 | E17: 0 | F17: 0 | G17: 2962 | H17: 0 | I17: =G17+H17 -> 2962 | J17: =D17-I17 -> 0 | K17: 200DB | L17: 5.0
A18: 2 | B18: 7 - Land Improvements - Kayla - 15yr | C18: 12/08/17 | D18: 336 | E18: 0 | F18: 0 | G18: 336 | H18: 0 | I18: =G18+H18 -> 336 | J18: =D18-I18 -> 0 | K18: 150DB | L18: 15.0
A19: 3 | B19: 7 - Land Improvements - Kayla - 27.5yr | C19: 12/08/17 | D19: 14813 | E19: 0 | F19: 0 | G19: 3254.34 | H19: 538.65 | I19: =G19+H19 -> 3792.99 | J19: =D19-I19 -> 11020.01 | K19: S/L | L19: 27.5
A20: 4 | B20: 8 - Buidling - Kayla - 5yr | C20: 12/08/17 | D20: 38500 | E20: 0 | F20: 38500 | G20: 38500 | H20: 0 | I20: =G20+H20 -> 38500 | J20: =D20-I20 -> 0 | K20: 200DB | L20: 5.0
A21: 5 | B21: 8 - Buidling - Kayla - 15yr | C21: 12/08/17 | D21: 4364 | E21: 0 | F21: 4364 | G21: 4364 | H21: 0 | I21: =G21+H21 -> 4364 | J21: =D21-I21 -> 0 | K21: 150DB | L21: 15.0
A22: 6 | B22: 8 - Buidling - Kayla - 27.5yr | C22: 12/08/17 | D22: 192572 | E22: 0 | F22: 0 | G22: 42307.5 | H22: 7002.62 | I22: =G22+H22 -> 49310.12 | J22: =D22-I22 -> 143261.88 | K22: S/L | L22: 27.5
A23: 7 | B23: 9 - Equipment - Kayla - 5yr | C23: 12/08/17 | D23: 7898 | E23: 0 | F23: 7898 | G23: 7898 | H23: 0 | I23: =G23+H23 -> 7898 | J23: =D23-I23 -> 0 | K23: 200DB | L23: 5.0
A24: 8 | B24: 9 - Equipment - Kayla - 15yr | C24: 12/08/17 | D24: 895 | E24: 0 | F24: 895 | G24: 895 | H24: 0 | I24: =G24+H24 -> 895 | J24: =D24-I24 -> 0 | K24: 150DB | L24: 15.0
A25: 9 | B25: 9 - Equipment - Kayla - 27.5yr | C25: 12/08/17 | D25: 39501 | E25: 0 | F25: 0 | G25: 8678.49 | H25: 1436.4 | I25: =G25+H25 -> 10114.89 | J25: =D25-I25 -> 29386.11 | K25: S/L | L25: 27.5
B26: Grand Total | D26: =SUM(D17:D25) -> 301841 | E26: =SUM(E17:E25) -> 0 | F26: =SUM(F17:F25) -> 51657 | G26: =SUM(G17:G25) -> 109195.33 | H26: =SUM(H17:H25) -> 8977.67 | I26: =SUM(I17:I25) -> 118173 | J26: =SUM(J17:J25) -> 183668
B28: Section 481(a) Adjustment — Regular Tax
B29: Depreciation reported previously | D29: =I13 -> 118225.12
B30: Cost Segregation Corrected Depreciation | D30: =I26 -> 118173
B31: Section 481(a) Adjustment — Regular Tax | D31: =D29-D30 -> 52.12
A33: CALCULATION OF §481(a) ADJUSTMENT — AMT
A34: As Previously Filed — AMT
A35: Asset | B35: Property Description | C35: Date In Service | D35: Cost | E35: Sec 179 Exp | F35: Bonus Amt | G35: AMT Prior Depreciation | H35: AMT Current Depreciation | I35: End Depreciation | J35: Net Book Value | K35: Method | L35: Period
A36: 1 | B36: 7 - Land Improvements - Kayla | C36: 12/08/17 | D36: 18110 | E36: 0 | F36: 0 | G36: 8574.6 | H36: 1069.43 | I36: =G36+H36 -> 9644.03 | J36: =D36-I36 -> 8465.97 | K36: 150DB | L36: 15.0
A37: 2 | B37: 8 - Buidling - Kayla | C37: 12/08/17 | D37: 235436 | E37: 0 | F37: 0 | G37: 51724.74 | H37: 8561.35 | I37: =G37+H37 -> 60286.09 | J37: =D37-I37 -> 175149.91 | K37: S/L | L37: 27.5
A38: 3 | B38: 9 - Equipment - Kayla | C38: 12/08/17 | D38: 48295 | E38: 0 | F38: 48295 | G38: 48295 | H38: 0 | I38: =G38+H38 -> 48295 | J38: =D38-I38 -> 0 | K38: 200DB | L38: 5.0
B39: Grand Total | D39: =SUM(D36:D38) -> 301841 | E39: =SUM(E36:E38) -> 0 | F39: =SUM(F36:F38) -> 48295 | G39: =SUM(G36:G38) -> 108594.34 | H39: =SUM(H36:H38) -> 9630.78 | I39: =SUM(I36:I38) -> 118225.12 | J39: =SUM(J36:J38) -> 183615.88
A41: After Cost Segregation Correction — AMT
A42: Asset | B42: Property Description | C42: Date In Service | D42: Cost | E42: Sec 179 Exp | F42: Bonus Amt | G42: AMT Prior Depreciation | H42: AMT Current Depreciation | I42: End Depreciation | J42: Net Book Value | K42: Method | L42: Period
A43: 1 | B43: 7 - Land Improvements - Kayla - 5yr | C43: 12/08/17 | D43: 2962 | E43: 0 | F43: 0 | G43: 2962 | H43: 0 | I43: =G43+H43 -> 2962 | J43: =D43-I43 -> 0 | K43: 200DB | L43: 5.0
A44: 2 | B44: 7 - Land Improvements - Kayla - 15yr | C44: 12/08/17 | D44: 336 | E44: 0 | F44: 0 | G44: 336 | H44: 0 | I44: =G44+H44 -> 336 | J44: =D44-I44 -> 0 | K44: 150DB | L44: 15.0
A45: 3 | B45: 7 - Land Improvements - Kayla - 27.5yr | C45: 12/08/17 | D45: 14813 | E45: 0 | F45: 0 | G45: 3254.34 | H45: 538.65 | I45: =G45+H45 -> 3792.99 | J45: =D45-I45 -> 11020.01 | K45: S/L | L45: 27.5
A46: 4 | B46: 8 - Buidling - Kayla - 5yr | C46: 12/08/17 | D46: 38500 | E46: 0 | F46: 38500 | G46: 38500 | H46: 0 | I46: =G46+H46 -> 38500 | J46: =D46-I46 -> 0 | K46: 200DB | L46: 5.0
A47: 5 | B47: 8 - Buidling - Kayla - 15yr | C47: 12/08/17 | D47: 4364 | E47: 0 | F47: 4364 | G47: 4364 | H47: 0 | I47: =G47+H47 -> 4364 | J47: =D47-I47 -> 0 | K47: 150DB | L47: 15.0
A48: 6 | B48: 8 - Buidling - Kayla - 27.5yr | C48: 12/08/17 | D48: 192572 | E48: 0 | F48: 0 | G48: 42307.5 | H48: 7002.62 | I48: =G48+H48 -> 49310.12 | J48: =D48-I48 -> 143261.88 | K48: S/L | L48: 27.5
A49: 7 | B49: 9 - Equipment - Kayla - 5yr | C49: 12/08/17 | D49: 7898 | E49: 0 | F49: 7898 | G49: 7898 | H49: 0 | I49: =G49+H49 -> 7898 | J49: =D49-I49 -> 0 | K49: 200DB | L49: 5.0
A50: 8 | B50: 9 - Equipment - Kayla - 15yr | C50: 12/08/17 | D50: 895 | E50: 0 | F50: 895 | G50: 895 | H50: 0 | I50: =G50+H50 -> 895 | J50: =D50-I50 -> 0 | K50: 150DB | L50: 15.0
A51: 9 | B51: 9 - Equipment - Kayla - 27.5yr | C51: 12/08/17 | D51: 39501 | E51: 0 | F51: 0 | G51: 8678.49 | H51: 1436.4 | I51: =G51+H51 -> 10114.89 | J51: =D51-I51 -> 29386.11 | K51: S/L | L51: 27.5
B52: Grand Total | D52: =SUM(D43:D51) -> 301841 | E52: =SUM(E43:E51) -> 0 | F52: =SUM(F43:F51) -> 51657 | G52: =SUM(G43:G51) -> 109195.33 | H52: =SUM(H43:H51) -> 8977.67 | I52: =SUM(I43:I51) -> 118173 | J52: =SUM(J43:J51) -> 183668
B54: Section 481(a) Adjustment — AMT
B55: Depreciation reported previously | D55: =I39 -> 118225.12
B56: Cost Segregation Corrected Depreciation | D56: =I52 -> 118173
B57: Section 481(a) Adjustment — AMT | D57: =D55-D56 -> 52.12
A59: COST SEGREGATION STUDY — COST SUMMARY
B60: Total Building Cost | D60: =D107 -> 43120.19
B61: Building Components: 5 Year | D61: =F107 -> 7051.36
B62: % of Cost | D62: =F108 -> 0.16352804
B63: Site Improvements: 15 Year | D63: =H107 -> 799.21
B64: % of Cost | D64: =H108 -> 0.018534473
B65: Building Structure: 27.5 Year | D65: =J107 -> 35269.62
B66: % of Cost | D66: =J108 -> 0.81793749
A68: COST SEGREGATION STUDY — COST DETAIL
B69: Property Category | D69: Cost | F69: 5 Year | H69: 15 Year | J69: 27.5 Year
B70: Building Components
B71: Cabinets / Millwork | D71: =SUM(F71:J71) -> 1224.05 | F71: 1224.05
B72: Moldings | D72: =SUM(F72:J72) -> 1003.14 | F72: 1003.14
B73: Flooring - Wood Laminate | D73: =SUM(F73:J73) -> 1894.04 | F73: 1894.04
B74: Security System | D74: =SUM(F74:J74) -> 398.36 | F74: 398.36
B75: Window Treatments | D75: =SUM(F75:J75) -> 254.6 | F75: 254.6
B76: Specialty HVAC - Dryer Vents | D76: =SUM(F76:J76) -> 33.89 | F76: 33.89
B77: Building Signage | D77: =SUM(F77:J77) -> 22.29 | F77: 22.29
B78: Specialty Electrical - Appliances | D78: =SUM(F78:J78) -> 578.78 | F78: 578.78
B79: Communication / Data | D79: =SUM(F79:J79) -> 248.02 | F79: 248.02
B80: Specialty Plumbing - Kitchen Sink / Laundry | D80: =SUM(F80:J80) -> 633.66 | F80: 633.66
B81: Security / Exterior Lighting | D81: =SUM(F81:J81) -> 125.71 | F81: 125.71
B82: Appliances | D82: =SUM(F82:J82) -> 634.82 | F82: 634.82
B83: Site Work / Improvements
B84: Driveway | D84: =SUM(F84:J84) -> 506.65 | H84: 506.65
B85: Sidewalks / Curbs | D85: =SUM(F85:J85) -> 229.17 | H85: 229.17
B86: Exterior Equipment Concrete Pads | D86: =SUM(F86:J86) -> 39.13 | H86: 39.13
B87: Mailboxes | D87: =SUM(F87:J87) -> 24.26 | H87: 24.26
B88: Building Structure
B89: Roofing Systems | D89: =SUM(F89:J89) -> 2548.43 | J89: 2548.43
B90: Foundations | D90: =SUM(F90:J90) -> 5484.79 | J90: 5484.79
B91: HVAC | D91: =SUM(F91:J91) -> 2549.45 | J91: 2549.45
B92: Electrical | D92: =SUM(F92:J92) -> 2713.95 | J92: 2713.95
B93: Plumbing | D93: =SUM(F93:J93) -> 2245.68 | J93: 2245.68
B94: Fire Protection & Alarm | D94: =SUM(F94:J94) -> 169.07 | J94: 169.07
B95: Exterior Façade / Building Skin | D95: =SUM(F95:J95) -> 2358.3 | J95: 2358.3
B96: Doors & Frames | D96: =SUM(F96:J96) -> 1892.23 | J96: 1892.23
B97: Windows | D97: =SUM(F97:J97) -> 1122.14 | J97: 1122.14
B98: Ceiling Systems | D98: =SUM(F98:J98) -> 1326.93 | J98: 1326.93
B99: Interior Framing / Partitions | D99: =SUM(F99:J99) -> 4881.53 | J99: 4881.53
B100: Painting | D100: =SUM(F100:J100) -> 1557.23 | J100: 1557.23
... B106: Cabinets / Millwork - Restrooms | D106: =SUM(F106:J106) -> 314.69 | J106: 314.69
B107: Total Building Cost | D107: =SUM(D70:D106) -> 43120.19 | F107: =SUM(F70:F106) -> 7051.36 | H107: =SUM(H70:H106) -> 799.21 | J107: =SUM(J70:J106) -> 35269.62
B108: % of Cost | F108: =F107/D107 -> 0.16352804 | H108: =H107/D107 -> 0.018534473 | J108: =J107/D107 -> 0.81793749
A110: ASSET ALLOCATION (per After Cost Segregation schedule)
B111: Asset (as reclassified) | D111: Cost | F111: 5 Year | H111: 15 Year | J111: 27.5 Year
B112: ='7141 Kayla'!B17 -> 7 - Land Improvements - Kayla - 5yr | D112: =SUM(F112:J112) -> 2962 | F112: ='7141 Kayla'!D17 -> 2962
B113: ='7141 Kayla'!B18 -> 7 - Land Improvements - Kayla - 15yr | D113: =SUM(F113:J113) -> 336 | H113: ='7141 Kayla'!D18 -> 336
B114: ='7141 Kayla'!B19 -> 7 - Land Improvements - Kayla - 27.5yr | D114: =SUM(F114:J114) -> 14813 | J114: ='7141 Kayla'!D19 -> 14813
...
