Workbook

Sheet Summary
A1: River Garden Estates Housing LP
A2: River Garden Estates — 2201 Northview Dr & 712 Northfield Dr, Sacramento, CA 95833
A3: EIN: 93-2096487 · FYE: December 31, 2024 · Year of Change: 1/1/2024
A4: Summary of Cost Segregation Adjustments — CSSI Report #107552-43 (CAM — DCN #7)
A7: Acq Date | B7: Asset Description | C7: Total | D7: Site | E7: Building 1 | F7: Building 2 | G7: Building 3 | H7: Building 4 | I7: Building 5 | J7: Building 6 | K7: Building 7 | L7: Building 8 | M7: Building 9 | N7: Building 10 | O7: Building 11 | P7: Building 12 | Q7: Building 13 | R7: Building 14 | S7: Building 15 | T7: Building 16 | U7: Building 17 | V7: Building 18 | W7: Building 19 | X7: Building 20 | Y7: Building 21 | Z7: Building 22 | AA7: Shed A | AB7: Shed B | AC7: Laundry
A8: 7/30/24 | B8: 2-Building-712 Northfield Dr | C8: =SUM(D8:AC8) -> 1018903 | D8: =Site!$D$10 -> 166583.41 | E8: ='Building 1'!$D$10 -> 45270.97 | F8: ='Building 2'!$D$10 -> 34585.09 | G8: ='Building 3'!$D$10 -> 27290.76 | H8: ='Building 4'!$D$10 -> 53518.91 | I8: ='Building 5'!$D$10 -> 27290.76 | J8: ='Building 6'!$D$10 -> 53518.91 | K8: ='Building 7'!$D$10 -> 34585.09 | L8: ='Building 8'!$D$10 -> 46450.25 | M8: ='Building 9'!$D$10 -> 46321.61 | N8: ='Building 10'!$D$10 -> 27290.76 | O8: ='Building 11'!$D$10 -> 60219.73 | P8: ='Building 12'!$D$10 -> 39989.86 | Q8: ='Building 13'!$D$10 -> 39989.86 | R8: ='Building 14'!$D$10 -> 39989.86 | S8: ='Building 15'!$D$10 -> 60219.73 | T8: ='Building 16'!$D$10 -> 27290.76 | U8: ='Building 17'!$D$10 -> 20620.86 | V8: ='Building 18'!$D$10 -> 20620.86 | W8: ='Building 19'!$D$10 -> 34211.45 | X8: ='Building 20'!$D$10 -> 45795.35 | Y8: ='Building 21'!$D$10 -> 27290.76 | Z8: ='Building 22'!$D$10 -> 34211.45 | AA8: ='Shed A'!$D$10 -> 1082.72 | AB8: ='Shed B'!$D$10 -> 1082.23 | AC8: =Laundry!$D$10 -> 3581
A9: 7/30/24 | B9: 3-Northfield Dr | C9: =SUM(D9:AC9) -> 131471 | D9: =Site!$D$11 -> 21494.58 | E9: ='Building 1'!$D$11 -> 5841.4 | F9: ='Building 2'!$D$11 -> 4462.58 | G9: ='Building 3'!$D$11 -> 3521.38 | H9: ='Building 4'!$D$11 -> 6905.65 | I9: ='Building 5'!$D$11 -> 3521.38 | J9: ='Building 6'!$D$11 -> 6905.65 | K9: ='Building 7'!$D$11 -> 4462.58 | L9: ='Building 8'!$D$11 -> 5993.57 | M9: ='Building 9'!$D$11 -> 5976.97 | N9: ='Building 10'!$D$11 -> 3521.38 | O9: ='Building 11'!$D$11 -> 7770.26 | P9: ='Building 12'!$D$11 -> 5159.97 | Q9: ='Building 13'!$D$11 -> 5159.97 | R9: ='Building 14'!$D$11 -> 5159.97 | S9: ='Building 15'!$D$11 -> 7770.26 | T9: ='Building 16'!$D$11 -> 3521.38 | U9: ='Building 17'!$D$11 -> 2660.75 | V9: ='Building 18'!$D$11 -> 2660.75 | W9: ='Building 19'!$D$11 -> 4414.37 | X9: ='Building 20'!$D$11 -> 5909.06 | Y9: ='Building 21'!$D$11 -> 3521.38 | Z9: ='Building 22'!$D$11 -> 4414.37 | AA9: ='Shed A'!$D$11 -> 139.71 | AB9: ='Shed B'!$D$11 -> 139.64 | AC9: =Laundry!$D$11 -> 462.04
A10: 7/30/24 | B10: 4-Northfield Dr | C10: =SUM(D10:AC10) -> 246509 | D10: =Site!$D$12 -> 40302.47 | E10: ='Building 1'!$D$12 -> 10952.66 | F10: ='Building 2'!$D$12 -> 8367.37 | G10: ='Building 3'!$D$12 -> 6602.61 | H10: ='Building 4'!$D$12 -> 12948.13 | I10: ='Building 5'!$D$12 -> 6602.61 | J10: ='Building 6'!$D$12 -> 12948.13 | K10: ='Building 7'!$D$12 -> 8367.37 | L10: ='Building 8'!$D$12 -> 11237.98 | M10: ='Building 9'!$D$12 -> 11206.85 | N10: ='Building 10'!$D$12 -> 6602.61 | O10: ='Building 11'!$D$12 -> 14569.3 | P10: ='Building 12'!$D$12 -> 9674.97 | Q10: ='Building 13'!$D$12 -> 9674.97 | R10: ='Building 14'!$D$12 -> 9674.97 | S10: ='Building 15'!$D$12 -> 14569.3 | T10: ='Building 16'!$D$12 -> 6602.61 | U10: ='Building 17'!$D$12 -> 4988.92 | V10: ='Building 18'!$D$12 -> 4988.92 | W10: ='Building 19'!$D$12 -> 8276.98 | X10: ='Building 20'!$D$12 -> 11079.53 | Y10: ='Building 21'!$D$12 -> 6602.61 | Z10: ='Building 22'!$D$12 -> 8276.98 | AA10: ='Shed A'!$D$12 -> 261.95 | AB10: ='Shed B'!$D$12 -> 261.83 | AC10: =Laundry!$D$12 -> 866.37
A11: 7/30/24 | B11: 7-Building-2202 Northview Dr | C11: =SUM(D11:AC11) -> 4692432 | D11: =Site!$D$13 -> 767179.32 | E11: ='Building 1'!$D$13 -> 208489.87 | F11: ='Building 2'!$D$13 -> 159277.36 | G11: ='Building 3'!$D$13 -> 125684.23 | H11: ='Building 4'!$D$13 -> 246474.74 | I11: ='Building 5'!$D$13 -> 125684.23 | J11: ='Building 6'!$D$13 -> 246474.74 | K11: ='Building 7'!$D$13 -> 159277.36 | L11: ='Building 8'!$D$13 -> 213920.95 | M11: ='Building 9'!$D$13 -> 213328.45 | N11: ='Building 10'!$D$13 -> 125684.23 | O11: ='Building 11'!$D$13 -> 277334.53 | P11: ='Building 12'!$D$13 -> 184168.35 | Q11: ='Building 13'!$D$13 -> 184168.35 | R11: ='Building 14'!$D$13 -> 184168.35 | S11: ='Building 15'!$D$13 -> 277334.53 | T11: ='Building 16'!$D$13 -> 125684.23 | U11: ='Building 17'!$D$13 -> 94966.8 | V11: ='Building 18'!$D$13 -> 94966.8 | W11: ='Building 19'!$D$13 -> 157556.61 | X11: ='Building 20'!$D$13 -> 210904.84 | Y11: ='Building 21'!$D$13 -> 125684.23 | Z11: ='Building 22'!$D$13 -> 157556.61 | AA11: ='Shed A'!$D$13 -> 4986.32 | AB11: ='Shed B'!$D$13 -> 4984.09 | AC11: =Laundry!$D$13 -> 16491.88
A12: 7/30/24 | B12: 8-Northiew Dr | C12: =SUM(D12:AC12) -> 605475 | D12: =Site!$D$14 -> 98990.86 | E12: ='Building 1'!$D$14 -> 26901.91 | F12: ='Building 2'!$D$14 -> 20551.91 | G12: ='Building 3'!$D$14 -> 16217.32 | H12: ='Building 4'!$D$14 -> 31803.19 | I12: ='Building 5'!$D$14 -> 16217.32 | J12: ='Building 6'!$D$14 -> 31803.19 | K12: ='Building 7'!$D$14 -> 20551.91 | L12: ='Building 8'!$D$14 -> 27602.7 | M12: ='Building 9'!$D$14 -> 27526.25 | N12: ='Building 10'!$D$14 -> 16217.32 | O12: ='Building 11'!$D$14 -> 35785.1 | P12: ='Building 12'!$D$14 -> 23763.65 | Q12: ='Building 13'!$D$14 -> 23763.65 | R12: ='Building 14'!$D$14 -> 23763.65 | S12: ='Building 15'!$D$14 -> 35785.1 | T12: ='Building 16'!$D$14 -> 16217.32 | U12: ='Building 17'!$D$14 -> 12253.78 | V12: ='Building 18'!$D$14 -> 12253.78 | W12: ='Building 19'!$D$14 -> 20329.88 | X12: ='Building 20'!$D$14 -> 27213.52 | Y12: ='Building 21'!$D$14 -> 16217.32 | Z12: ='Building 22'!$D$14 -> 20329.88 | AA12: ='Shed A'!$D$14 -> 643.4 | AB12: ='Shed B'!$D$14 -> 643.11 | AC12: =Laundry!$D$14 -> 2127.98
A13: 7/30/24 | B13: 9-Northview Dr | C13: =SUM(D13:AC13) -> 1135266 | D13: =Site!$D$15 -> 185607.93 | E13: ='Building 1'!$D$15 -> 50441.11 | F13: ='Building 2'!$D$15 -> 38534.85 | G13: ='Building 3'!$D$15 -> 30407.48 | H13: ='Building 4'!$D$15 -> 59631 | I13: ='Building 5'!$D$15 -> 30407.48 | J13: ='Building 6'!$D$15 -> 59631 | K13: ='Building 7'!$D$15 -> 38534.85 | L13: ='Building 8'!$D$15 -> 51755.08 | M13: ='Building 9'!$D$15 -> 51611.73 | N13: ='Building 10'!$D$15 -> 30407.48 | O13: ='Building 11'!$D$15 -> 67097.08 | P13: ='Building 12'!$D$15 -> 44556.87 | Q13: ='Building 13'!$D$15 -> 44556.87 | R13: ='Building 14'!$D$15 -> 44556.87 | S13: ='Building 15'!$D$15 -> 67097.08 | T13: ='Building 16'!$D$15 -> 30407.48 | U13: ='Building 17'!$D$15 -> 22975.84 | V13: ='Building 18'!$D$15 -> 22975.84 | W13: ='Building 19'!$D$15 -> 38118.54 | X13: ='Building 20'!$D$15 -> 51025.37 | Y13: ='Building 21'!$D$15 -> 30407.48 | Z13: ='Building 22'!$D$15 -> 38118.54 | AA13: ='Shed A'!$D$15 -> 1206.36 | AB13: ='Shed B'!$D$15 -> 1205.83 | AC13: =Laundry!$D$15 -> 3989.96
B14: Grand Total | C14: =SUM(C8:C13) -> 7830056 | D14: =SUM(D8:D13) -> 1280158.6 | E14: =SUM(E8:E13) -> 347897.92 | F14: =SUM(F8:F13) -> 265779.16 | G14: =SUM(G8:G13) -> 209723.78 | H14: =SUM(H8:H13) -> 411281.62 | I14: =SUM(I8:I13) -> 209723.78 | J14: =SUM(J8:J13) -> 411281.62 | ... AC14: =SUM(AC8:AC13) -> 27519.23
B16: MACRS Reclassification
A17: 7/30/24 | B17: 2-Building-712 Northfield Dr - 5 Year | C17: =SUM(D17:AC17) -> 159168.46 | D17: =Site!$D$20 -> 866.85 | E17: ='Building 1'!$D$20 -> 7916.21 | F17: ='Building 2'!$D$20 -> 6299.49 | G17: ='Building 3'!$D$20 -> 5001.64 | H17: ='Building 4'!$D$20 -> 9996.83 | I17: ='Building 5'!$D$20 -> 5001.64 | J17: ='Building 6'!$D$20 -> 9996.83 | K17: ='Building 7'!$D$20 -> 6299.49 | L17: ='Building 8'!$D$20 -> 8679.19 | M17: ='Building 9'!$D$20 -> 8603.17 | N17: ='Building 10'!$D$20 -> 5001.64 | O17: ='Building 11'!$D$20 -> 11223.57 | P17: ='Building 12'!$D$20 -> 7464.18 | Q17: ='Building 13'!$D$20 -> 7464.18 | R17: ='Building 14'!$D$20 -> 7464.18 | S17: ='Building 15'!$D$20 -> 11223.57 | T17: ='Building 16'!$D$20 -> 5001.64 | U17: ='Building 17'!$D$20 -> 3763.31 | V17: ='Building 18'!$D$20 -> 3763.31 | W17: ='Building 19'!$D$20 -> 6184.29 | X17: ='Building 20'!$D$20 -> 8473.25 | Y17: ='Building 21'!$D$20 -> 5001.64 | Z17: ='Building 22'!$D$20 -> 6184.29 | AB17: ='Shed B'!$D$20 -> 21.89 | AC17: =Laundry!$D$20 -> 2272.18
A18: 7/30/24 | B18: 2-Building-712 Northfield Dr - 15 Year | C18: =SUM(D18:AC18) -> 110068.96 | D18: =Site!$D$21 -> 110068.96
A19: 7/30/24 | B19: 2-Building-712 Northfield Dr - 27.5 Year | C19: =SUM(D19:AC19) -> 749665.58 | D19: =Site!$D$22 -> 55647.6 | E19: ='Building 1'!$D$21 -> 37354.76 | F19: ='Building 2'!$D$21 -> 28285.6 | G19: ='Building 3'!$D$21 -> 22289.12 | H19: ='Building 4'!$D$21 -> 43522.08 | I19: ='Building 5'!$D$21 -> 22289.12 | J19: ='Building 6'!$D$21 -> 43522.08 | K19: ='Building 7'!$D$21 -> 28285.6 | L19: ='Building 8'!$D$21 -> 37771.06 | M19: ='Building 9'!$D$21 -> 37718.44 | N19: ='Building 10'!$D$21 -> 22289.12 | O19: ='Building 11'!$D$21 -> 48996.16 | P19: ='Building 12'!$D$21 -> 32525.68 | Q19: ='Building 13'!$D$21 -> 32525.68 | R19: ='Building 14'!$D$21 -> 32525.68 | S19: ='Building 15'!$D$21 -> 48996.16 | T19: ='Building 16'!$D$21 -> 22289.12 | U19: ='Building 17'!$D$21 -> 16857.55 | V19: ='Building 18'!$D$21 -> 16857.55 | W19: ='Building 19'!$D$21 -> 28027.16 | X19: ='Building 20'!$D$21 -> 37322.1 | Y19: ='Building 21'!$D$21 -> 22289.12 | Z19: ='Building 22'!$D$21 -> 28027.16 | AA19: ='Shed A'!$D$20 -> 1082.72 | AB19: ='Shed B'!$D$21 -> 1060.34 | AC19: =Laundry!$D$21 -> 1308.82
A20: 7/30/24 | B20: 3-Northfield Dr - 5 Year | C20: =SUM(D20:AC20) -> 20537.8 | D20: =Site!$D$23 -> 111.85 | E20: ='Building 1'!$D$22 -> 1021.44 | F20: ='Building 2'!$D$22 -> 812.84 | G20: ='Building 3'!$D$22 -> 645.37 | H20: ='Building 4'!$D$22 -> 1289.91 | I20: ='Building 5'!$D$22 -> 645.37 | J20: ='Building 6'!$D$22 -> 1289.91 | K20: ='Building 7'!$D$22 -> 812.84 | L20: ='Building 8'!$D$22 -> 1119.89 | M20: ='Building 9'!$D$22 -> 1110.08 | N20: ='Building 10'!$D$22 -> 645.37 | O20: ='Building 11'!$D$22 -> 1448.2 | P20: ='Building 12'!$D$22 -> 963.12 | Q20: ='Building 13'!$D$22 -> 963.12 | R20: ='Building 14'!$D$22 -> 963.12 | S20: ='Building 15'!$D$22 -> 1448.2 | T20: ='Building 16'!$D$22 -> 645.37 | U20: ='Building 17'!$D$22 -> 485.59 | V20: ='Building 18'!$D$22 -> 485.59 | W20: ='Building 19'!$D$22 -> 797.97 | X20: ='Building 20'!$D$22 -> 1093.32 | Y20: ='Building 21'!$D$22 -> 645.37 | Z20: ='Building 22'!$D$22 -> 797.97 | AB20: ='Shed B'!$D$22 -> 2.82 | AC20: =Laundry!$D$22 -> 293.17
A21: 7/30/24 | B21: 3-Northfield Dr - 15 Year | C21: =SUM(D21:AC21) -> 14202.41 | D21: =Site!$D$24 -> 14202.41
A22: 7/30/24 | B22: 3-Northfield Dr - 27.5 Year | C22: =SUM(D22:AC22) -> 96730.79 | D22: =Site!$D$25 -> 7180.32 | E22: ='Building 1'!$D$23 -> 4819.96 | F22: ='Building 2'!$D$23 -> 3649.74 | G22: ='Building 3'!$D$23 -> 2876.01 | H22: ='Building 4'!$D$23 -> 5615.74 | I22: ='Building 5'!$D$23 -> 2876.01 | J22: ='Building 6'!$D$23 -> 5615.74 | K22: ='Building 7'!$D$23 -> 3649.74 | L22: ='Building 8'!$D$23 -> 4873.68 | M22: ='Building 9'!$D$23 -> 4866.89 | N22: ='Building 10'!$D$23 -> 2876.01 | O22: ='Building 11'!$D$23 -> 6322.06 | P22: ='Building 12'!$D$23 -> 4196.85 | Q22: ='Building 13'!$D$23 -> 4196.85 | R22: ='Building 14'!$D$23 -> 4196.85 | S22: ='Building 15'!$D$23 -> 6322.06 | T22: ='Building 16'!$D$23 -> 2876.01 | U22: ='Building 17'!$D$23 -> 2175.16 | V22: ='Building 18'!$D$23 -> 2175.16 | W22: ='Building 19'!$D$23 -> 3616.4 | X22: ='Building 20'!$D$23 -> 4815.74 | Y22: ='Building 21'!$D$23 -> 2876.01 | Z22: ='Building 22'!$D$23 -> 3616.4 | AA22: ='Shed A'!$D$21 -> 139.71 | AB22: ='Shed B'!$D$23 -> 136.82 | AC22: =Laundry!$D$23 -> 168.87
A23: 7/30/24 | B23: 4-Northfield Dr - 5 Year | C23: =SUM(D23:AC23) -> 38508.54 | D23: =Site!$D$26 -> 209.72 | E23: ='Building 1'!$D$24 -> 1915.21 | F23: ='Building 2'!$D$24 -> 1524.07 | G23: ='Building 3'!$D$24 -> 1210.08 | H23: ='Building 4'!$D$24 -> 2418.59 | I23: ='Building 5'!$D$24 -> 1210.08 | J23: ='Building 6'!$D$24 -> 2418.59 | K23: ='Building 7'!$D$24 -> 1524.07 | L23: ='Building 8'!$D$24 -> 2099.81 | M23: ='Building 9'!$D$24 -> 2081.41 | N23: ='Building 10'!$D$24 -> 1210.08 | O23: ='Building 11'!$D$24 -> 2715.38 | P23: ='Building 12'!$D$24 -> 1805.85 | Q23: ='Building 13'!$D$24 -> 1805.85 | R23: ='Building 14'!$D$24 -> 1805.85 | S23: ='Building 15'!$D$24 -> 2715.38 | T23: ='Building 16'!$D$24 -> 1210.08 | U23: ='Building 17'!$D$24 -> 910.48 | V23: ='Building 18'!$D$24 -> 910.48 | W23: ='Building 19'!$D$24 -> 1496.2 | X23: ='Building 20'!$D$24 -> 2049.98 | Y23: ='Building 21'!$D$24 -> 1210.08 | Z23: ='Building 22'!$D$24 -> 1496.2 | AB23: ='Shed B'!$D$24 -> 5.3 | AC23: =Laundry!$D$24 -> 549.72
A24: 7/30/24 | B24: 4-Northfield Dr - 15 Year | C24: =SUM(D24:AC24) -> 26629.61 | D24: =Site!$D$27 -> 26629.61
A25: 7/30/24 | B25: 4-Northfield Dr - 27.5 Year | C25: =SUM(D25:AC25) -> 181370.85 | D25: =Site!$D$28 -> 13463.14 | E25: ='Building 1'!$D$25 -> 9037.45 | F25: ='Building 2'!$D$25 -> 6843.3 | G25: ='Building 3'!$D$25 -> 5392.53 | H25: ='Building 4'!$D$25 -> 10529.54 | I25: ='Building 5'!$D$25 -> 5392.53 | J25: ='Building 6'!$D$25 -> 10529.54 | K25: ='Building 7'!$D$25 -> 6843.3 | L25: ='Building 8'!$D$25 -> 9138.17 | M25: ='Building 9'!$D$25 -> 9125.44 | N25: ='Building 10'!$D$25 -> 5392.53 | O25: ='Building 11'!$D$25 -> 11853.92 | P25: ='Building 12'!$D$25 -> 7869.12 | Q25: ='Building 13'!$D$25 -> 7869.12 | R25: ='Building 14'!$D$25 -> 7869.12 | S25: ='Building 15'!$D$25 -> 11853.92 | T25: ='Building 16'!$D$25 -> 5392.53 | U25: ='Building 17'!$D$25 -> 4078.44 | V25: ='Building 18'!$D$25 -> 4078.44 | W25: ='Building 19'!$D$25 -> 6780.78 | X25: ='Building 20'!$D$25 -> 9029.55 | Y25: ='Building 21'!$D$25 -> 5392.53 | Z25: ='Building 22'!$D$25 -> 6780.78 | AA25: ='Shed A'!$D$22 -> 261.95 | AB25: ='Shed B'!$D$25 -> 256.53 | AC25: =Laundry!$D$25 -> 316.65
A26: 7/30/24 | B26: 7-Building-2202 Northview Dr - 5 Year | C26: =SUM(D26:AC26) -> 733030.85 | D26: =Site!$D$29 -> 3992.15 | E26: ='Building 1'!$D$26 -> 36457.14 | F26: ='Building 2'!$D$26 -> 29011.54 | G26: ='Building 3'!$D$26 -> 23034.43 | H26: ='Building 4'!$D$26 -> 46039.18 | I26: ='Building 5'!$D$26 -> 23034.43 | J26: ='Building 6'!$D$26 -> 46039.18 | K26: ='Building 7'!$D$26 -> 29011.54 | L26: ='Building 8'!$D$26 -> 39970.95 | M26: ='Building 9'!$D$26 -> 39620.83 | N26: ='Building 10'!$D$26 -> 23034.43 | O26: ='Building 11'!$D$26 -> 51688.76 | P26: ='Building 12'!$D$26 -> 34375.37 | Q26: ='Building 13'!$D$26 -> 34375.37 | R26: ='Building 14'!$D$26 -> 34375.37 | S26: ='Building 15'!$D$26 -> 51688.76 | T26: ='Building 16'!$D$26 -> 23034.43 | U26: ='Building 17'!$D$26 -> 17331.47 | V26: ='Building 18'!$D$26 -> 17331.47 | W26: ='Building 19'!$D$26 -> 28481.01 | X26: ='Building 20'!$D$26 -> 39022.5 | Y26: ='Building 21'!$D$26 -> 23034.43 | Z26: ='Building 22'!$D$26 -> 28481.01 | AB26: ='Shed B'!$D$26 -> 100.82 | AC26: =Laundry!$D$26 -> 10464.28
A27: 7/30/24 | B27: 7-Building-2202 Northview Dr - 15 Year | C27: =SUM(D27:AC27) -> 506909.01 | D27: =Site!$D$30 -> 506909.01
A28: 7/30/24 | B28: 7-Building-2202 Northview Dr - 27.5 Year | C28: =SUM(D28:AC28) -> 3452492.1 | D28: =Site!$D$31 -> 256278.16 | E28: ='Building 1'!$D$27 -> 172032.73 | F28: ='Building 2'!$D$27 -> 130265.82 | G28: ='Building 3'!$D$27 -> 102649.8 | H28: ='Building 4'!$D$27 -> 200435.56 | I28: ='Building 5'!$D$27 -> 102649.8 | J28: ='Building 6'!$D$27 -> 200435.56 | K28: ='Building 7'!$D$27 -> 130265.82 | L28: ='Building 8'!$D$27 -> 173950 | M28: ='Building 9'!$D$27 -> 173707.62 | N28: ='Building 10'!$D$27 -> 102649.8 | O28: ='Building 11'!$D$27 -> 225645.77 | P28: ='Building 12'!$D$27 -> 149792.98 | Q28: ='Building 13'!$D$27 -> 149792.98 | R28: ='Building 14'!$D$27 -> 149792.98 | S28: ='Building 15'!$D$27 -> 225645.77 | T28: ='Building 16'!$D$27 -> 102649.8 | U28: ='Building 17'!$D$27 -> 77635.33 | V28: ='Building 18'!$D$27 -> 77635.33 | W28: ='Building 19'!$D$27 -> 129075.6 | X28: ='Building 20'!$D$27 -> 171882.34 | Y28: ='Building 21'!$D$27 -> 102649.8 | Z28: ='Building 22'!$D$27 -> 129075.6 | AA28: ='Shed A'!$D$23 -> 4986.32 | AB28: ='Shed B'!$D$27 -> 4883.27 | AC28: =Laundry!$D$27 -> 6027.6
A29: 7/30/24 | B29: 8-Northiew Dr - 5 Year | C29: =SUM(D29:AC29) -> 94584.6 | D29: =Site!$D$32 -> 515.12 | E29: ='Building 1'!$D$28 -> 4704.15 | F29: ='Building 2'!$D$28 -> 3743.42 | G29: ='Building 3'!$D$28 -> 2972.18 | H29: ='Building 4'!$D$28 -> 5940.54 | I29: ='Building 5'!$D$28 -> 2972.18 | J29: ='Building 6'!$D$28 -> 5940.54 | K29: ='Building 7'!$D$28 -> 3743.42 | L29: ='Building 8'!$D$28 -> 5157.54 | M29: ='Building 9'!$D$28 -> 5112.36 | N29: ='Building 10'!$D$28 -> 2972.18 | O29: ='Building 11'!$D$28 -> 6669.52 | P29: ='Building 12'!$D$28 -> 4435.53 | Q29: ='Building 13'!$D$28 -> 4435.53 | R29: ='Building 14'!$D$28 -> 4435.53 | S29: ='Building 15'!$D$28 -> 6669.52 | T29: ='Building 16'!$D$28 -> 2972.18 | U29: ='Building 17'!$D$28 -> 2236.32 | V29: ='Building 18'!$D$28 -> 2236.32 | W29: ='Building 19'!$D$28 -> 3674.97 | X29: ='Building 20'!$D$28 -> 5035.16 | Y29: ='Building 21'!$D$28 -> 2972.18 | Z29: ='Building 22'!$D$28 -> 3674.97 | AB29: ='Shed B'!$D$28 -> 13.01 | AC29: =Laundry!$D$28 -> 1350.23
A30: 7/30/24 | B30: 8-Northiew Dr - 15 Year | C30: =SUM(D30:AC30) -> 65407.6 | D30: =Site!$D$33 -> 65407.6
A31: 7/30/24 | B31: 8-Northiew Dr - 27.5 Year | C31: =SUM(D31:AC31) -> 445482.8 | D31: =Site!$D$34 -> 33068.14 | E31: ='Building 1'!$D$29 -> 22197.76 | F31: ='Building 2'!$D$29 -> 16808.49 | G31: ='Building 3'!$D$29 -> 13245.14 | H31: ='Building 4'!$D$29 -> 25862.65 | I31: ='Building 5'!$D$29 -> 13245.14 | J31: ='Building 6'!$D$29 -> 25862.65 | K31: ='Building 7'!$D$29 -> 16808.49 | L31: ='Building 8'!$D$29 -> 22445.16 | M31: ='Building 9'!$D$29 -> 22413.89 | N31: ='Building 10'!$D$29 -> 13245.14 | O31: ='Building 11'!$D$29 -> 29115.58 | P31: ='Building 12'!$D$29 -> 19328.12 | Q31: ='Building 13'!$D$29 -> 19328.12 | R31: ='Building 14'!$D$29 -> 19328.12 | S31: ='Building 15'!$D$29 -> 29115.58 | T31: ='Building 16'!$D$29 -> 13245.14 | U31: ='Building 17'!$D$29 -> 10017.46 | V31: ='Building 18'!$D$29 -> 10017.46 | W31: ='Building 19'!$D$29 -> 16654.91 | X31: ='Building 20'!$D$29 -> 22178.36 | Y31: ='Building 21'!$D$29 -> 13245.14 | Z31: ='Building 22'!$D$29 -> 16654.91 | AA31: ='Shed A'!$D$24 -> 643.4 | AB31: ='Shed B'!$D$29 -> 630.1 | AC31: =Laundry!$D$29 -> 777.75
A32: 7/30/24 | B32: 9-Northview Dr - 5 Year | C32: =SUM(D32:AC32) -> 177346.2 | D32: =Site!$D$35 -> 965.84 | E32: ='Building 1'!$D$30 -> 8820.29 | F32: ='Building 2'!$D$30 -> 7018.93 | G32: ='Building 3'!$D$30 -> 5572.85 | H32: ='Building 4'!$D$30 -> 11138.51 | I32: ='Building 5'!$D$30 -> 5572.85 | J32: ='Building 6'!$D$30 -> 11138.51 | K32: ='Building 7'!$D$30 -> 7018.93 | L32: ='Building 8'!$D$30 -> 9670.4 | M32: ='Building 9'!$D$30 -> 9585.69 | N32: ='Building 10'!$D$30 -> 5572.85 | O32: ='Building 11'!$D$30 -> 12505.34 | P32: ='Building 12'!$D$30 -> 8316.62 | Q32: ='Building 13'!$D$30 -> 8316.62 | R32: ='Building 14'!$D$30 -> 8316.62 | S32: ='Building 15'!$D$30 -> 12505.34 | T32: ='Building 16'!$D$30 -> 5572.85 | U32: ='Building 17'!$D$30 -> 4193.09 | V32: ='Building 18'!$D$30 -> 4193.09 | W32: ='Building 19'!$D$30 -> 6890.57 | X32: ='Building 20'!$D$30 -> 9440.93 | Y32: ='Building 21'!$D$30 -> 5572.85 | Z32: ='Building 22'!$D$30 -> 6890.57 | AB32: ='Shed B'!$D$30 -> 24.39 | AC32: =Laundry!$D$30 -> 2531.67
A33: 7/30/24 | B33: 9-Northview Dr - 15 Year | C33: =SUM(D33:AC33) -> 122639.3 | D33: =Site!$D$36 -> 122639.3
A34: 7/30/24 | B34: 9-Northview Dr - 27.5 Year | C34: =SUM(D34:AC34) -> 835280.5 | D34: =Site!$D$37 -> 62002.79 | E34: ='Building 1'!$D$31 -> 41620.82 | F34: ='Building 2'!$D$31 -> 31515.92 | G34: ='Building 3'!$D$31 -> 24834.63 | H34: ='Building 4'!$D$31 -> 48492.49 | I34: ='Building 5'!$D$31 -> 24834.63 | J34: ='Building 6'!$D$31 -> 48492.49 | K34: ='Building 7'!$D$31 -> 31515.92 | L34: ='Building 8'!$D$31 -> 42084.68 | M34: ='Building 9'!$D$31 -> 42026.04 | N34: ='Building 10'!$D$31 -> 24834.63 | O34: ='Building 11'!$D$31 -> 54591.74 | P34: ='Building 12'!$D$31 -> 36240.25 | Q34: ='Building 13'!$D$31 -> 36240.25 | R34: ='Building 14'!$D$31 -> 36240.25 | S34: ='Building 15'!$D$31 -> 54591.74 | T34: ='Building 16'!$D$31 -> 24834.63 | U34: ='Building 17'!$D$31 -> 18782.75 | V34: ='Building 18'!$D$31 -> 18782.75 | W34: ='Building 19'!$D$31 -> 31227.97 | X34: ='Building 20'!$D$31 -> 41584.44 | Y34: ='Building 21'!$D$31 -> 24834.63 | Z34: ='Building 22'!$D$31 -> 31227.97 | AA34: ='Shed A'!$D$25 -> 1206.36 | AB34: ='Shed B'!$D$31 -> 1181.44 | AC34: =Laundry!$D$31 -> 1458.29
B35: Total MACRS Reclassification | C35: =SUM(C17:C34) -> 7830056 | D35: =SUM(D17:D34) -> 1280158.6 | E35: =SUM(E17:E34) -> 347897.92 | F35: =SUM(F17:F34) -> 265779.16 | G35: =SUM(G17:G34) -> 209723.78 | H35: =SUM(H17:H34) -> 411281.62 | I35: =SUM(I17:I34) -> 209723.78 | J35: =SUM(J17:J34) -> 411281.62 | ... AC35: =SUM(AC17:AC34) -> 27519.23
B36: Difference (should be zero) | C36: =C14-C35 -> 0 | D36: =D14-D35 -> 0 | E36: =E14-E35 -> 0 | F36: =F14-F35 -> 0 | G36: =G14-G35 -> 0 | H36: =H14-H35 -> 0 | I36: =I14-I35 -> 0 | J36: =J14-J35 -> 0 | ... AC36: =AC14-AC35 -> 0
B38: End Depreciation Reconciliation
B39: Before Cost Segregation (As Previously Filed) | C39: =SUM(D39:AC39) -> 1486790 | D39: =Site!$I$16 -> 243079.61 | E39: ='Building 1'!$I$16 -> 66059.7 | F39: ='Building 2'!$I$16 -> 50466.79 | G39: ='Building 3'!$I$16 -> 39822.85 | H39: ='Building 4'!$I$16 -> 78095.16 | I39: ='Building 5'!$I$16 -> 39822.85 | J39: ='Building 6'!$I$16 -> 78095.16 | K39: ='Building 7'!$I$16 -> 50466.79 | L39: ='Building 8'!$I$16 -> 67780.54 | M39: ='Building 9'!$I$16 -> 67592.81 | N39: ='Building 10'!$I$16 -> 39822.85 | O39: ='Building 11'!$I$16 -> 87873.03 | P39: ='Building 12'!$I$16 -> 58353.46 | Q39: ='Building 13'!$I$16 -> 58353.46 | R39: ='Building 14'!$I$16 -> 58353.46 | S39: ='Building 15'!$I$16 -> 87873.03 | T39: ='Building 16'!$I$16 -> 39822.85 | U39: ='Building 17'!$I$16 -> 30090.09 | V39: ='Building 18'!$I$16 -> 30090.09 | W39: ='Building 19'!$I$16 -> 49921.58 | X39: ='Building 20'!$I$16 -> 66824.88 | Y39: ='Building 21'!$I$16 -> 39822.85 | Z39: ='Building 22'!$I$16 -> 49921.58 | AA39: ='Shed A'!$I$16 -> 1579.91 | AB39: ='Shed B'!$I$16 -> 1579.19 | AC39: =Laundry!$I$16 -> 5225.43
B40: 2-Building-712 Northfield Dr - 5 Year | C40: =SUM(D40:AC40) -> 108234.51 | D40: =Site!$I$20 -> 589.46 | E40: ='Building 1'!$I$20 -> 5383.03 | F40: ='Building 2'!$I$20 -> 4283.65 | G40: ='Building 3'!$I$20 -> 3401.11 | H40: ='Building 4'!$I$20 -> 6797.85 | I40: ='Building 5'!$I$20 -> 3401.11 | J40: ='Building 6'!$I$20 -> 6797.85 | K40: ='Building 7'!$I$20 -> 4283.65 | L40: ='Building 8'!$I$20 -> 5901.85 | M40: ='Building 9'!$I$20 -> 5850.15 | N40: ='Building 10'!$I$20 -> 3401.11 | O40: ='Building 11'!$I$20 -> 7632.03 | P40: ='Building 12'!$I$20 -> 5075.64 | Q40: ='Building 13'!$I$20 -> 5075.64 | R40: ='Building 14'!$I$20 -> 5075.64 | S40: ='Building 15'!$I$20 -> 7632.03 | T40: ='Building 16'!$I$20 -> 3401.11 | U40: ='Building 17'!$I$20 -> 2559.05 | V40: ='Building 18'!$I$20 -> 2559.05 | W40: ='Building 19'!$I$20 -> 4205.31 | X40: ='Building 20'!$I$20 -> 5761.81 | Y40: ='Building 21'!$I$20 -> 3401.11 | Z40: ='Building 22'!$I$20 -> 4205.31 | AB40: ='Shed B'!$I$20 -> 14.88 | AC40: =Laundry!$I$20 -> 1545.08
B41: 2-Building-712 Northfield Dr - 15 Year | C41: =SUM(D41:AC41) -> 68242.76 | D41: =Site!$I$21 -> 68242.76
B42: 2-Building-712 Northfield Dr - 27.5 Year | C42: =SUM(D42:AC42) -> 12494.44 | D42: =Site!$I$22 -> 927.46 | E42: ='Building 1'!$I$21 -> 622.58 | F42: ='Building 2'!$I$21 -> 471.43 | G42: ='Building 3'!$I$21 -> 371.49 | H42: ='Building 4'!$I$21 -> 725.37 | I42: ='Building 5'!$I$21 -> 371.49 | J42: ='Building 6'!$I$21 -> 725.37 | K42: ='Building 7'!$I$21 -> 471.43 | L42: ='Building 8'!$I$21 -> 629.52 | M42: ='Building 9'!$I$21 -> 628.64 | N42: ='Building 10'!$I$21 -> 371.49 | O42: ='Building 11'!$I$21 -> 816.6 | P42: ='Building 12'!$I$21 -> 542.09 | Q42: ='Building 13'!$I$21 -> 542.09 | R42: ='Building 14'!$I$21 -> 542.09 | S42: ='Building 15'!$I$21 -> 816.6 | T42: ='Building 16'!$I$21 -> 371.49 | U42: ='Building 17'!$I$21 -> 280.96 | V42: ='Building 18'!$I$21 -> 280.96 | W42: ='Building 19'!$I$21 -> 467.12 | X42: ='Building 20'!$I$21 -> 622.03 | Y42: ='Building 21'!$I$21 -> 371.49 | Z42: ='Building 22'!$I$21 -> 467.12 | AA42: ='Shed A'!$I$20 -> 18.05 | AB42: ='Shed B'!$I$21 -> 17.67 | AC42: =Laundry!$I$21 -> 21.81
B43: 3-Northfield Dr - 5 Year | C43: =SUM(D43:AC43) -> 13966.6 | D43: =Site!$I$23 -> 76.06 | E43: ='Building 1'!$I$22 -> 694.58 | F43: ='Building 2'!$I$22 -> 552.73 | G43: ='Building 3'!$I$22 -> 438.85 | H43: ='Building 4'!$I$22 -> 877.14 | I43: ='Building 5'!$I$22 -> 438.85 | J43: ='Building 6'!$I$22 -> 877.14 | K43: ='Building 7'!$I$22 -> 552.73 | L43: ='Building 8'!$I$22 -> 761.52 | M43: ='Building 9'!$I$22 -> 754.86 | N43: ='Building 10'!$I$22 -> 438.85 | O43: ='Building 11'!$I$22 -> 984.78 | P43: ='Building 12'!$I$22 -> 654.92 | Q43: ='Building 13'!$I$22 -> 654.92 | R43: ='Building 14'!$I$22 -> 654.92 | S43: ='Building 15'!$I$22 -> 984.78 | T43: ='Building 16'!$I$22 -> 438.85 | U43: ='Building 17'!$I$22 -> 330.2 | V43: ='Building 18'!$I$22 -> 330.2 | W43: ='Building 19'!$I$22 -> 542.62 | X43: ='Building 20'!$I$22 -> 743.46 | Y43: ='Building 21'!$I$22 -> 438.85 | Z43: ='Building 22'!$I$22 -> 542.62 | AB43: ='Shed B'!$I$22 -> 2.82 | AC43: =Laundry!$I$22 -> 199.35
B44: 3-Northfield Dr - 15 Year | C44: =SUM(D44:AC44) -> 8805.5 | D44: =Site!$I$24 -> 8805.5
B45: 3-Northfield Dr - 27.5 Year | C45: =SUM(D45:AC45) -> 1612.16 | D45: =Site!$I$25 -> 119.67 | E45: ='Building 1'!$I$23 -> 80.33 | F45: ='Building 2'!$I$23 -> 60.83 | G45: ='Building 3'!$I$23 -> 47.93 | H45: ='Building 4'!$I$23 -> 93.6 | I45: ='Building 5'!$I$23 -> 47.93 | J45: ='Building 6'!$I$23 -> 93.6 | K45: ='Building 7'!$I$23 -> 60.83 | L45: ='Building 8'!$I$23 -> 81.23 | M45: ='Building 9'!$I$23 -> 81.11 | N45: ='Building 10'!$I$23 -> 47.93 | O45: ='Building 11'!$I$23 -> 105.37 | P45: ='Building 12'!$I$23 -> 69.95 | Q45: ='Building 13'!$I$23 -> 69.95 | R45: ='Building 14'!$I$23 -> 69.95 | S45: ='Building 15'!$I$23 -> 105.37 | T45: ='Building 16'!$I$23 -> 47.93 | U45: ='Building 17'!$I$23 -> 36.25 | V45: ='Building 18'!$I$23 -> 36.25 | W45: ='Building 19'!$I$23 -> 60.27 | X45: ='Building 20'!$I$23 -> 80.26 | Y45: ='Building 21'!$I$23 -> 47.93 | Z45: ='Building 22'!$I$23 -> 60.27 | AA45: ='Shed A'!$I$21 -> 2.33 | AB45: ='Shed B'!$I$23 -> 2.28 | AC45: =Laundry!$I$23 -> 2.81
B46: 4-Northfield Dr - 5 Year | C46: =SUM(D46:AC46) -> 26185.87 | D46: =Site!$I$26 -> 142.61 | E46: ='Building 1'!$I$24 -> 1302.35 | F46: ='Building 2'!$I$24 -> 1036.37 | G46: ='Building 3'!$I$24 -> 822.86 | H46: ='Building 4'!$I$24 -> 1644.64 | I46: ='Building 5'!$I$24 -> 822.86 | J46: ='Building 6'!$I$24 -> 1644.64 | K46: ='Building 7'!$I$24 -> 1036.37 | L46: ='Building 8'!$I$24 -> 1427.87 | M46: ='Building 9'!$I$24 -> 1415.36 | N46: ='Building 10'!$I$24 -> 822.86 | O46: ='Building 11'!$I$24 -> 1846.46 | P46: ='Building 12'!$I$24 -> 1227.98 | Q46: ='Building 13'!$I$24 -> 1227.98 | R46: ='Building 14'!$I$24 -> 1227.98 | S46: ='Building 15'!$I$24 -> 1846.46 | T46: ='Building 16'!$I$24 -> 822.86 | U46: ='Building 17'!$I$24 -> 619.13 | V46: ='Building 18'!$I$24 -> 619.13 | W46: ='Building 19'!$I$24 -> 1017.42 | X46: ='Building 20'!$I$24 -> 1393.99 | Y46: ='Building 21'!$I$24 -> 822.86 | Z46: ='Building 22'!$I$24 -> 1017.42 | AB46: ='Shed B'!$I$24 -> 3.6 | AC46: =Laundry!$I$24 -> 373.81
B47: 4-Northfield Dr - 15 Year | C47: =SUM(D47:AC47) -> 16510.36 | D47: =Site!$I$27 -> 16510.36
B48: 4-Northfield Dr - 27.5 Year | C48: =SUM(D48:AC48) -> 3022.87 | D48: =Site!$I$28 -> 224.39 | E48: ='Building 1'!$I$25 -> 150.62 | F48: ='Building 2'!$I$25 -> 114.06 | G48: ='Building 3'!$I$25 -> 89.88 | H48: ='Building 4'!$I$25 -> 175.49 | I48: ='Building 5'!$I$25 -> 89.88 | J48: ='Building 6'!$I$25 -> 175.49 | K48: ='Building 7'!$I$25 -> 114.06 | L48: ='Building 8'!$I$25 -> 152.3 | M48: ='Building 9'!$I$25 -> 152.09 | N48: ='Building 10'!$I$25 -> 89.88 | O48: ='Building 11'!$I$25 -> 197.57 | P48: ='Building 12'!$I$25 -> 131.15 | Q48: ='Building 13'!$I$25 -> 131.15 | R48: ='Building 14'!$I$25 -> 131.15 | S48: ='Building 15'!$I$25 -> 197.57 | T48: ='Building 16'!$I$25 -> 89.88 | U48: ='Building 17'!$I$25 -> 67.97 | V48: ='Building 18'!$I$25 -> 67.97 | W48: ='Building 19'!$I$25 -> 113.01 | X48: ='Building 20'!$I$25 -> 150.49 | Y48: ='Building 21'!$I$25 -> 89.88 | Z48: ='Building 22'!$I$25 -> 113.01 | AA48: ='Shed A'!$I$22 -> 4.37 | AB48: ='Shed B'!$I$25 -> 4.28 | AC48: =Laundry!$I$25 -> 5.28
B49: 7-Building-2202 Northview Dr - 5 Year | C49: =SUM(D49:AC49) -> 498460.96 | D49: =Site!$I$29 -> 2714.66 | E49: ='Building 1'!$I$26 -> 24790.85 | F49: ='Building 2'!$I$26 -> 19727.84 | G49: ='Building 3'!$I$26 -> 15663.41 | H49: ='Building 4'!$I$26 -> 31306.64 | I49: ='Building 5'!$I$26 -> 15663.41 | J49: ='Building 6'!$I$26 -> 31306.64 | K49: ='Building 7'!$I$26 -> 19727.84 | L49: ='Building 8'!$I$26 -> 27180.25 | M49: ='Building 9'!$I$26 -> 26942.17 | N49: ='Building 10'!$I$26 -> 15663.41 | O49: ='Building 11'!$I$26 -> 35148.36 | P49: ='Building 12'!$I$26 -> 23375.25 | Q49: ='Building 13'!$I$26 -> 23375.25 | R49: ='Building 14'!$I$26 -> 23375.25 | S49: ='Building 15'!$I$26 -> 35148.36 | T49: ='Building 16'!$I$26 -> 15663.41 | U49: ='Building 17'!$I$26 -> 11785.4 | V49: ='Building 18'!$I$26 -> 11785.4 | W49: ='Building 19'!$I$26 -> 19367.09 | X49: ='Building 20'!$I$26 -> 26535.3 | Y49: ='Building 21'!$I$26 -> 15663.41 | Z49: ='Building 22'!$I$26 -> 19367.09 | AB49: ='Shed B'!$I$26 -> 68.56 | AC49: =Laundry!$I$26 -> 7115.71
B50: 7-Building-2202 Northview Dr - 15 Year | C50: =SUM(D50:AC50) -> 314283.59 | D50: =Site!$I$30 -> 314283.59
B51: 7-Building-2202 Northview Dr - 27.5 Year | C51: =SUM(D51:AC51) -> 57541.54 | D51: =Site!$I$31 -> 4271.3 | E51: ='Building 1'!$I$27 -> 2867.21 | F51: ='Building 2'!$I$27 -> 2171.1 | G51: ='Building 3'!$I$27 -> 1710.83 | H51: ='Building 4'!$I$27 -> 3340.59 | I51: ='Building 5'!$I$27 -> 1710.83 | J51: ='Building 6'!$I$27 -> 3340.59 | K51: ='Building 7'!$I$27 -> 2171.1 | L51: ='Building 8'!$I$27 -> 2899.17 | M51: ='Building 9'!$I$27 -> 2895.13 | N51: ='Building 10'!$I$27 -> 1710.83 | O51: ='Building 11'!$I$27 -> 3760.76 | P51: ='Building 12'!$I$27 -> 2496.55 | Q51: ='Building 13'!$I$27 -> 2496.55 | R51: ='Building 14'!$I$27 -> 2496.55 | S51: ='Building 15'!$I$27 -> 3760.76 | T51: ='Building 16'!$I$27 -> 1710.83 | U51: ='Building 17'!$I$27 -> 1293.92 | V51: ='Building 18'!$I$27 -> 1293.92 | W51: ='Building 19'!$I$27 -> 2151.26 | X51: ='Building 20'!$I$27 -> 2864.71 | Y51: ='Building 21'!$I$27 -> 1710.83 | Z51: ='Building 22'!$I$27 -> 2151.26 | AA51: ='Shed A'!$I$23 -> 83.11 | AB51: ='Shed B'!$I$27 -> 81.39 | AC51: =Laundry!$I$27 -> 100.46
B52: 8-Northiew Dr - 5 Year | C52: =SUM(D52:AC52) -> 64317.49 | D52: =Site!$I$32 -> 350.28 | E52: ='Building 1'!$I$28 -> 3198.82 | F52: ='Building 2'!$I$28 -> 2545.52 | G52: ='Building 3'!$I$28 -> 2021.08 | H52: ='Building 4'!$I$28 -> 4039.56 | I52: ='Building 5'!$I$28 -> 2021.08 | J52: ='Building 6'!$I$28 -> 4039.56 | K52: ='Building 7'!$I$28 -> 2545.52 | L52: ='Building 8'!$I$28 -> 3507.12 | M52: ='Building 9'!$I$28 -> 3476.41 | N52: ='Building 10'!$I$28 -> 2021.08 | O52: ='Building 11'!$I$28 -> 4535.27 | P52: ='Building 12'!$I$28 -> 3016.16 | Q52: ='Building 13'!$I$28 -> 3016.16 | R52: ='Building 14'!$I$28 -> 3016.16 | S52: ='Building 15'!$I$28 -> 4535.27 | T52: ='Building 16'!$I$28 -> 2021.08 | U52: ='Building 17'!$I$28 -> 1520.7 | V52: ='Building 18'!$I$28 -> 1520.7 | W52: ='Building 19'!$I$28 -> 2498.98 | X52: ='Building 20'!$I$28 -> 3423.91 | Y52: ='Building 21'!$I$28 -> 2021.08 | Z52: ='Building 22'!$I$28 -> 2498.98 | AB52: ='Shed B'!$I$28 -> 8.85 | AC52: =Laundry!$I$28 -> 918.16
B53: 8-Northiew Dr - 15 Year | C53: =SUM(D53:AC53) -> 40552.71 | D53: =Site!$I$33 -> 40552.71
B54: 8-Northiew Dr - 27.5 Year | C54: =SUM(D54:AC54) -> 7424.7 | D54: =Site!$I$34 -> 551.14 | E54: ='Building 1'!$I$29 -> 369.96 | F54: ='Building 2'!$I$29 -> 280.14 | G54: ='Building 3'!$I$29 -> 220.75 | H54: ='Building 4'!$I$29 -> 431.04 | I54: ='Building 5'!$I$29 -> 220.75 | J54: ='Building 6'!$I$29 -> 431.04 | K54: ='Building 7'!$I$29 -> 280.14 | L54: ='Building 8'!$I$29 -> 374.09 | M54: ='Building 9'!$I$29 -> 373.56 | N54: ='Building 10'!$I$29 -> 220.75 | O54: ='Building 11'!$I$29 -> 485.26 | P54: ='Building 12'!$I$29 -> 322.14 | Q54: ='Building 13'!$I$29 -> 322.14 | R54: ='Building 14'!$I$29 -> 322.14 | S54: ='Building 15'!$I$29 -> 485.26 | T54: ='Building 16'!$I$29 -> 220.75 | U54: ='Building 17'!$I$29 -> 166.96 | V54: ='Building 18'!$I$29 -> 166.96 | W54: ='Building 19'!$I$29 -> 277.58 | X54: ='Building 20'!$I$29 -> 369.64 | Y54: ='Building 21'!$I$29 -> 220.75 | Z54: ='Building 22'!$I$29 -> 277.58 | AA54: ='Shed A'!$I$24 -> 10.72 | AB54: ='Shed B'!$I$29 -> 10.5 | AC54: =Laundry!$I$29 -> 12.96
B55: 9-Northview Dr - 5 Year | C55: =SUM(D55:AC55) -> 120595.4 | D55: =Site!$I$35 -> 656.77 | E55: ='Building 1'!$I$30 -> 5997.79 | F55: ='Building 2'!$I$30 -> 4772.87 | G55: ='Building 3'!$I$30 -> 3789.54 | H55: ='Building 4'!$I$30 -> 7574.19 | I55: ='Building 5'!$I$30 -> 3789.54 | J55: ='Building 6'!$I$30 -> 7574.19 | K55: ='Building 7'!$I$30 -> 4772.87 | L55: ='Building 8'!$I$30 -> 6575.87 | M55: ='Building 9'!$I$30 -> 6518.27 | N55: ='Building 10'!$I$30 -> 3789.54 | O55: ='Building 11'!$I$30 -> 8503.63 | P55: ='Building 12'!$I$30 -> 5655.3 | Q55: ='Building 13'!$I$30 -> 5655.3 | R55: ='Building 14'!$I$30 -> 5655.3 | S55: ='Building 15'!$I$30 -> 8503.63 | T55: ='Building 16'!$I$30 -> 3789.54 | U55: ='Building 17'!$I$30 -> 2851.3 | V55: ='Building 18'!$I$30 -> 2851.3 | W55: ='Building 19'!$I$30 -> 4685.59 | X55: ='Building 20'!$I$30 -> 6419.83 | Y55: ='Building 21'!$I$30 -> 3789.54 | Z55: ='Building 22'!$I$30 -> 4685.59 | AB55: ='Shed B'!$I$30 -> 16.58 | AC55: =Laundry!$I$30 -> 1721.53
B56: 9-Northview Dr - 15 Year | C56: =SUM(D56:AC56) -> 76036.37 | D56: =Site!$I$36 -> 76036.37
B57: 9-Northview Dr - 27.5 Year | C57: =SUM(D57:AC57) -> 13921.34 | D57: =Site!$I$37 -> 1033.38 | E57: ='Building 1'!$I$31 -> 693.68 | F57: ='Building 2'!$I$31 -> 525.27 | G57: ='Building 3'!$I$31 -> 413.91 | H57: ='Building 4'!$I$31 -> 808.21 | I57: ='Building 5'!$I$31 -> 413.91 | J57: ='Building 6'!$I$31 -> 808.21 | K57: ='Building 7'!$I$31 -> 525.27 | L57: ='Building 8'!$I$31 -> 701.41 | M57: ='Building 9'!$I$31 -> 700.43 | N57: ='Building 10'!$I$31 -> 413.91 | O57: ='Building 11'!$I$31 -> 909.86 | P57: ='Building 12'!$I$31 -> 604 | Q57: ='Building 13'!$I$31 -> 604 | R57: ='Building 14'!$I$31 -> 604 | S57: ='Building 15'!$I$31 -> 909.86 | T57: ='Building 16'!$I$31 -> 413.91 | U57: ='Building 17'!$I$31 -> 313.05 | V57: ='Building 18'!$I$31 -> 313.05 | W57: ='Building 19'!$I$31 -> 520.47 | X57: ='Building 20'!$I$31 -> 693.07 | Y57: ='Building 21'!$I$31 -> 413.91 | Z57: ='Building 22'!$I$31 -> 520.47 | AA57: ='Shed A'!$I$25 -> 20.11 | AB57: ='Shed B'!$I$31 -> 19.69 | AC57: =Laundry!$I$31 -> 24.3
B58: After Cost Segregation (Corrected) | C58: =SUM(C40:C57) -> 1452209.2 | D58: =SUM(D40:D57) -> 536088.47 | E58: =SUM(E40:E57) -> 46151.8 | F58: =SUM(F40:F57) -> 36541.81 | G58: =SUM(G40:G57) -> 28991.64 | H58: =SUM(H40:H57) -> 57814.32 | I58: =SUM(I40:I57) -> 28991.64 | J58: =SUM(J40:J57) -> 57814.32 | ... AC58: =SUM(AC40:AC57) -> 12041.26
B59: Section 481(a) Adjustment | C59: =C39-C58 -> 34580.83 | D59: =D39-D58 -> -293008.86 | E59: =E39-E58 -> 19907.9 | F59: =F39-F58 -> 13924.98 | G59: =G39-G58 -> 10831.21 | H59: =H39-H58 -> 20280.84 | I59: =I39-I58 -> 10831.21 | J59: =J39-J58 -> 20280.84 | ... AC59: =AC39-AC58 -> -6815.83
B60: Check vs. unit-tab 481(a) cells (should be zero) | C60: =C59-(34580.83) -> -1.6007107e-10 | D60: =D59-Site!$D$43 -> 0 | E60: =E59-'Building 1'!$D$37 -> 0 | F60: =F59-'Building 2'!$D$37 -> 0 | G60: =G59-'Building 3'!$D$37 -> 0 | H60: =H59-'Building 4'!$D$37 -> 0 | I60: =I59-'Building 5'!$D$37 -> 0 | J60: =J59-'Building 6'!$D$37 -> 0 | K60: =K59-'Building 7'!$D$37 -> 0 | L60: =L59-'Building 8'!$D$37 -> 0 | M60: =M59-'Building 9'!$D$37 -> 0 | N60: =N59-'Building 10'!$D$37 -> 0 | O60: =O59-'Building 11'!$D$37 -> 0 | P60: =P59-'Building 12'!$D$37 -> 0 | Q60: =Q59-'Building 13'!$D$37 -> 0 | R60: =R59-'Building 14'!$D$37 -> 0 | S60: =S59-'Building 15'!$D$37 -> 0 | T60: =T59-'Building 16'!$D$37 -> 0 | U60: =U59-'Building 17'!$D$37 -> 0 | V60: =V59-'Building 18'!$D$37 -> 0 | W60: =W59-'Building 19'!$D$37 -> 0 | X60: =X59-'Building 20'!$D$37 -> 0 | Y60: =Y59-'Building 21'!$D$37 -> 0 | Z60: =Z59-'Building 22'!$D$37 -> 0 | AA60: =AA59-'Shed A'!$D$31 -> 0 | AB60: =AB59-'Shed B'!$D$37 -> 0 | AC60: =AC59-Laundry!$D$37 -> 0
B62: Notes
B63: 1. Total footed §481(a) adjustment across all units: 34,580.83 (Regular Tax; AMT equals Regular Tax on every unit in this report).
B64: 2. 'Building 15': Regular Tax page missing from PDF; AMT schedule used for both (values verified vs Summary Sheet)
B65: 3. The Form 3115 face page states a tax year of change beginning 1/1/2025, while the attached statements and all 481(a) schedules use a year of change beginning 1/1/2024 (FYE 12/31/2024). Confirm the intended year of change with the preparer before filing.
B66: 4. All End Depreciation, Net Book Value, totals, and 481(a) cells are live formulas; asset-level inputs are transcribed from the CSSI PDF. The Difference and Check rows must remain zero after any edit.

Sheet Site
A1: River Garden Estates Housing LP
A2: River Garden Estates — 2201 Northview Dr & 712 Northfield Dr, Sacramento, CA 95833
A3: EIN: 93-2096487 · FYE: December 31, 2024 · Year of Change: 1/1/2024
A4: Site — Attachment to Form 3115 (DCN #7, Rev. Proc. 2024-23 §6.01)
A5: Source: CSSI Report #107552-43, "#107552-43_River Garden Estates Housing LP_3115_Combined.pdf"
A7: CALCULATION OF §481(a) ADJUSTMENT — REGULAR TAX
A8: As Previously Filed
A9: Asset | B9: Property Description | C9: Date In Service | D9: Cost | E9: Sec 179 Exp | F9: Bonus Amt | G9: Tax Prior Depreciation | H9: Tax Current Depreciation | I9: End Depreciation | J9: Net Book Value | K9: Method | L9: Period
A10: 1 | B10: 2-Building-712 Northfield Dr | C10: 7/30/24 | D10: 166583.41 | E10: 0 | F10: 0 | G10: 0 | H10: 2776.44 | I10: =G10+H10 -> 2776.44 | J10: =D10-I10 -> 163806.97 | K10: S/L | L10: 27.5
A11: 2 | B11: 3-Northfield Dr | C11: 7/30/24 | D11: 21494.58 | E11: 0 | F11: 12896.75 | G11: 0 | H11: 13183.42 | I11: =G11+H11 -> 13183.42 | J11: =D11-I11 -> 8311.16 | K11: 150DB | L11: 15.0
A12: 3 | B12: 4-Northfield Dr | C12: 7/30/24 | D12: 40302.47 | E12: 0 | F12: 24181.48 | G12: 0 | H12: 27405.66 | I12: =G12+H12 -> 27405.66 | J12: =D12-I12 -> 12896.81 | K12: 200DB | L12: 5.0
A13: 4 | B13: 7-Building-2202 Northview Dr | C13: 7/30/24 | D13: 767179.32 | E13: 0 | F13: 0 | G13: 0 | H13: 12786.29 | I13: =G13+H13 -> 12786.29 | J13: =D13-I13 -> 754393.03 | K13: S/L | L13: 27.5
A14: 5 | B14: 8-Northiew Dr | C14: 7/30/24 | D14: 98990.86 | E14: 0 | F14: 59394.52 | G14: 0 | H14: 60714.39 | I14: =G14+H14 -> 60714.39 | J14: =D14-I14 -> 38276.47 | K14: 150DB | L14: 15.0
A15: 6 | B15: 9-Northview Dr | C15: 7/30/24 | D15: 185607.93 | E15: 0 | F15: 111364.76 | G15: 0 | H15: 126213.41 | I15: =G15+H15 -> 126213.41 | J15: =D15-I15 -> 59394.52 | K15: 200DB | L15: 5.0
B16: Grand Total | D16: =SUM(D10:D15) -> 1280158.6 | E16: =SUM(E10:E15) -> 0 | F16: =SUM(F10:F15) -> 207837.51 | G16: =SUM(G10:G15) -> 0 | H16: =SUM(H10:H15) -> 243079.61 | I16: =SUM(I10:I15) -> 243079.61 | J16: =SUM(J10:J15) -> 1037079
A18: After Cost Segregation Correction
A19: Asset | B19: Property Description | C19: Date In Service | D19: Cost | E19: Sec 179 Exp | F19: Bonus Amt | G19: Tax Prior Depreciation | H19: Tax Current Depreciation | I19: End Depreciation | J19: Net Book Value | K19: Method | L19: Period
A20: 1 | B20: 2-Building-712 Northfield Dr - 5 Year | C20: 7/30/24 | D20: 866.85 | E20: 0 | F20: 520.11 | G20: 0 | H20: 589.46 | I20: =G20+H20 -> 589.46 | J20: =D20-I20 -> 277.39 | K20: 200DB | L20: 5.0
A21: 2 | B21: 2-Building-712 Northfield Dr - 15 Year | C21: 7/30/24 | D21: 110068.96 | E21: 0 | F21: 66041.38 | G21: 0 | H21: 68242.76 | I21: =G21+H21 -> 68242.76 | J21: =D21-I21 -> 41826.2 | K21: 150DB | L21: 15.0
A22: 3 | B22: 2-Building-712 Northfield Dr - 27.5 Year | C22: 7/30/24 | D22: 55647.6 | E22: 0 | F22: 0 | G22: 0 | H22: 927.46 | I22: =G22+H22 -> 927.46 | J22: =D22-I22 -> 54720.14 | K22: S/L | L22: 27.5
A23: 4 | B23: 3-Northfield Dr - 5 Year | C23: 7/30/24 | D23: 111.85 | E23: 0 | F23: 67.11 | G23: 0 | H23: 76.06 | I23: =G23+H23 -> 76.06 | J23: =D23-I23 -> 35.79 | K23: 200DB | L23: 5.0
A24: 5 | B24: 3-Northfield Dr - 15 Year | C24: 7/30/24 | D24: 14202.41 | E24: 0 | F24: 8521.45 | G24: 0 | H24: 8805.5 | I24: =G24+H24 -> 8805.5 | J24: =D24-I24 -> 5396.91 | K24: 150DB | L24: 15.0
A25: 6 | B25: 3-Northfield Dr - 27.5 Year | C25: 7/30/24 | D25: 7180.32 | E25: 0 | F25: 0 | G25: 0 | H25: 119.67 | I25: =G25+H25 -> 119.67 | J25: =D25-I25 -> 7060.65 | K25: S/L | L25: 27.5
A26: 7 | B26: 4-Northfield Dr - 5 Year | C26: 7/30/24 | D26: 209.72 | E26: 0 | F26: 125.83 | G26: 0 | H26: 142.61 | I26: =G26+H26 -> 142.61 | J26: =D26-I26 -> 67.11 | K26: 200DB | L26: 5.0
A27: 8 | B27: 4-Northfield Dr - 15 Year | C27: 7/30/24 | D27: 26629.61 | E27: 0 | F27: 15977.77 | G27: 0 | H27: 16510.36 | I27: =G27+H27 -> 16510.36 | J27: =D27-I27 -> 10119.25 | K27: 150DB | L27: 15.0
A28: 9 | B28: 4-Northfield Dr - 27.5 Year | C28: 7/30/24 | D28: 13463.14 | E28: 0 | F28: 0 | G28: 0 | H28: 224.39 | I28: =G28+H28 -> 224.39 | J28: =D28-I28 -> 13238.75 | K28: S/L | L28: 27.5
A29: 10 | B29: 7-Building-2202 Northview Dr - 5 Year | C29: 7/30/24 | D29: 3992.15 | E29: 0 | F29: 2395.29 | G29: 0 | H29: 2714.66 | I29: =G29+H29 -> 2714.66 | J29: =D29-I29 -> 1277.49 | K29: 200DB | L29: 5.0
A30: 11 | B30: 7-Building-2202 Northview Dr - 15 Year | C30: 7/30/24 | D30: 506909.01 | E30: 0 | F30: 304145.41 | G30: 0 | H30: 314283.59 | I30: =G30+H30 -> 314283.59 | J30: =D30-I30 -> 192625.42 | K30: 150DB | L30: 15.0
A31: 12 | B31: 7-Building-2202 Northview Dr - 27.5 Year | C31: 7/30/24 | D31: 256278.16 | E31: 0 | F31: 0 | G31: 0 | H31: 4271.3 | I31: =G31+H31 -> 4271.3 | J31: =D31-I31 -> 252006.86 | K31: S/L | L31: 27.5
... A37: 18 | B37: 9-Northview Dr - 27.5 Year | C37: 7/30/24 | D37: 62002.79 | E37: 0 | F37: 0 | G37: 0 | H37: 1033.38 | I37: =G37+H37 -> 1033.38 | J37: =D37-I37 -> 60969.41 | K37: S/L | L37: 27.5
B38: Grand Total | D38: =SUM(D20:D37) -> 1280158.6 | E38: =SUM(E20:E37) -> 0 | F38: =SUM(F20:F37) -> 511511.06 | G38: =SUM(G20:G37) -> 0 | H38: =SUM(H20:H37) -> 536088.47 | I38: =SUM(I20:I37) -> 536088.47 | J38: =SUM(J20:J37) -> 744070.1
B40: Section 481(a) Adjustment — Regular Tax
B41: Depreciation reported previously | D41: =I16 -> 243079.61
B42: Cost Segregation Corrected Depreciation | D42: =I38 -> 536088.47
B43: Section 481(a) Adjustment — Regular Tax | D43: =D41-D42 -> -293008.86
A45: CALCULATION OF §481(a) ADJUSTMENT — AMT
A46: As Previously Filed — AMT
A47: Asset | B47: Property Description | C47: Date In Service | D47: Cost | E47: Sec 179 Exp | F47: Bonus Amt | G47: AMT Prior Depreciation | H47: AMT Current Depreciation | I47: End Depreciation | J47: Net Book Value | K47: Method | L47: Period
A48: 1 | B48: 2-Building-712 Northfield Dr | C48: 7/30/24 | D48: 166583.41 | E48: 0 | F48: 0 | G48: 0 | H48: 2776.44 | I48: =G48+H48 -> 2776.44 | J48: =D48-I48 -> 163806.97 | K48: S/L | L48: 27.5
A49: 2 | B49: 3-Northfield Dr | C49: 7/30/24 | D49: 21494.58 | E49: 0 | F49: 12896.75 | G49: 0 | H49: 13183.42 | I49: =G49+H49 -> 13183.42 | J49: =D49-I49 -> 8311.16 | K49: 150DB | L49: 15.0
A50: 3 | B50: 4-Northfield Dr | C50: 7/30/24 | D50: 40302.47 | E50: 0 | F50: 24181.48 | G50: 0 | H50: 27405.66 | I50: =G50+H50 -> 27405.66 | J50: =D50-I50 -> 12896.81 | K50: 200DB | L50: 5.0
A51: 4 | B51: 7-Building-2202 Northview Dr | C51: 7/30/24 | D51: 767179.32 | E51: 0 | F51: 0 | G51: 0 | H51: 12786.29 | I51: =G51+H51 -> 12786.29 | J51: =D51-I51 -> 754393.03 | K51: S/L | L51: 27.5
A52: 5 | B52: 8-Northiew Dr | C52: 7/30/24 | D52: 98990.86 | E52: 0 | F52: 59394.52 | G52: 0 | H52: 60714.39 | I52: =G52+H52 -> 60714.39 | J52: =D52-I52 -> 38276.47 | K52: 150DB | L52: 15.0
A53: 6 | B53: 9-Northview Dr | C53: 7/30/24 | D53: 185607.93 | E53: 0 | F53: 111364.76 | G53: 0 | H53: 126213.41 | I53: =G53+H53 -> 126213.41 | J53: =D53-I53 -> 59394.52 | K53: 200DB | L53: 5.0
B54: Grand Total | D54: =SUM(D48:D53) -> 1280158.6 | E54: =SUM(E48:E53) -> 0 | F54: =SUM(F48:F53) -> 207837.51 | G54: =SUM(G48:G53) -> 0 | H54: =SUM(H48:H53) -> 243079.61 | I54: =SUM(I48:I53) -> 243079.61 | J54: =SUM(J48:J53) -> 1037079
A56: After Cost Segregation Correction — AMT
A57: Asset | B57: Property Description | C57: Date In Service | D57: Cost | E57: Sec 179 Exp | F57: Bonus Amt | G57: AMT Prior Depreciation | H57: AMT Current Depreciation | I57: End Depreciation | J57: Net Book Value | K57: Method | L57: Period
A58: 1 | B58: 2-Building-712 Northfield Dr - 5 Year | C58: 7/30/24 | D58: 866.85 | E58: 0 | F58: 520.11 | G58: 0 | H58: 589.46 | I58: =G58+H58 -> 589.46 | J58: =D58-I58 -> 277.39 | K58: 200DB | L58: 5.0
A59: 2 | B59: 2-Building-712 Northfield Dr - 15 Year | C59: 7/30/24 | D59: 110068.96 | E59: 0 | F59: 66041.38 | G59: 0 | H59: 68242.76 | I59: =G59+H59 -> 68242.76 | J59: =D59-I59 -> 41826.2 | K59: 150DB | L59: 15.0
A60: 3 | B60: 2-Building-712 Northfield Dr - 27.5 Year | C60: 7/30/24 | D60: 55647.6 | E60: 0 | F60: 0 | G60: 0 | H60: 927.46 | I60: =G60+H60 -> 927.46 | J60: =D60-I60 -> 54720.14 | K60: S/L | L60: 27.5
A61: 4 | B61: 3-Northfield Dr - 5 Year | C61: 7/30/24 | D61: 111.85 | E61: 0 | F61: 67.11 | G61: 0 | H61: 76.06 | I61: =G61+H61 -> 76.06 | J61: =D61-I61 -> 35.79 | K61: 200DB | L61: 5.0
A62: 5 | B62: 3-Northfield Dr - 15 Year | C62: 7/30/24 | D62: 14202.41 | E62: 0 | F62: 8521.45 | G62: 0 | H62: 8805.5 | I62: =G62+H62 -> 8805.5 | J62: =D62-I62 -> 5396.91 | K62: 150DB | L62: 15.0
A63: 6 | B63: 3-Northfield Dr - 27.5 Year | C63: 7/30/24 | D63: 7180.32 | E63: 0 | F63: 0 | G63: 0 | H63: 119.67 | I63: =G63+H63 -> 119.67 | J63: =D63-I63 -> 7060.65 | K63: S/L | L63: 27.5
A64: 7 | B64: 4-Northfield Dr - 5 Year | C64: 7/30/24 | D64: 209.72 | E64: 0 | F64: 125.83 | G64: 0 | H64: 142.61 | I64: =G64+H64 -> 142.61 | J64: =D64-I64 -> 67.11 | K64: 200DB | L64: 5.0
A65: 8 | B65: 4-Northfield Dr - 15 Year | C65: 7/30/24 | D65: 26629.61 | E65: 0 | F65: 15977.77 | G65: 0 | H65: 16510.36 | I65: =G65+H65 -> 16510.36 | J65: =D65-I65 -> 10119.25 | K65: 150DB | L65: 15.0
A66: 9 | B66: 4-Northfield Dr - 27.5 Year | C66: 7/30/24 | D66: 13463.14 | E66: 0 | F66: 0 | G66: 0 | H66: 224.39 | I66: =G66+H66 -> 224.39 | J66: =D66-I66 -> 13238.75 | K66: S/L | L66: 27.5
A67: 10 | B67: 7-Building-2202 Northview Dr - 5 Year | C67: 7/30/24 | D67: 3992.15 | E67: 0 | F67: 2395.29 | G67: 0 | H67: 2714.66 | I67: =G67+H67 -> 2714.66 | J67: =D67-I67 -> 1277.49 | K67: 200DB | L67: 5.0
A68: 11 | B68: 7-Building-2202 Northview Dr - 15 Year | C68: 7/30/24 | D68: 506909.01 | E68: 0 | F68: 304145.41 | G68: 0 | H68: 314283.59 | I68: =G68+H68 -> 314283.59 | J68: =D68-I68 -> 192625.42 | K68: 150DB | L68: 15.0
A69: 12 | B69: 7-Building-2202 Northview Dr - 27.5 Year | C69: 7/30/24 | D69: 256278.16 | E69: 0 | F69: 0 | G69: 0 | H69: 4271.3 | I69: =G69+H69 -> 4271.3 | J69: =D69-I69 -> 252006.86 | K69: S/L | L69: 27.5
... A75: 18 | B75: 9-Northview Dr - 27.5 Year | C75: 7/30/24 | D75: 62002.79 | E75: 0 | F75: 0 | G75: 0 | H75: 1033.38 | I75: =G75+H75 -> 1033.38 | J75: =D75-I75 -> 60969.41 | K75: S/L | L75: 27.5
B76: Grand Total | D76: =SUM(D58:D75) -> 1280158.6 | E76: =SUM(E58:E75) -> 0 | F76: =SUM(F58:F75) -> 511511.06 | G76: =SUM(G58:G75) -> 0 | H76: =SUM(H58:H75) -> 536088.47 | I76: =SUM(I58:I75) -> 536088.47 | J76: =SUM(J58:J75) -> 744070.1
B78: Section 481(a) Adjustment — AMT
B79: Depreciation reported previously | D79: =I54 -> 243079.61
B80: Cost Segregation Corrected Depreciation | D80: =I76 -> 536088.47
B81: Section 481(a) Adjustment — AMT | D81: =D79-D80 -> -293008.86
A83: COST SEGREGATION STUDY — COST SUMMARY
B84: Total Building Cost | D84: =D116 -> 1280158.6
B85: Building Components: 5 Year | D85: =F116 -> 6661.53
B86: % of Cost | D86: =F117 -> 0.0052036757
B87: Site Improvements: 15 Year | D87: =H116 -> 845856.89
B88: % of Cost | D88: =H117 -> 0.66074384
B89: Building Structure: 27.5 Year | D89: =J116 -> 427640.15
B90: % of Cost | D90: =J117 -> 0.33405248
A92: COST SEGREGATION STUDY — COST DETAIL
B93: Property Category | D93: Cost | F93: 5 Year | H93: 15 Year | J93: 27.5 Year
B94: Building Components
B95: Access Control | D95: =SUM(F95:J95) -> 6661.53 | F95: 6661.53
B96: Site Work / Improvements
B97: Site Drainage | D97: =SUM(F97:J97) -> 76326.73 | H97: 76326.73
B98: Parking Lot | D98: =SUM(F98:J98) -> 192460.32 | H98: 192460.32
B99: Exterior Signage | D99: =SUM(F99:J99) -> 1455.53 | H99: 1455.53
B100: Parking Lot Striping / Barriers | D100: =SUM(F100:J100) -> 10024.14 | H100: 10024.14
B101: Sidewalks / Curbs | D101: =SUM(F101:J101) -> 222825.4 | H101: 222825.4
B102: Landscaping | D102: =SUM(F102:J102) -> 7131.4 | H102: 7131.4
B103: Security Lighting Poles | D103: =SUM(F103:J103) -> 3738.18 | H103: 3738.18
B104: Exterior Fencing | D104: =SUM(F104:J104) -> 230042.3 | H104: 230042.3
B105: Dumpster Enclosures | D105: =SUM(F105:J105) -> 30860.5 | H105: 30860.5
B106: Fabricated Steel - Exterior Bollards | D106: =SUM(F106:J106) -> 2802.66 | H106: 2802.66
B107: Fire Hydrants | D107: =SUM(F107:J107) -> 9369.69 | H107: 9369.69
B108: Exterior Equipment Concrete Pads | D108: =SUM(F108:J108) -> 1024.32 | H108: 1024.32
... B113: Free Standing Canopies | D113: =SUM(F113:J113) -> 1092.8 | H113: 1092.8
B114: Building Structure
B115: Site Utilities | D115: =SUM(F115:J115) -> 427640.15 | J115: 427640.15
B116: Total Building Cost | D116: =SUM(D94:D115) -> 1280158.6 | F116: =SUM(F94:F115) -> 6661.53 | H116: =SUM(H94:H115) -> 845856.89 | J116: =SUM(J94:J115) -> 427640.15
B117: % of Cost | F117: =F116/D116 -> 0.0052036757 | H117: =H116/D116 -> 0.66074384 | J117: =J116/D116 -> 0.33405248
A119: ASSET ALLOCATION (per After Cost Segregation schedule)
B120: Asset (as reclassified) | D120: Cost | F120: 5 Year | H120: 15 Year | J120: 27.5 Year
B121: =Site!B20 -> 2-Building-712 Northfield Dr - 5 Year | D121: =SUM(F121:J121) -> 866.85 | F121: =Site!D20 -> 866.85
B122: =Site!B21 -> 2-Building-712 Northfield Dr - 15 Year | D122: =SUM(F122:J122) -> 110068.96 | H122: =Site!D21 -> 110068.96
B123: =Site!B22 -> 2-Building-712 Northfield Dr - 27.5 Year | D123: =SUM(F123:J123) -> 55647.6 | J123: =Site!D22 -> 55647.6
...

Sheet Building 1
A1: River Garden Estates Housing LP
A2: River Garden Estates — 2201 Northview Dr & 712 Northfield Dr, Sacramento, CA 95833
A3: EIN: 93-2096487 · FYE: December 31, 2024 · Year of Change: 1/1/2024
A4: Building 1 — Attachment to Form 3115 (DCN #7, Rev. Proc. 2024-23 §6.01)
A5: Source: CSSI Report #107552-43, "#107552-43_River Garden Estates Housing LP_3115_Combined.pdf"
A7: CALCULATION OF §481(a) ADJUSTMENT — REGULAR TAX
A8: As Previously Filed
A9: Asset | B9: Property Description | C9: Date In Service | D9: Cost | E9: Sec 179 Exp | F9: Bonus Amt | G9: Tax Prior Depreciation | H9: Tax Current Depreciation | I9: End Depreciation | J9: Net Book Value | K9: Method | L9: Period
A10: 1 | B10: 2-Building-712 Northfield Dr | C10: 7/30/24 | D10: 45270.97 | E10: 0 | F10: 0 | G10: 0 | H10: 754.53 | I10: =G10+H10 -> 754.53 | J10: =D10-I10 -> 44516.44 | K10: S/L | L10: 27.5
A11: 2 | B11: 3-Northfield Dr | C11: 7/30/24 | D11: 5841.4 | E11: 0 | F11: 3504.84 | G11: 0 | H11: 3582.75 | I11: =G11+H11 -> 3582.75 | J11: =D11-I11 -> 2258.65 | K11: 150DB | L11: 15.0
A12: 3 | B12: 4-Northfield Dr | C12: 7/30/24 | D12: 10952.66 | E12: 0 | F12: 6571.6 | G12: 0 | H12: 7447.8 | I12: =G12+H12 -> 7447.8 | J12: =D12-I12 -> 3504.86 | K12: 200DB | L12: 5.0
A13: 4 | B13: 7-Building-2202 Northview Dr | C13: 7/30/24 | D13: 208489.87 | E13: 0 | F13: 0 | G13: 0 | H13: 3474.82 | I13: =G13+H13 -> 3474.82 | J13: =D13-I13 -> 205015.05 | K13: S/L | L13: 27.5
A14: 5 | B14: 8-Northiew Dr | C14: 7/30/24 | D14: 26901.91 | E14: 0 | F14: 16141.15 | G14: 0 | H14: 16499.84 | I14: =G14+H14 -> 16499.84 | J14: =D14-I14 -> 10402.07 | K14: 150DB | L14: 15.0
A15: 6 | B15: 9-Northview Dr | C15: 7/30/24 | D15: 50441.11 | E15: 0 | F15: 30264.67 | G15: 0 | H15: 34299.96 | I15: =G15+H15 -> 34299.96 | J15: =D15-I15 -> 16141.15 | K15: 200DB | L15: 5.0
B16: Grand Total | D16: =SUM(D10:D15) -> 347897.92 | E16: =SUM(E10:E15) -> 0 | F16: =SUM(F10:F15) -> 56482.26 | G16: =SUM(G10:G15) -> 0 | H16: =SUM(H10:H15) -> 66059.7 | I16: =SUM(I10:I15) -> 66059.7 | J16: =SUM(J10:J15) -> 281838.22
A18: After Cost Segregation Correction
A19: Asset | B19: Property Description | C19: Date In Service | D19: Cost | E19: Sec 179 Exp | F19: Bonus Amt | G19: Tax Prior Depreciation | H19: Tax Current Depreciation | I19: End Depreciation | J19: Net Book Value | K19: Method | L19: Period
A20: 1 | B20: 2-Building-712 Northfield Dr - 5 Year | C20: 7/30/24 | D20: 7916.21 | E20: 0 | F20: 4749.73 | G20: 0 | H20: 5383.03 | I20: =G20+H20 -> 5383.03 | J20: =D20-I20 -> 2533.18 | K20: 200DB | L20: 5.0
A21: 2 | B21: 2-Building-712 Northfield Dr - 27.5 Year | C21: 7/30/24 | D21: 37354.76 | E21: 0 | F21: 0 | G21: 0 | H21: 622.58 | I21: =G21+H21 -> 622.58 | J21: =D21-I21 -> 36732.18 | K21: S/L | L21: 27.5
A22: 3 | B22: 3-Northfield Dr - 5 Year | C22: 7/30/24 | D22: 1021.44 | E22: 0 | F22: 612.86 | G22: 0 | H22: 694.58 | I22: =G22+H22 -> 694.58 | J22: =D22-I22 -> 326.86 | K22: 200DB | L22: 5.0
A23: 4 | B23: 3-Northfield Dr - 27.5 Year | C23: 7/30/24 | D23: 4819.96 | E23: 0 | F23: 0 | G23: 0 | H23: 80.33 | I23: =G23+H23 -> 80.33 | J23: =D23-I23 -> 4739.63 | K23: S/L | L23: 27.5
A24: 5 | B24: 4-Northfield Dr - 5 Year | C24: 7/30/24 | D24: 1915.21 | E24: 0 | F24: 1149.13 | G24: 0 | H24: 1302.35 | I24: =G24+H24 -> 1302.35 | J24: =D24-I24 -> 612.86 | K24: 200DB | L24: 5.0
A25: 6 | B25: 4-Northfield Dr - 27.5 Year | C25: 7/30/24 | D25: 9037.45 | E25: 0 | F25: 0 | G25: 0 | H25: 150.62 | I25: =G25+H25 -> 150.62 | J25: =D25-I25 -> 8886.83 | K25: S/L | L25: 27.5
A26: 7 | B26: 7-Building-2202 Northview Dr - 5 Year | C26: 7/30/24 | D26: 36457.14 | E26: 0 | F26: 21874.28 | G26: 0 | H26: 24790.85 | I26: =G26+H26 -> 24790.85 | J26: =D26-I26 -> 11666.29 | K26: 200DB | L26: 5.0
A27: 8 | B27: 7-Building-2202 Northview Dr - 27.5 Year | C27: 7/30/24 | D27: 172032.73 | E27: 0 | F27: 0 | G27: 0 | H27: 2867.21 | I27: =G27+H27 -> 2867.21 | J27: =D27-I27 -> 169165.52 | K27: S/L | L27: 27.5
A28: 9 | B28: 8-Northiew Dr - 5 Year | C28: 7/30/24 | D28: 4704.15 | E28: 0 | F28: 2822.49 | G28: 0 | H28: 3198.82 | I28: =G28+H28 -> 3198.82 | J28: =D28-I28 -> 1505.33 | K28: 200DB | L28: 5.0
A29: 10 | B29: 8-Northiew Dr - 27.5 Year | C29: 7/30/24 | D29: 22197.76 | E29: 0 | F29: 0 | G29: 0 | H29: 369.96 | I29: =G29+H29 -> 369.96 | J29: =D29-I29 -> 21827.8 | K29: S/L | L29: 27.5
A30: 11 | B30: 9-Northview Dr - 5 Year | C30: 7/30/24 | D30: 8820.29 | E30: 0 | F30: 5292.17 | G30: 0 | H30: 5997.79 | I30: =G30+H30 -> 5997.79 | J30: =D30-I30 -> 2822.5 | K30: 200DB | L30: 5.0
A31: 12 | B31: 9-Northview Dr - 27.5 Year | C31: 7/30/24 | D31: 41620.82 | E31: 0 | F31: 0 | G31: 0 | H31: 693.68 | I31: =G31+H31 -> 693.68 | J31: =D31-I31 -> 40927.14 | K31: S/L | L31: 27.5
B32: Grand Total | D32: =SUM(D20:D31) -> 347897.92 | E32: =SUM(E20:E31) -> 0 | F32: =SUM(F20:F31) -> 36500.66 | G32: =SUM(G20:G31) -> 0 | H32: =SUM(H20:H31) -> 46151.8 | I32: =SUM(I20:I31) -> 46151.8 | J32: =SUM(J20:J31) -> 301746.12
B34: Section 481(a) Adjustment — Regular Tax
B35: Depreciation reported previously | D35: =I16 -> 66059.7
B36: Cost Segregation Corrected Depreciation | D36: =I32 -> 46151.8
B37: Section 481(a) Adjustment — Regular Tax | D37: =D35-D36 -> 19907.9
A39: CALCULATION OF §481(a) ADJUSTMENT — AMT
A40: As Previously Filed — AMT
A41: Asset | B41: Property Description | C41: Date In Service | D41: Cost | E41: Sec 179 Exp | F41: Bonus Amt | G41: AMT Prior Depreciation | H41: AMT Current Depreciation | I41: End Depreciation | J41: Net Book Value | K41: Method | L41: Period
A42: 1 | B42: 2-Building-712 Northfield Dr | C42: 7/30/24 | D42: 45270.97 | E42: 0 | F42: 0 | G42: 0 | H42: 754.53 | I42: =G42+H42 -> 754.53 | J42: =D42-I42 -> 44516.44 | K42: S/L | L42: 27.5
A43: 2 | B43: 3-Northfield Dr | C43: 7/30/24 | D43: 5841.4 | E43: 0 | F43: 3504.84 | G43: 0 | H43: 3582.75 | I43: =G43+H43 -> 3582.75 | J43: =D43-I43 -> 2258.65 | K43: 150DB | L43: 15.0
A44: 3 | B44: 4-Northfield Dr | C44: 7/30/24 | D44: 10952.66 | E44: 0 | F44: 6571.6 | G44: 0 | H44: 7447.8 | I44: =G44+H44 -> 7447.8 | J44: =D44-I44 -> 3504.86 | K44: 200DB | L44: 5.0
A45: 4 | B45: 7-Building-2202 Northview Dr | C45: 7/30/24 | D45: 208489.87 | E45: 0 | F45: 0 | G45: 0 | H45: 3474.82 | I45: =G45+H45 -> 3474.82 | J45: =D45-I45 -> 205015.05 | K45: S/L | L45: 27.5
A46: 5 | B46: 8-Northiew Dr | C46: 7/30/24 | D46: 26901.91 | E46: 0 | F46: 16141.15 | G46: 0 | H46: 16499.84 | I46: =G46+H46 -> 16499.84 | J46: =D46-I46 -> 10402.07 | K46: 150DB | L46: 15.0
A47: 6 | B47: 9-Northview Dr | C47: 7/30/24 | D47: 50441.11 | E47: 0 | F47: 30264.67 | G47: 0 | H47: 34299.96 | I47: =G47+H47 -> 34299.96 | J47: =D47-I47 -> 16141.15 | K47: 200DB | L47: 5.0
B48: Grand Total | D48: =SUM(D42:D47) -> 347897.92 | E48: =SUM(E42:E47) -> 0 | F48: =SUM(F42:F47) -> 56482.26 | G48: =SUM(G42:G47) -> 0 | H48: =SUM(H42:H47) -> 66059.7 | I48: =SUM(I42:I47) -> 66059.7 | J48: =SUM(J42:J47) -> 281838.22
A50: After Cost Segregation Correction — AMT
A51: Asset | B51: Property Description | C51: Date In Service | D51: Cost | E51: Sec 179 Exp | F51: Bonus Amt | G51: AMT Prior Depreciation | H51: AMT Current Depreciation | I51: End Depreciation | J51: Net Book Value | K51: Method | L51: Period
A52: 1 | B52: 2-Building-712 Northfield Dr - 5 Year | C52: 7/30/24 | D52: 7916.21 | E52: 0 | F52: 4749.73 | G52: 0 | H52: 5383.03 | I52: =G52+H52 -> 5383.03 | J52: =D52-I52 -> 2533.18 | K52: 200DB | L52: 5.0
A53: 2 | B53: 2-Building-712 Northfield Dr - 27.5 Year | C53: 7/30/24 | D53: 37354.76 | E53: 0 | F53: 0 | G53: 0 | H53: 622.58 | I53: =G53+H53 -> 622.58 | J53: =D53-I53 -> 36732.18 | K53: S/L | L53: 27.5
A54: 3 | B54: 3-Northfield Dr - 5 Year | C54: 7/30/24 | D54: 1021.44 | E54: 0 | F54: 612.86 | G54: 0 | H54: 694.58 | I54: =G54+H54 -> 694.58 | J54: =D54-I54 -> 326.86 | K54: 200DB | L54: 5.0
A55: 4 | B55: 3-Northfield Dr - 27.5 Year | C55: 7/30/24 | D55: 4819.96 | E55: 0 | F55: 0 | G55: 0 | H55: 80.33 | I55: =G55+H55 -> 80.33 | J55: =D55-I55 -> 4739.63 | K55: S/L | L55: 27.5
A56: 5 | B56: 4-Northfield Dr - 5 Year | C56: 7/30/24 | D56: 1915.21 | E56: 0 | F56: 1149.13 | G56: 0 | H56: 1302.35 | I56: =G56+H56 -> 1302.35 | J56: =D56-I56 -> 612.86 | K56: 200DB | L56: 5.0
A57: 6 | B57: 4-Northfield Dr - 27.5 Year | C57: 7/30/24 | D57: 9037.45 | E57: 0 | F57: 0 | G57: 0 | H57: 150.62 | I57: =G57+H57 -> 150.62 | J57: =D57-I57 -> 8886.83 | K57: S/L | L57: 27.5
A58: 7 | B58: 7-Building-2202 Northview Dr - 5 Year | C58: 7/30/24 | D58: 36457.14 | E58: 0 | F58: 21874.28 | G58: 0 | H58: 24790.85 | I58: =G58+H58 -> 24790.85 | J58: =D58-I58 -> 11666.29 | K58: 200DB | L58: 5.0
A59: 8 | B59: 7-Building-2202 Northview Dr - 27.5 Year | C59: 7/30/24 | D59: 172032.73 | E59: 0 | F59: 0 | G59: 0 | H59: 2867.21 | I59: =G59+H59 -> 2867.21 | J59: =D59-I59 -> 169165.52 | K59: S/L | L59: 27.5
A60: 9 | B60: 8-Northiew Dr - 5 Year | C60: 7/30/24 | D60: 4704.15 | E60: 0 | F60: 2822.49 | G60: 0 | H60: 3198.82 | I60: =G60+H60 -> 3198.82 | J60: =D60-I60 -> 1505.33 | K60: 200DB | L60: 5.0
A61: 10 | B61: 8-Northiew Dr - 27.5 Year | C61: 7/30/24 | D61: 22197.76 | E61: 0 | F61: 0 | G61: 0 | H61: 369.96 | I61: =G61+H61 -> 369.96 | J61: =D61-I61 -> 21827.8 | K61: S/L | L61: 27.5
A62: 11 | B62: 9-Northview Dr - 5 Year | C62: 7/30/24 | D62: 8820.29 | E62: 0 | F62: 5292.17 | G62: 0 | H62: 5997.79 | I62: =G62+H62 -> 5997.79 | J62: =D62-I62 -> 2822.5 | K62: 200DB | L62: 5.0
A63: 12 | B63: 9-Northview Dr - 27.5 Year | C63: 7/30/24 | D63: 41620.82 | E63: 0 | F63: 0 | G63: 0 | H63: 693.68 | I63: =G63+H63 -> 693.68 | J63: =D63-I63 -> 40927.14 | K63: S/L | L63: 27.5
B64: Grand Total | D64: =SUM(D52:D63) -> 347897.92 | E64: =SUM(E52:E63) -> 0 | F64: =SUM(F52:F63) -> 36500.66 | G64: =SUM(G52:G63) -> 0 | H64: =SUM(H52:H63) -> 46151.8 | I64: =SUM(I52:I63) -> 46151.8 | J64: =SUM(J52:J63) -> 301746.12
B66: Section 481(a) Adjustment — AMT
B67: Depreciation reported previously | D67: =I48 -> 66059.7
B68: Cost Segregation Corrected Depreciation | D68: =I64 -> 46151.8
B69: Section 481(a) Adjustment — AMT | D69: =D67-D68 -> 19907.9
A71: COST SEGREGATION STUDY — COST SUMMARY
B72: Total Building Cost | D72: =D113 -> 347897.92
B73: Building Components: 5 Year | D73: =F113 -> 60834.44
B74: % of Cost | D74: =F114 -> 0.1748629
B75: Building Structure: 27.5 Year | D75: =H113 -> 287063.48
B76: % of Cost | D76: =H114 -> 0.8251371
A78: COST SEGREGATION STUDY — COST DETAIL
B79: Property Category | D79: Cost | F79: 5 Year | H79: 27.5 Year
B80: Building Components
B81: Cabinets / Millwork | D81: =SUM(F81:H81) -> 12358.73 | F81: 12358.73
B82: Moldings | D82: =SUM(F82:H82) -> 5146.33 | F82: 5146.33
B83: Flooring - Vinyl Tile | D83: =SUM(F83:H83) -> 3208.38 | F83: 3208.38
B84: Flooring - Wood Laminate | D84: =SUM(F84:H84) -> 15651.6 | F84: 15651.6
B85: Security System | D85: =SUM(F85:H85) -> 355.5 | F85: 355.5
B86: Window Treatments | D86: =SUM(F86:H86) -> 4419.8 | F86: 4419.8
B87: Building Signage | D87: =SUM(F87:H87) -> 171.07 | F87: 171.07
B88: Specialty Electrical - Appliances | D88: =SUM(F88:H88) -> 2691.07 | F88: 2691.07
B89: Communication / Data | D89: =SUM(F89:H89) -> 4781.49 | F89: 4781.49
B90: Specialty Plumbing - Kitchen Sinks | D90: =SUM(F90:H90) -> 4922.4 | F90: 4922.4
B91: Security / Exterior Lighting | D91: =SUM(F91:H91) -> 1746.74 | F91: 1746.74
B92: Access Control | D92: =SUM(F92:H92) -> 66.45 | F92: 66.45
... B95: Appliances | D95: =SUM(F95:H95) -> 3538.89 | F95: 3538.89
B96: Building Structure
B97: Roofing Systems | D97: =SUM(F97:H97) -> 16847.82 | H97: 16847.82
B98: Foundations | D98: =SUM(F98:H98) -> 20376.05 | H98: 20376.05
B99: HVAC | D99: =SUM(F99:H99) -> 30335.08 | H99: 30335.08
B100: Electrical | D100: =SUM(F100:H100) -> 32785.09 | H100: 32785.09
B101: Plumbing | D101: =SUM(F101:H101) -> 26370.11 | H101: 26370.11
B102: Fire Protection & Alarm | D102: =SUM(F102:H102) -> 1900.26 | H102: 1900.26
B103: Exterior Façade / Building Skin | D103: =SUM(F103:H103) -> 11317.23 | H103: 11317.23
B104: Doors & Frames | D104: =SUM(F104:H104) -> 16611.21 | H104: 16611.21
B105: Windows | D105: =SUM(F105:H105) -> 9575.83 | H105: 9575.83
B106: Ceiling Systems | D106: =SUM(F106:H106) -> 13952.82 | H106: 13952.82
B107: Interior Framing / Partitions | D107: =SUM(F107:H107) -> 31819.16 | H107: 31819.16
B108: Painting | D108: =SUM(F108:H108) -> 14251.16 | H108: 14251.16
... B112: Bathroom Accessories | D112: =SUM(F112:H112) -> 3946.85 | H112: 3946.85
B113: Total Building Cost | D113: =SUM(D80:D112) -> 347897.92 | F113: =SUM(F80:F112) -> 60834.44 | H113: =SUM(H80:H112) -> 287063.48
...

Sheet Building 2
A1: River Garden Estates Housing LP
A2: River Garden Estates — 2201 Northview Dr & 712 Northfield Dr, Sacramento, CA 95833
A3: EIN: 93-2096487 · FYE: December 31, 2024 · Year of Change: 1/1/2024
A4: Building 2 — Attachment to Form 3115 (DCN #7, Rev. Proc. 2024-23 §6.01)
A5: Source: CSSI Report #107552-43, "#107552-43_River Garden Estates Housing LP_3115_Combined.pdf"
A7: CALCULATION OF §481(a) ADJUSTMENT — REGULAR TAX
A8: As Previously Filed
A9: Asset | B9: Property Description | C9: Date In Service | D9: Cost | E9: Sec 179 Exp | F9: Bonus Amt | G9: Tax Prior Depreciation | H9: Tax Current Depreciation | I9: End Depreciation | J9: Net Book Value | K9: Method | L9: Period
A10: 1 | B10: 2-Building-712 Northfield Dr | C10: 7/30/24 | D10: 34585.09 | E10: 0 | F10: 0 | G10: 0 | H10: 576.43 | I10: =G10+H10 -> 576.43 | J10: =D10-I10 -> 34008.66 | K10: S/L | L10: 27.5
A11: 2 | B11: 3-Northfield Dr | C11: 7/30/24 | D11: 4462.58 | E11: 0 | F11: 2677.55 | G11: 0 | H11: 2737.06 | I11: =G11+H11 -> 2737.06 | J11: =D11-I11 -> 1725.52 | K11: 150DB | L11: 15.0
A12: 3 | B12: 4-Northfield Dr | C12: 7/30/24 | D12: 8367.37 | E12: 0 | F12: 5020.42 | G12: 0 | H12: 5689.81 | I12: =G12+H12 -> 5689.81 | J12: =D12-I12 -> 2677.56 | K12: 200DB | L12: 5.0
A13: 4 | B13: 7-Building-2202 Northview Dr | C13: 7/30/24 | D13: 159277.36 | E13: 0 | F13: 0 | G13: 0 | H13: 2654.62 | I13: =G13+H13 -> 2654.62 | J13: =D13-I13 -> 156622.74 | K13: S/L | L13: 27.5
A14: 5 | B14: 8-Northiew Dr | C14: 7/30/24 | D14: 20551.91 | E14: 0 | F14: 12331.15 | G14: 0 | H14: 12605.17 | I14: =G14+H14 -> 12605.17 | J14: =D14-I14 -> 7946.74 | K14: 150DB | L14: 15.0
A15: 6 | B15: 9-Northview Dr | C15: 7/30/24 | D15: 38534.85 | E15: 0 | F15: 23120.91 | G15: 0 | H15: 26203.7 | I15: =G15+H15 -> 26203.7 | J15: =D15-I15 -> 12331.15 | K15: 200DB | L15: 5.0
B16: Grand Total | D16: =SUM(D10:D15) -> 265779.16 | E16: =SUM(E10:E15) -> 0 | F16: =SUM(F10:F15) -> 43150.03 | G16: =SUM(G10:G15) -> 0 | H16: =SUM(H10:H15) -> 50466.79 | I16: =SUM(I10:I15) -> 50466.79 | J16: =SUM(J10:J15) -> 215312.37
A18: After Cost Segregation Correction
A19: Asset | B19: Property Description | C19: Date In Service | D19: Cost | E19: Sec 179 Exp | F19: Bonus Amt | G19: Tax Prior Depreciation | H19: Tax Current Depreciation | I19: End Depreciation | J19: Net Book Value | K19: Method | L19: Period
A20: 1 | B20: 2-Building-712 Northfield Dr - 5 Year | C20: 7/30/24 | D20: 6299.49 | E20: 0 | F20: 3779.69 | G20: 0 | H20: 4283.65 | I20: =G20+H20 -> 4283.65 | J20: =D20-I20 -> 2015.84 | K20: 200DB | L20: 5.0
A21: 2 | B21: 2-Building-712 Northfield Dr - 27.5 Year | C21: 7/30/24 | D21: 28285.6 | E21: 0 | F21: 0 | G21: 0 | H21: 471.43 | I21: =G21+H21 -> 471.43 | J21: =D21-I21 -> 27814.17 | K21: S/L | L21: 27.5
A22: 3 | B22: 3-Northfield Dr - 5 Year | C22: 7/30/24 | D22: 812.84 | E22: 0 | F22: 487.7 | G22: 0 | H22: 552.73 | I22: =G22+H22 -> 552.73 | J22: =D22-I22 -> 260.11 | K22: 200DB | L22: 5.0
A23: 4 | B23: 3-Northfield Dr - 27.5 Year | C23: 7/30/24 | D23: 3649.74 | E23: 0 | F23: 0 | G23: 0 | H23: 60.83 | I23: =G23+H23 -> 60.83 | J23: =D23-I23 -> 3588.91 | K23: S/L | L23: 27.5
A24: 5 | B24: 4-Northfield Dr - 5 Year | C24: 7/30/24 | D24: 1524.07 | E24: 0 | F24: 914.44 | G24: 0 | H24: 1036.37 | I24: =G24+H24 -> 1036.37 | J24: =D24-I24 -> 487.7 | K24: 200DB | L24: 5.0
A25: 6 | B25: 4-Northfield Dr - 27.5 Year | C25: 7/30/24 | D25: 6843.3 | E25: 0 | F25: 0 | G25: 0 | H25: 114.06 | I25: =G25+H25 -> 114.06 | J25: =D25-I25 -> 6729.24 | K25: S/L | L25: 27.5
A26: 7 | B26: 7-Building-2202 Northview Dr - 5 Year | C26: 7/30/24 | D26: 29011.54 | E26: 0 | F26: 17406.92 | G26: 0 | H26: 19727.84 | I26: =G26+H26 -> 19727.84 | J26: =D26-I26 -> 9283.7 | K26: 200DB | L26: 5.0
A27: 8 | B27: 7-Building-2202 Northview Dr - 27.5 Year | C27: 7/30/24 | D27: 130265.82 | E27: 0 | F27: 0 | G27: 0 | H27: 2171.1 | I27: =G27+H27 -> 2171.1 | J27: =D27-I27 -> 128094.72 | K27: S/L | L27: 27.5
A28: 9 | B28: 8-Northiew Dr - 5 Year | C28: 7/30/24 | D28: 3743.42 | E28: 0 | F28: 2246.05 | G28: 0 | H28: 2545.52 | I28: =G28+H28 -> 2545.52 | J28: =D28-I28 -> 1197.9 | K28: 200DB | L28: 5.0
A29: 10 | B29: 8-Northiew Dr - 27.5 Year | C29: 7/30/24 | D29: 16808.49 | E29: 0 | F29: 0 | G29: 0 | H29: 280.14 | I29: =G29+H29 -> 280.14 | J29: =D29-I29 -> 16528.35 | K29: S/L | L29: 27.5
A30: 11 | B30: 9-Northview Dr - 5 Year | C30: 7/30/24 | D30: 7018.93 | E30: 0 | F30: 4211.36 | G30: 0 | H30: 4772.87 | I30: =G30+H30 -> 4772.87 | J30: =D30-I30 -> 2246.06 | K30: 200DB | L30: 5.0
A31: 12 | B31: 9-Northview Dr - 27.5 Year | C31: 7/30/24 | D31: 31515.92 | E31: 0 | F31: 0 | G31: 0 | H31: 525.27 | I31: =G31+H31 -> 525.27 | J31: =D31-I31 -> 30990.65 | K31: S/L | L31: 27.5
B32: Grand Total | D32: =SUM(D20:D31) -> 265779.16 | E32: =SUM(E20:E31) -> 0 | F32: =SUM(F20:F31) -> 29046.16 | G32: =SUM(G20:G31) -> 0 | H32: =SUM(H20:H31) -> 36541.81 | I32: =SUM(I20:I31) -> 36541.81 | J32: =SUM(J20:J31) -> 229237.35
B34: Section 481(a) Adjustment — Regular Tax
B35: Depreciation reported previously | D35: =I16 -> 50466.79
B36: Cost Segregation Corrected Depreciation | D36: =I32 -> 36541.81
B37: Section 481(a) Adjustment — Regular Tax | D37: =D35-D36 -> 13924.98
A39: CALCULATION OF §481(a) ADJUSTMENT — AMT
A40: As Previously Filed — AMT
A41: Asset | B41: Property Description | C41: Date In Service | D41: Cost | E41: Sec 179 Exp | F41: Bonus Amt | G41: AMT Prior Depreciation | H41: AMT Current Depreciation | I41: End Depreciation | J41: Net Book Value | K41: Method | L41: Period
A42: 1 | B42: 2-Building-712 Northfield Dr | C42: 7/30/24 | D42: 34585.09 | E42: 0 | F42: 0 | G42: 0 | H42: 576.43 | I42: =G42+H42 -> 576.43 | J42: =D42-I42 -> 34008.66 | K42: S/L | L42: 27.5
A43: 2 | B43: 3-Northfield Dr | C43: 7/30/24 | D43: 4462.58 | E43: 0 | F43: 2677.55 | G43: 0 | H43: 2737.06 | I43: =G43+H43 -> 2737.06 | J43: =D43-I43 -> 1725.52 | K43: 150DB | L43: 15.0
A44: 3 | B44: 4-Northfield Dr | C44: 7/30/24 | D44: 8367.37 | E44: 0 | F44: 5020.42 | G44: 0 | H44: 5689.81 | I44: =G44+H44 -> 5689.81 | J44: =D44-I44 -> 2677.56 | K44: 200DB | L44: 5.0
A45: 4 | B45: 7-Building-2202 Northview Dr | C45: 7/30/24 | D45: 159277.36 | E45: 0 | F45: 0 | G45: 0 | H45: 2654.62 | I45: =G45+H45 -> 2654.62 | J45: =D45-I45 -> 156622.74 | K45: S/L | L45: 27.5
A46: 5 | B46: 8-Northiew Dr | C46: 7/30/24 | D46: 20551.91 | E46: 0 | F46: 12331.15 | G46: 0 | H46: 12605.17 | I46: =G46+H46 -> 12605.17 | J46: =D46-I46 -> 7946.74 | K46: 150DB | L46: 15.0
A47: 6 | B47: 9-Northview Dr | C47: 7/30/24 | D47: 38534.85 | E47: 0 | F47: 23120.91 | G47: 0 | H47: 26203.7 | I47: =G47+H47 -> 26203.7 | J47: =D47-I47 -> 12331.15 | K47: 200DB | L47: 5.0
B48: Grand Total | D48: =SUM(D42:D47) -> 265779.16 | E48: =SUM(E42:E47) -> 0 | F48: =SUM(F42:F47) -> 43150.03 | G48: =SUM(G42:G47) -> 0 | H48: =SUM(H42:H47) -> 50466.79 | I48: =SUM(I42:I47) -> 50466.79 | J48: =SUM(J42:J47) -> 215312.37
A50: After Cost Segregation Correction — AMT
A51: Asset | B51: Property Description | C51: Date In Service | D51: Cost | E51: Sec 179 Exp | F51: Bonus Amt | G51: AMT Prior Depreciation | H51: AMT Current Depreciation | I51: End Depreciation | J51: Net Book Value | K51: Method | L51: Period
A52: 1 | B52: 2-Building-712 Northfield Dr - 5 Year | C52: 7/30/24 | D52: 6299.49 | E52: 0 | F52: 3779.69 | G52: 0 | H52: 4283.65 | I52: =G52+H52 -> 4283.65 | J52: =D52-I52 -> 2015.84 | K52: 200DB | L52: 5.0
A53: 2 | B53: 2-Building-712 Northfield Dr - 27.5 Year | C53: 7/30/24 | D53: 28285.6 | E53: 0 | F53: 0 | G53: 0 | H53: 471.43 | I53: =G53+H53 -> 471.43 | J53: =D53-I53 -> 27814.17 | K53: S/L | L53: 27.5
A54: 3 | B54: 3-Northfield Dr - 5 Year | C54: 7/30/24 | D54: 812.84 | E54: 0 | F54: 487.7 | G54: 0 | H54: 552.73 | I54: =G54+H54 -> 552.73 | J54: =D54-I54 -> 260.11 | K54: 200DB | L54: 5.0
A55: 4 | B55: 3-Northfield Dr - 27.5 Year | C55: 7/30/24 | D55: 3649.74 | E55: 0 | F55: 0 | G55: 0 | H55: 60.83 | I55: =G55+H55 -> 60.83 | J55: =D55-I55 -> 3588.91 | K55: S/L | L55: 27.5
A56: 5 | B56: 4-Northfield Dr - 5 Year | C56: 7/30/24 | D56: 1524.07 | E56: 0 | F56: 914.44 | G56: 0 | H56: 1036.37 | I56: =G56+H56 -> 1036.37 | J56: =D56-I56 -> 487.7 | K56: 200DB | L56: 5.0
A57: 6 | B57: 4-Northfield Dr - 27.5 Year | C57: 7/30/24 | D57: 6843.3 | E57: 0 | F57: 0 | G57: 0 | H57: 114.06 | I57: =G57+H57 -> 114.06 | J57: =D57-I57 -> 6729.24 | K57: S/L | L57: 27.5
A58: 7 | B58: 7-Building-2202 Northview Dr - 5 Year | C58: 7/30/24 | D58: 29011.54 | E58: 0 | F58: 17406.92 | G58: 0 | H58: 19727.84 | I58: =G58+H58 -> 19727.84 | J58: =D58-I58 -> 9283.7 | K58: 200DB | L58: 5.0
A59: 8 | B59: 7-Building-2202 Northview Dr - 27.5 Year | C59: 7/30/24 | D59: 130265.82 | E59: 0 | F59: 0 | G59: 0 | H59: 2171.1 | I59: =G59+H59 -> 2171.1 | J59: =D59-I59 -> 128094.72 | K59: S/L | L59: 27.5
A60: 9 | B60: 8-Northiew Dr - 5 Year | C60: 7/30/24 | D60: 3743.42 | E60: 0 | F60: 2246.05 | G60: 0 | H60: 2545.52 | I60: =G60+H60 -> 2545.52 | J60: =D60-I60 -> 1197.9 | K60: 200DB | L60: 5.0
A61: 10 | B61: 8-Northiew Dr - 27.5 Year | C61: 7/30/24 | D61: 16808.49 | E61: 0 | F61: 0 | G61: 0 | H61: 280.14 | I61: =G61+H61 -> 280.14 | J61: =D61-I61 -> 16528.35 | K61: S/L | L61: 27.5
A62: 11 | B62: 9-Northview Dr - 5 Year | C62: 7/30/24 | D62: 7018.93 | E62: 0 | F62: 4211.36 | G62: 0 | H62: 4772.87 | I62: =G62+H62 -> 4772.87 | J62: =D62-I62 -> 2246.06 | K62: 200DB | L62: 5.0
A63: 12 | B63: 9-Northview Dr - 27.5 Year | C63: 7/30/24 | D63: 31515.92 | E63: 0 | F63: 0 | G63: 0 | H63: 525.27 | I63: =G63+H63 -> 525.27 | J63: =D63-I63 -> 30990.65 | K63: S/L | L63: 27.5
B64: Grand Total | D64: =SUM(D52:D63) -> 265779.16 | E64: =SUM(E52:E63) -> 0 | F64: =SUM(F52:F63) -> 29046.16 | G64: =SUM(G52:G63) -> 0 | H64: =SUM(H52:H63) -> 36541.81 | I64: =SUM(I52:I63) -> 36541.81 | J64: =SUM(J52:J63) -> 229237.35
B66: Section 481(a) Adjustment — AMT
B67: Depreciation reported previously | D67: =I48 -> 50466.79
B68: Cost Segregation Corrected Depreciation | D68: =I64 -> 36541.81
B69: Section 481(a) Adjustment — AMT | D69: =D67-D68 -> 13924.98
A71: COST SEGREGATION STUDY — COST SUMMARY
B72: Total Building Cost | D72: =D110 -> 265779.16
B73: Building Components: 5 Year | D73: =F110 -> 48410.29
B74: % of Cost | D74: =F111 -> 0.18214479
B75: Building Structure: 27.5 Year | D75: =H110 -> 217368.87
B76: % of Cost | D76: =H111 -> 0.81785521
A78: COST SEGREGATION STUDY — COST DETAIL
B79: Property Category | D79: Cost | F79: 5 Year | H79: 27.5 Year
B80: Building Components
B81: Cabinets / Millwork | D81: =SUM(F81:H81) -> 10896.11 | F81: 10896.11
B82: Moldings | D82: =SUM(F82:H82) -> 4110.75 | F82: 4110.75
B83: Flooring - Wood Laminate | D83: =SUM(F83:H83) -> 15651.6 | F83: 15651.6
B84: Window Treatments | D84: =SUM(F84:H84) -> 3613.14 | F84: 3613.14
B85: Building Signage | D85: =SUM(F85:H85) -> 105.28 | F85: 105.28
B86: Specialty Electrical - Appliances | D86: =SUM(F86:H86) -> 2242.57 | F86: 2242.57
B87: Communication / Data | D87: =SUM(F87:H87) -> 1932.23 | F87: 1932.23
B88: Specialty Plumbing - Kitchen Sinks | D88: =SUM(F88:H88) -> 4101.99 | F88: 4101.99
B89: Security / Exterior Lighting | D89: =SUM(F89:H89) -> 1746.74 | F89: 1746.74
B90: Access Control | D90: =SUM(F90:H90) -> 66.45 | F90: 66.45
B91: Entry Canopies | D91: =SUM(F91:H91) -> 404.54 | F91: 404.54
B92: Appliances | D92: =SUM(F92:H92) -> 3538.89 | F92: 3538.89
B93: Building Structure
B94: Roofing Systems | D94: =SUM(F94:H94) -> 12887.37 | H94: 12887.37
B95: Foundations | D95: =SUM(F95:H95) -> 14646.87 | H95: 14646.87
B96: HVAC | D96: =SUM(F96:H96) -> 21749.99 | H96: 21749.99
B97: Electrical | D97: =SUM(F97:H97) -> 23506.63 | H97: 23506.63
B98: Plumbing | D98: =SUM(F98:H98) -> 18907.15 | H98: 18907.15
B99: Fire Protection & Alarm | D99: =SUM(F99:H99) -> 1701.46 | H99: 1701.46
B100: Exterior Façade / Building Skin | D100: =SUM(F100:H100) -> 9148.73 | H100: 9148.73
B101: Doors & Frames | D101: =SUM(F101:H101) -> 14572.68 | H101: 14572.68
B102: Windows | D102: =SUM(F102:H102) -> 7194.27 | H102: 7194.27
B103: Ceiling Systems | D103: =SUM(F103:H103) -> 10004.05 | H103: 10004.05
B104: Interior Framing / Partitions | D104: =SUM(F104:H104) -> 25350.08 | H104: 25350.08
B105: Painting | D105: =SUM(F105:H105) -> 11072.6 | H105: 11072.6
... B109: Bathroom Accessories | D109: =SUM(F109:H109) -> 3697.16 | H109: 3697.16
B110: Total Building Cost | D110: =SUM(D80:D109) -> 265779.16 | F110: =SUM(F80:F109) -> 48410.29 | H110: =SUM(H80:H109) -> 217368.87
B111: % of Cost | F111: =F110/D110 -> 0.18214479 | H111: =H110/D110 -> 0.81785521
...

Sheet Building 3
A1: River Garden Estates Housing LP
A2: River Garden Estates — 2201 Northview Dr & 712 Northfield Dr, Sacramento, CA 95833
A3: EIN: 93-2096487 · FYE: December 31, 2024 · Year of Change: 1/1/2024
A4: Building 3 — Attachment to Form 3115 (DCN #7, Rev. Proc. 2024-23 §6.01)
A5: Source: CSSI Report #107552-43, "#107552-43_River Garden Estates Housing LP_3115_Combined.pdf"
A7: CALCULATION OF §481(a) ADJUSTMENT — REGULAR TAX
A8: As Previously Filed
A9: Asset | B9: Property Description | C9: Date In Service | D9: Cost | E9: Sec 179 Exp | F9: Bonus Amt | G9: Tax Prior Depreciation | H9: Tax Current Depreciation | I9: End Depreciation | J9: Net Book Value | K9: Method | L9: Period
A10: 1 | B10: 2-Building-712 Northfield Dr | C10: 7/30/24 | D10: 27290.76 | E10: 0 | F10: 0 | G10: 0 | H10: 454.85 | I10: =G10+H10 -> 454.85 | J10: =D10-I10 -> 26835.91 | K10: S/L | L10: 27.5
A11: 2 | B11: 3-Northfield Dr | C11: 7/30/24 | D11: 3521.38 | E11: 0 | F11: 2112.83 | G11: 0 | H11: 2159.79 | I11: =G11+H11 -> 2159.79 | J11: =D11-I11 -> 1361.59 | K11: 150DB | L11: 15.0
A12: 3 | B12: 4-Northfield Dr | C12: 7/30/24 | D12: 6602.61 | E12: 0 | F12: 3961.57 | G12: 0 | H12: 4489.77 | I12: =G12+H12 -> 4489.77 | J12: =D12-I12 -> 2112.84 | K12: 200DB | L12: 5.0
A13: 4 | B13: 7-Building-2202 Northview Dr | C13: 7/30/24 | D13: 125684.23 | E13: 0 | F13: 0 | G13: 0 | H13: 2094.73 | I13: =G13+H13 -> 2094.73 | J13: =D13-I13 -> 123589.5 | K13: S/L | L13: 27.5
A14: 5 | B14: 8-Northiew Dr | C14: 7/30/24 | D14: 16217.32 | E14: 0 | F14: 9730.39 | G14: 0 | H14: 9946.62 | I14: =G14+H14 -> 9946.62 | J14: =D14-I14 -> 6270.7 | K14: 150DB | L14: 15.0
A15: 6 | B15: 9-Northview Dr | C15: 7/30/24 | D15: 30407.48 | E15: 0 | F15: 18244.49 | G15: 0 | H15: 20677.09 | I15: =G15+H15 -> 20677.09 | J15: =D15-I15 -> 9730.39 | K15: 200DB | L15: 5.0
B16: Grand Total | D16: =SUM(D10:D15) -> 209723.78 | E16: =SUM(E10:E15) -> 0 | F16: =SUM(F10:F15) -> 34049.28 | G16: =SUM(G10:G15) -> 0 | H16: =SUM(H10:H15) -> 39822.85 | I16: =SUM(I10:I15) -> 39822.85 | J16: =SUM(J10:J15) -> 169900.93
A18: After Cost Segregation Correction
A19: Asset | B19: Property Description | C19: Date In Service | D19: Cost | E19: Sec 179 Exp | F19: Bonus Amt | G19: Tax Prior Depreciation | H19: Tax Current Depreciation | I19: End Depreciation | J19: Net Book Value | K19: Method | L19: Period
A20: 1 | B20: 2-Building-712 Northfield Dr - 5 Year | C20: 7/30/24 | D20: 5001.64 | E20: 0 | F20: 3000.98 | G20: 0 | H20: 3401.11 | I20: =G20+H20 -> 3401.11 | J20: =D20-I20 -> 1600.53 | K20: 200DB | L20: 5.0
A21: 2 | B21: 2-Building-712 Northfield Dr - 27.5 Year | C21: 7/30/24 | D21: 22289.12 | E21: 0 | F21: 0 | G21: 0 | H21: 371.49 | I21: =G21+H21 -> 371.49 | J21: =D21-I21 -> 21917.63 | K21: S/L | L21: 27.5
A22: 3 | B22: 3-Northfield Dr - 5 Year | C22: 7/30/24 | D22: 645.37 | E22: 0 | F22: 387.22 | G22: 0 | H22: 438.85 | I22: =G22+H22 -> 438.85 | J22: =D22-I22 -> 206.52 | K22: 200DB | L22: 5.0
A23: 4 | B23: 3-Northfield Dr - 27.5 Year | C23: 7/30/24 | D23: 2876.01 | E23: 0 | F23: 0 | G23: 0 | H23: 47.93 | I23: =G23+H23 -> 47.93 | J23: =D23-I23 -> 2828.08 | K23: S/L | L23: 27.5
A24: 5 | B24: 4-Northfield Dr - 5 Year | C24: 7/30/24 | D24: 1210.08 | E24: 0 | F24: 726.05 | G24: 0 | H24: 822.86 | I24: =G24+H24 -> 822.86 | J24: =D24-I24 -> 387.22 | K24: 200DB | L24: 5.0
A25: 6 | B25: 4-Northfield Dr - 27.5 Year | C25: 7/30/24 | D25: 5392.53 | E25: 0 | F25: 0 | G25: 0 | H25: 89.88 | I25: =G25+H25 -> 89.88 | J25: =D25-I25 -> 5302.65 | K25: S/L | L25: 27.5
A26: 7 | B26: 7-Building-2202 Northview Dr - 5 Year | C26: 7/30/24 | D26: 23034.43 | E26: 0 | F26: 13820.66 | G26: 0 | H26: 15663.41 | I26: =G26+H26 -> 15663.41 | J26: =D26-I26 -> 7371.02 | K26: 200DB | L26: 5.0
A27: 8 | B27: 7-Building-2202 Northview Dr - 27.5 Year | C27: 7/30/24 | D27: 102649.8 | E27: 0 | F27: 0 | G27: 0 | H27: 1710.83 | I27: =G27+H27 -> 1710.83 | J27: =D27-I27 -> 100938.97 | K27: S/L | L27: 27.5
A28: 9 | B28: 8-Northiew Dr - 5 Year | C28: 7/30/24 | D28: 2972.18 | E28: 0 | F28: 1783.31 | G28: 0 | H28: 2021.08 | I28: =G28+H28 -> 2021.08 | J28: =D28-I28 -> 951.1 | K28: 200DB | L28: 5.0
A29: 10 | B29: 8-Northiew Dr - 27.5 Year | C29: 7/30/24 | D29: 13245.14 | E29: 0 | F29: 0 | G29: 0 | H29: 220.75 | I29: =G29+H29 -> 220.75 | J29: =D29-I29 -> 13024.39 | K29: S/L | L29: 27.5
A30: 11 | B30: 9-Northview Dr - 5 Year | C30: 7/30/24 | D30: 5572.85 | E30: 0 | F30: 3343.71 | G30: 0 | H30: 3789.54 | I30: =G30+H30 -> 3789.54 | J30: =D30-I30 -> 1783.31 | K30: 200DB | L30: 5.0
A31: 12 | B31: 9-Northview Dr - 27.5 Year | C31: 7/30/24 | D31: 24834.63 | E31: 0 | F31: 0 | G31: 0 | H31: 413.91 | I31: =G31+H31 -> 413.91 | J31: =D31-I31 -> 24420.72 | K31: S/L | L31: 27.5
B32: Grand Total | D32: =SUM(D20:D31) -> 209723.78 | E32: =SUM(E20:E31) -> 0 | F32: =SUM(F20:F31) -> 23061.93 | G32: =SUM(G20:G31) -> 0 | H32: =SUM(H20:H31) -> 28991.64 | I32: =SUM(I20:I31) -> 28991.64 | J32: =SUM(J20:J31) -> 180732.14
B34: Section 481(a) Adjustment — Regular Tax
B35: Depreciation reported previously | D35: =I16 -> 39822.85
B36: Cost Segregation Corrected Depreciation | D36: =I32 -> 28991.64
B37: Section 481(a) Adjustment — Regular Tax | D37: =D35-D36 -> 10831.21
A39: CALCULATION OF §481(a) ADJUSTMENT — AMT
A40: As Previously Filed — AMT
A41: Asset | B41: Property Description | C41: Date In Service | D41: Cost | E41: Sec 179 Exp | F41: Bonus Amt | G41: AMT Prior Depreciation | H41: AMT Current Depreciation | I41: End Depreciation | J41: Net Book Value | K41: Method | L41: Period
A42: 1 | B42: 2-Building-712 Northfield Dr | C42: 7/30/24 | D42: 27290.76 | E42: 0 | F42: 0 | G42: 0 | H42: 454.85 | I42: =G42+H42 -> 454.85 | J42: =D42-I42 -> 26835.91 | K42: S/L | L42: 27.5
A43: 2 | B43: 3-Northfield Dr | C43: 7/30/24 | D43: 3521.38 | E43: 0 | F43: 2112.83 | G43: 0 | H43: 2159.79 | I43: =G43+H43 -> 2159.79 | J43: =D43-I43 -> 1361.59 | K43: 150DB | L43: 15.0
A44: 3 | B44: 4-Northfield Dr | C44: 7/30/24 | D44: 6602.61 | E44: 0 | F44: 3961.57 | G44: 0 | H44: 4489.77 | I44: =G44+H44 -> 4489.77 | J44: =D44-I44 -> 2112.84 | K44: 200DB | L44: 5.0
A45: 4 | B45: 7-Building-2202 Northview Dr | C45: 7/30/24 | D45: 125684.23 | E45: 0 | F45: 0 | G45: 0 | H45: 2094.73 | I45: =G45+H45 -> 2094.73 | J45: =D45-I45 -> 123589.5 | K45: S/L | L45: 27.5
A46: 5 | B46: 8-Northiew Dr | C46: 7/30/24 | D46: 16217.32 | E46: 0 | F46: 9730.39 | G46: 0 | H46: 9946.62 | I46: =G46+H46 -> 9946.62 | J46: =D46-I46 -> 6270.7 | K46: 150DB | L46: 15.0
A47: 6 | B47: 9-Northview Dr | C47: 7/30/24 | D47: 30407.48 | E47: 0 | F47: 18244.49 | G47: 0 | H47: 20677.09 | I47: =G47+H47 -> 20677.09 | J47: =D47-I47 -> 9730.39 | K47: 200DB | L47: 5.0
B48: Grand Total | D48: =SUM(D42:D47) -> 209723.78 | E48: =SUM(E42:E47) -> 0 | F48: =SUM(F42:F47) -> 34049.28 | G48: =SUM(G42:G47) -> 0 | H48: =SUM(H42:H47) -> 39822.85 | I48: =SUM(I42:I47) -> 39822.85 | J48: =SUM(J42:J47) -> 169900.93
A50: After Cost Segregation Correction — AMT
A51: Asset | B51: Property Description | C51: Date In Service | D51: Cost | E51: Sec 179 Exp | F51: Bonus Amt | G51: AMT Prior Depreciation | H51: AMT Current Depreciation | I51: End Depreciation | J51: Net Book Value | K51: Method | L51: Period
A52: 1 | B52: 2-Building-712 Northfield Dr - 5 Year | C52: 7/30/24 | D52: 5001.64 | E52: 0 | F52: 3000.98 | G52: 0 | H52: 3401.11 | I52: =G52+H52 -> 3401.11 | J52: =D52-I52 -> 1600.53 | K52: 200DB | L52: 5.0
A53: 2 | B53: 2-Building-712 Northfield Dr - 27.5 Year | C53: 7/30/24 | D53: 22289.12 | E53: 0 | F53: 0 | G53: 0 | H53: 371.49 | I53: =G53+H53 -> 371.49 | J53: =D53-I53 -> 21917.63 | K53: S/L | L53: 27.5
A54: 3 | B54: 3-Northfield Dr - 5 Year | C54: 7/30/24 | D54: 645.37 | E54: 0 | F54: 387.22 | G54: 0 | H54: 438.85 | I54: =G54+H54 -> 438.85 | J54: =D54-I54 -> 206.52 | K54: 200DB | L54: 5.0
A55: 4 | B55: 3-Northfield Dr - 27.5 Year | C55: 7/30/24 | D55: 2876.01 | E55: 0 | F55: 0 | G55: 0 | H55: 47.93 | I55: =G55+H55 -> 47.93 | J55: =D55-I55 -> 2828.08 | K55: S/L | L55: 27.5
A56: 5 | B56: 4-Northfield Dr - 5 Year | C56: 7/30/24 | D56: 1210.08 | E56: 0 | F56: 726.05 | G56: 0 | H56: 822.86 | I56: =G56+H56 -> 822.86 | J56: =D56-I56 -> 387.22 | K56: 200DB | L56: 5.0
A57: 6 | B57: 4-Northfield Dr - 27.5 Year | C57: 7/30/24 | D57: 5392.53 | E57: 0 | F57: 0 | G57: 0 | H57: 89.88 | I57: =G57+H57 -> 89.88 | J57: =D57-I57 -> 5302.65 | K57: S/L | L57: 27.5
A58: 7 | B58: 7-Building-2202 Northview Dr - 5 Year | C58: 7/30/24 | D58: 23034.43 | E58: 0 | F58: 13820.66 | G58: 0 | H58: 15663.41 | I58: =G58+H58 -> 15663.41 | J58: =D58-I58 -> 7371.02 | K58: 200DB | L58: 5.0
A59: 8 | B59: 7-Building-2202 Northview Dr - 27.5 Year | C59: 7/30/24 | D59: 102649.8 | E59: 0 | F59: 0 | G59: 0 | H59: 1710.83 | I59: =G59+H59 -> 1710.83 | J59: =D59-I59 -> 100938.97 | K59: S/L | L59: 27.5
A60: 9 | B60: 8-Northiew Dr - 5 Year | C60: 7/30/24 | D60: 2972.18 | E60: 0 | F60: 1783.31 | G60: 0 | H60: 2021.08 | I60: =G60+H60 -> 2021.08 | J60: =D60-I60 -> 951.1 | K60: 200DB | L60: 5.0
A61: 10 | B61: 8-Northiew Dr - 27.5 Year | C61: 7/30/24 | D61: 13245.14 | E61: 0 | F61: 0 | G61: 0 | H61: 220.75 | I61: =G61+H61 -> 220.75 | J61: =D61-I61 -> 13024.39 | K61: S/L | L61: 27.5
A62: 11 | B62: 9-Northview Dr - 5 Year | C62: 7/30/24 | D62: 5572.85 | E62: 0 | F62: 3343.71 | G62: 0 | H62: 3789.54 | I62: =G62+H62 -> 3789.54 | J62: =D62-I62 -> 1783.31 | K62: 200DB | L62: 5.0
A63: 12 | B63: 9-Northview Dr - 27.5 Year | C63: 7/30/24 | D63: 24834.63 | E63: 0 | F63: 0 | G63: 0 | H63: 413.91 | I63: =G63+H63 -> 413.91 | J63: =D63-I63 -> 24420.72 | K63: S/L | L63: 27.5
B64: Grand Total | D64: =SUM(D52:D63) -> 209723.78 | E64: =SUM(E52:E63) -> 0 | F64: =SUM(F52:F63) -> 23061.93 | G64: =SUM(G52:G63) -> 0 | H64: =SUM(H52:H63) -> 28991.64 | I64: =SUM(I52:I63) -> 28991.64 | J64: =SUM(J52:J63) -> 180732.14
B66: Section 481(a) Adjustment — AMT
B67: Depreciation reported previously | D67: =I48 -> 39822.85
B68: Cost Segregation Corrected Depreciation | D68: =I64 -> 28991.64
B69: Section 481(a) Adjustment — AMT | D69: =D67-D68 -> 10831.21
A71: COST SEGREGATION STUDY — COST SUMMARY
B72: Total Building Cost | D72: =D110 -> 209723.78
B73: Building Components: 5 Year | D73: =F110 -> 38436.55
B74: % of Cost | D74: =F111 -> 0.18327225
B75: Building Structure: 27.5 Year | D75: =H110 -> 171287.23
B76: % of Cost | D76: =H111 -> 0.81672775
A78: COST SEGREGATION STUDY — COST DETAIL
B79: Property Category | D79: Cost | F79: 5 Year | H79: 27.5 Year
B80: Building Components
B81: Cabinets / Millwork | D81: =SUM(F81:H81) -> 8655.83 | F81: 8655.83
B82: Moldings | D82: =SUM(F82:H82) -> 3397.22 | F82: 3397.22
B83: Flooring - Wood Laminate | D83: =SUM(F83:H83) -> 12211.66 | F83: 12211.66
B84: Window Treatments | D84: =SUM(F84:H84) -> 2823.29 | F84: 2823.29
B85: Building Signage | D85: =SUM(F85:H85) -> 90.34 | F85: 90.34
B86: Specialty Electrical - Appliances | D86: =SUM(F86:H86) -> 1794.05 | F86: 1794.05
B87: Communication / Data | D87: =SUM(F87:H87) -> 1507.56 | F87: 1507.56
B88: Specialty Plumbing - Kitchen Sinks | D88: =SUM(F88:H88) -> 3281.59 | F88: 3281.59
B89: Security / Exterior Lighting | D89: =SUM(F89:H89) -> 1386.19 | F89: 1386.19
B90: Access Control | D90: =SUM(F90:H90) -> 53.16 | F90: 53.16
B91: Entry Canopies | D91: =SUM(F91:H91) -> 404.54 | F91: 404.54
B92: Appliances | D92: =SUM(F92:H92) -> 2831.12 | F92: 2831.12
B93: Building Structure
B94: Roofing Systems | D94: =SUM(F94:H94) -> 9211.22 | H94: 9211.22
B95: Foundations | D95: =SUM(F95:H95) -> 11470.72 | H95: 11470.72
B96: HVAC | D96: =SUM(F96:H96) -> 16969.73 | H96: 16969.73
B97: Electrical | D97: =SUM(F97:H97) -> 18340.3 | H97: 18340.3
B98: Plumbing | D98: =SUM(F98:H98) -> 14751.7 | H98: 14751.7
B99: Fire Protection & Alarm | D99: =SUM(F99:H99) -> 1388.53 | H99: 1388.53
B100: Exterior Façade / Building Skin | D100: =SUM(F100:H100) -> 7649.12 | H100: 7649.12
B101: Doors & Frames | D101: =SUM(F101:H101) -> 11108.31 | H101: 11108.31
B102: Windows | D102: =SUM(F102:H102) -> 5556.95 | H102: 5556.95
B103: Ceiling Systems | D103: =SUM(F103:H103) -> 7805.36 | H103: 7805.36
B104: Interior Framing / Partitions | D104: =SUM(F104:H104) -> 21030.97 | H104: 21030.97
B105: Painting | D105: =SUM(F105:H105) -> 9062.11 | H105: 9062.11
... B109: Bathroom Accessories | D109: =SUM(F109:H109) -> 2975.88 | H109: 2975.88
B110: Total Building Cost | D110: =SUM(D80:D109) -> 209723.78 | F110: =SUM(F80:F109) -> 38436.55 | H110: =SUM(H80:H109) -> 171287.23
B111: % of Cost | F111: =F110/D110 -> 0.18327225 | H111: =H110/D110 -> 0.81672775
...

Sheet Building 4
A1: River Garden Estates Housing LP
A2: River Garden Estates — 2201 Northview Dr & 712 Northfield Dr, Sacramento, CA 95833
A3: EIN: 93-2096487 · FYE: December 31, 2024 · Year of Change: 1/1/2024
A4: Building 4 — Attachment to Form 3115 (DCN #7, Rev. Proc. 2024-23 §6.01)
A5: Source: CSSI Report #107552-43, "#107552-43_River Garden Estates Housing LP_3115_Combined.pdf"
A7: CALCULATION OF §481(a) ADJUSTMENT — REGULAR TAX
A8: As Previously Filed
A9: Asset | B9: Property Description | C9: Date In Service | D9: Cost | E9: Sec 179 Exp | F9: Bonus Amt | G9: Tax Prior Depreciation | H9: Tax Current Depreciation | I9: End Depreciation | J9: Net Book Value | K9: Method | L9: Period
A10: 1 | B10: 2-Building-712 Northfield Dr | C10: 7/30/24 | D10: 53518.91 | E10: 0 | F10: 0 | G10: 0 | H10: 892 | I10: =G10+H10 -> 892 | J10: =D10-I10 -> 52626.91 | K10: S/L | L10: 27.5
A11: 2 | B11: 3-Northfield Dr | C11: 7/30/24 | D11: 6905.65 | E11: 0 | F11: 4143.39 | G11: 0 | H11: 4235.49 | I11: =G11+H11 -> 4235.49 | J11: =D11-I11 -> 2670.16 | K11: 150DB | L11: 15.0
A12: 3 | B12: 4-Northfield Dr | C12: 7/30/24 | D12: 12948.13 | E12: 0 | F12: 7768.88 | G12: 0 | H12: 8804.72 | I12: =G12+H12 -> 8804.72 | J12: =D12-I12 -> 4143.41 | K12: 200DB | L12: 5.0
A13: 4 | B13: 7-Building-2202 Northview Dr | C13: 7/30/24 | D13: 246474.74 | E13: 0 | F13: 0 | G13: 0 | H13: 4107.9 | I13: =G13+H13 -> 4107.9 | J13: =D13-I13 -> 242366.84 | K13: S/L | L13: 27.5
A14: 5 | B14: 8-Northiew Dr | C14: 7/30/24 | D14: 31803.19 | E14: 0 | F14: 19081.91 | G14: 0 | H14: 19505.96 | I14: =G14+H14 -> 19505.96 | J14: =D14-I14 -> 12297.23 | K14: 150DB | L14: 15.0
A15: 6 | B15: 9-Northview Dr | C15: 7/30/24 | D15: 59631 | E15: 0 | F15: 35778.6 | G15: 0 | H15: 40549.09 | I15: =G15+H15 -> 40549.09 | J15: =D15-I15 -> 19081.91 | K15: 200DB | L15: 5.0
B16: Grand Total | D16: =SUM(D10:D15) -> 411281.62 | E16: =SUM(E10:E15) -> 0 | F16: =SUM(F10:F15) -> 66772.78 | G16: =SUM(G10:G15) -> 0 | H16: =SUM(H10:H15) -> 78095.16 | I16: =SUM(I10:I15) -> 78095.16 | J16: =SUM(J10:J15) -> 333186.46
A18: After Cost Segregation Correction
A19: Asset | B19: Property Description | C19: Date In Service | D19: Cost | E19: Sec 179 Exp | F19: Bonus Amt | G19: Tax Prior Depreciation | H19: Tax Current Depreciation | I19: End Depreciation | J19: Net Book Value | K19: Method | L19: Period
A20: 1 | B20: 2-Building-712 Northfield Dr - 5 Year | C20: 7/30/24 | D20: 9996.83 | E20: 0 | F20: 5998.1 | G20: 0 | H20: 6797.85 | I20: =G20+H20 -> 6797.85 | J20: =D20-I20 -> 3198.98 | K20: 200DB | L20: 5.0
A21: 2 | B21: 2-Building-712 Northfield Dr - 27.5 Year | C21: 7/30/24 | D21: 43522.08 | E21: 0 | F21: 0 | G21: 0 | H21: 725.37 | I21: =G21+H21 -> 725.37 | J21: =D21-I21 -> 42796.71 | K21: S/L | L21: 27.5
A22: 3 | B22: 3-Northfield Dr - 5 Year | C22: 7/30/24 | D22: 1289.91 | E22: 0 | F22: 773.95 | G22: 0 | H22: 877.14 | I22: =G22+H22 -> 877.14 | J22: =D22-I22 -> 412.77 | K22: 200DB | L22: 5.0
A23: 4 | B23: 3-Northfield Dr - 27.5 Year | C23: 7/30/24 | D23: 5615.74 | E23: 0 | F23: 0 | G23: 0 | H23: 93.6 | I23: =G23+H23 -> 93.6 | J23: =D23-I23 -> 5522.14 | K23: S/L | L23: 27.5
A24: 5 | B24: 4-Northfield Dr - 5 Year | C24: 7/30/24 | D24: 2418.59 | E24: 0 | F24: 1451.15 | G24: 0 | H24: 1644.64 | I24: =G24+H24 -> 1644.64 | J24: =D24-I24 -> 773.95 | K24: 200DB | L24: 5.0
A25: 6 | B25: 4-Northfield Dr - 27.5 Year | C25: 7/30/24 | D25: 10529.54 | E25: 0 | F25: 0 | G25: 0 | H25: 175.49 | I25: =G25+H25 -> 175.49 | J25: =D25-I25 -> 10354.05 | K25: S/L | L25: 27.5
A26: 7 | B26: 7-Building-2202 Northview Dr - 5 Year | C26: 7/30/24 | D26: 46039.18 | E26: 0 | F26: 27623.51 | G26: 0 | H26: 31306.64 | I26: =G26+H26 -> 31306.64 | J26: =D26-I26 -> 14732.54 | K26: 200DB | L26: 5.0
A27: 8 | B27: 7-Building-2202 Northview Dr - 27.5 Year | C27: 7/30/24 | D27: 200435.56 | E27: 0 | F27: 0 | G27: 0 | H27: 3340.59 | I27: =G27+H27 -> 3340.59 | J27: =D27-I27 -> 197094.97 | K27: S/L | L27: 27.5
A28: 9 | B28: 8-Northiew Dr - 5 Year | C28: 7/30/24 | D28: 5940.54 | E28: 0 | F28: 3564.32 | G28: 0 | H28: 4039.56 | I28: =G28+H28 -> 4039.56 | J28: =D28-I28 -> 1900.98 | K28: 200DB | L28: 5.0
A29: 10 | B29: 8-Northiew Dr - 27.5 Year | C29: 7/30/24 | D29: 25862.65 | E29: 0 | F29: 0 | G29: 0 | H29: 431.04 | I29: =G29+H29 -> 431.04 | J29: =D29-I29 -> 25431.61 | K29: S/L | L29: 27.5
A30: 11 | B30: 9-Northview Dr - 5 Year | C30: 7/30/24 | D30: 11138.51 | E30: 0 | F30: 6683.11 | G30: 0 | H30: 7574.19 | I30: =G30+H30 -> 7574.19 | J30: =D30-I30 -> 3564.32 | K30: 200DB | L30: 5.0
A31: 12 | B31: 9-Northview Dr - 27.5 Year | C31: 7/30/24 | D31: 48492.49 | E31: 0 | F31: 0 | G31: 0 | H31: 808.21 | I31: =G31+H31 -> 808.21 | J31: =D31-I31 -> 47684.28 | K31: S/L | L31: 27.5
B32: Grand Total | D32: =SUM(D20:D31) -> 411281.62 | E32: =SUM(E20:E31) -> 0 | F32: =SUM(F20:F31) -> 46094.14 | G32: =SUM(G20:G31) -> 0 | H32: =SUM(H20:H31) -> 57814.32 | I32: =SUM(I20:I31) -> 57814.32 | J32: =SUM(J20:J31) -> 353467.3
B34: Section 481(a) Adjustment — Regular Tax
B35: Depreciation reported previously | D35: =I16 -> 78095.16
B36: Cost Segregation Corrected Depreciation | D36: =I32 -> 57814.32
B37: Section 481(a) Adjustment — Regular Tax | D37: =D35-D36 -> 20280.84
A39: CALCULATION OF §481(a) ADJUSTMENT — AMT
A40: As Previously Filed — AMT
A41: Asset | B41: Property Description | C41: Date In Service | D41: Cost | E41: Sec 179 Exp | F41: Bonus Amt | G41: AMT Prior Depreciation | H41: AMT Current Depreciation | I41: End Depreciation | J41: Net Book Value | K41: Method | L41: Period
A42: 1 | B42: 2-Building-712 Northfield Dr | C42: 7/30/24 | D42: 53518.91 | E42: 0 | F42: 0 | G42: 0 | H42: 892 | I42: =G42+H42 -> 892 | J42: =D42-I42 -> 52626.91 | K42: S/L | L42: 27.5
A43: 2 | B43: 3-Northfield Dr | C43: 7/30/24 | D43: 6905.65 | E43: 0 | F43: 4143.39 | G43: 0 | H43: 4235.49 | I43: =G43+H43 -> 4235.49 | J43: =D43-I43 -> 2670.16 | K43: 150DB | L43: 15.0
A44: 3 | B44: 4-Northfield Dr | C44: 7/30/24 | D44: 12948.13 | E44: 0 | F44: 7768.88 | G44: 0 | H44: 8804.72 | I44: =G44+H44 -> 8804.72 | J44: =D44-I44 -> 4143.41 | K44: 200DB | L44: 5.0
A45: 4 | B45: 7-Building-2202 Northview Dr | C45: 7/30/24 | D45: 246474.74 | E45: 0 | F45: 0 | G45: 0 | H45: 4107.9 | I45: =G45+H45 -> 4107.9 | J45: =D45-I45 -> 242366.84 | K45: S/L | L45: 27.5
A46: 5 | B46: 8-Northiew Dr | C46: 7/30/24 | D46: 31803.19 | E46: 0 | F46: 19081.91 | G46: 0 | H46: 19505.96 | I46: =G46+H46 -> 19505.96 | J46: =D46-I46 -> 12297.23 | K46: 150DB | L46: 15.0
A47: 6 | B47: 9-Northview Dr | C47: 7/30/24 | D47: 59631 | E47: 0 | F47: 35778.6 | G47: 0 | H47: 40549.09 | I47: =G47+H47 -> 40549.09 | J47: =D47-I47 -> 19081.91 | K47: 200DB | L47: 5.0
B48: Grand Total | D48: =SUM(D42:D47) -> 411281.62 | E48: =SUM(E42:E47) -> 0 | F48: =SUM(F42:F47) -> 66772.78 | G48: =SUM(G42:G47) -> 0 | H48: =SUM(H42:H47) -> 78095.16 | I48: =SUM(I42:I47) -> 78095.16 | J48: =SUM(J42:J47) -> 333186.46
A50: After Cost Segregation Correction — AMT
A51: Asset | B51: Property Description | C51: Date In Service | D51: Cost | E51: Sec 179 Exp | F51: Bonus Amt | G51: AMT Prior Depreciation | H51: AMT Current Depreciation | I51: End Depreciation | J51: Net Book Value | K51: Method | L51: Period
A52: 1 | B52: 2-Building-712 Northfield Dr - 5 Year | C52: 7/30/24 | D52: 9996.83 | E52: 0 | F52: 5998.1 | G52: 0 | H52: 6797.85 | I52: =G52+H52 -> 6797.85 | J52: =D52-I52 -> 3198.98 | K52: 200DB | L52: 5.0
A53: 2 | B53: 2-Building-712 Northfield Dr - 27.5 Year | C53: 7/30/24 | D53: 43522.08 | E53: 0 | F53: 0 | G53: 0 | H53: 725.37 | I53: =G53+H53 -> 725.37 | J53: =D53-I53 -> 42796.71 | K53: S/L | L53: 27.5
A54: 3 | B54: 3-Northfield Dr - 5 Year | C54: 7/30/24 | D54: 1289.91 | E54: 0 | F54: 773.95 | G54: 0 | H54: 877.14 | I54: =G54+H54 -> 877.14 | J54: =D54-I54 -> 412.77 | K54: 200DB | L54: 5.0
A55: 4 | B55: 3-Northfield Dr - 27.5 Year | C55: 7/30/24 | D55: 5615.74 | E55: 0 | F55: 0 | G55: 0 | H55: 93.6 | I55: =G55+H55 -> 93.6 | J55: =D55-I55 -> 5522.14 | K55: S/L | L55: 27.5
A56: 5 | B56: 4-Northfield Dr - 5 Year | C56: 7/30/24 | D56: 2418.59 | E56: 0 | F56: 1451.15 | G56: 0 | H56: 1644.64 | I56: =G56+H56 -> 1644.64 | J56: =D56-I56 -> 773.95 | K56: 200DB | L56: 5.0
A57: 6 | B57: 4-Northfield Dr - 27.5 Year | C57: 7/30/24 | D57: 10529.54 | E57: 0 | F57: 0 | G57: 0 | H57: 175.49 | I57: =G57+H57 -> 175.49 | J57: =D57-I57 -> 10354.05 | K57: S/L | L57: 27.5
A58: 7 | B58: 7-Building-2202 Northview Dr - 5 Year | C58: 7/30/24 | D58: 46039.18 | E58: 0 | F58: 27623.51 | G58: 0 | H58: 31306.64 | I58: =G58+H58 -> 31306.64 | J58: =D58-I58 -> 14732.54 | K58: 200DB | L58: 5.0
A59: 8 | B59: 7-Building-2202 Northview Dr - 27.5 Year | C59: 7/30/24 | D59: 200435.56 | E59: 0 | F59: 0 | G59: 0 | H59: 3340.59 | I59: =G59+H59 -> 3340.59 | J59: =D59-I59 -> 197094.97 | K59: S/L | L59: 27.5
A60: 9 | B60: 8-Northiew Dr - 5 Year | C60: 7/30/24 | D60: 5940.54 | E60: 0 | F60: 3564.32 | G60: 0 | H60: 4039.56 | I60: =G60+H60 -> 4039.56 | J60: =D60-I60 -> 1900.98 | K60: 200DB | L60: 5.0
A61: 10 | B61: 8-Northiew Dr - 27.5 Year | C61: 7/30/24 | D61: 25862.65 | E61: 0 | F61: 0 | G61: 0 | H61: 431.04 | I61: =G61+H61 -> 431.04 | J61: =D61-I61 -> 25431.61 | K61: S/L | L61: 27.5
A62: 11 | B62: 9-Northview Dr - 5 Year | C62: 7/30/24 | D62: 11138.51 | E62: 0 | F62: 6683.11 | G62: 0 | H62: 7574.19 | I62: =G62+H62 -> 7574.19 | J62: =D62-I62 -> 3564.32 | K62: 200DB | L62: 5.0
A63: 12 | B63: 9-Northview Dr - 27.5 Year | C63: 7/30/24 | D63: 48492.49 | E63: 0 | F63: 0 | G63: 0 | H63: 808.21 | I63: =G63+H63 -> 808.21 | J63: =D63-I63 -> 47684.28 | K63: S/L | L63: 27.5
B64: Grand Total | D64: =SUM(D52:D63) -> 411281.62 | E64: =SUM(E52:E63) -> 0 | F64: =SUM(F52:F63) -> 46094.14 | G64: =SUM(G52:G63) -> 0 | H64: =SUM(H52:H63) -> 57814.32 | I64: =SUM(I52:I63) -> 57814.32 | J64: =SUM(J52:J63) -> 353467.3
B66: Section 481(a) Adjustment — AMT
B67: Depreciation reported previously | D67: =I48 -> 78095.16
B68: Cost Segregation Corrected Depreciation | D68: =I64 -> 57814.32
B69: Section 481(a) Adjustment — AMT | D69: =D67-D68 -> 20280.84
A71: COST SEGREGATION STUDY — COST SUMMARY
B72: Total Building Cost | D72: =D112 -> 411281.62
B73: Building Components: 5 Year | D73: =F112 -> 76823.56
B74: % of Cost | D74: =F113 -> 0.18679065
B75: Building Structure: 27.5 Year | D75: =H112 -> 334458.06
B76: % of Cost | D76: =H113 -> 0.81320935
A78: COST SEGREGATION STUDY — COST DETAIL
B79: Property Category | D79: Cost | F79: 5 Year | H79: 27.5 Year
B80: Building Components
B81: Cabinets / Millwork | D81: =SUM(F81:H81) -> 17269.54 | F81: 17269.54
B82: Moldings | D82: =SUM(F82:H82) -> 5872.52 | F82: 5872.52
B83: Flooring - Carpet | D83: =SUM(F83:H83) -> 1061.02 | F83: 1061.02
B84: Flooring - Wood Laminate | D84: =SUM(F84:H84) -> 24005.05 | F84: 24005.05
B85: Flooring - Seamless Vinyl | D85: =SUM(F85:H85) -> 164.32 | F85: 164.32
B86: Window Treatments | D86: =SUM(F86:H86) -> 5825.84 | F86: 5825.84
B87: Building Signage | D87: =SUM(F87:H87) -> 150.1 | F87: 150.1
B88: Specialty Electrical - Appliances | D88: =SUM(F88:H88) -> 3588.08 | F88: 3588.08
B89: Communication / Data | D89: =SUM(F89:H89) -> 3097.62 | F89: 3097.62
B90: Specialty Plumbing - Kitchen Sinks | D90: =SUM(F90:H90) -> 6563.2 | F90: 6563.2
B91: Security / Exterior Lighting | D91: =SUM(F91:H91) -> 2648.6 | F91: 2648.6
B92: Access Control | D92: =SUM(F92:H92) -> 106.32 | F92: 106.32
... B94: Appliances | D94: =SUM(F94:H94) -> 5662.23 | F94: 5662.23
B95: Building Structure
B96: Roofing Systems | D96: =SUM(F96:H96) -> 19965.05 | H96: 19965.05
B97: Foundations | D97: =SUM(F97:H97) -> 23099.53 | H97: 23099.53
B98: HVAC | D98: =SUM(F98:H98) -> 34868.14 | H98: 34868.14
B99: Electrical | D99: =SUM(F99:H99) -> 37684.26 | H99: 37684.26
B100: Plumbing | D100: =SUM(F100:H100) -> 30310.68 | H100: 30310.68
B101: Fire Protection & Alarm | D101: =SUM(F101:H101) -> 2483.74 | H101: 2483.74
B102: Exterior Façade / Building Skin | D102: =SUM(F102:H102) -> 12802.47 | H102: 12802.47
B103: Doors & Frames | D103: =SUM(F103:H103) -> 21480.24 | H103: 21480.24
B104: Windows | D104: =SUM(F104:H104) -> 11643.15 | H104: 11643.15
B105: Ceiling Systems | D105: =SUM(F105:H105) -> 16037.83 | H105: 16037.83
B106: Interior Framing / Partitions | D106: =SUM(F106:H106) -> 35969.2 | H106: 35969.2
B107: Painting | D107: =SUM(F107:H107) -> 16182.61 | H107: 16182.61
... B111: Bathroom Accessories | D111: =SUM(F111:H111) -> 5500.39 | H111: 5500.39
B112: Total Building Cost | D112: =SUM(D80:D111) -> 411281.62 | F112: =SUM(F80:F111) -> 76823.56 | H112: =SUM(H80:H111) -> 334458.06
...

Sheet Building 5
A1: River Garden Estates Housing LP
A2: River Garden Estates — 2201 Northview Dr & 712 Northfield Dr, Sacramento, CA 95833
A3: EIN: 93-2096487 · FYE: December 31, 2024 · Year of Change: 1/1/2024
A4: Building 5 — Attachment to Form 3115 (DCN #7, Rev. Proc. 2024-23 §6.01)
A5: Source: CSSI Report #107552-43, "#107552-43_River Garden Estates Housing LP_3115_Combined.pdf"
A7: CALCULATION OF §481(a) ADJUSTMENT — REGULAR TAX
A8: As Previously Filed
A9: Asset | B9: Property Description | C9: Date In Service | D9: Cost | E9: Sec 179 Exp | F9: Bonus Amt | G9: Tax Prior Depreciation | H9: Tax Current Depreciation | I9: End Depreciation | J9: Net Book Value | K9: Method | L9: Period
A10: 1 | B10: 2-Building-712 Northfield Dr | C10: 7/30/24 | D10: 27290.76 | E10: 0 | F10: 0 | G10: 0 | H10: 454.85 | I10: =G10+H10 -> 454.85 | J10: =D10-I10 -> 26835.91 | K10: S/L | L10: 27.5
A11: 2 | B11: 3-Northfield Dr | C11: 7/30/24 | D11: 3521.38 | E11: 0 | F11: 2112.83 | G11: 0 | H11: 2159.79 | I11: =G11+H11 -> 2159.79 | J11: =D11-I11 -> 1361.59 | K11: 150DB | L11: 15.0
A12: 3 | B12: 4-Northfield Dr | C12: 7/30/24 | D12: 6602.61 | E12: 0 | F12: 3961.57 | G12: 0 | H12: 4489.77 | I12: =G12+H12 -> 4489.77 | J12: =D12-I12 -> 2112.84 | K12: 200DB | L12: 5.0
A13: 4 | B13: 7-Building-2202 Northview Dr | C13: 7/30/24 | D13: 125684.23 | E13: 0 | F13: 0 | G13: 0 | H13: 2094.73 | I13: =G13+H13 -> 2094.73 | J13: =D13-I13 -> 123589.5 | K13: S/L | L13: 27.5
A14: 5 | B14: 8-Northiew Dr | C14: 7/30/24 | D14: 16217.32 | E14: 0 | F14: 9730.39 | G14: 0 | H14: 9946.62 | I14: =G14+H14 -> 9946.62 | J14: =D14-I14 -> 6270.7 | K14: 150DB | L14: 15.0
A15: 6 | B15: 9-Northview Dr | C15: 7/30/24 | D15: 30407.48 | E15: 0 | F15: 18244.49 | G15: 0 | H15: 20677.09 | I15: =G15+H15 -> 20677.09 | J15: =D15-I15 -> 9730.39 | K15: 200DB | L15: 5.0
B16: Grand Total | D16: =SUM(D10:D15) -> 209723.78 | E16: =SUM(E10:E15) -> 0 | F16: =SUM(F10:F15) -> 34049.28 | G16: =SUM(G10:G15) -> 0 | H16: =SUM(H10:H15) -> 39822.85 | I16: =SUM(I10:I15) -> 39822.85 | J16: =SUM(J10:J15) -> 169900.93
A18: After Cost Segregation Correction
A19: Asset | B19: Property Description | C19: Date In Service | D19: Cost | E19: Sec 179 Exp | F19: Bonus Amt | G19: Tax Prior Depreciation | H19: Tax Current Depreciation | I19: End Depreciation | J19: Net Book Value | K19: Method | L19: Period
A20: 1 | B20: 2-Building-712 Northfield Dr - 5 Year | C20: 7/30/24 | D20: 5001.64 | E20: 0 | F20: 3000.98 | G20: 0 | H20: 3401.11 | I20: =G20+H20 -> 3401.11 | J20: =D20-I20 -> 1600.53 | K20: 200DB | L20: 5.0
A21: 2 | B21: 2-Building-712 Northfield Dr - 27.5 Year | C21: 7/30/24 | D21: 22289.12 | E21: 0 | F21: 0 | G21: 0 | H21: 371.49 | I21: =G21+H21 -> 371.49 | J21: =D21-I21 -> 21917.63 | K21: S/L | L21: 27.5
A22: 3 | B22: 3-Northfield Dr - 5 Year | C22: 7/30/24 | D22: 645.37 | E22: 0 | F22: 387.22 | G22: 0 | H22: 438.85 | I22: =G22+H22 -> 438.85 | J22: =D22-I22 -> 206.52 | K22: 200DB | L22: 5.0
A23: 4 | B23: 3-Northfield Dr - 27.5 Year | C23: 7/30/24 | D23: 2876.01 | E23: 0 | F23: 0 | G23: 0 | H23: 47.93 | I23: =G23+H23 -> 47.93 | J23: =D23-I23 -> 2828.08 | K23: S/L | L23: 27.5
A24: 5 | B24: 4-Northfield Dr - 5 Year | C24: 7/30/24 | D24: 1210.08 | E24: 0 | F24: 726.05 | G24: 0 | H24: 822.86 | I24: =G24+H24 -> 822.86 | J24: =D24-I24 -> 387.22 | K24: 200DB | L24: 5.0
A25: 6 | B25: 4-Northfield Dr - 27.5 Year | C25: 7/30/24 | D25: 5392.53 | E25: 0 | F25: 0 | G25: 0 | H25: 89.88 | I25: =G25+H25 -> 89.88 | J25: =D25-I25 -> 5302.65 | K25: S/L | L25: 27.5
A26: 7 | B26: 7-Building-2202 Northview Dr - 5 Year | C26: 7/30/24 | D26: 23034.43 | E26: 0 | F26: 13820.66 | G26: 0 | H26: 15663.41 | I26: =G26+H26 -> 15663.41 | J26: =D26-I26 -> 7371.02 | K26: 200DB | L26: 5.0
A27: 8 | B27: 7-Building-2202 Northview Dr - 27.5 Year | C27: 7/30/24 | D27: 102649.8 | E27: 0 | F27: 0 | G27: 0 | H27: 1710.83 | I27: =G27+H27 -> 1710.83 | J27: =D27-I27 -> 100938.97 | K27: S/L | L27: 27.5
A28: 9 | B28: 8-Northiew Dr - 5 Year | C28: 7/30/24 | D28: 2972.18 | E28: 0 | F28: 1783.31 | G28: 0 | H28: 2021.08 | I28: =G28+H28 -> 2021.08 | J28: =D28-I28 -> 951.1 | K28: 200DB | L28: 5.0
A29: 10 | B29: 8-Northiew Dr - 27.5 Year | C29: 7/30/24 | D29: 13245.14 | E29: 0 | F29: 0 | G29: 0 | H29: 220.75 | I29: =G29+H29 -> 220.75 | J29: =D29-I29 -> 13024.39 | K29: S/L | L29: 27.5
A30: 11 | B30: 9-Northview Dr - 5 Year | C30: 7/30/24 | D30: 5572.85 | E30: 0 | F30: 3343.71 | G30: 0 | H30: 3789.54 | I30: =G30+H30 -> 3789.54 | J30: =D30-I30 -> 1783.31 | K30: 200DB | L30: 5.0
A31: 12 | B31: 9-Northview Dr - 27.5 Year | C31: 7/30/24 | D31: 24834.63 | E31: 0 | F31: 0 | G31: 0 | H31: 413.91 | I31: =G31+H31 -> 413.91 | J31: =D31-I31 -> 24420.72 | K31: S/L | L31: 27.5
B32: Grand Total | D32: =SUM(D20:D31) -> 209723.78 | E32: =SUM(E20:E31) -> 0 | F32: =SUM(F20:F31) -> 23061.93 | G32: =SUM(G20:G31) -> 0 | H32: =SUM(H20:H31) -> 28991.64 | I32: =SUM(I20:I31) -> 28991.64 | J32: =SUM(J20:J31) -> 180732.14
B34: Section 481(a) Adjustment — Regular Tax
B35: Depreciation reported previously | D35: =I16 -> 39822.85
B36: Cost Segregation Corrected Depreciation | D36: =I32 -> 28991.64
B37: Section 481(a) Adjustment — Regular Tax | D37: =D35-D36 -> 10831.21
A39: CALCULATION OF §481(a) ADJUSTMENT — AMT
A40: As Previously Filed — AMT
A41: Asset | B41: Property Description | C41: Date In Service | D41: Cost | E41: Sec 179 Exp | F41: Bonus Amt | G41: AMT Prior Depreciation | H41: AMT Current Depreciation | I41: End Depreciation | J41: Net Book Value | K41: Method | L41: Period
A42: 1 | B42: 2-Building-712 Northfield Dr | C42: 7/30/24 | D42: 27290.76 | E42: 0 | F42: 0 | G42: 0 | H42: 454.85 | I42: =G42+H42 -> 454.85 | J42: =D42-I42 -> 26835.91 | K42: S/L | L42: 27.5
A43: 2 | B43: 3-Northfield Dr | C43: 7/30/24 | D43: 3521.38 | E43: 0 | F43: 2112.83 | G43: 0 | H43: 2159.79 | I43: =G43+H43 -> 2159.79 | J43: =D43-I43 -> 1361.59 | K43: 150DB | L43: 15.0
A44: 3 | B44: 4-Northfield Dr | C44: 7/30/24 | D44: 6602.61 | E44: 0 | F44: 3961.57 | G44: 0 | H44: 4489.77 | I44: =G44+H44 -> 4489.77 | J44: =D44-I44 -> 2112.84 | K44: 200DB | L44: 5.0
A45: 4 | B45: 7-Building-2202 Northview Dr | C45: 7/30/24 | D45: 125684.23 | E45: 0 | F45: 0 | G45: 0 | H45: 2094.73 | I45: =G45+H45 -> 2094.73 | J45: =D45-I45 -> 123589.5 | K45: S/L | L45: 27.5
A46: 5 | B46: 8-Northiew Dr | C46: 7/30/24 | D46: 16217.32 | E46: 0 | F46: 9730.39 | G46: 0 | H46: 9946.62 | I46: =G46+H46 -> 9946.62 | J46: =D46-I46 -> 6270.7 | K46: 150DB | L46: 15.0
A47: 6 | B47: 9-Northview Dr | C47: 7/30/24 | D47: 30407.48 | E47: 0 | F47: 18244.49 | G47: 0 | H47: 20677.09 | I47: =G47+H47 -> 20677.09 | J47: =D47-I47 -> 9730.39 | K47: 200DB | L47: 5.0
B48: Grand Total | D48: =SUM(D42:D47) -> 209723.78 | E48: =SUM(E42:E47) -> 0 | F48: =SUM(F42:F47) -> 34049.28 | G48: =SUM(G42:G47) -> 0 | H48: =SUM(H42:H47) -> 39822.85 | I48: =SUM(I42:I47) -> 39822.85 | J48: =SUM(J42:J47) -> 169900.93
A50: After Cost Segregation Correction — AMT
A51: Asset | B51: Property Description | C51: Date In Service | D51: Cost | E51: Sec 179 Exp | F51: Bonus Amt | G51: AMT Prior Depreciation | H51: AMT Current Depreciation | I51: End Depreciation | J51: Net Book Value | K51: Method | L51: Period
A52: 1 | B52: 2-Building-712 Northfield Dr - 5 Year | C52: 7/30/24 | D52: 5001.64 | E52: 0 | F52: 3000.98 | G52: 0 | H52: 3401.11 | I52: =G52+H52 -> 3401.11 | J52: =D52-I52 -> 1600.53 | K52: 200DB | L52: 5.0
A53: 2 | B53: 2-Building-712 Northfield Dr - 27.5 Year | C53: 7/30/24 | D53: 22289.12 | E53: 0 | F53: 0 | G53: 0 | H53: 371.49 | I53: =G53+H53 -> 371.49 | J53: =D53-I53 -> 21917.63 | K53: S/L | L53: 27.5
A54: 3 | B54: 3-Northfield Dr - 5 Year | C54: 7/30/24 | D54: 645.37 | E54: 0 | F54: 387.22 | G54: 0 | H54: 438.85 | I54: =G54+H54 -> 438.85 | J54: =D54-I54 -> 206.52 | K54: 200DB | L54: 5.0
A55: 4 | B55: 3-Northfield Dr - 27.5 Year | C55: 7/30/24 | D55: 2876.01 | E55: 0 | F55: 0 | G55: 0 | H55: 47.93 | I55: =G55+H55 -> 47.93 | J55: =D55-I55 -> 2828.08 | K55: S/L | L55: 27.5
A56: 5 | B56: 4-Northfield Dr - 5 Year | C56: 7/30/24 | D56: 1210.08 | E56: 0 | F56: 726.05 | G56: 0 | H56: 822.86 | I56: =G56+H56 -> 822.86 | J56: =D56-I56 -> 387.22 | K56: 200DB | L56: 5.0
A57: 6 | B57: 4-Northfield Dr - 27.5 Year | C57: 7/30/24 | D57: 5392.53 | E57: 0 | F57: 0 | G57: 0 | H57: 89.88 | I57: =G57+H57 -> 89.88 | J57: =D57-I57 -> 5302.65 | K57: S/L | L57: 27.5
A58: 7 | B58: 7-Building-2202 Northview Dr - 5 Year | C58: 7/30/24 | D58: 23034.43 | E58: 0 | F58: 13820.66 | G58: 0 | H58: 15663.41 | I58: =G58+H58 -> 15663.41 | J58: =D58-I58 -> 7371.02 | K58: 200DB | L58: 5.0
A59: 8 | B59: 7-Building-2202 Northview Dr - 27.5 Year | C59: 7/30/24 | D59: 102649.8 | E59: 0 | F59: 0 | G59: 0 | H59: 1710.83 | I59: =G59+H59 -> 1710.83 | J59: =D59-I59 -> 100938.97 | K59: S/L | L59: 27.5
A60: 9 | B60: 8-Northiew Dr - 5 Year | C60: 7/30/24 | D60: 2972.18 | E60: 0 | F60: 1783.31 | G60: 0 | H60: 2021.08 | I60: =G60+H60 -> 2021.08 | J60: =D60-I60 -> 951.1 | K60: 200DB | L60: 5.0
A61: 10 | B61: 8-Northiew Dr - 27.5 Year | C61: 7/30/24 | D61: 13245.14 | E61: 0 | F61: 0 | G61: 0 | H61: 220.75 | I61: =G61+H61 -> 220.75 | J61: =D61-I61 -> 13024.39 | K61: S/L | L61: 27.5
A62: 11 | B62: 9-Northview Dr - 5 Year | C62: 7/30/24 | D62: 5572.85 | E62: 0 | F62: 3343.71 | G62: 0 | H62: 3789.54 | I62: =G62+H62 -> 3789.54 | J62: =D62-I62 -> 1783.31 | K62: 200DB | L62: 5.0
A63: 12 | B63: 9-Northview Dr - 27.5 Year | C63: 7/30/24 | D63: 24834.63 | E63: 0 | F63: 0 | G63: 0 | H63: 413.91 | I63: =G63+H63 -> 413.91 | J63: =D63-I63 -> 24420.72 | K63: S/L | L63: 27.5
B64: Grand Total | D64: =SUM(D52:D63) -> 209723.78 | E64: =SUM(E52:E63) -> 0 | F64: =SUM(F52:F63) -> 23061.93 | G64: =SUM(G52:G63) -> 0 | H64: =SUM(H52:H63) -> 28991.64 | I64: =SUM(I52:I63) -> 28991.64 | J64: =SUM(J52:J63) -> 180732.14
B66: Section 481(a) Adjustment — AMT
B67: Depreciation reported previously | D67: =I48 -> 39822.85
B68: Cost Segregation Corrected Depreciation | D68: =I64 -> 28991.64
B69: Section 481(a) Adjustment — AMT | D69: =D67-D68 -> 10831.21
A71: COST SEGREGATION STUDY — COST SUMMARY
B72: Total Building Cost | D72: =D110 -> 209723.78
B73: Building Components: 5 Year | D73: =F110 -> 38436.55
B74: % of Cost | D74: =F111 -> 0.18327225
B75: Building Structure: 27.5 Year | D75: =H110 -> 171287.23
B76: % of Cost | D76: =H111 -> 0.81672775
A78: COST SEGREGATION STUDY — COST DETAIL
B79: Property Category | D79: Cost | F79: 5 Year | H79: 27.5 Year
B80: Building Components
B81: Cabinets / Millwork | D81: =SUM(F81:H81) -> 8655.83 | F81: 8655.83
B82: Moldings | D82: =SUM(F82:H82) -> 3397.22 | F82: 3397.22
B83: Flooring - Wood Laminate | D83: =SUM(F83:H83) -> 12211.66 | F83: 12211.66
B84: Window Treatments | D84: =SUM(F84:H84) -> 2823.29 | F84: 2823.29
B85: Building Signage | D85: =SUM(F85:H85) -> 90.34 | F85: 90.34
B86: Specialty Electrical - Appliances | D86: =SUM(F86:H86) -> 1794.05 | F86: 1794.05
B87: Communication / Data | D87: =SUM(F87:H87) -> 1507.56 | F87: 1507.56
B88: Specialty Plumbing - Kitchen Sinks | D88: =SUM(F88:H88) -> 3281.59 | F88: 3281.59
B89: Security / Exterior Lighting | D89: =SUM(F89:H89) -> 1386.19 | F89: 1386.19
B90: Access Control | D90: =SUM(F90:H90) -> 53.16 | F90: 53.16
B91: Entry Canopies | D91: =SUM(F91:H91) -> 404.54 | F91: 404.54
B92: Appliances | D92: =SUM(F92:H92) -> 2831.12 | F92: 2831.12
B93: Building Structure
B94: Roofing Systems | D94: =SUM(F94:H94) -> 9211.22 | H94: 9211.22
B95: Foundations | D95: =SUM(F95:H95) -> 11470.72 | H95: 11470.72
B96: HVAC | D96: =SUM(F96:H96) -> 16969.73 | H96: 16969.73
B97: Electrical | D97: =SUM(F97:H97) -> 18340.3 | H97: 18340.3
B98: Plumbing | D98: =SUM(F98:H98) -> 14751.7 | H98: 14751.7
B99: Fire Protection & Alarm | D99: =SUM(F99:H99) -> 1388.53 | H99: 1388.53
B100: Exterior Façade / Building Skin | D100: =SUM(F100:H100) -> 7649.12 | H100: 7649.12
B101: Doors & Frames | D101: =SUM(F101:H101) -> 11108.31 | H101: 11108.31
B102: Windows | D102: =SUM(F102:H102) -> 5556.95 | H102: 5556.95
B103: Ceiling Systems | D103: =SUM(F103:H103) -> 7805.36 | H103: 7805.36
B104: Interior Framing / Partitions | D104: =SUM(F104:H104) -> 21030.97 | H104: 21030.97
B105: Painting | D105: =SUM(F105:H105) -> 9062.11 | H105: 9062.11
... B109: Bathroom Accessories | D109: =SUM(F109:H109) -> 2975.88 | H109: 2975.88
B110: Total Building Cost | D110: =SUM(D80:D109) -> 209723.78 | F110: =SUM(F80:F109) -> 38436.55 | H110: =SUM(H80:H109) -> 171287.23
B111: % of Cost | F111: =F110/D110 -> 0.18327225 | H111: =H110/D110 -> 0.81672775
...

Sheet Building 6
A1: River Garden Estates Housing LP
A2: River Garden Estates — 2201 Northview Dr & 712 Northfield Dr, Sacramento, CA 95833
A3: EIN: 93-2096487 · FYE: December 31, 2024 · Year of Change: 1/1/2024
A4: Building 6 — Attachment to Form 3115 (DCN #7, Rev. Proc. 2024-23 §6.01)
A5: Source: CSSI Report #107552-43, "#107552-43_River Garden Estates Housing LP_3115_Combined.pdf"
A7: CALCULATION OF §481(a) ADJUSTMENT — REGULAR TAX
A8: As Previously Filed
A9: Asset | B9: Property Description | C9: Date In Service | D9: Cost | E9: Sec 179 Exp | F9: Bonus Amt | G9: Tax Prior Depreciation | H9: Tax Current Depreciation | I9: End Depreciation | J9: Net Book Value | K9: Method | L9: Period
A10: 1 | B10: 2-Building-712 Northfield Dr | C10: 7/30/24 | D10: 53518.91 | E10: 0 | F10: 0 | G10: 0 | H10: 892 | I10: =G10+H10 -> 892 | J10: =D10-I10 -> 52626.91 | K10: S/L | L10: 27.5
A11: 2 | B11: 3-Northfield Dr | C11: 7/30/24 | D11: 6905.65 | E11: 0 | F11: 4143.39 | G11: 0 | H11: 4235.49 | I11: =G11+H11 -> 4235.49 | J11: =D11-I11 -> 2670.16 | K11: 150DB | L11: 15.0
A12: 3 | B12: 4-Northfield Dr | C12: 7/30/24 | D12: 12948.13 | E12: 0 | F12: 7768.88 | G12: 0 | H12: 8804.72 | I12: =G12+H12 -> 8804.72 | J12: =D12-I12 -> 4143.41 | K12: 200DB | L12: 5.0
A13: 4 | B13: 7-Building-2202 Northview Dr | C13: 7/30/24 | D13: 246474.74 | E13: 0 | F13: 0 | G13: 0 | H13: 4107.9 | I13: =G13+H13 -> 4107.9 | J13: =D13-I13 -> 242366.84 | K13: S/L | L13: 27.5
A14: 5 | B14: 8-Northiew Dr | C14: 7/30/24 | D14: 31803.19 | E14: 0 | F14: 19081.91 | G14: 0 | H14: 19505.96 | I14: =G14+H14 -> 19505.96 | J14: =D14-I14 -> 12297.23 | K14: 150DB | L14: 15.0
A15: 6 | B15: 9-Northview Dr | C15: 7/30/24 | D15: 59631 | E15: 0 | F15: 35778.6 | G15: 0 | H15: 40549.09 | I15: =G15+H15 -> 40549.09 | J15: =D15-I15 -> 19081.91 | K15: 200DB | L15: 5.0
B16: Grand Total | D16: =SUM(D10:D15) -> 411281.62 | E16: =SUM(E10:E15) -> 0 | F16: =SUM(F10:F15) -> 66772.78 | G16: =SUM(G10:G15) -> 0 | H16: =SUM(H10:H15) -> 78095.16 | I16: =SUM(I10:I15) -> 78095.16 | J16: =SUM(J10:J15) -> 333186.46
A18: After Cost Segregation Correction
A19: Asset | B19: Property Description | C19: Date In Service | D19: Cost | E19: Sec 179 Exp | F19: Bonus Amt | G19: Tax Prior Depreciation | H19: Tax Current Depreciation | I19: End Depreciation | J19: Net Book Value | K19: Method | L19: Period
A20: 1 | B20: 2-Building-712 Northfield Dr - 5 Year | C20: 7/30/24 | D20: 9996.83 | E20: 0 | F20: 5998.1 | G20: 0 | H20: 6797.85 | I20: =G20+H20 -> 6797.85 | J20: =D20-I20 -> 3198.98 | K20: 200DB | L20: 5.0
A21: 2 | B21: 2-Building-712 Northfield Dr - 27.5 Year | C21: 7/30/24 | D21: 43522.08 | E21: 0 | F21: 0 | G21: 0 | H21: 725.37 | I21: =G21+H21 -> 725.37 | J21: =D21-I21 -> 42796.71 | K21: S/L | L21: 27.5
A22: 3 | B22: 3-Northfield Dr - 5 Year | C22: 7/30/24 | D22: 1289.91 | E22: 0 | F22: 773.95 | G22: 0 | H22: 877.14 | I22: =G22+H22 -> 877.14 | J22: =D22-I22 -> 412.77 | K22: 200DB | L22: 5.0
A23: 4 | B23: 3-Northfield Dr - 27.5 Year | C23: 7/30/24 | D23: 5615.74 | E23: 0 | F23: 0 | G23: 0 | H23: 93.6 | I23: =G23+H23 -> 93.6 | J23: =D23-I23 -> 5522.14 | K23: S/L | L23: 27.5
A24: 5 | B24: 4-Northfield Dr - 5 Year | C24: 7/30/24 | D24: 2418.59 | E24: 0 | F24: 1451.15 | G24: 0 | H24: 1644.64 | I24: =G24+H24 -> 1644.64 | J24: =D24-I24 -> 773.95 | K24: 200DB | L24: 5.0
A25: 6 | B25: 4-Northfield Dr - 27.5 Year | C25: 7/30/24 | D25: 10529.54 | E25: 0 | F25: 0 | G25: 0 | H25: 175.49 | I25: =G25+H25 -> 175.49 | J25: =D25-I25 -> 10354.05 | K25: S/L | L25: 27.5
A26: 7 | B26: 7-Building-2202 Northview Dr - 5 Year | C26: 7/30/24 | D26: 46039.18 | E26: 0 | F26: 27623.51 | G26: 0 | H26: 31306.64 | I26: =G26+H26 -> 31306.64 | J26: =D26-I26 -> 14732.54 | K26: 200DB | L26: 5.0
A27: 8 | B27: 7-Building-2202 Northview Dr - 27.5 Year | C27: 7/30/24 | D27: 200435.56 | E27: 0 | F27: 0 | G27: 0 | H27: 3340.59 | I27: =G27+H27 -> 3340.59 | J27: =D27-I27 -> 197094.97 | K27: S/L | L27: 27.5
A28: 9 | B28: 8-Northiew Dr - 5 Year | C28: 7/30/24 | D28: 5940.54 | E28: 0 | F28: 3564.32 | G28: 0 | H28: 4039.56 | I28: =G28+H28 -> 4039.56 | J28: =D28-I28 -> 1900.98 | K28: 200DB | L28: 5.0
A29: 10 | B29: 8-Northiew Dr - 27.5 Year | C29: 7/30/24 | D29: 25862.65 | E29: 0 | F29: 0 | G29: 0 | H29: 431.04 | I29: =G29+H29 -> 431.04 | J29: =D29-I29 -> 25431.61 | K29: S/L | L29: 27.5
A30: 11 | B30: 9-Northview Dr - 5 Year | C30: 7/30/24 | D30: 11138.51 | E30: 0 | F30: 6683.11 | G30: 0 | H30: 7574.19 | I30: =G30+H30 -> 7574.19 | J30: =D30-I30 -> 3564.32 | K30: 200DB | L30: 5.0
A31: 12 | B31: 9-Northview Dr - 27.5 Year | C31: 7/30/24 | D31: 48492.49 | E31: 0 | F31: 0 | G31: 0 | H31: 808.21 | I31: =G31+H31 -> 808.21 | J31: =D31-I31 -> 47684.28 | K31: S/L | L31: 27.5
B32: Grand Total | D32: =SUM(D20:D31) -> 411281.62 | E32: =SUM(E20:E31) -> 0 | F32: =SUM(F20:F31) -> 46094.14 | G32: =SUM(G20:G31) -> 0 | H32: =SUM(H20:H31) -> 57814.32 | I32: =SUM(I20:I31) -> 57814.32 | J32: =SUM(J20:J31) -> 353467.3
B34: Section 481(a) Adjustment — Regular Tax
B35: Depreciation reported previously | D35: =I16 -> 78095.16
B36: Cost Segregation Corrected Depreciation | D36: =I32 -> 57814.32
B37: Section 481(a) Adjustment — Regular Tax | D37: =D35-D36 -> 20280.84
A39: CALCULATION OF §481(a) ADJUSTMENT — AMT
A40: As Previously Filed — AMT
A41: Asset | B41: Property Description | C41: Date In Service | D41: Cost | E41: Sec 179 Exp | F41: Bonus Amt | G41: AMT Prior Depreciation | H41: AMT Current Depreciation | I41: End Depreciation | J41: Net Book Value | K41: Method | L41: Period
A42: 1 | B42: 2-Building-712 Northfield Dr | C42: 7/30/24 | D42: 53518.91 | E42: 0 | F42: 0 | G42: 0 | H42: 892 | I42: =G42+H42 -> 892 | J42: =D42-I42 -> 52626.91 | K42: S/L | L42: 27.5
A43: 2 | B43: 3-Northfield Dr | C43: 7/30/24 | D43: 6905.65 | E43: 0 | F43: 4143.39 | G43: 0 | H43: 4235.49 | I43: =G43+H43 -> 4235.49 | J43: =D43-I43 -> 2670.16 | K43: 150DB | L43: 15.0
A44: 3 | B44: 4-Northfield Dr | C44: 7/30/24 | D44: 12948.13 | E44: 0 | F44: 7768.88 | G44: 0 | H44: 8804.72 | I44: =G44+H44 -> 8804.72 | J44: =D44-I44 -> 4143.41 | K44: 200DB | L44: 5.0
A45: 4 | B45: 7-Building-2202 Northview Dr | C45: 7/30/24 | D45: 246474.74 | E45: 0 | F45: 0 | G45: 0 | H45: 4107.9 | I45: =G45+H45 -> 4107.9 | J45: =D45-I45 -> 242366.84 | K45: S/L | L45: 27.5
A46: 5 | B46: 8-Northiew Dr | C46: 7/30/24 | D46: 31803.19 | E46: 0 | F46: 19081.91 | G46: 0 | H46: 19505.96 | I46: =G46+H46 -> 19505.96 | J46: =D46-I46 -> 12297.23 | K46: 150DB | L46: 15.0
A47: 6 | B47: 9-Northview Dr | C47: 7/30/24 | D47: 59631 | E47: 0 | F47: 35778.6 | G47: 0 | H47: 40549.09 | I47: =G47+H47 -> 40549.09 | J47: =D47-I47 -> 19081.91 | K47: 200DB | L47: 5.0
B48: Grand Total | D48: =SUM(D42:D47) -> 411281.62 | E48: =SUM(E42:E47) -> 0 | F48: =SUM(F42:F47) -> 66772.78 | G48: =SUM(G42:G47) -> 0 | H48: =SUM(H42:H47) -> 78095.16 | I48: =SUM(I42:I47) -> 78095.16 | J48: =SUM(J42:J47) -> 333186.46
A50: After Cost Segregation Correction — AMT
A51: Asset | B51: Property Description | C51: Date In Service | D51: Cost | E51: Sec 179 Exp | F51: Bonus Amt | G51: AMT Prior Depreciation | H51: AMT Current Depreciation | I51: End Depreciation | J51: Net Book Value | K51: Method | L51: Period
A52: 1 | B52: 2-Building-712 Northfield Dr - 5 Year | C52: 7/30/24 | D52: 9996.83 | E52: 0 | F52: 5998.1 | G52: 0 | H52: 6797.85 | I52: =G52+H52 -> 6797.85 | J52: =D52-I52 -> 3198.98 | K52: 200DB | L52: 5.0
A53: 2 | B53: 2-Building-712 Northfield Dr - 27.5 Year | C53: 7/30/24 | D53: 43522.08 | E53: 0 | F53: 0 | G53: 0 | H53: 725.37 | I53: =G53+H53 -> 725.37 | J53: =D53-I53 -> 42796.71 | K53: S/L | L53: 27.5
A54: 3 | B54: 3-Northfield Dr - 5 Year | C54: 7/30/24 | D54: 1289.91 | E54: 0 | F54: 773.95 | G54: 0 | H54: 877.14 | I54: =G54+H54 -> 877.14 | J54: =D54-I54 -> 412.77 | K54: 200DB | L54: 5.0
A55: 4 | B55: 3-Northfield Dr - 27.5 Year | C55: 7/30/24 | D55: 5615.74 | E55: 0 | F55: 0 | G55: 0 | H55: 93.6 | I55: =G55+H55 -> 93.6 | J55: =D55-I55 -> 5522.14 | K55: S/L | L55: 27.5
A56: 5 | B56: 4-Northfield Dr - 5 Year | C56: 7/30/24 | D56: 2418.59 | E56: 0 | F56: 1451.15 | G56: 0 | H56: 1644.64 | I56: =G56+H56 -> 1644.64 | J56: =D56-I56 -> 773.95 | K56: 200DB | L56: 5.0
A57: 6 | B57: 4-Northfield Dr - 27.5 Year | C57: 7/30/24 | D57: 10529.54 | E57: 0 | F57: 0 | G57: 0 | H57: 175.49 | I57: =G57+H57 -> 175.49 | J57: =D57-I57 -> 10354.05 | K57: S/L | L57: 27.5
A58: 7 | B58: 7-Building-2202 Northview Dr - 5 Year | C58: 7/30/24 | D58: 46039.18 | E58: 0 | F58: 27623.51 | G58: 0 | H58: 31306.64 | I58: =G58+H58 -> 31306.64 | J58: =D58-I58 -> 14732.54 | K58: 200DB | L58: 5.0
A59: 8 | B59: 7-Building-2202 Northview Dr - 27.5 Year | C59: 7/30/24 | D59: 200435.56 | E59: 0 | F59: 0 | G59: 0 | H59: 3340.59 | I59: =G59+H59 -> 3340.59 | J59: =D59-I59 -> 197094.97 | K59: S/L | L59: 27.5
A60: 9 | B60: 8-Northiew Dr - 5 Year | C60: 7/30/24 | D60: 5940.54 | E60: 0 | F60: 3564.32 | G60: 0 | H60: 4039.56 | I60: =G60+H60 -> 4039.56 | J60: =D60-I60 -> 1900.98 | K60: 200DB | L60: 5.0
A61: 10 | B61: 8-Northiew Dr - 27.5 Year | C61: 7/30/24 | D61: 25862.65 | E61: 0 | F61: 0 | G61: 0 | H61: 431.04 | I61: =G61+H61 -> 431.04 | J61: =D61-I61 -> 25431.61 | K61: S/L | L61: 27.5
A62: 11 | B62: 9-Northview Dr - 5 Year | C62: 7/30/24 | D62: 11138.51 | E62: 0 | F62: 6683.11 | G62: 0 | H62: 7574.19 | I62: =G62+H62 -> 7574.19 | J62: =D62-I62 -> 3564.32 | K62: 200DB | L62: 5.0
A63: 12 | B63: 9-Northview Dr - 27.5 Year | C63: 7/30/24 | D63: 48492.49 | E63: 0 | F63: 0 | G63: 0 | H63: 808.21 | I63: =G63+H63 -> 808.21 | J63: =D63-I63 -> 47684.28 | K63: S/L | L63: 27.5
B64: Grand Total | D64: =SUM(D52:D63) -> 411281.62 | E64: =SUM(E52:E63) -> 0 | F64: =SUM(F52:F63) -> 46094.14 | G64: =SUM(G52:G63) -> 0 | H64: =SUM(H52:H63) -> 57814.32 | I64: =SUM(I52:I63) -> 57814.32 | J64: =SUM(J52:J63) -> 353467.3
B66: Section 481(a) Adjustment — AMT
B67: Depreciation reported previously | D67: =I48 -> 78095.16
B68: Cost Segregation Corrected Depreciation | D68: =I64 -> 57814.32
B69: Section 481(a) Adjustment — AMT | D69: =D67-D68 -> 20280.84
A71: COST SEGREGATION STUDY — COST SUMMARY
B72: Total Building Cost | D72: =D112 -> 411281.62
B73: Building Components: 5 Year | D73: =F112 -> 76823.56
B74: % of Cost | D74: =F113 -> 0.18679065
B75: Building Structure: 27.5 Year | D75: =H112 -> 334458.06
B76: % of Cost | D76: =H113 -> 0.81320935
A78: COST SEGREGATION STUDY — COST DETAIL
B79: Property Category | D79: Cost | F79: 5 Year | H79: 27.5 Year
B80: Building Components
B81: Cabinets / Millwork | D81: =SUM(F81:H81) -> 17269.54 | F81: 17269.54
B82: Moldings | D82: =SUM(F82:H82) -> 5872.52 | F82: 5872.52
B83: Flooring - Carpet | D83: =SUM(F83:H83) -> 1061.02 | F83: 1061.02
B84: Flooring - Wood Laminate | D84: =SUM(F84:H84) -> 24005.05 | F84: 24005.05
B85: Flooring - Seamless Vinyl | D85: =SUM(F85:H85) -> 164.32 | F85: 164.32
B86: Window Treatments | D86: =SUM(F86:H86) -> 5825.84 | F86: 5825.84
B87: Building Signage | D87: =SUM(F87:H87) -> 150.1 | F87: 150.1
B88: Specialty Electrical - Appliances | D88: =SUM(F88:H88) -> 3588.08 | F88: 3588.08
B89: Communication / Data | D89: =SUM(F89:H89) -> 3097.62 | F89: 3097.62
B90: Specialty Plumbing - Kitchen Sinks | D90: =SUM(F90:H90) -> 6563.2 | F90: 6563.2
B91: Security / Exterior Lighting | D91: =SUM(F91:H91) -> 2648.6 | F91: 2648.6
B92: Access Control | D92: =SUM(F92:H92) -> 106.32 | F92: 106.32
... B94: Appliances | D94: =SUM(F94:H94) -> 5662.23 | F94: 5662.23
B95: Building Structure
B96: Roofing Systems | D96: =SUM(F96:H96) -> 19965.05 | H96: 19965.05
B97: Foundations | D97: =SUM(F97:H97) -> 23099.53 | H97: 23099.53
B98: HVAC | D98: =SUM(F98:H98) -> 34868.14 | H98: 34868.14
B99: Electrical | D99: =SUM(F99:H99) -> 37684.26 | H99: 37684.26
B100: Plumbing | D100: =SUM(F100:H100) -> 30310.68 | H100: 30310.68
B101: Fire Protection & Alarm | D101: =SUM(F101:H101) -> 2483.74 | H101: 2483.74
B102: Exterior Façade / Building Skin | D102: =SUM(F102:H102) -> 12802.47 | H102: 12802.47
B103: Doors & Frames | D103: =SUM(F103:H103) -> 21480.24 | H103: 21480.24
B104: Windows | D104: =SUM(F104:H104) -> 11643.15 | H104: 11643.15
B105: Ceiling Systems | D105: =SUM(F105:H105) -> 16037.83 | H105: 16037.83
B106: Interior Framing / Partitions | D106: =SUM(F106:H106) -> 35969.2 | H106: 35969.2
B107: Painting | D107: =SUM(F107:H107) -> 16182.61 | H107: 16182.61
... B111: Bathroom Accessories | D111: =SUM(F111:H111) -> 5500.39 | H111: 5500.39
B112: Total Building Cost | D112: =SUM(D80:D111) -> 411281.62 | F112: =SUM(F80:F111) -> 76823.56 | H112: =SUM(H80:H111) -> 334458.06
...

Sheet Building 7
A1: River Garden Estates Housing LP
A2: River Garden Estates — 2201 Northview Dr & 712 Northfield Dr, Sacramento, CA 95833
A3: EIN: 93-2096487 · FYE: December 31, 2024 · Year of Change: 1/1/2024
A4: Building 7 — Attachment to Form 3115 (DCN #7, Rev. Proc. 2024-23 §6.01)
A5: Source: CSSI Report #107552-43, "#107552-43_River Garden Estates Housing LP_3115_Combined.pdf"
A7: CALCULATION OF §481(a) ADJUSTMENT — REGULAR TAX
A8: As Previously Filed
A9: Asset | B9: Property Description | C9: Date In Service | D9: Cost | E9: Sec 179 Exp | F9: Bonus Amt | G9: Tax Prior Depreciation | H9: Tax Current Depreciation | I9: End Depreciation | J9: Net Book Value | K9: Method | L9: Period
A10: 1 | B10: 2-Building-712 Northfield Dr | C10: 7/30/24 | D10: 34585.09 | E10: 0 | F10: 0 | G10: 0 | H10: 576.43 | I10: =G10+H10 -> 576.43 | J10: =D10-I10 -> 34008.66 | K10: S/L | L10: 27.5
A11: 2 | B11: 3-Northfield Dr | C11: 7/30/24 | D11: 4462.58 | E11: 0 | F11: 2677.55 | G11: 0 | H11: 2737.06 | I11: =G11+H11 -> 2737.06 | J11: =D11-I11 -> 1725.52 | K11: 150DB | L11: 15.0
A12: 3 | B12: 4-Northfield Dr | C12: 7/30/24 | D12: 8367.37 | E12: 0 | F12: 5020.42 | G12: 0 | H12: 5689.81 | I12: =G12+H12 -> 5689.81 | J12: =D12-I12 -> 2677.56 | K12: 200DB | L12: 5.0
A13: 4 | B13: 7-Building-2202 Northview Dr | C13: 7/30/24 | D13: 159277.36 | E13: 0 | F13: 0 | G13: 0 | H13: 2654.62 | I13: =G13+H13 -> 2654.62 | J13: =D13-I13 -> 156622.74 | K13: S/L | L13: 27.5
A14: 5 | B14: 8-Northiew Dr | C14: 7/30/24 | D14: 20551.91 | E14: 0 | F14: 12331.15 | G14: 0 | H14: 12605.17 | I14: =G14+H14 -> 12605.17 | J14: =D14-I14 -> 7946.74 | K14: 150DB | L14: 15.0
A15: 6 | B15: 9-Northview Dr | C15: 7/30/24 | D15: 38534.85 | E15: 0 | F15: 23120.91 | G15: 0 | H15: 26203.7 | I15: =G15+H15 -> 26203.7 | J15: =D15-I15 -> 12331.15 | K15: 200DB | L15: 5.0
B16: Grand Total | D16: =SUM(D10:D15) -> 265779.16 | E16: =SUM(E10:E15) -> 0 | F16: =SUM(F10:F15) -> 43150.03 | G16: =SUM(G10:G15) -> 0 | H16: =SUM(H10:H15) -> 50466.79 | I16: =SUM(I10:I15) -> 50466.79 | J16: =SUM(J10:J15) -> 215312.37
A18: After Cost Segregation Correction
A19: Asset | B19: Property Description | C19: Date In Service | D19: Cost | E19: Sec 179 Exp | F19: Bonus Amt | G19: Tax Prior Depreciation | H19: Tax Current Depreciation | I19: End Depreciation | J19: Net Book Value | K19: Method | L19: Period
A20: 1 | B20: 2-Building-712 Northfield Dr - 5 Year | C20: 7/30/24 | D20: 6299.49 | E20: 0 | F20: 3779.69 | G20: 0 | H20: 4283.65 | I20: =G20+H20 -> 4283.65 | J20: =D20-I20 -> 2015.84 | K20: 200DB | L20: 5.0
A21: 2 | B21: 2-Building-712 Northfield Dr - 27.5 Year | C21: 7/30/24 | D21: 28285.6 | E21: 0 | F21: 0 | G21: 0 | H21: 471.43 | I21: =G21+H21 -> 471.43 | J21: =D21-I21 -> 27814.17 | K21: S/L | L21: 27.5
A22: 3 | B22: 3-Northfield Dr - 5 Year | C22: 7/30/24 | D22: 812.84 | E22: 0 | F22: 487.7 | G22: 0 | H22: 552.73 | I22: =G22+H22 -> 552.73 | J22: =D22-I22 -> 260.11 | K22: 200DB | L22: 5.0
A23: 4 | B23: 3-Northfield Dr - 27.5 Year | C23: 7/30/24 | D23: 3649.74 | E23: 0 | F23: 0 | G23: 0 | H23: 60.83 | I23: =G23+H23 -> 60.83 | J23: =D23-I23 -> 3588.91 | K23: S/L | L23: 27.5
A24: 5 | B24: 4-Northfield Dr - 5 Year | C24: 7/30/24 | D24: 1524.07 | E24: 0 | F24: 914.44 | G24: 0 | H24: 1036.37 | I24: =G24+H24 -> 1036.37 | J24: =D24-I24 -> 487.7 | K24: 200DB | L24: 5.0
A25: 6 | B25: 4-Northfield Dr - 27.5 Year | C25: 7/30/24 | D25: 6843.3 | E25: 0 | F25: 0 | G25: 0 | H25: 114.06 | I25: =G25+H25 -> 114.06 | J25: =D25-I25 -> 6729.24 | K25: S/L | L25: 27.5
A26: 7 | B26: 7-Building-2202 Northview Dr - 5 Year | C26: 7/30/24 | D26: 29011.54 | E26: 0 | F26: 17406.92 | G26: 0 | H26: 19727.84 | I26: =G26+H26 -> 19727.84 | J26: =D26-I26 -> 9283.7 | K26: 200DB | L26: 5.0
A27: 8 | B27: 7-Building-2202 Northview Dr - 27.5 Year | C27: 7/30/24 | D27: 130265.82 | E27: 0 | F27: 0 | G27: 0 | H27: 2171.1 | I27: =G27+H27 -> 2171.1 | J27: =D27-I27 -> 128094.72 | K27: S/L | L27: 27.5
A28: 9 | B28: 8-Northiew Dr - 5 Year | C28: 7/30/24 | D28: 3743.42 | E28: 0 | F28: 2246.05 | G28: 0 | H28: 2545.52 | I28: =G28+H28 -> 2545.52 | J28: =D28-I28 -> 1197.9 | K28: 200DB | L28: 5.0
A29: 10 | B29: 8-Northiew Dr - 27.5 Year | C29: 7/30/24 | D29: 16808.49 | E29: 0 | F29: 0 | G29: 0 | H29: 280.14 | I29: =G29+H29 -> 280.14 | J29: =D29-I29 -> 16528.35 | K29: S/L | L29: 27.5
A30: 11 | B30: 9-Northview Dr - 5 Year | C30: 7/30/24 | D30: 7018.93 | E30: 0 | F30: 4211.36 | G30: 0 | H30: 4772.87 | I30: =G30+H30 -> 4772.87 | J30: =D30-I30 -> 2246.06 | K30: 200DB | L30: 5.0
A31: 12 | B31: 9-Northview Dr - 27.5 Year | C31: 7/30/24 | D31: 31515.92 | E31: 0 | F31: 0 | G31: 0 | H31: 525.27 | I31: =G31+H31 -> 525.27 | J31: =D31-I31 -> 30990.65 | K31: S/L | L31: 27.5
B32: Grand Total | D32: =SUM(D20:D31) -> 265779.16 | E32: =SUM(E20:E31) -> 0 | F32: =SUM(F20:F31) -> 29046.16 | G32: =SUM(G20:G31) -> 0 | H32: =SUM(H20:H31) -> 36541.81 | I32: =SUM(I20:I31) -> 36541.81 | J32: =SUM(J20:J31) -> 229237.35
B34: Section 481(a) Adjustment — Regular Tax
B35: Depreciation reported previously | D35: =I16 -> 50466.79
B36: Cost Segregation Corrected Depreciation | D36: =I32 -> 36541.81
B37: Section 481(a) Adjustment — Regular Tax | D37: =D35-D36 -> 13924.98
A39: CALCULATION OF §481(a) ADJUSTMENT — AMT
A40: As Previously Filed — AMT
A41: Asset | B41: Property Description | C41: Date In Service | D41: Cost | E41: Sec 179 Exp | F41: Bonus Amt | G41: AMT Prior Depreciation | H41: AMT Current Depreciation | I41: End Depreciation | J41: Net Book Value | K41: Method | L41: Period
A42: 1 | B42: 2-Building-712 Northfield Dr | C42: 7/30/24 | D42: 34585.09 | E42: 0 | F42: 0 | G42: 0 | H42: 576.43 | I42: =G42+H42 -> 576.43 | J42: =D42-I42 -> 34008.66 | K42: S/L | L42: 27.5
A43: 2 | B43: 3-Northfield Dr | C43: 7/30/24 | D43: 4462.58 | E43: 0 | F43: 2677.55 | G43: 0 | H43: 2737.06 | I43: =G43+H43 -> 2737.06 | J43: =D43-I43 -> 1725.52 | K43: 150DB | L43: 15.0
A44: 3 | B44: 4-Northfield Dr | C44: 7/30/24 | D44: 8367.37 | E44: 0 | F44: 5020.42 | G44: 0 | H44: 5689.81 | I44: =G44+H44 -> 5689.81 | J44: =D44-I44 -> 2677.56 | K44: 200DB | L44: 5.0
A45: 4 | B45: 7-Building-2202 Northview Dr | C45: 7/30/24 | D45: 159277.36 | E45: 0 | F45: 0 | G45: 0 | H45: 2654.62 | I45: =G45+H45 -> 2654.62 | J45: =D45-I45 -> 156622.74 | K45: S/L | L45: 27.5
A46: 5 | B46: 8-Northiew Dr | C46: 7/30/24 | D46: 20551.91 | E46: 0 | F46: 12331.15 | G46: 0 | H46: 12605.17 | I46: =G46+H46 -> 12605.17 | J46: =D46-I46 -> 7946.74 | K46: 150DB | L46: 15.0
A47: 6 | B47: 9-Northview Dr | C47: 7/30/24 | D47: 38534.85 | E47: 0 | F47: 23120.91 | G47: 0 | H47: 26203.7 | I47: =G47+H47 -> 26203.7 | J47: =D47-I47 -> 12331.15 | K47: 200DB | L47: 5.0
B48: Grand Total | D48: =SUM(D42:D47) -> 265779.16 | E48: =SUM(E42:E47) -> 0 | F48: =SUM(F42:F47) -> 43150.03 | G48: =SUM(G42:G47) -> 0 | H48: =SUM(H42:H47) -> 50466.79 | I48: =SUM(I42:I47) -> 50466.79 | J48: =SUM(J42:J47) -> 215312.37
A50: After Cost Segregation Correction — AMT
A51: Asset | B51: Property Description | C51: Date In Service | D51: Cost | E51: Sec 179 Exp | F51: Bonus Amt | G51: AMT Prior Depreciation | H51: AMT Current Depreciation | I51: End Depreciation | J51: Net Book Value | K51: Method | L51: Period
A52: 1 | B52: 2-Building-712 Northfield Dr - 5 Year | C52: 7/30/24 | D52: 6299.49 | E52: 0 | F52: 3779.69 | G52: 0 | H52: 4283.65 | I52: =G52+H52 -> 4283.65 | J52: =D52-I52 -> 2015.84 | K52: 200DB | L52: 5.0
A53: 2 | B53: 2-Building-712 Northfield Dr - 27.5 Year | C53: 7/30/24 | D53: 28285.6 | E53: 0 | F53: 0 | G53: 0 | H53: 471.43 | I53: =G53+H53 -> 471.43 | J53: =D53-I53 -> 27814.17 | K53: S/L | L53: 27.5
A54: 3 | B54: 3-Northfield Dr - 5 Year | C54: 7/30/24 | D54: 812.84 | E54: 0 | F54: 487.7 | G54: 0 | H54: 552.73 | I54: =G54+H54 -> 552.73 | J54: =D54-I54 -> 260.11 | K54: 200DB | L54: 5.0
A55: 4 | B55: 3-Northfield Dr - 27.5 Year | C55: 7/30/24 | D55: 3649.74 | E55: 0 | F55: 0 | G55: 0 | H55: 60.83 | I55: =G55+H55 -> 60.83 | J55: =D55-I55 -> 3588.91 | K55: S/L | L55: 27.5
A56: 5 | B56: 4-Northfield Dr - 5 Year | C56: 7/30/24 | D56: 1524.07 | E56: 0 | F56: 914.44 | G56: 0 | H56: 1036.37 | I56: =G56+H56 -> 1036.37 | J56: =D56-I56 -> 487.7 | K56: 200DB | L56: 5.0
A57: 6 | B57: 4-Northfield Dr - 27.5 Year | C57: 7/30/24 | D57: 6843.3 | E57: 0 | F57: 0 | G57: 0 | H57: 114.06 | I57: =G57+H57 -> 114.06 | J57: =D57-I57 -> 6729.24 | K57: S/L | L57: 27.5
A58: 7 | B58: 7-Building-2202 Northview Dr - 5 Year | C58: 7/30/24 | D58: 29011.54 | E58: 0 | F58: 17406.92 | G58: 0 | H58: 19727.84 | I58: =G58+H58 -> 19727.84 | J58: =D58-I58 -> 9283.7 | K58: 200DB | L58: 5.0
A59: 8 | B59: 7-Building-2202 Northview Dr - 27.5 Year | C59: 7/30/24 | D59: 130265.82 | E59: 0 | F59: 0 | G59: 0 | H59: 2171.1 | I59: =G59+H59 -> 2171.1 | J59: =D59-I59 -> 128094.72 | K59: S/L | L59: 27.5
A60: 9 | B60: 8-Northiew Dr - 5 Year | C60: 7/30/24 | D60: 3743.42 | E60: 0 | F60: 2246.05 | G60: 0 | H60: 2545.52 | I60: =G60+H60 -> 2545.52 | J60: =D60-I60 -> 1197.9 | K60: 200DB | L60: 5.0
A61: 10 | B61: 8-Northiew Dr - 27.5 Year | C61: 7/30/24 | D61: 16808.49 | E61: 0 | F61: 0 | G61: 0 | H61: 280.14 | I61: =G61+H61 -> 280.14 | J61: =D61-I61 -> 16528.35 | K61: S/L | L61: 27.5
A62: 11 | B62: 9-Northview Dr - 5 Year | C62: 7/30/24 | D62: 7018.93 | E62: 0 | F62: 4211.36 | G62: 0 | H62: 4772.87 | I62: =G62+H62 -> 4772.87 | J62: =D62-I62 -> 2246.06 | K62: 200DB | L62: 5.0
A63: 12 | B63: 9-Northview Dr - 27.5 Year | C63: 7/30/24 | D63: 31515.92 | E63: 0 | F63: 0 | G63: 0 | H63: 525.27 | I63: =G63+H63 -> 525.27 | J63: =D63-I63 -> 30990.65 | K63: S/L | L63: 27.5
B64: Grand Total | D64: =SUM(D52:D63) -> 265779.16 | E64: =SUM(E52:E63) -> 0 | F64: =SUM(F52:F63) -> 29046.16 | G64: =SUM(G52:G63) -> 0 | H64: =SUM(H52:H63) -> 36541.81 | I64: =SUM(I52:I63) -> 36541.81 | J64: =SUM(J52:J63) -> 229237.35
B66: Section 481(a) Adjustment — AMT
B67: Depreciation reported previously | D67: =I48 -> 50466.79
B68: Cost Segregation Corrected Depreciation | D68: =I64 -> 36541.81
B69: Section 481(a) Adjustment — AMT | D69: =D67-D68 -> 13924.98
A71: COST SEGREGATION STUDY — COST SUMMARY
B72: Total Building Cost | D72: =D110 -> 265779.16
B73: Building Components: 5 Year | D73: =F110 -> 48410.29
B74: % of Cost | D74: =F111 -> 0.18214479
B75: Building Structure: 27.5 Year | D75: =H110 -> 217368.87
B76: % of Cost | D76: =H111 -> 0.81785521
A78: COST SEGREGATION STUDY — COST DETAIL
B79: Property Category | D79: Cost | F79: 5 Year | H79: 27.5 Year
B80: Building Components
B81: Cabinets / Millwork | D81: =SUM(F81:H81) -> 10896.11 | F81: 10896.11
B82: Moldings | D82: =SUM(F82:H82) -> 4110.75 | F82: 4110.75
B83: Flooring - Wood Laminate | D83: =SUM(F83:H83) -> 15651.6 | F83: 15651.6
B84: Window Treatments | D84: =SUM(F84:H84) -> 3613.14 | F84: 3613.14
B85: Building Signage | D85: =SUM(F85:H85) -> 105.28 | F85: 105.28
B86: Specialty Electrical - Appliances | D86: =SUM(F86:H86) -> 2242.57 | F86: 2242.57
B87: Communication / Data | D87: =SUM(F87:H87) -> 1932.23 | F87: 1932.23
B88: Specialty Plumbing - Kitchen Sinks | D88: =SUM(F88:H88) -> 4101.99 | F88: 4101.99
B89: Security / Exterior Lighting | D89: =SUM(F89:H89) -> 1746.74 | F89: 1746.74
B90: Access Control | D90: =SUM(F90:H90) -> 66.45 | F90: 66.45
B91: Entry Canopies | D91: =SUM(F91:H91) -> 404.54 | F91: 404.54
B92: Appliances | D92: =SUM(F92:H92) -> 3538.89 | F92: 3538.89
B93: Building Structure
B94: Roofing Systems | D94: =SUM(F94:H94) -> 12887.37 | H94: 12887.37
B95: Foundations | D95: =SUM(F95:H95) -> 14646.87 | H95: 14646.87
B96: HVAC | D96: =SUM(F96:H96) -> 21749.99 | H96: 21749.99
B97: Electrical | D97: =SUM(F97:H97) -> 23506.63 | H97: 23506.63
B98: Plumbing | D98: =SUM(F98:H98) -> 18907.15 | H98: 18907.15
B99: Fire Protection & Alarm | D99: =SUM(F99:H99) -> 1701.46 | H99: 1701.46
B100: Exterior Façade / Building Skin | D100: =SUM(F100:H100) -> 9148.73 | H100: 9148.73
B101: Doors & Frames | D101: =SUM(F101:H101) -> 14572.68 | H101: 14572.68
B102: Windows | D102: =SUM(F102:H102) -> 7194.27 | H102: 7194.27
B103: Ceiling Systems | D103: =SUM(F103:H103) -> 10004.05 | H103: 10004.05
B104: Interior Framing / Partitions | D104: =SUM(F104:H104) -> 25350.08 | H104: 25350.08
B105: Painting | D105: =SUM(F105:H105) -> 11072.6 | H105: 11072.6
... B109: Bathroom Accessories | D109: =SUM(F109:H109) -> 3697.16 | H109: 3697.16
B110: Total Building Cost | D110: =SUM(D80:D109) -> 265779.16 | F110: =SUM(F80:F109) -> 48410.29 | H110: =SUM(H80:H109) -> 217368.87
B111: % of Cost | F111: =F110/D110 -> 0.18214479 | H111: =H110/D110 -> 0.81785521
...

Sheet Building 8
A1: River Garden Estates Housing LP
A2: River Garden Estates — 2201 Northview Dr & 712 Northfield Dr, Sacramento, CA 95833
A3: EIN: 93-2096487 · FYE: December 31, 2024 · Year of Change: 1/1/2024
A4: Building 8 — Attachment to Form 3115 (DCN #7, Rev. Proc. 2024-23 §6.01)
A5: Source: CSSI Report #107552-43, "#107552-43_River Garden Estates Housing LP_3115_Combined.pdf"
A7: CALCULATION OF §481(a) ADJUSTMENT — REGULAR TAX
A8: As Previously Filed
A9: Asset | B9: Property Description | C9: Date In Service | D9: Cost | E9: Sec 179 Exp | F9: Bonus Amt | G9: Tax Prior Depreciation | H9: Tax Current Depreciation | I9: End Depreciation | J9: Net Book Value | K9: Method | L9: Period
A10: 1 | B10: 2-Building-712 Northfield Dr | C10: 7/30/24 | D10: 46450.25 | E10: 0 | F10: 0 | G10: 0 | H10: 774.18 | I10: =G10+H10 -> 774.18 | J10: =D10-I10 -> 45676.07 | K10: S/L | L10: 27.5
A11: 2 | B11: 3-Northfield Dr | C11: 7/30/24 | D11: 5993.57 | E11: 0 | F11: 3596.14 | G11: 0 | H11: 3676.08 | I11: =G11+H11 -> 3676.08 | J11: =D11-I11 -> 2317.49 | K11: 150DB | L11: 15.0
A12: 3 | B12: 4-Northfield Dr | C12: 7/30/24 | D12: 11237.98 | E12: 0 | F12: 6742.79 | G12: 0 | H12: 7641.82 | I12: =G12+H12 -> 7641.82 | J12: =D12-I12 -> 3596.16 | K12: 200DB | L12: 5.0
A13: 4 | B13: 7-Building-2202 Northview Dr | C13: 7/30/24 | D13: 213920.95 | E13: 0 | F13: 0 | G13: 0 | H13: 3565.34 | I13: =G13+H13 -> 3565.34 | J13: =D13-I13 -> 210355.61 | K13: S/L | L13: 27.5
A14: 5 | B14: 8-Northiew Dr | C14: 7/30/24 | D14: 27602.7 | E14: 0 | F14: 16561.62 | G14: 0 | H14: 16929.66 | I14: =G14+H14 -> 16929.66 | J14: =D14-I14 -> 10673.04 | K14: 150DB | L14: 15.0
A15: 6 | B15: 9-Northview Dr | C15: 7/30/24 | D15: 51755.08 | E15: 0 | F15: 31053.05 | G15: 0 | H15: 35193.46 | I15: =G15+H15 -> 35193.46 | J15: =D15-I15 -> 16561.62 | K15: 200DB | L15: 5.0
B16: Grand Total | D16: =SUM(D10:D15) -> 356960.53 | E16: =SUM(E10:E15) -> 0 | F16: =SUM(F10:F15) -> 57953.6 | G16: =SUM(G10:G15) -> 0 | H16: =SUM(H10:H15) -> 67780.54 | I16: =SUM(I10:I15) -> 67780.54 | J16: =SUM(J10:J15) -> 289179.99
A18: After Cost Segregation Correction
A19: Asset | B19: Property Description | C19: Date In Service | D19: Cost | E19: Sec 179 Exp | F19: Bonus Amt | G19: Tax Prior Depreciation | H19: Tax Current Depreciation | I19: End Depreciation | J19: Net Book Value | K19: Method | L19: Period
A20: 1 | B20: 2-Building-712 Northfield Dr - 5 Year | C20: 7/30/24 | D20: 8679.19 | E20: 0 | F20: 5207.51 | G20: 0 | H20: 5901.85 | I20: =G20+H20 -> 5901.85 | J20: =D20-I20 -> 2777.34 | K20: 200DB | L20: 5.0
A21: 2 | B21: 2-Building-712 Northfield Dr - 27.5 Year | C21: 7/30/24 | D21: 37771.06 | E21: 0 | F21: 0 | G21: 0 | H21: 629.52 | I21: =G21+H21 -> 629.52 | J21: =D21-I21 -> 37141.54 | K21: S/L | L21: 27.5
A22: 3 | B22: 3-Northfield Dr - 5 Year | C22: 7/30/24 | D22: 1119.89 | E22: 0 | F22: 671.93 | G22: 0 | H22: 761.52 | I22: =G22+H22 -> 761.52 | J22: =D22-I22 -> 358.37 | K22: 200DB | L22: 5.0
A23: 4 | B23: 3-Northfield Dr - 27.5 Year | C23: 7/30/24 | D23: 4873.68 | E23: 0 | F23: 0 | G23: 0 | H23: 81.23 | I23: =G23+H23 -> 81.23 | J23: =D23-I23 -> 4792.45 | K23: S/L | L23: 27.5
A24: 5 | B24: 4-Northfield Dr - 5 Year | C24: 7/30/24 | D24: 2099.81 | E24: 0 | F24: 1259.89 | G24: 0 | H24: 1427.87 | I24: =G24+H24 -> 1427.87 | J24: =D24-I24 -> 671.94 | K24: 200DB | L24: 5.0
A25: 6 | B25: 4-Northfield Dr - 27.5 Year | C25: 7/30/24 | D25: 9138.17 | E25: 0 | F25: 0 | G25: 0 | H25: 152.3 | I25: =G25+H25 -> 152.3 | J25: =D25-I25 -> 8985.87 | K25: S/L | L25: 27.5
A26: 7 | B26: 7-Building-2202 Northview Dr - 5 Year | C26: 7/30/24 | D26: 39970.95 | E26: 0 | F26: 23982.57 | G26: 0 | H26: 27180.25 | I26: =G26+H26 -> 27180.25 | J26: =D26-I26 -> 12790.7 | K26: 200DB | L26: 5.0
A27: 8 | B27: 7-Building-2202 Northview Dr - 27.5 Year | C27: 7/30/24 | D27: 173950 | E27: 0 | F27: 0 | G27: 0 | H27: 2899.17 | I27: =G27+H27 -> 2899.17 | J27: =D27-I27 -> 171050.83 | K27: S/L | L27: 27.5
A28: 9 | B28: 8-Northiew Dr - 5 Year | C28: 7/30/24 | D28: 5157.54 | E28: 0 | F28: 3094.52 | G28: 0 | H28: 3507.12 | I28: =G28+H28 -> 3507.12 | J28: =D28-I28 -> 1650.42 | K28: 200DB | L28: 5.0
A29: 10 | B29: 8-Northiew Dr - 27.5 Year | C29: 7/30/24 | D29: 22445.16 | E29: 0 | F29: 0 | G29: 0 | H29: 374.09 | I29: =G29+H29 -> 374.09 | J29: =D29-I29 -> 22071.07 | K29: S/L | L29: 27.5
A30: 11 | B30: 9-Northview Dr - 5 Year | C30: 7/30/24 | D30: 9670.4 | E30: 0 | F30: 5802.24 | G30: 0 | H30: 6575.87 | I30: =G30+H30 -> 6575.87 | J30: =D30-I30 -> 3094.53 | K30: 200DB | L30: 5.0
A31: 12 | B31: 9-Northview Dr - 27.5 Year | C31: 7/30/24 | D31: 42084.68 | E31: 0 | F31: 0 | G31: 0 | H31: 701.41 | I31: =G31+H31 -> 701.41 | J31: =D31-I31 -> 41383.27 | K31: S/L | L31: 27.5
B32: Grand Total | D32: =SUM(D20:D31) -> 356960.53 | E32: =SUM(E20:E31) -> 0 | F32: =SUM(F20:F31) -> 40018.66 | G32: =SUM(G20:G31) -> 0 | H32: =SUM(H20:H31) -> 50192.2 | I32: =SUM(I20:I31) -> 50192.2 | J32: =SUM(J20:J31) -> 306768.33
B34: Section 481(a) Adjustment — Regular Tax
B35: Depreciation reported previously | D35: =I16 -> 67780.54
B36: Cost Segregation Corrected Depreciation | D36: =I32 -> 50192.2
B37: Section 481(a) Adjustment — Regular Tax | D37: =D35-D36 -> 17588.34
A39: CALCULATION OF §481(a) ADJUSTMENT — AMT
A40: As Previously Filed — AMT
A41: Asset | B41: Property Description | C41: Date In Service | D41: Cost | E41: Sec 179 Exp | F41: Bonus Amt | G41: AMT Prior Depreciation | H41: AMT Current Depreciation | I41: End Depreciation | J41: Net Book Value | K41: Method | L41: Period
A42: 1 | B42: 2-Building-712 Northfield Dr | C42: 7/30/24 | D42: 46450.25 | E42: 0 | F42: 0 | G42: 0 | H42: 774.18 | I42: =G42+H42 -> 774.18 | J42: =D42-I42 -> 45676.07 | K42: S/L | L42: 27.5
A43: 2 | B43: 3-Northfield Dr | C43: 7/30/24 | D43: 5993.57 | E43: 0 | F43: 3596.14 | G43: 0 | H43: 3676.08 | I43: =G43+H43 -> 3676.08 | J43: =D43-I43 -> 2317.49 | K43: 150DB | L43: 15.0
A44: 3 | B44: 4-Northfield Dr | C44: 7/30/24 | D44: 11237.98 | E44: 0 | F44: 6742.79 | G44: 0 | H44: 7641.82 | I44: =G44+H44 -> 7641.82 | J44: =D44-I44 -> 3596.16 | K44: 200DB | L44: 5.0
A45: 4 | B45: 7-Building-2202 Northview Dr | C45: 7/30/24 | D45: 213920.95 | E45: 0 | F45: 0 | G45: 0 | H45: 3565.34 | I45: =G45+H45 -> 3565.34 | J45: =D45-I45 -> 210355.61 | K45: S/L | L45: 27.5
A46: 5 | B46: 8-Northiew Dr | C46: 7/30/24 | D46: 27602.7 | E46: 0 | F46: 16561.62 | G46: 0 | H46: 16929.66 | I46: =G46+H46 -> 16929.66 | J46: =D46-I46 -> 10673.04 | K46: 150DB | L46: 15.0
A47: 6 | B47: 9-Northview Dr | C47: 7/30/24 | D47: 51755.08 | E47: 0 | F47: 31053.05 | G47: 0 | H47: 35193.46 | I47: =G47+H47 -> 35193.46 | J47: =D47-I47 -> 16561.62 | K47: 200DB | L47: 5.0
B48: Grand Total | D48: =SUM(D42:D47) -> 356960.53 | E48: =SUM(E42:E47) -> 0 | F48: =SUM(F42:F47) -> 57953.6 | G48: =SUM(G42:G47) -> 0 | H48: =SUM(H42:H47) -> 67780.54 | I48: =SUM(I42:I47) -> 67780.54 | J48: =SUM(J42:J47) -> 289179.99
A50: After Cost Segregation Correction — AMT
A51: Asset | B51: Property Description | C51: Date In Service | D51: Cost | E51: Sec 179 Exp | F51: Bonus Amt | G51: AMT Prior Depreciation | H51: AMT Current Depreciation | I51: End Depreciation | J51: Net Book Value | K51: Method | L51: Period
A52: 1 | B52: 2-Building-712 Northfield Dr - 5 Year | C52: 7/30/24 | D52: 8679.19 | E52: 0 | F52: 5207.51 | G52: 0 | H52: 5901.85 | I52: =G52+H52 -> 5901.85 | J52: =D52-I52 -> 2777.34 | K52: 200DB | L52: 5.0
A53: 2 | B53: 2-Building-712 Northfield Dr - 27.5 Year | C53: 7/30/24 | D53: 37771.06 | E53: 0 | F53: 0 | G53: 0 | H53: 629.52 | I53: =G53+H53 -> 629.52 | J53: =D53-I53 -> 37141.54 | K53: S/L | L53: 27.5
A54: 3 | B54: 3-Northfield Dr - 5 Year | C54: 7/30/24 | D54: 1119.89 | E54: 0 | F54: 671.93 | G54: 0 | H54: 761.52 | I54: =G54+H54 -> 761.52 | J54: =D54-I54 -> 358.37 | K54: 200DB | L54: 5.0
A55: 4 | B55: 3-Northfield Dr - 27.5 Year | C55: 7/30/24 | D55: 4873.68 | E55: 0 | F55: 0 | G55: 0 | H55: 81.23 | I55: =G55+H55 -> 81.23 | J55: =D55-I55 -> 4792.45 | K55: S/L | L55: 27.5
A56: 5 | B56: 4-Northfield Dr - 5 Year | C56: 7/30/24 | D56: 2099.81 | E56: 0 | F56: 1259.89 | G56: 0 | H56: 1427.87 | I56: =G56+H56 -> 1427.87 | J56: =D56-I56 -> 671.94 | K56: 200DB | L56: 5.0
A57: 6 | B57: 4-Northfield Dr - 27.5 Year | C57: 7/30/24 | D57: 9138.17 | E57: 0 | F57: 0 | G57: 0 | H57: 152.3 | I57: =G57+H57 -> 152.3 | J57: =D57-I57 -> 8985.87 | K57: S/L | L57: 27.5
A58: 7 | B58: 7-Building-2202 Northview Dr - 5 Year | C58: 7/30/24 | D58: 39970.95 | E58: 0 | F58: 23982.57 | G58: 0 | H58: 27180.25 | I58: =G58+H58 -> 27180.25 | J58: =D58-I58 -> 12790.7 | K58: 200DB | L58: 5.0
A59: 8 | B59: 7-Building-2202 Northview Dr - 27.5 Year | C59: 7/30/24 | D59: 173950 | E59: 0 | F59: 0 | G59: 0 | H59: 2899.17 | I59: =G59+H59 -> 2899.17 | J59: =D59-I59 -> 171050.83 | K59: S/L | L59: 27.5
A60: 9 | B60: 8-Northiew Dr - 5 Year | C60: 7/30/24 | D60: 5157.54 | E60: 0 | F60: 3094.52 | G60: 0 | H60: 3507.12 | I60: =G60+H60 -> 3507.12 | J60: =D60-I60 -> 1650.42 | K60: 200DB | L60: 5.0
A61: 10 | B61: 8-Northiew Dr - 27.5 Year | C61: 7/30/24 | D61: 22445.16 | E61: 0 | F61: 0 | G61: 0 | H61: 374.09 | I61: =G61+H61 -> 374.09 | J61: =D61-I61 -> 22071.07 | K61: S/L | L61: 27.5
A62: 11 | B62: 9-Northview Dr - 5 Year | C62: 7/30/24 | D62: 9670.4 | E62: 0 | F62: 5802.24 | G62: 0 | H62: 6575.87 | I62: =G62+H62 -> 6575.87 | J62: =D62-I62 -> 3094.53 | K62: 200DB | L62: 5.0
A63: 12 | B63: 9-Northview Dr - 27.5 Year | C63: 7/30/24 | D63: 42084.68 | E63: 0 | F63: 0 | G63: 0 | H63: 701.41 | I63: =G63+H63 -> 701.41 | J63: =D63-I63 -> 41383.27 | K63: S/L | L63: 27.5
B64: Grand Total | D64: =SUM(D52:D63) -> 356960.53 | E64: =SUM(E52:E63) -> 0 | F64: =SUM(F52:F63) -> 40018.66 | G64: =SUM(G52:G63) -> 0 | H64: =SUM(H52:H63) -> 50192.2 | I64: =SUM(I52:I63) -> 50192.2 | J64: =SUM(J52:J63) -> 306768.33
B66: Section 481(a) Adjustment — AMT
B67: Depreciation reported previously | D67: =I48 -> 67780.54
B68: Cost Segregation Corrected Depreciation | D68: =I64 -> 50192.2
B69: Section 481(a) Adjustment — AMT | D69: =D67-D68 -> 17588.34
A71: COST SEGREGATION STUDY — COST SUMMARY
B72: Total Building Cost | D72: =D112 -> 356960.53
B73: Building Components: 5 Year | D73: =F112 -> 66697.78
B74: % of Cost | D74: =F113 -> 0.18684917
B75: Building Structure: 27.5 Year | D75: =H112 -> 290262.75
B76: % of Cost | D76: =H113 -> 0.81315083
A78: COST SEGREGATION STUDY — COST DETAIL
B79: Property Category | D79: Cost | F79: 5 Year | H79: 27.5 Year
B80: Building Components
B81: Cabinets / Millwork | D81: =SUM(F81:H81) -> 15196.4 | F81: 15196.4
B82: Moldings | D82: =SUM(F82:H82) -> 5234.75 | F82: 5234.75
B83: Flooring - Carpet | D83: =SUM(F83:H83) -> 1061.02 | F83: 1061.02
B84: Flooring - Wood Laminate | D84: =SUM(F84:H84) -> 20353.56 | F84: 20353.56
B85: Flooring - Seamless Vinyl | D85: =SUM(F85:H85) -> 164.32 | F85: 164.32
B86: Window Treatments | D86: =SUM(F86:H86) -> 5013.59 | F86: 5013.59
B87: Building Signage | D87: =SUM(F87:H87) -> 135.16 | F87: 135.16
B88: Specialty Electrical - Appliances | D88: =SUM(F88:H88) -> 3139.57 | F88: 3139.57
B89: Communication / Data | D89: =SUM(F89:H89) -> 2646.84 | F89: 2646.84
B90: Specialty Plumbing - Kitchen Sinks | D90: =SUM(F90:H90) -> 5742.77 | F90: 5742.77
B91: Security / Exterior Lighting | D91: =SUM(F91:H91) -> 2288.05 | F91: 2288.05
B92: Access Control | D92: =SUM(F92:H92) -> 93.04 | F92: 93.04
... B94: Appliances | D94: =SUM(F94:H94) -> 4954.45 | F94: 4954.45
B95: Building Structure
B96: Roofing Systems | D96: =SUM(F96:H96) -> 16445.38 | H96: 16445.38
B97: Foundations | D97: =SUM(F97:H97) -> 19790.61 | H97: 19790.61
B98: HVAC | D98: =SUM(F98:H98) -> 29793.92 | H98: 29793.92
B99: Electrical | D99: =SUM(F99:H99) -> 32200.21 | H99: 32200.21
B100: Plumbing | D100: =SUM(F100:H100) -> 25899.68 | H100: 25899.68
B101: Fire Protection & Alarm | D101: =SUM(F101:H101) -> 2118.67 | H101: 2118.67
B102: Exterior Façade / Building Skin | D102: =SUM(F102:H102) -> 11504.23 | H102: 11504.23
B103: Doors & Frames | D103: =SUM(F103:H103) -> 19980.87 | H103: 19980.87
B104: Windows | D104: =SUM(F104:H104) -> 9939.67 | H104: 9939.67
B105: Ceiling Systems | D105: =SUM(F105:H105) -> 13703.91 | H105: 13703.91
B106: Interior Framing / Partitions | D106: =SUM(F106:H106) -> 32147.45 | H106: 32147.45
B107: Painting | D107: =SUM(F107:H107) -> 14302.21 | H107: 14302.21
... B111: Bathroom Accessories | D111: =SUM(F111:H111) -> 4869.81 | H111: 4869.81
B112: Total Building Cost | D112: =SUM(D80:D111) -> 356960.53 | F112: =SUM(F80:F111) -> 66697.78 | H112: =SUM(H80:H111) -> 290262.75
...

Sheet Building 9
A1: River Garden Estates Housing LP
A2: River Garden Estates — 2201 Northview Dr & 712 Northfield Dr, Sacramento, CA 95833
A3: EIN: 93-2096487 · FYE: December 31, 2024 · Year of Change: 1/1/2024
A4: Building 9 — Attachment to Form 3115 (DCN #7, Rev. Proc. 2024-23 §6.01)
A5: Source: CSSI Report #107552-43, "#107552-43_River Garden Estates Housing LP_3115_Combined.pdf"
A7: CALCULATION OF §481(a) ADJUSTMENT — REGULAR TAX
A8: As Previously Filed
A9: Asset | B9: Property Description | C9: Date In Service | D9: Cost | E9: Sec 179 Exp | F9: Bonus Amt | G9: Tax Prior Depreciation | H9: Tax Current Depreciation | I9: End Depreciation | J9: Net Book Value | K9: Method | L9: Period
A10: 1 | B10: 2-Building-712 Northfield Dr | C10: 7/30/24 | D10: 46321.61 | E10: 0 | F10: 0 | G10: 0 | H10: 772.04 | I10: =G10+H10 -> 772.04 | J10: =D10-I10 -> 45549.57 | K10: S/L | L10: 27.5
A11: 2 | B11: 3-Northfield Dr | C11: 7/30/24 | D11: 5976.97 | E11: 0 | F11: 3586.18 | G11: 0 | H11: 3665.9 | I11: =G11+H11 -> 3665.9 | J11: =D11-I11 -> 2311.07 | K11: 150DB | L11: 15.0
A12: 3 | B12: 4-Northfield Dr | C12: 7/30/24 | D12: 11206.85 | E12: 0 | F12: 6724.11 | G12: 0 | H12: 7620.65 | I12: =G12+H12 -> 7620.65 | J12: =D12-I12 -> 3586.2 | K12: 200DB | L12: 5.0
A13: 4 | B13: 7-Building-2202 Northview Dr | C13: 7/30/24 | D13: 213328.45 | E13: 0 | F13: 0 | G13: 0 | H13: 3555.47 | I13: =G13+H13 -> 3555.47 | J13: =D13-I13 -> 209772.98 | K13: S/L | L13: 27.5
A14: 5 | B14: 8-Northiew Dr | C14: 7/30/24 | D14: 27526.25 | E14: 0 | F14: 16515.75 | G14: 0 | H14: 16882.77 | I14: =G14+H14 -> 16882.77 | J14: =D14-I14 -> 10643.48 | K14: 150DB | L14: 15.0
A15: 6 | B15: 9-Northview Dr | C15: 7/30/24 | D15: 51611.73 | E15: 0 | F15: 30967.04 | G15: 0 | H15: 35095.98 | I15: =G15+H15 -> 35095.98 | J15: =D15-I15 -> 16515.75 | K15: 200DB | L15: 5.0
B16: Grand Total | D16: =SUM(D10:D15) -> 355971.86 | E16: =SUM(E10:E15) -> 0 | F16: =SUM(F10:F15) -> 57793.08 | G16: =SUM(G10:G15) -> 0 | H16: =SUM(H10:H15) -> 67592.81 | I16: =SUM(I10:I15) -> 67592.81 | J16: =SUM(J10:J15) -> 288379.05
A18: After Cost Segregation Correction
A19: Asset | B19: Property Description | C19: Date In Service | D19: Cost | E19: Sec 179 Exp | F19: Bonus Amt | G19: Tax Prior Depreciation | H19: Tax Current Depreciation | I19: End Depreciation | J19: Net Book Value | K19: Method | L19: Period
A20: 1 | B20: 2-Building-712 Northfield Dr - 5 Year | C20: 7/30/24 | D20: 8603.17 | E20: 0 | F20: 5161.9 | G20: 0 | H20: 5850.15 | I20: =G20+H20 -> 5850.15 | J20: =D20-I20 -> 2753.02 | K20: 200DB | L20: 5.0
A21: 2 | B21: 2-Building-712 Northfield Dr - 27.5 Year | C21: 7/30/24 | D21: 37718.44 | E21: 0 | F21: 0 | G21: 0 | H21: 628.64 | I21: =G21+H21 -> 628.64 | J21: =D21-I21 -> 37089.8 | K21: S/L | L21: 27.5
A22: 3 | B22: 3-Northfield Dr - 5 Year | C22: 7/30/24 | D22: 1110.08 | E22: 0 | F22: 666.05 | G22: 0 | H22: 754.86 | I22: =G22+H22 -> 754.86 | J22: =D22-I22 -> 355.22 | K22: 200DB | L22: 5.0
A23: 4 | B23: 3-Northfield Dr - 27.5 Year | C23: 7/30/24 | D23: 4866.89 | E23: 0 | F23: 0 | G23: 0 | H23: 81.11 | I23: =G23+H23 -> 81.11 | J23: =D23-I23 -> 4785.78 | K23: S/L | L23: 27.5
A24: 5 | B24: 4-Northfield Dr - 5 Year | C24: 7/30/24 | D24: 2081.41 | E24: 0 | F24: 1248.85 | G24: 0 | H24: 1415.36 | I24: =G24+H24 -> 1415.36 | J24: =D24-I24 -> 666.05 | K24: 200DB | L24: 5.0
A25: 6 | B25: 4-Northfield Dr - 27.5 Year | C25: 7/30/24 | D25: 9125.44 | E25: 0 | F25: 0 | G25: 0 | H25: 152.09 | I25: =G25+H25 -> 152.09 | J25: =D25-I25 -> 8973.35 | K25: S/L | L25: 27.5
A26: 7 | B26: 7-Building-2202 Northview Dr - 5 Year | C26: 7/30/24 | D26: 39620.83 | E26: 0 | F26: 23772.5 | G26: 0 | H26: 26942.17 | I26: =G26+H26 -> 26942.17 | J26: =D26-I26 -> 12678.66 | K26: 200DB | L26: 5.0
A27: 8 | B27: 7-Building-2202 Northview Dr - 27.5 Year | C27: 7/30/24 | D27: 173707.62 | E27: 0 | F27: 0 | G27: 0 | H27: 2895.13 | I27: =G27+H27 -> 2895.13 | J27: =D27-I27 -> 170812.49 | K27: S/L | L27: 27.5
A28: 9 | B28: 8-Northiew Dr - 5 Year | C28: 7/30/24 | D28: 5112.36 | E28: 0 | F28: 3067.42 | G28: 0 | H28: 3476.41 | I28: =G28+H28 -> 3476.41 | J28: =D28-I28 -> 1635.95 | K28: 200DB | L28: 5.0
A29: 10 | B29: 8-Northiew Dr - 27.5 Year | C29: 7/30/24 | D29: 22413.89 | E29: 0 | F29: 0 | G29: 0 | H29: 373.56 | I29: =G29+H29 -> 373.56 | J29: =D29-I29 -> 22040.33 | K29: S/L | L29: 27.5
A30: 11 | B30: 9-Northview Dr - 5 Year | C30: 7/30/24 | D30: 9585.69 | E30: 0 | F30: 5751.41 | G30: 0 | H30: 6518.27 | I30: =G30+H30 -> 6518.27 | J30: =D30-I30 -> 3067.42 | K30: 200DB | L30: 5.0
A31: 12 | B31: 9-Northview Dr - 27.5 Year | C31: 7/30/24 | D31: 42026.04 | E31: 0 | F31: 0 | G31: 0 | H31: 700.43 | I31: =G31+H31 -> 700.43 | J31: =D31-I31 -> 41325.61 | K31: S/L | L31: 27.5
B32: Grand Total | D32: =SUM(D20:D31) -> 355971.86 | E32: =SUM(E20:E31) -> 0 | F32: =SUM(F20:F31) -> 39668.13 | G32: =SUM(G20:G31) -> 0 | H32: =SUM(H20:H31) -> 49788.18 | I32: =SUM(I20:I31) -> 49788.18 | J32: =SUM(J20:J31) -> 306183.68
B34: Section 481(a) Adjustment — Regular Tax
B35: Depreciation reported previously | D35: =I16 -> 67592.81
B36: Cost Segregation Corrected Depreciation | D36: =I32 -> 49788.18
B37: Section 481(a) Adjustment — Regular Tax | D37: =D35-D36 -> 17804.63
A39: CALCULATION OF §481(a) ADJUSTMENT — AMT
A40: As Previously Filed — AMT
A41: Asset | B41: Property Description | C41: Date In Service | D41: Cost | E41: Sec 179 Exp | F41: Bonus Amt | G41: AMT Prior Depreciation | H41: AMT Current Depreciation | I41: End Depreciation | J41: Net Book Value | K41: Method | L41: Period
A42: 1 | B42: 2-Building-712 Northfield Dr | C42: 7/30/24 | D42: 46321.61 | E42: 0 | F42: 0 | G42: 0 | H42: 772.04 | I42: =G42+H42 -> 772.04 | J42: =D42-I42 -> 45549.57 | K42: S/L | L42: 27.5
A43: 2 | B43: 3-Northfield Dr | C43: 7/30/24 | D43: 5976.97 | E43: 0 | F43: 3586.18 | G43: 0 | H43: 3665.9 | I43: =G43+H43 -> 3665.9 | J43: =D43-I43 -> 2311.07 | K43: 150DB | L43: 15.0
A44: 3 | B44: 4-Northfield Dr | C44: 7/30/24 | D44: 11206.85 | E44: 0 | F44: 6724.11 | G44: 0 | H44: 7620.65 | I44: =G44+H44 -> 7620.65 | J44: =D44-I44 -> 3586.2 | K44: 200DB | L44: 5.0
A45: 4 | B45: 7-Building-2202 Northview Dr | C45: 7/30/24 | D45: 213328.45 | E45: 0 | F45: 0 | G45: 0 | H45: 3555.47 | I45: =G45+H45 -> 3555.47 | J45: =D45-I45 -> 209772.98 | K45: S/L | L45: 27.5
A46: 5 | B46: 8-Northiew Dr | C46: 7/30/24 | D46: 27526.25 | E46: 0 | F46: 16515.75 | G46: 0 | H46: 16882.77 | I46: =G46+H46 -> 16882.77 | J46: =D46-I46 -> 10643.48 | K46: 150DB | L46: 15.0
A47: 6 | B47: 9-Northview Dr | C47: 7/30/24 | D47: 51611.73 | E47: 0 | F47: 30967.04 | G47: 0 | H47: 35095.98 | I47: =G47+H47 -> 35095.98 | J47: =D47-I47 -> 16515.75 | K47: 200DB | L47: 5.0
B48: Grand Total | D48: =SUM(D42:D47) -> 355971.86 | E48: =SUM(E42:E47) -> 0 | F48: =SUM(F42:F47) -> 57793.08 | G48: =SUM(G42:G47) -> 0 | H48: =SUM(H42:H47) -> 67592.81 | I48: =SUM(I42:I47) -> 67592.81 | J48: =SUM(J42:J47) -> 288379.05
A50: After Cost Segregation Correction — AMT
A51: Asset | B51: Property Description | C51: Date In Service | D51: Cost | E51: Sec 179 Exp | F51: Bonus Amt | G51: AMT Prior Depreciation | H51: AMT Current Depreciation | I51: End Depreciation | J51: Net Book Value | K51: Method | L51: Period
A52: 1 | B52: 2-Building-712 Northfield Dr - 5 Year | C52: 7/30/24 | D52: 8603.17 | E52: 0 | F52: 5161.9 | G52: 0 | H52: 5850.15 | I52: =G52+H52 -> 5850.15 | J52: =D52-I52 -> 2753.02 | K52: 200DB | L52: 5.0
A53: 2 | B53: 2-Building-712 Northfield Dr - 27.5 Year | C53: 7/30/24 | D53: 37718.44 | E53: 0 | F53: 0 | G53: 0 | H53: 628.64 | I53: =G53+H53 -> 628.64 | J53: =D53-I53 -> 37089.8 | K53: S/L | L53: 27.5
A54: 3 | B54: 3-Northfield Dr - 5 Year | C54: 7/30/24 | D54: 1110.08 | E54: 0 | F54: 666.05 | G54: 0 | H54: 754.86 | I54: =G54+H54 -> 754.86 | J54: =D54-I54 -> 355.22 | K54: 200DB | L54: 5.0
A55: 4 | B55: 3-Northfield Dr - 27.5 Year | C55: 7/30/24 | D55: 4866.89 | E55: 0 | F55: 0 | G55: 0 | H55: 81.11 | I55: =G55+H55 -> 81.11 | J55: =D55-I55 -> 4785.78 | K55: S/L | L55: 27.5
A56: 5 | B56: 4-Northfield Dr - 5 Year | C56: 7/30/24 | D56: 2081.41 | E56: 0 | F56: 1248.85 | G56: 0 | H56: 1415.36 | I56: =G56+H56 -> 1415.36 | J56: =D56-I56 -> 666.05 | K56: 200DB | L56: 5.0
A57: 6 | B57: 4-Northfield Dr - 27.5 Year | C57: 7/30/24 | D57: 9125.44 | E57: 0 | F57: 0 | G57: 0 | H57: 152.09 | I57: =G57+H57 -> 152.09 | J57: =D57-I57 -> 8973.35 | K57: S/L | L57: 27.5
A58: 7 | B58: 7-Building-2202 Northview Dr - 5 Year | C58: 7/30/24 | D58: 39620.83 | E58: 0 | F58: 23772.5 | G58: 0 | H58: 26942.17 | I58: =G58+H58 -> 26942.17 | J58: =D58-I58 -> 12678.66 | K58: 200DB | L58: 5.0
A59: 8 | B59: 7-Building-2202 Northview Dr - 27.5 Year | C59: 7/30/24 | D59: 173707.62 | E59: 0 | F59: 0 | G59: 0 | H59: 2895.13 | I59: =G59+H59 -> 2895.13 | J59: =D59-I59 -> 170812.49 | K59: S/L | L59: 27.5
A60: 9 | B60: 8-Northiew Dr - 5 Year | C60: 7/30/24 | D60: 5112.36 | E60: 0 | F60: 3067.42 | G60: 0 | H60: 3476.41 | I60: =G60+H60 -> 3476.41 | J60: =D60-I60 -> 1635.95 | K60: 200DB | L60: 5.0
A61: 10 | B61: 8-Northiew Dr - 27.5 Year | C61: 7/30/24 | D61: 22413.89 | E61: 0 | F61: 0 | G61: 0 | H61: 373.56 | I61: =G61+H61 -> 373.56 | J61: =D61-I61 -> 22040.33 | K61: S/L | L61: 27.5
A62: 11 | B62: 9-Northview Dr - 5 Year | C62: 7/30/24 | D62: 9585.69 | E62: 0 | F62: 5751.41 | G62: 0 | H62: 6518.27 | I62: =G62+H62 -> 6518.27 | J62: =D62-I62 -> 3067.42 | K62: 200DB | L62: 5.0
A63: 12 | B63: 9-Northview Dr - 27.5 Year | C63: 7/30/24 | D63: 42026.04 | E63: 0 | F63: 0 | G63: 0 | H63: 700.43 | I63: =G63+H63 -> 700.43 | J63: =D63-I63 -> 41325.61 | K63: S/L | L63: 27.5
B64: Grand Total | D64: =SUM(D52:D63) -> 355971.86 | E64: =SUM(E52:E63) -> 0 | F64: =SUM(F52:F63) -> 39668.13 | G64: =SUM(G52:G63) -> 0 | H64: =SUM(H52:H63) -> 49788.18 | I64: =SUM(I52:I63) -> 49788.18 | J64: =SUM(J52:J63) -> 306183.68
B66: Section 481(a) Adjustment — AMT
B67: Depreciation reported previously | D67: =I48 -> 67592.81
B68: Cost Segregation Corrected Depreciation | D68: =I64 -> 49788.18
B69: Section 481(a) Adjustment — AMT | D69: =D67-D68 -> 17804.63
A71: COST SEGREGATION STUDY — COST SUMMARY
B72: Total Building Cost | D72: =D112 -> 355971.86
B73: Building Components: 5 Year | D73: =F112 -> 66113.54
B74: % of Cost | D74: =F113 -> 0.18572687
B75: Building Structure: 27.5 Year | D75: =H112 -> 289858.32
B76: % of Cost | D76: =H113 -> 0.81427313
A78: COST SEGREGATION STUDY — COST DETAIL
B79: Property Category | D79: Cost | F79: 5 Year | H79: 27.5 Year
B80: Building Components
B81: Cabinets / Millwork | D81: =SUM(F81:H81) -> 15245.45 | F81: 15245.45
B82: Moldings | D82: =SUM(F82:H82) -> 5405.24 | F82: 5405.24
B83: Flooring - Carpet | D83: =SUM(F83:H83) -> 1061.02 | F83: 1061.02
B84: Flooring - Wood Laminate | D84: =SUM(F84:H84) -> 19807.88 | F84: 19807.88
B85: Flooring - Seamless Vinyl | D85: =SUM(F85:H85) -> 164.32 | F85: 164.32
B86: Window Treatments | D86: =SUM(F86:H86) -> 4912.76 | F86: 4912.76
B87: Building Signage | D87: =SUM(F87:H87) -> 135.16 | F87: 135.16
B88: Specialty Electrical - Appliances | D88: =SUM(F88:H88) -> 3139.57 | F88: 3139.57
B89: Communication / Data | D89: =SUM(F89:H89) -> 2579.47 | F89: 2579.47
B90: Specialty Plumbing - Kitchen Sinks | D90: =SUM(F90:H90) -> 5742.77 | F90: 5742.77
B91: Security / Exterior Lighting | D91: =SUM(F91:H91) -> 2198.15 | F91: 2198.15
B92: Access Control | D92: =SUM(F92:H92) -> 93.04 | F92: 93.04
... B94: Appliances | D94: =SUM(F94:H94) -> 4954.45 | F94: 4954.45
B95: Building Structure
B96: Roofing Systems | D96: =SUM(F96:H96) -> 16518.85 | H96: 16518.85
B97: Foundations | D97: =SUM(F97:H97) -> 19369.96 | H97: 19369.96
B98: HVAC | D98: =SUM(F98:H98) -> 29035.62 | H98: 29035.62
B99: Electrical | D99: =SUM(F99:H99) -> 31380.68 | H99: 31380.68
B100: Plumbing | D100: =SUM(F100:H100) -> 25240.5 | H100: 25240.5
B101: Fire Protection & Alarm | D101: =SUM(F101:H101) -> 2014.37 | H101: 2014.37
B102: Exterior Façade / Building Skin | D102: =SUM(F102:H102) -> 12011.3 | H102: 12011.3
B103: Doors & Frames | D103: =SUM(F103:H103) -> 20767.35 | H103: 20767.35
B104: Windows | D104: =SUM(F104:H104) -> 9641.98 | H104: 9641.98
B105: Ceiling Systems | D105: =SUM(F105:H105) -> 13355.12 | H105: 13355.12
B106: Interior Framing / Partitions | D106: =SUM(F106:H106) -> 33315.95 | H106: 33315.95
B107: Painting | D107: =SUM(F107:H107) -> 14606.85 | H107: 14606.85
... B111: Bathroom Accessories | D111: =SUM(F111:H111) -> 4960.5 | H111: 4960.5
B112: Total Building Cost | D112: =SUM(D80:D111) -> 355971.86 | F112: =SUM(F80:F111) -> 66113.54 | H112: =SUM(H80:H111) -> 289858.32
...

Sheet Building 10
A1: River Garden Estates Housing LP
A2: River Garden Estates — 2201 Northview Dr & 712 Northfield Dr, Sacramento, CA 95833
A3: EIN: 93-2096487 · FYE: December 31, 2024 · Year of Change: 1/1/2024
A4: Building 10 — Attachment to Form 3115 (DCN #7, Rev. Proc. 2024-23 §6.01)
A5: Source: CSSI Report #107552-43, "#107552-43_River Garden Estates Housing LP_3115_Combined.pdf"
A7: CALCULATION OF §481(a) ADJUSTMENT — REGULAR TAX
A8: As Previously Filed
A9: Asset | B9: Property Description | C9: Date In Service | D9: Cost | E9: Sec 179 Exp | F9: Bonus Amt | G9: Tax Prior Depreciation | H9: Tax Current Depreciation | I9: End Depreciation | J9: Net Book Value | K9: Method | L9: Period
A10: 1 | B10: 2-Building-712 Northfield Dr | C10: 7/30/24 | D10: 27290.76 | E10: 0 | F10: 0 | G10: 0 | H10: 454.85 | I10: =G10+H10 -> 454.85 | J10: =D10-I10 -> 26835.91 | K10: S/L | L10: 27.5
A11: 2 | B11: 3-Northfield Dr | C11: 7/30/24 | D11: 3521.38 | E11: 0 | F11: 2112.83 | G11: 0 | H11: 2159.79 | I11: =G11+H11 -> 2159.79 | J11: =D11-I11 -> 1361.59 | K11: 150DB | L11: 15.0
A12: 3 | B12: 4-Northfield Dr | C12: 7/30/24 | D12: 6602.61 | E12: 0 | F12: 3961.57 | G12: 0 | H12: 4489.77 | I12: =G12+H12 -> 4489.77 | J12: =D12-I12 -> 2112.84 | K12: 200DB | L12: 5.0
A13: 4 | B13: 7-Building-2202 Northview Dr | C13: 7/30/24 | D13: 125684.23 | E13: 0 | F13: 0 | G13: 0 | H13: 2094.73 | I13: =G13+H13 -> 2094.73 | J13: =D13-I13 -> 123589.5 | K13: S/L | L13: 27.5
A14: 5 | B14: 8-Northiew Dr | C14: 7/30/24 | D14: 16217.32 | E14: 0 | F14: 9730.39 | G14: 0 | H14: 9946.62 | I14: =G14+H14 -> 9946.62 | J14: =D14-I14 -> 6270.7 | K14: 150DB | L14: 15.0
A15: 6 | B15: 9-Northview Dr | C15: 7/30/24 | D15: 30407.48 | E15: 0 | F15: 18244.49 | G15: 0 | H15: 20677.09 | I15: =G15+H15 -> 20677.09 | J15: =D15-I15 -> 9730.39 | K15: 200DB | L15: 5.0
B16: Grand Total | D16: =SUM(D10:D15) -> 209723.78 | E16: =SUM(E10:E15) -> 0 | F16: =SUM(F10:F15) -> 34049.28 | G16: =SUM(G10:G15) -> 0 | H16: =SUM(H10:H15) -> 39822.85 | I16: =SUM(I10:I15) -> 39822.85 | J16: =SUM(J10:J15) -> 169900.93
A18: After Cost Segregation Correction
A19: Asset | B19: Property Description | C19: Date In Service | D19: Cost | E19: Sec 179 Exp | F19: Bonus Amt | G19: Tax Prior Depreciation | H19: Tax Current Depreciation | I19: End Depreciation | J19: Net Book Value | K19: Method | L19: Period
A20: 1 | B20: 2-Building-712 Northfield Dr - 5 Year | C20: 7/30/24 | D20: 5001.64 | E20: 0 | F20: 3000.98 | G20: 0 | H20: 3401.11 | I20: =G20+H20 -> 3401.11 | J20: =D20-I20 -> 1600.53 | K20: 200DB | L20: 5.0
A21: 2 | B21: 2-Building-712 Northfield Dr - 27.5 Year | C21: 7/30/24 | D21: 22289.12 | E21: 0 | F21: 0 | G21: 0 | H21: 371.49 | I21: =G21+H21 -> 371.49 | J21: =D21-I21 -> 21917.63 | K21: S/L | L21: 27.5
A22: 3 | B22: 3-Northfield Dr - 5 Year | C22: 7/30/24 | D22: 645.37 | E22: 0 | F22: 387.22 | G22: 0 | H22: 438.85 | I22: =G22+H22 -> 438.85 | J22: =D22-I22 -> 206.52 | K22: 200DB | L22: 5.0
A23: 4 | B23: 3-Northfield Dr - 27.5 Year | C23: 7/30/24 | D23: 2876.01 | E23: 0 | F23: 0 | G23: 0 | H23: 47.93 | I23: =G23+H23 -> 47.93 | J23: =D23-I23 -> 2828.08 | K23: S/L | L23: 27.5
A24: 5 | B24: 4-Northfield Dr - 5 Year | C24: 7/30/24 | D24: 1210.08 | E24: 0 | F24: 726.05 | G24: 0 | H24: 822.86 | I24: =G24+H24 -> 822.86 | J24: =D24-I24 -> 387.22 | K24: 200DB | L24: 5.0
A25: 6 | B25: 4-Northfield Dr - 27.5 Year | C25: 7/30/24 | D25: 5392.53 | E25: 0 | F25: 0 | G25: 0 | H25: 89.88 | I25: =G25+H25 -> 89.88 | J25: =D25-I25 -> 5302.65 | K25: S/L | L25: 27.5
A26: 7 | B26: 7-Building-2202 Northview Dr - 5 Year | C26: 7/30/24 | D26: 23034.43 | E26: 0 | F26: 13820.66 | G26: 0 | H26: 15663.41 | I26: =G26+H26 -> 15663.41 | J26: =D26-I26 -> 7371.02 | K26: 200DB | L26: 5.0
A27: 8 | B27: 7-Building-2202 Northview Dr - 27.5 Year | C27: 7/30/24 | D27: 102649.8 | E27: 0 | F27: 0 | G27: 0 | H27: 1710.83 | I27: =G27+H27 -> 1710.83 | J27: =D27-I27 -> 100938.97 | K27: S/L | L27: 27.5
A28: 9 | B28: 8-Northiew Dr - 5 Year | C28: 7/30/24 | D28: 2972.18 | E28: 0 | F28: 1783.31 | G28: 0 | H28: 2021.08 | I28: =G28+H28 -> 2021.08 | J28: =D28-I28 -> 951.1 | K28: 200DB | L28: 5.0
A29: 10 | B29: 8-Northiew Dr - 27.5 Year | C29: 7/30/24 | D29: 13245.14 | E29: 0 | F29: 0 | G29: 0 | H29: 220.75 | I29: =G29+H29 -> 220.75 | J29: =D29-I29 -> 13024.39 | K29: S/L | L29: 27.5
A30: 11 | B30: 9-Northview Dr - 5 Year | C30: 7/30/24 | D30: 5572.85 | E30: 0 | F30: 3343.71 | G30: 0 | H30: 3789.54 | I30: =G30+H30 -> 3789.54 | J30: =D30-I30 -> 1783.31 | K30: 200DB | L30: 5.0
A31: 12 | B31: 9-Northview Dr - 27.5 Year | C31: 7/30/24 | D31: 24834.63 | E31: 0 | F31: 0 | G31: 0 | H31: 413.91 | I31: =G31+H31 -> 413.91 | J31: =D31-I31 -> 24420.72 | K31: S/L | L31: 27.5
B32: Grand Total | D32: =SUM(D20:D31) -> 209723.78 | E32: =SUM(E20:E31) -> 0 | F32: =SUM(F20:F31) -> 23061.93 | G32: =SUM(G20:G31) -> 0 | H32: =SUM(H20:H31) -> 28991.64 | I32: =SUM(I20:I31) -> 28991.64 | J32: =SUM(J20:J31) -> 180732.14
B34: Section 481(a) Adjustment — Regular Tax
B35: Depreciation reported previously | D35: =I16 -> 39822.85
B36: Cost Segregation Corrected Depreciation | D36: =I32 -> 28991.64
B37: Section 481(a) Adjustment — Regular Tax | D37: =D35-D36 -> 10831.21
A39: CALCULATION OF §481(a) ADJUSTMENT — AMT
A40: As Previously Filed — AMT
A41: Asset | B41: Property Description | C41: Date In Service | D41: Cost | E41: Sec 179 Exp | F41: Bonus Amt | G41: AMT Prior Depreciation | H41: AMT Current Depreciation | I41: End Depreciation | J41: Net Book Value | K41: Method | L41: Period
A42: 1 | B42: 2-Building-712 Northfield Dr | C42: 7/30/24 | D42: 27290.76 | E42: 0 | F42: 0 | G42: 0 | H42: 454.85 | I42: =G42+H42 -> 454.85 | J42: =D42-I42 -> 26835.91 | K42: S/L | L42: 27.5
A43: 2 | B43: 3-Northfield Dr | C43: 7/30/24 | D43: 3521.38 | E43: 0 | F43: 2112.83 | G43: 0 | H43: 2159.79 | I43: =G43+H43 -> 2159.79 | J43: =D43-I43 -> 1361.59 | K43: 150DB | L43: 15.0
A44: 3 | B44: 4-Northfield Dr | C44: 7/30/24 | D44: 6602.61 | E44: 0 | F44: 3961.57 | G44: 0 | H44: 4489.77 | I44: =G44+H44 -> 4489.77 | J44: =D44-I44 -> 2112.84 | K44: 200DB | L44: 5.0
A45: 4 | B45: 7-Building-2202 Northview Dr | C45: 7/30/24 | D45: 125684.23 | E45: 0 | F45: 0 | G45: 0 | H45: 2094.73 | I45: =G45+H45 -> 2094.73 | J45: =D45-I45 -> 123589.5 | K45: S/L | L45: 27.5
A46: 5 | B46: 8-Northiew Dr | C46: 7/30/24 | D46: 16217.32 | E46: 0 | F46: 9730.39 | G46: 0 | H46: 9946.62 | I46: =G46+H46 -> 9946.62 | J46: =D46-I46 -> 6270.7 | K46: 150DB | L46: 15.0
A47: 6 | B47: 9-Northview Dr | C47: 7/30/24 | D47: 30407.48 | E47: 0 | F47: 18244.49 | G47: 0 | H47: 20677.09 | I47: =G47+H47 -> 20677.09 | J47: =D47-I47 -> 9730.39 | K47: 200DB | L47: 5.0
B48: Grand Total | D48: =SUM(D42:D47) -> 209723.78 | E48: =SUM(E42:E47) -> 0 | F48: =SUM(F42:F47) -> 34049.28 | G48: =SUM(G42:G47) -> 0 | H48: =SUM(H42:H47) -> 39822.85 | I48: =SUM(I42:I47) -> 39822.85 | J48: =SUM(J42:J47) -> 169900.93
A50: After Cost Segregation Correction — AMT
A51: Asset | B51: Property Description | C51: Date In Service | D51: Cost | E51: Sec 179 Exp | F51: Bonus Amt | G51: AMT Prior Depreciation | H51: AMT Current Depreciation | I51: End Depreciation | J51: Net Book Value | K51: Method | L51: Period
A52: 1 | B52: 2-Building-712 Northfield Dr - 5 Year | C52: 7/30/24 | D52: 5001.64 | E52: 0 | F52: 3000.98 | G52: 0 | H52: 3401.11 | I52: =G52+H52 -> 3401.11 | J52: =D52-I52 -> 1600.53 | K52: 200DB | L52: 5.0
A53: 2 | B53: 2-Building-712 Northfield Dr - 27.5 Year | C53: 7/30/24 | D53: 22289.12 | E53: 0 | F53: 0 | G53: 0 | H53: 371.49 | I53: =G53+H53 -> 371.49 | J53: =D53-I53 -> 21917.63 | K53: S/L | L53: 27.5
A54: 3 | B54: 3-Northfield Dr - 5 Year | C54: 7/30/24 | D54: 645.37 | E54: 0 | F54: 387.22 | G54: 0 | H54: 438.85 | I54: =G54+H54 -> 438.85 | J54: =D54-I54 -> 206.52 | K54: 200DB | L54: 5.0
A55: 4 | B55: 3-Northfield Dr - 27.5 Year | C55: 7/30/24 | D55: 2876.01 | E55: 0 | F55: 0 | G55: 0 | H55: 47.93 | I55: =G55+H55 -> 47.93 | J55: =D55-I55 -> 2828.08 | K55: S/L | L55: 27.5
A56: 5 | B56: 4-Northfield Dr - 5 Year | C56: 7/30/24 | D56: 1210.08 | E56: 0 | F56: 726.05 | G56: 0 | H56: 822.86 | I56: =G56+H56 -> 822.86 | J56: =D56-I56 -> 387.22 | K56: 200DB | L56: 5.0
A57: 6 | B57: 4-Northfield Dr - 27.5 Year | C57: 7/30/24 | D57: 5392.53 | E57: 0 | F57: 0 | G57: 0 | H57: 89.88 | I57: =G57+H57 -> 89.88 | J57: =D57-I57 -> 5302.65 | K57: S/L | L57: 27.5
A58: 7 | B58: 7-Building-2202 Northview Dr - 5 Year | C58: 7/30/24 | D58: 23034.43 | E58: 0 | F58: 13820.66 | G58: 0 | H58: 15663.41 | I58: =G58+H58 -> 15663.41 | J58: =D58-I58 -> 7371.02 | K58: 200DB | L58: 5.0
A59: 8 | B59: 7-Building-2202 Northview Dr - 27.5 Year | C59: 7/30/24 | D59: 102649.8 | E59: 0 | F59: 0 | G59: 0 | H59: 1710.83 | I59: =G59+H59 -> 1710.83 | J59: =D59-I59 -> 100938.97 | K59: S/L | L59: 27.5
A60: 9 | B60: 8-Northiew Dr - 5 Year | C60: 7/30/24 | D60: 2972.18 | E60: 0 | F60: 1783.31 | G60: 0 | H60: 2021.08 | I60: =G60+H60 -> 2021.08 | J60: =D60-I60 -> 951.1 | K60: 200DB | L60: 5.0
A61: 10 | B61: 8-Northiew Dr - 27.5 Year | C61: 7/30/24 | D61: 13245.14 | E61: 0 | F61: 0 | G61: 0 | H61: 220.75 | I61: =G61+H61 -> 220.75 | J61: =D61-I61 -> 13024.39 | K61: S/L | L61: 27.5
A62: 11 | B62: 9-Northview Dr - 5 Year | C62: 7/30/24 | D62: 5572.85 | E62: 0 | F62: 3343.71 | G62: 0 | H62: 3789.54 | I62: =G62+H62 -> 3789.54 | J62: =D62-I62 -> 1783.31 | K62: 200DB | L62: 5.0
A63: 12 | B63: 9-Northview Dr - 27.5 Year | C63: 7/30/24 | D63: 24834.63 | E63: 0 | F63: 0 | G63: 0 | H63: 413.91 | I63: =G63+H63 -> 413.91 | J63: =D63-I63 -> 24420.72 | K63: S/L | L63: 27.5
B64: Grand Total | D64: =SUM(D52:D63) -> 209723.78 | E64: =SUM(E52:E63) -> 0 | F64: =SUM(F52:F63) -> 23061.93 | G64: =SUM(G52:G63) -> 0 | H64: =SUM(H52:H63) -> 28991.64 | I64: =SUM(I52:I63) -> 28991.64 | J64: =SUM(J52:J63) -> 180732.14
B66: Section 481(a) Adjustment — AMT
B67: Depreciation reported previously | D67: =I48 -> 39822.85
B68: Cost Segregation Corrected Depreciation | D68: =I64 -> 28991.64
B69: Section 481(a) Adjustment — AMT | D69: =D67-D68 -> 10831.21
A71: COST SEGREGATION STUDY — COST SUMMARY
B72: Total Building Cost | D72: =D110 -> 209723.78
B73: Building Components: 5 Year | D73: =F110 -> 38436.55
B74: % of Cost | D74: =F111 -> 0.18327225
B75: Building Structure: 27.5 Year | D75: =H110 -> 171287.23
B76: % of Cost | D76: =H111 -> 0.81672775
A78: COST SEGREGATION STUDY — COST DETAIL
B79: Property Category | D79: Cost | F79: 5 Year | H79: 27.5 Year
B80: Building Components
B81: Cabinets / Millwork | D81: =SUM(F81:H81) -> 8655.83 | F81: 8655.83
B82: Moldings | D82: =SUM(F82:H82) -> 3397.22 | F82: 3397.22
B83: Flooring - Wood Laminate | D83: =SUM(F83:H83) -> 12211.66 | F83: 12211.66
B84: Window Treatments | D84: =SUM(F84:H84) -> 2823.29 | F84: 2823.29
B85: Building Signage | D85: =SUM(F85:H85) -> 90.34 | F85: 90.34
B86: Specialty Electrical - Appliances | D86: =SUM(F86:H86) -> 1794.05 | F86: 1794.05
B87: Communication / Data | D87: =SUM(F87:H87) -> 1507.56 | F87: 1507.56
B88: Specialty Plumbing - Kitchen Sinks | D88: =SUM(F88:H88) -> 3281.59 | F88: 3281.59
B89: Security / Exterior Lighting | D89: =SUM(F89:H89) -> 1386.19 | F89: 1386.19
B90: Access Control | D90: =SUM(F90:H90) -> 53.16 | F90: 53.16
B91: Entry Canopies | D91: =SUM(F91:H91) -> 404.54 | F91: 404.54
B92: Appliances | D92: =SUM(F92:H92) -> 2831.12 | F92: 2831.12
B93: Building Structure
B94: Roofing Systems | D94: =SUM(F94:H94) -> 9211.22 | H94: 9211.22
B95: Foundations | D95: =SUM(F95:H95) -> 11470.72 | H95: 11470.72
B96: HVAC | D96: =SUM(F96:H96) -> 16969.73 | H96: 16969.73
B97: Electrical | D97: =SUM(F97:H97) -> 18340.3 | H97: 18340.3
B98: Plumbing | D98: =SUM(F98:H98) -> 14751.7 | H98: 14751.7
B99: Fire Protection & Alarm | D99: =SUM(F99:H99) -> 1388.53 | H99: 1388.53
B100: Exterior Façade / Building Skin | D100: =SUM(F100:H100) -> 7649.12 | H100: 7649.12
B101: Doors & Frames | D101: =SUM(F101:H101) -> 11108.31 | H101: 11108.31
B102: Windows | D102: =SUM(F102:H102) -> 5556.95 | H102: 5556.95
B103: Ceiling Systems | D103: =SUM(F103:H103) -> 7805.36 | H103: 7805.36
B104: Interior Framing / Partitions | D104: =SUM(F104:H104) -> 21030.97 | H104: 21030.97
B105: Painting | D105: =SUM(F105:H105) -> 9062.11 | H105: 9062.11
... B109: Bathroom Accessories | D109: =SUM(F109:H109) -> 2975.88 | H109: 2975.88
B110: Total Building Cost | D110: =SUM(D80:D109) -> 209723.78 | F110: =SUM(F80:F109) -> 38436.55 | H110: =SUM(H80:H109) -> 171287.23
B111: % of Cost | F111: =F110/D110 -> 0.18327225 | H111: =H110/D110 -> 0.81672775
...

Sheet Building 11
A1: River Garden Estates Housing LP
A2: River Garden Estates — 2201 Northview Dr & 712 Northfield Dr, Sacramento, CA 95833
A3: EIN: 93-2096487 · FYE: December 31, 2024 · Year of Change: 1/1/2024
A4: Building 11 — Attachment to Form 3115 (DCN #7, Rev. Proc. 2024-23 §6.01)
A5: Source: CSSI Report #107552-43, "#107552-43_River Garden Estates Housing LP_3115_Combined.pdf"
A7: CALCULATION OF §481(a) ADJUSTMENT — REGULAR TAX
A8: As Previously Filed
A9: Asset | B9: Property Description | C9: Date In Service | D9: Cost | E9: Sec 179 Exp | F9: Bonus Amt | G9: Tax Prior Depreciation | H9: Tax Current Depreciation | I9: End Depreciation | J9: Net Book Value | K9: Method | L9: Period
A10: 1 | B10: 2-Building-712 Northfield Dr | C10: 7/30/24 | D10: 60219.73 | E10: 0 | F10: 0 | G10: 0 | H10: 1003.68 | I10: =G10+H10 -> 1003.68 | J10: =D10-I10 -> 59216.05 | K10: S/L | L10: 27.5
A11: 2 | B11: 3-Northfield Dr | C11: 7/30/24 | D11: 7770.26 | E11: 0 | F11: 4662.16 | G11: 0 | H11: 4765.79 | I11: =G11+H11 -> 4765.79 | J11: =D11-I11 -> 3004.47 | K11: 150DB | L11: 15.0
A12: 3 | B12: 4-Northfield Dr | C12: 7/30/24 | D12: 14569.3 | E12: 0 | F12: 8741.58 | G12: 0 | H12: 9907.12 | I12: =G12+H12 -> 9907.12 | J12: =D12-I12 -> 4662.18 | K12: 200DB | L12: 5.0
A13: 4 | B13: 7-Building-2202 Northview Dr | C13: 7/30/24 | D13: 277334.53 | E13: 0 | F13: 0 | G13: 0 | H13: 4622.23 | I13: =G13+H13 -> 4622.23 | J13: =D13-I13 -> 272712.3 | K13: S/L | L13: 27.5
A14: 5 | B14: 8-Northiew Dr | C14: 7/30/24 | D14: 35785.1 | E14: 0 | F14: 21471.06 | G14: 0 | H14: 21948.19 | I14: =G14+H14 -> 21948.19 | J14: =D14-I14 -> 13836.91 | K14: 150DB | L14: 15.0
A15: 6 | B15: 9-Northview Dr | C15: 7/30/24 | D15: 67097.08 | E15: 0 | F15: 40258.25 | G15: 0 | H15: 45626.02 | I15: =G15+H15 -> 45626.02 | J15: =D15-I15 -> 21471.06 | K15: 200DB | L15: 5.0
B16: Grand Total | D16: =SUM(D10:D15) -> 462776 | E16: =SUM(E10:E15) -> 0 | F16: =SUM(F10:F15) -> 75133.05 | G16: =SUM(G10:G15) -> 0 | H16: =SUM(H10:H15) -> 87873.03 | I16: =SUM(I10:I15) -> 87873.03 | J16: =SUM(J10:J15) -> 374902.97
A18: After Cost Segregation Correction
A19: Asset | B19: Property Description | C19: Date In Service | D19: Cost | E19: Sec 179 Exp | F19: Bonus Amt | G19: Tax Prior Depreciation | H19: Tax Current Depreciation | I19: End Depreciation | J19: Net Book Value | K19: Method | L19: Period
A20: 1 | B20: 2-Building-712 Northfield Dr - 5 Year | C20: 7/30/24 | D20: 11223.57 | E20: 0 | F20: 6734.14 | G20: 0 | H20: 7632.03 | I20: =G20+H20 -> 7632.03 | J20: =D20-I20 -> 3591.54 | K20: 200DB | L20: 5.0
A21: 2 | B21: 2-Building-712 Northfield Dr - 27.5 Year | C21: 7/30/24 | D21: 48996.16 | E21: 0 | F21: 0 | G21: 0 | H21: 816.6 | I21: =G21+H21 -> 816.6 | J21: =D21-I21 -> 48179.56 | K21: S/L | L21: 27.5
A22: 3 | B22: 3-Northfield Dr - 5 Year | C22: 7/30/24 | D22: 1448.2 | E22: 0 | F22: 868.92 | G22: 0 | H22: 984.78 | I22: =G22+H22 -> 984.78 | J22: =D22-I22 -> 463.42 | K22: 200DB | L22: 5.0
A23: 4 | B23: 3-Northfield Dr - 27.5 Year | C23: 7/30/24 | D23: 6322.06 | E23: 0 | F23: 0 | G23: 0 | H23: 105.37 | I23: =G23+H23 -> 105.37 | J23: =D23-I23 -> 6216.69 | K23: S/L | L23: 27.5
A24: 5 | B24: 4-Northfield Dr - 5 Year | C24: 7/30/24 | D24: 2715.38 | E24: 0 | F24: 1629.23 | G24: 0 | H24: 1846.46 | I24: =G24+H24 -> 1846.46 | J24: =D24-I24 -> 868.92 | K24: 200DB | L24: 5.0
A25: 6 | B25: 4-Northfield Dr - 27.5 Year | C25: 7/30/24 | D25: 11853.92 | E25: 0 | F25: 0 | G25: 0 | H25: 197.57 | I25: =G25+H25 -> 197.57 | J25: =D25-I25 -> 11656.35 | K25: S/L | L25: 27.5
A26: 7 | B26: 7-Building-2202 Northview Dr - 5 Year | C26: 7/30/24 | D26: 51688.76 | E26: 0 | F26: 31013.26 | G26: 0 | H26: 35148.36 | I26: =G26+H26 -> 35148.36 | J26: =D26-I26 -> 16540.4 | K26: 200DB | L26: 5.0
A27: 8 | B27: 7-Building-2202 Northview Dr - 27.5 Year | C27: 7/30/24 | D27: 225645.77 | E27: 0 | F27: 0 | G27: 0 | H27: 3760.76 | I27: =G27+H27 -> 3760.76 | J27: =D27-I27 -> 221885.01 | K27: S/L | L27: 27.5
A28: 9 | B28: 8-Northiew Dr - 5 Year | C28: 7/30/24 | D28: 6669.52 | E28: 0 | F28: 4001.71 | G28: 0 | H28: 4535.27 | I28: =G28+H28 -> 4535.27 | J28: =D28-I28 -> 2134.25 | K28: 200DB | L28: 5.0
A29: 10 | B29: 8-Northiew Dr - 27.5 Year | C29: 7/30/24 | D29: 29115.58 | E29: 0 | F29: 0 | G29: 0 | H29: 485.26 | I29: =G29+H29 -> 485.26 | J29: =D29-I29 -> 28630.32 | K29: S/L | L29: 27.5
A30: 11 | B30: 9-Northview Dr - 5 Year | C30: 7/30/24 | D30: 12505.34 | E30: 0 | F30: 7503.2 | G30: 0 | H30: 8503.63 | I30: =G30+H30 -> 8503.63 | J30: =D30-I30 -> 4001.71 | K30: 200DB | L30: 5.0
A31: 12 | B31: 9-Northview Dr - 27.5 Year | C31: 7/30/24 | D31: 54591.74 | E31: 0 | F31: 0 | G31: 0 | H31: 909.86 | I31: =G31+H31 -> 909.86 | J31: =D31-I31 -> 53681.88 | K31: S/L | L31: 27.5
B32: Grand Total | D32: =SUM(D20:D31) -> 462776 | E32: =SUM(E20:E31) -> 0 | F32: =SUM(F20:F31) -> 51750.46 | G32: =SUM(G20:G31) -> 0 | H32: =SUM(H20:H31) -> 64925.95 | I32: =SUM(I20:I31) -> 64925.95 | J32: =SUM(J20:J31) -> 397850.05
B34: Section 481(a) Adjustment — Regular Tax
B35: Depreciation reported previously | D35: =I16 -> 87873.03
B36: Cost Segregation Corrected Depreciation | D36: =I32 -> 64925.95
B37: Section 481(a) Adjustment — Regular Tax | D37: =D35-D36 -> 22947.08
A39: CALCULATION OF §481(a) ADJUSTMENT — AMT
A40: As Previously Filed — AMT
A41: Asset | B41: Property Description | C41: Date In Service | D41: Cost | E41: Sec 179 Exp | F41: Bonus Amt | G41: AMT Prior Depreciation | H41: AMT Current Depreciation | I41: End Depreciation | J41: Net Book Value | K41: Method | L41: Period
A42: 1 | B42: 2-Building-712 Northfield Dr | C42: 7/30/24 | D42: 60219.73 | E42: 0 | F42: 0 | G42: 0 | H42: 1003.68 | I42: =G42+H42 -> 1003.68 | J42: =D42-I42 -> 59216.05 | K42: S/L | L42: 27.5
A43: 2 | B43: 3-Northfield Dr | C43: 7/30/24 | D43: 7770.26 | E43: 0 | F43: 4662.16 | G43: 0 | H43: 4765.79 | I43: =G43+H43 -> 4765.79 | J43: =D43-I43 -> 3004.47 | K43: 150DB | L43: 15.0
A44: 3 | B44: 4-Northfield Dr | C44: 7/30/24 | D44: 14569.3 | E44: 0 | F44: 8741.58 | G44: 0 | H44: 9907.12 | I44: =G44+H44 -> 9907.12 | J44: =D44-I44 -> 4662.18 | K44: 200DB | L44: 5.0
A45: 4 | B45: 7-Building-2202 Northview Dr | C45: 7/30/24 | D45: 277334.53 | E45: 0 | F45: 0 | G45: 0 | H45: 4622.23 | I45: =G45+H45 -> 4622.23 | J45: =D45-I45 -> 272712.3 | K45: S/L | L45: 27.5
A46: 5 | B46: 8-Northiew Dr | C46: 7/30/24 | D46: 35785.1 | E46: 0 | F46: 21471.06 | G46: 0 | H46: 21948.19 | I46: =G46+H46 -> 21948.19 | J46: =D46-I46 -> 13836.91 | K46: 150DB | L46: 15.0
A47: 6 | B47: 9-Northview Dr | C47: 7/30/24 | D47: 67097.08 | E47: 0 | F47: 40258.25 | G47: 0 | H47: 45626.02 | I47: =G47+H47 -> 45626.02 | J47: =D47-I47 -> 21471.06 | K47: 200DB | L47: 5.0
B48: Grand Total | D48: =SUM(D42:D47) -> 462776 | E48: =SUM(E42:E47) -> 0 | F48: =SUM(F42:F47) -> 75133.05 | G48: =SUM(G42:G47) -> 0 | H48: =SUM(H42:H47) -> 87873.03 | I48: =SUM(I42:I47) -> 87873.03 | J48: =SUM(J42:J47) -> 374902.97
A50: After Cost Segregation Correction — AMT
A51: Asset | B51: Property Description | C51: Date In Service | D51: Cost | E51: Sec 179 Exp | F51: Bonus Amt | G51: AMT Prior Depreciation | H51: AMT Current Depreciation | I51: End Depreciation | J51: Net Book Value | K51: Method | L51: Period
A52: 1 | B52: 2-Building-712 Northfield Dr - 5 Year | C52: 7/30/24 | D52: 11223.57 | E52: 0 | F52: 6734.14 | G52: 0 | H52: 7632.03 | I52: =G52+H52 -> 7632.03 | J52: =D52-I52 -> 3591.54 | K52: 200DB | L52: 5.0
A53: 2 | B53: 2-Building-712 Northfield Dr - 27.5 Year | C53: 7/30/24 | D53: 48996.16 | E53: 0 | F53: 0 | G53: 0 | H53: 816.6 | I53: =G53+H53 -> 816.6 | J53: =D53-I53 -> 48179.56 | K53: S/L | L53: 27.5
A54: 3 | B54: 3-Northfield Dr - 5 Year | C54: 7/30/24 | D54: 1448.2 | E54: 0 | F54: 868.92 | G54: 0 | H54: 984.78 | I54: =G54+H54 -> 984.78 | J54: =D54-I54 -> 463.42 | K54: 200DB | L54: 5.0
A55: 4 | B55: 3-Northfield Dr - 27.5 Year | C55: 7/30/24 | D55: 6322.06 | E55: 0 | F55: 0 | G55: 0 | H55: 105.37 | I55: =G55+H55 -> 105.37 | J55: =D55-I55 -> 6216.69 | K55: S/L | L55: 27.5
A56: 5 | B56: 4-Northfield Dr - 5 Year | C56: 7/30/24 | D56: 2715.38 | E56: 0 | F56: 1629.23 | G56: 0 | H56: 1846.46 | I56: =G56+H56 -> 1846.46 | J56: =D56-I56 -> 868.92 | K56: 200DB | L56: 5.0
A57: 6 | B57: 4-Northfield Dr - 27.5 Year | C57: 7/30/24 | D57: 11853.92 | E57: 0 | F57: 0 | G57: 0 | H57: 197.57 | I57: =G57+H57 -> 197.57 | J57: =D57-I57 -> 11656.35 | K57: S/L | L57: 27.5
A58: 7 | B58: 7-Building-2202 Northview Dr - 5 Year | C58: 7/30/24 | D58: 51688.76 | E58: 0 | F58: 31013.26 | G58: 0 | H58: 35148.36 | I58: =G58+H58 -> 35148.36 | J58: =D58-I58 -> 16540.4 | K58: 200DB | L58: 5.0
A59: 8 | B59: 7-Building-2202 Northview Dr - 27.5 Year | C59: 7/30/24 | D59: 225645.77 | E59: 0 | F59: 0 | G59: 0 | H59: 3760.76 | I59: =G59+H59 -> 3760.76 | J59: =D59-I59 -> 221885.01 | K59: S/L | L59: 27.5
A60: 9 | B60: 8-Northiew Dr - 5 Year | C60: 7/30/24 | D60: 6669.52 | E60: 0 | F60: 4001.71 | G60: 0 | H60: 4535.27 | I60: =G60+H60 -> 4535.27 | J60: =D60-I60 -> 2134.25 | K60: 200DB | L60: 5.0
A61: 10 | B61: 8-Northiew Dr - 27.5 Year | C61: 7/30/24 | D61: 29115.58 | E61: 0 | F61: 0 | G61: 0 | H61: 485.26 | I61: =G61+H61 -> 485.26 | J61: =D61-I61 -> 28630.32 | K61: S/L | L61: 27.5
A62: 11 | B62: 9-Northview Dr - 5 Year | C62: 7/30/24 | D62: 12505.34 | E62: 0 | F62: 7503.2 | G62: 0 | H62: 8503.63 | I62: =G62+H62 -> 8503.63 | J62: =D62-I62 -> 4001.71 | K62: 200DB | L62: 5.0
A63: 12 | B63: 9-Northview Dr - 27.5 Year | C63: 7/30/24 | D63: 54591.74 | E63: 0 | F63: 0 | G63: 0 | H63: 909.86 | I63: =G63+H63 -> 909.86 | J63: =D63-I63 -> 53681.88 | K63: S/L | L63: 27.5
B64: Grand Total | D64: =SUM(D52:D63) -> 462776 | E64: =SUM(E52:E63) -> 0 | F64: =SUM(F52:F63) -> 51750.46 | G64: =SUM(G52:G63) -> 0 | H64: =SUM(H52:H63) -> 64925.95 | I64: =SUM(I52:I63) -> 64925.95 | J64: =SUM(J52:J63) -> 397850.05
B66: Section 481(a) Adjustment — AMT
B67: Depreciation reported previously | D67: =I48 -> 87873.03
B68: Cost Segregation Corrected Depreciation | D68: =I64 -> 64925.95
B69: Section 481(a) Adjustment — AMT | D69: =D67-D68 -> 22947.08
A71: COST SEGREGATION STUDY — COST SUMMARY
B72: Total Building Cost | D72: =D110 -> 462776
B73: Building Components: 5 Year | D73: =F110 -> 86250.77
B74: % of Cost | D74: =F111 -> 0.18637693
B75: Building Structure: 27.5 Year | D75: =H110 -> 376525.23
B76: % of Cost | D76: =H111 -> 0.81362307
A78: COST SEGREGATION STUDY — COST DETAIL
B79: Property Category | D79: Cost | F79: 5 Year | H79: 27.5 Year
B80: Building Components
B81: Cabinets / Millwork | D81: =SUM(F81:H81) -> 19502.86 | F81: 19502.86
B82: Moldings | D82: =SUM(F82:H82) -> 6491.33 | F82: 6491.33
B83: Flooring - Wood Laminate | D83: =SUM(F83:H83) -> 28408.94 | F83: 28408.94
B84: Window Treatments | D84: =SUM(F84:H84) -> 6537.27 | F84: 6537.27
B85: Building Signage | D85: =SUM(F85:H85) -> 165.04 | F85: 165.04
B86: Specialty Electrical - Appliances | D86: =SUM(F86:H86) -> 4036.61 | F86: 4036.61
B87: Communication / Data | D87: =SUM(F87:H87) -> 3507.15 | F87: 3507.15
B88: Specialty Plumbing - Kitchen Sinks | D88: =SUM(F88:H88) -> 7383.57 | F88: 7383.57
B89: Security / Exterior Lighting | D89: =SUM(F89:H89) -> 2919.25 | F89: 2919.25
B90: Access Control | D90: =SUM(F90:H90) -> 119.61 | F90: 119.61
B91: Entry Canopies | D91: =SUM(F91:H91) -> 809.12 | F91: 809.12
B92: Appliances | D92: =SUM(F92:H92) -> 6370.02 | F92: 6370.02
B93: Building Structure
B94: Roofing Systems | D94: =SUM(F94:H94) -> 22264.67 | H94: 22264.67
B95: Foundations | D95: =SUM(F95:H95) -> 26055.7 | H95: 26055.7
B96: HVAC | D96: =SUM(F96:H96) -> 39478.02 | H96: 39478.02
B97: Electrical | D97: =SUM(F97:H97) -> 42666.46 | H97: 42666.46
B98: Plumbing | D98: =SUM(F98:H98) -> 34318.04 | H98: 34318.04
B99: Fire Protection & Alarm | D99: =SUM(F99:H99) -> 2796.66 | H99: 2796.66
B100: Exterior Façade / Building Skin | D100: =SUM(F100:H100) -> 14122.27 | H100: 14122.27
B101: Doors & Frames | D101: =SUM(F101:H101) -> 24894.53 | H101: 24894.53
B102: Windows | D102: =SUM(F102:H102) -> 13048.93 | H102: 13048.93
B103: Ceiling Systems | D103: =SUM(F103:H103) -> 18158.19 | H103: 18158.19
B104: Interior Framing / Partitions | D104: =SUM(F104:H104) -> 39732.62 | H104: 39732.62
B105: Painting | D105: =SUM(F105:H105) -> 17994.21 | H105: 17994.21
... B109: Bathroom Accessories | D109: =SUM(F109:H109) -> 6582.34 | H109: 6582.34
B110: Total Building Cost | D110: =SUM(D80:D109) -> 462776 | F110: =SUM(F80:F109) -> 86250.77 | H110: =SUM(H80:H109) -> 376525.23
B111: % of Cost | F111: =F110/D110 -> 0.18637693 | H111: =H110/D110 -> 0.81362307
...

Sheet Building 12
A1: River Garden Estates Housing LP
A2: River Garden Estates — 2201 Northview Dr & 712 Northfield Dr, Sacramento, CA 95833
A3: EIN: 93-2096487 · FYE: December 31, 2024 · Year of Change: 1/1/2024
A4: Building 12 — Attachment to Form 3115 (DCN #7, Rev. Proc. 2024-23 §6.01)
A5: Source: CSSI Report #107552-43, "#107552-43_River Garden Estates Housing LP_3115_Combined.pdf"
A7: CALCULATION OF §481(a) ADJUSTMENT — REGULAR TAX
A8: As Previously Filed
A9: Asset | B9: Property Description | C9: Date In Service | D9: Cost | E9: Sec 179 Exp | F9: Bonus Amt | G9: Tax Prior Depreciation | H9: Tax Current Depreciation | I9: End Depreciation | J9: Net Book Value | K9: Method | L9: Period
A10: 1 | B10: 2-Building-712 Northfield Dr | C10: 7/30/24 | D10: 39989.86 | E10: 0 | F10: 0 | G10: 0 | H10: 666.51 | I10: =G10+H10 -> 666.51 | J10: =D10-I10 -> 39323.35 | K10: S/L | L10: 27.5
A11: 2 | B11: 3-Northfield Dr | C11: 7/30/24 | D11: 5159.97 | E11: 0 | F11: 3095.98 | G11: 0 | H11: 3164.8 | I11: =G11+H11 -> 3164.8 | J11: =D11-I11 -> 1995.17 | K11: 150DB | L11: 15.0
A12: 3 | B12: 4-Northfield Dr | C12: 7/30/24 | D12: 9674.97 | E12: 0 | F12: 5804.98 | G12: 0 | H12: 6578.97 | I12: =G12+H12 -> 6578.97 | J12: =D12-I12 -> 3096 | K12: 200DB | L12: 5.0
A13: 4 | B13: 7-Building-2202 Northview Dr | C13: 7/30/24 | D13: 184168.35 | E13: 0 | F13: 0 | G13: 0 | H13: 3069.46 | I13: =G13+H13 -> 3069.46 | J13: =D13-I13 -> 181098.89 | K13: S/L | L13: 27.5
A14: 5 | B14: 8-Northiew Dr | C14: 7/30/24 | D14: 23763.65 | E14: 0 | F14: 14258.19 | G14: 0 | H14: 14575.04 | I14: =G14+H14 -> 14575.04 | J14: =D14-I14 -> 9188.61 | K14: 150DB | L14: 15.0
A15: 6 | B15: 9-Northview Dr | C15: 7/30/24 | D15: 44556.87 | E15: 0 | F15: 26734.12 | G15: 0 | H15: 30298.68 | I15: =G15+H15 -> 30298.68 | J15: =D15-I15 -> 14258.19 | K15: 200DB | L15: 5.0
B16: Grand Total | D16: =SUM(D10:D15) -> 307313.67 | E16: =SUM(E10:E15) -> 0 | F16: =SUM(F10:F15) -> 49893.27 | G16: =SUM(G10:G15) -> 0 | H16: =SUM(H10:H15) -> 58353.46 | I16: =SUM(I10:I15) -> 58353.46 | J16: =SUM(J10:J15) -> 248960.21
A18: After Cost Segregation Correction
A19: Asset | B19: Property Description | C19: Date In Service | D19: Cost | E19: Sec 179 Exp | F19: Bonus Amt | G19: Tax Prior Depreciation | H19: Tax Current Depreciation | I19: End Depreciation | J19: Net Book Value | K19: Method | L19: Period
A20: 1 | B20: 2-Building-712 Northfield Dr - 5 Year | C20: 7/30/24 | D20: 7464.18 | E20: 0 | F20: 4478.51 | G20: 0 | H20: 5075.64 | I20: =G20+H20 -> 5075.64 | J20: =D20-I20 -> 2388.54 | K20: 200DB | L20: 5.0
A21: 2 | B21: 2-Building-712 Northfield Dr - 27.5 Year | C21: 7/30/24 | D21: 32525.68 | E21: 0 | F21: 0 | G21: 0 | H21: 542.09 | I21: =G21+H21 -> 542.09 | J21: =D21-I21 -> 31983.59 | K21: S/L | L21: 27.5
A22: 3 | B22: 3-Northfield Dr - 5 Year | C22: 7/30/24 | D22: 963.12 | E22: 0 | F22: 577.87 | G22: 0 | H22: 654.92 | I22: =G22+H22 -> 654.92 | J22: =D22-I22 -> 308.2 | K22: 200DB | L22: 5.0
A23: 4 | B23: 3-Northfield Dr - 27.5 Year | C23: 7/30/24 | D23: 4196.85 | E23: 0 | F23: 0 | G23: 0 | H23: 69.95 | I23: =G23+H23 -> 69.95 | J23: =D23-I23 -> 4126.9 | K23: S/L | L23: 27.5
A24: 5 | B24: 4-Northfield Dr - 5 Year | C24: 7/30/24 | D24: 1805.85 | E24: 0 | F24: 1083.51 | G24: 0 | H24: 1227.98 | I24: =G24+H24 -> 1227.98 | J24: =D24-I24 -> 577.87 | K24: 200DB | L24: 5.0
A25: 6 | B25: 4-Northfield Dr - 27.5 Year | C25: 7/30/24 | D25: 7869.12 | E25: 0 | F25: 0 | G25: 0 | H25: 131.15 | I25: =G25+H25 -> 131.15 | J25: =D25-I25 -> 7737.97 | K25: S/L | L25: 27.5
A26: 7 | B26: 7-Building-2202 Northview Dr - 5 Year | C26: 7/30/24 | D26: 34375.37 | E26: 0 | F26: 20625.22 | G26: 0 | H26: 23375.25 | I26: =G26+H26 -> 23375.25 | J26: =D26-I26 -> 11000.12 | K26: 200DB | L26: 5.0
A27: 8 | B27: 7-Building-2202 Northview Dr - 27.5 Year | C27: 7/30/24 | D27: 149792.98 | E27: 0 | F27: 0 | G27: 0 | H27: 2496.55 | I27: =G27+H27 -> 2496.55 | J27: =D27-I27 -> 147296.43 | K27: S/L | L27: 27.5
A28: 9 | B28: 8-Northiew Dr - 5 Year | C28: 7/30/24 | D28: 4435.53 | E28: 0 | F28: 2661.32 | G28: 0 | H28: 3016.16 | I28: =G28+H28 -> 3016.16 | J28: =D28-I28 -> 1419.37 | K28: 200DB | L28: 5.0
A29: 10 | B29: 8-Northiew Dr - 27.5 Year | C29: 7/30/24 | D29: 19328.12 | E29: 0 | F29: 0 | G29: 0 | H29: 322.14 | I29: =G29+H29 -> 322.14 | J29: =D29-I29 -> 19005.98 | K29: S/L | L29: 27.5
A30: 11 | B30: 9-Northview Dr - 5 Year | C30: 7/30/24 | D30: 8316.62 | E30: 0 | F30: 4989.97 | G30: 0 | H30: 5655.3 | I30: =G30+H30 -> 5655.3 | J30: =D30-I30 -> 2661.32 | K30: 200DB | L30: 5.0
A31: 12 | B31: 9-Northview Dr - 27.5 Year | C31: 7/30/24 | D31: 36240.25 | E31: 0 | F31: 0 | G31: 0 | H31: 604 | I31: =G31+H31 -> 604 | J31: =D31-I31 -> 35636.25 | K31: S/L | L31: 27.5
B32: Grand Total | D32: =SUM(D20:D31) -> 307313.67 | E32: =SUM(E20:E31) -> 0 | F32: =SUM(F20:F31) -> 34416.4 | G32: =SUM(G20:G31) -> 0 | H32: =SUM(H20:H31) -> 43171.13 | I32: =SUM(I20:I31) -> 43171.13 | J32: =SUM(J20:J31) -> 264142.54
B34: Section 481(a) Adjustment — Regular Tax
B35: Depreciation reported previously | D35: =I16 -> 58353.46
B36: Cost Segregation Corrected Depreciation | D36: =I32 -> 43171.13
B37: Section 481(a) Adjustment — Regular Tax | D37: =D35-D36 -> 15182.33
A39: CALCULATION OF §481(a) ADJUSTMENT — AMT
A40: As Previously Filed — AMT
A41: Asset | B41: Property Description | C41: Date In Service | D41: Cost | E41: Sec 179 Exp | F41: Bonus Amt | G41: AMT Prior Depreciation | H41: AMT Current Depreciation | I41: End Depreciation | J41: Net Book Value | K41: Method | L41: Period
A42: 1 | B42: 2-Building-712 Northfield Dr | C42: 7/30/24 | D42: 39989.86 | E42: 0 | F42: 0 | G42: 0 | H42: 666.51 | I42: =G42+H42 -> 666.51 | J42: =D42-I42 -> 39323.35 | K42: S/L | L42: 27.5
A43: 2 | B43: 3-Northfield Dr | C43: 7/30/24 | D43: 5159.97 | E43: 0 | F43: 3095.98 | G43: 0 | H43: 3164.8 | I43: =G43+H43 -> 3164.8 | J43: =D43-I43 -> 1995.17 | K43: 150DB | L43: 15.0
A44: 3 | B44: 4-Northfield Dr | C44: 7/30/24 | D44: 9674.97 | E44: 0 | F44: 5804.98 | G44: 0 | H44: 6578.97 | I44: =G44+H44 -> 6578.97 | J44: =D44-I44 -> 3096 | K44: 200DB | L44: 5.0
A45: 4 | B45: 7-Building-2202 Northview Dr | C45: 7/30/24 | D45: 184168.35 | E45: 0 | F45: 0 | G45: 0 | H45: 3069.46 | I45: =G45+H45 -> 3069.46 | J45: =D45-I45 -> 181098.89 | K45: S/L | L45: 27.5
A46: 5 | B46: 8-Northiew Dr | C46: 7/30/24 | D46: 23763.65 | E46: 0 | F46: 14258.19 | G46: 0 | H46: 14575.04 | I46: =G46+H46 -> 14575.04 | J46: =D46-I46 -> 9188.61 | K46: 150DB | L46: 15.0
A47: 6 | B47: 9-Northview Dr | C47: 7/30/24 | D47: 44556.87 | E47: 0 | F47: 26734.12 | G47: 0 | H47: 30298.68 | I47: =G47+H47 -> 30298.68 | J47: =D47-I47 -> 14258.19 | K47: 200DB | L47: 5.0
B48: Grand Total | D48: =SUM(D42:D47) -> 307313.67 | E48: =SUM(E42:E47) -> 0 | F48: =SUM(F42:F47) -> 49893.27 | G48: =SUM(G42:G47) -> 0 | H48: =SUM(H42:H47) -> 58353.46 | I48: =SUM(I42:I47) -> 58353.46 | J48: =SUM(J42:J47) -> 248960.21
A50: After Cost Segregation Correction — AMT
A51: Asset | B51: Property Description | C51: Date In Service | D51: Cost | E51: Sec 179 Exp | F51: Bonus Amt | G51: AMT Prior Depreciation | H51: AMT Current Depreciation | I51: End Depreciation | J51: Net Book Value | K51: Method | L51: Period
A52: 1 | B52: 2-Building-712 Northfield Dr - 5 Year | C52: 7/30/24 | D52: 7464.18 | E52: 0 | F52: 4478.51 | G52: 0 | H52: 5075.64 | I52: =G52+H52 -> 5075.64 | J52: =D52-I52 -> 2388.54 | K52: 200DB | L52: 5.0
A53: 2 | B53: 2-Building-712 Northfield Dr - 27.5 Year | C53: 7/30/24 | D53: 32525.68 | E53: 0 | F53: 0 | G53: 0 | H53: 542.09 | I53: =G53+H53 -> 542.09 | J53: =D53-I53 -> 31983.59 | K53: S/L | L53: 27.5
A54: 3 | B54: 3-Northfield Dr - 5 Year | C54: 7/30/24 | D54: 963.12 | E54: 0 | F54: 577.87 | G54: 0 | H54: 654.92 | I54: =G54+H54 -> 654.92 | J54: =D54-I54 -> 308.2 | K54: 200DB | L54: 5.0
A55: 4 | B55: 3-Northfield Dr - 27.5 Year | C55: 7/30/24 | D55: 4196.85 | E55: 0 | F55: 0 | G55: 0 | H55: 69.95 | I55: =G55+H55 -> 69.95 | J55: =D55-I55 -> 4126.9 | K55: S/L | L55: 27.5
A56: 5 | B56: 4-Northfield Dr - 5 Year | C56: 7/30/24 | D56: 1805.85 | E56: 0 | F56: 1083.51 | G56: 0 | H56: 1227.98 | I56: =G56+H56 -> 1227.98 | J56: =D56-I56 -> 577.87 | K56: 200DB | L56: 5.0
A57: 6 | B57: 4-Northfield Dr - 27.5 Year | C57: 7/30/24 | D57: 7869.12 | E57: 0 | F57: 0 | G57: 0 | H57: 131.15 | I57: =G57+H57 -> 131.15 | J57: =D57-I57 -> 7737.97 | K57: S/L | L57: 27.5
A58: 7 | B58: 7-Building-2202 Northview Dr - 5 Year | C58: 7/30/24 | D58: 34375.37 | E58: 0 | F58: 20625.22 | G58: 0 | H58: 23375.25 | I58: =G58+H58 -> 23375.25 | J58: =D58-I58 -> 11000.12 | K58: 200DB | L58: 5.0
A59: 8 | B59: 7-Building-2202 Northview Dr - 27.5 Year | C59: 7/30/24 | D59: 149792.98 | E59: 0 | F59: 0 | G59: 0 | H59: 2496.55 | I59: =G59+H59 -> 2496.55 | J59: =D59-I59 -> 147296.43 | K59: S/L | L59: 27.5
A60: 9 | B60: 8-Northiew Dr - 5 Year | C60: 7/30/24 | D60: 4435.53 | E60: 0 | F60: 2661.32 | G60: 0 | H60: 3016.16 | I60: =G60+H60 -> 3016.16 | J60: =D60-I60 -> 1419.37 | K60: 200DB | L60: 5.0
A61: 10 | B61: 8-Northiew Dr - 27.5 Year | C61: 7/30/24 | D61: 19328.12 | E61: 0 | F61: 0 | G61: 0 | H61: 322.14 | I61: =G61+H61 -> 322.14 | J61: =D61-I61 -> 19005.98 | K61: S/L | L61: 27.5
A62: 11 | B62: 9-Northview Dr - 5 Year | C62: 7/30/24 | D62: 8316.62 | E62: 0 | F62: 4989.97 | G62: 0 | H62: 5655.3 | I62: =G62+H62 -> 5655.3 | J62: =D62-I62 -> 2661.32 | K62: 200DB | L62: 5.0
A63: 12 | B63: 9-Northview Dr - 27.5 Year | C63: 7/30/24 | D63: 36240.25 | E63: 0 | F63: 0 | G63: 0 | H63: 604 | I63: =G63+H63 -> 604 | J63: =D63-I63 -> 35636.25 | K63: S/L | L63: 27.5
B64: Grand Total | D64: =SUM(D52:D63) -> 307313.67 | E64: =SUM(E52:E63) -> 0 | F64: =SUM(F52:F63) -> 34416.4 | G64: =SUM(G52:G63) -> 0 | H64: =SUM(H52:H63) -> 43171.13 | I64: =SUM(I52:I63) -> 43171.13 | J64: =SUM(J52:J63) -> 264142.54
B66: Section 481(a) Adjustment — AMT
B67: Depreciation reported previously | D67: =I48 -> 58353.46
B68: Cost Segregation Corrected Depreciation | D68: =I64 -> 43171.13
B69: Section 481(a) Adjustment — AMT | D69: =D67-D68 -> 15182.33
A71: COST SEGREGATION STUDY — COST SUMMARY
B72: Total Building Cost | D72: =D110 -> 307313.67
B73: Building Components: 5 Year | D73: =F110 -> 57360.67
B74: % of Cost | D74: =F111 -> 0.18665187
B75: Building Structure: 27.5 Year | D75: =H110 -> 249953
B76: % of Cost | D76: =H111 -> 0.81334813
A78: COST SEGREGATION STUDY — COST DETAIL
B79: Property Category | D79: Cost | F79: 5 Year | H79: 27.5 Year
B80: Building Components
B81: Cabinets / Millwork | D81: =SUM(F81:H81) -> 13303.54 | F81: 13303.54
B82: Moldings | D82: =SUM(F82:H82) -> 4028.66 | F82: 4028.66
B83: Flooring - Wood Laminate | D83: =SUM(F83:H83) -> 18880 | F83: 18880
B84: Window Treatments | D84: =SUM(F84:H84) -> 4380.58 | F84: 4380.58
B85: Building Signage | D85: =SUM(F85:H85) -> 120.21 | F85: 120.21
B86: Specialty Electrical - Appliances | D86: =SUM(F86:H86) -> 2691.07 | F86: 2691.07
B87: Communication / Data | D87: =SUM(F87:H87) -> 2330.78 | F87: 2330.78
B88: Specialty Plumbing - Kitchen Sinks | D88: =SUM(F88:H88) -> 4922.4 | F88: 4922.4
B89: Security / Exterior Lighting | D89: =SUM(F89:H89) -> 2107.3 | F89: 2107.3
B90: Access Control | D90: =SUM(F90:H90) -> 79.75 | F90: 79.75
B91: Entry Canopies | D91: =SUM(F91:H91) -> 269.71 | F91: 269.71
B92: Appliances | D92: =SUM(F92:H92) -> 4246.67 | F92: 4246.67
B93: Building Structure
B94: Roofing Systems | D94: =SUM(F94:H94) -> 14675.94 | H94: 14675.94
B95: Foundations | D95: =SUM(F95:H95) -> 17193.38 | H95: 17193.38
B96: HVAC | D96: =SUM(F96:H96) -> 26236.29 | H96: 26236.29
B97: Electrical | D97: =SUM(F97:H97) -> 28355.25 | H97: 28355.25
B98: Plumbing | D98: =SUM(F98:H98) -> 22807.05 | H98: 22807.05
B99: Fire Protection & Alarm | D99: =SUM(F99:H99) -> 1962.21 | H99: 1962.21
