Workbook

Sheet Summary
A1: Silver Springs Housing, LP
A2: Silver Spring Terrace Apartments — 950 20th St NE, Hickory, NC 28601
A3: EIN: 82-0773652 · FYE: December 31, 2024 · Year of Change: 1/1/2024
A4: Summary of Cost Segregation Adjustments — CSSI Report #107752-39 (CAM — DCN #7)
A5: All unit columns are linked to the individual unit tabs; totals and 481(a) figures are live formulas.
A7: Acq Date | B7: Asset Description | C7: Total | D7: Site | E7: Office | F7: Building 1 | G7: Building 2 | H7: Building 3 | I7: Building 5 | J7: Building 6 | K7: Building 7 | L7: Building 8 | M7: Building 9 | N7: Building 10 | O7: Building 11 | P7: Building 12 | Q7: Building 13 | R7: Building 14 | S7: Building 15 | T7: Building 16 | U7: Building 17 | V7: Maintenance Building | W7: Asset #15
A8: 9/15/21 | B8: Asset # 19-Building - 754 "Menowitz" | C8: =SUM(D8:W8) -> 10818 | D8: =Site!$D$10 -> 1183.32 | E8: =Office!$D$10 -> 262.41 | F8: ='Building 1'!$D$10 -> 662.06 | G8: ='Building 2'!$D$10 -> 662.06 | H8: ='Building 3'!$D$10 -> 662.06 | I8: ='Building 5'!$D$10 -> 479.53 | J8: ='Building 6'!$D$10 -> 750.82 | K8: ='Building 7'!$D$10 -> 750.82 | L8: ='Building 8'!$D$10 -> 479.53 | M8: ='Building 9'!$D$10 -> 750.82 | N8: ='Building 10'!$D$10 -> 750.82 | O8: ='Building 11'!$D$10 -> 662.06 | P8: ='Building 12'!$D$10 -> 479.53 | Q8: ='Building 13'!$D$10 -> 479.53 | R8: ='Building 14'!$D$10 -> 407.79 | S8: ='Building 15'!$D$10 -> 316.3 | T8: ='Building 16'!$D$10 -> 316.3 | U8: ='Building 17'!$D$10 -> 750.82 | V8: ='Maintenance Building'!$D$10 -> 11.42
A9: 5/31/17 | B9: Asset # 3-Building | C9: =SUM(D9:W9) -> 3219130 | D9: =Site!$D$11 -> 352122.24 | E9: =Office!$D$11 -> 78086.63 | F9: ='Building 1'!$D$11 -> 197009.25 | G9: ='Building 2'!$D$11 -> 197009.25 | H9: ='Building 3'!$D$11 -> 197009.25 | I9: ='Building 5'!$D$11 -> 142694.3 | J9: ='Building 6'!$D$11 -> 223422.8 | K9: ='Building 7'!$D$11 -> 223422.8 | L9: ='Building 8'!$D$11 -> 142694.3 | M9: ='Building 9'!$D$11 -> 223422.8 | N9: ='Building 10'!$D$11 -> 223422.8 | O9: ='Building 11'!$D$11 -> 197009.25 | P9: ='Building 12'!$D$11 -> 142694.3 | Q9: ='Building 13'!$D$11 -> 142694.3 | R9: ='Building 14'!$D$11 -> 121347 | S9: ='Building 15'!$D$11 -> 94123.92 | T9: ='Building 16'!$D$11 -> 94123.92 | U9: ='Building 17'!$D$11 -> 223422.8 | V9: ='Maintenance Building'!$D$11 -> 3398.09
A10: 5/31/17 | B10: Asset # 4-Personal Property | C10: =SUM(D10:W10) -> 200000 | D10: =Site!$D$12 -> 21876.86 | E10: =Office!$D$12 -> 4851.41 | F10: ='Building 1'!$D$12 -> 12239.91 | G10: ='Building 2'!$D$12 -> 12239.91 | H10: ='Building 3'!$D$12 -> 12239.91 | I10: ='Building 5'!$D$12 -> 8865.4 | J10: ='Building 6'!$D$12 -> 13880.94 | K10: ='Building 7'!$D$12 -> 13880.94 | L10: ='Building 8'!$D$12 -> 8865.4 | M10: ='Building 9'!$D$12 -> 13880.94 | N10: ='Building 10'!$D$12 -> 13880.94 | O10: ='Building 11'!$D$12 -> 12239.91 | P10: ='Building 12'!$D$12 -> 8865.4 | Q10: ='Building 13'!$D$12 -> 8865.4 | R10: ='Building 14'!$D$12 -> 7539.11 | S10: ='Building 15'!$D$12 -> 5847.79 | T10: ='Building 16'!$D$12 -> 5847.79 | U10: ='Building 17'!$D$12 -> 13880.94 | V10: ='Maintenance Building'!$D$12 -> 211.1
A11: 5/31/17 | B11: Asset # 2-Land Improvements | C11: =SUM(D11:W11) -> 400000 | D11: =Site!$D$13 -> 43753.71 | E11: =Office!$D$13 -> 9702.83 | F11: ='Building 1'!$D$13 -> 24479.81 | G11: ='Building 2'!$D$13 -> 24479.81 | H11: ='Building 3'!$D$13 -> 24479.81 | I11: ='Building 5'!$D$13 -> 17730.79 | J11: ='Building 6'!$D$13 -> 27761.89 | K11: ='Building 7'!$D$13 -> 27761.89 | L11: ='Building 8'!$D$13 -> 17730.79 | M11: ='Building 9'!$D$13 -> 27761.89 | N11: ='Building 10'!$D$13 -> 27761.89 | O11: ='Building 11'!$D$13 -> 24479.81 | P11: ='Building 12'!$D$13 -> 17730.79 | Q11: ='Building 13'!$D$13 -> 17730.79 | R11: ='Building 14'!$D$13 -> 15078.24 | S11: ='Building 15'!$D$13 -> 11695.57 | T11: ='Building 16'!$D$13 -> 11695.57 | U11: ='Building 17'!$D$13 -> 27761.89 | V11: ='Maintenance Building'!$D$13 -> 422.23
A12: 5/01/21 | B12: Asset # 15-Building Improvements | C12: =SUM(D12:W12) -> 87540 | W12: ='Asset #15'!$D$10 -> 87540
B13: Grand Total | C13: =SUM(C8:C12) -> 3917488 | D13: =SUM(D8:D12) -> 418936.13 | E13: =SUM(E8:E12) -> 92903.28 | F13: =SUM(F8:F12) -> 234391.03 | G13: =SUM(G8:G12) -> 234391.03 | H13: =SUM(H8:H12) -> 234391.03 | I13: =SUM(I8:I12) -> 169770.02 | J13: =SUM(J8:J12) -> 265816.45 | ... W13: =SUM(W8:W12) -> 87540
B15: MACRS Reclassification
B16: Asset # 19-Building - 754 "Menowitz" - 5yr | C16: =SUM(D16:W16) -> 1954.79 | E16: =Office!$D$18 -> 53.44 | F16: ='Building 1'!$D$18 -> 137.19 | G16: ='Building 2'!$D$18 -> 137.19 | H16: ='Building 3'!$D$18 -> 137.19 | I16: ='Building 5'!$D$18 -> 89.94 | J16: ='Building 6'!$D$18 -> 157.52 | K16: ='Building 7'!$D$18 -> 157.52 | L16: ='Building 8'!$D$18 -> 89.94 | M16: ='Building 9'!$D$18 -> 157.52 | N16: ='Building 10'!$D$18 -> 157.52 | O16: ='Building 11'!$D$18 -> 137.19 | P16: ='Building 12'!$D$18 -> 89.94 | Q16: ='Building 13'!$D$18 -> 89.94 | R16: ='Building 14'!$D$18 -> 77.21 | S16: ='Building 15'!$D$18 -> 63.33 | T16: ='Building 16'!$D$18 -> 63.33 | U16: ='Building 17'!$D$18 -> 157.52 | V16: ='Maintenance Building'!$D$18 -> 1.36
B17: Asset # 19-Building - 754 "Menowitz" - Site-15yr | C17: =SUM(D17:W17) -> 802.92 | D17: =Site!$D$18 -> 802.92
B18: Asset # 19-Building - 754 "Menowitz" - 30yr | C18: =SUM(D18:W18) -> 8060.29 | D18: =Site!$D$19 -> 380.4 | E18: =Office!$D$19 -> 208.97 | F18: ='Building 1'!$D$19 -> 524.87 | G18: ='Building 2'!$D$19 -> 524.87 | H18: ='Building 3'!$D$19 -> 524.87 | I18: ='Building 5'!$D$19 -> 389.59 | J18: ='Building 6'!$D$19 -> 593.3 | K18: ='Building 7'!$D$19 -> 593.3 | L18: ='Building 8'!$D$19 -> 389.59 | M18: ='Building 9'!$D$19 -> 593.3 | N18: ='Building 10'!$D$19 -> 593.3 | O18: ='Building 11'!$D$19 -> 524.87 | P18: ='Building 12'!$D$19 -> 389.59 | Q18: ='Building 13'!$D$19 -> 389.59 | R18: ='Building 14'!$D$19 -> 330.58 | S18: ='Building 15'!$D$19 -> 252.97 | T18: ='Building 16'!$D$19 -> 252.97 | U18: ='Building 17'!$D$19 -> 593.3 | V18: ='Maintenance Building'!$D$19 -> 10.06
B19: Asset # 3-Building - 5yr | C19: =SUM(D19:W19) -> 581688.28 | E19: =Office!$D$20 -> 15901.52 | F19: ='Building 1'!$D$20 -> 40824.27 | G19: ='Building 2'!$D$20 -> 40824.27 | H19: ='Building 3'!$D$20 -> 40824.27 | I19: ='Building 5'!$D$20 -> 26763.65 | J19: ='Building 6'!$D$20 -> 46872.91 | K19: ='Building 7'!$D$20 -> 46872.91 | L19: ='Building 8'!$D$20 -> 26763.65 | M19: ='Building 9'!$D$20 -> 46872.91 | N19: ='Building 10'!$D$20 -> 46872.91 | O19: ='Building 11'!$D$20 -> 40824.27 | P19: ='Building 12'!$D$20 -> 26763.65 | Q19: ='Building 13'!$D$20 -> 26763.65 | R19: ='Building 14'!$D$20 -> 22974.45 | S19: ='Building 15'!$D$20 -> 18845.76 | T19: ='Building 16'!$D$20 -> 18845.76 | U19: ='Building 17'!$D$20 -> 46872.91 | V19: ='Maintenance Building'!$D$20 -> 404.56
B20: Asset # 3-Building - Site-15yr | C20: =SUM(D20:W20) -> 238926.62 | D20: =Site!$D$20 -> 238926.62
B21: Asset # 3-Building - 30yr | C21: =SUM(D21:W21) -> 2398515.1 | D21: =Site!$D$21 -> 113195.62 | E21: =Office!$D$21 -> 62185.11 | F21: ='Building 1'!$D$21 -> 156184.98 | G21: ='Building 2'!$D$21 -> 156184.98 | H21: ='Building 3'!$D$21 -> 156184.98 | I21: ='Building 5'!$D$21 -> 115930.65 | J21: ='Building 6'!$D$21 -> 176549.89 | K21: ='Building 7'!$D$21 -> 176549.89 | L21: ='Building 8'!$D$21 -> 115930.65 | M21: ='Building 9'!$D$21 -> 176549.89 | N21: ='Building 10'!$D$21 -> 176549.89 | O21: ='Building 11'!$D$21 -> 156184.98 | P21: ='Building 12'!$D$21 -> 115930.65 | Q21: ='Building 13'!$D$21 -> 115930.65 | R21: ='Building 14'!$D$21 -> 98372.55 | S21: ='Building 15'!$D$21 -> 75278.16 | T21: ='Building 16'!$D$21 -> 75278.16 | U21: ='Building 17'!$D$21 -> 176549.89 | V21: ='Maintenance Building'!$D$21 -> 2993.53
B22: Asset # 4-Personal Property - 5yr | C22: =SUM(D22:W22) -> 36139.47 | E22: =Office!$D$22 -> 987.94 | F22: ='Building 1'!$D$22 -> 2536.35 | G22: ='Building 2'!$D$22 -> 2536.35 | H22: ='Building 3'!$D$22 -> 2536.35 | I22: ='Building 5'!$D$22 -> 1662.79 | J22: ='Building 6'!$D$22 -> 2912.15 | K22: ='Building 7'!$D$22 -> 2912.15 | L22: ='Building 8'!$D$22 -> 1662.79 | M22: ='Building 9'!$D$22 -> 2912.15 | N22: ='Building 10'!$D$22 -> 2912.15 | O22: ='Building 11'!$D$22 -> 2536.35 | P22: ='Building 12'!$D$22 -> 1662.79 | Q22: ='Building 13'!$D$22 -> 1662.79 | R22: ='Building 14'!$D$22 -> 1427.37 | S22: ='Building 15'!$D$22 -> 1170.86 | T22: ='Building 16'!$D$22 -> 1170.86 | U22: ='Building 17'!$D$22 -> 2912.15 | V22: ='Maintenance Building'!$D$22 -> 25.13
B23: Asset # 4-Personal Property - Site-15yr | C23: =SUM(D23:W23) -> 14844.18 | D23: =Site!$D$22 -> 14844.18
B24: Asset # 4-Personal Property - 30yr | C24: =SUM(D24:W24) -> 149016.35 | D24: =Site!$D$23 -> 7032.68 | E24: =Office!$D$23 -> 3863.47 | F24: ='Building 1'!$D$23 -> 9703.56 | G24: ='Building 2'!$D$23 -> 9703.56 | H24: ='Building 3'!$D$23 -> 9703.56 | I24: ='Building 5'!$D$23 -> 7202.61 | J24: ='Building 6'!$D$23 -> 10968.79 | K24: ='Building 7'!$D$23 -> 10968.79 | L24: ='Building 8'!$D$23 -> 7202.61 | M24: ='Building 9'!$D$23 -> 10968.79 | N24: ='Building 10'!$D$23 -> 10968.79 | O24: ='Building 11'!$D$23 -> 9703.56 | P24: ='Building 12'!$D$23 -> 7202.61 | Q24: ='Building 13'!$D$23 -> 7202.61 | R24: ='Building 14'!$D$23 -> 6111.74 | S24: ='Building 15'!$D$23 -> 4676.93 | T24: ='Building 16'!$D$23 -> 4676.93 | U24: ='Building 17'!$D$23 -> 10968.79 | V24: ='Maintenance Building'!$D$23 -> 185.97
B25: Asset # 2-Land Improvements - 5yr | C25: =SUM(D25:W25) -> 72278.9 | E25: =Office!$D$24 -> 1975.88 | F25: ='Building 1'!$D$24 -> 5072.71 | G25: ='Building 2'!$D$24 -> 5072.71 | H25: ='Building 3'!$D$24 -> 5072.71 | I25: ='Building 5'!$D$24 -> 3325.57 | J25: ='Building 6'!$D$24 -> 5824.29 | K25: ='Building 7'!$D$24 -> 5824.29 | L25: ='Building 8'!$D$24 -> 3325.57 | M25: ='Building 9'!$D$24 -> 5824.29 | N25: ='Building 10'!$D$24 -> 5824.29 | O25: ='Building 11'!$D$24 -> 5072.71 | P25: ='Building 12'!$D$24 -> 3325.57 | Q25: ='Building 13'!$D$24 -> 3325.57 | R25: ='Building 14'!$D$24 -> 2854.74 | S25: ='Building 15'!$D$24 -> 2341.72 | T25: ='Building 16'!$D$24 -> 2341.72 | U25: ='Building 17'!$D$24 -> 5824.29 | V25: ='Maintenance Building'!$D$24 -> 50.27
B26: Asset # 2-Land Improvements - Site-15yr | C26: =SUM(D26:W26) -> 29688.34 | D26: =Site!$D$24 -> 29688.34
B27: Asset # 2-Land Improvements - 30yr | C27: =SUM(D27:W27) -> 298032.76 | D27: =Site!$D$25 -> 14065.37 | E27: =Office!$D$25 -> 7726.95 | F27: ='Building 1'!$D$25 -> 19407.1 | G27: ='Building 2'!$D$25 -> 19407.1 | H27: ='Building 3'!$D$25 -> 19407.1 | I27: ='Building 5'!$D$25 -> 14405.22 | J27: ='Building 6'!$D$25 -> 21937.6 | K27: ='Building 7'!$D$25 -> 21937.6 | L27: ='Building 8'!$D$25 -> 14405.22 | M27: ='Building 9'!$D$25 -> 21937.6 | N27: ='Building 10'!$D$25 -> 21937.6 | O27: ='Building 11'!$D$25 -> 19407.1 | P27: ='Building 12'!$D$25 -> 14405.22 | Q27: ='Building 13'!$D$25 -> 14405.22 | R27: ='Building 14'!$D$25 -> 12223.5 | S27: ='Building 15'!$D$25 -> 9353.85 | T27: ='Building 16'!$D$25 -> 9353.85 | U27: ='Building 17'!$D$25 -> 21937.6 | V27: ='Maintenance Building'!$D$25 -> 371.96
B28: Asset # 15-Building Improvements - 5yr | C28: =SUM(D28:W28) -> 25900 | W28: ='Asset #15'!$D$15 -> 25900
B29: Asset # 15-Building Improvements - 30yr | C29: =SUM(D29:W29) -> 61640 | W29: ='Asset #15'!$D$16 -> 61640
B30: Total MACRS Reclassification | C30: =SUM(C16:C29) -> 3917488 | D30: =SUM(D16:D29) -> 418936.13 | E30: =SUM(E16:E29) -> 92903.28 | F30: =SUM(F16:F29) -> 234391.03 | G30: =SUM(G16:G29) -> 234391.03 | H30: =SUM(H16:H29) -> 234391.03 | I30: =SUM(I16:I29) -> 169770.02 | J30: =SUM(J16:J29) -> 265816.45 | ... W30: =SUM(W16:W29) -> 87540
B31: Difference (should be zero) | C31: =C13-C30 -> 0 | D31: =D13-D30 -> 0 | E31: =E13-E30 -> 0 | F31: =F13-F30 -> 0 | G31: =G13-G30 -> 0 | H31: =H13-H30 -> 0 | I31: =I13-I30 -> 0 | J31: =J13-J30 -> 0 | ... W31: =W13-W30 -> 0
B33: End Depreciation Reconciliation
B34: Before Cost Segregation (As Previously Filed) | C34: =SUM(D34:W34) -> 1180668.9 | D34: =Site!$I$14 -> 128215.81 | E34: =Office!$I$14 -> 28433.18 | F34: ='Building 1'!$I$14 -> 71735.7 | G34: ='Building 2'!$I$14 -> 71735.7 | H34: ='Building 3'!$I$14 -> 71735.7 | I34: ='Building 5'!$I$14 -> 51958.37 | J34: ='Building 6'!$I$14 -> 81353.51 | K34: ='Building 7'!$I$14 -> 81353.51 | L34: ='Building 8'!$I$14 -> 51958.37 | M34: ='Building 9'!$I$14 -> 81353.51 | N34: ='Building 10'!$I$14 -> 81353.51 | O34: ='Building 11'!$I$14 -> 71735.7 | P34: ='Building 12'!$I$14 -> 51958.37 | Q34: ='Building 13'!$I$14 -> 51958.37 | R34: ='Building 14'!$I$14 -> 44185.31 | S34: ='Building 15'!$I$14 -> 34272.73 | T34: ='Building 16'!$I$14 -> 34272.73 | U34: ='Building 17'!$I$14 -> 81353.51 | V34: ='Maintenance Building'!$I$14 -> 1237.3 | W34: ='Asset #15'!$I$11 -> 8508
B35: Asset # 19-Building - 754 "Menowitz" - 5yr | C35: =SUM(D35:W35) -> 1954.79 | E35: =Office!$I$18 -> 53.44 | F35: ='Building 1'!$I$18 -> 137.19 | G35: ='Building 2'!$I$18 -> 137.19 | H35: ='Building 3'!$I$18 -> 137.19 | I35: ='Building 5'!$I$18 -> 89.94 | J35: ='Building 6'!$I$18 -> 157.52 | K35: ='Building 7'!$I$18 -> 157.52 | L35: ='Building 8'!$I$18 -> 89.94 | M35: ='Building 9'!$I$18 -> 157.52 | N35: ='Building 10'!$I$18 -> 157.52 | O35: ='Building 11'!$I$18 -> 137.19 | P35: ='Building 12'!$I$18 -> 89.94 | Q35: ='Building 13'!$I$18 -> 89.94 | R35: ='Building 14'!$I$18 -> 77.21 | S35: ='Building 15'!$I$18 -> 63.33 | T35: ='Building 16'!$I$18 -> 63.33 | U35: ='Building 17'!$I$18 -> 157.52 | V35: ='Maintenance Building'!$I$18 -> 1.36
B36: Asset # 19-Building - 754 "Menowitz" - Site-15yr | C36: =SUM(D36:W36) -> 802.92 | D36: =Site!$I$18 -> 802.92
B37: Asset # 19-Building - 754 "Menowitz" - 30yr | C37: =SUM(D37:W37) -> 884.56 | D37: =Site!$I$19 -> 41.74 | E37: =Office!$I$19 -> 22.94 | F37: ='Building 1'!$I$19 -> 57.6 | G37: ='Building 2'!$I$19 -> 57.6 | H37: ='Building 3'!$I$19 -> 57.6 | I37: ='Building 5'!$I$19 -> 42.76 | J37: ='Building 6'!$I$19 -> 65.11 | K37: ='Building 7'!$I$19 -> 65.11 | L37: ='Building 8'!$I$19 -> 42.76 | M37: ='Building 9'!$I$19 -> 65.11 | N37: ='Building 10'!$I$19 -> 65.11 | O37: ='Building 11'!$I$19 -> 57.6 | P37: ='Building 12'!$I$19 -> 42.76 | Q37: ='Building 13'!$I$19 -> 42.76 | R37: ='Building 14'!$I$19 -> 36.27 | S37: ='Building 15'!$I$19 -> 27.75 | T37: ='Building 16'!$I$19 -> 27.75 | U37: ='Building 17'!$I$19 -> 65.11 | V37: ='Maintenance Building'!$I$19 -> 1.12
B38: Asset # 3-Building - 5yr | C38: =SUM(D38:W38) -> 581688.28 | E38: =Office!$I$20 -> 15901.52 | F38: ='Building 1'!$I$20 -> 40824.27 | G38: ='Building 2'!$I$20 -> 40824.27 | H38: ='Building 3'!$I$20 -> 40824.27 | I38: ='Building 5'!$I$20 -> 26763.65 | J38: ='Building 6'!$I$20 -> 46872.91 | K38: ='Building 7'!$I$20 -> 46872.91 | L38: ='Building 8'!$I$20 -> 26763.65 | M38: ='Building 9'!$I$20 -> 46872.91 | N38: ='Building 10'!$I$20 -> 46872.91 | O38: ='Building 11'!$I$20 -> 40824.27 | P38: ='Building 12'!$I$20 -> 26763.65 | Q38: ='Building 13'!$I$20 -> 26763.65 | R38: ='Building 14'!$I$20 -> 22974.45 | S38: ='Building 15'!$I$20 -> 18845.76 | T38: ='Building 16'!$I$20 -> 18845.76 | U38: ='Building 17'!$I$20 -> 46872.91 | V38: ='Maintenance Building'!$I$20 -> 404.56
B39: Asset # 3-Building - Site-15yr | C39: =SUM(D39:W39) -> 133113.79 | D39: =Site!$I$20 -> 133113.79
B40: Asset # 3-Building - 30yr | C40: =SUM(D40:W40) -> 609622.68 | D40: =Site!$I$21 -> 28770.57 | E40: =Office!$I$21 -> 15805.4 | F40: ='Building 1'!$I$21 -> 39697.04 | G40: ='Building 2'!$I$21 -> 39697.04 | H40: ='Building 3'!$I$21 -> 39697.04 | I40: ='Building 5'!$I$21 -> 29465.67 | J40: ='Building 6'!$I$21 -> 44873.12 | K40: ='Building 7'!$I$21 -> 44873.12 | L40: ='Building 8'!$I$21 -> 29465.67 | M40: ='Building 9'!$I$21 -> 44873.12 | N40: ='Building 10'!$I$21 -> 44873.12 | O40: ='Building 11'!$I$21 -> 39697.04 | P40: ='Building 12'!$I$21 -> 29465.67 | Q40: ='Building 13'!$I$21 -> 29465.67 | R40: ='Building 14'!$I$21 -> 25003.06 | S40: ='Building 15'!$I$21 -> 19133.19 | T40: ='Building 16'!$I$21 -> 19133.19 | U40: ='Building 17'!$I$21 -> 44873.12 | V40: ='Maintenance Building'!$I$21 -> 760.83
B41: Asset # 4-Personal Property - 5yr | C41: =SUM(D41:W41) -> 36139.47 | E41: =Office!$I$22 -> 987.94 | F41: ='Building 1'!$I$22 -> 2536.35 | G41: ='Building 2'!$I$22 -> 2536.35 | H41: ='Building 3'!$I$22 -> 2536.35 | I41: ='Building 5'!$I$22 -> 1662.79 | J41: ='Building 6'!$I$22 -> 2912.15 | K41: ='Building 7'!$I$22 -> 2912.15 | L41: ='Building 8'!$I$22 -> 1662.79 | M41: ='Building 9'!$I$22 -> 2912.15 | N41: ='Building 10'!$I$22 -> 2912.15 | O41: ='Building 11'!$I$22 -> 2536.35 | P41: ='Building 12'!$I$22 -> 1662.79 | Q41: ='Building 13'!$I$22 -> 1662.79 | R41: ='Building 14'!$I$22 -> 1427.37 | S41: ='Building 15'!$I$22 -> 1170.86 | T41: ='Building 16'!$I$22 -> 1170.86 | U41: ='Building 17'!$I$22 -> 2912.15 | V41: ='Maintenance Building'!$I$22 -> 25.13
B42: Asset # 4-Personal Property - Site-15yr | C42: =SUM(D42:W42) -> 8270.17 | D42: =Site!$I$22 -> 8270.17
B43: Asset # 4-Personal Property - 30yr | C43: =SUM(D43:W43) -> 37875.13 | D43: =Site!$I$23 -> 1787.45 | E43: =Office!$I$23 -> 981.95 | F43: ='Building 1'!$I$23 -> 2466.31 | G43: ='Building 2'!$I$23 -> 2466.31 | H43: ='Building 3'!$I$23 -> 2466.31 | I43: ='Building 5'!$I$23 -> 1830.68 | J43: ='Building 6'!$I$23 -> 2787.93 | K43: ='Building 7'!$I$23 -> 2787.93 | L43: ='Building 8'!$I$23 -> 1830.68 | M43: ='Building 9'!$I$23 -> 2787.93 | N43: ='Building 10'!$I$23 -> 2787.93 | O43: ='Building 11'!$I$23 -> 2466.31 | P43: ='Building 12'!$I$23 -> 1830.68 | Q43: ='Building 13'!$I$23 -> 1830.68 | R43: ='Building 14'!$I$23 -> 1553.37 | S43: ='Building 15'!$I$23 -> 1188.74 | T43: ='Building 16'!$I$23 -> 1188.74 | U43: ='Building 17'!$I$23 -> 2787.93 | V43: ='Maintenance Building'!$I$23 -> 47.27
B44: Asset # 2-Land Improvements - 5yr | C44: =SUM(D44:W44) -> 72278.9 | E44: =Office!$I$24 -> 1975.88 | F44: ='Building 1'!$I$24 -> 5072.71 | G44: ='Building 2'!$I$24 -> 5072.71 | H44: ='Building 3'!$I$24 -> 5072.71 | I44: ='Building 5'!$I$24 -> 3325.57 | J44: ='Building 6'!$I$24 -> 5824.29 | K44: ='Building 7'!$I$24 -> 5824.29 | L44: ='Building 8'!$I$24 -> 3325.57 | M44: ='Building 9'!$I$24 -> 5824.29 | N44: ='Building 10'!$I$24 -> 5824.29 | O44: ='Building 11'!$I$24 -> 5072.71 | P44: ='Building 12'!$I$24 -> 3325.57 | Q44: ='Building 13'!$I$24 -> 3325.57 | R44: ='Building 14'!$I$24 -> 2854.74 | S44: ='Building 15'!$I$24 -> 2341.72 | T44: ='Building 16'!$I$24 -> 2341.72 | U44: ='Building 17'!$I$24 -> 5824.29 | V44: ='Maintenance Building'!$I$24 -> 50.27
B45: Asset # 2-Land Improvements - Site-15yr | C45: =SUM(D45:W45) -> 16540.35 | D45: =Site!$I$24 -> 16540.35
B46: Asset # 2-Land Improvements - 30yr | C46: =SUM(D46:W46) -> 76032.15 | D46: =Site!$I$25 -> 3857.34 | E46: =Office!$I$25 -> 1963.97 | F46: ='Building 1'!$I$25 -> 4932.61 | G46: ='Building 2'!$I$25 -> 4932.61 | H46: ='Building 3'!$I$25 -> 4932.61 | I46: ='Building 5'!$I$25 -> 3661.3 | J46: ='Building 6'!$I$25 -> 5575.78 | K46: ='Building 7'!$I$25 -> 5575.78 | L46: ='Building 8'!$I$25 -> 3661.3 | M46: ='Building 9'!$I$25 -> 5575.78 | N46: ='Building 10'!$I$25 -> 5575.78 | O46: ='Building 11'!$I$25 -> 4932.61 | P46: ='Building 12'!$I$25 -> 3661.3 | Q46: ='Building 13'!$I$25 -> 3661.3 | R46: ='Building 14'!$I$25 -> 3106.81 | S46: ='Building 15'!$I$25 -> 2377.47 | T46: ='Building 16'!$I$25 -> 2377.47 | U46: ='Building 17'!$I$25 -> 5575.78 | V46: ='Maintenance Building'!$I$25 -> 94.55
B47: Asset # 15-Building Improvements - 5yr | C47: =SUM(D47:W47) -> 25900 | W47: ='Asset #15'!$I$15 -> 25900
B48: Asset # 15-Building Improvements - 30yr | C48: =SUM(D48:W48) -> 7448.18 | W48: ='Asset #15'!$I$16 -> 7448.18
B49: After Cost Segregation (Corrected) | C49: =SUM(C35:C48) -> 1608551.4 | D49: =SUM(D35:D48) -> 193184.33 | E49: =SUM(E35:E48) -> 37693.04 | F49: =SUM(F35:F48) -> 95724.08 | G49: =SUM(G35:G48) -> 95724.08 | H49: =SUM(H35:H48) -> 95724.08 | I49: =SUM(I35:I48) -> 66842.36 | J49: =SUM(J35:J48) -> 109068.81 | ... W49: =SUM(W35:W48) -> 33348.18
B50: Section 481(a) Adjustment | C50: =C34-C49 -> -427882.48 | D50: =D34-D49 -> -64968.52 | E50: =E34-E49 -> -9259.86 | F50: =F34-F49 -> -23988.38 | G50: =G34-G49 -> -23988.38 | H50: =H34-H49 -> -23988.38 | I50: =I34-I49 -> -14883.99 | J50: =J34-J49 -> -27715.3 | ... W50: =W34-W49 -> -24840.18
B51: Check vs. unit-tab 481(a) cells (should be zero) | C51: =C50-(-427882.48) -> 0 | D51: =D50-(Site!$D$31) -> 0 | E51: =E50-(Office!$D$31) -> 0 | F51: =F50-('Building 1'!$D$31) -> 0 | G51: =G50-('Building 2'!$D$31) -> 0 | H51: =H50-('Building 3'!$D$31) -> 0 | I51: =I50-('Building 5'!$D$31) -> 0 | J51: =J50-('Building 6'!$D$31) -> 0 | K51: =K50-('Building 7'!$D$31) -> 0 | L51: =L50-('Building 8'!$D$31) -> 0 | M51: =M50-('Building 9'!$D$31) -> 0 | N51: =N50-('Building 10'!$D$31) -> 0 | O51: =O50-('Building 11'!$D$31) -> 0 | P51: =P50-('Building 12'!$D$31) -> 0 | Q51: =Q50-('Building 13'!$D$31) -> 0 | R51: =R50-('Building 14'!$D$31) -> 0 | S51: =S50-('Building 15'!$D$31) -> 0 | T51: =T50-('Building 16'!$D$31) -> 0 | U51: =U50-('Building 17'!$D$31) -> 0 | V51: =V50-('Maintenance Building'!$D$31) -> 0 | W51: =W50-('Asset #15'!$D$22) -> 0
B53: Notes
B54: 1. Total column ties to the CSSI report: total negative §481(a) adjustment of ($427,882.48) — Regular Tax; AMT equals Regular Tax for every unit.
B55: 2. Structure reclassified to a 30-year S/L recovery period per the depreciation schedules; the Building 2 Cost Summary page of the PDF labels
B56: structure as 27.5-year, but its depreciation schedule uses 30-year S/L consistent with every other unit — 30-year is used throughout.
B57: 3. Bonus depreciation (100%) applies to the 754 "Menowitz" (9/15/21) and Asset #15 Building Improvements (5/01/21) reclassified components.
B58: 4. Every unit column links live to that unit's tab; the Difference and Check rows must remain zero after any edit.

Sheet Site
A1: Silver Springs Housing, LP
A2: Silver Spring Terrace Apartments — 950 20th St NE, Hickory, NC 28601
A3: EIN: 82-0773652 · FYE: December 31, 2024 · Year of Change: 1/1/2024
A4: Site — Attachment to Form 3115 (DCN #7, Rev. Proc. 2024-23 §6.01)
A5: Source: CSSI Report #107752-39, "Silver Springs Housing LP_#107752-39_3115_Combined R1.pdf"
A7: CALCULATION OF §481(a) ADJUSTMENT — REGULAR TAX
A8: As Previously Filed
A9: Asset | B9: Property Description | C9: Date In Service | D9: Cost | E9: Sec 179 Exp | F9: Bonus Amt | G9: Tax Prior Depreciation | H9: Tax Current Depreciation | I9: End Depreciation | J9: Net Book Value | K9: Method | L9: Period
A10: 1 | B10: 19 - Building - 754 "Menowitz" | C10: 9/15/21 | D10: 1183.32 | E10: 0 | F10: 0 | G10: 71.65 | H10: 29.43 | I10: =G10+H10 -> 101.08 | J10: =D10-I10 -> 1082.24 | K10: S/L | L10: 40.00
A11: 2 | B11: 3 - Building | C11: 5/31/17 | D11: 352122.24 | E11: 0 | F11: 0 | G11: 75780.32 | H11: 8280.01 | I11: =G11+H11 -> 84060.33 | J11: =D11-I11 -> 268061.91 | K11: S/L | L11: 40.00
A12: 3 | B12: 4 - Personal Property | C12: 5/31/17 | D12: 21876.86 | E12: 0 | F12: 0 | G12: 20418.39 | H12: 0 | I12: =G12+H12 -> 20418.39 | J12: =D12-I12 -> 1458.47 | K12: S/L | L12: 40.00
A13: 4 | B13: 2 - Land Improvements | C13: 5/31/17 | D13: 43753.71 | E13: 0 | F13: 0 | G13: 21054.54 | H13: 2581.47 | I13: =G13+H13 -> 23636.01 | J13: =D13-I13 -> 20117.7 | K13: S/L | L13: 40.00
B14: Grand Total | D14: =SUM(D10:D13) -> 418936.13 | E14: =SUM(E10:E13) -> 0 | F14: =SUM(F10:F13) -> 0 | G14: =SUM(G10:G13) -> 117324.9 | H14: =SUM(H10:H13) -> 10890.91 | I14: =SUM(I10:I13) -> 128215.81 | J14: =SUM(J10:J13) -> 290720.32
A16: After Cost Segregation Correction
A17: Asset | B17: Property Description | C17: Date In Service | D17: Cost | E17: Sec 179 Exp | F17: Bonus Amt | G17: Tax Prior Depreciation | H17: Tax Current Depreciation | I17: End Depreciation | J17: Net Book Value | K17: Method | L17: Period
A18: 1 | B18: 19 - Building - 754 "Menowitz" - 15 year | C18: 9/15/21 | D18: 802.92 | E18: 0 | F18: 802.92 | G18: 802.92 | H18: 0 | I18: =G18+H18 -> 802.92 | J18: =D18-I18 -> 0 | K18: 150DB | L18: 15.0
A19: 2 | B19: 19 - Building - 754 "Menowitz" - 30 year | C19: 9/15/21 | D19: 380.4 | E19: 0 | F19: 0 | G19: 29.06 | H19: 12.68 | I19: =G19+H19 -> 41.74 | J19: =D19-I19 -> 338.66 | K19: S/L | L19: 30.00
A20: 3 | B20: 3 - Building - 15 year | C20: 5/31/17 | D20: 238926.62 | E20: 0 | F20: 0 | G20: 119005.41 | H20: 14108.38 | I20: =G20+H20 -> 133113.79 | J20: =D20-I20 -> 105812.83 | K20: 150DB | L20: 15.0
A21: 4 | B21: 3 - Building - 30 year | C21: 5/31/17 | D21: 113195.62 | E21: 0 | F21: 0 | G21: 24997.38 | H21: 3773.19 | I21: =G21+H21 -> 28770.57 | J21: =D21-I21 -> 84425.05 | K21: S/L | L21: 30.00
A22: 5 | B22: 4 - Personal Property - 15 year | C22: 5/31/17 | D22: 14844.18 | E22: 0 | F22: 0 | G22: 7393.64 | H22: 876.53 | I22: =G22+H22 -> 8270.17 | J22: =D22-I22 -> 6574.01 | K22: 150DB | L22: 15.0
A23: 6 | B23: 4 - Personal Property - 30 year | C23: 5/31/17 | D23: 7032.68 | E23: 0 | F23: 0 | G23: 1553.03 | H23: 234.42 | I23: =G23+H23 -> 1787.45 | J23: =D23-I23 -> 5245.23 | K23: S/L | L23: 30.00
A24: 7 | B24: 2 - Land Improvements - 15 year | C24: 5/31/17 | D24: 29688.34 | E24: 0 | F24: 0 | G24: 14787.28 | H24: 1753.07 | I24: =G24+H24 -> 16540.35 | J24: =D24-I24 -> 13147.99 | K24: 150DB | L24: 15.0
A25: 8 | B25: 2 - Land Improvements - 30 year | C25: 5/31/17 | D25: 14065.37 | E25: 0 | F25: 0 | G25: 3388.49 | H25: 468.85 | I25: =G25+H25 -> 3857.34 | J25: =D25-I25 -> 10208.03 | K25: S/L | L25: 30.00
B26: Grand Total | D26: =SUM(D18:D25) -> 418936.13 | E26: =SUM(E18:E25) -> 0 | F26: =SUM(F18:F25) -> 802.92 | G26: =SUM(G18:G25) -> 171957.21 | H26: =SUM(H18:H25) -> 21227.12 | I26: =SUM(I18:I25) -> 193184.33 | J26: =SUM(J18:J25) -> 225751.8
B28: Section 481(a) Adjustment — Regular Tax
B29: Depreciation reported previously | D29: =I14 -> 128215.81
B30: Cost Segregation Corrected Depreciation | D30: =I26 -> 193184.33
B31: Section 481(a) Adjustment — Regular Tax | D31: =D29-D30 -> -64968.52
A33: CALCULATION OF §481(a) ADJUSTMENT — AMT
A34: As Previously Filed — AMT
A35: Asset | B35: Property Description | C35: Date In Service | D35: Cost | E35: Sec 179 Exp | F35: Bonus Amt | G35: AMT Prior Depreciation | H35: AMT Current Depreciation | I35: End Depreciation | J35: Net Book Value | K35: Method | L35: Period
A36: 1 | B36: 19 - Building - 754 "Menowitz" | C36: 9/15/21 | D36: 1183.32 | E36: 0 | F36: 0 | G36: 71.65 | H36: 29.43 | I36: =G36+H36 -> 101.08 | J36: =D36-I36 -> 1082.24 | K36: S/L | L36: 40.00
A37: 2 | B37: 3 - Building | C37: 5/31/17 | D37: 352122.24 | E37: 0 | F37: 0 | G37: 75780.32 | H37: 8280.01 | I37: =G37+H37 -> 84060.33 | J37: =D37-I37 -> 268061.91 | K37: S/L | L37: 40.00
A38: 3 | B38: 4 - Personal Property | C38: 5/31/17 | D38: 21876.86 | E38: 0 | F38: 0 | G38: 20418.39 | H38: 0 | I38: =G38+H38 -> 20418.39 | J38: =D38-I38 -> 1458.47 | K38: S/L | L38: 40.00
A39: 4 | B39: 2 - Land Improvements | C39: 5/31/17 | D39: 43753.71 | E39: 0 | F39: 0 | G39: 21054.54 | H39: 2581.47 | I39: =G39+H39 -> 23636.01 | J39: =D39-I39 -> 20117.7 | K39: S/L | L39: 40.00
B40: Grand Total | D40: =SUM(D36:D39) -> 418936.13 | E40: =SUM(E36:E39) -> 0 | F40: =SUM(F36:F39) -> 0 | G40: =SUM(G36:G39) -> 117324.9 | H40: =SUM(H36:H39) -> 10890.91 | I40: =SUM(I36:I39) -> 128215.81 | J40: =SUM(J36:J39) -> 290720.32
A42: After Cost Segregation Correction — AMT
A43: Asset | B43: Property Description | C43: Date In Service | D43: Cost | E43: Sec 179 Exp | F43: Bonus Amt | G43: AMT Prior Depreciation | H43: AMT Current Depreciation | I43: End Depreciation | J43: Net Book Value | K43: Method | L43: Period
A44: 1 | B44: 19 - Building - 754 "Menowitz" - 15 year | C44: 9/15/21 | D44: 802.92 | E44: 0 | F44: 802.92 | G44: 802.92 | H44: 0 | I44: =G44+H44 -> 802.92 | J44: =D44-I44 -> 0 | K44: 150DB | L44: 15.0
A45: 2 | B45: 19 - Building - 754 "Menowitz" - 30 year | C45: 9/15/21 | D45: 380.4 | E45: 0 | F45: 0 | G45: 29.06 | H45: 12.68 | I45: =G45+H45 -> 41.74 | J45: =D45-I45 -> 338.66 | K45: S/L | L45: 30.00
A46: 3 | B46: 3 - Building - 15 year | C46: 5/31/17 | D46: 238926.62 | E46: 0 | F46: 0 | G46: 119005.41 | H46: 14108.38 | I46: =G46+H46 -> 133113.79 | J46: =D46-I46 -> 105812.83 | K46: 150DB | L46: 15.0
A47: 4 | B47: 3 - Building - 30 year | C47: 5/31/17 | D47: 113195.62 | E47: 0 | F47: 0 | G47: 24997.38 | H47: 3773.19 | I47: =G47+H47 -> 28770.57 | J47: =D47-I47 -> 84425.05 | K47: S/L | L47: 30.00
A48: 5 | B48: 4 - Personal Property - 15 year | C48: 5/31/17 | D48: 14844.18 | E48: 0 | F48: 0 | G48: 7393.64 | H48: 876.53 | I48: =G48+H48 -> 8270.17 | J48: =D48-I48 -> 6574.01 | K48: 150DB | L48: 15.0
A49: 6 | B49: 4 - Personal Property - 30 year | C49: 5/31/17 | D49: 7032.68 | E49: 0 | F49: 0 | G49: 1553.03 | H49: 234.42 | I49: =G49+H49 -> 1787.45 | J49: =D49-I49 -> 5245.23 | K49: S/L | L49: 30.00
A50: 7 | B50: 2 - Land Improvements - 15 year | C50: 5/31/17 | D50: 29688.34 | E50: 0 | F50: 0 | G50: 14787.28 | H50: 1753.07 | I50: =G50+H50 -> 16540.35 | J50: =D50-I50 -> 13147.99 | K50: 150DB | L50: 15.0
A51: 8 | B51: 2 - Land Improvements - 30 year | C51: 5/31/17 | D51: 14065.37 | E51: 0 | F51: 0 | G51: 3388.49 | H51: 468.85 | I51: =G51+H51 -> 3857.34 | J51: =D51-I51 -> 10208.03 | K51: S/L | L51: 30.00
B52: Grand Total | D52: =SUM(D44:D51) -> 418936.13 | E52: =SUM(E44:E51) -> 0 | F52: =SUM(F44:F51) -> 802.92 | G52: =SUM(G44:G51) -> 171957.21 | H52: =SUM(H44:H51) -> 21227.12 | I52: =SUM(I44:I51) -> 193184.33 | J52: =SUM(J44:J51) -> 225751.8
B54: Section 481(a) Adjustment — AMT
B55: Depreciation reported previously | D55: =I40 -> 128215.81
B56: Cost Segregation Corrected Depreciation | D56: =I52 -> 193184.33
B57: Section 481(a) Adjustment — AMT | D57: =D55-D56 -> -64968.52
A59: COST SEGREGATION STUDY — COST SUMMARY
B60: Total Site Cost | D60: =D86 -> 418936.13
B61: Site Work / Improvements: 15 Year | D61: =F86 -> 284262.06
B62: % of Site Cost | D62: =F87 -> 0.67853317
B63: Site Utilities: 30 Year | D63: =H86 -> 134674.07
B64: % of Site Cost | D64: =H87 -> 0.32146683
A66: COST SEGREGATION STUDY — COST DETAIL
B67: Property Category | D67: Cost | F67: 15 Year | H67: 30 Year
B68: Site Work / Improvements
B69: Site Drainage | D69: =SUM(F69:H69) -> 18138.39 | F69: 18138.39
B70: Parking Lot | D70: =SUM(F70:H70) -> 108041.17 | F70: 108041.17
B71: Exterior Signage | D71: =SUM(F71:H71) -> 1298.37 | F71: 1298.37
B72: Parking Lot Striping / Barriers | D72: =SUM(F72:H72) -> 2443.43 | F72: 2443.43
B73: Sidewalks / Curbs | D73: =SUM(F73:H73) -> 90363.64 | F73: 90363.64
B74: Landscaping & Flagpole | D74: =SUM(F74:H74) -> 8205.48 | F74: 8205.48
B75: Security Lighting Poles | D75: =SUM(F75:H75) -> 11851.54 | F75: 11851.54
B76: Exterior Fencing | D76: =SUM(F76:H76) -> 246.69 | F76: 246.69
B77: Dumpster Enclosures | D77: =SUM(F77:H77) -> 7825.15 | F77: 7825.15
B78: Fabricated Steel - Exterior Bollards | D78: =SUM(F78:H78) -> 888.97 | F78: 888.97
B79: Fire Hydrants | D79: =SUM(F79:H79) -> 3748.31 | F79: 3748.31
B80: Exterior Equipment Concrete Pads | D80: =SUM(F80:H80) -> 4557.68 | F80: 4557.68
... B83: Playground | D83: =SUM(F83:H83) -> 6071.99 | F83: 6071.99
B84: Site Utilities
B85: Site Utilities | D85: =SUM(F85:H85) -> 134674.07 | H85: 134674.07
B86: Total Site Cost | D86: =SUM(D69:D85) -> 418936.13 | F86: =SUM(F69:F83) -> 284262.06 | H86: =SUM(H85:H85) -> 134674.07
B87: % of Site Cost | F87: =F86/D86 -> 0.67853317 | H87: =H86/D86 -> 0.32146683
A89: ASSET ALLOCATION
B90: Asset | D90: Cost | F90: 15 Year | H90: 30 Year
B91: Asset # 19 - Building - 754 "Menowitz" | D91: =F91+H91 -> 1183.32 | F91: 802.92 | H91: 380.4
B92: Asset # 3 - Building | D92: =F92+H92 -> 352122.24 | F92: 238926.62 | H92: 113195.62
B93: Asset # 4 - Personal Property | D93: =F93+H93 -> 21876.86 | F93: 14844.18 | H93: 7032.68
B94: Asset # 2 - Land Improvements | D94: =F94+H94 -> 43753.71 | F94: 29688.34 | H94: 14065.37
B95: Total Allocation | D95: =SUM(D91:D94) -> 418936.13 | F95: =SUM(F91:F94) -> 284262.06 | H95: =SUM(H91:H94) -> 134674.07
B96: Check: Allocation vs. Cost Detail (should be zero) | D96: =D95-D86 -> 0

Sheet Building 1
A1: Silver Springs Housing, LP
A2: Silver Spring Terrace Apartments — 950 20th St NE, Hickory, NC 28601
A3: EIN: 82-0773652 · FYE: December 31, 2024 · Year of Change: 1/1/2024
A4: Building 1 — Attachment to Form 3115 (DCN #7, Rev. Proc. 2024-23 §6.01)
A5: Source: CSSI Report #107752-39, "Silver Springs Housing LP_#107752-39_3115_Combined R1.pdf"
A7: CALCULATION OF §481(a) ADJUSTMENT — REGULAR TAX
A8: As Previously Filed
A9: Asset | B9: Property Description | C9: Date In Service | D9: Cost | E9: Sec 179 Exp | F9: Bonus Amt | G9: Tax Prior Depreciation | H9: Tax Current Depreciation | I9: End Depreciation | J9: Net Book Value | K9: Method | L9: Period
A10: 1 | B10: 19 - Building - 754 "Menowitz" | C10: 9/15/21 | D10: 662.06 | E10: 0 | F10: 0 | G10: 40.09 | H10: 16.52 | I10: =G10+H10 -> 56.61 | J10: =D10-I10 -> 605.45 | K10: S/L | L10: 40.00
A11: 2 | B11: 3 - Building | C11: 5/31/17 | D11: 197009.25 | E11: 0 | F11: 0 | G11: 42398.42 | H11: 4632.55 | I11: =G11+H11 -> 47030.97 | J11: =D11-I11 -> 149978.28 | K11: S/L | L11: 40.00
A12: 3 | B12: 4 - Personal Property | C12: 5/31/17 | D12: 12239.91 | E12: 0 | F12: 0 | G12: 11423.94 | H12: 0 | I12: =G12+H12 -> 11423.94 | J12: =D12-I12 -> 815.97 | K12: S/L | L12: 40.00
A13: 4 | B13: 2 - Land Improvements | C13: 5/31/17 | D13: 24479.81 | E13: 0 | F13: 0 | G13: 11779.87 | H13: 1444.31 | I13: =G13+H13 -> 13224.18 | J13: =D13-I13 -> 11255.63 | K13: S/L | L13: 40.00
B14: Grand Total | D14: =SUM(D10:D13) -> 234391.03 | E14: =SUM(E10:E13) -> 0 | F14: =SUM(F10:F13) -> 0 | G14: =SUM(G10:G13) -> 65642.32 | H14: =SUM(H10:H13) -> 6093.38 | I14: =SUM(I10:I13) -> 71735.7 | J14: =SUM(J10:J13) -> 162655.33
A16: After Cost Segregation Correction
A17: Asset | B17: Property Description | C17: Date In Service | D17: Cost | E17: Sec 179 Exp | F17: Bonus Amt | G17: Tax Prior Depreciation | H17: Tax Current Depreciation | I17: End Depreciation | J17: Net Book Value | K17: Method | L17: Period
A18: 1 | B18: 19 - Building - 754 "Menowitz" - 5 year | C18: 9/15/21 | D18: 137.19 | E18: 0 | F18: 137.19 | G18: 137.19 | H18: 0 | I18: =G18+H18 -> 137.19 | J18: =D18-I18 -> 0 | K18: 200DB | L18: 5.0
A19: 2 | B19: 19 - Building - 754 "Menowitz" - 30 year | C19: 9/15/21 | D19: 524.87 | E19: 0 | F19: 0 | G19: 40.1 | H19: 17.5 | I19: =G19+H19 -> 57.6 | J19: =D19-I19 -> 467.27 | K19: S/L | L19: 30.00
A20: 3 | B20: 3 - Building - 5 year | C20: 5/31/17 | D20: 40824.27 | E20: 0 | F20: 0 | G20: 40824.27 | H20: 0 | I20: =G20+H20 -> 40824.27 | J20: =D20-I20 -> 0 | K20: 200DB | L20: 5.0
A21: 4 | B21: 3 - Building - 30 year | C21: 5/31/17 | D21: 156184.98 | E21: 0 | F21: 0 | G21: 34490.87 | H21: 5206.17 | I21: =G21+H21 -> 39697.04 | J21: =D21-I21 -> 116487.94 | K21: S/L | L21: 30.00
A22: 5 | B22: 4 - Personal Property - 5 year | C22: 5/31/17 | D22: 2536.35 | E22: 0 | F22: 0 | G22: 2536.35 | H22: 0 | I22: =G22+H22 -> 2536.35 | J22: =D22-I22 -> 0 | K22: 200DB | L22: 5.0
A23: 6 | B23: 4 - Personal Property - 30 year | C23: 5/31/17 | D23: 9703.56 | E23: 0 | F23: 0 | G23: 2142.86 | H23: 323.45 | I23: =G23+H23 -> 2466.31 | J23: =D23-I23 -> 7237.25 | K23: S/L | L23: 30.00
A24: 7 | B24: 2 - Land Improvements - 5 year | C24: 5/31/17 | D24: 5072.71 | E24: 0 | F24: 0 | G24: 5072.71 | H24: 0 | I24: =G24+H24 -> 5072.71 | J24: =D24-I24 -> 0 | K24: 200DB | L24: 5.0
A25: 8 | B25: 2 - Land Improvements - 30 year | C25: 5/31/17 | D25: 19407.1 | E25: 0 | F25: 0 | G25: 4285.71 | H25: 646.9 | I25: =G25+H25 -> 4932.61 | J25: =D25-I25 -> 14474.49 | K25: S/L | L25: 30.00
B26: Grand Total | D26: =SUM(D18:D25) -> 234391.03 | E26: =SUM(E18:E25) -> 0 | F26: =SUM(F18:F25) -> 137.19 | G26: =SUM(G18:G25) -> 89530.06 | H26: =SUM(H18:H25) -> 6194.02 | I26: =SUM(I18:I25) -> 95724.08 | J26: =SUM(J18:J25) -> 138666.95
B28: Section 481(a) Adjustment — Regular Tax
B29: Depreciation reported previously | D29: =I14 -> 71735.7
B30: Cost Segregation Corrected Depreciation | D30: =I26 -> 95724.08
B31: Section 481(a) Adjustment — Regular Tax | D31: =D29-D30 -> -23988.38
A33: CALCULATION OF §481(a) ADJUSTMENT — AMT
A34: As Previously Filed — AMT
A35: Asset | B35: Property Description | C35: Date In Service | D35: Cost | E35: Sec 179 Exp | F35: Bonus Amt | G35: AMT Prior Depreciation | H35: AMT Current Depreciation | I35: End Depreciation | J35: Net Book Value | K35: Method | L35: Period
A36: 1 | B36: 19 - Building - 754 "Menowitz" | C36: 9/15/21 | D36: 662.06 | E36: 0 | F36: 0 | G36: 40.09 | H36: 16.52 | I36: =G36+H36 -> 56.61 | J36: =D36-I36 -> 605.45 | K36: S/L | L36: 40.00
A37: 2 | B37: 3 - Building | C37: 5/31/17 | D37: 197009.25 | E37: 0 | F37: 0 | G37: 42398.42 | H37: 4632.55 | I37: =G37+H37 -> 47030.97 | J37: =D37-I37 -> 149978.28 | K37: S/L | L37: 40.00
A38: 3 | B38: 4 - Personal Property | C38: 5/31/17 | D38: 12239.91 | E38: 0 | F38: 0 | G38: 11423.94 | H38: 0 | I38: =G38+H38 -> 11423.94 | J38: =D38-I38 -> 815.97 | K38: S/L | L38: 40.00
A39: 4 | B39: 2 - Land Improvements | C39: 5/31/17 | D39: 24479.81 | E39: 0 | F39: 0 | G39: 11779.87 | H39: 1444.31 | I39: =G39+H39 -> 13224.18 | J39: =D39-I39 -> 11255.63 | K39: S/L | L39: 40.00
B40: Grand Total | D40: =SUM(D36:D39) -> 234391.03 | E40: =SUM(E36:E39) -> 0 | F40: =SUM(F36:F39) -> 0 | G40: =SUM(G36:G39) -> 65642.32 | H40: =SUM(H36:H39) -> 6093.38 | I40: =SUM(I36:I39) -> 71735.7 | J40: =SUM(J36:J39) -> 162655.33
A42: After Cost Segregation Correction — AMT
A43: Asset | B43: Property Description | C43: Date In Service | D43: Cost | E43: Sec 179 Exp | F43: Bonus Amt | G43: AMT Prior Depreciation | H43: AMT Current Depreciation | I43: End Depreciation | J43: Net Book Value | K43: Method | L43: Period
A44: 1 | B44: 19 - Building - 754 "Menowitz" - 5 year | C44: 9/15/21 | D44: 137.19 | E44: 0 | F44: 137.19 | G44: 137.19 | H44: 0 | I44: =G44+H44 -> 137.19 | J44: =D44-I44 -> 0 | K44: 200DB | L44: 5.0
A45: 2 | B45: 19 - Building - 754 "Menowitz" - 30 year | C45: 9/15/21 | D45: 524.87 | E45: 0 | F45: 0 | G45: 40.1 | H45: 17.5 | I45: =G45+H45 -> 57.6 | J45: =D45-I45 -> 467.27 | K45: S/L | L45: 30.00
A46: 3 | B46: 3 - Building - 5 year | C46: 5/31/17 | D46: 40824.27 | E46: 0 | F46: 0 | G46: 40824.27 | H46: 0 | I46: =G46+H46 -> 40824.27 | J46: =D46-I46 -> 0 | K46: 200DB | L46: 5.0
A47: 4 | B47: 3 - Building - 30 year | C47: 5/31/17 | D47: 156184.98 | E47: 0 | F47: 0 | G47: 34490.87 | H47: 5206.17 | I47: =G47+H47 -> 39697.04 | J47: =D47-I47 -> 116487.94 | K47: S/L | L47: 30.00
A48: 5 | B48: 4 - Personal Property - 5 year | C48: 5/31/17 | D48: 2536.35 | E48: 0 | F48: 0 | G48: 2536.35 | H48: 0 | I48: =G48+H48 -> 2536.35 | J48: =D48-I48 -> 0 | K48: 200DB | L48: 5.0
A49: 6 | B49: 4 - Personal Property - 30 year | C49: 5/31/17 | D49: 9703.56 | E49: 0 | F49: 0 | G49: 2142.86 | H49: 323.45 | I49: =G49+H49 -> 2466.31 | J49: =D49-I49 -> 7237.25 | K49: S/L | L49: 30.00
A50: 7 | B50: 2 - Land Improvements - 5 year | C50: 5/31/17 | D50: 5072.71 | E50: 0 | F50: 0 | G50: 5072.71 | H50: 0 | I50: =G50+H50 -> 5072.71 | J50: =D50-I50 -> 0 | K50: 200DB | L50: 5.0
A51: 8 | B51: 2 - Land Improvements - 30 year | C51: 5/31/17 | D51: 19407.1 | E51: 0 | F51: 0 | G51: 4285.71 | H51: 646.9 | I51: =G51+H51 -> 4932.61 | J51: =D51-I51 -> 14474.49 | K51: S/L | L51: 30.00
B52: Grand Total | D52: =SUM(D44:D51) -> 234391.03 | E52: =SUM(E44:E51) -> 0 | F52: =SUM(F44:F51) -> 137.19 | G52: =SUM(G44:G51) -> 89530.06 | H52: =SUM(H44:H51) -> 6194.02 | I52: =SUM(I44:I51) -> 95724.08 | J52: =SUM(J44:J51) -> 138666.95
B54: Section 481(a) Adjustment — AMT
B55: Depreciation reported previously | D55: =I40 -> 71735.7
B56: Cost Segregation Corrected Depreciation | D56: =I52 -> 95724.08
B57: Section 481(a) Adjustment — AMT | D57: =D55-D56 -> -23988.38
A59: COST SEGREGATION STUDY — COST SUMMARY
B60: Total Building Cost | D60: =D98 -> 234391.03
B61: Building Components: 5 Year | D61: =F98 -> 48570.52
B62: % of Building Cost | D62: =F99 -> 0.20722005
B63: Building Structure: 30 Year | D63: =H98 -> 185820.51
B64: % of Building Cost | D64: =H99 -> 0.79277995
A66: COST SEGREGATION STUDY — COST DETAIL
B67: Property Category | D67: Cost | F67: 5 Year | H67: 30 Year
B68: Building Components
B69: Cabinets / Millwork | D69: =SUM(F69:H69) -> 11319.08 | F69: 11319.08
B70: Moldings | D70: =SUM(F70:H70) -> 4407.51 | F70: 4407.51
B71: Flooring - Vinyl Plank | D71: =SUM(F71:H71) -> 17858.88 | F71: 17858.88
B72: Window Treatments | D72: =SUM(F72:H72) -> 1586.91 | F72: 1586.91
B73: Building Signage | D73: =SUM(F73:H73) -> 127.35 | F73: 127.35
B74: Specialty Electrical - Appliances | D74: =SUM(F74:H74) -> 2548.79 | F74: 2548.79
B75: Communication / Data | D75: =SUM(F75:H75) -> 1548.16 | F75: 1548.16
B76: Specialty Plumbing - Kitchen Sinks | D76: =SUM(F76:H76) -> 4626.46 | F76: 4626.46
B77: Security / Exterior Lighting | D77: =SUM(F77:H77) -> 480.75 | F77: 480.75
B78: Access Control | D78: =SUM(F78:H78) -> 75.53 | F78: 75.53
B79: Appliances | D79: =SUM(F79:H79) -> 3991.1 | F79: 3991.1
B80: Building Structure
B81: Roofing Systems | D81: =SUM(F81:H81) -> 7270.82 | H81: 7270.82
B82: Foundations | D82: =SUM(F82:H82) -> 12116.84 | H82: 12116.84
B83: HVAC | D83: =SUM(F83:H83) -> 17293.33 | H83: 17293.33
B84: Electrical | D84: =SUM(F84:H84) -> 16285.45 | H84: 16285.45
B85: Plumbing | D85: =SUM(F85:H85) -> 15033 | H85: 15033
B86: Fire Protection & Alarm | D86: =SUM(F86:H86) -> 958.91 | H86: 958.91
B87: Exterior Façade / Building Skin | D87: =SUM(F87:H87) -> 26187.51 | H87: 26187.51
B88: Doors & Frames | D88: =SUM(F88:H88) -> 11772.85 | H88: 11772.85
B89: Windows | D89: =SUM(F89:H89) -> 6994.46 | H89: 6994.46
B90: Ceiling Systems | D90: =SUM(F90:H90) -> 7953.64 | H90: 7953.64
B91: Interior Framing / Partitions | D91: =SUM(F91:H91) -> 19168.95 | H91: 19168.95
B92: Painting | D92: =SUM(F92:H92) -> 7364.73 | H92: 7364.73
... B97: Cabinets / Millwork - Restrooms | D97: =SUM(F97:H97) -> 901.51 | H97: 901.51
B98: Total Building Cost | D98: =SUM(D69:D97) -> 234391.03 | F98: =SUM(F69:F79) -> 48570.52 | H98: =SUM(H81:H97) -> 185820.51
B99: % of Building Cost | F99: =F98/D98 -> 0.20722005 | H99: =H98/D98 -> 0.79277995
A101: ASSET ALLOCATION
B102: Asset | D102: Cost | F102: 5 Year | H102: 30 Year
B103: Asset # 19 - Building - 754 "Menowitz" | D103: =F103+H103 -> 662.06 | F103: 137.19 | H103: 524.87
B104: Asset # 3 - Building | D104: =F104+H104 -> 197009.25 | F104: 40824.27 | H104: 156184.98
B105: Asset # 4 - Personal Property | D105: =F105+H105 -> 12239.91 | F105: 2536.35 | H105: 9703.56
B106: Asset # 2 - Land Improvements | D106: =F106+H106 -> 24479.81 | F106: 5072.71 | H106: 19407.1
B107: Total Allocation | D107: =SUM(D103:D106) -> 234391.03 | F107: =SUM(F103:F106) -> 48570.52 | H107: =SUM(H103:H106) -> 185820.51
B108: Check: Allocation vs. Cost Detail (should be zero) | D108: =D107-D98 -> 0

Sheet Building 2
A1: Silver Springs Housing, LP
A2: Silver Spring Terrace Apartments — 950 20th St NE, Hickory, NC 28601
A3: EIN: 82-0773652 · FYE: December 31, 2024 · Year of Change: 1/1/2024
A4: Building 2 — Attachment to Form 3115 (DCN #7, Rev. Proc. 2024-23 §6.01)
A5: Source: CSSI Report #107752-39, "Silver Springs Housing LP_#107752-39_3115_Combined R1.pdf"
A7: CALCULATION OF §481(a) ADJUSTMENT — REGULAR TAX
A8: As Previously Filed
A9: Asset | B9: Property Description | C9: Date In Service | D9: Cost | E9: Sec 179 Exp | F9: Bonus Amt | G9: Tax Prior Depreciation | H9: Tax Current Depreciation | I9: End Depreciation | J9: Net Book Value | K9: Method | L9: Period
A10: 1 | B10: 19 - Building - 754 "Menowitz" | C10: 9/15/21 | D10: 662.06 | E10: 0 | F10: 0 | G10: 40.09 | H10: 16.52 | I10: =G10+H10 -> 56.61 | J10: =D10-I10 -> 605.45 | K10: S/L | L10: 40.00
A11: 2 | B11: 3 - Building | C11: 5/31/17 | D11: 197009.25 | E11: 0 | F11: 0 | G11: 42398.42 | H11: 4632.55 | I11: =G11+H11 -> 47030.97 | J11: =D11-I11 -> 149978.28 | K11: S/L | L11: 40.00
A12: 3 | B12: 4 - Personal Property | C12: 5/31/17 | D12: 12239.91 | E12: 0 | F12: 0 | G12: 11423.94 | H12: 0 | I12: =G12+H12 -> 11423.94 | J12: =D12-I12 -> 815.97 | K12: S/L | L12: 40.00
A13: 4 | B13: 2 - Land Improvements | C13: 5/31/17 | D13: 24479.81 | E13: 0 | F13: 0 | G13: 11779.87 | H13: 1444.31 | I13: =G13+H13 -> 13224.18 | J13: =D13-I13 -> 11255.63 | K13: S/L | L13: 40.00
B14: Grand Total | D14: =SUM(D10:D13) -> 234391.03 | E14: =SUM(E10:E13) -> 0 | F14: =SUM(F10:F13) -> 0 | G14: =SUM(G10:G13) -> 65642.32 | H14: =SUM(H10:H13) -> 6093.38 | I14: =SUM(I10:I13) -> 71735.7 | J14: =SUM(J10:J13) -> 162655.33
A16: After Cost Segregation Correction
A17: Asset | B17: Property Description | C17: Date In Service | D17: Cost | E17: Sec 179 Exp | F17: Bonus Amt | G17: Tax Prior Depreciation | H17: Tax Current Depreciation | I17: End Depreciation | J17: Net Book Value | K17: Method | L17: Period
A18: 1 | B18: 19 - Building - 754 "Menowitz" - 5 year | C18: 9/15/21 | D18: 137.19 | E18: 0 | F18: 137.19 | G18: 137.19 | H18: 0 | I18: =G18+H18 -> 137.19 | J18: =D18-I18 -> 0 | K18: 200DB | L18: 5.0
A19: 2 | B19: 19 - Building - 754 "Menowitz" - 30 year | C19: 9/15/21 | D19: 524.87 | E19: 0 | F19: 0 | G19: 40.1 | H19: 17.5 | I19: =G19+H19 -> 57.6 | J19: =D19-I19 -> 467.27 | K19: S/L | L19: 30.00
A20: 3 | B20: 3 - Building - 5 year | C20: 5/31/17 | D20: 40824.27 | E20: 0 | F20: 0 | G20: 40824.27 | H20: 0 | I20: =G20+H20 -> 40824.27 | J20: =D20-I20 -> 0 | K20: 200DB | L20: 5.0
A21: 4 | B21: 3 - Building - 30 year | C21: 5/31/17 | D21: 156184.98 | E21: 0 | F21: 0 | G21: 34490.87 | H21: 5206.17 | I21: =G21+H21 -> 39697.04 | J21: =D21-I21 -> 116487.94 | K21: S/L | L21: 30.00
A22: 5 | B22: 4 - Personal Property - 5 year | C22: 5/31/17 | D22: 2536.35 | E22: 0 | F22: 0 | G22: 2536.35 | H22: 0 | I22: =G22+H22 -> 2536.35 | J22: =D22-I22 -> 0 | K22: 200DB | L22: 5.0
A23: 6 | B23: 4 - Personal Property - 30 year | C23: 5/31/17 | D23: 9703.56 | E23: 0 | F23: 0 | G23: 2142.86 | H23: 323.45 | I23: =G23+H23 -> 2466.31 | J23: =D23-I23 -> 7237.25 | K23: S/L | L23: 30.00
A24: 7 | B24: 2 - Land Improvements - 5 year | C24: 5/31/17 | D24: 5072.71 | E24: 0 | F24: 0 | G24: 5072.71 | H24: 0 | I24: =G24+H24 -> 5072.71 | J24: =D24-I24 -> 0 | K24: 200DB | L24: 5.0
A25: 8 | B25: 2 - Land Improvements - 30 year | C25: 5/31/17 | D25: 19407.1 | E25: 0 | F25: 0 | G25: 4285.71 | H25: 646.9 | I25: =G25+H25 -> 4932.61 | J25: =D25-I25 -> 14474.49 | K25: S/L | L25: 30.00
B26: Grand Total | D26: =SUM(D18:D25) -> 234391.03 | E26: =SUM(E18:E25) -> 0 | F26: =SUM(F18:F25) -> 137.19 | G26: =SUM(G18:G25) -> 89530.06 | H26: =SUM(H18:H25) -> 6194.02 | I26: =SUM(I18:I25) -> 95724.08 | J26: =SUM(J18:J25) -> 138666.95
B28: Section 481(a) Adjustment — Regular Tax
B29: Depreciation reported previously | D29: =I14 -> 71735.7
B30: Cost Segregation Corrected Depreciation | D30: =I26 -> 95724.08
B31: Section 481(a) Adjustment — Regular Tax | D31: =D29-D30 -> -23988.38
A33: CALCULATION OF §481(a) ADJUSTMENT — AMT
A34: As Previously Filed — AMT
A35: Asset | B35: Property Description | C35: Date In Service | D35: Cost | E35: Sec 179 Exp | F35: Bonus Amt | G35: AMT Prior Depreciation | H35: AMT Current Depreciation | I35: End Depreciation | J35: Net Book Value | K35: Method | L35: Period
A36: 1 | B36: 19 - Building - 754 "Menowitz" | C36: 9/15/21 | D36: 662.06 | E36: 0 | F36: 0 | G36: 40.09 | H36: 16.52 | I36: =G36+H36 -> 56.61 | J36: =D36-I36 -> 605.45 | K36: S/L | L36: 40.00
A37: 2 | B37: 3 - Building | C37: 5/31/17 | D37: 197009.25 | E37: 0 | F37: 0 | G37: 42398.42 | H37: 4632.55 | I37: =G37+H37 -> 47030.97 | J37: =D37-I37 -> 149978.28 | K37: S/L | L37: 40.00
A38: 3 | B38: 4 - Personal Property | C38: 5/31/17 | D38: 12239.91 | E38: 0 | F38: 0 | G38: 11423.94 | H38: 0 | I38: =G38+H38 -> 11423.94 | J38: =D38-I38 -> 815.97 | K38: S/L | L38: 40.00
A39: 4 | B39: 2 - Land Improvements | C39: 5/31/17 | D39: 24479.81 | E39: 0 | F39: 0 | G39: 11779.87 | H39: 1444.31 | I39: =G39+H39 -> 13224.18 | J39: =D39-I39 -> 11255.63 | K39: S/L | L39: 40.00
B40: Grand Total | D40: =SUM(D36:D39) -> 234391.03 | E40: =SUM(E36:E39) -> 0 | F40: =SUM(F36:F39) -> 0 | G40: =SUM(G36:G39) -> 65642.32 | H40: =SUM(H36:H39) -> 6093.38 | I40: =SUM(I36:I39) -> 71735.7 | J40: =SUM(J36:J39) -> 162655.33
A42: After Cost Segregation Correction — AMT
A43: Asset | B43: Property Description | C43: Date In Service | D43: Cost | E43: Sec 179 Exp | F43: Bonus Amt | G43: AMT Prior Depreciation | H43: AMT Current Depreciation | I43: End Depreciation | J43: Net Book Value | K43: Method | L43: Period
A44: 1 | B44: 19 - Building - 754 "Menowitz" - 5 year | C44: 9/15/21 | D44: 137.19 | E44: 0 | F44: 137.19 | G44: 137.19 | H44: 0 | I44: =G44+H44 -> 137.19 | J44: =D44-I44 -> 0 | K44: 200DB | L44: 5.0
A45: 2 | B45: 19 - Building - 754 "Menowitz" - 30 year | C45: 9/15/21 | D45: 524.87 | E45: 0 | F45: 0 | G45: 40.1 | H45: 17.5 | I45: =G45+H45 -> 57.6 | J45: =D45-I45 -> 467.27 | K45: S/L | L45: 30.00
A46: 3 | B46: 3 - Building - 5 year | C46: 5/31/17 | D46: 40824.27 | E46: 0 | F46: 0 | G46: 40824.27 | H46: 0 | I46: =G46+H46 -> 40824.27 | J46: =D46-I46 -> 0 | K46: 200DB | L46: 5.0
A47: 4 | B47: 3 - Building - 30 year | C47: 5/31/17 | D47: 156184.98 | E47: 0 | F47: 0 | G47: 34490.87 | H47: 5206.17 | I47: =G47+H47 -> 39697.04 | J47: =D47-I47 -> 116487.94 | K47: S/L | L47: 30.00
A48: 5 | B48: 4 - Personal Property - 5 year | C48: 5/31/17 | D48: 2536.35 | E48: 0 | F48: 0 | G48: 2536.35 | H48: 0 | I48: =G48+H48 -> 2536.35 | J48: =D48-I48 -> 0 | K48: 200DB | L48: 5.0
A49: 6 | B49: 4 - Personal Property - 30 year | C49: 5/31/17 | D49: 9703.56 | E49: 0 | F49: 0 | G49: 2142.86 | H49: 323.45 | I49: =G49+H49 -> 2466.31 | J49: =D49-I49 -> 7237.25 | K49: S/L | L49: 30.00
A50: 7 | B50: 2 - Land Improvements - 5 year | C50: 5/31/17 | D50: 5072.71 | E50: 0 | F50: 0 | G50: 5072.71 | H50: 0 | I50: =G50+H50 -> 5072.71 | J50: =D50-I50 -> 0 | K50: 200DB | L50: 5.0
A51: 8 | B51: 2 - Land Improvements - 30 year | C51: 5/31/17 | D51: 19407.1 | E51: 0 | F51: 0 | G51: 4285.71 | H51: 646.9 | I51: =G51+H51 -> 4932.61 | J51: =D51-I51 -> 14474.49 | K51: S/L | L51: 30.00
B52: Grand Total | D52: =SUM(D44:D51) -> 234391.03 | E52: =SUM(E44:E51) -> 0 | F52: =SUM(F44:F51) -> 137.19 | G52: =SUM(G44:G51) -> 89530.06 | H52: =SUM(H44:H51) -> 6194.02 | I52: =SUM(I44:I51) -> 95724.08 | J52: =SUM(J44:J51) -> 138666.95
B54: Section 481(a) Adjustment — AMT
B55: Depreciation reported previously | D55: =I40 -> 71735.7
B56: Cost Segregation Corrected Depreciation | D56: =I52 -> 95724.08
B57: Section 481(a) Adjustment — AMT | D57: =D55-D56 -> -23988.38
A59: COST SEGREGATION STUDY — COST SUMMARY
B60: Total Building Cost | D60: =D98 -> 234391.03
B61: Building Components: 5 Year | D61: =F98 -> 48570.52
B62: % of Building Cost | D62: =F99 -> 0.20722005
B63: Building Structure: 30 Year | D63: =H98 -> 185820.51
B64: % of Building Cost | D64: =H99 -> 0.79277995
A66: COST SEGREGATION STUDY — COST DETAIL
B67: Property Category | D67: Cost | F67: 5 Year | H67: 30 Year
B68: Building Components
B69: Cabinets / Millwork | D69: =SUM(F69:H69) -> 11319.08 | F69: 11319.08
B70: Moldings | D70: =SUM(F70:H70) -> 4407.51 | F70: 4407.51
B71: Flooring - Vinyl Plank | D71: =SUM(F71:H71) -> 17858.88 | F71: 17858.88
B72: Window Treatments | D72: =SUM(F72:H72) -> 1586.91 | F72: 1586.91
B73: Building Signage | D73: =SUM(F73:H73) -> 127.35 | F73: 127.35
B74: Specialty Electrical - Appliances | D74: =SUM(F74:H74) -> 2548.79 | F74: 2548.79
B75: Communication / Data | D75: =SUM(F75:H75) -> 1548.16 | F75: 1548.16
B76: Specialty Plumbing - Kitchen Sinks | D76: =SUM(F76:H76) -> 4626.46 | F76: 4626.46
B77: Security / Exterior Lighting | D77: =SUM(F77:H77) -> 480.75 | F77: 480.75
B78: Access Control | D78: =SUM(F78:H78) -> 75.53 | F78: 75.53
B79: Appliances | D79: =SUM(F79:H79) -> 3991.1 | F79: 3991.1
B80: Building Structure
B81: Roofing Systems | D81: =SUM(F81:H81) -> 7270.82 | H81: 7270.82
B82: Foundations | D82: =SUM(F82:H82) -> 12116.84 | H82: 12116.84
B83: HVAC | D83: =SUM(F83:H83) -> 17293.33 | H83: 17293.33
B84: Electrical | D84: =SUM(F84:H84) -> 16285.45 | H84: 16285.45
B85: Plumbing | D85: =SUM(F85:H85) -> 15033 | H85: 15033
B86: Fire Protection & Alarm | D86: =SUM(F86:H86) -> 958.91 | H86: 958.91
B87: Exterior Façade / Building Skin | D87: =SUM(F87:H87) -> 26187.51 | H87: 26187.51
B88: Doors & Frames | D88: =SUM(F88:H88) -> 11772.85 | H88: 11772.85
B89: Windows | D89: =SUM(F89:H89) -> 6994.46 | H89: 6994.46
B90: Ceiling Systems | D90: =SUM(F90:H90) -> 7953.64 | H90: 7953.64
B91: Interior Framing / Partitions | D91: =SUM(F91:H91) -> 19168.95 | H91: 19168.95
B92: Painting | D92: =SUM(F92:H92) -> 7364.73 | H92: 7364.73
... B97: Cabinets / Millwork - Restrooms | D97: =SUM(F97:H97) -> 901.51 | H97: 901.51
B98: Total Building Cost | D98: =SUM(D69:D97) -> 234391.03 | F98: =SUM(F69:F79) -> 48570.52 | H98: =SUM(H81:H97) -> 185820.51
B99: % of Building Cost | F99: =F98/D98 -> 0.20722005 | H99: =H98/D98 -> 0.79277995
A101: ASSET ALLOCATION
B102: Asset | D102: Cost | F102: 5 Year | H102: 30 Year
B103: Asset # 19 - Building - 754 "Menowitz" | D103: =F103+H103 -> 662.06 | F103: 137.19 | H103: 524.87
B104: Asset # 3 - Building | D104: =F104+H104 -> 197009.25 | F104: 40824.27 | H104: 156184.98
B105: Asset # 4 - Personal Property | D105: =F105+H105 -> 12239.91 | F105: 2536.35 | H105: 9703.56
B106: Asset # 2 - Land Improvements | D106: =F106+H106 -> 24479.81 | F106: 5072.71 | H106: 19407.1
B107: Total Allocation | D107: =SUM(D103:D106) -> 234391.03 | F107: =SUM(F103:F106) -> 48570.52 | H107: =SUM(H103:H106) -> 185820.51
B108: Check: Allocation vs. Cost Detail (should be zero) | D108: =D107-D98 -> 0

Sheet Building 3
A1: Silver Springs Housing, LP
A2: Silver Spring Terrace Apartments — 950 20th St NE, Hickory, NC 28601
A3: EIN: 82-0773652 · FYE: December 31, 2024 · Year of Change: 1/1/2024
A4: Building 3 — Attachment to Form 3115 (DCN #7, Rev. Proc. 2024-23 §6.01)
A5: Source: CSSI Report #107752-39, "Silver Springs Housing LP_#107752-39_3115_Combined R1.pdf"
A7: CALCULATION OF §481(a) ADJUSTMENT — REGULAR TAX
A8: As Previously Filed
A9: Asset | B9: Property Description | C9: Date In Service | D9: Cost | E9: Sec 179 Exp | F9: Bonus Amt | G9: Tax Prior Depreciation | H9: Tax Current Depreciation | I9: End Depreciation | J9: Net Book Value | K9: Method | L9: Period
A10: 1 | B10: 19 - Building - 754 "Menowitz" | C10: 9/15/21 | D10: 662.06 | E10: 0 | F10: 0 | G10: 40.09 | H10: 16.52 | I10: =G10+H10 -> 56.61 | J10: =D10-I10 -> 605.45 | K10: S/L | L10: 40.00
A11: 2 | B11: 3 - Building | C11: 5/31/17 | D11: 197009.25 | E11: 0 | F11: 0 | G11: 42398.42 | H11: 4632.55 | I11: =G11+H11 -> 47030.97 | J11: =D11-I11 -> 149978.28 | K11: S/L | L11: 40.00
A12: 3 | B12: 4 - Personal Property | C12: 5/31/17 | D12: 12239.91 | E12: 0 | F12: 0 | G12: 11423.94 | H12: 0 | I12: =G12+H12 -> 11423.94 | J12: =D12-I12 -> 815.97 | K12: S/L | L12: 40.00
A13: 4 | B13: 2 - Land Improvements | C13: 5/31/17 | D13: 24479.81 | E13: 0 | F13: 0 | G13: 11779.87 | H13: 1444.31 | I13: =G13+H13 -> 13224.18 | J13: =D13-I13 -> 11255.63 | K13: S/L | L13: 40.00
B14: Grand Total | D14: =SUM(D10:D13) -> 234391.03 | E14: =SUM(E10:E13) -> 0 | F14: =SUM(F10:F13) -> 0 | G14: =SUM(G10:G13) -> 65642.32 | H14: =SUM(H10:H13) -> 6093.38 | I14: =SUM(I10:I13) -> 71735.7 | J14: =SUM(J10:J13) -> 162655.33
A16: After Cost Segregation Correction
A17: Asset | B17: Property Description | C17: Date In Service | D17: Cost | E17: Sec 179 Exp | F17: Bonus Amt | G17: Tax Prior Depreciation | H17: Tax Current Depreciation | I17: End Depreciation | J17: Net Book Value | K17: Method | L17: Period
A18: 1 | B18: 19 - Building - 754 "Menowitz" - 5 year | C18: 9/15/21 | D18: 137.19 | E18: 0 | F18: 137.19 | G18: 137.19 | H18: 0 | I18: =G18+H18 -> 137.19 | J18: =D18-I18 -> 0 | K18: 200DB | L18: 5.0
A19: 2 | B19: 19 - Building - 754 "Menowitz" - 30 year | C19: 9/15/21 | D19: 524.87 | E19: 0 | F19: 0 | G19: 40.1 | H19: 17.5 | I19: =G19+H19 -> 57.6 | J19: =D19-I19 -> 467.27 | K19: S/L | L19: 30.00
A20: 3 | B20: 3 - Building - 5 year | C20: 5/31/17 | D20: 40824.27 | E20: 0 | F20: 0 | G20: 40824.27 | H20: 0 | I20: =G20+H20 -> 40824.27 | J20: =D20-I20 -> 0 | K20: 200DB | L20: 5.0
A21: 4 | B21: 3 - Building - 30 year | C21: 5/31/17 | D21: 156184.98 | E21: 0 | F21: 0 | G21: 34490.87 | H21: 5206.17 | I21: =G21+H21 -> 39697.04 | J21: =D21-I21 -> 116487.94 | K21: S/L | L21: 30.00
A22: 5 | B22: 4 - Personal Property - 5 year | C22: 5/31/17 | D22: 2536.35 | E22: 0 | F22: 0 | G22: 2536.35 | H22: 0 | I22: =G22+H22 -> 2536.35 | J22: =D22-I22 -> 0 | K22: 200DB | L22: 5.0
A23: 6 | B23: 4 - Personal Property - 30 year | C23: 5/31/17 | D23: 9703.56 | E23: 0 | F23: 0 | G23: 2142.86 | H23: 323.45 | I23: =G23+H23 -> 2466.31 | J23: =D23-I23 -> 7237.25 | K23: S/L | L23: 30.00
A24: 7 | B24: 2 - Land Improvements - 5 year | C24: 5/31/17 | D24: 5072.71 | E24: 0 | F24: 0 | G24: 5072.71 | H24: 0 | I24: =G24+H24 -> 5072.71 | J24: =D24-I24 -> 0 | K24: 200DB | L24: 5.0
A25: 8 | B25: 2 - Land Improvements - 30 year | C25: 5/31/17 | D25: 19407.1 | E25: 0 | F25: 0 | G25: 4285.71 | H25: 646.9 | I25: =G25+H25 -> 4932.61 | J25: =D25-I25 -> 14474.49 | K25: S/L | L25: 30.00
B26: Grand Total | D26: =SUM(D18:D25) -> 234391.03 | E26: =SUM(E18:E25) -> 0 | F26: =SUM(F18:F25) -> 137.19 | G26: =SUM(G18:G25) -> 89530.06 | H26: =SUM(H18:H25) -> 6194.02 | I26: =SUM(I18:I25) -> 95724.08 | J26: =SUM(J18:J25) -> 138666.95
B28: Section 481(a) Adjustment — Regular Tax
B29: Depreciation reported previously | D29: =I14 -> 71735.7
B30: Cost Segregation Corrected Depreciation | D30: =I26 -> 95724.08
B31: Section 481(a) Adjustment — Regular Tax | D31: =D29-D30 -> -23988.38
A33: CALCULATION OF §481(a) ADJUSTMENT — AMT
A34: As Previously Filed — AMT
A35: Asset | B35: Property Description | C35: Date In Service | D35: Cost | E35: Sec 179 Exp | F35: Bonus Amt | G35: AMT Prior Depreciation | H35: AMT Current Depreciation | I35: End Depreciation | J35: Net Book Value | K35: Method | L35: Period
A36: 1 | B36: 19 - Building - 754 "Menowitz" | C36: 9/15/21 | D36: 662.06 | E36: 0 | F36: 0 | G36: 40.09 | H36: 16.52 | I36: =G36+H36 -> 56.61 | J36: =D36-I36 -> 605.45 | K36: S/L | L36: 40.00
A37: 2 | B37: 3 - Building | C37: 5/31/17 | D37: 197009.25 | E37: 0 | F37: 0 | G37: 42398.42 | H37: 4632.55 | I37: =G37+H37 -> 47030.97 | J37: =D37-I37 -> 149978.28 | K37: S/L | L37: 40.00
A38: 3 | B38: 4 - Personal Property | C38: 5/31/17 | D38: 12239.91 | E38: 0 | F38: 0 | G38: 11423.94 | H38: 0 | I38: =G38+H38 -> 11423.94 | J38: =D38-I38 -> 815.97 | K38: S/L | L38: 40.00
A39: 4 | B39: 2 - Land Improvements | C39: 5/31/17 | D39: 24479.81 | E39: 0 | F39: 0 | G39: 11779.87 | H39: 1444.31 | I39: =G39+H39 -> 13224.18 | J39: =D39-I39 -> 11255.63 | K39: S/L | L39: 40.00
B40: Grand Total | D40: =SUM(D36:D39) -> 234391.03 | E40: =SUM(E36:E39) -> 0 | F40: =SUM(F36:F39) -> 0 | G40: =SUM(G36:G39) -> 65642.32 | H40: =SUM(H36:H39) -> 6093.38 | I40: =SUM(I36:I39) -> 71735.7 | J40: =SUM(J36:J39) -> 162655.33
A42: After Cost Segregation Correction — AMT
A43: Asset | B43: Property Description | C43: Date In Service | D43: Cost | E43: Sec 179 Exp | F43: Bonus Amt | G43: AMT Prior Depreciation | H43: AMT Current Depreciation | I43: End Depreciation | J43: Net Book Value | K43: Method | L43: Period
A44: 1 | B44: 19 - Building - 754 "Menowitz" - 5 year | C44: 9/15/21 | D44: 137.19 | E44: 0 | F44: 137.19 | G44: 137.19 | H44: 0 | I44: =G44+H44 -> 137.19 | J44: =D44-I44 -> 0 | K44: 200DB | L44: 5.0
A45: 2 | B45: 19 - Building - 754 "Menowitz" - 30 year | C45: 9/15/21 | D45: 524.87 | E45: 0 | F45: 0 | G45: 40.1 | H45: 17.5 | I45: =G45+H45 -> 57.6 | J45: =D45-I45 -> 467.27 | K45: S/L | L45: 30.00
A46: 3 | B46: 3 - Building - 5 year | C46: 5/31/17 | D46: 40824.27 | E46: 0 | F46: 0 | G46: 40824.27 | H46: 0 | I46: =G46+H46 -> 40824.27 | J46: =D46-I46 -> 0 | K46: 200DB | L46: 5.0
A47: 4 | B47: 3 - Building - 30 year | C47: 5/31/17 | D47: 156184.98 | E47: 0 | F47: 0 | G47: 34490.87 | H47: 5206.17 | I47: =G47+H47 -> 39697.04 | J47: =D47-I47 -> 116487.94 | K47: S/L | L47: 30.00
A48: 5 | B48: 4 - Personal Property - 5 year | C48: 5/31/17 | D48: 2536.35 | E48: 0 | F48: 0 | G48: 2536.35 | H48: 0 | I48: =G48+H48 -> 2536.35 | J48: =D48-I48 -> 0 | K48: 200DB | L48: 5.0
A49: 6 | B49: 4 - Personal Property - 30 year | C49: 5/31/17 | D49: 9703.56 | E49: 0 | F49: 0 | G49: 2142.86 | H49: 323.45 | I49: =G49+H49 -> 2466.31 | J49: =D49-I49 -> 7237.25 | K49: S/L | L49: 30.00
A50: 7 | B50: 2 - Land Improvements - 5 year | C50: 5/31/17 | D50: 5072.71 | E50: 0 | F50: 0 | G50: 5072.71 | H50: 0 | I50: =G50+H50 -> 5072.71 | J50: =D50-I50 -> 0 | K50: 200DB | L50: 5.0
A51: 8 | B51: 2 - Land Improvements - 30 year | C51: 5/31/17 | D51: 19407.1 | E51: 0 | F51: 0 | G51: 4285.71 | H51: 646.9 | I51: =G51+H51 -> 4932.61 | J51: =D51-I51 -> 14474.49 | K51: S/L | L51: 30.00
B52: Grand Total | D52: =SUM(D44:D51) -> 234391.03 | E52: =SUM(E44:E51) -> 0 | F52: =SUM(F44:F51) -> 137.19 | G52: =SUM(G44:G51) -> 89530.06 | H52: =SUM(H44:H51) -> 6194.02 | I52: =SUM(I44:I51) -> 95724.08 | J52: =SUM(J44:J51) -> 138666.95
B54: Section 481(a) Adjustment — AMT
B55: Depreciation reported previously | D55: =I40 -> 71735.7
B56: Cost Segregation Corrected Depreciation | D56: =I52 -> 95724.08
B57: Section 481(a) Adjustment — AMT | D57: =D55-D56 -> -23988.38
A59: COST SEGREGATION STUDY — COST SUMMARY
B60: Total Building Cost | D60: =D98 -> 234391.03
B61: Building Components: 5 Year | D61: =F98 -> 48570.52
B62: % of Building Cost | D62: =F99 -> 0.20722005
B63: Building Structure: 30 Year | D63: =H98 -> 185820.51
B64: % of Building Cost | D64: =H99 -> 0.79277995
A66: COST SEGREGATION STUDY — COST DETAIL
B67: Property Category | D67: Cost | F67: 5 Year | H67: 30 Year
B68: Building Components
B69: Cabinets / Millwork | D69: =SUM(F69:H69) -> 11319.08 | F69: 11319.08
B70: Moldings | D70: =SUM(F70:H70) -> 4407.51 | F70: 4407.51
B71: Flooring - Vinyl Plank | D71: =SUM(F71:H71) -> 17858.88 | F71: 17858.88
B72: Window Treatments | D72: =SUM(F72:H72) -> 1586.91 | F72: 1586.91
B73: Building Signage | D73: =SUM(F73:H73) -> 127.35 | F73: 127.35
B74: Specialty Electrical - Appliances | D74: =SUM(F74:H74) -> 2548.79 | F74: 2548.79
B75: Communication / Data | D75: =SUM(F75:H75) -> 1548.16 | F75: 1548.16
B76: Specialty Plumbing - Kitchen Sinks | D76: =SUM(F76:H76) -> 4626.46 | F76: 4626.46
B77: Security / Exterior Lighting | D77: =SUM(F77:H77) -> 480.75 | F77: 480.75
B78: Access Control | D78: =SUM(F78:H78) -> 75.53 | F78: 75.53
B79: Appliances | D79: =SUM(F79:H79) -> 3991.1 | F79: 3991.1
B80: Building Structure
B81: Roofing Systems | D81: =SUM(F81:H81) -> 7270.82 | H81: 7270.82
B82: Foundations | D82: =SUM(F82:H82) -> 12116.84 | H82: 12116.84
B83: HVAC | D83: =SUM(F83:H83) -> 17293.33 | H83: 17293.33
B84: Electrical | D84: =SUM(F84:H84) -> 16285.45 | H84: 16285.45
B85: Plumbing | D85: =SUM(F85:H85) -> 15033 | H85: 15033
B86: Fire Protection & Alarm | D86: =SUM(F86:H86) -> 958.91 | H86: 958.91
B87: Exterior Façade / Building Skin | D87: =SUM(F87:H87) -> 26187.51 | H87: 26187.51
B88: Doors & Frames | D88: =SUM(F88:H88) -> 11772.85 | H88: 11772.85
B89: Windows | D89: =SUM(F89:H89) -> 6994.46 | H89: 6994.46
B90: Ceiling Systems | D90: =SUM(F90:H90) -> 7953.64 | H90: 7953.64
B91: Interior Framing / Partitions | D91: =SUM(F91:H91) -> 19168.95 | H91: 19168.95
B92: Painting | D92: =SUM(F92:H92) -> 7364.73 | H92: 7364.73
... B97: Cabinets / Millwork - Restrooms | D97: =SUM(F97:H97) -> 901.51 | H97: 901.51
B98: Total Building Cost | D98: =SUM(D69:D97) -> 234391.03 | F98: =SUM(F69:F79) -> 48570.52 | H98: =SUM(H81:H97) -> 185820.51
B99: % of Building Cost | F99: =F98/D98 -> 0.20722005 | H99: =H98/D98 -> 0.79277995
A101: ASSET ALLOCATION
B102: Asset | D102: Cost | F102: 5 Year | H102: 30 Year
B103: Asset # 19 - Building - 754 "Menowitz" | D103: =F103+H103 -> 662.06 | F103: 137.19 | H103: 524.87
B104: Asset # 3 - Building | D104: =F104+H104 -> 197009.25 | F104: 40824.27 | H104: 156184.98
B105: Asset # 4 - Personal Property | D105: =F105+H105 -> 12239.91 | F105: 2536.35 | H105: 9703.56
B106: Asset # 2 - Land Improvements | D106: =F106+H106 -> 24479.81 | F106: 5072.71 | H106: 19407.1
B107: Total Allocation | D107: =SUM(D103:D106) -> 234391.03 | F107: =SUM(F103:F106) -> 48570.52 | H107: =SUM(H103:H106) -> 185820.51
B108: Check: Allocation vs. Cost Detail (should be zero) | D108: =D107-D98 -> 0

Sheet Office
A1: Silver Springs Housing, LP
A2: Silver Spring Terrace Apartments — 950 20th St NE, Hickory, NC 28601
A3: EIN: 82-0773652 · FYE: December 31, 2024 · Year of Change: 1/1/2024
A4: Office — Attachment to Form 3115 (DCN #7, Rev. Proc. 2024-23 §6.01)
A5: Source: CSSI Report #107752-39, "Silver Springs Housing LP_#107752-39_3115_Combined R1.pdf"
A7: CALCULATION OF §481(a) ADJUSTMENT — REGULAR TAX
A8: As Previously Filed
A9: Asset | B9: Property Description | C9: Date In Service | D9: Cost | E9: Sec 179 Exp | F9: Bonus Amt | G9: Tax Prior Depreciation | H9: Tax Current Depreciation | I9: End Depreciation | J9: Net Book Value | K9: Method | L9: Period
A10: 1 | B10: 19 - Building - 754 "Menowitz" | C10: 9/15/21 | D10: 262.41 | E10: 0 | F10: 0 | G10: 15.89 | H10: 6.55 | I10: =G10+H10 -> 22.44 | J10: =D10-I10 -> 239.97 | K10: S/L | L10: 40.00
A11: 2 | B11: 3 - Building | C11: 5/31/17 | D11: 78086.63 | E11: 0 | F11: 0 | G11: 16805.05 | H11: 1836.16 | I11: =G11+H11 -> 18641.21 | J11: =D11-I11 -> 59445.42 | K11: S/L | L11: 40.00
A12: 3 | B12: 4 - Personal Property | C12: 5/31/17 | D12: 4851.41 | E12: 0 | F12: 0 | G12: 4527.99 | H12: 0 | I12: =G12+H12 -> 4527.99 | J12: =D12-I12 -> 323.42 | K12: S/L | L12: 40.00
A13: 4 | B13: 2 - Land Improvements | C13: 5/31/17 | D13: 9702.83 | E13: 0 | F13: 0 | G13: 4669.07 | H13: 572.47 | I13: =G13+H13 -> 5241.54 | J13: =D13-I13 -> 4461.29 | K13: S/L | L13: 40.00
B14: Grand Total | D14: =SUM(D10:D13) -> 92903.28 | E14: =SUM(E10:E13) -> 0 | F14: =SUM(F10:F13) -> 0 | G14: =SUM(G10:G13) -> 26018 | H14: =SUM(H10:H13) -> 2415.18 | I14: =SUM(I10:I13) -> 28433.18 | J14: =SUM(J10:J13) -> 64470.1
A16: After Cost Segregation Correction
A17: Asset | B17: Property Description | C17: Date In Service | D17: Cost | E17: Sec 179 Exp | F17: Bonus Amt | G17: Tax Prior Depreciation | H17: Tax Current Depreciation | I17: End Depreciation | J17: Net Book Value | K17: Method | L17: Period
A18: 1 | B18: 19 - Building - 754 "Menowitz" - 5 year | C18: 9/15/21 | D18: 53.44 | E18: 0 | F18: 53.44 | G18: 53.44 | H18: 0 | I18: =G18+H18 -> 53.44 | J18: =D18-I18 -> 0 | K18: 200DB | L18: 5.0
A19: 2 | B19: 19 - Building - 754 "Menowitz" - 30 year | C19: 9/15/21 | D19: 208.97 | E19: 0 | F19: 0 | G19: 15.97 | H19: 6.97 | I19: =G19+H19 -> 22.94 | J19: =D19-I19 -> 186.03 | K19: S/L | L19: 30.00
A20: 3 | B20: 3 - Building - 5 year | C20: 5/31/17 | D20: 15901.52 | E20: 0 | F20: 0 | G20: 15901.52 | H20: 0 | I20: =G20+H20 -> 15901.52 | J20: =D20-I20 -> 0 | K20: 200DB | L20: 5.0
A21: 4 | B21: 3 - Building - 30 year | C21: 5/31/17 | D21: 62185.11 | E21: 0 | F21: 0 | G21: 13732.56 | H21: 2072.84 | I21: =G21+H21 -> 15805.4 | J21: =D21-I21 -> 46379.71 | K21: S/L | L21: 30.00
A22: 5 | B22: 4 - Personal Property - 5 year | C22: 5/31/17 | D22: 987.94 | E22: 0 | F22: 0 | G22: 987.94 | H22: 0 | I22: =G22+H22 -> 987.94 | J22: =D22-I22 -> 0 | K22: 200DB | L22: 5.0
A23: 6 | B23: 4 - Personal Property - 30 year | C23: 5/31/17 | D23: 3863.47 | E23: 0 | F23: 0 | G23: 853.17 | H23: 128.78 | I23: =G23+H23 -> 981.95 | J23: =D23-I23 -> 2881.52 | K23: S/L | L23: 30.00
A24: 7 | B24: 2 - Land Improvements - 5 year | C24: 5/31/17 | D24: 1975.88 | E24: 0 | F24: 0 | G24: 1975.88 | H24: 0 | I24: =G24+H24 -> 1975.88 | J24: =D24-I24 -> 0 | K24: 200DB | L24: 5.0
A25: 8 | B25: 2 - Land Improvements - 30 year | C25: 5/31/17 | D25: 7726.95 | E25: 0 | F25: 0 | G25: 1706.4 | H25: 257.57 | I25: =G25+H25 -> 1963.97 | J25: =D25-I25 -> 5762.98 | K25: S/L | L25: 30.00
B26: Grand Total | D26: =SUM(D18:D25) -> 92903.28 | E26: =SUM(E18:E25) -> 0 | F26: =SUM(F18:F25) -> 53.44 | G26: =SUM(G18:G25) -> 35226.88 | H26: =SUM(H18:H25) -> 2466.16 | I26: =SUM(I18:I25) -> 37693.04 | J26: =SUM(J18:J25) -> 55210.24
B28: Section 481(a) Adjustment — Regular Tax
B29: Depreciation reported previously | D29: =I14 -> 28433.18
B30: Cost Segregation Corrected Depreciation | D30: =I26 -> 37693.04
B31: Section 481(a) Adjustment — Regular Tax | D31: =D29-D30 -> -9259.86
A33: CALCULATION OF §481(a) ADJUSTMENT — AMT
A34: As Previously Filed — AMT
A35: Asset | B35: Property Description | C35: Date In Service | D35: Cost | E35: Sec 179 Exp | F35: Bonus Amt | G35: AMT Prior Depreciation | H35: AMT Current Depreciation | I35: End Depreciation | J35: Net Book Value | K35: Method | L35: Period
A36: 1 | B36: 19 - Building - 754 "Menowitz" | C36: 9/15/21 | D36: 262.41 | E36: 0 | F36: 0 | G36: 15.89 | H36: 6.55 | I36: =G36+H36 -> 22.44 | J36: =D36-I36 -> 239.97 | K36: S/L | L36: 40.00
A37: 2 | B37: 3 - Building | C37: 5/31/17 | D37: 78086.63 | E37: 0 | F37: 0 | G37: 16805.05 | H37: 1836.16 | I37: =G37+H37 -> 18641.21 | J37: =D37-I37 -> 59445.42 | K37: S/L | L37: 40.00
A38: 3 | B38: 4 - Personal Property | C38: 5/31/17 | D38: 4851.41 | E38: 0 | F38: 0 | G38: 4527.99 | H38: 0 | I38: =G38+H38 -> 4527.99 | J38: =D38-I38 -> 323.42 | K38: S/L | L38: 40.00
A39: 4 | B39: 2 - Land Improvements | C39: 5/31/17 | D39: 9702.83 | E39: 0 | F39: 0 | G39: 4669.07 | H39: 572.47 | I39: =G39+H39 -> 5241.54 | J39: =D39-I39 -> 4461.29 | K39: S/L | L39: 40.00
B40: Grand Total | D40: =SUM(D36:D39) -> 92903.28 | E40: =SUM(E36:E39) -> 0 | F40: =SUM(F36:F39) -> 0 | G40: =SUM(G36:G39) -> 26018 | H40: =SUM(H36:H39) -> 2415.18 | I40: =SUM(I36:I39) -> 28433.18 | J40: =SUM(J36:J39) -> 64470.1
A42: After Cost Segregation Correction — AMT
A43: Asset | B43: Property Description | C43: Date In Service | D43: Cost | E43: Sec 179 Exp | F43: Bonus Amt | G43: AMT Prior Depreciation | H43: AMT Current Depreciation | I43: End Depreciation | J43: Net Book Value | K43: Method | L43: Period
A44: 1 | B44: 19 - Building - 754 "Menowitz" - 5 year | C44: 9/15/21 | D44: 53.44 | E44: 0 | F44: 53.44 | G44: 53.44 | H44: 0 | I44: =G44+H44 -> 53.44 | J44: =D44-I44 -> 0 | K44: 200DB | L44: 5.0
A45: 2 | B45: 19 - Building - 754 "Menowitz" - 30 year | C45: 9/15/21 | D45: 208.97 | E45: 0 | F45: 0 | G45: 15.97 | H45: 6.97 | I45: =G45+H45 -> 22.94 | J45: =D45-I45 -> 186.03 | K45: S/L | L45: 30.00
A46: 3 | B46: 3 - Building - 5 year | C46: 5/31/17 | D46: 15901.52 | E46: 0 | F46: 0 | G46: 15901.52 | H46: 0 | I46: =G46+H46 -> 15901.52 | J46: =D46-I46 -> 0 | K46: 200DB | L46: 5.0
A47: 4 | B47: 3 - Building - 30 year | C47: 5/31/17 | D47: 62185.11 | E47: 0 | F47: 0 | G47: 13732.56 | H47: 2072.84 | I47: =G47+H47 -> 15805.4 | J47: =D47-I47 -> 46379.71 | K47: S/L | L47: 30.00
A48: 5 | B48: 4 - Personal Property - 5 year | C48: 5/31/17 | D48: 987.94 | E48: 0 | F48: 0 | G48: 987.94 | H48: 0 | I48: =G48+H48 -> 987.94 | J48: =D48-I48 -> 0 | K48: 200DB | L48: 5.0
A49: 6 | B49: 4 - Personal Property - 30 year | C49: 5/31/17 | D49: 3863.47 | E49: 0 | F49: 0 | G49: 853.17 | H49: 128.78 | I49: =G49+H49 -> 981.95 | J49: =D49-I49 -> 2881.52 | K49: S/L | L49: 30.00
A50: 7 | B50: 2 - Land Improvements - 5 year | C50: 5/31/17 | D50: 1975.88 | E50: 0 | F50: 0 | G50: 1975.88 | H50: 0 | I50: =G50+H50 -> 1975.88 | J50: =D50-I50 -> 0 | K50: 200DB | L50: 5.0
A51: 8 | B51: 2 - Land Improvements - 30 year | C51: 5/31/17 | D51: 7726.95 | E51: 0 | F51: 0 | G51: 1706.4 | H51: 257.57 | I51: =G51+H51 -> 1963.97 | J51: =D51-I51 -> 5762.98 | K51: S/L | L51: 30.00
B52: Grand Total | D52: =SUM(D44:D51) -> 92903.28 | E52: =SUM(E44:E51) -> 0 | F52: =SUM(F44:F51) -> 53.44 | G52: =SUM(G44:G51) -> 35226.88 | H52: =SUM(H44:H51) -> 2466.16 | I52: =SUM(I44:I51) -> 37693.04 | J52: =SUM(J44:J51) -> 55210.24
B54: Section 481(a) Adjustment — AMT
B55: Depreciation reported previously | D55: =I40 -> 28433.18
B56: Cost Segregation Corrected Depreciation | D56: =I52 -> 37693.04
B57: Section 481(a) Adjustment — AMT | D57: =D55-D56 -> -9259.86
A59: COST SEGREGATION STUDY — COST SUMMARY
B60: Total Building Cost | D60: =D101 -> 92903.28
B61: Building Components: 5 Year | D61: =F101 -> 18918.78
B62: % of Building Cost | D62: =F102 -> 0.20363953
B63: Building Structure: 30 Year | D63: =H101 -> 73984.5
B64: % of Building Cost | D64: =H102 -> 0.79636047
A66: COST SEGREGATION STUDY — COST DETAIL
B67: Property Category | D67: Cost | F67: 5 Year | H67: 30 Year
B68: Building Components
B69: Cabinets / Millwork | D69: =SUM(F69:H69) -> 520.44 | F69: 520.44
B70: Moldings | D70: =SUM(F70:H70) -> 1317.26 | F70: 1317.26
B71: Flooring - Carpet | D71: =SUM(F71:H71) -> 3476.89 | F71: 3476.89
B72: Flooring - Vinyl Plank | D72: =SUM(F72:H72) -> 1033.5 | F72: 1033.5
B73: Interior Half Walls | D73: =SUM(F73:H73) -> 80.4 | F73: 80.4
B74: Window Treatments | D74: =SUM(F74:H74) -> 417.88 | F74: 417.88
B75: Specialty HVAC - Dryer Vents | D75: =SUM(F75:H75) -> 318.53 | F75: 318.53
B76: Specialty Electrical - Appliances | D76: =SUM(F76:H76) -> 2056.7 | F76: 2056.7
B77: Communication / Data | D77: =SUM(F77:H77) -> 2255.5 | F77: 2255.5
B78: Specialty Plumbing - Breakroom Sink / Laundry | D78: =SUM(F78:H78) -> 1908.2 | F78: 1908.2
B79: Security / Exterior Lighting | D79: =SUM(F79:H79) -> 264.96 | F79: 264.96
B80: Interior Windows | D80: =SUM(F80:H80) -> 104.91 | F80: 104.91
... B82: Appliances | D82: =SUM(F82:H82) -> 5131.77 | F82: 5131.77
B83: Building Structure
B84: Roofing Systems | D84: =SUM(F84:H84) -> 5390.21 | H84: 5390.21
B85: Foundations | D85: =SUM(F85:H85) -> 9199.73 | H85: 9199.73
B86: HVAC | D86: =SUM(F86:H86) -> 6425.49 | H86: 6425.49
B87: Electrical | D87: =SUM(F87:H87) -> 5288.25 | H87: 5288.25
B88: Plumbing | D88: =SUM(F88:H88) -> 5862.54 | H88: 5862.54
B89: Fire Protection & Alarm | D89: =SUM(F89:H89) -> 31.08 | H89: 31.08
B90: Exterior Façade / Building Skin | D90: =SUM(F90:H90) -> 7191.13 | H90: 7191.13
B91: Doors & Frames | D91: =SUM(F91:H91) -> 3067.26 | H91: 3067.26
B92: Windows | D92: =SUM(F92:H92) -> 1771.93 | H92: 1771.93
B93: Ceiling Systems | D93: =SUM(F93:H93) -> 3101.74 | H93: 3101.74
B94: Interior Framing / Partitions | D94: =SUM(F94:H94) -> 10409.1 | H94: 10409.1
B95: Painting | D95: =SUM(F95:H95) -> 3502.1 | H95: 3502.1
... B100: Bathroom Accessories | D100: =SUM(F100:H100) -> 176 | H100: 176
B101: Total Building Cost | D101: =SUM(D69:D100) -> 92903.28 | F101: =SUM(F69:F82) -> 18918.78 | H101: =SUM(H84:H100) -> 73984.5
B102: % of Building Cost | F102: =F101/D101 -> 0.20363953 | H102: =H101/D101 -> 0.79636047
A104: ASSET ALLOCATION
B105: Asset | D105: Cost | F105: 5 Year | H105: 30 Year
B106: Asset # 19 - Building - 754 "Menowitz" | D106: =F106+H106 -> 262.41 | F106: 53.44 | H106: 208.97
B107: Asset # 3 - Building | D107: =F107+H107 -> 78086.63 | F107: 15901.52 | H107: 62185.11
B108: Asset # 4 - Personal Property | D108: =F108+H108 -> 4851.41 | F108: 987.94 | H108: 3863.47
B109: Asset # 2 - Land Improvements | D109: =F109+H109 -> 9702.83 | F109: 1975.88 | H109: 7726.95
B110: Total Allocation | D110: =SUM(D106:D109) -> 92903.28 | F110: =SUM(F106:F109) -> 18918.78 | H110: =SUM(H106:H109) -> 73984.5
B111: Check: Allocation vs. Cost Detail (should be zero) | D111: =D110-D101 -> 0

Sheet Building 5
A1: Silver Springs Housing, LP
A2: Silver Spring Terrace Apartments — 950 20th St NE, Hickory, NC 28601
A3: EIN: 82-0773652 · FYE: December 31, 2024 · Year of Change: 1/1/2024
A4: Building 5 — Attachment to Form 3115 (DCN #7, Rev. Proc. 2024-23 §6.01)
A5: Source: CSSI Report #107752-39, "Silver Springs Housing LP_#107752-39_3115_Combined R1.pdf"
A7: CALCULATION OF §481(a) ADJUSTMENT — REGULAR TAX
A8: As Previously Filed
A9: Asset | B9: Property Description | C9: Date In Service | D9: Cost | E9: Sec 179 Exp | F9: Bonus Amt | G9: Tax Prior Depreciation | H9: Tax Current Depreciation | I9: End Depreciation | J9: Net Book Value | K9: Method | L9: Period
A10: 1 | B10: 19 - Building - 754 "Menowitz" | C10: 9/15/21 | D10: 479.53 | E10: 0 | F10: 0 | G10: 29.03 | H10: 11.97 | I10: =G10+H10 -> 41 | J10: =D10-I10 -> 438.53 | K10: S/L | L10: 40.00
A11: 2 | B11: 3 - Building | C11: 5/31/17 | D11: 142694.3 | E11: 0 | F11: 0 | G11: 30709.29 | H11: 3355.37 | I11: =G11+H11 -> 34064.66 | J11: =D11-I11 -> 108629.64 | K11: S/L | L11: 40.00
A12: 3 | B12: 4 - Personal Property | C12: 5/31/17 | D12: 8865.4 | E12: 0 | F12: 0 | G12: 8274.39 | H12: 0 | I12: =G12+H12 -> 8274.39 | J12: =D12-I12 -> 591.01 | K12: S/L | L12: 40.00
A13: 4 | B13: 2 - Land Improvements | C13: 5/31/17 | D13: 17730.79 | E13: 0 | F13: 0 | G13: 8532.2 | H13: 1046.12 | I13: =G13+H13 -> 9578.32 | J13: =D13-I13 -> 8152.47 | K13: S/L | L13: 40.00
B14: Grand Total | D14: =SUM(D10:D13) -> 169770.02 | E14: =SUM(E10:E13) -> 0 | F14: =SUM(F10:F13) -> 0 | G14: =SUM(G10:G13) -> 47544.91 | H14: =SUM(H10:H13) -> 4413.46 | I14: =SUM(I10:I13) -> 51958.37 | J14: =SUM(J10:J13) -> 117811.65
A16: After Cost Segregation Correction
A17: Asset | B17: Property Description | C17: Date In Service | D17: Cost | E17: Sec 179 Exp | F17: Bonus Amt | G17: Tax Prior Depreciation | H17: Tax Current Depreciation | I17: End Depreciation | J17: Net Book Value | K17: Method | L17: Period
A18: 1 | B18: 19 - Building - 754 "Menowitz" - 5 year | C18: 9/15/21 | D18: 89.94 | E18: 0 | F18: 89.94 | G18: 89.94 | H18: 0 | I18: =G18+H18 -> 89.94 | J18: =D18-I18 -> 0 | K18: 200DB | L18: 5.0
A19: 2 | B19: 19 - Building - 754 "Menowitz" - 30 year | C19: 9/15/21 | D19: 389.59 | E19: 0 | F19: 0 | G19: 29.77 | H19: 12.99 | I19: =G19+H19 -> 42.76 | J19: =D19-I19 -> 346.83 | K19: S/L | L19: 30.00
A20: 3 | B20: 3 - Building - 5 year | C20: 5/31/17 | D20: 26763.65 | E20: 0 | F20: 0 | G20: 26763.65 | H20: 0 | I20: =G20+H20 -> 26763.65 | J20: =D20-I20 -> 0 | K20: 200DB | L20: 5.0
A21: 4 | B21: 3 - Building - 30 year | C21: 5/31/17 | D21: 115930.65 | E21: 0 | F21: 0 | G21: 25601.32 | H21: 3864.35 | I21: =G21+H21 -> 29465.67 | J21: =D21-I21 -> 86464.98 | K21: S/L | L21: 30.00
A22: 5 | B22: 4 - Personal Property - 5 year | C22: 5/31/17 | D22: 1662.79 | E22: 0 | F22: 0 | G22: 1662.79 | H22: 0 | I22: =G22+H22 -> 1662.79 | J22: =D22-I22 -> 0 | K22: 200DB | L22: 5.0
A23: 6 | B23: 4 - Personal Property - 30 year | C23: 5/31/17 | D23: 7202.61 | E23: 0 | F23: 0 | G23: 1590.59 | H23: 240.09 | I23: =G23+H23 -> 1830.68 | J23: =D23-I23 -> 5371.93 | K23: S/L | L23: 30.00
A24: 7 | B24: 2 - Land Improvements - 5 year | C24: 5/31/17 | D24: 3325.57 | E24: 0 | F24: 0 | G24: 3325.57 | H24: 0 | I24: =G24+H24 -> 3325.57 | J24: =D24-I24 -> 0 | K24: 200DB | L24: 5.0
A25: 8 | B25: 2 - Land Improvements - 30 year | C25: 5/31/17 | D25: 14405.22 | E25: 0 | F25: 0 | G25: 3181.13 | H25: 480.17 | I25: =G25+H25 -> 3661.3 | J25: =D25-I25 -> 10743.92 | K25: S/L | L25: 30.00
B26: Grand Total | D26: =SUM(D18:D25) -> 169770.02 | E26: =SUM(E18:E25) -> 0 | F26: =SUM(F18:F25) -> 89.94 | G26: =SUM(G18:G25) -> 62244.76 | H26: =SUM(H18:H25) -> 4597.6 | I26: =SUM(I18:I25) -> 66842.36 | J26: =SUM(J18:J25) -> 102927.66
B28: Section 481(a) Adjustment — Regular Tax
B29: Depreciation reported previously | D29: =I14 -> 51958.37
B30: Cost Segregation Corrected Depreciation | D30: =I26 -> 66842.36
B31: Section 481(a) Adjustment — Regular Tax | D31: =D29-D30 -> -14883.99
A33: CALCULATION OF §481(a) ADJUSTMENT — AMT
A34: As Previously Filed — AMT
A35: Asset | B35: Property Description | C35: Date In Service | D35: Cost | E35: Sec 179 Exp | F35: Bonus Amt | G35: AMT Prior Depreciation | H35: AMT Current Depreciation | I35: End Depreciation | J35: Net Book Value | K35: Method | L35: Period
A36: 1 | B36: 19 - Building - 754 "Menowitz" | C36: 9/15/21 | D36: 479.53 | E36: 0 | F36: 0 | G36: 29.03 | H36: 11.97 | I36: =G36+H36 -> 41 | J36: =D36-I36 -> 438.53 | K36: S/L | L36: 40.00
A37: 2 | B37: 3 - Building | C37: 5/31/17 | D37: 142694.3 | E37: 0 | F37: 0 | G37: 30709.29 | H37: 3355.37 | I37: =G37+H37 -> 34064.66 | J37: =D37-I37 -> 108629.64 | K37: S/L | L37: 40.00
A38: 3 | B38: 4 - Personal Property | C38: 5/31/17 | D38: 8865.4 | E38: 0 | F38: 0 | G38: 8274.39 | H38: 0 | I38: =G38+H38 -> 8274.39 | J38: =D38-I38 -> 591.01 | K38: S/L | L38: 40.00
A39: 4 | B39: 2 - Land Improvements | C39: 5/31/17 | D39: 17730.79 | E39: 0 | F39: 0 | G39: 8532.2 | H39: 1046.12 | I39: =G39+H39 -> 9578.32 | J39: =D39-I39 -> 8152.47 | K39: S/L | L39: 40.00
B40: Grand Total | D40: =SUM(D36:D39) -> 169770.02 | E40: =SUM(E36:E39) -> 0 | F40: =SUM(F36:F39) -> 0 | G40: =SUM(G36:G39) -> 47544.91 | H40: =SUM(H36:H39) -> 4413.46 | I40: =SUM(I36:I39) -> 51958.37 | J40: =SUM(J36:J39) -> 117811.65
A42: After Cost Segregation Correction — AMT
A43: Asset | B43: Property Description | C43: Date In Service | D43: Cost | E43: Sec 179 Exp | F43: Bonus Amt | G43: AMT Prior Depreciation | H43: AMT Current Depreciation | I43: End Depreciation | J43: Net Book Value | K43: Method | L43: Period
A44: 1 | B44: 19 - Building - 754 "Menowitz" - 5 year | C44: 9/15/21 | D44: 89.94 | E44: 0 | F44: 89.94 | G44: 89.94 | H44: 0 | I44: =G44+H44 -> 89.94 | J44: =D44-I44 -> 0 | K44: 200DB | L44: 5.0
A45: 2 | B45: 19 - Building - 754 "Menowitz" - 30 year | C45: 9/15/21 | D45: 389.59 | E45: 0 | F45: 0 | G45: 29.77 | H45: 12.99 | I45: =G45+H45 -> 42.76 | J45: =D45-I45 -> 346.83 | K45: S/L | L45: 30.00
A46: 3 | B46: 3 - Building - 5 year | C46: 5/31/17 | D46: 26763.65 | E46: 0 | F46: 0 | G46: 26763.65 | H46: 0 | I46: =G46+H46 -> 26763.65 | J46: =D46-I46 -> 0 | K46: 200DB | L46: 5.0
A47: 4 | B47: 3 - Building - 30 year | C47: 5/31/17 | D47: 115930.65 | E47: 0 | F47: 0 | G47: 25601.32 | H47: 3864.35 | I47: =G47+H47 -> 29465.67 | J47: =D47-I47 -> 86464.98 | K47: S/L | L47: 30.00
A48: 5 | B48: 4 - Personal Property - 5 year | C48: 5/31/17 | D48: 1662.79 | E48: 0 | F48: 0 | G48: 1662.79 | H48: 0 | I48: =G48+H48 -> 1662.79 | J48: =D48-I48 -> 0 | K48: 200DB | L48: 5.0
A49: 6 | B49: 4 - Personal Property - 30 year | C49: 5/31/17 | D49: 7202.61 | E49: 0 | F49: 0 | G49: 1590.59 | H49: 240.09 | I49: =G49+H49 -> 1830.68 | J49: =D49-I49 -> 5371.93 | K49: S/L | L49: 30.00
A50: 7 | B50: 2 - Land Improvements - 5 year | C50: 5/31/17 | D50: 3325.57 | E50: 0 | F50: 0 | G50: 3325.57 | H50: 0 | I50: =G50+H50 -> 3325.57 | J50: =D50-I50 -> 0 | K50: 200DB | L50: 5.0
A51: 8 | B51: 2 - Land Improvements - 30 year | C51: 5/31/17 | D51: 14405.22 | E51: 0 | F51: 0 | G51: 3181.13 | H51: 480.17 | I51: =G51+H51 -> 3661.3 | J51: =D51-I51 -> 10743.92 | K51: S/L | L51: 30.00
B52: Grand Total | D52: =SUM(D44:D51) -> 169770.02 | E52: =SUM(E44:E51) -> 0 | F52: =SUM(F44:F51) -> 89.94 | G52: =SUM(G44:G51) -> 62244.76 | H52: =SUM(H44:H51) -> 4597.6 | I52: =SUM(I44:I51) -> 66842.36 | J52: =SUM(J44:J51) -> 102927.66
B54: Section 481(a) Adjustment — AMT
B55: Depreciation reported previously | D55: =I40 -> 51958.37
B56: Cost Segregation Corrected Depreciation | D56: =I52 -> 66842.36
B57: Section 481(a) Adjustment — AMT | D57: =D55-D56 -> -14883.99
A59: COST SEGREGATION STUDY — COST SUMMARY
B60: Total Building Cost | D60: =D98 -> 169770.02
B61: Building Components: 5 Year | D61: =F98 -> 31841.95
B62: % of Building Cost | D62: =F99 -> 0.18755932
B63: Building Structure: 30 Year | D63: =H98 -> 137928.07
B64: % of Building Cost | D64: =H99 -> 0.81244068
A66: COST SEGREGATION STUDY — COST DETAIL
B67: Property Category | D67: Cost | F67: 5 Year | H67: 30 Year
B68: Building Components
B69: Cabinets / Millwork | D69: =SUM(F69:H69) -> 7800.47 | F69: 7800.47
B70: Moldings | D70: =SUM(F70:H70) -> 3748.91 | F70: 3748.91
B71: Flooring - Vinyl Plank | D71: =SUM(F71:H71) -> 12139.37 | F71: 12139.37
B72: Window Treatments | D72: =SUM(F72:H72) -> 1142.58 | F72: 1142.58
B73: Building Signage | D73: =SUM(F73:H73) -> 85.24 | F73: 85.24
B74: Specialty Electrical - Appliances | D74: =SUM(F74:H74) -> 1274.42 | F74: 1274.42
B75: Communication / Data | D75: =SUM(F75:H75) -> 1052.34 | F75: 1052.34
B76: Specialty Plumbing - Kitchen Sinks | D76: =SUM(F76:H76) -> 2313.24 | F76: 2313.24
B77: Security / Exterior Lighting | D77: =SUM(F77:H77) -> 252.07 | F77: 252.07
B78: Access Control | D78: =SUM(F78:H78) -> 37.76 | F78: 37.76
B79: Appliances | D79: =SUM(F79:H79) -> 1995.55 | F79: 1995.55
B80: Building Structure
B81: Roofing Systems | D81: =SUM(F81:H81) -> 5090 | H81: 5090
B82: Foundations | D82: =SUM(F82:H82) -> 8538.11 | H82: 8538.11
B83: HVAC | D83: =SUM(F83:H83) -> 11754.94 | H83: 11754.94
B84: Electrical | D84: =SUM(F84:H84) -> 11527.95 | H84: 11527.95
B85: Plumbing | D85: =SUM(F85:H85) -> 10218.5 | H85: 10218.5
B86: Fire Protection & Alarm | D86: =SUM(F86:H86) -> 775.83 | H86: 775.83
B87: Exterior Façade / Building Skin | D87: =SUM(F87:H87) -> 22829.89 | H87: 22829.89
B88: Doors & Frames | D88: =SUM(F88:H88) -> 5886.42 | H88: 5886.42
B89: Windows | D89: =SUM(F89:H89) -> 5036.01 | H89: 5036.01
B90: Ceiling Systems | D90: =SUM(F90:H90) -> 5406.4 | H90: 5406.4
B91: Interior Framing / Partitions | D91: =SUM(F91:H91) -> 16464.28 | H91: 16464.28
B92: Painting | D92: =SUM(F92:H92) -> 5938.8 | H92: 5938.8
... B97: Cabinets / Millwork - Restrooms | D97: =SUM(F97:H97) -> 901.51 | H97: 901.51
B98: Total Building Cost | D98: =SUM(D69:D97) -> 169770.02 | F98: =SUM(F69:F79) -> 31841.95 | H98: =SUM(H81:H97) -> 137928.07
B99: % of Building Cost | F99: =F98/D98 -> 0.18755932 | H99: =H98/D98 -> 0.81244068
A101: ASSET ALLOCATION
B102: Asset | D102: Cost | F102: 5 Year | H102: 30 Year
B103: Asset # 19 - Building - 754 "Menowitz" | D103: =F103+H103 -> 479.53 | F103: 89.94 | H103: 389.59
B104: Asset # 3 - Building | D104: =F104+H104 -> 142694.3 | F104: 26763.65 | H104: 115930.65
B105: Asset # 4 - Personal Property | D105: =F105+H105 -> 8865.4 | F105: 1662.79 | H105: 7202.61
B106: Asset # 2 - Land Improvements | D106: =F106+H106 -> 17730.79 | F106: 3325.57 | H106: 14405.22
B107: Total Allocation | D107: =SUM(D103:D106) -> 169770.02 | F107: =SUM(F103:F106) -> 31841.95 | H107: =SUM(H103:H106) -> 137928.07
B108: Check: Allocation vs. Cost Detail (should be zero) | D108: =D107-D98 -> 0

Sheet Building 6
A1: Silver Springs Housing, LP
A2: Silver Spring Terrace Apartments — 950 20th St NE, Hickory, NC 28601
A3: EIN: 82-0773652 · FYE: December 31, 2024 · Year of Change: 1/1/2024
A4: Building 6 — Attachment to Form 3115 (DCN #7, Rev. Proc. 2024-23 §6.01)
A5: Source: CSSI Report #107752-39, "Silver Springs Housing LP_#107752-39_3115_Combined R1.pdf"
A7: CALCULATION OF §481(a) ADJUSTMENT — REGULAR TAX
A8: As Previously Filed
A9: Asset | B9: Property Description | C9: Date In Service | D9: Cost | E9: Sec 179 Exp | F9: Bonus Amt | G9: Tax Prior Depreciation | H9: Tax Current Depreciation | I9: End Depreciation | J9: Net Book Value | K9: Method | L9: Period
A10: 1 | B10: 19 - Building - 754 "Menowitz" | C10: 9/15/21 | D10: 750.82 | E10: 0 | F10: 0 | G10: 45.46 | H10: 18.74 | I10: =G10+H10 -> 64.2 | J10: =D10-I10 -> 686.62 | K10: S/L | L10: 40.00
A11: 2 | B11: 3 - Building | C11: 5/31/17 | D11: 223422.8 | E11: 0 | F11: 0 | G11: 48082.9 | H11: 5253.66 | I11: =G11+H11 -> 53336.56 | J11: =D11-I11 -> 170086.24 | K11: S/L | L11: 40.00
A12: 3 | B12: 4 - Personal Property | C12: 5/31/17 | D12: 13880.94 | E12: 0 | F12: 0 | G12: 12955.57 | H12: 0 | I12: =G12+H12 -> 12955.57 | J12: =D12-I12 -> 925.37 | K12: S/L | L12: 40.00
A13: 4 | B13: 2 - Land Improvements | C13: 5/31/17 | D13: 27761.89 | E13: 0 | F13: 0 | G13: 13359.23 | H13: 1637.95 | I13: =G13+H13 -> 14997.18 | J13: =D13-I13 -> 12764.71 | K13: S/L | L13: 40.00
B14: Grand Total | D14: =SUM(D10:D13) -> 265816.45 | E14: =SUM(E10:E13) -> 0 | F14: =SUM(F10:F13) -> 0 | G14: =SUM(G10:G13) -> 74443.16 | H14: =SUM(H10:H13) -> 6910.35 | I14: =SUM(I10:I13) -> 81353.51 | J14: =SUM(J10:J13) -> 184462.94
A16: After Cost Segregation Correction
A17: Asset | B17: Property Description | C17: Date In Service | D17: Cost | E17: Sec 179 Exp | F17: Bonus Amt | G17: Tax Prior Depreciation | H17: Tax Current Depreciation | I17: End Depreciation | J17: Net Book Value | K17: Method | L17: Period
A18: 1 | B18: 19 - Building - 754 "Menowitz" - 5 year | C18: 9/15/21 | D18: 157.52 | E18: 0 | F18: 157.52 | G18: 157.52 | H18: 0 | I18: =G18+H18 -> 157.52 | J18: =D18-I18 -> 0 | K18: 200DB | L18: 5.0
A19: 2 | B19: 19 - Building - 754 "Menowitz" - 30 year | C19: 9/15/21 | D19: 593.3 | E19: 0 | F19: 0 | G19: 45.33 | H19: 19.78 | I19: =G19+H19 -> 65.11 | J19: =D19-I19 -> 528.19 | K19: S/L | L19: 30.00
A20: 3 | B20: 3 - Building - 5 year | C20: 5/31/17 | D20: 46872.91 | E20: 0 | F20: 0 | G20: 46872.91 | H20: 0 | I20: =G20+H20 -> 46872.91 | J20: =D20-I20 -> 0 | K20: 200DB | L20: 5.0
A21: 4 | B21: 3 - Building - 30 year | C21: 5/31/17 | D21: 176549.89 | E21: 0 | F21: 0 | G21: 38988.12 | H21: 5885 | I21: =G21+H21 -> 44873.12 | J21: =D21-I21 -> 131676.77 | K21: S/L | L21: 30.00
A22: 5 | B22: 4 - Personal Property - 5 year | C22: 5/31/17 | D22: 2912.15 | E22: 0 | F22: 0 | G22: 2912.15 | H22: 0 | I22: =G22+H22 -> 2912.15 | J22: =D22-I22 -> 0 | K22: 200DB | L22: 5.0
A23: 6 | B23: 4 - Personal Property - 30 year | C23: 5/31/17 | D23: 10968.79 | E23: 0 | F23: 0 | G23: 2422.3 | H23: 365.63 | I23: =G23+H23 -> 2787.93 | J23: =D23-I23 -> 8180.86 | K23: S/L | L23: 30.00
A24: 7 | B24: 2 - Land Improvements - 5 year | C24: 5/31/17 | D24: 5824.29 | E24: 0 | F24: 0 | G24: 5824.29 | H24: 0 | I24: =G24+H24 -> 5824.29 | J24: =D24-I24 -> 0 | K24: 200DB | L24: 5.0
A25: 8 | B25: 2 - Land Improvements - 30 year | C25: 5/31/17 | D25: 21937.6 | E25: 0 | F25: 0 | G25: 4844.53 | H25: 731.25 | I25: =G25+H25 -> 5575.78 | J25: =D25-I25 -> 16361.82 | K25: S/L | L25: 30.00
B26: Grand Total | D26: =SUM(D18:D25) -> 265816.45 | E26: =SUM(E18:E25) -> 0 | F26: =SUM(F18:F25) -> 157.52 | G26: =SUM(G18:G25) -> 102067.15 | H26: =SUM(H18:H25) -> 7001.66 | I26: =SUM(I18:I25) -> 109068.81 | J26: =SUM(J18:J25) -> 156747.64
B28: Section 481(a) Adjustment — Regular Tax
B29: Depreciation reported previously | D29: =I14 -> 81353.51
B30: Cost Segregation Corrected Depreciation | D30: =I26 -> 109068.81
B31: Section 481(a) Adjustment — Regular Tax | D31: =D29-D30 -> -27715.3
A33: CALCULATION OF §481(a) ADJUSTMENT — AMT
A34: As Previously Filed — AMT
A35: Asset | B35: Property Description | C35: Date In Service | D35: Cost | E35: Sec 179 Exp | F35: Bonus Amt | G35: AMT Prior Depreciation | H35: AMT Current Depreciation | I35: End Depreciation | J35: Net Book Value | K35: Method | L35: Period
A36: 1 | B36: 19 - Building - 754 "Menowitz" | C36: 9/15/21 | D36: 750.82 | E36: 0 | F36: 0 | G36: 45.46 | H36: 18.74 | I36: =G36+H36 -> 64.2 | J36: =D36-I36 -> 686.62 | K36: S/L | L36: 40.00
A37: 2 | B37: 3 - Building | C37: 5/31/17 | D37: 223422.8 | E37: 0 | F37: 0 | G37: 48082.9 | H37: 5253.66 | I37: =G37+H37 -> 53336.56 | J37: =D37-I37 -> 170086.24 | K37: S/L | L37: 40.00
A38: 3 | B38: 4 - Personal Property | C38: 5/31/17 | D38: 13880.94 | E38: 0 | F38: 0 | G38: 12955.57 | H38: 0 | I38: =G38+H38 -> 12955.57 | J38: =D38-I38 -> 925.37 | K38: S/L | L38: 40.00
A39: 4 | B39: 2 - Land Improvements | C39: 5/31/17 | D39: 27761.89 | E39: 0 | F39: 0 | G39: 13359.23 | H39: 1637.95 | I39: =G39+H39 -> 14997.18 | J39: =D39-I39 -> 12764.71 | K39: S/L | L39: 40.00
B40: Grand Total | D40: =SUM(D36:D39) -> 265816.45 | E40: =SUM(E36:E39) -> 0 | F40: =SUM(F36:F39) -> 0 | G40: =SUM(G36:G39) -> 74443.16 | H40: =SUM(H36:H39) -> 6910.35 | I40: =SUM(I36:I39) -> 81353.51 | J40: =SUM(J36:J39) -> 184462.94
A42: After Cost Segregation Correction — AMT
A43: Asset | B43: Property Description | C43: Date In Service | D43: Cost | E43: Sec 179 Exp | F43: Bonus Amt | G43: AMT Prior Depreciation | H43: AMT Current Depreciation | I43: End Depreciation | J43: Net Book Value | K43: Method | L43: Period
A44: 1 | B44: 19 - Building - 754 "Menowitz" - 5 year | C44: 9/15/21 | D44: 157.52 | E44: 0 | F44: 157.52 | G44: 157.52 | H44: 0 | I44: =G44+H44 -> 157.52 | J44: =D44-I44 -> 0 | K44: 200DB | L44: 5.0
A45: 2 | B45: 19 - Building - 754 "Menowitz" - 30 year | C45: 9/15/21 | D45: 593.3 | E45: 0 | F45: 0 | G45: 45.33 | H45: 19.78 | I45: =G45+H45 -> 65.11 | J45: =D45-I45 -> 528.19 | K45: S/L | L45: 30.00
A46: 3 | B46: 3 - Building - 5 year | C46: 5/31/17 | D46: 46872.91 | E46: 0 | F46: 0 | G46: 46872.91 | H46: 0 | I46: =G46+H46 -> 46872.91 | J46: =D46-I46 -> 0 | K46: 200DB | L46: 5.0
A47: 4 | B47: 3 - Building - 30 year | C47: 5/31/17 | D47: 176549.89 | E47: 0 | F47: 0 | G47: 38988.12 | H47: 5885 | I47: =G47+H47 -> 44873.12 | J47: =D47-I47 -> 131676.77 | K47: S/L | L47: 30.00
A48: 5 | B48: 4 - Personal Property - 5 year | C48: 5/31/17 | D48: 2912.15 | E48: 0 | F48: 0 | G48: 2912.15 | H48: 0 | I48: =G48+H48 -> 2912.15 | J48: =D48-I48 -> 0 | K48: 200DB | L48: 5.0
A49: 6 | B49: 4 - Personal Property - 30 year | C49: 5/31/17 | D49: 10968.79 | E49: 0 | F49: 0 | G49: 2422.3 | H49: 365.63 | I49: =G49+H49 -> 2787.93 | J49: =D49-I49 -> 8180.86 | K49: S/L | L49: 30.00
A50: 7 | B50: 2 - Land Improvements - 5 year | C50: 5/31/17 | D50: 5824.29 | E50: 0 | F50: 0 | G50: 5824.29 | H50: 0 | I50: =G50+H50 -> 5824.29 | J50: =D50-I50 -> 0 | K50: 200DB | L50: 5.0
A51: 8 | B51: 2 - Land Improvements - 30 year | C51: 5/31/17 | D51: 21937.6 | E51: 0 | F51: 0 | G51: 4844.53 | H51: 731.25 | I51: =G51+H51 -> 5575.78 | J51: =D51-I51 -> 16361.82 | K51: S/L | L51: 30.00
B52: Grand Total | D52: =SUM(D44:D51) -> 265816.45 | E52: =SUM(E44:E51) -> 0 | F52: =SUM(F44:F51) -> 157.52 | G52: =SUM(G44:G51) -> 102067.15 | H52: =SUM(H44:H51) -> 7001.66 | I52: =SUM(I44:I51) -> 109068.81 | J52: =SUM(J44:J51) -> 156747.64
B54: Section 481(a) Adjustment — AMT
B55: Depreciation reported previously | D55: =I40 -> 81353.51
B56: Cost Segregation Corrected Depreciation | D56: =I52 -> 109068.81
B57: Section 481(a) Adjustment — AMT | D57: =D55-D56 -> -27715.3
A59: COST SEGREGATION STUDY — COST SUMMARY
B60: Total Building Cost | D60: =D98 -> 265816.45
B61: Building Components: 5 Year | D61: =F98 -> 55766.87
B62: % of Building Cost | D62: =F99 -> 0.20979465
B63: Building Structure: 30 Year | D63: =H98 -> 210049.58
B64: % of Building Cost | D64: =H99 -> 0.79020535
A66: COST SEGREGATION STUDY — COST DETAIL
B67: Property Category | D67: Cost | F67: 5 Year | H67: 30 Year
B68: Building Components
B69: Cabinets / Millwork | D69: =SUM(F69:H69) -> 13932.37 | F69: 13932.37
B70: Moldings | D70: =SUM(F70:H70) -> 4762.13 | F70: 4762.13
B71: Flooring - Vinyl Plank | D71: =SUM(F71:H71) -> 21399.52 | F71: 21399.52
B72: Window Treatments | D72: =SUM(F72:H72) -> 1967.77 | F72: 1967.77
B73: Building Signage | D73: =SUM(F73:H73) -> 127.35 | F73: 127.35
B74: Specialty Electrical - Appliances | D74: =SUM(F74:H74) -> 2548.79 | F74: 2548.79
B75: Communication / Data | D75: =SUM(F75:H75) -> 1855.1 | F75: 1855.1
B76: Specialty Plumbing - Kitchen Sinks | D76: =SUM(F76:H76) -> 4626.46 | F76: 4626.46
B77: Security / Exterior Lighting | D77: =SUM(F77:H77) -> 480.75 | F77: 480.75
B78: Access Control | D78: =SUM(F78:H78) -> 75.53 | F78: 75.53
B79: Appliances | D79: =SUM(F79:H79) -> 3991.1 | F79: 3991.1
B80: Building Structure
B81: Roofing Systems | D81: =SUM(F81:H81) -> 8726.14 | H81: 8726.14
B82: Foundations | D82: =SUM(F82:H82) -> 14310.97 | H82: 14310.97
B83: HVAC | D83: =SUM(F83:H83) -> 20721.85 | H83: 20721.85
B84: Electrical | D84: =SUM(F84:H84) -> 20019.46 | H84: 20019.46
B85: Plumbing | D85: =SUM(F85:H85) -> 18013.39 | H85: 18013.39
B86: Fire Protection & Alarm | D86: =SUM(F86:H86) -> 1255.28 | H86: 1255.28
B87: Exterior Façade / Building Skin | D87: =SUM(F87:H87) -> 28034.85 | H87: 28034.85
B88: Doors & Frames | D88: =SUM(F88:H88) -> 9209.33 | H88: 9209.33
B89: Windows | D89: =SUM(F89:H89) -> 8673.12 | H89: 8673.12
B90: Ceiling Systems | D90: =SUM(F90:H90) -> 9530.52 | H90: 9530.52
B91: Interior Framing / Partitions | D91: =SUM(F91:H91) -> 20615.67 | H91: 20615.67
B92: Painting | D92: =SUM(F92:H92) -> 8186.44 | H92: 8186.44
... B97: Cabinets / Millwork - Restrooms | D97: =SUM(F97:H97) -> 901.51 | H97: 901.51
B98: Total Building Cost | D98: =SUM(D69:D97) -> 265816.45 | F98: =SUM(F69:F79) -> 55766.87 | H98: =SUM(H81:H97) -> 210049.58
B99: % of Building Cost | F99: =F98/D98 -> 0.20979465 | H99: =H98/D98 -> 0.79020535
A101: ASSET ALLOCATION
B102: Asset | D102: Cost | F102: 5 Year | H102: 30 Year
B103: Asset # 19 - Building - 754 "Menowitz" | D103: =F103+H103 -> 750.82 | F103: 157.52 | H103: 593.3
B104: Asset # 3 - Building | D104: =F104+H104 -> 223422.8 | F104: 46872.91 | H104: 176549.89
B105: Asset # 4 - Personal Property | D105: =F105+H105 -> 13880.94 | F105: 2912.15 | H105: 10968.79
B106: Asset # 2 - Land Improvements | D106: =F106+H106 -> 27761.89 | F106: 5824.29 | H106: 21937.6
B107: Total Allocation | D107: =SUM(D103:D106) -> 265816.45 | F107: =SUM(F103:F106) -> 55766.87 | H107: =SUM(H103:H106) -> 210049.58
B108: Check: Allocation vs. Cost Detail (should be zero) | D108: =D107-D98 -> 0

Sheet Building 7
A1: Silver Springs Housing, LP
A2: Silver Spring Terrace Apartments — 950 20th St NE, Hickory, NC 28601
A3: EIN: 82-0773652 · FYE: December 31, 2024 · Year of Change: 1/1/2024
A4: Building 7 — Attachment to Form 3115 (DCN #7, Rev. Proc. 2024-23 §6.01)
A5: Source: CSSI Report #107752-39, "Silver Springs Housing LP_#107752-39_3115_Combined R1.pdf"
A7: CALCULATION OF §481(a) ADJUSTMENT — REGULAR TAX
A8: As Previously Filed
A9: Asset | B9: Property Description | C9: Date In Service | D9: Cost | E9: Sec 179 Exp | F9: Bonus Amt | G9: Tax Prior Depreciation | H9: Tax Current Depreciation | I9: End Depreciation | J9: Net Book Value | K9: Method | L9: Period
A10: 1 | B10: 19 - Building - 754 "Menowitz" | C10: 9/15/21 | D10: 750.82 | E10: 0 | F10: 0 | G10: 45.46 | H10: 18.74 | I10: =G10+H10 -> 64.2 | J10: =D10-I10 -> 686.62 | K10: S/L | L10: 40.00
A11: 2 | B11: 3 - Building | C11: 5/31/17 | D11: 223422.8 | E11: 0 | F11: 0 | G11: 48082.9 | H11: 5253.66 | I11: =G11+H11 -> 53336.56 | J11: =D11-I11 -> 170086.24 | K11: S/L | L11: 40.00
A12: 3 | B12: 4 - Personal Property | C12: 5/31/17 | D12: 13880.94 | E12: 0 | F12: 0 | G12: 12955.57 | H12: 0 | I12: =G12+H12 -> 12955.57 | J12: =D12-I12 -> 925.37 | K12: S/L | L12: 40.00
A13: 4 | B13: 2 - Land Improvements | C13: 5/31/17 | D13: 27761.89 | E13: 0 | F13: 0 | G13: 13359.23 | H13: 1637.95 | I13: =G13+H13 -> 14997.18 | J13: =D13-I13 -> 12764.71 | K13: S/L | L13: 40.00
B14: Grand Total | D14: =SUM(D10:D13) -> 265816.45 | E14: =SUM(E10:E13) -> 0 | F14: =SUM(F10:F13) -> 0 | G14: =SUM(G10:G13) -> 74443.16 | H14: =SUM(H10:H13) -> 6910.35 | I14: =SUM(I10:I13) -> 81353.51 | J14: =SUM(J10:J13) -> 184462.94
A16: After Cost Segregation Correction
A17: Asset | B17: Property Description | C17: Date In Service | D17: Cost | E17: Sec 179 Exp | F17: Bonus Amt | G17: Tax Prior Depreciation | H17: Tax Current Depreciation | I17: End Depreciation | J17: Net Book Value | K17: Method | L17: Period
A18: 1 | B18: 19 - Building - 754 "Menowitz" - 5 year | C18: 9/15/21 | D18: 157.52 | E18: 0 | F18: 157.52 | G18: 157.52 | H18: 0 | I18: =G18+H18 -> 157.52 | J18: =D18-I18 -> 0 | K18: 200DB | L18: 5.0
A19: 2 | B19: 19 - Building - 754 "Menowitz" - 30 year | C19: 9/15/21 | D19: 593.3 | E19: 0 | F19: 0 | G19: 45.33 | H19: 19.78 | I19: =G19+H19 -> 65.11 | J19: =D19-I19 -> 528.19 | K19: S/L | L19: 30.00
A20: 3 | B20: 3 - Building - 5 year | C20: 5/31/17 | D20: 46872.91 | E20: 0 | F20: 0 | G20: 46872.91 | H20: 0 | I20: =G20+H20 -> 46872.91 | J20: =D20-I20 -> 0 | K20: 200DB | L20: 5.0
A21: 4 | B21: 3 - Building - 30 year | C21: 5/31/17 | D21: 176549.89 | E21: 0 | F21: 0 | G21: 38988.12 | H21: 5885 | I21: =G21+H21 -> 44873.12 | J21: =D21-I21 -> 131676.77 | K21: S/L | L21: 30.00
A22: 5 | B22: 4 - Personal Property - 5 year | C22: 5/31/17 | D22: 2912.15 | E22: 0 | F22: 0 | G22: 2912.15 | H22: 0 | I22: =G22+H22 -> 2912.15 | J22: =D22-I22 -> 0 | K22: 200DB | L22: 5.0
A23: 6 | B23: 4 - Personal Property - 30 year | C23: 5/31/17 | D23: 10968.79 | E23: 0 | F23: 0 | G23: 2422.3 | H23: 365.63 | I23: =G23+H23 -> 2787.93 | J23: =D23-I23 -> 8180.86 | K23: S/L | L23: 30.00
A24: 7 | B24: 2 - Land Improvements - 5 year | C24: 5/31/17 | D24: 5824.29 | E24: 0 | F24: 0 | G24: 5824.29 | H24: 0 | I24: =G24+H24 -> 5824.29 | J24: =D24-I24 -> 0 | K24: 200DB | L24: 5.0
A25: 8 | B25: 2 - Land Improvements - 30 year | C25: 5/31/17 | D25: 21937.6 | E25: 0 | F25: 0 | G25: 4844.53 | H25: 731.25 | I25: =G25+H25 -> 5575.78 | J25: =D25-I25 -> 16361.82 | K25: S/L | L25: 30.00
B26: Grand Total | D26: =SUM(D18:D25) -> 265816.45 | E26: =SUM(E18:E25) -> 0 | F26: =SUM(F18:F25) -> 157.52 | G26: =SUM(G18:G25) -> 102067.15 | H26: =SUM(H18:H25) -> 7001.66 | I26: =SUM(I18:I25) -> 109068.81 | J26: =SUM(J18:J25) -> 156747.64
B28: Section 481(a) Adjustment — Regular Tax
B29: Depreciation reported previously | D29: =I14 -> 81353.51
B30: Cost Segregation Corrected Depreciation | D30: =I26 -> 109068.81
B31: Section 481(a) Adjustment — Regular Tax | D31: =D29-D30 -> -27715.3
A33: CALCULATION OF §481(a) ADJUSTMENT — AMT
A34: As Previously Filed — AMT
A35: Asset | B35: Property Description | C35: Date In Service | D35: Cost | E35: Sec 179 Exp | F35: Bonus Amt | G35: AMT Prior Depreciation | H35: AMT Current Depreciation | I35: End Depreciation | J35: Net Book Value | K35: Method | L35: Period
A36: 1 | B36: 19 - Building - 754 "Menowitz" | C36: 9/15/21 | D36: 750.82 | E36: 0 | F36: 0 | G36: 45.46 | H36: 18.74 | I36: =G36+H36 -> 64.2 | J36: =D36-I36 -> 686.62 | K36: S/L | L36: 40.00
A37: 2 | B37: 3 - Building | C37: 5/31/17 | D37: 223422.8 | E37: 0 | F37: 0 | G37: 48082.9 | H37: 5253.66 | I37: =G37+H37 -> 53336.56 | J37: =D37-I37 -> 170086.24 | K37: S/L | L37: 40.00
A38: 3 | B38: 4 - Personal Property | C38: 5/31/17 | D38: 13880.94 | E38: 0 | F38: 0 | G38: 12955.57 | H38: 0 | I38: =G38+H38 -> 12955.57 | J38: =D38-I38 -> 925.37 | K38: S/L | L38: 40.00
A39: 4 | B39: 2 - Land Improvements | C39: 5/31/17 | D39: 27761.89 | E39: 0 | F39: 0 | G39: 13359.23 | H39: 1637.95 | I39: =G39+H39 -> 14997.18 | J39: =D39-I39 -> 12764.71 | K39: S/L | L39: 40.00
B40: Grand Total | D40: =SUM(D36:D39) -> 265816.45 | E40: =SUM(E36:E39) -> 0 | F40: =SUM(F36:F39) -> 0 | G40: =SUM(G36:G39) -> 74443.16 | H40: =SUM(H36:H39) -> 6910.35 | I40: =SUM(I36:I39) -> 81353.51 | J40: =SUM(J36:J39) -> 184462.94
A42: After Cost Segregation Correction — AMT
A43: Asset | B43: Property Description | C43: Date In Service | D43: Cost | E43: Sec 179 Exp | F43: Bonus Amt | G43: AMT Prior Depreciation | H43: AMT Current Depreciation | I43: End Depreciation | J43: Net Book Value | K43: Method | L43: Period
A44: 1 | B44: 19 - Building - 754 "Menowitz" - 5 year | C44: 9/15/21 | D44: 157.52 | E44: 0 | F44: 157.52 | G44: 157.52 | H44: 0 | I44: =G44+H44 -> 157.52 | J44: =D44-I44 -> 0 | K44: 200DB | L44: 5.0
A45: 2 | B45: 19 - Building - 754 "Menowitz" - 30 year | C45: 9/15/21 | D45: 593.3 | E45: 0 | F45: 0 | G45: 45.33 | H45: 19.78 | I45: =G45+H45 -> 65.11 | J45: =D45-I45 -> 528.19 | K45: S/L | L45: 30.00
A46: 3 | B46: 3 - Building - 5 year | C46: 5/31/17 | D46: 46872.91 | E46: 0 | F46: 0 | G46: 46872.91 | H46: 0 | I46: =G46+H46 -> 46872.91 | J46: =D46-I46 -> 0 | K46: 200DB | L46: 5.0
A47: 4 | B47: 3 - Building - 30 year | C47: 5/31/17 | D47: 176549.89 | E47: 0 | F47: 0 | G47: 38988.12 | H47: 5885 | I47: =G47+H47 -> 44873.12 | J47: =D47-I47 -> 131676.77 | K47: S/L | L47: 30.00
A48: 5 | B48: 4 - Personal Property - 5 year | C48: 5/31/17 | D48: 2912.15 | E48: 0 | F48: 0 | G48: 2912.15 | H48: 0 | I48: =G48+H48 -> 2912.15 | J48: =D48-I48 -> 0 | K48: 200DB | L48: 5.0
A49: 6 | B49: 4 - Personal Property - 30 year | C49: 5/31/17 | D49: 10968.79 | E49: 0 | F49: 0 | G49: 2422.3 | H49: 365.63 | I49: =G49+H49 -> 2787.93 | J49: =D49-I49 -> 8180.86 | K49: S/L | L49: 30.00
A50: 7 | B50: 2 - Land Improvements - 5 year | C50: 5/31/17 | D50: 5824.29 | E50: 0 | F50: 0 | G50: 5824.29 | H50: 0 | I50: =G50+H50 -> 5824.29 | J50: =D50-I50 -> 0 | K50: 200DB | L50: 5.0
A51: 8 | B51: 2 - Land Improvements - 30 year | C51: 5/31/17 | D51: 21937.6 | E51: 0 | F51: 0 | G51: 4844.53 | H51: 731.25 | I51: =G51+H51 -> 5575.78 | J51: =D51-I51 -> 16361.82 | K51: S/L | L51: 30.00
B52: Grand Total | D52: =SUM(D44:D51) -> 265816.45 | E52: =SUM(E44:E51) -> 0 | F52: =SUM(F44:F51) -> 157.52 | G52: =SUM(G44:G51) -> 102067.15 | H52: =SUM(H44:H51) -> 7001.66 | I52: =SUM(I44:I51) -> 109068.81 | J52: =SUM(J44:J51) -> 156747.64
B54: Section 481(a) Adjustment — AMT
B55: Depreciation reported previously | D55: =I40 -> 81353.51
B56: Cost Segregation Corrected Depreciation | D56: =I52 -> 109068.81
B57: Section 481(a) Adjustment — AMT | D57: =D55-D56 -> -27715.3
A59: COST SEGREGATION STUDY — COST SUMMARY
B60: Total Building Cost | D60: =D98 -> 265816.45
B61: Building Components: 5 Year | D61: =F98 -> 55766.87
B62: % of Building Cost | D62: =F99 -> 0.20979465
B63: Building Structure: 30 Year | D63: =H98 -> 210049.58
B64: % of Building Cost | D64: =H99 -> 0.79020535
A66: COST SEGREGATION STUDY — COST DETAIL
B67: Property Category | D67: Cost | F67: 5 Year | H67: 30 Year
B68: Building Components
B69: Cabinets / Millwork | D69: =SUM(F69:H69) -> 13932.37 | F69: 13932.37
B70: Moldings | D70: =SUM(F70:H70) -> 4762.13 | F70: 4762.13
B71: Flooring - Vinyl Plank | D71: =SUM(F71:H71) -> 21399.52 | F71: 21399.52
B72: Window Treatments | D72: =SUM(F72:H72) -> 1967.77 | F72: 1967.77
B73: Building Signage | D73: =SUM(F73:H73) -> 127.35 | F73: 127.35
B74: Specialty Electrical - Appliances | D74: =SUM(F74:H74) -> 2548.79 | F74: 2548.79
B75: Communication / Data | D75: =SUM(F75:H75) -> 1855.1 | F75: 1855.1
B76: Specialty Plumbing - Kitchen Sinks | D76: =SUM(F76:H76) -> 4626.46 | F76: 4626.46
B77: Security / Exterior Lighting | D77: =SUM(F77:H77) -> 480.75 | F77: 480.75
B78: Access Control | D78: =SUM(F78:H78) -> 75.53 | F78: 75.53
B79: Appliances | D79: =SUM(F79:H79) -> 3991.1 | F79: 3991.1
B80: Building Structure
B81: Roofing Systems | D81: =SUM(F81:H81) -> 8726.14 | H81: 8726.14
B82: Foundations | D82: =SUM(F82:H82) -> 14310.97 | H82: 14310.97
B83: HVAC | D83: =SUM(F83:H83) -> 20721.85 | H83: 20721.85
B84: Electrical | D84: =SUM(F84:H84) -> 20019.46 | H84: 20019.46
B85: Plumbing | D85: =SUM(F85:H85) -> 18013.39 | H85: 18013.39
B86: Fire Protection & Alarm | D86: =SUM(F86:H86) -> 1255.28 | H86: 1255.28
B87: Exterior Façade / Building Skin | D87: =SUM(F87:H87) -> 28034.85 | H87: 28034.85
B88: Doors & Frames | D88: =SUM(F88:H88) -> 9209.33 | H88: 9209.33
B89: Windows | D89: =SUM(F89:H89) -> 8673.12 | H89: 8673.12
B90: Ceiling Systems | D90: =SUM(F90:H90) -> 9530.52 | H90: 9530.52
B91: Interior Framing / Partitions | D91: =SUM(F91:H91) -> 20615.67 | H91: 20615.67
B92: Painting | D92: =SUM(F92:H92) -> 8186.44 | H92: 8186.44
... B97: Cabinets / Millwork - Restrooms | D97: =SUM(F97:H97) -> 901.51 | H97: 901.51
B98: Total Building Cost | D98: =SUM(D69:D97) -> 265816.45 | F98: =SUM(F69:F79) -> 55766.87 | H98: =SUM(H81:H97) -> 210049.58
B99: % of Building Cost | F99: =F98/D98 -> 0.20979465 | H99: =H98/D98 -> 0.79020535
A101: ASSET ALLOCATION
B102: Asset | D102: Cost | F102: 5 Year | H102: 30 Year
B103: Asset # 19 - Building - 754 "Menowitz" | D103: =F103+H103 -> 750.82 | F103: 157.52 | H103: 593.3
B104: Asset # 3 - Building | D104: =F104+H104 -> 223422.8 | F104: 46872.91 | H104: 176549.89
B105: Asset # 4 - Personal Property | D105: =F105+H105 -> 13880.94 | F105: 2912.15 | H105: 10968.79
B106: Asset # 2 - Land Improvements | D106: =F106+H106 -> 27761.89 | F106: 5824.29 | H106: 21937.6
B107: Total Allocation | D107: =SUM(D103:D106) -> 265816.45 | F107: =SUM(F103:F106) -> 55766.87 | H107: =SUM(H103:H106) -> 210049.58
B108: Check: Allocation vs. Cost Detail (should be zero) | D108: =D107-D98 -> 0

Sheet Building 8
A1: Silver Springs Housing, LP
A2: Silver Spring Terrace Apartments — 950 20th St NE, Hickory, NC 28601
A3: EIN: 82-0773652 · FYE: December 31, 2024 · Year of Change: 1/1/2024
A4: Building 8 — Attachment to Form 3115 (DCN #7, Rev. Proc. 2024-23 §6.01)
A5: Source: CSSI Report #107752-39, "Silver Springs Housing LP_#107752-39_3115_Combined R1.pdf"
A7: CALCULATION OF §481(a) ADJUSTMENT — REGULAR TAX
A8: As Previously Filed
A9: Asset | B9: Property Description | C9: Date In Service | D9: Cost | E9: Sec 179 Exp | F9: Bonus Amt | G9: Tax Prior Depreciation | H9: Tax Current Depreciation | I9: End Depreciation | J9: Net Book Value | K9: Method | L9: Period
A10: 1 | B10: 19 - Building - 754 "Menowitz" | C10: 9/15/21 | D10: 479.53 | E10: 0 | F10: 0 | G10: 29.03 | H10: 11.97 | I10: =G10+H10 -> 41 | J10: =D10-I10 -> 438.53 | K10: S/L | L10: 40.00
A11: 2 | B11: 3 - Building | C11: 5/31/17 | D11: 142694.3 | E11: 0 | F11: 0 | G11: 30709.29 | H11: 3355.37 | I11: =G11+H11 -> 34064.66 | J11: =D11-I11 -> 108629.64 | K11: S/L | L11: 40.00
A12: 3 | B12: 4 - Personal Property | C12: 5/31/17 | D12: 8865.4 | E12: 0 | F12: 0 | G12: 8274.39 | H12: 0 | I12: =G12+H12 -> 8274.39 | J12: =D12-I12 -> 591.01 | K12: S/L | L12: 40.00
A13: 4 | B13: 2 - Land Improvements | C13: 5/31/17 | D13: 17730.79 | E13: 0 | F13: 0 | G13: 8532.2 | H13: 1046.12 | I13: =G13+H13 -> 9578.32 | J13: =D13-I13 -> 8152.47 | K13: S/L | L13: 40.00
B14: Grand Total | D14: =SUM(D10:D13) -> 169770.02 | E14: =SUM(E10:E13) -> 0 | F14: =SUM(F10:F13) -> 0 | G14: =SUM(G10:G13) -> 47544.91 | H14: =SUM(H10:H13) -> 4413.46 | I14: =SUM(I10:I13) -> 51958.37 | J14: =SUM(J10:J13) -> 117811.65
A16: After Cost Segregation Correction
A17: Asset | B17: Property Description | C17: Date In Service | D17: Cost | E17: Sec 179 Exp | F17: Bonus Amt | G17: Tax Prior Depreciation | H17: Tax Current Depreciation | I17: End Depreciation | J17: Net Book Value | K17: Method | L17: Period
A18: 1 | B18: 19 - Building - 754 "Menowitz" - 5 year | C18: 9/15/21 | D18: 89.94 | E18: 0 | F18: 89.94 | G18: 89.94 | H18: 0 | I18: =G18+H18 -> 89.94 | J18: =D18-I18 -> 0 | K18: 200DB | L18: 5.0
A19: 2 | B19: 19 - Building - 754 "Menowitz" - 30 year | C19: 9/15/21 | D19: 389.59 | E19: 0 | F19: 0 | G19: 29.77 | H19: 12.99 | I19: =G19+H19 -> 42.76 | J19: =D19-I19 -> 346.83 | K19: S/L | L19: 30.00
A20: 3 | B20: 3 - Building - 5 year | C20: 5/31/17 | D20: 26763.65 | E20: 0 | F20: 0 | G20: 26763.65 | H20: 0 | I20: =G20+H20 -> 26763.65 | J20: =D20-I20 -> 0 | K20: 200DB | L20: 5.0
A21: 4 | B21: 3 - Building - 30 year | C21: 5/31/17 | D21: 115930.65 | E21: 0 | F21: 0 | G21: 25601.32 | H21: 3864.35 | I21: =G21+H21 -> 29465.67 | J21: =D21-I21 -> 86464.98 | K21: S/L | L21: 30.00
A22: 5 | B22: 4 - Personal Property - 5 year | C22: 5/31/17 | D22: 1662.79 | E22: 0 | F22: 0 | G22: 1662.79 | H22: 0 | I22: =G22+H22 -> 1662.79 | J22: =D22-I22 -> 0 | K22: 200DB | L22: 5.0
A23: 6 | B23: 4 - Personal Property - 30 year | C23: 5/31/17 | D23: 7202.61 | E23: 0 | F23: 0 | G23: 1590.59 | H23: 240.09 | I23: =G23+H23 -> 1830.68 | J23: =D23-I23 -> 5371.93 | K23: S/L | L23: 30.00
A24: 7 | B24: 2 - Land Improvements - 5 year | C24: 5/31/17 | D24: 3325.57 | E24: 0 | F24: 0 | G24: 3325.57 | H24: 0 | I24: =G24+H24 -> 3325.57 | J24: =D24-I24 -> 0 | K24: 200DB | L24: 5.0
A25: 8 | B25: 2 - Land Improvements - 30 year | C25: 5/31/17 | D25: 14405.22 | E25: 0 | F25: 0 | G25: 3181.13 | H25: 480.17 | I25: =G25+H25 -> 3661.3 | J25: =D25-I25 -> 10743.92 | K25: S/L | L25: 30.00
B26: Grand Total | D26: =SUM(D18:D25) -> 169770.02 | E26: =SUM(E18:E25) -> 0 | F26: =SUM(F18:F25) -> 89.94 | G26: =SUM(G18:G25) -> 62244.76 | H26: =SUM(H18:H25) -> 4597.6 | I26: =SUM(I18:I25) -> 66842.36 | J26: =SUM(J18:J25) -> 102927.66
B28: Section 481(a) Adjustment — Regular Tax
B29: Depreciation reported previously | D29: =I14 -> 51958.37
B30: Cost Segregation Corrected Depreciation | D30: =I26 -> 66842.36
B31: Section 481(a) Adjustment — Regular Tax | D31: =D29-D30 -> -14883.99
A33: CALCULATION OF §481(a) ADJUSTMENT — AMT
A34: As Previously Filed — AMT
A35: Asset | B35: Property Description | C35: Date In Service | D35: Cost | E35: Sec 179 Exp | F35: Bonus Amt | G35: AMT Prior Depreciation | H35: AMT Current Depreciation | I35: End Depreciation | J35: Net Book Value | K35: Method | L35: Period
A36: 1 | B36: 19 - Building - 754 "Menowitz" | C36: 9/15/21 | D36: 479.53 | E36: 0 | F36: 0 | G36: 29.03 | H36: 11.97 | I36: =G36+H36 -> 41 | J36: =D36-I36 -> 438.53 | K36: S/L | L36: 40.00
A37: 2 | B37: 3 - Building | C37: 5/31/17 | D37: 142694.3 | E37: 0 | F37: 0 | G37: 30709.29 | H37: 3355.37 | I37: =G37+H37 -> 34064.66 | J37: =D37-I37 -> 108629.64 | K37: S/L | L37: 40.00
A38: 3 | B38: 4 - Personal Property | C38: 5/31/17 | D38: 8865.4 | E38: 0 | F38: 0 | G38: 8274.39 | H38: 0 | I38: =G38+H38 -> 8274.39 | J38: =D38-I38 -> 591.01 | K38: S/L | L38: 40.00
A39: 4 | B39: 2 - Land Improvements | C39: 5/31/17 | D39: 17730.79 | E39: 0 | F39: 0 | G39: 8532.2 | H39: 1046.12 | I39: =G39+H39 -> 9578.32 | J39: =D39-I39 -> 8152.47 | K39: S/L | L39: 40.00
B40: Grand Total | D40: =SUM(D36:D39) -> 169770.02 | E40: =SUM(E36:E39) -> 0 | F40: =SUM(F36:F39) -> 0 | G40: =SUM(G36:G39) -> 47544.91 | H40: =SUM(H36:H39) -> 4413.46 | I40: =SUM(I36:I39) -> 51958.37 | J40: =SUM(J36:J39) -> 117811.65
A42: After Cost Segregation Correction — AMT
A43: Asset | B43: Property Description | C43: Date In Service | D43: Cost | E43: Sec 179 Exp | F43: Bonus Amt | G43: AMT Prior Depreciation | H43: AMT Current Depreciation | I43: End Depreciation | J43: Net Book Value | K43: Method | L43: Period
A44: 1 | B44: 19 - Building - 754 "Menowitz" - 5 year | C44: 9/15/21 | D44: 89.94 | E44: 0 | F44: 89.94 | G44: 89.94 | H44: 0 | I44: =G44+H44 -> 89.94 | J44: =D44-I44 -> 0 | K44: 200DB | L44: 5.0
A45: 2 | B45: 19 - Building - 754 "Menowitz" - 30 year | C45: 9/15/21 | D45: 389.59 | E45: 0 | F45: 0 | G45: 29.77 | H45: 12.99 | I45: =G45+H45 -> 42.76 | J45: =D45-I45 -> 346.83 | K45: S/L | L45: 30.00
A46: 3 | B46: 3 - Building - 5 year | C46: 5/31/17 | D46: 26763.65 | E46: 0 | F46: 0 | G46: 26763.65 | H46: 0 | I46: =G46+H46 -> 26763.65 | J46: =D46-I46 -> 0 | K46: 200DB | L46: 5.0
A47: 4 | B47: 3 - Building - 30 year | C47: 5/31/17 | D47: 115930.65 | E47: 0 | F47: 0 | G47: 25601.32 | H47: 3864.35 | I47: =G47+H47 -> 29465.67 | J47: =D47-I47 -> 86464.98 | K47: S/L | L47: 30.00
A48: 5 | B48: 4 - Personal Property - 5 year | C48: 5/31/17 | D48: 1662.79 | E48: 0 | F48: 0 | G48: 1662.79 | H48: 0 | I48: =G48+H48 -> 1662.79 | J48: =D48-I48 -> 0 | K48: 200DB | L48: 5.0
A49: 6 | B49: 4 - Personal Property - 30 year | C49: 5/31/17 | D49: 7202.61 | E49: 0 | F49: 0 | G49: 1590.59 | H49: 240.09 | I49: =G49+H49 -> 1830.68 | J49: =D49-I49 -> 5371.93 | K49: S/L | L49: 30.00
A50: 7 | B50: 2 - Land Improvements - 5 year | C50: 5/31/17 | D50: 3325.57 | E50: 0 | F50: 0 | G50: 3325.57 | H50: 0 | I50: =G50+H50 -> 3325.57 | J50: =D50-I50 -> 0 | K50: 200DB | L50: 5.0
A51: 8 | B51: 2 - Land Improvements - 30 year | C51: 5/31/17 | D51: 14405.22 | E51: 0 | F51: 0 | G51: 3181.13 | H51: 480.17 | I51: =G51+H51 -> 3661.3 | J51: =D51-I51 -> 10743.92 | K51: S/L | L51: 30.00
B52: Grand Total | D52: =SUM(D44:D51) -> 169770.02 | E52: =SUM(E44:E51) -> 0 | F52: =SUM(F44:F51) -> 89.94 | G52: =SUM(G44:G51) -> 62244.76 | H52: =SUM(H44:H51) -> 4597.6 | I52: =SUM(I44:I51) -> 66842.36 | J52: =SUM(J44:J51) -> 102927.66
B54: Section 481(a) Adjustment — AMT
B55: Depreciation reported previously | D55: =I40 -> 51958.37
B56: Cost Segregation Corrected Depreciation | D56: =I52 -> 66842.36
B57: Section 481(a) Adjustment — AMT | D57: =D55-D56 -> -14883.99
A59: COST SEGREGATION STUDY — COST SUMMARY
B60: Total Building Cost | D60: =D98 -> 169770.02
B61: Building Components: 5 Year | D61: =F98 -> 31841.95
B62: % of Building Cost | D62: =F99 -> 0.18755932
B63: Building Structure: 30 Year | D63: =H98 -> 137928.07
B64: % of Building Cost | D64: =H99 -> 0.81244068
A66: COST SEGREGATION STUDY — COST DETAIL
B67: Property Category | D67: Cost | F67: 5 Year | H67: 30 Year
B68: Building Components
B69: Cabinets / Millwork | D69: =SUM(F69:H69) -> 7800.47 | F69: 7800.47
B70: Moldings | D70: =SUM(F70:H70) -> 3748.91 | F70: 3748.91
B71: Flooring - Vinyl Plank | D71: =SUM(F71:H71) -> 12139.37 | F71: 12139.37
B72: Window Treatments | D72: =SUM(F72:H72) -> 1142.58 | F72: 1142.58
B73: Building Signage | D73: =SUM(F73:H73) -> 85.24 | F73: 85.24
B74: Specialty Electrical - Appliances | D74: =SUM(F74:H74) -> 1274.42 | F74: 1274.42
B75: Communication / Data | D75: =SUM(F75:H75) -> 1052.34 | F75: 1052.34
B76: Specialty Plumbing - Kitchen Sinks | D76: =SUM(F76:H76) -> 2313.24 | F76: 2313.24
B77: Security / Exterior Lighting | D77: =SUM(F77:H77) -> 252.07 | F77: 252.07
B78: Access Control | D78: =SUM(F78:H78) -> 37.76 | F78: 37.76
B79: Appliances | D79: =SUM(F79:H79) -> 1995.55 | F79: 1995.55
B80: Building Structure
B81: Roofing Systems | D81: =SUM(F81:H81) -> 5090 | H81: 5090
B82: Foundations | D82: =SUM(F82:H82) -> 8538.11 | H82: 8538.11
B83: HVAC | D83: =SUM(F83:H83) -> 11754.94 | H83: 11754.94
B84: Electrical | D84: =SUM(F84:H84) -> 11527.95 | H84: 11527.95
B85: Plumbing | D85: =SUM(F85:H85) -> 10218.5 | H85: 10218.5
B86: Fire Protection & Alarm | D86: =SUM(F86:H86) -> 775.83 | H86: 775.83
B87: Exterior Façade / Building Skin | D87: =SUM(F87:H87) -> 22829.89 | H87: 22829.89
B88: Doors & Frames | D88: =SUM(F88:H88) -> 5886.42 | H88: 5886.42
B89: Windows | D89: =SUM(F89:H89) -> 5036.01 | H89: 5036.01
B90: Ceiling Systems | D90: =SUM(F90:H90) -> 5406.4 | H90: 5406.4
B91: Interior Framing / Partitions | D91: =SUM(F91:H91) -> 16464.28 | H91: 16464.28
B92: Painting | D92: =SUM(F92:H92) -> 5938.8 | H92: 5938.8
... B97: Cabinets / Millwork - Restrooms | D97: =SUM(F97:H97) -> 901.51 | H97: 901.51
B98: Total Building Cost | D98: =SUM(D69:D97) -> 169770.02 | F98: =SUM(F69:F79) -> 31841.95 | H98: =SUM(H81:H97) -> 137928.07
B99: % of Building Cost | F99: =F98/D98 -> 0.18755932 | H99: =H98/D98 -> 0.81244068
A101: ASSET ALLOCATION
B102: Asset | D102: Cost | F102: 5 Year | H102: 30 Year
B103: Asset # 19 - Building - 754 "Menowitz" | D103: =F103+H103 -> 479.53 | F103: 89.94 | H103: 389.59
B104: Asset # 3 - Building | D104: =F104+H104 -> 142694.3 | F104: 26763.65 | H104: 115930.65
B105: Asset # 4 - Personal Property | D105: =F105+H105 -> 8865.4 | F105: 1662.79 | H105: 7202.61
B106: Asset # 2 - Land Improvements | D106: =F106+H106 -> 17730.79 | F106: 3325.57 | H106: 14405.22
B107: Total Allocation | D107: =SUM(D103:D106) -> 169770.02 | F107: =SUM(F103:F106) -> 31841.95 | H107: =SUM(H103:H106) -> 137928.07
B108: Check: Allocation vs. Cost Detail (should be zero) | D108: =D107-D98 -> 0

Sheet Building 9
A1: Silver Springs Housing, LP
A2: Silver Spring Terrace Apartments — 950 20th St NE, Hickory, NC 28601
A3: EIN: 82-0773652 · FYE: December 31, 2024 · Year of Change: 1/1/2024
A4: Building 9 — Attachment to Form 3115 (DCN #7, Rev. Proc. 2024-23 §6.01)
A5: Source: CSSI Report #107752-39, "Silver Springs Housing LP_#107752-39_3115_Combined R1.pdf"
A7: CALCULATION OF §481(a) ADJUSTMENT — REGULAR TAX
A8: As Previously Filed
A9: Asset | B9: Property Description | C9: Date In Service | D9: Cost | E9: Sec 179 Exp | F9: Bonus Amt | G9: Tax Prior Depreciation | H9: Tax Current Depreciation | I9: End Depreciation | J9: Net Book Value | K9: Method | L9: Period
A10: 1 | B10: 19 - Building - 754 "Menowitz" | C10: 9/15/21 | D10: 750.82 | E10: 0 | F10: 0 | G10: 45.46 | H10: 18.74 | I10: =G10+H10 -> 64.2 | J10: =D10-I10 -> 686.62 | K10: S/L | L10: 40.00
A11: 2 | B11: 3 - Building | C11: 5/31/17 | D11: 223422.8 | E11: 0 | F11: 0 | G11: 48082.9 | H11: 5253.66 | I11: =G11+H11 -> 53336.56 | J11: =D11-I11 -> 170086.24 | K11: S/L | L11: 40.00
A12: 3 | B12: 4 - Personal Property | C12: 5/31/17 | D12: 13880.94 | E12: 0 | F12: 0 | G12: 12955.57 | H12: 0 | I12: =G12+H12 -> 12955.57 | J12: =D12-I12 -> 925.37 | K12: S/L | L12: 40.00
A13: 4 | B13: 2 - Land Improvements | C13: 5/31/17 | D13: 27761.89 | E13: 0 | F13: 0 | G13: 13359.23 | H13: 1637.95 | I13: =G13+H13 -> 14997.18 | J13: =D13-I13 -> 12764.71 | K13: S/L | L13: 40.00
B14: Grand Total | D14: =SUM(D10:D13) -> 265816.45 | E14: =SUM(E10:E13) -> 0 | F14: =SUM(F10:F13) -> 0 | G14: =SUM(G10:G13) -> 74443.16 | H14: =SUM(H10:H13) -> 6910.35 | I14: =SUM(I10:I13) -> 81353.51 | J14: =SUM(J10:J13) -> 184462.94
A16: After Cost Segregation Correction
A17: Asset | B17: Property Description | C17: Date In Service | D17: Cost | E17: Sec 179 Exp | F17: Bonus Amt | G17: Tax Prior Depreciation | H17: Tax Current Depreciation | I17: End Depreciation | J17: Net Book Value | K17: Method | L17: Period
A18: 1 | B18: 19 - Building - 754 "Menowitz" - 5 year | C18: 9/15/21 | D18: 157.52 | E18: 0 | F18: 157.52 | G18: 157.52 | H18: 0 | I18: =G18+H18 -> 157.52 | J18: =D18-I18 -> 0 | K18: 200DB | L18: 5.0
A19: 2 | B19: 19 - Building - 754 "Menowitz" - 30 year | C19: 9/15/21 | D19: 593.3 | E19: 0 | F19: 0 | G19: 45.33 | H19: 19.78 | I19: =G19+H19 -> 65.11 | J19: =D19-I19 -> 528.19 | K19: S/L | L19: 30.00
A20: 3 | B20: 3 - Building - 5 year | C20: 5/31/17 | D20: 46872.91 | E20: 0 | F20: 0 | G20: 46872.91 | H20: 0 | I20: =G20+H20 -> 46872.91 | J20: =D20-I20 -> 0 | K20: 200DB | L20: 5.0
A21: 4 | B21: 3 - Building - 30 year | C21: 5/31/17 | D21: 176549.89 | E21: 0 | F21: 0 | G21: 38988.12 | H21: 5885 | I21: =G21+H21 -> 44873.12 | J21: =D21-I21 -> 131676.77 | K21: S/L | L21: 30.00
A22: 5 | B22: 4 - Personal Property - 5 year | C22: 5/31/17 | D22: 2912.15 | E22: 0 | F22: 0 | G22: 2912.15 | H22: 0 | I22: =G22+H22 -> 2912.15 | J22: =D22-I22 -> 0 | K22: 200DB | L22: 5.0
A23: 6 | B23: 4 - Personal Property - 30 year | C23: 5/31/17 | D23: 10968.79 | E23: 0 | F23: 0 | G23: 2422.3 | H23: 365.63 | I23: =G23+H23 -> 2787.93 | J23: =D23-I23 -> 8180.86 | K23: S/L | L23: 30.00
A24: 7 | B24: 2 - Land Improvements - 5 year | C24: 5/31/17 | D24: 5824.29 | E24: 0 | F24: 0 | G24: 5824.29 | H24: 0 | I24: =G24+H24 -> 5824.29 | J24: =D24-I24 -> 0 | K24: 200DB | L24: 5.0
A25: 8 | B25: 2 - Land Improvements - 30 year | C25: 5/31/17 | D25: 21937.6 | E25: 0 | F25: 0 | G25: 4844.53 | H25: 731.25 | I25: =G25+H25 -> 5575.78 | J25: =D25-I25 -> 16361.82 | K25: S/L | L25: 30.00
B26: Grand Total | D26: =SUM(D18:D25) -> 265816.45 | E26: =SUM(E18:E25) -> 0 | F26: =SUM(F18:F25) -> 157.52 | G26: =SUM(G18:G25) -> 102067.15 | H26: =SUM(H18:H25) -> 7001.66 | I26: =SUM(I18:I25) -> 109068.81 | J26: =SUM(J18:J25) -> 156747.64
B28: Section 481(a) Adjustment — Regular Tax
B29: Depreciation reported previously | D29: =I14 -> 81353.51
B30: Cost Segregation Corrected Depreciation | D30: =I26 -> 109068.81
B31: Section 481(a) Adjustment — Regular Tax | D31: =D29-D30 -> -27715.3
A33: CALCULATION OF §481(a) ADJUSTMENT — AMT
A34: As Previously Filed — AMT
A35: Asset | B35: Property Description | C35: Date In Service | D35: Cost | E35: Sec 179 Exp | F35: Bonus Amt | G35: AMT Prior Depreciation | H35: AMT Current Depreciation | I35: End Depreciation | J35: Net Book Value | K35: Method | L35: Period
A36: 1 | B36: 19 - Building - 754 "Menowitz" | C36: 9/15/21 | D36: 750.82 | E36: 0 | F36: 0 | G36: 45.46 | H36: 18.74 | I36: =G36+H36 -> 64.2 | J36: =D36-I36 -> 686.62 | K36: S/L | L36: 40.00
A37: 2 | B37: 3 - Building | C37: 5/31/17 | D37: 223422.8 | E37: 0 | F37: 0 | G37: 48082.9 | H37: 5253.66 | I37: =G37+H37 -> 53336.56 | J37: =D37-I37 -> 170086.24 | K37: S/L | L37: 40.00
A38: 3 | B38: 4 - Personal Property | C38: 5/31/17 | D38: 13880.94 | E38: 0 | F38: 0 | G38: 12955.57 | H38: 0 | I38: =G38+H38 -> 12955.57 | J38: =D38-I38 -> 925.37 | K38: S/L | L38: 40.00
A39: 4 | B39: 2 - Land Improvements | C39: 5/31/17 | D39: 27761.89 | E39: 0 | F39: 0 | G39: 13359.23 | H39: 1637.95 | I39: =G39+H39 -> 14997.18 | J39: =D39-I39 -> 12764.71 | K39: S/L | L39: 40.00
B40: Grand Total | D40: =SUM(D36:D39) -> 265816.45 | E40: =SUM(E36:E39) -> 0 | F40: =SUM(F36:F39) -> 0 | G40: =SUM(G36:G39) -> 74443.16 | H40: =SUM(H36:H39) -> 6910.35 | I40: =SUM(I36:I39) -> 81353.51 | J40: =SUM(J36:J39) -> 184462.94
A42: After Cost Segregation Correction — AMT
A43: Asset | B43: Property Description | C43: Date In Service | D43: Cost | E43: Sec 179 Exp | F43: Bonus Amt | G43: AMT Prior Depreciation | H43: AMT Current Depreciation | I43: End Depreciation | J43: Net Book Value | K43: Method | L43: Period
A44: 1 | B44: 19 - Building - 754 "Menowitz" - 5 year | C44: 9/15/21 | D44: 157.52 | E44: 0 | F44: 157.52 | G44: 157.52 | H44: 0 | I44: =G44+H44 -> 157.52 | J44: =D44-I44 -> 0 | K44: 200DB | L44: 5.0
A45: 2 | B45: 19 - Building - 754 "Menowitz" - 30 year | C45: 9/15/21 | D45: 593.3 | E45: 0 | F45: 0 | G45: 45.33 | H45: 19.78 | I45: =G45+H45 -> 65.11 | J45: =D45-I45 -> 528.19 | K45: S/L | L45: 30.00
A46: 3 | B46: 3 - Building - 5 year | C46: 5/31/17 | D46: 46872.91 | E46: 0 | F46: 0 | G46: 46872.91 | H46: 0 | I46: =G46+H46 -> 46872.91 | J46: =D46-I46 -> 0 | K46: 200DB | L46: 5.0
A47: 4 | B47: 3 - Building - 30 year | C47: 5/31/17 | D47: 176549.89 | E47: 0 | F47: 0 | G47: 38988.12 | H47: 5885 | I47: =G47+H47 -> 44873.12 | J47: =D47-I47 -> 131676.77 | K47: S/L | L47: 30.00
A48: 5 | B48: 4 - Personal Property - 5 year | C48: 5/31/17 | D48: 2912.15 | E48: 0 | F48: 0 | G48: 2912.15 | H48: 0 | I48: =G48+H48 -> 2912.15 | J48: =D48-I48 -> 0 | K48: 200DB | L48: 5.0
A49: 6 | B49: 4 - Personal Property - 30 year | C49: 5/31/17 | D49: 10968.79 | E49: 0 | F49: 0 | G49: 2422.3 | H49: 365.63 | I49: =G49+H49 -> 2787.93 | J49: =D49-I49 -> 8180.86 | K49: S/L | L49: 30.00
A50: 7 | B50: 2 - Land Improvements - 5 year | C50: 5/31/17 | D50: 5824.29 | E50: 0 | F50: 0 | G50: 5824.29 | H50: 0 | I50: =G50+H50 -> 5824.29 | J50: =D50-I50 -> 0 | K50: 200DB | L50: 5.0
A51: 8 | B51: 2 - Land Improvements - 30 year | C51: 5/31/17 | D51: 21937.6 | E51: 0 | F51: 0 | G51: 4844.53 | H51: 731.25 | I51: =G51+H51 -> 5575.78 | J51: =D51-I51 -> 16361.82 | K51: S/L | L51: 30.00
B52: Grand Total | D52: =SUM(D44:D51) -> 265816.45 | E52: =SUM(E44:E51) -> 0 | F52: =SUM(F44:F51) -> 157.52 | G52: =SUM(G44:G51) -> 102067.15 | H52: =SUM(H44:H51) -> 7001.66 | I52: =SUM(I44:I51) -> 109068.81 | J52: =SUM(J44:J51) -> 156747.64
B54: Section 481(a) Adjustment — AMT
B55: Depreciation reported previously | D55: =I40 -> 81353.51
B56: Cost Segregation Corrected Depreciation | D56: =I52 -> 109068.81
B57: Section 481(a) Adjustment — AMT | D57: =D55-D56 -> -27715.3
A59: COST SEGREGATION STUDY — COST SUMMARY
B60: Total Building Cost | D60: =D98 -> 265816.45
B61: Building Components: 5 Year | D61: =F98 -> 55766.87
B62: % of Building Cost | D62: =F99 -> 0.20979465
B63: Building Structure: 30 Year | D63: =H98 -> 210049.58
B64: % of Building Cost | D64: =H99 -> 0.79020535
A66: COST SEGREGATION STUDY — COST DETAIL
B67: Property Category | D67: Cost | F67: 5 Year | H67: 30 Year
B68: Building Components
B69: Cabinets / Millwork | D69: =SUM(F69:H69) -> 13932.37 | F69: 13932.37
B70: Moldings | D70: =SUM(F70:H70) -> 4762.13 | F70: 4762.13
B71: Flooring - Vinyl Plank | D71: =SUM(F71:H71) -> 21399.52 | F71: 21399.52
B72: Window Treatments | D72: =SUM(F72:H72) -> 1967.77 | F72: 1967.77
B73: Building Signage | D73: =SUM(F73:H73) -> 127.35 | F73: 127.35
B74: Specialty Electrical - Appliances | D74: =SUM(F74:H74) -> 2548.79 | F74: 2548.79
B75: Communication / Data | D75: =SUM(F75:H75) -> 1855.1 | F75: 1855.1
B76: Specialty Plumbing - Kitchen Sinks | D76: =SUM(F76:H76) -> 4626.46 | F76: 4626.46
B77: Security / Exterior Lighting | D77: =SUM(F77:H77) -> 480.75 | F77: 480.75
B78: Access Control | D78: =SUM(F78:H78) -> 75.53 | F78: 75.53
B79: Appliances | D79: =SUM(F79:H79) -> 3991.1 | F79: 3991.1
B80: Building Structure
B81: Roofing Systems | D81: =SUM(F81:H81) -> 8726.14 | H81: 8726.14
B82: Foundations | D82: =SUM(F82:H82) -> 14310.97 | H82: 14310.97
B83: HVAC | D83: =SUM(F83:H83) -> 20721.85 | H83: 20721.85
B84: Electrical | D84: =SUM(F84:H84) -> 20019.46 | H84: 20019.46
B85: Plumbing | D85: =SUM(F85:H85) -> 18013.39 | H85: 18013.39
B86: Fire Protection & Alarm | D86: =SUM(F86:H86) -> 1255.28 | H86: 1255.28
B87: Exterior Façade / Building Skin | D87: =SUM(F87:H87) -> 28034.85 | H87: 28034.85
B88: Doors & Frames | D88: =SUM(F88:H88) -> 9209.33 | H88: 9209.33
B89: Windows | D89: =SUM(F89:H89) -> 8673.12 | H89: 8673.12
B90: Ceiling Systems | D90: =SUM(F90:H90) -> 9530.52 | H90: 9530.52
B91: Interior Framing / Partitions | D91: =SUM(F91:H91) -> 20615.67 | H91: 20615.67
B92: Painting | D92: =SUM(F92:H92) -> 8186.44 | H92: 8186.44
... B97: Cabinets / Millwork - Restrooms | D97: =SUM(F97:H97) -> 901.51 | H97: 901.51
B98: Total Building Cost | D98: =SUM(D69:D97) -> 265816.45 | F98: =SUM(F69:F79) -> 55766.87 | H98: =SUM(H81:H97) -> 210049.58
B99: % of Building Cost | F99: =F98/D98 -> 0.20979465 | H99: =H98/D98 -> 0.79020535
A101: ASSET ALLOCATION
B102: Asset | D102: Cost | F102: 5 Year | H102: 30 Year
B103: Asset # 19 - Building - 754 "Menowitz" | D103: =F103+H103 -> 750.82 | F103: 157.52 | H103: 593.3
B104: Asset # 3 - Building | D104: =F104+H104 -> 223422.8 | F104: 46872.91 | H104: 176549.89
B105: Asset # 4 - Personal Property | D105: =F105+H105 -> 13880.94 | F105: 2912.15 | H105: 10968.79
B106: Asset # 2 - Land Improvements | D106: =F106+H106 -> 27761.89 | F106: 5824.29 | H106: 21937.6
B107: Total Allocation | D107: =SUM(D103:D106) -> 265816.45 | F107: =SUM(F103:F106) -> 55766.87 | H107: =SUM(H103:H106) -> 210049.58
B108: Check: Allocation vs. Cost Detail (should be zero) | D108: =D107-D98 -> 0

Sheet Building 10
A1: Silver Springs Housing, LP
A2: Silver Spring Terrace Apartments — 950 20th St NE, Hickory, NC 28601
A3: EIN: 82-0773652 · FYE: December 31, 2024 · Year of Change: 1/1/2024
A4: Building 10 — Attachment to Form 3115 (DCN #7, Rev. Proc. 2024-23 §6.01)
A5: Source: CSSI Report #107752-39, "Silver Springs Housing LP_#107752-39_3115_Combined R1.pdf"
A7: CALCULATION OF §481(a) ADJUSTMENT — REGULAR TAX
A8: As Previously Filed
A9: Asset | B9: Property Description | C9: Date In Service | D9: Cost | E9: Sec 179 Exp | F9: Bonus Amt | G9: Tax Prior Depreciation | H9: Tax Current Depreciation | I9: End Depreciation | J9: Net Book Value | K9: Method | L9: Period
A10: 1 | B10: 19 - Building - 754 "Menowitz" | C10: 9/15/21 | D10: 750.82 | E10: 0 | F10: 0 | G10: 45.46 | H10: 18.74 | I10: =G10+H10 -> 64.2 | J10: =D10-I10 -> 686.62 | K10: S/L | L10: 40.00
A11: 2 | B11: 3 - Building | C11: 5/31/17 | D11: 223422.8 | E11: 0 | F11: 0 | G11: 48082.9 | H11: 5253.66 | I11: =G11+H11 -> 53336.56 | J11: =D11-I11 -> 170086.24 | K11: S/L | L11: 40.00
A12: 3 | B12: 4 - Personal Property | C12: 5/31/17 | D12: 13880.94 | E12: 0 | F12: 0 | G12: 12955.57 | H12: 0 | I12: =G12+H12 -> 12955.57 | J12: =D12-I12 -> 925.37 | K12: S/L | L12: 40.00
A13: 4 | B13: 2 - Land Improvements | C13: 5/31/17 | D13: 27761.89 | E13: 0 | F13: 0 | G13: 13359.23 | H13: 1637.95 | I13: =G13+H13 -> 14997.18 | J13: =D13-I13 -> 12764.71 | K13: S/L | L13: 40.00
B14: Grand Total | D14: =SUM(D10:D13) -> 265816.45 | E14: =SUM(E10:E13) -> 0 | F14: =SUM(F10:F13) -> 0 | G14: =SUM(G10:G13) -> 74443.16 | H14: =SUM(H10:H13) -> 6910.35 | I14: =SUM(I10:I13) -> 81353.51 | J14: =SUM(J10:J13) -> 184462.94
A16: After Cost Segregation Correction
A17: Asset | B17: Property Description | C17: Date In Service | D17: Cost | E17: Sec 179 Exp | F17: Bonus Amt | G17: Tax Prior Depreciation | H17: Tax Current Depreciation | I17: End Depreciation | J17: Net Book Value | K17: Method | L17: Period
A18: 1 | B18: 19 - Building - 754 "Menowitz" - 5 year | C18: 9/15/21 | D18: 157.52 | E18: 0 | F18: 157.52 | G18: 157.52 | H18: 0 | I18: =G18+H18 -> 157.52 | J18: =D18-I18 -> 0 | K18: 200DB | L18: 5.0
A19: 2 | B19: 19 - Building - 754 "Menowitz" - 30 year | C19: 9/15/21 | D19: 593.3 | E19: 0 | F19: 0 | G19: 45.33 | H19: 19.78 | I19: =G19+H19 -> 65.11 | J19: =D19-I19 -> 528.19 | K19: S/L | L19: 30.00
A20: 3 | B20: 3 - Building - 5 year | C20: 5/31/17 | D20: 46872.91 | E20: 0 | F20: 0 | G20: 46872.91 | H20: 0 | I20: =G20+H20 -> 46872.91 | J20: =D20-I20 -> 0 | K20: 200DB | L20: 5.0
A21: 4 | B21: 3 - Building - 30 year | C21: 5/31/17 | D21: 176549.89 | E21: 0 | F21: 0 | G21: 38988.12 | H21: 5885 | I21: =G21+H21 -> 44873.12 | J21: =D21-I21 -> 131676.77 | K21: S/L | L21: 30.00
A22: 5 | B22: 4 - Personal Property - 5 year | C22: 5/31/17 | D22: 2912.15 | E22: 0 | F22: 0 | G22: 2912.15 | H22: 0 | I22: =G22+H22 -> 2912.15 | J22: =D22-I22 -> 0 | K22: 200DB | L22: 5.0
A23: 6 | B23: 4 - Personal Property - 30 year | C23: 5/31/17 | D23: 10968.79 | E23: 0 | F23: 0 | G23: 2422.3 | H23: 365.63 | I23: =G23+H23 -> 2787.93 | J23: =D23-I23 -> 8180.86 | K23: S/L | L23: 30.00
A24: 7 | B24: 2 - Land Improvements - 5 year | C24: 5/31/17 | D24: 5824.29 | E24: 0 | F24: 0 | G24: 5824.29 | H24: 0 | I24: =G24+H24 -> 5824.29 | J24: =D24-I24 -> 0 | K24: 200DB | L24: 5.0
A25: 8 | B25: 2 - Land Improvements - 30 year | C25: 5/31/17 | D25: 21937.6 | E25: 0 | F25: 0 | G25: 4844.53 | H25: 731.25 | I25: =G25+H25 -> 5575.78 | J25: =D25-I25 -> 16361.82 | K25: S/L | L25: 30.00
B26: Grand Total | D26: =SUM(D18:D25) -> 265816.45 | E26: =SUM(E18:E25) -> 0 | F26: =SUM(F18:F25) -> 157.52 | G26: =SUM(G18:G25) -> 102067.15 | H26: =SUM(H18:H25) -> 7001.66 | I26: =SUM(I18:I25) -> 109068.81 | J26: =SUM(J18:J25) -> 156747.64
B28: Section 481(a) Adjustment — Regular Tax
B29: Depreciation reported previously | D29: =I14 -> 81353.51
B30: Cost Segregation Corrected Depreciation | D30: =I26 -> 109068.81
B31: Section 481(a) Adjustment — Regular Tax | D31: =D29-D30 -> -27715.3
A33: CALCULATION OF §481(a) ADJUSTMENT — AMT
A34: As Previously Filed — AMT
A35: Asset | B35: Property Description | C35: Date In Service | D35: Cost | E35: Sec 179 Exp | F35: Bonus Amt | G35: AMT Prior Depreciation | H35: AMT Current Depreciation | I35: End Depreciation | J35: Net Book Value | K35: Method | L35: Period
A36: 1 | B36: 19 - Building - 754 "Menowitz" | C36: 9/15/21 | D36: 750.82 | E36: 0 | F36: 0 | G36: 45.46 | H36: 18.74 | I36: =G36+H36 -> 64.2 | J36: =D36-I36 -> 686.62 | K36: S/L | L36: 40.00
A37: 2 | B37: 3 - Building | C37: 5/31/17 | D37: 223422.8 | E37: 0 | F37: 0 | G37: 48082.9 | H37: 5253.66 | I37: =G37+H37 -> 53336.56 | J37: =D37-I37 -> 170086.24 | K37: S/L | L37: 40.00
A38: 3 | B38: 4 - Personal Property | C38: 5/31/17 | D38: 13880.94 | E38: 0 | F38: 0 | G38: 12955.57 | H38: 0 | I38: =G38+H38 -> 12955.57 | J38: =D38-I38 -> 925.37 | K38: S/L | L38: 40.00
A39: 4 | B39: 2 - Land Improvements | C39: 5/31/17 | D39: 27761.89 | E39: 0 | F39: 0 | G39: 13359.23 | H39: 1637.95 | I39: =G39+H39 -> 14997.18 | J39: =D39-I39 -> 12764.71 | K39: S/L | L39: 40.00
B40: Grand Total | D40: =SUM(D36:D39) -> 265816.45 | E40: =SUM(E36:E39) -> 0 | F40: =SUM(F36:F39) -> 0 | G40: =SUM(G36:G39) -> 74443.16 | H40: =SUM(H36:H39) -> 6910.35 | I40: =SUM(I36:I39) -> 81353.51 | J40: =SUM(J36:J39) -> 184462.94
A42: After Cost Segregation Correction — AMT
A43: Asset | B43: Property Description | C43: Date In Service | D43: Cost | E43: Sec 179 Exp | F43: Bonus Amt | G43: AMT Prior Depreciation | H43: AMT Current Depreciation | I43: End Depreciation | J43: Net Book Value | K43: Method | L43: Period
A44: 1 | B44: 19 - Building - 754 "Menowitz" - 5 year | C44: 9/15/21 | D44: 157.52 | E44: 0 | F44: 157.52 | G44: 157.52 | H44: 0 | I44: =G44+H44 -> 157.52 | J44: =D44-I44 -> 0 | K44: 200DB | L44: 5.0
A45: 2 | B45: 19 - Building - 754 "Menowitz" - 30 year | C45: 9/15/21 | D45: 593.3 | E45: 0 | F45: 0 | G45: 45.33 | H45: 19.78 | I45: =G45+H45 -> 65.11 | J45: =D45-I45 -> 528.19 | K45: S/L | L45: 30.00
A46: 3 | B46: 3 - Building - 5 year | C46: 5/31/17 | D46: 46872.91 | E46: 0 | F46: 0 | G46: 46872.91 | H46: 0 | I46: =G46+H46 -> 46872.91 | J46: =D46-I46 -> 0 | K46: 200DB | L46: 5.0
A47: 4 | B47: 3 - Building - 30 year | C47: 5/31/17 | D47: 176549.89 | E47: 0 | F47: 0 | G47: 38988.12 | H47: 5885 | I47: =G47+H47 -> 44873.12 | J47: =D47-I47 -> 131676.77 | K47: S/L | L47: 30.00
A48: 5 | B48: 4 - Personal Property - 5 year | C48: 5/31/17 | D48: 2912.15 | E48: 0 | F48: 0 | G48: 2912.15 | H48: 0 | I48: =G48+H48 -> 2912.15 | J48: =D48-I48 -> 0 | K48: 200DB | L48: 5.0
A49: 6 | B49: 4 - Personal Property - 30 year | C49: 5/31/17 | D49: 10968.79 | E49: 0 | F49: 0 | G49: 2422.3 | H49: 365.63 | I49: =G49+H49 -> 2787.93 | J49: =D49-I49 -> 8180.86 | K49: S/L | L49: 30.00
A50: 7 | B50: 2 - Land Improvements - 5 year | C50: 5/31/17 | D50: 5824.29 | E50: 0 | F50: 0 | G50: 5824.29 | H50: 0 | I50: =G50+H50 -> 5824.29 | J50: =D50-I50 -> 0 | K50: 200DB | L50: 5.0
A51: 8 | B51: 2 - Land Improvements - 30 year | C51: 5/31/17 | D51: 21937.6 | E51: 0 | F51: 0 | G51: 4844.53 | H51: 731.25 | I51: =G51+H51 -> 5575.78 | J51: =D51-I51 -> 16361.82 | K51: S/L | L51: 30.00
B52: Grand Total | D52: =SUM(D44:D51) -> 265816.45 | E52: =SUM(E44:E51) -> 0 | F52: =SUM(F44:F51) -> 157.52 | G52: =SUM(G44:G51) -> 102067.15 | H52: =SUM(H44:H51) -> 7001.66 | I52: =SUM(I44:I51) -> 109068.81 | J52: =SUM(J44:J51) -> 156747.64
B54: Section 481(a) Adjustment — AMT
B55: Depreciation reported previously | D55: =I40 -> 81353.51
B56: Cost Segregation Corrected Depreciation | D56: =I52 -> 109068.81
B57: Section 481(a) Adjustment — AMT | D57: =D55-D56 -> -27715.3
A59: COST SEGREGATION STUDY — COST SUMMARY
B60: Total Building Cost | D60: =D98 -> 265816.45
B61: Building Components: 5 Year | D61: =F98 -> 55766.87
B62: % of Building Cost | D62: =F99 -> 0.20979465
B63: Building Structure: 30 Year | D63: =H98 -> 210049.58
B64: % of Building Cost | D64: =H99 -> 0.79020535
A66: COST SEGREGATION STUDY — COST DETAIL
B67: Property Category | D67: Cost | F67: 5 Year | H67: 30 Year
B68: Building Components
B69: Cabinets / Millwork | D69: =SUM(F69:H69) -> 13932.37 | F69: 13932.37
B70: Moldings | D70: =SUM(F70:H70) -> 4762.13 | F70: 4762.13
B71: Flooring - Vinyl Plank | D71: =SUM(F71:H71) -> 21399.52 | F71: 21399.52
B72: Window Treatments | D72: =SUM(F72:H72) -> 1967.77 | F72: 1967.77
B73: Building Signage | D73: =SUM(F73:H73) -> 127.35 | F73: 127.35
B74: Specialty Electrical - Appliances | D74: =SUM(F74:H74) -> 2548.79 | F74: 2548.79
B75: Communication / Data | D75: =SUM(F75:H75) -> 1855.1 | F75: 1855.1
B76: Specialty Plumbing - Kitchen Sinks | D76: =SUM(F76:H76) -> 4626.46 | F76: 4626.46
B77: Security / Exterior Lighting | D77: =SUM(F77:H77) -> 480.75 | F77: 480.75
B78: Access Control | D78: =SUM(F78:H78) -> 75.53 | F78: 75.53
B79: Appliances | D79: =SUM(F79:H79) -> 3991.1 | F79: 3991.1
B80: Building Structure
B81: Roofing Systems | D81: =SUM(F81:H81) -> 8726.14 | H81: 8726.14
B82: Foundations | D82: =SUM(F82:H82) -> 14310.97 | H82: 14310.97
B83: HVAC | D83: =SUM(F83:H83) -> 20721.85 | H83: 20721.85
B84: Electrical | D84: =SUM(F84:H84) -> 20019.46 | H84: 20019.46
B85: Plumbing | D85: =SUM(F85:H85) -> 18013.39 | H85: 18013.39
B86: Fire Protection & Alarm | D86: =SUM(F86:H86) -> 1255.28 | H86: 1255.28
B87: Exterior Façade / Building Skin | D87: =SUM(F87:H87) -> 28034.85 | H87: 28034.85
B88: Doors & Frames | D88: =SUM(F88:H88) -> 9209.33 | H88: 9209.33
B89: Windows | D89: =SUM(F89:H89) -> 8673.12 | H89: 8673.12
B90: Ceiling Systems | D90: =SUM(F90:H90) -> 9530.52 | H90: 9530.52
B91: Interior Framing / Partitions | D91: =SUM(F91:H91) -> 20615.67 | H91: 20615.67
B92: Painting | D92: =SUM(F92:H92) -> 8186.44 | H92: 8186.44
... B97: Cabinets / Millwork - Restrooms | D97: =SUM(F97:H97) -> 901.51 | H97: 901.51
B98: Total Building Cost | D98: =SUM(D69:D97) -> 265816.45 | F98: =SUM(F69:F79) -> 55766.87 | H98: =SUM(H81:H97) -> 210049.58
B99: % of Building Cost | F99: =F98/D98 -> 0.20979465 | H99: =H98/D98 -> 0.79020535
A101: ASSET ALLOCATION
B102: Asset | D102: Cost | F102: 5 Year | H102: 30 Year
B103: Asset # 19 - Building - 754 "Menowitz" | D103: =F103+H103 -> 750.82 | F103: 157.52 | H103: 593.3
B104: Asset # 3 - Building | D104: =F104+H104 -> 223422.8 | F104: 46872.91 | H104: 176549.89
B105: Asset # 4 - Personal Property | D105: =F105+H105 -> 13880.94 | F105: 2912.15 | H105: 10968.79
B106: Asset # 2 - Land Improvements | D106: =F106+H106 -> 27761.89 | F106: 5824.29 | H106: 21937.6
B107: Total Allocation | D107: =SUM(D103:D106) -> 265816.45 | F107: =SUM(F103:F106) -> 55766.87 | H107: =SUM(H103:H106) -> 210049.58
B108: Check: Allocation vs. Cost Detail (should be zero) | D108: =D107-D98 -> 0

Sheet Building 11
A1: Silver Springs Housing, LP
A2: Silver Spring Terrace Apartments — 950 20th St NE, Hickory, NC 28601
A3: EIN: 82-0773652 · FYE: December 31, 2024 · Year of Change: 1/1/2024
A4: Building 11 — Attachment to Form 3115 (DCN #7, Rev. Proc. 2024-23 §6.01)
A5: Source: CSSI Report #107752-39, "Silver Springs Housing LP_#107752-39_3115_Combined R1.pdf"
A7: CALCULATION OF §481(a) ADJUSTMENT — REGULAR TAX
A8: As Previously Filed
A9: Asset | B9: Property Description | C9: Date In Service | D9: Cost | E9: Sec 179 Exp | F9: Bonus Amt | G9: Tax Prior Depreciation | H9: Tax Current Depreciation | I9: End Depreciation | J9: Net Book Value | K9: Method | L9: Period
A10: 1 | B10: 19 - Building - 754 "Menowitz" | C10: 9/15/21 | D10: 662.06 | E10: 0 | F10: 0 | G10: 40.09 | H10: 16.52 | I10: =G10+H10 -> 56.61 | J10: =D10-I10 -> 605.45 | K10: S/L | L10: 40.00
A11: 2 | B11: 3 - Building | C11: 5/31/17 | D11: 197009.25 | E11: 0 | F11: 0 | G11: 42398.42 | H11: 4632.55 | I11: =G11+H11 -> 47030.97 | J11: =D11-I11 -> 149978.28 | K11: S/L | L11: 40.00
A12: 3 | B12: 4 - Personal Property | C12: 5/31/17 | D12: 12239.91 | E12: 0 | F12: 0 | G12: 11423.94 | H12: 0 | I12: =G12+H12 -> 11423.94 | J12: =D12-I12 -> 815.97 | K12: S/L | L12: 40.00
A13: 4 | B13: 2 - Land Improvements | C13: 5/31/17 | D13: 24479.81 | E13: 0 | F13: 0 | G13: 11779.87 | H13: 1444.31 | I13: =G13+H13 -> 13224.18 | J13: =D13-I13 -> 11255.63 | K13: S/L | L13: 40.00
B14: Grand Total | D14: =SUM(D10:D13) -> 234391.03 | E14: =SUM(E10:E13) -> 0 | F14: =SUM(F10:F13) -> 0 | G14: =SUM(G10:G13) -> 65642.32 | H14: =SUM(H10:H13) -> 6093.38 | I14: =SUM(I10:I13) -> 71735.7 | J14: =SUM(J10:J13) -> 162655.33
A16: After Cost Segregation Correction
A17: Asset | B17: Property Description | C17: Date In Service | D17: Cost | E17: Sec 179 Exp | F17: Bonus Amt | G17: Tax Prior Depreciation | H17: Tax Current Depreciation | I17: End Depreciation | J17: Net Book Value | K17: Method | L17: Period
A18: 1 | B18: 19 - Building - 754 "Menowitz" - 5 year | C18: 9/15/21 | D18: 137.19 | E18: 0 | F18: 137.19 | G18: 137.19 | H18: 0 | I18: =G18+H18 -> 137.19 | J18: =D18-I18 -> 0 | K18: 200DB | L18: 5.0
A19: 2 | B19: 19 - Building - 754 "Menowitz" - 30 year | C19: 9/15/21 | D19: 524.87 | E19: 0 | F19: 0 | G19: 40.1 | H19: 17.5 | I19: =G19+H19 -> 57.6 | J19: =D19-I19 -> 467.27 | K19: S/L | L19: 30.00
A20: 3 | B20: 3 - Building - 5 year | C20: 5/31/17 | D20: 40824.27 | E20: 0 | F20: 0 | G20: 40824.27 | H20: 0 | I20: =G20+H20 -> 40824.27 | J20: =D20-I20 -> 0 | K20: 200DB | L20: 5.0
A21: 4 | B21: 3 - Building - 30 year | C21: 5/31/17 | D21: 156184.98 | E21: 0 | F21: 0 | G21: 34490.87 | H21: 5206.17 | I21: =G21+H21 -> 39697.04 | J21: =D21-I21 -> 116487.94 | K21: S/L | L21: 30.00
A22: 5 | B22: 4 - Personal Property - 5 year | C22: 5/31/17 | D22: 2536.35 | E22: 0 | F22: 0 | G22: 2536.35 | H22: 0 | I22: =G22+H22 -> 2536.35 | J22: =D22-I22 -> 0 | K22: 200DB | L22: 5.0
A23: 6 | B23: 4 - Personal Property - 30 year | C23: 5/31/17 | D23: 9703.56 | E23: 0 | F23: 0 | G23: 2142.86 | H23: 323.45 | I23: =G23+H23 -> 2466.31 | J23: =D23-I23 -> 7237.25 | K23: S/L | L23: 30.00
A24: 7 | B24: 2 - Land Improvements - 5 year | C24: 5/31/17 | D24: 5072.71 | E24: 0 | F24: 0 | G24: 5072.71 | H24: 0 | I24: =G24+H24 -> 5072.71 | J24: =D24-I24 -> 0 | K24: 200DB | L24: 5.0
A25: 8 | B25: 2 - Land Improvements - 30 year | C25: 5/31/17 | D25: 19407.1 | E25: 0 | F25: 0 | G25: 4285.71 | H25: 646.9 | I25: =G25+H25 -> 4932.61 | J25: =D25-I25 -> 14474.49 | K25: S/L | L25: 30.00
B26: Grand Total | D26: =SUM(D18:D25) -> 234391.03 | E26: =SUM(E18:E25) -> 0 | F26: =SUM(F18:F25) -> 137.19 | G26: =SUM(G18:G25) -> 89530.06 | H26: =SUM(H18:H25) -> 6194.02 | I26: =SUM(I18:I25) -> 95724.08 | J26: =SUM(J18:J25) -> 138666.95
B28: Section 481(a) Adjustment — Regular Tax
B29: Depreciation reported previously | D29: =I14 -> 71735.7
B30: Cost Segregation Corrected Depreciation | D30: =I26 -> 95724.08
B31: Section 481(a) Adjustment — Regular Tax | D31: =D29-D30 -> -23988.38
A33: CALCULATION OF §481(a) ADJUSTMENT — AMT
A34: As Previously Filed — AMT
A35: Asset | B35: Property Description | C35: Date In Service | D35: Cost | E35: Sec 179 Exp | F35: Bonus Amt | G35: AMT Prior Depreciation | H35: AMT Current Depreciation | I35: End Depreciation | J35: Net Book Value | K35: Method | L35: Period
A36: 1 | B36: 19 - Building - 754 "Menowitz" | C36: 9/15/21 | D36: 662.06 | E36: 0 | F36: 0 | G36: 40.09 | H36: 16.52 | I36: =G36+H36 -> 56.61 | J36: =D36-I36 -> 605.45 | K36: S/L | L36: 40.00
A37: 2 | B37: 3 - Building | C37: 5/31/17 | D37: 197009.25 | E37: 0 | F37: 0 | G37: 42398.42 | H37: 4632.55 | I37: =G37+H37 -> 47030.97 | J37: =D37-I37 -> 149978.28 | K37: S/L | L37: 40.00
A38: 3 | B38: 4 - Personal Property | C38: 5/31/17 | D38: 12239.91 | E38: 0 | F38: 0 | G38: 11423.94 | H38: 0 | I38: =G38+H38 -> 11423.94 | J38: =D38-I38 -> 815.97 | K38: S/L | L38: 40.00
A39: 4 | B39: 2 - Land Improvements | C39: 5/31/17 | D39: 24479.81 | E39: 0 | F39: 0 | G39: 11779.87 | H39: 1444.31 | I39: =G39+H39 -> 13224.18 | J39: =D39-I39 -> 11255.63 | K39: S/L | L39: 40.00
B40: Grand Total | D40: =SUM(D36:D39) -> 234391.03 | E40: =SUM(E36:E39) -> 0 | F40: =SUM(F36:F39) -> 0 | G40: =SUM(G36:G39) -> 65642.32 | H40: =SUM(H36:H39) -> 6093.38 | I40: =SUM(I36:I39) -> 71735.7 | J40: =SUM(J36:J39) -> 162655.33
A42: After Cost Segregation Correction — AMT
A43: Asset | B43: Property Description | C43: Date In Service | D43: Cost | E43: Sec 179 Exp | F43: Bonus Amt | G43: AMT Prior Depreciation | H43: AMT Current Depreciation | I43: End Depreciation | J43: Net Book Value | K43: Method | L43: Period
A44: 1 | B44: 19 - Building - 754 "Menowitz" - 5 year | C44: 9/15/21 | D44: 137.19 | E44: 0 | F44: 137.19 | G44: 137.19 | H44: 0 | I44: =G44+H44 -> 137.19 | J44: =D44-I44 -> 0 | K44: 200DB | L44: 5.0
A45: 2 | B45: 19 - Building - 754 "Menowitz" - 30 year | C45: 9/15/21 | D45: 524.87 | E45: 0 | F45: 0 | G45: 40.1 | H45: 17.5 | I45: =G45+H45 -> 57.6 | J45: =D45-I45 -> 467.27 | K45: S/L | L45: 30.00
A46: 3 | B46: 3 - Building - 5 year | C46: 5/31/17 | D46: 40824.27 | E46: 0 | F46: 0 | G46: 40824.27 | H46: 0 | I46: =G46+H46 -> 40824.27 | J46: =D46-I46 -> 0 | K46: 200DB | L46: 5.0
A47: 4 | B47: 3 - Building - 30 year | C47: 5/31/17 | D47: 156184.98 | E47: 0 | F47: 0 | G47: 34490.87 | H47: 5206.17 | I47: =G47+H47 -> 39697.04 | J47: =D47-I47 -> 116487.94 | K47: S/L | L47: 30.00
A48: 5 | B48: 4 - Personal Property - 5 year | C48: 5/31/17 | D48: 2536.35 | E48: 0 | F48: 0 | G48: 2536.35 | H48: 0 | I48: =G48+H48 -> 2536.35 | J48: =D48-I48 -> 0 | K48: 200DB | L48: 5.0
A49: 6 | B49: 4 - Personal Property - 30 year | C49: 5/31/17 | D49: 9703.56 | E49: 0 | F49: 0 | G49: 2142.86 | H49: 323.45 | I49: =G49+H49 -> 2466.31 | J49: =D49-I49 -> 7237.25 | K49: S/L | L49: 30.00
A50: 7 | B50: 2 - Land Improvements - 5 year | C50: 5/31/17 | D50: 5072.71 | E50: 0 | F50: 0 | G50: 5072.71 | H50: 0 | I50: =G50+H50 -> 5072.71 | J50: =D50-I50 -> 0 | K50: 200DB | L50: 5.0
A51: 8 | B51: 2 - Land Improvements - 30 year | C51: 5/31/17 | D51: 19407.1 | E51: 0 | F51: 0 | G51: 4285.71 | H51: 646.9 | I51: =G51+H51 -> 4932.61 | J51: =D51-I51 -> 14474.49 | K51: S/L | L51: 30.00
B52: Grand Total | D52: =SUM(D44:D51) -> 234391.03 | E52: =SUM(E44:E51) -> 0 | F52: =SUM(F44:F51) -> 137.19 | G52: =SUM(G44:G51) -> 89530.06 | H52: =SUM(H44:H51) -> 6194.02 | I52: =SUM(I44:I51) -> 95724.08 | J52: =SUM(J44:J51) -> 138666.95
B54: Section 481(a) Adjustment — AMT
B55: Depreciation reported previously | D55: =I40 -> 71735.7
B56: Cost Segregation Corrected Depreciation | D56: =I52 -> 95724.08
B57: Section 481(a) Adjustment — AMT | D57: =D55-D56 -> -23988.38
A59: COST SEGREGATION STUDY — COST SUMMARY
B60: Total Building Cost | D60: =D98 -> 234391.03
B61: Building Components: 5 Year | D61: =F98 -> 48570.52
B62: % of Building Cost | D62: =F99 -> 0.20722005
B63: Building Structure: 30 Year | D63: =H98 -> 185820.51
B64: % of Building Cost | D64: =H99 -> 0.79277995
A66: COST SEGREGATION STUDY — COST DETAIL
B67: Property Category | D67: Cost | F67: 5 Year | H67: 30 Year
B68: Building Components
B69: Cabinets / Millwork | D69: =SUM(F69:H69) -> 11319.08 | F69: 11319.08
B70: Moldings | D70: =SUM(F70:H70) -> 4407.51 | F70: 4407.51
B71: Flooring - Vinyl Plank | D71: =SUM(F71:H71) -> 17858.88 | F71: 17858.88
B72: Window Treatments | D72: =SUM(F72:H72) -> 1586.91 | F72: 1586.91
B73: Building Signage | D73: =SUM(F73:H73) -> 127.35 | F73: 127.35
B74: Specialty Electrical - Appliances | D74: =SUM(F74:H74) -> 2548.79 | F74: 2548.79
B75: Communication / Data | D75: =SUM(F75:H75) -> 1548.16 | F75: 1548.16
B76: Specialty Plumbing - Kitchen Sinks | D76: =SUM(F76:H76) -> 4626.46 | F76: 4626.46
B77: Security / Exterior Lighting | D77: =SUM(F77:H77) -> 480.75 | F77: 480.75
B78: Access Control | D78: =SUM(F78:H78) -> 75.53 | F78: 75.53
B79: Appliances | D79: =SUM(F79:H79) -> 3991.1 | F79: 3991.1
B80: Building Structure
B81: Roofing Systems | D81: =SUM(F81:H81) -> 7270.82 | H81: 7270.82
B82: Foundations | D82: =SUM(F82:H82) -> 12116.84 | H82: 12116.84
B83: HVAC | D83: =SUM(F83:H83) -> 17293.33 | H83: 17293.33
B84: Electrical | D84: =SUM(F84:H84) -> 16285.45 | H84: 16285.45
B85: Plumbing | D85: =SUM(F85:H85) -> 15033 | H85: 15033
B86: Fire Protection & Alarm | D86: =SUM(F86:H86) -> 958.91 | H86: 958.91
B87: Exterior Façade / Building Skin | D87: =SUM(F87:H87) -> 26187.51 | H87: 26187.51
B88: Doors & Frames | D88: =SUM(F88:H88) -> 11772.85 | H88: 11772.85
B89: Windows | D89: =SUM(F89:H89) -> 6994.46 | H89: 6994.46
B90: Ceiling Systems | D90: =SUM(F90:H90) -> 7953.64 | H90: 7953.64
B91: Interior Framing / Partitions | D91: =SUM(F91:H91) -> 19168.95 | H91: 19168.95
B92: Painting | D92: =SUM(F92:H92) -> 7364.73 | H92: 7364.73
... B97: Cabinets / Millwork - Restrooms | D97: =SUM(F97:H97) -> 901.51 | H97: 901.51
B98: Total Building Cost | D98: =SUM(D69:D97) -> 234391.03 | F98: =SUM(F69:F79) -> 48570.52 | H98: =SUM(H81:H97) -> 185820.51
B99: % of Building Cost | F99: =F98/D98 -> 0.20722005 | H99: =H98/D98 -> 0.79277995
A101: ASSET ALLOCATION
B102: Asset | D102: Cost | F102: 5 Year | H102: 30 Year
B103: Asset # 19 - Building - 754 "Menowitz" | D103: =F103+H103 -> 662.06 | F103: 137.19 | H103: 524.87
B104: Asset # 3 - Building | D104: =F104+H104 -> 197009.25 | F104: 40824.27 | H104: 156184.98
B105: Asset # 4 - Personal Property | D105: =F105+H105 -> 12239.91 | F105: 2536.35 | H105: 9703.56
B106: Asset # 2 - Land Improvements | D106: =F106+H106 -> 24479.81 | F106: 5072.71 | H106: 19407.1
B107: Total Allocation | D107: =SUM(D103:D106) -> 234391.03 | F107: =SUM(F103:F106) -> 48570.52 | H107: =SUM(H103:H106) -> 185820.51
B108: Check: Allocation vs. Cost Detail (should be zero) | D108: =D107-D98 -> 0

Sheet Building 12
A1: Silver Springs Housing, LP
A2: Silver Spring Terrace Apartments — 950 20th St NE, Hickory, NC 28601
A3: EIN: 82-0773652 · FYE: December 31, 2024 · Year of Change: 1/1/2024
A4: Building 12 — Attachment to Form 3115 (DCN #7, Rev. Proc. 2024-23 §6.01)
A5: Source: CSSI Report #107752-39, "Silver Springs Housing LP_#107752-39_3115_Combined R1.pdf"
A7: CALCULATION OF §481(a) ADJUSTMENT — REGULAR TAX
A8: As Previously Filed
A9: Asset | B9: Property Description | C9: Date In Service | D9: Cost | E9: Sec 179 Exp | F9: Bonus Amt | G9: Tax Prior Depreciation | H9: Tax Current Depreciation | I9: End Depreciation | J9: Net Book Value | K9: Method | L9: Period
A10: 1 | B10: 19 - Building - 754 "Menowitz" | C10: 9/15/21 | D10: 479.53 | E10: 0 | F10: 0 | G10: 29.03 | H10: 11.97 | I10: =G10+H10 -> 41 | J10: =D10-I10 -> 438.53 | K10: S/L | L10: 40.00
A11: 2 | B11: 3 - Building | C11: 5/31/17 | D11: 142694.3 | E11: 0 | F11: 0 | G11: 30709.29 | H11: 3355.37 | I11: =G11+H11 -> 34064.66 | J11: =D11-I11 -> 108629.64 | K11: S/L | L11: 40.00
A12: 3 | B12: 4 - Personal Property | C12: 5/31/17 | D12: 8865.4 | E12: 0 | F12: 0 | G12: 8274.39 | H12: 0 | I12: =G12+H12 -> 8274.39 | J12: =D12-I12 -> 591.01 | K12: S/L | L12: 40.00
A13: 4 | B13: 2 - Land Improvements | C13: 5/31/17 | D13: 17730.79 | E13: 0 | F13: 0 | G13: 8532.2 | H13: 1046.12 | I13: =G13+H13 -> 9578.32 | J13: =D13-I13 -> 8152.47 | K13: S/L | L13: 40.00
B14: Grand Total | D14: =SUM(D10:D13) -> 169770.02 | E14: =SUM(E10:E13) -> 0 | F14: =SUM(F10:F13) -> 0 | G14: =SUM(G10:G13) -> 47544.91 | H14: =SUM(H10:H13) -> 4413.46 | I14: =SUM(I10:I13) -> 51958.37 | J14: =SUM(J10:J13) -> 117811.65
A16: After Cost Segregation Correction
A17: Asset | B17: Property Description | C17: Date In Service | D17: Cost | E17: Sec 179 Exp | F17: Bonus Amt | G17: Tax Prior Depreciation | H17: Tax Current Depreciation | I17: End Depreciation | J17: Net Book Value | K17: Method | L17: Period
A18: 1 | B18: 19 - Building - 754 "Menowitz" - 5 year | C18: 9/15/21 | D18: 89.94 | E18: 0 | F18: 89.94 | G18: 89.94 | H18: 0 | I18: =G18+H18 -> 89.94 | J18: =D18-I18 -> 0 | K18: 200DB | L18: 5.0
A19: 2 | B19: 19 - Building - 754 "Menowitz" - 30 year | C19: 9/15/21 | D19: 389.59 | E19: 0 | F19: 0 | G19: 29.77 | H19: 12.99 | I19: =G19+H19 -> 42.76 | J19: =D19-I19 -> 346.83 | K19: S/L | L19: 30.00
A20: 3 | B20: 3 - Building - 5 year | C20: 5/31/17 | D20: 26763.65 | E20: 0 | F20: 0 | G20: 26763.65 | H20: 0 | I20: =G20+H20 -> 26763.65 | J20: =D20-I20 -> 0 | K20: 200DB | L20: 5.0
A21: 4 | B21: 3 - Building - 30 year | C21: 5/31/17 | D21: 115930.65 | E21: 0 | F21: 0 | G21: 25601.32 | H21: 3864.35 | I21: =G21+H21 -> 29465.67 | J21: =D21-I21 -> 86464.98 | K21: S/L | L21: 30.00
A22: 5 | B22: 4 - Personal Property - 5 year | C22: 5/31/17 | D22: 1662.79 | E22: 0 | F22: 0 | G22: 1662.79 | H22: 0 | I22: =G22+H22 -> 1662.79 | J22: =D22-I22 -> 0 | K22: 200DB | L22: 5.0
A23: 6 | B23: 4 - Personal Property - 30 year | C23: 5/31/17 | D23: 7202.61 | E23: 0 | F23: 0 | G23: 1590.59 | H23: 240.09 | I23: =G23+H23 -> 1830.68 | J23: =D23-I23 -> 5371.93 | K23: S/L | L23: 30.00
A24: 7 | B24: 2 - Land Improvements - 5 year | C24: 5/31/17 | D24: 3325.57 | E24: 0 | F24: 0 | G24: 3325.57 | H24: 0 | I24: =G24+H24 -> 3325.57 | J24: =D24-I24 -> 0 | K24: 200DB | L24: 5.0
A25: 8 | B25: 2 - Land Improvements - 30 year | C25: 5/31/17 | D25: 14405.22 | E25: 0 | F25: 0 | G25: 3181.13 | H25: 480.17 | I25: =G25+H25 -> 3661.3 | J25: =D25-I25 -> 10743.92 | K25: S/L | L25: 30.00
B26: Grand Total | D26: =SUM(D18:D25) -> 169770.02 | E26: =SUM(E18:E25) -> 0 | F26: =SUM(F18:F25) -> 89.94 | G26: =SUM(G18:G25) -> 62244.76 | H26: =SUM(H18:H25) -> 4597.6 | I26: =SUM(I18:I25) -> 66842.36 | J26: =SUM(J18:J25) -> 102927.66
B28: Section 481(a) Adjustment — Regular Tax
B29: Depreciation reported previously | D29: =I14 -> 51958.37
B30: Cost Segregation Corrected Depreciation | D30: =I26 -> 66842.36
B31: Section 481(a) Adjustment — Regular Tax | D31: =D29-D30 -> -14883.99
A33: CALCULATION OF §481(a) ADJUSTMENT — AMT
A34: As Previously Filed — AMT
A35: Asset | B35: Property Description | C35: Date In Service | D35: Cost | E35: Sec 179 Exp | F35: Bonus Amt | G35: AMT Prior Depreciation | H35: AMT Current Depreciation | I35: End Depreciation | J35: Net Book Value | K35: Method | L35: Period
A36: 1 | B36: 19 - Building - 754 "Menowitz" | C36: 9/15/21 | D36: 479.53 | E36: 0 | F36: 0 | G36: 29.03 | H36: 11.97 | I36: =G36+H36 -> 41 | J36: =D36-I36 -> 438.53 | K36: S/L | L36: 40.00
A37: 2 | B37: 3 - Building | C37: 5/31/17 | D37: 142694.3 | E37: 0 | F37: 0 | G37: 30709.29 | H37: 3355.37 | I37: =G37+H37 -> 34064.66 | J37: =D37-I37 -> 108629.64 | K37: S/L | L37: 40.00
A38: 3 | B38: 4 - Personal Property | C38: 5/31/17 | D38: 8865.4 | E38: 0 | F38: 0 | G38: 8274.39 | H38: 0 | I38: =G38+H38 -> 8274.39 | J38: =D38-I38 -> 591.01 | K38: S/L | L38: 40.00
A39: 4 | B39: 2 - Land Improvements | C39: 5/31/17 | D39: 17730.79 | E39: 0 | F39: 0 | G39: 8532.2 | H39: 1046.12 | I39: =G39+H39 -> 9578.32 | J39: =D39-I39 -> 8152.47 | K39: S/L | L39: 40.00
B40: Grand Total | D40: =SUM(D36:D39) -> 169770.02 | E40: =SUM(E36:E39) -> 0 | F40: =SUM(F36:F39) -> 0 | G40: =SUM(G36:G39) -> 47544.91 | H40: =SUM(H36:H39) -> 4413.46 | I40: =SUM(I36:I39) -> 51958.37 | J40: =SUM(J36:J39) -> 117811.65
A42: After Cost Segregation Correction — AMT
A43: Asset | B43: Property Description | C43: Date In Service | D43: Cost | E43: Sec 179 Exp | F43: Bonus Amt | G43: AMT Prior Depreciation | H43: AMT Current Depreciation | I43: End Depreciation | J43: Net Book Value | K43: Method | L43: Period
A44: 1 | B44: 19 - Building - 754 "Menowitz" - 5 year | C44: 9/15/21 | D44: 89.94 | E44: 0 | F44: 89.94 | G44: 89.94 | H44: 0 | I44: =G44+H44 -> 89.94 | J44: =D44-I44 -> 0 | K44: 200DB | L44: 5.0
A45: 2 | B45: 19 - Building - 754 "Menowitz" - 30 year | C45: 9/15/21 | D45: 389.59 | E45: 0 | F45: 0 | G45: 29.77 | H45: 12.99 | I45: =G45+H45 -> 42.76 | J45: =D45-I45 -> 346.83 | K45: S/L | L45: 30.00
A46: 3 | B46: 3 - Building - 5 year | C46: 5/31/17 | D46: 26763.65 | E46: 0 | F46: 0 | G46: 26763.65 | H46: 0 | I46: =G46+H46 -> 26763.65 | J46: =D46-I46 -> 0 | K46: 200DB | L46: 5.0
A47: 4 | B47: 3 - Building - 30 year | C47: 5/31/17 | D47: 115930.65 | E47: 0 | F47: 0 | G47: 25601.32 | H47: 3864.35 | I47: =G47+H47 -> 29465.67 | J47: =D47-I47 -> 86464.98 | K47: S/L | L47: 30.00
A48: 5 | B48: 4 - Personal Property - 5 year | C48: 5/31/17 | D48: 1662.79 | E48: 0 | F48: 0 | G48: 1662.79 | H48: 0 | I48: =G48+H48 -> 1662.79 | J48: =D48-I48 -> 0 | K48: 200DB | L48: 5.0
A49: 6 | B49: 4 - Personal Property - 30 year | C49: 5/31/17 | D49: 7202.61 | E49: 0 | F49: 0 | G49: 1590.59 | H49: 240.09 | I49: =G49+H49 -> 1830.68 | J49: =D49-I49 -> 5371.93 | K49: S/L | L49: 30.00
A50: 7 | B50: 2 - Land Improvements - 5 year | C50: 5/31/17 | D50: 3325.57 | E50: 0 | F50: 0 | G50: 3325.57 | H50: 0 | I50: =G50+H50 -> 3325.57 | J50: =D50-I50 -> 0 | K50: 200DB | L50: 5.0
A51: 8 | B51: 2 - Land Improvements - 30 year | C51: 5/31/17 | D51: 14405.22 | E51: 0 | F51: 0 | G51: 3181.13 | H51: 480.17 | I51: =G51+H51 -> 3661.3 | J51: =D51-I51 -> 10743.92 | K51: S/L | L51: 30.00
B52: Grand Total | D52: =SUM(D44:D51) -> 169770.02 | E52: =SUM(E44:E51) -> 0 | F52: =SUM(F44:F51) -> 89.94 | G52: =SUM(G44:G51) -> 62244.76 | H52: =SUM(H44:H51) -> 4597.6 | I52: =SUM(I44:I51) -> 66842.36 | J52: =SUM(J44:J51) -> 102927.66
B54: Section 481(a) Adjustment — AMT
B55: Depreciation reported previously | D55: =I40 -> 51958.37
B56: Cost Segregation Corrected Depreciation | D56: =I52 -> 66842.36
B57: Section 481(a) Adjustment — AMT | D57: =D55-D56 -> -14883.99
A59: COST SEGREGATION STUDY — COST SUMMARY
B60: Total Building Cost | D60: =D98 -> 169770.02
B61: Building Components: 5 Year | D61: =F98 -> 31841.95
B62: % of Building Cost | D62: =F99 -> 0.18755932
B63: Building Structure: 30 Year | D63: =H98 -> 137928.07
B64: % of Building Cost | D64: =H99 -> 0.81244068
A66: COST SEGREGATION STUDY — COST DETAIL
B67: Property Category | D67: Cost | F67: 5 Year | H67: 30 Year
B68: Building Components
B69: Cabinets / Millwork | D69: =SUM(F69:H69) -> 7800.47 | F69: 7800.47
B70: Moldings | D70: =SUM(F70:H70) -> 3748.91 | F70: 3748.91
B71: Flooring - Vinyl Plank | D71: =SUM(F71:H71) -> 12139.37 | F71: 12139.37
B72: Window Treatments | D72: =SUM(F72:H72) -> 1142.58 | F72: 1142.58
B73: Building Signage | D73: =SUM(F73:H73) -> 85.24 | F73: 85.24
B74: Specialty Electrical - Appliances | D74: =SUM(F74:H74) -> 1274.42 | F74: 1274.42
B75: Communication / Data | D75: =SUM(F75:H75) -> 1052.34 | F75: 1052.34
B76: Specialty Plumbing - Kitchen Sinks | D76: =SUM(F76:H76) -> 2313.24 | F76: 2313.24
B77: Security / Exterior Lighting | D77: =SUM(F77:H77) -> 252.07 | F77: 252.07
B78: Access Control | D78: =SUM(F78:H78) -> 37.76 | F78: 37.76
B79: Appliances | D79: =SUM(F79:H79) -> 1995.55 | F79: 1995.55
B80: Building Structure
B81: Roofing Systems | D81: =SUM(F81:H81) -> 5090 | H81: 5090
B82: Foundations | D82: =SUM(F82:H82) -> 8538.11 | H82: 8538.11
B83: HVAC | D83: =SUM(F83:H83) -> 11754.94 | H83: 11754.94
B84: Electrical | D84: =SUM(F84:H84) -> 11527.95 | H84: 11527.95
B85: Plumbing | D85: =SUM(F85:H85) -> 10218.5 | H85: 10218.5
B86: Fire Protection & Alarm | D86: =SUM(F86:H86) -> 775.83 | H86: 775.83
B87: Exterior Façade / Building Skin | D87: =SUM(F87:H87) -> 22829.89 | H87: 22829.89
B88: Doors & Frames | D88: =SUM(F88:H88) -> 5886.42 | H88: 5886.42
B89: Windows | D89: =SUM(F89:H89) -> 5036.01 | H89: 5036.01
B90: Ceiling Systems | D90: =SUM(F90:H90) -> 5406.4 | H90: 5406.4
B91: Interior Framing / Partitions | D91: =SUM(F91:H91) -> 16464.28 | H91: 16464.28
B92: Painting | D92: =SUM(F92:H92) -> 5938.8 | H92: 5938.8
... B97: Cabinets / Millwork - Restrooms | D97: =SUM(F97:H97) -> 901.51 | H97: 901.51
B98: Total Building Cost | D98: =SUM(D69:D97) -> 169770.02 | F98: =SUM(F69:F79) -> 31841.95 | H98: =SUM(H81:H97) -> 137928.07
B99: % of Building Cost | F99: =F98/D98 -> 0.18755932 | H99: =H98/D98 -> 0.81244068
A101: ASSET ALLOCATION
B102: Asset | D102: Cost | F102: 5 Year | H102: 30 Year
B103: Asset # 19 - Building - 754 "Menowitz" | D103: =F103+H103 -> 479.53 | F103: 89.94 | H103: 389.59
B104: Asset # 3 - Building | D104: =F104+H104 -> 142694.3 | F104: 26763.65 | H104: 115930.65
B105: Asset # 4 - Personal Property | D105: =F105+H105 -> 8865.4 | F105: 1662.79 | H105: 7202.61
B106: Asset # 2 - Land Improvements | D106: =F106+H106 -> 17730.79 | F106: 3325.57 | H106: 14405.22
B107: Total Allocation | D107: =SUM(D103:D106) -> 169770.02 | F107: =SUM(F103:F106) -> 31841.95 | H107: =SUM(H103:H106) -> 137928.07
B108: Check: Allocation vs. Cost Detail (should be zero) | D108: =D107-D98 -> 0

Sheet Building 13
A1: Silver Springs Housing, LP
A2: Silver Spring Terrace Apartments — 950 20th St NE, Hickory, NC 28601
A3: EIN: 82-0773652 · FYE: December 31, 2024 · Year of Change: 1/1/2024
A4: Building 13 — Attachment to Form 3115 (DCN #7, Rev. Proc. 2024-23 §6.01)
A5: Source: CSSI Report #107752-39, "Silver Springs Housing LP_#107752-39_3115_Combined R1.pdf"
A7: CALCULATION OF §481(a) ADJUSTMENT — REGULAR TAX
A8: As Previously Filed
A9: Asset | B9: Property Description | C9: Date In Service | D9: Cost | E9: Sec 179 Exp | F9: Bonus Amt | G9: Tax Prior Depreciation | H9: Tax Current Depreciation | I9: End Depreciation | J9: Net Book Value | K9: Method | L9: Period
A10: 1 | B10: 19 - Building - 754 "Menowitz" | C10: 9/15/21 | D10: 479.53 | E10: 0 | F10: 0 | G10: 29.03 | H10: 11.97 | I10: =G10+H10 -> 41 | J10: =D10-I10 -> 438.53 | K10: S/L | L10: 40.00
A11: 2 | B11: 3 - Building | C11: 5/31/17 | D11: 142694.3 | E11: 0 | F11: 0 | G11: 30709.29 | H11: 3355.37 | I11: =G11+H11 -> 34064.66 | J11: =D11-I11 -> 108629.64 | K11: S/L | L11: 40.00
A12: 3 | B12: 4 - Personal Property | C12: 5/31/17 | D12: 8865.4 | E12: 0 | F12: 0 | G12: 8274.39 | H12: 0 | I12: =G12+H12 -> 8274.39 | J12: =D12-I12 -> 591.01 | K12: S/L | L12: 40.00
A13: 4 | B13: 2 - Land Improvements | C13: 5/31/17 | D13: 17730.79 | E13: 0 | F13: 0 | G13: 8532.2 | H13: 1046.12 | I13: =G13+H13 -> 9578.32 | J13: =D13-I13 -> 8152.47 | K13: S/L | L13: 40.00
B14: Grand Total | D14: =SUM(D10:D13) -> 169770.02 | E14: =SUM(E10:E13) -> 0 | F14: =SUM(F10:F13) -> 0 | G14: =SUM(G10:G13) -> 47544.91 | H14: =SUM(H10:H13) -> 4413.46 | I14: =SUM(I10:I13) -> 51958.37 | J14: =SUM(J10:J13) -> 117811.65
A16: After Cost Segregation Correction
A17: Asset | B17: Property Description | C17: Date In Service | D17: Cost | E17: Sec 179 Exp | F17: Bonus Amt | G17: Tax Prior Depreciation | H17: Tax Current Depreciation | I17: End Depreciation | J17: Net Book Value | K17: Method | L17: Period
A18: 1 | B18: 19 - Building - 754 "Menowitz" - 5 year | C18: 9/15/21 | D18: 89.94 | E18: 0 | F18: 89.94 | G18: 89.94 | H18: 0 | I18: =G18+H18 -> 89.94 | J18: =D18-I18 -> 0 | K18: 200DB | L18: 5.0
A19: 2 | B19: 19 - Building - 754 "Menowitz" - 30 year | C19: 9/15/21 | D19: 389.59 | E19: 0 | F19: 0 | G19: 29.77 | H19: 12.99 | I19: =G19+H19 -> 42.76 | J19: =D19-I19 -> 346.83 | K19: S/L | L19: 30.00
A20: 3 | B20: 3 - Building - 5 year | C20: 5/31/17 | D20: 26763.65 | E20: 0 | F20: 0 | G20: 26763.65 | H20: 0 | I20: =G20+H20 -> 26763.65 | J20: =D20-I20 -> 0 | K20: 200DB | L20: 5.0
A21: 4 | B21: 3 - Building - 30 year | C21: 5/31/17 | D21: 115930.65 | E21: 0 | F21: 0 | G21: 25601.32 | H21: 3864.35 | I21: =G21+H21 -> 29465.67 | J21: =D21-I21 -> 86464.98 | K21: S/L | L21: 30.00
A22: 5 | B22: 4 - Personal Property - 5 year | C22: 5/31/17 | D22: 1662.79 | E22: 0 | F22: 0 | G22: 1662.79 | H22: 0 | I22: =G22+H22 -> 1662.79 | J22: =D22-I22 -> 0 | K22: 200DB | L22: 5.0
A23: 6 | B23: 4 - Personal Property - 30 year | C23: 5/31/17 | D23: 7202.61 | E23: 0 | F23: 0 | G23: 1590.59 | H23: 240.09 | I23: =G23+H23 -> 1830.68 | J23: =D23-I23 -> 5371.93 | K23: S/L | L23: 30.00
A24: 7 | B24: 2 - Land Improvements - 5 year | C24: 5/31/17 | D24: 3325.57 | E24: 0 | F24: 0 | G24: 3325.57 | H24: 0 | I24: =G24+H24 -> 3325.57 | J24: =D24-I24 -> 0 | K24: 200DB | L24: 5.0
A25: 8 | B25: 2 - Land Improvements - 30 year | C25: 5/31/17 | D25: 14405.22 | E25: 0 | F25: 0 | G25: 3181.13 | H25: 480.17 | I25: =G25+H25 -> 3661.3 | J25: =D25-I25 -> 10743.92 | K25: S/L | L25: 30.00
B26: Grand Total | D26: =SUM(D18:D25) -> 169770.02 | E26: =SUM(E18:E25) -> 0 | F26: =SUM(F18:F25) -> 89.94 | G26: =SUM(G18:G25) -> 62244.76 | H26: =SUM(H18:H25) -> 4597.6 | I26: =SUM(I18:I25) -> 66842.36 | J26: =SUM(J18:J25) -> 102927.66
B28: Section 481(a) Adjustment — Regular Tax
B29: Depreciation reported previously | D29: =I14 -> 51958.37
B30: Cost Segregation Corrected Depreciation | D30: =I26 -> 66842.36
B31: Section 481(a) Adjustment — Regular Tax | D31: =D29-D30 -> -14883.99
A33: CALCULATION OF §481(a) ADJUSTMENT — AMT
A34: As Previously Filed — AMT
A35: Asset | B35: Property Description | C35: Date In Service | D35: Cost | E35: Sec 179 Exp | F35: Bonus Amt | G35: AMT Prior Depreciation | H35: AMT Current Depreciation | I35: End Depreciation | J35: Net Book Value | K35: Method | L35: Period
A36: 1 | B36: 19 - Building - 754 "Menowitz" | C36: 9/15/21 | D36: 479.53 | E36: 0 | F36: 0 | G36: 29.03 | H36: 11.97 | I36: =G36+H36 -> 41 | J36: =D36-I36 -> 438.53 | K36: S/L | L36: 40.00
A37: 2 | B37: 3 - Building | C37: 5/31/17 | D37: 142694.3 | E37: 0 | F37: 0 | G37: 30709.29 | H37: 3355.37 | I37: =G37+H37 -> 34064.66 | J37: =D37-I37 -> 108629.64 | K37: S/L | L37: 40.00
A38: 3 | B38: 4 - Personal Property | C38: 5/31/17 | D38: 8865.4 | E38: 0 | F38: 0 | G38: 8274.39 | H38: 0 | I38: =G38+H38 -> 8274.39 | J38: =D38-I38 -> 591.01 | K38: S/L | L38: 40.00
A39: 4 | B39: 2 - Land Improvements | C39: 5/31/17 | D39: 17730.79 | E39: 0 | F39: 0 | G39: 8532.2 | H39: 1046.12 | I39: =G39+H39 -> 9578.32 | J39: =D39-I39 -> 8152.47 | K39: S/L | L39: 40.00
B40: Grand Total | D40: =SUM(D36:D39) -> 169770.02 | E40: =SUM(E36:E39) -> 0 | F40: =SUM(F36:F39) -> 0 | G40: =SUM(G36:G39) -> 47544.91 | H40: =SUM(H36:H39) -> 4413.46 | I40: =SUM(I36:I39) -> 51958.37 | J40: =SUM(J36:J39) -> 117811.65
A42: After Cost Segregation Correction — AMT
A43: Asset | B43: Property Description | C43: Date In Service | D43: Cost | E43: Sec 179 Exp | F43: Bonus Amt | G43: AMT Prior Depreciation | H43: AMT Current Depreciation | I43: End Depreciation | J43: Net Book Value | K43: Method | L43: Period
A44: 1 | B44: 19 - Building - 754 "Menowitz" - 5 year | C44: 9/15/21 | D44: 89.94 | E44: 0 | F44: 89.94 | G44: 89.94 | H44: 0 | I44: =G44+H44 -> 89.94 | J44: =D44-I44 -> 0 | K44: 200DB | L44: 5.0
A45: 2 | B45: 19 - Building - 754 "Menowitz" - 30 year | C45: 9/15/21 | D45: 389.59 | E45: 0 | F45: 0 | G45: 29.77 | H45: 12.99 | I45: =G45+H45 -> 42.76 | J45: =D45-I45 -> 346.83 | K45: S/L | L45: 30.00
A46: 3 | B46: 3 - Building - 5 year | C46: 5/31/17 | D46: 26763.65 | E46: 0 | F46: 0 | G46: 26763.65 | H46: 0 | I46: =G46+H46 -> 26763.65 | J46: =D46-I46 -> 0 | K46: 200DB | L46: 5.0
A47: 4 | B47: 3 - Building - 30 year | C47: 5/31/17 | D47: 115930.65 | E47: 0 | F47: 0 | G47: 25601.32 | H47: 3864.35 | I47: =G47+H47 -> 29465.67 | J47: =D47-I47 -> 86464.98 | K47: S/L | L47: 30.00
A48: 5 | B48: 4 - Personal Property - 5 year | C48: 5/31/17 | D48: 1662.79 | E48: 0 | F48: 0 | G48: 1662.79 | H48: 0 | I48: =G48+H48 -> 1662.79 | J48: =D48-I48 -> 0 | K48: 200DB | L48: 5.0
A49: 6 | B49: 4 - Personal Property - 30 year | C49: 5/31/17 | D49: 7202.61 | E49: 0 | F49: 0 | G49: 1590.59 | H49: 240.09 | I49: =G49+H49 -> 1830.68 | J49: =D49-I49 -> 5371.93 | K49: S/L | L49: 30.00
A50: 7 | B50: 2 - Land Improvements - 5 year | C50: 5/31/17 | D50: 3325.57 | E50: 0 | F50: 0 | G50: 3325.57 | H50: 0 | I50: =G50+H50 -> 3325.57 | J50: =D50-I50 -> 0 | K50: 200DB | L50: 5.0
A51: 8 | B51: 2 - Land Improvements - 30 year | C51: 5/31/17 | D51: 14405.22 | E51: 0 | F51: 0 | G51: 3181.13 | H51: 480.17 | I51: =G51+H51 -> 3661.3 | J51: =D51-I51 -> 10743.92 | K51: S/L | L51: 30.00
B52: Grand Total | D52: =SUM(D44:D51) -> 169770.02 | E52: =SUM(E44:E51) -> 0 | F52: =SUM(F44:F51) -> 89.94 | G52: =SUM(G44:G51) -> 62244.76 | H52: =SUM(H44:H51) -> 4597.6 | I52: =SUM(I44:I51) -> 66842.36 | J52: =SUM(J44:J51) -> 102927.66
B54: Section 481(a) Adjustment — AMT
B55: Depreciation reported previously | D55: =I40 -> 51958.37
B56: Cost Segregation Corrected Depreciation | D56: =I52 -> 66842.36
B57: Section 481(a) Adjustment — AMT | D57: =D55-D56 -> -14883.99
A59: COST SEGREGATION STUDY — COST SUMMARY
B60: Total Building Cost | D60: =D98 -> 169770.02
B61: Building Components: 5 Year | D61: =F98 -> 31841.95
B62: % of Building Cost | D62: =F99 -> 0.18755932
B63: Building Structure: 30 Year | D63: =H98 -> 137928.07
B64: % of Building Cost | D64: =H99 -> 0.81244068
A66: COST SEGREGATION STUDY — COST DETAIL
B67: Property Category | D67: Cost | F67: 5 Year | H67: 30 Year
B68: Building Components
B69: Cabinets / Millwork | D69: =SUM(F69:H69) -> 7800.47 | F69: 7800.47
B70: Moldings | D70: =SUM(F70:H70) -> 3748.91 | F70: 3748.91
B71: Flooring - Vinyl Plank | D71: =SUM(F71:H71) -> 12139.37 | F71: 12139.37
B72: Window Treatments | D72: =SUM(F72:H72) -> 1142.58 | F72: 1142.58
B73: Building Signage | D73: =SUM(F73:H73) -> 85.24 | F73: 85.24
B74: Specialty Electrical - Appliances | D74: =SUM(F74:H74) -> 1274.42 | F74: 1274.42
B75: Communication / Data | D75: =SUM(F75:H75) -> 1052.34 | F75: 1052.34
B76: Specialty Plumbing - Kitchen Sinks | D76: =SUM(F76:H76) -> 2313.24 | F76: 2313.24
B77: Security / Exterior Lighting | D77: =SUM(F77:H77) -> 252.07 | F77: 252.07
B78: Access Control | D78: =SUM(F78:H78) -> 37.76 | F78: 37.76
B79: Appliances | D79: =SUM(F79:H79) -> 1995.55 | F79: 1995.55
B80: Building Structure
B81: Roofing Systems | D81: =SUM(F81:H81) -> 5090 | H81: 5090
B82: Foundations | D82: =SUM(F82:H82) -> 8538.11 | H82: 8538.11
B83: HVAC | D83: =SUM(F83:H83) -> 11754.94 | H83: 11754.94
B84: Electrical | D84: =SUM(F84:H84) -> 11527.95 | H84: 11527.95
B85: Plumbing | D85: =SUM(F85:H85) -> 10218.5 | H85: 10218.5
B86: Fire Protection & Alarm | D86: =SUM(F86:H86) -> 775.83 | H86: 775.83
B87: Exterior Façade / Building Skin | D87: =SUM(F87:H87) -> 22829.89 | H87: 22829.89
B88: Doors & Frames | D88: =SUM(F88:H88) -> 5886.42 | H88: 5886.42
B89: Windows | D89: =SUM(F89:H89) -> 5036.01 | H89: 5036.01
B90: Ceiling Systems | D90: =SUM(F90:H90) -> 5406.4 | H90: 5406.4
B91: Interior Framing / Partitions | D91: =SUM(F91:H91) -> 16464.28 | H91: 16464.28
B92: Painting | D92: =SUM(F92:H92) -> 5938.8 | H92: 5938.8
... B97: Cabinets / Millwork - Restrooms | D97: =SUM(F97:H97) -> 901.51 | H97: 901.51
B98: Total Building Cost | D98: =SUM(D69:D97) -> 169770.02 | F98: =SUM(F69:F79) -> 31841.95 | H98: =SUM(H81:H97) -> 137928.07
B99: % of Building Cost | F99: =F98/D98 -> 0.18755932 | H99: =H98/D98 -> 0.81244068
A101: ASSET ALLOCATION
B102: Asset | D102: Cost | F102: 5 Year | H102: 30 Year
B103: Asset # 19 - Building - 754 "Menowitz" | D103: =F103+H103 -> 479.53 | F103: 89.94 | H103: 389.59
B104: Asset # 3 - Building | D104: =F104+H104 -> 142694.3 | F104: 26763.65 | H104: 115930.65
B105: Asset # 4 - Personal Property | D105: =F105+H105 -> 8865.4 | F105: 1662.79 | H105: 7202.61
B106: Asset # 2 - Land Improvements | D106: =F106+H106 -> 17730.79 | F106: 3325.57 | H106: 14405.22
B107: Total Allocation | D107: =SUM(D103:D106) -> 169770.02 | F107: =SUM(F103:F106) -> 31841.95 | H107: =SUM(H103:H106) -> 137928.07
B108: Check: Allocation vs. Cost Detail (should be zero) | D108: =D107-D98 -> 0

Sheet Building 14
A1: Silver Springs Housing, LP
A2: Silver Spring Terrace Apartments — 950 20th St NE, Hickory, NC 28601
A3: EIN: 82-0773652 · FYE: December 31, 2024 · Year of Change: 1/1/2024
A4: Building 14 — Attachment to Form 3115 (DCN #7, Rev. Proc. 2024-23 §6.01)
A5: Source: CSSI Report #107752-39, "Silver Springs Housing LP_#107752-39_3115_Combined R1.pdf"
A7: CALCULATION OF §481(a) ADJUSTMENT — REGULAR TAX
A8: As Previously Filed
A9: Asset | B9: Property Description | C9: Date In Service | D9: Cost | E9: Sec 179 Exp | F9: Bonus Amt | G9: Tax Prior Depreciation | H9: Tax Current Depreciation | I9: End Depreciation | J9: Net Book Value | K9: Method | L9: Period
A10: 1 | B10: 19 - Building - 754 "Menowitz" | C10: 9/15/21 | D10: 407.79 | E10: 0 | F10: 0 | G10: 24.69 | H10: 10.18 | I10: =G10+H10 -> 34.87 | J10: =D10-I10 -> 372.92 | K10: S/L | L10: 40.00
A11: 2 | B11: 3 - Building | C11: 5/31/17 | D11: 121347 | E11: 0 | F11: 0 | G11: 26115.13 | H11: 2853.41 | I11: =G11+H11 -> 28968.54 | J11: =D11-I11 -> 92378.46 | K11: S/L | L11: 40.00
A12: 3 | B12: 4 - Personal Property | C12: 5/31/17 | D12: 7539.11 | E12: 0 | F12: 0 | G12: 7036.52 | H12: 0 | I12: =G12+H12 -> 7036.52 | J12: =D12-I12 -> 502.59 | K12: S/L | L12: 40.00
A13: 4 | B13: 2 - Land Improvements | C13: 5/31/17 | D13: 15078.24 | E13: 0 | F13: 0 | G13: 7255.76 | H13: 889.62 | I13: =G13+H13 -> 8145.38 | J13: =D13-I13 -> 6932.86 | K13: S/L | L13: 40.00
B14: Grand Total | D14: =SUM(D10:D13) -> 144372.14 | E14: =SUM(E10:E13) -> 0 | F14: =SUM(F10:F13) -> 0 | G14: =SUM(G10:G13) -> 40432.1 | H14: =SUM(H10:H13) -> 3753.21 | I14: =SUM(I10:I13) -> 44185.31 | J14: =SUM(J10:J13) -> 100186.83
A16: After Cost Segregation Correction
A17: Asset | B17: Property Description | C17: Date In Service | D17: Cost | E17: Sec 179 Exp | F17: Bonus Amt | G17: Tax Prior Depreciation | H17: Tax Current Depreciation | I17: End Depreciation | J17: Net Book Value | K17: Method | L17: Period
A18: 1 | B18: 19 - Building - 754 "Menowitz" - 5 year | C18: 9/15/21 | D18: 77.21 | E18: 0 | F18: 77.21 | G18: 77.21 | H18: 0 | I18: =G18+H18 -> 77.21 | J18: =D18-I18 -> 0 | K18: 200DB | L18: 5.0
A19: 2 | B19: 19 - Building - 754 "Menowitz" - 30 year | C19: 9/15/21 | D19: 330.58 | E19: 0 | F19: 0 | G19: 25.25 | H19: 11.02 | I19: =G19+H19 -> 36.27 | J19: =D19-I19 -> 294.31 | K19: S/L | L19: 30.00
A20: 3 | B20: 3 - Building - 5 year | C20: 5/31/17 | D20: 22974.45 | E20: 0 | F20: 0 | G20: 22974.45 | H20: 0 | I20: =G20+H20 -> 22974.45 | J20: =D20-I20 -> 0 | K20: 200DB | L20: 5.0
A21: 4 | B21: 3 - Building - 30 year | C21: 5/31/17 | D21: 98372.55 | E21: 0 | F21: 0 | G21: 21723.97 | H21: 3279.09 | I21: =G21+H21 -> 25003.06 | J21: =D21-I21 -> 73369.49 | K21: S/L | L21: 30.00
A22: 5 | B22: 4 - Personal Property - 5 year | C22: 5/31/17 | D22: 1427.37 | E22: 0 | F22: 0 | G22: 1427.37 | H22: 0 | I22: =G22+H22 -> 1427.37 | J22: =D22-I22 -> 0 | K22: 200DB | L22: 5.0
A23: 6 | B23: 4 - Personal Property - 30 year | C23: 5/31/17 | D23: 6111.74 | E23: 0 | F23: 0 | G23: 1349.65 | H23: 203.72 | I23: =G23+H23 -> 1553.37 | J23: =D23-I23 -> 4558.37 | K23: S/L | L23: 30.00
A24: 7 | B24: 2 - Land Improvements - 5 year | C24: 5/31/17 | D24: 2854.74 | E24: 0 | F24: 0 | G24: 2854.74 | H24: 0 | I24: =G24+H24 -> 2854.74 | J24: =D24-I24 -> 0 | K24: 200DB | L24: 5.0
A25: 8 | B25: 2 - Land Improvements - 30 year | C25: 5/31/17 | D25: 12223.5 | E25: 0 | F25: 0 | G25: 2699.36 | H25: 407.45 | I25: =G25+H25 -> 3106.81 | J25: =D25-I25 -> 9116.69 | K25: S/L | L25: 30.00
B26: Grand Total | D26: =SUM(D18:D25) -> 144372.14 | E26: =SUM(E18:E25) -> 0 | F26: =SUM(F18:F25) -> 77.21 | G26: =SUM(G18:G25) -> 53132 | H26: =SUM(H18:H25) -> 3901.28 | I26: =SUM(I18:I25) -> 57033.28 | J26: =SUM(J18:J25) -> 87338.86
B28: Section 481(a) Adjustment — Regular Tax
B29: Depreciation reported previously | D29: =I14 -> 44185.31
B30: Cost Segregation Corrected Depreciation | D30: =I26 -> 57033.28
B31: Section 481(a) Adjustment — Regular Tax | D31: =D29-D30 -> -12847.97
A33: CALCULATION OF §481(a) ADJUSTMENT — AMT
A34: As Previously Filed — AMT
A35: Asset | B35: Property Description | C35: Date In Service | D35: Cost | E35: Sec 179 Exp | F35: Bonus Amt | G35: AMT Prior Depreciation | H35: AMT Current Depreciation | I35: End Depreciation | J35: Net Book Value | K35: Method | L35: Period
A36: 1 | B36: 19 - Building - 754 "Menowitz" | C36: 9/15/21 | D36: 407.79 | E36: 0 | F36: 0 | G36: 24.69 | H36: 10.18 | I36: =G36+H36 -> 34.87 | J36: =D36-I36 -> 372.92 | K36: S/L | L36: 40.00
A37: 2 | B37: 3 - Building | C37: 5/31/17 | D37: 121347 | E37: 0 | F37: 0 | G37: 26115.13 | H37: 2853.41 | I37: =G37+H37 -> 28968.54 | J37: =D37-I37 -> 92378.46 | K37: S/L | L37: 40.00
A38: 3 | B38: 4 - Personal Property | C38: 5/31/17 | D38: 7539.11 | E38: 0 | F38: 0 | G38: 7036.52 | H38: 0 | I38: =G38+H38 -> 7036.52 | J38: =D38-I38 -> 502.59 | K38: S/L | L38: 40.00
A39: 4 | B39: 2 - Land Improvements | C39: 5/31/17 | D39: 15078.24 | E39: 0 | F39: 0 | G39: 7255.76 | H39: 889.62 | I39: =G39+H39 -> 8145.38 | J39: =D39-I39 -> 6932.86 | K39: S/L | L39: 40.00
B40: Grand Total | D40: =SUM(D36:D39) -> 144372.14 | E40: =SUM(E36:E39) -> 0 | F40: =SUM(F36:F39) -> 0 | G40: =SUM(G36:G39) -> 40432.1 | H40: =SUM(H36:H39) -> 3753.21 | I40: =SUM(I36:I39) -> 44185.31 | J40: =SUM(J36:J39) -> 100186.83
A42: After Cost Segregation Correction — AMT
A43: Asset | B43: Property Description | C43: Date In Service | D43: Cost | E43: Sec 179 Exp | F43: Bonus Amt | G43: AMT Prior Depreciation | H43: AMT Current Depreciation | I43: End Depreciation | J43: Net Book Value | K43: Method | L43: Period
A44: 1 | B44: 19 - Building - 754 "Menowitz" - 5 year | C44: 9/15/21 | D44: 77.21 | E44: 0 | F44: 77.21 | G44: 77.21 | H44: 0 | I44: =G44+H44 -> 77.21 | J44: =D44-I44 -> 0 | K44: 200DB | L44: 5.0
A45: 2 | B45: 19 - Building - 754 "Menowitz" - 30 year | C45: 9/15/21 | D45: 330.58 | E45: 0 | F45: 0 | G45: 25.25 | H45: 11.02 | I45: =G45+H45 -> 36.27 | J45: =D45-I45 -> 294.31 | K45: S/L | L45: 30.00
A46: 3 | B46: 3 - Building - 5 year | C46: 5/31/17 | D46: 22974.45 | E46: 0 | F46: 0 | G46: 22974.45 | H46: 0 | I46: =G46+H46 -> 22974.45 | J46: =D46-I46 -> 0 | K46: 200DB | L46: 5.0
A47: 4 | B47: 3 - Building - 30 year | C47: 5/31/17 | D47: 98372.55 | E47: 0 | F47: 0 | G47: 21723.97 | H47: 3279.09 | I47: =G47+H47 -> 25003.06 | J47: =D47-I47 -> 73369.49 | K47: S/L | L47: 30.00
A48: 5 | B48: 4 - Personal Property - 5 year | C48: 5/31/17 | D48: 1427.37 | E48: 0 | F48: 0 | G48: 1427.37 | H48: 0 | I48: =G48+H48 -> 1427.37 | J48: =D48-I48 -> 0 | K48: 200DB | L48: 5.0
A49: 6 | B49: 4 - Personal Property - 30 year | C49: 5/31/17 | D49: 6111.74 | E49: 0 | F49: 0 | G49: 1349.65 | H49: 203.72 | I49: =G49+H49 -> 1553.37 | J49: =D49-I49 -> 4558.37 | K49: S/L | L49: 30.00
A50: 7 | B50: 2 - Land Improvements - 5 year | C50: 5/31/17 | D50: 2854.74 | E50: 0 | F50: 0 | G50: 2854.74 | H50: 0 | I50: =G50+H50 -> 2854.74 | J50: =D50-I50 -> 0 | K50: 200DB | L50: 5.0
A51: 8 | B51: 2 - Land Improvements - 30 year | C51: 5/31/17 | D51: 12223.5 | E51: 0 | F51: 0 | G51: 2699.36 | H51: 407.45 | I51: =G51+H51 -> 3106.81 | J51: =D51-I51 -> 9116.69 | K51: S/L | L51: 30.00
B52: Grand Total | D52: =SUM(D44:D51) -> 144372.14 | E52: =SUM(E44:E51) -> 0 | F52: =SUM(F44:F51) -> 77.21 | G52: =SUM(G44:G51) -> 53132 | H52: =SUM(H44:H51) -> 3901.28 | I52: =SUM(I44:I51) -> 57033.28 | J52: =SUM(J44:J51) -> 87338.86
B54: Section 481(a) Adjustment — AMT
B55: Depreciation reported previously | D55: =I40 -> 44185.31
B56: Cost Segregation Corrected Depreciation | D56: =I52 -> 57033.28
B57: Section 481(a) Adjustment — AMT | D57: =D55-D56 -> -12847.97
A59: COST SEGREGATION STUDY — COST SUMMARY
B60: Total Building Cost | D60: =D98 -> 144372.14
B61: Building Components: 5 Year | D61: =F98 -> 27333.77
B62: % of Building Cost | D62: =F99 -> 0.18932856
B63: Building Structure: 30 Year | D63: =H98 -> 117038.37
B64: % of Building Cost | D64: =H99 -> 0.81067144
A66: COST SEGREGATION STUDY — COST DETAIL
B67: Property Category | D67: Cost | F67: 5 Year | H67: 30 Year
B68: Building Components
B69: Cabinets / Millwork | D69: =SUM(F69:H69) -> 6312.84 | F69: 6312.84
B70: Moldings | D70: =SUM(F70:H70) -> 3318.29 | F70: 3318.29
B71: Flooring - Vinyl Plank | D71: =SUM(F71:H71) -> 9989.69 | F71: 9989.69
B72: Window Treatments | D72: =SUM(F72:H72) -> 888.68 | F72: 888.68
B73: Building Signage | D73: =SUM(F73:H73) -> 85.24 | F73: 85.24
B74: Specialty Electrical - Appliances | D74: =SUM(F74:H74) -> 1274.42 | F74: 1274.42
B75: Communication / Data | D75: =SUM(F75:H75) -> 865.99 | F75: 865.99
B76: Specialty Plumbing - Kitchen Sinks | D76: =SUM(F76:H76) -> 2313.24 | F76: 2313.24
B77: Security / Exterior Lighting | D77: =SUM(F77:H77) -> 252.07 | F77: 252.07
B78: Access Control | D78: =SUM(F78:H78) -> 37.76 | F78: 37.76
B79: Appliances | D79: =SUM(F79:H79) -> 1995.55 | F79: 1995.55
B80: Building Structure
B81: Roofing Systems | D81: =SUM(F81:H81) -> 4400.88 | H81: 4400.88
B82: Foundations | D82: =SUM(F82:H82) -> 7119.64 | H82: 7119.64
B83: HVAC | D83: =SUM(F83:H83) -> 9673.34 | H83: 9673.34
B84: Electrical | D84: =SUM(F84:H84) -> 9260.86 | H84: 9260.86
B85: Plumbing | D85: =SUM(F85:H85) -> 8408.98 | H85: 8408.98
B86: Fire Protection & Alarm | D86: =SUM(F86:H86) -> 553.55 | H86: 553.55
B87: Exterior Façade / Building Skin | D87: =SUM(F87:H87) -> 20503.5 | H87: 20503.5
B88: Doors & Frames | D88: =SUM(F88:H88) -> 5245.53 | H88: 5245.53
B89: Windows | D89: =SUM(F89:H89) -> 3916.9 | H89: 3916.9
B90: Ceiling Systems | D90: =SUM(F90:H90) -> 4449.02 | H90: 4449.02
B91: Interior Framing / Partitions | D91: =SUM(F91:H91) -> 14615.82 | H91: 14615.82
B92: Painting | D92: =SUM(F92:H92) -> 5177.37 | H92: 5177.37
... B97: Cabinets / Millwork - Restrooms | D97: =SUM(F97:H97) -> 450.76 | H97: 450.76
B98: Total Building Cost | D98: =SUM(D69:D97) -> 144372.14 | F98: =SUM(F69:F79) -> 27333.77 | H98: =SUM(H81:H97) -> 117038.37
B99: % of Building Cost | F99: =F98/D98 -> 0.18932856 | H99: =H98/D98 -> 0.81067144
A101: ASSET ALLOCATION
B102: Asset | D102: Cost | F102: 5 Year | H102: 30 Year
B103: Asset # 19 - Building - 754 "Menowitz" | D103: =F103+H103 -> 407.79 | F103: 77.21 | H103: 330.58
B104: Asset # 3 - Building | D104: =F104+H104 -> 121347 | F104: 22974.45 | H104: 98372.55
B105: Asset # 4 - Personal Property | D105: =F105+H105 -> 7539.11 | F105: 1427.37 | H105: 6111.74
B106: Asset # 2 - Land Improvements | D106: =F106+H106 -> 15078.24 | F106: 2854.74 | H106: 12223.5
B107: Total Allocation | D107: =SUM(D103:D106) -> 144372.14 | F107: =SUM(F103:F106) -> 27333.77 | H107: =SUM(H103:H106) -> 117038.37
B108: Check: Allocation vs. Cost Detail (should be zero) | D108: =D107-D98 -> 0

Sheet Building 15
A1: Silver Springs Housing, LP
A2: Silver Spring Terrace Apartments — 950 20th St NE, Hickory, NC 28601
A3: EIN: 82-0773652 · FYE: December 31, 2024 · Year of Change: 1/1/2024
A4: Building 15 — Attachment to Form 3115 (DCN #7, Rev. Proc. 2024-23 §6.01)
A5: Source: CSSI Report #107752-39, "Silver Springs Housing LP_#107752-39_3115_Combined R1.pdf"
A7: CALCULATION OF §481(a) ADJUSTMENT — REGULAR TAX
A8: As Previously Filed
A9: Asset | B9: Property Description | C9: Date In Service | D9: Cost | E9: Sec 179 Exp | F9: Bonus Amt | G9: Tax Prior Depreciation | H9: Tax Current Depreciation | I9: End Depreciation | J9: Net Book Value | K9: Method | L9: Period
A10: 1 | B10: 19 - Building - 754 "Menowitz" | C10: 9/15/21 | D10: 316.3 | E10: 0 | F10: 0 | G10: 19.15 | H10: 7.89 | I10: =G10+H10 -> 27.04 | J10: =D10-I10 -> 289.26 | K10: S/L | L10: 40.00
A11: 2 | B11: 3 - Building | C11: 5/31/17 | D11: 94123.92 | E11: 0 | F11: 0 | G11: 20256.43 | H11: 2213.27 | I11: =G11+H11 -> 22469.7 | J11: =D11-I11 -> 71654.22 | K11: S/L | L11: 40.00
A12: 3 | B12: 4 - Personal Property | C12: 5/31/17 | D12: 5847.79 | E12: 0 | F12: 0 | G12: 5457.95 | H12: 0 | I12: =G12+H12 -> 5457.95 | J12: =D12-I12 -> 389.84 | K12: S/L | L12: 40.00
A13: 4 | B13: 2 - Land Improvements | C13: 5/31/17 | D13: 11695.57 | E13: 0 | F13: 0 | G13: 5628.01 | H13: 690.03 | I13: =G13+H13 -> 6318.04 | J13: =D13-I13 -> 5377.53 | K13: S/L | L13: 40.00
B14: Grand Total | D14: =SUM(D10:D13) -> 111983.58 | E14: =SUM(E10:E13) -> 0 | F14: =SUM(F10:F13) -> 0 | G14: =SUM(G10:G13) -> 31361.54 | H14: =SUM(H10:H13) -> 2911.19 | I14: =SUM(I10:I13) -> 34272.73 | J14: =SUM(J10:J13) -> 77710.85
A16: After Cost Segregation Correction
A17: Asset | B17: Property Description | C17: Date In Service | D17: Cost | E17: Sec 179 Exp | F17: Bonus Amt | G17: Tax Prior Depreciation | H17: Tax Current Depreciation | I17: End Depreciation | J17: Net Book Value | K17: Method | L17: Period
A18: 1 | B18: 19 - Building - 754 "Menowitz" - 5 year | C18: 9/15/21 | D18: 63.33 | E18: 0 | F18: 63.33 | G18: 63.33 | H18: 0 | I18: =G18+H18 -> 63.33 | J18: =D18-I18 -> 0 | K18: 200DB | L18: 5.0
A19: 2 | B19: 19 - Building - 754 "Menowitz" - 30 year | C19: 9/15/21 | D19: 252.97 | E19: 0 | F19: 0 | G19: 19.32 | H19: 8.43 | I19: =G19+H19 -> 27.75 | J19: =D19-I19 -> 225.22 | K19: S/L | L19: 30.00
A20: 3 | B20: 3 - Building - 5 year | C20: 5/31/17 | D20: 18845.76 | E20: 0 | F20: 0 | G20: 18845.76 | H20: 0 | I20: =G20+H20 -> 18845.76 | J20: =D20-I20 -> 0 | K20: 200DB | L20: 5.0
A21: 4 | B21: 3 - Building - 30 year | C21: 5/31/17 | D21: 75278.16 | E21: 0 | F21: 0 | G21: 16623.92 | H21: 2509.27 | I21: =G21+H21 -> 19133.19 | J21: =D21-I21 -> 56144.97 | K21: S/L | L21: 30.00
A22: 5 | B22: 4 - Personal Property - 5 year | C22: 5/31/17 | D22: 1170.86 | E22: 0 | F22: 0 | G22: 1170.86 | H22: 0 | I22: =G22+H22 -> 1170.86 | J22: =D22-I22 -> 0 | K22: 200DB | L22: 5.0
A23: 6 | B23: 4 - Personal Property - 30 year | C23: 5/31/17 | D23: 4676.93 | E23: 0 | F23: 0 | G23: 1032.84 | H23: 155.9 | I23: =G23+H23 -> 1188.74 | J23: =D23-I23 -> 3488.19 | K23: S/L | L23: 30.00
A24: 7 | B24: 2 - Land Improvements - 5 year | C24: 5/31/17 | D24: 2341.72 | E24: 0 | F24: 0 | G24: 2341.72 | H24: 0 | I24: =G24+H24 -> 2341.72 | J24: =D24-I24 -> 0 | K24: 200DB | L24: 5.0
A25: 8 | B25: 2 - Land Improvements - 30 year | C25: 5/31/17 | D25: 9353.85 | E25: 0 | F25: 0 | G25: 2065.67 | H25: 311.8 | I25: =G25+H25 -> 2377.47 | J25: =D25-I25 -> 6976.38 | K25: S/L | L25: 30.00
B26: Grand Total | D26: =SUM(D18:D25) -> 111983.58 | E26: =SUM(E18:E25) -> 0 | F26: =SUM(F18:F25) -> 63.33 | G26: =SUM(G18:G25) -> 42163.42 | H26: =SUM(H18:H25) -> 2985.4 | I26: =SUM(I18:I25) -> 45148.82 | J26: =SUM(J18:J25) -> 66834.76
B28: Section 481(a) Adjustment — Regular Tax
B29: Depreciation reported previously | D29: =I14 -> 34272.73
B30: Cost Segregation Corrected Depreciation | D30: =I26 -> 45148.82
B31: Section 481(a) Adjustment — Regular Tax | D31: =D29-D30 -> -10876.09
A33: CALCULATION OF §481(a) ADJUSTMENT — AMT
A34: As Previously Filed — AMT
A35: Asset | B35: Property Description | C35: Date In Service | D35: Cost | E35: Sec 179 Exp | F35: Bonus Amt | G35: AMT Prior Depreciation | H35: AMT Current Depreciation | I35: End Depreciation | J35: Net Book Value | K35: Method | L35: Period
A36: 1 | B36: 19 - Building - 754 "Menowitz" | C36: 9/15/21 | D36: 316.3 | E36: 0 | F36: 0 | G36: 19.15 | H36: 7.89 | I36: =G36+H36 -> 27.04 | J36: =D36-I36 -> 289.26 | K36: S/L | L36: 40.00
A37: 2 | B37: 3 - Building | C37: 5/31/17 | D37: 94123.92 | E37: 0 | F37: 0 | G37: 20256.43 | H37: 2213.27 | I37: =G37+H37 -> 22469.7 | J37: =D37-I37 -> 71654.22 | K37: S/L | L37: 40.00
A38: 3 | B38: 4 - Personal Property | C38: 5/31/17 | D38: 5847.79 | E38: 0 | F38: 0 | G38: 5457.95 | H38: 0 | I38: =G38+H38 -> 5457.95 | J38: =D38-I38 -> 389.84 | K38: S/L | L38: 40.00
A39: 4 | B39: 2 - Land Improvements | C39: 5/31/17 | D39: 11695.57 | E39: 0 | F39: 0 | G39: 5628.01 | H39: 690.03 | I39: =G39+H39 -> 6318.04 | J39: =D39-I39 -> 5377.53 | K39: S/L | L39: 40.00
B40: Grand Total | D40: =SUM(D36:D39) -> 111983.58 | E40: =SUM(E36:E39) -> 0 | F40: =SUM(F36:F39) -> 0 | G40: =SUM(G36:G39) -> 31361.54 | H40: =SUM(H36:H39) -> 2911.19 | I40: =SUM(I36:I39) -> 34272.73 | J40: =SUM(J36:J39) -> 77710.85
A42: After Cost Segregation Correction — AMT
A43: Asset | B43: Property Description | C43: Date In Service | D43: Cost | E43: Sec 179 Exp | F43: Bonus Amt | G43: AMT Prior Depreciation | H43: AMT Current Depreciation | I43: End Depreciation | J43: Net Book Value | K43: Method | L43: Period
A44: 1 | B44: 19 - Building - 754 "Menowitz" - 5 year | C44: 9/15/21 | D44: 63.33 | E44: 0 | F44: 63.33 | G44: 63.33 | H44: 0 | I44: =G44+H44 -> 63.33 | J44: =D44-I44 -> 0 | K44: 200DB | L44: 5.0
A45: 2 | B45: 19 - Building - 754 "Menowitz" - 30 year | C45: 9/15/21 | D45: 252.97 | E45: 0 | F45: 0 | G45: 19.32 | H45: 8.43 | I45: =G45+H45 -> 27.75 | J45: =D45-I45 -> 225.22 | K45: S/L | L45: 30.00
A46: 3 | B46: 3 - Building - 5 year | C46: 5/31/17 | D46: 18845.76 | E46: 0 | F46: 0 | G46: 18845.76 | H46: 0 | I46: =G46+H46 -> 18845.76 | J46: =D46-I46 -> 0 | K46: 200DB | L46: 5.0
A47: 4 | B47: 3 - Building - 30 year | C47: 5/31/17 | D47: 75278.16 | E47: 0 | F47: 0 | G47: 16623.92 | H47: 2509.27 | I47: =G47+H47 -> 19133.19 | J47: =D47-I47 -> 56144.97 | K47: S/L | L47: 30.00
A48: 5 | B48: 4 - Personal Property - 5 year | C48: 5/31/17 | D48: 1170.86 | E48: 0 | F48: 0 | G48: 1170.86 | H48: 0 | I48: =G48+H48 -> 1170.86 | J48: =D48-I48 -> 0 | K48: 200DB | L48: 5.0
A49: 6 | B49: 4 - Personal Property - 30 year | C49: 5/31/17 | D49: 4676.93 | E49: 0 | F49: 0 | G49: 1032.84 | H49: 155.9 | I49: =G49+H49 -> 1188.74 | J49: =D49-I49 -> 3488.19 | K49: S/L | L49: 30.00
A50: 7 | B50: 2 - Land Improvements - 5 year | C50: 5/31/17 | D50: 2341.72 | E50: 0 | F50: 0 | G50: 2341.72 | H50: 0 | I50: =G50+H50 -> 2341.72 | J50: =D50-I50 -> 0 | K50: 200DB | L50: 5.0
A51: 8 | B51: 2 - Land Improvements - 30 year | C51: 5/31/17 | D51: 9353.85 | E51: 0 | F51: 0 | G51: 2065.67 | H51: 311.8 | I51: =G51+H51 -> 2377.47 | J51: =D51-I51 -> 6976.38 | K51: S/L | L51: 30.00
B52: Grand Total | D52: =SUM(D44:D51) -> 111983.58 | E52: =SUM(E44:E51) -> 0 | F52: =SUM(F44:F51) -> 63.33 | G52: =SUM(G44:G51) -> 42163.42 | H52: =SUM(H44:H51) -> 2985.4 | I52: =SUM(I44:I51) -> 45148.82 | J52: =SUM(J44:J51) -> 66834.76
B54: Section 481(a) Adjustment — AMT
B55: Depreciation reported previously | D55: =I40 -> 34272.73
B56: Cost Segregation Corrected Depreciation | D56: =I52 -> 45148.82
B57: Section 481(a) Adjustment — AMT | D57: =D55-D56 -> -10876.09
A59: COST SEGREGATION STUDY — COST SUMMARY
B60: Total Building Cost | D60: =D98 -> 111983.58
B61: Building Components: 5 Year | D61: =F98 -> 22421.67
B62: % of Building Cost | D62: =F99 -> 0.20022284
B63: Building Structure: 30 Year | D63: =H98 -> 89561.91
B64: % of Building Cost | D64: =H99 -> 0.79977716
A66: COST SEGREGATION STUDY — COST DETAIL
B67: Property Category | D67: Cost | F67: 5 Year | H67: 30 Year
B68: Building Components
B69: Cabinets / Millwork | D69: =SUM(F69:H69) -> 5461.24 | F69: 5461.24
B70: Moldings | D70: =SUM(F70:H70) -> 2735.7 | F70: 2735.7
B71: Flooring - Vinyl Plank | D71: =SUM(F71:H71) -> 7081.3 | F71: 7081.3
B72: Window Treatments | D72: =SUM(F72:H72) -> 571.28 | F72: 571.28
B73: Building Signage | D73: =SUM(F73:H73) -> 85.24 | F73: 85.24
B74: Specialty Electrical - Appliances | D74: =SUM(F74:H74) -> 1274.42 | F74: 1274.42
B75: Communication / Data | D75: =SUM(F75:H75) -> 613.87 | F75: 613.87
B76: Specialty Plumbing - Kitchen Sinks | D76: =SUM(F76:H76) -> 2313.24 | F76: 2313.24
B77: Security / Exterior Lighting | D77: =SUM(F77:H77) -> 252.07 | F77: 252.07
B78: Access Control | D78: =SUM(F78:H78) -> 37.76 | F78: 37.76
B79: Appliances | D79: =SUM(F79:H79) -> 1995.55 | F79: 1995.55
B80: Building Structure
B81: Roofing Systems | D81: =SUM(F81:H81) -> 3371.24 | H81: 3371.24
B82: Foundations | D82: =SUM(F82:H82) -> 5200.56 | H82: 5200.56
B83: HVAC | D83: =SUM(F83:H83) -> 6857.05 | H83: 6857.05
B84: Electrical | D84: =SUM(F84:H84) -> 6193.63 | H84: 6193.63
B85: Plumbing | D85: =SUM(F85:H85) -> 5960.79 | H85: 5960.79
B86: Fire Protection & Alarm | D86: =SUM(F86:H86) -> 331.27 | H86: 331.27
B87: Exterior Façade / Building Skin | D87: =SUM(F87:H87) -> 17225.23 | H87: 17225.23
B88: Doors & Frames | D88: =SUM(F88:H88) -> 3322.88 | H88: 3322.88
B89: Windows | D89: =SUM(F89:H89) -> 2518.01 | H89: 2518.01
B90: Ceiling Systems | D90: =SUM(F90:H90) -> 3153.72 | H90: 3153.72
B91: Interior Framing / Partitions | D91: =SUM(F91:H91) -> 12103.51 | H91: 12103.51
B92: Painting | D92: =SUM(F92:H92) -> 4143.45 | H92: 4143.45
... B97: Cabinets / Millwork - Restrooms | D97: =SUM(F97:H97) -> 450.76 | H97: 450.76
B98: Total Building Cost | D98: =SUM(D69:D97) -> 111983.58 | F98: =SUM(F69:F79) -> 22421.67 | H98: =SUM(H81:H97) -> 89561.91
B99: % of Building Cost | F99: =F98/D98 -> 0.20022284 | H99: =H98/D98 -> 0.79977716
A101: ASSET ALLOCATION
B102: Asset | D102: Cost | F102: 5 Year | H102: 30 Year
B103: Asset # 19 - Building - 754 "Menowitz" | D103: =F103+H103 -> 316.3 | F103: 63.33 | H103: 252.97
B104: Asset # 3 - Building | D104: =F104+H104 -> 94123.92 | F104: 18845.76 | H104: 75278.16
B105: Asset # 4 - Personal Property | D105: =F105+H105 -> 5847.79 | F105: 1170.86 | H105: 4676.93
B106: Asset # 2 - Land Improvements | D106: =F106+H106 -> 11695.57 | F106: 2341.72 | H106: 9353.85
B107: Total Allocation | D107: =SUM(D103:D106) -> 111983.58 | F107: =SUM(F103:F106) -> 22421.67 | H107: =SUM(H103:H106) -> 89561.91
B108: Check: Allocation vs. Cost Detail (should be zero) | D108: =D107-D98 -> 0

Sheet Building 16
A1: Silver Springs Housing, LP
A2: Silver Spring Terrace Apartments — 950 20th St NE, Hickory, NC 28601
A3: EIN: 82-0773652 · FYE: December 31, 2024 · Year of Change: 1/1/2024
A4: Building 16 — Attachment to Form 3115 (DCN #7, Rev. Proc. 2024-23 §6.01)
A5: Source: CSSI Report #107752-39, "Silver Springs Housing LP_#107752-39_3115_Combined R1.pdf"
A7: CALCULATION OF §481(a) ADJUSTMENT — REGULAR TAX
A8: As Previously Filed
A9: Asset | B9: Property Description | C9: Date In Service | D9: Cost | E9: Sec 179 Exp | F9: Bonus Amt | G9: Tax Prior Depreciation | H9: Tax Current Depreciation | I9: End Depreciation | J9: Net Book Value | K9: Method | L9: Period
A10: 1 | B10: 19 - Building - 754 "Menowitz" | C10: 9/15/21 | D10: 316.3 | E10: 0 | F10: 0 | G10: 19.15 | H10: 7.89 | I10: =G10+H10 -> 27.04 | J10: =D10-I10 -> 289.26 | K10: S/L | L10: 40.00
A11: 2 | B11: 3 - Building | C11: 5/31/17 | D11: 94123.92 | E11: 0 | F11: 0 | G11: 20256.43 | H11: 2213.27 | I11: =G11+H11 -> 22469.7 | J11: =D11-I11 -> 71654.22 | K11: S/L | L11: 40.00
A12: 3 | B12: 4 - Personal Property | C12: 5/31/17 | D12: 5847.79 | E12: 0 | F12: 0 | G12: 5457.95 | H12: 0 | I12: =G12+H12 -> 5457.95 | J12: =D12-I12 -> 389.84 | K12: S/L | L12: 40.00
A13: 4 | B13: 2 - Land Improvements | C13: 5/31/17 | D13: 11695.57 | E13: 0 | F13: 0 | G13: 5628.01 | H13: 690.03 | I13: =G13+H13 -> 6318.04 | J13: =D13-I13 -> 5377.53 | K13: S/L | L13: 40.00
B14: Grand Total | D14: =SUM(D10:D13) -> 111983.58 | E14: =SUM(E10:E13) -> 0 | F14: =SUM(F10:F13) -> 0 | G14: =SUM(G10:G13) -> 31361.54 | H14: =SUM(H10:H13) -> 2911.19 | I14: =SUM(I10:I13) -> 34272.73 | J14: =SUM(J10:J13) -> 77710.85
A16: After Cost Segregation Correction
A17: Asset | B17: Property Description | C17: Date In Service | D17: Cost | E17: Sec 179 Exp | F17: Bonus Amt | G17: Tax Prior Depreciation | H17: Tax Current Depreciation | I17: End Depreciation | J17: Net Book Value | K17: Method | L17: Period
A18: 1 | B18: 19 - Building - 754 "Menowitz" - 5 year | C18: 9/15/21 | D18: 63.33 | E18: 0 | F18: 63.33 | G18: 63.33 | H18: 0 | I18: =G18+H18 -> 63.33 | J18: =D18-I18 -> 0 | K18: 200DB | L18: 5.0
A19: 2 | B19: 19 - Building - 754 "Menowitz" - 30 year | C19: 9/15/21 | D19: 252.97 | E19: 0 | F19: 0 | G19: 19.32 | H19: 8.43 | I19: =G19+H19 -> 27.75 | J19: =D19-I19 -> 225.22 | K19: S/L | L19: 30.00
A20: 3 | B20: 3 - Building - 5 year | C20: 5/31/17 | D20: 18845.76 | E20: 0 | F20: 0 | G20: 18845.76 | H20: 0 | I20: =G20+H20 -> 18845.76 | J20: =D20-I20 -> 0 | K20: 200DB | L20: 5.0
A21: 4 | B21: 3 - Building - 30 year | C21: 5/31/17 | D21: 75278.16 | E21: 0 | F21: 0 | G21: 16623.92 | H21: 2509.27 | I21: =G21+H21 -> 19133.19 | J21: =D21-I21 -> 56144.97 | K21: S/L | L21: 30.00
A22: 5 | B22: 4 - Personal Property - 5 year | C22: 5/31/17 | D22: 1170.86 | E22: 0 | F22: 0 | G22: 1170.86 | H22: 0 | I22: =G22+H22 -> 1170.86 | J22: =D22-I22 -> 0 | K22: 200DB | L22: 5.0
A23: 6 | B23: 4 - Personal Property - 30 year | C23: 5/31/17 | D23: 4676.93 | E23: 0 | F23: 0 | G23: 1032.84 | H23: 155.9 | I23: =G23+H23 -> 1188.74 | J23: =D23-I23 -> 3488.19 | K23: S/L | L23: 30.00
A24: 7 | B24: 2 - Land Improvements - 5 year | C24: 5/31/17 | D24: 2341.72 | E24: 0 | F24: 0 | G24: 2341.72 | H24: 0 | I24: =G24+H24 -> 2341.72 | J24: =D24-I24 -> 0 | K24: 200DB | L24: 5.0
A25: 8 | B25: 2 - Land Improvements - 30 year | C25: 5/31/17 | D25: 9353.85 | E25: 0 | F25: 0 | G25: 2065.67 | H25: 311.8 | I25: =G25+H25 -> 2377.47 | J25: =D25-I25 -> 6976.38 | K25: S/L | L25: 30.00
B26: Grand Total | D26: =SUM(D18:D25) -> 111983.58 | E26: =SUM(E18:E25) -> 0 | F26: =SUM(F18:F25) -> 63.33 | G26: =SUM(G18:G25) -> 42163.42 | H26: =SUM(H18:H25) -> 2985.4 | I26: =SUM(I18:I25) -> 45148.82 | J26: =SUM(J18:J25) -> 66834.76
B28: Section 481(a) Adjustment — Regular Tax
B29: Depreciation reported previously | D29: =I14 -> 34272.73
B30: Cost Segregation Corrected Depreciation | D30: =I26 -> 45148.82
B31: Section 481(a) Adjustment — Regular Tax | D31: =D29-D30 -> -10876.09
A33: CALCULATION OF §481(a) ADJUSTMENT — AMT
A34: As Previously Filed — AMT
A35: Asset | B35: Property Description | C35: Date In Service | D35: Cost | E35: Sec 179 Exp | F35: Bonus Amt | G35: AMT Prior Depreciation | H35: AMT Current Depreciation | I35: End Depreciation | J35: Net Book Value | K35: Method | L35: Period
A36: 1 | B36: 19 - Building - 754 "Menowitz" | C36: 9/15/21 | D36: 316.3 | E36: 0 | F36: 0 | G36: 19.15 | H36: 7.89 | I36: =G36+H36 -> 27.04 | J36: =D36-I36 -> 289.26 | K36: S/L | L36: 40.00
A37: 2 | B37: 3 - Building | C37: 5/31/17 | D37: 94123.92 | E37: 0 | F37: 0 | G37: 20256.43 | H37: 2213.27 | I37: =G37+H37 -> 22469.7 | J37: =D37-I37 -> 71654.22 | K37: S/L | L37: 40.00
A38: 3 | B38: 4 - Personal Property | C38: 5/31/17 | D38: 5847.79 | E38: 0 | F38: 0 | G38: 5457.95 | H38: 0 | I38: =G38+H38 -> 5457.95 | J38: =D38-I38 -> 389.84 | K38: S/L | L38: 40.00
A39: 4 | B39: 2 - Land Improvements | C39: 5/31/17 | D39: 11695.57 | E39: 0 | F39: 0 | G39: 5628.01 | H39: 690.03 | I39: =G39+H39 -> 6318.04 | J39: =D39-I39 -> 5377.53 | K39: S/L | L39: 40.00
B40: Grand Total | D40: =SUM(D36:D39) -> 111983.58 | E40: =SUM(E36:E39) -> 0 | F40: =SUM(F36:F39) -> 0 | G40: =SUM(G36:G39) -> 31361.54 | H40: =SUM(H36:H39) -> 2911.19 | I40: =SUM(I36:I39) -> 34272.73 | J40: =SUM(J36:J39) -> 77710.85
A42: After Cost Segregation Correction — AMT
A43: Asset | B43: Property Description | C43: Date In Service | D43: Cost | E43: Sec 179 Exp | F43: Bonus Amt | G43: AMT Prior Depreciation | H43: AMT Current Depreciation | I43: End Depreciation | J43: Net Book Value | K43: Method | L43: Period
A44: 1 | B44: 19 - Building - 754 "Menowitz" - 5 year | C44: 9/15/21 | D44: 63.33 | E44: 0 | F44: 63.33 | G44: 63.33 | H44: 0 | I44: =G44+H44 -> 63.33 | J44: =D44-I44 -> 0 | K44: 200DB | L44: 5.0
A45: 2 | B45: 19 - Building - 754 "Menowitz" - 30 year | C45: 9/15/21 | D45: 252.97 | E45: 0 | F45: 0 | G45: 19.32 | H45: 8.43 | I45: =G45+H45 -> 27.75 | J45: =D45-I45 -> 225.22 | K45: S/L | L45: 30.00
A46: 3 | B46: 3 - Building - 5 year | C46: 5/31/17 | D46: 18845.76 | E46: 0 | F46: 0 | G46: 18845.76 | H46: 0 | I46: =G46+H46 -> 18845.76 | J46: =D46-I46 -> 0 | K46: 200DB | L46: 5.0
A47: 4 | B47: 3 - Building - 30 year | C47: 5/31/17 | D47: 75278.16 | E47: 0 | F47: 0 | G47: 16623.92 | H47: 2509.27 | I47: =G47+H47 -> 19133.19 | J47: =D47-I47 -> 56144.97 | K47: S/L | L47: 30.00
A48: 5 | B48: 4 - Personal Property - 5 year | C48: 5/31/17 | D48: 1170.86 | E48: 0 | F48: 0 | G48: 1170.86 | H48: 0 | I48: =G48+H48 -> 1170.86 | J48: =D48-I48 -> 0 | K48: 200DB | L48: 5.0
A49: 6 | B49: 4 - Personal Property - 30 year | C49: 5/31/17 | D49: 4676.93 | E49: 0 | F49: 0 | G49: 1032.84 | H49: 155.9 | I49: =G49+H49 -> 1188.74 | J49: =D49-I49 -> 3488.19 | K49: S/L | L49: 30.00
A50: 7 | B50: 2 - Land Improvements - 5 year | C50: 5/31/17 | D50: 2341.72 | E50: 0 | F50: 0 | G50: 2341.72 | H50: 0 | I50: =G50+H50 -> 2341.72 | J50: =D50-I50 -> 0 | K50: 200DB | L50: 5.0
A51: 8 | B51: 2 - Land Improvements - 30 year | C51: 5/31/17 | D51: 9353.85 | E51: 0 | F51: 0 | G51: 2065.67 | H51: 311.8 | I51: =G51+H51 -> 2377.47 | J51: =D51-I51 -> 6976.38 | K51: S/L | L51: 30.00
