Workbook

Sheet Summary
A1: St Charles Housing LP
A2: St. Charles — 1011 W 18th St, Lake Charles, LA 70607
A3: EIN: 82-5349206 · FYE: December 31, 2024 · Year of Change: 1/1/2024
A4: Summary of Cost Segregation Adjustments — CSSI Report #107752-24 (CAM — DCN #7)
A7: Acq Date | B7: Asset Description | C7: Total | D7: Site | E7: Building 1 | F7: Building 2 | G7: Building 3 | H7: Building 4 | I7: Building 5 | J7: Building 6 | K7: Building 7 | L7: Building 8 | M7: Building 9 | N7: Building 10 | O7: Building 11 | P7: Building 12 | Q7: Building 13 | R7: Building 14 | S7: Building 15 | T7: Building 16 | U7: Office
A8: 8/15/18 | B8: 10-Building(Post Casualty Loss Basis)-site | C8: =SUM(D8:U8) -> 116091.65 | D8: =Site!$D$10 -> 116091.65
A9: 12/20/22 | B9: 12-New Buildings(16 units)-site | C9: =SUM(D9:U9) -> 62263.6 | D9: =Site!$D$11 -> 62263.6
A10: 4/01/23 | B10: 14-New Buildings(105 units)-site | C10: =SUM(D10:U10) -> 417320.48 | D10: =Site!$D$12 -> 417320.48
A11: 9/02/20 | B11: 11-Building Imp)Post-Casulty Loss Basis)-site | C11: =SUM(D11:U11) -> 2917.69 | D11: =Site!$D$13 -> 2917.69
A12: 8/15/18 | B12: 2-Land Improvements-site | C12: =SUM(D12:U12) -> 15876.41 | D12: =Site!$D$14 -> 15876.41
A13: 12/20/22 | B13: 13-New Equipment(16 units)-site | C13: =SUM(D13:U13) -> 13667.6 | D13: =Site!$D$15 -> 13667.6
A14: 4/01/23 | B14: 15-New Equipment(105 units)-site | C14: =SUM(D14:U14) -> 91606.97 | D14: =Site!$D$16 -> 91606.97
A15: 8/15/18 | B15: 10-Building(Post Casualty Loss Basis)-bldg 1 | C15: =SUM(D15:U15) -> 64257.99 | E15: ='Building 1'!$D$10 -> 64257.99
A16: 12/20/22 | B16: 12-New Buildings(16 units)-bldg 1 | C16: =SUM(D16:U16) -> 34463.6 | E16: ='Building 1'!$D$11 -> 34463.6
A17: 4/01/23 | B17: 14-New Buildings(105 units)-bldg 1 | C17: =SUM(D17:U17) -> 230991.49 | E17: ='Building 1'!$D$12 -> 230991.49
A18: 9/02/20 | B18: 11-Building Imp)Post-Casulty Loss Basis)-bldg | C18: =SUM(D18:U18) -> 25941.71 | E18: ='Building 1'!$D$13 -> 1614.97 | F18: ='Building 2'!$D$13 -> 1615.35 | G18: ='Building 3'!$D$13 -> 1615.41 | H18: ='Building 4'!$D$13 -> 1607.95 | I18: ='Building 5'!$D$13 -> 1809.19 | J18: ='Building 6'!$D$13 -> 1616.48 | K18: ='Building 7'!$D$13 -> 1817.72 | L18: ='Building 8'!$D$13 -> 1616.48 | M18: ='Building 9'!$D$13 -> 719.75 | N18: ='Building 10'!$D$13 -> 1816.65 | O18: ='Building 11'!$D$13 -> 1616.48 | P18: ='Building 12'!$D$13 -> 1817.72 | Q18: ='Building 13'!$D$13 -> 1616.48 | R18: ='Building 14'!$D$13 -> 1816.65 | S18: ='Building 15'!$D$13 -> 1607.95 | T18: ='Building 16'!$D$13 -> 1616.48
A19: 8/15/18 | B19: 2-Land Improvements-bldg 1 | C19: =SUM(D19:U19) -> 8787.77 | E19: ='Building 1'!$D$14 -> 8787.77
A20: 12/20/22 | B20: 13-New Equipment(16 units)-bldg 1 | C20: =SUM(D20:U20) -> 7565.17 | E20: ='Building 1'!$D$15 -> 7565.17
A21: 4/01/23 | B21: 15-New Equipment(105 units)-bldg 1 | C21: =SUM(D21:U21) -> 50705.47 | E21: ='Building 1'!$D$16 -> 50705.47
A22: 8/15/18 | B22: 10-Building(Post Casualty Loss Basis)-bldg 2 | C22: =SUM(D22:U22) -> 64273.15 | F22: ='Building 2'!$D$10 -> 64273.15
A23: 12/20/22 | B23: 12-New Buildings(16 units)-bldg 2 | C23: =SUM(D23:U23) -> 34471.7 | F23: ='Building 2'!$D$11 -> 34471.7
A24: 4/01/23 | B24: 14-New Buildings(105 units)-bldg 2 | C24: =SUM(D24:U24) -> 231045.9 | F24: ='Building 2'!$D$12 -> 231045.9
A25: 8/15/18 | B25: 2-Land Improvements-bldg 2 | C25: =SUM(D25:U25) -> 8789.84 | F25: ='Building 2'!$D$14 -> 8789.84
A26: 12/20/22 | B26: 13-New Equipment(16 units)-bldg 2 | C26: =SUM(D26:U26) -> 7566.95 | F26: ='Building 2'!$D$15 -> 7566.95
A27: 4/01/23 | B27: 15-New Equipment(105 units)-bldg 2 | C27: =SUM(D27:U27) -> 50717.41 | F27: ='Building 2'!$D$16 -> 50717.41
A28: 8/15/18 | B28: 10-Building(Post Casualty Loss Basis)-bldg 3 | C28: =SUM(D28:U28) -> 64275.31 | G28: ='Building 3'!$D$10 -> 64275.31
A29: 12/20/22 | B29: 12-New Buildings(16 units)-bldg 3 | C29: =SUM(D29:U29) -> 34472.86 | G29: ='Building 3'!$D$11 -> 34472.86
A30: 4/01/23 | B30: 14-New Buildings(105 units)-bldg 3 | C30: =SUM(D30:U30) -> 231053.67 | G30: ='Building 3'!$D$12 -> 231053.67
A31: 8/15/18 | B31: 2-Land Improvements-bldg 3 | C31: =SUM(D31:U31) -> 8790.13 | G31: ='Building 3'!$D$14 -> 8790.13
A32: 12/20/22 | B32: 13-New Equipment(16 units)-bldg 3 | C32: =SUM(D32:U32) -> 7567.2 | G32: ='Building 3'!$D$15 -> 7567.2
A33: 4/01/23 | B33: 15-New Equipment(105 units)-bldg 3 | C33: =SUM(D33:U33) -> 50719.12 | G33: ='Building 3'!$D$16 -> 50719.12
A34: 8/15/18 | B34: 10-Building(Post Casualty Loss Basis)-bldg 4 | C34: =SUM(D34:U34) -> 63978.69 | H34: ='Building 4'!$D$10 -> 63978.69
A35: 12/20/22 | B35: 12-New Buildings(16 units)-bldg 4 | C35: =SUM(D35:U35) -> 34313.78 | H35: ='Building 4'!$D$11 -> 34313.78
A36: 4/01/23 | B36: 14-New Buildings(105 units)-bldg 4 | C36: =SUM(D36:U36) -> 229987.39 | H36: ='Building 4'!$D$12 -> 229987.39
A37: 8/15/18 | B37: 2-Land Improvements-bldg 4 | C37: =SUM(D37:U37) -> 8749.57 | H37: ='Building 4'!$D$14 -> 8749.57
A38: 12/20/22 | B38: 13-New Equipment(16 units)-bldg 4 | C38: =SUM(D38:U38) -> 7532.28 | H38: ='Building 4'!$D$15 -> 7532.28
A39: 4/01/23 | B39: 15-New Equipment(105 units)-bldg 4 | C39: =SUM(D39:U39) -> 50485.05 | H39: ='Building 4'!$D$16 -> 50485.05
A40: 8/15/18 | B40: 10-Building(Post Casualty Loss Basis)-bldg 5 | C40: =SUM(D40:U40) -> 71985.95 | I40: ='Building 5'!$D$10 -> 71985.95
A41: 12/20/22 | B41: 12-New Buildings(16 units)-bldg 5 | C41: =SUM(D41:U41) -> 38608.32 | I41: ='Building 5'!$D$11 -> 38608.32
A42: 4/01/23 | B42: 14-New Buildings(105 units)-bldg 5 | C42: =SUM(D42:U42) -> 258771.48 | I42: ='Building 5'!$D$12 -> 258771.48
A43: 8/15/18 | B43: 2-Land Improvements-bldg 5 | C43: =SUM(D43:U43) -> 9844.62 | I43: ='Building 5'!$D$14 -> 9844.62
A44: 12/20/22 | B44: 13-New Equipment(16 units)-bldg 5 | C44: =SUM(D44:U44) -> 8474.99 | I44: ='Building 5'!$D$15 -> 8474.99
A45: 4/01/23 | B45: 15-New Equipment(105 units)-bldg 5 | C45: =SUM(D45:U45) -> 56803.51 | I45: ='Building 5'!$D$16 -> 56803.51
A46: 8/15/18 | B46: 10-Building(Post Casualty Loss Basis)-bldg 6 | C46: =SUM(D46:U46) -> 64317.98 | J46: ='Building 6'!$D$10 -> 64317.98
A47: 12/20/22 | B47: 12-New Buildings(16 units)-bldg 6 | C47: =SUM(D47:U47) -> 34495.74 | J47: ='Building 6'!$D$11 -> 34495.74
A48: 4/01/23 | B48: 14-New Buildings(105 units)-bldg 6 | C48: =SUM(D48:U48) -> 231207.03 | J48: ='Building 6'!$D$12 -> 231207.03
A49: 8/15/18 | B49: 2-Land Improvements-bldg 6 | C49: =SUM(D49:U49) -> 8795.97 | J49: ='Building 6'!$D$14 -> 8795.97
A50: 12/20/22 | B50: 13-New Equipment(16 units)-bldg 6 | C50: =SUM(D50:U50) -> 7572.23 | J50: ='Building 6'!$D$15 -> 7572.23
A51: 4/01/23 | B51: 15-New Equipment(105 units)-bldg 6 | C51: =SUM(D51:U51) -> 50752.78 | J51: ='Building 6'!$D$16 -> 50752.78
A52: 8/15/18 | B52: 10-Building(Post Casualty Loss Basis)-bldg 7 | C52: =SUM(D52:U52) -> 72325.23 | K52: ='Building 7'!$D$10 -> 72325.23
A53: 12/20/22 | B53: 12-New Buildings(16 units)-bldg 7 | C53: =SUM(D53:U53) -> 38790.29 | K53: ='Building 7'!$D$11 -> 38790.29
A54: 4/01/23 | B54: 14-New Buildings(105 units)-bldg 7 | C54: =SUM(D54:U54) -> 259991.11 | K54: ='Building 7'!$D$12 -> 259991.11
A55: 8/15/18 | B55: 2-Land Improvements-bldg 7 | C55: =SUM(D55:U55) -> 9891.01 | K55: ='Building 7'!$D$14 -> 9891.01
A56: 12/20/22 | B56: 13-New Equipment(16 units)-bldg 7 | C56: =SUM(D56:U56) -> 8514.93 | K56: ='Building 7'!$D$15 -> 8514.93
A57: 4/01/23 | B57: 15-New Equipment(105 units)-bldg 7 | C57: =SUM(D57:U57) -> 57071.24 | K57: ='Building 7'!$D$16 -> 57071.24
A58: 8/15/18 | B58: 10-Building(Post Casualty Loss Basis)-bldg 8 | C58: =SUM(D58:U58) -> 64317.98 | L58: ='Building 8'!$D$10 -> 64317.98
A59: 12/20/22 | B59: 12-New Buildings(16 units)-bldg 8 | C59: =SUM(D59:U59) -> 34495.74 | L59: ='Building 8'!$D$11 -> 34495.74
A60: 4/01/23 | B60: 14-New Buildings(105 units)-bldg 8 | C60: =SUM(D60:U60) -> 231207.03 | L60: ='Building 8'!$D$12 -> 231207.03
A61: 8/15/18 | B61: 2-Land Improvements-bldg 8 | C61: =SUM(D61:U61) -> 8795.97 | L61: ='Building 8'!$D$14 -> 8795.97
A62: 12/20/22 | B62: 13-New Equipment(16 units)-bldg 8 | C62: =SUM(D62:U62) -> 7572.23 | L62: ='Building 8'!$D$15 -> 7572.23
A63: 4/01/23 | B63: 15-New Equipment(105 units)-bldg 8 | C63: =SUM(D63:U63) -> 50752.78 | L63: ='Building 8'!$D$16 -> 50752.78
A64: 8/15/18 | B64: 10-Building(Post Casualty Loss Basis)-bldg 9 | C64: =SUM(D64:U64) -> 28637.97 | M64: ='Building 9'!$D$10 -> 28637.97
A65: 12/20/22 | B65: 12-New Buildings(16 units)-bldg 9 | C65: =SUM(D65:U65) -> 15359.44 | M65: ='Building 9'!$D$11 -> 15359.44
A66: 4/01/23 | B66: 14-New Buildings(105 units)-bldg 9 | C66: =SUM(D66:U66) -> 102946.35 | M66: ='Building 9'!$D$12 -> 102946.35
A67: 8/15/18 | B67: 2-Land Improvements-bldg 9 | C67: =SUM(D67:U67) -> 3916.46 | M67: ='Building 9'!$D$14 -> 3916.46
A68: 12/20/22 | B68: 13-New Equipment(16 units)-bldg 9 | C68: =SUM(D68:U68) -> 3371.57 | M68: ='Building 9'!$D$15 -> 3371.57
A69: 4/01/23 | B69: 15-New Equipment(105 units)-bldg 9 | C69: =SUM(D69:U69) -> 22597.99 | M69: ='Building 9'!$D$16 -> 22597.99
A70: 8/15/18 | B70: 10-Building(Post Casualty Loss Basis)-bldg 10 | C70: =SUM(D70:U70) -> 72282.57 | N70: ='Building 10'!$D$10 -> 72282.57
A71: 12/20/22 | B71: 12-New Buildings(16 units)-bldg 10 | C71: =SUM(D71:U71) -> 38767.41 | N71: ='Building 10'!$D$11 -> 38767.41
A72: 4/01/23 | B72: 14-New Buildings(105 units)-bldg 10 | C72: =SUM(D72:U72) -> 259837.74 | N72: ='Building 10'!$D$12 -> 259837.74
A73: 8/15/18 | B73: 2-Land Improvements-bldg 10 | C73: =SUM(D73:U73) -> 9885.18 | N73: ='Building 10'!$D$14 -> 9885.18
A74: 12/20/22 | B74: 13-New Equipment(16 units)-bldg 10 | C74: =SUM(D74:U74) -> 8509.91 | N74: ='Building 10'!$D$15 -> 8509.91
A75: 4/01/23 | B75: 15-New Equipment(105 units)-bldg 10 | C75: =SUM(D75:U75) -> 57037.57 | N75: ='Building 10'!$D$16 -> 57037.57
A76: 8/15/18 | B76: 10-Building(Post Casualty Loss Basis)-bldg 11 | C76: =SUM(D76:U76) -> 64317.98 | O76: ='Building 11'!$D$10 -> 64317.98
A77: 12/20/22 | B77: 12-New Buildings(16 units)-bldg 11 | C77: =SUM(D77:U77) -> 34495.74 | O77: ='Building 11'!$D$11 -> 34495.74
A78: 4/01/23 | B78: 14-New Buildings(105 units)-bldg 11 | C78: =SUM(D78:U78) -> 231207.03 | O78: ='Building 11'!$D$12 -> 231207.03
A79: 8/15/18 | B79: 2-Land Improvements-bldg 11 | C79: =SUM(D79:U79) -> 8795.97 | O79: ='Building 11'!$D$14 -> 8795.97
A80: 12/20/22 | B80: 13-New Equipment(16 units)-bldg 11 | C80: =SUM(D80:U80) -> 7572.23 | O80: ='Building 11'!$D$15 -> 7572.23
A81: 4/01/23 | B81: 15-New Equipment(105 units)-bldg 11 | C81: =SUM(D81:U81) -> 50752.78 | O81: ='Building 11'!$D$16 -> 50752.78
A82: 8/15/18 | B82: 10-Building(Post Casualty Loss Basis)-bldg 12 | C82: =SUM(D82:U82) -> 72325.23 | P82: ='Building 12'!$D$10 -> 72325.23
A83: 12/20/22 | B83: 12-New Buildings(16 units)-bldg 12 | C83: =SUM(D83:U83) -> 38790.29 | P83: ='Building 12'!$D$11 -> 38790.29
A84: 4/01/23 | B84: 14-New Buildings(105 units)-bldg 12 | C84: =SUM(D84:U84) -> 259991.11 | P84: ='Building 12'!$D$12 -> 259991.11
A85: 8/15/18 | B85: 2-Land Improvements-bldg 12 | C85: =SUM(D85:U85) -> 9891.01 | P85: ='Building 12'!$D$14 -> 9891.01
A86: 12/20/22 | B86: 13-New Equipment(16 units)-bldg 12 | C86: =SUM(D86:U86) -> 8514.93 | P86: ='Building 12'!$D$15 -> 8514.93
A87: 4/01/23 | B87: 15-New Equipment(105 units)-bldg 12 | C87: =SUM(D87:U87) -> 57071.24 | P87: ='Building 12'!$D$16 -> 57071.24
A88: 8/15/18 | B88: 10-Building(Post Casualty Loss Basis)-bldg 13 | C88: =SUM(D88:U88) -> 64317.98 | Q88: ='Building 13'!$D$10 -> 64317.98
A89: 12/20/22 | B89: 12-New Buildings(16 units)-bldg 13 | C89: =SUM(D89:U89) -> 34495.74 | Q89: ='Building 13'!$D$11 -> 34495.74
A90: 4/01/23 | B90: 14-New Buildings(105 units)-bldg 13 | C90: =SUM(D90:U90) -> 231207.03 | Q90: ='Building 13'!$D$12 -> 231207.03
A91: 8/15/18 | B91: 2-Land Improvements-bldg 13 | C91: =SUM(D91:U91) -> 8795.97 | Q91: ='Building 13'!$D$14 -> 8795.97
A92: 12/20/22 | B92: 13-New Equipment(16 units)-bldg 13 | C92: =SUM(D92:U92) -> 7572.23 | Q92: ='Building 13'!$D$15 -> 7572.23
A93: 4/01/23 | B93: 15-New Equipment(105 units)-bldg 13 | C93: =SUM(D93:U93) -> 50752.78 | Q93: ='Building 13'!$D$16 -> 50752.78
A94: 8/15/18 | B94: 10-Building(Post Casualty Loss Basis)-bldg 14 | C94: =SUM(D94:U94) -> 72282.57 | R94: ='Building 14'!$D$10 -> 72282.57
A95: 12/20/22 | B95: 12-New Buildings(16 units)-bldg 14 | C95: =SUM(D95:U95) -> 38767.41 | R95: ='Building 14'!$D$11 -> 38767.41
A96: 4/01/23 | B96: 14-New Buildings(105 units)-bldg 14 | C96: =SUM(D96:U96) -> 259837.74 | R96: ='Building 14'!$D$12 -> 259837.74
A97: 8/15/18 | B97: 2-Land Improvements-bldg 14 | C97: =SUM(D97:U97) -> 9885.18 | R97: ='Building 14'!$D$14 -> 9885.18
A98: 12/20/22 | B98: 13-New Equipment(16 units)-bldg 14 | C98: =SUM(D98:U98) -> 8509.91 | R98: ='Building 14'!$D$15 -> 8509.91
A99: 4/01/23 | B99: 15-New Equipment(105 units)-bldg 14 | C99: =SUM(D99:U99) -> 57037.57 | R99: ='Building 14'!$D$16 -> 57037.57
A100: 8/15/18 | B100: 10-Building(Post Casualty Loss Basis)-bldg 15 | C100: =SUM(D100:U100) -> 63978.69 | S100: ='Building 15'!$D$10 -> 63978.69
A101: 12/20/22 | B101: 12-New Buildings(16 units)-bldg 15 | C101: =SUM(D101:U101) -> 34313.78 | S101: ='Building 15'!$D$11 -> 34313.78
A102: 4/01/23 | B102: 14-New Buildings(105 units)-bldg 15 | C102: =SUM(D102:U102) -> 229987.39 | S102: ='Building 15'!$D$12 -> 229987.39
...

Sheet Site
A1: St Charles Housing LP
A2: St. Charles — 1011 W 18th St, Lake Charles, LA 70607
A3: EIN: 82-5349206 · FYE: December 31, 2024 · Year of Change: 1/1/2024
A4: Site — Attachment to Form 3115 (DCN #7, Rev. Proc. 2024-23 §6.01)
A5: Source: CSSI Report #107752-24, "St. Charles Housing LP_107752-24_3115_Combined.pdf"
A7: CALCULATION OF §481(a) ADJUSTMENT — REGULAR TAX
A8: As Previously Filed
A9: Asset | B9: Property Description | C9: Date In Service | D9: Cost | E9: Sec 179 Exp | F9: Bonus Amt | G9: Tax Prior Depreciation | H9: Tax Current Depreciation | I9: End Depreciation | J9: Net Book Value | K9: Method | L9: Period
A10: 1 | B10: 10-Building(Post Casualty Loss Basis)-site | C10: 8/15/18 | D10: 116091.65 | E10: 0 | F10: 0 | G10: 11989.37 | H10: 4227.49 | I10: =G10+H10 -> 16216.86 | J10: =D10-I10 -> 99874.79 | K10: S/L | L10: 30.00
A11: 2 | B11: 12-New Buildings(16 units)-site | C11: 12/20/22 | D11: 62263.6 | E11: 0 | F11: 0 | G11: 2161.97 | H11: 2075.44 | I11: =G11+H11 -> 4237.41 | J11: =D11-I11 -> 58026.19 | K11: S/L | L11: 30.00
A12: 3 | B12: 14-New Buildings(105 units)-site | C12: 4/01/23 | D12: 417320.48 | E12: 0 | F12: 0 | G12: 9853.39 | H12: 13910.71 | I12: =G12+H12 -> 23764.1 | J12: =D12-I12 -> 393556.38 | K12: S/L | L12: 30.00
A13: 4 | B13: 11-Building Imp)Post-Casulty Loss Basis)-site | C13: 9/02/20 | D13: 2917.69 | E13: 0 | F13: 0 | G13: 219.69 | H13: 101.01 | I13: =G13+H13 -> 320.7 | J13: =D13-I13 -> 2596.99 | K13: S/L | L13: 30.00
A14: 5 | B14: 2-Land Improvements-site | C14: 8/15/18 | D14: 15876.41 | E14: 0 | F14: 4073.29 | G14: 4073.29 | H14: 1221 | I14: =G14+H14 -> 5294.29 | J14: =D14-I14 -> 10582.12 | K14: 150DB | L14: 15.0
A15: 6 | B15: 13-New Equipment(16 units)-site | C15: 12/20/22 | D15: 13667.6 | E15: 0 | F15: 0 | G15: 0 | H15: 0 | I15: =G15+H15 -> 0 | J15: =D15-I15 -> 13667.6 | K15: 200DB | L15: 5.0
A16: 7 | B16: 15-New Equipment(105 units)-site | C16: 4/01/23 | D16: 91606.97 | E16: 0 | F16: 0 | G16: 3664.27 | H16: 5862.86 | I16: =G16+H16 -> 9527.13 | J16: =D16-I16 -> 82079.84 | K16: 200DB | L16: 5.0
B17: Grand Total | D17: =SUM(D10:D16) -> 719744.4 | E17: =SUM(E10:E16) -> 0 | F17: =SUM(F10:F16) -> 4073.29 | G17: =SUM(G10:G16) -> 31961.98 | H17: =SUM(H10:H16) -> 27398.51 | I17: =SUM(I10:I16) -> 59360.49 | J17: =SUM(J10:J16) -> 660383.91
A19: After Cost Segregation Correction
A20: Asset | B20: Property Description | C20: Date In Service | D20: Cost | E20: Sec 179 Exp | F20: Bonus Amt | G20: Tax Prior Depreciation | H20: Tax Current Depreciation | I20: End Depreciation | J20: Net Book Value | K20: Method | L20: Period
A21: 1 | B21: 10-Building-Post Casualty Loss Basis-site-15yr | C21: 8/15/18 | D21: 65091.76 | E21: 0 | F21: 65091.76 | G21: 65091.76 | H21: 0 | I21: =G21+H21 -> 65091.76 | J21: =D21-I21 -> 0 | K21: 150DB | L21: 15.0
A22: 2 | B22: 10-Building-Post Casualty Loss Basis-site-30yr | C22: 8/15/18 | D22: 50999.89 | E22: 0 | F22: 0 | G22: 9137.5 | H22: 1700 | I22: =G22+H22 -> 10837.5 | J22: =D22-I22 -> 40162.39 | K22: S/L | L22: 30.00
A23: 3 | B23: 12-New Buildings(16 units)-site-15yr | C23: 12/20/22 | D23: 34910.75 | E23: 0 | F23: 34910.75 | G23: 34910.75 | H23: 0 | I23: =G23+H23 -> 34910.75 | J23: =D23-I23 -> 0 | K23: 150DB | L23: 15.0
A24: 4 | B24: 12-New Buildings(16 units)-site-30yr | C24: 12/20/22 | D24: 27352.85 | E24: 0 | F24: 0 | G24: 949.75 | H24: 911.76 | I24: =G24+H24 -> 1861.51 | J24: =D24-I24 -> 25491.34 | K24: S/L | L24: 30.00
A25: 5 | B25: 14-New Buildings(105 units)-site-15yr | C25: 4/01/23 | D25: 233988.6 | E25: 0 | F25: 187190.88 | G25: 189530.77 | H25: 4445.78 | I25: =G25+H25 -> 193976.55 | J25: =D25-I25 -> 40012.05 | K25: 150DB | L25: 15.0
A26: 6 | B26: 14-New Buildings(105 units)-site-30yr | C26: 4/01/23 | D26: 183331.88 | E26: 0 | F26: 0 | G26: 4328.67 | H26: 6111.06 | I26: =G26+H26 -> 10439.73 | J26: =D26-I26 -> 172892.15 | K26: S/L | L26: 30.00
A27: 7 | B27: 11-Building Imp-Post-Casulty Loss Basis-site-15yr | C27: 9/02/20 | D27: 1635.93 | E27: 0 | F27: 1635.93 | G27: 1635.93 | H27: 0 | I27: =G27+H27 -> 1635.93 | J27: =D27-I27 -> 0 | K27: 150DB | L27: 15.0
A28: 8 | B28: 11-Building Imp-Post-Casulty Loss Basis-site-30yr | C28: 9/02/20 | D28: 1281.76 | E28: 0 | F28: 0 | G28: 140.65 | H28: 42.73 | I28: =G28+H28 -> 183.38 | J28: =D28-I28 -> 1098.38 | K28: S/L | L28: 30.00
A29: 9 | B29: 2-Land Improvements-site-15yr | C29: 8/15/18 | D29: 8901.79 | E29: 0 | F29: 8901.79 | G29: 8901.79 | H29: 0 | I29: =G29+H29 -> 8901.79 | J29: =D29-I29 -> 0 | K29: 150DB | L29: 15.0
A30: 10 | B30: 2-Land Improvements-site-30yr | C30: 8/15/18 | D30: 6974.62 | E30: 0 | F30: 0 | G30: 1249.63 | H30: 232.49 | I30: =G30+H30 -> 1482.12 | J30: =D30-I30 -> 5492.5 | K30: S/L | L30: 30.00
A31: 11 | B31: 13-New Equipment(16 units)-site-15yr | C31: 12/20/22 | D31: 7663.33 | E31: 0 | F31: 7663.33 | G31: 7663.33 | H31: 0 | I31: =G31+H31 -> 7663.33 | J31: =D31-I31 -> 0 | K31: 150DB | L31: 15.0
A32: 12 | B32: 13-New Equipment(16 units)-site-30yr | C32: 12/20/22 | D32: 6004.27 | E32: 0 | F32: 0 | G32: 208.48 | H32: 200.14 | I32: =G32+H32 -> 408.62 | J32: =D32-I32 -> 5595.65 | K32: S/L | L32: 30.00
... A34: 14 | B34: 15-New Equipment(105 units)-site-30yr | C34: 4/01/23 | D34: 40243.6 | E34: 0 | F34: 0 | G34: 950.2 | H34: 1341.45 | I34: =G34+H34 -> 2291.65 | J34: =D34-I34 -> 37951.95 | K34: S/L | L34: 30.00
B35: Grand Total | D35: =SUM(D21:D34) -> 719744.4 | E35: =SUM(E21:E34) -> 0 | F35: =SUM(F21:F34) -> 346485.14 | G35: =SUM(G21:G34) -> 366303.54 | H35: =SUM(H21:H34) -> 15961.31 | I35: =SUM(I21:I34) -> 382264.85 | J35: =SUM(J21:J34) -> 337479.55
B37: Section 481(a) Adjustment — Regular Tax
B38: Depreciation reported previously | D38: =I17 -> 59360.49
B39: Cost Segregation Corrected Depreciation | D39: =I35 -> 382264.85
B40: Section 481(a) Adjustment — Regular Tax | D40: =D38-D39 -> -322904.36
A42: CALCULATION OF §481(a) ADJUSTMENT — AMT
A43: As Previously Filed — AMT
A44: Asset | B44: Property Description | C44: Date In Service | D44: Cost | E44: Sec 179 Exp | F44: Bonus Amt | G44: AMT Prior Depreciation | H44: AMT Current Depreciation | I44: End Depreciation | J44: Net Book Value | K44: Method | L44: Period
A45: 1 | B45: 10-Building(Post Casualty Loss Basis)-site | C45: 8/15/18 | D45: 116091.65 | E45: 0 | F45: 0 | G45: 11989.37 | H45: 4227.49 | I45: =G45+H45 -> 16216.86 | J45: =D45-I45 -> 99874.79 | K45: S/L | L45: 30.00
A46: 2 | B46: 12-New Buildings(16 units)-site | C46: 12/20/22 | D46: 62263.6 | E46: 0 | F46: 0 | G46: 2161.97 | H46: 2075.44 | I46: =G46+H46 -> 4237.41 | J46: =D46-I46 -> 58026.19 | K46: S/L | L46: 30.00
A47: 3 | B47: 14-New Buildings(105 units)-site | C47: 4/01/23 | D47: 417320.48 | E47: 0 | F47: 0 | G47: 9853.39 | H47: 13910.71 | I47: =G47+H47 -> 23764.1 | J47: =D47-I47 -> 393556.38 | K47: S/L | L47: 30.00
A48: 4 | B48: 11-Building Imp)Post-Casulty Loss Basis)-site | C48: 9/02/20 | D48: 2917.69 | E48: 0 | F48: 0 | G48: 219.69 | H48: 101.01 | I48: =G48+H48 -> 320.7 | J48: =D48-I48 -> 2596.99 | K48: S/L | L48: 30.00
A49: 5 | B49: 2-Land Improvements-site | C49: 8/15/18 | D49: 15876.41 | E49: 0 | F49: 4073.29 | G49: 4073.29 | H49: 1221 | I49: =G49+H49 -> 5294.29 | J49: =D49-I49 -> 10582.12 | K49: 150DB | L49: 15.0
A50: 6 | B50: 13-New Equipment(16 units)-site | C50: 12/20/22 | D50: 13667.6 | E50: 0 | F50: 0 | G50: 0 | H50: 0 | I50: =G50+H50 -> 0 | J50: =D50-I50 -> 13667.6 | K50: 200DB | L50: 5.0
A51: 7 | B51: 15-New Equipment(105 units)-site | C51: 4/01/23 | D51: 91606.97 | E51: 0 | F51: 0 | G51: 3664.27 | H51: 5862.86 | I51: =G51+H51 -> 9527.13 | J51: =D51-I51 -> 82079.84 | K51: 200DB | L51: 5.0
B52: Grand Total | D52: =SUM(D45:D51) -> 719744.4 | E52: =SUM(E45:E51) -> 0 | F52: =SUM(F45:F51) -> 4073.29 | G52: =SUM(G45:G51) -> 31961.98 | H52: =SUM(H45:H51) -> 27398.51 | I52: =SUM(I45:I51) -> 59360.49 | J52: =SUM(J45:J51) -> 660383.91
A54: After Cost Segregation Correction — AMT
A55: Asset | B55: Property Description | C55: Date In Service | D55: Cost | E55: Sec 179 Exp | F55: Bonus Amt | G55: AMT Prior Depreciation | H55: AMT Current Depreciation | I55: End Depreciation | J55: Net Book Value | K55: Method | L55: Period
A56: 1 | B56: 10-Building-Post Casualty Loss Basis-site-15yr | C56: 8/15/18 | D56: 65091.76 | E56: 0 | F56: 65091.76 | G56: 65091.76 | H56: 0 | I56: =G56+H56 -> 65091.76 | J56: =D56-I56 -> 0 | K56: 150DB | L56: 15.0
A57: 2 | B57: 10-Building-Post Casualty Loss Basis-site-30yr | C57: 8/15/18 | D57: 50999.89 | E57: 0 | F57: 0 | G57: 9137.5 | H57: 1700 | I57: =G57+H57 -> 10837.5 | J57: =D57-I57 -> 40162.39 | K57: S/L | L57: 30.00
A58: 3 | B58: 12-New Buildings(16 units)-site-15yr | C58: 12/20/22 | D58: 34910.75 | E58: 0 | F58: 34910.75 | G58: 34910.75 | H58: 0 | I58: =G58+H58 -> 34910.75 | J58: =D58-I58 -> 0 | K58: 150DB | L58: 15.0
A59: 4 | B59: 12-New Buildings(16 units)-site-30yr | C59: 12/20/22 | D59: 27352.85 | E59: 0 | F59: 0 | G59: 949.75 | H59: 911.76 | I59: =G59+H59 -> 1861.51 | J59: =D59-I59 -> 25491.34 | K59: S/L | L59: 30.00
A60: 5 | B60: 14-New Buildings(105 units)-site-15yr | C60: 4/01/23 | D60: 233988.6 | E60: 0 | F60: 187190.88 | G60: 189530.77 | H60: 4445.78 | I60: =G60+H60 -> 193976.55 | J60: =D60-I60 -> 40012.05 | K60: 150DB | L60: 15.0
A61: 6 | B61: 14-New Buildings(105 units)-site-30yr | C61: 4/01/23 | D61: 183331.88 | E61: 0 | F61: 0 | G61: 4328.67 | H61: 6111.06 | I61: =G61+H61 -> 10439.73 | J61: =D61-I61 -> 172892.15 | K61: S/L | L61: 30.00
A62: 7 | B62: 11-Building Imp-Post-Casulty Loss Basis-site-15yr | C62: 9/02/20 | D62: 1635.93 | E62: 0 | F62: 1635.93 | G62: 1635.93 | H62: 0 | I62: =G62+H62 -> 1635.93 | J62: =D62-I62 -> 0 | K62: 150DB | L62: 15.0
A63: 8 | B63: 11-Building Imp-Post-Casulty Loss Basis-site-30yr | C63: 9/02/20 | D63: 1281.76 | E63: 0 | F63: 0 | G63: 140.65 | H63: 42.73 | I63: =G63+H63 -> 183.38 | J63: =D63-I63 -> 1098.38 | K63: S/L | L63: 30.00
A64: 9 | B64: 2-Land Improvements-site-15yr | C64: 8/15/18 | D64: 8901.79 | E64: 0 | F64: 8901.79 | G64: 8901.79 | H64: 0 | I64: =G64+H64 -> 8901.79 | J64: =D64-I64 -> 0 | K64: 150DB | L64: 15.0
A65: 10 | B65: 2-Land Improvements-site-30yr | C65: 8/15/18 | D65: 6974.62 | E65: 0 | F65: 0 | G65: 1249.63 | H65: 232.49 | I65: =G65+H65 -> 1482.12 | J65: =D65-I65 -> 5492.5 | K65: S/L | L65: 30.00
A66: 11 | B66: 13-New Equipment(16 units)-site-15yr | C66: 12/20/22 | D66: 7663.33 | E66: 0 | F66: 7663.33 | G66: 7663.33 | H66: 0 | I66: =G66+H66 -> 7663.33 | J66: =D66-I66 -> 0 | K66: 150DB | L66: 15.0
A67: 12 | B67: 13-New Equipment(16 units)-site-30yr | C67: 12/20/22 | D67: 6004.27 | E67: 0 | F67: 0 | G67: 208.48 | H67: 200.14 | I67: =G67+H67 -> 408.62 | J67: =D67-I67 -> 5595.65 | K67: S/L | L67: 30.00
... A69: 14 | B69: 15-New Equipment(105 units)-site-30yr | C69: 4/01/23 | D69: 40243.6 | E69: 0 | F69: 0 | G69: 950.2 | H69: 1341.45 | I69: =G69+H69 -> 2291.65 | J69: =D69-I69 -> 37951.95 | K69: S/L | L69: 30.00
B70: Grand Total | D70: =SUM(D56:D69) -> 719744.4 | E70: =SUM(E56:E69) -> 0 | F70: =SUM(F56:F69) -> 346485.14 | G70: =SUM(G56:G69) -> 366303.54 | H70: =SUM(H56:H69) -> 15961.31 | I70: =SUM(I56:I69) -> 382264.85 | J70: =SUM(J56:J69) -> 337479.55
B72: Section 481(a) Adjustment — AMT
B73: Depreciation reported previously | D73: =I52 -> 59360.49
B74: Cost Segregation Corrected Depreciation | D74: =I70 -> 382264.85
B75: Section 481(a) Adjustment — AMT | D75: =D73-D74 -> -322904.36
A77: COST SEGREGATION STUDY — COST SUMMARY
B78: Total Site Cost | D78: =D96 -> 719744.4
B79: Site Improvements: 15 Year | D79: =F96 -> 403555.53
B80: % of Cost | D80: =F97 -> 0.56069284
B81: Site Utilities: 30 Year | D81: =H96 -> 316188.87
B82: % of Cost | D82: =H97 -> 0.43930716
A84: COST SEGREGATION STUDY — COST DETAIL
B85: Property Category | D85: Cost | F85: 15 Year | H85: 30 Year
B86: Site Work / Improvements
B87: Parking Lot | D87: =SUM(F87:H87) -> 195356.18 | F87: 195356.18
B88: Parking Lot Striping / Barriers | D88: =SUM(F88:H88) -> 4120.58 | F88: 4120.58
B89: Sidewalks / Curbs | D89: =SUM(F89:H89) -> 136600.91 | F89: 136600.91
B90: Landscaping | D90: =SUM(F90:H90) -> 4236.31 | F90: 4236.31
B91: Exterior Fencing | D91: =SUM(F91:H91) -> 53960.1 | F91: 53960.1
B92: Exterior Equipment Concrete Pads | D92: =SUM(F92:H92) -> 6941.9 | F92: 6941.9
B93: Playground | D93: =SUM(F93:H93) -> 2339.55 | F93: 2339.55
B94: Site Utilities
B95: Site Utilities | D95: =SUM(F95:H95) -> 316188.87 | H95: 316188.87
B96: Total Site Cost | D96: =SUM(D86:D95) -> 719744.4 | F96: =SUM(F86:F95) -> 403555.53 | H96: =SUM(H86:H95) -> 316188.87
B97: % of Cost | F97: =F96/D96 -> 0.56069284 | H97: =H96/D96 -> 0.43930716
A99: ASSET ALLOCATION (per After Cost Segregation schedule)
B100: Asset (as reclassified) | D100: Cost | F100: 15 Year | H100: 30 Year
B101: =Site!B21 -> 10-Building-Post Casualty Loss Basis-site-15yr | D101: =SUM(F101:H101) -> 65091.76 | F101: =Site!D21 -> 65091.76
B102: =Site!B22 -> 10-Building-Post Casualty Loss Basis-site-30yr | D102: =SUM(F102:H102) -> 50999.89 | H102: =Site!D22 -> 50999.89
B103: =Site!B23 -> 12-New Buildings(16 units)-site-15yr | D103: =SUM(F103:H103) -> 34910.75 | F103: =Site!D23 -> 34910.75
B104: =Site!B24 -> 12-New Buildings(16 units)-site-30yr | D104: =SUM(F104:H104) -> 27352.85 | H104: =Site!D24 -> 27352.85
B105: =Site!B25 -> 14-New Buildings(105 units)-site-15yr | D105: =SUM(F105:H105) -> 233988.6 | F105: =Site!D25 -> 233988.6
B106: =Site!B26 -> 14-New Buildings(105 units)-site-30yr | D106: =SUM(F106:H106) -> 183331.88 | H106: =Site!D26 -> 183331.88
B107: =Site!B27 -> 11-Building Imp-Post-Casulty Loss Basis-site-15yr | D107: =SUM(F107:H107) -> 1635.93 | F107: =Site!D27 -> 1635.93
B108: =Site!B28 -> 11-Building Imp-Post-Casulty Loss Basis-site-30yr | D108: =SUM(F108:H108) -> 1281.76 | H108: =Site!D28 -> 1281.76
B109: =Site!B29 -> 2-Land Improvements-site-15yr | D109: =SUM(F109:H109) -> 8901.79 | F109: =Site!D29 -> 8901.79
B110: =Site!B30 -> 2-Land Improvements-site-30yr | D110: =SUM(F110:H110) -> 6974.62 | H110: =Site!D30 -> 6974.62
B111: =Site!B31 -> 13-New Equipment(16 units)-site-15yr | D111: =SUM(F111:H111) -> 7663.33 | F111: =Site!D31 -> 7663.33
...

Sheet Building 1
A1: St Charles Housing LP
A2: St. Charles — 1011 W 18th St, Lake Charles, LA 70607
A3: EIN: 82-5349206 · FYE: December 31, 2024 · Year of Change: 1/1/2024
A4: Building 1 — Attachment to Form 3115 (DCN #7, Rev. Proc. 2024-23 §6.01)
A5: Source: CSSI Report #107752-24, "St. Charles Housing LP_107752-24_3115_Combined.pdf"
A7: CALCULATION OF §481(a) ADJUSTMENT — REGULAR TAX
A8: As Previously Filed
A9: Asset | B9: Property Description | C9: Date In Service | D9: Cost | E9: Sec 179 Exp | F9: Bonus Amt | G9: Tax Prior Depreciation | H9: Tax Current Depreciation | I9: End Depreciation | J9: Net Book Value | K9: Method | L9: Period
A10: 1 | B10: 10-Building(Post Casualty Loss Basis)-bldg 1 | C10: 8/15/18 | D10: 64257.99 | E10: 0 | F10: 0 | G10: 6636.24 | H10: 2339.95 | I10: =G10+H10 -> 8976.19 | J10: =D10-I10 -> 55281.8 | K10: S/L | L10: 30.00
A11: 2 | B11: 12-New Buildings(16 units)-bldg 1 | C11: 12/20/22 | D11: 34463.6 | E11: 0 | F11: 0 | G11: 1196.67 | H11: 1148.8 | I11: =G11+H11 -> 2345.47 | J11: =D11-I11 -> 32118.13 | K11: S/L | L11: 30.00
A12: 3 | B12: 14-New Buildings(105 units)-bldg 1 | C12: 4/01/23 | D12: 230991.49 | E12: 0 | F12: 0 | G12: 5453.96 | H12: 7699.73 | I12: =G12+H12 -> 13153.69 | J12: =D12-I12 -> 217837.8 | K12: S/L | L12: 30.00
A13: 4 | B13: 11-Building Imp)Post-Casulty Loss Basis)-bldg | C13: 9/02/20 | D13: 1614.97 | E13: 0 | F13: 0 | G13: 121.6 | H13: 55.91 | I13: =G13+H13 -> 177.51 | J13: =D13-I13 -> 1437.46 | K13: S/L | L13: 30.00
A14: 5 | B14: 2-Land Improvements-bldg 1 | C14: 8/15/18 | D14: 8787.77 | E14: 0 | F14: 2254.61 | G14: 2254.61 | H14: 675.84 | I14: =G14+H14 -> 2930.45 | J14: =D14-I14 -> 5857.32 | K14: 150DB | L14: 15.0
A15: 6 | B15: 13-New Equipment(16 units)-bldg 1 | C15: 12/20/22 | D15: 7565.17 | E15: 0 | F15: 0 | G15: 0 | H15: 0 | I15: =G15+H15 -> 0 | J15: =D15-I15 -> 7565.17 | K15: 200DB | L15: 5.0
A16: 7 | B16: 15-New Equipment(105 units)-bldg 1 | C16: 4/01/23 | D16: 50705.47 | E16: 0 | F16: 0 | G16: 2028.22 | H16: 3245.16 | I16: =G16+H16 -> 5273.38 | J16: =D16-I16 -> 45432.09 | K16: 200DB | L16: 5.0
B17: Grand Total | D17: =SUM(D10:D16) -> 398386.46 | E17: =SUM(E10:E16) -> 0 | F17: =SUM(F10:F16) -> 2254.61 | G17: =SUM(G10:G16) -> 17691.3 | H17: =SUM(H10:H16) -> 15165.39 | I17: =SUM(I10:I16) -> 32856.69 | J17: =SUM(J10:J16) -> 365529.77
A19: After Cost Segregation Correction
A20: Asset | B20: Property Description | C20: Date In Service | D20: Cost | E20: Sec 179 Exp | F20: Bonus Amt | G20: Tax Prior Depreciation | H20: Tax Current Depreciation | I20: End Depreciation | J20: Net Book Value | K20: Method | L20: Period
A21: 1 | B21: 10-Building-Post Casualty Loss Basis-bldg1-5yr | C21: 8/15/18 | D21: 16865.31 | E21: 0 | F21: 16865.31 | G21: 16865.31 | H21: 0 | I21: =G21+H21 -> 16865.31 | J21: =D21-I21 -> 0 | K21: 200DB | L21: 5.0
A22: 2 | B22: 10-Building-Post Casualty Loss Basis-bldg1-30yr | C22: 8/15/18 | D22: 47392.68 | E22: 0 | F22: 0 | G22: 8491.21 | H22: 1579.76 | I22: =G22+H22 -> 10070.97 | J22: =D22-I22 -> 37321.71 | K22: S/L | L22: 30.00
A23: 3 | B23: 12-New Buildings(16 units)-bldg1-5yr | C23: 12/20/22 | D23: 9045.4 | E23: 0 | F23: 9045.4 | G23: 9045.4 | H23: 0 | I23: =G23+H23 -> 9045.4 | J23: =D23-I23 -> 0 | K23: 200DB | L23: 5.0
A24: 4 | B24: 12-New Buildings(16 units)-bldg1-30yr | C24: 12/20/22 | D24: 25418.2 | E24: 0 | F24: 0 | G24: 882.57 | H24: 847.27 | I24: =G24+H24 -> 1729.84 | J24: =D24-I24 -> 23688.36 | K24: S/L | L24: 30.00
A25: 5 | B25: 14-New Buildings(105 units)-bldg1-5yr | C25: 4/01/23 | D25: 60626.59 | E25: 0 | F25: 48501.27 | G25: 50926.33 | H25: 3880.1 | I25: =G25+H25 -> 54806.43 | J25: =D25-I25 -> 5820.16 | K25: 200DB | L25: 5.0
A26: 6 | B26: 14-New Buildings(105 units)-bldg1-30yr | C26: 4/01/23 | D26: 170364.9 | E26: 0 | F26: 0 | G26: 4022.5 | H26: 5678.83 | I26: =G26+H26 -> 9701.33 | J26: =D26-I26 -> 160663.57 | K26: S/L | L26: 30.00
A27: 7 | B27: 11-Building Imp-Post-Casulty Loss Basis-bldg1-5yr | C27: 9/02/20 | D27: 423.87 | E27: 0 | F27: 423.87 | G27: 423.87 | H27: 0 | I27: =G27+H27 -> 423.87 | J27: =D27-I27 -> 0 | K27: 200DB | L27: 5.0
A28: 8 | B28: 11-Building Imp-Post-Casulty Loss Basis-bldg1-30yr | C28: 9/02/20 | D28: 1191.1 | E28: 0 | F28: 0 | G28: 130.68 | H28: 39.7 | I28: =G28+H28 -> 170.38 | J28: =D28-I28 -> 1020.72 | K28: S/L | L28: 30.00
A29: 9 | B29: 2-Land Improvements-bldg1-5yr | C29: 8/15/18 | D29: 2306.46 | E29: 0 | F29: 2306.46 | G29: 2306.46 | H29: 0 | I29: =G29+H29 -> 2306.46 | J29: =D29-I29 -> 0 | K29: 200DB | L29: 5.0
A30: 10 | B30: 2-Land Improvements-bldg1-30yr | C30: 8/15/18 | D30: 6481.31 | E30: 0 | F30: 0 | G30: 1161.22 | H30: 216.04 | I30: =G30+H30 -> 1377.26 | J30: =D30-I30 -> 5104.05 | K30: S/L | L30: 30.00
A31: 11 | B31: 13-New Equipment(16 units)-bldg1-5yr | C31: 12/20/22 | D31: 1985.57 | E31: 0 | F31: 1985.57 | G31: 1985.57 | H31: 0 | I31: =G31+H31 -> 1985.57 | J31: =D31-I31 -> 0 | K31: 200DB | L31: 5.0
A32: 12 | B32: 13-New Equipment(16 units)-bldg1-30yr | C32: 12/20/22 | D32: 5579.6 | E32: 0 | F32: 0 | G32: 193.74 | H32: 185.99 | I32: =G32+H32 -> 379.73 | J32: =D32-I32 -> 5199.87 | K32: S/L | L32: 30.00
... A34: 14 | B34: 15-New Equipment(105 units)-bldg1-30yr | C34: 4/01/23 | D34: 37397.19 | E34: 0 | F34: 0 | G34: 882.99 | H34: 1246.57 | I34: =G34+H34 -> 2129.56 | J34: =D34-I34 -> 35267.63 | K34: S/L | L34: 30.00
B35: Grand Total | D35: =SUM(D21:D34) -> 398386.46 | E35: =SUM(E21:E34) -> 0 | F35: =SUM(F21:F34) -> 89774.5 | G35: =SUM(G21:G34) -> 108496.8 | H35: =SUM(H21:H34) -> 14525.99 | I35: =SUM(I21:I34) -> 123022.79 | J35: =SUM(J21:J34) -> 275363.67
B37: Section 481(a) Adjustment — Regular Tax
B38: Depreciation reported previously | D38: =I17 -> 32856.69
B39: Cost Segregation Corrected Depreciation | D39: =I35 -> 123022.79
B40: Section 481(a) Adjustment — Regular Tax | D40: =D38-D39 -> -90166.1
A42: CALCULATION OF §481(a) ADJUSTMENT — AMT
A43: As Previously Filed — AMT
A44: Asset | B44: Property Description | C44: Date In Service | D44: Cost | E44: Sec 179 Exp | F44: Bonus Amt | G44: AMT Prior Depreciation | H44: AMT Current Depreciation | I44: End Depreciation | J44: Net Book Value | K44: Method | L44: Period
A45: 1 | B45: 10-Building(Post Casualty Loss Basis)-bldg 1 | C45: 8/15/18 | D45: 64257.99 | E45: 0 | F45: 0 | G45: 6636.24 | H45: 2339.95 | I45: =G45+H45 -> 8976.19 | J45: =D45-I45 -> 55281.8 | K45: S/L | L45: 30.00
A46: 2 | B46: 12-New Buildings(16 units)-bldg 1 | C46: 12/20/22 | D46: 34463.6 | E46: 0 | F46: 0 | G46: 1196.67 | H46: 1148.8 | I46: =G46+H46 -> 2345.47 | J46: =D46-I46 -> 32118.13 | K46: S/L | L46: 30.00
A47: 3 | B47: 14-New Buildings(105 units)-bldg 1 | C47: 4/01/23 | D47: 230991.49 | E47: 0 | F47: 0 | G47: 5453.96 | H47: 7699.73 | I47: =G47+H47 -> 13153.69 | J47: =D47-I47 -> 217837.8 | K47: S/L | L47: 30.00
A48: 4 | B48: 11-Building Imp)Post-Casulty Loss Basis)-bldg | C48: 9/02/20 | D48: 1614.97 | E48: 0 | F48: 0 | G48: 121.6 | H48: 55.91 | I48: =G48+H48 -> 177.51 | J48: =D48-I48 -> 1437.46 | K48: S/L | L48: 30.00
A49: 5 | B49: 2-Land Improvements-bldg 1 | C49: 8/15/18 | D49: 8787.77 | E49: 0 | F49: 2254.61 | G49: 2254.61 | H49: 675.84 | I49: =G49+H49 -> 2930.45 | J49: =D49-I49 -> 5857.32 | K49: 150DB | L49: 15.0
A50: 6 | B50: 13-New Equipment(16 units)-bldg 1 | C50: 12/20/22 | D50: 7565.17 | E50: 0 | F50: 0 | G50: 0 | H50: 0 | I50: =G50+H50 -> 0 | J50: =D50-I50 -> 7565.17 | K50: 200DB | L50: 5.0
A51: 7 | B51: 15-New Equipment(105 units)-bldg 1 | C51: 4/01/23 | D51: 50705.47 | E51: 0 | F51: 0 | G51: 2028.22 | H51: 3245.16 | I51: =G51+H51 -> 5273.38 | J51: =D51-I51 -> 45432.09 | K51: 200DB | L51: 5.0
B52: Grand Total | D52: =SUM(D45:D51) -> 398386.46 | E52: =SUM(E45:E51) -> 0 | F52: =SUM(F45:F51) -> 2254.61 | G52: =SUM(G45:G51) -> 17691.3 | H52: =SUM(H45:H51) -> 15165.39 | I52: =SUM(I45:I51) -> 32856.69 | J52: =SUM(J45:J51) -> 365529.77
A54: After Cost Segregation Correction — AMT
A55: Asset | B55: Property Description | C55: Date In Service | D55: Cost | E55: Sec 179 Exp | F55: Bonus Amt | G55: AMT Prior Depreciation | H55: AMT Current Depreciation | I55: End Depreciation | J55: Net Book Value | K55: Method | L55: Period
A56: 1 | B56: 10-Building-Post Casualty Loss Basis-bldg1-5yr | C56: 8/15/18 | D56: 16865.31 | E56: 0 | F56: 16865.31 | G56: 16865.31 | H56: 0 | I56: =G56+H56 -> 16865.31 | J56: =D56-I56 -> 0 | K56: 200DB | L56: 5.0
A57: 2 | B57: 10-Building-Post Casualty Loss Basis-bldg1-30yr | C57: 8/15/18 | D57: 47392.68 | E57: 0 | F57: 0 | G57: 8491.21 | H57: 1579.76 | I57: =G57+H57 -> 10070.97 | J57: =D57-I57 -> 37321.71 | K57: S/L | L57: 30.00
A58: 3 | B58: 12-New Buildings(16 units)-bldg1-5yr | C58: 12/20/22 | D58: 9045.4 | E58: 0 | F58: 9045.4 | G58: 9045.4 | H58: 0 | I58: =G58+H58 -> 9045.4 | J58: =D58-I58 -> 0 | K58: 200DB | L58: 5.0
A59: 4 | B59: 12-New Buildings(16 units)-bldg1-30yr | C59: 12/20/22 | D59: 25418.2 | E59: 0 | F59: 0 | G59: 882.57 | H59: 847.27 | I59: =G59+H59 -> 1729.84 | J59: =D59-I59 -> 23688.36 | K59: S/L | L59: 30.00
A60: 5 | B60: 14-New Buildings(105 units)-bldg1-5yr | C60: 4/01/23 | D60: 60626.59 | E60: 0 | F60: 48501.27 | G60: 50926.33 | H60: 3880.1 | I60: =G60+H60 -> 54806.43 | J60: =D60-I60 -> 5820.16 | K60: 200DB | L60: 5.0
A61: 6 | B61: 14-New Buildings(105 units)-bldg1-30yr | C61: 4/01/23 | D61: 170364.9 | E61: 0 | F61: 0 | G61: 4022.5 | H61: 5678.83 | I61: =G61+H61 -> 9701.33 | J61: =D61-I61 -> 160663.57 | K61: S/L | L61: 30.00
A62: 7 | B62: 11-Building Imp-Post-Casulty Loss Basis-bldg1-5yr | C62: 9/02/20 | D62: 423.87 | E62: 0 | F62: 423.87 | G62: 423.87 | H62: 0 | I62: =G62+H62 -> 423.87 | J62: =D62-I62 -> 0 | K62: 200DB | L62: 5.0
A63: 8 | B63: 11-Building Imp-Post-Casulty Loss Basis-bldg1-30yr | C63: 9/02/20 | D63: 1191.1 | E63: 0 | F63: 0 | G63: 130.68 | H63: 39.7 | I63: =G63+H63 -> 170.38 | J63: =D63-I63 -> 1020.72 | K63: S/L | L63: 30.00
A64: 9 | B64: 2-Land Improvements-bldg1-5yr | C64: 8/15/18 | D64: 2306.46 | E64: 0 | F64: 2306.46 | G64: 2306.46 | H64: 0 | I64: =G64+H64 -> 2306.46 | J64: =D64-I64 -> 0 | K64: 200DB | L64: 5.0
A65: 10 | B65: 2-Land Improvements-bldg1-30yr | C65: 8/15/18 | D65: 6481.31 | E65: 0 | F65: 0 | G65: 1161.22 | H65: 216.04 | I65: =G65+H65 -> 1377.26 | J65: =D65-I65 -> 5104.05 | K65: S/L | L65: 30.00
A66: 11 | B66: 13-New Equipment(16 units)-bldg1-5yr | C66: 12/20/22 | D66: 1985.57 | E66: 0 | F66: 1985.57 | G66: 1985.57 | H66: 0 | I66: =G66+H66 -> 1985.57 | J66: =D66-I66 -> 0 | K66: 200DB | L66: 5.0
A67: 12 | B67: 13-New Equipment(16 units)-bldg1-30yr | C67: 12/20/22 | D67: 5579.6 | E67: 0 | F67: 0 | G67: 193.74 | H67: 185.99 | I67: =G67+H67 -> 379.73 | J67: =D67-I67 -> 5199.87 | K67: S/L | L67: 30.00
... A69: 14 | B69: 15-New Equipment(105 units)-bldg1-30yr | C69: 4/01/23 | D69: 37397.19 | E69: 0 | F69: 0 | G69: 882.99 | H69: 1246.57 | I69: =G69+H69 -> 2129.56 | J69: =D69-I69 -> 35267.63 | K69: S/L | L69: 30.00
B70: Grand Total | D70: =SUM(D56:D69) -> 398386.46 | E70: =SUM(E56:E69) -> 0 | F70: =SUM(F56:F69) -> 89774.5 | G70: =SUM(G56:G69) -> 108496.8 | H70: =SUM(H56:H69) -> 14525.99 | I70: =SUM(I56:I69) -> 123022.79 | J70: =SUM(J56:J69) -> 275363.67
B72: Section 481(a) Adjustment — AMT
B73: Depreciation reported previously | D73: =I52 -> 32856.69
B74: Cost Segregation Corrected Depreciation | D74: =I70 -> 123022.79
B75: Section 481(a) Adjustment — AMT | D75: =D73-D74 -> -90166.1
A77: COST SEGREGATION STUDY — COST SUMMARY
B78: Total Building Cost | D78: =D115 -> 398386.46
B79: Building Components: 5 Year | D79: =F115 -> 104561.48
B80: % of Cost | D80: =F116 -> 0.26246243
B81: Building Structure: 30 Year | D81: =H115 -> 293824.98
B82: % of Cost | D82: =H116 -> 0.73753757
A84: COST SEGREGATION STUDY — COST DETAIL
B85: Property Category | D85: Cost | F85: 5 Year | H85: 30 Year
B86: Building Components
B87: Cabinets / Millwork | D87: =SUM(F87:H87) -> 31452.73 | F87: 31452.73
B88: Moldings | D88: =SUM(F88:H88) -> 8394.17 | F88: 8394.17
B89: Flooring - Vinyl Plank | D89: =SUM(F89:H89) -> 32815.89 | F89: 32815.89
B90: Window Treatments | D90: =SUM(F90:H90) -> 2648.72 | F90: 2648.72
B91: Building Signage | D91: =SUM(F91:H91) -> 287.16 | F91: 287.16
B92: Specialty Electrical - Appliances | D92: =SUM(F92:H92) -> 5344.3 | F92: 5344.3
B93: Communication / Data | D93: =SUM(F93:H93) -> 2858.97 | F93: 2858.97
B94: Specialty Plumbing - Kitchen Sinks | D94: =SUM(F94:H94) -> 9687.68 | F94: 9687.68
B95: Security / Exterior Lighting | D95: =SUM(F95:H95) -> 2139.23 | F95: 2139.23
B96: Canopies / Awnings | D96: =SUM(F96:H96) -> 605.69 | F96: 605.69
B97: Appliances | D97: =SUM(F97:H97) -> 8326.94 | F97: 8326.94
B98: Building Structure
B99: Roofing Systems | D99: =SUM(F99:H99) -> 16256.27 | H99: 16256.27
B100: Foundations | D100: =SUM(F100:H100) -> 21691.78 | H100: 21691.78
B101: HVAC | D101: =SUM(F101:H101) -> 31892.38 | H101: 31892.38
B102: Electrical | D102: =SUM(F102:H102) -> 29436.62 | H102: 29436.62
B103: Plumbing | D103: =SUM(F103:H103) -> 27723.88 | H103: 27723.88
B104: Fire Protection & Alarm | D104: =SUM(F104:H104) -> 1864.29 | H104: 1864.29
B105: Exterior Façade / Building Skin | D105: =SUM(F105:H105) -> 21001.52 | H105: 21001.52
B106: Doors & Frames | D106: =SUM(F106:H106) -> 16292.68 | H106: 16292.68
B107: Windows | D107: =SUM(F107:H107) -> 12258.17 | H107: 12258.17
B108: Ceiling Systems | D108: =SUM(F108:H108) -> 14614.91 | H108: 14614.91
B109: Interior Framing / Partitions | D109: =SUM(F109:H109) -> 38542.73 | H109: 38542.73
B110: Painting | D110: =SUM(F110:H110) -> 15289.77 | H110: 15289.77
...

Sheet Building 2
A1: St Charles Housing LP
A2: St. Charles — 1011 W 18th St, Lake Charles, LA 70607
A3: EIN: 82-5349206 · FYE: December 31, 2024 · Year of Change: 1/1/2024
A4: Building 2 — Attachment to Form 3115 (DCN #7, Rev. Proc. 2024-23 §6.01)
A5: Source: CSSI Report #107752-24, "St. Charles Housing LP_107752-24_3115_Combined.pdf"
A7: CALCULATION OF §481(a) ADJUSTMENT — REGULAR TAX
A8: As Previously Filed
A9: Asset | B9: Property Description | C9: Date In Service | D9: Cost | E9: Sec 179 Exp | F9: Bonus Amt | G9: Tax Prior Depreciation | H9: Tax Current Depreciation | I9: End Depreciation | J9: Net Book Value | K9: Method | L9: Period
A10: 1 | B10: 10-Building(Post Casualty Loss Basis)-bldg 2 | C10: 8/15/18 | D10: 64273.15 | E10: 0 | F10: 0 | G10: 6637.81 | H10: 2340.51 | I10: =G10+H10 -> 8978.32 | J10: =D10-I10 -> 55294.83 | K10: S/L | L10: 30.00
A11: 2 | B11: 12-New Buildings(16 units)-bldg 2 | C11: 12/20/22 | D11: 34471.7 | E11: 0 | F11: 0 | G11: 1196.96 | H11: 1149.05 | I11: =G11+H11 -> 2346.01 | J11: =D11-I11 -> 32125.69 | K11: S/L | L11: 30.00
A12: 3 | B12: 14-New Buildings(105 units)-bldg 2 | C12: 4/01/23 | D12: 231045.9 | E12: 0 | F12: 0 | G12: 5455.25 | H12: 7701.54 | I12: =G12+H12 -> 13156.79 | J12: =D12-I12 -> 217889.11 | K12: S/L | L12: 30.00
A13: 4 | B13: 11-Building Imp)Post-Casulty Loss Basis)-bldg | C13: 9/02/20 | D13: 1615.35 | E13: 0 | F13: 0 | G13: 121.63 | H13: 55.93 | I13: =G13+H13 -> 177.56 | J13: =D13-I13 -> 1437.79 | K13: S/L | L13: 30.00
A14: 5 | B14: 2-Land Improvements-bldg 2 | C14: 8/15/18 | D14: 8789.84 | E14: 0 | F14: 2255.14 | G14: 2255.14 | H14: 676 | I14: =G14+H14 -> 2931.14 | J14: =D14-I14 -> 5858.7 | K14: 150DB | L14: 15.0
A15: 6 | B15: 13-New Equipment(16 units)-bldg 2 | C15: 12/20/22 | D15: 7566.95 | E15: 0 | F15: 0 | G15: 0 | H15: 0 | I15: =G15+H15 -> 0 | J15: =D15-I15 -> 7566.95 | K15: 200DB | L15: 5.0
A16: 7 | B16: 15-New Equipment(105 units)-bldg 2 | C16: 4/01/23 | D16: 50717.41 | E16: 0 | F16: 0 | G16: 2028.69 | H16: 3245.92 | I16: =G16+H16 -> 5274.61 | J16: =D16-I16 -> 45442.8 | K16: 200DB | L16: 5.0
B17: Grand Total | D17: =SUM(D10:D16) -> 398480.3 | E17: =SUM(E10:E16) -> 0 | F17: =SUM(F10:F16) -> 2255.14 | G17: =SUM(G10:G16) -> 17695.48 | H17: =SUM(H10:H16) -> 15168.95 | I17: =SUM(I10:I16) -> 32864.43 | J17: =SUM(J10:J16) -> 365615.87
A19: After Cost Segregation Correction
A20: Asset | B20: Property Description | C20: Date In Service | D20: Cost | E20: Sec 179 Exp | F20: Bonus Amt | G20: Tax Prior Depreciation | H20: Tax Current Depreciation | I20: End Depreciation | J20: Net Book Value | K20: Method | L20: Period
A21: 1 | B21: 10-Building-Post Casualty Loss Basis-bldg2-5y | C21: 8/15/18 | D21: 16880.45 | E21: 0 | F21: 16880.45 | G21: 16880.45 | H21: 0 | I21: =G21+H21 -> 16880.45 | J21: =D21-I21 -> 0 | K21: 200DB | L21: 5.0
A22: 2 | B22: 10-Building-Post Casualty Loss Basis-bldg2-30 | C22: 8/15/18 | D22: 47392.7 | E22: 0 | F22: 0 | G22: 8491.21 | H22: 1579.76 | I22: =G22+H22 -> 10070.97 | J22: =D22-I22 -> 37321.73 | K22: S/L | L22: 30.00
A23: 3 | B23: 12-New Buildings(16 units)-bldg2-5yr | C23: 12/20/22 | D23: 9053.51 | E23: 0 | F23: 9053.51 | G23: 9053.51 | H23: 0 | I23: =G23+H23 -> 9053.51 | J23: =D23-I23 -> 0 | K23: 200DB | L23: 5.0
A24: 4 | B24: 12-New Buildings(16 units)-bldg2-30yr | C24: 12/20/22 | D24: 25418.19 | E24: 0 | F24: 0 | G24: 882.57 | H24: 847.27 | I24: =G24+H24 -> 1729.84 | J24: =D24-I24 -> 23688.35 | K24: S/L | L24: 30.00
A25: 5 | B25: 14-New Buildings(105 units)-bldg2-5yr | C25: 4/01/23 | D25: 60681 | E25: 0 | F25: 48544.8 | G25: 50972.04 | H25: 3883.58 | I25: =G25+H25 -> 54855.62 | J25: =D25-I25 -> 5825.38 | K25: 200DB | L25: 5.0
A26: 6 | B26: 14-New Buildings(105 units)-bldg2-30yr | C26: 4/01/23 | D26: 170364.9 | E26: 0 | F26: 0 | G26: 4022.5 | H26: 5678.83 | I26: =G26+H26 -> 9701.33 | J26: =D26-I26 -> 160663.57 | K26: S/L | L26: 30.00
A27: 7 | B27: 11-Building Imp-Post-Casulty Loss Basis-bldg2 | C27: 9/02/20 | D27: 424.25 | E27: 0 | F27: 424.25 | G27: 424.25 | H27: 0 | I27: =G27+H27 -> 424.25 | J27: =D27-I27 -> 0 | K27: 200DB | L27: 5.0
A28: 8 | B28: 11-Building Imp-Post-Casulty Loss Basis-bldg2 | C28: 9/02/20 | D28: 1191.1 | E28: 0 | F28: 0 | G28: 130.68 | H28: 39.7 | I28: =G28+H28 -> 170.38 | J28: =D28-I28 -> 1020.72 | K28: S/L | L28: 30.00
A29: 9 | B29: 2-Land Improvements-bldg2-5yr | C29: 8/15/18 | D29: 2308.53 | E29: 0 | F29: 2308.53 | G29: 2308.53 | H29: 0 | I29: =G29+H29 -> 2308.53 | J29: =D29-I29 -> 0 | K29: 200DB | L29: 5.0
A30: 10 | B30: 2-Land Improvements-bldg2-30yr | C30: 8/15/18 | D30: 6481.31 | E30: 0 | F30: 0 | G30: 1161.22 | H30: 216.04 | I30: =G30+H30 -> 1377.26 | J30: =D30-I30 -> 5104.05 | K30: S/L | L30: 30.00
A31: 11 | B31: 13-New Equipment(16 units)-bldg2-5yr | C31: 12/20/22 | D31: 1987.35 | E31: 0 | F31: 1987.35 | G31: 1987.35 | H31: 0 | I31: =G31+H31 -> 1987.35 | J31: =D31-I31 -> 0 | K31: 200DB | L31: 5.0
A32: 12 | B32: 13-New Equipment(16 units)-bldg2-30yr | C32: 12/20/22 | D32: 5579.6 | E32: 0 | F32: 0 | G32: 193.74 | H32: 185.99 | I32: =G32+H32 -> 379.73 | J32: =D32-I32 -> 5199.87 | K32: S/L | L32: 30.00
... A34: 14 | B34: 15-New Equipment(105 units)-bldg2-30yr | C34: 4/01/23 | D34: 37397.18 | E34: 0 | F34: 0 | G34: 882.99 | H34: 1246.57 | I34: =G34+H34 -> 2129.56 | J34: =D34-I34 -> 35267.62 | K34: S/L | L34: 30.00
B35: Grand Total | D35: =SUM(D21:D34) -> 398480.3 | E35: =SUM(E21:E34) -> 0 | F35: =SUM(F21:F34) -> 89855.07 | G35: =SUM(G21:G34) -> 108580.03 | H35: =SUM(H21:H34) -> 14530.24 | I35: =SUM(I21:I34) -> 123110.27 | J35: =SUM(J21:J34) -> 275370.03
B37: Section 481(a) Adjustment — Regular Tax
B38: Depreciation reported previously | D38: =I17 -> 32864.43
B39: Cost Segregation Corrected Depreciation | D39: =I35 -> 123110.27
B40: Section 481(a) Adjustment — Regular Tax | D40: =D38-D39 -> -90245.84
A42: CALCULATION OF §481(a) ADJUSTMENT — AMT
A43: As Previously Filed — AMT
A44: Asset | B44: Property Description | C44: Date In Service | D44: Cost | E44: Sec 179 Exp | F44: Bonus Amt | G44: AMT Prior Depreciation | H44: AMT Current Depreciation | I44: End Depreciation | J44: Net Book Value | K44: Method | L44: Period
A45: 1 | B45: 10-Building(Post Casualty Loss Basis)-bldg 2 | C45: 8/15/18 | D45: 64273.15 | E45: 0 | F45: 0 | G45: 6637.81 | H45: 2340.51 | I45: =G45+H45 -> 8978.32 | J45: =D45-I45 -> 55294.83 | K45: S/L | L45: 30.00
A46: 2 | B46: 12-New Buildings(16 units)-bldg 2 | C46: 12/20/22 | D46: 34471.7 | E46: 0 | F46: 0 | G46: 1196.96 | H46: 1149.05 | I46: =G46+H46 -> 2346.01 | J46: =D46-I46 -> 32125.69 | K46: S/L | L46: 30.00
A47: 3 | B47: 14-New Buildings(105 units)-bldg 2 | C47: 4/01/23 | D47: 231045.9 | E47: 0 | F47: 0 | G47: 5455.25 | H47: 7701.54 | I47: =G47+H47 -> 13156.79 | J47: =D47-I47 -> 217889.11 | K47: S/L | L47: 30.00
A48: 4 | B48: 11-Building Imp)Post-Casulty Loss Basis)-bldg | C48: 9/02/20 | D48: 1615.35 | E48: 0 | F48: 0 | G48: 121.63 | H48: 55.93 | I48: =G48+H48 -> 177.56 | J48: =D48-I48 -> 1437.79 | K48: S/L | L48: 30.00
A49: 5 | B49: 2-Land Improvements-bldg 2 | C49: 8/15/18 | D49: 8789.84 | E49: 0 | F49: 2255.14 | G49: 2255.14 | H49: 676 | I49: =G49+H49 -> 2931.14 | J49: =D49-I49 -> 5858.7 | K49: 150DB | L49: 15.0
A50: 6 | B50: 13-New Equipment(16 units)-bldg 2 | C50: 12/20/22 | D50: 7566.95 | E50: 0 | F50: 0 | G50: 0 | H50: 0 | I50: =G50+H50 -> 0 | J50: =D50-I50 -> 7566.95 | K50: 200DB | L50: 5.0
A51: 7 | B51: 15-New Equipment(105 units)-bldg 2 | C51: 4/01/23 | D51: 50717.41 | E51: 0 | F51: 0 | G51: 2028.69 | H51: 3245.92 | I51: =G51+H51 -> 5274.61 | J51: =D51-I51 -> 45442.8 | K51: 200DB | L51: 5.0
B52: Grand Total | D52: =SUM(D45:D51) -> 398480.3 | E52: =SUM(E45:E51) -> 0 | F52: =SUM(F45:F51) -> 2255.14 | G52: =SUM(G45:G51) -> 17695.48 | H52: =SUM(H45:H51) -> 15168.95 | I52: =SUM(I45:I51) -> 32864.43 | J52: =SUM(J45:J51) -> 365615.87
A54: After Cost Segregation Correction — AMT
A55: Asset | B55: Property Description | C55: Date In Service | D55: Cost | E55: Sec 179 Exp | F55: Bonus Amt | G55: AMT Prior Depreciation | H55: AMT Current Depreciation | I55: End Depreciation | J55: Net Book Value | K55: Method | L55: Period
A56: 1 | B56: 12-New Buildings(16 units)-bldg2-5yr | C56: 12/20/22 | D56: 9053.51 | E56: 0 | F56: 9053.51 | G56: 9053.51 | H56: 0 | I56: =G56+H56 -> 9053.51 | J56: =D56-I56 -> 0 | K56: 200DB | L56: 5.0
A57: 2 | B57: 12-New Buildings(16 units)-bldg2-30yr | C57: 12/20/22 | D57: 25418.19 | E57: 0 | F57: 0 | G57: 882.57 | H57: 847.27 | I57: =G57+H57 -> 1729.84 | J57: =D57-I57 -> 23688.35 | K57: S/L | L57: 30.00
A58: 3 | B58: 14-New Buildings(105 units)-bldg2-5yr | C58: 4/01/23 | D58: 60681 | E58: 0 | F58: 48544.8 | G58: 50972.04 | H58: 3883.58 | I58: =G58+H58 -> 54855.62 | J58: =D58-I58 -> 5825.38 | K58: 200DB | L58: 5.0
A59: 4 | B59: 14-New Buildings(105 units)-bldg2-30yr | C59: 4/01/23 | D59: 170364.9 | E59: 0 | F59: 0 | G59: 4022.5 | H59: 5678.83 | I59: =G59+H59 -> 9701.33 | J59: =D59-I59 -> 160663.57 | K59: S/L | L59: 30.00
A60: 5 | B60: 2-Land Improvements-bldg2-5yr | C60: 8/15/18 | D60: 2308.53 | E60: 0 | F60: 2308.53 | G60: 2308.53 | H60: 0 | I60: =G60+H60 -> 2308.53 | J60: =D60-I60 -> 0 | K60: 200DB | L60: 5.0
A61: 6 | B61: 2-Land Improvements-bldg2-30yr | C61: 8/15/18 | D61: 6481.31 | E61: 0 | F61: 0 | G61: 1161.22 | H61: 216.04 | I61: =G61+H61 -> 1377.26 | J61: =D61-I61 -> 5104.05 | K61: S/L | L61: 30.00
A62: 7 | B62: 13-New Equipment(16 units)-bldg2-5yr | C62: 12/20/22 | D62: 1987.35 | E62: 0 | F62: 1987.35 | G62: 1987.35 | H62: 0 | I62: =G62+H62 -> 1987.35 | J62: =D62-I62 -> 0 | K62: 200DB | L62: 5.0
A63: 8 | B63: 13-New Equipment(16 units)-bldg2-30yr | C63: 12/20/22 | D63: 5579.6 | E63: 0 | F63: 0 | G63: 193.74 | H63: 185.99 | I63: =G63+H63 -> 379.73 | J63: =D63-I63 -> 5199.87 | K63: S/L | L63: 30.00
A64: 9 | B64: 15-New Equipment(105 units)-bldg2-5yr | C64: 4/01/23 | D64: 13320.23 | E64: 0 | F64: 10656.18 | G64: 11188.99 | H64: 852.5 | I64: =G64+H64 -> 12041.49 | J64: =D64-I64 -> 1278.74 | K64: 200DB | L64: 5.0
A65: 10 | B65: 15-New Equipment(105 units)-bldg2-30yr | C65: 4/01/23 | D65: 37397.18 | E65: 0 | F65: 0 | G65: 882.99 | H65: 1246.57 | I65: =G65+H65 -> 2129.56 | J65: =D65-I65 -> 35267.62 | K65: S/L | L65: 30.00
B66: Grand Total | D66: =SUM(D56:D65) -> 332591.8 | E66: =SUM(E56:E65) -> 0 | F66: =SUM(F56:F65) -> 72550.37 | G66: =SUM(G56:G65) -> 82653.44 | H66: =SUM(H56:H65) -> 12910.78 | I66: =SUM(I56:I65) -> 95564.22 | J66: =SUM(J56:J65) -> 237027.58
B68: Section 481(a) Adjustment — AMT
B69: Depreciation reported previously | D69: =I52 -> 32864.43
B70: Cost Segregation Corrected Depreciation | D70: =I66 -> 95564.22
B71: Section 481(a) Adjustment — AMT | D71: =D69-D70 -> -62699.79
A73: COST SEGREGATION STUDY — COST SUMMARY
B74: Total Building Cost | D74: =D111 -> 398480.3
B75: Building Components: 5 Year | D75: =F111 -> 104655.32
B76: % of Cost | D76: =F112 -> 0.26263612
B77: Building Structure: 30 Year | D77: =H111 -> 293824.98
B78: % of Cost | D78: =H112 -> 0.73736388
A80: COST SEGREGATION STUDY — COST DETAIL
B81: Property Category | D81: Cost | F81: 5 Year | H81: 30 Year
B82: Building Components
B83: Cabinets / Millwork | D83: =SUM(F83:H83) -> 31452.73 | F83: 31452.73
B84: Moldings | D84: =SUM(F84:H84) -> 8394.17 | F84: 8394.17
B85: Flooring - Vinyl Plank | D85: =SUM(F85:H85) -> 32815.89 | F85: 32815.89
B86: Window Treatments | D86: =SUM(F86:H86) -> 2648.72 | F86: 2648.72
B87: Building Signage | D87: =SUM(F87:H87) -> 381 | F87: 381
B88: Specialty Electrical - Appliances | D88: =SUM(F88:H88) -> 5344.3 | F88: 5344.3
B89: Communication / Data | D89: =SUM(F89:H89) -> 2858.97 | F89: 2858.97
B90: Specialty Plumbing - Kitchen Sinks | D90: =SUM(F90:H90) -> 9687.68 | F90: 9687.68
B91: Security / Exterior Lighting | D91: =SUM(F91:H91) -> 2139.23 | F91: 2139.23
B92: Canopies / Awnings | D92: =SUM(F92:H92) -> 605.69 | F92: 605.69
B93: Appliances | D93: =SUM(F93:H93) -> 8326.94 | F93: 8326.94
B94: Building Structure
B95: Roofing Systems | D95: =SUM(F95:H95) -> 16256.28 | H95: 16256.28
B96: Foundations | D96: =SUM(F96:H96) -> 21691.78 | H96: 21691.78
B97: HVAC | D97: =SUM(F97:H97) -> 31892.38 | H97: 31892.38
B98: Electrical | D98: =SUM(F98:H98) -> 29436.62 | H98: 29436.62
B99: Plumbing | D99: =SUM(F99:H99) -> 27723.88 | H99: 27723.88
B100: Fire Protection & Alarm | D100: =SUM(F100:H100) -> 1864.29 | H100: 1864.29
B101: Exterior Façade / Building Skin | D101: =SUM(F101:H101) -> 21001.51 | H101: 21001.51
B102: Doors & Frames | D102: =SUM(F102:H102) -> 16292.68 | H102: 16292.68
B103: Windows | D103: =SUM(F103:H103) -> 12258.17 | H103: 12258.17
B104: Ceiling Systems | D104: =SUM(F104:H104) -> 14614.91 | H104: 14614.91
B105: Interior Framing / Partitions | D105: =SUM(F105:H105) -> 38542.73 | H105: 38542.73
B106: Painting | D106: =SUM(F106:H106) -> 15289.77 | H106: 15289.77
... B110: Cabinets / Millwork - Restrooms | D110: =SUM(F110:H110) -> 1880.89 | H110: 1880.89
B111: Total Building Cost | D111: =SUM(D82:D110) -> 398480.3 | F111: =SUM(F82:F110) -> 104655.32 | H111: =SUM(H82:H110) -> 293824.98
B112: % of Cost | F112: =F111/D111 -> 0.26263612 | H112: =H111/D111 -> 0.73736388
...

Sheet Building 3
A1: St Charles Housing LP
A2: St. Charles — 1011 W 18th St, Lake Charles, LA 70607
A3: EIN: 82-5349206 · FYE: December 31, 2024 · Year of Change: 1/1/2024
A4: Building 3 — Attachment to Form 3115 (DCN #7, Rev. Proc. 2024-23 §6.01)
A5: Source: CSSI Report #107752-24, "St. Charles Housing LP_107752-24_3115_Combined.pdf"
A7: CALCULATION OF §481(a) ADJUSTMENT — REGULAR TAX
A8: As Previously Filed
A9: Asset | B9: Property Description | C9: Date In Service | D9: Cost | E9: Sec 179 Exp | F9: Bonus Amt | G9: Tax Prior Depreciation | H9: Tax Current Depreciation | I9: End Depreciation | J9: Net Book Value | K9: Method | L9: Period
A10: 1 | B10: 10-Building(Post Casualty Loss Basis)-bldg 3 | C10: 8/15/18 | D10: 64275.31 | E10: 0 | F10: 0 | G10: 6638.03 | H10: 2340.59 | I10: =G10+H10 -> 8978.62 | J10: =D10-I10 -> 55296.69 | K10: S/L | L10: 30.00
A11: 2 | B11: 12-New Buildings(16 units)-bldg 3 | C11: 12/20/22 | D11: 34472.86 | E11: 0 | F11: 0 | G11: 1197 | H11: 1149.09 | I11: =G11+H11 -> 2346.09 | J11: =D11-I11 -> 32126.77 | K11: S/L | L11: 30.00
A12: 3 | B12: 14-New Buildings(105 units)-bldg 3 | C12: 4/01/23 | D12: 231053.67 | E12: 0 | F12: 0 | G12: 5455.43 | H12: 7701.8 | I12: =G12+H12 -> 13157.23 | J12: =D12-I12 -> 217896.44 | K12: S/L | L12: 30.00
A13: 4 | B13: 11-Building Imp)Post-Casulty Loss Basis)-bldg | C13: 9/02/20 | D13: 1615.41 | E13: 0 | F13: 0 | G13: 121.63 | H13: 55.93 | I13: =G13+H13 -> 177.56 | J13: =D13-I13 -> 1437.85 | K13: S/L | L13: 30.00
A14: 5 | B14: 2-Land Improvements-bldg 3 | C14: 8/15/18 | D14: 8790.13 | E14: 0 | F14: 2255.21 | G14: 2255.21 | H14: 676.02 | I14: =G14+H14 -> 2931.23 | J14: =D14-I14 -> 5858.9 | K14: 150DB | L14: 15.0
A15: 6 | B15: 13-New Equipment(16 units)-bldg 3 | C15: 12/20/22 | D15: 7567.2 | E15: 0 | F15: 0 | G15: 0 | H15: 0 | I15: =G15+H15 -> 0 | J15: =D15-I15 -> 7567.2 | K15: 200DB | L15: 5.0
A16: 7 | B16: 15-New Equipment(105 units)-bldg 3 | C16: 4/01/23 | D16: 50719.12 | E16: 0 | F16: 0 | G16: 2028.76 | H16: 3246.03 | I16: =G16+H16 -> 5274.79 | J16: =D16-I16 -> 45444.33 | K16: 200DB | L16: 5.0
B17: Grand Total | D17: =SUM(D10:D16) -> 398493.7 | E17: =SUM(E10:E16) -> 0 | F17: =SUM(F10:F16) -> 2255.21 | G17: =SUM(G10:G16) -> 17696.06 | H17: =SUM(H10:H16) -> 15169.46 | I17: =SUM(I10:I16) -> 32865.52 | J17: =SUM(J10:J16) -> 365628.18
A19: After Cost Segregation Correction
A20: Asset | B20: Property Description | C20: Date In Service | D20: Cost | E20: Sec 179 Exp | F20: Bonus Amt | G20: Tax Prior Depreciation | H20: Tax Current Depreciation | I20: End Depreciation | J20: Net Book Value | K20: Method | L20: Period
A21: 1 | B21: 10-Building-Post Casualty Loss Basis-bldg3-5y | C21: 8/15/18 | D21: 16882.61 | E21: 0 | F21: 16882.61 | G21: 16882.61 | H21: 0 | I21: =G21+H21 -> 16882.61 | J21: =D21-I21 -> 0 | K21: 200DB | L21: 5.0
A22: 2 | B22: 10-Building-Post Casualty Loss Basis-bldg3-30 | C22: 8/15/18 | D22: 47392.7 | E22: 0 | F22: 0 | G22: 8491.21 | H22: 1579.76 | I22: =G22+H22 -> 10070.97 | J22: =D22-I22 -> 37321.73 | K22: S/L | L22: 30.00
A23: 3 | B23: 12-New Buildings(16 units)-bldg3-5yr | C23: 12/20/22 | D23: 9054.67 | E23: 0 | F23: 9054.67 | G23: 9054.67 | H23: 0 | I23: =G23+H23 -> 9054.67 | J23: =D23-I23 -> 0 | K23: 200DB | L23: 5.0
A24: 4 | B24: 12-New Buildings(16 units)-bldg3-30yr | C24: 12/20/22 | D24: 25418.19 | E24: 0 | F24: 0 | G24: 882.57 | H24: 847.27 | I24: =G24+H24 -> 1729.84 | J24: =D24-I24 -> 23688.35 | K24: S/L | L24: 30.00
A25: 5 | B25: 14-New Buildings(105 units)-bldg3-5yr | C25: 4/01/23 | D25: 60688.77 | E25: 0 | F25: 48551.02 | G25: 50978.57 | H25: 3884.08 | I25: =G25+H25 -> 54862.65 | J25: =D25-I25 -> 5826.12 | K25: 200DB | L25: 5.0
A26: 6 | B26: 14-New Buildings(105 units)-bldg3-30yr | C26: 4/01/23 | D26: 170364.9 | E26: 0 | F26: 0 | G26: 4022.5 | H26: 5678.83 | I26: =G26+H26 -> 9701.33 | J26: =D26-I26 -> 160663.57 | K26: S/L | L26: 30.00
A27: 7 | B27: 11-Building Imp-Post-Casulty Loss Basis-bldg3 | C27: 9/02/20 | D27: 424.31 | E27: 0 | F27: 424.31 | G27: 424.31 | H27: 0 | I27: =G27+H27 -> 424.31 | J27: =D27-I27 -> 0 | K27: 200DB | L27: 5.0
A28: 8 | B28: 11-Building Imp-Post-Casulty Loss Basis-bldg3 | C28: 9/02/20 | D28: 1191.1 | E28: 0 | F28: 0 | G28: 130.68 | H28: 39.7 | I28: =G28+H28 -> 170.38 | J28: =D28-I28 -> 1020.72 | K28: S/L | L28: 30.00
A29: 9 | B29: 2-Land Improvements-bldg3-5yr | C29: 8/15/18 | D29: 2308.82 | E29: 0 | F29: 2308.82 | G29: 2308.82 | H29: 0 | I29: =G29+H29 -> 2308.82 | J29: =D29-I29 -> 0 | K29: 200DB | L29: 5.0
A30: 10 | B30: 2-Land Improvements-bldg3-30yr | C30: 8/15/18 | D30: 6481.31 | E30: 0 | F30: 0 | G30: 1161.22 | H30: 216.04 | I30: =G30+H30 -> 1377.26 | J30: =D30-I30 -> 5104.05 | K30: S/L | L30: 30.00
A31: 11 | B31: 13-New Equipment(16 units)-bldg3-5yr | C31: 12/20/22 | D31: 1987.61 | E31: 0 | F31: 1987.61 | G31: 1987.61 | H31: 0 | I31: =G31+H31 -> 1987.61 | J31: =D31-I31 -> 0 | K31: 200DB | L31: 5.0
A32: 12 | B32: 13-New Equipment(16 units)-bldg3-30yr | C32: 12/20/22 | D32: 5579.59 | E32: 0 | F32: 0 | G32: 193.74 | H32: 185.99 | I32: =G32+H32 -> 379.73 | J32: =D32-I32 -> 5199.86 | K32: S/L | L32: 30.00
... A34: 14 | B34: 15-New Equipment(105 units)-bldg3-30yr | C34: 4/01/23 | D34: 37397.19 | E34: 0 | F34: 0 | G34: 882.99 | H34: 1246.57 | I34: =G34+H34 -> 2129.56 | J34: =D34-I34 -> 35267.63 | K34: S/L | L34: 30.00
B35: Grand Total | D35: =SUM(D21:D34) -> 398493.7 | E35: =SUM(E21:E34) -> 0 | F35: =SUM(F21:F34) -> 89866.58 | G35: =SUM(G21:G34) -> 108591.92 | H35: =SUM(H21:H34) -> 14530.84 | I35: =SUM(I21:I34) -> 123122.76 | J35: =SUM(J21:J34) -> 275370.94
B37: Section 481(a) Adjustment — Regular Tax
B38: Depreciation reported previously | D38: =I17 -> 32865.52
B39: Cost Segregation Corrected Depreciation | D39: =I35 -> 123122.76
B40: Section 481(a) Adjustment — Regular Tax | D40: =D38-D39 -> -90257.24
A42: CALCULATION OF §481(a) ADJUSTMENT — AMT
A43: As Previously Filed — AMT
A44: Asset | B44: Property Description | C44: Date In Service | D44: Cost | E44: Sec 179 Exp | F44: Bonus Amt | G44: AMT Prior Depreciation | H44: AMT Current Depreciation | I44: End Depreciation | J44: Net Book Value | K44: Method | L44: Period
A45: 1 | B45: 10-Building(Post Casualty Loss Basis)-bldg 3 | C45: 8/15/18 | D45: 64275.31 | E45: 0 | F45: 0 | G45: 6638.03 | H45: 2340.59 | I45: =G45+H45 -> 8978.62 | J45: =D45-I45 -> 55296.69 | K45: S/L | L45: 30.00
A46: 2 | B46: 12-New Buildings(16 units)-bldg 3 | C46: 12/20/22 | D46: 34472.86 | E46: 0 | F46: 0 | G46: 1197 | H46: 1149.09 | I46: =G46+H46 -> 2346.09 | J46: =D46-I46 -> 32126.77 | K46: S/L | L46: 30.00
A47: 3 | B47: 14-New Buildings(105 units)-bldg 3 | C47: 4/01/23 | D47: 231053.67 | E47: 0 | F47: 0 | G47: 5455.43 | H47: 7701.8 | I47: =G47+H47 -> 13157.23 | J47: =D47-I47 -> 217896.44 | K47: S/L | L47: 30.00
A48: 4 | B48: 11-Building Imp)Post-Casulty Loss Basis)-bldg | C48: 9/02/20 | D48: 1615.41 | E48: 0 | F48: 0 | G48: 121.63 | H48: 55.93 | I48: =G48+H48 -> 177.56 | J48: =D48-I48 -> 1437.85 | K48: S/L | L48: 30.00
A49: 5 | B49: 2-Land Improvements-bldg 3 | C49: 8/15/18 | D49: 8790.13 | E49: 0 | F49: 2255.21 | G49: 2255.21 | H49: 676.02 | I49: =G49+H49 -> 2931.23 | J49: =D49-I49 -> 5858.9 | K49: 150DB | L49: 15.0
A50: 6 | B50: 13-New Equipment(16 units)-bldg 3 | C50: 12/20/22 | D50: 7567.2 | E50: 0 | F50: 0 | G50: 0 | H50: 0 | I50: =G50+H50 -> 0 | J50: =D50-I50 -> 7567.2 | K50: 200DB | L50: 5.0
A51: 7 | B51: 15-New Equipment(105 units)-bldg 3 | C51: 4/01/23 | D51: 50719.12 | E51: 0 | F51: 0 | G51: 2028.76 | H51: 3246.03 | I51: =G51+H51 -> 5274.79 | J51: =D51-I51 -> 45444.33 | K51: 200DB | L51: 5.0
B52: Grand Total | D52: =SUM(D45:D51) -> 398493.7 | E52: =SUM(E45:E51) -> 0 | F52: =SUM(F45:F51) -> 2255.21 | G52: =SUM(G45:G51) -> 17696.06 | H52: =SUM(H45:H51) -> 15169.46 | I52: =SUM(I45:I51) -> 32865.52 | J52: =SUM(J45:J51) -> 365628.18
A54: After Cost Segregation Correction — AMT
A55: Asset | B55: Property Description | C55: Date In Service | D55: Cost | E55: Sec 179 Exp | F55: Bonus Amt | G55: AMT Prior Depreciation | H55: AMT Current Depreciation | I55: End Depreciation | J55: Net Book Value | K55: Method | L55: Period
A56: 1 | B56: 12-New Buildings(16 units)-bldg3-5yr | C56: 12/20/22 | D56: 9054.67 | E56: 0 | F56: 9054.67 | G56: 9054.67 | H56: 0 | I56: =G56+H56 -> 9054.67 | J56: =D56-I56 -> 0 | K56: 200DB | L56: 5.0
A57: 2 | B57: 12-New Buildings(16 units)-bldg3-30yr | C57: 12/20/22 | D57: 25418.19 | E57: 0 | F57: 0 | G57: 882.57 | H57: 847.27 | I57: =G57+H57 -> 1729.84 | J57: =D57-I57 -> 23688.35 | K57: S/L | L57: 30.00
A58: 3 | B58: 14-New Buildings(105 units)-bldg3-5yr | C58: 4/01/23 | D58: 60688.77 | E58: 0 | F58: 48551.02 | G58: 50978.57 | H58: 3884.08 | I58: =G58+H58 -> 54862.65 | J58: =D58-I58 -> 5826.12 | K58: 200DB | L58: 5.0
A59: 4 | B59: 14-New Buildings(105 units)-bldg3-30yr | C59: 4/01/23 | D59: 170364.9 | E59: 0 | F59: 0 | G59: 4022.5 | H59: 5678.83 | I59: =G59+H59 -> 9701.33 | J59: =D59-I59 -> 160663.57 | K59: S/L | L59: 30.00
A60: 5 | B60: 2-Land Improvements-bldg3-5yr | C60: 8/15/18 | D60: 2308.82 | E60: 0 | F60: 2308.82 | G60: 2308.82 | H60: 0 | I60: =G60+H60 -> 2308.82 | J60: =D60-I60 -> 0 | K60: 200DB | L60: 5.0
A61: 6 | B61: 2-Land Improvements-bldg3-30yr | C61: 8/15/18 | D61: 6481.31 | E61: 0 | F61: 0 | G61: 1161.22 | H61: 216.04 | I61: =G61+H61 -> 1377.26 | J61: =D61-I61 -> 5104.05 | K61: S/L | L61: 30.00
A62: 7 | B62: 13-New Equipment(16 units)-bldg3-5yr | C62: 12/20/22 | D62: 1987.61 | E62: 0 | F62: 1987.61 | G62: 1987.61 | H62: 0 | I62: =G62+H62 -> 1987.61 | J62: =D62-I62 -> 0 | K62: 200DB | L62: 5.0
A63: 8 | B63: 13-New Equipment(16 units)-bldg3-30yr | C63: 12/20/22 | D63: 5579.59 | E63: 0 | F63: 0 | G63: 193.74 | H63: 185.99 | I63: =G63+H63 -> 379.73 | J63: =D63-I63 -> 5199.86 | K63: S/L | L63: 30.00
A64: 9 | B64: 15-New Equipment(105 units)-bldg3-5yr | C64: 4/01/23 | D64: 13321.93 | E64: 0 | F64: 10657.54 | G64: 11190.42 | H64: 852.6 | I64: =G64+H64 -> 12043.02 | J64: =D64-I64 -> 1278.91 | K64: 200DB | L64: 5.0
A65: 10 | B65: 15-New Equipment(105 units)-bldg3-30yr | C65: 4/01/23 | D65: 37397.19 | E65: 0 | F65: 0 | G65: 882.99 | H65: 1246.57 | I65: =G65+H65 -> 2129.56 | J65: =D65-I65 -> 35267.63 | K65: S/L | L65: 30.00
B66: Grand Total | D66: =SUM(D56:D65) -> 332602.98 | E66: =SUM(E56:E65) -> 0 | F66: =SUM(F56:F65) -> 72559.66 | G66: =SUM(G56:G65) -> 82663.11 | H66: =SUM(H56:H65) -> 12911.38 | I66: =SUM(I56:I65) -> 95574.49 | J66: =SUM(J56:J65) -> 237028.49
B68: Section 481(a) Adjustment — AMT
B69: Depreciation reported previously | D69: =I52 -> 32865.52
B70: Cost Segregation Corrected Depreciation | D70: =I66 -> 95574.49
B71: Section 481(a) Adjustment — AMT | D71: =D69-D70 -> -62708.97
A73: COST SEGREGATION STUDY — COST SUMMARY
B74: Total Building Cost | D74: =D111 -> 398493.7
B75: Building Components: 5 Year | D75: =F111 -> 104668.72
B76: % of Cost | D76: =F112 -> 0.26266092
B77: Building Structure: 30 Year | D77: =H111 -> 293824.98
B78: % of Cost | D78: =H112 -> 0.73733908
A80: COST SEGREGATION STUDY — COST DETAIL
B81: Property Category | D81: Cost | F81: 5 Year | H81: 30 Year
B82: Building Components
B83: Cabinets / Millwork | D83: =SUM(F83:H83) -> 31452.73 | F83: 31452.73
B84: Moldings | D84: =SUM(F84:H84) -> 8394.17 | F84: 8394.17
B85: Flooring - Vinyl Plank | D85: =SUM(F85:H85) -> 32815.89 | F85: 32815.89
B86: Window Treatments | D86: =SUM(F86:H86) -> 2648.72 | F86: 2648.72
B87: Building Signage | D87: =SUM(F87:H87) -> 394.4 | F87: 394.4
B88: Specialty Electrical - Appliances | D88: =SUM(F88:H88) -> 5344.3 | F88: 5344.3
B89: Communication / Data | D89: =SUM(F89:H89) -> 2858.97 | F89: 2858.97
B90: Specialty Plumbing - Kitchen Sinks | D90: =SUM(F90:H90) -> 9687.68 | F90: 9687.68
B91: Security / Exterior Lighting | D91: =SUM(F91:H91) -> 2139.23 | F91: 2139.23
B92: Canopies / Awnings | D92: =SUM(F92:H92) -> 605.69 | F92: 605.69
B93: Appliances | D93: =SUM(F93:H93) -> 8326.94 | F93: 8326.94
B94: Building Structure
B95: Roofing Systems | D95: =SUM(F95:H95) -> 16256.27 | H95: 16256.27
B96: Foundations | D96: =SUM(F96:H96) -> 21691.78 | H96: 21691.78
B97: HVAC | D97: =SUM(F97:H97) -> 31892.38 | H97: 31892.38
B98: Electrical | D98: =SUM(F98:H98) -> 29436.62 | H98: 29436.62
B99: Plumbing | D99: =SUM(F99:H99) -> 27723.88 | H99: 27723.88
B100: Fire Protection & Alarm | D100: =SUM(F100:H100) -> 1864.29 | H100: 1864.29
B101: Exterior Façade / Building Skin | D101: =SUM(F101:H101) -> 21001.52 | H101: 21001.52
B102: Doors & Frames | D102: =SUM(F102:H102) -> 16292.68 | H102: 16292.68
B103: Windows | D103: =SUM(F103:H103) -> 12258.17 | H103: 12258.17
B104: Ceiling Systems | D104: =SUM(F104:H104) -> 14614.91 | H104: 14614.91
B105: Interior Framing / Partitions | D105: =SUM(F105:H105) -> 38542.73 | H105: 38542.73
B106: Painting | D106: =SUM(F106:H106) -> 15289.77 | H106: 15289.77
... B110: Cabinets / Millwork - Restrooms | D110: =SUM(F110:H110) -> 1880.89 | H110: 1880.89
B111: Total Building Cost | D111: =SUM(D82:D110) -> 398493.7 | F111: =SUM(F82:F110) -> 104668.72 | H111: =SUM(H82:H110) -> 293824.98
B112: % of Cost | F112: =F111/D111 -> 0.26266092 | H112: =H111/D111 -> 0.73733908
...

Sheet Building 4
A1: St Charles Housing LP
A2: St. Charles — 1011 W 18th St, Lake Charles, LA 70607
A3: EIN: 82-5349206 · FYE: December 31, 2024 · Year of Change: 1/1/2024
A4: Building 4 — Attachment to Form 3115 (DCN #7, Rev. Proc. 2024-23 §6.01)
A5: Source: CSSI Report #107752-24, "St. Charles Housing LP_107752-24_3115_Combined.pdf"
A7: CALCULATION OF §481(a) ADJUSTMENT — REGULAR TAX
A8: As Previously Filed
A9: Asset | B9: Property Description | C9: Date In Service | D9: Cost | E9: Sec 179 Exp | F9: Bonus Amt | G9: Tax Prior Depreciation | H9: Tax Current Depreciation | I9: End Depreciation | J9: Net Book Value | K9: Method | L9: Period
A10: 1 | B10: 10-Building(Post Casualty Loss Basis)-bldg 4 | C10: 8/15/18 | D10: 63978.69 | E10: 0 | F10: 0 | G10: 6607.4 | H10: 2329.79 | I10: =G10+H10 -> 8937.19 | J10: =D10-I10 -> 55041.5 | K10: S/L | L10: 30.00
A11: 2 | B11: 12-New Buildings(16 units)-bldg 4 | C11: 12/20/22 | D11: 34313.78 | E11: 0 | F11: 0 | G11: 1191.47 | H11: 1143.79 | I11: =G11+H11 -> 2335.26 | J11: =D11-I11 -> 31978.52 | K11: S/L | L11: 30.00
A12: 3 | B12: 14-New Buildings(105 units)-bldg 4 | C12: 4/01/23 | D12: 229987.39 | E12: 0 | F12: 0 | G12: 5430.25 | H12: 7666.27 | I12: =G12+H12 -> 13096.52 | J12: =D12-I12 -> 216890.87 | K12: S/L | L12: 30.00
A13: 4 | B13: 11-Building Imp)Post-Casulty Loss Basis)-bldg | C13: 9/02/20 | D13: 1607.95 | E13: 0 | F13: 0 | G13: 121.07 | H13: 55.67 | I13: =G13+H13 -> 176.74 | J13: =D13-I13 -> 1431.21 | K13: S/L | L13: 30.00
A14: 5 | B14: 2-Land Improvements-bldg 4 | C14: 8/15/18 | D14: 8749.57 | E14: 0 | F14: 2244.81 | G14: 2244.81 | H14: 672.9 | I14: =G14+H14 -> 2917.71 | J14: =D14-I14 -> 5831.86 | K14: 150DB | L14: 15.0
A15: 6 | B15: 13-New Equipment(16 units)-bldg 4 | C15: 12/20/22 | D15: 7532.28 | E15: 0 | F15: 0 | G15: 0 | H15: 0 | I15: =G15+H15 -> 0 | J15: =D15-I15 -> 7532.28 | K15: 200DB | L15: 5.0
A16: 7 | B16: 15-New Equipment(105 units)-bldg 4 | C16: 4/01/23 | D16: 50485.05 | E16: 0 | F16: 0 | G16: 2019.4 | H16: 3231.05 | I16: =G16+H16 -> 5250.45 | J16: =D16-I16 -> 45234.6 | K16: 200DB | L16: 5.0
B17: Grand Total | D17: =SUM(D10:D16) -> 396654.71 | E17: =SUM(E10:E16) -> 0 | F17: =SUM(F10:F16) -> 2244.81 | G17: =SUM(G10:G16) -> 17614.4 | H17: =SUM(H10:H16) -> 15099.47 | I17: =SUM(I10:I16) -> 32713.87 | J17: =SUM(J10:J16) -> 363940.84
A19: After Cost Segregation Correction
A20: Asset | B20: Property Description | C20: Date In Service | D20: Cost | E20: Sec 179 Exp | F20: Bonus Amt | G20: Tax Prior Depreciation | H20: Tax Current Depreciation | I20: End Depreciation | J20: Net Book Value | K20: Method | L20: Period
A21: 1 | B21: 10-Building-Post Casualty Loss Basis-bldg4-5y | C21: 8/15/18 | D21: 16882.61 | E21: 0 | F21: 16882.61 | G21: 16882.61 | H21: 0 | I21: =G21+H21 -> 16882.61 | J21: =D21-I21 -> 0 | K21: 200DB | L21: 5.0
A22: 2 | B22: 10-Building-Post Casualty Loss Basis-bldg4-30 | C22: 8/15/18 | D22: 47096.08 | E22: 0 | F22: 0 | G22: 8438.05 | H22: 1569.87 | I22: =G22+H22 -> 10007.92 | J22: =D22-I22 -> 37088.16 | K22: S/L | L22: 30.00
A23: 3 | B23: 12-New Buildings(16 units)-bldg4-5yr | C23: 12/20/22 | D23: 9054.67 | E23: 0 | F23: 9054.67 | G23: 9054.67 | H23: 0 | I23: =G23+H23 -> 9054.67 | J23: =D23-I23 -> 0 | K23: 200DB | L23: 5.0
A24: 4 | B24: 12-New Buildings(16 units)-bldg4-30yr | C24: 12/20/22 | D24: 25259.11 | E24: 0 | F24: 0 | G24: 877.05 | H24: 841.97 | I24: =G24+H24 -> 1719.02 | J24: =D24-I24 -> 23540.09 | K24: S/L | L24: 30.00
A25: 5 | B25: 14-New Buildings(105 units)-bldg4-5yr | C25: 4/01/23 | D25: 60688.77 | E25: 0 | F25: 48551.02 | G25: 50978.57 | H25: 3884.08 | I25: =G25+H25 -> 54862.65 | J25: =D25-I25 -> 5826.12 | K25: 200DB | L25: 5.0
A26: 6 | B26: 14-New Buildings(105 units)-bldg4-30yr | C26: 4/01/23 | D26: 169298.62 | E26: 0 | F26: 0 | G26: 3997.33 | H26: 5643.29 | I26: =G26+H26 -> 9640.62 | J26: =D26-I26 -> 159658 | K26: S/L | L26: 30.00
A27: 7 | B27: 11-Building Imp-Post-Casulty Loss Basis-bldg4 | C27: 9/02/20 | D27: 424.3 | E27: 0 | F27: 424.3 | G27: 424.3 | H27: 0 | I27: =G27+H27 -> 424.3 | J27: =D27-I27 -> 0 | K27: 200DB | L27: 5.0
A28: 8 | B28: 11-Building Imp-Post-Casulty Loss Basis-bldg4 | C28: 9/02/20 | D28: 1183.65 | E28: 0 | F28: 0 | G28: 129.89 | H28: 39.46 | I28: =G28+H28 -> 169.35 | J28: =D28-I28 -> 1014.3 | K28: S/L | L28: 30.00
A29: 9 | B29: 2-Land Improvements-bldg4-5yr | C29: 8/15/18 | D29: 2308.82 | E29: 0 | F29: 2308.82 | G29: 2308.82 | H29: 0 | I29: =G29+H29 -> 2308.82 | J29: =D29-I29 -> 0 | K29: 200DB | L29: 5.0
A30: 10 | B30: 2-Land Improvements-bldg4-30yr | C30: 8/15/18 | D30: 6440.75 | E30: 0 | F30: 0 | G30: 1153.96 | H30: 214.69 | I30: =G30+H30 -> 1368.65 | J30: =D30-I30 -> 5072.1 | K30: S/L | L30: 30.00
A31: 11 | B31: 13-New Equipment(16 units)-bldg4-5yr | C31: 12/20/22 | D31: 1987.61 | E31: 0 | F31: 1987.61 | G31: 1987.61 | H31: 0 | I31: =G31+H31 -> 1987.61 | J31: =D31-I31 -> 0 | K31: 200DB | L31: 5.0
A32: 12 | B32: 13-New Equipment(16 units)-bldg4-30yr | C32: 12/20/22 | D32: 5544.67 | E32: 0 | F32: 0 | G32: 192.52 | H32: 184.82 | I32: =G32+H32 -> 377.34 | J32: =D32-I32 -> 5167.33 | K32: S/L | L32: 30.00
... A34: 14 | B34: 15-New Equipment(105 units)-bldg4-30yr | C34: 4/01/23 | D34: 37163.11 | E34: 0 | F34: 0 | G34: 877.46 | H34: 1238.77 | I34: =G34+H34 -> 2116.23 | J34: =D34-I34 -> 35046.88 | K34: S/L | L34: 30.00
B35: Grand Total | D35: =SUM(D21:D34) -> 396654.71 | E35: =SUM(E21:E34) -> 0 | F35: =SUM(F21:F34) -> 89866.58 | G35: =SUM(G21:G34) -> 108493.27 | H35: =SUM(H21:H34) -> 14469.55 | I35: =SUM(I21:I34) -> 122962.82 | J35: =SUM(J21:J34) -> 273691.89
B37: Section 481(a) Adjustment — Regular Tax
B38: Depreciation reported previously | D38: =I17 -> 32713.87
B39: Cost Segregation Corrected Depreciation | D39: =I35 -> 122962.82
B40: Section 481(a) Adjustment — Regular Tax | D40: =D38-D39 -> -90248.95
A42: CALCULATION OF §481(a) ADJUSTMENT — AMT
A43: As Previously Filed — AMT
A44: Asset | B44: Property Description | C44: Date In Service | D44: Cost | E44: Sec 179 Exp | F44: Bonus Amt | G44: AMT Prior Depreciation | H44: AMT Current Depreciation | I44: End Depreciation | J44: Net Book Value | K44: Method | L44: Period
A45: 1 | B45: 10-Building(Post Casualty Loss Basis)-bldg 4 | C45: 8/15/18 | D45: 63978.69 | E45: 0 | F45: 0 | G45: 6607.4 | H45: 2329.79 | I45: =G45+H45 -> 8937.19 | J45: =D45-I45 -> 55041.5 | K45: S/L | L45: 30.00
A46: 2 | B46: 12-New Buildings(16 units)-bldg 4 | C46: 12/20/22 | D46: 34313.78 | E46: 0 | F46: 0 | G46: 1191.47 | H46: 1143.79 | I46: =G46+H46 -> 2335.26 | J46: =D46-I46 -> 31978.52 | K46: S/L | L46: 30.00
A47: 3 | B47: 14-New Buildings(105 units)-bldg 4 | C47: 4/01/23 | D47: 229987.39 | E47: 0 | F47: 0 | G47: 5430.25 | H47: 7666.27 | I47: =G47+H47 -> 13096.52 | J47: =D47-I47 -> 216890.87 | K47: S/L | L47: 30.00
A48: 4 | B48: 11-Building Imp)Post-Casulty Loss Basis)-bldg | C48: 9/02/20 | D48: 1607.95 | E48: 0 | F48: 0 | G48: 121.07 | H48: 55.67 | I48: =G48+H48 -> 176.74 | J48: =D48-I48 -> 1431.21 | K48: S/L | L48: 30.00
A49: 5 | B49: 2-Land Improvements-bldg 4 | C49: 8/15/18 | D49: 8749.57 | E49: 0 | F49: 2244.81 | G49: 2244.81 | H49: 672.9 | I49: =G49+H49 -> 2917.71 | J49: =D49-I49 -> 5831.86 | K49: 150DB | L49: 15.0
A50: 6 | B50: 13-New Equipment(16 units)-bldg 4 | C50: 12/20/22 | D50: 7532.28 | E50: 0 | F50: 0 | G50: 0 | H50: 0 | I50: =G50+H50 -> 0 | J50: =D50-I50 -> 7532.28 | K50: 200DB | L50: 5.0
A51: 7 | B51: 15-New Equipment(105 units)-bldg 4 | C51: 4/01/23 | D51: 50485.05 | E51: 0 | F51: 0 | G51: 2019.4 | H51: 3231.05 | I51: =G51+H51 -> 5250.45 | J51: =D51-I51 -> 45234.6 | K51: 200DB | L51: 5.0
B52: Grand Total | D52: =SUM(D45:D51) -> 396654.71 | E52: =SUM(E45:E51) -> 0 | F52: =SUM(F45:F51) -> 2244.81 | G52: =SUM(G45:G51) -> 17614.4 | H52: =SUM(H45:H51) -> 15099.47 | I52: =SUM(I45:I51) -> 32713.87 | J52: =SUM(J45:J51) -> 363940.84
A54: After Cost Segregation Correction — AMT
A55: Asset | B55: Property Description | C55: Date In Service | D55: Cost | E55: Sec 179 Exp | F55: Bonus Amt | G55: AMT Prior Depreciation | H55: AMT Current Depreciation | I55: End Depreciation | J55: Net Book Value | K55: Method | L55: Period
A56: 1 | B56: 12-New Buildings(16 units)-bldg4-5yr | C56: 12/20/22 | D56: 9054.67 | E56: 0 | F56: 9054.67 | G56: 9054.67 | H56: 0 | I56: =G56+H56 -> 9054.67 | J56: =D56-I56 -> 0 | K56: 200DB | L56: 5.0
A57: 2 | B57: 12-New Buildings(16 units)-bldg4-30yr | C57: 12/20/22 | D57: 25259.11 | E57: 0 | F57: 0 | G57: 877.05 | H57: 841.97 | I57: =G57+H57 -> 1719.02 | J57: =D57-I57 -> 23540.09 | K57: S/L | L57: 30.00
A58: 3 | B58: 14-New Buildings(105 units)-bldg4-5yr | C58: 4/01/23 | D58: 60688.77 | E58: 0 | F58: 48551.02 | G58: 50978.57 | H58: 3884.08 | I58: =G58+H58 -> 54862.65 | J58: =D58-I58 -> 5826.12 | K58: 200DB | L58: 5.0
A59: 4 | B59: 14-New Buildings(105 units)-bldg4-30yr | C59: 4/01/23 | D59: 169298.62 | E59: 0 | F59: 0 | G59: 3997.33 | H59: 5643.29 | I59: =G59+H59 -> 9640.62 | J59: =D59-I59 -> 159658 | K59: S/L | L59: 30.00
A60: 5 | B60: 2-Land Improvements-bldg4-5yr | C60: 8/15/18 | D60: 2308.82 | E60: 0 | F60: 2308.82 | G60: 2308.82 | H60: 0 | I60: =G60+H60 -> 2308.82 | J60: =D60-I60 -> 0 | K60: 200DB | L60: 5.0
A61: 6 | B61: 2-Land Improvements-bldg4-30yr | C61: 8/15/18 | D61: 6440.75 | E61: 0 | F61: 0 | G61: 1153.96 | H61: 214.69 | I61: =G61+H61 -> 1368.65 | J61: =D61-I61 -> 5072.1 | K61: S/L | L61: 30.00
A62: 7 | B62: 13-New Equipment(16 units)-bldg4-5yr | C62: 12/20/22 | D62: 1987.61 | E62: 0 | F62: 1987.61 | G62: 1987.61 | H62: 0 | I62: =G62+H62 -> 1987.61 | J62: =D62-I62 -> 0 | K62: 200DB | L62: 5.0
A63: 8 | B63: 13-New Equipment(16 units)-bldg4-30yr | C63: 12/20/22 | D63: 5544.67 | E63: 0 | F63: 0 | G63: 192.52 | H63: 184.82 | I63: =G63+H63 -> 377.34 | J63: =D63-I63 -> 5167.33 | K63: S/L | L63: 30.00
A64: 9 | B64: 15-New Equipment(105 units)-bldg4-5yr | C64: 4/01/23 | D64: 13321.94 | E64: 0 | F64: 10657.55 | G64: 11190.43 | H64: 852.6 | I64: =G64+H64 -> 12043.03 | J64: =D64-I64 -> 1278.91 | K64: 200DB | L64: 5.0
A65: 10 | B65: 15-New Equipment(105 units)-bldg4-30yr | C65: 4/01/23 | D65: 37163.11 | E65: 0 | F65: 0 | G65: 877.46 | H65: 1238.77 | I65: =G65+H65 -> 2116.23 | J65: =D65-I65 -> 35046.88 | K65: S/L | L65: 30.00
B66: Grand Total | D66: =SUM(D56:D65) -> 331068.07 | E66: =SUM(E56:E65) -> 0 | F66: =SUM(F56:F65) -> 72559.67 | G66: =SUM(G56:G65) -> 82618.42 | H66: =SUM(H56:H65) -> 12860.22 | I66: =SUM(I56:I65) -> 95478.64 | J66: =SUM(J56:J65) -> 235589.43
B68: Section 481(a) Adjustment — AMT
B69: Depreciation reported previously | D69: =I52 -> 32713.87
B70: Cost Segregation Corrected Depreciation | D70: =I66 -> 95478.64
B71: Section 481(a) Adjustment — AMT | D71: =D69-D70 -> -62764.77
A73: COST SEGREGATION STUDY — COST SUMMARY
B74: Total Building Cost | D74: =D111 -> 396654.71
B75: Building Components: 5 Year | D75: =F111 -> 104668.72
B76: % of Cost | D76: =F112 -> 0.26387868
B77: Building Structure: 30 Year | D77: =H111 -> 291985.99
B78: % of Cost | D78: =H112 -> 0.73612132
A80: COST SEGREGATION STUDY — COST DETAIL
B81: Property Category | D81: Cost | F81: 5 Year | H81: 30 Year
B82: Building Components
B83: Cabinets / Millwork | D83: =SUM(F83:H83) -> 31452.73 | F83: 31452.73
B84: Moldings | D84: =SUM(F84:H84) -> 8394.17 | F84: 8394.17
B85: Flooring - Vinyl Plank | D85: =SUM(F85:H85) -> 32815.89 | F85: 32815.89
B86: Window Treatments | D86: =SUM(F86:H86) -> 2648.72 | F86: 2648.72
B87: Building Signage | D87: =SUM(F87:H87) -> 394.4 | F87: 394.4
B88: Specialty Electrical - Appliances | D88: =SUM(F88:H88) -> 5344.3 | F88: 5344.3
B89: Communication / Data | D89: =SUM(F89:H89) -> 2858.97 | F89: 2858.97
B90: Specialty Plumbing - Kitchen Sinks | D90: =SUM(F90:H90) -> 9687.68 | F90: 9687.68
B91: Security / Exterior Lighting | D91: =SUM(F91:H91) -> 2139.23 | F91: 2139.23
B92: Canopies / Awnings | D92: =SUM(F92:H92) -> 605.69 | F92: 605.69
B93: Appliances | D93: =SUM(F93:H93) -> 8326.94 | F93: 8326.94
B94: Building Structure
B95: Roofing Systems | D95: =SUM(F95:H95) -> 16256.27 | H95: 16256.27
B96: Foundations | D96: =SUM(F96:H96) -> 21691.78 | H96: 21691.78
B97: HVAC | D97: =SUM(F97:H97) -> 31892.38 | H97: 31892.38
B98: Electrical | D98: =SUM(F98:H98) -> 29436.62 | H98: 29436.62
B99: Plumbing | D99: =SUM(F99:H99) -> 27723.88 | H99: 27723.88
B100: Fire Protection & Alarm | D100: =SUM(F100:H100) -> 1864.29 | H100: 1864.29
B101: Exterior Façade / Building Skin | D101: =SUM(F101:H101) -> 19256.3 | H101: 19256.3
B102: Doors & Frames | D102: =SUM(F102:H102) -> 16292.68 | H102: 16292.68
B103: Windows | D103: =SUM(F103:H103) -> 12258.17 | H103: 12258.17
B104: Ceiling Systems | D104: =SUM(F104:H104) -> 14614.91 | H104: 14614.91
B105: Interior Framing / Partitions | D105: =SUM(F105:H105) -> 38542.73 | H105: 38542.73
B106: Painting | D106: =SUM(F106:H106) -> 15196 | H106: 15196
... B110: Cabinets / Millwork - Restrooms | D110: =SUM(F110:H110) -> 1880.89 | H110: 1880.89
B111: Total Building Cost | D111: =SUM(D82:D110) -> 396654.71 | F111: =SUM(F82:F110) -> 104668.72 | H111: =SUM(H82:H110) -> 291985.99
B112: % of Cost | F112: =F111/D111 -> 0.26387868 | H112: =H111/D111 -> 0.73612132
...

Sheet Building 5
A1: St Charles Housing LP
A2: St. Charles — 1011 W 18th St, Lake Charles, LA 70607
A3: EIN: 82-5349206 · FYE: December 31, 2024 · Year of Change: 1/1/2024
A4: Building 5 — Attachment to Form 3115 (DCN #7, Rev. Proc. 2024-23 §6.01)
A5: Source: CSSI Report #107752-24, "St. Charles Housing LP_107752-24_3115_Combined.pdf"
A7: CALCULATION OF §481(a) ADJUSTMENT — REGULAR TAX
A8: As Previously Filed
A9: Asset | B9: Property Description | C9: Date In Service | D9: Cost | E9: Sec 179 Exp | F9: Bonus Amt | G9: Tax Prior Depreciation | H9: Tax Current Depreciation | I9: End Depreciation | J9: Net Book Value | K9: Method | L9: Period
A10: 1 | B10: 10-Building(Post Casualty Loss Basis)-bldg 5 | C10: 8/15/18 | D10: 71985.95 | E10: 0 | F10: 0 | G10: 7434.35 | H10: 2621.38 | I10: =G10+H10 -> 10055.73 | J10: =D10-I10 -> 61930.22 | K10: S/L | L10: 30.00
A11: 2 | B11: 12-New Buildings(16 units)-bldg 5 | C11: 12/20/22 | D11: 38608.32 | E11: 0 | F11: 0 | G11: 1340.59 | H11: 1286.94 | I11: =G11+H11 -> 2627.53 | J11: =D11-I11 -> 35980.79 | K11: S/L | L11: 30.00
A12: 3 | B12: 14-New Buildings(105 units)-bldg 5 | C12: 4/01/23 | D12: 258771.48 | E12: 0 | F12: 0 | G12: 6109.88 | H12: 8625.73 | I12: =G12+H12 -> 14735.61 | J12: =D12-I12 -> 244035.87 | K12: S/L | L12: 30.00
A13: 4 | B13: 11-Building Imp)Post-Casulty Loss Basis)-bldg | C13: 9/02/20 | D13: 1809.19 | E13: 0 | F13: 0 | G13: 136.22 | H13: 62.64 | I13: =G13+H13 -> 198.86 | J13: =D13-I13 -> 1610.33 | K13: S/L | L13: 30.00
A14: 5 | B14: 2-Land Improvements-bldg 5 | C14: 8/15/18 | D14: 9844.62 | E14: 0 | F14: 2525.76 | G14: 2525.76 | H14: 757.11 | I14: =G14+H14 -> 3282.87 | J14: =D14-I14 -> 6561.75 | K14: 150DB | L14: 15.0
A15: 6 | B15: 13-New Equipment(16 units)-bldg 5 | C15: 12/20/22 | D15: 8474.99 | E15: 0 | F15: 0 | G15: 0 | H15: 0 | I15: =G15+H15 -> 0 | J15: =D15-I15 -> 8474.99 | K15: 200DB | L15: 5.0
A16: 7 | B16: 15-New Equipment(105 units)-bldg 5 | C16: 4/01/23 | D16: 56803.51 | E16: 0 | F16: 0 | G16: 2272.14 | H16: 3635.43 | I16: =G16+H16 -> 5907.57 | J16: =D16-I16 -> 50895.94 | K16: 200DB | L16: 5.0
B17: Grand Total | D17: =SUM(D10:D16) -> 446298.06 | E17: =SUM(E10:E16) -> 0 | F17: =SUM(F10:F16) -> 2525.76 | G17: =SUM(G10:G16) -> 19818.94 | H17: =SUM(H10:H16) -> 16989.23 | I17: =SUM(I10:I16) -> 36808.17 | J17: =SUM(J10:J16) -> 409489.89
A19: After Cost Segregation Correction
A20: Asset | B20: Property Description | C20: Date In Service | D20: Cost | E20: Sec 179 Exp | F20: Bonus Amt | G20: Tax Prior Depreciation | H20: Tax Current Depreciation | I20: End Depreciation | J20: Net Book Value | K20: Method | L20: Period
A21: 1 | B21: 10-Building-Post Casualty Loss Basis-bldg5-5y | C21: 8/15/18 | D21: 18042.22 | E21: 0 | F21: 18042.22 | G21: 18042.22 | H21: 0 | I21: =G21+H21 -> 18042.22 | J21: =D21-I21 -> 0 | K21: 200DB | L21: 5.0
A22: 2 | B22: 10-Building-Post Casualty Loss Basis-bldg5-30 | C22: 8/15/18 | D22: 53943.73 | E22: 0 | F22: 0 | G22: 9664.9 | H22: 1798.12 | I22: =G22+H22 -> 11463.02 | J22: =D22-I22 -> 42480.71 | K22: S/L | L22: 30.00
A23: 3 | B23: 12-New Buildings(16 units)-bldg5-5yr | C23: 12/20/22 | D23: 9676.61 | E23: 0 | F23: 9676.61 | G23: 9676.61 | H23: 0 | I23: =G23+H23 -> 9676.61 | J23: =D23-I23 -> 0 | K23: 200DB | L23: 5.0
A24: 4 | B24: 12-New Buildings(16 units)-bldg5-30yr | C24: 12/20/22 | D24: 28931.71 | E24: 0 | F24: 0 | G24: 1004.57 | H24: 964.39 | I24: =G24+H24 -> 1968.96 | J24: =D24-I24 -> 26962.75 | K24: S/L | L24: 30.00
A25: 5 | B25: 14-New Buildings(105 units)-bldg5-5yr | C25: 4/01/23 | D25: 64857.26 | E25: 0 | F25: 51885.81 | G25: 54480.1 | H25: 4150.86 | I25: =G25+H25 -> 58630.96 | J25: =D25-I25 -> 6226.3 | K25: 200DB | L25: 5.0
A26: 6 | B26: 14-New Buildings(105 units)-bldg5-30yr | C26: 4/01/23 | D26: 193914.22 | E26: 0 | F26: 0 | G26: 4578.53 | H26: 6463.81 | I26: =G26+H26 -> 11042.34 | J26: =D26-I26 -> 182871.88 | K26: S/L | L26: 30.00
A27: 7 | B27: 11-Building Imp-Post-Casulty Loss Basis-bldg5 | C27: 9/02/20 | D27: 453.45 | E27: 0 | F27: 453.45 | G27: 453.45 | H27: 0 | I27: =G27+H27 -> 453.45 | J27: =D27-I27 -> 0 | K27: 200DB | L27: 5.0
A28: 8 | B28: 11-Building Imp-Post-Casulty Loss Basis-bldg5 | C28: 9/02/20 | D28: 1355.74 | E28: 0 | F28: 0 | G28: 148.75 | H28: 45.19 | I28: =G28+H28 -> 193.94 | J28: =D28-I28 -> 1161.8 | K28: S/L | L28: 30.00
A29: 9 | B29: 2-Land Improvements-bldg5-5yr | C29: 8/15/18 | D29: 2467.41 | E29: 0 | F29: 2467.41 | G29: 2467.41 | H29: 0 | I29: =G29+H29 -> 2467.41 | J29: =D29-I29 -> 0 | K29: 200DB | L29: 5.0
A30: 10 | B30: 2-Land Improvements-bldg5-30yr | C30: 8/15/18 | D30: 7377.21 | E30: 0 | F30: 0 | G30: 1321.77 | H30: 245.91 | I30: =G30+H30 -> 1567.68 | J30: =D30-I30 -> 5809.53 | K30: S/L | L30: 30.00
A31: 11 | B31: 13-New Equipment(16 units)-bldg5-5yr | C31: 12/20/22 | D31: 2124.13 | E31: 0 | F31: 2124.13 | G31: 2124.13 | H31: 0 | I31: =G31+H31 -> 2124.13 | J31: =D31-I31 -> 0 | K31: 200DB | L31: 5.0
A32: 12 | B32: 13-New Equipment(16 units)-bldg5-30yr | C32: 12/20/22 | D32: 6350.86 | E32: 0 | F32: 0 | G32: 220.52 | H32: 211.7 | I32: =G32+H32 -> 432.22 | J32: =D32-I32 -> 5918.64 | K32: S/L | L32: 30.00
... A34: 14 | B34: 15-New Equipment(105 units)-bldg5-30yr | C34: 4/01/23 | D34: 42566.56 | E34: 0 | F34: 0 | G34: 1005.04 | H34: 1418.89 | I34: =G34+H34 -> 2423.93 | J34: =D34-I34 -> 40142.63 | K34: S/L | L34: 30.00
B35: Grand Total | D35: =SUM(D21:D34) -> 446298.06 | E35: =SUM(E21:E34) -> 0 | F35: =SUM(F21:F34) -> 96039.19 | G35: =SUM(G21:G34) -> 117147.04 | H35: =SUM(H21:H34) -> 16210.03 | I35: =SUM(I21:I34) -> 133357.07 | J35: =SUM(J21:J34) -> 312940.99
B37: Section 481(a) Adjustment — Regular Tax
B38: Depreciation reported previously | D38: =I17 -> 36808.17
B39: Cost Segregation Corrected Depreciation | D39: =I35 -> 133357.07
B40: Section 481(a) Adjustment — Regular Tax | D40: =D38-D39 -> -96548.9
A42: CALCULATION OF §481(a) ADJUSTMENT — AMT
A43: As Previously Filed — AMT
A44: Asset | B44: Property Description | C44: Date In Service | D44: Cost | E44: Sec 179 Exp | F44: Bonus Amt | G44: AMT Prior Depreciation | H44: AMT Current Depreciation | I44: End Depreciation | J44: Net Book Value | K44: Method | L44: Period
A45: 1 | B45: 10-Building(Post Casualty Loss Basis)-bldg 5 | C45: 8/15/18 | D45: 71985.95 | E45: 0 | F45: 0 | G45: 7434.35 | H45: 2621.38 | I45: =G45+H45 -> 10055.73 | J45: =D45-I45 -> 61930.22 | K45: S/L | L45: 30.00
A46: 2 | B46: 12-New Buildings(16 units)-bldg 5 | C46: 12/20/22 | D46: 38608.32 | E46: 0 | F46: 0 | G46: 1340.59 | H46: 1286.94 | I46: =G46+H46 -> 2627.53 | J46: =D46-I46 -> 35980.79 | K46: S/L | L46: 30.00
A47: 3 | B47: 14-New Buildings(105 units)-bldg 5 | C47: 4/01/23 | D47: 258771.48 | E47: 0 | F47: 0 | G47: 6109.88 | H47: 8625.73 | I47: =G47+H47 -> 14735.61 | J47: =D47-I47 -> 244035.87 | K47: S/L | L47: 30.00
A48: 4 | B48: 11-Building Imp)Post-Casulty Loss Basis)-bldg | C48: 9/02/20 | D48: 1809.19 | E48: 0 | F48: 0 | G48: 136.22 | H48: 62.64 | I48: =G48+H48 -> 198.86 | J48: =D48-I48 -> 1610.33 | K48: S/L | L48: 30.00
A49: 5 | B49: 2-Land Improvements-bldg 5 | C49: 8/15/18 | D49: 9844.62 | E49: 0 | F49: 2525.76 | G49: 2525.76 | H49: 757.11 | I49: =G49+H49 -> 3282.87 | J49: =D49-I49 -> 6561.75 | K49: 150DB | L49: 15.0
A50: 6 | B50: 13-New Equipment(16 units)-bldg 5 | C50: 12/20/22 | D50: 8474.99 | E50: 0 | F50: 0 | G50: 0 | H50: 0 | I50: =G50+H50 -> 0 | J50: =D50-I50 -> 8474.99 | K50: 200DB | L50: 5.0
A51: 7 | B51: 15-New Equipment(105 units)-bldg 5 | C51: 4/01/23 | D51: 56803.51 | E51: 0 | F51: 0 | G51: 2272.14 | H51: 3635.43 | I51: =G51+H51 -> 5907.57 | J51: =D51-I51 -> 50895.94 | K51: 200DB | L51: 5.0
B52: Grand Total | D52: =SUM(D45:D51) -> 446298.06 | E52: =SUM(E45:E51) -> 0 | F52: =SUM(F45:F51) -> 2525.76 | G52: =SUM(G45:G51) -> 19818.94 | H52: =SUM(H45:H51) -> 16989.23 | I52: =SUM(I45:I51) -> 36808.17 | J52: =SUM(J45:J51) -> 409489.89
A54: After Cost Segregation Correction — AMT
A55: Asset | B55: Property Description | C55: Date In Service | D55: Cost | E55: Sec 179 Exp | F55: Bonus Amt | G55: AMT Prior Depreciation | H55: AMT Current Depreciation | I55: End Depreciation | J55: Net Book Value | K55: Method | L55: Period
A56: 1 | B56: 12-New Buildings(16 units)-bldg5-5yr | C56: 12/20/22 | D56: 9676.61 | E56: 0 | F56: 9676.61 | G56: 9676.61 | H56: 0 | I56: =G56+H56 -> 9676.61 | J56: =D56-I56 -> 0 | K56: 200DB | L56: 5.0
A57: 2 | B57: 12-New Buildings(16 units)-bldg5-30yr | C57: 12/20/22 | D57: 28931.71 | E57: 0 | F57: 0 | G57: 1004.57 | H57: 964.39 | I57: =G57+H57 -> 1968.96 | J57: =D57-I57 -> 26962.75 | K57: S/L | L57: 30.00
A58: 3 | B58: 14-New Buildings(105 units)-bldg5-5yr | C58: 4/01/23 | D58: 64857.26 | E58: 0 | F58: 51885.81 | G58: 54480.1 | H58: 4150.86 | I58: =G58+H58 -> 58630.96 | J58: =D58-I58 -> 6226.3 | K58: 200DB | L58: 5.0
A59: 4 | B59: 14-New Buildings(105 units)-bldg5-30yr | C59: 4/01/23 | D59: 193914.22 | E59: 0 | F59: 0 | G59: 4578.53 | H59: 6463.81 | I59: =G59+H59 -> 11042.34 | J59: =D59-I59 -> 182871.88 | K59: S/L | L59: 30.00
A60: 5 | B60: 2-Land Improvements-bldg5-5yr | C60: 8/15/18 | D60: 2467.41 | E60: 0 | F60: 2467.41 | G60: 2467.41 | H60: 0 | I60: =G60+H60 -> 2467.41 | J60: =D60-I60 -> 0 | K60: 200DB | L60: 5.0
A61: 6 | B61: 2-Land Improvements-bldg5-30yr | C61: 8/15/18 | D61: 7377.21 | E61: 0 | F61: 0 | G61: 1321.77 | H61: 245.91 | I61: =G61+H61 -> 1567.68 | J61: =D61-I61 -> 5809.53 | K61: S/L | L61: 30.00
A62: 7 | B62: 13-New Equipment(16 units)-bldg5-5yr | C62: 12/20/22 | D62: 2124.13 | E62: 0 | F62: 2124.13 | G62: 2124.13 | H62: 0 | I62: =G62+H62 -> 2124.13 | J62: =D62-I62 -> 0 | K62: 200DB | L62: 5.0
A63: 8 | B63: 13-New Equipment(16 units)-bldg5-30yr | C63: 12/20/22 | D63: 6350.86 | E63: 0 | F63: 0 | G63: 220.52 | H63: 211.7 | I63: =G63+H63 -> 432.22 | J63: =D63-I63 -> 5918.64 | K63: S/L | L63: 30.00
A64: 9 | B64: 15-New Equipment(105 units)-bldg5-5yr | C64: 4/01/23 | D64: 14236.95 | E64: 0 | F64: 11389.56 | G64: 11959.04 | H64: 911.16 | I64: =G64+H64 -> 12870.2 | J64: =D64-I64 -> 1366.75 | K64: 200DB | L64: 5.0
A65: 10 | B65: 15-New Equipment(105 units)-bldg5-30yr | C65: 4/01/23 | D65: 42566.56 | E65: 0 | F65: 0 | G65: 1005.04 | H65: 1418.89 | I65: =G65+H65 -> 2423.93 | J65: =D65-I65 -> 40142.63 | K65: S/L | L65: 30.00
B66: Grand Total | D66: =SUM(D56:D65) -> 372502.92 | E66: =SUM(E56:E65) -> 0 | F66: =SUM(F56:F65) -> 77543.52 | G66: =SUM(G56:G65) -> 88837.72 | H66: =SUM(H56:H65) -> 14366.72 | I66: =SUM(I56:I65) -> 103204.44 | J66: =SUM(J56:J65) -> 269298.48
B68: Section 481(a) Adjustment — AMT
B69: Depreciation reported previously | D69: =I52 -> 36808.17
B70: Cost Segregation Corrected Depreciation | D70: =I66 -> 103204.44
B71: Section 481(a) Adjustment — AMT | D71: =D69-D70 -> -66396.27
A73: COST SEGREGATION STUDY — COST SUMMARY
B74: Total Building Cost | D74: =D111 -> 446298.06
B75: Building Components: 5 Year | D75: =F111 -> 111858.03
B76: % of Cost | D76: =F112 -> 0.25063526
B77: Building Structure: 30 Year | D77: =H111 -> 334440.03
B78: % of Cost | D78: =H112 -> 0.74936474
A80: COST SEGREGATION STUDY — COST DETAIL
B81: Property Category | D81: Cost | F81: 5 Year | H81: 30 Year
B82: Building Components
B83: Cabinets / Millwork | D83: =SUM(F83:H83) -> 31452.73 | F83: 31452.73
B84: Moldings | D84: =SUM(F84:H84) -> 8975.5 | F84: 8975.5
B85: Flooring - Vinyl Plank | D85: =SUM(F85:H85) -> 38285.2 | F85: 38285.2
B86: Window Treatments | D86: =SUM(F86:H86) -> 3310.89 | F86: 3310.89
B87: Building Signage | D87: =SUM(F87:H87) -> 394.4 | F87: 394.4
B88: Specialty Electrical - Appliances | D88: =SUM(F88:H88) -> 5344.3 | F88: 5344.3
B89: Communication / Data | D89: =SUM(F89:H89) -> 3335.47 | F89: 3335.47
B90: Specialty Plumbing - Kitchen Sinks | D90: =SUM(F90:H90) -> 9687.68 | F90: 9687.68
B91: Security / Exterior Lighting | D91: =SUM(F91:H91) -> 2139.23 | F91: 2139.23
B92: Canopies / Awnings | D92: =SUM(F92:H92) -> 605.69 | F92: 605.69
B93: Appliances | D93: =SUM(F93:H93) -> 8326.94 | F93: 8326.94
B94: Building Structure
B95: Roofing Systems | D95: =SUM(F95:H95) -> 18787.9 | H95: 18787.9
B96: Foundations | D96: =SUM(F96:H96) -> 25094.53 | H96: 25094.53
B97: HVAC | D97: =SUM(F97:H97) -> 37207.78 | H97: 37207.78
B98: Electrical | D98: =SUM(F98:H98) -> 35233.43 | H98: 35233.43
B99: Plumbing | D99: =SUM(F99:H99) -> 32344.52 | H99: 32344.52
B100: Fire Protection & Alarm | D100: =SUM(F100:H100) -> 2485.72 | H100: 2485.72
B101: Exterior Façade / Building Skin | D101: =SUM(F101:H101) -> 22801.69 | H101: 22801.69
B102: Doors & Frames | D102: =SUM(F102:H102) -> 18966.91 | H102: 18966.91
B103: Windows | D103: =SUM(F103:H103) -> 15176.79 | H103: 15176.79
B104: Ceiling Systems | D104: =SUM(F104:H104) -> 17050.73 | H104: 17050.73
B105: Interior Framing / Partitions | D105: =SUM(F105:H105) -> 40897.65 | H105: 40897.65
B106: Painting | D106: =SUM(F106:H106) -> 16494.95 | H106: 16494.95
... B110: Cabinets / Millwork - Restrooms | D110: =SUM(F110:H110) -> 1880.89 | H110: 1880.89
B111: Total Building Cost | D111: =SUM(D82:D110) -> 446298.06 | F111: =SUM(F82:F110) -> 111858.03 | H111: =SUM(H82:H110) -> 334440.03
B112: % of Cost | F112: =F111/D111 -> 0.25063526 | H112: =H111/D111 -> 0.74936474
...

Sheet Building 6
A1: St Charles Housing LP
A2: St. Charles — 1011 W 18th St, Lake Charles, LA 70607
A3: EIN: 82-5349206 · FYE: December 31, 2024 · Year of Change: 1/1/2024
A4: Building 6 — Attachment to Form 3115 (DCN #7, Rev. Proc. 2024-23 §6.01)
A5: Source: CSSI Report #107752-24, "St. Charles Housing LP_107752-24_3115_Combined.pdf"
A7: CALCULATION OF §481(a) ADJUSTMENT — REGULAR TAX
A8: As Previously Filed
A9: Asset | B9: Property Description | C9: Date In Service | D9: Cost | E9: Sec 179 Exp | F9: Bonus Amt | G9: Tax Prior Depreciation | H9: Tax Current Depreciation | I9: End Depreciation | J9: Net Book Value | K9: Method | L9: Period
A10: 1 | B10: 10-Building(Post Casualty Loss Basis)-bldg 6 | C10: 8/15/18 | D10: 64317.98 | E10: 0 | F10: 0 | G10: 6642.44 | H10: 2342.15 | I10: =G10+H10 -> 8984.59 | J10: =D10-I10 -> 55333.39 | K10: S/L | L10: 30.00
A11: 2 | B11: 12-New Buildings(16 units)-bldg 6 | C11: 12/20/22 | D11: 34495.74 | E11: 0 | F11: 0 | G11: 1197.79 | H11: 1149.85 | I11: =G11+H11 -> 2347.64 | J11: =D11-I11 -> 32148.1 | K11: S/L | L11: 30.00
A12: 3 | B12: 14-New Buildings(105 units)-bldg 6 | C12: 4/01/23 | D12: 231207.03 | E12: 0 | F12: 0 | G12: 5459.05 | H12: 7706.92 | I12: =G12+H12 -> 13165.97 | J12: =D12-I12 -> 218041.06 | K12: S/L | L12: 30.00
A13: 4 | B13: 11-Building Imp)Post-Casulty Loss Basis)-bldg | C13: 9/02/20 | D13: 1616.48 | E13: 0 | F13: 0 | G13: 121.71 | H13: 55.97 | I13: =G13+H13 -> 177.68 | J13: =D13-I13 -> 1438.8 | K13: S/L | L13: 30.00
A14: 5 | B14: 2-Land Improvements-bldg 6 | C14: 8/15/18 | D14: 8795.97 | E14: 0 | F14: 2256.71 | G14: 2256.71 | H14: 676.47 | I14: =G14+H14 -> 2933.18 | J14: =D14-I14 -> 5862.79 | K14: 150DB | L14: 15.0
A15: 6 | B15: 13-New Equipment(16 units)-bldg 6 | C15: 12/20/22 | D15: 7572.23 | E15: 0 | F15: 0 | G15: 0 | H15: 0 | I15: =G15+H15 -> 0 | J15: =D15-I15 -> 7572.23 | K15: 200DB | L15: 5.0
A16: 7 | B16: 15-New Equipment(105 units)-bldg 6 | C16: 4/01/23 | D16: 50752.78 | E16: 0 | F16: 0 | G16: 2030.1 | H16: 3248.19 | I16: =G16+H16 -> 5278.29 | J16: =D16-I16 -> 45474.49 | K16: 200DB | L16: 5.0
B17: Grand Total | D17: =SUM(D10:D16) -> 398758.21 | E17: =SUM(E10:E16) -> 0 | F17: =SUM(F10:F16) -> 2256.71 | G17: =SUM(G10:G16) -> 17707.8 | H17: =SUM(H10:H16) -> 15179.55 | I17: =SUM(I10:I16) -> 32887.35 | J17: =SUM(J10:J16) -> 365870.86
A19: After Cost Segregation Correction
A20: Asset | B20: Property Description | C20: Date In Service | D20: Cost | E20: Sec 179 Exp | F20: Bonus Amt | G20: Tax Prior Depreciation | H20: Tax Current Depreciation | I20: End Depreciation | J20: Net Book Value | K20: Method | L20: Period
A21: 1 | B21: 10-Building-Post Casualty Loss Basis-bldg6-5y | C21: 8/15/18 | D21: 16882.61 | E21: 0 | F21: 16882.61 | G21: 16882.61 | H21: 0 | I21: =G21+H21 -> 16882.61 | J21: =D21-I21 -> 0 | K21: 200DB | L21: 5.0
A22: 2 | B22: 10-Building-Post Casualty Loss Basis-bldg6-30 | C22: 8/15/18 | D22: 47435.37 | E22: 0 | F22: 0 | G22: 8498.84 | H22: 1581.18 | I22: =G22+H22 -> 10080.02 | J22: =D22-I22 -> 37355.35 | K22: S/L | L22: 30.00
A23: 3 | B23: 12-New Buildings(16 units)-bldg6-5yr | C23: 12/20/22 | D23: 9054.67 | E23: 0 | F23: 9054.67 | G23: 9054.67 | H23: 0 | I23: =G23+H23 -> 9054.67 | J23: =D23-I23 -> 0 | K23: 200DB | L23: 5.0
A24: 4 | B24: 12-New Buildings(16 units)-bldg6-30yr | C24: 12/20/22 | D24: 25441.07 | E24: 0 | F24: 0 | G24: 883.37 | H24: 848.04 | I24: =G24+H24 -> 1731.41 | J24: =D24-I24 -> 23709.66 | K24: S/L | L24: 30.00
A25: 5 | B25: 14-New Buildings(105 units)-bldg6-5yr | C25: 4/01/23 | D25: 60688.77 | E25: 0 | F25: 48551.02 | G25: 50978.57 | H25: 3884.08 | I25: =G25+H25 -> 54862.65 | J25: =D25-I25 -> 5826.12 | K25: 200DB | L25: 5.0
A26: 6 | B26: 14-New Buildings(105 units)-bldg6-30yr | C26: 4/01/23 | D26: 170518.26 | E26: 0 | F26: 0 | G26: 4026.13 | H26: 5683.94 | I26: =G26+H26 -> 9710.07 | J26: =D26-I26 -> 160808.19 | K26: S/L | L26: 30.00
A27: 7 | B27: 11-Building Imp-Post-Casulty Loss Basis-bldg6 | C27: 9/02/20 | D27: 424.3 | E27: 0 | F27: 424.3 | G27: 424.3 | H27: 0 | I27: =G27+H27 -> 424.3 | J27: =D27-I27 -> 0 | K27: 200DB | L27: 5.0
A28: 8 | B28: 11-Building Imp-Post-Casulty Loss Basis-bldg6 | C28: 9/02/20 | D28: 1192.18 | E28: 0 | F28: 0 | G28: 130.81 | H28: 39.74 | I28: =G28+H28 -> 170.55 | J28: =D28-I28 -> 1021.63 | K28: S/L | L28: 30.00
A29: 9 | B29: 2-Land Improvements-bldg6-5yr | C29: 8/15/18 | D29: 2308.83 | E29: 0 | F29: 2308.83 | G29: 2308.83 | H29: 0 | I29: =G29+H29 -> 2308.83 | J29: =D29-I29 -> 0 | K29: 200DB | L29: 5.0
A30: 10 | B30: 2-Land Improvements-bldg6-30yr | C30: 8/15/18 | D30: 6487.14 | E30: 0 | F30: 0 | G30: 1162.29 | H30: 216.24 | I30: =G30+H30 -> 1378.53 | J30: =D30-I30 -> 5108.61 | K30: S/L | L30: 30.00
A31: 11 | B31: 13-New Equipment(16 units)-bldg6-5yr | C31: 12/20/22 | D31: 1987.61 | E31: 0 | F31: 1987.61 | G31: 1987.61 | H31: 0 | I31: =G31+H31 -> 1987.61 | J31: =D31-I31 -> 0 | K31: 200DB | L31: 5.0
A32: 12 | B32: 13-New Equipment(16 units)-bldg6-30yr | C32: 12/20/22 | D32: 5584.62 | E32: 0 | F32: 0 | G32: 193.91 | H32: 186.15 | I32: =G32+H32 -> 380.06 | J32: =D32-I32 -> 5204.56 | K32: S/L | L32: 30.00
... A34: 14 | B34: 15-New Equipment(105 units)-bldg6-30yr | C34: 4/01/23 | D34: 37430.84 | E34: 0 | F34: 0 | G34: 883.78 | H34: 1247.69 | I34: =G34+H34 -> 2131.47 | J34: =D34-I34 -> 35299.37 | K34: S/L | L34: 30.00
B35: Grand Total | D35: =SUM(D21:D34) -> 398758.21 | E35: =SUM(E21:E34) -> 0 | F35: =SUM(F21:F34) -> 89866.59 | G35: =SUM(G21:G34) -> 108606.15 | H35: =SUM(H21:H34) -> 14539.66 | I35: =SUM(I21:I34) -> 123145.81 | J35: =SUM(J21:J34) -> 275612.4
B37: Section 481(a) Adjustment — Regular Tax
B38: Depreciation reported previously | D38: =I17 -> 32887.35
B39: Cost Segregation Corrected Depreciation | D39: =I35 -> 123145.81
B40: Section 481(a) Adjustment — Regular Tax | D40: =D38-D39 -> -90258.46
A42: CALCULATION OF §481(a) ADJUSTMENT — AMT
A43: As Previously Filed — AMT
A44: Asset | B44: Property Description | C44: Date In Service | D44: Cost | E44: Sec 179 Exp | F44: Bonus Amt | G44: AMT Prior Depreciation | H44: AMT Current Depreciation | I44: End Depreciation | J44: Net Book Value | K44: Method | L44: Period
A45: 1 | B45: 10-Building(Post Casualty Loss Basis)-bldg 6 | C45: 8/15/18 | D45: 64317.98 | E45: 0 | F45: 0 | G45: 6642.44 | H45: 2342.15 | I45: =G45+H45 -> 8984.59 | J45: =D45-I45 -> 55333.39 | K45: S/L | L45: 30.00
A46: 2 | B46: 12-New Buildings(16 units)-bldg 6 | C46: 12/20/22 | D46: 34495.74 | E46: 0 | F46: 0 | G46: 1197.79 | H46: 1149.85 | I46: =G46+H46 -> 2347.64 | J46: =D46-I46 -> 32148.1 | K46: S/L | L46: 30.00
A47: 3 | B47: 14-New Buildings(105 units)-bldg 6 | C47: 4/01/23 | D47: 231207.03 | E47: 0 | F47: 0 | G47: 5459.05 | H47: 7706.92 | I47: =G47+H47 -> 13165.97 | J47: =D47-I47 -> 218041.06 | K47: S/L | L47: 30.00
A48: 4 | B48: 11-Building Imp)Post-Casulty Loss Basis)-bldg | C48: 9/02/20 | D48: 1616.48 | E48: 0 | F48: 0 | G48: 121.71 | H48: 55.97 | I48: =G48+H48 -> 177.68 | J48: =D48-I48 -> 1438.8 | K48: S/L | L48: 30.00
A49: 5 | B49: 2-Land Improvements-bldg 6 | C49: 8/15/18 | D49: 8795.97 | E49: 0 | F49: 2256.71 | G49: 2256.71 | H49: 676.47 | I49: =G49+H49 -> 2933.18 | J49: =D49-I49 -> 5862.79 | K49: 150DB | L49: 15.0
A50: 6 | B50: 13-New Equipment(16 units)-bldg 6 | C50: 12/20/22 | D50: 7572.23 | E50: 0 | F50: 0 | G50: 0 | H50: 0 | I50: =G50+H50 -> 0 | J50: =D50-I50 -> 7572.23 | K50: 200DB | L50: 5.0
A51: 7 | B51: 15-New Equipment(105 units)-bldg 6 | C51: 4/01/23 | D51: 50752.78 | E51: 0 | F51: 0 | G51: 2030.1 | H51: 3248.19 | I51: =G51+H51 -> 5278.29 | J51: =D51-I51 -> 45474.49 | K51: 200DB | L51: 5.0
B52: Grand Total | D52: =SUM(D45:D51) -> 398758.21 | E52: =SUM(E45:E51) -> 0 | F52: =SUM(F45:F51) -> 2256.71 | G52: =SUM(G45:G51) -> 17707.8 | H52: =SUM(H45:H51) -> 15179.55 | I52: =SUM(I45:I51) -> 32887.35 | J52: =SUM(J45:J51) -> 365870.86
A54: After Cost Segregation Correction — AMT
A55: Asset | B55: Property Description | C55: Date In Service | D55: Cost | E55: Sec 179 Exp | F55: Bonus Amt | G55: AMT Prior Depreciation | H55: AMT Current Depreciation | I55: End Depreciation | J55: Net Book Value | K55: Method | L55: Period
A56: 1 | B56: 12-New Buildings(16 units)-bldg6-5yr | C56: 12/20/22 | D56: 9054.67 | E56: 0 | F56: 9054.67 | G56: 9054.67 | H56: 0 | I56: =G56+H56 -> 9054.67 | J56: =D56-I56 -> 0 | K56: 200DB | L56: 5.0
A57: 2 | B57: 12-New Buildings(16 units)-bldg6-30yr | C57: 12/20/22 | D57: 25441.07 | E57: 0 | F57: 0 | G57: 883.37 | H57: 848.04 | I57: =G57+H57 -> 1731.41 | J57: =D57-I57 -> 23709.66 | K57: S/L | L57: 30.00
A58: 3 | B58: 14-New Buildings(105 units)-bldg6-5yr | C58: 4/01/23 | D58: 60688.77 | E58: 0 | F58: 48551.02 | G58: 50978.57 | H58: 3884.08 | I58: =G58+H58 -> 54862.65 | J58: =D58-I58 -> 5826.12 | K58: 200DB | L58: 5.0
A59: 4 | B59: 14-New Buildings(105 units)-bldg6-30yr | C59: 4/01/23 | D59: 170518.26 | E59: 0 | F59: 0 | G59: 4026.13 | H59: 5683.94 | I59: =G59+H59 -> 9710.07 | J59: =D59-I59 -> 160808.19 | K59: S/L | L59: 30.00
A60: 5 | B60: 2-Land Improvements-bldg6-5yr | C60: 8/15/18 | D60: 2308.83 | E60: 0 | F60: 2308.83 | G60: 2308.83 | H60: 0 | I60: =G60+H60 -> 2308.83 | J60: =D60-I60 -> 0 | K60: 200DB | L60: 5.0
A61: 6 | B61: 2-Land Improvements-bldg6-30yr | C61: 8/15/18 | D61: 6487.14 | E61: 0 | F61: 0 | G61: 1162.29 | H61: 216.24 | I61: =G61+H61 -> 1378.53 | J61: =D61-I61 -> 5108.61 | K61: S/L | L61: 30.00
A62: 7 | B62: 13-New Equipment(16 units)-bldg6-5yr | C62: 12/20/22 | D62: 1987.61 | E62: 0 | F62: 1987.61 | G62: 1987.61 | H62: 0 | I62: =G62+H62 -> 1987.61 | J62: =D62-I62 -> 0 | K62: 200DB | L62: 5.0
A63: 8 | B63: 13-New Equipment(16 units)-bldg6-30yr | C63: 12/20/22 | D63: 5584.62 | E63: 0 | F63: 0 | G63: 193.91 | H63: 186.15 | I63: =G63+H63 -> 380.06 | J63: =D63-I63 -> 5204.56 | K63: S/L | L63: 30.00
A64: 9 | B64: 15-New Equipment(105 units)-bldg6-5yr | C64: 4/01/23 | D64: 13321.94 | E64: 0 | F64: 10657.55 | G64: 11190.43 | H64: 852.6 | I64: =G64+H64 -> 12043.03 | J64: =D64-I64 -> 1278.91 | K64: 200DB | L64: 5.0
A65: 10 | B65: 15-New Equipment(105 units)-bldg6-30yr | C65: 4/01/23 | D65: 37430.84 | E65: 0 | F65: 0 | G65: 883.78 | H65: 1247.69 | I65: =G65+H65 -> 2131.47 | J65: =D65-I65 -> 35299.37 | K65: S/L | L65: 30.00
B66: Grand Total | D66: =SUM(D56:D65) -> 332823.75 | E66: =SUM(E56:E65) -> 0 | F66: =SUM(F56:F65) -> 72559.68 | G66: =SUM(G56:G65) -> 82669.59 | H66: =SUM(H56:H65) -> 12918.74 | I66: =SUM(I56:I65) -> 95588.33 | J66: =SUM(J56:J65) -> 237235.42
B68: Section 481(a) Adjustment — AMT
B69: Depreciation reported previously | D69: =I52 -> 32887.35
B70: Cost Segregation Corrected Depreciation | D70: =I66 -> 95588.33
B71: Section 481(a) Adjustment — AMT | D71: =D69-D70 -> -62700.98
A73: COST SEGREGATION STUDY — COST SUMMARY
B74: Total Building Cost | D74: =D111 -> 398758.21
B75: Building Components: 5 Year | D75: =F111 -> 104668.73
B76: % of Cost | D76: =F112 -> 0.26248671
B77: Building Structure: 30 Year | D77: =H111 -> 294089.48
B78: % of Cost | D78: =H112 -> 0.73751329
A80: COST SEGREGATION STUDY — COST DETAIL
B81: Property Category | D81: Cost | F81: 5 Year | H81: 30 Year
B82: Building Components
B83: Cabinets / Millwork | D83: =SUM(F83:H83) -> 31452.73 | F83: 31452.73
B84: Moldings | D84: =SUM(F84:H84) -> 8394.17 | F84: 8394.17
B85: Flooring - Vinyl Plank | D85: =SUM(F85:H85) -> 32815.9 | F85: 32815.9
B86: Window Treatments | D86: =SUM(F86:H86) -> 2648.72 | F86: 2648.72
B87: Building Signage | D87: =SUM(F87:H87) -> 394.4 | F87: 394.4
B88: Specialty Electrical - Appliances | D88: =SUM(F88:H88) -> 5344.3 | F88: 5344.3
B89: Communication / Data | D89: =SUM(F89:H89) -> 2858.97 | F89: 2858.97
B90: Specialty Plumbing - Kitchen Sinks | D90: =SUM(F90:H90) -> 9687.68 | F90: 9687.68
B91: Security / Exterior Lighting | D91: =SUM(F91:H91) -> 2139.23 | F91: 2139.23
B92: Canopies / Awnings | D92: =SUM(F92:H92) -> 605.69 | F92: 605.69
B93: Appliances | D93: =SUM(F93:H93) -> 8326.94 | F93: 8326.94
B94: Building Structure
B95: Roofing Systems | D95: =SUM(F95:H95) -> 16256.26 | H95: 16256.26
B96: Foundations | D96: =SUM(F96:H96) -> 21691.79 | H96: 21691.79
B97: HVAC | D97: =SUM(F97:H97) -> 31892.38 | H97: 31892.38
B98: Electrical | D98: =SUM(F98:H98) -> 29436.62 | H98: 29436.62
B99: Plumbing | D99: =SUM(F99:H99) -> 27723.88 | H99: 27723.88
B100: Fire Protection & Alarm | D100: =SUM(F100:H100) -> 1864.29 | H100: 1864.29
B101: Exterior Façade / Building Skin | D101: =SUM(F101:H101) -> 21222.77 | H101: 21222.77
B102: Doors & Frames | D102: =SUM(F102:H102) -> 16292.68 | H102: 16292.68
B103: Windows | D103: =SUM(F103:H103) -> 12258.17 | H103: 12258.17
B104: Ceiling Systems | D104: =SUM(F104:H104) -> 14614.91 | H104: 14614.91
B105: Interior Framing / Partitions | D105: =SUM(F105:H105) -> 38542.73 | H105: 38542.73
B106: Painting | D106: =SUM(F106:H106) -> 15289.77 | H106: 15289.77
... B110: Cabinets / Millwork - Restrooms | D110: =SUM(F110:H110) -> 1880.89 | H110: 1880.89
B111: Total Building Cost | D111: =SUM(D82:D110) -> 398758.21 | F111: =SUM(F82:F110) -> 104668.73 | H111: =SUM(H82:H110) -> 294089.48
B112: % of Cost | F112: =F111/D111 -> 0.26248671 | H112: =H111/D111 -> 0.73751329
...

Sheet Building 7
A1: St Charles Housing LP
A2: St. Charles — 1011 W 18th St, Lake Charles, LA 70607
A3: EIN: 82-5349206 · FYE: December 31, 2024 · Year of Change: 1/1/2024
A4: Building 7 — Attachment to Form 3115 (DCN #7, Rev. Proc. 2024-23 §6.01)
A5: Source: CSSI Report #107752-24, "St. Charles Housing LP_107752-24_3115_Combined.pdf"
A7: CALCULATION OF §481(a) ADJUSTMENT — REGULAR TAX
A8: As Previously Filed
A9: Asset | B9: Property Description | C9: Date In Service | D9: Cost | E9: Sec 179 Exp | F9: Bonus Amt | G9: Tax Prior Depreciation | H9: Tax Current Depreciation | I9: End Depreciation | J9: Net Book Value | K9: Method | L9: Period
A10: 1 | B10: 10-Building(Post Casualty Loss Basis)-bldg 7 | C10: 8/15/18 | D10: 72325.23 | E10: 0 | F10: 0 | G10: 7469.39 | H10: 2633.73 | I10: =G10+H10 -> 10103.12 | J10: =D10-I10 -> 62222.11 | K10: S/L | L10: 30.00
A11: 2 | B11: 12-New Buildings(16 units)-bldg 7 | C11: 12/20/22 | D11: 38790.29 | E11: 0 | F11: 0 | G11: 1346.91 | H11: 1293 | I11: =G11+H11 -> 2639.91 | J11: =D11-I11 -> 36150.38 | K11: S/L | L11: 30.00
A12: 3 | B12: 14-New Buildings(105 units)-bldg 7 | C12: 4/01/23 | D12: 259991.11 | E12: 0 | F12: 0 | G12: 6138.68 | H12: 8666.38 | I12: =G12+H12 -> 14805.06 | J12: =D12-I12 -> 245186.05 | K12: S/L | L12: 30.00
A13: 4 | B13: 11-Building Imp)Post-Casulty Loss Basis)-bldg | C13: 9/02/20 | D13: 1817.72 | E13: 0 | F13: 0 | G13: 136.87 | H13: 62.93 | I13: =G13+H13 -> 199.8 | J13: =D13-I13 -> 1617.92 | K13: S/L | L13: 30.00
A14: 5 | B14: 2-Land Improvements-bldg 7 | C14: 8/15/18 | D14: 9891.01 | E14: 0 | F14: 2537.66 | G14: 2537.66 | H14: 760.68 | I14: =G14+H14 -> 3298.34 | J14: =D14-I14 -> 6592.67 | K14: 150DB | L14: 15.0
A15: 6 | B15: 13-New Equipment(16 units)-bldg 7 | C15: 12/20/22 | D15: 8514.93 | E15: 0 | F15: 0 | G15: 0 | H15: 0 | I15: =G15+H15 -> 0 | J15: =D15-I15 -> 8514.93 | K15: 200DB | L15: 5.0
A16: 7 | B16: 15-New Equipment(105 units)-bldg 7 | C16: 4/01/23 | D16: 57071.24 | E16: 0 | F16: 0 | G16: 2282.85 | H16: 3652.56 | I16: =G16+H16 -> 5935.41 | J16: =D16-I16 -> 51135.83 | K16: 200DB | L16: 5.0
B17: Grand Total | D17: =SUM(D10:D16) -> 448401.53 | E17: =SUM(E10:E16) -> 0 | F17: =SUM(F10:F16) -> 2537.66 | G17: =SUM(G10:G16) -> 19912.36 | H17: =SUM(H10:H16) -> 17069.28 | I17: =SUM(I10:I16) -> 36981.64 | J17: =SUM(J10:J16) -> 411419.89
A19: After Cost Segregation Correction
A20: Asset | B20: Property Description | C20: Date In Service | D20: Cost | E20: Sec 179 Exp | F20: Bonus Amt | G20: Tax Prior Depreciation | H20: Tax Current Depreciation | I20: End Depreciation | J20: Net Book Value | K20: Method | L20: Period
A21: 1 | B21: 10-Building-Post Casualty Loss Basis-bldg7-5y | C21: 8/15/18 | D21: 18042.22 | E21: 0 | F21: 18042.22 | G21: 18042.22 | H21: 0 | I21: =G21+H21 -> 18042.22 | J21: =D21-I21 -> 0 | K21: 200DB | L21: 5.0
A22: 2 | B22: 10-Building-Post Casualty Loss Basis-bldg7-30 | C22: 8/15/18 | D22: 54283.01 | E22: 0 | F22: 0 | G22: 9725.69 | H22: 1809.43 | I22: =G22+H22 -> 11535.12 | J22: =D22-I22 -> 42747.89 | K22: S/L | L22: 30.00
A23: 3 | B23: 12-New Buildings(16 units)-bldg7-5yr | C23: 12/20/22 | D23: 9676.61 | E23: 0 | F23: 9676.61 | G23: 9676.61 | H23: 0 | I23: =G23+H23 -> 9676.61 | J23: =D23-I23 -> 0 | K23: 200DB | L23: 5.0
A24: 4 | B24: 12-New Buildings(16 units)-bldg7-30yr | C24: 12/20/22 | D24: 29113.68 | E24: 0 | F24: 0 | G24: 1010.9 | H24: 970.46 | I24: =G24+H24 -> 1981.36 | J24: =D24-I24 -> 27132.32 | K24: S/L | L24: 30.00
A25: 5 | B25: 14-New Buildings(105 units)-bldg7-5yr | C25: 4/01/23 | D25: 64857.26 | E25: 0 | F25: 51885.81 | G25: 54480.1 | H25: 4150.86 | I25: =G25+H25 -> 58630.96 | J25: =D25-I25 -> 6226.3 | K25: 200DB | L25: 5.0
A26: 6 | B26: 14-New Buildings(105 units)-bldg7-30yr | C26: 4/01/23 | D26: 195133.85 | E26: 0 | F26: 0 | G26: 4607.33 | H26: 6504.46 | I26: =G26+H26 -> 11111.79 | J26: =D26-I26 -> 184022.06 | K26: S/L | L26: 30.00
A27: 7 | B27: 11-Building Imp-Post-Casulty Loss Basis-bldg7 | C27: 9/02/20 | D27: 453.45 | E27: 0 | F27: 453.45 | G27: 453.45 | H27: 0 | I27: =G27+H27 -> 453.45 | J27: =D27-I27 -> 0 | K27: 200DB | L27: 5.0
A28: 8 | B28: 11-Building Imp-Post-Casulty Loss Basis-bldg7 | C28: 9/02/20 | D28: 1364.27 | E28: 0 | F28: 0 | G28: 149.7 | H28: 45.48 | I28: =G28+H28 -> 195.18 | J28: =D28-I28 -> 1169.09 | K28: S/L | L28: 30.00
A29: 9 | B29: 2-Land Improvements-bldg7-5yr | C29: 8/15/18 | D29: 2467.41 | E29: 0 | F29: 2467.41 | G29: 2467.41 | H29: 0 | I29: =G29+H29 -> 2467.41 | J29: =D29-I29 -> 0 | K29: 200DB | L29: 5.0
A30: 10 | B30: 2-Land Improvements-bldg7-30yr | C30: 8/15/18 | D30: 7423.6 | E30: 0 | F30: 0 | G30: 1330.05 | H30: 247.45 | I30: =G30+H30 -> 1577.5 | J30: =D30-I30 -> 5846.1 | K30: S/L | L30: 30.00
A31: 11 | B31: 13-New Equipment(16 units)-bldg7-5yr | C31: 12/20/22 | D31: 2124.13 | E31: 0 | F31: 2124.13 | G31: 2124.13 | H31: 0 | I31: =G31+H31 -> 2124.13 | J31: =D31-I31 -> 0 | K31: 200DB | L31: 5.0
A32: 12 | B32: 13-New Equipment(16 units)-bldg7-30yr | C32: 12/20/22 | D32: 6390.8 | E32: 0 | F32: 0 | G32: 221.91 | H32: 213.03 | I32: =G32+H32 -> 434.94 | J32: =D32-I32 -> 5955.86 | K32: S/L | L32: 30.00
... A34: 14 | B34: 15-New Equipment(105 units)-bldg7-30yr | C34: 4/01/23 | D34: 42834.29 | E34: 0 | F34: 0 | G34: 1011.37 | H34: 1427.81 | I34: =G34+H34 -> 2439.18 | J34: =D34-I34 -> 40395.11 | K34: S/L | L34: 30.00
B35: Grand Total | D35: =SUM(D21:D34) -> 448401.53 | E35: =SUM(E21:E34) -> 0 | F35: =SUM(F21:F34) -> 96039.19 | G35: =SUM(G21:G34) -> 117259.91 | H35: =SUM(H21:H34) -> 16280.14 | I35: =SUM(I21:I34) -> 133540.05 | J35: =SUM(J21:J34) -> 314861.48
B37: Section 481(a) Adjustment — Regular Tax
B38: Depreciation reported previously | D38: =I17 -> 36981.64
B39: Cost Segregation Corrected Depreciation | D39: =I35 -> 133540.05
B40: Section 481(a) Adjustment — Regular Tax | D40: =D38-D39 -> -96558.41
A42: CALCULATION OF §481(a) ADJUSTMENT — AMT
A43: As Previously Filed — AMT
A44: Asset | B44: Property Description | C44: Date In Service | D44: Cost | E44: Sec 179 Exp | F44: Bonus Amt | G44: AMT Prior Depreciation | H44: AMT Current Depreciation | I44: End Depreciation | J44: Net Book Value | K44: Method | L44: Period
A45: 1 | B45: 10-Building(Post Casualty Loss Basis)-bldg 7 | C45: 8/15/18 | D45: 72325.23 | E45: 0 | F45: 0 | G45: 7469.39 | H45: 2633.73 | I45: =G45+H45 -> 10103.12 | J45: =D45-I45 -> 62222.11 | K45: S/L | L45: 30.00
A46: 2 | B46: 12-New Buildings(16 units)-bldg 7 | C46: 12/20/22 | D46: 38790.29 | E46: 0 | F46: 0 | G46: 1346.91 | H46: 1293 | I46: =G46+H46 -> 2639.91 | J46: =D46-I46 -> 36150.38 | K46: S/L | L46: 30.00
A47: 3 | B47: 14-New Buildings(105 units)-bldg 7 | C47: 4/01/23 | D47: 259991.11 | E47: 0 | F47: 0 | G47: 6138.68 | H47: 8666.38 | I47: =G47+H47 -> 14805.06 | J47: =D47-I47 -> 245186.05 | K47: S/L | L47: 30.00
A48: 4 | B48: 11-Building Imp)Post-Casulty Loss Basis)-bldg | C48: 9/02/20 | D48: 1817.72 | E48: 0 | F48: 0 | G48: 136.87 | H48: 62.93 | I48: =G48+H48 -> 199.8 | J48: =D48-I48 -> 1617.92 | K48: S/L | L48: 30.00
A49: 5 | B49: 2-Land Improvements-bldg 7 | C49: 8/15/18 | D49: 9891.01 | E49: 0 | F49: 2537.66 | G49: 2537.66 | H49: 760.68 | I49: =G49+H49 -> 3298.34 | J49: =D49-I49 -> 6592.67 | K49: 150DB | L49: 15.0
A50: 6 | B50: 13-New Equipment(16 units)-bldg 7 | C50: 12/20/22 | D50: 8514.93 | E50: 0 | F50: 0 | G50: 0 | H50: 0 | I50: =G50+H50 -> 0 | J50: =D50-I50 -> 8514.93 | K50: 200DB | L50: 5.0
A51: 7 | B51: 15-New Equipment(105 units)-bldg 7 | C51: 4/01/23 | D51: 57071.24 | E51: 0 | F51: 0 | G51: 2282.85 | H51: 3652.56 | I51: =G51+H51 -> 5935.41 | J51: =D51-I51 -> 51135.83 | K51: 200DB | L51: 5.0
B52: Grand Total | D52: =SUM(D45:D51) -> 448401.53 | E52: =SUM(E45:E51) -> 0 | F52: =SUM(F45:F51) -> 2537.66 | G52: =SUM(G45:G51) -> 19912.36 | H52: =SUM(H45:H51) -> 17069.28 | I52: =SUM(I45:I51) -> 36981.64 | J52: =SUM(J45:J51) -> 411419.89
A54: After Cost Segregation Correction — AMT
A55: Asset | B55: Property Description | C55: Date In Service | D55: Cost | E55: Sec 179 Exp | F55: Bonus Amt | G55: AMT Prior Depreciation | H55: AMT Current Depreciation | I55: End Depreciation | J55: Net Book Value | K55: Method | L55: Period
A56: 1 | B56: 12-New Buildings(16 units)-bldg7-5yr | C56: 12/20/22 | D56: 9676.61 | E56: 0 | F56: 9676.61 | G56: 9676.61 | H56: 0 | I56: =G56+H56 -> 9676.61 | J56: =D56-I56 -> 0 | K56: 200DB | L56: 5.0
A57: 2 | B57: 12-New Buildings(16 units)-bldg7-30yr | C57: 12/20/22 | D57: 29113.68 | E57: 0 | F57: 0 | G57: 1010.9 | H57: 970.46 | I57: =G57+H57 -> 1981.36 | J57: =D57-I57 -> 27132.32 | K57: S/L | L57: 30.00
A58: 3 | B58: 14-New Buildings(105 units)-bldg7-5yr | C58: 4/01/23 | D58: 64857.26 | E58: 0 | F58: 51885.81 | G58: 54480.1 | H58: 4150.86 | I58: =G58+H58 -> 58630.96 | J58: =D58-I58 -> 6226.3 | K58: 200DB | L58: 5.0
A59: 4 | B59: 14-New Buildings(105 units)-bldg7-30yr | C59: 4/01/23 | D59: 195133.85 | E59: 0 | F59: 0 | G59: 4607.33 | H59: 6504.46 | I59: =G59+H59 -> 11111.79 | J59: =D59-I59 -> 184022.06 | K59: S/L | L59: 30.00
A60: 5 | B60: 2-Land Improvements-bldg7-5yr | C60: 8/15/18 | D60: 2467.41 | E60: 0 | F60: 2467.41 | G60: 2467.41 | H60: 0 | I60: =G60+H60 -> 2467.41 | J60: =D60-I60 -> 0 | K60: 200DB | L60: 5.0
A61: 6 | B61: 2-Land Improvements-bldg7-30yr | C61: 8/15/18 | D61: 7423.6 | E61: 0 | F61: 0 | G61: 1330.05 | H61: 247.45 | I61: =G61+H61 -> 1577.5 | J61: =D61-I61 -> 5846.1 | K61: S/L | L61: 30.00
A62: 7 | B62: 13-New Equipment(16 units)-bldg7-5yr | C62: 12/20/22 | D62: 2124.13 | E62: 0 | F62: 2124.13 | G62: 2124.13 | H62: 0 | I62: =G62+H62 -> 2124.13 | J62: =D62-I62 -> 0 | K62: 200DB | L62: 5.0
A63: 8 | B63: 13-New Equipment(16 units)-bldg7-30yr | C63: 12/20/22 | D63: 6390.8 | E63: 0 | F63: 0 | G63: 221.91 | H63: 213.03 | I63: =G63+H63 -> 434.94 | J63: =D63-I63 -> 5955.86 | K63: S/L | L63: 30.00
A64: 9 | B64: 15-New Equipment(105 units)-bldg7-5yr | C64: 4/01/23 | D64: 14236.95 | E64: 0 | F64: 11389.56 | G64: 11959.04 | H64: 911.16 | I64: =G64+H64 -> 12870.2 | J64: =D64-I64 -> 1366.75 | K64: 200DB | L64: 5.0
A65: 10 | B65: 15-New Equipment(105 units)-bldg7-30yr | C65: 4/01/23 | D65: 42834.29 | E65: 0 | F65: 0 | G65: 1011.37 | H65: 1427.81 | I65: =G65+H65 -> 2439.18 | J65: =D65-I65 -> 40395.11 | K65: S/L | L65: 30.00
B66: Grand Total | D66: =SUM(D56:D65) -> 374258.58 | E66: =SUM(E56:E65) -> 0 | F66: =SUM(F56:F65) -> 77543.52 | G66: =SUM(G56:G65) -> 88888.85 | H66: =SUM(H56:H65) -> 14425.23 | I66: =SUM(I56:I65) -> 103314.08 | J66: =SUM(J56:J65) -> 270944.5
B68: Section 481(a) Adjustment — AMT
B69: Depreciation reported previously | D69: =I52 -> 36981.64
B70: Cost Segregation Corrected Depreciation | D70: =I66 -> 103314.08
B71: Section 481(a) Adjustment — AMT | D71: =D69-D70 -> -66332.44
A73: COST SEGREGATION STUDY — COST SUMMARY
B74: Total Building Cost | D74: =D111 -> 448401.53
B75: Building Components: 5 Year | D75: =F111 -> 111858.03
B76: % of Cost | D76: =F112 -> 0.24945952
B77: Building Structure: 30 Year | D77: =H111 -> 336543.5
B78: % of Cost | D78: =H112 -> 0.75054048
A80: COST SEGREGATION STUDY — COST DETAIL
B81: Property Category | D81: Cost | F81: 5 Year | H81: 30 Year
B82: Building Components
B83: Cabinets / Millwork | D83: =SUM(F83:H83) -> 31452.73 | F83: 31452.73
B84: Moldings | D84: =SUM(F84:H84) -> 8975.5 | F84: 8975.5
B85: Flooring - Vinyl Plank | D85: =SUM(F85:H85) -> 38285.2 | F85: 38285.2
B86: Window Treatments | D86: =SUM(F86:H86) -> 3310.89 | F86: 3310.89
B87: Building Signage | D87: =SUM(F87:H87) -> 394.4 | F87: 394.4
B88: Specialty Electrical - Appliances | D88: =SUM(F88:H88) -> 5344.3 | F88: 5344.3
B89: Communication / Data | D89: =SUM(F89:H89) -> 3335.47 | F89: 3335.47
B90: Specialty Plumbing - Kitchen Sinks | D90: =SUM(F90:H90) -> 9687.68 | F90: 9687.68
B91: Security / Exterior Lighting | D91: =SUM(F91:H91) -> 2139.23 | F91: 2139.23
B92: Canopies / Awnings | D92: =SUM(F92:H92) -> 605.69 | F92: 605.69
B93: Appliances | D93: =SUM(F93:H93) -> 8326.94 | F93: 8326.94
B94: Building Structure
B95: Roofing Systems | D95: =SUM(F95:H95) -> 18787.91 | H95: 18787.91
B96: Foundations | D96: =SUM(F96:H96) -> 25094.53 | H96: 25094.53
B97: HVAC | D97: =SUM(F97:H97) -> 37207.78 | H97: 37207.78
B98: Electrical | D98: =SUM(F98:H98) -> 35233.43 | H98: 35233.43
B99: Plumbing | D99: =SUM(F99:H99) -> 32344.52 | H99: 32344.52
B100: Fire Protection & Alarm | D100: =SUM(F100:H100) -> 2485.72 | H100: 2485.72
B101: Exterior Façade / Building Skin | D101: =SUM(F101:H101) -> 24768.13 | H101: 24768.13
B102: Doors & Frames | D102: =SUM(F102:H102) -> 18966.91 | H102: 18966.91
B103: Windows | D103: =SUM(F103:H103) -> 15176.79 | H103: 15176.79
B104: Ceiling Systems | D104: =SUM(F104:H104) -> 17050.73 | H104: 17050.73
B105: Interior Framing / Partitions | D105: =SUM(F105:H105) -> 40897.65 | H105: 40897.65
B106: Painting | D106: =SUM(F106:H106) -> 16588.72 | H106: 16588.72
... B110: Cabinets / Millwork - Restrooms | D110: =SUM(F110:H110) -> 1880.89 | H110: 1880.89
B111: Total Building Cost | D111: =SUM(D82:D110) -> 448401.53 | F111: =SUM(F82:F110) -> 111858.03 | H111: =SUM(H82:H110) -> 336543.5
B112: % of Cost | F112: =F111/D111 -> 0.24945952 | H112: =H111/D111 -> 0.75054048
...

Sheet Building 8
A1: St Charles Housing LP
A2: St. Charles — 1011 W 18th St, Lake Charles, LA 70607
A3: EIN: 82-5349206 · FYE: December 31, 2024 · Year of Change: 1/1/2024
A4: Building 8 — Attachment to Form 3115 (DCN #7, Rev. Proc. 2024-23 §6.01)
A5: Source: CSSI Report #107752-24, "St. Charles Housing LP_107752-24_3115_Combined.pdf"
A7: CALCULATION OF §481(a) ADJUSTMENT — REGULAR TAX
A8: As Previously Filed
A9: Asset | B9: Property Description | C9: Date In Service | D9: Cost | E9: Sec 179 Exp | F9: Bonus Amt | G9: Tax Prior Depreciation | H9: Tax Current Depreciation | I9: End Depreciation | J9: Net Book Value | K9: Method | L9: Period
A10: 1 | B10: 10-Building(Post Casualty Loss Basis)-bldg 8 | C10: 8/15/18 | D10: 64317.98 | E10: 0 | F10: 0 | G10: 6642.44 | H10: 2342.15 | I10: =G10+H10 -> 8984.59 | J10: =D10-I10 -> 55333.39 | K10: S/L | L10: 30.00
A11: 2 | B11: 12-New Buildings(16 units)-bldg 8 | C11: 12/20/22 | D11: 34495.74 | E11: 0 | F11: 0 | G11: 1197.79 | H11: 1149.85 | I11: =G11+H11 -> 2347.64 | J11: =D11-I11 -> 32148.1 | K11: S/L | L11: 30.00
A12: 3 | B12: 14-New Buildings(105 units)-bldg 8 | C12: 4/01/23 | D12: 231207.03 | E12: 0 | F12: 0 | G12: 5459.05 | H12: 7706.92 | I12: =G12+H12 -> 13165.97 | J12: =D12-I12 -> 218041.06 | K12: S/L | L12: 30.00
A13: 4 | B13: 11-Building Imp)Post-Casulty Loss Basis)-bldg | C13: 9/02/20 | D13: 1616.48 | E13: 0 | F13: 0 | G13: 121.71 | H13: 55.97 | I13: =G13+H13 -> 177.68 | J13: =D13-I13 -> 1438.8 | K13: S/L | L13: 30.00
A14: 5 | B14: 2-Land Improvements-bldg 8 | C14: 8/15/18 | D14: 8795.97 | E14: 0 | F14: 2256.71 | G14: 2256.71 | H14: 676.47 | I14: =G14+H14 -> 2933.18 | J14: =D14-I14 -> 5862.79 | K14: 150DB | L14: 15.0
A15: 6 | B15: 13-New Equipment(16 units)-bldg 8 | C15: 12/20/22 | D15: 7572.23 | E15: 0 | F15: 0 | G15: 0 | H15: 0 | I15: =G15+H15 -> 0 | J15: =D15-I15 -> 7572.23 | K15: 200DB | L15: 5.0
A16: 7 | B16: 15-New Equipment(105 units)-bldg 8 | C16: 4/01/23 | D16: 50752.78 | E16: 0 | F16: 0 | G16: 2030.1 | H16: 3248.19 | I16: =G16+H16 -> 5278.29 | J16: =D16-I16 -> 45474.49 | K16: 200DB | L16: 5.0
B17: Grand Total | D17: =SUM(D10:D16) -> 398758.21 | E17: =SUM(E10:E16) -> 0 | F17: =SUM(F10:F16) -> 2256.71 | G17: =SUM(G10:G16) -> 17707.8 | H17: =SUM(H10:H16) -> 15179.55 | I17: =SUM(I10:I16) -> 32887.35 | J17: =SUM(J10:J16) -> 365870.86
A19: After Cost Segregation Correction
A20: Asset | B20: Property Description | C20: Date In Service | D20: Cost | E20: Sec 179 Exp | F20: Bonus Amt | G20: Tax Prior Depreciation | H20: Tax Current Depreciation | I20: End Depreciation | J20: Net Book Value | K20: Method | L20: Period
A21: 1 | B21: 10-Building-Post Casualty Loss Basis-bldg8-5y | C21: 8/15/18 | D21: 16882.61 | E21: 0 | F21: 16882.61 | G21: 16882.61 | H21: 0 | I21: =G21+H21 -> 16882.61 | J21: =D21-I21 -> 0 | K21: 200DB | L21: 5.0
A22: 2 | B22: 10-Building-Post Casualty Loss Basis-bldg8-30 | C22: 8/15/18 | D22: 47435.37 | E22: 0 | F22: 0 | G22: 8498.84 | H22: 1581.18 | I22: =G22+H22 -> 10080.02 | J22: =D22-I22 -> 37355.35 | K22: S/L | L22: 30.00
A23: 3 | B23: 12-New Buildings(16 units)-bldg8-5yr | C23: 12/20/22 | D23: 9054.67 | E23: 0 | F23: 9054.67 | G23: 9054.67 | H23: 0 | I23: =G23+H23 -> 9054.67 | J23: =D23-I23 -> 0 | K23: 200DB | L23: 5.0
A24: 4 | B24: 12-New Buildings(16 units)-bldg8-30yr | C24: 12/20/22 | D24: 25441.07 | E24: 0 | F24: 0 | G24: 883.37 | H24: 848.04 | I24: =G24+H24 -> 1731.41 | J24: =D24-I24 -> 23709.66 | K24: S/L | L24: 30.00
A25: 5 | B25: 14-New Buildings(105 units)-bldg8-5yr | C25: 4/01/23 | D25: 60688.77 | E25: 0 | F25: 48551.02 | G25: 50978.57 | H25: 3884.08 | I25: =G25+H25 -> 54862.65 | J25: =D25-I25 -> 5826.12 | K25: 200DB | L25: 5.0
A26: 6 | B26: 14-New Buildings(105 units)-bldg8-30yr | C26: 4/01/23 | D26: 170518.26 | E26: 0 | F26: 0 | G26: 4026.13 | H26: 5683.94 | I26: =G26+H26 -> 9710.07 | J26: =D26-I26 -> 160808.19 | K26: S/L | L26: 30.00
A27: 7 | B27: 11-Building Imp-Post-Casulty Loss Basis-bldg8 | C27: 9/02/20 | D27: 424.3 | E27: 0 | F27: 424.3 | G27: 424.3 | H27: 0 | I27: =G27+H27 -> 424.3 | J27: =D27-I27 -> 0 | K27: 200DB | L27: 5.0
A28: 8 | B28: 11-Building Imp-Post-Casulty Loss Basis-bldg8 | C28: 9/02/20 | D28: 1192.18 | E28: 0 | F28: 0 | G28: 130.81 | H28: 39.74 | I28: =G28+H28 -> 170.55 | J28: =D28-I28 -> 1021.63 | K28: S/L | L28: 30.00
A29: 9 | B29: 2-Land Improvements-bldg8-5yr | C29: 8/15/18 | D29: 2308.83 | E29: 0 | F29: 2308.83 | G29: 2308.83 | H29: 0 | I29: =G29+H29 -> 2308.83 | J29: =D29-I29 -> 0 | K29: 200DB | L29: 5.0
A30: 10 | B30: 2-Land Improvements-bldg8-30yr | C30: 8/15/18 | D30: 6487.14 | E30: 0 | F30: 0 | G30: 1162.29 | H30: 216.24 | I30: =G30+H30 -> 1378.53 | J30: =D30-I30 -> 5108.61 | K30: S/L | L30: 30.00
A31: 11 | B31: 13-New Equipment(16 units)-bldg8-5yr | C31: 12/20/22 | D31: 1987.61 | E31: 0 | F31: 1987.61 | G31: 1987.61 | H31: 0 | I31: =G31+H31 -> 1987.61 | J31: =D31-I31 -> 0 | K31: 200DB | L31: 5.0
A32: 12 | B32: 13-New Equipment(16 units)-bldg8-30yr | C32: 12/20/22 | D32: 5584.62 | E32: 0 | F32: 0 | G32: 193.91 | H32: 186.15 | I32: =G32+H32 -> 380.06 | J32: =D32-I32 -> 5204.56 | K32: S/L | L32: 30.00
... A34: 14 | B34: 15-New Equipment(105 units)-bldg8-30yr | C34: 4/01/23 | D34: 37430.84 | E34: 0 | F34: 0 | G34: 883.78 | H34: 1247.69 | I34: =G34+H34 -> 2131.47 | J34: =D34-I34 -> 35299.37 | K34: S/L | L34: 30.00
B35: Grand Total | D35: =SUM(D21:D34) -> 398758.21 | E35: =SUM(E21:E34) -> 0 | F35: =SUM(F21:F34) -> 89866.59 | G35: =SUM(G21:G34) -> 108606.15 | H35: =SUM(H21:H34) -> 14539.66 | I35: =SUM(I21:I34) -> 123145.81 | J35: =SUM(J21:J34) -> 275612.4
B37: Section 481(a) Adjustment — Regular Tax
B38: Depreciation reported previously | D38: =I17 -> 32887.35
B39: Cost Segregation Corrected Depreciation | D39: =I35 -> 123145.81
B40: Section 481(a) Adjustment — Regular Tax | D40: =D38-D39 -> -90258.46
A42: CALCULATION OF §481(a) ADJUSTMENT — AMT
A43: As Previously Filed — AMT
A44: Asset | B44: Property Description | C44: Date In Service | D44: Cost | E44: Sec 179 Exp | F44: Bonus Amt | G44: AMT Prior Depreciation | H44: AMT Current Depreciation | I44: End Depreciation | J44: Net Book Value | K44: Method | L44: Period
A45: 1 | B45: 10-Building(Post Casualty Loss Basis)-bldg 8 | C45: 8/15/18 | D45: 64317.98 | E45: 0 | F45: 0 | G45: 6642.44 | H45: 2342.15 | I45: =G45+H45 -> 8984.59 | J45: =D45-I45 -> 55333.39 | K45: S/L | L45: 30.00
A46: 2 | B46: 12-New Buildings(16 units)-bldg 8 | C46: 12/20/22 | D46: 34495.74 | E46: 0 | F46: 0 | G46: 1197.79 | H46: 1149.85 | I46: =G46+H46 -> 2347.64 | J46: =D46-I46 -> 32148.1 | K46: S/L | L46: 30.00
A47: 3 | B47: 14-New Buildings(105 units)-bldg 8 | C47: 4/01/23 | D47: 231207.03 | E47: 0 | F47: 0 | G47: 5459.05 | H47: 7706.92 | I47: =G47+H47 -> 13165.97 | J47: =D47-I47 -> 218041.06 | K47: S/L | L47: 30.00
A48: 4 | B48: 11-Building Imp)Post-Casulty Loss Basis)-bldg | C48: 9/02/20 | D48: 1616.48 | E48: 0 | F48: 0 | G48: 121.71 | H48: 55.97 | I48: =G48+H48 -> 177.68 | J48: =D48-I48 -> 1438.8 | K48: S/L | L48: 30.00
A49: 5 | B49: 2-Land Improvements-bldg 8 | C49: 8/15/18 | D49: 8795.97 | E49: 0 | F49: 2256.71 | G49: 2256.71 | H49: 676.47 | I49: =G49+H49 -> 2933.18 | J49: =D49-I49 -> 5862.79 | K49: 150DB | L49: 15.0
A50: 6 | B50: 13-New Equipment(16 units)-bldg 8 | C50: 12/20/22 | D50: 7572.23 | E50: 0 | F50: 0 | G50: 0 | H50: 0 | I50: =G50+H50 -> 0 | J50: =D50-I50 -> 7572.23 | K50: 200DB | L50: 5.0
A51: 7 | B51: 15-New Equipment(105 units)-bldg 8 | C51: 4/01/23 | D51: 50752.78 | E51: 0 | F51: 0 | G51: 2030.1 | H51: 3248.19 | I51: =G51+H51 -> 5278.29 | J51: =D51-I51 -> 45474.49 | K51: 200DB | L51: 5.0
B52: Grand Total | D52: =SUM(D45:D51) -> 398758.21 | E52: =SUM(E45:E51) -> 0 | F52: =SUM(F45:F51) -> 2256.71 | G52: =SUM(G45:G51) -> 17707.8 | H52: =SUM(H45:H51) -> 15179.55 | I52: =SUM(I45:I51) -> 32887.35 | J52: =SUM(J45:J51) -> 365870.86
A54: After Cost Segregation Correction — AMT
A55: Asset | B55: Property Description | C55: Date In Service | D55: Cost | E55: Sec 179 Exp | F55: Bonus Amt | G55: AMT Prior Depreciation | H55: AMT Current Depreciation | I55: End Depreciation | J55: Net Book Value | K55: Method | L55: Period
A56: 1 | B56: 12-New Buildings(16 units)-bldg8-5yr | C56: 12/20/22 | D56: 9054.67 | E56: 0 | F56: 9054.67 | G56: 9054.67 | H56: 0 | I56: =G56+H56 -> 9054.67 | J56: =D56-I56 -> 0 | K56: 200DB | L56: 5.0
A57: 2 | B57: 12-New Buildings(16 units)-bldg8-30yr | C57: 12/20/22 | D57: 25441.07 | E57: 0 | F57: 0 | G57: 883.37 | H57: 848.04 | I57: =G57+H57 -> 1731.41 | J57: =D57-I57 -> 23709.66 | K57: S/L | L57: 30.00
A58: 3 | B58: 14-New Buildings(105 units)-bldg8-5yr | C58: 4/01/23 | D58: 60688.77 | E58: 0 | F58: 48551.02 | G58: 50978.57 | H58: 3884.08 | I58: =G58+H58 -> 54862.65 | J58: =D58-I58 -> 5826.12 | K58: 200DB | L58: 5.0
A59: 4 | B59: 14-New Buildings(105 units)-bldg8-30yr | C59: 4/01/23 | D59: 170518.26 | E59: 0 | F59: 0 | G59: 4026.13 | H59: 5683.94 | I59: =G59+H59 -> 9710.07 | J59: =D59-I59 -> 160808.19 | K59: S/L | L59: 30.00
A60: 5 | B60: 2-Land Improvements-bldg8-5yr | C60: 8/15/18 | D60: 2308.83 | E60: 0 | F60: 2308.83 | G60: 2308.83 | H60: 0 | I60: =G60+H60 -> 2308.83 | J60: =D60-I60 -> 0 | K60: 200DB | L60: 5.0
A61: 6 | B61: 2-Land Improvements-bldg8-30yr | C61: 8/15/18 | D61: 6487.14 | E61: 0 | F61: 0 | G61: 1162.29 | H61: 216.24 | I61: =G61+H61 -> 1378.53 | J61: =D61-I61 -> 5108.61 | K61: S/L | L61: 30.00
A62: 7 | B62: 13-New Equipment(16 units)-bldg8-5yr | C62: 12/20/22 | D62: 1987.61 | E62: 0 | F62: 1987.61 | G62: 1987.61 | H62: 0 | I62: =G62+H62 -> 1987.61 | J62: =D62-I62 -> 0 | K62: 200DB | L62: 5.0
A63: 8 | B63: 13-New Equipment(16 units)-bldg8-30yr | C63: 12/20/22 | D63: 5584.62 | E63: 0 | F63: 0 | G63: 193.91 | H63: 186.15 | I63: =G63+H63 -> 380.06 | J63: =D63-I63 -> 5204.56 | K63: S/L | L63: 30.00
A64: 9 | B64: 15-New Equipment(105 units)-bldg8-5yr | C64: 4/01/23 | D64: 13321.94 | E64: 0 | F64: 10657.55 | G64: 11190.43 | H64: 852.6 | I64: =G64+H64 -> 12043.03 | J64: =D64-I64 -> 1278.91 | K64: 200DB | L64: 5.0
A65: 10 | B65: 15-New Equipment(105 units)-bldg8-30yr | C65: 4/01/23 | D65: 37430.84 | E65: 0 | F65: 0 | G65: 883.78 | H65: 1247.69 | I65: =G65+H65 -> 2131.47 | J65: =D65-I65 -> 35299.37 | K65: S/L | L65: 30.00
B66: Grand Total | D66: =SUM(D56:D65) -> 332823.75 | E66: =SUM(E56:E65) -> 0 | F66: =SUM(F56:F65) -> 72559.68 | G66: =SUM(G56:G65) -> 82669.59 | H66: =SUM(H56:H65) -> 12918.74 | I66: =SUM(I56:I65) -> 95588.33 | J66: =SUM(J56:J65) -> 237235.42
B68: Section 481(a) Adjustment — AMT
B69: Depreciation reported previously | D69: =I52 -> 32887.35
B70: Cost Segregation Corrected Depreciation | D70: =I66 -> 95588.33
B71: Section 481(a) Adjustment — AMT | D71: =D69-D70 -> -62700.98
A73: COST SEGREGATION STUDY — COST SUMMARY
B74: Total Building Cost | D74: =D111 -> 398758.21
B75: Building Components: 5 Year | D75: =F111 -> 104668.73
B76: % of Cost | D76: =F112 -> 0.26248671
B77: Building Structure: 30 Year | D77: =H111 -> 294089.48
B78: % of Cost | D78: =H112 -> 0.73751329
A80: COST SEGREGATION STUDY — COST DETAIL
B81: Property Category | D81: Cost | F81: 5 Year | H81: 30 Year
B82: Building Components
B83: Cabinets / Millwork | D83: =SUM(F83:H83) -> 31452.73 | F83: 31452.73
B84: Moldings | D84: =SUM(F84:H84) -> 8394.17 | F84: 8394.17
B85: Flooring - Vinyl Plank | D85: =SUM(F85:H85) -> 32815.9 | F85: 32815.9
B86: Window Treatments | D86: =SUM(F86:H86) -> 2648.72 | F86: 2648.72
B87: Building Signage | D87: =SUM(F87:H87) -> 394.4 | F87: 394.4
B88: Specialty Electrical - Appliances | D88: =SUM(F88:H88) -> 5344.3 | F88: 5344.3
B89: Communication / Data | D89: =SUM(F89:H89) -> 2858.97 | F89: 2858.97
B90: Specialty Plumbing - Kitchen Sinks | D90: =SUM(F90:H90) -> 9687.68 | F90: 9687.68
B91: Security / Exterior Lighting | D91: =SUM(F91:H91) -> 2139.23 | F91: 2139.23
B92: Canopies / Awnings | D92: =SUM(F92:H92) -> 605.69 | F92: 605.69
B93: Appliances | D93: =SUM(F93:H93) -> 8326.94 | F93: 8326.94
B94: Building Structure
B95: Roofing Systems | D95: =SUM(F95:H95) -> 16256.26 | H95: 16256.26
B96: Foundations | D96: =SUM(F96:H96) -> 21691.79 | H96: 21691.79
B97: HVAC | D97: =SUM(F97:H97) -> 31892.38 | H97: 31892.38
B98: Electrical | D98: =SUM(F98:H98) -> 29436.62 | H98: 29436.62
B99: Plumbing | D99: =SUM(F99:H99) -> 27723.88 | H99: 27723.88
B100: Fire Protection & Alarm | D100: =SUM(F100:H100) -> 1864.29 | H100: 1864.29
B101: Exterior Façade / Building Skin | D101: =SUM(F101:H101) -> 21222.77 | H101: 21222.77
B102: Doors & Frames | D102: =SUM(F102:H102) -> 16292.68 | H102: 16292.68
B103: Windows | D103: =SUM(F103:H103) -> 12258.17 | H103: 12258.17
B104: Ceiling Systems | D104: =SUM(F104:H104) -> 14614.91 | H104: 14614.91
B105: Interior Framing / Partitions | D105: =SUM(F105:H105) -> 38542.73 | H105: 38542.73
B106: Painting | D106: =SUM(F106:H106) -> 15289.77 | H106: 15289.77
... B110: Cabinets / Millwork - Restrooms | D110: =SUM(F110:H110) -> 1880.89 | H110: 1880.89
B111: Total Building Cost | D111: =SUM(D82:D110) -> 398758.21 | F111: =SUM(F82:F110) -> 104668.73 | H111: =SUM(H82:H110) -> 294089.48
B112: % of Cost | F112: =F111/D111 -> 0.26248671 | H112: =H111/D111 -> 0.73751329
...

Sheet Building 9
A1: St Charles Housing LP
A2: St. Charles — 1011 W 18th St, Lake Charles, LA 70607
A3: EIN: 82-5349206 · FYE: December 31, 2024 · Year of Change: 1/1/2024
A4: Building 9 — Attachment to Form 3115 (DCN #7, Rev. Proc. 2024-23 §6.01)
A5: Source: CSSI Report #107752-24, "St. Charles Housing LP_107752-24_3115_Combined.pdf"
A7: CALCULATION OF §481(a) ADJUSTMENT — REGULAR TAX
A8: As Previously Filed
A9: Asset | B9: Property Description | C9: Date In Service | D9: Cost | E9: Sec 179 Exp | F9: Bonus Amt | G9: Tax Prior Depreciation | H9: Tax Current Depreciation | I9: End Depreciation | J9: Net Book Value | K9: Method | L9: Period
A10: 1 | B10: 10-Building(Post Casualty Loss Basis)-bldg 9 | C10: 8/15/18 | D10: 28637.97 | E10: 0 | F10: 0 | G10: 2957.59 | H10: 1042.85 | I10: =G10+H10 -> 4000.44 | J10: =D10-I10 -> 24637.53 | K10: S/L | L10: 30.00
A11: 2 | B11: 12-New Buildings(16 units)-bldg 9 | C11: 12/20/22 | D11: 15359.44 | E11: 0 | F11: 0 | G11: 533.32 | H11: 511.98 | I11: =G11+H11 -> 1045.3 | J11: =D11-I11 -> 14314.14 | K11: S/L | L11: 30.00
A12: 3 | B12: 14-New Buildings(105 units)-bldg 9 | C12: 4/01/23 | D12: 102946.35 | E12: 0 | F12: 0 | G12: 2430.68 | H12: 3431.55 | I12: =G12+H12 -> 5862.23 | J12: =D12-I12 -> 97084.12 | K12: S/L | L12: 30.00
A13: 4 | B13: 11-Building Imp)Post-Casulty Loss Basis)-bldg | C13: 9/02/20 | D13: 719.75 | E13: 0 | F13: 0 | G13: 54.19 | H13: 24.92 | I13: =G13+H13 -> 79.11 | J13: =D13-I13 -> 640.64 | K13: S/L | L13: 30.00
A14: 5 | B14: 2-Land Improvements-bldg 9 | C14: 8/15/18 | D14: 3916.46 | E14: 0 | F14: 1004.82 | G14: 1004.82 | H14: 301.2 | I14: =G14+H14 -> 1306.02 | J14: =D14-I14 -> 2610.44 | K14: 150DB | L14: 15.0
A15: 6 | B15: 13-New Equipment(16 units)-bldg 9 | C15: 12/20/22 | D15: 3371.57 | E15: 0 | F15: 0 | G15: 0 | H15: 0 | I15: =G15+H15 -> 0 | J15: =D15-I15 -> 3371.57 | K15: 200DB | L15: 5.0
A16: 7 | B16: 15-New Equipment(105 units)-bldg 9 | C16: 4/01/23 | D16: 22597.99 | E16: 0 | F16: 0 | G16: 903.92 | H16: 1446.27 | I16: =G16+H16 -> 2350.19 | J16: =D16-I16 -> 20247.8 | K16: 200DB | L16: 5.0
B17: Grand Total | D17: =SUM(D10:D16) -> 177549.53 | E17: =SUM(E10:E16) -> 0 | F17: =SUM(F10:F16) -> 1004.82 | G17: =SUM(G10:G16) -> 7884.52 | H17: =SUM(H10:H16) -> 6758.77 | I17: =SUM(I10:I16) -> 14643.29 | J17: =SUM(J10:J16) -> 162906.24
A19: After Cost Segregation Correction
A20: Asset | B20: Property Description | C20: Date In Service | D20: Cost | E20: Sec 179 Exp | F20: Bonus Amt | G20: Tax Prior Depreciation | H20: Tax Current Depreciation | I20: End Depreciation | J20: Net Book Value | K20: Method | L20: Period
A21: 1 | B21: 10-Building-Post Casualty Loss Basis-bldg9-5 | C21: 8/15/18 | D21: 8201.31 | E21: 0 | F21: 8201.31 | G21: 8201.31 | H21: 0 | I21: =G21+H21 -> 8201.31 | J21: =D21-I21 -> 0 | K21: 200DB | L21: 5.0
A22: 2 | B22: 10-Building-Post Casualty Loss Basis-bldg9-30 | C22: 8/15/18 | D22: 20436.66 | E22: 0 | F22: 0 | G22: 3661.56 | H22: 681.22 | I22: =G22+H22 -> 4342.78 | J22: =D22-I22 -> 16093.88 | K22: S/L | L22: 30.00
A23: 3 | B23: 12-New Buildings(16 units)-bldg9-5yr | C23: 12/20/22 | D23: 4398.62 | E23: 0 | F23: 4398.62 | G23: 4398.62 | H23: 0 | I23: =G23+H23 -> 4398.62 | J23: =D23-I23 -> 0 | K23: 200DB | L23: 5.0
A24: 4 | B24: 12-New Buildings(16 units)-bldg9-30yr | C24: 12/20/22 | D24: 10960.82 | E24: 0 | F24: 0 | G24: 380.58 | H24: 365.36 | I24: =G24+H24 -> 745.94 | J24: =D24-I24 -> 10214.88 | K24: S/L | L24: 30.00
A25: 5 | B25: 14-New Buildings(105 units)-bldg9-5yr | C25: 4/01/23 | D25: 29481.65 | E25: 0 | F25: 23585.32 | G25: 24764.59 | H25: 1886.82 | I25: =G25+H25 -> 26651.41 | J25: =D25-I25 -> 2830.24 | K25: 200DB | L25: 5.0
A26: 6 | B26: 14-New Buildings(105 units)-bldg9-30yr | C26: 4/01/23 | D26: 73464.7 | E26: 0 | F26: 0 | G26: 1734.58 | H26: 2448.82 | I26: =G26+H26 -> 4183.4 | J26: =D26-I26 -> 69281.3 | K26: S/L | L26: 30.00
A27: 7 | B27: 11-Building Imp-Post-Casulty Loss Basis-bldg9 | C27: 9/02/20 | D27: 206.12 | E27: 0 | F27: 206.12 | G27: 206.12 | H27: 0 | I27: =G27+H27 -> 206.12 | J27: =D27-I27 -> 0 | K27: 200DB | L27: 5.0
A28: 8 | B28: 11-Building Imp-Post-Casulty Loss Basis-bldg9 | C28: 9/02/20 | D28: 513.63 | E28: 0 | F28: 0 | G28: 56.35 | H28: 17.12 | I28: =G28+H28 -> 73.47 | J28: =D28-I28 -> 440.16 | K28: S/L | L28: 30.00
A29: 9 | B29: 2-Land Improvements-bldg9-5yr | C29: 8/15/18 | D29: 1121.59 | E29: 0 | F29: 1121.59 | G29: 1121.59 | H29: 0 | I29: =G29+H29 -> 1121.59 | J29: =D29-I29 -> 0 | K29: 200DB | L29: 5.0
A30: 10 | B30: 2-Land Improvements-bldg9-30yr | C30: 8/15/18 | D30: 2794.87 | E30: 0 | F30: 0 | G30: 500.74 | H30: 93.16 | I30: =G30+H30 -> 593.9 | J30: =D30-I30 -> 2200.97 | K30: S/L | L30: 30.00
A31: 11 | B31: 13-New Equipment(16 units)-bldg9-5yr | C31: 12/20/22 | D31: 965.55 | E31: 0 | F31: 965.55 | G31: 965.55 | H31: 0 | I31: =G31+H31 -> 965.55 | J31: =D31-I31 -> 0 | K31: 200DB | L31: 5.0
A32: 12 | B32: 13-New Equipment(16 units)-bldg9-30yr | C32: 12/20/22 | D32: 2406.02 | E32: 0 | F32: 0 | G32: 83.54 | H32: 80.2 | I32: =G32+H32 -> 163.74 | J32: =D32-I32 -> 2242.28 | K32: S/L | L32: 30.00
... A34: 14 | B34: 15-New Equipment(105 units)-bldg9-30yr | C34: 4/01/23 | D34: 16126.42 | E34: 0 | F34: 0 | G34: 380.76 | H34: 537.55 | I34: =G34+H34 -> 918.31 | J34: =D34-I34 -> 15208.11 | K34: S/L | L34: 30.00
B35: Grand Total | D35: =SUM(D21:D34) -> 177549.53 | E35: =SUM(E21:E34) -> 0 | F35: =SUM(F21:F34) -> 43655.77 | G35: =SUM(G21:G34) -> 51892.01 | H35: =SUM(H21:H34) -> 6524.43 | I35: =SUM(I21:I34) -> 58416.44 | J35: =SUM(J21:J34) -> 119133.09
B37: Section 481(a) Adjustment — Regular Tax
B38: Depreciation reported previously | D38: =I17 -> 14643.29
B39: Cost Segregation Corrected Depreciation | D39: =I35 -> 58416.44
B40: Section 481(a) Adjustment — Regular Tax | D40: =D38-D39 -> -43773.15
A42: CALCULATION OF §481(a) ADJUSTMENT — AMT
A43: As Previously Filed — AMT
A44: Asset | B44: Property Description | C44: Date In Service | D44: Cost | E44: Sec 179 Exp | F44: Bonus Amt | G44: AMT Prior Depreciation | H44: AMT Current Depreciation | I44: End Depreciation | J44: Net Book Value | K44: Method | L44: Period
A45: 1 | B45: 10-Building(Post Casualty Loss Basis)-bldg 9 | C45: 8/15/18 | D45: 28637.97 | E45: 0 | F45: 0 | G45: 2957.59 | H45: 1042.85 | I45: =G45+H45 -> 4000.44 | J45: =D45-I45 -> 24637.53 | K45: S/L | L45: 30.00
A46: 2 | B46: 12-New Buildings(16 units)-bldg 9 | C46: 12/20/22 | D46: 15359.44 | E46: 0 | F46: 0 | G46: 533.32 | H46: 511.98 | I46: =G46+H46 -> 1045.3 | J46: =D46-I46 -> 14314.14 | K46: S/L | L46: 30.00
A47: 3 | B47: 14-New Buildings(105 units)-bldg 9 | C47: 4/01/23 | D47: 102946.35 | E47: 0 | F47: 0 | G47: 2430.68 | H47: 3431.55 | I47: =G47+H47 -> 5862.23 | J47: =D47-I47 -> 97084.12 | K47: S/L | L47: 30.00
A48: 4 | B48: 11-Building Imp)Post-Casulty Loss Basis)-bldg | C48: 9/02/20 | D48: 719.75 | E48: 0 | F48: 0 | G48: 54.19 | H48: 24.92 | I48: =G48+H48 -> 79.11 | J48: =D48-I48 -> 640.64 | K48: S/L | L48: 30.00
A49: 5 | B49: 2-Land Improvements-bldg 9 | C49: 8/15/18 | D49: 3916.46 | E49: 0 | F49: 1004.82 | G49: 1004.82 | H49: 301.2 | I49: =G49+H49 -> 1306.02 | J49: =D49-I49 -> 2610.44 | K49: 150DB | L49: 15.0
A50: 6 | B50: 13-New Equipment(16 units)-bldg 9 | C50: 12/20/22 | D50: 3371.57 | E50: 0 | F50: 0 | G50: 0 | H50: 0 | I50: =G50+H50 -> 0 | J50: =D50-I50 -> 3371.57 | K50: 200DB | L50: 5.0
A51: 7 | B51: 15-New Equipment(105 units)-bldg 9 | C51: 4/01/23 | D51: 22597.99 | E51: 0 | F51: 0 | G51: 903.92 | H51: 1446.27 | I51: =G51+H51 -> 2350.19 | J51: =D51-I51 -> 20247.8 | K51: 200DB | L51: 5.0
B52: Grand Total | D52: =SUM(D45:D51) -> 177549.53 | E52: =SUM(E45:E51) -> 0 | F52: =SUM(F45:F51) -> 1004.82 | G52: =SUM(G45:G51) -> 7884.52 | H52: =SUM(H45:H51) -> 6758.77 | I52: =SUM(I45:I51) -> 14643.29 | J52: =SUM(J45:J51) -> 162906.24
A54: After Cost Segregation Correction — AMT
A55: Asset | B55: Property Description | C55: Date In Service | D55: Cost | E55: Sec 179 Exp | F55: Bonus Amt | G55: AMT Prior Depreciation | H55: AMT Current Depreciation | I55: End Depreciation | J55: Net Book Value | K55: Method | L55: Period
A56: 1 | B56: 10-Building-Post Casualty Loss Basis-bldg9-5 | C56: 8/15/18 | D56: 8201.31 | E56: 0 | F56: 8201.31 | G56: 8201.31 | H56: 0 | I56: =G56+H56 -> 8201.31 | J56: =D56-I56 -> 0 | K56: 200DB | L56: 5.0
A57: 2 | B57: 12-New Buildings(16 units)-bldg9-5yr | C57: 12/20/22 | D57: 4398.62 | E57: 0 | F57: 4398.62 | G57: 4398.62 | H57: 0 | I57: =G57+H57 -> 4398.62 | J57: =D57-I57 -> 0 | K57: 200DB | L57: 5.0
A58: 3 | B58: 12-New Buildings(16 units)-bldg9-30yr | C58: 12/20/22 | D58: 10960.82 | E58: 0 | F58: 0 | G58: 380.58 | H58: 365.36 | I58: =G58+H58 -> 745.94 | J58: =D58-I58 -> 10214.88 | K58: S/L | L58: 30.00
A59: 4 | B59: 14-New Buildings(105 units)-bldg9-5yr | C59: 4/01/23 | D59: 29481.65 | E59: 0 | F59: 23585.32 | G59: 24764.59 | H59: 1886.82 | I59: =G59+H59 -> 26651.41 | J59: =D59-I59 -> 2830.24 | K59: 200DB | L59: 5.0
A60: 5 | B60: 14-New Buildings(105 units)-bldg9-30yr | C60: 4/01/23 | D60: 73464.7 | E60: 0 | F60: 0 | G60: 1734.58 | H60: 2448.82 | I60: =G60+H60 -> 4183.4 | J60: =D60-I60 -> 69281.3 | K60: S/L | L60: 30.00
A61: 6 | B61: 2-Land Improvements-bldg9-5yr | C61: 8/15/18 | D61: 1121.59 | E61: 0 | F61: 1121.59 | G61: 1121.59 | H61: 0 | I61: =G61+H61 -> 1121.59 | J61: =D61-I61 -> 0 | K61: 200DB | L61: 5.0
A62: 7 | B62: 2-Land Improvements-bldg9-30yr | C62: 8/15/18 | D62: 2794.87 | E62: 0 | F62: 0 | G62: 500.74 | H62: 93.16 | I62: =G62+H62 -> 593.9 | J62: =D62-I62 -> 2200.97 | K62: S/L | L62: 30.00
A63: 8 | B63: 13-New Equipment(16 units)-bldg9-5yr | C63: 12/20/22 | D63: 965.55 | E63: 0 | F63: 965.55 | G63: 965.55 | H63: 0 | I63: =G63+H63 -> 965.55 | J63: =D63-I63 -> 0 | K63: 200DB | L63: 5.0
A64: 9 | B64: 13-New Equipment(16 units)-bldg9-30yr | C64: 12/20/22 | D64: 2406.02 | E64: 0 | F64: 0 | G64: 83.54 | H64: 80.2 | I64: =G64+H64 -> 163.74 | J64: =D64-I64 -> 2242.28 | K64: S/L | L64: 30.00
A65: 10 | B65: 15-New Equipment(105 units)-bldg9-5yr | C65: 4/01/23 | D65: 6471.57 | E65: 0 | F65: 5177.26 | G65: 5436.12 | H65: 414.18 | I65: =G65+H65 -> 5850.3 | J65: =D65-I65 -> 621.27 | K65: 200DB | L65: 5.0
A66: 11 | B66: 15-New Equipment(105 units)-bldg9-30yr | C66: 4/01/23 | D66: 16126.42 | E66: 0 | F66: 0 | G66: 380.76 | H66: 537.55 | I66: =G66+H66 -> 918.31 | J66: =D66-I66 -> 15208.11 | K66: S/L | L66: 30.00
B67: Grand Total | D67: =SUM(D56:D66) -> 156393.12 | E67: =SUM(E56:E66) -> 0 | F67: =SUM(F56:F66) -> 43449.65 | G67: =SUM(G56:G66) -> 47967.98 | H67: =SUM(H56:H66) -> 5826.09 | I67: =SUM(I56:I66) -> 53794.07 | J67: =SUM(J56:J66) -> 102599.05
B69: Section 481(a) Adjustment — AMT
B70: Depreciation reported previously | D70: =I52 -> 14643.29
B71: Cost Segregation Corrected Depreciation | D71: =I67 -> 53794.07
B72: Section 481(a) Adjustment — AMT | D72: =D70-D71 -> -39150.78
A74: COST SEGREGATION STUDY — COST SUMMARY
B75: Total Building Cost | D75: =D114 -> 177549.53
B76: Building Components: 5 Year | D76: =F114 -> 50846.41
B77: % of Cost | D77: =F115 -> 0.28637874
B78: Building Structure: 30 Year | D78: =H114 -> 126703.12
B79: % of Cost | D79: =H115 -> 0.71362126
A81: COST SEGREGATION STUDY — COST DETAIL
B82: Property Category | D82: Cost | F82: 5 Year | H82: 30 Year
B83: Building Components
B84: Cabinets / Millwork | D84: =SUM(F84:H84) -> 3931.6 | F84: 3931.6
B85: Moldings | D85: =SUM(F85:H85) -> 3025.61 | F85: 3025.61
B86: Flooring - Vinyl Tile | D86: =SUM(F86:H86) -> 2941.12 | F86: 2941.12
B87: Flooring - Vinyl Plank | D87: =SUM(F87:H87) -> 3937.09 | F87: 3937.09
B88: Window Treatments | D88: =SUM(F88:H88) -> 496.64 | F88: 496.64
B89: Specialty HVAC - Dryer Vents | D89: =SUM(F89:H89) -> 833.73 | F89: 833.73
B90: Building Signage | D90: =SUM(F90:H90) -> 71.8 | F90: 71.8
B91: Specialty Electrical - Appliances | D91: =SUM(F91:H91) -> 5223.52 | F91: 5223.52
B92: Communication / Data | D92: =SUM(F92:H92) -> 1051.12 | F92: 1051.12
B93: Specialty Plumbing - Kitchen Sink / Laundry | D93: =SUM(F93:H93) -> 4691.93 | F93: 4691.93
B94: Security / Exterior Lighting | D94: =SUM(F94:H94) -> 316.82 | F94: 316.82
B95: Mailboxes | D95: =SUM(F95:H95) -> 11202.14 | F95: 11202.14
B96: Appliances | D96: =SUM(F96:H96) -> 13123.29 | F96: 13123.29
B97: Building Structure
B98: Roofing Systems | D98: =SUM(F98:H98) -> 12188.65 | H98: 12188.65
B99: Foundations | D99: =SUM(F99:H99) -> 16410.11 | H99: 16410.11
B100: HVAC | D100: =SUM(F100:H100) -> 11725.43 | H100: 11725.43
B101: Electrical | D101: =SUM(F101:H101) -> 12787.42 | H101: 12787.42
B102: Plumbing | D102: =SUM(F102:H102) -> 10192.86 | H102: 10192.86
B103: Fire Protection & Alarm | D103: =SUM(F103:H103) -> 233.04 | H103: 233.04
B104: Exterior Façade / Building Skin | D104: =SUM(F104:H104) -> 21043.31 | H104: 21043.31
B105: Doors & Frames | D105: =SUM(F105:H105) -> 2797.83 | H105: 2797.83
B106: Windows | D106: =SUM(F106:H106) -> 2188.95 | H106: 2188.95
B107: Ceiling Systems | D107: =SUM(F107:H107) -> 5373.26 | H107: 5373.26
B108: Interior Framing / Partitions | D108: =SUM(F108:H108) -> 13233.31 | H108: 13233.31
B109: Painting | D109: =SUM(F109:H109) -> 5712.33 | H109: 5712.33
...

Sheet Building 10
A1: St Charles Housing LP
A2: St. Charles — 1011 W 18th St, Lake Charles, LA 70607
A3: EIN: 82-5349206 · FYE: December 31, 2024 · Year of Change: 1/1/2024
A4: Building 10 — Attachment to Form 3115 (DCN #7, Rev. Proc. 2024-23 §6.01)
A5: Source: CSSI Report #107752-24, "St. Charles Housing LP_107752-24_3115_Combined.pdf"
A7: CALCULATION OF §481(a) ADJUSTMENT — REGULAR TAX
A8: As Previously Filed
A9: Asset | B9: Property Description | C9: Date In Service | D9: Cost | E9: Sec 179 Exp | F9: Bonus Amt | G9: Tax Prior Depreciation | H9: Tax Current Depreciation | I9: End Depreciation | J9: Net Book Value | K9: Method | L9: Period
A10: 1 | B10: 10-Building(Post Casualty Loss Basis)-bldg 10 | C10: 8/15/18 | D10: 72282.57 | E10: 0 | F10: 0 | G10: 7464.98 | H10: 2632.18 | I10: =G10+H10 -> 10097.16 | J10: =D10-I10 -> 62185.41 | K10: S/L | L10: 30.00
A11: 2 | B11: 12-New Buildings(16 units)-bldg 10 | C11: 12/20/22 | D11: 38767.41 | E11: 0 | F11: 0 | G11: 1346.12 | H11: 1292.24 | I11: =G11+H11 -> 2638.36 | J11: =D11-I11 -> 36129.05 | K11: S/L | L11: 30.00
A12: 3 | B12: 14-New Buildings(105 units)-bldg 10 | C12: 4/01/23 | D12: 259837.74 | E12: 0 | F12: 0 | G12: 6135.05 | H12: 8661.27 | I12: =G12+H12 -> 14796.32 | J12: =D12-I12 -> 245041.42 | K12: S/L | L12: 30.00
A13: 4 | B13: 11-Building Imp)Post-Casulty Loss Basis)-bldg | C13: 9/02/20 | D13: 1816.65 | E13: 0 | F13: 0 | G13: 136.79 | H13: 62.89 | I13: =G13+H13 -> 199.68 | J13: =D13-I13 -> 1616.97 | K13: S/L | L13: 30.00
A14: 5 | B14: 2-Land Improvements-bldg 10 | C14: 8/15/18 | D14: 9885.18 | E14: 0 | F14: 2536.17 | G14: 2536.17 | H14: 760.23 | I14: =G14+H14 -> 3296.4 | J14: =D14-I14 -> 6588.78 | K14: 150DB | L14: 15.0
A15: 6 | B15: 13-New Equipment(16 units)-bldg 10 | C15: 12/20/22 | D15: 8509.91 | E15: 0 | F15: 0 | G15: 0 | H15: 0 | I15: =G15+H15 -> 0 | J15: =D15-I15 -> 8509.91 | K15: 200DB | L15: 5.0
A16: 7 | B16: 15-New Equipment(105 units)-bldg 10 | C16: 4/01/23 | D16: 57037.57 | E16: 0 | F16: 0 | G16: 2281.5 | H16: 3650.41 | I16: =G16+H16 -> 5931.91 | J16: =D16-I16 -> 51105.66 | K16: 200DB | L16: 5.0
B17: Grand Total | D17: =SUM(D10:D16) -> 448137.03 | E17: =SUM(E10:E16) -> 0 | F17: =SUM(F10:F16) -> 2536.17 | G17: =SUM(G10:G16) -> 19900.61 | H17: =SUM(H10:H16) -> 17059.22 | I17: =SUM(I10:I16) -> 36959.83 | J17: =SUM(J10:J16) -> 411177.2
A19: After Cost Segregation Correction
A20: Asset | B20: Property Description | C20: Date In Service | D20: Cost | E20: Sec 179 Exp | F20: Bonus Amt | G20: Tax Prior Depreciation | H20: Tax Current Depreciation | I20: End Depreciation | J20: Net Book Value | K20: Method | L20: Period
A21: 1 | B21: 10-Building-Post Casualty Loss Basis-bldg10- | C21: 8/15/18 | D21: 18042.22 | E21: 0 | F21: 18042.22 | G21: 18042.22 | H21: 0 | I21: =G21+H21 -> 18042.22 | J21: =D21-I21 -> 0 | K21: 200DB | L21: 5.0
A22: 2 | B22: 10-Building-Post Casualty Loss Basis-bldg10-3 | C22: 8/15/18 | D22: 54240.35 | E22: 0 | F22: 0 | G22: 9718.05 | H22: 1808.01 | I22: =G22+H22 -> 11526.06 | J22: =D22-I22 -> 42714.29 | K22: S/L | L22: 30.00
A23: 3 | B23: 12-New Buildings(16 units)-bldg10-5yr | C23: 12/20/22 | D23: 9676.61 | E23: 0 | F23: 9676.61 | G23: 9676.61 | H23: 0 | I23: =G23+H23 -> 9676.61 | J23: =D23-I23 -> 0 | K23: 200DB | L23: 5.0
A24: 4 | B24: 12-New Buildings(16 units)-bldg10-30yr | C24: 12/20/22 | D24: 29090.8 | E24: 0 | F24: 0 | G24: 1010.09 | H24: 969.69 | I24: =G24+H24 -> 1979.78 | J24: =D24-I24 -> 27111.02 | K24: S/L | L24: 30.00
A25: 5 | B25: 14-New Buildings(105 units)-bldg10-5yr | C25: 4/01/23 | D25: 64857.26 | E25: 0 | F25: 51885.81 | G25: 54480.1 | H25: 4150.86 | I25: =G25+H25 -> 58630.96 | J25: =D25-I25 -> 6226.3 | K25: 200DB | L25: 5.0
A26: 6 | B26: 14-New Buildings(105 units)-bldg10-30yr | C26: 4/01/23 | D26: 194980.48 | E26: 0 | F26: 0 | G26: 4603.71 | H26: 6499.35 | I26: =G26+H26 -> 11103.06 | J26: =D26-I26 -> 183877.42 | K26: S/L | L26: 30.00
A27: 7 | B27: 11-Building Imp-Post-Casulty Loss Basis-bld10 | C27: 9/02/20 | D27: 453.45 | E27: 0 | F27: 453.45 | G27: 453.45 | H27: 0 | I27: =G27+H27 -> 453.45 | J27: =D27-I27 -> 0 | K27: 200DB | L27: 5.0
A28: 8 | B28: 11-Building Imp-Post-Casulty Loss Basis-bld10 | C28: 9/02/20 | D28: 1363.2 | E28: 0 | F28: 0 | G28: 149.57 | H28: 45.44 | I28: =G28+H28 -> 195.01 | J28: =D28-I28 -> 1168.19 | K28: S/L | L28: 30.00
A29: 9 | B29: 2-Land Improvements-bldg10-5yr | C29: 8/15/18 | D29: 2467.41 | E29: 0 | F29: 2467.41 | G29: 2467.41 | H29: 0 | I29: =G29+H29 -> 2467.41 | J29: =D29-I29 -> 0 | K29: 200DB | L29: 5.0
A30: 10 | B30: 2-Land Improvements-bldg10-30yr | C30: 8/15/18 | D30: 7417.77 | E30: 0 | F30: 0 | G30: 1329.02 | H30: 247.26 | I30: =G30+H30 -> 1576.28 | J30: =D30-I30 -> 5841.49 | K30: S/L | L30: 30.00
A31: 11 | B31: 13-New Equipment(16 units)-bldg10-5yr | C31: 12/20/22 | D31: 2124.13 | E31: 0 | F31: 2124.13 | G31: 2124.13 | H31: 0 | I31: =G31+H31 -> 2124.13 | J31: =D31-I31 -> 0 | K31: 200DB | L31: 5.0
A32: 12 | B32: 13-New Equipment(16 units)-bldg10-30yr | C32: 12/20/22 | D32: 6385.78 | E32: 0 | F32: 0 | G32: 221.73 | H32: 212.86 | I32: =G32+H32 -> 434.59 | J32: =D32-I32 -> 5951.19 | K32: S/L | L32: 30.00
... A34: 14 | B34: 15-New Equipment(105 units)-bldg10-30yr | C34: 4/01/23 | D34: 42800.62 | E34: 0 | F34: 0 | G34: 1010.57 | H34: 1426.69 | I34: =G34+H34 -> 2437.26 | J34: =D34-I34 -> 40363.36 | K34: S/L | L34: 30.00
B35: Grand Total | D35: =SUM(D21:D34) -> 448137.03 | E35: =SUM(E21:E34) -> 0 | F35: =SUM(F21:F34) -> 96039.19 | G35: =SUM(G21:G34) -> 117245.7 | H35: =SUM(H21:H34) -> 16271.32 | I35: =SUM(I21:I34) -> 133517.02 | J35: =SUM(J21:J34) -> 314620.01
B37: Section 481(a) Adjustment — Regular Tax
B38: Depreciation reported previously | D38: =I17 -> 36959.83
B39: Cost Segregation Corrected Depreciation | D39: =I35 -> 133517.02
B40: Section 481(a) Adjustment — Regular Tax | D40: =D38-D39 -> -96557.19
A42: CALCULATION OF §481(a) ADJUSTMENT — AMT
A43: As Previously Filed — AMT
A44: Asset | B44: Property Description | C44: Date In Service | D44: Cost | E44: Sec 179 Exp | F44: Bonus Amt | G44: AMT Prior Depreciation | H44: AMT Current Depreciation | I44: End Depreciation | J44: Net Book Value | K44: Method | L44: Period
A45: 1 | B45: 10-Building(Post Casualty Loss Basis)-bldg 10 | C45: 8/15/18 | D45: 72282.57 | E45: 0 | F45: 0 | G45: 7464.98 | H45: 2632.18 | I45: =G45+H45 -> 10097.16 | J45: =D45-I45 -> 62185.41 | K45: S/L | L45: 30.00
A46: 2 | B46: 12-New Buildings(16 units)-bldg 10 | C46: 12/20/22 | D46: 38767.41 | E46: 0 | F46: 0 | G46: 1346.12 | H46: 1292.24 | I46: =G46+H46 -> 2638.36 | J46: =D46-I46 -> 36129.05 | K46: S/L | L46: 30.00
A47: 3 | B47: 14-New Buildings(105 units)-bldg 10 | C47: 4/01/23 | D47: 259837.74 | E47: 0 | F47: 0 | G47: 6135.05 | H47: 8661.27 | I47: =G47+H47 -> 14796.32 | J47: =D47-I47 -> 245041.42 | K47: S/L | L47: 30.00
A48: 4 | B48: 11-Building Imp)Post-Casulty Loss Basis)-bldg | C48: 9/02/20 | D48: 1816.65 | E48: 0 | F48: 0 | G48: 136.79 | H48: 62.89 | I48: =G48+H48 -> 199.68 | J48: =D48-I48 -> 1616.97 | K48: S/L | L48: 30.00
A49: 5 | B49: 2-Land Improvements-bldg 10 | C49: 8/15/18 | D49: 9885.18 | E49: 0 | F49: 2536.17 | G49: 2536.17 | H49: 760.23 | I49: =G49+H49 -> 3296.4 | J49: =D49-I49 -> 6588.78 | K49: 150DB | L49: 15.0
A50: 6 | B50: 13-New Equipment(16 units)-bldg 10 | C50: 12/20/22 | D50: 8509.91 | E50: 0 | F50: 0 | G50: 0 | H50: 0 | I50: =G50+H50 -> 0 | J50: =D50-I50 -> 8509.91 | K50: 200DB | L50: 5.0
A51: 7 | B51: 15-New Equipment(105 units)-bldg 10 | C51: 4/01/23 | D51: 57037.57 | E51: 0 | F51: 0 | G51: 2281.5 | H51: 3650.41 | I51: =G51+H51 -> 5931.91 | J51: =D51-I51 -> 51105.66 | K51: 200DB | L51: 5.0
B52: Grand Total | D52: =SUM(D45:D51) -> 448137.03 | E52: =SUM(E45:E51) -> 0 | F52: =SUM(F45:F51) -> 2536.17 | G52: =SUM(G45:G51) -> 19900.61 | H52: =SUM(H45:H51) -> 17059.22 | I52: =SUM(I45:I51) -> 36959.83 | J52: =SUM(J45:J51) -> 411177.2
A54: After Cost Segregation Correction — AMT
A55: Asset | B55: Property Description | C55: Date In Service | D55: Cost | E55: Sec 179 Exp | F55: Bonus Amt | G55: AMT Prior Depreciation | H55: AMT Current Depreciation | I55: End Depreciation | J55: Net Book Value | K55: Method | L55: Period
A56: 1 | B56: 10-Building-Post Casualty Loss Basis-bldg10- | C56: 8/15/18 | D56: 18042.22 | E56: 0 | F56: 18042.22 | G56: 18042.22 | H56: 0 | I56: =G56+H56 -> 18042.22 | J56: =D56-I56 -> 0 | K56: 200DB | L56: 5.0
A57: 2 | B57: 12-New Buildings(16 units)-bldg10-5yr | C57: 12/20/22 | D57: 9676.61 | E57: 0 | F57: 9676.61 | G57: 9676.61 | H57: 0 | I57: =G57+H57 -> 9676.61 | J57: =D57-I57 -> 0 | K57: 200DB | L57: 5.0
A58: 3 | B58: 12-New Buildings(16 units)-bldg10-30yr | C58: 12/20/22 | D58: 29090.8 | E58: 0 | F58: 0 | G58: 1010.09 | H58: 969.69 | I58: =G58+H58 -> 1979.78 | J58: =D58-I58 -> 27111.02 | K58: S/L | L58: 30.00
A59: 4 | B59: 14-New Buildings(105 units)-bldg10-5yr | C59: 4/01/23 | D59: 64857.26 | E59: 0 | F59: 51885.81 | G59: 54480.1 | H59: 4150.86 | I59: =G59+H59 -> 58630.96 | J59: =D59-I59 -> 6226.3 | K59: 200DB | L59: 5.0
A60: 5 | B60: 14-New Buildings(105 units)-bldg10-30yr | C60: 4/01/23 | D60: 194980.48 | E60: 0 | F60: 0 | G60: 4603.71 | H60: 6499.35 | I60: =G60+H60 -> 11103.06 | J60: =D60-I60 -> 183877.42 | K60: S/L | L60: 30.00
A61: 6 | B61: 2-Land Improvements-bldg10-5yr | C61: 8/15/18 | D61: 2467.41 | E61: 0 | F61: 2467.41 | G61: 2467.41 | H61: 0 | I61: =G61+H61 -> 2467.41 | J61: =D61-I61 -> 0 | K61: 200DB | L61: 5.0
A62: 7 | B62: 2-Land Improvements-bldg10-30yr | C62: 8/15/18 | D62: 7417.77 | E62: 0 | F62: 0 | G62: 1329.02 | H62: 247.26 | I62: =G62+H62 -> 1576.28 | J62: =D62-I62 -> 5841.49 | K62: S/L | L62: 30.00
A63: 8 | B63: 13-New Equipment(16 units)-bldg10-5yr | C63: 12/20/22 | D63: 2124.13 | E63: 0 | F63: 2124.13 | G63: 2124.13 | H63: 0 | I63: =G63+H63 -> 2124.13 | J63: =D63-I63 -> 0 | K63: 200DB | L63: 5.0
A64: 9 | B64: 13-New Equipment(16 units)-bldg10-30yr | C64: 12/20/22 | D64: 6385.78 | E64: 0 | F64: 0 | G64: 221.73 | H64: 212.86 | I64: =G64+H64 -> 434.59 | J64: =D64-I64 -> 5951.19 | K64: S/L | L64: 30.00
A65: 10 | B65: 15-New Equipment(105 units)-bldg10-5yr | C65: 4/01/23 | D65: 14236.95 | E65: 0 | F65: 11389.56 | G65: 11959.04 | H65: 911.16 | I65: =G65+H65 -> 12870.2 | J65: =D65-I65 -> 1366.75 | K65: 200DB | L65: 5.0
A66: 11 | B66: 15-New Equipment(105 units)-bldg10-30yr | C66: 4/01/23 | D66: 42800.62 | E66: 0 | F66: 0 | G66: 1010.57 | H66: 1426.69 | I66: =G66+H66 -> 2437.26 | J66: =D66-I66 -> 40363.36 | K66: S/L | L66: 30.00
B67: Grand Total | D67: =SUM(D56:D66) -> 392080.03 | E67: =SUM(E56:E66) -> 0 | F67: =SUM(F56:F66) -> 95585.74 | G67: =SUM(G56:G66) -> 106924.63 | H67: =SUM(H56:H66) -> 14417.87 | I67: =SUM(I56:I66) -> 121342.5 | J67: =SUM(J56:J66) -> 270737.53
B69: Section 481(a) Adjustment — AMT
B70: Depreciation reported previously | D70: =I52 -> 36959.83
B71: Cost Segregation Corrected Depreciation | D71: =I67 -> 121342.5
B72: Section 481(a) Adjustment — AMT | D72: =D70-D71 -> -84382.67
A74: COST SEGREGATION STUDY — COST SUMMARY
B75: Total Building Cost | D75: =D112 -> 448137.03
B76: Building Components: 5 Year | D76: =F112 -> 111858.03
B77: % of Cost | D77: =F113 -> 0.24960676
B78: Building Structure: 30 Year | D78: =H112 -> 336279
B79: % of Cost | D79: =H113 -> 0.75039324
A81: COST SEGREGATION STUDY — COST DETAIL
B82: Property Category | D82: Cost | F82: 5 Year | H82: 30 Year
B83: Building Components
B84: Cabinets / Millwork | D84: =SUM(F84:H84) -> 31452.73 | F84: 31452.73
B85: Moldings | D85: =SUM(F85:H85) -> 8975.5 | F85: 8975.5
B86: Flooring - Vinyl Plank | D86: =SUM(F86:H86) -> 38285.2 | F86: 38285.2
B87: Window Treatments | D87: =SUM(F87:H87) -> 3310.89 | F87: 3310.89
B88: Building Signage | D88: =SUM(F88:H88) -> 394.4 | F88: 394.4
B89: Specialty Electrical - Appliances | D89: =SUM(F89:H89) -> 5344.3 | F89: 5344.3
B90: Communication / Data | D90: =SUM(F90:H90) -> 3335.47 | F90: 3335.47
B91: Specialty Plumbing - Kitchen Sinks | D91: =SUM(F91:H91) -> 9687.68 | F91: 9687.68
B92: Security / Exterior Lighting | D92: =SUM(F92:H92) -> 2139.23 | F92: 2139.23
B93: Canopies / Awnings | D93: =SUM(F93:H93) -> 605.69 | F93: 605.69
B94: Appliances | D94: =SUM(F94:H94) -> 8326.94 | F94: 8326.94
B95: Building Structure
B96: Roofing Systems | D96: =SUM(F96:H96) -> 18787.87 | H96: 18787.87
B97: Foundations | D97: =SUM(F97:H97) -> 25094.55 | H97: 25094.55
B98: HVAC | D98: =SUM(F98:H98) -> 37207.78 | H98: 37207.78
B99: Electrical | D99: =SUM(F99:H99) -> 35233.43 | H99: 35233.43
B100: Plumbing | D100: =SUM(F100:H100) -> 32344.52 | H100: 32344.52
B101: Fire Protection & Alarm | D101: =SUM(F101:H101) -> 2485.72 | H101: 2485.72
B102: Exterior Façade / Building Skin | D102: =SUM(F102:H102) -> 24546.88 | H102: 24546.88
B103: Doors & Frames | D103: =SUM(F103:H103) -> 18966.92 | H103: 18966.92
B104: Windows | D104: =SUM(F104:H104) -> 15176.79 | H104: 15176.79
B105: Ceiling Systems | D105: =SUM(F105:H105) -> 17050.73 | H105: 17050.73
B106: Interior Framing / Partitions | D106: =SUM(F106:H106) -> 40897.65 | H106: 40897.65
B107: Painting | D107: =SUM(F107:H107) -> 16588.72 | H107: 16588.72
... B111: Cabinets / Millwork - Restrooms | D111: =SUM(F111:H111) -> 1880.89 | H111: 1880.89
B112: Total Building Cost | D112: =SUM(D83:D111) -> 448137.03 | F112: =SUM(F83:F111) -> 111858.03 | H112: =SUM(H83:H111) -> 336279
...

Sheet Building 11
A1: St Charles Housing LP
A2: St. Charles — 1011 W 18th St, Lake Charles, LA 70607
A3: EIN: 82-5349206 · FYE: December 31, 2024 · Year of Change: 1/1/2024
A4: Building 11 — Attachment to Form 3115 (DCN #7, Rev. Proc. 2024-23 §6.01)
A5: Source: CSSI Report #107752-24, "St. Charles Housing LP_107752-24_3115_Combined.pdf"
A7: CALCULATION OF §481(a) ADJUSTMENT — REGULAR TAX
A8: As Previously Filed
A9: Asset | B9: Property Description | C9: Date In Service | D9: Cost | E9: Sec 179 Exp | F9: Bonus Amt | G9: Tax Prior Depreciation | H9: Tax Current Depreciation | I9: End Depreciation | J9: Net Book Value | K9: Method | L9: Period
A10: 1 | B10: 10-Building(Post Casualty Loss Basis)-bldg 11 | C10: 8/15/18 | D10: 64317.98 | E10: 0 | F10: 0 | G10: 6642.44 | H10: 2342.15 | I10: =G10+H10 -> 8984.59 | J10: =D10-I10 -> 55333.39 | K10: S/L | L10: 30.00
A11: 2 | B11: 12-New Buildings(16 units)-bldg 11 | C11: 12/20/22 | D11: 34495.74 | E11: 0 | F11: 0 | G11: 1197.79 | H11: 1149.85 | I11: =G11+H11 -> 2347.64 | J11: =D11-I11 -> 32148.1 | K11: S/L | L11: 30.00
A12: 3 | B12: 14-New Buildings(105 units)-bldg 11 | C12: 4/01/23 | D12: 231207.03 | E12: 0 | F12: 0 | G12: 5459.05 | H12: 7706.92 | I12: =G12+H12 -> 13165.97 | J12: =D12-I12 -> 218041.06 | K12: S/L | L12: 30.00
A13: 4 | B13: 11-Building Imp)Post-Casulty Loss Basis)-bldg | C13: 9/02/20 | D13: 1616.48 | E13: 0 | F13: 0 | G13: 121.71 | H13: 55.97 | I13: =G13+H13 -> 177.68 | J13: =D13-I13 -> 1438.8 | K13: S/L | L13: 30.00
A14: 5 | B14: 2-Land Improvements-bldg 11 | C14: 8/15/18 | D14: 8795.97 | E14: 0 | F14: 2256.71 | G14: 2256.71 | H14: 676.47 | I14: =G14+H14 -> 2933.18 | J14: =D14-I14 -> 5862.79 | K14: 150DB | L14: 15.0
A15: 6 | B15: 13-New Equipment(16 units)-bldg 11 | C15: 12/20/22 | D15: 7572.23 | E15: 0 | F15: 0 | G15: 0 | H15: 0 | I15: =G15+H15 -> 0 | J15: =D15-I15 -> 7572.23 | K15: 200DB | L15: 5.0
A16: 7 | B16: 15-New Equipment(105 units)-bldg 11 | C16: 4/01/23 | D16: 50752.78 | E16: 0 | F16: 0 | G16: 2030.1 | H16: 3248.19 | I16: =G16+H16 -> 5278.29 | J16: =D16-I16 -> 45474.49 | K16: 200DB | L16: 5.0
B17: Grand Total | D17: =SUM(D10:D16) -> 398758.21 | E17: =SUM(E10:E16) -> 0 | F17: =SUM(F10:F16) -> 2256.71 | G17: =SUM(G10:G16) -> 17707.8 | H17: =SUM(H10:H16) -> 15179.55 | I17: =SUM(I10:I16) -> 32887.35 | J17: =SUM(J10:J16) -> 365870.86
A19: After Cost Segregation Correction
A20: Asset | B20: Property Description | C20: Date In Service | D20: Cost | E20: Sec 179 Exp | F20: Bonus Amt | G20: Tax Prior Depreciation | H20: Tax Current Depreciation | I20: End Depreciation | J20: Net Book Value | K20: Method | L20: Period
A21: 1 | B21: 10-Building-Post Casualty Loss Basis-bldg11-5 | C21: 8/15/18 | D21: 16882.61 | E21: 0 | F21: 16882.61 | G21: 16882.61 | H21: 0 | I21: =G21+H21 -> 16882.61 | J21: =D21-I21 -> 0 | K21: 200DB | L21: 5.0
A22: 2 | B22: 10-Building-Post Casualty Loss Basis-bldg11- | C22: 8/15/18 | D22: 47435.37 | E22: 0 | F22: 0 | G22: 8498.84 | H22: 1581.18 | I22: =G22+H22 -> 10080.02 | J22: =D22-I22 -> 37355.35 | K22: S/L | L22: 30.00
A23: 3 | B23: 12-New Buildings(16 units)-bldg11-5yr | C23: 12/20/22 | D23: 9054.67 | E23: 0 | F23: 9054.67 | G23: 9054.67 | H23: 0 | I23: =G23+H23 -> 9054.67 | J23: =D23-I23 -> 0 | K23: 200DB | L23: 5.0
A24: 4 | B24: 12-New Buildings(16 units)-bldg11-30yr | C24: 12/20/22 | D24: 25441.07 | E24: 0 | F24: 0 | G24: 883.37 | H24: 848.04 | I24: =G24+H24 -> 1731.41 | J24: =D24-I24 -> 23709.66 | K24: S/L | L24: 30.00
A25: 5 | B25: 14-New Buildings(105 units)-bldg11-5yr | C25: 4/01/23 | D25: 60688.77 | E25: 0 | F25: 48551.02 | G25: 50978.57 | H25: 3884.08 | I25: =G25+H25 -> 54862.65 | J25: =D25-I25 -> 5826.12 | K25: 200DB | L25: 5.0
A26: 6 | B26: 14-New Buildings(105 units)-bldg11-30yr | C26: 4/01/23 | D26: 170518.26 | E26: 0 | F26: 0 | G26: 4026.13 | H26: 5683.94 | I26: =G26+H26 -> 9710.07 | J26: =D26-I26 -> 160808.19 | K26: S/L | L26: 30.00
A27: 7 | B27: 11-Building Imp-Post-Casulty Loss Basis-bld11 | C27: 9/02/20 | D27: 424.3 | E27: 0 | F27: 424.3 | G27: 424.3 | H27: 0 | I27: =G27+H27 -> 424.3 | J27: =D27-I27 -> 0 | K27: 200DB | L27: 5.0
A28: 8 | B28: 11-Building Imp-Post-Casulty Loss Basis-bld11 | C28: 9/02/20 | D28: 1192.18 | E28: 0 | F28: 0 | G28: 130.81 | H28: 39.74 | I28: =G28+H28 -> 170.55 | J28: =D28-I28 -> 1021.63 | K28: S/L | L28: 30.00
A29: 9 | B29: 2-Land Improvements-bldg11-5yr | C29: 8/15/18 | D29: 2308.83 | E29: 0 | F29: 2308.83 | G29: 2308.83 | H29: 0 | I29: =G29+H29 -> 2308.83 | J29: =D29-I29 -> 0 | K29: 200DB | L29: 5.0
A30: 10 | B30: 2-Land Improvements-bldg11-30yr | C30: 8/15/18 | D30: 6487.14 | E30: 0 | F30: 0 | G30: 1162.29 | H30: 216.24 | I30: =G30+H30 -> 1378.53 | J30: =D30-I30 -> 5108.61 | K30: S/L | L30: 30.00
A31: 11 | B31: 13-New Equipment(16 units)-bldg11-5yr | C31: 12/20/22 | D31: 1987.61 | E31: 0 | F31: 1987.61 | G31: 1987.61 | H31: 0 | I31: =G31+H31 -> 1987.61 | J31: =D31-I31 -> 0 | K31: 200DB | L31: 5.0
A32: 12 | B32: 13-New Equipment(16 units)-bldg11-30yr | C32: 12/20/22 | D32: 5584.62 | E32: 0 | F32: 0 | G32: 193.91 | H32: 186.15 | I32: =G32+H32 -> 380.06 | J32: =D32-I32 -> 5204.56 | K32: S/L | L32: 30.00
... A34: 14 | B34: 15-New Equipment(105 units)-bldg11-30yr | C34: 4/01/23 | D34: 37430.84 | E34: 0 | F34: 0 | G34: 883.78 | H34: 1247.69 | I34: =G34+H34 -> 2131.47 | J34: =D34-I34 -> 35299.37 | K34: S/L | L34: 30.00
B35: Grand Total | D35: =SUM(D21:D34) -> 398758.21 | E35: =SUM(E21:E34) -> 0 | F35: =SUM(F21:F34) -> 89866.59 | G35: =SUM(G21:G34) -> 108606.15 | H35: =SUM(H21:H34) -> 14539.66 | I35: =SUM(I21:I34) -> 123145.81 | J35: =SUM(J21:J34) -> 275612.4
B37: Section 481(a) Adjustment — Regular Tax
B38: Depreciation reported previously | D38: =I17 -> 32887.35
B39: Cost Segregation Corrected Depreciation | D39: =I35 -> 123145.81
B40: Section 481(a) Adjustment — Regular Tax | D40: =D38-D39 -> -90258.46
A42: CALCULATION OF §481(a) ADJUSTMENT — AMT
A43: As Previously Filed — AMT
A44: Asset | B44: Property Description | C44: Date In Service | D44: Cost | E44: Sec 179 Exp | F44: Bonus Amt | G44: AMT Prior Depreciation | H44: AMT Current Depreciation | I44: End Depreciation | J44: Net Book Value | K44: Method | L44: Period
A45: 1 | B45: 10-Building(Post Casualty Loss Basis)-bldg 11 | C45: 8/15/18 | D45: 64317.98 | E45: 0 | F45: 0 | G45: 6642.44 | H45: 2342.15 | I45: =G45+H45 -> 8984.59 | J45: =D45-I45 -> 55333.39 | K45: S/L | L45: 30.00
A46: 2 | B46: 12-New Buildings(16 units)-bldg 11 | C46: 12/20/22 | D46: 34495.74 | E46: 0 | F46: 0 | G46: 1197.79 | H46: 1149.85 | I46: =G46+H46 -> 2347.64 | J46: =D46-I46 -> 32148.1 | K46: S/L | L46: 30.00
A47: 3 | B47: 14-New Buildings(105 units)-bldg 11 | C47: 4/01/23 | D47: 231207.03 | E47: 0 | F47: 0 | G47: 5459.05 | H47: 7706.92 | I47: =G47+H47 -> 13165.97 | J47: =D47-I47 -> 218041.06 | K47: S/L | L47: 30.00
A48: 4 | B48: 11-Building Imp)Post-Casulty Loss Basis)-bldg | C48: 9/02/20 | D48: 1616.48 | E48: 0 | F48: 0 | G48: 121.71 | H48: 55.97 | I48: =G48+H48 -> 177.68 | J48: =D48-I48 -> 1438.8 | K48: S/L | L48: 30.00
A49: 5 | B49: 2-Land Improvements-bldg 11 | C49: 8/15/18 | D49: 8795.97 | E49: 0 | F49: 2256.71 | G49: 2256.71 | H49: 676.47 | I49: =G49+H49 -> 2933.18 | J49: =D49-I49 -> 5862.79 | K49: 150DB | L49: 15.0
A50: 6 | B50: 13-New Equipment(16 units)-bldg 11 | C50: 12/20/22 | D50: 7572.23 | E50: 0 | F50: 0 | G50: 0 | H50: 0 | I50: =G50+H50 -> 0 | J50: =D50-I50 -> 7572.23 | K50: 200DB | L50: 5.0
A51: 7 | B51: 15-New Equipment(105 units)-bldg 11 | C51: 4/01/23 | D51: 50752.78 | E51: 0 | F51: 0 | G51: 2030.1 | H51: 3248.19 | I51: =G51+H51 -> 5278.29 | J51: =D51-I51 -> 45474.49 | K51: 200DB | L51: 5.0
B52: Grand Total | D52: =SUM(D45:D51) -> 398758.21 | E52: =SUM(E45:E51) -> 0 | F52: =SUM(F45:F51) -> 2256.71 | G52: =SUM(G45:G51) -> 17707.8 | H52: =SUM(H45:H51) -> 15179.55 | I52: =SUM(I45:I51) -> 32887.35 | J52: =SUM(J45:J51) -> 365870.86
A54: After Cost Segregation Correction — AMT
A55: Asset | B55: Property Description | C55: Date In Service | D55: Cost | E55: Sec 179 Exp | F55: Bonus Amt | G55: AMT Prior Depreciation | H55: AMT Current Depreciation | I55: End Depreciation | J55: Net Book Value | K55: Method | L55: Period
A56: 1 | B56: 10-Building-Post Casualty Loss Basis-bldg11- | C56: 8/15/18 | D56: 47435.37 | E56: 0 | F56: 0 | G56: 8498.84 | H56: 1581.18 | I56: =G56+H56 -> 10080.02 | J56: =D56-I56 -> 37355.35 | K56: S/L | L56: 30.00
A57: 2 | B57: 12-New Buildings(16 units)-bldg11-5yr | C57: 12/20/22 | D57: 9054.67 | E57: 0 | F57: 9054.67 | G57: 9054.67 | H57: 0 | I57: =G57+H57 -> 9054.67 | J57: =D57-I57 -> 0 | K57: 200DB | L57: 5.0
A58: 3 | B58: 12-New Buildings(16 units)-bldg11-30yr | C58: 12/20/22 | D58: 25441.07 | E58: 0 | F58: 0 | G58: 883.37 | H58: 848.04 | I58: =G58+H58 -> 1731.41 | J58: =D58-I58 -> 23709.66 | K58: S/L | L58: 30.00
A59: 4 | B59: 14-New Buildings(105 units)-bldg11-5yr | C59: 4/01/23 | D59: 60688.77 | E59: 0 | F59: 48551.02 | G59: 50978.57 | H59: 3884.08 | I59: =G59+H59 -> 54862.65 | J59: =D59-I59 -> 5826.12 | K59: 200DB | L59: 5.0
A60: 5 | B60: 14-New Buildings(105 units)-bldg11-30yr | C60: 4/01/23 | D60: 170518.26 | E60: 0 | F60: 0 | G60: 4026.13 | H60: 5683.94 | I60: =G60+H60 -> 9710.07 | J60: =D60-I60 -> 160808.19 | K60: S/L | L60: 30.00
A61: 6 | B61: 2-Land Improvements-bldg11-5yr | C61: 8/15/18 | D61: 2308.83 | E61: 0 | F61: 2308.83 | G61: 2308.83 | H61: 0 | I61: =G61+H61 -> 2308.83 | J61: =D61-I61 -> 0 | K61: 200DB | L61: 5.0
A62: 7 | B62: 2-Land Improvements-bldg11-30yr | C62: 8/15/18 | D62: 6487.14 | E62: 0 | F62: 0 | G62: 1162.29 | H62: 216.24 | I62: =G62+H62 -> 1378.53 | J62: =D62-I62 -> 5108.61 | K62: S/L | L62: 30.00
A63: 8 | B63: 13-New Equipment(16 units)-bldg11-5yr | C63: 12/20/22 | D63: 1987.61 | E63: 0 | F63: 1987.61 | G63: 1987.61 | H63: 0 | I63: =G63+H63 -> 1987.61 | J63: =D63-I63 -> 0 | K63: 200DB | L63: 5.0
A64: 9 | B64: 13-New Equipment(16 units)-bldg11-30yr | C64: 12/20/22 | D64: 5584.62 | E64: 0 | F64: 0 | G64: 193.91 | H64: 186.15 | I64: =G64+H64 -> 380.06 | J64: =D64-I64 -> 5204.56 | K64: S/L | L64: 30.00
A65: 10 | B65: 15-New Equipment(105 units)-bldg11-5yr | C65: 4/01/23 | D65: 13321.94 | E65: 0 | F65: 10657.55 | G65: 11190.43 | H65: 852.6 | I65: =G65+H65 -> 12043.03 | J65: =D65-I65 -> 1278.91 | K65: 200DB | L65: 5.0
A66: 11 | B66: 15-New Equipment(105 units)-bldg11-30yr | C66: 4/01/23 | D66: 37430.84 | E66: 0 | F66: 0 | G66: 883.78 | H66: 1247.69 | I66: =G66+H66 -> 2131.47 | J66: =D66-I66 -> 35299.37 | K66: S/L | L66: 30.00
B67: Grand Total | D67: =SUM(D56:D66) -> 380259.12 | E67: =SUM(E56:E66) -> 0 | F67: =SUM(F56:F66) -> 72559.68 | G67: =SUM(G56:G66) -> 91168.43 | H67: =SUM(H56:H66) -> 14499.92 | I67: =SUM(I56:I66) -> 105668.35 | J67: =SUM(J56:J66) -> 274590.77
B69: Section 481(a) Adjustment — AMT
B70: Depreciation reported previously | D70: =I52 -> 32887.35
B71: Cost Segregation Corrected Depreciation | D71: =I67 -> 105668.35
B72: Section 481(a) Adjustment — AMT | D72: =D70-D71 -> -72781
A74: COST SEGREGATION STUDY — COST SUMMARY
B75: Total Building Cost | D75: =D112 -> 398758.21
B76: Building Components: 5 Year | D76: =F112 -> 104668.73
B77: % of Cost | D77: =F113 -> 0.26248671
B78: Building Structure: 30 Year | D78: =H112 -> 294089.48
B79: % of Cost | D79: =H113 -> 0.73751329
A81: COST SEGREGATION STUDY — COST DETAIL
B82: Property Category | D82: Cost | F82: 5 Year | H82: 30 Year
B83: Building Components
B84: Cabinets / Millwork | D84: =SUM(F84:H84) -> 31452.73 | F84: 31452.73
B85: Moldings | D85: =SUM(F85:H85) -> 8394.17 | F85: 8394.17
B86: Flooring - Vinyl Plank | D86: =SUM(F86:H86) -> 32815.9 | F86: 32815.9
B87: Window Treatments | D87: =SUM(F87:H87) -> 2648.72 | F87: 2648.72
B88: Building Signage | D88: =SUM(F88:H88) -> 394.4 | F88: 394.4
B89: Specialty Electrical - Appliances | D89: =SUM(F89:H89) -> 5344.3 | F89: 5344.3
B90: Communication / Data | D90: =SUM(F90:H90) -> 2858.97 | F90: 2858.97
B91: Specialty Plumbing - Kitchen Sinks | D91: =SUM(F91:H91) -> 9687.68 | F91: 9687.68
B92: Security / Exterior Lighting | D92: =SUM(F92:H92) -> 2139.23 | F92: 2139.23
B93: Canopies / Awnings | D93: =SUM(F93:H93) -> 605.69 | F93: 605.69
B94: Appliances | D94: =SUM(F94:H94) -> 8326.94 | F94: 8326.94
B95: Building Structure
B96: Roofing Systems | D96: =SUM(F96:H96) -> 16256.26 | H96: 16256.26
B97: Foundations | D97: =SUM(F97:H97) -> 21691.79 | H97: 21691.79
B98: HVAC | D98: =SUM(F98:H98) -> 31892.38 | H98: 31892.38
B99: Electrical | D99: =SUM(F99:H99) -> 29436.62 | H99: 29436.62
B100: Plumbing | D100: =SUM(F100:H100) -> 27723.88 | H100: 27723.88
B101: Fire Protection & Alarm | D101: =SUM(F101:H101) -> 1864.29 | H101: 1864.29
B102: Exterior Façade / Building Skin | D102: =SUM(F102:H102) -> 21222.77 | H102: 21222.77
B103: Doors & Frames | D103: =SUM(F103:H103) -> 16292.68 | H103: 16292.68
B104: Windows | D104: =SUM(F104:H104) -> 12258.17 | H104: 12258.17
B105: Ceiling Systems | D105: =SUM(F105:H105) -> 14614.91 | H105: 14614.91
B106: Interior Framing / Partitions | D106: =SUM(F106:H106) -> 38542.73 | H106: 38542.73
B107: Painting | D107: =SUM(F107:H107) -> 15289.77 | H107: 15289.77
... B111: Cabinets / Millwork - Restrooms | D111: =SUM(F111:H111) -> 1880.89 | H111: 1880.89
B112: Total Building Cost | D112: =SUM(D83:D111) -> 398758.21 | F112: =SUM(F83:F111) -> 104668.73 | H112: =SUM(H83:H111) -> 294089.48
...

Sheet Building 12
A1: St Charles Housing LP
A2: St. Charles — 1011 W 18th St, Lake Charles, LA 70607
A3: EIN: 82-5349206 · FYE: December 31, 2024 · Year of Change: 1/1/2024
A4: Building 12 — Attachment to Form 3115 (DCN #7, Rev. Proc. 2024-23 §6.01)
A5: Source: CSSI Report #107752-24, "St. Charles Housing LP_107752-24_3115_Combined.pdf"
A7: CALCULATION OF §481(a) ADJUSTMENT — REGULAR TAX
A8: As Previously Filed
A9: Asset | B9: Property Description | C9: Date In Service | D9: Cost | E9: Sec 179 Exp | F9: Bonus Amt | G9: Tax Prior Depreciation | H9: Tax Current Depreciation | I9: End Depreciation | J9: Net Book Value | K9: Method | L9: Period
A10: 1 | B10: 10-Building(Post Casualty Loss Basis)-bldg 12 | C10: 8/15/18 | D10: 72325.23 | E10: 0 | F10: 0 | G10: 7469.39 | H10: 2633.73 | I10: =G10+H10 -> 10103.12 | J10: =D10-I10 -> 62222.11 | K10: S/L | L10: 30.00
A11: 2 | B11: 12-New Buildings(16 units)-bldg 12 | C11: 12/20/22 | D11: 38790.29 | E11: 0 | F11: 0 | G11: 1346.91 | H11: 1293 | I11: =G11+H11 -> 2639.91 | J11: =D11-I11 -> 36150.38 | K11: S/L | L11: 30.00
A12: 3 | B12: 14-New Buildings(105 units)-bldg 12 | C12: 4/01/23 | D12: 259991.11 | E12: 0 | F12: 0 | G12: 6138.68 | H12: 8666.38 | I12: =G12+H12 -> 14805.06 | J12: =D12-I12 -> 245186.05 | K12: S/L | L12: 30.00
A13: 4 | B13: 11-Building Imp)Post-Casulty Loss Basis)-bldg | C13: 9/02/20 | D13: 1817.72 | E13: 0 | F13: 0 | G13: 136.87 | H13: 62.93 | I13: =G13+H13 -> 199.8 | J13: =D13-I13 -> 1617.92 | K13: S/L | L13: 30.00
A14: 5 | B14: 2-Land Improvements-bldg 12 | C14: 8/15/18 | D14: 9891.01 | E14: 0 | F14: 2537.66 | G14: 2537.66 | H14: 760.68 | I14: =G14+H14 -> 3298.34 | J14: =D14-I14 -> 6592.67 | K14: 150DB | L14: 15.0
A15: 6 | B15: 13-New Equipment(16 units)-bldg 12 | C15: 12/20/22 | D15: 8514.93 | E15: 0 | F15: 0 | G15: 0 | H15: 0 | I15: =G15+H15 -> 0 | J15: =D15-I15 -> 8514.93 | K15: 200DB | L15: 5.0
A16: 7 | B16: 15-New Equipment(105 units)-bldg 12 | C16: 4/01/23 | D16: 57071.24 | E16: 0 | F16: 0 | G16: 2282.85 | H16: 3652.56 | I16: =G16+H16 -> 5935.41 | J16: =D16-I16 -> 51135.83 | K16: 200DB | L16: 5.0
B17: Grand Total | D17: =SUM(D10:D16) -> 448401.53 | E17: =SUM(E10:E16) -> 0 | F17: =SUM(F10:F16) -> 2537.66 | G17: =SUM(G10:G16) -> 19912.36 | H17: =SUM(H10:H16) -> 17069.28 | I17: =SUM(I10:I16) -> 36981.64 | J17: =SUM(J10:J16) -> 411419.89
A19: After Cost Segregation Correction
A20: Asset | B20: Property Description | C20: Date In Service | D20: Cost | E20: Sec 179 Exp | F20: Bonus Amt | G20: Tax Prior Depreciation | H20: Tax Current Depreciation | I20: End Depreciation | J20: Net Book Value | K20: Method | L20: Period
A21: 1 | B21: 10-Building-Post Casualty Loss Basis-bldg12-5 | C21: 8/15/18 | D21: 18042.22 | E21: 0 | F21: 18042.22 | G21: 18042.22 | H21: 0 | I21: =G21+H21 -> 18042.22 | J21: =D21-I21 -> 0 | K21: 200DB | L21: 5.0
A22: 2 | B22: 10-Building-Post Casualty Loss Basis-bldg12-3 | C22: 8/15/18 | D22: 54283.01 | E22: 0 | F22: 0 | G22: 9725.69 | H22: 1809.43 | I22: =G22+H22 -> 11535.12 | J22: =D22-I22 -> 42747.89 | K22: S/L | L22: 30.00
A23: 3 | B23: 12-New Buildings(16 units)-bldg12-5yr | C23: 12/20/22 | D23: 9676.61 | E23: 0 | F23: 9676.61 | G23: 9676.61 | H23: 0 | I23: =G23+H23 -> 9676.61 | J23: =D23-I23 -> 0 | K23: 200DB | L23: 5.0
A24: 4 | B24: 12-New Buildings(16 units)-bldg12-30yr | C24: 12/20/22 | D24: 29113.68 | E24: 0 | F24: 0 | G24: 1010.9 | H24: 970.46 | I24: =G24+H24 -> 1981.36 | J24: =D24-I24 -> 27132.32 | K24: S/L | L24: 30.00
A25: 5 | B25: 14-New Buildings(105 units)-bldg12-5yr | C25: 4/01/23 | D25: 64857.26 | E25: 0 | F25: 51885.81 | G25: 54480.1 | H25: 4150.86 | I25: =G25+H25 -> 58630.96 | J25: =D25-I25 -> 6226.3 | K25: 200DB | L25: 5.0
A26: 6 | B26: 14-New Buildings(105 units)-bldg12-30yr | C26: 4/01/23 | D26: 195133.85 | E26: 0 | F26: 0 | G26: 4607.33 | H26: 6504.46 | I26: =G26+H26 -> 11111.79 | J26: =D26-I26 -> 184022.06 | K26: S/L | L26: 30.00
A27: 7 | B27: 11-Building Imp-Post-Casulty Loss Basis-bld12 | C27: 9/02/20 | D27: 453.45 | E27: 0 | F27: 453.45 | G27: 453.45 | H27: 0 | I27: =G27+H27 -> 453.45 | J27: =D27-I27 -> 0 | K27: 200DB | L27: 5.0
A28: 8 | B28: 11-Building Imp-Post-Casulty Loss Basis-bld12 | C28: 9/02/20 | D28: 1364.27 | E28: 0 | F28: 0 | G28: 149.7 | H28: 45.48 | I28: =G28+H28 -> 195.18 | J28: =D28-I28 -> 1169.09 | K28: S/L | L28: 30.00
A29: 9 | B29: 2-Land Improvements-bldg12-5yr | C29: 8/15/18 | D29: 2467.41 | E29: 0 | F29: 2467.41 | G29: 2467.41 | H29: 0 | I29: =G29+H29 -> 2467.41 | J29: =D29-I29 -> 0 | K29: 200DB | L29: 5.0
A30: 10 | B30: 2-Land Improvements-bldg12-30yr | C30: 8/15/18 | D30: 7423.6 | E30: 0 | F30: 0 | G30: 1330.05 | H30: 247.45 | I30: =G30+H30 -> 1577.5 | J30: =D30-I30 -> 5846.1 | K30: S/L | L30: 30.00
A31: 11 | B31: 13-New Equipment(16 units)-bldg12-5yr | C31: 12/20/22 | D31: 2124.13 | E31: 0 | F31: 2124.13 | G31: 2124.13 | H31: 0 | I31: =G31+H31 -> 2124.13 | J31: =D31-I31 -> 0 | K31: 200DB | L31: 5.0
A32: 12 | B32: 13-New Equipment(16 units)-bldg12-30yr | C32: 12/20/22 | D32: 6390.8 | E32: 0 | F32: 0 | G32: 221.91 | H32: 213.03 | I32: =G32+H32 -> 434.94 | J32: =D32-I32 -> 5955.86 | K32: S/L | L32: 30.00
... A34: 14 | B34: 15-New Equipment(105 units)-bldg12-30yr | C34: 4/01/23 | D34: 42834.29 | E34: 0 | F34: 0 | G34: 1011.37 | H34: 1427.81 | I34: =G34+H34 -> 2439.18 | J34: =D34-I34 -> 40395.11 | K34: S/L | L34: 30.00
B35: Grand Total | D35: =SUM(D21:D34) -> 448401.53 | E35: =SUM(E21:E34) -> 0 | F35: =SUM(F21:F34) -> 96039.19 | G35: =SUM(G21:G34) -> 117259.91 | H35: =SUM(H21:H34) -> 16280.14 | I35: =SUM(I21:I34) -> 133540.05 | J35: =SUM(J21:J34) -> 314861.48
B37: Section 481(a) Adjustment — Regular Tax
B38: Depreciation reported previously | D38: =I17 -> 36981.64
B39: Cost Segregation Corrected Depreciation | D39: =I35 -> 133540.05
B40: Section 481(a) Adjustment — Regular Tax | D40: =D38-D39 -> -96558.41
A42: CALCULATION OF §481(a) ADJUSTMENT — AMT
A43: As Previously Filed — AMT
A44: Asset | B44: Property Description | C44: Date In Service | D44: Cost | E44: Sec 179 Exp | F44: Bonus Amt | G44: AMT Prior Depreciation | H44: AMT Current Depreciation | I44: End Depreciation | J44: Net Book Value | K44: Method | L44: Period
A45: 1 | B45: 10-Building(Post Casualty Loss Basis)-bldg 12 | C45: 8/15/18 | D45: 72325.23 | E45: 0 | F45: 0 | G45: 7469.39 | H45: 2633.73 | I45: =G45+H45 -> 10103.12 | J45: =D45-I45 -> 62222.11 | K45: S/L | L45: 30.00
A46: 2 | B46: 12-New Buildings(16 units)-bldg 12 | C46: 12/20/22 | D46: 38790.29 | E46: 0 | F46: 0 | G46: 1346.91 | H46: 1293 | I46: =G46+H46 -> 2639.91 | J46: =D46-I46 -> 36150.38 | K46: S/L | L46: 30.00
A47: 3 | B47: 14-New Buildings(105 units)-bldg 12 | C47: 4/01/23 | D47: 259991.11 | E47: 0 | F47: 0 | G47: 6138.68 | H47: 8666.38 | I47: =G47+H47 -> 14805.06 | J47: =D47-I47 -> 245186.05 | K47: S/L | L47: 30.00
A48: 4 | B48: 11-Building Imp)Post-Casulty Loss Basis)-bldg | C48: 9/02/20 | D48: 1817.72 | E48: 0 | F48: 0 | G48: 136.87 | H48: 62.93 | I48: =G48+H48 -> 199.8 | J48: =D48-I48 -> 1617.92 | K48: S/L | L48: 30.00
A49: 5 | B49: 2-Land Improvements-bldg 12 | C49: 8/15/18 | D49: 9891.01 | E49: 0 | F49: 2537.66 | G49: 2537.66 | H49: 760.68 | I49: =G49+H49 -> 3298.34 | J49: =D49-I49 -> 6592.67 | K49: 150DB | L49: 15.0
A50: 6 | B50: 13-New Equipment(16 units)-bldg 12 | C50: 12/20/22 | D50: 8514.93 | E50: 0 | F50: 0 | G50: 0 | H50: 0 | I50: =G50+H50 -> 0 | J50: =D50-I50 -> 8514.93 | K50: 200DB | L50: 5.0
A51: 7 | B51: 15-New Equipment(105 units)-bldg 12 | C51: 4/01/23 | D51: 57071.24 | E51: 0 | F51: 0 | G51: 2282.85 | H51: 3652.56 | I51: =G51+H51 -> 5935.41 | J51: =D51-I51 -> 51135.83 | K51: 200DB | L51: 5.0
B52: Grand Total | D52: =SUM(D45:D51) -> 448401.53 | E52: =SUM(E45:E51) -> 0 | F52: =SUM(F45:F51) -> 2537.66 | G52: =SUM(G45:G51) -> 19912.36 | H52: =SUM(H45:H51) -> 17069.28 | I52: =SUM(I45:I51) -> 36981.64 | J52: =SUM(J45:J51) -> 411419.89
A54: After Cost Segregation Correction — AMT
A55: Asset | B55: Property Description | C55: Date In Service | D55: Cost | E55: Sec 179 Exp | F55: Bonus Amt | G55: AMT Prior Depreciation | H55: AMT Current Depreciation | I55: End Depreciation | J55: Net Book Value | K55: Method | L55: Period
A56: 1 | B56: 12-New Buildings(16 units)-bldg12-5yr | C56: 12/20/22 | D56: 9676.61 | E56: 0 | F56: 9676.61 | G56: 9676.61 | H56: 0 | I56: =G56+H56 -> 9676.61 | J56: =D56-I56 -> 0 | K56: 200DB | L56: 5.0
A57: 2 | B57: 12-New Buildings(16 units)-bldg12-30yr | C57: 12/20/22 | D57: 29113.68 | E57: 0 | F57: 0 | G57: 1010.9 | H57: 970.46 | I57: =G57+H57 -> 1981.36 | J57: =D57-I57 -> 27132.32 | K57: S/L | L57: 30.00
A58: 3 | B58: 14-New Buildings(105 units)-bldg12-5yr | C58: 4/01/23 | D58: 64857.26 | E58: 0 | F58: 51885.81 | G58: 54480.1 | H58: 4150.86 | I58: =G58+H58 -> 58630.96 | J58: =D58-I58 -> 6226.3 | K58: 200DB | L58: 5.0
A59: 4 | B59: 14-New Buildings(105 units)-bldg12-30yr | C59: 4/01/23 | D59: 195133.85 | E59: 0 | F59: 0 | G59: 4607.33 | H59: 6504.46 | I59: =G59+H59 -> 11111.79 | J59: =D59-I59 -> 184022.06 | K59: S/L | L59: 30.00
A60: 5 | B60: 2-Land Improvements-bldg12-5yr | C60: 8/15/18 | D60: 2467.41 | E60: 0 | F60: 2467.41 | G60: 2467.41 | H60: 0 | I60: =G60+H60 -> 2467.41 | J60: =D60-I60 -> 0 | K60: 200DB | L60: 5.0
A61: 6 | B61: 2-Land Improvements-bldg12-30yr | C61: 8/15/18 | D61: 7423.6 | E61: 0 | F61: 0 | G61: 1330.05 | H61: 247.45 | I61: =G61+H61 -> 1577.5 | J61: =D61-I61 -> 5846.1 | K61: S/L | L61: 30.00
A62: 7 | B62: 13-New Equipment(16 units)-bldg12-5yr | C62: 12/20/22 | D62: 2124.13 | E62: 0 | F62: 2124.13 | G62: 2124.13 | H62: 0 | I62: =G62+H62 -> 2124.13 | J62: =D62-I62 -> 0 | K62: 200DB | L62: 5.0
A63: 8 | B63: 13-New Equipment(16 units)-bldg12-30yr | C63: 12/20/22 | D63: 6390.8 | E63: 0 | F63: 0 | G63: 221.91 | H63: 213.03 | I63: =G63+H63 -> 434.94 | J63: =D63-I63 -> 5955.86 | K63: S/L | L63: 30.00
A64: 9 | B64: 15-New Equipment(105 units)-bldg12-5yr | C64: 4/01/23 | D64: 14236.95 | E64: 0 | F64: 11389.56 | G64: 11959.04 | H64: 911.16 | I64: =G64+H64 -> 12870.2 | J64: =D64-I64 -> 1366.75 | K64: 200DB | L64: 5.0
A65: 10 | B65: 15-New Equipment(105 units)-bldg12-30yr | C65: 4/01/23 | D65: 42834.29 | E65: 0 | F65: 0 | G65: 1011.37 | H65: 1427.81 | I65: =G65+H65 -> 2439.18 | J65: =D65-I65 -> 40395.11 | K65: S/L | L65: 30.00
B66: Grand Total | D66: =SUM(D56:D65) -> 374258.58 | E66: =SUM(E56:E65) -> 0 | F66: =SUM(F56:F65) -> 77543.52 | G66: =SUM(G56:G65) -> 88888.85 | H66: =SUM(H56:H65) -> 14425.23 | I66: =SUM(I56:I65) -> 103314.08 | J66: =SUM(J56:J65) -> 270944.5
B68: Section 481(a) Adjustment — AMT
B69: Depreciation reported previously | D69: =I52 -> 36981.64
B70: Cost Segregation Corrected Depreciation | D70: =I66 -> 103314.08
B71: Section 481(a) Adjustment — AMT | D71: =D69-D70 -> -66332.44
A73: COST SEGREGATION STUDY — COST SUMMARY
B74: Total Building Cost | D74: =D111 -> 448401.53
B75: Building Components: 5 Year | D75: =F111 -> 111858.03
B76: % of Cost | D76: =F112 -> 0.24945952
B77: Building Structure: 30 Year | D77: =H111 -> 336543.5
B78: % of Cost | D78: =H112 -> 0.75054048
A80: COST SEGREGATION STUDY — COST DETAIL
B81: Property Category | D81: Cost | F81: 5 Year | H81: 30 Year
B82: Building Components
B83: Cabinets / Millwork | D83: =SUM(F83:H83) -> 31452.73 | F83: 31452.73
B84: Moldings | D84: =SUM(F84:H84) -> 8975.5 | F84: 8975.5
B85: Flooring - Vinyl Plank | D85: =SUM(F85:H85) -> 38285.2 | F85: 38285.2
B86: Window Treatments | D86: =SUM(F86:H86) -> 3310.89 | F86: 3310.89
B87: Building Signage | D87: =SUM(F87:H87) -> 394.4 | F87: 394.4
B88: Specialty Electrical - Appliances | D88: =SUM(F88:H88) -> 5344.3 | F88: 5344.3
B89: Communication / Data | D89: =SUM(F89:H89) -> 3335.47 | F89: 3335.47
B90: Specialty Plumbing - Kitchen Sinks | D90: =SUM(F90:H90) -> 9687.68 | F90: 9687.68
B91: Security / Exterior Lighting | D91: =SUM(F91:H91) -> 2139.23 | F91: 2139.23
B92: Canopies / Awnings | D92: =SUM(F92:H92) -> 605.69 | F92: 605.69
B93: Appliances | D93: =SUM(F93:H93) -> 8326.94 | F93: 8326.94
B94: Building Structure
B95: Roofing Systems | D95: =SUM(F95:H95) -> 18787.91 | H95: 18787.91
B96: Foundations | D96: =SUM(F96:H96) -> 25094.53 | H96: 25094.53
B97: HVAC | D97: =SUM(F97:H97) -> 37207.78 | H97: 37207.78
B98: Electrical | D98: =SUM(F98:H98) -> 35233.43 | H98: 35233.43
B99: Plumbing | D99: =SUM(F99:H99) -> 32344.52 | H99: 32344.52
B100: Fire Protection & Alarm | D100: =SUM(F100:H100) -> 2485.72 | H100: 2485.72
B101: Exterior Façade / Building Skin | D101: =SUM(F101:H101) -> 24768.13 | H101: 24768.13
B102: Doors & Frames | D102: =SUM(F102:H102) -> 18966.91 | H102: 18966.91
B103: Windows | D103: =SUM(F103:H103) -> 15176.79 | H103: 15176.79
B104: Ceiling Systems | D104: =SUM(F104:H104) -> 17050.73 | H104: 17050.73
B105: Interior Framing / Partitions | D105: =SUM(F105:H105) -> 40897.65 | H105: 40897.65
B106: Painting | D106: =SUM(F106:H106) -> 16588.72 | H106: 16588.72
... B110: Cabinets / Millwork - Restrooms | D110: =SUM(F110:H110) -> 1880.89 | H110: 1880.89
B111: Total Building Cost | D111: =SUM(D82:D110) -> 448401.53 | F111: =SUM(F82:F110) -> 111858.03 | H111: =SUM(H82:H110) -> 336543.5
B112: % of Cost | F112: =F111/D111 -> 0.24945952 | H112: =H111/D111 -> 0.75054048
...

Sheet Building 13
A1: St Charles Housing LP
A2: St. Charles — 1011 W 18th St, Lake Charles, LA 70607
A3: EIN: 82-5349206 · FYE: December 31, 2024 · Year of Change: 1/1/2024
A4: Building 13 — Attachment to Form 3115 (DCN #7, Rev. Proc. 2024-23 §6.01)
A5: Source: CSSI Report #107752-24, "St. Charles Housing LP_107752-24_3115_Combined.pdf"
A7: CALCULATION OF §481(a) ADJUSTMENT — REGULAR TAX
A8: As Previously Filed
A9: Asset | B9: Property Description | C9: Date In Service | D9: Cost | E9: Sec 179 Exp | F9: Bonus Amt | G9: Tax Prior Depreciation | H9: Tax Current Depreciation | I9: End Depreciation | J9: Net Book Value | K9: Method | L9: Period
A10: 1 | B10: 10-Building(Post Casualty Loss Basis)-bldg 13 | C10: 8/15/18 | D10: 64317.98 | E10: 0 | F10: 0 | G10: 6642.44 | H10: 2342.15 | I10: =G10+H10 -> 8984.59 | J10: =D10-I10 -> 55333.39 | K10: S/L | L10: 30.00
A11: 2 | B11: 12-New Buildings(16 units)-bldg 13 | C11: 12/20/22 | D11: 34495.74 | E11: 0 | F11: 0 | G11: 1197.79 | H11: 1149.85 | I11: =G11+H11 -> 2347.64 | J11: =D11-I11 -> 32148.1 | K11: S/L | L11: 30.00
A12: 3 | B12: 14-New Buildings(105 units)-bldg 13 | C12: 4/01/23 | D12: 231207.03 | E12: 0 | F12: 0 | G12: 5459.05 | H12: 7706.92 | I12: =G12+H12 -> 13165.97 | J12: =D12-I12 -> 218041.06 | K12: S/L | L12: 30.00
A13: 4 | B13: 11-Building Imp)Post-Casulty Loss Basis)-bldg | C13: 9/02/20 | D13: 1616.48 | E13: 0 | F13: 0 | G13: 121.71 | H13: 55.97 | I13: =G13+H13 -> 177.68 | J13: =D13-I13 -> 1438.8 | K13: S/L | L13: 30.00
A14: 5 | B14: 2-Land Improvements-bldg 13 | C14: 8/15/18 | D14: 8795.97 | E14: 0 | F14: 2256.71 | G14: 2256.71 | H14: 676.47 | I14: =G14+H14 -> 2933.18 | J14: =D14-I14 -> 5862.79 | K14: 150DB | L14: 15.0
A15: 6 | B15: 13-New Equipment(16 units)-bldg 13 | C15: 12/20/22 | D15: 7572.23 | E15: 0 | F15: 0 | G15: 0 | H15: 0 | I15: =G15+H15 -> 0 | J15: =D15-I15 -> 7572.23 | K15: 200DB | L15: 5.0
A16: 7 | B16: 15-New Equipment(105 units)-bldg 13 | C16: 4/01/23 | D16: 50752.78 | E16: 0 | F16: 0 | G16: 2030.1 | H16: 3248.19 | I16: =G16+H16 -> 5278.29 | J16: =D16-I16 -> 45474.49 | K16: 200DB | L16: 5.0
B17: Grand Total | D17: =SUM(D10:D16) -> 398758.21 | E17: =SUM(E10:E16) -> 0 | F17: =SUM(F10:F16) -> 2256.71 | G17: =SUM(G10:G16) -> 17707.8 | H17: =SUM(H10:H16) -> 15179.55 | I17: =SUM(I10:I16) -> 32887.35 | J17: =SUM(J10:J16) -> 365870.86
A19: After Cost Segregation Correction
A20: Asset | B20: Property Description | C20: Date In Service | D20: Cost | E20: Sec 179 Exp | F20: Bonus Amt | G20: Tax Prior Depreciation | H20: Tax Current Depreciation | I20: End Depreciation | J20: Net Book Value | K20: Method | L20: Period
A21: 1 | B21: 10-Building-Post Casualty Loss Basis-bldg13-5 | C21: 8/15/18 | D21: 16882.61 | E21: 0 | F21: 16882.61 | G21: 16882.61 | H21: 0 | I21: =G21+H21 -> 16882.61 | J21: =D21-I21 -> 0 | K21: 200DB | L21: 5.0
A22: 2 | B22: 10-Building-Post Casualty Loss Basis-bldg13- | C22: 8/15/18 | D22: 47435.37 | E22: 0 | F22: 0 | G22: 8498.84 | H22: 1581.18 | I22: =G22+H22 -> 10080.02 | J22: =D22-I22 -> 37355.35 | K22: S/L | L22: 30.00
A23: 3 | B23: 12-New Buildings(16 units)-bldg13-5yr | C23: 12/20/22 | D23: 9054.67 | E23: 0 | F23: 9054.67 | G23: 9054.67 | H23: 0 | I23: =G23+H23 -> 9054.67 | J23: =D23-I23 -> 0 | K23: 200DB | L23: 5.0
A24: 4 | B24: 12-New Buildings(16 units)-bldg13-30yr | C24: 12/20/22 | D24: 25441.07 | E24: 0 | F24: 0 | G24: 883.37 | H24: 848.04 | I24: =G24+H24 -> 1731.41 | J24: =D24-I24 -> 23709.66 | K24: S/L | L24: 30.00
A25: 5 | B25: 14-New Buildings(105 units)-bldg13-5yr | C25: 4/01/23 | D25: 60688.77 | E25: 0 | F25: 48551.02 | G25: 50978.57 | H25: 3884.08 | I25: =G25+H25 -> 54862.65 | J25: =D25-I25 -> 5826.12 | K25: 200DB | L25: 5.0
A26: 6 | B26: 14-New Buildings(105 units)-bldg13-30yr | C26: 4/01/23 | D26: 170518.26 | E26: 0 | F26: 0 | G26: 4026.13 | H26: 5683.94 | I26: =G26+H26 -> 9710.07 | J26: =D26-I26 -> 160808.19 | K26: S/L | L26: 30.00
A27: 7 | B27: 11-Building Imp-Post-Casulty Loss Basis-bld13 | C27: 9/02/20 | D27: 424.3 | E27: 0 | F27: 424.3 | G27: 424.3 | H27: 0 | I27: =G27+H27 -> 424.3 | J27: =D27-I27 -> 0 | K27: 200DB | L27: 5.0
A28: 8 | B28: 11-Building Imp-Post-Casulty Loss Basis-bld13 | C28: 9/02/20 | D28: 1192.18 | E28: 0 | F28: 0 | G28: 130.81 | H28: 39.74 | I28: =G28+H28 -> 170.55 | J28: =D28-I28 -> 1021.63 | K28: S/L | L28: 30.00
A29: 9 | B29: 2-Land Improvements-bldg13-5yr | C29: 8/15/18 | D29: 2308.83 | E29: 0 | F29: 2308.83 | G29: 2308.83 | H29: 0 | I29: =G29+H29 -> 2308.83 | J29: =D29-I29 -> 0 | K29: 200DB | L29: 5.0
A30: 10 | B30: 2-Land Improvements-bldg13-30yr | C30: 8/15/18 | D30: 6487.14 | E30: 0 | F30: 0 | G30: 1162.29 | H30: 216.24 | I30: =G30+H30 -> 1378.53 | J30: =D30-I30 -> 5108.61 | K30: S/L | L30: 30.00
A31: 11 | B31: 13-New Equipment(16 units)-bldg13-5yr | C31: 12/20/22 | D31: 1987.61 | E31: 0 | F31: 1987.61 | G31: 1987.61 | H31: 0 | I31: =G31+H31 -> 1987.61 | J31: =D31-I31 -> 0 | K31: 200DB | L31: 5.0
A32: 12 | B32: 13-New Equipment(16 units)-bldg13-30yr | C32: 12/20/22 | D32: 5584.62 | E32: 0 | F32: 0 | G32: 193.91 | H32: 186.15 | I32: =G32+H32 -> 380.06 | J32: =D32-I32 -> 5204.56 | K32: S/L | L32: 30.00
... A34: 14 | B34: 15-New Equipment(105 units)-bldg13-30yr | C34: 4/01/23 | D34: 37430.84 | E34: 0 | F34: 0 | G34: 883.78 | H34: 1247.69 | I34: =G34+H34 -> 2131.47 | J34: =D34-I34 -> 35299.37 | K34: S/L | L34: 30.00
B35: Grand Total | D35: =SUM(D21:D34) -> 398758.21 | E35: =SUM(E21:E34) -> 0 | F35: =SUM(F21:F34) -> 89866.59 | G35: =SUM(G21:G34) -> 108606.15 | H35: =SUM(H21:H34) -> 14539.66 | I35: =SUM(I21:I34) -> 123145.81 | J35: =SUM(J21:J34) -> 275612.4
B37: Section 481(a) Adjustment — Regular Tax
B38: Depreciation reported previously | D38: =I17 -> 32887.35
B39: Cost Segregation Corrected Depreciation | D39: =I35 -> 123145.81
B40: Section 481(a) Adjustment — Regular Tax | D40: =D38-D39 -> -90258.46
A42: CALCULATION OF §481(a) ADJUSTMENT — AMT
A43: As Previously Filed — AMT
A44: Asset | B44: Property Description | C44: Date In Service | D44: Cost | E44: Sec 179 Exp | F44: Bonus Amt | G44: AMT Prior Depreciation | H44: AMT Current Depreciation | I44: End Depreciation | J44: Net Book Value | K44: Method | L44: Period
A45: 1 | B45: 10-Building(Post Casualty Loss Basis)-bldg 13 | C45: 8/15/18 | D45: 64317.98 | E45: 0 | F45: 0 | G45: 6642.44 | H45: 2342.15 | I45: =G45+H45 -> 8984.59 | J45: =D45-I45 -> 55333.39 | K45: S/L | L45: 30.00
A46: 2 | B46: 12-New Buildings(16 units)-bldg 13 | C46: 12/20/22 | D46: 34495.74 | E46: 0 | F46: 0 | G46: 1197.79 | H46: 1149.85 | I46: =G46+H46 -> 2347.64 | J46: =D46-I46 -> 32148.1 | K46: S/L | L46: 30.00
A47: 3 | B47: 14-New Buildings(105 units)-bldg 13 | C47: 4/01/23 | D47: 231207.03 | E47: 0 | F47: 0 | G47: 5459.05 | H47: 7706.92 | I47: =G47+H47 -> 13165.97 | J47: =D47-I47 -> 218041.06 | K47: S/L | L47: 30.00
A48: 4 | B48: 11-Building Imp)Post-Casulty Loss Basis)-bldg | C48: 9/02/20 | D48: 1616.48 | E48: 0 | F48: 0 | G48: 121.71 | H48: 55.97 | I48: =G48+H48 -> 177.68 | J48: =D48-I48 -> 1438.8 | K48: S/L | L48: 30.00
A49: 5 | B49: 2-Land Improvements-bldg 13 | C49: 8/15/18 | D49: 8795.97 | E49: 0 | F49: 2256.71 | G49: 2256.71 | H49: 676.47 | I49: =G49+H49 -> 2933.18 | J49: =D49-I49 -> 5862.79 | K49: 150DB | L49: 15.0
A50: 6 | B50: 13-New Equipment(16 units)-bldg 13 | C50: 12/20/22 | D50: 7572.23 | E50: 0 | F50: 0 | G50: 0 | H50: 0 | I50: =G50+H50 -> 0 | J50: =D50-I50 -> 7572.23 | K50: 200DB | L50: 5.0
A51: 7 | B51: 15-New Equipment(105 units)-bldg 13 | C51: 4/01/23 | D51: 50752.78 | E51: 0 | F51: 0 | G51: 2030.1 | H51: 3248.19 | I51: =G51+H51 -> 5278.29 | J51: =D51-I51 -> 45474.49 | K51: 200DB | L51: 5.0
B52: Grand Total | D52: =SUM(D45:D51) -> 398758.21 | E52: =SUM(E45:E51) -> 0 | F52: =SUM(F45:F51) -> 2256.71 | G52: =SUM(G45:G51) -> 17707.8 | H52: =SUM(H45:H51) -> 15179.55 | I52: =SUM(I45:I51) -> 32887.35 | J52: =SUM(J45:J51) -> 365870.86
A54: After Cost Segregation Correction — AMT
A55: Asset | B55: Property Description | C55: Date In Service | D55: Cost | E55: Sec 179 Exp | F55: Bonus Amt | G55: AMT Prior Depreciation | H55: AMT Current Depreciation | I55: End Depreciation | J55: Net Book Value | K55: Method | L55: Period
A56: 1 | B56: 10-Building-Post Casualty Loss Basis-bldg13- | C56: 8/15/18 | D56: 47435.37 | E56: 0 | F56: 0 | G56: 8498.84 | H56: 1581.18 | I56: =G56+H56 -> 10080.02 | J56: =D56-I56 -> 37355.35 | K56: S/L | L56: 30.00
A57: 2 | B57: 12-New Buildings(16 units)-bldg13-5yr | C57: 12/20/22 | D57: 9054.67 | E57: 0 | F57: 9054.67 | G57: 9054.67 | H57: 0 | I57: =G57+H57 -> 9054.67 | J57: =D57-I57 -> 0 | K57: 200DB | L57: 5.0
A58: 3 | B58: 12-New Buildings(16 units)-bldg13-30yr | C58: 12/20/22 | D58: 25441.07 | E58: 0 | F58: 0 | G58: 883.37 | H58: 848.04 | I58: =G58+H58 -> 1731.41 | J58: =D58-I58 -> 23709.66 | K58: S/L | L58: 30.00
A59: 4 | B59: 14-New Buildings(105 units)-bldg13-5yr | C59: 4/01/23 | D59: 60688.77 | E59: 0 | F59: 48551.02 | G59: 50978.57 | H59: 3884.08 | I59: =G59+H59 -> 54862.65 | J59: =D59-I59 -> 5826.12 | K59: 200DB | L59: 5.0
A60: 5 | B60: 14-New Buildings(105 units)-bldg13-30yr | C60: 4/01/23 | D60: 170518.26 | E60: 0 | F60: 0 | G60: 4026.13 | H60: 5683.94 | I60: =G60+H60 -> 9710.07 | J60: =D60-I60 -> 160808.19 | K60: S/L | L60: 30.00
A61: 6 | B61: 2-Land Improvements-bldg13-5yr | C61: 8/15/18 | D61: 2308.83 | E61: 0 | F61: 2308.83 | G61: 2308.83 | H61: 0 | I61: =G61+H61 -> 2308.83 | J61: =D61-I61 -> 0 | K61: 200DB | L61: 5.0
A62: 7 | B62: 2-Land Improvements-bldg13-30yr | C62: 8/15/18 | D62: 6487.14 | E62: 0 | F62: 0 | G62: 1162.29 | H62: 216.24 | I62: =G62+H62 -> 1378.53 | J62: =D62-I62 -> 5108.61 | K62: S/L | L62: 30.00
A63: 8 | B63: 13-New Equipment(16 units)-bldg13-5yr | C63: 12/20/22 | D63: 1987.61 | E63: 0 | F63: 1987.61 | G63: 1987.61 | H63: 0 | I63: =G63+H63 -> 1987.61 | J63: =D63-I63 -> 0 | K63: 200DB | L63: 5.0
A64: 9 | B64: 13-New Equipment(16 units)-bldg13-30yr | C64: 12/20/22 | D64: 5584.62 | E64: 0 | F64: 0 | G64: 193.91 | H64: 186.15 | I64: =G64+H64 -> 380.06 | J64: =D64-I64 -> 5204.56 | K64: S/L | L64: 30.00
A65: 10 | B65: 15-New Equipment(105 units)-bldg13-5yr | C65: 4/01/23 | D65: 13321.94 | E65: 0 | F65: 10657.55 | G65: 11190.43 | H65: 852.6 | I65: =G65+H65 -> 12043.03 | J65: =D65-I65 -> 1278.91 | K65: 200DB | L65: 5.0
A66: 11 | B66: 15-New Equipment(105 units)-bldg13-30yr | C66: 4/01/23 | D66: 37430.84 | E66: 0 | F66: 0 | G66: 883.78 | H66: 1247.69 | I66: =G66+H66 -> 2131.47 | J66: =D66-I66 -> 35299.37 | K66: S/L | L66: 30.00
B67: Grand Total | D67: =SUM(D56:D66) -> 380259.12 | E67: =SUM(E56:E66) -> 0 | F67: =SUM(F56:F66) -> 72559.68 | G67: =SUM(G56:G66) -> 91168.43 | H67: =SUM(H56:H66) -> 14499.92 | I67: =SUM(I56:I66) -> 105668.35 | J67: =SUM(J56:J66) -> 274590.77
B69: Section 481(a) Adjustment — AMT
B70: Depreciation reported previously | D70: =I52 -> 32887.35
B71: Cost Segregation Corrected Depreciation | D71: =I67 -> 105668.35
B72: Section 481(a) Adjustment — AMT | D72: =D70-D71 -> -72781
A74: COST SEGREGATION STUDY — COST SUMMARY
B75: Total Building Cost | D75: =D112 -> 398758.21
B76: Building Components: 5 Year | D76: =F112 -> 104668.73
B77: % of Cost | D77: =F113 -> 0.26248671
B78: Building Structure: 30 Year | D78: =H112 -> 294089.48
B79: % of Cost | D79: =H113 -> 0.73751329
A81: COST SEGREGATION STUDY — COST DETAIL
B82: Property Category | D82: Cost | F82: 5 Year | H82: 30 Year
B83: Building Components
B84: Cabinets / Millwork | D84: =SUM(F84:H84) -> 31452.73 | F84: 31452.73
B85: Moldings | D85: =SUM(F85:H85) -> 8394.17 | F85: 8394.17
B86: Flooring - Vinyl Plank | D86: =SUM(F86:H86) -> 32815.9 | F86: 32815.9
B87: Window Treatments | D87: =SUM(F87:H87) -> 2648.72 | F87: 2648.72
B88: Building Signage | D88: =SUM(F88:H88) -> 394.4 | F88: 394.4
B89: Specialty Electrical - Appliances | D89: =SUM(F89:H89) -> 5344.3 | F89: 5344.3
B90: Communication / Data | D90: =SUM(F90:H90) -> 2858.97 | F90: 2858.97
B91: Specialty Plumbing - Kitchen Sinks | D91: =SUM(F91:H91) -> 9687.68 | F91: 9687.68
B92: Security / Exterior Lighting | D92: =SUM(F92:H92) -> 2139.23 | F92: 2139.23
B93: Canopies / Awnings | D93: =SUM(F93:H93) -> 605.69 | F93: 605.69
B94: Appliances | D94: =SUM(F94:H94) -> 8326.94 | F94: 8326.94
B95: Building Structure
B96: Roofing Systems | D96: =SUM(F96:H96) -> 16256.26 | H96: 16256.26
B97: Foundations | D97: =SUM(F97:H97) -> 21691.79 | H97: 21691.79
B98: HVAC | D98: =SUM(F98:H98) -> 31892.38 | H98: 31892.38
B99: Electrical | D99: =SUM(F99:H99) -> 29436.62 | H99: 29436.62
B100: Plumbing | D100: =SUM(F100:H100) -> 27723.88 | H100: 27723.88
B101: Fire Protection & Alarm | D101: =SUM(F101:H101) -> 1864.29 | H101: 1864.29
B102: Exterior Façade / Building Skin | D102: =SUM(F102:H102) -> 21222.77 | H102: 21222.77
B103: Doors & Frames | D103: =SUM(F103:H103) -> 16292.68 | H103: 16292.68
B104: Windows | D104: =SUM(F104:H104) -> 12258.17 | H104: 12258.17
B105: Ceiling Systems | D105: =SUM(F105:H105) -> 14614.91 | H105: 14614.91
B106: Interior Framing / Partitions | D106: =SUM(F106:H106) -> 38542.73 | H106: 38542.73
B107: Painting | D107: =SUM(F107:H107) -> 15289.77 | H107: 15289.77
... B111: Cabinets / Millwork - Restrooms | D111: =SUM(F111:H111) -> 1880.89 | H111: 1880.89
B112: Total Building Cost | D112: =SUM(D83:D111) -> 398758.21 | F112: =SUM(F83:F111) -> 104668.73 | H112: =SUM(H83:H111) -> 294089.48
...

Sheet Building 14
A1: St Charles Housing LP
A2: St. Charles — 1011 W 18th St, Lake Charles, LA 70607
A3: EIN: 82-5349206 · FYE: December 31, 2024 · Year of Change: 1/1/2024
A4: Building 14 — Attachment to Form 3115 (DCN #7, Rev. Proc. 2024-23 §6.01)
A5: Source: CSSI Report #107752-24, "St. Charles Housing LP_107752-24_3115_Combined.pdf"
A7: CALCULATION OF §481(a) ADJUSTMENT — REGULAR TAX
A8: As Previously Filed
A9: Asset | B9: Property Description | C9: Date In Service | D9: Cost | E9: Sec 179 Exp | F9: Bonus Amt | G9: Tax Prior Depreciation | H9: Tax Current Depreciation | I9: End Depreciation | J9: Net Book Value | K9: Method | L9: Period
A10: 1 | B10: 10-Building(Post Casualty Loss Basis)-bldg 14 | C10: 8/15/18 | D10: 72282.57 | E10: 0 | F10: 0 | G10: 7464.98 | H10: 2632.18 | I10: =G10+H10 -> 10097.16 | J10: =D10-I10 -> 62185.41 | K10: S/L | L10: 30.00
A11: 2 | B11: 12-New Buildings(16 units)-bldg 14 | C11: 12/20/22 | D11: 38767.41 | E11: 0 | F11: 0 | G11: 1346.12 | H11: 1292.24 | I11: =G11+H11 -> 2638.36 | J11: =D11-I11 -> 36129.05 | K11: S/L | L11: 30.00
A12: 3 | B12: 14-New Buildings(105 units)-bldg 14 | C12: 4/01/23 | D12: 259837.74 | E12: 0 | F12: 0 | G12: 6135.05 | H12: 8661.27 | I12: =G12+H12 -> 14796.32 | J12: =D12-I12 -> 245041.42 | K12: S/L | L12: 30.00
A13: 4 | B13: 11-Building Imp)Post-Casulty Loss Basis)-bldg | C13: 9/02/20 | D13: 1816.65 | E13: 0 | F13: 0 | G13: 136.79 | H13: 62.89 | I13: =G13+H13 -> 199.68 | J13: =D13-I13 -> 1616.97 | K13: S/L | L13: 30.00
